Workbook

Sheet Overview
B2: Ticker
B3: Price | C3: =[1]Sheet1!$C$4 -> 103.45
B7: Units | C7: K
B11: PE | C11: =$C$3/'Statement Q'!$N$22 -> #DIV/0!
B12: PE adjusted | C12: =$C$3/Statements!S20 -> #DIV/0!
B13: PS | C13: =$C$3/('Statement Q'!$N$5/'Statement Q'!$N$20) -> #DIV/0!
B15: Market cap | C15: =C3*'Statement Q'!N116 -> 0
B16: Cash | C16: =Statements!S23 -> 0
B17: Debt | C17: ='Statement Q'!N47 -> 0
B18: EV | C18: =C15+C17-C16 -> 0
B19: Cash per share | C19: =C16/'Statement Q'!J116 -> #DIV/0!
B21: CAGR 10y Revenue | C21: =_xlfn.RRI(5,Statements!C5,Statements!H5) -> 0
B22: YoY Net income | C22: =(Statements!H18-Statements!C18)/ABS(Statements!C18) -> #DIV/0!
B23: YoY EPS | C23: =(Statements!H20-Statements!C20)/ABS(Statements!C20) -> #DIV/0!
B28: Notes
B29: For ownership shearch in the proxy statement for: "Security Ownership of Certain Beneficial Owners and Management"
B30: Calculate insider ownership: ClassA + ClassB held by insiders/Total classA + classB shares
B31: The total share number is on the 10-K/Q front page
B33: Shares held by insiders
B34: Total shares | C34: ='Statement Y'!H113 -> 0
B35: Insider % | C35: =C33/C34 -> #DIV/0!
B37: ROIC = NOPAT/Invested capital
B38: NOPAT = EBIT * (1-tax rate)
B39: Invested capital = (Total assets - Cash and equivalents) -non-interest bearing current liabilities
B40: NIBCL usually are accounts payable and accrued expenses and other operating items that do not have interest attached
B41: NIBCL does not include any sort of debt
B42: An easier denominator is Total debt + Equity -Cash
B44: NOPAT | C44: =Statements!S12*(1-'Statement Y'!G117) -> #DIV/0!
B45: Debt
B46: Equity
B47: Cash
B48: ROIC | C48: =C44/(C45+C46-C47) -> #DIV/0!

Sheet Financials ->
B13: Financials ->

Sheet Statement Y
B2: Date | C2: 31.12.2020 | D2: 31.12.2021 | E2: 30.09.2022 | F2: 31.12.2023 | G2: 31.12.2024 | H2: 31.12.2025
B3: FY | C3: 2020 | D3: =C3+1 -> 2021 | E3: =D3+1 -> 2022 | F3: =E3+1 -> 2023 | G3: =F3+1 -> 2024 | H3: =G3+1 -> 2025 | I3: =H3+1 -> 2026 | J3: =I3+1 -> 2027 | K3: =J3+1 -> 2028 | L3: =K3+1 -> 2029
B4: Income statement
B5: Revenue
B6: COGS
B7: Gross Profit | C7: =C5-C6 -> 0 | D7: =D5-D6 -> 0 | E7: =E5-E6 -> 0 | F7: =F5-F6 -> 0 | G7: =G5-G6 -> 0 | H7: =H5-H6 -> 0 | I7: =I5-I6 -> 0 | J7: =J5-J6 -> 0 | ... L7: =L5-L6 -> 0
B8: R&D
B9: Sales and marketing
B10: General and administrative
B11: OpEx | C11: =SUM(C8:C10) -> 0 | D11: =SUM(D8:D10) -> 0 | E11: =SUM(E8:E10) -> 0 | F11: =SUM(F8:F10) -> 0 | G11: =SUM(G8:G10) -> 0 | H11: =SUM(H8:H10) -> 0 | I11: =SUM(I8:I10) -> 0 | J11: =SUM(J8:J10) -> 0 | ... L11: =SUM(L8:L10) -> 0
B12: Operating income
B13: Other income
B14: Other expense
B15: Interest income
B16: Income before taxes
B17: Income tax expense/benefit
B18: Net income
B19: Basic Shares outstanding avg
B20: Diluted Shares outstanding avg
B21: Basic EPS
B22: Diluted EPS
B24: Balance sheet
... B39: Other assets
B40: Long term assets | C40: =SUM(C32:C39) -> 0 | D40: =SUM(D32:D39) -> 0 | E40: =SUM(E32:E39) -> 0 | F40: =SUM(F32:F39) -> 0 | G40: =SUM(G32:G39) -> 0 | H40: =SUM(H32:H39) -> 0 | I40: =SUM(I32:I39) -> 0 | J40: =SUM(J32:J39) -> 0 | ... L40: =SUM(L32:L39) -> 0
B41: Total assets
B42: Acc payable
B43: Deferred revenues
B44: Income tax payable
B45: Accrued expenses and other current
B46: Current liabilities
B47: Long term obligation operating lease
B48: Deferred tax liabilities
B49: Long term liabilities | C49: =SUM(C47:C48) -> 0 | D49: =SUM(D47:D48) -> 0 | E49: =SUM(E47:E48) -> 0 | F49: =SUM(F47:F48) -> 0 | G49: =SUM(G47:G48) -> 0 | H49: =SUM(H47:H48) -> 0 | I49: =SUM(I47:I48) -> 0 | J49: =SUM(J47:J48) -> 0 | ... L49: =SUM(L47:L48) -> 0
B50: Total liabilities
B51: Common stock par value
B52: Additional paid-in capital
B53: Retained earnings
B54: Stockholder equity
B55: Total liabilities and equity
B57: Cashflow statement
B58: Net income | C58: =C18 -> 0 | D58: =D18 -> 0 | E58: =E18 -> 0 | F58: =F18 -> 0 | G58: =G18 -> 0 | H58: =H18 -> 0 | I58: =I18 -> 0 | J58: =J18 -> 0 | ... L58: =L18 -> 0
B59: D&A
B60: Deferred income taxes
B61: Stock-based compensation
B62: Accretion on marketable securitirs
B63: Gain sale capitalized software
B64: Loss disposal leasehold improvments
B65: Impairment on capitalized software
B66: Change deferred revenue
B67: Change acc receivable
B68: Change deferred cost of revenues
B69: Change prepaid expenses
B70: Change acc payable
... B93: Sanity checks
B94: Calculated Net Income | C94: =C5-C6-C11+C13+C14+C15+C17 -> 0 | D94: =D5-D6-D11+D13+D14+D15+D17 -> 0 | E94: =E5-E6-E11+E13+E14+E15+E17 -> 0 | F94: =F5-F6-F11+F13+F14+F15+F17 -> 0 | G94: =G5-G6-G11+G13+G14+G15+G17 -> 0 | H94: =H5-H6-H11+H13+H14+H15+H17 -> 0 | I94: =I5-I6-I11+I13+I14+I15+I17 -> 0 | J94: =J5-J6-J11+J13+J14+J15+J17 -> 0 | ... L94: =L5-L6-L11+L13+L14+L15+L17 -> 0
B95: Check Net Income | C95: =C18-C94 -> 0 | D95: =D18-D94 -> 0 | E95: =E18-E94 -> 0 | F95: =F18-F94 -> 0 | G95: =G18-G94 -> 0 | H95: =H18-H94 -> 0 | I95: =I18-I94 -> 0 | J95: =J18-J94 -> 0 | ... L95: =L18-L94 -> 0
B96: Calculated Assets | C96: =SUM(C25:C30)+SUM(C32:C39) -> 0 | D96: =SUM(D25:D30)+SUM(D32:D39) -> 0 | E96: =SUM(E25:E30)+SUM(E32:E39) -> 0 | F96: =SUM(F25:F30)+SUM(F32:F39) -> 0 | G96: =SUM(G25:G30)+SUM(G32:G39) -> 0 | H96: =SUM(H25:H30)+SUM(H32:H39) -> 0 | I96: =SUM(I25:I30)+SUM(I32:I39) -> 0 | J96: =SUM(J25:J30)+SUM(J32:J39) -> 0 | ... L96: =SUM(L25:L30)+SUM(L32:L39) -> 0
B97: Check Assets | C97: =C41-C96 -> 0 | D97: =D41-D96 -> 0 | E97: =E41-E96 -> 0 | F97: =F41-F96 -> 0 | G97: =G41-G96 -> 0 | H97: =H41-H96 -> 0 | I97: =I41-I96 -> 0 | J97: =J41-J96 -> 0 | ... L97: =L41-L96 -> 0
B98: Calculated Liabilities | C98: =SUM(C42:C45)+SUM(C47:C48) -> 0 | D98: =SUM(D42:D45)+SUM(D47:D48) -> 0 | E98: =SUM(E42:E45)+SUM(E47:E48) -> 0 | F98: =SUM(F42:F45)+SUM(F47:F48) -> 0 | G98: =SUM(G42:G45)+SUM(G47:G48) -> 0 | H98: =SUM(H42:H45)+SUM(H47:H48) -> 0 | I98: =SUM(I42:I45)+SUM(I47:I47) -> 0 | J98: =SUM(J42:J45)+SUM(J47:J47) -> 0 | K98: =SUM(K42:K45)+SUM(K47:K47) -> 0 | L98: =SUM(L42:L45)+SUM(L47:L47) -> 0
B99: Check Liabilities | C99: =C50-C98 -> 0 | D99: =D50-D98 -> 0 | E99: =E50-E98 -> 0 | F99: =F50-F98 -> 0 | G99: =G50-G98 -> 0 | H99: =H50-H98 -> 0 | I99: =I50-I98 -> 0 | J99: =J50-J98 -> 0 | ... L99: =L50-L98 -> 0
B100: Calculated Stockholder Equity | C100: =SUM(C51:C53) -> 0 | D100: =SUM(D51:D53) -> 0 | E100: =SUM(E51:E53) -> 0 | F100: =SUM(F51:F53) -> 0 | G100: =SUM(G51:G53) -> 0 | H100: =SUM(H51:H53) -> 0 | I100: =SUM(I51:I53) -> 0 | J100: =SUM(J51:J53) -> 0 | ... L100: =SUM(L51:L53) -> 0
B101: Check Stockholder Equity | C101: =C54-C100 -> 0 | D101: =D54-D100 -> 0 | E101: =E54-E100 -> 0 | F101: =F54-F100 -> 0 | G101: =G54-G100 -> 0 | H101: =H54-H100 -> 0 | I101: =I54-I100 -> 0 | J101: =J54-J100 -> 0 | ... L101: =L54-L100 -> 0
B102: Check balance | C102: =C41-(C50+C54) -> 0 | D102: =D41-(D50+D54) -> 0 | E102: =E41-(E50+E54) -> 0 | F102: =F41-(F50+F54) -> 0 | G102: =G41-(G50+G54) -> 0 | H102: =H41-(H50+H54) -> 0 | I102: =I41-(I50+I54) -> 0 | J102: =J41-(J50+J54) -> 0 | ... L102: =L41-(L50+L54) -> 0
B103: Calculated Operating Cashflow | C103: =SUM(C58:C72) -> 0 | D103: =SUM(D58:D72) -> 0 | E103: =SUM(E58:E72) -> 0 | F103: =SUM(F58:F72) -> 0 | G103: =SUM(G58:G72) -> 0 | H103: =SUM(H58:H72) -> 0 | I103: =SUM(I58:I72) -> 0 | J103: =SUM(J58:J72) -> 0 | ... L103: =SUM(L58:L72) -> 0
B104: Check Operating Cashflow | C104: =C73-C103 -> 0 | D104: =D73-D103 -> 0 | E104: =E73-E103 -> 0 | F104: =F73-F103 -> 0 | G104: =G73-G103 -> 0 | H104: =H73-H103 -> 0 | I104: =I73-I103 -> 0 | J104: =J73-J103 -> 0 | ... L104: =L73-L103 -> 0
B105: Calculated Investing Cashflow | C105: =SUM(C74:C79) -> 0 | D105: =SUM(D74:D79) -> 0 | E105: =SUM(E74:E79) -> 0 | F105: =SUM(F74:F79) -> 0 | G105: =SUM(G74:G79) -> 0 | H105: =SUM(H74:H79) -> 0 | I105: =SUM(I74:I79) -> 0 | J105: =SUM(J74:J79) -> 0 | ... L105: =SUM(L74:L79) -> 0
B106: Check Investing Cashflow | C106: =C80-C105 -> 0 | D106: =D80-D105 -> 0 | E106: =E80-E105 -> 0 | F106: =F80-F105 -> 0 | G106: =G80-G105 -> 0 | H106: =H80-H105 -> 0 | I106: =I80-I105 -> 0 | J106: =J80-J105 -> 0 | ... L106: =L80-L105 -> 0
B107: Calculated Financing Cashflow | C107: =SUM(C81:C87) -> 0 | D107: =SUM(D81:D87) -> 0 | E107: =SUM(E81:E87) -> 0 | F107: =SUM(F81:F87) -> 0 | G107: =SUM(G81:G87) -> 0 | H107: =SUM(H81:H87) -> 0 | I107: =SUM(I81:I87) -> 0 | J107: =SUM(J81:J87) -> 0 | ... L107: =SUM(L81:L87) -> 0
B108: Check Financing Cashflow | C108: =C88-C107 -> 0 | D108: =D88-D107 -> 0 | E108: =E88-E107 -> 0 | F108: =F88-F107 -> 0 | G108: =G88-G107 -> 0 | H108: =H88-H107 -> 0 | I108: =I88-I107 -> 0 | J108: =J88-J107 -> 0 | ... L108: =L88-L107 -> 0
B109: Calculated End Cash | C109: =C73+C80+C88+C90 -> 0 | D109: =D73+D80+D88+D90 -> 0 | E109: =E73+E80+E88+E90 -> 0 | F109: =F73+F80+F88+F90 -> 0 | G109: =G73+G80+G88+G90 -> 0 | H109: =H73+H80+H88+H90 -> 0 | I109: =I73+I80+I88+I90 -> 0 | J109: =J73+J80+J88+J90 -> 0 | ... L109: =L73+L80+L88+L90 -> 0
B110: Check End Cash | C110: =C91-C109 -> 0 | D110: =D91-D109 -> 0 | E110: =E91-E109 -> 0 | F110: =F91-F109 -> 0 | G110: =G91-G109 -> 0 | H110: =H91-H109 -> 0 | I110: =I91-I109 -> 0 | J110: =J91-J109 -> 0 | ... L110: =L91-L109 -> 0
B112: Other data
B113: Shares outstanding
B114: Dividends per share
B115: Depreciation
B116: Amortization
B117: Tax rate | C117: =(C17)/C16 -> #DIV/0! | D117: =(D17)/D16 -> #DIV/0! | E117: =(-1*E17)/E16 -> #DIV/0! | F117: =(-1*F17)/F16 -> #DIV/0! | G117: =(-1*G17)/G16 -> #DIV/0! | H117: =(-1*H17)/H16 -> #DIV/0!
B118: Employees
B119: Gross PP&E
B120: Accumulated depreciation
B121: Gross intangible assets
B122: Accumulated amortization
B125: Growth rates Income Statement
B126: Revenue | D126: =IF(C5=0, IF(D5=0,0,IF(D5>0,1,-1)), (D5-C5)/ABS(C5) ) -> 0 | E126: =IF(D5=0, IF(E5=0,0,IF(E5>0,1,-1)), (E5-D5)/ABS(D5) ) -> 0 | F126: =IF(E5=0, IF(F5=0,0,IF(F5>0,1,-1)), (F5-E5)/ABS(E5) ) -> 0 | G126: =IF(F5=0, IF(G5=0,0,IF(G5>0,1,-1)), (G5-F5)/ABS(F5) ) -> 0 | H126: =IF(G5=0, IF(H5=0,0,IF(H5>0,1,-1)), (H5-G5)/ABS(G5) ) -> 0
B127: COGS | D127: =IF(C6=0, IF(D6=0,0,IF(D6>0,1,-1)), (D6-C6)/ABS(C6) ) -> 0 | E127: =IF(D6=0, IF(E6=0,0,IF(E6>0,1,-1)), (E6-D6)/ABS(D6) ) -> 0 | F127: =IF(E6=0, IF(F6=0,0,IF(F6>0,1,-1)), (F6-E6)/ABS(E6) ) -> 0 | G127: =IF(F6=0, IF(G6=0,0,IF(G6>0,1,-1)), (G6-F6)/ABS(F6) ) -> 0 | H127: =IF(G6=0, IF(H6=0,0,IF(H6>0,1,-1)), (H6-G6)/ABS(G6) ) -> 0
B128: Gross Profit | D128: =IF(C7=0, IF(D7=0,0,IF(D7>0,1,-1)), (D7-C7)/ABS(C7) ) -> 0 | E128: =IF(D7=0, IF(E7=0,0,IF(E7>0,1,-1)), (E7-D7)/ABS(D7) ) -> 0 | F128: =IF(E7=0, IF(F7=0,0,IF(F7>0,1,-1)), (F7-E7)/ABS(E7) ) -> 0 | G128: =IF(F7=0, IF(G7=0,0,IF(G7>0,1,-1)), (G7-F7)/ABS(F7) ) -> 0 | H128: =IF(G7=0, IF(H7=0,0,IF(H7>0,1,-1)), (H7-G7)/ABS(G7) ) -> 0
B129: R&D | D129: =IF(C8=0, IF(D8=0,0,IF(D8>0,1,-1)), (D8-C8)/ABS(C8) ) -> 0 | E129: =IF(D8=0, IF(E8=0,0,IF(E8>0,1,-1)), (E8-D8)/ABS(D8) ) -> 0 | F129: =IF(E8=0, IF(F8=0,0,IF(F8>0,1,-1)), (F8-E8)/ABS(E8) ) -> 0 | G129: =IF(F8=0, IF(G8=0,0,IF(G8>0,1,-1)), (G8-F8)/ABS(F8) ) -> 0 | H129: =IF(G8=0, IF(H8=0,0,IF(H8>0,1,-1)), (H8-G8)/ABS(G8) ) -> 0
B130: SG&A | D130: =IF(C9=0, IF(D9=0,0,IF(D9>0,1,-1)), (D9-C9)/ABS(C9) ) -> 0 | E130: =IF(D9=0, IF(E9=0,0,IF(E9>0,1,-1)), (E9-D9)/ABS(D9) ) -> 0 | F130: =IF(E9=0, IF(F9=0,0,IF(F9>0,1,-1)), (F9-E9)/ABS(E9) ) -> 0 | G130: =IF(F9=0, IF(G9=0,0,IF(G9>0,1,-1)), (G9-F9)/ABS(F9) ) -> 0 | H130: =IF(G9=0, IF(H9=0,0,IF(H9>0,1,-1)), (H9-G9)/ABS(G9) ) -> 0
B131: OpEx | D131: =IF(C11=0, IF(D11=0,0,IF(D11>0,1,-1)), (D11-C11)/ABS(C11) ) -> 0 | E131: =IF(D11=0, IF(E11=0,0,IF(E11>0,1,-1)), (E11-D11)/ABS(D11) ) -> 0 | F131: =IF(E11=0, IF(F11=0,0,IF(F11>0,1,-1)), (F11-E11)/ABS(E11) ) -> 0 | G131: =IF(F11=0, IF(G11=0,0,IF(G11>0,1,-1)), (G11-F11)/ABS(F11) ) -> 0 | H131: =IF(G11=0, IF(H11=0,0,IF(H11>0,1,-1)), (H11-G11)/ABS(G11) ) -> 0
B132: Operating income | D132: =IF(C12=0, IF(D12=0,0,IF(D12>0,1,-1)), (D12-C12)/ABS(C12) ) -> 0 | E132: =IF(D12=0, IF(E12=0,0,IF(E12>0,1,-1)), (E12-D12)/ABS(D12) ) -> 0 | F132: =IF(E12=0, IF(F12=0,0,IF(F12>0,1,-1)), (F12-E12)/ABS(E12) ) -> 0 | G132: =IF(F12=0, IF(G12=0,0,IF(G12>0,1,-1)), (G12-F12)/ABS(F12) ) -> 0 | H132: =IF(G12=0, IF(H12=0,0,IF(H12>0,1,-1)), (H12-G12)/ABS(G12) ) -> 0
B133: Income before taxes | D133: =IF(C16=0, IF(D16=0,0,IF(D16>0,1,-1)), (D16-C16)/ABS(C16) ) -> 0 | E133: =IF(D16=0, IF(E16=0,0,IF(E16>0,1,-1)), (E16-D16)/ABS(D16) ) -> 0 | F133: =IF(E16=0, IF(F16=0,0,IF(F16>0,1,-1)), (F16-E16)/ABS(E16) ) -> 0 | G133: =IF(F16=0, IF(G16=0,0,IF(G16>0,1,-1)), (G16-F16)/ABS(F16) ) -> 0 | H133: =IF(G16=0, IF(H16=0,0,IF(H16>0,1,-1)), (H16-G16)/ABS(G16) ) -> 0
B134: Net income | D134: =IF(C18=0, IF(D18=0,0,IF(D18>0,1,-1)), (D18-C18)/ABS(C18) ) -> 0 | E134: =IF(D18=0, IF(E18=0,0,IF(E18>0,1,-1)), (E18-D18)/ABS(D18) ) -> 0 | F134: =IF(E18=0, IF(F18=0,0,IF(F18>0,1,-1)), (F18-E18)/ABS(E18) ) -> 0 | G134: =IF(F18=0, IF(G18=0,0,IF(G18>0,1,-1)), (G18-F18)/ABS(F18) ) -> 0 | H134: =IF(G18=0, IF(H18=0,0,IF(H18>0,1,-1)), (H18-G18)/ABS(G18) ) -> 0
B136: Margins
B137: Gross margin | C137: =C7/C5 -> #DIV/0! | D137: =D7/D5 -> #DIV/0! | E137: =E7/E5 -> #DIV/0! | F137: =F7/F5 -> #DIV/0! | G137: =G7/G5 -> #DIV/0! | H137: =H7/H5 -> #DIV/0!
B138: Operating margin | C138: =C12/C5 -> #DIV/0! | D138: =D12/D5 -> #DIV/0! | E138: =E12/E5 -> #DIV/0! | F138: =F12/F5 -> #DIV/0! | G138: =G12/G5 -> #DIV/0! | H138: =H12/H5 -> #DIV/0!
B139: Net margin | C139: =C18/C5 -> #DIV/0! | D139: =D18/D5 -> #DIV/0! | E139: =E18/E5 -> #DIV/0! | F139: =F18/F5 -> #DIV/0! | G139: =G18/G5 -> #DIV/0! | H139: =H18/H5 -> #DIV/0!
B141: Company specifics
B144: Revenue breakdown
B147: Company specific metrics

Sheet Statement Q
B2: Date | C2: 31.03.2024 | D2: 30.06.2024 | E2: 30.09.2024 | F2: 31.12.2024 | G2: 31.03.2025 | H2: 30.06.2025 | I2: 30.09.2025 | J2: 31.12.2025
B3: Q | C3: Q1 2024 | D3: Q2 2024 | E3: Q3 2024 | F3: Q4 2024 | G3: Q1 2025 | H3: Q2 2025 | I3: Q3 2025 | J3: Q4 2025 | P3: =I3 -> Q3 2025 | Q3: =J3 -> Q4 2025 | R3: Growth Rate
B4: Income statement | N4: TTM | P4: Quarter compare
B5: Revenue | N5: =SUM(G5:J5) -> 0 | P5: =I5 -> 0 | Q5: =J5 -> 0 | R5: =IF(P5=0, IF(Q5=0,0,IF(Q5>0,1,-1)), (Q5-P5)/ABS(P5) ) -> 0
B6: COGS | N6: =SUM(G6:J6) -> 0 | P6: =I6 -> 0 | Q6: =J6 -> 0 | R6: =IF(P6=0, IF(Q6=0,0,IF(Q6>0,1,-1)), (Q6-P6)/ABS(P6) ) -> 0
B7: Gross Profit | C7: =C5-C6 -> 0 | D7: =D5-D6 -> 0 | E7: =E5-E6 -> 0 | F7: =F5-F6 -> 0 | G7: =G5-G6 -> 0 | H7: =H5-H6 -> 0 | I7: =I5-I6 -> 0 | J7: =J5-J6 -> 0 | N7: =SUM(G7:J7) -> 0 | P7: =I7 -> 0 | Q7: =J7 -> 0 | R7: =IF(P7=0, IF(Q7=0,0,IF(Q7>0,1,-1)), (Q7-P7)/ABS(P7) ) -> 0
B8: R&D | N8: =SUM(G8:J8) -> 0 | P8: =I8 -> 0 | Q8: =J8 -> 0 | R8: =IF(P8=0, IF(Q8=0,0,IF(Q8>0,1,-1)), (Q8-P8)/ABS(P8) ) -> 0
B9: Sales and marketing | N9: =SUM(G9:J9) -> 0 | P9: =I9 -> 0 | Q9: =J9 -> 0 | R9: =IF(P9=0, IF(Q9=0,0,IF(Q9>0,1,-1)), (Q9-P9)/ABS(P9) ) -> 0
B10: General and administrative | N10: =SUM(G10:J10) -> 0 | P10: =I10 -> 0 | Q10: =J10 -> 0 | R10: =IF(P10=0, IF(Q10=0,0,IF(Q10>0,1,-1)), (Q10-P10)/ABS(P10) ) -> 0
B11: OpEx | C11: =SUM(C8:C10) -> 0 | D11: =SUM(D8:D10) -> 0 | E11: =SUM(E8:E10) -> 0 | F11: =SUM(F8:F10) -> 0 | G11: =SUM(G8:G10) -> 0 | H11: =SUM(H8:H10) -> 0 | I11: =SUM(I8:I10) -> 0 | J11: =SUM(J8:J10) -> 0 | N11: =SUM(G11:J11) -> 0 | P11: =I11 -> 0 | Q11: =J11 -> 0 | R11: =IF(P11=0, IF(Q11=0,0,IF(Q11>0,1,-1)), (Q11-P11)/ABS(P11) ) -> 0
B12: Operating income | N12: =SUM(G12:J12) -> 0 | P12: =I12 -> 0 | Q12: =J12 -> 0 | R12: =IF(P12=0, IF(Q12=0,0,IF(Q12>0,1,-1)), (Q12-P12)/ABS(P12) ) -> 0
B13: Other income | N13: =SUM(G13:J13) -> 0 | P13: =I13 -> 0 | Q13: =J13 -> 0 | R13: =IF(P13=0, IF(Q13=0,0,IF(Q13>0,1,-1)), (Q13-P13)/ABS(P13) ) -> 0
B14: Other expense | N14: =SUM(G14:J14) -> 0 | P14: =I14 -> 0 | Q14: =J14 -> 0 | R14: =IF(P14=0, IF(Q14=0,0,IF(Q14>0,1,-1)), (Q14-P14)/ABS(P14) ) -> 0
B15: Interest income | N15: =SUM(G15:J15) -> 0 | P15: =I15 -> 0 | Q15: =J15 -> 0 | R15: =IF(P15=0, IF(Q15=0,0,IF(Q15>0,1,-1)), (Q15-P15)/ABS(P15) ) -> 0
B16: Income before taxes | N16: =SUM(G16:J16) -> 0 | P16: =I16 -> 0 | Q16: =J16 -> 0 | R16: =IF(P16=0, IF(Q16=0,0,IF(Q16>0,1,-1)), (Q16-P16)/ABS(P16) ) -> 0
B17: Income tax expense/benefit | N17: =SUM(G17:J17) -> 0 | P17: =I17 -> 0 | Q17: =J17 -> 0 | R17: =IF(P17=0, IF(Q17=0,0,IF(Q17>0,1,-1)), (Q17-P17)/ABS(P17) ) -> 0
B18: Net income | N18: =SUM(G18:J18) -> 0 | P18: =I18 -> 0 | Q18: =J18 -> 0 | R18: =IF(P18=0, IF(Q18=0,0,IF(Q18>0,1,-1)), (Q18-P18)/ABS(P18) ) -> 0
B19: Basic Shares outstanding avg | N19: =AVERAGE(G19:J19) -> #DIV/0! | P19: =I19 -> 0 | Q19: =J19 -> 0 | R19: =IF(P19=0, IF(Q19=0,0,IF(Q19>0,1,-1)), (Q19-P19)/ABS(P19) ) -> 0
B20: Diluted Shares outstanding avg | N20: =AVERAGE((G20:J20)) -> #DIV/0! | P20: =I20 -> 0 | Q20: =J20 -> 0 | R20: =IF(P20=0, IF(Q20=0,0,IF(Q20>0,1,-1)), (Q20-P20)/ABS(P20) ) -> 0
B21: Basic EPS | N21: =N18/N19 -> #DIV/0! | P21: =I21 -> 0 | Q21: =J21 -> 0 | R21: =IF(P21=0, IF(Q21=0,0,IF(Q21>0,1,-1)), (Q21-P21)/ABS(P21) ) -> 0
B22: Diluted EPS | N22: =N18/N20 -> #DIV/0! | P22: =I22 -> 0 | Q22: =J22 -> 0 | R22: =IF(P22=0, IF(Q22=0,0,IF(Q22>0,1,-1)), (Q22-P22)/ABS(P22) ) -> 0
B24: Balance sheet
B25: Cash and cash equivalents | N25: =J25 -> 0
B26: Short-term investments | N26: =J26 -> 0
B27: Acc receivable | N27: =J27 -> 0
B28: Deferred cost of revenues | N28: =J28 -> 0
B29: Income tax receivable | N29: =J29 -> 0
B30: Prepaid expenses & Other current assets | N30: =J30 -> 0
B31: Current assets | N31: =J31 -> 0
B32: PP&E | N32: =J32 -> 0
B33: Goodwill | N33: =J33 -> 0
B34: Intangible assets | N34: =J34 -> 0
B35: Operating lease right of use | N35: =J35 -> 0
B36: Long term investments | N36: =J36 -> 0
... B39: Other assets | N39: =J39 -> 0
B40: Long term assets | C40: =SUM(C32:C39) -> 0 | D40: =SUM(D32:D39) -> 0 | E40: =SUM(E32:E39) -> 0 | F40: =SUM(F32:F39) -> 0 | G40: =SUM(G32:G39) -> 0 | H40: =SUM(H32:H39) -> 0 | I40: =SUM(I32:I39) -> 0 | J40: =SUM(J32:J39) -> 0 | N40: =J40 -> 0
B41: Total assets | N41: =J41 -> 0
B42: Acc payable | N42: =J42 -> 0
B43: Deferred revenues | N43: =J43 -> 0
B44: Income tax payable | N44: =J44 -> 0
B45: Accrued expenses and other current | N45: =J45 -> 0
B46: Current liabilities | N46: =J46 -> 0
B47: Long term obligation operating lease | N47: =J47 -> 0
B48: Deferred tax liabilities | N48: =J48 -> 0
B49: Long term liabilities | C49: =SUM(C47:C48) -> 0 | D49: =SUM(D47:D48) -> 0 | E49: =SUM(E47:E48) -> 0 | F49: =SUM(F47:F48) -> 0 | G49: =SUM(G47:G48) -> 0 | H49: =SUM(H47:H48) -> 0 | I49: =SUM(I47:I48) -> 0 | J49: =SUM(J47:J48) -> 0 | N49: =J49 -> 0
B50: Total liabilities | N50: =J50 -> 0
B51: Common stock par value | N51: =J51 -> 0
B52: Additional paid-in capital | N52: =J52 -> 0
B53: Retained earnings | N53: =J53 -> 0
B54: Stockholder equity | N54: =J54 -> 0
B55: Total liabilities and equity | N55: =J55 -> 0
B57: Cashflow statement
B58: Net income | C58: =C18 -> 0 | D58: =D18 -> 0 | E58: =E18 -> 0 | F58: =F18 -> 0 | G58: =G18 -> 0 | H58: =H18 -> 0 | I58: =I18 -> 0 | J58: =J18 -> 0 | N58: =SUM(G58:J58) -> 0
B59: D&A | N59: =SUM(G59:J59) -> 0
B60: Deferred income taxes | N60: =SUM(G60:J60) -> 0
B61: Stock-based compensation | N61: =SUM(G61:J61) -> 0
B62: Accretion on marketable securitirs | N62: =SUM(G62:J62) -> 0
B63: Gain sale capitalized software | N63: =SUM(G63:J63) -> 0
B64: Loss disposal leasehold improvments | N64: =SUM(G64:J64) -> 0
B65: Impairment on capitalized software | N65: =SUM(G65:J65) -> 0
B66: Change deferred revenue | N66: =SUM(G66:J66) -> 0
B67: Change acc receivable | N67: =SUM(G67:J67) -> 0
B68: Change deferred cost of revenues | N68: =SUM(G68:J68) -> 0
B69: Change prepaid expenses | N69: =SUM(G69:J69) -> 0
B70: Change acc payable | N70: =SUM(G70:J70) -> 0
... B92: Net increase/decrease in cash | N92: =SUM(G92:J92) -> 0
B93: Begin cash | N93: =G93 -> 0
B94: End cash | N94: =J94 -> 0
B96: Sanity checks
B97: Calculated Net Income | C97: =C5-C6-C11+C13+C14+C15+C17 -> 0 | D97: =D5-D6-D11+D13+D14++D15+D17 -> 0 | E97: =E5-E6-E11+E13+E14++E15+E17 -> 0 | F97: =F5-F6-F11+F13+F14++F15+F17 -> 0 | G97: =G5-G6-G11+G13+G14++G15+G17 -> 0 | H97: =H5-H6-H11+H13+H14++H15+H17 -> 0 | I97: =I5-I6-I11+I13+I14++I15+I17 -> 0 | J97: =J5-J6-J11+J13+J14++J15+J17 -> 0
B98: Check Net Income | C98: =C18-C97 -> 0 | D98: =D18-D97 -> 0 | E98: =E18-E97 -> 0 | F98: =F18-F97 -> 0 | G98: =G18-G97 -> 0 | H98: =H18-H97 -> 0 | I98: =I18-I97 -> 0 | J98: =J18-J97 -> 0
B99: Calculated Assets | C99: =SUM(C25:C30)+SUM(C32:C39) -> 0 | D99: =SUM(D25:D30)+SUM(D32:D39) -> 0 | E99: =SUM(E25:E30)+SUM(E32:E39) -> 0 | F99: =SUM(F25:F30)+SUM(F32:F39) -> 0 | G99: =SUM(G25:G30)+SUM(G32:G39) -> 0 | H99: =SUM(H25:H30)+SUM(H32:H39) -> 0 | I99: =SUM(I25:I30)+SUM(I32:I39) -> 0 | J99: =SUM(J25:J30)+SUM(J32:J39) -> 0
B100: Check Assets | C100: =C41-C99 -> 0 | D100: =D41-D99 -> 0 | E100: =E41-E99 -> 0 | F100: =F41-F99 -> 0 | G100: =G41-G99 -> 0 | H100: =H41-H99 -> 0 | I100: =I41-I99 -> 0 | J100: =J41-J99 -> 0
B101: Calculated Liabilities | C101: =SUM(C42:C45)+SUM(C47:C48) -> 0 | D101: =SUM(D42:D45)+SUM(D47:D48) -> 0 | E101: =SUM(E42:E45)+SUM(E47:E48) -> 0 | F101: =SUM(F42:F45)+SUM(F47:F48) -> 0 | G101: =SUM(G42:G45)+SUM(G47:G48) -> 0 | H101: =SUM(H42:H45)+SUM(H47:H48) -> 0 | I101: =SUM(I42:I45)+SUM(I47:I48) -> 0 | J101: =SUM(J42:J45)+SUM(J47:J48) -> 0
B102: Check Liabilities | C102: =C50-C101 -> 0 | D102: =D50-D101 -> 0 | E102: =E50-E101 -> 0 | F102: =F50-F101 -> 0 | G102: =G50-G101 -> 0 | H102: =H50-H101 -> 0 | I102: =I50-I101 -> 0 | J102: =J50-J101 -> 0
B103: Calculated Stockholder Equity | C103: =SUM(C51:C53) -> 0 | D103: =SUM(D51:D53) -> 0 | E103: =SUM(E51:E53) -> 0 | F103: =SUM(F51:F53) -> 0 | G103: =SUM(G51:G53) -> 0 | H103: =SUM(H51:H53) -> 0 | I103: =SUM(I51:I53) -> 0 | J103: =SUM(J51:J53) -> 0
B104: Check Stockholder Equity | C104: =C54-C103 -> 0 | D104: =D54-D103 -> 0 | E104: =E54-E103 -> 0 | F104: =F54-F103 -> 0 | G104: =G54-G103 -> 0 | H104: =H54-H103 -> 0 | I104: =I54-I103 -> 0 | J104: =J54-J103 -> 0
B105: Check balance | C105: =C41-(C50+C54) -> 0 | D105: =D41-(D50+D54) -> 0 | E105: =E41-(E50+E54) -> 0 | F105: =F41-(F50+F54) -> 0 | G105: =G41-(G50+G54) -> 0 | H105: =H41-(H50+H54) -> 0 | I105: =I41-(I50+I54) -> 0 | J105: =J41-(J50+J54) -> 0
B106: Calculated Operating Cashflow | C106: =SUM(C58:C72) -> 0 | D106: =SUM(D58:D72) -> 0 | E106: =SUM(E58:E72) -> 0 | F106: =SUM(F58:F72) -> 0 | G106: =SUM(G58:G72) -> 0 | H106: =SUM(H58:H72) -> 0 | I106: =SUM(I58:I72) -> 0 | J106: =SUM(J58:J72) -> 0
B107: Check Operating Cashflow | C107: =C73-C106 -> 0 | D107: =D73-D106 -> 0 | E107: =E73-E106 -> 0 | F107: =F73-F106 -> 0 | G107: =G73-G106 -> 0 | H107: =H73-H106 -> 0 | I107: =I73-I106 -> 0 | J107: =J73-J106 -> 0
B108: Calculated Investing Cashflow | C108: =SUM(C74:C80) -> 0 | D108: =SUM(D74:D80) -> 0 | E108: =SUM(E74:E80) -> 0 | F108: =SUM(F74:F80) -> 0 | G108: =SUM(G74:G80) -> 0 | H108: =SUM(H74:H80) -> 0 | I108: =SUM(I74:I80) -> 0 | J108: =SUM(J74:J80) -> 0
B109: Check Investing Cashflow | C109: =C81-C108 -> 0 | D109: =D81-D108 -> 0 | E109: =E81-E108 -> 0 | F109: =F81-F108 -> 0 | G109: =G81-G108 -> 0 | H109: =H81-H108 -> 0 | I109: =I81-I108 -> 0 | J109: =J81-J108 -> 0
B110: Calculated Financing Cashflow | C110: =SUM(C82:C90) -> 0 | D110: =SUM(D82:D90) -> 0 | E110: =SUM(E82:E90) -> 0 | F110: =SUM(F82:F90) -> 0 | G110: =SUM(G82:G90) -> 0 | H110: =SUM(H82:H90) -> 0 | I110: =SUM(I82:I90) -> 0 | J110: =SUM(J82:J90) -> 0
B111: Check Financing Cashflow | C111: =C91-C110 -> 0 | D111: =D91-D110 -> 0 | E111: =E91-E110 -> 0 | F111: =F91-F110 -> 0 | G111: =G91-G110 -> 0 | H111: =H91-H110 -> 0 | I111: =I91-I110 -> 0 | J111: =J91-J110 -> 0
B112: Calculated End Cash | C112: =C73+C81+C91+C93 -> 0 | D112: =D73+D81+D91+D93 -> 0 | E112: =E73+E81+E91+E93 -> 0 | F112: =F73+F81+F91+F93 -> 0 | G112: =G73+G81+G91+G93 -> 0 | H112: =H73+H81+H91+H93 -> 0 | I112: =I73+I81+I91+I93 -> 0 | J112: =J73+J81+J91+J93 -> 0
B113: Check End Cash | C113: =C94-C112 -> 0 | D113: =D94-D112 -> 0 | E113: =E94-E112 -> 0 | F113: =F94-F112 -> 0 | G113: =G94-G112 -> 0 | H113: =H94-H112 -> 0 | I113: =I94-I112 -> 0 | J113: =J94-J112 -> 0
B115: Other data
B116: Shares outstanding | N116: =J116 -> 0
B117: Dividends per share
B120: Company guidance next Quarter
B121: Revenue Lower
B122: Revenue Upper
B123: Actual Revenue | C123: =D5 -> 0 | D123: =E5 -> 0 | E123: =F5 -> 0 | F123: =G5 -> 0 | G123: =H5 -> 0 | H123: =I5 -> 0 | I123: =J5 -> 0 | J123: =K5 -> 0
B124: Result | C124: =IF(D5>C122, "BEAT", IF(D5<C121, "MISSED", "MET")) -> MET | D124: =IF(E5>D122, "BEAT", IF(E5<D121, "MISSED", "MET")) -> MET | E124: =IF(F5>E122, "BEAT", IF(F5<E121, "MISSED", "MET")) -> MET | F124: =IF(G5>F122, "BEAT", IF(G5<F121, "MISSED", "MET")) -> MET | G124: =IF(H5>G122, "BEAT", IF(H5<G121, "MISSED", "MET")) -> MET | H124: =IF(I5>H122, "BEAT", IF(I5<H121, "MISSED", "MET")) -> MET | I124: =IF(J5>I122, "BEAT", IF(J5<I121, "MISSED", "MET")) -> MET | J124: =IF(K5>J122, "BEAT", IF(K5<J121, "MISSED", "MET")) -> MET
B125: EPS Lower
B126: EPS Upper
B127: Actual EPS
B128: Result
B130: Company specifics
B133: Revenue breakdown
...

Sheet Statements
B2: Date | C2: ='Statement Y'!C2 -> 31.12.2020 | D2: ='Statement Y'!D2 -> 31.12.2021 | E2: ='Statement Y'!E2 -> 30.09.2022 | F2: ='Statement Y'!F2 -> 31.12.2023 | G2: ='Statement Y'!G2 -> 31.12.2024 | H2: ='Statement Y'!H2 -> 31.12.2025 | J2: ='Statement Q'!C2 -> 31.03.2024 | K2: ='Statement Q'!D2 -> 30.06.2024 | L2: ='Statement Q'!E2 -> 30.09.2024 | M2: ='Statement Q'!F2 -> 31.12.2024 | N2: ='Statement Q'!G2 -> 31.03.2025 | O2: ='Statement Q'!H2 -> 30.06.2025 | P2: ='Statement Q'!I2 -> 30.09.2025 | Q2: ='Statement Q'!J2 -> 31.12.2025
B3: FY | C3: ='Statement Y'!C3 -> 2020 | D3: ='Statement Y'!D3 -> 2021 | E3: ='Statement Y'!E3 -> 2022 | F3: ='Statement Y'!F3 -> 2023 | G3: ='Statement Y'!G3 -> 2024 | H3: ='Statement Y'!H3 -> 2025 | J3: ='Statement Q'!C3 -> Q1 2024 | K3: ='Statement Q'!D3 -> Q2 2024 | L3: ='Statement Q'!E3 -> Q3 2024 | M3: ='Statement Q'!F3 -> Q4 2024 | N3: ='Statement Q'!G3 -> Q1 2025 | O3: ='Statement Q'!H3 -> Q2 2025 | P3: ='Statement Q'!I3 -> Q3 2025 | Q3: ='Statement Q'!J3 -> Q4 2025 | S3: TTM
B4: Income statement
B5: Revenue | C5: ='Statement Y'!C5 -> 0 | D5: ='Statement Y'!D5 -> 0 | E5: ='Statement Y'!E5 -> 0 | F5: ='Statement Y'!F5 -> 0 | G5: ='Statement Y'!G5 -> 0 | H5: ='Statement Y'!H5 -> 0 | J5: ='Statement Q'!C5 -> 0 | K5: ='Statement Q'!D5 -> 0 | L5: ='Statement Q'!E5 -> 0 | M5: ='Statement Q'!F5 -> 0 | N5: ='Statement Q'!G5 -> 0 | O5: ='Statement Q'!H5 -> 0 | P5: ='Statement Q'!I5 -> 0 | Q5: ='Statement Q'!J5 -> 0 | S5: =SUM(N5:Q5) -> 0
B6: COGS | C6: ='Statement Y'!C6 -> 0 | D6: ='Statement Y'!D6 -> 0 | E6: ='Statement Y'!E6 -> 0 | F6: ='Statement Y'!F6 -> 0 | G6: ='Statement Y'!G6 -> 0 | H6: ='Statement Y'!H6 -> 0 | J6: ='Statement Q'!C6 -> 0 | K6: ='Statement Q'!D6 -> 0 | L6: ='Statement Q'!E6 -> 0 | M6: ='Statement Q'!F6 -> 0 | N6: ='Statement Q'!G6 -> 0 | O6: ='Statement Q'!H6 -> 0 | P6: ='Statement Q'!I6 -> 0 | Q6: ='Statement Q'!J6 -> 0 | S6: =SUM(N6:Q6) -> 0
B7: Gross Profit | C7: ='Statement Y'!C7 -> 0 | D7: ='Statement Y'!D7 -> 0 | E7: ='Statement Y'!E7 -> 0 | F7: ='Statement Y'!F7 -> 0 | G7: ='Statement Y'!G7 -> 0 | H7: ='Statement Y'!H7 -> 0 | J7: ='Statement Q'!C7 -> 0 | K7: ='Statement Q'!D7 -> 0 | L7: ='Statement Q'!E7 -> 0 | M7: ='Statement Q'!F7 -> 0 | N7: ='Statement Q'!G7 -> 0 | O7: ='Statement Q'!H7 -> 0 | P7: ='Statement Q'!I7 -> 0 | Q7: ='Statement Q'!J7 -> 0 | S7: =SUM(N7:Q7) -> 0
B8: R&D | C8: ='Statement Y'!C8 -> 0 | D8: ='Statement Y'!D8 -> 0 | E8: ='Statement Y'!E8 -> 0 | F8: ='Statement Y'!F8 -> 0 | G8: ='Statement Y'!G8 -> 0 | H8: ='Statement Y'!H8 -> 0 | J8: ='Statement Q'!C8 -> 0 | K8: ='Statement Q'!D8 -> 0 | L8: ='Statement Q'!E8 -> 0 | M8: ='Statement Q'!F8 -> 0 | N8: ='Statement Q'!G8 -> 0 | O8: ='Statement Q'!H8 -> 0 | P8: ='Statement Q'!I8 -> 0 | Q8: ='Statement Q'!J8 -> 0 | S8: =SUM(N8:Q8) -> 0
B9: Sales and marketing | C9: ='Statement Y'!C9 -> 0 | D9: ='Statement Y'!D9 -> 0 | E9: ='Statement Y'!E9 -> 0 | F9: ='Statement Y'!F9 -> 0 | G9: ='Statement Y'!G9 -> 0 | H9: ='Statement Y'!H9 -> 0 | J9: ='Statement Q'!C9 -> 0 | K9: ='Statement Q'!D9 -> 0 | L9: ='Statement Q'!E9 -> 0 | M9: ='Statement Q'!F9 -> 0 | N9: ='Statement Q'!G9 -> 0 | O9: ='Statement Q'!H9 -> 0 | P9: ='Statement Q'!I9 -> 0 | Q9: ='Statement Q'!J9 -> 0 | S9: =SUM(N9:Q9) -> 0
B10: General and administrative | C10: ='Statement Y'!C10 -> 0 | D10: ='Statement Y'!D10 -> 0 | E10: ='Statement Y'!E10 -> 0 | F10: ='Statement Y'!F10 -> 0 | G10: ='Statement Y'!G10 -> 0 | H10: ='Statement Y'!H10 -> 0 | J10: ='Statement Q'!C10 -> 0 | K10: ='Statement Q'!D10 -> 0 | L10: ='Statement Q'!E10 -> 0 | M10: ='Statement Q'!F10 -> 0 | N10: ='Statement Q'!G10 -> 0 | O10: ='Statement Q'!H10 -> 0 | P10: ='Statement Q'!I10 -> 0 | Q10: ='Statement Q'!J10 -> 0 | S10: =SUM(N10:Q10) -> 0
B11: OpEx | C11: ='Statement Y'!C11 -> 0 | D11: ='Statement Y'!D11 -> 0 | E11: ='Statement Y'!E11 -> 0 | F11: ='Statement Y'!F11 -> 0 | G11: ='Statement Y'!G11 -> 0 | H11: ='Statement Y'!H11 -> 0 | J11: ='Statement Q'!C11 -> 0 | K11: ='Statement Q'!D11 -> 0 | L11: ='Statement Q'!E11 -> 0 | M11: ='Statement Q'!F11 -> 0 | N11: ='Statement Q'!G11 -> 0 | O11: ='Statement Q'!H11 -> 0 | P11: ='Statement Q'!I11 -> 0 | Q11: ='Statement Q'!J11 -> 0 | S11: =SUM(N11:Q11) -> 0
B12: Operating income | C12: ='Statement Y'!C12 -> 0 | D12: ='Statement Y'!D12 -> 0 | E12: ='Statement Y'!E12 -> 0 | F12: ='Statement Y'!F12 -> 0 | G12: ='Statement Y'!G12 -> 0 | H12: ='Statement Y'!H12 -> 0 | J12: ='Statement Q'!C12 -> 0 | K12: ='Statement Q'!D12 -> 0 | L12: ='Statement Q'!E12 -> 0 | M12: ='Statement Q'!F12 -> 0 | N12: ='Statement Q'!G12 -> 0 | O12: ='Statement Q'!H12 -> 0 | P12: ='Statement Q'!I12 -> 0 | Q12: ='Statement Q'!J12 -> 0 | S12: =SUM(N12:Q12) -> 0
B13: EBITDA | C13: =C12+C56 -> 0 | D13: =D12+D56 -> 0 | E13: =E12+E56 -> 0 | F13: =F12+F56 -> 0 | G13: =G12+G56 -> 0 | H13: =H12+H56 -> 0 | J13: =J12+J56 -> 0 | K13: =K12+K56 -> 0 | L13: =L12+L56 -> 0 | M13: =M12+M56 -> 0 | N13: =N12+N56 -> 0 | O13: =O12+O56 -> 0 | P13: =P12+P56 -> 0 | Q13: =Q12+Q56 -> 0 | S13: =SUM(N13:Q13) -> 0
B14: Other income/expense | C14: ='Statement Y'!C13+'Statement Y'!C14 -> 0 | D14: ='Statement Y'!D13+'Statement Y'!D14 -> 0 | E14: ='Statement Y'!E13+'Statement Y'!E14 -> 0 | F14: ='Statement Y'!F13+'Statement Y'!F14 -> 0 | G14: ='Statement Y'!G13+'Statement Y'!G14 -> 0 | H14: ='Statement Y'!H13+'Statement Y'!H14 -> 0 | J14: ='Statement Q'!C13+'Statement Q'!C14 -> 0 | K14: ='Statement Q'!D13+'Statement Q'!D14 -> 0 | L14: ='Statement Q'!E13+'Statement Q'!E14 -> 0 | M14: ='Statement Q'!F13+'Statement Q'!F14 -> 0 | N14: ='Statement Q'!G13+'Statement Q'!G14 -> 0 | O14: ='Statement Q'!H13+'Statement Q'!H14 -> 0 | P14: ='Statement Q'!I13+'Statement Q'!I14 -> 0 | Q14: ='Statement Q'!J13+'Statement Q'!J14 -> 0 | S14: =SUM(N14:Q14) -> 0
B15: Interest income/expense | C15: ='Statement Y'!C15 -> 0 | D15: ='Statement Y'!D15 -> 0 | E15: ='Statement Y'!E15 -> 0 | F15: ='Statement Y'!F15 -> 0 | G15: ='Statement Y'!G15 -> 0 | H15: ='Statement Y'!H15 -> 0 | J15: ='Statement Q'!C15 -> 0 | K15: ='Statement Q'!D15 -> 0 | L15: ='Statement Q'!E15 -> 0 | M15: ='Statement Q'!F15 -> 0 | N15: ='Statement Q'!G15 -> 0 | O15: ='Statement Q'!H15 -> 0 | P15: ='Statement Q'!I15 -> 0 | Q15: ='Statement Q'!J15 -> 0 | S15: =SUM(N15:Q15) -> 0
B16: Income before taxes | C16: ='Statement Y'!C16 -> 0 | D16: ='Statement Y'!D16 -> 0 | E16: ='Statement Y'!E16 -> 0 | F16: ='Statement Y'!F16 -> 0 | G16: ='Statement Y'!G16 -> 0 | H16: ='Statement Y'!H16 -> 0 | J16: ='Statement Q'!C16 -> 0 | K16: ='Statement Q'!D16 -> 0 | L16: ='Statement Q'!E16 -> 0 | M16: ='Statement Q'!F16 -> 0 | N16: ='Statement Q'!G16 -> 0 | O16: ='Statement Q'!H16 -> 0 | P16: ='Statement Q'!I16 -> 0 | Q16: ='Statement Q'!J16 -> 0 | S16: =SUM(N16:Q16) -> 0
B17: Income tax expense/benefit | C17: ='Statement Y'!C17 -> 0 | D17: ='Statement Y'!D17 -> 0 | E17: ='Statement Y'!E17 -> 0 | F17: ='Statement Y'!F17 -> 0 | G17: ='Statement Y'!G17 -> 0 | H17: ='Statement Y'!H17 -> 0 | J17: ='Statement Q'!C17 -> 0 | K17: ='Statement Q'!D17 -> 0 | L17: ='Statement Q'!E17 -> 0 | M17: ='Statement Q'!F17 -> 0 | N17: ='Statement Q'!G17 -> 0 | O17: ='Statement Q'!H17 -> 0 | P17: ='Statement Q'!I17 -> 0 | Q17: ='Statement Q'!J17 -> 0 | S17: =SUM(N17:Q17) -> 0
B18: Net income | C18: ='Statement Y'!C18 -> 0 | D18: ='Statement Y'!D18 -> 0 | E18: ='Statement Y'!E18 -> 0 | F18: ='Statement Y'!F18 -> 0 | G18: ='Statement Y'!G18 -> 0 | H18: ='Statement Y'!H18 -> 0 | J18: ='Statement Q'!C18 -> 0 | K18: ='Statement Q'!D18 -> 0 | L18: ='Statement Q'!E18 -> 0 | M18: ='Statement Q'!F18 -> 0 | N18: ='Statement Q'!G18 -> 0 | O18: ='Statement Q'!H18 -> 0 | P18: ='Statement Q'!I18 -> 0 | Q18: ='Statement Q'!J18 -> 0 | S18: =SUM(N18:Q18) -> 0
B19: Diluted Shares outstanding avg | C19: ='Statement Y'!C20 -> 0 | D19: ='Statement Y'!D20 -> 0 | E19: ='Statement Y'!E20 -> 0 | F19: ='Statement Y'!F20 -> 0 | G19: ='Statement Y'!G20 -> 0 | H19: ='Statement Y'!H20 -> 0 | J19: ='Statement Q'!C20 -> 0 | K19: ='Statement Q'!D20 -> 0 | L19: ='Statement Q'!E20 -> 0 | M19: ='Statement Q'!F20 -> 0 | N19: ='Statement Q'!G20 -> 0 | O19: ='Statement Q'!H20 -> 0 | P19: ='Statement Q'!I20 -> 0 | Q19: ='Statement Q'!J20 -> 0 | S19: =AVERAGE(N19:Q19) -> 0
B20: Diluted EPS | C20: ='Statement Y'!C22 -> 0 | D20: ='Statement Y'!D22 -> 0 | E20: ='Statement Y'!E22 -> 0 | F20: ='Statement Y'!F22 -> 0 | G20: ='Statement Y'!G22 -> 0 | H20: ='Statement Y'!H22 -> 0 | J20: ='Statement Q'!C22 -> 0 | K20: ='Statement Q'!D22 -> 0 | L20: ='Statement Q'!E22 -> 0 | M20: ='Statement Q'!F22 -> 0 | N20: ='Statement Q'!G22 -> 0 | O20: ='Statement Q'!H22 -> 0 | P20: ='Statement Q'!I22 -> 0 | Q20: ='Statement Q'!J22 -> 0 | S20: =S18/S19 -> #DIV/0!
B22: Balance sheet
B23: Cash and cash equivalents | C23: ='Statement Y'!C25+'Statement Y'!C26 -> 0 | D23: ='Statement Y'!D25+'Statement Y'!D26 -> 0 | E23: ='Statement Y'!E25+'Statement Y'!E26 -> 0 | F23: ='Statement Y'!F25+'Statement Y'!F26 -> 0 | G23: ='Statement Y'!G25+'Statement Y'!G26 -> 0 | H23: ='Statement Y'!H25+'Statement Y'!H26 -> 0 | J23: ='Statement Q'!C25+'Statement Q'!C26 -> 0 | K23: ='Statement Q'!D25+'Statement Q'!D26 -> 0 | L23: ='Statement Q'!E25+'Statement Q'!E26 -> 0 | M23: ='Statement Q'!F25+'Statement Q'!F26 -> 0 | N23: ='Statement Q'!G25+'Statement Q'!G26 -> 0 | O23: ='Statement Q'!H25+'Statement Q'!H26 -> 0 | P23: ='Statement Q'!I25+'Statement Q'!I26 -> 0 | Q23: ='Statement Q'!J25+'Statement Q'!J26 -> 0 | S23: =Q23 -> 0
B24: Acc receivable | C24: ='Statement Y'!C27 -> 0 | D24: ='Statement Y'!D27 -> 0 | E24: ='Statement Y'!E27 -> 0 | F24: ='Statement Y'!F27 -> 0 | G24: ='Statement Y'!G27 -> 0 | H24: ='Statement Y'!H27 -> 0 | J24: ='Statement Q'!C27 -> 0 | K24: ='Statement Q'!D27 -> 0 | L24: ='Statement Q'!E27 -> 0 | M24: ='Statement Q'!F27 -> 0 | N24: ='Statement Q'!G27 -> 0 | O24: ='Statement Q'!H27 -> 0 | P24: ='Statement Q'!I27 -> 0 | Q24: ='Statement Q'!J27 -> 0 | S24: =Q24 -> 0
B25: Deferred cost of revenues | C25: ='Statement Y'!C28 -> 0 | D25: ='Statement Y'!D28 -> 0 | E25: ='Statement Y'!E28 -> 0 | F25: ='Statement Y'!F28 -> 0 | G25: ='Statement Y'!G28 -> 0 | H25: ='Statement Y'!H28 -> 0 | J25: ='Statement Q'!C28 -> 0 | K25: ='Statement Q'!D28 -> 0 | L25: ='Statement Q'!E28 -> 0 | M25: ='Statement Q'!F28 -> 0 | N25: ='Statement Q'!G28 -> 0 | O25: ='Statement Q'!H28 -> 0 | P25: ='Statement Q'!I28 -> 0 | Q25: ='Statement Q'!J28 -> 0 | S25: =Q25 -> 0
B26: Income tax receivable | C26: ='Statement Y'!C29 -> 0 | D26: ='Statement Y'!D29 -> 0 | E26: ='Statement Y'!E29 -> 0 | F26: ='Statement Y'!F29 -> 0 | G26: ='Statement Y'!G29 -> 0 | H26: ='Statement Y'!H29 -> 0 | J26: ='Statement Q'!C29 -> 0 | K26: ='Statement Q'!D29 -> 0 | L26: ='Statement Q'!E29 -> 0 | M26: ='Statement Q'!F29 -> 0 | N26: ='Statement Q'!G29 -> 0 | O26: ='Statement Q'!H29 -> 0 | P26: ='Statement Q'!I29 -> 0 | Q26: ='Statement Q'!J29 -> 0 | S26: =Q26 -> 0
B27: Prepaid expenses & Other current assets | C27: ='Statement Y'!C30 -> 0 | D27: ='Statement Y'!D30 -> 0 | E27: ='Statement Y'!E30 -> 0 | F27: ='Statement Y'!F30 -> 0 | G27: ='Statement Y'!G30 -> 0 | H27: ='Statement Y'!H30 -> 0 | J27: ='Statement Q'!C30 -> 0 | K27: ='Statement Q'!D30 -> 0 | L27: ='Statement Q'!E30 -> 0 | M27: ='Statement Q'!F30 -> 0 | N27: ='Statement Q'!G30 -> 0 | O27: ='Statement Q'!H30 -> 0 | P27: ='Statement Q'!I30 -> 0 | Q27: ='Statement Q'!J30 -> 0 | S27: =Q27 -> 0
B28: Current assets | C28: ='Statement Y'!C31 -> 0 | D28: ='Statement Y'!D31 -> 0 | E28: ='Statement Y'!E31 -> 0 | F28: ='Statement Y'!F31 -> 0 | G28: ='Statement Y'!G31 -> 0 | H28: ='Statement Y'!H31 -> 0 | J28: ='Statement Q'!C31 -> 0 | K28: ='Statement Q'!D31 -> 0 | L28: ='Statement Q'!E31 -> 0 | M28: ='Statement Q'!F31 -> 0 | N28: ='Statement Q'!G31 -> 0 | O28: ='Statement Q'!H31 -> 0 | P28: ='Statement Q'!I31 -> 0 | Q28: ='Statement Q'!J31 -> 0 | S28: =Q28 -> 0
B29: PP&E | C29: ='Statement Y'!C32 -> 0 | D29: ='Statement Y'!D32 -> 0 | E29: ='Statement Y'!E32 -> 0 | F29: ='Statement Y'!F32 -> 0 | G29: ='Statement Y'!G32 -> 0 | H29: ='Statement Y'!H32 -> 0 | J29: ='Statement Q'!C32 -> 0 | K29: ='Statement Q'!D32 -> 0 | L29: ='Statement Q'!E32 -> 0 | M29: ='Statement Q'!F32 -> 0 | N29: ='Statement Q'!G32 -> 0 | O29: ='Statement Q'!H32 -> 0 | P29: ='Statement Q'!I32 -> 0 | Q29: ='Statement Q'!J32 -> 0 | S29: =Q29 -> 0
B30: Goodwill | C30: ='Statement Y'!C33 -> 0 | D30: ='Statement Y'!D33 -> 0 | E30: ='Statement Y'!E33 -> 0 | F30: ='Statement Y'!F33 -> 0 | G30: ='Statement Y'!G33 -> 0 | H30: ='Statement Y'!H33 -> 0 | J30: ='Statement Q'!C33 -> 0 | K30: ='Statement Q'!D33 -> 0 | L30: ='Statement Q'!E33 -> 0 | M30: ='Statement Q'!F33 -> 0 | N30: ='Statement Q'!G33 -> 0 | O30: ='Statement Q'!H33 -> 0 | P30: ='Statement Q'!I33 -> 0 | Q30: ='Statement Q'!J33 -> 0 | S30: =Q30 -> 0
B31: Intangible assets | C31: ='Statement Y'!C34 -> 0 | D31: ='Statement Y'!D34 -> 0 | E31: ='Statement Y'!E34 -> 0 | F31: ='Statement Y'!F34 -> 0 | G31: ='Statement Y'!G34 -> 0 | H31: ='Statement Y'!H34 -> 0 | J31: ='Statement Q'!C34 -> 0 | K31: ='Statement Q'!D34 -> 0 | L31: ='Statement Q'!E34 -> 0 | M31: ='Statement Q'!F34 -> 0 | N31: ='Statement Q'!G34 -> 0 | O31: ='Statement Q'!H34 -> 0 | P31: ='Statement Q'!I34 -> 0 | Q31: ='Statement Q'!J34 -> 0 | S31: =Q31 -> 0
B32: Operating lease right of use | C32: ='Statement Y'!C35 -> 0 | D32: ='Statement Y'!D35 -> 0 | E32: ='Statement Y'!E35 -> 0 | F32: ='Statement Y'!F35 -> 0 | G32: ='Statement Y'!G35 -> 0 | H32: ='Statement Y'!H35 -> 0 | J32: ='Statement Q'!C35 -> 0 | K32: ='Statement Q'!D35 -> 0 | L32: ='Statement Q'!E35 -> 0 | M32: ='Statement Q'!F35 -> 0 | N32: ='Statement Q'!G35 -> 0 | O32: ='Statement Q'!H35 -> 0 | P32: ='Statement Q'!I35 -> 0 | Q32: ='Statement Q'!J35 -> 0 | S32: =Q32 -> 0
B33: Long term investments | C33: ='Statement Y'!C36 -> 0 | D33: ='Statement Y'!D36 -> 0 | E33: ='Statement Y'!E36 -> 0 | F33: ='Statement Y'!F36 -> 0 | G33: ='Statement Y'!G36 -> 0 | H33: ='Statement Y'!H36 -> 0 | J33: ='Statement Q'!C36 -> 0 | K33: ='Statement Q'!D36 -> 0 | L33: ='Statement Q'!E36 -> 0 | M33: ='Statement Q'!F36 -> 0 | N33: ='Statement Q'!G36 -> 0 | O33: ='Statement Q'!H36 -> 0 | P33: ='Statement Q'!I36 -> 0 | Q33: ='Statement Q'!J36 -> 0 | S33: =Q33 -> 0
B34: Deferred tax assets | C34: ='Statement Y'!C37 -> 0 | D34: ='Statement Y'!D37 -> 0 | E34: ='Statement Y'!E37 -> 0 | F34: ='Statement Y'!F37 -> 0 | G34: ='Statement Y'!G37 -> 0 | H34: ='Statement Y'!H37 -> 0 | J34: ='Statement Q'!C37 -> 0 | K34: ='Statement Q'!D37 -> 0 | L34: ='Statement Q'!E37 -> 0 | M34: ='Statement Q'!F37 -> 0 | N34: ='Statement Q'!G37 -> 0 | O34: ='Statement Q'!H37 -> 0 | P34: ='Statement Q'!I37 -> 0 | Q34: ='Statement Q'!J37 -> 0 | S34: =Q34 -> 0
B35: Restricted cash | C35: ='Statement Y'!C38 -> 0 | D35: ='Statement Y'!D38 -> 0 | E35: ='Statement Y'!E38 -> 0 | F35: ='Statement Y'!F38 -> 0 | G35: ='Statement Y'!G38 -> 0 | H35: ='Statement Y'!H38 -> 0 | J35: ='Statement Q'!C38 -> 0 | K35: ='Statement Q'!D38 -> 0 | L35: ='Statement Q'!E38 -> 0 | M35: ='Statement Q'!F38 -> 0 | N35: ='Statement Q'!G38 -> 0 | O35: ='Statement Q'!H38 -> 0 | P35: ='Statement Q'!I38 -> 0 | Q35: ='Statement Q'!J38 -> 0 | S35: =Q35 -> 0
... B52: Total liabilities and equity | C52: ='Statement Y'!C55 -> 0 | D52: ='Statement Y'!D55 -> 0 | E52: ='Statement Y'!E55 -> 0 | F52: ='Statement Y'!F55 -> 0 | G52: ='Statement Y'!G55 -> 0 | H52: ='Statement Y'!H55 -> 0 | J52: ='Statement Q'!C55 -> 0 | K52: ='Statement Q'!D55 -> 0 | L52: ='Statement Q'!E55 -> 0 | M52: ='Statement Q'!F55 -> 0 | N52: ='Statement Q'!G55 -> 0 | O52: ='Statement Q'!H55 -> 0 | P52: ='Statement Q'!I55 -> 0 | Q52: ='Statement Q'!J55 -> 0 | S52: =Q52 -> 0
B54: Cashflow statement
B55: Net income | C55: ='Statement Y'!C58 -> 0 | D55: ='Statement Y'!D58 -> 0 | E55: ='Statement Y'!E58 -> 0 | F55: ='Statement Y'!F58 -> 0 | G55: ='Statement Y'!G58 -> 0 | H55: ='Statement Y'!H58 -> 0 | J55: ='Statement Q'!C58 -> 0 | K55: ='Statement Q'!D58 -> 0 | L55: ='Statement Q'!E58 -> 0 | M55: ='Statement Q'!F58 -> 0 | N55: ='Statement Q'!G58 -> 0 | O55: ='Statement Q'!H58 -> 0 | P55: ='Statement Q'!I58 -> 0 | Q55: ='Statement Q'!J58 -> 0 | S55: =SUM(N55:Q55) -> 0
B56: D&A | C56: ='Statement Y'!C59 -> 0 | D56: ='Statement Y'!D59 -> 0 | E56: ='Statement Y'!E59 -> 0 | F56: ='Statement Y'!F59 -> 0 | G56: ='Statement Y'!G59 -> 0 | H56: ='Statement Y'!H59 -> 0 | J56: ='Statement Q'!C59 -> 0 | K56: ='Statement Q'!D59 -> 0 | L56: ='Statement Q'!E59 -> 0 | M56: ='Statement Q'!F59 -> 0 | N56: ='Statement Q'!G59 -> 0 | O56: ='Statement Q'!H59 -> 0 | P56: ='Statement Q'!I59 -> 0 | Q56: ='Statement Q'!J59 -> 0 | S56: =SUM(N56:Q56) -> 0
B57: Deferred income taxes | C57: ='Statement Y'!C60 -> 0 | D57: ='Statement Y'!D60 -> 0 | E57: ='Statement Y'!E60 -> 0 | F57: ='Statement Y'!F60 -> 0 | G57: ='Statement Y'!G60 -> 0 | H57: ='Statement Y'!H60 -> 0 | J57: ='Statement Q'!C60 -> 0 | K57: ='Statement Q'!D60 -> 0 | L57: ='Statement Q'!E60 -> 0 | M57: ='Statement Q'!F60 -> 0 | N57: ='Statement Q'!G60 -> 0 | O57: ='Statement Q'!H60 -> 0 | P57: ='Statement Q'!I60 -> 0 | Q57: ='Statement Q'!J60 -> 0 | S57: =SUM(N57:Q57) -> 0
B58: Stock-based compensation | C58: ='Statement Y'!C61 -> 0 | D58: ='Statement Y'!D61 -> 0 | E58: ='Statement Y'!E61 -> 0 | F58: ='Statement Y'!F61 -> 0 | G58: ='Statement Y'!G61 -> 0 | H58: ='Statement Y'!H61 -> 0 | J58: ='Statement Q'!C61 -> 0 | K58: ='Statement Q'!D61 -> 0 | L58: ='Statement Q'!E61 -> 0 | M58: ='Statement Q'!F61 -> 0 | N58: ='Statement Q'!G61 -> 0 | O58: ='Statement Q'!H61 -> 0 | P58: ='Statement Q'!I61 -> 0 | Q58: ='Statement Q'!J61 -> 0 | S58: =SUM(N58:Q58) -> 0
B59: Accretion on marketable securitirs | C59: ='Statement Y'!C62 -> 0 | D59: ='Statement Y'!D62 -> 0 | E59: ='Statement Y'!E62 -> 0 | F59: ='Statement Y'!F62 -> 0 | G59: ='Statement Y'!G62 -> 0 | H59: ='Statement Y'!H62 -> 0 | J59: ='Statement Q'!C62 -> 0 | K59: ='Statement Q'!D62 -> 0 | L59: ='Statement Q'!E62 -> 0 | M59: ='Statement Q'!F62 -> 0 | N59: ='Statement Q'!G62 -> 0 | O59: ='Statement Q'!H62 -> 0 | P59: ='Statement Q'!I62 -> 0 | Q59: ='Statement Q'!J62 -> 0 | S59: =SUM(N59:Q59) -> 0
B60: Gain sale capitalized software | C60: ='Statement Y'!C63 -> 0 | D60: ='Statement Y'!D63 -> 0 | E60: ='Statement Y'!E63 -> 0 | F60: ='Statement Y'!F63 -> 0 | G60: ='Statement Y'!G63 -> 0 | H60: ='Statement Y'!H63 -> 0 | J60: ='Statement Q'!C63 -> 0 | K60: ='Statement Q'!D63 -> 0 | L60: ='Statement Q'!E63 -> 0 | M60: ='Statement Q'!F63 -> 0 | N60: ='Statement Q'!G63 -> 0 | O60: ='Statement Q'!H63 -> 0 | P60: ='Statement Q'!I63 -> 0 | Q60: ='Statement Q'!J63 -> 0 | S60: =SUM(N60:Q60) -> 0
B61: Loss disposal leasehold improvments | C61: ='Statement Y'!C64 -> 0 | D61: ='Statement Y'!D64 -> 0 | E61: ='Statement Y'!E64 -> 0 | F61: ='Statement Y'!F64 -> 0 | G61: ='Statement Y'!G64 -> 0 | H61: ='Statement Y'!H64 -> 0 | J61: ='Statement Q'!C64 -> 0 | K61: ='Statement Q'!D64 -> 0 | L61: ='Statement Q'!E64 -> 0 | M61: ='Statement Q'!F64 -> 0 | N61: ='Statement Q'!G64 -> 0 | O61: ='Statement Q'!H64 -> 0 | P61: ='Statement Q'!I64 -> 0 | Q61: ='Statement Q'!J64 -> 0 | S61: =SUM(N61:Q61) -> 0
B62: Impairment on capitalized software | C62: ='Statement Y'!C65 -> 0 | D62: ='Statement Y'!D65 -> 0 | E62: ='Statement Y'!E65 -> 0 | F62: ='Statement Y'!F65 -> 0 | G62: ='Statement Y'!G65 -> 0 | H62: ='Statement Y'!H65 -> 0 | J62: ='Statement Q'!C65 -> 0 | K62: ='Statement Q'!D65 -> 0 | L62: ='Statement Q'!E65 -> 0 | M62: ='Statement Q'!F65 -> 0 | N62: ='Statement Q'!G65 -> 0 | O62: ='Statement Q'!H65 -> 0 | P62: ='Statement Q'!I65 -> 0 | Q62: ='Statement Q'!J65 -> 0 | S62: =SUM(N62:Q62) -> 0
B63: Change NWC | C63: =SUM('Statement Y'!C66:C72) -> 0 | D63: =SUM('Statement Y'!D66:D72) -> 0 | E63: =SUM('Statement Y'!E66:E72) -> 0 | F63: =SUM('Statement Y'!F66:F72) -> 0 | G63: =SUM('Statement Y'!G66:G72) -> 0 | H63: =SUM('Statement Y'!H66:H72) -> 0 | J63: =SUM('Statement Q'!C66:C72) -> 0 | K63: =SUM('Statement Q'!D66:D72) -> 0 | L63: =SUM('Statement Q'!E66:E72) -> 0 | M63: =SUM('Statement Q'!F66:F72) -> 0 | N63: =SUM('Statement Q'!G66:G72) -> 0 | O63: =SUM('Statement Q'!H66:H72) -> 0 | P63: =SUM('Statement Q'!I66:I72) -> 0 | Q63: =SUM('Statement Q'!J66:J72) -> 0 | S63: =SUM(N63:Q63) -> 0
B64: Operating cashflow | C64: ='Statement Y'!C73 -> 0 | D64: ='Statement Y'!D73 -> 0 | E64: ='Statement Y'!E73 -> 0 | F64: ='Statement Y'!F73 -> 0 | G64: ='Statement Y'!G73 -> 0 | H64: ='Statement Y'!H73 -> 0 | J64: ='Statement Q'!C73 -> 0 | K64: ='Statement Q'!D73 -> 0 | L64: ='Statement Q'!E73 -> 0 | M64: ='Statement Q'!F73 -> 0 | N64: ='Statement Q'!G73 -> 0 | O64: ='Statement Q'!H73 -> 0 | P64: ='Statement Q'!I73 -> 0 | Q64: ='Statement Q'!J73 -> 0 | S64: =SUM(N64:Q64) -> 0
B65: CapEx | C65: ='Statement Y'!C74 -> 0 | D65: ='Statement Y'!D74 -> 0 | E65: ='Statement Y'!E74 -> 0 | F65: ='Statement Y'!F74 -> 0 | G65: ='Statement Y'!G74 -> 0 | H65: ='Statement Y'!H74 -> 0 | J65: ='Statement Q'!C74 -> 0 | K65: ='Statement Q'!D74 -> 0 | L65: ='Statement Q'!E74 -> 0 | M65: ='Statement Q'!F74 -> 0 | N65: ='Statement Q'!G74 -> 0 | O65: ='Statement Q'!H74 -> 0 | P65: ='Statement Q'!I74 -> 0 | Q65: ='Statement Q'!J74 -> 0 | S65: =SUM(N65:Q65) -> 0
B66: Capitalized software | C66: ='Statement Y'!C79 -> 0 | D66: ='Statement Y'!D79 -> 0 | E66: ='Statement Y'!E79 -> 0 | F66: ='Statement Y'!F79 -> 0 | G66: ='Statement Y'!G79 -> 0 | H66: ='Statement Y'!H79 -> 0 | J66: ='Statement Q'!C80 -> 0 | K66: ='Statement Q'!D80 -> 0 | L66: ='Statement Q'!E80 -> 0 | M66: ='Statement Q'!F80 -> 0 | N66: ='Statement Q'!G80 -> 0 | O66: ='Statement Q'!H80 -> 0 | P66: ='Statement Q'!I80 -> 0 | Q66: ='Statement Q'!J80 -> 0 | S66: =SUM(N66:Q66) -> 0
B67: Investing cashflow | C67: ='Statement Y'!C80 -> 0 | D67: ='Statement Y'!D80 -> 0 | E67: ='Statement Y'!E80 -> 0 | F67: ='Statement Y'!F80 -> 0 | G67: ='Statement Y'!G80 -> 0 | H67: ='Statement Y'!H80 -> 0 | J67: ='Statement Q'!C81 -> 0 | K67: ='Statement Q'!D81 -> 0 | L67: ='Statement Q'!E81 -> 0 | M67: ='Statement Q'!F81 -> 0 | N67: ='Statement Q'!G81 -> 0 | O67: ='Statement Q'!H81 -> 0 | P67: ='Statement Q'!I81 -> 0 | Q67: ='Statement Q'!J81 -> 0 | S67: =SUM(N67:Q67) -> 0
B68: Issuance common stock | C68: ='Statement Y'!C81 -> 0 | D68: ='Statement Y'!D81 -> 0 | E68: ='Statement Y'!E81 -> 0 | F68: ='Statement Y'!F81 -> 0 | G68: ='Statement Y'!G81 -> 0 | H68: ='Statement Y'!H81 -> 0 | J68: ='Statement Q'!C89 -> 0 | K68: ='Statement Q'!D89 -> 0 | L68: ='Statement Q'!E89 -> 0 | M68: ='Statement Q'!F89 -> 0 | N68: ='Statement Q'!G89 -> 0 | O68: ='Statement Q'!H89 -> 0 | P68: ='Statement Q'!I89 -> 0 | Q68: ='Statement Q'!J89 -> 0 | S68: =SUM(N68:Q68) -> 0
B69: Repurchase common stock | C69: ='Statement Y'!C86 -> 0 | D69: ='Statement Y'!D86 -> 0 | E69: ='Statement Y'!E86 -> 0 | F69: ='Statement Y'!F86 -> 0 | G69: ='Statement Y'!G86 -> 0 | H69: ='Statement Y'!H86 -> 0 | J69: 0 | K69: 0 | L69: 0 | M69: 0 | N69: 0 | O69: 0 | P69: 0 | Q69: 0 | S69: =SUM(N69:Q69) -> 0
B70: Financing cashflow | C70: ='Statement Y'!C88 -> 0 | D70: ='Statement Y'!D88 -> 0 | E70: ='Statement Y'!E88 -> 0 | F70: ='Statement Y'!F88 -> 0 | G70: ='Statement Y'!G88 -> 0 | H70: ='Statement Y'!H88 -> 0 | J70: ='Statement Q'!C91 -> 0 | K70: ='Statement Q'!D91 -> 0 | L70: ='Statement Q'!E91 -> 0 | M70: ='Statement Q'!F91 -> 0 | N70: ='Statement Q'!G91 -> 0 | O70: ='Statement Q'!H91 -> 0 | P70: ='Statement Q'!I91 -> 0 | Q70: ='Statement Q'!J91 -> 0 | S70: =SUM(N70:Q70) -> 0
B71: Net increase/decrease in cash | C71: ='Statement Y'!C89 -> 0 | D71: ='Statement Y'!D89 -> 0 | E71: ='Statement Y'!E89 -> 0 | F71: ='Statement Y'!F89 -> 0 | G71: ='Statement Y'!G89 -> 0 | H71: ='Statement Y'!H89 -> 0 | J71: ='Statement Q'!C92 -> 0 | K71: ='Statement Q'!D92 -> 0 | L71: ='Statement Q'!E92 -> 0 | M71: ='Statement Q'!F92 -> 0 | N71: ='Statement Q'!G92 -> 0 | O71: ='Statement Q'!H92 -> 0 | P71: ='Statement Q'!I92 -> 0 | Q71: ='Statement Q'!J92 -> 0 | S71: =SUM(N71:Q71) -> 0
B72: Begin cash | C72: ='Statement Y'!C90 -> 0 | D72: ='Statement Y'!D90 -> 0 | E72: ='Statement Y'!E90 -> 0 | F72: ='Statement Y'!F90 -> 0 | G72: ='Statement Y'!G90 -> 0 | H72: ='Statement Y'!H90 -> 0 | J72: ='Statement Q'!C93 -> 0 | K72: ='Statement Q'!D93 -> 0 | L72: ='Statement Q'!E93 -> 0 | M72: ='Statement Q'!F93 -> 0 | N72: ='Statement Q'!G93 -> 0 | O72: ='Statement Q'!H93 -> 0 | P72: ='Statement Q'!I93 -> 0 | Q72: ='Statement Q'!J93 -> 0 | S72: =N72 -> 0
B73: End cash | C73: ='Statement Y'!C91 -> 0 | D73: ='Statement Y'!D91 -> 0 | E73: ='Statement Y'!E91 -> 0 | F73: ='Statement Y'!F91 -> 0 | G73: ='Statement Y'!G91 -> 0 | H73: ='Statement Y'!H91 -> 0 | J73: ='Statement Q'!C94 -> 0 | K73: ='Statement Q'!D94 -> 0 | L73: ='Statement Q'!E94 -> 0 | M73: ='Statement Q'!F94 -> 0 | N73: ='Statement Q'!G94 -> 0 | O73: ='Statement Q'!H94 -> 0 | P73: ='Statement Q'!I94 -> 0 | Q73: ='Statement Q'!J94 -> 0 | S73: =Q73 -> 0
B75: DuPont Identity
B76: Profit Margin (Earnings/Revenue) | C76: =C18/C5 -> #DIV/0! | D76: =D18/D5 -> #DIV/0! | E76: =E18/E5 -> #DIV/0! | F76: =F18/F5 -> #DIV/0! | G76: =G18/G5 -> #DIV/0! | H76: =H18/H5 -> #DIV/0! | S76: =S18/S5 -> #DIV/0!
B77: Asset Turnover (Revenue/Total assets) | C77: =C5/C38 -> #DIV/0! | D77: =D5/D38 -> #DIV/0! | E77: =E5/E38 -> #DIV/0! | F77: =F5/F38 -> #DIV/0! | G77: =G5/G38 -> #DIV/0! | H77: =H5/H38 -> #DIV/0! | S77: =S5/S38 -> #DIV/0!
B78: ROA | C78: =C76*C77 -> #DIV/0! | D78: =D76*D77 -> #DIV/0! | E78: =E76*E77 -> #DIV/0! | F78: =F76*F77 -> #DIV/0! | G78: =G76*G77 -> #DIV/0! | H78: =H76*H77 -> #DIV/0! | S78: =S76*S77 -> #DIV/0!
B79: Equity Multiplier (Total assets/Equity) | C79: =C38/C51 -> #DIV/0! | D79: =D38/D51 -> #DIV/0! | E79: =E38/E51 -> #DIV/0! | F79: =F38/F51 -> #DIV/0! | G79: =G38/G51 -> #DIV/0! | H79: =H38/H51 -> #DIV/0! | S79: =S38/S51 -> #DIV/0!
B80: ROE | C80: =C78*C79 -> #DIV/0! | D80: =D78*D79 -> #DIV/0! | E80: =E78*E79 -> #DIV/0! | F80: =F78*F79 -> #DIV/0! | G80: =G78*G79 -> #DIV/0! | H80: =H78*H79 -> #DIV/0! | S80: =S78*S79 -> #DIV/0!
B82: Growth rates
B83: Revenue | D83: =(D5-C5)/C5 -> #DIV/0! | E83: =(E5-D5)/D5 -> #DIV/0! | F83: =(F5-E5)/E5 -> #DIV/0! | G83: =(G5-F5)/F5 -> #DIV/0! | H83: =(H5-G5)/G5 -> #DIV/0! | K83: =(K5-J5)/J5 -> #DIV/0! | L83: =(L5-K5)/K5 -> #DIV/0! | M83: =(M5-L5)/L5 -> #DIV/0! | N83: =(N5-M5)/M5 -> #DIV/0! | O83: =(O5-N5)/N5 -> #DIV/0! | P83: =(P5-O5)/O5 -> #DIV/0! | Q83: =(Q5-P5)/P5 -> #DIV/0!
B84: COGS | D84: =(D6-C6)/C6 -> #DIV/0! | E84: =(E6-D6)/D6 -> #DIV/0! | F84: =(F6-E6)/E6 -> #DIV/0! | G84: =(G6-F6)/F6 -> #DIV/0! | H84: =(H6-G6)/G6 -> #DIV/0! | K84: =(K6-J6)/J6 -> #DIV/0! | L84: =(L6-K6)/K6 -> #DIV/0! | M84: =(M6-L6)/L6 -> #DIV/0! | N84: =(N6-M6)/M6 -> #DIV/0! | O84: =(O6-N6)/N6 -> #DIV/0! | P84: =(P6-O6)/O6 -> #DIV/0! | Q84: =(Q6-P6)/P6 -> #DIV/0!
B85: Gross Profit | D85: =IF(C7=0, IF(D7=0,0,IF(D7>0,1,-1)), (D7-C7)/ABS(C7) ) -> 0 | E85: =IF(D7=0, IF(E7=0,0,IF(E7>0,1,-1)), (E7-D7)/ABS(D7) ) -> 0 | F85: =IF(E7=0, IF(F7=0,0,IF(F7>0,1,-1)), (F7-E7)/ABS(E7) ) -> 0 | G85: =IF(F7=0, IF(G7=0,0,IF(G7>0,1,-1)), (G7-F7)/ABS(F7) ) -> 0 | H85: =IF(G7=0, IF(H7=0,0,IF(H7>0,1,-1)), (H7-G7)/ABS(G7) ) -> 0 | K85: =IF(J7=0, IF(K7=0,0,IF(K7>0,1,-1)), (K7-J7)/ABS(J7) ) -> 0 | L85: =IF(K7=0, IF(L7=0,0,IF(L7>0,1,-1)), (L7-K7)/ABS(K7) ) -> 0 | M85: =IF(L7=0, IF(M7=0,0,IF(M7>0,1,-1)), (M7-L7)/ABS(L7) ) -> 0 | N85: =IF(M7=0, IF(N7=0,0,IF(N7>0,1,-1)), (N7-M7)/ABS(M7) ) -> 0 | O85: =IF(N7=0, IF(O7=0,0,IF(O7>0,1,-1)), (O7-N7)/ABS(N7) ) -> 0 | P85: =IF(O7=0, IF(P7=0,0,IF(P7>0,1,-1)), (P7-O7)/ABS(O7) ) -> 0 | Q85: =IF(P7=0, IF(Q7=0,0,IF(Q7>0,1,-1)), (Q7-P7)/ABS(P7) ) -> 0
B86: OpEx | D86: =IF(C11=0, IF(D11=0,0,IF(D11>0,1,-1)), (D11-C11)/ABS(C11) ) -> 0 | E86: =IF(D11=0, IF(E11=0,0,IF(E11>0,1,-1)), (E11-D11)/ABS(D11) ) -> 0 | F86: =IF(E11=0, IF(F11=0,0,IF(F11>0,1,-1)), (F11-E11)/ABS(E11) ) -> 0 | G86: =IF(F11=0, IF(G11=0,0,IF(G11>0,1,-1)), (G11-F11)/ABS(F11) ) -> 0 | H86: =IF(G11=0, IF(H11=0,0,IF(H11>0,1,-1)), (H11-G11)/ABS(G11) ) -> 0 | K86: =IF(J11=0, IF(K11=0,0,IF(K11>0,1,-1)), (K11-J11)/ABS(J11) ) -> 0 | L86: =IF(K11=0, IF(L11=0,0,IF(L11>0,1,-1)), (L11-K11)/ABS(K11) ) -> 0 | M86: =IF(L11=0, IF(M11=0,0,IF(M11>0,1,-1)), (M11-L11)/ABS(L11) ) -> 0 | N86: =IF(M11=0, IF(N11=0,0,IF(N11>0,1,-1)), (N11-M11)/ABS(M11) ) -> 0 | O86: =IF(N11=0, IF(O11=0,0,IF(O11>0,1,-1)), (O11-N11)/ABS(N11) ) -> 0 | P86: =IF(O11=0, IF(P11=0,0,IF(P11>0,1,-1)), (P11-O11)/ABS(O11) ) -> 0 | Q86: =IF(P11=0, IF(Q11=0,0,IF(Q11>0,1,-1)), (Q11-P11)/ABS(P11) ) -> 0
B87: Operating income | D87: =IF(C12=0, IF(D12=0,0,IF(D12>0,1,-1)), (D12-C12)/ABS(C12) ) -> 0 | E87: =IF(D12=0, IF(E12=0,0,IF(E12>0,1,-1)), (E12-D12)/ABS(D12) ) -> 0 | F87: =IF(E12=0, IF(F12=0,0,IF(F12>0,1,-1)), (F12-E12)/ABS(E12) ) -> 0 | G87: =IF(F12=0, IF(G12=0,0,IF(G12>0,1,-1)), (G12-F12)/ABS(F12) ) -> 0 | H87: =IF(G12=0, IF(H12=0,0,IF(H12>0,1,-1)), (H12-G12)/ABS(G12) ) -> 0 | K87: =IF(J12=0, IF(K12=0,0,IF(K12>0,1,-1)), (K12-J12)/ABS(J12) ) -> 0 | L87: =IF(K12=0, IF(L12=0,0,IF(L12>0,1,-1)), (L12-K12)/ABS(K12) ) -> 0 | M87: =IF(L12=0, IF(M12=0,0,IF(M12>0,1,-1)), (M12-L12)/ABS(L12) ) -> 0 | N87: =IF(M12=0, IF(N12=0,0,IF(N12>0,1,-1)), (N12-M12)/ABS(M12) ) -> 0 | O87: =IF(N12=0, IF(O12=0,0,IF(O12>0,1,-1)), (O12-N12)/ABS(N12) ) -> 0 | P87: =IF(O12=0, IF(P12=0,0,IF(P12>0,1,-1)), (P12-O12)/ABS(O12) ) -> 0 | Q87: =IF(P12=0, IF(Q12=0,0,IF(Q12>0,1,-1)), (Q12-P12)/ABS(P12) ) -> 0
B88: Income before taxes | D88: =IF(C16=0, IF(D16=0,0,IF(D16>0,1,-1)), (D16-C16)/ABS(C16) ) -> 0 | E88: =IF(D16=0, IF(E16=0,0,IF(E16>0,1,-1)), (E16-D16)/ABS(D16) ) -> 0 | F88: =IF(E16=0, IF(F16=0,0,IF(F16>0,1,-1)), (F16-E16)/ABS(E16) ) -> 0 | G88: =IF(F16=0, IF(G16=0,0,IF(G16>0,1,-1)), (G16-F16)/ABS(F16) ) -> 0 | H88: =IF(G16=0, IF(H16=0,0,IF(H16>0,1,-1)), (H16-G16)/ABS(G16) ) -> 0 | K88: =IF(J16=0, IF(K16=0,0,IF(K16>0,1,-1)), (K16-J16)/ABS(J16) ) -> 0 | L88: =IF(K16=0, IF(L16=0,0,IF(L16>0,1,-1)), (L16-K16)/ABS(K16) ) -> 0 | M88: =IF(L16=0, IF(M16=0,0,IF(M16>0,1,-1)), (M16-L16)/ABS(L16) ) -> 0 | N88: =IF(M16=0, IF(N16=0,0,IF(N16>0,1,-1)), (N16-M16)/ABS(M16) ) -> 0 | O88: =IF(N16=0, IF(O16=0,0,IF(O16>0,1,-1)), (O16-N16)/ABS(N16) ) -> 0 | P88: =IF(O16=0, IF(P16=0,0,IF(P16>0,1,-1)), (P16-O16)/ABS(O16) ) -> 0 | Q88: =IF(P16=0, IF(Q16=0,0,IF(Q16>0,1,-1)), (Q16-P16)/ABS(P16) ) -> 0
B89: Net income | D89: =IF(C18=0, IF(D18=0,0,IF(D18>0,1,-1)), (D18-C18)/ABS(C18) ) -> 0 | E89: =IF(D18=0, IF(E18=0,0,IF(E18>0,1,-1)), (E18-D18)/ABS(D18) ) -> 0 | F89: =IF(E18=0, IF(F18=0,0,IF(F18>0,1,-1)), (F18-E18)/ABS(E18) ) -> 0 | G89: =IF(F18=0, IF(G18=0,0,IF(G18>0,1,-1)), (G18-F18)/ABS(F18) ) -> 0 | H89: =IF(G18=0, IF(H18=0,0,IF(H18>0,1,-1)), (H18-G18)/ABS(G18) ) -> 0 | K89: =IF(J18=0, IF(K18=0,0,IF(K18>0,1,-1)), (K18-J18)/ABS(J18) ) -> 0 | L89: =IF(K18=0, IF(L18=0,0,IF(L18>0,1,-1)), (L18-K18)/ABS(K18) ) -> 0 | M89: =IF(L18=0, IF(M18=0,0,IF(M18>0,1,-1)), (M18-L18)/ABS(L18) ) -> 0 | N89: =IF(M18=0, IF(N18=0,0,IF(N18>0,1,-1)), (N18-M18)/ABS(M18) ) -> 0 | O89: =IF(N18=0, IF(O18=0,0,IF(O18>0,1,-1)), (O18-N18)/ABS(N18) ) -> 0 | P89: =IF(O18=0, IF(P18=0,0,IF(P18>0,1,-1)), (P18-O18)/ABS(O18) ) -> 0 | Q89: =IF(P18=0, IF(Q18=0,0,IF(Q18>0,1,-1)), (Q18-P18)/ABS(P18) ) -> 0
B90: Diluted Shares outstanding avg | D90: =(D11-C11)/C11 -> #DIV/0! | E90: =(E11-D11)/D11 -> #DIV/0! | F90: =(F11-E11)/E11 -> #DIV/0! | G90: =(G11-F11)/F11 -> #DIV/0! | H90: =(H11-G11)/G11 -> #DIV/0! | K90: =(K11-J11)/J11 -> #DIV/0! | L90: =(L11-K11)/K11 -> #DIV/0! | M90: =(M11-L11)/L11 -> #DIV/0! | N90: =(N11-M11)/M11 -> #DIV/0! | O90: =(O11-N11)/N11 -> #DIV/0! | P90: =(P11-O11)/O11 -> #DIV/0! | Q90: =(Q11-P11)/P11 -> #DIV/0!
B91: Diluted EPS | D91: =IF(C20=0, IF(D20=0,0,IF(D20>0,1,-1)), (D20-C20)/ABS(C20) ) -> 0 | E91: =IF(D20=0, IF(E20=0,0,IF(E20>0,1,-1)), (E20-D20)/ABS(D20) ) -> 0 | F91: =IF(E20=0, IF(F20=0,0,IF(F20>0,1,-1)), (F20-E20)/ABS(E20) ) -> 0 | G91: =IF(F20=0, IF(G20=0,0,IF(G20>0,1,-1)), (G20-F20)/ABS(F20) ) -> 0 | H91: =IF(G20=0, IF(H20=0,0,IF(H20>0,1,-1)), (H20-G20)/ABS(G20) ) -> 0 | K91: =IF(J20=0, IF(K20=0,0,IF(K20>0,1,-1)), (K20-J20)/ABS(J20) ) -> 0 | L91: =IF(K20=0, IF(L20=0,0,IF(L20>0,1,-1)), (L20-K20)/ABS(K20) ) -> 0 | M91: =IF(L20=0, IF(M20=0,0,IF(M20>0,1,-1)), (M20-L20)/ABS(L20) ) -> 0 | N91: =IF(M20=0, IF(N20=0,0,IF(N20>0,1,-1)), (N20-M20)/ABS(M20) ) -> 0 | O91: =IF(N20=0, IF(O20=0,0,IF(O20>0,1,-1)), (O20-N20)/ABS(N20) ) -> 0 | P91: =IF(O20=0, IF(P20=0,0,IF(P20>0,1,-1)), (P20-O20)/ABS(O20) ) -> 0 | Q91: =IF(P20=0, IF(Q20=0,0,IF(Q20>0,1,-1)), (Q20-P20)/ABS(P20) ) -> 0
B93: Margins
B94: Gross margin | C94: =C7/C5 -> #DIV/0! | D94: =D7/D5 -> #DIV/0! | E94: =E7/E5 -> #DIV/0! | F94: =F7/F5 -> #DIV/0! | G94: =G7/G5 -> #DIV/0! | H94: =H7/H5 -> #DIV/0! | J94: =J7/J5 -> #DIV/0! | K94: =K7/K5 -> #DIV/0! | L94: =L7/L5 -> #DIV/0! | M94: =M7/M5 -> #DIV/0! | N94: =N7/N5 -> #DIV/0! | O94: =O7/O5 -> #DIV/0! | P94: =P7/P5 -> #DIV/0! | Q94: =Q7/Q5 -> #DIV/0! | S94: =S7/S5 -> #DIV/0!
B95: Operating margin | C95: =C12/C5 -> #DIV/0! | D95: =D12/D5 -> #DIV/0! | E95: =E12/E5 -> #DIV/0! | F95: =F12/F5 -> #DIV/0! | G95: =G12/G5 -> #DIV/0! | H95: =H12/H5 -> #DIV/0! | J95: =J12/J5 -> #DIV/0! | K95: =K12/K5 -> #DIV/0! | L95: =L12/L5 -> #DIV/0! | M95: =M12/M5 -> #DIV/0! | N95: =N12/N5 -> #DIV/0! | O95: =O12/O5 -> #DIV/0! | P95: =P12/P5 -> #DIV/0! | Q95: =Q12/Q5 -> #DIV/0! | S95: =S12/S5 -> #DIV/0!
B96: Net margin | C96: =C18/C5 -> #DIV/0! | D96: =D18/D5 -> #DIV/0! | E96: =E18/E5 -> #DIV/0! | F96: =F18/F5 -> #DIV/0! | G96: =G18/G5 -> #DIV/0! | H96: =H18/H5 -> #DIV/0! | J96: =J18/J5 -> #DIV/0! | K96: =K18/K5 -> #DIV/0! | L96: =L18/L5 -> #DIV/0! | M96: =M18/M5 -> #DIV/0! | N96: =N18/N5 -> #DIV/0! | O96: =O18/O5 -> #DIV/0! | P96: =P18/P5 -> #DIV/0! | Q96: =Q18/Q5 -> #DIV/0! | S96: =S18/S5 -> #DIV/0!

Sheet Forecast ->
B13: Forecast ->

Sheet Revenue
B1: Revenue forecast
C2: History | H2: Forecast | S2: History | AA2: Forecast | AE2: TTM
C4: Revenues | S4: Revenues | AE4: Q1-Q2-Q3
B5: Revenues (thousand) | C5: ='Statement Y'!D3 -> 2021 | D5: ='Statement Y'!E3 -> 2022 | E5: ='Statement Y'!F3 -> 2023 | F5: ='Statement Y'!G3 -> 2024 | G5: ='Statement Y'!H3 -> 2025 | H5: =G5+1 -> 2026 | I5: =H5+1 -> 2027 | J5: =I5+1 -> 2028 | K5: =J5+1 -> 2029 | L5: =K5+1 -> 2030 | R5: Revenues (thousand) | S5: ='Statement Q'!C3 -> Q1 2024 | T5: ='Statement Q'!D3 -> Q2 2024 | U5: ='Statement Q'!E3 -> Q3 2024 | V5: ='Statement Q'!F3 -> Q4 2024 | W5: ='Statement Q'!G3 -> Q1 2025 | X5: ='Statement Q'!H3 -> Q2 2025 | Y5: ='Statement Q'!I3 -> Q3 2025 | Z5: ='Statement Q'!J3 -> Q4 2025 | AA5: FQ1 | AB5: FQ2 | AC5: FQ3 | AE5: FQ1
B6: ='Statement Y'!#REF! -> #REF! | C6: ='Statement Y'!#REF! -> #REF! | D6: ='Statement Y'!#REF! -> #REF! | E6: ='Statement Y'!#REF! -> #REF! | F6: ='Statement Y'!#REF! -> #REF! | G6: ='Statement Y'!#REF! -> #REF! | H6: =H39*H36 -> #REF! | I6: =I39*I36 -> #REF! | J6: =J39*J36 -> #REF! | K6: =K39*K36 -> #REF! | L6: =L39*L36 -> #REF! | N6: Avg revenue/Paid user * Paid subscribers | Q6: Avg revenue/Paid user * Paid subscribers | R6: ='Statement Q'!#REF! -> #REF! | S6: ='Statement Q'!#REF! -> #REF! | T6: ='Statement Q'!#REF! -> #REF! | U6: ='Statement Q'!#REF! -> #REF! | V6: ='Statement Q'!#REF! -> #REF! | W6: ='Statement Q'!#REF! -> #REF! | X6: ='Statement Q'!#REF! -> #REF! | Y6: ='Statement Q'!#REF! -> #REF! | Z6: ='Statement Q'!#REF! -> #REF! | AA6: =AA39*AA36 -> #REF! | AE6: =SUM(X6:AA6) -> #REF!
B7: ='Statement Y'!#REF! -> #REF! | C7: ='Statement Y'!#REF! -> #REF! | D7: ='Statement Y'!#REF! -> #REF! | E7: ='Statement Y'!#REF! -> #REF! | F7: ='Statement Y'!#REF! -> #REF! | G7: ='Statement Y'!#REF! -> #REF! | H7: =H37*H33 -> #REF! | I7: =I37*I33 -> #REF! | J7: =J37*J33 -> #REF! | K7: =K37*K33 -> #REF! | L7: =L37*L33 -> #REF! | N7: Free users * Ad revenue/Free user | Q7: Free users * Ad revenue/Free user | R7: ='Statement Q'!#REF! -> #REF! | S7: ='Statement Q'!#REF! -> #REF! | T7: ='Statement Q'!#REF! -> #REF! | U7: ='Statement Q'!#REF! -> #REF! | V7: ='Statement Q'!#REF! -> #REF! | W7: ='Statement Q'!#REF! -> #REF! | X7: ='Statement Q'!#REF! -> #REF! | Y7: ='Statement Q'!#REF! -> #REF! | Z7: ='Statement Q'!#REF! -> #REF! | AA7: =AA37*AA33 -> #REF! | AE7: =SUM(X7:AA7) -> #REF!
B8: ='Statement Y'!#REF! -> #REF! | C8: ='Statement Y'!#REF! -> #REF! | D8: ='Statement Y'!#REF! -> #REF! | E8: ='Statement Y'!#REF! -> #REF! | F8: ='Statement Y'!#REF! -> #REF! | G8: ='Statement Y'!#REF! -> #REF! | H8: =G8*(1+H27) -> #REF! | I8: =H8*(1+I27) -> #REF! | J8: =I8*(1+J27) -> #REF! | K8: =J8*(1+K27) -> #REF! | L8: =K8*(1+L27) -> #REF! | N8: English test growth rate | Q8: English test growth rate | R8: ='Statement Q'!#REF! -> #REF! | S8: ='Statement Q'!#REF! -> #REF! | T8: ='Statement Q'!#REF! -> #REF! | U8: ='Statement Q'!#REF! -> #REF! | V8: ='Statement Q'!#REF! -> #REF! | W8: ='Statement Q'!#REF! -> #REF! | X8: ='Statement Q'!#REF! -> #REF! | Y8: ='Statement Q'!#REF! -> #REF! | Z8: ='Statement Q'!#REF! -> #REF! | AA8: =Z8*(1+AA27) -> #REF! | AE8: =SUM(X8:AA8) -> #REF!
B9: ='Statement Y'!#REF! -> #REF! | C9: ='Statement Y'!#REF! -> #REF! | D9: ='Statement Y'!#REF! -> #REF! | E9: ='Statement Y'!#REF! -> #REF! | F9: ='Statement Y'!#REF! -> #REF! | G9: ='Statement Y'!#REF! -> #REF! | H9: =H29*H38 -> #REF! | I9: =I29*I38 -> #REF! | J9: =J29*J38 -> #REF! | K9: =K29*K38 -> #REF! | L9: =L29*L38 -> #REF! | N9: DAU * In-app purchases % of DAU | Q9: DAU * In-app purchases % of DAU | R9: ='Statement Q'!#REF! -> #REF! | S9: ='Statement Q'!#REF! -> #REF! | T9: ='Statement Q'!#REF! -> #REF! | U9: ='Statement Q'!#REF! -> #REF! | V9: ='Statement Q'!#REF! -> #REF! | W9: ='Statement Q'!#REF! -> #REF! | X9: ='Statement Q'!#REF! -> #REF! | Y9: ='Statement Q'!#REF! -> #REF! | Z9: ='Statement Q'!#REF! -> #REF! | AA9: =AA29*AA38 -> #REF! | AE9: =SUM(X9:AA9) -> #REF!
B10: ='Statement Y'!#REF! -> #REF! | C10: ='Statement Y'!#REF! -> #REF! | D10: ='Statement Y'!#REF! -> #REF! | E10: ='Statement Y'!#REF! -> #REF! | F10: ='Statement Y'!#REF! -> #REF! | G10: ='Statement Y'!#REF! -> #REF! | H10: =G10*(1+H28) -> #REF! | I10: =H10*(1+I28) -> #REF! | J10: =I10*(1+J28) -> #REF! | K10: =J10*(1+K28) -> #REF! | L10: =K10*(1+L28) -> #REF! | N10: Other growth rate | Q10: Other growth rate | R10: ='Statement Q'!#REF! -> #REF! | S10: ='Statement Q'!#REF! -> #REF! | T10: ='Statement Q'!#REF! -> #REF! | U10: ='Statement Q'!#REF! -> #REF! | V10: ='Statement Q'!#REF! -> #REF! | W10: ='Statement Q'!#REF! -> #REF! | X10: ='Statement Q'!#REF! -> #REF! | Y10: ='Statement Q'!#REF! -> #REF! | Z10: ='Statement Q'!#REF! -> #REF! | AA10: =Z10*(1+AA28) -> #REF! | AE10: =SUM(X10:AA10) -> #REF!
B11: ='Statement Y'!#REF! -> #REF! | C11: ='Statement Y'!#REF! -> #REF! | D11: ='Statement Y'!#REF! -> #REF! | E11: ='Statement Y'!#REF! -> #REF! | F11: ='Statement Y'!#REF! -> #REF! | G11: ='Statement Y'!#REF! -> #REF! | H11: =SUM(H7:H10) -> #REF! | I11: =SUM(I7:I10) -> #REF! | J11: =SUM(J7:J10) -> #REF! | K11: =SUM(K7:K10) -> #REF! | L11: =SUM(L7:L10) -> #REF! | R11: ='Statement Q'!#REF! -> #REF! | S11: ='Statement Q'!#REF! -> #REF! | T11: ='Statement Q'!#REF! -> #REF! | U11: ='Statement Q'!#REF! -> #REF! | V11: ='Statement Q'!#REF! -> #REF! | W11: ='Statement Q'!#REF! -> #REF! | X11: ='Statement Q'!#REF! -> #REF! | Y11: ='Statement Q'!#REF! -> #REF! | Z11: ='Statement Q'!#REF! -> #REF! | AA11: =SUM(AA7:AA10) -> #REF! | AB11: =SUM(AB7:AB10) -> 0 | AC11: =SUM(AC7:AC10) -> 0 | AE11: =SUM(AE7:AE10) -> #REF!
B12: Total | C12: ='Statement Y'!D5 -> 0 | D12: ='Statement Y'!E5 -> 0 | E12: ='Statement Y'!F5 -> 0 | F12: ='Statement Y'!G5 -> 0 | G12: ='Statement Y'!H5 -> 0 | H12: =H6+H11 -> #REF! | I12: =I6+I11 -> #REF! | J12: =J6+J11 -> #REF! | K12: =K6+K11 -> #REF! | L12: =L6+L11 -> #REF! | R12: Total | S12: ='Statement Q'!C5 -> 0 | T12: ='Statement Q'!D5 -> 0 | U12: ='Statement Q'!E5 -> 0 | V12: ='Statement Q'!F5 -> 0 | W12: ='Statement Q'!G5 -> 0 | X12: ='Statement Q'!H5 -> 0 | Y12: ='Statement Q'!I5 -> 0 | Z12: ='Statement Q'!J5 -> 0 | AA12: =AA6+AA11 -> #REF! | AB12: =AB6+AB11 -> 0 | AC12: =AC6+AC11 -> 0 | AE12: =AE6+AE11 -> #REF!
C14: Growth rates | S14: Growth rates
B15: Revenue growth % | C15: =C5 -> 2021 | D15: =D5 -> 2022 | E15: =E5 -> 2023 | F15: =F5 -> 2024 | G15: =G5 -> 2025 | H15: =H5 -> 2026 | I15: =I5 -> 2027 | J15: =J5 -> 2028 | ... L15: =L5 -> 2030 | R15: Revenue growth % | S15: =S5 -> Q1 2024 | T15: =T5 -> Q2 2024 | U15: =U5 -> Q3 2024 | V15: =V5 -> Q4 2024 | W15: =W5 -> Q1 2025 | X15: =X5 -> Q2 2025 | Y15: =Y5 -> Q3 2025 | Z15: =Z5 -> Q4 2025 | ... AC15: =AC5 -> FQ3
B16: =B6 -> #REF! | D16: =D6/C6-1 -> #REF! | E16: =E6/D6-1 -> #REF! | F16: =F6/E6-1 -> #REF! | G16: =G6/F6-1 -> #REF! | H16: =H6/G6-1 -> #REF! | I16: =I6/H6-1 -> #REF! | J16: =J6/I6-1 -> #REF! | K16: =K6/J6-1 -> #REF! | L16: =L6/K6-1 -> #REF! | R16: =R6 -> #REF! | T16: =T6/S6-1 -> #REF! | U16: =U6/T6-1 -> #REF! | V16: =V6/U6-1 -> #REF! | W16: =W6/V6-1 -> #REF! | X16: =X6/W6-1 -> #REF! | Y16: =Y6/X6-1 -> #REF! | Z16: =Z6/Y6-1 -> #REF! | AA16: =AA6/Z6-1 -> #REF!
B17: =B7 -> #REF! | D17: =D7/C7-1 -> #REF! | E17: =E7/D7-1 -> #REF! | F17: =F7/E7-1 -> #REF! | G17: =G7/F7-1 -> #REF! | H17: =H7/G7-1 -> #REF! | I17: =I7/H7-1 -> #REF! | J17: =J7/I7-1 -> #REF! | K17: =K7/J7-1 -> #REF! | L17: =L7/K7-1 -> #REF! | R17: =R7 -> #REF! | T17: =T7/S7-1 -> #REF! | U17: =U7/T7-1 -> #REF! | V17: =V7/U7-1 -> #REF! | W17: =W7/V7-1 -> #REF! | X17: =X7/W7-1 -> #REF! | Y17: =Y7/X7-1 -> #REF! | Z17: =Z7/Y7-1 -> #REF! | AA17: =AA7/Z7-1 -> #REF!
B18: =B8 -> #REF! | D18: =D8/C8-1 -> #REF! | E18: =E8/D8-1 -> #REF! | F18: =F8/E8-1 -> #REF! | G18: =G8/F8-1 -> #REF! | H18: =H8/G8-1 -> #REF! | I18: =I8/H8-1 -> #REF! | J18: =J8/I8-1 -> #REF! | K18: =K8/J8-1 -> #REF! | L18: =L8/K8-1 -> #REF! | R18: =R8 -> #REF! | T18: =T8/S8-1 -> #REF! | U18: =U8/T8-1 -> #REF! | V18: =V8/U8-1 -> #REF! | W18: =W8/V8-1 -> #REF! | X18: =X8/W8-1 -> #REF! | Y18: =Y8/X8-1 -> #REF! | Z18: =Z8/Y8-1 -> #REF! | AA18: =AA8/Z8-1 -> #REF!
B19: =B9 -> #REF! | D19: =D9/C9-1 -> #REF! | E19: =E9/D9-1 -> #REF! | F19: =F9/E9-1 -> #REF! | G19: =G9/F9-1 -> #REF! | H19: =H9/G9-1 -> #REF! | I19: =I9/H9-1 -> #REF! | J19: =J9/I9-1 -> #REF! | K19: =K9/J9-1 -> #REF! | L19: =L9/K9-1 -> #REF! | R19: =R9 -> #REF! | T19: =T9/S9-1 -> #REF! | U19: =U9/T9-1 -> #REF! | V19: =V9/U9-1 -> #REF! | W19: =W9/V9-1 -> #REF! | X19: =X9/W9-1 -> #REF! | Y19: =Y9/X9-1 -> #REF! | Z19: =Z9/Y9-1 -> #REF! | AA19: =AA9/Z9-1 -> #REF!
B20: =B10 -> #REF! | D20: =D10/C10-1 -> #REF! | E20: =E10/D10-1 -> #REF! | F20: =F10/E10-1 -> #REF! | G20: =G10/F10-1 -> #REF! | H20: =H10/G10-1 -> #REF! | I20: =I10/H10-1 -> #REF! | J20: =J10/I10-1 -> #REF! | K20: =K10/J10-1 -> #REF! | L20: =L10/K10-1 -> #REF! | R20: =R10 -> #REF! | T20: =T10/S10-1 -> #REF! | U20: =U10/T10-1 -> #REF! | V20: =V10/U10-1 -> #REF! | W20: =W10/V10-1 -> #REF! | X20: =X10/W10-1 -> #REF! | Y20: =Y10/X10-1 -> #REF! | Z20: =Z10/Y10-1 -> #REF! | AA20: =AA10/Z10-1 -> #REF!
B21: =B11 -> #REF! | D21: =D11/C11-1 -> #REF! | E21: =E11/D11-1 -> #REF! | F21: =F11/E11-1 -> #REF! | G21: =G11/F11-1 -> #REF! | H21: =H11/G11-1 -> #REF! | I21: =I11/H11-1 -> #REF! | J21: =J11/I11-1 -> #REF! | K21: =K11/J11-1 -> #REF! | L21: =L11/K11-1 -> #REF! | R21: =R11 -> #REF! | T21: =T11/S11-1 -> #REF! | U21: =U11/T11-1 -> #REF! | V21: =V11/U11-1 -> #REF! | W21: =W11/V11-1 -> #REF! | X21: =X11/W11-1 -> #REF! | Y21: =Y11/X11-1 -> #REF! | Z21: =Z11/Y11-1 -> #REF! | AA21: =AA11/Z11-1 -> #REF!
B22: =B12 -> Total | D22: =D12/C12-1 -> #DIV/0! | E22: =E12/D12-1 -> #DIV/0! | F22: =F12/E12-1 -> #DIV/0! | G22: =G12/F12-1 -> #DIV/0! | H22: =H12/G12-1 -> #REF! | I22: =I12/H12-1 -> #REF! | J22: =J12/I12-1 -> #REF! | K22: =K12/J12-1 -> #REF! | L22: =L12/K12-1 -> #REF! | R22: =R12 -> Total | T22: =T12/S12-1 -> #DIV/0! | U22: =U12/T12-1 -> #DIV/0! | V22: =V12/U12-1 -> #DIV/0! | W22: =W12/V12-1 -> #DIV/0! | X22: =X12/W12-1 -> #DIV/0! | Y22: =Y12/X12-1 -> #DIV/0! | Z22: =Z12/Y12-1 -> #DIV/0! | AA22: =AA12/Z12-1 -> #REF!
C25: Drivers and metrics | S25: Drivers and metrics | AE25: =AE4 -> Q1-Q2-Q3
B26: Metric (thousand) | C26: =C5 -> 2021 | D26: =D5 -> 2022 | E26: =E5 -> 2023 | F26: =F5 -> 2024 | G26: =G5 -> 2025 | H26: =H5 -> 2026 | I26: =I5 -> 2027 | J26: =J5 -> 2028 | ... L26: =L5 -> 2030 | R26: Metric (thousand) | S26: =S5 -> Q1 2024 | T26: =T5 -> Q2 2024 | U26: =U5 -> Q3 2024 | V26: =V5 -> Q4 2024 | W26: =W5 -> Q1 2025 | X26: =X5 -> Q2 2025 | Y26: =Y5 -> Q3 2025 | Z26: =Z5 -> Q4 2025 | ... AC26: =AC5 -> FQ3 | AE26: =AE5 -> FQ1
B27: English test growth rate | D27: =D18 -> #REF! | E27: =E18 -> #REF! | F27: =F18 -> #REF! | G27: =G18 -> #REF! | H27: -0.05 | I27: -0.02 | J27: 0.03 | K27: 0.06 | L27: 0.08 | R27: English test growth rate | T27: =T18 -> #REF! | U27: =U18 -> #REF! | V27: =V18 -> #REF! | W27: =W18 -> #REF! | X27: =X18 -> #REF! | Y27: =Y18 -> #REF! | Z27: =Z18 -> #REF! | AA27: 0.01
B28: Other growth rate | D28: =D20 -> #REF! | E28: =E20 -> #REF! | F28: =F20 -> #REF! | G28: =G20 -> #REF! | H28: 0.45 | I28: 0.35 | J28: 0.3 | K28: 0.25 | L28: 0.2 | R28: Other growth rate | T28: =T19 -> #REF! | U28: =U19 -> #REF! | V28: =V19 -> #REF! | W28: =W19 -> #REF! | X28: =X19 -> #REF! | Y28: =Y19 -> #REF! | Z28: =Z19 -> #REF! | AA28: 0.04
B29: DAU | C29: ='Statement Y'!#REF! -> #REF! | D29: ='Statement Y'!#REF! -> #REF! | E29: ='Statement Y'!#REF! -> #REF! | F29: ='Statement Y'!#REF! -> #REF! | G29: ='Statement Y'!#REF! -> #REF! | H29: =G29*(1+H31) -> #REF! | I29: =H29*(1+I31) -> #REF! | J29: =I29*(1+J31) -> #REF! | K29: =J29*(1+K31) -> #REF! | L29: =K29*(1+L31) -> #REF! | N29: DAU growth rate | Q29: DAU growth rate | R29: DAU | S29: ='Statement Q'!#REF! -> #REF! | T29: ='Statement Q'!#REF! -> #REF! | U29: ='Statement Q'!#REF! -> #REF! | V29: ='Statement Q'!#REF! -> #REF! | W29: ='Statement Q'!#REF! -> #REF! | X29: ='Statement Q'!#REF! -> #REF! | Y29: ='Statement Q'!#REF! -> #REF! | Z29: ='Statement Q'!#REF! -> #REF! | AA29: =Z29*(1+AA31) -> #REF! | AE29: =AA29 -> #REF!
B30: MAU | C30: ='Statement Y'!#REF! -> #REF! | D30: ='Statement Y'!#REF! -> #REF! | E30: ='Statement Y'!#REF! -> #REF! | F30: ='Statement Y'!#REF! -> #REF! | G30: ='Statement Y'!#REF! -> #REF! | H30: =G30*(1+H32) -> #REF! | I30: =H30*(1+I32) -> #REF! | J30: =I30*(1+J32) -> #REF! | K30: =J30*(1+K32) -> #REF! | L30: =K30*(1+L32) -> #REF! | N30: MAU growth rate | Q30: MAU growth rate | R30: MAU | S30: ='Statement Q'!#REF! -> #REF! | T30: ='Statement Q'!#REF! -> #REF! | U30: ='Statement Q'!#REF! -> #REF! | V30: ='Statement Q'!#REF! -> #REF! | W30: ='Statement Q'!#REF! -> #REF! | X30: ='Statement Q'!#REF! -> #REF! | Y30: ='Statement Q'!#REF! -> #REF! | Z30: ='Statement Q'!#REF! -> #REF! | AA30: =Z30*(1+AA32) -> #REF! | AE30: =AA30 -> #REF!
B31: DAU growth rate | D31: =D29/C29-1 -> #REF! | E31: =E29/D29-1 -> #REF! | F31: =F29/E29-1 -> #REF! | G31: =G29/F29-1 -> #REF! | H31: 0.35 | I31: 0.37 | J31: 0.39 | K31: 0.41 | L31: 0.39 | R31: DAU growth rate | T31: =T29/S29-1 -> #REF! | U31: =U29/T29-1 -> #REF! | V31: =V29/U29-1 -> #REF! | W31: =W29/V29-1 -> #REF! | X31: =X29/W29-1 -> #REF! | Y31: =Y29/X29-1 -> #REF! | Z31: =Z29/Y29-1 -> #REF! | AA31: 0.06
B32: MAU growth rate | D32: =D30/C30-1 -> #REF! | E32: =E30/D30-1 -> #REF! | F32: =F30/E30-1 -> #REF! | G32: =G30/F30-1 -> #REF! | H32: 0.19 | I32: 0.26 | J32: 0.24 | K32: 0.28 | L32: 0.31 | R32: MAU growth rate | T32: =T30/S30-1 -> #REF! | U32: =U30/T30-1 -> #REF! | V32: =V30/U30-1 -> #REF! | W32: =W30/V30-1 -> #REF! | X32: =X30/W30-1 -> #REF! | Y32: =Y30/X30-1 -> #REF! | Z32: =Z30/Y30-1 -> #REF! | AA32: 0.03
B33: Ad revenue/Free user | C33: ='Statement Y'!#REF! -> #REF! | D33: ='Statement Y'!#REF! -> #REF! | E33: ='Statement Y'!#REF! -> #REF! | F33: ='Statement Y'!#REF! -> #REF! | G33: ='Statement Y'!#REF! -> #REF! | H33: 0.73 | I33: 0.75 | J33: 0.7 | K33: 0.75 | L33: 0.8 | R33: Ad revenue/Free user | S33: ='Statement Q'!#REF! -> #REF! | T33: ='Statement Q'!#REF! -> #REF! | U33: ='Statement Q'!#REF! -> #REF! | V33: ='Statement Q'!#REF! -> #REF! | W33: ='Statement Q'!#REF! -> #REF! | X33: ='Statement Q'!#REF! -> #REF! | Y33: ='Statement Q'!#REF! -> #REF! | Z33: ='Statement Q'!#REF! -> #REF! | AA33: 0.18 | AE33: =AE7/AE37 -> #REF!
B34: Subscribers to MAU ratio | C34: ='Statement Y'!#REF! -> #REF! | D34: ='Statement Y'!#REF! -> #REF! | E34: ='Statement Y'!#REF! -> #REF! | F34: ='Statement Y'!#REF! -> #REF! | G34: ='Statement Y'!#REF! -> #REF! | H34: =G34*(1+H35) -> #REF! | I34: =H34*(1+I35) -> #REF! | J34: =I34*(1+J35) -> #REF! | K34: =J34*(1+K35) -> #REF! | L34: =K34*(1+L35) -> #REF! | N34: Subscribers to MAU growth | Q34: Subscribers to MAU growth | R34: Subscribers to MAU ratio | S34: ='Statement Q'!#REF! -> #REF! | T34: ='Statement Q'!#REF! -> #REF! | U34: ='Statement Q'!#REF! -> #REF! | V34: ='Statement Q'!#REF! -> #REF! | W34: ='Statement Q'!#REF! -> #REF! | X34: ='Statement Q'!#REF! -> #REF! | Y34: ='Statement Q'!#REF! -> #REF! | Z34: ='Statement Q'!#REF! -> #REF! | AA34: =Z34*(1+AA35) -> #REF!
B35: Subscribers to MAU growth | D35: =D34/C34-1 -> #REF! | E35: =E34/D34-1 -> #REF! | F35: =F34/E34-1 -> #REF! | G35: =G34/F34-1 -> #REF! | H35: -0.06 | I35: -0.06 | J35: 0.05 | K35: 0.08 | L35: 0.11 | R35: Subscribers to MAU growth | T35: =T34/S34-1 -> #REF! | U35: =U34/T34-1 -> #REF! | V35: =V34/U34-1 -> #REF! | W35: =W34/V34-1 -> #REF! | X35: =X34/W34-1 -> #REF! | Y35: =Y34/X34-1 -> #REF! | Z35: =Z34/Y34-1 -> #REF! | AA35: -0.02
B36: Paid subscribers | C36: ='Statement Y'!#REF! -> #REF! | D36: ='Statement Y'!#REF! -> #REF! | E36: ='Statement Y'!#REF! -> #REF! | F36: ='Statement Y'!#REF! -> #REF! | G36: ='Statement Y'!#REF! -> #REF! | H36: =H34*H30 -> #REF! | I36: =I34*I30 -> #REF! | J36: =J34*J30 -> #REF! | K36: =K34*K30 -> #REF! | L36: =L34*L30 -> #REF! | N36: Subscribers to MAU ratio * MAU | Q36: Subscribers to MAU ratio * MAU | R36: Paid subscribers | S36: ='Statement Q'!#REF! -> #REF! | T36: ='Statement Q'!#REF! -> #REF! | U36: ='Statement Q'!#REF! -> #REF! | V36: ='Statement Q'!#REF! -> #REF! | W36: ='Statement Q'!#REF! -> #REF! | X36: ='Statement Q'!#REF! -> #REF! | Y36: ='Statement Q'!#REF! -> #REF! | Z36: ='Statement Q'!#REF! -> #REF! | AA36: =AA34*AA30 -> #REF! | AE36: =AA36 -> #REF!
B37: Free users | C37: ='Statement Y'!#REF! -> #REF! | D37: ='Statement Y'!#REF! -> #REF! | E37: ='Statement Y'!#REF! -> #REF! | F37: ='Statement Y'!#REF! -> #REF! | G37: ='Statement Y'!#REF! -> #REF! | H37: =H30-H36 -> #REF! | I37: =I30-I36 -> #REF! | J37: =J30-J36 -> #REF! | K37: =K30-K36 -> #REF! | L37: =L30-L36 -> #REF! | N37: MAU - Paid subscribers | Q37: MAU - Paid subscribers | R37: Free users | S37: ='Statement Q'!#REF! -> #REF! | T37: ='Statement Q'!#REF! -> #REF! | U37: ='Statement Q'!#REF! -> #REF! | V37: ='Statement Q'!#REF! -> #REF! | W37: ='Statement Q'!#REF! -> #REF! | X37: ='Statement Q'!#REF! -> #REF! | Y37: ='Statement Q'!#REF! -> #REF! | Z37: ='Statement Q'!#REF! -> #REF! | AA37: =AA30-AA36 -> #REF! | AE37: =AA37 -> #REF!
B38: In-App purchases % of DAU | C38: ='Statement Y'!#REF! -> #REF! | D38: ='Statement Y'!#REF! -> #REF! | E38: ='Statement Y'!#REF! -> #REF! | F38: ='Statement Y'!#REF! -> #REF! | G38: ='Statement Y'!#REF! -> #REF! | H38: 0.7 | I38: 0.65 | J38: 0.6 | K38: 0.65 | L38: 0.65 | R38: In-App purchases % of DAU | S38: ='Statement Q'!#REF! -> #REF! | T38: ='Statement Q'!#REF! -> #REF! | U38: ='Statement Q'!#REF! -> #REF! | V38: ='Statement Q'!#REF! -> #REF! | W38: ='Statement Q'!#REF! -> #REF! | X38: ='Statement Q'!#REF! -> #REF! | Y38: ='Statement Q'!#REF! -> #REF! | Z38: ='Statement Q'!#REF! -> #REF! | AA38: 0.16
B39: Avg revenue/Paid user | C39: ='Statement Y'!#REF! -> #REF! | D39: ='Statement Y'!#REF! -> #REF! | E39: ='Statement Y'!#REF! -> #REF! | F39: ='Statement Y'!#REF! -> #REF! | G39: ='Statement Y'!#REF! -> #REF! | H39: 73.5 | I39: 75 | J39: 73 | K39: 76 | L39: 78 | R39: Avg revenue/Paid user | S39: ='Statement Q'!#REF! -> #REF! | T39: ='Statement Q'!#REF! -> #REF! | U39: ='Statement Q'!#REF! -> #REF! | V39: ='Statement Q'!#REF! -> #REF! | W39: ='Statement Q'!#REF! -> #REF! | X39: ='Statement Q'!#REF! -> #REF! | Y39: ='Statement Q'!#REF! -> #REF! | Z39: ='Statement Q'!#REF! -> #REF! | AA39: 20
B40: DAU to MAU ratio | C40: ='Statement Y'!#REF! -> #REF! | D40: ='Statement Y'!#REF! -> #REF! | E40: ='Statement Y'!#REF! -> #REF! | F40: ='Statement Y'!#REF! -> #REF! | G40: ='Statement Y'!#REF! -> #REF! | H40: 0.44 | I40: =I29/I30 -> #REF! | J40: =J29/J30 -> #REF! | K40: =K29/K30 -> #REF! | L40: =L29/L30 -> #REF! | R40: DAU to MAU ratio | S40: ='Statement Q'!#REF! -> #REF! | T40: ='Statement Q'!#REF! -> #REF! | U40: ='Statement Q'!#REF! -> #REF! | V40: ='Statement Q'!#REF! -> #REF! | W40: ='Statement Q'!#REF! -> #REF! | X40: ='Statement Q'!#REF! -> #REF! | Y40: ='Statement Q'!#REF! -> #REF! | Z40: ='Statement Q'!#REF! -> #REF! | AA40: =AA29/AA30 -> #REF!
C43: Growth rates for metrics | S43: Growth rates for metrics
B44: Metrics growth % | C44: =C5 -> 2021 | D44: =D5 -> 2022 | E44: =E5 -> 2023 | F44: =F5 -> 2024 | G44: =G5 -> 2025 | H44: =H5 -> 2026 | I44: =I5 -> 2027 | J44: =J5 -> 2028 | ... L44: =L5 -> 2030 | R44: Metrics growth % | S44: =S5 -> Q1 2024 | T44: =T5 -> Q2 2024 | U44: =U5 -> Q3 2024 | V44: =V5 -> Q4 2024 | W44: =W5 -> Q1 2025 | X44: =X5 -> Q2 2025 | Y44: =Y5 -> Q3 2025 | Z44: =Z5 -> Q4 2025 | ... AC44: =AC5 -> FQ3
B45: Ad revenue/Free user | D45: =D33/C33-1 -> #REF! | E45: =E33/D33-1 -> #REF! | F45: =F33/E33-1 -> #REF! | G45: =G33/F33-1 -> #REF! | H45: =H33/G33-1 -> #REF! | I45: =I33/H33-1 -> 0.02739726 | J45: =J33/I33-1 -> -0.066666667 | K45: =K33/J33-1 -> 0.071428571 | L45: =L33/K33-1 -> 0.066666667 | R45: Ad revenue/Free user | T45: =T33/S33-1 -> #REF! | U45: =U33/T33-1 -> #REF! | V45: =V33/U33-1 -> #REF! | W45: =W33/V33-1 -> #REF! | X45: =X33/W33-1 -> #REF! | Y45: =Y33/X33-1 -> #REF! | Z45: =Z33/Y33-1 -> #REF! | AA45: =AA33/Z33-1 -> #REF!
B46: Paid subscribers | D46: =D36/C36-1 -> #REF! | E46: =E36/D36-1 -> #REF! | F46: =F36/E36-1 -> #REF! | G46: =G36/F36-1 -> #REF! | H46: =H36/G36-1 -> #REF! | I46: =I36/H36-1 -> #REF! | J46: =J36/I36-1 -> #REF! | K46: =K36/J36-1 -> #REF! | L46: =L36/K36-1 -> #REF! | R46: Paid subscribers | T46: =T36/S36-1 -> #REF! | U46: =U36/T36-1 -> #REF! | V46: =V36/U36-1 -> #REF! | W46: =W36/V36-1 -> #REF! | X46: =X36/W36-1 -> #REF! | Y46: =Y36/X36-1 -> #REF! | Z46: =Z36/Y36-1 -> #REF! | AA46: =AA36/Z36-1 -> #REF!
B47: Free users | D47: =D37/C37-1 -> #REF! | E47: =E37/D37-1 -> #REF! | F47: =F37/E37-1 -> #REF! | G47: =G37/F37-1 -> #REF! | H47: =H37/G37-1 -> #REF! | I47: =I37/H37-1 -> #REF! | J47: =J37/I37-1 -> #REF! | K47: =K37/J37-1 -> #REF! | L47: =L37/K37-1 -> #REF! | R47: Free users | T47: =T37/S37-1 -> #REF! | U47: =U37/T37-1 -> #REF! | V47: =V37/U37-1 -> #REF! | W47: =W37/V37-1 -> #REF! | X47: =X37/W37-1 -> #REF! | Y47: =Y37/X37-1 -> #REF! | Z47: =Z37/Y37-1 -> #REF! | AA47: =AA37/Z37-1 -> #REF!
B48: In-App purchases % of DAU | D48: =D38/C38-1 -> #REF! | E48: =E38/D38-1 -> #REF! | F48: =F38/E38-1 -> #REF! | G48: =G38/F38-1 -> #REF! | H48: =H38/G38-1 -> #REF! | I48: =I38/H38-1 -> -0.071428571 | J48: =J38/I38-1 -> -0.076923077 | K48: =K38/J38-1 -> 0.083333333 | L48: =L38/K38-1 -> 0 | R48: In-App purchases % of DAU | T48: =T38/S38-1 -> #REF! | U48: =U38/T38-1 -> #REF! | V48: =V38/U38-1 -> #REF! | W48: =W38/V38-1 -> #REF! | X48: =X38/W38-1 -> #REF! | Y48: =Y38/X38-1 -> #REF! | Z48: =Z38/Y38-1 -> #REF! | AA48: =AA38/Z38-1 -> #REF!
B49: Avg revenue/Paid user | D49: =D39/C39-1 -> #REF! | E49: =E39/D39-1 -> #REF! | F49: =F39/E39-1 -> #REF! | G49: =G39/F39-1 -> #REF! | H49: =H39/G39-1 -> #REF! | I49: =I39/H39-1 -> 0.020408163 | J49: =J39/I39-1 -> -0.026666667 | K49: =K39/J39-1 -> 0.04109589 | L49: =L39/K39-1 -> 0.026315789 | R49: Avg revenue/Paid user | T49: =T39/S39-1 -> #REF! | U49: =U39/T39-1 -> #REF! | V49: =V39/U39-1 -> #REF! | W49: =W39/V39-1 -> #REF! | X49: =X39/W39-1 -> #REF! | Y49: =Y39/X39-1 -> #REF! | Z49: =Z39/Y39-1 -> #REF! | AA49: =AA39/Z39-1 -> #REF!
B50: DAU to MAU ratio | D50: =D40/C40-1 -> #REF! | E50: =E40/D40-1 -> #REF! | F50: =F40/E40-1 -> #REF! | G50: =G40/F40-1 -> #REF! | H50: =H40/G40-1 -> #REF! | I50: =I40/H40-1 -> #REF! | J50: =J40/I40-1 -> #REF! | K50: =K40/J40-1 -> #REF! | L50: =L40/K40-1 -> #REF! | R50: DAU to MAU ratio | T50: =T40/S40-1 -> #REF! | U50: =U40/T40-1 -> #REF! | V50: =V40/U40-1 -> #REF! | W50: =W40/V40-1 -> #REF! | X50: =X40/W40-1 -> #REF! | Y50: =Y40/X40-1 -> #REF! | Z50: =Z40/Y40-1 -> #REF! | AA50: =AA40/Z40-1 -> #REF!

Sheet COGS & OpEx
B1: COGS & OpEx forecast
C2: History | H2: Forecast | P2: History | X2: Forecast | AB2: TTM
C4: Revenues | P4: Revenues | AB4: Q1-Q2-Q3
B5: Revenues (thousand) | C5: ='Statement Y'!D3 -> 2021 | D5: ='Statement Y'!E3 -> 2022 | E5: ='Statement Y'!F3 -> 2023 | F5: ='Statement Y'!G3 -> 2024 | G5: ='Statement Y'!H3 -> 2025 | H5: =G5+1 -> 2026 | I5: =H5+1 -> 2027 | J5: =I5+1 -> 2028 | K5: =J5+1 -> 2029 | L5: =K5+1 -> 2030 | O5: Revenues (thousand) | P5: ='Statement Q'!C3 -> Q1 2024 | Q5: ='Statement Q'!D3 -> Q2 2024 | R5: ='Statement Q'!E3 -> Q3 2024 | S5: ='Statement Q'!F3 -> Q4 2024 | T5: ='Statement Q'!G3 -> Q1 2025 | U5: ='Statement Q'!H3 -> Q2 2025 | V5: ='Statement Q'!I3 -> Q3 2025 | W5: ='Statement Q'!J3 -> Q4 2025 | X5: FQ1 | Y5: FQ2 | Z5: FQ3 | AB5: FQ1
B6: Revenue | C6: ='Statement Y'!D5 -> 0 | D6: ='Statement Y'!E5 -> 0 | E6: ='Statement Y'!F5 -> 0 | F6: ='Statement Y'!G5 -> 0 | G6: ='Statement Y'!H5 -> 0 | H6: =Revenue!H12 -> #REF! | I6: =Revenue!I12 -> #REF! | J6: =Revenue!J12 -> #REF! | K6: =Revenue!K12 -> #REF! | L6: =Revenue!L12 -> #REF! | O6: Revenue | P6: ='Statement Q'!C5 -> 0 | Q6: ='Statement Q'!D5 -> 0 | R6: ='Statement Q'!E5 -> 0 | S6: ='Statement Q'!F5 -> 0 | T6: ='Statement Q'!G5 -> 0 | U6: ='Statement Q'!H5 -> 0 | V6: ='Statement Q'!I5 -> 0 | W6: ='Statement Q'!J5 -> 0 | X6: =Revenue!AA12 -> #REF! | Y6: =Revenue!AB12 -> 0 | Z6: =Revenue!AC12 -> 0 | AB6: =SUM(U6:X6) -> #REF!
C9: COGS and OpEx | P9: COGS & OpEx | AB9: =AB4 -> Q1-Q2-Q3
B10: Expenses (thousand) | C10: =C5 -> 2021 | D10: =D5 -> 2022 | E10: =E5 -> 2023 | F10: =F5 -> 2024 | G10: =G5 -> 2025 | H10: =H5 -> 2026 | I10: =I5 -> 2027 | J10: =J5 -> 2028 | ... L10: =L5 -> 2030 | O10: Expenses (thousand) | P10: =P5 -> Q1 2024 | Q10: =Q5 -> Q2 2024 | R10: =R5 -> Q3 2024 | S10: =S5 -> Q4 2024 | T10: =T5 -> Q1 2025 | U10: =U5 -> Q2 2025 | V10: =V5 -> Q3 2025 | W10: =W5 -> Q4 2025 | ... Z10: =Z5 -> FQ3 | AB10: =AB5 -> FQ1
B11: COGS | C11: ='Statement Y'!D6 -> 0 | D11: ='Statement Y'!E6 -> 0 | E11: ='Statement Y'!F6 -> 0 | F11: ='Statement Y'!G6 -> 0 | G11: ='Statement Y'!H6 -> 0 | H11: =H20*H$6 -> #REF! | I11: =I20*I$6 -> #REF! | J11: =J20*J$6 -> #REF! | K11: =K20*K$6 -> #REF! | L11: =L20*L$6 -> #REF! | O11: COGS | P11: ='Statement Q'!C6 -> 0 | Q11: ='Statement Q'!D6 -> 0 | R11: ='Statement Q'!E6 -> 0 | S11: ='Statement Q'!F6 -> 0 | T11: ='Statement Q'!G6 -> 0 | U11: ='Statement Q'!H6 -> 0 | V11: ='Statement Q'!I6 -> 0 | W11: ='Statement Q'!J6 -> 0 | X11: =X20*X$6 -> #REF! | AB11: =SUM(U11:X11) -> #REF!
B12: R&D | C12: ='Statement Y'!D8 -> 0 | D12: ='Statement Y'!E8 -> 0 | E12: ='Statement Y'!F8 -> 0 | F12: ='Statement Y'!G8 -> 0 | G12: ='Statement Y'!H8 -> 0 | H12: =H21*H$6 -> #REF! | I12: =I21*I$6 -> #REF! | J12: =J21*J$6 -> #REF! | K12: =K21*K$6 -> #REF! | L12: =L21*L$6 -> #REF! | O12: R&D | P12: ='Statement Q'!C8 -> 0 | Q12: ='Statement Q'!D8 -> 0 | R12: ='Statement Q'!E8 -> 0 | S12: ='Statement Q'!F8 -> 0 | T12: ='Statement Q'!G8 -> 0 | U12: ='Statement Q'!H8 -> 0 | V12: ='Statement Q'!I8 -> 0 | W12: ='Statement Q'!J8 -> 0 | X12: =X21*X$6 -> #REF! | AB12: =SUM(U12:X12) -> #REF!
B13: Sales and marketing | C13: ='Statement Y'!D9 -> 0 | D13: ='Statement Y'!E9 -> 0 | E13: ='Statement Y'!F9 -> 0 | F13: ='Statement Y'!G9 -> 0 | G13: ='Statement Y'!H9 -> 0 | H13: =H22*H$6 -> #REF! | I13: =I22*I$6 -> #REF! | J13: =J22*J$6 -> #REF! | K13: =K22*K$6 -> #REF! | L13: =L22*L$6 -> #REF! | O13: Sales and marketing | P13: ='Statement Q'!C9 -> 0 | Q13: ='Statement Q'!D9 -> 0 | R13: ='Statement Q'!E9 -> 0 | S13: ='Statement Q'!F9 -> 0 | T13: ='Statement Q'!G9 -> 0 | U13: ='Statement Q'!H9 -> 0 | V13: ='Statement Q'!I9 -> 0 | W13: ='Statement Q'!J9 -> 0 | X13: =X22*X$6 -> #REF! | AB13: =SUM(U13:X13) -> #REF!
B14: General & administrative | C14: ='Statement Y'!D10 -> 0 | D14: ='Statement Y'!E10 -> 0 | E14: ='Statement Y'!F10 -> 0 | F14: ='Statement Y'!G10 -> 0 | G14: ='Statement Y'!H10 -> 0 | H14: =H23*H$6 -> #REF! | I14: =I23*I$6 -> #REF! | J14: =J23*J$6 -> #REF! | K14: =K23*K$6 -> #REF! | L14: =L23*L$6 -> #REF! | O14: General & administrative | P14: ='Statement Q'!C10 -> 0 | Q14: ='Statement Q'!D10 -> 0 | R14: ='Statement Q'!E10 -> 0 | S14: ='Statement Q'!F10 -> 0 | T14: ='Statement Q'!G10 -> 0 | U14: ='Statement Q'!H10 -> 0 | V14: ='Statement Q'!I10 -> 0 | W14: ='Statement Q'!J10 -> 0 | X14: =X23*X$6 -> #REF! | AB14: =SUM(U14:X14) -> #REF!
B15: OpEx | C15: ='Statement Y'!D11 -> 0 | D15: ='Statement Y'!E11 -> 0 | E15: ='Statement Y'!F11 -> 0 | F15: ='Statement Y'!G11 -> 0 | G15: ='Statement Y'!H11 -> 0 | H15: =SUM(H12:H14) -> #REF! | I15: =SUM(I12:I14) -> #REF! | J15: =SUM(J12:J14) -> #REF! | K15: =SUM(K12:K14) -> #REF! | L15: =SUM(L12:L14) -> #REF! | O15: OpEx | P15: ='Statement Q'!C11 -> 0 | Q15: ='Statement Q'!D11 -> 0 | R15: ='Statement Q'!E11 -> 0 | S15: ='Statement Q'!F11 -> 0 | T15: ='Statement Q'!G11 -> 0 | U15: ='Statement Q'!H11 -> 0 | V15: ='Statement Q'!I11 -> 0 | W15: ='Statement Q'!J11 -> 0 | X15: =SUM(X12:X14) -> #REF! | AB15: =SUM(U15:X15) -> #REF!
C18: Expenses % of Revenue | P18: Expenses % of Revenue
B19: % of revenue | C19: =C5 -> 2021 | D19: =D5 -> 2022 | E19: =E5 -> 2023 | F19: =F5 -> 2024 | G19: =G5 -> 2025 | H19: =H5 -> 2026 | I19: =I5 -> 2027 | J19: =J5 -> 2028 | ... L19: =L5 -> 2030 | O19: % of revenue | P19: =P5 -> Q1 2024 | Q19: =Q5 -> Q2 2024 | R19: =R5 -> Q3 2024 | S19: =S5 -> Q4 2024 | T19: =T5 -> Q1 2025 | U19: =U5 -> Q2 2025 | V19: =V5 -> Q3 2025 | W19: =W5 -> Q4 2025 | ... Z19: =Z5 -> FQ3
B20: =B11 -> COGS | C20: =C11/C$6 -> #DIV/0! | D20: =D11/D$6 -> #DIV/0! | E20: =E11/E$6 -> #DIV/0! | F20: =F11/F$6 -> #DIV/0! | G20: =G11/G$6 -> #DIV/0! | H20: 0.28 | I20: 0.275 | J20: 0.28 | K20: 0.268 | L20: 0.276 | O20: =O11 -> COGS | P20: =P11/P$6 -> #DIV/0! | Q20: =Q11/Q$6 -> #DIV/0! | R20: =R11/R$6 -> #DIV/0! | S20: =S11/S$6 -> #DIV/0! | T20: =T11/T$6 -> #DIV/0! | U20: =U11/U$6 -> #DIV/0! | V20: =V11/V$6 -> #DIV/0! | W20: =W11/W$6 -> #DIV/0! | X20: 0.28
B21: =B12 -> R&D | C21: =C12/C$6 -> #DIV/0! | D21: =D12/D$6 -> #DIV/0! | E21: =E12/E$6 -> #DIV/0! | F21: =F12/F$6 -> #DIV/0! | G21: =G12/G$6 -> #DIV/0! | H21: 0.35 | I21: 0.3 | J21: 0.3 | K21: 0.31 | L21: 0.29 | O21: =O12 -> R&D | P21: =P12/P$6 -> #DIV/0! | Q21: =Q12/Q$6 -> #DIV/0! | R21: =R12/R$6 -> #DIV/0! | S21: =S12/S$6 -> #DIV/0! | T21: =T12/T$6 -> #DIV/0! | U21: =U12/U$6 -> #DIV/0! | V21: =V12/V$6 -> #DIV/0! | W21: =W12/W$6 -> #DIV/0! | X21: 0.296
B22: =B13 -> Sales and marketing | C22: =C13/C$6 -> #DIV/0! | D22: =D13/D$6 -> #DIV/0! | E22: =E13/E$6 -> #DIV/0! | F22: =F13/F$6 -> #DIV/0! | G22: =G13/G$6 -> #DIV/0! | H22: 0.13 | I22: 0.125 | J22: 0.12 | K22: 0.115 | L22: 0.11 | O22: =O13 -> Sales and marketing | P22: =P13/P$6 -> #DIV/0! | Q22: =Q13/Q$6 -> #DIV/0! | R22: =R13/R$6 -> #DIV/0! | S22: =S13/S$6 -> #DIV/0! | T22: =T13/T$6 -> #DIV/0! | U22: =U13/U$6 -> #DIV/0! | V22: =V13/V$6 -> #DIV/0! | W22: =W13/W$6 -> #DIV/0! | X22: 0.115
B23: =B14 -> General & administrative | C23: =C14/C$6 -> #DIV/0! | D23: =D14/D$6 -> #DIV/0! | E23: =E14/E$6 -> #DIV/0! | F23: =F14/F$6 -> #DIV/0! | G23: =G14/G$6 -> #DIV/0! | H23: 0.18 | I23: 0.17 | J23: 0.16 | K23: 0.175 | L23: 0.17 | O23: =O14 -> General & administrative | P23: =P14/P$6 -> #DIV/0! | Q23: =Q14/Q$6 -> #DIV/0! | R23: =R14/R$6 -> #DIV/0! | S23: =S14/S$6 -> #DIV/0! | T23: =T14/T$6 -> #DIV/0! | U23: =U14/U$6 -> #DIV/0! | V23: =V14/V$6 -> #DIV/0! | W23: =W14/W$6 -> #DIV/0! | X23: 0.185

Sheet PP&E
B1: PP&E, D&A and CapEx
B3: ="CapEx:"&CHOOSE(C3," as a % of PP&E"," as a % of revenue") -> CapEx: as a % of revenue | C3: 2
C5: History | H5: Forecast
C7: Revenues
B8: Revenues (thousand) | C8: ='Statement Y'!D3 -> 2021 | D8: ='Statement Y'!E3 -> 2022 | E8: ='Statement Y'!F3 -> 2023 | F8: ='Statement Y'!G3 -> 2024 | G8: ='Statement Y'!H3 -> 2025 | H8: =G8+1 -> 2026 | I8: =H8+1 -> 2027 | J8: =I8+1 -> 2028 | K8: =J8+1 -> 2029 | L8: =K8+1 -> 2030
B9: Revenue | C9: ='Statement Y'!D5 -> 0 | D9: ='Statement Y'!E5 -> 0 | E9: ='Statement Y'!F5 -> 0 | F9: ='Statement Y'!G5 -> 0 | G9: ='Statement Y'!H5 -> 0 | H9: =Revenue!H12 -> #REF! | I9: =Revenue!I12 -> #REF! | J9: =Revenue!J12 -> #REF! | K9: =Revenue!K12 -> #REF! | L9: =Revenue!L12 -> #REF!
C12: PP&E
B13: $ (thousand) | C13: =C8 -> 2021 | D13: =D8 -> 2022 | E13: =E8 -> 2023 | F13: =F8 -> 2024 | G13: =G8 -> 2025 | H13: =H8 -> 2026 | I13: =I8 -> 2027 | J13: =J8 -> 2028 | ... L13: =L8 -> 2030
B14: Beginning PP&E | C14: ='Statement Y'!C32 -> 0 | D14: =C17 -> 0 | E14: =D17 -> 0 | F14: =E17 -> 0 | G14: =F17 -> 0 | H14: =G17 -> 0 | I14: =H17 -> #DIV/0! | J14: =I17 -> #DIV/0! | K14: =J17 -> #DIV/0! | L14: =K17 -> #DIV/0!
B15: CapEx | C15: =-'Statement Y'!D74 -> 0 | D15: =-'Statement Y'!E74 -> 0 | E15: =-'Statement Y'!F74 -> 0 | F15: =-'Statement Y'!G74 -> 0 | G15: =-'Statement Y'!H74 -> 0 | H15: =CHOOSE($C$3,H34*H14,H35*H9) -> #DIV/0! | I15: =CHOOSE($C$3,I34*I14,I35*I9) -> #DIV/0! | J15: =CHOOSE($C$3,J34*J14,J35*J9) -> #DIV/0! | K15: =CHOOSE($C$3,K34*K14,K35*K9) -> #DIV/0! | L15: =CHOOSE($C$3,L34*L14,L35*L9) -> #DIV/0!
B16: Depreciation | C16: ='Statement Y'!D115 -> 0 | D16: ='Statement Y'!E115 -> 0 | E16: ='Statement Y'!F115 -> 0 | F16: ='Statement Y'!G115 -> 0 | G16: ='Statement Y'!H115 -> 0 | H16: =H27 -> #DIV/0! | I16: =I27 -> #DIV/0! | J16: =J27 -> #DIV/0! | K16: =K27 -> #DIV/0! | L16: =L27 -> #DIV/0!
B17: Ending PP&E | C17: ='Statement Y'!D32 -> 0 | D17: ='Statement Y'!E32 -> 0 | E17: ='Statement Y'!F32 -> 0 | F17: ='Statement Y'!G32 -> 0 | G17: ='Statement Y'!H32 -> 0 | H17: =H14+H15-H16 -> #DIV/0! | I17: =I14+I15-I16 -> #DIV/0! | J17: =J14+J15-J16 -> #DIV/0! | K17: =K14+K15-K16 -> #DIV/0! | L17: =L14+L15-L16 -> #DIV/0!
C20: Depreciation schedule
B21: $ (thousand) | C21: =C8 -> 2021 | D21: =D8 -> 2022 | E21: =E8 -> 2023 | F21: =F8 -> 2024 | G21: =G8 -> 2025 | H21: =H8 -> 2026 | I21: =I8 -> 2027 | J21: =J8 -> 2028 | ... L21: =L8 -> 2030
B22: =H8 -> 2026 | H22: =IF(COUNT($H$22:H22) <= $C$39, $H$14/$C$39+$H$15/$C$38, 0) -> #DIV/0! | I22: =IF(COUNT($H$22:I22) <= $C$39, $H$14/$C$39+$H$15/$C$38, 0) -> #DIV/0! | J22: =IF(COUNT($H$22:J22) <= $C$39, $H$14/$C$39+$H$15/$C$38, 0) -> #DIV/0! | K22: =IF(COUNT($H$22:K22) <= $C$39, $H$14/$C$39+$H$15/$C$38, 0) -> #DIV/0! | L22: =IF(COUNT($H$22:L22) <= $C$39, $H$14/$C$39+$H$15/$C$38, 0) -> #DIV/0!
B23: =I8 -> 2027 | I23: =$I$15/$C$38 -> #DIV/0! | J23: =$I$15/$C$38 -> #DIV/0! | K23: =$I$15/$C$38 -> #DIV/0! | L23: =$I$15/$C$38 -> #DIV/0!
B24: =J8 -> 2028 | J24: =$J$15/$C$38 -> #DIV/0! | K24: =$J$15/$C$38 -> #DIV/0! | L24: =$J$15/$C$38 -> #DIV/0!
B25: =K8 -> 2029 | K25: =$K$15/$C$38 -> #DIV/0! | L25: =$K$15/$C$38 -> #DIV/0!
B26: =L8 -> 2030 | L26: =L15/C38 -> #DIV/0!
B27: Total | H27: =SUM(H22:H26) -> #DIV/0! | I27: =SUM(I22:I26) -> #DIV/0! | J27: =SUM(J22:J26) -> #DIV/0! | K27: =SUM(K22:K26) -> #DIV/0! | L27: =SUM(L22:L26) -> #DIV/0!
C30: CapEx Drivers
B31: % of | C31: =C8 -> 2021 | D31: =D8 -> 2022 | E31: =E8 -> 2023 | F31: =F8 -> 2024 | G31: =G8 -> 2025 | H31: =H8 -> 2026 | I31: =I8 -> 2027 | J31: =J8 -> 2028 | ... L31: =L8 -> 2030
B32: D&A % of PP&E | C32: =C16/C14 -> #DIV/0! | D32: =D16/D14 -> #DIV/0! | E32: =E16/E14 -> #DIV/0! | F32: =F16/F14 -> #DIV/0! | G32: =G16/G14 -> #DIV/0! | H32: =H16/H14 -> #DIV/0! | I32: =I16/I14 -> #DIV/0! | J32: =J16/J14 -> #DIV/0! | ... L32: =L16/L14 -> #DIV/0!
B33: D&A % of revenue | C33: =C16/C9 -> #DIV/0! | D33: =D16/D9 -> #DIV/0! | E33: =E16/E9 -> #DIV/0! | F33: =F16/F9 -> #DIV/0! | G33: =G16/G9 -> #DIV/0! | H33: =H16/H9 -> #DIV/0! | I33: =I16/I9 -> #DIV/0! | J33: =J16/J9 -> #DIV/0! | ... L33: =L16/L9 -> #DIV/0!
B34: CapEx % of PP&E | C34: =C15/C14 -> #DIV/0! | D34: =D15/D14 -> #DIV/0! | E34: =E15/E14 -> #DIV/0! | F34: =F15/F14 -> #DIV/0! | G34: =G15/G14 -> #DIV/0! | H34: =AVERAGE(D34:G34) -> #DIV/0! | I34: =$H$34 -> #DIV/0! | J34: =$H$34 -> #DIV/0! | K34: =$H$34 -> #DIV/0! | L34: =$H$34 -> #DIV/0!
B35: CapEx % of revenue | C35: =C15/C9 -> #DIV/0! | D35: =D15/D9 -> #DIV/0! | E35: =E15/E9 -> #DIV/0! | F35: =F15/F9 -> #DIV/0! | G35: =G15/G9 -> #DIV/0! | H35: =AVERAGE(D35:G35) -> #DIV/0! | I35: =$H$35 -> #DIV/0! | J35: =$H$35 -> #DIV/0! | K35: =$H$35 -> #DIV/0! | L35: =$H$35 -> #DIV/0!
B37: PP&E and CapEx useful life
B38: Useful life CapEx | C38: 7
B39: Useful life historical PP&E | C39: 6
C42: Historical PP&E data
B43: $ (thousands) | C43: =C8 -> 2021 | D43: =D8 -> 2022 | E43: =E8 -> 2023 | F43: =F8 -> 2024 | G43: =G8 -> 2025
B44: ='Statement Y'!B119 -> Gross PP&E | C44: ='Statement Y'!C119 -> 0 | D44: ='Statement Y'!D119 -> 0 | E44: ='Statement Y'!E119 -> 0 | F44: ='Statement Y'!F119 -> 0 | G44: ='Statement Y'!G119 -> 0
B45: ='Statement Y'!B120 -> Accumulated depreciation | C45: ='Statement Y'!C120 -> 0 | D45: ='Statement Y'!D120 -> 0 | E45: ='Statement Y'!E120 -> 0 | F45: ='Statement Y'!F120 -> 0 | G45: ='Statement Y'!G120 -> 0
B46: Remaining useful life years | C46: =C17/C16 -> #DIV/0! | D46: =D17/D16 -> #DIV/0! | E46: =E17/E16 -> #DIV/0! | F46: =F17/F16 -> #DIV/0! | G46: =G17/G16 -> #DIV/0!
B47: Percent depreciated | C47: =C45/C44 -> #DIV/0! | D47: =D45/D44 -> #DIV/0! | E47: =E45/E44 -> #DIV/0! | F47: =F45/F44 -> #DIV/0! | G47: =G45/G44 -> #DIV/0!
B50: Average useful life PP&E
B51: Avg Gross PP&E | C51: =AVERAGE(C44:G44) -> 0
B52: Avg accumulated deprec | C52: =AVERAGE(C16:G16) -> 0
B53: Avg useful life years | C53: =C51/C52 -> #DIV/0!

Sheet Intangibles
B1: Intangibles
B3: ="CapEx:"&CHOOSE(C3," as a % of Intangibles"," as a % of revenue") -> CapEx: as a % of revenue | C3: 2
C5: History | H5: Forecast
C7: Revenues
B8: Revenues (thousand) | C8: ='Statement Y'!D3 -> 2021 | D8: ='Statement Y'!E3 -> 2022 | E8: ='Statement Y'!F3 -> 2023 | F8: ='Statement Y'!G3 -> 2024 | G8: ='Statement Y'!H3 -> 2025 | H8: =G8+1 -> 2026 | I8: =H8+1 -> 2027 | J8: =I8+1 -> 2028 | K8: =J8+1 -> 2029 | L8: =K8+1 -> 2030
B9: Revenue | C9: ='Statement Y'!D5 -> 0 | D9: ='Statement Y'!E5 -> 0 | E9: ='Statement Y'!F5 -> 0 | F9: ='Statement Y'!G5 -> 0 | G9: ='Statement Y'!H5 -> 0 | H9: =Revenue!H12 -> #REF! | I9: =Revenue!I12 -> #REF! | J9: =Revenue!J12 -> #REF! | K9: =Revenue!K12 -> #REF! | L9: =Revenue!L12 -> #REF!
C12: PP&E
B13: $ (thousand) | C13: =C8 -> 2021 | D13: =D8 -> 2022 | E13: =E8 -> 2023 | F13: =F8 -> 2024 | G13: =G8 -> 2025 | H13: =H8 -> 2026 | I13: =I8 -> 2027 | J13: =J8 -> 2028 | ... L13: =L8 -> 2030
B14: Beginning Inangibles | C14: ='Statement Y'!C34 -> 0 | D14: =C17 -> 0 | E14: =D17 -> 0 | F14: =E17 -> 0 | G14: =F17 -> 0 | H14: =G17 -> 0 | I14: =H17 -> #DIV/0! | J14: =I17 -> #DIV/0! | K14: =J17 -> #DIV/0! | L14: =K17 -> #DIV/0!
B15: CapEx | C15: =-'Statement Y'!D79 -> 0 | D15: =-'Statement Y'!E79 -> 0 | E15: =-'Statement Y'!F79 -> 0 | F15: =-'Statement Y'!G79 -> 0 | G15: =-'Statement Y'!H79 -> 0 | H15: =CHOOSE($C$3,H24*H14,H25*H9) -> #DIV/0! | I15: =CHOOSE($C$3,I24*I14,I25*I9) -> #DIV/0! | J15: =CHOOSE($C$3,J24*J14,J25*J9) -> #REF! | K15: =CHOOSE($C$3,K24*K14,K25*K9) -> #REF! | L15: =CHOOSE($C$3,L24*L14,L25*L9) -> #REF!
B16: Amortization | C16: ='Statement Y'!D116 -> 0 | D16: ='Statement Y'!E116 -> 0 | E16: ='Statement Y'!F116 -> 0 | F16: ='Statement Y'!G116 -> 0 | G16: ='Statement Y'!H116 -> 0 | H16: =H38+H43 -> #DIV/0! | I16: =I38+I43 -> #DIV/0! | J16: =J38+J43 -> #DIV/0! | K16: =K38+K43 -> #DIV/0! | L16: =L38+L43 -> #DIV/0!
B17: Ending Intangibles | C17: ='Statement Y'!D34 -> 0 | D17: ='Statement Y'!E34 -> 0 | E17: ='Statement Y'!F34 -> 0 | F17: ='Statement Y'!G34 -> 0 | G17: ='Statement Y'!H34 -> 0 | H17: =H14+H15-H16 -> #DIV/0! | I17: =I14+I15-I16 -> #DIV/0! | J17: =J14+J15-J16 -> #DIV/0! | K17: =K14+K15-K16 -> #DIV/0! | L17: =L14+L15-L16 -> #DIV/0!
C20: CapEx Drivers
B21: % of | C21: =C8 -> 2021 | D21: =D8 -> 2022 | E21: =E8 -> 2023 | F21: =F8 -> 2024 | G21: =G8 -> 2025 | H21: =H8 -> 2026 | I21: =I8 -> 2027 | J21: =J8 -> 2028 | ... L21: =L8 -> 2030
B22: D&A % of Intangibles | C22: =C16/C14 -> #DIV/0! | D22: =D16/D14 -> #DIV/0! | E22: =E16/E14 -> #DIV/0! | F22: =F16/F14 -> #DIV/0! | G22: =G16/G14 -> #DIV/0! | H22: =H16/H14 -> #DIV/0! | I22: =I16/I14 -> #DIV/0! | J22: =J16/J14 -> #DIV/0! | ... L22: =L16/L14 -> #DIV/0!
B23: D&A % of revenue | C23: =C16/C9 -> #DIV/0! | D23: =D16/D9 -> #DIV/0! | E23: =E16/E9 -> #DIV/0! | F23: =F16/F9 -> #DIV/0! | G23: =G16/G9 -> #DIV/0! | H23: =H16/H9 -> #DIV/0! | I23: =I16/I9 -> #DIV/0! | J23: =J16/J9 -> #DIV/0! | ... L23: =L16/L9 -> #DIV/0!
B24: CapEx % of intangibles | C24: =C15/C14 -> #DIV/0! | D24: =D15/D14 -> #DIV/0! | E24: =E15/E14 -> #DIV/0! | F24: =F15/F14 -> #DIV/0! | G24: =G15/G14 -> #DIV/0! | H24: 0.75 | I24: =$H$24 -> 0.75 | J24: 0.6 | K24: 0.55 | L24: 0.5
B25: CapEx % of revenue | C25: =C15/C9 -> #DIV/0! | D25: =D15/D9 -> #DIV/0! | E25: =E15/E9 -> #DIV/0! | F25: =F15/F9 -> #DIV/0! | G25: =G15/G9 -> #DIV/0! | H25: =AVERAGE(C25:G25) -> #DIV/0! | I25: =$H$25 -> #DIV/0! | J25: 0.011 | K25: 0.01 | L25: 0.008
B28: CapEx useful life
B29: Useful life CapEx | C29: 3
C31: New amortization schedule
B32: $ (thousand) | C32: =C8 -> 2021 | D32: =D8 -> 2022 | E32: =E8 -> 2023 | F32: =F8 -> 2024 | G32: =G8 -> 2025 | H32: =H8 -> 2026 | I32: =I8 -> 2027 | J32: =J8 -> 2028 | ... L32: =L8 -> 2030
B33: =H8 -> 2026 | H33: =IF(COUNT($H$33:H33) <= $C$29, $H$15/$C$29, 0) -> #DIV/0! | I33: =IF(COUNT($H$33:I33) <= $C$29, $H$15/$C$29, 0) -> #DIV/0! | J33: =IF(COUNT($H$33:J33) <= $C$29, $H$15/$C$29, 0) -> #DIV/0! | K33: =IF(COUNT($H$33:K33) <= $C$29, $H$15/$C$29, 0) -> #DIV/0! | L33: =IF(COUNT($H$33:L33) <= $C$29, $H$15/$C$29, 0) -> #DIV/0!
B34: =I8 -> 2027 | I34: =IF(COUNT($I$33:I33) <= $C$29, $I$15/$C$29, 0) -> #DIV/0! | J34: =IF(COUNT($I$33:J33) <= $C$29, $I$15/$C$29, 0) -> #DIV/0! | K34: =IF(COUNT($I$33:K33) <= $C$29, $I$15/$C$29, 0) -> #DIV/0! | L34: =IF(COUNT($I$33:L33) <= $C$29, $I$15/$C$29, 0) -> #DIV/0!
B35: =J8 -> 2028 | J35: =IF(COUNT($J$34:J34) <= $C$29, $J$15/$C$29, 0) -> #REF! | K35: =IF(COUNT($J$34:K34) <= $C$29, $J$15/$C$29, 0) -> #REF! | L35: =IF(COUNT($J$34:L34) <= $C$29, $J$15/$C$29, 0) -> #REF!
B36: =K8 -> 2029 | K36: =IF(COUNT($K$36:K36) <= $C$29, $K$15/$C$29, 0) -> #REF! | L36: =IF(COUNT($K$36:L36) <= $C$29, $K$15/$C$29, 0) -> #REF!
B37: =L8 -> 2030 | L37: =IF(COUNT($L$37:L37) <= $C$29, $L$15/$C$29, 0) -> #REF!
B38: Total | H38: =SUM(H33:H37) -> #DIV/0! | I38: =SUM(I33:I37) -> #DIV/0! | J38: =SUM(J33:J37) -> #DIV/0! | K38: =SUM(K33:K37) -> #DIV/0! | L38: =SUM(L33:L37) -> #DIV/0!
C41: Future amortization
B42: $ (thousand) | C42: =C8 -> 2021 | D42: =D8 -> 2022 | E42: =E8 -> 2023 | F42: =F8 -> 2024 | G42: =G8 -> 2025 | H42: =H8 -> 2026 | I42: =I8 -> 2027 | J42: =J8 -> 2028 | ... L42: =L8 -> 2030
B43: Amortization | H43: 12084 | I43: 8778 | J43: 4396 | K43: 1726 | L43: 1073

Sheet WC
B1: Working Capital
C3: History | H3: Forecast
C5: Revenues
B6: Revenues (thousand) | C6: ='Statement Y'!D3 -> 2021 | D6: ='Statement Y'!E3 -> 2022 | E6: ='Statement Y'!F3 -> 2023 | F6: ='Statement Y'!G3 -> 2024 | G6: ='Statement Y'!H3 -> 2025 | H6: =G6+1 -> 2026 | I6: =H6+1 -> 2027 | J6: =I6+1 -> 2028 | K6: =J6+1 -> 2029 | L6: =K6+1 -> 2030
B7: Revenue | C7: ='Statement Y'!D5 -> 0 | D7: ='Statement Y'!E5 -> 0 | E7: ='Statement Y'!F5 -> 0 | F7: ='Statement Y'!G5 -> 0 | G7: ='Statement Y'!H5 -> 0 | H7: =Revenue!H12 -> #REF! | I7: =Revenue!I12 -> #REF! | J7: =Revenue!J12 -> #REF! | K7: =Revenue!K12 -> #REF! | L7: =Revenue!L12 -> #REF!
B8: COGS | C8: ='Statement Y'!D6 -> 0 | D8: ='Statement Y'!E6 -> 0 | E8: ='Statement Y'!F6 -> 0 | F8: ='Statement Y'!G6 -> 0 | G8: ='Statement Y'!H6 -> 0 | H8: ='COGS & OpEx'!H11 -> #REF! | I8: ='COGS & OpEx'!I11 -> #REF! | J8: ='COGS & OpEx'!J11 -> #REF! | K8: ='COGS & OpEx'!K11 -> #REF! | L8: ='COGS & OpEx'!L11 -> #REF!
B9: OpEx | C9: ='COGS & OpEx'!C15 -> 0 | D9: ='COGS & OpEx'!D15 -> 0 | E9: ='COGS & OpEx'!E15 -> 0 | F9: ='COGS & OpEx'!F15 -> 0 | G9: ='COGS & OpEx'!G15 -> 0 | H9: ='COGS & OpEx'!H15 -> #REF! | I9: ='COGS & OpEx'!I15 -> #REF! | J9: ='COGS & OpEx'!J15 -> #REF! | ... L9: ='COGS & OpEx'!L15 -> #REF!
C12: Working Capital
B13: $ (thousand) | C13: =C6 -> 2021 | D13: =D6 -> 2022 | E13: =E6 -> 2023 | F13: =F6 -> 2024 | G13: =G6 -> 2025 | H13: =H6 -> 2026 | I13: =I6 -> 2027 | J13: =J6 -> 2028 | ... L13: =L6 -> 2030
B14: Accounts receivable | C14: ='Statement Y'!D27 -> 0 | D14: ='Statement Y'!E27 -> 0 | E14: ='Statement Y'!F27 -> 0 | F14: ='Statement Y'!G27 -> 0 | G14: ='Statement Y'!H27 -> 0 | H14: =H21*H7/365 -> #DIV/0! | I14: =I21*I7/365 -> #DIV/0! | J14: =J21*J7/365 -> #DIV/0! | K14: =K21*K7/365 -> #DIV/0! | L14: =L21*L7/365 -> #DIV/0!
B15: Accounts payable | C15: ='Statement Y'!D42 -> 0 | D15: ='Statement Y'!E42 -> 0 | E15: ='Statement Y'!F42 -> 0 | F15: ='Statement Y'!G42 -> 0 | G15: ='Statement Y'!H42 -> 0 | H15: =H22*H8/365 -> #DIV/0! | I15: =I22*I8/365 -> #DIV/0! | J15: =J22*J8/365 -> #DIV/0! | K15: =K22*K8/365 -> #DIV/0! | L15: =L22*L8/365 -> #DIV/0!
B16: Net trade cycle | C16: =C14-C15 -> 0 | D16: =D14-D15 -> 0 | E16: =E14-E15 -> 0 | F16: =F14-F15 -> 0 | G16: =G14-G15 -> 0 | H16: =H14-H15 -> #DIV/0! | I16: =I14-I15 -> #DIV/0! | J16: =J14-J15 -> #DIV/0! | ... L16: =L14-L15 -> #DIV/0!
C19: WC metrics and drivers
B20: Days | C20: =C6 -> 2021 | D20: =D6 -> 2022 | E20: =E6 -> 2023 | F20: =F6 -> 2024 | G20: =G6 -> 2025 | H20: =H6 -> 2026 | I20: =I6 -> 2027 | J20: =J6 -> 2028 | ... L20: =L6 -> 2030
B21: DSO | C21: =C14/C7*365 -> #DIV/0! | D21: =D14/D7*365 -> #DIV/0! | E21: =E14/E7*365 -> #DIV/0! | F21: =F14/F7*365 -> #DIV/0! | G21: =G14/G7*365 -> #DIV/0! | H21: =AVERAGE($C$21:$G$21) -> #DIV/0! | I21: =AVERAGE($C$21:$G$21) -> #DIV/0! | J21: =AVERAGE($C$21:$G$21) -> #DIV/0! | K21: =AVERAGE($C$21:$G$21) -> #DIV/0! | L21: =AVERAGE($C$21:$G$21) -> #DIV/0!
B22: DPO | C22: =C15/C8*365 -> #DIV/0! | D22: =D15/D8*365 -> #DIV/0! | E22: =E15/E8*365 -> #DIV/0! | F22: =F15/F8*365 -> #DIV/0! | G22: =G15/G8*365 -> #DIV/0! | H22: =AVERAGE($D$22:$G$22) -> #DIV/0! | I22: =AVERAGE($D$22:$G$22) -> #DIV/0! | J22: =AVERAGE($D$22:$G$22) -> #DIV/0! | K22: =AVERAGE($D$22:$G$22) -> #DIV/0! | L22: =AVERAGE($D$22:$G$22) -> #DIV/0!
B23: Net trade cycle | C23: =C21-C22 -> #DIV/0! | D23: =D21-D22 -> #DIV/0! | E23: =E21-E22 -> #DIV/0! | F23: =F21-F22 -> #DIV/0! | G23: =G21-G22 -> #DIV/0! | H23: =H21-H22 -> #DIV/0! | I23: =I21-I22 -> #DIV/0! | J23: =J21-J22 -> #DIV/0! | ... L23: =L21-L22 -> #DIV/0!
C26: Other WC items
B27: $ (thousand) | C27: =C6 -> 2021 | D27: =D6 -> 2022 | E27: =E6 -> 2023 | F27: =F6 -> 2024 | G27: =G6 -> 2025 | H27: =H6 -> 2026 | I27: =I6 -> 2027 | J27: =J6 -> 2028 | ... L27: =L6 -> 2030
B28: Deferred cost of revenues | C28: ='Statement Y'!D28 -> 0 | D28: ='Statement Y'!E28 -> 0 | E28: ='Statement Y'!F28 -> 0 | F28: ='Statement Y'!G28 -> 0 | G28: ='Statement Y'!H28 -> 0 | H28: =H8*H36 -> #REF! | I28: =I8*I36 -> #REF! | J28: =J8*J36 -> #REF! | K28: =K8*K36 -> #REF! | L28: =L8*L36 -> #REF!
B29: Prepaid expenses & Other current assets | C29: ='Statement Y'!D30 -> 0 | D29: ='Statement Y'!E30 -> 0 | E29: ='Statement Y'!F30 -> 0 | F29: ='Statement Y'!G30 -> 0 | G29: ='Statement Y'!H30 -> 0 | H29: =H9*H37 -> #REF! | I29: =I9*I37 -> #REF! | J29: =J9*J37 -> #REF! | K29: =K9*K37 -> #REF! | L29: =L9*L37 -> #REF!
B30: Deferred revenues | C30: ='Statement Y'!D43 -> 0 | D30: ='Statement Y'!E43 -> 0 | E30: ='Statement Y'!F43 -> 0 | F30: ='Statement Y'!G43 -> 0 | G30: ='Statement Y'!H43 -> 0 | H30: =H7*H38 -> #REF! | I30: =I7*I38 -> #REF! | J30: =J7*J38 -> #REF! | K30: =K7*K38 -> #REF! | L30: =L7*L38 -> #REF!
B31: Accrued expenses and other current liab | C31: ='Statement Y'!D45 -> 0 | D31: ='Statement Y'!E45 -> 0 | E31: ='Statement Y'!F45 -> 0 | F31: ='Statement Y'!G45 -> 0 | G31: ='Statement Y'!H45 -> 0 | H31: =H9*H39 -> #REF! | I31: =I9*I39 -> #REF! | J31: =J9*J39 -> #REF! | K31: =K9*K39 -> #REF! | L31: =L9*L39 -> #REF!
C34: Other WC metrics and drivers
B35: % | C35: =C6 -> 2021 | D35: =D6 -> 2022 | E35: =E6 -> 2023 | F35: =F6 -> 2024 | G35: =G6 -> 2025 | H35: =H6 -> 2026 | I35: =I6 -> 2027 | J35: =J6 -> 2028 | ... L35: =L6 -> 2030
B36: Deferred cost of revenues % COGS | C36: =C28/C8 -> #DIV/0! | D36: =D28/D8 -> #DIV/0! | E36: =E28/E8 -> #DIV/0! | F36: =F28/F8 -> #DIV/0! | G36: =G28/G8 -> #DIV/0! | H36: 0.36 | I36: 0.36 | J36: 0.36 | K36: 0.36 | L36: 0.36
B37: Prepaid exp & Other c assets % OpEx | C37: =C29/C9 -> #DIV/0! | D37: =D29/D9 -> #DIV/0! | E37: =E29/E9 -> #DIV/0! | F37: =F29/F9 -> #DIV/0! | G37: =G29/G9 -> #DIV/0! | H37: 0.03 | I37: 0.03 | J37: 0.03 | K37: 0.03 | L37: 0.03
B38: Deferred revenues % of Revenue | C38: =C30/C7 -> #DIV/0! | D38: =D30/D7 -> #DIV/0! | E38: =E30/E7 -> #DIV/0! | F38: =F30/F7 -> #DIV/0! | G38: =G30/G7 -> #DIV/0! | H38: 0.5 | I38: 0.5 | J38: 0.5 | K38: 0.5 | L38: 0.5
B39: Accrued exp & other c liab % OpEx | C39: =C31/C9 -> #DIV/0! | D39: =D31/D9 -> #DIV/0! | E39: =E31/E9 -> #DIV/0! | F39: =F31/F9 -> #DIV/0! | G39: =G31/G9 -> #DIV/0! | H39: 0.075 | I39: 0.075 | J39: 0.075 | K39: 0.075 | L39: 0.075

Sheet Other Assets & Liabilities
B1: Other Assets and Liabilities
C3: History | H3: Forecast
C5: Revenues
B6: Revenues (thousand) | C6: ='Statement Y'!D3 -> 2021 | D6: ='Statement Y'!E3 -> 2022 | E6: ='Statement Y'!F3 -> 2023 | F6: ='Statement Y'!G3 -> 2024 | G6: ='Statement Y'!H3 -> 2025 | H6: =G6+1 -> 2026 | I6: =H6+1 -> 2027 | J6: =I6+1 -> 2028 | K6: =J6+1 -> 2029 | L6: =K6+1 -> 2030
B7: Revenue | C7: ='Statement Y'!D5 -> 0 | D7: ='Statement Y'!E5 -> 0 | E7: ='Statement Y'!F5 -> 0 | F7: ='Statement Y'!G5 -> 0 | G7: ='Statement Y'!H5 -> 0 | H7: =Revenue!H12 -> #REF! | I7: =Revenue!I12 -> #REF! | J7: =Revenue!J12 -> #REF! | K7: =Revenue!K12 -> #REF! | L7: =Revenue!L12 -> #REF!
B8: COGS | C8: ='Statement Y'!D6 -> 0 | D8: ='Statement Y'!E6 -> 0 | E8: ='Statement Y'!F6 -> 0 | F8: ='Statement Y'!G6 -> 0 | G8: ='Statement Y'!H6 -> 0 | H8: ='COGS & OpEx'!H11 -> #REF! | I8: ='COGS & OpEx'!I11 -> #REF! | J8: ='COGS & OpEx'!J11 -> #REF! | K8: ='COGS & OpEx'!K11 -> #REF! | L8: ='COGS & OpEx'!L11 -> #REF!
B9: OpEx | C9: ='COGS & OpEx'!C15 -> 0 | D9: ='COGS & OpEx'!D15 -> 0 | E9: ='COGS & OpEx'!E15 -> 0 | F9: ='COGS & OpEx'!F15 -> 0 | G9: ='COGS & OpEx'!G15 -> 0 | H9: ='COGS & OpEx'!H15 -> #REF! | I9: ='COGS & OpEx'!I15 -> #REF! | J9: ='COGS & OpEx'!J15 -> #REF! | ... L9: ='COGS & OpEx'!L15 -> #REF!
B10: Income tax expense | C10: ='Statement Y'!D17 -> 0 | D10: ='Statement Y'!E17 -> 0 | E10: ='Statement Y'!F17 -> 0 | F10: ='Statement Y'!G17 -> 0 | G10: ='Statement Y'!H17 -> 0 | H10: ='P&L'!H16 -> #REF! | I10: ='P&L'!I16 -> #REF! | J10: ='P&L'!J16 -> #REF! | K10: ='P&L'!K16 -> #REF! | L10: ='P&L'!L16 -> #REF!
C13: Other Assets & Liabilities
B14: $ (thousand) | C14: =C6 -> 2021 | D14: =D6 -> 2022 | E14: =E6 -> 2023 | F14: =F6 -> 2024 | G14: =G6 -> 2025 | H14: =H6 -> 2026 | I14: =I6 -> 2027 | J14: =J6 -> 2028 | ... L14: =L6 -> 2030
B15: Operating lease right of use | C15: ='Statement Y'!D35 -> 0 | D15: ='Statement Y'!E35 -> 0 | E15: ='Statement Y'!F35 -> 0 | F15: ='Statement Y'!G35 -> 0 | G15: ='Statement Y'!H35 -> 0 | H15: =H9*H23 -> #REF! | I15: =I9*I23 -> #REF! | J15: =J9*J23 -> #REF! | K15: =K9*K23 -> #REF! | L15: =L9*L23 -> #REF!
B16: Other assets | C16: ='Statement Y'!D39 -> 0 | D16: ='Statement Y'!E39 -> 0 | E16: ='Statement Y'!F39 -> 0 | F16: ='Statement Y'!G39 -> 0 | G16: ='Statement Y'!H39 -> 0 | H16: =H7*H24 -> #REF! | I16: =I7*I24 -> #REF! | J16: =J7*J24 -> #REF! | K16: =K7*K24 -> #REF! | L16: =L7*L24 -> #REF!
B17: Income tax payable | C17: ='Statement Y'!D44 -> 0 | D17: ='Statement Y'!E44 -> 0 | E17: ='Statement Y'!F44 -> 0 | F17: ='Statement Y'!G44 -> 0 | G17: ='Statement Y'!H44 -> 0 | H17: =-(H10*H25) -> #REF! | I17: =-(I10*I25) -> #REF! | J17: =-(J10*J25) -> #REF! | K17: =-(K10*K25) -> #REF! | L17: =-(L10*L25) -> #REF!
B18: Operating lease obligation | C18: ='Statement Y'!D47 -> 0 | D18: ='Statement Y'!E47 -> 0 | E18: ='Statement Y'!F47 -> 0 | F18: ='Statement Y'!G47 -> 0 | G18: ='Statement Y'!H47 -> 0 | H18: =H9*H26 -> #REF! | I18: =I9*I26 -> #REF! | J18: =J9*J26 -> #REF! | K18: =K9*K26 -> #REF! | L18: =L9*L26 -> #REF!
C21: Other WC metrics and drivers
B22: % | C22: =C6 -> 2021 | D22: =D6 -> 2022 | E22: =E6 -> 2023 | F22: =F6 -> 2024 | G22: =G6 -> 2025 | H22: =H6 -> 2026 | I22: =I6 -> 2027 | J22: =J6 -> 2028 | ... L22: =L6 -> 2030
B23: Operating lease right of use % OpEx | C23: =C15/C9 -> #DIV/0! | D23: =D15/D9 -> #DIV/0! | E23: =E15/E9 -> #DIV/0! | F23: =F15/F9 -> #DIV/0! | G23: =G15/G9 -> #DIV/0! | H23: =AVERAGE(C23:G23) -> #DIV/0! | I23: =$H23 -> #DIV/0! | J23: =$H23 -> #DIV/0! | K23: =$H23 -> #DIV/0! | L23: =$H23 -> #DIV/0!
B24: Other assets % Revenue | C24: =C16/C7 -> #DIV/0! | D24: =D16/D7 -> #DIV/0! | E24: =E16/E7 -> #DIV/0! | F24: =F16/F7 -> #DIV/0! | G24: =G16/G7 -> #DIV/0! | H24: =AVERAGE(C24:G24) -> #DIV/0! | I24: =$H24 -> #DIV/0! | J24: =$H24 -> #DIV/0! | K24: =$H24 -> #DIV/0! | L24: =$H24 -> #DIV/0!
B25: Income tax payable % of Tax expense | C25: =-C17/C10 -> #DIV/0! | D25: =-D17/D10 -> #DIV/0! | E25: =-E17/E10 -> #DIV/0! | F25: =-F17/F10 -> #DIV/0! | G25: =-G17/G10 -> #DIV/0! | H25: 0.5 | I25: 0.5 | J25: 0.5 | K25: 0.5 | L25: 0.5
B26: Operating lease obligation % OpEx | C26: =C18/C9 -> #DIV/0! | D26: =D18/D9 -> #DIV/0! | E26: =E18/E9 -> #DIV/0! | F26: =F18/F9 -> #DIV/0! | G26: =G18/G9 -> #DIV/0! | H26: =H23 -> #DIV/0! | I26: =I23 -> #DIV/0! | J26: =J23 -> #DIV/0! | K26: =K23 -> #DIV/0! | L26: =L23 -> #DIV/0!

Sheet Financing
B1: Financing
C3: History | H3: Forecast
C5: Financing
B6: $ (thousand) | C6: ='Statement Y'!D3 -> 2021 | D6: ='Statement Y'!E3 -> 2022 | E6: ='Statement Y'!F3 -> 2023 | F6: ='Statement Y'!G3 -> 2024 | G6: ='Statement Y'!H3 -> 2025 | H6: =G6+1 -> 2026 | I6: =H6+1 -> 2027 | J6: =I6+1 -> 2028 | K6: =J6+1 -> 2029 | L6: =K6+1 -> 2030
B7: Interest expense | C7: 0 | D7: 0 | E7: 0 | F7: 0 | G7: 0 | H7: =H18 -> #REF! | I7: =I18 -> #REF! | J7: =J18 -> #REF! | K7: =K18 -> #REF! | L7: =L18 -> #REF! | M7: 0
B8: Interest income | C8: =C25 -> 0 | D8: =D25 -> 0 | E8: =E25 -> 0 | F8: =F25 -> 0 | G8: =G25 -> 0 | H8: =H25 -> 0 | I8: =I25 -> #REF! | J8: =J25 -> #REF! | ... L8: =L25 -> #REF!
C11: Financing
B12: $ (thousand) | C12: =C6 -> 2021 | D12: =D6 -> 2022 | E12: =E6 -> 2023 | F12: =F6 -> 2024 | G12: =G6 -> 2025 | H12: =H6 -> 2026 | I12: =I6 -> 2027 | J12: =J6 -> 2028 | ... L12: =L6 -> 2030
B13: UFCF | C13: ='Cash Flow'!C20 -> #DIV/0! | D13: ='Cash Flow'!D20 -> #DIV/0! | E13: ='Cash Flow'!E20 -> #DIV/0! | F13: ='Cash Flow'!F20 -> #DIV/0! | G13: ='Cash Flow'!G20 -> 0 | H13: ='Cash Flow'!H20 -> #REF! | I13: ='Cash Flow'!I20 -> #REF! | J13: ='Cash Flow'!J20 -> #REF! | ... L13: ='Cash Flow'!L20 -> #REF!
B14: Debt | C14: 0 | D14: 0 | E14: 0 | F14: 0 | G14: 0 | H14: =IF(H$13<0,H$13*$C30,0) -> #REF! | I14: =IF(I$13<0,I$13*$C30,0) -> #REF! | J14: =IF(J$13<0,J$13*$C30,0) -> #REF! | K14: =IF(K$13<0,K$13*$C30,0) -> #REF! | L14: =IF(L$13<0,L$13*$C30,0) -> #REF!
B15: Equity | C15: 0 | D15: 0 | E15: 0 | F15: 0 | G15: 0 | H15: =IF(H$13<0,H$13*$C31,0) -> #REF! | I15: =IF(I$13<0,I$13*$C31,0) -> #REF! | J15: =IF(J$13<0,J$13*$C31,0) -> #REF! | K15: =IF(K$13<0,K$13*$C31,0) -> #REF! | L15: =IF(L$13<0,L$13*$C31,0) -> #REF!
B16: Bond yield | H16: =C32 -> 0 | I16: =D32 -> 0 | J16: =E32 -> 0 | K16: =F32 -> 0 | L16: =G32 -> 0
B17: Outstanding debt | C17: 0 | D17: 0 | E17: 0 | F17: 0 | G17: 0 | H17: =G17+H14 -> #REF! | I17: =H17+I14 -> #REF! | J17: =I17+J14 -> #REF! | K17: =J17+K14 -> #REF! | L17: =K17+L14 -> #REF!
B18: Interest expense | H18: =H17*H16 -> #REF! | I18: =I17*I16 -> #REF! | J18: =J17*J16 -> #REF! | K18: =K17*K16 -> #REF! | L18: =L17*L16 -> #REF!
C21: Cash and interest income
B22: $ (thousand) | C22: =C6 -> 2021 | D22: =D6 -> 2022 | E22: =E6 -> 2023 | F22: =F6 -> 2024 | G22: =G6 -> 2025 | H22: =H6 -> 2026 | I22: =I6 -> 2027 | J22: =J6 -> 2028 | ... L22: =L6 -> 2030
B23: Biginning cash & equivalents | C23: ='Statement Y'!C25+'Statement Y'!C26+'Statement Y'!C36 -> 0 | D23: ='Statement Y'!D25+'Statement Y'!D26+'Statement Y'!D36 -> 0 | E23: ='Statement Y'!E25+'Statement Y'!E26+'Statement Y'!E36 -> 0 | F23: ='Statement Y'!F25+'Statement Y'!F26+'Statement Y'!F36 -> 0 | G23: ='Statement Y'!G25+'Statement Y'!G26+'Statement Y'!G36 -> 0 | H23: =G24 -> 0 | I23: =H24 -> #REF! | J23: =I24 -> #REF! | K23: =J24 -> #REF! | L23: =K24 -> #REF!
B24: Ending cash & equivalents | C24: ='Statement Y'!D25+'Statement Y'!D26+'Statement Y'!D36 -> 0 | D24: ='Statement Y'!E25+'Statement Y'!E26+'Statement Y'!E36 -> 0 | E24: ='Statement Y'!F25+'Statement Y'!F26+'Statement Y'!F36 -> 0 | F24: ='Statement Y'!G25+'Statement Y'!G26+'Statement Y'!G36 -> 0 | G24: ='Statement Y'!H25+'Statement Y'!H26+'Statement Y'!H36 -> 0 | H24: ='Balance Sheet'!H6+'Balance Sheet'!H7+'Balance Sheet'!H16 -> #REF! | I24: ='Balance Sheet'!I6+'Balance Sheet'!I7+'Balance Sheet'!I16 -> #REF! | J24: ='Balance Sheet'!J6+'Balance Sheet'!J7+'Balance Sheet'!J16 -> #REF! | K24: ='Balance Sheet'!K6+'Balance Sheet'!K7+'Balance Sheet'!K16 -> #REF! | L24: ='Balance Sheet'!L6+'Balance Sheet'!L7+'Balance Sheet'!L16 -> #REF!
B25: Interest income | C25: ='Statement Y'!D15 -> 0 | D25: ='Statement Y'!E15 -> 0 | E25: ='Statement Y'!F15 -> 0 | F25: ='Statement Y'!G15 -> 0 | G25: ='Statement Y'!H15 -> 0 | H25: =H23*H26 -> 0 | I25: =I23*I26 -> #REF! | J25: =J23*J26 -> #REF! | K25: =K23*K26 -> #REF! | L25: =L23*L26 -> #REF!
B26: Interest rate | C26: =C25/AVERAGE(C23:C24) -> #DIV/0! | D26: =D25/AVERAGE(D23:D24) -> #DIV/0! | E26: =E25/AVERAGE(E23:E24) -> #DIV/0! | F26: =F25/AVERAGE(F23:F24) -> #DIV/0! | G26: =G25/AVERAGE(G23:G24) -> #DIV/0! | H26: 0.04 | I26: 0.04 | J26: 0.04 | K26: 0.04 | L26: 0.04
B29: Financing parameters
B30: Debt to raise | C30: 0.5
B31: Equity to raise | C31: 0.5
B32: Bond yield | C32: 0
C35: Revenues
B36: Revenues (thousand) | C36: =C6 -> 2021 | D36: =D6 -> 2022 | E36: =E6 -> 2023 | F36: =F6 -> 2024 | G36: =G6 -> 2025 | H36: =H6 -> 2026 | I36: =I6 -> 2027 | J36: =J6 -> 2028 | ... L36: =L6 -> 2030
B37: Revenue | C37: ='Statement Y'!D5 -> 0 | D37: ='Statement Y'!E5 -> 0 | E37: ='Statement Y'!F5 -> 0 | F37: ='Statement Y'!G5 -> 0 | G37: ='Statement Y'!H5 -> 0 | H37: =Revenue!H12 -> #REF! | I37: =Revenue!I12 -> #REF! | J37: =Revenue!J12 -> #REF! | K37: =Revenue!K12 -> #REF! | L37: =Revenue!L12 -> #REF!
C39: Stock based compensation and stock options
C40: =C6 -> 2021 | D40: =D6 -> 2022 | E40: =E6 -> 2023 | F40: =F6 -> 2024 | G40: =G6 -> 2025 | H40: =H6 -> 2026 | I40: =I6 -> 2027 | J40: =J6 -> 2028 | ... L40: =L6 -> 2030
B41: Stock based compensation | C41: ='Statement Y'!D61 -> 0 | D41: ='Statement Y'!E61 -> 0 | E41: ='Statement Y'!F61 -> 0 | F41: ='Statement Y'!G61 -> 0 | G41: ='Statement Y'!H61 -> 0 | H41: =H37*H46 -> #REF! | I41: =I37*I46 -> #REF! | J41: =J37*J46 -> #REF! | K41: =K37*K46 -> #REF! | L41: =L37*L46 -> #REF!
B42: Proceeds stock options | C42: ='Statement Y'!D83 -> 0 | D42: ='Statement Y'!E83 -> 0 | E42: ='Statement Y'!F83 -> 0 | F42: ='Statement Y'!G83 -> 0 | G42: ='Statement Y'!H83 -> 0 | H42: =H37*H47 -> #REF! | I42: =I37*I47 -> #REF! | J42: =J37*J47 -> #REF! | K42: =K37*K47 -> #REF! | L42: =L37*L47 -> #REF!
C44: SBC and options drivers
B45: % | C45: =C6 -> 2021 | D45: =D6 -> 2022 | E45: =E6 -> 2023 | F45: =F6 -> 2024 | G45: =G6 -> 2025 | H45: =H6 -> 2026 | I45: =I6 -> 2027 | J45: =J6 -> 2028 | ... L45: =L6 -> 2030
B46: SBC % revenue | C46: =C41/C37 -> #DIV/0! | D46: =D41/D37 -> #DIV/0! | E46: =E41/E37 -> #DIV/0! | F46: =F41/F37 -> #DIV/0! | G46: =G41/G37 -> #DIV/0! | H46: 0.12 | I46: 0.11 | J46: 0.1 | K46: 0.1 | L46: 0.1
B47: Options % revenue | C47: =C42/C37 -> #DIV/0! | D47: =D42/D37 -> #DIV/0! | E47: =E42/E37 -> #DIV/0! | F47: =F42/F37 -> #DIV/0! | G47: =G42/G37 -> #DIV/0! | H47: 0.02 | I47: 0.02 | J47: 0.02 | K47: 0.015 | L47: 0.015

Sheet Output ->
B13: Output ->

Sheet P&L
B1: Profit & Loss
C2: History | H2: Forecast
C4: Income statement
B5: $ (thousand) | C5: ='Statement Y'!D3 -> 2021 | D5: ='Statement Y'!E3 -> 2022 | E5: ='Statement Y'!F3 -> 2023 | F5: ='Statement Y'!G3 -> 2024 | G5: ='Statement Y'!H3 -> 2025 | H5: =G5+1 -> 2026 | I5: =H5+1 -> 2027 | J5: =I5+1 -> 2028 | K5: =J5+1 -> 2029 | L5: =K5+1 -> 2030
B6: Revenue | C6: =Revenue!C12 -> 0 | D6: =Revenue!D12 -> 0 | E6: =Revenue!E12 -> 0 | F6: =Revenue!F12 -> 0 | G6: =Revenue!G12 -> 0 | H6: =Revenue!H12 -> #REF! | I6: =Revenue!I12 -> #REF! | J6: =Revenue!J12 -> #REF! | ... L6: =Revenue!L12 -> #REF! | N6: From Revenue Sheet
B7: COGS | C7: ='COGS & OpEx'!C11 -> 0 | D7: ='COGS & OpEx'!D11 -> 0 | E7: ='COGS & OpEx'!E11 -> 0 | F7: ='COGS & OpEx'!F11 -> 0 | G7: ='COGS & OpEx'!G11 -> 0 | H7: ='COGS & OpEx'!H11 -> #REF! | I7: ='COGS & OpEx'!I11 -> #REF! | J7: ='COGS & OpEx'!J11 -> #REF! | ... L7: ='COGS & OpEx'!L11 -> #REF! | N7: From COGS and OpEx Sheet
B8: Gross profit | C8: =C6-C7 -> 0 | D8: =D6-D7 -> 0 | E8: =E6-E7 -> 0 | F8: =F6-F7 -> 0 | G8: =G6-G7 -> 0 | H8: =H6-H7 -> #REF! | I8: =I6-I7 -> #REF! | J8: =J6-J7 -> #REF! | ... L8: =L6-L7 -> #REF!
B9: R&D | C9: ='COGS & OpEx'!C12 -> 0 | D9: ='COGS & OpEx'!D12 -> 0 | E9: ='COGS & OpEx'!E12 -> 0 | F9: ='COGS & OpEx'!F12 -> 0 | G9: ='COGS & OpEx'!G12 -> 0 | H9: ='COGS & OpEx'!H12 -> #REF! | I9: ='COGS & OpEx'!I12 -> #REF! | J9: ='COGS & OpEx'!J12 -> #REF! | ... L9: ='COGS & OpEx'!L12 -> #REF! | N9: From COGS and OpEx Sheet
B10: Sales & marketing | C10: ='COGS & OpEx'!C13 -> 0 | D10: ='COGS & OpEx'!D13 -> 0 | E10: ='COGS & OpEx'!E13 -> 0 | F10: ='COGS & OpEx'!F13 -> 0 | G10: ='COGS & OpEx'!G13 -> 0 | H10: ='COGS & OpEx'!H13 -> #REF! | I10: ='COGS & OpEx'!I13 -> #REF! | J10: ='COGS & OpEx'!J13 -> #REF! | ... L10: ='COGS & OpEx'!L13 -> #REF! | N10: From COGS and OpEx Sheet
B11: General & administrative | C11: ='COGS & OpEx'!C14 -> 0 | D11: ='COGS & OpEx'!D14 -> 0 | E11: ='COGS & OpEx'!E14 -> 0 | F11: ='COGS & OpEx'!F14 -> 0 | G11: ='COGS & OpEx'!G14 -> 0 | H11: ='COGS & OpEx'!H14 -> #REF! | I11: ='COGS & OpEx'!I14 -> #REF! | J11: ='COGS & OpEx'!J14 -> #REF! | ... L11: ='COGS & OpEx'!L14 -> #REF! | N11: From COGS and OpEx Sheet
B12: OpEx | C12: ='COGS & OpEx'!C15 -> 0 | D12: ='COGS & OpEx'!D15 -> 0 | E12: ='COGS & OpEx'!E15 -> 0 | F12: ='COGS & OpEx'!F15 -> 0 | G12: ='COGS & OpEx'!G15 -> 0 | H12: ='COGS & OpEx'!H15 -> #REF! | I12: ='COGS & OpEx'!I15 -> #REF! | J12: ='COGS & OpEx'!J15 -> #REF! | ... L12: ='COGS & OpEx'!L15 -> #REF! | N12: From COGS and OpEx Sheet
B13: EBIT | C13: =C8-C12 -> 0 | D13: =D8-D12 -> 0 | E13: =E8-E12 -> 0 | F13: =F8-F12 -> 0 | G13: =G8-G12 -> 0 | H13: =H8-H12 -> #REF! | I13: =I8-I12 -> #REF! | J13: =J8-J12 -> #REF! | ... L13: =L8-L12 -> #REF!
B14: Interest income/expense | C14: ='Statement Y'!D15 -> 0 | D14: ='Statement Y'!E15 -> 0 | E14: ='Statement Y'!F15 -> 0 | F14: ='Statement Y'!G15 -> 0 | G14: ='Statement Y'!H15 -> 0 | H14: =Financing!H8-Financing!H7 -> #REF! | I14: =Financing!I8-Financing!I7 -> #REF! | J14: =Financing!J8-Financing!J7 -> #REF! | K14: =Financing!K8-Financing!K7 -> #REF! | L14: =Financing!L8-Financing!L7 -> #REF! | N14: From Financing Sheet
B15: EBT | C15: =C13+C14 -> 0 | D15: =D13+D14 -> 0 | E15: =E13+E14 -> 0 | F15: =F13+F14 -> 0 | G15: =G13+G14 -> 0 | H15: =H13+H14 -> #REF! | I15: =I13+I14 -> #REF! | J15: =J13+J14 -> #REF! | ... L15: =L13+L14 -> #REF!
B16: Income tax expense/benefit | C16: ='Statement Y'!D17 -> 0 | D16: ='Statement Y'!E17 -> 0 | E16: ='Statement Y'!F17 -> 0 | F16: ='Statement Y'!G17 -> 0 | G16: ='Statement Y'!H17 -> 0 | H16: =-H15*H22 -> #REF! | I16: =-I15*I22 -> #REF! | J16: =-J15*J22 -> #REF! | K16: =-K15*K22 -> #REF! | L16: =-L15*L22 -> #REF!
B17: Net income | C17: =C15+C16 -> 0 | D17: =D15+D16 -> 0 | E17: =E15+E16 -> 0 | F17: =F15+F16 -> 0 | G17: =G15+G16 -> 0 | H17: =H15+H16 -> #REF! | I17: =I15+I16 -> #REF! | J17: =J15+J16 -> #REF! | ... L17: =L15+L16 -> #REF!
C20: Drivers
C21: =C5 -> 2021 | D21: =D5 -> 2022 | E21: =E5 -> 2023 | F21: =F5 -> 2024 | G21: =G5 -> 2025 | H21: =H5 -> 2026 | I21: =I5 -> 2027 | J21: =J5 -> 2028 | ... L21: =L5 -> 2030
B22: Tax rate | C22: ='Statement Y'!D117 -> #DIV/0! | D22: ='Statement Y'!E117 -> #DIV/0! | E22: ='Statement Y'!F117 -> #DIV/0! | F22: ='Statement Y'!G117 -> #DIV/0! | G22: ='Statement Y'!H117 -> #DIV/0! | H22: 0.21 | I22: 0.22 | J22: 0.23 | K22: 0.22 | L22: 0.21

Sheet Balance Sheet
B1: Balance Sheet
C2: History | H2: Forecast
C4: Balance Sheet
B5: $ (thousand) | C5: ='Statement Y'!D3 -> 2021 | D5: ='Statement Y'!E3 -> 2022 | E5: ='Statement Y'!F3 -> 2023 | F5: ='Statement Y'!G3 -> 2024 | G5: ='Statement Y'!H3 -> 2025 | H5: =G5+1 -> 2026 | I5: =H5+1 -> 2027 | J5: =I5+1 -> 2028 | K5: =J5+1 -> 2029 | L5: =K5+1 -> 2030
B6: Cash and cash equivalents | C6: ='Statement Y'!D25 -> 0 | D6: ='Statement Y'!E25 -> 0 | E6: ='Statement Y'!F25 -> 0 | F6: ='Statement Y'!G25 -> 0 | G6: ='Statement Y'!H25 -> 0 | H6: =G6+'Cash Flow'!H26 -> #REF! | I6: =H6+'Cash Flow'!I26 -> #REF! | J6: =I6+'Cash Flow'!J26 -> #REF! | K6: =J6+'Cash Flow'!K26 -> #REF! | L6: =K6+'Cash Flow'!L26 -> #REF! | N6: From cashflow statement
B7: Short-term investments | C7: ='Statement Y'!D26 -> 0 | D7: ='Statement Y'!E26 -> 0 | E7: ='Statement Y'!F26 -> 0 | F7: ='Statement Y'!G26 -> 0 | G7: ='Statement Y'!H26 -> 0 | H7: =$G$7 -> 0 | I7: =$G$7 -> 0 | J7: =$G$7 -> 0 | K7: =$G$7 -> 0 | L7: =$G$7 -> 0 | N7: Flat
B8: Acc receivable | C8: ='Statement Y'!D27 -> 0 | D8: ='Statement Y'!E27 -> 0 | E8: ='Statement Y'!F27 -> 0 | F8: ='Statement Y'!G27 -> 0 | G8: ='Statement Y'!H27 -> 0 | H8: =WC!H14 -> #DIV/0! | I8: =WC!I14 -> #DIV/0! | J8: =WC!J14 -> #DIV/0! | K8: =WC!K14 -> #DIV/0! | L8: =WC!L14 -> #DIV/0! | N8: From WC Sheet
B9: Deferred cost of revenues | C9: ='Statement Y'!D28 -> 0 | D9: ='Statement Y'!E28 -> 0 | E9: ='Statement Y'!F28 -> 0 | F9: ='Statement Y'!G28 -> 0 | G9: ='Statement Y'!H28 -> 0 | H9: =WC!H28 -> #REF! | I9: =WC!I28 -> #REF! | J9: =WC!J28 -> #REF! | K9: =WC!K28 -> #REF! | L9: =WC!L28 -> #REF! | N9: From WC Sheet
B10: Prepaid expenses & Other current assets | C10: ='Statement Y'!D30 -> 0 | D10: ='Statement Y'!E30 -> 0 | E10: ='Statement Y'!F30 -> 0 | F10: ='Statement Y'!G30 -> 0 | G10: ='Statement Y'!H30 -> 0 | H10: =WC!H29 -> #REF! | I10: =WC!I29 -> #REF! | J10: =WC!J29 -> #REF! | K10: =WC!K29 -> #REF! | L10: =WC!L29 -> #REF! | N10: From WC Sheet
B11: Current assets | C11: =SUM(C6:C10) -> 0 | D11: =SUM(D6:D10) -> 0 | E11: =SUM(E6:E10) -> 0 | F11: =SUM(F6:F10) -> 0 | G11: =SUM(G6:G10) -> 0 | H11: =SUM(H6:H10) -> #REF! | I11: =SUM(I6:I10) -> #REF! | J11: =SUM(J6:J10) -> #REF! | ... L11: =SUM(L6:L10) -> #REF!
B12: PP&E | C12: ='Statement Y'!D32 -> 0 | D12: ='Statement Y'!E32 -> 0 | E12: ='Statement Y'!F32 -> 0 | F12: ='Statement Y'!G32 -> 0 | G12: ='Statement Y'!H32 -> 0 | H12: ='PP&E'!H17 -> #DIV/0! | I12: ='PP&E'!I17 -> #DIV/0! | J12: ='PP&E'!J17 -> #DIV/0! | K12: ='PP&E'!K17 -> #DIV/0! | L12: ='PP&E'!L17 -> #DIV/0! | N12: From PP&E Sheet
B13: Goodwill | C13: ='Statement Y'!D33 -> 0 | D13: ='Statement Y'!E33 -> 0 | E13: ='Statement Y'!F33 -> 0 | F13: ='Statement Y'!G33 -> 0 | G13: ='Statement Y'!H33 -> 0 | H13: =$G$13 -> 0 | I13: =$G$13 -> 0 | J13: =$G$13 -> 0 | K13: =$G$13 -> 0 | L13: =$G$13 -> 0 | N13: Flat
B14: Intangible assets | C14: ='Statement Y'!D34 -> 0 | D14: ='Statement Y'!E34 -> 0 | E14: ='Statement Y'!F34 -> 0 | F14: ='Statement Y'!G34 -> 0 | G14: ='Statement Y'!H34 -> 0 | H14: =Intangibles!H17 -> #DIV/0! | I14: =Intangibles!I17 -> #DIV/0! | J14: =Intangibles!J17 -> #DIV/0! | K14: =Intangibles!K17 -> #DIV/0! | L14: =Intangibles!L17 -> #DIV/0! | N14: From Intangibles Sheet
B15: Operating lease right of use | C15: ='Statement Y'!D35 -> 0 | D15: ='Statement Y'!E35 -> 0 | E15: ='Statement Y'!F35 -> 0 | F15: ='Statement Y'!G35 -> 0 | G15: ='Statement Y'!H35 -> 0 | H15: ='Other Assets & Liabilities'!H15 -> #REF! | I15: ='Other Assets & Liabilities'!I15 -> #REF! | J15: ='Other Assets & Liabilities'!J15 -> #REF! | K15: ='Other Assets & Liabilities'!K15 -> #REF! | L15: ='Other Assets & Liabilities'!L15 -> #REF! | N15: From other assets and liabilities Sheet
B16: Long term investments | C16: ='Statement Y'!D36 -> 0 | D16: ='Statement Y'!E36 -> 0 | E16: ='Statement Y'!F36 -> 0 | F16: ='Statement Y'!G36 -> 0 | G16: ='Statement Y'!H36 -> 0 | H16: =$G$16 -> 0 | I16: =$G$16 -> 0 | J16: =$G$16 -> 0 | K16: =$G$16 -> 0 | L16: =$G$16 -> 0 | N16: Flat
B17: Deferred tax assets | C17: ='Statement Y'!D37 -> 0 | D17: ='Statement Y'!E37 -> 0 | E17: ='Statement Y'!F37 -> 0 | F17: ='Statement Y'!G37 -> 0 | G17: ='Statement Y'!H37 -> 0 | H17: =$G$17 -> 0 | I17: =$G$17 -> 0 | J17: =$G$17 -> 0 | K17: =$G$17 -> 0 | L17: =$G$17 -> 0 | N17: Flat
B18: Restricted cash | C18: ='Statement Y'!D38 -> 0 | D18: ='Statement Y'!E38 -> 0 | E18: ='Statement Y'!F38 -> 0 | F18: ='Statement Y'!G38 -> 0 | G18: ='Statement Y'!H38 -> 0 | H18: =$G$18 -> 0 | I18: =$G$18 -> 0 | J18: =$G$18 -> 0 | K18: =$G$18 -> 0 | L18: =$G$18 -> 0 | N18: Flat
B19: Other assets | C19: ='Statement Y'!D39 -> 0 | D19: ='Statement Y'!E39 -> 0 | E19: ='Statement Y'!F39 -> 0 | F19: ='Statement Y'!G39 -> 0 | G19: ='Statement Y'!H39 -> 0 | H19: ='Other Assets & Liabilities'!H16 -> #REF! | I19: ='Other Assets & Liabilities'!I16 -> #REF! | J19: ='Other Assets & Liabilities'!J16 -> #REF! | K19: ='Other Assets & Liabilities'!K16 -> #REF! | L19: ='Other Assets & Liabilities'!L16 -> #REF! | N19: From other assets and liabilities Sheet
B20: Long Term Assets | C20: =SUM(C12:C19) -> 0 | D20: =SUM(D12:D19) -> 0 | E20: =SUM(E12:E19) -> 0 | F20: =SUM(F12:F19) -> 0 | G20: =SUM(G12:G19) -> 0 | H20: =SUM(H12:H19) -> #DIV/0! | I20: =SUM(I12:I19) -> #DIV/0! | J20: =SUM(J12:J19) -> #DIV/0! | ... L20: =SUM(L12:L19) -> #DIV/0!
B21: Total Assets | C21: =C11+C20 -> 0 | D21: =D11+D20 -> 0 | E21: =E11+E20 -> 0 | F21: =F11+F20 -> 0 | G21: =G11+G20 -> 0 | H21: =H11+H20 -> #REF! | I21: =I11+I20 -> #REF! | J21: =J11+J20 -> #REF! | ... L21: =L11+L20 -> #REF!
B22: Acc payable | C22: ='Statement Y'!D42 -> 0 | D22: ='Statement Y'!E42 -> 0 | E22: ='Statement Y'!F42 -> 0 | F22: ='Statement Y'!G42 -> 0 | G22: ='Statement Y'!H42 -> 0 | H22: =WC!H15 -> #DIV/0! | I22: =WC!I15 -> #DIV/0! | J22: =WC!J15 -> #DIV/0! | K22: =WC!K15 -> #DIV/0! | L22: =WC!L15 -> #DIV/0! | N22: From WC Sheet
B23: Deferred revenues | C23: ='Statement Y'!D43 -> 0 | D23: ='Statement Y'!E43 -> 0 | E23: ='Statement Y'!F43 -> 0 | F23: ='Statement Y'!G43 -> 0 | G23: ='Statement Y'!H43 -> 0 | H23: =WC!H30 -> #REF! | I23: =WC!I30 -> #REF! | J23: =WC!J30 -> #REF! | K23: =WC!K30 -> #REF! | L23: =WC!L30 -> #REF! | N23: From WC Sheet
B24: Income tax payable | C24: ='Statement Y'!D44 -> 0 | D24: ='Statement Y'!E44 -> 0 | E24: ='Statement Y'!F44 -> 0 | F24: ='Statement Y'!G44 -> 0 | G24: ='Statement Y'!H44 -> 0 | H24: ='Other Assets & Liabilities'!H17 -> #REF! | I24: ='Other Assets & Liabilities'!I17 -> #REF! | J24: ='Other Assets & Liabilities'!J17 -> #REF! | K24: ='Other Assets & Liabilities'!K17 -> #REF! | L24: ='Other Assets & Liabilities'!L17 -> #REF! | N24: From other assets and liabilities Sheet
B25: Accrued expenses and other current | C25: ='Statement Y'!D45 -> 0 | D25: ='Statement Y'!E45 -> 0 | E25: ='Statement Y'!F45 -> 0 | F25: ='Statement Y'!G45 -> 0 | G25: ='Statement Y'!H45 -> 0 | H25: =WC!H31 -> #REF! | I25: =WC!I31 -> #REF! | J25: =WC!J31 -> #REF! | K25: =WC!K31 -> #REF! | L25: =WC!L31 -> #REF! | N25: From WC Sheet
B26: Current liabilities | C26: =SUM(C22:C25) -> 0 | D26: =SUM(D22:D25) -> 0 | E26: =SUM(E22:E25) -> 0 | F26: =SUM(F22:F25) -> 0 | G26: =SUM(G22:G25) -> 0 | H26: =SUM(H22:H25) -> #DIV/0! | I26: =SUM(I22:I25) -> #DIV/0! | J26: =SUM(J22:J25) -> #DIV/0! | ... L26: =SUM(L22:L25) -> #DIV/0!
B27: Long term obligation operating lease | C27: ='Statement Y'!D47 -> 0 | D27: ='Statement Y'!E47 -> 0 | E27: ='Statement Y'!F47 -> 0 | F27: ='Statement Y'!G47 -> 0 | G27: ='Statement Y'!H47 -> 0 | H27: ='Other Assets & Liabilities'!H18 -> #REF! | I27: ='Other Assets & Liabilities'!I18 -> #REF! | J27: ='Other Assets & Liabilities'!J18 -> #REF! | K27: ='Other Assets & Liabilities'!K18 -> #REF! | L27: ='Other Assets & Liabilities'!L18 -> #REF! | N27: From other assets and liabilities Sheet
B28: Deferred tax liabilities | C28: ='Statement Y'!D48 -> 0 | D28: ='Statement Y'!E48 -> 0 | E28: ='Statement Y'!F48 -> 0 | F28: ='Statement Y'!G48 -> 0 | G28: ='Statement Y'!H48 -> 0 | H28: =$G28 -> 0 | I28: =$G28 -> 0 | J28: =$G28 -> 0 | K28: =$G28 -> 0 | L28: =$G28 -> 0 | N28: Flat
B29: Long term liabilities | C29: =SUM(C27:C28) -> 0 | D29: =SUM(D27:D28) -> 0 | E29: =SUM(E27:E28) -> 0 | F29: =SUM(F27:F28) -> 0 | G29: =SUM(G27:G28) -> 0 | H29: =SUM(H27:H28) -> #REF! | I29: =SUM(I27:I28) -> #REF! | J29: =SUM(J27:J28) -> #REF! | ... L29: =SUM(L27:L28) -> #REF!
B30: Total Liabilities | C30: =C26+C29 -> 0 | D30: =D26+D29 -> 0 | E30: =E26+E29 -> 0 | F30: =F26+F29 -> 0 | G30: =G26+G29 -> 0 | H30: =H26+H29 -> #DIV/0! | I30: =I26+I29 -> #DIV/0! | J30: =J26+J29 -> #DIV/0! | ... L30: =L26+L29 -> #DIV/0!
B31: Common stock par value | C31: ='Statement Y'!D51 -> 0 | D31: ='Statement Y'!E51 -> 0 | E31: ='Statement Y'!F51 -> 0 | F31: ='Statement Y'!G51 -> 0 | G31: ='Statement Y'!H51 -> 0 | H31: =$G31 -> 0 | I31: =$G31 -> 0 | J31: =$G31 -> 0 | K31: =$G31 -> 0 | L31: =$G31 -> 0 | N31: Flat
B32: Additional paid-in capital | C32: ='Statement Y'!D52 -> 0 | D32: ='Statement Y'!E52 -> 0 | E32: ='Statement Y'!F52 -> 0 | F32: ='Statement Y'!G52 -> 0 | G32: ='Statement Y'!H52 -> 0 | H32: =G32+Financing!H41+Financing!H42 -> #REF! | I32: =H32+Financing!I41+Financing!I42 -> #REF! | J32: =I32+Financing!J41+Financing!J42 -> #REF! | K32: =J32+Financing!K41+Financing!K42 -> #REF! | L32: =K32+Financing!L41+Financing!L42 -> #REF! | N32: From Financing Sheet
B33: Retained earnings | C33: ='Statement Y'!D53 -> 0 | D33: ='Statement Y'!E53 -> 0 | E33: ='Statement Y'!F53 -> 0 | F33: ='Statement Y'!G53 -> 0 | G33: ='Statement Y'!H53 -> 0 | H33: =G33+'P&L'!H17 -> #REF! | I33: =H33+'P&L'!I17 -> #REF! | J33: =I33+'P&L'!J17 -> #REF! | K33: =J33+'P&L'!K17 -> #REF! | L33: =K33+'P&L'!L17 -> #REF! | N33: From P&L Sheet
B34: Stockholder equity | C34: =SUM(C31:C33) -> 0 | D34: =SUM(D31:D33) -> 0 | E34: =SUM(E31:E33) -> 0 | F34: =SUM(F31:F33) -> 0 | G34: =SUM(G31:G33) -> 0 | H34: =SUM(H31:H33) -> #REF! | I34: =SUM(I31:I33) -> #REF! | J34: =SUM(J31:J33) -> #REF! | ... L34: =SUM(L31:L33) -> #REF!
B35: Total liabilities and equity | C35: =C30+C34 -> 0 | D35: =D30+D34 -> 0 | E35: =E30+E34 -> 0 | F35: =F30+F34 -> 0 | G35: =G30+G34 -> 0 | H35: =H30+H34 -> #DIV/0! | I35: =I30+I34 -> #DIV/0! | J35: =J30+J34 -> #DIV/0! | ... L35: =L30+L34 -> #DIV/0!
B37: Check balance | C37: =C21-C35 -> 0 | D37: =D21-D35 -> 0 | E37: =E21-E35 -> 0 | F37: =F21-F35 -> 0 | G37: =G21-G35 -> 0 | H37: =H21-H35 -> #REF! | I37: =I21-I35 -> #REF! | J37: =J21-J35 -> #REF! | ... L37: =L21-L35 -> #REF!

Sheet Cash Flow
B1: Cash Flow
C2: History | H2: Forecast
C4: Cash Flow
B5: $ (thousand) | C5: ='Statement Y'!D3 -> 2021 | D5: ='Statement Y'!E3 -> 2022 | E5: ='Statement Y'!F3 -> 2023 | F5: ='Statement Y'!G3 -> 2024 | G5: ='Statement Y'!H3 -> 2025 | H5: =G5+1 -> 2026 | I5: =H5+1 -> 2027 | J5: =I5+1 -> 2028 | K5: =J5+1 -> 2029 | L5: =K5+1 -> 2030
B6: EBIT | C6: ='P&L'!C13 -> 0 | D6: ='P&L'!D13 -> 0 | E6: ='P&L'!E13 -> 0 | F6: ='P&L'!F13 -> 0 | G6: ='P&L'!G13 -> 0 | H6: ='P&L'!H13 -> #REF! | I6: ='P&L'!I13 -> #REF! | J6: ='P&L'!J13 -> #REF! | ... L6: ='P&L'!L13 -> #REF! | N6: From P&L Sheet
B7: NOPAT | C7: =C6*(1-C31) -> #DIV/0! | D7: =D6*(1-D31) -> #DIV/0! | E7: =E6*(1-E31) -> #DIV/0! | F7: =F6*(1-F31) -> #DIV/0! | G7: =G6*(1-G31) -> 0 | H7: =H6*(1-H31) -> #REF! | I7: =I6*(1-I31) -> #REF! | J7: =J6*(1-J31) -> #REF! | ... L7: =L6*(1-L31) -> #REF!
B8: (+) D&A | C8: =C32+C33 -> 0 | D8: =D32+D33 -> 0 | E8: =E32+E33 -> 0 | F8: =F32+F33 -> 0 | G8: =G32+G33 -> 0 | H8: =H32+H33 -> #DIV/0! | I8: =I32+I33 -> #DIV/0! | J8: =J32+J33 -> #DIV/0! | ... L8: =L32+L33 -> #DIV/0!
B9: Gross Cash Flow | C9: =C7+C8 -> #DIV/0! | D9: =D7+D8 -> #DIV/0! | E9: =E7+E8 -> #DIV/0! | F9: =F7+F8 -> #DIV/0! | G9: =G7+G8 -> 0 | H9: =H7+H8 -> #REF! | I9: =I7+I8 -> #REF! | J9: =J7+J8 -> #REF! | ... L9: =L7+L8 -> #REF!
B10: Change Acc receivable | C10: ='Statement Y'!D67 -> 0 | D10: ='Statement Y'!E67 -> 0 | E10: ='Statement Y'!F67 -> 0 | F10: ='Statement Y'!G67 -> 0 | G10: ='Statement Y'!H67 -> 0 | H10: =-('Balance Sheet'!H8-'Balance Sheet'!G8) -> #DIV/0! | I10: =-('Balance Sheet'!I8-'Balance Sheet'!H8) -> #DIV/0! | J10: =-('Balance Sheet'!J8-'Balance Sheet'!I8) -> #DIV/0! | K10: =-('Balance Sheet'!K8-'Balance Sheet'!J8) -> #DIV/0! | L10: =-('Balance Sheet'!L8-'Balance Sheet'!K8) -> #DIV/0!
B11: Change Cost of revenue | C11: ='Statement Y'!D68 -> 0 | D11: ='Statement Y'!E68 -> 0 | E11: ='Statement Y'!F68 -> 0 | F11: ='Statement Y'!G68 -> 0 | G11: ='Statement Y'!H68 -> 0 | H11: =-(WC!H28-WC!G28) -> #REF! | I11: =-(WC!I28-WC!H28) -> #REF! | J11: =-(WC!J28-WC!I28) -> #REF! | K11: =-(WC!K28-WC!J28) -> #REF! | L11: =-(WC!L28-WC!K28) -> #REF!
B12: Change Prepaid expenses | C12: ='Statement Y'!D69 -> 0 | D12: ='Statement Y'!E69 -> 0 | E12: ='Statement Y'!F69 -> 0 | F12: ='Statement Y'!G69 -> 0 | G12: ='Statement Y'!H69 -> 0 | H12: =-(WC!H29-WC!G29) -> #REF! | I12: =-(WC!I29-WC!H29) -> #REF! | J12: =-(WC!J29-WC!I29) -> #REF! | K12: =-(WC!K29-WC!J29) -> #REF! | L12: =-(WC!L29-WC!K29) -> #REF!
B13: Change Acc payable | C13: ='Statement Y'!D70 -> 0 | D13: ='Statement Y'!E70 -> 0 | E13: ='Statement Y'!F70 -> 0 | F13: ='Statement Y'!G70 -> 0 | G13: ='Statement Y'!H70 -> 0 | H13: =WC!H15-WC!G15 -> #DIV/0! | I13: =WC!I15-WC!H15 -> #DIV/0! | J13: =WC!J15-WC!I15 -> #DIV/0! | K13: =WC!K15-WC!J15 -> #DIV/0! | L13: =WC!L15-WC!K15 -> #DIV/0!
B14: Change deferred revenues | C14: ='Statement Y'!D66 -> 0 | D14: ='Statement Y'!E66 -> 0 | E14: ='Statement Y'!F66 -> 0 | F14: ='Statement Y'!G66 -> 0 | G14: ='Statement Y'!H66 -> 0 | H14: ='Balance Sheet'!H23-'Balance Sheet'!G23 -> #REF! | I14: ='Balance Sheet'!I23-'Balance Sheet'!H23 -> #REF! | J14: ='Balance Sheet'!J23-'Balance Sheet'!I23 -> #REF! | K14: ='Balance Sheet'!K23-'Balance Sheet'!J23 -> #REF! | L14: ='Balance Sheet'!L23-'Balance Sheet'!K23 -> #REF!
B15: Change accrued expenses | C15: ='Statement Y'!D71 -> 0 | D15: ='Statement Y'!E71 -> 0 | E15: ='Statement Y'!F71 -> 0 | F15: ='Statement Y'!G71 -> 0 | G15: ='Statement Y'!H71 -> 0 | H15: ='Balance Sheet'!H25-'Balance Sheet'!G25 -> #REF! | I15: ='Balance Sheet'!I25-'Balance Sheet'!H25 -> #REF! | J15: ='Balance Sheet'!J25-'Balance Sheet'!I25 -> #REF! | K15: ='Balance Sheet'!K25-'Balance Sheet'!J25 -> #REF! | L15: ='Balance Sheet'!L25-'Balance Sheet'!K25 -> #REF!
B16: (+) Investments Working Capital | C16: =SUM(C10:C14) -> 0 | D16: =SUM(D10:D14) -> 0 | E16: =SUM(E10:E14) -> 0 | F16: =SUM(F10:F14) -> 0 | G16: =SUM(G10:G14) -> 0 | H16: =SUM(H10:H14) -> #DIV/0! | I16: =SUM(I10:I14) -> #DIV/0! | J16: =SUM(J10:J14) -> #DIV/0! | ... L16: =SUM(L10:L14) -> #DIV/0!
B17: (-) Total CapEx | C17: =C34+C35 -> 0 | D17: =D34+D35 -> 0 | E17: =E34+E35 -> 0 | F17: =F34+F35 -> 0 | G17: =G34+G35 -> 0 | H17: =H34+H35 -> #DIV/0! | I17: =I34+I35 -> #DIV/0! | J17: =J34+J35 -> #DIV/0! | ... L17: =L34+L35 -> #DIV/0!
B18: (+) Other Assets | C18: ='Statement Y'!D72 -> 0 | D18: ='Statement Y'!E72 -> 0 | E18: ='Statement Y'!F72 -> 0 | F18: ='Statement Y'!G72 -> 0 | G18: ='Statement Y'!H72 -> 0 | H18: =-('Balance Sheet'!H15-'Balance Sheet'!G15)-('Balance Sheet'!H17-'Balance Sheet'!G17)-('Balance Sheet'!H19-'Balance Sheet'!G19) -> #REF! | I18: =-('Balance Sheet'!I15-'Balance Sheet'!H15)-('Balance Sheet'!I17-'Balance Sheet'!H17)-('Balance Sheet'!I19-'Balance Sheet'!H19) -> #REF! | J18: =-('Balance Sheet'!J15-'Balance Sheet'!I15)-('Balance Sheet'!J17-'Balance Sheet'!I17)-('Balance Sheet'!J19-'Balance Sheet'!I19) -> #REF! | K18: =-('Balance Sheet'!K15-'Balance Sheet'!J15)-('Balance Sheet'!K17-'Balance Sheet'!J17)-('Balance Sheet'!K19-'Balance Sheet'!J19) -> #REF! | L18: =-('Balance Sheet'!L15-'Balance Sheet'!K15)-('Balance Sheet'!L17-'Balance Sheet'!K17)-('Balance Sheet'!L19-'Balance Sheet'!K19) -> #REF!
B19: (+) Other Liabilities | H19: =('Balance Sheet'!H24-'Balance Sheet'!G24)+('Balance Sheet'!H27-'Balance Sheet'!G27)+('Balance Sheet'!H28-'Balance Sheet'!G28) -> #REF! | I19: =('Balance Sheet'!I24-'Balance Sheet'!H24)+('Balance Sheet'!I27-'Balance Sheet'!H27)+('Balance Sheet'!I28-'Balance Sheet'!H28) -> #REF! | J19: =('Balance Sheet'!J24-'Balance Sheet'!I24)+('Balance Sheet'!J27-'Balance Sheet'!I27)+('Balance Sheet'!J28-'Balance Sheet'!I28) -> #REF! | K19: =('Balance Sheet'!K24-'Balance Sheet'!J24)+('Balance Sheet'!K27-'Balance Sheet'!J27)+('Balance Sheet'!K28-'Balance Sheet'!J28) -> #REF! | L19: =('Balance Sheet'!L24-'Balance Sheet'!K24)+('Balance Sheet'!L27-'Balance Sheet'!K27)+('Balance Sheet'!L28-'Balance Sheet'!K28) -> #REF!
B20: UFCF | C20: =C9+C16-C17+C18+C19 -> #DIV/0! | D20: =D9+D16-D17+D18+D19 -> #DIV/0! | E20: =E9+E16-E17+E18+E19 -> #DIV/0! | F20: =F9+F16-F17+F18+F19 -> #DIV/0! | G20: =G9+G16-G17+G18+G19 -> 0 | H20: =H9+H16-H17+H18+H19 -> #REF! | I20: =I9+I16-I17+I18+I19 -> #REF! | J20: =J9+J16-J17+J18+J19 -> #REF! | ... L20: =L9+L16-L17+L18+L19 -> #REF!
B21: (+) Net Interest income | C21: ='P&L'!C14 -> 0 | D21: ='P&L'!D14 -> 0 | E21: ='P&L'!E14 -> 0 | F21: ='P&L'!F14 -> 0 | G21: ='P&L'!G14 -> 0 | H21: ='P&L'!H14 -> #REF! | I21: ='P&L'!I14 -> #REF! | J21: ='P&L'!J14 -> #REF! | ... L21: ='P&L'!L14 -> #REF!
B22: (+) Change in financial liabilities | C22: 0 | D22: 0 | E22: 0 | F22: 0 | G22: 0 | H22: =Financing!H14-Financing!G14 -> #REF! | I22: =Financing!I14-Financing!H14 -> #REF! | J22: =Financing!J14-Financing!I14 -> #REF! | K22: =Financing!K14-Financing!J14 -> #REF! | L22: =Financing!L14-Financing!K14 -> #REF!
B23: (+) Tax adjustment | C23: ='P&L'!C16+(C6-C7) -> #DIV/0! | D23: ='P&L'!D16+(D6-D7) -> #DIV/0! | E23: ='P&L'!E16+(E6-E7) -> #DIV/0! | F23: ='P&L'!F16+(F6-F7) -> #DIV/0! | G23: ='P&L'!G16+(G6-G7) -> 0 | H23: ='P&L'!H16+(H6-H7) -> #REF! | I23: ='P&L'!I16+(I6-I7) -> #REF! | J23: ='P&L'!J16+(J6-J7) -> #REF! | ... L23: ='P&L'!L16+(L6-L7) -> #REF!
B24: (+) SBC | D24: ='Balance Sheet'!D34-'Balance Sheet'!C34 -> 0 | E24: ='Balance Sheet'!E34-'Balance Sheet'!D34 -> 0 | F24: ='Balance Sheet'!F34-'Balance Sheet'!E34 -> 0 | G24: ='Balance Sheet'!G34-'Balance Sheet'!F34 -> 0 | H24: =Financing!H41 -> #REF! | I24: =Financing!I41 -> #REF! | J24: =Financing!J41 -> #REF! | K24: =Financing!K41 -> #REF! | L24: =Financing!L41 -> #REF!
B25: (+) Options | H25: =Financing!H42 -> #REF! | I25: =Financing!I42 -> #REF! | J25: =Financing!J42 -> #REF! | K25: =Financing!K42 -> #REF! | L25: =Financing!L42 -> #REF!
B26: Net Cash | C26: =C20+C21+C22+C23+C24 -> #DIV/0! | D26: =D20+D21+D22+D23+D24 -> #DIV/0! | E26: =E20+E21+E22+E23+E24 -> #DIV/0! | F26: =F20+F21+F22+F23+F24 -> #DIV/0! | G26: =G20+G21+G22+G23+G24 -> 0 | H26: =H20+H21+H22+H23+H24+H25 -> #REF! | I26: =I20+I21+I22+I23+I24+I25 -> #REF! | J26: =J20+J21+J22+J23+J24+J25 -> #REF! | K26: =K20+K21+K22+K23+K24+K25 -> #REF! | L26: =L20+L21+L22+L23+L24+L25 -> #REF!
C29: Drivers
C30: =C5 -> 2021 | D30: =D5 -> 2022 | E30: =E5 -> 2023 | F30: =F5 -> 2024 | G30: =G5 -> 2025 | H30: =H5 -> 2026 | I30: =I5 -> 2027 | J30: =J5 -> 2028 | ... L30: =L5 -> 2030
B31: Tax rate | C31: ='P&L'!C22 -> #DIV/0! | D31: ='P&L'!D22 -> #DIV/0! | E31: ='P&L'!E22 -> #DIV/0! | F31: ='P&L'!F22 -> #DIV/0! | G31: 0.21 | H31: ='P&L'!H22 -> 0.21 | I31: ='P&L'!I22 -> 0.22 | J31: ='P&L'!J22 -> 0.23 | K31: ='P&L'!K22 -> 0.22 | L31: ='P&L'!L22 -> 0.21 | N31: From P&L Sheet
B32: Depreciation | C32: ='PP&E'!C16 -> 0 | D32: ='PP&E'!D16 -> 0 | E32: ='PP&E'!E16 -> 0 | F32: ='PP&E'!F16 -> 0 | G32: ='PP&E'!G16 -> 0 | H32: ='PP&E'!H16 -> #DIV/0! | I32: ='PP&E'!I16 -> #DIV/0! | J32: ='PP&E'!J16 -> #DIV/0! | ... L32: ='PP&E'!L16 -> #DIV/0! | N32: From PP&E Sheet
B33: Amortization | C33: =Intangibles!C16 -> 0 | D33: =Intangibles!D16 -> 0 | E33: =Intangibles!E16 -> 0 | F33: =Intangibles!F16 -> 0 | G33: =Intangibles!G16 -> 0 | H33: =Intangibles!H16 -> #DIV/0! | I33: =Intangibles!I16 -> #DIV/0! | J33: =Intangibles!J16 -> #DIV/0! | ... L33: =Intangibles!L16 -> #DIV/0! | N33: From Intangibles Sheet
B34: Capex | C34: ='PP&E'!C15 -> 0 | D34: ='PP&E'!D15 -> 0 | E34: ='PP&E'!E15 -> 0 | F34: ='PP&E'!F15 -> 0 | G34: ='PP&E'!G15 -> 0 | H34: ='PP&E'!H15 -> #DIV/0! | I34: ='PP&E'!I15 -> #DIV/0! | J34: ='PP&E'!J15 -> #DIV/0! | ... L34: ='PP&E'!L15 -> #DIV/0! | N34: From PP&E Sheet
B35: CapEx Intangibles | C35: =Intangibles!C15 -> 0 | D35: =Intangibles!D15 -> 0 | E35: =Intangibles!E15 -> 0 | F35: =Intangibles!F15 -> 0 | G35: =Intangibles!G15 -> 0 | H35: =Intangibles!H15 -> #DIV/0! | I35: =Intangibles!I15 -> #DIV/0! | J35: =Intangibles!J15 -> #REF! | ... L35: =Intangibles!L15 -> #REF! | N35: From Intangibles Sheet

Sheet Valuation ->
B13: Valuation ->

Sheet WACC
B1: WACC
B4: Inputs
B5: Shares Outstanding | C5: ='Statement Q'!N116 -> 0
B6: Price | C6: =Overview!C3 -> 103.45
B7: Equity | C7: =C5*C6 -> 0
B8: Debt | C8: ='Statement Q'!J47 -> 0
B9: Risk free rate | C9: =[1]Sheet1!$C$10/1000 -> 0.04323
B10: Beta | C10: 0.8435
B11: Market risk premium | C11: 0.055
B12: Tax rate | C12: 0.21
B13: Cost of debt | C13: 0.0691
B15: Calculations
B16: Debt/(Debt+Equity) | C16: =C8/(C8+C7) -> #DIV/0!
B17: Equity/(Debt+Equity) | C17: =C7/(C8+C7) -> #DIV/0!
B18: Cost of debt with tax | C18: =C13*(1-C12) -> 0.054589
B19: Cost of equity | C19: =C9+C10*C11 -> 0.0896225
B20: WACC | C20: =(C17*C19)+(C16*C18) -> #DIV/0!

Sheet DCF
B1: DCF
C3: History | H3: Forecast
C5: PV of FCF
B6: $ (thousand) | C6: ='Statement Y'!D3 -> 2021 | D6: ='Statement Y'!E3 -> 2022 | E6: ='Statement Y'!F3 -> 2023 | F6: ='Statement Y'!G3 -> 2024 | G6: ='Statement Y'!H3 -> 2025 | H6: =G6+1 -> 2026 | I6: =H6+1 -> 2027 | J6: =I6+1 -> 2028 | K6: =J6+1 -> 2029 | L6: =K6+1 -> 2030
B7: UFCF | C7: ='Cash Flow'!C20 -> #DIV/0! | D7: ='Cash Flow'!D20 -> #DIV/0! | E7: ='Cash Flow'!E20 -> #DIV/0! | F7: ='Cash Flow'!F20 -> #DIV/0! | G7: ='Cash Flow'!G20 -> 0 | H7: ='Cash Flow'!H20 -> #REF! | I7: ='Cash Flow'!I20 -> #REF! | J7: ='Cash Flow'!J20 -> #REF! | ... L7: ='Cash Flow'!L20 -> #REF!
B8: Perpetual cashflow | C8: 0 | D8: 0 | E8: 0 | F8: 0 | G8: 0 | H8: 0 | I8: 0 | J8: 0 | K8: 0 | L8: =L7*(1+C14)/(C15-C14) -> #REF!
B9: Period | H9: 1 | I9: 2 | J9: 3 | K9: 4 | L9: 5
B10: PV of UFCF | H10: =H7/(1+$C$15)^H9 -> #REF! | I10: =I7/(1+$C$15)^I9 -> #REF! | J10: =J7/(1+$C$15)^J9 -> #REF! | K10: =K7/(1+$C$15)^K9 -> #REF! | L10: =L7/(1+$C$15)^L9 -> #REF!
B11: PV of Perpetual cashflow | L11: =L8/(1+C15)^L9 -> #REF!
B13: Input parameters
B14: Perpetual growth | C14: 0.02
B15: WACC | C15: =WACC!C20 -> #DIV/0!
B18: Result
B19: Total PV of Unlevered FCF | C19: =SUM(H10:L10) -> #REF!
B20: PV of Perpetual cashflow | C20: =L11 -> #REF!
B21: Enterprise value | C21: =C19+C20 -> #REF!
B22: (+) Cash | C22: ='Statement Q'!N25+'Statement Q'!N26 -> 0
B23: (-) Debt | C23: ='Statement Q'!N47 -> 0
B24: Equity value | C24: =C21+C22-C23 -> #REF!
B25: Shares outstanding | C25: ='Statement Q'!N20 -> #DIV/0!
B26: Price per share | C26: =C24/C25 -> #REF!

Sheet PE and PS
B1: PE and PS
C2: History | H2: Forecast
C4: Revenues
B5: Revenues (thousand) | C5: ='Statement Y'!D3 -> 2021 | D5: ='Statement Y'!E3 -> 2022 | E5: ='Statement Y'!F3 -> 2023 | F5: ='Statement Y'!G3 -> 2024 | G5: ='Statement Y'!H3 -> 2025 | H5: =G5+1 -> 2026 | I5: =H5+1 -> 2027 | J5: =I5+1 -> 2028 | K5: =J5+1 -> 2029 | L5: =K5+1 -> 2030
B6: Revenue | C6: ='Statement Y'!D5 -> 0 | D6: ='Statement Y'!E5 -> 0 | E6: ='Statement Y'!F5 -> 0 | F6: ='Statement Y'!G5 -> 0 | G6: ='Statement Y'!H5 -> 0 | H6: =Revenue!H12 -> #REF! | I6: =Revenue!I12 -> #REF! | J6: =Revenue!J12 -> #REF! | K6: =Revenue!K12 -> #REF! | L6: =Revenue!L12 -> #REF!
B7: Net income | C7: ='Statement Y'!D18 -> 0 | D7: ='Statement Y'!E18 -> 0 | E7: ='Statement Y'!F18 -> 0 | F7: ='Statement Y'!G18 -> 0 | G7: ='Statement Y'!H18 -> 0 | H7: ='P&L'!H17 -> #REF! | I7: ='P&L'!I17 -> #REF! | J7: ='P&L'!J17 -> #REF! | K7: ='P&L'!K17 -> #REF! | L7: ='P&L'!L17 -> #REF!
C9: Growth rates
B10: % Growth | C10: =C5 -> 2021 | D10: =D5 -> 2022 | E10: =E5 -> 2023 | F10: =F5 -> 2024 | G10: =G5 -> 2025 | H10: =H5 -> 2026 | I10: =I5 -> 2027 | J10: =J5 -> 2028 | ... L10: =L5 -> 2030
B11: Revenue | D11: =(D6-C6)/C6 -> #DIV/0! | E11: =(E6-D6)/D6 -> #DIV/0! | F11: =(F6-E6)/E6 -> #DIV/0! | G11: =(G6-F6)/F6 -> #DIV/0! | H11: =(H6-G6)/G6 -> #REF! | I11: =(I6-H6)/H6 -> #REF! | J11: =(J6-I6)/I6 -> #REF! | K11: =(K6-J6)/J6 -> #REF! | L11: =(L6-K6)/K6 -> #REF!
B12: Net income | D12: =IF(C7=0, IF(D7=0,0,IF(D7>0,1,-1)), (D7-C7)/ABS(C7) ) -> 0 | E12: =IF(D7=0, IF(E7=0,0,IF(E7>0,1,-1)), (E7-D7)/ABS(D7) ) -> 0 | F12: =IF(E7=0, IF(F7=0,0,IF(F7>0,1,-1)), (F7-E7)/ABS(E7) ) -> 0 | G12: =IF(F7=0, IF(G7=0,0,IF(G7>0,1,-1)), (G7-F7)/ABS(F7) ) -> 0 | H12: =IF(G7=0, IF(H7=0,0,IF(H7>0,1,-1)), (H7-G7)/ABS(G7) ) -> #REF! | I12: =IF(H7=0, IF(I7=0,0,IF(I7>0,1,-1)), (I7-H7)/ABS(H7) ) -> #REF! | J12: =IF(I7=0, IF(J7=0,0,IF(J7>0,1,-1)), (J7-I7)/ABS(I7) ) -> #REF! | K12: =IF(J7=0, IF(K7=0,0,IF(K7>0,1,-1)), (K7-J7)/ABS(J7) ) -> #REF! | L12: =IF(K7=0, IF(L7=0,0,IF(L7>0,1,-1)), (L7-K7)/ABS(K7) ) -> #REF!
C14: Shares
C15: =C5 -> 2021 | D15: =D5 -> 2022 | E15: =E5 -> 2023 | F15: =F5 -> 2024 | G15: =G5 -> 2025 | H15: =H5 -> 2026 | I15: =I5 -> 2027 | J15: =J5 -> 2028 | ... L15: =L5 -> 2030
B16: Avg diluted shares | C16: ='Statement Y'!D20 -> 0 | D16: ='Statement Y'!E20 -> 0 | E16: ='Statement Y'!F20 -> 0 | F16: ='Statement Y'!G20 -> 0 | G16: ='Statement Y'!H20 -> 0 | H16: =G16*(1+H17) -> 0 | I16: =H16*(1+I17) -> 0 | J16: =I16*(1+J17) -> 0 | K16: =J16*(1+K17) -> 0 | L16: =K16*(1+L17) -> 0
B17: Dilution rate | D17: =D16/C16-1 -> #DIV/0! | E17: =E16/D16-1 -> #DIV/0! | F17: =F16/E16-1 -> #DIV/0! | G17: =G16/F16-1 -> #DIV/0! | H17: 0.03 | I17: 0.03 | J17: 0.03 | K17: 0.02 | L17: 0.02
B20: PE valuation
B21: Year 5 earnings | C21: =L7 -> #REF!
B22: WACC | C22: =WACC!C20 -> #DIV/0!
B23: Applied PE ratio | C23: 25
B24: Shares outstanding diluted | C24: =L16 -> 0
B25: PV of earnings | C25: =C21/(1+C22)^5 -> #REF!
B26: Price per share | C26: =C25/C24*C23 -> #REF!
B28: PS valuation
B29: Year 5 sales | C29: =L6 -> #REF!
B30: WACC | C30: =WACC!C20 -> #DIV/0!
B31: Applied PS ratio | C31: 3.5
B32: Shares outstanding diluted | C32: =L16 -> 0
B33: PV of sales | C33: =C29/(1+C30)^5 -> #REF!
B34: Price per share | C34: =C33/C32*C31 -> #REF!

Sheet AVG target price
B1: AVG target price
B4: AVG target price
B5: DCF price | C5: =DCF!C26 -> #REF!
B6: PE price | C6: ='PE and PS'!C26 -> #REF!
B7: PS price | C7: ='PE and PS'!C34 -> #REF!
B8: AVG price | C8: =AVERAGE(C5:C7) -> #REF!
