Workbook

Sheet Overview
B2: Automatic Data | E2: At a glance | H2: Valuation | K2: Links
B3: Company | C3: #VALUE! | E3: Market capitalization | F3: =Statement!AC154 -> 49043.4 | H3: ='AVG target price'!B5 -> DCF price | I3: ='AVG target price'!C5 -> 117.44825 | K3: Financials ->'!B13
B4: Ticker | C4: {=_FV(C3,"Ticker symbol",TRUE)} -> ADSK | E4: Enterprise value | F4: =Statement!AC155 -> 48164.4 | H4: ='AVG target price'!B6 -> EV/EBIT price | I4: ='AVG target price'!C6 -> 346.52062 | K4: Analysis ->'!B13
B5: Price | C5: {=_FV(C3,"Price",TRUE)} -> 233.54 | E5: EPS | F5: =Statement!AC27 -> 7.73 | H5: ='AVG target price'!B7 -> PS price | I5: ='AVG target price'!C7 -> 188.26132 | K5: Forecast ->'!B13
B6: Price Extended Hours | C6: {=_FV(C3,"Price (Extended hours)",TRUE)} -> 233.65 | E6: PE | F6: =Statement!AC151 -> 30.21216 | H6: ='AVG target price'!B8 -> EV/FCFF price | I6: ='AVG target price'!C8 -> 344.98288 | K6: Valuation ->'!B13
B7: Day change | C7: {=_FV(C3,"Change")} -> -1.81 | E7: PS | F7: =Statement!AC152 -> 6.3856252 | H7: ='AVG target price'!B9 -> EV/Sales price | I7: ='AVG target price'!C9 -> 219.72591
B8: Day change extended | C8: {=_FV(C3,"Change (extended hours)",TRUE)} -> 0.11 | E8: FCF Yield | F8: =Statement!AC162 -> 0.042778437 | H8: ='AVG target price'!B10 -> AVG price | I8: ='AVG target price'!C10 -> 243.3878
B9: Day change % | C9: {=_FV(C3,"Change (%)",TRUE)} -> -0.007691 | E9: Earnings Yield | F9: =Statement!AC163 -> 0.033099255 | H9: ='AVG target price'!B12 -> Upside/Downside | I9: ='AVG target price'!C12 -> 0.042167502
B10: Day change extended % | C10: {=_FV(C3,"Change % (extended hours)",TRUE)} -> 0.000471 | E10: Buyback Yield | F10: =Statement!AC165 -> 0.032440655
B11: 52 week high | C11: {=_FV(C3,"52 week high",TRUE)} -> 320 | E11: Dividend Yield | F11: =Statement!AC164 -> 0 | H11: DDM price | I11: =DDM!C26 -> 0
B12: 52 week low | C12: {=_FV(C3,"52 week low",TRUE)} -> 185.5 | E12: ROA | F12: =Statement!AC124 -> 0.12647308
B13: Beta | C13: {=_FV(C3,"Beta")} -> 1.3195 | E13: ROE | F13: =Statement!AC126 -> 0.48536802 | H13: Reverse DCF rate | I13: ='Reverse DCF'!C17 -> 0.465
B14: Avg volume | C14: {=_FV(C3,"Volume average",TRUE)} -> 2316106 | E14: ROIC | F14: =Statement!AC141 -> 0.63581348
E15: Net Cash/Market Cap | F15: =Statement!AC177 -> 0.017922901
E16: Net Cash/Share | F16: =Statement!AC176 -> 4.2057416 | H16: Discount rates used
B17: Unit data and other info | E17: Insider Ownership | F17: =Statement!AC172 -> 0.0047619048 | H17: WACC | I17: =DCF!C15 -> 0.10760405
B18: Units | C18: M | E18: Net Trade Cycle | F18: =Statement!AC145 -> -212.53333 | H18: Cost of Equity | I18: =Multiples!C54 -> 0.1118175
B19: Units conversion | C19: 1000000 | E19: Net Debt/Equity | F19: =Statement!AC147 -> -0.25982855
B20: Has operating lease | C20: Yes | E20: Quick Ratio | F20: =Statement!AC148 -> 0.76056126
B21: Has finance lease | C21: No
B22: Has debt | C22: Yes
B25: Constants | E25: 10 Year Bond Yield
B26: Default tax rate | C26: 0.21 | E26: #VALUE! | F26: {=_FV(E26,"Price")} -> 52.44
B27: Cost of debt | C27: 0.061 | E27: Percentage | F27: =F26/1000 -> 0.05244
B28: Manual WACC | C28: 0
B29: Manual Cost of Equity | C29: 0
B33: Info
B35: Mission: | C35: Empower everyone, everywhere, to design and make anything
B36: Auditor: | C36: Ernst & Young LLP
B37: Business units: | C37: AECO has the Architecure, Engineering and Construction Collection, AutoCAD Civil 3D, Building Connected and other related products
C38: AutoCAD and AutoCAD LT
C39: Manufacturing Fusion, Inventor, Vault and other related software
C40: Media and Entertainment contains Maya, 3ds Max plus other related programs
B41: Competitors: | C41: Adobe
C42: Bentley Systems
C43: Dassault Systemes
C44: MSC Software Corporation
C45: Oracle
C46: PTC
C47: Siemens
B48: Patents: | C48: 1168
B54: Notes
B56: Date: | C56: 21.08.2026 | E56: Q2 2027
B57: - | C57: AECO will become AEC with O moving to the Other category
B58: - | C58: M&E will be placed into the Other category
B64: Adjustments
B66: Date: | C66: 29.11.2024 | E66: FY 2024

Sheet Financials ->
H5: Links
H6: Overview'!B3
H7: Financials ->'!B13
H8: Analysis ->'!B13
H9: Forecast ->'!B13
H10: Valuation ->'!B13
B13: Financials ->

Sheet Statement
B2: Date | M2: 31.01.2022 | N2: 31.01.2023 | O2: 31.01.2024 | P2: 31.01.2025 | Q2: 31.01.2026 | T2: 31.10.2024 | U2: 31.01.2025 | V2: 30.04.2025 | W2: 31.07.2025 | X2: 31.10.2025 | Y2: 31.01.2026 | Z2: 30.04.2026 | AA2: 31.07.2026
B3: FY | M3: 2022 | N3: 2023 | O3: 2024 | P3: 2025 | Q3: 2026 | T3: Q3 2025 | U3: Q4 2025 | V3: Q1 2026 | W3: Q2 2026 | X3: Q3 2026 | Y3: Q4 2026 | Z3: Q1 2027 | AA3: Q2 2027 | AC3: TTM/YTD
B4: Income statement
B5: Revenue | M5: 4386 | N5: 5005 | O5: 5497 | P5: 6131 | Q5: 7206 | T5: 1570 | U5: 1639 | V5: 1633 | W5: 1763 | X5: 1853 | Y5: 1957 | Z5: 1934 | AA5: 2046 | AC5: =SUM(X5:AA5) -> 7790
B6: COGS | M6: 418 | N6: 480 | O6: 511 | P6: 578 | Q6: 650 | T6: 147 | U6: 154 | V6: 160 | W6: 159 | X6: 165 | Y6: 166 | Z6: 175 | AA6: 176 | AC6: =SUM(X6:AA6) -> 682
B7: Gross Profit | C7: =C5-C6 -> 0 | D7: =D5-D6 -> 0 | E7: =E5-E6 -> 0 | F7: =F5-F6 -> 0 | G7: =G5-G6 -> 0 | H7: =H5-H6 -> 0 | I7: =I5-I6 -> 0 | J7: =J5-J6 -> 0 | ... Q7: =Q5-Q6 -> 6556 | T7: =T5-T6 -> 1423 | U7: =U5-U6 -> 1485 | V7: =V5-V6 -> 1473 | W7: =W5-W6 -> 1604 | X7: =X5-X6 -> 1688 | Y7: =Y5-Y6 -> 1791 | Z7: =Z5-Z6 -> 1759 | AA7: =AA5-AA6 -> 1870 | AC7: =SUM(X7:AA7) -> 7108
B8: Sales and marketing | M8: 1623 | N8: 1745 | O8: 1823 | P8: 2000 | Q8: 2373 | T8: 525 | U8: 526 | V8: 566 | W8: 559 | X8: 612 | Y8: 636 | Z8: 593 | AA8: 616 | AC8: =SUM(X8:AA8) -> 2457
B9: R&D | M9: 1115 | N9: 1219 | O9: 1373 | P9: 1485 | Q9: 1643 | T9: 378 | U9: 393 | V9: 394 | W9: 413 | X9: 416 | Y9: 420 | Z9: 421 | AA9: 464 | AC9: =SUM(X9:AA9) -> 1721
B10: General and administrative | M10: 572 | N10: 532 | O10: 620 | P10: 650 | Q10: 693 | T10: 161 | U10: 173 | V10: 162 | W10: 168 | X10: 172 | Y10: 191 | Z10: 162 | AA10: 179 | AC10: =SUM(X10:AA10) -> 704
B11: Amortization purchased intangibles | M11: 40 | N11: 40 | O11: 42 | P11: 49 | Q11: 53 | T11: 13 | U11: 12 | V11: 13 | W11: 14 | X11: 13 | Y11: 13 | Z11: 12 | AA11: 13 | AC11: =SUM(X11:AA11) -> 51
B12: OpEx | M12: 3350 | N12: 3536 | O12: 3858 | P12: 4199 | Q12: 4978 | T12: 1077 | U12: 1119 | V12: 1240 | W12: 1160 | X12: 1218 | Y12: 1360 | Z12: 1218 | AA12: 1271 | AC12: =SUM(X12:AA12) -> 5067
B13: Operating income | M13: 618 | N13: 989 | O13: 1128 | P13: 1354 | Q13: 1578 | T13: 346 | U13: 366 | V13: 233 | W13: 444 | X13: 470 | Y13: 431 | Z13: 541 | AA13: 599 | AC13: =SUM(X13:AA13) -> 2041
B14: Interest income/expense | M14: -53 | N14: -43 | O14: 8 | P14: 30 | Q14: 25 | T14: 5 | U14: 6 | V14: 1 | W14: 12 | X14: -2 | Y14: 14 | Z14: 58 | AA14: -6 | AC14: =SUM(X14:AA14) -> 64
B15: Other income/expense | M15: 0 | N15: 0 | O15: 0 | P15: 0 | Q15: 0 | T15: 0 | U15: 0 | V15: 0 | W15: 0 | X15: 0 | Y15: 0 | Z15: 0 | AA15: 0 | AC15: =SUM(X15:AA15) -> 0
B16: Income before taxes | M16: 565 | N16: 946 | O16: 1136 | P16: 1384 | Q16: 1603 | T16: 351 | U16: 372 | V16: 234 | W16: 456 | X16: 468 | Y16: 445 | Z16: 599 | AA16: 593 | AC16: =SUM(X16:AA16) -> 2105
B17: Income tax expense/benefit | M17: -68 | N17: -123 | O17: -230 | P17: -272 | Q17: -479 | T17: -76 | U17: -69 | V17: -82 | W17: -143 | X17: -125 | Y17: -129 | Z17: -108 | AA17: -101 | AC17: =SUM(X17:AA17) -> -463
B18: Non-controlling interest | M18: 0 | N18: 0 | O18: 0 | P18: 0 | Q18: 0 | T18: 0 | U18: 0 | V18: 0 | W18: 0 | X18: 0 | Y18: 0 | Z18: 0 | AA18: 0 | AC18: =SUM(X18:AA18) -> 0
B19: Net income | M19: 497 | N19: 823 | O19: 906 | P19: 1112 | Q19: 1124 | T19: 275 | U19: 303 | V19: 152 | W19: 313 | X19: 343 | Y19: 316 | Z19: 491 | AA19: 492 | AC19: =SUM(X19:AA19) -> 1642
B20: Basic Shares outstanding avg | M20: 220 | N20: 216 | O20: 214 | P20: 215 | Q20: 213 | T20: 215 | U20: 214 | V20: 214 | W20: 213 | X20: 213 | Y20: 212 | Z20: 211 | AA20: 210 | AC20: =AVERAGE(X20:AA20) -> 211.5
B21: Basic Shares outstanding avg adjusted | C21: =C20*C$86 -> 0 | D21: =D20*D$86 -> 0 | E21: =E20*E$86 -> 0 | F21: =F20*F$86 -> 0 | G21: =G20*G$86 -> 0 | H21: =H20*H$86 -> 0 | I21: =I20*I$86 -> 0 | J21: =J20*J$86 -> 0 | ... Q21: =Q20*Q$86 -> 213 | T21: =T20*T$86 -> 215 | U21: =U20*U$86 -> 214 | V21: =V20*V$86 -> 214 | W21: =W20*W$86 -> 213 | X21: =X20*X$86 -> 213 | Y21: =Y20*Y$86 -> 212 | Z21: =Z20*Z$86 -> 211 | AA21: =AA20*AA$86 -> 210 | AC21: =AC20*AC$86 -> 211.5
B22: Diluted Shares outstanding avg | M22: 222 | N22: 218 | O22: 216 | P22: 217 | Q22: 215 | T22: 217 | U22: 217 | V22: 216 | W22: 215 | X22: 215 | Y22: 214 | Z22: 212 | AA22: 211 | AC22: =AVERAGE(X22:AA22) -> 213
B23: Diluted Shares outstanding avg adjusted | C23: =C22*C$86 -> 0 | D23: =D22*D$86 -> 0 | E23: =E22*E$86 -> 0 | F23: =F22*F$86 -> 0 | G23: =G22*G$86 -> 0 | H23: =H22*H$86 -> 0 | I23: =I22*I$86 -> 0 | J23: =J22*J$86 -> 0 | ... Q23: =Q22*Q$86 -> 215 | T23: =T22*T$86 -> 217 | U23: =U22*U$86 -> 217 | V23: =V22*V$86 -> 216 | W23: =W22*W$86 -> 215 | X23: =X22*X$86 -> 215 | Y23: =Y22*Y$86 -> 214 | Z23: =Z22*Z$86 -> 212 | AA23: =AA22*AA$86 -> 211 | AC23: =AC22*AC$86 -> 213
B24: Basic EPS | M24: 2.26 | N24: 3.81 | O24: 4.23 | P24: 5.17 | Q24: 5.28 | T24: 1.28 | U24: 1.42 | V24: 0.71 | W24: 1.47 | X24: 1.61 | Y24: 1.49 | Z24: 2.33 | AA24: 2.34 | AC24: =SUM(X24:AA24) -> 7.77
B25: Basic EPS adjusted | M25: =M24/M$86 -> 2.26 | N25: =N24/N$86 -> 3.81 | O25: =O24/O$86 -> 4.23 | P25: =P24/P$86 -> 5.17 | Q25: =Q24/Q$86 -> 5.28 | T25: =T24/T$86 -> 1.28 | U25: =U24/U$86 -> 1.42 | V25: =V24/V$86 -> 0.71 | W25: =W24/W$86 -> 1.47 | X25: =X24/X$86 -> 1.61 | Y25: =Y24/Y$86 -> 1.49 | Z25: =Z24/Z$86 -> 2.33 | AA25: =AA24/AA$86 -> 2.34 | AC25: =AC24/AC$86 -> 7.77
B26: Diluted EPS | M26: 2.24 | N26: 3.78 | O26: 4.19 | P26: 5.12 | Q26: 5.23 | T26: 1.27 | U26: 1.4 | V26: 0.7 | W26: 1.46 | X26: 1.6 | Y26: 1.48 | Z26: 2.32 | AA26: 2.33 | AC26: =SUM(X26:AA26) -> 7.73
B27: Diluted EPS adjusted | M27: =M26/M$86 -> 2.24 | N27: =N26/N$86 -> 3.78 | O27: =O26/O$86 -> 4.19 | P27: =P26/P$86 -> 5.12 | Q27: =Q26/Q$86 -> 5.23 | T27: =T26/T$86 -> 1.27 | U27: =U26/U$86 -> 1.4 | V27: =V26/V$86 -> 0.7 | W27: =W26/W$86 -> 1.46 | X27: =X26/X$86 -> 1.6 | Y27: =Y26/Y$86 -> 1.48 | Z27: =Z26/Z$86 -> 2.32 | AA27: =AA26/AA$86 -> 2.33 | AC27: =AC26/AC$86 -> 7.73
B29: Balance sheet
B30: Cash and cash equivalents | M30: =1528+236 -> 1764 | N30: =1947+125 -> 2072 | O30: =1892+354 -> 2246 | P30: =1599+287 -> 1886 | Q30: =2249+348 -> 2597 | T30: =1437+276 -> 1713 | U30: =1599+287 -> 1886 | V30: =1816+224 -> 2040 | W30: =2003+233 -> 2236 | X30: =1989+300 -> 2289 | Y30: =2249+348 -> 2597 | Z30: =2671+253 -> 2924 | AA30: =4098+57 -> 4155 | AC30: =AA30 -> 4155
B31: Acc receivable | M31: 716 | N31: 961 | O31: 876 | P31: 1008 | Q31: 1439 | T31: 702 | U31: 1008 | V31: 494 | W31: 532 | X31: 806 | Y31: 1439 | Z31: 579 | AA31: 684 | AC31: =AA31 -> 684
B32: Inventory | M32: 0 | N32: 0 | O32: 0 | P32: 0 | Q32: 0 | T32: 0 | U32: 0 | V32: 0 | W32: 0 | X32: 0 | Y32: 0 | Z32: 0 | AA32: 0 | AC32: =AA32 -> 0
B33: Current assets | M33: 2764 | N33: 3341 | O33: 3579 | P33: 3482 | Q33: 4942 | T33: 2899 | U33: 3482 | V33: 3215 | W33: 3489 | X33: 3895 | Y33: 4942 | Z33: 4374 | AA33: 5670 | AC33: =AA33 -> 5670
B34: PP&E | M34: 163 | N34: 144 | O34: 121 | P34: 117 | Q34: 121 | T34: 116 | U34: 117 | V34: 111 | W34: 109 | X34: 118 | Y34: 121 | Z34: 122 | AA34: 124 | AC34: =AA34 -> 124
B35: Marketable securities and investments | M35: 45 | N35: 102 | O35: 234 | P35: 267 | Q35: 376 | T35: 264 | U35: 267 | V35: 261 | W35: 282 | X35: 302 | Y35: 376 | Z35: 385 | AA35: 202 | AC35: =AA35 -> 202
B36: Goodwill | M36: 3604 | N36: 3625 | O36: 3653 | P36: 4242 | Q36: 4295 | T36: 4256 | U36: 4242 | V36: 4275 | W36: 4275 | X36: 4278 | Y36: 4295 | Z36: 4337 | AA36: 4331 | AC36: =AA36 -> 4331
B37: Long term assets | M37: =M38-M33 -> 5843 | N37: =N38-N33 -> 6097 | O37: =O38-O33 -> 6333 | P37: =P38-P33 -> 7351 | Q37: =Q38-Q33 -> 7525 | T37: =T38-T33 -> 7234 | U37: =U38-U33 -> 7351 | V37: =V38-V33 -> 7370 | W37: =W38-W33 -> 7367 | X37: =X38-X33 -> 7303 | Y37: =Y38-Y33 -> 7525 | Z37: =Z38-Z33 -> 7558 | AA37: =AA38-AA33 -> 7313 | AC37: =AA37 -> 7313
B38: Total assets | M38: 8607 | N38: 9438 | O38: 9912 | P38: 10833 | Q38: 12467 | T38: 10133 | U38: 10833 | V38: 10585 | W38: 10856 | X38: 11198 | Y38: 12467 | Z38: 11932 | AA38: 12983 | AC38: =AA38 -> 12983
B39: Acc payable | M39: 121 | N39: 102 | O39: 100 | P39: 242 | Q39: 422 | T39: 217 | U39: 242 | V39: 277 | W39: 324 | X39: 384 | Y39: 422 | Z39: 403 | AA39: 457 | AC39: =AA39 -> 457
B40: Debt | M40: 0 | N40: 0 | O40: 0 | P40: 300 | Q40: 0 | T40: 300 | U40: 300 | V40: 300 | W40: 0 | X40: 0 | Y40: 0 | Z40: 0 | AA40: =994+499 -> 1493 | AC40: =AA40 -> 1493
B41: Current liabilities | M41: 4009 | N41: 4000 | O41: 4351 | P41: 5151 | Q41: 5808 | T41: 4468 | U41: 5151 | V41: 4919 | W41: 4566 | X41: 4735 | Y41: 5808 | Z41: 5240 | AA41: 6628 | AC41: =AA41 -> 6628
B42: Debt | M42: 2280 | N42: 2281 | O42: 2284 | P42: 1987 | Q42: 2483 | T42: 1986 | U42: 1987 | V42: 1988 | W42: 2481 | X42: 2482 | Y42: 2483 | Z42: 2484 | AA42: 1985 | AC42: =AA42 -> 1985
B43: Long term liabilities | M43: =M44-M41 -> 3749 | N43: =N44-N41 -> 4293 | O43: =O44-O41 -> 3706 | P43: =P44-P41 -> 3061 | Q43: =Q44-Q41 -> 3614 | T43: =T44-T41 -> 3049 | U43: =U44-U41 -> 3061 | V43: =V44-V41 -> 3049 | W43: =W44-W41 -> 3575 | X43: =X44-X41 -> 3570 | Y43: =Y44-Y41 -> 3614 | Z43: =Z44-Z41 -> 3503 | AA43: =AA44-AA41 -> 2972 | AC43: =AA43 -> 2972
B44: Total liabilities | M44: 7758 | N44: 8293 | O44: 8057 | P44: 8212 | Q44: 9422 | T44: 7517 | U44: 8212 | V44: 7968 | W44: 8141 | X44: 8305 | Y44: 9422 | Z44: 8743 | AA44: 9600 | AC44: =AA44 -> 9600
B45: Treasury stock | M45: 0 | N45: 0 | O45: 0 | P45: 0 | Q45: 0 | T45: 0 | U45: 0 | V45: 0 | W45: 0 | X45: 0 | Y45: 0 | Z45: 0 | AA45: 0 | AC45: =AA45 -> 0
B46: Preferred stock | M46: 0 | N46: 0 | O46: 0 | P46: 0 | Q46: 0 | T46: 0 | U46: 0 | V46: 0 | W46: 0 | X46: 0 | Y46: 0 | Z46: 0 | AA46: 0 | AC46: =AA46 -> 0
B47: Paid in capital | M47: 2923 | N47: 3325 | O47: 3802 | P47: 4239 | Q47: 4709 | T47: 4100 | U47: 4239 | V47: 4324 | W47: 4456 | X47: 4588 | Y47: 4709 | Z47: 4726 | AA47: 4846 | AC47: =AA47 -> 4846
B48: Accumulated income/loss | M48: -1950 | N48: -1995 | O48: -1713 | P48: -1333 | Q48: -1432 | T48: -1224 | U48: -1333 | V48: -1459 | W48: -1487 | X48: -1432 | Y48: -1432 | Z48: -1303 | AA48: -1230 | AC48: =AA48 -> -1230
B49: Non-controlling interest | M49: 0 | N49: 0 | O49: 0 | P49: 0 | Q49: 0 | T49: 0 | U49: 0 | V49: 0 | W49: 0 | X49: 0 | Y49: 0 | Z49: 0 | AA49: 0 | AC49: =AA49 -> 0
B50: Stockholder equity | M50: 849 | N50: 1145 | O50: 1855 | P50: 2621 | Q50: 3045 | T50: 2616 | U50: 2621 | V50: 2617 | W50: 2715 | X50: 2893 | Y50: 3045 | Z50: 3189 | AA50: 3383 | AC50: =AA50 -> 3383
B51: Total liabilities and equity | M51: 8607 | N51: 9438 | O51: 9912 | P51: 10833 | Q51: 12467 | T51: 10133 | U51: 10833 | V51: 10585 | W51: 10856 | X51: 11198 | Y51: 12467 | Z51: 11932 | AA51: 12983 | AC51: =AA51 -> 12983
B53: Cashflow statement
B54: D&A | M54: 148 | N54: 150 | O54: 139 | P54: 180 | Q54: 195 | V54: 48 | W54: 47 | X54: 50 | Y54: 50 | Z54: 51 | AA54: 50 | AC54: =SUM(X54:AA54) -> 201
B55: Stock-based compensation | M55: 555 | N55: 657 | O55: 703 | P55: 683 | Q55: 788 | V55: 230 | W55: 191 | X55: 186 | Y55: 181 | Z55: 155 | AA55: 184 | AC55: =SUM(X55:AA55) -> 706
B56: Change in accounts receivable | M56: -66 | N56: -247 | O56: 86 | P56: -132 | Q56: -431 | V56: 515 | W56: -39 | X56: -274 | Y56: -633 | Z56: 859 | AA56: -106 | AC56: =SUM(X56:AA56) -> -154
B57: Change in inventory | M57: 0 | N57: 0 | O57: 0 | P57: 0 | Q57: 0 | V57: 0 | W57: 0 | X57: 0 | Y57: 0 | Z57: 0 | AA57: 0 | AC57: =SUM(X57:AA57) -> 0
B58: Change in accounts payable | M58: 10 | N58: -5 | O58: 27 | P58: 238 | Q58: 455 | V58: -111 | W58: 128 | X58: 78 | Y58: 360 | Z58: -488 | AA58: 80 | AC58: =SUM(X58:AA58) -> 30
B59: Change in other operating NWC | M59: =-134+419-12 -> 273 | N59: =-3+798+149 -> 944 | O59: =-256-316+8 -> -564 | P59: =-488-134+58 -> -564 | Q59: =-1051+555-29 -> -525 | V59: =-304-204+27 -> -481 | W59: -338 | X59: -236 | Y59: 530 | Z59: =-126-238+26 -> -338 | AA59: -317 | AC59: =SUM(X59:AA59) -> -361
B60: Operating cashflow | M60: 1531 | N60: 2071 | O60: 1313 | P60: 1607 | Q60: 2452 | V60: 564 | W60: 460 | X60: 439 | Y60: 989 | Z60: 893 | AA60: 575 | AC60: =SUM(X60:AA60) -> 2896
B61: CapEx | M61: =-11-56 -> -67 | N61: =-6-40 -> -46 | O61: =-30-31 -> -61 | P61: =-62-40 -> -102 | Q61: =-33-43 -> -76 | V61: =-8-7 -> -15 | W61: -16 | X61: -22 | Y61: -23 | Z61: =-17-9 -> -26 | AA61: -21 | AC61: =SUM(X61:AA61) -> -92
B62: Capitalized software | M62: 0 | N62: 0 | O62: 0 | P62: 0 | Q62: 0 | V62: 0 | W62: 0 | X62: 0 | Y62: 0 | Z62: 0 | AA62: 0 | AC62: =SUM(X62:AA62) -> 0
B63: Investing cashflow | M63: -1595 | N63: -143 | O63: -502 | P63: -903 | Q63: -451 | V63: 58 | W63: -50 | X63: -109 | Y63: -350 | Z63: 29 | AA63: 352 | AC63: =SUM(X63:AA63) -> -78
B64: Repurchase stock | M64: -1079 | N64: -1101 | O64: -795 | P64: -852 | Q64: -1402 | V64: -354 | W64: -358 | X64: -359 | Y64: -331 | Z64: -448 | AA64: -453 | AC64: =SUM(X64:AA64) -> -1591
B65: Dividends | M65: 0 | N65: 0 | O65: 0 | P65: 0 | Q65: 0 | V65: 0 | W65: 0 | X65: 0 | Y65: 0 | Z65: 0 | AA65: 0 | AC65: =SUM(X65:AA65) -> 0
B66: Dividends to minority interest | M66: 0 | N66: 0 | O66: 0 | P66: 0 | Q66: 0 | V66: 0 | W66: 0 | X66: 0 | Y66: 0 | Z66: 0 | AA66: 0 | AC66: =SUM(X66:AA66) -> 0
B67: Financing cashflow | M67: -169 | N67: -1487 | O67: -852 | P67: -987 | Q67: -1361 | V67: -415 | W67: -219 | X67: -345 | Y67: -382 | Z67: -498 | AA67: 502 | AC67: =SUM(X67:AA67) -> -723
B69: Sanity checks
B70: Calculated Net Income | C70: =C5-C6-C12+C14+C15+C17-C18 -> 0 | D70: =D5-D6-D12+D14+D15+D17-D18 -> 0 | E70: =E5-E6-E12+E14+E15+E17-E18 -> 0 | F70: =F5-F6-F12+F14+F15+F17-F18 -> 0 | G70: =G5-G6-G12+G14+G15+G17-G18 -> 0 | H70: =H5-H6-H12+H14+H15+H17-H18 -> 0 | I70: =I5-I6-I12+I14+I15+I17-I18 -> 0 | J70: =J5-J6-J12+J14+J15+J17-J18 -> 0 | ... Q70: =Q5-Q6-Q12+Q14+Q15+Q17-Q18 -> 1124 | T70: =T5-T6-T12+T14+T15+T17-T18 -> 275 | U70: =U5-U6-U12+U14+U15+U17-U18 -> 303 | V70: =V5-V6-V12+V14+V15+V17-V18 -> 152 | W70: =W5-W6-W12+W14+W15+W17-W18 -> 313 | X70: =X5-X6-X12+X14+X15+X17-X18 -> 343 | Y70: =Y5-Y6-Y12+Y14+Y15+Y17-Y18 -> 316 | Z70: =Z5-Z6-Z12+Z14+Z15+Z17-Z18 -> 491 | AA70: =AA5-AA6-AA12+AA14+AA15+AA17-AA18 -> 492 | AC70: =AC5-AC6-AC12+AC14+AC15+AC17-AC18 -> 1642
B71: Check Net Income | C71: =C19-C70 -> 0 | D71: =D19-D70 -> 0 | E71: =E19-E70 -> 0 | F71: =F19-F70 -> 0 | G71: =G19-G70 -> 0 | H71: =H19-H70 -> 0 | I71: =I19-I70 -> 0 | J71: =J19-J70 -> 0 | ... Q71: =Q19-Q70 -> 0 | T71: =T19-T70 -> 0 | U71: =U19-U70 -> 0 | V71: =V19-V70 -> 0 | W71: =W19-W70 -> 0 | X71: =X19-X70 -> 0 | Y71: =Y19-Y70 -> 0 | Z71: =Z19-Z70 -> 0 | AA71: =AA19-AA70 -> 0 | AC71: =AC19-AC70 -> 0
B72: Check balance | C72: =C38-(C44+C113) -> 0 | D72: =D38-(D44+D113) -> 0 | E72: =E38-(E44+E113) -> 0 | F72: =F38-(F44+F113) -> 0 | G72: =G38-(G44+G113) -> 0 | H72: =H38-(H44+H113) -> 0 | I72: =I38-(I44+I113) -> 0 | J72: =J38-(J44+J113) -> 0 | ... Q72: =Q38-(Q44+Q113) -> 0 | T72: =T38-(T44+T113) -> 0 | U72: =U38-(U44+U113) -> 0 | V72: =V38-(V44+V113) -> 0 | W72: =W38-(W44+W113) -> 0 | X72: =X38-(X44+X113) -> 0 | Y72: =Y38-(Y44+Y113) -> 0 | Z72: =Z38-(Z44+Z113) -> 0 | AA72: =AA38-(AA44+AA113) -> 0 | AC72: =AC38-(AC44+AC113) -> 0
B74: Other data
B75: Shares outstanding | M75: 217 | N75: 216 | O75: 214 | P75: 215 | Q75: 213 | T75: 215 | U75: 215 | V75: 214 | W75: 213 | X75: 212 | Y75: 213 | Z75: 211 | AA75: 209 | AC75: =AA75 -> 209
B76: Split adjusted shares outstanding | M76: =M75*M86 -> 217 | N76: =N75*N86 -> 216 | O76: =O75*O86 -> 214 | P76: =P75*P86 -> 215 | Q76: =Q75*Q86 -> 213 | T76: =T75*T86 -> 215 | U76: =U75*U86 -> 215 | V76: =V75*V86 -> 214 | W76: =W75*W86 -> 213 | X76: =X75*X86 -> 212 | Y76: =Y75*Y86 -> 213 | Z76: =Z75*Z86 -> 211 | AA76: =AA75*AA86 -> 209 | AC76: =AA76 -> 209
B77: Dilutive shares | M77: 2 | N77: 2 | O77: 2 | P77: 2 | Q77: 2 | T77: 2 | U77: 2 | V77: 2 | W77: 2 | X77: 2 | Y77: 2 | Z77: 1 | AA77: 1 | AC77: =AA77 -> 1
B78: Split adjusted dilutive shares | M78: =M77*M86 -> 2 | N78: =N77*N86 -> 2 | O78: =O77*O86 -> 2 | P78: =P77*P86 -> 2 | Q78: =Q77*Q86 -> 2 | T78: =T77*T86 -> 2 | U78: =U77*U86 -> 2 | V78: =V77*V86 -> 2 | W78: =W77*W86 -> 2 | X78: =X77*X86 -> 2 | Y78: =Y77*Y86 -> 2 | Z78: =Z77*Z86 -> 1 | AA78: =AA77*AA86 -> 1 | AC78: =AA78 -> 1
B79: Split adjusted diluted shares | M79: =M76+M78 -> 219 | N79: =N76+N78 -> 218 | O79: =O76+O78 -> 216 | P79: =P76+P78 -> 217 | Q79: =Q76+Q78 -> 215 | T79: =T76+T78 -> 217 | U79: =U76+U78 -> 217 | V79: =V76+V78 -> 216 | W79: =W76+W78 -> 215 | X79: =X76+X78 -> 214 | Y79: =Y76+Y78 -> 215 | Z79: =Z76+Z78 -> 212 | AA79: =AA76+AA78 -> 210 | AC79: =AA79 -> 210
B80: Shares held by insiders | M80: 1 | N80: 1 | O80: 1 | P80: 1 | Q80: 1 | AC80: =Q80 -> 1
B81: Split adjusted shares held by insiders | M81: =M80*M86 -> 1 | N81: =N80*N86 -> 1 | O81: =O80*O86 -> 1 | P81: =P80*P86 -> 1 | Q81: =Q80*Q86 -> 1 | AC81: =Q81 -> 1
B82: Dividends per share | M82: 0 | N82: 0 | O82: 0 | P82: 0 | Q82: 0 | T82: 0 | U82: 0 | V82: 0 | W82: 0 | X82: 0 | Y82: 0 | Z82: 0 | AA82: 0 | AC82: =SUM(X82:AA82) -> 0
B83: Split adjusted dividends per share | M83: =M82/M86 -> 0 | N83: =N82/N86 -> 0 | O83: =O82/O86 -> 0 | P83: =P82/P86 -> 0 | Q83: =Q82/Q86 -> 0 | T83: =T82/T86 -> 0 | U83: =U82/U86 -> 0 | V83: =V82/V86 -> 0 | W83: =W82/W86 -> 0 | X83: =X82/X86 -> 0 | Y83: =Y82/Y86 -> 0 | Z83: =Z82/Z86 -> 0 | AA83: =AA82/AA86 -> 0 | AC83: =SUM(X83:AA83) -> 0
B84: Tax rate | C84: =IF(AND(C16>0,C17<0),-(C17)/C16,0) -> 0 | D84: =IF(AND(D16>0,D17<0),-(D17)/D16,0) -> 0 | E84: =IF(AND(E16>0,E17<0),-(E17)/E16,0) -> 0 | F84: =IF(AND(F16>0,F17<0),-(F17)/F16,0) -> 0 | G84: =IF(AND(G16>0,G17<0),-(G17)/G16,0) -> 0 | H84: =IF(AND(H16>0,H17<0),-(H17)/H16,0) -> 0 | I84: =IF(AND(I16>0,I17<0),-(I17)/I16,0) -> 0 | J84: =IF(AND(J16>0,J17<0),-(J17)/J16,0) -> 0 | ... Q84: =IF(AND(Q16>0,Q17<0),-(Q17)/Q16,0) -> 0.29881472 | T84: =IF(AND(T16>0,T17<0),-(T17)/T16,0) -> 0.21652422 | U84: =IF(AND(U16>0,U17<0),-(U17)/U16,0) -> 0.18548387 | V84: =IF(AND(V16>0,V17<0),-(V17)/V16,0) -> 0.35042735 | W84: =IF(AND(W16>0,W17<0),-(W17)/W16,0) -> 0.31359649 | X84: =IF(AND(X16>0,X17<0),-(X17)/X16,0) -> 0.26709402 | Y84: =IF(AND(Y16>0,Y17<0),-(Y17)/Y16,0) -> 0.28988764 | Z84: =IF(AND(Z16>0,Z17<0),-(Z17)/Z16,0) -> 0.1803005 | AA84: =IF(AND(AA16>0,AA17<0),-(AA17)/AA16,0) -> 0.1703204 | AC84: =IF(AND(AC16>0,AC17<0),-(AC17)/AC16,0) -> 0.21995249
B85: Employees | M85: 12600 | N85: 13700 | O85: 14100 | P85: 15300 | Q85: 14300 | AC85: =Q85 -> 14300
B86: Stock split factor | M86: 1 | N86: 1 | O86: 1 | P86: 1 | Q86: 1 | T86: 1 | U86: 1 | V86: 1 | W86: 1 | X86: 1 | Y86: 1 | Z86: 1 | AA86: 1 | AC86: 1
B89: Growth rates Income Statement
B90: Revenue | M90: =IF(L5=0, IF(M5=0,0,IF(M5>0,1,-1)), (M5-L5)/ABS(L5) ) -> 1 | N90: =IF(M5=0, IF(N5=0,0,IF(N5>0,1,-1)), (N5-M5)/ABS(M5) ) -> 0.14113087 | O90: =IF(N5=0, IF(O5=0,0,IF(O5>0,1,-1)), (O5-N5)/ABS(N5) ) -> 0.098301698 | P90: =IF(O5=0, IF(P5=0,0,IF(P5>0,1,-1)), (P5-O5)/ABS(O5) ) -> 0.11533564 | Q90: =IF(P5=0, IF(Q5=0,0,IF(Q5>0,1,-1)), (Q5-P5)/ABS(P5) ) -> 0.17533844 | T90: =IF(S5=0, IF(T5=0,0,IF(T5>0,1,-1)), (T5-S5)/ABS(S5) ) -> 1 | U90: =IF(T5=0, IF(U5=0,0,IF(U5>0,1,-1)), (U5-T5)/ABS(T5) ) -> 0.043949045 | V90: =IF(U5=0, IF(V5=0,0,IF(V5>0,1,-1)), (V5-U5)/ABS(U5) ) -> -0.0036607688 | W90: =IF(V5=0, IF(W5=0,0,IF(W5>0,1,-1)), (W5-V5)/ABS(V5) ) -> 0.079608083 | X90: =IF(W5=0, IF(X5=0,0,IF(X5>0,1,-1)), (X5-W5)/ABS(W5) ) -> 0.051049348 | Y90: =IF(X5=0, IF(Y5=0,0,IF(Y5>0,1,-1)), (Y5-X5)/ABS(X5) ) -> 0.056125202 | Z90: =IF(Y5=0, IF(Z5=0,0,IF(Z5>0,1,-1)), (Z5-Y5)/ABS(Y5) ) -> -0.011752683 | AA90: =IF(Z5=0, IF(AA5=0,0,IF(AA5>0,1,-1)), (AA5-Z5)/ABS(Z5) ) -> 0.057911065
B91: COGS | M91: =IF(L6=0, IF(M6=0,0,IF(M6>0,1,-1)), (M6-L6)/ABS(L6) ) -> 1 | N91: =IF(M6=0, IF(N6=0,0,IF(N6>0,1,-1)), (N6-M6)/ABS(M6) ) -> 0.14832536 | O91: =IF(N6=0, IF(O6=0,0,IF(O6>0,1,-1)), (O6-N6)/ABS(N6) ) -> 0.064583333 | P91: =IF(O6=0, IF(P6=0,0,IF(P6>0,1,-1)), (P6-O6)/ABS(O6) ) -> 0.13111546 | Q91: =IF(P6=0, IF(Q6=0,0,IF(Q6>0,1,-1)), (Q6-P6)/ABS(P6) ) -> 0.12456747 | T91: =IF(S6=0, IF(T6=0,0,IF(T6>0,1,-1)), (T6-S6)/ABS(S6) ) -> 1 | U91: =IF(T6=0, IF(U6=0,0,IF(U6>0,1,-1)), (U6-T6)/ABS(T6) ) -> 0.047619048 | V91: =IF(U6=0, IF(V6=0,0,IF(V6>0,1,-1)), (V6-U6)/ABS(U6) ) -> 0.038961039 | W91: =IF(V6=0, IF(W6=0,0,IF(W6>0,1,-1)), (W6-V6)/ABS(V6) ) -> -0.00625 | X91: =IF(W6=0, IF(X6=0,0,IF(X6>0,1,-1)), (X6-W6)/ABS(W6) ) -> 0.037735849 | Y91: =IF(X6=0, IF(Y6=0,0,IF(Y6>0,1,-1)), (Y6-X6)/ABS(X6) ) -> 0.0060606061 | Z91: =IF(Y6=0, IF(Z6=0,0,IF(Z6>0,1,-1)), (Z6-Y6)/ABS(Y6) ) -> 0.054216867 | AA91: =IF(Z6=0, IF(AA6=0,0,IF(AA6>0,1,-1)), (AA6-Z6)/ABS(Z6) ) -> 0.0057142857
B92: Gross Profit | M92: =IF(L7=0, IF(M7=0,0,IF(M7>0,1,-1)), (M7-L7)/ABS(L7) ) -> 1 | N92: =IF(M7=0, IF(N7=0,0,IF(N7>0,1,-1)), (N7-M7)/ABS(M7) ) -> 0.14037298 | O92: =IF(N7=0, IF(O7=0,0,IF(O7>0,1,-1)), (O7-N7)/ABS(N7) ) -> 0.10187845 | P92: =IF(O7=0, IF(P7=0,0,IF(P7>0,1,-1)), (P7-O7)/ABS(O7) ) -> 0.11371841 | Q92: =IF(P7=0, IF(Q7=0,0,IF(Q7>0,1,-1)), (Q7-P7)/ABS(P7) ) -> 0.18062309 | T92: =IF(S7=0, IF(T7=0,0,IF(T7>0,1,-1)), (T7-S7)/ABS(S7) ) -> 1 | U92: =IF(T7=0, IF(U7=0,0,IF(U7>0,1,-1)), (U7-T7)/ABS(T7) ) -> 0.043569923 | V92: =IF(U7=0, IF(V7=0,0,IF(V7>0,1,-1)), (V7-U7)/ABS(U7) ) -> -0.0080808081 | W92: =IF(V7=0, IF(W7=0,0,IF(W7>0,1,-1)), (W7-V7)/ABS(V7) ) -> 0.088934148 | X92: =IF(W7=0, IF(X7=0,0,IF(X7>0,1,-1)), (X7-W7)/ABS(W7) ) -> 0.052369077 | Y92: =IF(X7=0, IF(Y7=0,0,IF(Y7>0,1,-1)), (Y7-X7)/ABS(X7) ) -> 0.061018957 | Z92: =IF(Y7=0, IF(Z7=0,0,IF(Z7>0,1,-1)), (Z7-Y7)/ABS(Y7) ) -> -0.017867113 | AA92: =IF(Z7=0, IF(AA7=0,0,IF(AA7>0,1,-1)), (AA7-Z7)/ABS(Z7) ) -> 0.063104036
B93: Sales and marketing | M93: =IF(L8=0, IF(M8=0,0,IF(M8>0,1,-1)), (M8-L8)/ABS(L8) ) -> 1 | N93: =IF(M8=0, IF(N8=0,0,IF(N8>0,1,-1)), (N8-M8)/ABS(M8) ) -> 0.075169439 | O93: =IF(N8=0, IF(O8=0,0,IF(O8>0,1,-1)), (O8-N8)/ABS(N8) ) -> 0.04469914 | P93: =IF(O8=0, IF(P8=0,0,IF(P8>0,1,-1)), (P8-O8)/ABS(O8) ) -> 0.097092704 | Q93: =IF(P8=0, IF(Q8=0,0,IF(Q8>0,1,-1)), (Q8-P8)/ABS(P8) ) -> 0.1865 | T93: =IF(S8=0, IF(T8=0,0,IF(T8>0,1,-1)), (T8-S8)/ABS(S8) ) -> 1 | U93: =IF(T8=0, IF(U8=0,0,IF(U8>0,1,-1)), (U8-T8)/ABS(T8) ) -> 0.0019047619 | V93: =IF(U8=0, IF(V8=0,0,IF(V8>0,1,-1)), (V8-U8)/ABS(U8) ) -> 0.076045627 | W93: =IF(V8=0, IF(W8=0,0,IF(W8>0,1,-1)), (W8-V8)/ABS(V8) ) -> -0.012367491 | X93: =IF(W8=0, IF(X8=0,0,IF(X8>0,1,-1)), (X8-W8)/ABS(W8) ) -> 0.094812165 | Y93: =IF(X8=0, IF(Y8=0,0,IF(Y8>0,1,-1)), (Y8-X8)/ABS(X8) ) -> 0.039215686 | Z93: =IF(Y8=0, IF(Z8=0,0,IF(Z8>0,1,-1)), (Z8-Y8)/ABS(Y8) ) -> -0.067610063 | AA93: =IF(Z8=0, IF(AA8=0,0,IF(AA8>0,1,-1)), (AA8-Z8)/ABS(Z8) ) -> 0.038785835
B94: R&D | M94: =IF(L9=0, IF(M9=0,0,IF(M9>0,1,-1)), (M9-L9)/ABS(L9) ) -> 1 | N94: =IF(M9=0, IF(N9=0,0,IF(N9>0,1,-1)), (N9-M9)/ABS(M9) ) -> 0.093273543 | O94: =IF(N9=0, IF(O9=0,0,IF(O9>0,1,-1)), (O9-N9)/ABS(N9) ) -> 0.12633306 | P94: =IF(O9=0, IF(P9=0,0,IF(P9>0,1,-1)), (P9-O9)/ABS(O9) ) -> 0.081573197 | Q94: =IF(P9=0, IF(Q9=0,0,IF(Q9>0,1,-1)), (Q9-P9)/ABS(P9) ) -> 0.10639731 | T94: =IF(S9=0, IF(T9=0,0,IF(T9>0,1,-1)), (T9-S9)/ABS(S9) ) -> 1 | U94: =IF(T9=0, IF(U9=0,0,IF(U9>0,1,-1)), (U9-T9)/ABS(T9) ) -> 0.03968254 | V94: =IF(U9=0, IF(V9=0,0,IF(V9>0,1,-1)), (V9-U9)/ABS(U9) ) -> 0.0025445293 | W94: =IF(V9=0, IF(W9=0,0,IF(W9>0,1,-1)), (W9-V9)/ABS(V9) ) -> 0.04822335 | X94: =IF(W9=0, IF(X9=0,0,IF(X9>0,1,-1)), (X9-W9)/ABS(W9) ) -> 0.0072639225 | Y94: =IF(X9=0, IF(Y9=0,0,IF(Y9>0,1,-1)), (Y9-X9)/ABS(X9) ) -> 0.0096153846 | Z94: =IF(Y9=0, IF(Z9=0,0,IF(Z9>0,1,-1)), (Z9-Y9)/ABS(Y9) ) -> 0.0023809524 | AA94: =IF(Z9=0, IF(AA9=0,0,IF(AA9>0,1,-1)), (AA9-Z9)/ABS(Z9) ) -> 0.10213777
B95: General and administrative | M95: =IF(L10=0, IF(M10=0,0,IF(M10>0,1,-1)), (M10-L10)/ABS(L10) ) -> 1 | N95: =IF(M10=0, IF(N10=0,0,IF(N10>0,1,-1)), (N10-M10)/ABS(M10) ) -> -0.06993007 | O95: =IF(N10=0, IF(O10=0,0,IF(O10>0,1,-1)), (O10-N10)/ABS(N10) ) -> 0.16541353 | P95: =IF(O10=0, IF(P10=0,0,IF(P10>0,1,-1)), (P10-O10)/ABS(O10) ) -> 0.048387097 | Q95: =IF(P10=0, IF(Q10=0,0,IF(Q10>0,1,-1)), (Q10-P10)/ABS(P10) ) -> 0.066153846 | T95: =IF(S10=0, IF(T10=0,0,IF(T10>0,1,-1)), (T10-S10)/ABS(S10) ) -> 1 | U95: =IF(T10=0, IF(U10=0,0,IF(U10>0,1,-1)), (U10-T10)/ABS(T10) ) -> 0.074534161 | V95: =IF(U10=0, IF(V10=0,0,IF(V10>0,1,-1)), (V10-U10)/ABS(U10) ) -> -0.063583815 | W95: =IF(V10=0, IF(W10=0,0,IF(W10>0,1,-1)), (W10-V10)/ABS(V10) ) -> 0.037037037 | X95: =IF(W10=0, IF(X10=0,0,IF(X10>0,1,-1)), (X10-W10)/ABS(W10) ) -> 0.023809524 | Y95: =IF(X10=0, IF(Y10=0,0,IF(Y10>0,1,-1)), (Y10-X10)/ABS(X10) ) -> 0.11046512 | Z95: =IF(Y10=0, IF(Z10=0,0,IF(Z10>0,1,-1)), (Z10-Y10)/ABS(Y10) ) -> -0.15183246 | AA95: =IF(Z10=0, IF(AA10=0,0,IF(AA10>0,1,-1)), (AA10-Z10)/ABS(Z10) ) -> 0.10493827
B96: OpEx | M96: =IF(L12=0, IF(M12=0,0,IF(M12>0,1,-1)), (M12-L12)/ABS(L12) ) -> 1 | N96: =IF(M12=0, IF(N12=0,0,IF(N12>0,1,-1)), (N12-M12)/ABS(M12) ) -> 0.055522388 | O96: =IF(N12=0, IF(O12=0,0,IF(O12>0,1,-1)), (O12-N12)/ABS(N12) ) -> 0.091063348 | P96: =IF(O12=0, IF(P12=0,0,IF(P12>0,1,-1)), (P12-O12)/ABS(O12) ) -> 0.088387766 | Q96: =IF(P12=0, IF(Q12=0,0,IF(Q12>0,1,-1)), (Q12-P12)/ABS(P12) ) -> 0.18552036 | T96: =IF(S12=0, IF(T12=0,0,IF(T12>0,1,-1)), (T12-S12)/ABS(S12) ) -> 1 | U96: =IF(T12=0, IF(U12=0,0,IF(U12>0,1,-1)), (U12-T12)/ABS(T12) ) -> 0.038997214 | V96: =IF(U12=0, IF(V12=0,0,IF(V12>0,1,-1)), (V12-U12)/ABS(U12) ) -> 0.10813226 | W96: =IF(V12=0, IF(W12=0,0,IF(W12>0,1,-1)), (W12-V12)/ABS(V12) ) -> -0.064516129 | X96: =IF(W12=0, IF(X12=0,0,IF(X12>0,1,-1)), (X12-W12)/ABS(W12) ) -> 0.05 | Y96: =IF(X12=0, IF(Y12=0,0,IF(Y12>0,1,-1)), (Y12-X12)/ABS(X12) ) -> 0.11658456 | Z96: =IF(Y12=0, IF(Z12=0,0,IF(Z12>0,1,-1)), (Z12-Y12)/ABS(Y12) ) -> -0.10441176 | AA96: =IF(Z12=0, IF(AA12=0,0,IF(AA12>0,1,-1)), (AA12-Z12)/ABS(Z12) ) -> 0.043513957
B97: Operating income | M97: =IF(L13=0, IF(M13=0,0,IF(M13>0,1,-1)), (M13-L13)/ABS(L13) ) -> 1 | N97: =IF(M13=0, IF(N13=0,0,IF(N13>0,1,-1)), (N13-M13)/ABS(M13) ) -> 0.60032362 | O97: =IF(N13=0, IF(O13=0,0,IF(O13>0,1,-1)), (O13-N13)/ABS(N13) ) -> 0.14054601 | P97: =IF(O13=0, IF(P13=0,0,IF(P13>0,1,-1)), (P13-O13)/ABS(O13) ) -> 0.20035461 | Q97: =IF(P13=0, IF(Q13=0,0,IF(Q13>0,1,-1)), (Q13-P13)/ABS(P13) ) -> 0.16543575 | T97: =IF(S13=0, IF(T13=0,0,IF(T13>0,1,-1)), (T13-S13)/ABS(S13) ) -> 1 | U97: =IF(T13=0, IF(U13=0,0,IF(U13>0,1,-1)), (U13-T13)/ABS(T13) ) -> 0.057803468 | V97: =IF(U13=0, IF(V13=0,0,IF(V13>0,1,-1)), (V13-U13)/ABS(U13) ) -> -0.36338798 | W97: =IF(V13=0, IF(W13=0,0,IF(W13>0,1,-1)), (W13-V13)/ABS(V13) ) -> 0.9055794 | X97: =IF(W13=0, IF(X13=0,0,IF(X13>0,1,-1)), (X13-W13)/ABS(W13) ) -> 0.058558559 | Y97: =IF(X13=0, IF(Y13=0,0,IF(Y13>0,1,-1)), (Y13-X13)/ABS(X13) ) -> -0.082978723 | Z97: =IF(Y13=0, IF(Z13=0,0,IF(Z13>0,1,-1)), (Z13-Y13)/ABS(Y13) ) -> 0.25522042 | AA97: =IF(Z13=0, IF(AA13=0,0,IF(AA13>0,1,-1)), (AA13-Z13)/ABS(Z13) ) -> 0.10720887
B98: Income before taxes | M98: =IF(L16=0, IF(M16=0,0,IF(M16>0,1,-1)), (M16-L16)/ABS(L16) ) -> 1 | N98: =IF(M16=0, IF(N16=0,0,IF(N16>0,1,-1)), (N16-M16)/ABS(M16) ) -> 0.67433628 | O98: =IF(N16=0, IF(O16=0,0,IF(O16>0,1,-1)), (O16-N16)/ABS(N16) ) -> 0.20084567 | P98: =IF(O16=0, IF(P16=0,0,IF(P16>0,1,-1)), (P16-O16)/ABS(O16) ) -> 0.21830986 | Q98: =IF(P16=0, IF(Q16=0,0,IF(Q16>0,1,-1)), (Q16-P16)/ABS(P16) ) -> 0.15823699 | T98: =IF(S16=0, IF(T16=0,0,IF(T16>0,1,-1)), (T16-S16)/ABS(S16) ) -> 1 | U98: =IF(T16=0, IF(U16=0,0,IF(U16>0,1,-1)), (U16-T16)/ABS(T16) ) -> 0.05982906 | V98: =IF(U16=0, IF(V16=0,0,IF(V16>0,1,-1)), (V16-U16)/ABS(U16) ) -> -0.37096774 | W98: =IF(V16=0, IF(W16=0,0,IF(W16>0,1,-1)), (W16-V16)/ABS(V16) ) -> 0.94871795 | X98: =IF(W16=0, IF(X16=0,0,IF(X16>0,1,-1)), (X16-W16)/ABS(W16) ) -> 0.026315789 | Y98: =IF(X16=0, IF(Y16=0,0,IF(Y16>0,1,-1)), (Y16-X16)/ABS(X16) ) -> -0.049145299 | Z98: =IF(Y16=0, IF(Z16=0,0,IF(Z16>0,1,-1)), (Z16-Y16)/ABS(Y16) ) -> 0.34606742 | AA98: =IF(Z16=0, IF(AA16=0,0,IF(AA16>0,1,-1)), (AA16-Z16)/ABS(Z16) ) -> -0.010016694
B99: Net income | M99: =IF(L19=0, IF(M19=0,0,IF(M19>0,1,-1)), (M19-L19)/ABS(L19) ) -> 1 | N99: =IF(M19=0, IF(N19=0,0,IF(N19>0,1,-1)), (N19-M19)/ABS(M19) ) -> 0.65593561 | O99: =IF(N19=0, IF(O19=0,0,IF(O19>0,1,-1)), (O19-N19)/ABS(N19) ) -> 0.10085055 | P99: =IF(O19=0, IF(P19=0,0,IF(P19>0,1,-1)), (P19-O19)/ABS(O19) ) -> 0.22737307 | Q99: =IF(P19=0, IF(Q19=0,0,IF(Q19>0,1,-1)), (Q19-P19)/ABS(P19) ) -> 0.010791367 | T99: =IF(S19=0, IF(T19=0,0,IF(T19>0,1,-1)), (T19-S19)/ABS(S19) ) -> 1 | U99: =IF(T19=0, IF(U19=0,0,IF(U19>0,1,-1)), (U19-T19)/ABS(T19) ) -> 0.10181818 | V99: =IF(U19=0, IF(V19=0,0,IF(V19>0,1,-1)), (V19-U19)/ABS(U19) ) -> -0.49834983 | W99: =IF(V19=0, IF(W19=0,0,IF(W19>0,1,-1)), (W19-V19)/ABS(V19) ) -> 1.0592105 | X99: =IF(W19=0, IF(X19=0,0,IF(X19>0,1,-1)), (X19-W19)/ABS(W19) ) -> 0.095846645 | Y99: =IF(X19=0, IF(Y19=0,0,IF(Y19>0,1,-1)), (Y19-X19)/ABS(X19) ) -> -0.078717201 | Z99: =IF(Y19=0, IF(Z19=0,0,IF(Z19>0,1,-1)), (Z19-Y19)/ABS(Y19) ) -> 0.55379747 | AA99: =IF(Z19=0, IF(AA19=0,0,IF(AA19>0,1,-1)), (AA19-Z19)/ABS(Z19) ) -> 0.0020366599
B101: Margins
B102: Gross margin | M102: =M7/M5 -> 0.90469676 | N102: =N7/N5 -> 0.9040959 | O102: =O7/O5 -> 0.9070402 | P102: =P7/P5 -> 0.905725 | Q102: =Q7/Q5 -> 0.90979739 | T102: =T7/T5 -> 0.90636943 | U102: =U7/U5 -> 0.90604027 | V102: =V7/V5 -> 0.90202082 | W102: =W7/W5 -> 0.90981282 | X102: =X7/X5 -> 0.91095521 | Y102: =Y7/Y5 -> 0.91517629 | Z102: =Z7/Z5 -> 0.90951396 | AA102: =AA7/AA5 -> 0.91397849 | AC102: =AC7/AC5 -> 0.91245186
B103: Operating margin | M103: =M13/M5 -> 0.14090287 | N103: =N13/N5 -> 0.1976024 | O103: =O13/O5 -> 0.20520284 | P103: =P13/P5 -> 0.22084489 | Q103: =Q13/Q5 -> 0.21898418 | T103: =T13/T5 -> 0.22038217 | U103: =U13/U5 -> 0.22330689 | V103: =V13/V5 -> 0.14268218 | W103: =W13/W5 -> 0.25184345 | X103: =X13/X5 -> 0.25364274 | Y103: =Y13/Y5 -> 0.22023505 | Z103: =Z13/Z5 -> 0.27973113 | AA103: =AA13/AA5 -> 0.29276637 | AC103: =AC13/AC5 -> 0.26200257
B104: Net margin | M104: =M112/M5 -> 0.11331509 | N104: =N112/N5 -> 0.16443556 | O104: =O112/O5 -> 0.16481717 | P104: =P112/P5 -> 0.18137335 | Q104: =Q112/Q5 -> 0.15598113 | T104: =T112/T5 -> 0.17515924 | U104: =U112/U5 -> 0.18486882 | V104: =V112/V5 -> 0.09308022 | W104: =W112/W5 -> 0.17753829 | X104: =X112/X5 -> 0.18510523 | Y104: =Y112/Y5 -> 0.16147164 | Z104: =Z112/Z5 -> 0.25387797 | AA104: =AA112/AA5 -> 0.24046921 | AC104: =AC112/AC5 -> 0.21078306
B106: Adjustments
B107: Tax rate | C107: =IF(AND(C84>=0,C13>=0),C84,0) -> 0 | D107: =IF(AND(D84>=0,D13>=0),D84,0) -> 0 | E107: =IF(AND(E84>=0,E13>=0),E84,0) -> 0 | F107: =IF(AND(F84>=0,F13>=0),F84,0) -> 0 | G107: =IF(AND(G84>=0,G13>=0),G84,0) -> 0 | H107: =IF(AND(H84>=0,H13>=0),H84,0) -> 0 | I107: =IF(AND(I84>=0,I13>=0),I84,0) -> 0 | J107: =IF(AND(J84>=0,J13>=0),J84,0) -> 0 | ... Q107: =IF(AND(Q84>=0,Q13>=0),Q84,0) -> 0.29881472 | T107: =IF(AND(T84>=0,T13>=0),T84,0) -> 0.21652422 | U107: =IF(AND(U84>=0,U13>=0),U84,0) -> 0.18548387 | V107: =IF(AND(V84>=0,V13>=0),V84,0) -> 0.35042735 | W107: =IF(AND(W84>=0,W13>=0),W84,0) -> 0.31359649 | X107: =IF(AND(X84>=0,X13>=0),X84,0) -> 0.26709402 | Y107: =IF(AND(Y84>=0,Y13>=0),Y84,0) -> 0.28988764 | Z107: =IF(AND(Z84>=0,Z13>=0),Z84,0) -> 0.1803005 | AA107: =IF(AND(AA84>=0,AA13>=0),AA84,0) -> 0.1703204 | AC107: =IF(AND(AC84>=0,AC13>=0),AC84,0) -> 0.21995249
B108: Cash | M108: =M30+M35 -> 1809 | N108: =N30+N35 -> 2174 | O108: =O30+O35 -> 2480 | P108: =P30+P35 -> 2153 | Q108: =Q30+Q35 -> 2973 | T108: =T30+T35 -> 1977 | U108: =U30+U35 -> 2153 | V108: =V30+V35 -> 2301 | W108: =W30+W35 -> 2518 | X108: =X30+X35 -> 2591 | Y108: =Y30+Y35 -> 2973 | Z108: =Z30+Z35 -> 3309 | AA108: =AA30+AA35 -> 4357 | AC108: =AA108 -> 4357
B109: Debt | C109: 0 | D109: 0 | E109: 0 | F109: 0 | G109: 0 | H109: 0 | I109: 0 | J109: 0 | K109: 0 | L109: 0 | M109: =M40+M42 -> 2280 | N109: =N40+N42 -> 2281 | O109: =O40+O42 -> 2284 | P109: =P40+P42 -> 2287 | Q109: =Q40+Q42 -> 2483 | T109: =T40+T42 -> 2286 | U109: =U40+U42 -> 2287 | V109: =V40+V42 -> 2288 | W109: =W40+W42 -> 2481 | X109: =X40+X42 -> 2482 | Y109: =Y40+Y42 -> 2483 | Z109: =Z40+Z42 -> 2484 | AA109: =AA40+AA42 -> 3478 | AC109: =AA109 -> 3478
...

Sheet Analysis ->
H5: Links
H6: Overview'!B3
H7: Financials ->'!B13
H8: Analysis ->'!B13
H9: Forecast ->'!B13
H10: Valuation ->'!B13
B13: Analysis ->

Sheet Basic
B1: TTM/YTD data
B4: Overview | E4: CAGR
B5: Price | C5: =Overview!C5 -> 233.54 | F5: 5Y | G5: 10Y
B6: Market capitalization | C6: =Statement!AC154 -> 49043.4 | E6: Revenue | F6: =IF(Statement!M5<=0,"N/A",_xlfn.RRI(4,Statement!M5,Statement!Q5)) -> 0.13215635 | G6: =IF(Statement!H5<=0,"N/A",_xlfn.RRI(9,Statement!H5,Statement!Q5)) -> N/A
B7: Enterprise value | C7: =Statement!AC155 -> 48164.4 | E7: Net income | F7: =IF(OR(Statement!M19<=0, Statement!Q19<=0), "N/A", _xlfn.RRI(4, Statement!M19, Statement!Q19)) -> 0.22631624 | G7: =IF(OR(Statement!H19<=0, Statement!Q19<=0), "N/A", _xlfn.RRI(9, Statement!H19, Statement!Q19)) -> N/A
B8: PE | C8: =Statement!AC151 -> 30.21216 | E8: EPS | F8: =IF(OR(Statement!M27<=0, Statement!Q27<=0), "N/A", _xlfn.RRI(4, Statement!M27, Statement!Q27)) -> 0.23612793 | G8: =IF(OR(Statement!H27<=0, Statement!Q27<=0), "N/A", _xlfn.RRI(9, Statement!H27, Statement!Q27)) -> N/A
B9: PS | C9: =Statement!AC152 -> 6.3856252 | E9: Dividend | F9: =IF(Statement!M83<=0,"N/A",_xlfn.RRI(4,Statement!M83,Statement!Q83)) -> N/A | G9: =IF(Statement!H83<=0,"N/A",_xlfn.RRI(9,Statement!H83,Statement!Q83)) -> N/A
B10: PB | C10: =Statement!AC153 -> 14.427981 | E10: Price | F10: =IF(Statement!M118<=0,"N/A",_xlfn.RRI(4,Statement!M118,Statement!Q118)) -> 0.0030684375 | G10: =IF(Statement!H118<=0,"N/A",_xlfn.RRI(9,Statement!H118,Statement!Q118)) -> N/A
B11: EV/Revenue | C11: =Statement!AC156 -> 6.1828498
B12: EV/EBIT | C12: =Statement!AC157 -> 23.598432
B15: Margins | E15: Earnings quality
B16: Gross margin | C16: =Statement!AC102 -> 0.91245186 | E16: Net income | F16: =Statement!AC19 -> 1642
B17: Operating margin | C17: =Statement!AC103 -> 0.26200257 | E17: Operating cash | F17: =Statement!AC60 -> 2896
B18: Net margin | C18: =Statement!AC104 -> 0.21078306 | E18: Cash accruals | F18: =IF(OR(F16<=0, F17<=0),"N/A",F16-F17) -> -1254
B21: DuPont Identity | E21: Performance indicators
B22: Profit Margin (Earnings/Revenue) | C22: =Statement!AC122 -> 0.21078306 | E22: ROA | F22: =C24 -> 0.12647308
B23: Asset Turnover (Revenue/Total assets) | C23: =Statement!AC123 -> 0.6000154 | E23: ROE | F23: =C26 -> 0.48536802
B24: ROA | C24: =Statement!AC124 -> 0.12647308 | E24: ROIC | F24: =Statement!AC141 -> 0.63581348
B25: Equity Multiplier (Total assets/Equity) | C25: =Statement!AC125 -> 3.837718
B26: ROE | C26: =Statement!AC126 -> 0.48536802
B29: Cash conversion cycle | E29: Liquidity ratios
B30: DSO | C30: =Statement!AC142 -> 32.04878 | E30: Debt/Equity | F30: =Statement!AC146 -> 1.0280816
B31: DIO | C31: =Statement!AC143 -> 0 | E31: Net Debt/Equity | F31: =Statement!AC147 -> -0.25982855
B32: DPO | C32: =Statement!AC144 -> 244.58211 | E32: Current ratio | F32: =Statement!AC149 -> 0.85546168
B33: Net trade cycle | C33: =Statement!AC145 -> -212.53333 | E33: Quick ratio | F33: =Statement!AC148 -> 0.76056126
E34: Interest coverage | F34: =Statement!AC150 -> N/A
B37: Earnings yields | E37: Payout ratios
B38: Earnings yield | C38: =Statement!AC163 -> 0.033099255 | E38: Dividend payout ratio | F38: =Statement!AC169 -> 0
B39: FCF yield | C39: =Statement!AC162 -> 0.042778437 | E39: Buyback payout ratio | F39: =Statement!AC170 -> 0.75834128
B40: Dividend yield | C40: =Statement!AC164 -> 0 | E40: Full payout ratio | F40: =Statement!AC171 -> 0.75834128
B41: Buyback yield | C41: =Statement!AC165 -> 0.032440655
B42: Total shareholder yield | C42: =Statement!AC166 -> 0.032440655
B45: Ownership | E45: Cash holdings
B46: Insider ownership | C46: =Statement!AC172 -> 0.0047619048 | E46: Cash per share | F46: =Statement!AC173 -> 20.84689
E47: Net cash per share | F47: =Statement!AC176 -> 4.2057416
E48: Net cash to market cap | F48: =Statement!AC177 -> 0.017922901
B51: Stock based compensation | E51: CapEx usage
B52: Stock based compensation % OCF | C52: =Statement!AC174 -> 0.24378453 | E52: Capex to Revenue | F52: =Statement!AC178 -> 0.011810013
B53: Stock based compensation % Revenue | C53: =Statement!AC175 -> 0.090629012 | E53: CapEx to OCF | F53: =Statement!AC179 -> 0.031767956
E54: CapEx to D&A | F54: =Statement!AC180 -> 0.45771144

Sheet Yearly Analysis
C2: =Statement!M2 -> 31.01.2022 | D2: =Statement!N2 -> 31.01.2023 | E2: =Statement!O2 -> 31.01.2024 | F2: =Statement!P2 -> 31.01.2025 | G2: =Statement!Q2 -> 31.01.2026
C3: =Statement!M3 -> 2022 | D3: =Statement!N3 -> 2023 | E3: =Statement!O3 -> 2024 | F3: =Statement!P3 -> 2025 | G3: =Statement!Q3 -> 2026 | I3: =Statement!AC3 -> TTM/YTD
B5: Overview
B6: Price | C6: =Statement!M117 -> 249.79 | D6: =Statement!N117 -> 215.16 | E6: =Statement!O117 -> 253.81 | F6: =Statement!P117 -> 311.21 | G6: =Statement!Q117 -> 252.87 | I6: =Statement!AC117 -> 233.54
B7: Market capitalization | C7: =Statement!M154 -> 54704.01 | D7: =Statement!N154 -> 46904.88 | E7: =Statement!O154 -> 54822.96 | F7: =Statement!P154 -> 67532.57 | G7: =Statement!Q154 -> 54367.05 | I7: =Statement!AC154 -> 49043.4
B8: Enterprise value | C8: =Statement!M155 -> 55175.01 | D8: =Statement!N155 -> 47011.88 | E8: =Statement!O155 -> 54626.96 | F8: =Statement!P155 -> 67666.57 | G8: =Statement!Q155 -> 53877.05 | I8: =Statement!AC155 -> 48164.4
B9: PE | C9: =Statement!M151 -> 111.51339 | D9: =Statement!N151 -> 56.920635 | E9: =Statement!O151 -> 60.575179 | F9: =Statement!P151 -> 60.783203 | G9: =Statement!Q151 -> 48.349904 | I9: =Statement!AC151 -> 30.21216
B10: PS | C10: =Statement!M152 -> 12.643269 | D10: =Statement!N152 -> 9.3716044 | E10: =Statement!O152 -> 9.9732509 | F10: =Statement!P152 -> 11.014936 | G10: =Statement!Q152 -> 7.5446919 | I10: =Statement!AC152 -> 6.3856252
B11: PB | C11: =Statement!M153 -> 63.845029 | D11: =Statement!N153 -> 40.589135 | E11: =Statement!O153 -> 29.280507 | F11: =Statement!P153 -> 25.528481 | G11: =Statement!Q153 -> 17.688443 | I11: =Statement!AC153 -> 14.427981
B12: EV/Revenue | C12: =Statement!M156 -> 12.579802 | D12: =Statement!N156 -> 9.392983 | E12: =Statement!O156 -> 9.9375951 | F12: =Statement!P156 -> 11.036792 | G12: =Statement!Q156 -> 7.476693 | I12: =Statement!AC156 -> 6.1828498
B13: EV/EBIT | C13: =Statement!M157 -> 89.279951 | D13: =Statement!N157 -> 47.534762 | E13: =Statement!O157 -> 48.428156 | F13: =Statement!P157 -> 49.97531 | G13: =Statement!Q157 -> 34.142617 | I13: =Statement!AC157 -> 23.598432
B15: Margins
B16: Gross margin | C16: =Statement!M102 -> 0.90469676 | D16: =Statement!N102 -> 0.9040959 | E16: =Statement!O102 -> 0.9070402 | F16: =Statement!P102 -> 0.905725 | G16: =Statement!Q102 -> 0.90979739 | I16: =Statement!AC102 -> 0.91245186
B17: Operating margin | C17: =Statement!M103 -> 0.14090287 | D17: =Statement!N103 -> 0.1976024 | E17: =Statement!O103 -> 0.20520284 | F17: =Statement!P103 -> 0.22084489 | G17: =Statement!Q103 -> 0.21898418 | I17: =Statement!AC103 -> 0.26200257
B18: Net margin | C18: =Statement!M104 -> 0.11331509 | D18: =Statement!N104 -> 0.16443556 | E18: =Statement!O104 -> 0.16481717 | F18: =Statement!P104 -> 0.18137335 | G18: =Statement!Q104 -> 0.15598113 | I18: =Statement!AC104 -> 0.21078306
B20: Earnings quality
B21: Net income | C21: =Statement!M19 -> 497 | D21: =Statement!N19 -> 823 | E21: =Statement!O19 -> 906 | F21: =Statement!P19 -> 1112 | G21: =Statement!Q19 -> 1124 | I21: =Statement!AC19 -> 1642
B22: Operating cash | C22: =Statement!M60 -> 1531 | D22: =Statement!N60 -> 2071 | E22: =Statement!O60 -> 1313 | F22: =Statement!P60 -> 1607 | G22: =Statement!Q60 -> 2452 | I22: =Statement!AC60 -> 2896
B23: Cash accruals | C23: =IF(OR(C21<=0, C22<=0),"N/A",C21-C22) -> -1034 | D23: =IF(OR(D21<=0, D22<=0),"N/A",D21-D22) -> -1248 | E23: =IF(OR(E21<=0, E22<=0),"N/A",E21-E22) -> -407 | F23: =IF(OR(F21<=0, F22<=0),"N/A",F21-F22) -> -495 | G23: =IF(OR(G21<=0, G22<=0),"N/A",G21-G22) -> -1328 | I23: =IF(OR(I21<=0, I22<=0),"N/A",I21-I22) -> -1254
B25: DuPont Identity
B26: Profit Margin (Earnings/Revenue) | C26: =Statement!M122 -> 0.11331509 | D26: =Statement!N122 -> 0.16443556 | E26: =Statement!O122 -> 0.16481717 | F26: =Statement!P122 -> 0.18137335 | G26: =Statement!Q122 -> 0.15598113 | I26: =Statement!AC122 -> 0.21078306
B27: Asset Turnover (Revenue/Total assets) | C27: =Statement!M123 -> 0.50958522 | D27: =Statement!N123 -> 0.53030303 | E27: =Statement!O123 -> 0.55458031 | F27: =Statement!P123 -> 0.56595588 | G27: =Statement!Q123 -> 0.57800594 | I27: =Statement!AC123 -> 0.6000154
B28: ROA | C28: =Statement!M124 -> 0.057743697 | D28: =Statement!N124 -> 0.087200678 | E28: =Statement!O124 -> 0.091404358 | F28: =Statement!P124 -> 0.10264931 | G28: =Statement!Q124 -> 0.090158017 | I28: =Statement!AC124 -> 0.12647308
B29: Equity Multiplier (Total assets/Equity) | C29: =Statement!M125 -> 10.137809 | D29: =Statement!N125 -> 8.2427948 | E29: =Statement!O125 -> 5.3433962 | F29: =Statement!P125 -> 4.1331553 | G29: =Statement!Q125 -> 4.0942529 | I29: =Statement!AC125 -> 3.837718
B30: ROE | C30: =Statement!M126 -> 0.58539458 | D30: =Statement!N126 -> 0.71877729 | E30: =Statement!O126 -> 0.4884097 | F30: =Statement!P126 -> 0.42426555 | G30: =Statement!Q126 -> 0.36912972 | I30: =Statement!AC126 -> 0.48536802
B32: Performance Indicators
B33: ROA | C33: =C28 -> 0.057743697 | D33: =D28 -> 0.087200678 | E33: =E28 -> 0.091404358 | F33: =F28 -> 0.10264931 | G33: =G28 -> 0.090158017 | I33: =I28 -> 0.12647308
B34: ROE | C34: =C30 -> 0.58539458 | D34: =D30 -> 0.71877729 | E34: =E30 -> 0.4884097 | F34: =F30 -> 0.42426555 | G34: =G30 -> 0.36912972 | I34: =I30 -> 0.48536802
B35: ROIC | C35: =Statement!M141 -> 0.41183427 | D35: =Statement!N141 -> 0.68722771 | E35: =Statement!O141 -> 0.54226626 | F35: =Statement!P141 -> 0.39488056 | G35: =Statement!Q141 -> 0.43306081 | I35: =Statement!AC141 -> 0.63581348
B37: Cash conversion cycle
B38: DSO | C38: =Statement!M142 -> 59.585043 | D38: =Statement!N142 -> 70.082917 | E38: =Statement!O142 -> 58.166273 | F38: =Statement!P142 -> 60.009786 | G38: =Statement!Q142 -> 72.888565 | I38: =Statement!AC142 -> 32.04878
B39: DIO | C39: =Statement!M143 -> 0 | D39: =Statement!N143 -> 0 | E39: =Statement!O143 -> 0 | F39: =Statement!P143 -> 0 | G39: =Statement!Q143 -> 0 | I39: =Statement!AC143 -> 0
B40: DPO | C40: =Statement!M144 -> 105.65789 | D40: =Statement!N144 -> 77.5625 | E40: =Statement!O144 -> 71.428571 | F40: =Statement!P144 -> 152.82007 | G40: =Statement!Q144 -> 236.96923 | I40: =Statement!AC144 -> 244.58211
B41: Net trade cycle | C41: =Statement!M145 -> -46.072851 | D41: =Statement!N145 -> -7.4795829 | E41: =Statement!O145 -> -13.262299 | F41: =Statement!P145 -> -92.810283 | G41: =Statement!Q145 -> -164.08067 | I41: =Statement!AC145 -> -212.53333
B43: Liquidity ratios
B44: Debt/Equity | C44: =Statement!M146 -> 2.6855124 | D44: =Statement!N146 -> 1.9921397 | E44: =Statement!O146 -> 1.2312668 | F44: =Statement!P146 -> 0.87256772 | G44: =Statement!Q146 -> 0.81543514 | I44: =Statement!AC146 -> 1.0280816
B45: Net Debt/Equity | C45: =Statement!M147 -> 0.55477032 | D45: =Statement!N147 -> 0.093449782 | E45: =Statement!O147 -> -0.10566038 | F45: =Statement!P147 -> 0.051125525 | G45: =Statement!Q147 -> -0.16091954 | I45: =Statement!AC147 -> -0.25982855
B46: Quick ratio | C46: =Statement!M148 -> 0.62983288 | D46: =Statement!N148 -> 0.78375 | E46: =Statement!O148 -> 0.77131694 | F46: =Statement!P148 -> 0.61366725 | G46: =Statement!Q148 -> 0.75964187 | I46: =Statement!AC148 -> 0.76056126
B47: Current ratio | C47: =Statement!M149 -> 0.68944874 | D47: =Statement!N149 -> 0.83525 | E47: =Statement!O149 -> 0.82256952 | F47: =Statement!P149 -> 0.67598525 | G47: =Statement!Q149 -> 0.85089532 | I47: =Statement!AC149 -> 0.85546168
B48: Interest coverage | C48: =Statement!M150 -> 11.660377 | D48: =Statement!N150 -> 23 | E48: =Statement!O150 -> N/A | F48: =Statement!P150 -> N/A | G48: =Statement!Q150 -> N/A | I48: =Statement!AC150 -> N/A
B50: Earnings yields
B51: Earnings yield | C51: =Statement!M163 -> 0.0089675327 | D51: =Statement!N163 -> 0.017568321 | E51: =Statement!O163 -> 0.016508412 | F51: =Statement!P163 -> 0.016451913 | G51: =Statement!Q163 -> 0.020682564 | I51: =Statement!AC163 -> 0.033099255
B52: FCF yield | C52: =Statement!M162 -> 0.016616698 | D52: =Statement!N162 -> 0.029165409 | E52: =Statement!O162 -> 0.010014053 | F52: =Statement!P162 -> 0.012171905 | G52: =Statement!Q162 -> 0.029208868 | I52: =Statement!AC162 -> 0.042778437
B53: Dividend yield | C53: =Statement!M164 -> 0 | D53: =Statement!N164 -> 0 | E53: =Statement!O164 -> 0 | F53: =Statement!P164 -> 0 | G53: =Statement!Q164 -> 0 | I53: =Statement!AC164 -> 0
B54: Buyback yield | C54: =Statement!M165 -> 0.019724331 | D54: =Statement!N165 -> 0.023473037 | E54: =Statement!O165 -> 0.014501224 | F54: =Statement!P165 -> 0.012616135 | G54: =Statement!Q165 -> 0.025787678 | I54: =Statement!AC165 -> 0.032440655
B55: Total shareholder yield | C55: =Statement!M166 -> 0.019724331 | D55: =Statement!N166 -> 0.023473037 | E55: =Statement!O166 -> 0.014501224 | F55: =Statement!P166 -> 0.012616135 | G55: =Statement!Q166 -> 0.025787678 | I55: =Statement!AC166 -> 0.032440655
B57: Payout ratios
B58: Dividend payout ratio | C58: =Statement!M169 -> 0 | D58: =Statement!N169 -> 0 | E58: =Statement!O169 -> 0 | F58: =Statement!P169 -> 0 | G58: =Statement!Q169 -> 0 | I58: =Statement!AC169 -> 0
B59: Buyback payout ratio | C59: =Statement!M170 -> 1.1870187 | D59: =Statement!N170 -> 0.80482456 | E59: =Statement!O170 -> 1.4480874 | F59: =Statement!P170 -> 1.0364964 | G59: =Statement!Q170 -> 0.88287154 | I59: =Statement!AC170 -> 0.75834128
B60: Full payout ratio | C60: =Statement!M171 -> 1.1870187 | D60: =Statement!N171 -> 0.80482456 | E60: =Statement!O171 -> 1.4480874 | F60: =Statement!P171 -> 1.0364964 | G60: =Statement!Q171 -> 0.88287154 | I60: =Statement!AC171 -> 0.75834128
B62: Ownership
B63: Insider ownership | C63: =Statement!M172 -> 0.00456621 | D63: =Statement!N172 -> 0.004587156 | E63: =Statement!O172 -> 0.0046296296 | F63: =Statement!P172 -> 0.0046082949 | G63: =Statement!Q172 -> 0.0046511628 | I63: =Statement!AC172 -> 0.0047619048
B65: Cash holdings
B66: Cash per share | C66: =Statement!M173 -> 8.3364055 | D66: =Statement!N173 -> 10.064815 | E66: =Statement!O173 -> 11.588785 | F66: =Statement!P173 -> 10.013953 | G66: =Statement!Q173 -> 13.957746 | I66: =Statement!AC173 -> 20.84689
B67: Net cash per share | C67: =Statement!M176 -> -2.1705069 | D67: =Statement!N176 -> -0.49537037 | E67: =Statement!O176 -> 0.91588785 | F67: =Statement!P176 -> -0.62325581 | G67: =Statement!Q176 -> 2.3004695 | I67: =Statement!AC176 -> 4.2057416
B68: Net cash to market cap | C68: =Statement!M177 -> -0.0086099721 | D68: =Statement!N177 -> -0.0022812125 | E68: =Statement!O177 -> 0.0035751444 | F68: =Statement!P177 -> -0.0019842278 | G68: =Statement!Q177 -> 0.009012812 | I68: =Statement!AC177 -> 0.017922901
B70: Stock Based Compensation
B71: Stock based compensation % OCF | C71: =Statement!M174 -> 0.36250816 | D71: =Statement!N174 -> 0.31723805 | E71: =Statement!O174 -> 0.53541508 | F71: =Statement!P174 -> 0.42501556 | G71: =Statement!Q174 -> 0.32137031 | I71: =Statement!AC174 -> 0.24378453
B72: Stock based compensation % Revenue | C72: =Statement!M175 -> 0.12653899 | D72: =Statement!N175 -> 0.13126873 | E72: =Statement!O175 -> 0.12788794 | F72: =Statement!P175 -> 0.11140108 | G72: =Statement!Q175 -> 0.10935332 | I72: =Statement!AC175 -> 0.090629012
B74: CapEx Usage
B75: Capex to Revenue | C75: =Statement!M178 -> 0.015275878 | D75: =Statement!N178 -> 0.0091908092 | E75: =Statement!O178 -> 0.011096962 | F75: =Statement!P178 -> 0.016636764 | G75: =Statement!Q178 -> 0.010546767 | I75: =Statement!AC178 -> 0.011810013
B76: CapEx to OCF | C76: =Statement!M179 -> 0.043762247 | D76: =Statement!N179 -> 0.022211492 | E76: =Statement!O179 -> 0.046458492 | F76: =Statement!P179 -> 0.063472309 | G76: =Statement!Q179 -> 0.030995106 | I76: =Statement!AC179 -> 0.031767956
B77: CapEx to D&A | C77: =Statement!M180 -> 0.4527027 | D77: =Statement!N180 -> 0.30666667 | E77: =Statement!O180 -> 0.43884892 | F77: =Statement!P180 -> 0.56666667 | G77: =Statement!Q180 -> 0.38974359 | I77: =Statement!AC180 -> 0.45771144
B79: Growth rates
B80: Revenue | C80: =Statement!M90 -> 1 | D80: =Statement!N90 -> 0.14113087 | E80: =Statement!O90 -> 0.098301698 | F80: =Statement!P90 -> 0.11533564 | G80: =Statement!Q90 -> 0.17533844
B81: COGS | C81: =Statement!M91 -> 1 | D81: =Statement!N91 -> 0.14832536 | E81: =Statement!O91 -> 0.064583333 | F81: =Statement!P91 -> 0.13111546 | G81: =Statement!Q91 -> 0.12456747
B82: Gross Profit | C82: =Statement!M92 -> 1 | D82: =Statement!N92 -> 0.14037298 | E82: =Statement!O92 -> 0.10187845 | F82: =Statement!P92 -> 0.11371841 | G82: =Statement!Q92 -> 0.18062309
B83: OpEx | C83: =Statement!M96 -> 1 | D83: =Statement!N96 -> 0.055522388 | E83: =Statement!O96 -> 0.091063348 | F83: =Statement!P96 -> 0.088387766 | G83: =Statement!Q96 -> 0.18552036
B84: Operating Income | C84: =Statement!M97 -> 1 | D84: =Statement!N97 -> 0.60032362 | E84: =Statement!O97 -> 0.14054601 | F84: =Statement!P97 -> 0.20035461 | G84: =Statement!Q97 -> 0.16543575
B85: Net Income | C85: =Statement!M99 -> 1 | D85: =Statement!N99 -> 0.65593561 | E85: =Statement!O99 -> 0.10085055 | F85: =Statement!P99 -> 0.22737307 | G85: =Statement!Q99 -> 0.010791367
B88: Growth rates breakdown
B89: =Statement!B188 -> Subscription | C89: =Statement!M203 -> 1 | D89: =Statement!N203 -> 0.14023211 | E89: =Statement!O203 -> 0.096268024 | F89: =Statement!P203 -> 0.11373308 | G89: =Statement!Q203 -> 0.1767975
B90: =Statement!B189 -> Other | C90: =Statement!M204 -> 1 | D90: =Statement!N204 -> 0.156 | E90: =Statement!O204 -> 0.13148789 | F90: =Statement!P204 -> 0.14067278 | G90: =Statement!Q204 -> 0.15281501
B92: Other growth rates
B93: Dividends | C93: =Statement!M214 -> 0 | D93: =Statement!N214 -> 0 | E93: =Statement!O214 -> 0 | F93: =Statement!P214 -> 0 | G93: =Statement!Q214 -> 0

Sheet Quarter analysis
C3: Latest 2 quarters | F3: YoY
C4: =Statement!Z2 -> 30.04.2026 | D4: =Statement!AA2 -> 31.07.2026 | F4: =Statement!W2 -> 31.07.2025 | G4: =Statement!AA2 -> 31.07.2026
B5: Income statement growth | C5: =Statement!Z3 -> Q1 2027 | D5: =Statement!AA3 -> Q2 2027 | F5: =Statement!W3 -> Q2 2026 | G5: =Statement!AA3 -> Q2 2027
B6: Revenue | C6: =Statement!Z5 -> 1934 | D6: =Statement!AA5 -> 2046 | F6: =Statement!W5 -> 1763 | G6: =Statement!AA5 -> 2046
B7: Growth | C7: =Statement!AA90 -> 0.057911065 | F7: =IF(F6=0, IF(G6=0,0,IF(G6>0,1,-1)), (G6-F6)/ABS(F6) ) -> 0.16052184
B8: COGS | C8: =Statement!Z6 -> 175 | D8: =Statement!AA6 -> 176 | F8: =Statement!W6 -> 159 | G8: =Statement!AA6 -> 176
B9: Growth | C9: =Statement!AA91 -> 0.0057142857 | F9: =IF(F8=0, IF(G8=0,0,IF(G8>0,1,-1)), (G8-F8)/ABS(F8) ) -> 0.10691824
B10: Gross Profit | C10: =Statement!Z7 -> 1759 | D10: =Statement!AA7 -> 1870 | F10: =Statement!W7 -> 1604 | G10: =Statement!AA7 -> 1870
B11: Growth | C11: =Statement!AA92 -> 0.063104036 | F11: =IF(F10=0, IF(G10=0,0,IF(G10>0,1,-1)), (G10-F10)/ABS(F10) ) -> 0.16583541
B12: OpEx | C12: =Statement!Z12 -> 1218 | D12: =Statement!AA12 -> 1271 | F12: =Statement!W12 -> 1160 | G12: =Statement!AA12 -> 1271
B13: Growth | C13: =Statement!AA96 -> 0.043513957 | F13: =IF(F12=0, IF(G12=0,0,IF(G12>0,1,-1)), (G12-F12)/ABS(F12) ) -> 0.095689655
B14: Operating profit | C14: =Statement!Z13 -> 541 | D14: =Statement!AA13 -> 599 | F14: =Statement!W13 -> 444 | G14: =Statement!AA13 -> 599
B15: Growth | C15: =Statement!AA97 -> 0.10720887 | F15: =IF(F14=0, IF(G14=0,0,IF(G14>0,1,-1)), (G14-F14)/ABS(F14) ) -> 0.3490991
B16: Net income | C16: =Statement!Z19 -> 491 | D16: =Statement!AA19 -> 492 | F16: =Statement!W19 -> 313 | G16: =Statement!AA19 -> 492
B17: Growth | C17: =Statement!AA99 -> 0.0020366599 | F17: =IF(F16=0, IF(G16=0,0,IF(G16>0,1,-1)), (G16-F16)/ABS(F16) ) -> 0.57188498
B18: Diluted shares outstanding | C18: =Statement!Z23 -> 212 | D18: =Statement!AA23 -> 211 | F18: =Statement!W23 -> 215 | G18: =Statement!AA23 -> 211
B19: Growth | C19: =IF(C18=0, IF(D18=0,0,IF(D18>0,1,-1)), (D18-C18)/ABS(C18) ) -> -0.0047169811 | F19: =IF(F18=0, IF(G18=0,0,IF(G18>0,1,-1)), (G18-F18)/ABS(F18) ) -> -0.018604651
B20: Diluted EPS | C20: =Statement!Z27 -> 2.32 | D20: =Statement!AA27 -> 2.33 | F20: =Statement!W27 -> 1.46 | G20: =Statement!AA27 -> 2.33
B21: Growth | C21: =IF(C20=0, IF(D20=0,0,IF(D20>0,1,-1)), (D20-C20)/ABS(C20) ) -> 0.0043103448 | F21: =IF(F20=0, IF(G20=0,0,IF(G20>0,1,-1)), (G20-F20)/ABS(F20) ) -> 0.59589041
B23: Revenue breakdown | C23: =C5 -> Q1 2027 | D23: =D5 -> Q2 2027 | F23: =F5 -> Q2 2026 | G23: =G5 -> Q2 2027
B24: =Statement!B188 -> Subscription | C24: =Statement!Z188 -> 1836 | D24: =Statement!AA188 -> 1952 | F24: =Statement!W188 -> 1667 | G24: =Statement!AA188 -> 1952
B25: Growth | C25: =IF(C24=0, IF(D24=0,0,IF(D24>0,1,-1)), (D24-C24)/ABS(C24) ) -> 0.063180828 | F25: =IF(F24=0, IF(G24=0,0,IF(G24>0,1,-1)), (G24-F24)/ABS(F24) ) -> 0.17096581
B26: =Statement!B189 -> Other | C26: =Statement!Z189 -> 98 | D26: =Statement!AA189 -> 94 | F26: =Statement!W189 -> 96 | G26: =Statement!AA189 -> 94
B27: Growth | C27: =IF(C26=0, IF(D26=0,0,IF(D26>0,1,-1)), (D26-C26)/ABS(C26) ) -> -0.040816327 | F27: =IF(F26=0, IF(G26=0,0,IF(G26>0,1,-1)), (G26-F26)/ABS(F26) ) -> -0.020833333
B29: =Statement!B195 -> AECO | C29: =Statement!Z195 -> 970 | D29: =Statement!AA195 -> 1029 | F29: =Statement!W195 -> 878 | G29: =Statement!AA195 -> 1029
B30: Growth | C30: =IF(C29=0, IF(D29=0,0,IF(D29>0,1,-1)), (D29-C29)/ABS(C29) ) -> 0.060824742 | F30: =IF(F29=0, IF(G29=0,0,IF(G29>0,1,-1)), (G29-F29)/ABS(F29) ) -> 0.17198178
B31: =Statement!B196 -> AutoCAD and AutoCAD LT | C31: =Statement!Z196 -> 474 | D31: =Statement!AA196 -> 500 | F31: =Statement!W196 -> 440 | G31: =Statement!AA196 -> 500
B32: Growth | C32: =IF(C31=0, IF(D31=0,0,IF(D31>0,1,-1)), (D31-C31)/ABS(C31) ) -> 0.054852321 | F32: =IF(F31=0, IF(G31=0,0,IF(G31>0,1,-1)), (G31-F31)/ABS(F31) ) -> 0.13636364
B33: =Statement!B197 -> Manufacturing | C33: =Statement!Z197 -> 367 | D33: =Statement!AA197 -> 385 | F33: =Statement!W197 -> 334 | G33: =Statement!AA197 -> 385
B34: Growth | C34: =IF(C33=0, IF(D33=0,0,IF(D33>0,1,-1)), (D33-C33)/ABS(C33) ) -> 0.049046322 | F34: =IF(F33=0, IF(G33=0,0,IF(G33>0,1,-1)), (G33-F33)/ABS(F33) ) -> 0.15269461
B35: =Statement!B198 -> Media and Entertainment | C35: =Statement!Z198 -> 86 | D35: =Statement!AA198 -> 92 | F35: =Statement!W198 -> 80 | G35: =Statement!AA198 -> 92
B36: Growth | C36: =IF(C35=0, IF(D35=0,0,IF(D35>0,1,-1)), (D35-C35)/ABS(C35) ) -> 0.069767442 | F36: =IF(F35=0, IF(G35=0,0,IF(G35>0,1,-1)), (G35-F35)/ABS(F35) ) -> 0.15
B37: =Statement!B199 -> Other | C37: =Statement!Z199 -> 37 | D37: =Statement!AA199 -> 40 | F37: =Statement!W199 -> 31 | G37: =Statement!AA199 -> 40
B38: Growth | C38: =IF(C37=0, IF(D37=0,0,IF(D37>0,1,-1)), (D37-C37)/ABS(C37) ) -> 0.081081081 | F38: =IF(F37=0, IF(G37=0,0,IF(G37>0,1,-1)), (G37-F37)/ABS(F37) ) -> 0.29032258

Sheet Graphs Year
C66: =Statement!H2 -> 0 | D66: =Statement!I2 -> 0 | E66: =Statement!J2 -> 0 | F66: =Statement!K2 -> 0 | G66: =Statement!L2 -> 0 | H66: =Statement!M2 -> 31.01.2022 | I66: =Statement!N2 -> 31.01.2023 | J66: =Statement!O2 -> 31.01.2024 | ... L66: =Statement!Q2 -> 31.01.2026
C67: =Statement!H3 -> 0 | D67: =Statement!I3 -> 0 | E67: =Statement!J3 -> 0 | F67: =Statement!K3 -> 0 | G67: =Statement!L3 -> 0 | H67: =Statement!M3 -> 2022 | I67: =Statement!N3 -> 2023 | J67: =Statement!O3 -> 2024 | ... L67: =Statement!Q3 -> 2026
B68: Revenue | C68: =Statement!H5 -> 0 | D68: =Statement!I5 -> 0 | E68: =Statement!J5 -> 0 | F68: =Statement!K5 -> 0 | G68: =Statement!L5 -> 0 | H68: =Statement!M5 -> 4386 | I68: =Statement!N5 -> 5005 | J68: =Statement!O5 -> 5497 | ... L68: =Statement!Q5 -> 7206
B69: Operating income | C69: =Statement!H13 -> 0 | D69: =Statement!I13 -> 0 | E69: =Statement!J13 -> 0 | F69: =Statement!K13 -> 0 | G69: =Statement!L13 -> 0 | H69: =Statement!M13 -> 618 | I69: =Statement!N13 -> 989 | J69: =Statement!O13 -> 1128 | ... L69: =Statement!Q13 -> 1578
B70: Net income | C70: =Statement!H19 -> 0 | D70: =Statement!I19 -> 0 | E70: =Statement!J19 -> 0 | F70: =Statement!K19 -> 0 | G70: =Statement!L19 -> 0 | H70: =Statement!M19 -> 497 | I70: =Statement!N19 -> 823 | J70: =Statement!O19 -> 906 | ... L70: =Statement!Q19 -> 1124
B71: FCFE | C71: =Statement!H158 -> 0 | D71: =Statement!I158 -> 0 | E71: =Statement!J158 -> 0 | F71: =Statement!K158 -> 0 | G71: =Statement!L158 -> 0 | H71: =Statement!M158 -> 909 | I71: =Statement!N158 -> 1368 | J71: =Statement!O158 -> 549 | ... L71: =Statement!Q158 -> 1588
B72: FCFF | C72: =Statement!H159 -> 0 | D72: =Statement!I159 -> 0 | E72: =Statement!J159 -> 0 | F72: =Statement!K159 -> 0 | G72: =Statement!L159 -> 0 | H72: =Statement!M159 -> 841.62124 | I72: =Statement!N159 -> 1656.4091 | J72: =Statement!O159 -> 526.61972 | ... L72: =Statement!Q159 -> 724.47037
B73: Gross margin | C73: =Statement!H102 -> 0 | D73: =Statement!I102 -> 0 | E73: =Statement!J102 -> 0 | F73: =Statement!K102 -> 0 | G73: =Statement!L102 -> 0 | H73: =Statement!M102 -> 0.90469676 | I73: =Statement!N102 -> 0.9040959 | J73: =Statement!O102 -> 0.9070402 | ... L73: =Statement!Q102 -> 0.90979739
B74: Operating margin | C74: =Statement!H103 -> 0 | D74: =Statement!I103 -> 0 | E74: =Statement!J103 -> 0 | F74: =Statement!K103 -> 0 | G74: =Statement!L103 -> 0 | H74: =Statement!M103 -> 0.14090287 | I74: =Statement!N103 -> 0.1976024 | J74: =Statement!O103 -> 0.20520284 | ... L74: =Statement!Q103 -> 0.21898418
B75: Net margin | C75: =Statement!H104 -> 0 | D75: =Statement!I104 -> 0 | E75: =Statement!J104 -> 0 | F75: =Statement!K104 -> 0 | G75: =Statement!L104 -> 0 | H75: =Statement!M104 -> 0.11331509 | I75: =Statement!N104 -> 0.16443556 | J75: =Statement!O104 -> 0.16481717 | ... L75: =Statement!Q104 -> 0.15598113
B76: ="Revenue "&Statement!B188 -> Revenue Subscription | C76: =Statement!H188 -> 0 | D76: =Statement!I188 -> 0 | E76: =Statement!J188 -> 0 | F76: =Statement!K188 -> 0 | G76: =Statement!L188 -> 0 | H76: =Statement!M188 -> 4136 | I76: =Statement!N188 -> 4716 | J76: =Statement!O188 -> 5170 | ... L76: =Statement!Q188 -> 6776
B77: ="Revenue "&Statement!B189 -> Revenue Other | C77: =Statement!H189 -> 0 | D77: =Statement!I189 -> 0 | E77: =Statement!J189 -> 0 | F77: =Statement!K189 -> 0 | G77: =Statement!L189 -> 0 | H77: =Statement!M189 -> 250 | I77: =Statement!N189 -> 289 | J77: =Statement!O189 -> 327 | ... L77: =Statement!Q189 -> 430
B78: ="Revenue "&Statement!B195 -> Revenue AECO | C78: =Statement!H195 -> 0 | D78: =Statement!I195 -> 0 | E78: =Statement!J195 -> 0 | F78: =Statement!K195 -> 0 | G78: =Statement!L195 -> 0 | H78: =Statement!M195 -> 1969 | I78: =Statement!N195 -> 2278 | J78: =Statement!O195 -> 2580 | ... L78: =Statement!Q195 -> 3583
B79: ="Revenue "&Statement!B196 -> Revenue AutoCAD and AutoCAD LT | C79: =Statement!H196 -> 0 | D79: =Statement!I196 -> 0 | E79: =Statement!J196 -> 0 | F79: =Statement!K196 -> 0 | G79: =Statement!L196 -> 0 | H79: =Statement!M196 -> 1244 | I79: =Statement!N196 -> 1387 | J79: =Statement!O196 -> 1462 | ... L79: =Statement!Q196 -> 1787
B80: ="Revenue "&Statement!B197 -> Revenue Manufacturing | C80: =Statement!H197 -> 0 | D80: =Statement!I197 -> 0 | E80: =Statement!J197 -> 0 | F80: =Statement!K197 -> 0 | G80: =Statement!L197 -> 0 | H80: =Statement!M197 -> 876 | I80: =Statement!N197 -> 978 | J80: =Statement!O197 -> 1063 | ... L80: =Statement!Q197 -> 1379
B81: ="Revenue "&Statement!B198 -> Revenue Media and Entertainment | C81: =Statement!H198 -> 0 | D81: =Statement!I198 -> 0 | E81: =Statement!J198 -> 0 | F81: =Statement!K198 -> 0 | G81: =Statement!L198 -> 0 | H81: =Statement!M198 -> 259 | I81: =Statement!N198 -> 291 | J81: =Statement!O198 -> 295 | ... L81: =Statement!Q198 -> 332
B82: ="Revenue "&Statement!B199 -> Revenue Other | C82: =Statement!H199 -> 0 | D82: =Statement!I199 -> 0 | E82: =Statement!J199 -> 0 | F82: =Statement!K199 -> 0 | G82: =Statement!L199 -> 0 | H82: =Statement!M199 -> 38 | I82: =Statement!N199 -> 71 | J82: =Statement!O199 -> 97 | ... L82: =Statement!Q199 -> 125
B83: ROA | C83: =Statement!H124 -> 0 | D83: =Statement!I124 -> 0 | E83: =Statement!J124 -> 0 | F83: =Statement!K124 -> 0 | G83: =Statement!L124 -> 0 | H83: =Statement!M124 -> 0.057743697 | I83: =Statement!N124 -> 0.087200678 | J83: =Statement!O124 -> 0.091404358 | ... L83: =Statement!Q124 -> 0.090158017
B84: ROE | C84: =Statement!H126 -> 0 | D84: =Statement!I126 -> 0 | E84: =Statement!J126 -> 0 | F84: =Statement!K126 -> 0 | G84: =Statement!L126 -> 0 | H84: =Statement!M126 -> 0.58539458 | I84: =Statement!N126 -> 0.71877729 | J84: =Statement!O126 -> 0.4884097 | ... L84: =Statement!Q126 -> 0.36912972
B85: ROIC | C85: =Statement!H141 -> 0 | D85: =Statement!I141 -> 0 | E85: =Statement!J141 -> 0 | F85: =Statement!K141 -> 0 | G85: =Statement!L141 -> 0 | H85: =Statement!M141 -> 0.41183427 | I85: =Statement!N141 -> 0.68722771 | J85: =Statement!O141 -> 0.54226626 | ... L85: =Statement!Q141 -> 0.43306081
B86: Price 5y | C86: =Statement!H218 -> 0 | D86: =Statement!I218 -> 0 | E86: =Statement!J218 -> 0 | F86: =Statement!K218 -> 0 | G86: =Statement!L218 -> 0 | H86: =Statement!M218 -> 100 | I86: =Statement!N218 -> 86.136355 | J86: =Statement!O218 -> 101.60935 | ... L86: =Statement!Q218 -> 101.23304
B87: Revenue 5y | C87: =Statement!H219 -> 0 | D87: =Statement!I219 -> 0 | E87: =Statement!J219 -> 0 | F87: =Statement!K219 -> 0 | G87: =Statement!L219 -> 0 | H87: =Statement!M219 -> 100 | I87: =Statement!N219 -> 114.11309 | J87: =Statement!O219 -> 125.3306 | ... L87: =Statement!Q219 -> 164.29549
B88: EPS 5y | C88: =Statement!H220 -> 0 | D88: =Statement!I220 -> 0 | E88: =Statement!J220 -> 0 | F88: =Statement!K220 -> 0 | G88: =Statement!L220 -> 0 | H88: =Statement!M220 -> 100 | I88: =Statement!N220 -> 168.75 | J88: =Statement!O220 -> 187.05357 | ... L88: =Statement!Q220 -> 233.48214

Sheet Graphs Quarter
C55: =Statement!T2 -> 31.10.2024 | D55: =Statement!U2 -> 31.01.2025 | E55: =Statement!V2 -> 30.04.2025 | F55: =Statement!W2 -> 31.07.2025 | G55: =Statement!X2 -> 31.10.2025 | H55: =Statement!Y2 -> 31.01.2026 | I55: =Statement!Z2 -> 30.04.2026 | J55: =Statement!AA2 -> 31.07.2026
C56: =Statement!T3 -> Q3 2025 | D56: =Statement!U3 -> Q4 2025 | E56: =Statement!V3 -> Q1 2026 | F56: =Statement!W3 -> Q2 2026 | G56: =Statement!X3 -> Q3 2026 | H56: =Statement!Y3 -> Q4 2026 | I56: =Statement!Z3 -> Q1 2027 | J56: =Statement!AA3 -> Q2 2027
B57: Revenue | C57: =Statement!T5 -> 1570 | D57: =Statement!U5 -> 1639 | E57: =Statement!V5 -> 1633 | F57: =Statement!W5 -> 1763 | G57: =Statement!X5 -> 1853 | H57: =Statement!Y5 -> 1957 | I57: =Statement!Z5 -> 1934 | J57: =Statement!AA5 -> 2046
B58: Operating income | C58: =Statement!T13 -> 346 | D58: =Statement!U13 -> 366 | E58: =Statement!V13 -> 233 | F58: =Statement!W13 -> 444 | G58: =Statement!X13 -> 470 | H58: =Statement!Y13 -> 431 | I58: =Statement!Z13 -> 541 | J58: =Statement!AA13 -> 599
B59: Net income | C59: =Statement!T19 -> 275 | D59: =Statement!U19 -> 303 | E59: =Statement!V19 -> 152 | F59: =Statement!W19 -> 313 | G59: =Statement!X19 -> 343 | H59: =Statement!Y19 -> 316 | I59: =Statement!Z19 -> 491 | J59: =Statement!AA19 -> 492
B60: Gross margin | C60: =Statement!T102 -> 0.90636943 | D60: =Statement!U102 -> 0.90604027 | E60: =Statement!V102 -> 0.90202082 | F60: =Statement!W102 -> 0.90981282 | G60: =Statement!X102 -> 0.91095521 | H60: =Statement!Y102 -> 0.91517629 | I60: =Statement!Z102 -> 0.90951396 | J60: =Statement!AA102 -> 0.91397849
B61: Operating margin | C61: =Statement!T103 -> 0.22038217 | D61: =Statement!U103 -> 0.22330689 | E61: =Statement!V103 -> 0.14268218 | F61: =Statement!W103 -> 0.25184345 | G61: =Statement!X103 -> 0.25364274 | H61: =Statement!Y103 -> 0.22023505 | I61: =Statement!Z103 -> 0.27973113 | J61: =Statement!AA103 -> 0.29276637
B62: Net margin | C62: =Statement!T104 -> 0.17515924 | D62: =Statement!U104 -> 0.18486882 | E62: =Statement!V104 -> 0.09308022 | F62: =Statement!W104 -> 0.17753829 | G62: =Statement!X104 -> 0.18510523 | H62: =Statement!Y104 -> 0.16147164 | I62: =Statement!Z104 -> 0.25387797 | J62: =Statement!AA104 -> 0.24046921
B63: ="Revenue "&Statement!B188 -> Revenue Subscription | C63: =Statement!T188 -> 1466 | D63: =Statement!U188 -> 1532 | E63: =Statement!V188 -> 1540 | F63: =Statement!W188 -> 1667 | G63: =Statement!X188 -> 1742 | H63: =Statement!Y188 -> 1827 | I63: =Statement!Z188 -> 1836 | J63: =Statement!AA188 -> 1952
B64: ="Revenue "&Statement!B189 -> Revenue Other | C64: =Statement!T189 -> 104 | D64: =Statement!U189 -> 107 | E64: =Statement!V189 -> 93 | F64: =Statement!W189 -> 96 | G64: =Statement!X189 -> 111 | H64: =Statement!Y189 -> 130 | I64: =Statement!Z189 -> 98 | J64: =Statement!AA189 -> 94
B65: ="Revenue "&Statement!B195 -> Revenue AECO | C65: =Statement!T195 -> 751 | D65: =Statement!U195 -> 799 | E65: =Statement!V195 -> 809 | F65: =Statement!W195 -> 878 | G65: =Statement!X195 -> 921 | H65: =Statement!Y195 -> 975 | I65: =Statement!Z195 -> 970 | J65: =Statement!AA195 -> 1029
B66: ="Revenue "&Statement!B196 -> Revenue AutoCAD and AutoCAD LT | C66: =Statement!T196 -> 398 | D66: =Statement!U196 -> 409 | E66: =Statement!V196 -> 411 | F66: =Statement!W196 -> 440 | G66: =Statement!X196 -> 458 | H66: =Statement!Y196 -> 478 | I66: =Statement!Z196 -> 474 | J66: =Statement!AA196 -> 500
B67: ="Revenue "&Statement!B197 -> Revenue Manufacturing | C67: =Statement!T197 -> 307 | D67: =Statement!U197 -> 318 | E67: =Statement!V197 -> 309 | F67: =Statement!W197 -> 334 | G67: =Statement!X197 -> 355 | H67: =Statement!Y197 -> 381 | I67: =Statement!Z197 -> 367 | J67: =Statement!AA197 -> 385
B68: ="Revenue "&Statement!B198 -> Revenue Media and Entertainment | C68: =Statement!T198 -> 83 | D68: =Statement!U198 -> 84 | E68: =Statement!V198 -> 76 | F68: =Statement!W198 -> 80 | G68: =Statement!X198 -> 86 | H68: =Statement!Y198 -> 90 | I68: =Statement!Z198 -> 86 | J68: =Statement!AA198 -> 92
B69: ="Revenue "&Statement!B199 -> Revenue Other | C69: =Statement!T199 -> 31 | D69: =Statement!U199 -> 29 | E69: =Statement!V199 -> 28 | F69: =Statement!W199 -> 31 | G69: =Statement!X199 -> 33 | H69: =Statement!Y199 -> 33 | I69: =Statement!Z199 -> 37 | J69: =Statement!AA199 -> 40
B70: FCFE | C70: =Statement!T158 -> 0 | D70: =Statement!U158 -> 0 | E70: =Statement!V158 -> 319 | F70: =Statement!W158 -> 253 | G70: =Statement!X158 -> 231 | H70: =Statement!Y158 -> 785 | I70: =Statement!Z158 -> 712 | J70: =Statement!AA158 -> 370

Sheet Forecast ->
H5: Links
H6: Overview'!B3
H7: Financials ->'!B13
H8: Analysis ->'!B13
H9: Forecast ->'!B13
H10: Valuation ->'!B13
B13: Forecast ->

Sheet Revenue
B1: Revenue forecast
C2: History | H2: Forecast | S2: History | AA2: Forecast | AE2: TTM
C4: Revenues | S4: Revenues
B5: Revenues (thousand) | C5: =Statement!M3 -> 2022 | D5: =Statement!N3 -> 2023 | E5: =Statement!O3 -> 2024 | F5: =Statement!P3 -> 2025 | G5: =Statement!Q3 -> 2026 | H5: =G5+1 -> 2027 | I5: =H5+1 -> 2028 | J5: =I5+1 -> 2029 | K5: =J5+1 -> 2030 | L5: =K5+1 -> 2031 | R5: =B5 -> Revenues (thousand) | S5: =Statement!T3 -> Q3 2025 | T5: =Statement!U3 -> Q4 2025 | U5: =Statement!V3 -> Q1 2026 | V5: =Statement!W3 -> Q2 2026 | W5: =Statement!X3 -> Q3 2026 | X5: =Statement!Y3 -> Q4 2026 | Y5: =Statement!Z3 -> Q1 2027 | Z5: =Statement!AA3 -> Q2 2027 | AA5: FQ1 | AB5: FQ2 | AC5: FQ3 | AE5: FQ1
B6: =Statement!B188 -> Subscription | C6: =Statement!M188 -> 4136 | D6: =Statement!N188 -> 4716 | E6: =Statement!O188 -> 5170 | F6: =Statement!P188 -> 5758 | G6: =Statement!Q188 -> 6776 | H6: =H14-H7 -> 7878.2949 | I6: =I14-I7 -> 9167.4253 | J6: =J14-J7 -> 10360.902 | K6: =K14-K7 -> 11639.445 | L6: =L14-L7 -> 12716.049 | N6: Revenue - Other | Q6: Revenue - Other | R6: =B6 -> Subscription | S6: =Statement!T188 -> 1466 | T6: =Statement!U188 -> 1532 | U6: =Statement!V188 -> 1540 | V6: =Statement!W188 -> 1667 | W6: =Statement!X188 -> 1742 | X6: =Statement!Y188 -> 1827 | Y6: =Statement!Z188 -> 1836 | Z6: =Statement!AA188 -> 1952 | AA6: =AA14-AA7 -> 2030.5585 | AE6: =SUM(X6:AA6) -> 7645.5585
B7: =Statement!B189 -> Other | C7: =Statement!M189 -> 250 | D7: =Statement!N189 -> 289 | E7: =Statement!O189 -> 327 | F7: =Statement!P189 -> 373 | G7: =Statement!Q189 -> 430 | H7: =H14*H30 -> 458.5251 | I7: =I14*I30 -> 533.55386 | J7: =J14*J30 -> 556.80293 | K7: =K14*K30 -> 612.60235 | L7: =L14*L30 -> 669.26571 | N7: Other % of Revenue | Q7: Other % of Revenue | R7: =B7 -> Other | S7: =Statement!T189 -> 104 | T7: =Statement!U189 -> 107 | U7: =Statement!V189 -> 93 | V7: =Statement!W189 -> 96 | W7: =Statement!X189 -> 111 | X7: =Statement!Y189 -> 130 | Y7: =Statement!Z189 -> 98 | Z7: =Statement!AA189 -> 94 | AA7: =AA14*AA30 -> 106.8715 | AE7: =SUM(X7:AA7) -> 428.8715
B9: =Statement!B195 -> AECO | C9: =Statement!M195 -> 1969 | D9: =Statement!N195 -> 2278 | E9: =Statement!O195 -> 2580 | F9: =Statement!P195 -> 2937 | G9: =Statement!Q195 -> 3583 | H9: =G9*(1+H21) -> 4299.6 | I9: =H9*(1+I21) -> 5159.52 | J9: =I9*(1+J21) -> 5933.448 | K9: =J9*(1+K21) -> 6823.4652 | L9: =K9*(1+L21) -> 7505.8117 | N9: AECO Growth Rate | Q9: AECO Growth Rate | R9: =B9 -> AECO | S9: =Statement!T195 -> 751 | T9: =Statement!U195 -> 799 | U9: =Statement!V195 -> 809 | V9: =Statement!W195 -> 878 | W9: =Statement!X195 -> 921 | X9: =Statement!Y195 -> 975 | Y9: =Statement!Z195 -> 970 | Z9: =Statement!AA195 -> 1029 | AA9: =Z9*(1+AA21) -> 1075.305 | AE9: =SUM(X9:AA9) -> 4049.305
B10: =Statement!B196 -> AutoCAD and AutoCAD LT | C10: =Statement!M196 -> 1244 | D10: =Statement!N196 -> 1387 | E10: =Statement!O196 -> 1462 | F10: =Statement!P196 -> 1572 | G10: =Statement!Q196 -> 1787 | H10: =G10*(1+H22) -> 1965.7 | I10: =H10*(1+I22) -> 2201.584 | J10: =I10*(1+J22) -> 2399.7266 | K10: =J10*(1+K22) -> 2615.702 | L10: =K10*(1+L22) -> 2824.9581 | N10: AutoCAD Growth Rate | Q10: AutoCAD Growth Rate | R10: =B10 -> AutoCAD and AutoCAD LT | S10: =Statement!T196 -> 398 | T10: =Statement!U196 -> 409 | U10: =Statement!V196 -> 411 | V10: =Statement!W196 -> 440 | W10: =Statement!X196 -> 458 | X10: =Statement!Y196 -> 478 | Y10: =Statement!Z196 -> 474 | Z10: =Statement!AA196 -> 500 | AA10: =Z10*(1+AA22) -> 520 | AE10: =SUM(X10:AA10) -> 1972
B11: =Statement!B197 -> Manufacturing | C11: =Statement!M197 -> 876 | D11: =Statement!N197 -> 978 | E11: =Statement!O197 -> 1063 | F11: =Statement!P197 -> 1189 | G11: =Statement!Q197 -> 1379 | H11: =G11*(1+H23) -> 1585.85 | I11: =H11*(1+I23) -> 1823.7275 | J11: =I11*(1+J23) -> 2042.5748 | K11: =J11*(1+K23) -> 2246.8323 | L11: =K11*(1+L23) -> 2471.5155 | N11: Manufacturing Growth Rate | Q11: Manufacturing Growth Rate | R11: =B11 -> Manufacturing | S11: =Statement!T197 -> 307 | T11: =Statement!U197 -> 318 | U11: =Statement!V197 -> 309 | V11: =Statement!W197 -> 334 | W11: =Statement!X197 -> 355 | X11: =Statement!Y197 -> 381 | Y11: =Statement!Z197 -> 367 | Z11: =Statement!AA197 -> 385 | AA11: =Z11*(1+AA23) -> 402.325 | AE11: =SUM(X11:AA11) -> 1535.325
B12: =Statement!B198 -> Media and Entertainment | C12: =Statement!M198 -> 259 | D12: =Statement!N198 -> 291 | E12: =Statement!O198 -> 295 | F12: =Statement!P198 -> 315 | G12: =Statement!Q198 -> 332 | H12: =G12*(1+H24) -> 351.92 | I12: =H12*(1+I24) -> 373.0352 | J12: =I12*(1+J24) -> 391.68696 | K12: =J12*(1+K24) -> 411.27131 | L12: =K12*(1+L24) -> 423.60945 | N12: Media Growth Rate | Q12: Media Growth Rate | R12: =B12 -> Media and Entertainment | S12: =Statement!T198 -> 83 | T12: =Statement!U198 -> 84 | U12: =Statement!V198 -> 76 | V12: =Statement!W198 -> 80 | W12: =Statement!X198 -> 86 | X12: =Statement!Y198 -> 90 | Y12: =Statement!Z198 -> 86 | Z12: =Statement!AA198 -> 92 | AA12: =Z12*(1+AA24) -> 96.6 | AE12: =SUM(X12:AA12) -> 364.6
B13: =Statement!B199 -> Other | C13: =Statement!M199 -> 38 | D13: =Statement!N199 -> 71 | E13: =Statement!O199 -> 97 | F13: =Statement!P199 -> 118 | G13: =Statement!Q199 -> 125 | H13: =G13*(1+H25) -> 133.75 | I13: =H13*(1+I25) -> 143.1125 | J13: =I13*(1+J25) -> 150.26813 | K13: =J13*(1+K25) -> 154.77617 | L13: =K13*(1+L25) -> 159.41945 | N13: Other Growth Rate | Q13: Other Growth Rate | R13: =B13 -> Other | S13: =Statement!T199 -> 31 | T13: =Statement!U199 -> 29 | U13: =Statement!V199 -> 28 | V13: =Statement!W199 -> 31 | W13: =Statement!X199 -> 33 | X13: =Statement!Y199 -> 33 | Y13: =Statement!Z199 -> 37 | Z13: =Statement!AA199 -> 40 | AA13: =Z13*(1+AA25) -> 43.2 | AE13: =SUM(X13:AA13) -> 153.2
B14: Total | C14: =Statement!M5 -> 4386 | D14: =Statement!N5 -> 5005 | E14: =Statement!O5 -> 5497 | F14: =Statement!P5 -> 6131 | G14: =Statement!Q5 -> 7206 | H14: =SUM(H9:H13) -> 8336.82 | I14: =SUM(I9:I13) -> 9700.9792 | J14: =SUM(J9:J13) -> 10917.704 | K14: =SUM(K9:K13) -> 12252.047 | L14: =SUM(L9:L13) -> 13385.314 | R14: Total | S14: =Statement!T5 -> 1570 | T14: =Statement!U5 -> 1639 | U14: =Statement!V5 -> 1633 | V14: =Statement!W5 -> 1763 | W14: =Statement!X5 -> 1853 | X14: =Statement!Y5 -> 1957 | Y14: =Statement!Z5 -> 1934 | Z14: =Statement!AA5 -> 2046 | AA14: =SUM(AA9:AA13) -> 2137.43 | AE14: =SUM(X14:AA14) -> 8074.43
C16: Growth rates | S16: Growth rates
B17: Revenue growth % | C17: =C5 -> 2022 | D17: =D5 -> 2023 | E17: =E5 -> 2024 | F17: =F5 -> 2025 | G17: =G5 -> 2026 | H17: =H5 -> 2027 | I17: =I5 -> 2028 | J17: =J5 -> 2029 | ... L17: =L5 -> 2031 | R17: Revenue growth % | S17: =S5 -> Q3 2025 | T17: =T5 -> Q4 2025 | U17: =U5 -> Q1 2026 | V17: =V5 -> Q2 2026 | W17: =W5 -> Q3 2026 | X17: =X5 -> Q4 2026 | Y17: =Y5 -> Q1 2027 | Z17: =Z5 -> Q2 2027 | ... AC17: =AC5 -> FQ3
B18: =B6 -> Subscription | D18: =D6/C6-1 -> 0.14023211 | E18: =E6/D6-1 -> 0.096268024 | F18: =F6/E6-1 -> 0.11373308 | G18: =G6/F6-1 -> 0.1767975 | H18: =H6/G6-1 -> 0.16267634 | I18: =I6/H6-1 -> 0.16363064 | J18: =J6/I6-1 -> 0.13018663 | K18: =K6/J6-1 -> 0.12340075 | L18: =L6/K6-1 -> 0.092496163 | R18: =R6 -> Subscription | T18: =T6/S6-1 -> 0.045020464 | U18: =U6/T6-1 -> 0.0052219321 | V18: =V6/U6-1 -> 0.082467532 | W18: =W6/V6-1 -> 0.044991002 | X18: =X6/W6-1 -> 0.048794489 | Y18: =Y6/X6-1 -> 0.0049261084 | Z18: =Z6/Y6-1 -> 0.063180828 | AA18: =AA6/Z6-1 -> 0.040245133
B19: =B7 -> Other | D19: =D7/C7-1 -> 0.156 | E19: =E7/D7-1 -> 0.13148789 | F19: =F7/E7-1 -> 0.14067278 | G19: =G7/F7-1 -> 0.15281501 | H19: =H7/G7-1 -> 0.066337442 | I19: =I7/H7-1 -> 0.16363064 | J19: =J7/I7-1 -> 0.043573991 | K19: =K7/J7-1 -> 0.10021395 | L19: =L7/K7-1 -> 0.092496163 | R19: =R7 -> Other | T19: =T7/S7-1 -> 0.028846154 | U19: =U7/T7-1 -> -0.13084112 | V19: =V7/U7-1 -> 0.032258065 | W19: =W7/V7-1 -> 0.15625 | X19: =X7/W7-1 -> 0.17117117 | Y19: =Y7/X7-1 -> -0.24615385 | Z19: =Z7/Y7-1 -> -0.040816327 | AA19: =AA7/Z7-1 -> 0.13693085
B21: =B9 -> AECO | D21: =D9/C9-1 -> 0.15693245 | E21: =E9/D9-1 -> 0.13257243 | F21: =F9/E9-1 -> 0.13837209 | G21: =G9/F9-1 -> 0.21995233 | H21: 0.2 | I21: 0.2 | J21: 0.15 | K21: 0.15 | L21: 0.1 | R21: =R9 -> AECO | T21: =T9/S9-1 -> 0.06391478 | U21: =U9/T9-1 -> 0.012515645 | V21: =V9/U9-1 -> 0.085290482 | W21: =W9/V9-1 -> 0.048974943 | X21: =X9/W9-1 -> 0.058631922 | Y21: =Y9/X9-1 -> -0.0051282051 | Z21: =Z9/Y9-1 -> 0.060824742 | AA21: 0.045
B22: =B10 -> AutoCAD and AutoCAD LT | D22: =D10/C10-1 -> 0.11495177 | E22: =E10/D10-1 -> 0.05407354 | F22: =F10/E10-1 -> 0.075239398 | G22: =G10/F10-1 -> 0.13676845 | H22: 0.1 | I22: 0.12 | J22: 0.09 | K22: 0.09 | L22: 0.08 | R22: =R10 -> AutoCAD and AutoCAD LT | T22: =T10/S10-1 -> 0.027638191 | U22: =U10/T10-1 -> 0.0048899756 | V22: =V10/U10-1 -> 0.070559611 | W22: =W10/V10-1 -> 0.040909091 | X22: =X10/W10-1 -> 0.043668122 | Y22: =Y10/X10-1 -> -0.0083682008 | Z22: =Z10/Y10-1 -> 0.054852321 | AA22: 0.04
B23: =B11 -> Manufacturing | D23: =D11/C11-1 -> 0.11643836 | E23: =E11/D11-1 -> 0.086912065 | F23: =F11/E11-1 -> 0.11853246 | G23: =G11/F11-1 -> 0.15979815 | H23: 0.15 | I23: 0.15 | J23: 0.12 | K23: 0.1 | L23: 0.1 | R23: =R11 -> Manufacturing | T23: =T11/S11-1 -> 0.035830619 | U23: =U11/T11-1 -> -0.028301887 | V23: =V11/U11-1 -> 0.080906149 | W23: =W11/V11-1 -> 0.062874251 | X23: =X11/W11-1 -> 0.073239437 | Y23: =Y11/X11-1 -> -0.036745407 | Z23: =Z11/Y11-1 -> 0.049046322 | AA23: 0.045
B24: =B12 -> Media and Entertainment | D24: =D12/C12-1 -> 0.12355212 | E24: =E12/D12-1 -> 0.013745704 | F24: =F12/E12-1 -> 0.06779661 | G24: =G12/F12-1 -> 0.053968254 | H24: 0.06 | I24: 0.06 | J24: 0.05 | K24: 0.05 | L24: 0.03 | R24: =R12 -> Media and Entertainment | T24: =T12/S12-1 -> 0.012048193 | U24: =U12/T12-1 -> -0.095238095 | V24: =V12/U12-1 -> 0.052631579 | W24: =W12/V12-1 -> 0.075 | X24: =X12/W12-1 -> 0.046511628 | Y24: =Y12/X12-1 -> -0.044444444 | Z24: =Z12/Y12-1 -> 0.069767442 | AA24: 0.05
B25: =B13 -> Other | D25: =D13/C13-1 -> 0.86842105 | E25: =E13/D13-1 -> 0.36619718 | F25: =F13/E13-1 -> 0.21649485 | G25: =G13/F13-1 -> 0.059322034 | H25: 0.07 | I25: 0.07 | J25: 0.05 | K25: 0.03 | L25: 0.03 | R25: =R13 -> Other | T25: =T13/S13-1 -> -0.064516129 | U25: =U13/T13-1 -> -0.034482759 | V25: =V13/U13-1 -> 0.10714286 | W25: =W13/V13-1 -> 0.064516129 | X25: =X13/W13-1 -> 0 | Y25: =Y13/X13-1 -> 0.12121212 | Z25: =Z13/Y13-1 -> 0.081081081 | AA25: 0.08
B26: =B14 -> Total | D26: =D14/C14-1 -> 0.14113087 | E26: =E14/D14-1 -> 0.098301698 | F26: =F14/E14-1 -> 0.11533564 | G26: =G14/F14-1 -> 0.17533844 | H26: =H14/G14-1 -> 0.15692756 | I26: =I14/H14-1 -> 0.16363064 | J26: =J14/I14-1 -> 0.12542293 | K26: =K14/J14-1 -> 0.12221823 | L26: =L14/K14-1 -> 0.092496163 | R26: =R14 -> Total | T26: =T14/S14-1 -> 0.043949045 | U26: =U14/T14-1 -> -0.0036607688 | V26: =V14/U14-1 -> 0.079608083 | W26: =W14/V14-1 -> 0.051049348 | X26: =X14/W14-1 -> 0.056125202 | Y26: =Y14/X14-1 -> -0.011752683 | Z26: =Z14/Y14-1 -> 0.057911065 | AA26: =AA14/Z14-1 -> 0.044687195
C28: Metrics | S28: Metrics
C29: =C17 -> 2022 | D29: =D17 -> 2023 | E29: =E17 -> 2024 | F29: =F17 -> 2025 | G29: =G17 -> 2026 | H29: =H17 -> 2027 | I29: =I17 -> 2028 | J29: =J17 -> 2029 | ... L29: =L17 -> 2031 | S29: =S17 -> Q3 2025 | T29: =T17 -> Q4 2025 | U29: =U17 -> Q1 2026 | V29: =V17 -> Q2 2026 | W29: =W17 -> Q3 2026 | X29: =X17 -> Q4 2026 | Y29: =Y17 -> Q1 2027 | Z29: =Z17 -> Q2 2027 | ... AC29: =AC17 -> FQ3 | AE29: FQ1
B30: =B7&" % of revenue" -> Other % of revenue | C30: =C7/C14 -> 0.056999544 | D30: =D7/D14 -> 0.057742258 | E30: =E7/E14 -> 0.059486993 | F30: =F7/F14 -> 0.060838362 | G30: =G7/G14 -> 0.059672495 | H30: 0.055 | I30: 0.055 | J30: 0.051 | K30: 0.05 | L30: 0.05 | R30: =R7&" % of revenue" -> Other % of revenue | S30: =S7/S14 -> 0.066242038 | T30: =T7/T14 -> 0.06528371 | U30: =U7/U14 -> 0.056950398 | V30: =V7/V14 -> 0.054452638 | W30: =W7/W14 -> 0.05990286 | X30: =X7/X14 -> 0.066428206 | Y30: =Y7/Y14 -> 0.050672182 | Z30: =Z7/Z14 -> 0.045943304 | AA30: 0.05 | AE30: =AE7/AE14 -> 0.053114771

Sheet COGS & OpEx
B1: COGS & OpEx forecast
C2: History | H2: Forecast | P2: History | X2: Forecast | AB2: TTM
C4: Revenues | P4: Revenues
B5: =Revenue!B5 -> Revenues (thousand) | C5: =Revenue!C5 -> 2022 | D5: =Revenue!D5 -> 2023 | E5: =Revenue!E5 -> 2024 | F5: =Revenue!F5 -> 2025 | G5: =Revenue!G5 -> 2026 | H5: =G5+1 -> 2027 | I5: =H5+1 -> 2028 | J5: =I5+1 -> 2029 | K5: =J5+1 -> 2030 | L5: =K5+1 -> 2031 | O5: Revenues (thousand) | P5: =Revenue!S5 -> Q3 2025 | Q5: =Revenue!T5 -> Q4 2025 | R5: =Revenue!U5 -> Q1 2026 | S5: =Revenue!V5 -> Q2 2026 | T5: =Revenue!W5 -> Q3 2026 | U5: =Revenue!X5 -> Q4 2026 | V5: =Revenue!Y5 -> Q1 2027 | W5: =Revenue!Z5 -> Q2 2027 | X5: FQ1 | Y5: FQ2 | Z5: FQ3 | AB5: =Revenue!AE5 -> FQ1
B6: Revenue | C6: =Revenue!C14 -> 4386 | D6: =Revenue!D14 -> 5005 | E6: =Revenue!E14 -> 5497 | F6: =Revenue!F14 -> 6131 | G6: =Revenue!G14 -> 7206 | H6: =Revenue!H14 -> 8336.82 | I6: =Revenue!I14 -> 9700.9792 | J6: =Revenue!J14 -> 10917.704 | ... L6: =Revenue!L14 -> 13385.314 | O6: Revenue | P6: =Revenue!S14 -> 1570 | Q6: =Revenue!T14 -> 1639 | R6: =Revenue!U14 -> 1633 | S6: =Revenue!V14 -> 1763 | T6: =Revenue!W14 -> 1853 | U6: =Revenue!X14 -> 1957 | V6: =Revenue!Y14 -> 1934 | W6: =Revenue!Z14 -> 2046 | X6: =Revenue!AA14 -> 2137.43 | AB6: =Revenue!AE14 -> 8074.43
C9: COGS and OpEx | P9: COGS & OpEx
B10: Expenses (tnousand) | C10: =C5 -> 2022 | D10: =D5 -> 2023 | E10: =E5 -> 2024 | F10: =F5 -> 2025 | G10: =G5 -> 2026 | H10: =H5 -> 2027 | I10: =I5 -> 2028 | J10: =J5 -> 2029 | ... L10: =L5 -> 2031 | O10: Expenses (thousand) | P10: =P5 -> Q3 2025 | Q10: =Q5 -> Q4 2025 | R10: =R5 -> Q1 2026 | S10: =S5 -> Q2 2026 | T10: =T5 -> Q3 2026 | U10: =U5 -> Q4 2026 | V10: =V5 -> Q1 2027 | W10: =W5 -> Q2 2027 | ... Z10: =Z5 -> FQ3 | AB10: =AB5 -> FQ1
B11: =Statement!B191 -> Subscription COGS | C11: =Statement!M191 -> 299 | D11: =Statement!N191 -> 343 | E11: =Statement!O191 -> 381 | F11: =Statement!P191 -> 413 | G11: =Statement!Q191 -> 463 | H11: =H6*H23 -> 516.88284 | I11: =I6*I23 -> 582.05875 | J11: =J6*J23 -> 655.06227 | K11: =K6*K23 -> 735.12281 | L11: =L6*L23 -> 803.11885 | O11: =B11 -> Subscription COGS | P11: =Statement!T191 -> 105 | Q11: =Statement!U191 -> 108 | R11: =Statement!V191 -> 111 | S11: =Statement!W191 -> 114 | T11: =Statement!X191 -> 118 | U11: =Statement!Y191 -> 120 | V11: =Statement!Z191 -> 129 | W11: =Statement!AA191 -> 130 | X11: =X23*X$6 -> 192.3687 | AB11: =SUM(U11:X11) -> 571.3687
B12: =Statement!B192 -> Other COGS | C12: =Statement!M192 -> 67 | D12: =Statement!N192 -> 79 | E12: =Statement!O192 -> 82 | F12: =Statement!P192 -> 80 | G12: =Statement!Q192 -> 90 | H12: =H6*H24 -> 100.04184 | I12: =I6*I24 -> 116.41175 | J12: =J6*J24 -> 131.01245 | K12: =K6*K24 -> 147.02456 | L12: =L6*L24 -> 160.62377 | O12: =B12 -> Other COGS | P12: =Statement!T192 -> 19 | Q12: =Statement!U192 -> 23 | R12: =Statement!V192 -> 24 | S12: =Statement!W192 -> 22 | T12: =Statement!X192 -> 22 | U12: =Statement!Y192 -> 22 | V12: =Statement!Z192 -> 21 | W12: =Statement!AA192 -> 22 | X12: =X24*X$6 -> 2.13743 | AB12: =SUM(U12:X12) -> 67.13743
B13: =Statement!B193 -> Amortization of developed tech COGS | C13: =Statement!M193 -> 52 | D13: =Statement!N193 -> 58 | E13: =Statement!O193 -> 48 | F13: =Statement!P193 -> 85 | G13: =Statement!Q193 -> 97 | H13: =H6*H25 -> 100.04184 | I13: =I6*I25 -> 106.71077 | J13: =J6*J25 -> 120.09475 | K13: =K6*K25 -> 134.77252 | L13: =L6*L25 -> 147.23846 | O13: =B13 -> Amortization of developed tech COGS | P13: =Statement!T193 -> 23 | Q13: =Statement!U193 -> 23 | R13: =Statement!V193 -> 25 | S13: =Statement!W193 -> 23 | T13: =Statement!X193 -> 25 | U13: =Statement!Y193 -> 24 | V13: =Statement!Z193 -> 25 | W13: =Statement!AA193 -> 24 | X13: =X25*X$6 -> 38.47374 | AB13: =SUM(U13:X13) -> 111.47374
B14: COGS | C14: =Statement!M6 -> 418 | D14: =Statement!N6 -> 480 | E14: =Statement!O6 -> 511 | F14: =Statement!P6 -> 578 | G14: =Statement!Q6 -> 650 | H14: =SUM(H11:H13) -> 716.96652 | I14: =SUM(I11:I13) -> 805.18127 | J14: =SUM(J11:J13) -> 906.16947 | K14: =SUM(K11:K13) -> 1016.9199 | L14: =SUM(L11:L13) -> 1110.9811 | O14: =B14 -> COGS | P14: =Statement!T6 -> 147 | Q14: =Statement!U6 -> 154 | R14: =Statement!V6 -> 160 | S14: =Statement!W6 -> 159 | T14: =Statement!X6 -> 165 | U14: =Statement!Y6 -> 166 | V14: =Statement!Z6 -> 175 | W14: =Statement!AA6 -> 176 | X14: =SUM(X11:X13) -> 232.97987 | AB14: =SUM(AB11:AB13) -> 749.97987
B15: =Statement!B8 -> Sales and marketing | C15: =Statement!M8 -> 1623 | D15: =Statement!N8 -> 1745 | E15: =Statement!O8 -> 1823 | F15: =Statement!P8 -> 2000 | G15: =Statement!Q8 -> 2373 | H15: =H6*H27 -> 2709.4665 | I15: =I6*I27 -> 3104.3133 | J15: =J6*J27 -> 3493.6654 | K15: =K6*K27 -> 3798.1345 | L15: =L6*L27 -> 4149.4474 | O15: =B15 -> Sales and marketing | P15: =Statement!T8 -> 525 | Q15: =Statement!U8 -> 526 | R15: =Statement!V8 -> 566 | S15: =Statement!W8 -> 559 | T15: =Statement!X8 -> 612 | U15: =Statement!Y8 -> 636 | V15: =Statement!Z8 -> 593 | W15: =Statement!AA8 -> 616 | X15: =X27*X$6 -> 384.7374 | AB15: =SUM(U15:X15) -> 2229.7374
B16: =Statement!B9 -> R&D | C16: =Statement!M9 -> 1115 | D16: =Statement!N9 -> 1219 | E16: =Statement!O9 -> 1373 | F16: =Statement!P9 -> 1485 | G16: =Statement!Q9 -> 1643 | H16: =H6*H28 -> 1834.1004 | I16: =I6*I28 -> 2134.2154 | J16: =J6*J28 -> 2292.7179 | K16: =K6*K28 -> 2572.9299 | L16: =L6*L28 -> 2810.916 | O16: =B16 -> R&D | P16: =Statement!T9 -> 378 | Q16: =Statement!U9 -> 393 | R16: =Statement!V9 -> 394 | S16: =Statement!W9 -> 413 | T16: =Statement!X9 -> 416 | U16: =Statement!Y9 -> 420 | V16: =Statement!Z9 -> 421 | W16: =Statement!AA9 -> 464 | X16: =X28*X$6 -> 577.1061 | AB16: =SUM(U16:X16) -> 1882.1061
B17: =Statement!B10 -> General and administrative | C17: =Statement!M10 -> 572 | D17: =Statement!N10 -> 532 | E17: =Statement!O10 -> 620 | F17: =Statement!P10 -> 650 | G17: =Statement!Q10 -> 693 | H17: =H6*H29 -> 875.3661 | I17: =I6*I29 -> 1067.1077 | J17: =J6*J29 -> 1200.9475 | K17: =K6*K29 -> 1225.2047 | L17: =L6*L29 -> 1338.5314 | O17: =B17 -> General and administrative | P17: =Statement!T10 -> 161 | Q17: =Statement!U10 -> 173 | R17: =Statement!V10 -> 162 | S17: =Statement!W10 -> 168 | T17: =Statement!X10 -> 172 | U17: =Statement!Y10 -> 191 | V17: =Statement!Z10 -> 162 | W17: =Statement!AA10 -> 179 | X17: =X29*X$6 -> 168.85697 | AB17: =SUM(U17:X17) -> 700.85697
B18: OpEx | C18: =Statement!M12 -> 3350 | D18: =Statement!N12 -> 3536 | E18: =Statement!O12 -> 3858 | F18: =Statement!P12 -> 4199 | G18: =Statement!Q12 -> 4978 | H18: =SUM(H15:H17) -> 5418.933 | I18: =SUM(I15:I17) -> 6305.6365 | J18: =SUM(J15:J17) -> 6987.3308 | K18: =SUM(K15:K17) -> 7596.2691 | L18: =SUM(L15:L17) -> 8298.8948 | O18: =B18 -> OpEx | P18: =Statement!T12 -> 1077 | Q18: =Statement!U12 -> 1119 | R18: =Statement!V12 -> 1240 | S18: =Statement!W12 -> 1160 | T18: =Statement!X12 -> 1218 | U18: =Statement!Y12 -> 1360 | V18: =Statement!Z12 -> 1218 | W18: =Statement!AA12 -> 1271 | X18: =SUM(X15:X17) -> 1130.7005 | AB18: =SUM(U18:X18) -> 4979.7005
C21: Expenses % of Revenue | P21: Expenses % of Revenue
B22: % of revenue | C22: =C5 -> 2022 | D22: =D5 -> 2023 | E22: =E5 -> 2024 | F22: =F5 -> 2025 | G22: =G5 -> 2026 | H22: =H5 -> 2027 | I22: =I5 -> 2028 | J22: =J5 -> 2029 | ... L22: =L5 -> 2031 | O22: % of revenue | P22: =P5 -> Q3 2025 | Q22: =Q5 -> Q4 2025 | R22: =R5 -> Q1 2026 | S22: =S5 -> Q2 2026 | T22: =T5 -> Q3 2026 | U22: =U5 -> Q4 2026 | V22: =V5 -> Q1 2027 | W22: =W5 -> Q2 2027 | ... Z22: =Z5 -> FQ3
B23: =B11 -> Subscription COGS | C23: =C11/C$6 -> 0.068171455 | D23: =D11/D$6 -> 0.068531469 | E23: =E11/E$6 -> 0.069310533 | F23: =F11/F$6 -> 0.067362584 | G23: =G11/G$6 -> 0.064252012 | H23: 0.062 | I23: 0.06 | J23: 0.06 | K23: 0.06 | L23: 0.06 | O23: =O11 -> Subscription COGS | P23: =P11/P$6 -> 0.066878981 | Q23: =Q11/Q$6 -> 0.065893838 | R23: =R11/R$6 -> 0.067973056 | S23: =S11/S$6 -> 0.064662507 | T23: =T11/T$6 -> 0.063680518 | U23: =U11/U$6 -> 0.061318344 | V23: =V11/V$6 -> 0.066701138 | W23: =W11/W$6 -> 0.063538612 | X23: 0.09
B24: =B12 -> Other COGS | C24: =C12/C$6 -> 0.015275878 | D24: =D12/D$6 -> 0.015784216 | E24: =E12/E$6 -> 0.014917228 | F24: =F12/F$6 -> 0.013048442 | G24: =G12/G$6 -> 0.012489592 | H24: 0.012 | I24: 0.012 | J24: 0.012 | K24: 0.012 | L24: 0.012 | O24: =O12 -> Other COGS | P24: =P12/P$6 -> 0.012101911 | Q24: =Q12/Q$6 -> 0.014032947 | R24: =R12/R$6 -> 0.014696877 | S24: =S12/S$6 -> 0.012478729 | T24: =T12/T$6 -> 0.011872639 | U24: =U12/U$6 -> 0.011241696 | V24: =V12/V$6 -> 0.010858325 | W24: =W12/W$6 -> 0.010752688 | X24: 0.001
B25: =B13 -> Amortization of developed tech COGS | C25: =C13/C$6 -> 0.011855905 | D25: =D13/D$6 -> 0.011588412 | E25: =E13/E$6 -> 0.0087320357 | F25: =F13/F$6 -> 0.01386397 | G25: =G13/G$6 -> 0.013461005 | H25: 0.012 | I25: 0.011 | J25: 0.011 | K25: 0.011 | L25: 0.011 | O25: =O13 -> Amortization of developed tech COGS | P25: =P13/P$6 -> 0.014649682 | Q25: =Q13/Q$6 -> 0.014032947 | R25: =R13/R$6 -> 0.015309247 | S25: =S13/S$6 -> 0.013045944 | T25: =T13/T$6 -> 0.013491635 | U25: =U13/U$6 -> 0.012263669 | V25: =V13/V$6 -> 0.012926577 | W25: =W13/W$6 -> 0.011730205 | X25: 0.018
B26: =B14 -> COGS | C26: =C14/C$6 -> 0.095303238 | D26: =D14/D$6 -> 0.095904096 | E26: =E14/E$6 -> 0.092959796 | F26: =F14/F$6 -> 0.094274996 | G26: =G14/G$6 -> 0.090202609 | H26: =H14/H$6 -> 0.086 | I26: =I14/I$6 -> 0.083 | J26: =J14/J$6 -> 0.083 | ... L26: =L14/L$6 -> 0.083 | O26: =O14 -> COGS | P26: =P14/P$6 -> 0.093630573 | Q26: =Q14/Q$6 -> 0.093959732 | R26: =R14/R$6 -> 0.097979179 | S26: =S14/S$6 -> 0.090187181 | T26: =T14/T$6 -> 0.089044792 | U26: =U14/U$6 -> 0.08482371 | V26: =V14/V$6 -> 0.090486039 | W26: =W14/W$6 -> 0.086021505 | X26: =X14/X$6 -> 0.109
B27: =B15 -> Sales and marketing | C27: =C15/C$6 -> 0.37004104 | D27: =D15/D$6 -> 0.34865135 | E27: =E15/E$6 -> 0.33163544 | F27: =F15/F$6 -> 0.32621106 | G27: =G15/G$6 -> 0.32930891 | H27: 0.325 | I27: 0.32 | J27: 0.32 | K27: 0.31 | L27: 0.31 | O27: =O15 -> Sales and marketing | P27: =P15/P$6 -> 0.3343949 | Q27: =Q15/Q$6 -> 0.32092739 | R27: =R15/R$6 -> 0.34660135 | S27: =S15/S$6 -> 0.31707317 | T27: =T15/T$6 -> 0.33027523 | U27: =U15/U$6 -> 0.32498723 | V27: =V15/V$6 -> 0.30661841 | W27: =W15/W$6 -> 0.30107527 | X27: 0.18
B28: =B16 -> R&D | C28: =C16/C$6 -> 0.25421797 | D28: =D16/D$6 -> 0.24355644 | E28: =E16/E$6 -> 0.2497726 | F28: =F16/F$6 -> 0.24221171 | G28: =G16/G$6 -> 0.22800444 | H28: 0.22 | I28: 0.22 | J28: 0.21 | K28: 0.21 | L28: 0.21 | O28: =O16 -> R&D | P28: =P16/P$6 -> 0.24076433 | Q28: =Q16/Q$6 -> 0.23978035 | R28: =R16/R$6 -> 0.24127373 | S28: =S16/S$6 -> 0.23425978 | T28: =T16/T$6 -> 0.22450081 | U28: =U16/U$6 -> 0.21461421 | V28: =V16/V$6 -> 0.21768356 | W28: =W16/W$6 -> 0.22678397 | X28: 0.27
B29: =B17 -> General and administrative | C29: =C17/C$6 -> 0.13041496 | D29: =D17/D$6 -> 0.10629371 | E29: =E17/E$6 -> 0.11278879 | F29: =F17/F$6 -> 0.10601859 | G29: =G17/G$6 -> 0.096169858 | H29: 0.105 | I29: 0.11 | J29: 0.11 | K29: 0.1 | L29: 0.1 | O29: =O17 -> General and administrative | P29: =P17/P$6 -> 0.10254777 | Q29: =Q17/Q$6 -> 0.10555217 | R29: =R17/R$6 -> 0.099203919 | S29: =S17/S$6 -> 0.095292116 | T29: =T17/T$6 -> 0.09282245 | U29: =U17/U$6 -> 0.097598365 | V29: =V17/V$6 -> 0.083764219 | W29: =W17/W$6 -> 0.087487781 | X29: 0.079
B30: =B18 -> OpEx | C30: =C18/C$6 -> 0.76379389 | D30: =D18/D$6 -> 0.70649351 | E30: =E18/E$6 -> 0.70183737 | F30: =F18/F$6 -> 0.68488012 | G30: =G18/G$6 -> 0.69081321 | H30: =H18/H$6 -> 0.65 | I30: =I18/I$6 -> 0.65 | J30: =J18/J$6 -> 0.64 | ... L30: =L18/L$6 -> 0.62 | O30: =O18 -> OpEx | P30: =P18/P$6 -> 0.68598726 | Q30: =Q18/Q$6 -> 0.68273337 | R30: =R18/R$6 -> 0.75933864 | S30: =S18/S$6 -> 0.65796937 | T30: =T18/T$6 -> 0.65731247 | U30: =U18/U$6 -> 0.69494124 | V30: =V18/V$6 -> 0.62978283 | W30: =W18/W$6 -> 0.62121212 | X30: =X18/X$6 -> 0.529

Sheet WC & Investments
B1: Working Capital, Capex, D&A
C3: History | H3: Forecast
C5: Revenues
B6: Revenues (thousand) | C6: =Revenue!C5 -> 2022 | D6: =Revenue!D5 -> 2023 | E6: =Revenue!E5 -> 2024 | F6: =Revenue!F5 -> 2025 | G6: =Revenue!G5 -> 2026 | H6: =G6+1 -> 2027 | I6: =H6+1 -> 2028 | J6: =I6+1 -> 2029 | K6: =J6+1 -> 2030 | L6: =K6+1 -> 2031
B7: Revenue | C7: =Revenue!C14 -> 4386 | D7: =Revenue!D14 -> 5005 | E7: =Revenue!E14 -> 5497 | F7: =Revenue!F14 -> 6131 | G7: =Revenue!G14 -> 7206 | H7: =Revenue!H14 -> 8336.82 | I7: =Revenue!I14 -> 9700.9792 | J7: =Revenue!J14 -> 10917.704 | ... L7: =Revenue!L14 -> 13385.314
B8: COGS | C8: ='COGS & OpEx'!C14 -> 418 | D8: ='COGS & OpEx'!D14 -> 480 | E8: ='COGS & OpEx'!E14 -> 511 | F8: ='COGS & OpEx'!F14 -> 578 | G8: ='COGS & OpEx'!G14 -> 650 | H8: ='COGS & OpEx'!H14 -> 716.96652 | I8: ='COGS & OpEx'!I14 -> 805.18127 | J8: ='COGS & OpEx'!J14 -> 906.16947 | ... L8: ='COGS & OpEx'!L14 -> 1110.9811
C11: Working Capital
B12: $ (thousand) | C12: =C6 -> 2022 | D12: =D6 -> 2023 | E12: =E6 -> 2024 | F12: =F6 -> 2025 | G12: =G6 -> 2026 | H12: =H6 -> 2027 | I12: =I6 -> 2028 | J12: =J6 -> 2029 | ... L12: =L6 -> 2031
B13: Accounts receivable | C13: =Statement!M31 -> 716 | D13: =Statement!N31 -> 961 | E13: =Statement!O31 -> 876 | F13: =Statement!P31 -> 1008 | G13: =Statement!Q31 -> 1439 | H13: =H20*H7/365 -> 799.4211 | I13: =I20*I7/365 -> 930.23088 | J13: =J20*J7/365 -> 2093.8063 | K13: =K20*K7/365 -> 2181.8714 | L13: =L20*L7/365 -> 2200.3256
B14: Inventory | C14: =Statement!M32 -> 0 | D14: =Statement!N32 -> 0 | E14: =Statement!O32 -> 0 | F14: =Statement!P32 -> 0 | G14: =Statement!Q32 -> 0 | H14: =H21*H8/365 -> 0 | I14: =I21*I8/365 -> 0 | J14: =J21*J8/365 -> 0 | K14: =K21*K8/365 -> 0 | L14: =L21*L8/365 -> 0
B15: Accounts payable | C15: =Statement!M39 -> 121 | D15: =Statement!N39 -> 102 | E15: =Statement!O39 -> 100 | F15: =Statement!P39 -> 242 | G15: =Statement!Q39 -> 422 | H15: =H22*H8/365 -> 471.43004 | I15: =I22*I8/365 -> 529.43426 | J15: =J22*J8/365 -> 546.18434 | K15: =K22*K8/365 -> 417.91228 | L15: =L22*L8/365 -> 319.5973
C18: WC metrics and drivers
B19: Days | C19: =C6 -> 2022 | D19: =D6 -> 2023 | E19: =E6 -> 2024 | F19: =F6 -> 2025 | G19: =G6 -> 2026 | H19: =H6 -> 2027 | I19: =I6 -> 2028 | J19: =J6 -> 2029 | ... L19: =L6 -> 2031
B20: DSO | C20: =C13/C7*365 -> 59.585043 | D20: =D13/D7*365 -> 70.082917 | E20: =E13/E7*365 -> 58.166273 | F20: =F13/F7*365 -> 60.009786 | G20: =G13/G7*365 -> 72.888565 | H20: 35 | I20: 35 | J20: 70 | K20: 65 | L20: 60
B21: DIO | C21: =C14/C8*365 -> 0 | D21: =D14/D8*365 -> 0 | E21: =E14/E8*365 -> 0 | F21: =F14/F8*365 -> 0 | G21: =G14/G8*365 -> 0 | H21: 0 | I21: 0 | J21: 0 | K21: 0 | L21: 0
B22: DPO | C22: =C15/C8*365 -> 105.65789 | D22: =D15/D8*365 -> 77.5625 | E22: =E15/E8*365 -> 71.428571 | F22: =F15/F8*365 -> 152.82007 | G22: =G15/G8*365 -> 236.96923 | H22: 240 | I22: 240 | J22: 220 | K22: 150 | L22: 105
B23: Net trade cycle | C23: =C20+C21-C22 -> -46.072851 | D23: =D20+D21-D22 -> -7.4795829 | E23: =E20+E21-E22 -> -13.262299 | F23: =F20+F21-F22 -> -92.810283 | G23: =G20+G21-G22 -> -164.08067 | H23: =H20+H21-H22 -> -205 | I23: =I20+I21-I22 -> -205 | J23: =J20+J21-J22 -> -150 | ... L23: =L20+L21-L22 -> -45
C26: Change in SIP NWC
B27: $ (thousand) | C27: =C6 -> 2022 | D27: =D6 -> 2023 | E27: =E6 -> 2024 | F27: =F6 -> 2025 | G27: =G6 -> 2026 | H27: =H6 -> 2027 | I27: =I6 -> 2028 | J27: =J6 -> 2029 | ... L27: =L6 -> 2031
B28: Change in acc receivable | C28: =Statement!M56 -> -66 | D28: =Statement!N56 -> -247 | E28: =Statement!O56 -> 86 | F28: =Statement!P56 -> -132 | G28: =Statement!Q56 -> -431 | H28: =-(H13-G13) -> 639.5789 | I28: =-(I13-H13) -> -130.80979 | J28: =-(J13-I13) -> -1163.5754 | K28: =-(K13-J13) -> -88.065035 | L28: =-(L13-K13) -> -18.454261
B29: Change in inventory | C29: =Statement!M57 -> 0 | D29: =Statement!N57 -> 0 | E29: =Statement!O57 -> 0 | F29: =Statement!P57 -> 0 | G29: =Statement!Q57 -> 0 | H29: =-(H14-G14) -> 0 | I29: =-(I14-H14) -> 0 | J29: =-(J14-I14) -> 0 | K29: =-(K14-J14) -> 0 | L29: =-(L14-K14) -> 0
B30: Change in acc payable | C30: =Statement!M58 -> 10 | D30: =Statement!N58 -> -5 | E30: =Statement!O58 -> 27 | F30: =Statement!P58 -> 238 | G30: =Statement!Q58 -> 455 | H30: =H15-G15 -> 49.430041 | I30: =I15-H15 -> 58.004222 | J30: =J15-I15 -> 16.750075 | K30: =K15-J15 -> -128.27205 | L30: =L15-K15 -> -98.314987
C33: Total change in NWC and less SIP
B34: $ (thousand) | C34: =C6 -> 2022 | D34: =D6 -> 2023 | E34: =E6 -> 2024 | F34: =F6 -> 2025 | G34: =G6 -> 2026 | H34: =H6 -> 2027 | I34: =I6 -> 2028 | J34: =J6 -> 2029 | ... L34: =L6 -> 2031
B35: Total change in NWC | C35: =Statement!M56+Statement!M57+Statement!M58+Statement!M59 -> 217 | D35: =Statement!N56+Statement!N57+Statement!N58+Statement!N59 -> 692 | E35: =Statement!O56+Statement!O57+Statement!O58+Statement!O59 -> -451 | F35: =Statement!P56+Statement!P57+Statement!P58+Statement!P59 -> -458 | G35: =Statement!Q56+Statement!Q57+Statement!Q58+Statement!Q59 -> -501 | H35: =H36+H28+H29+H30 -> 188.79974 | I35: =I36+I28+I29+I30 -> -654.86432 | J35: =J36+J28+J29+J30 -> -1801.8876 | K35: =K36+K28+K29+K30 -> -951.4599 | L35: =L36+L28+L29+L30 -> -919.8881
B36: Change in NWC less SIP | C36: =C35-C28-C29-C30 -> 273 | D36: =D35-D28-D29-D30 -> 944 | E36: =E35-E28-E29-E30 -> -564 | F36: =F35-F28-F29-F30 -> -564 | G36: =G35-G28-G29-G30 -> -525 | H36: =H7*H37 -> -500.2092 | I36: =I7*I37 -> -582.05875 | J36: =J7*J37 -> -655.06227 | K36: =K7*K37 -> -735.12281 | L36: =L7*L37 -> -803.11885
B37: % of revenue | C37: =C36/C7 -> 0.062243502 | D37: =D36/D7 -> 0.18861139 | E37: =E36/E7 -> -0.10260142 | F37: =F36/F7 -> -0.091991519 | G37: =G36/G7 -> -0.072855953 | H37: -0.06 | I37: -0.06 | J37: -0.06 | K37: -0.06 | L37: -0.06
C40: Investments
B41: $ (thousand) | C41: =C6 -> 2022 | D41: =D6 -> 2023 | E41: =E6 -> 2024 | F41: =F6 -> 2025 | G41: =G6 -> 2026 | H41: =H6 -> 2027 | I41: =I6 -> 2028 | J41: =J6 -> 2029 | ... L41: =L6 -> 2031
B42: D&A | C42: =Statement!M54 -> 148 | D42: =Statement!N54 -> 150 | E42: =Statement!O54 -> 139 | F42: =Statement!P54 -> 180 | G42: =Statement!Q54 -> 195 | H42: =H7*H43 -> 216.75732 | I42: =I7*I43 -> 271.62742 | J42: =J7*J43 -> 327.53113 | K42: =K7*K43 -> 343.05731 | L42: =L7*L43 -> 401.55943
B43: % of Revenue | C43: =C42/C7 -> 0.03374373 | D43: =D42/D7 -> 0.02997003 | E43: =E42/E7 -> 0.02528652 | F43: =F42/F7 -> 0.029358995 | G43: =G42/G7 -> 0.027060783 | H43: 0.026 | I43: 0.028 | J43: 0.03 | K43: 0.028 | L43: 0.03
B44: % of CapEx | C44: =C42/C45 -> 2.2089552 | D44: =D42/D45 -> 3.2608696 | E44: =E42/E45 -> 2.2786885 | F44: =F42/F45 -> 1.7647059 | G44: =G42/G45 -> 2.5657895 | H44: =H42/H45 -> 2.6 | I44: =I42/I45 -> 2.5454545 | J44: =J42/J45 -> 2.3076923 | ... L44: =L42/L45 -> 2.5
B45: CapEx | C45: =-Statement!M111 -> 67 | D45: =-Statement!N111 -> 46 | E45: =-Statement!O111 -> 61 | F45: =-Statement!P111 -> 102 | G45: =-Statement!Q111 -> 76 | H45: =H7*H46 -> 83.3682 | I45: =I7*I46 -> 106.71077 | J45: =J7*J46 -> 141.93016 | K45: =K7*K46 -> 134.77252 | L45: =L7*L46 -> 160.62377
B46: % of Revenue | C46: =C45/C7 -> 0.015275878 | D46: =D45/D7 -> 0.0091908092 | E46: =E45/E7 -> 0.011096962 | F46: =F45/F7 -> 0.016636764 | G46: =G45/G7 -> 0.010546767 | H46: 0.01 | I46: 0.011 | J46: 0.013 | K46: 0.011 | L46: 0.012

Sheet FCF & Other
B1: Results
C2: History | H2: Forecast
C4: Income statement
B5: $ (thousand) | C5: =Revenue!C5 -> 2022 | D5: =Revenue!D5 -> 2023 | E5: =Revenue!E5 -> 2024 | F5: =Revenue!F5 -> 2025 | G5: =Revenue!G5 -> 2026 | H5: =G5+1 -> 2027 | I5: =H5+1 -> 2028 | J5: =I5+1 -> 2029 | K5: =J5+1 -> 2030 | L5: =K5+1 -> 2031
B6: Revenue | C6: =Revenue!C14 -> 4386 | D6: =Revenue!D14 -> 5005 | E6: =Revenue!E14 -> 5497 | F6: =Revenue!F14 -> 6131 | G6: =Revenue!G14 -> 7206 | H6: =Revenue!H14 -> 8336.82 | I6: =Revenue!I14 -> 9700.9792 | J6: =Revenue!J14 -> 10917.704 | ... L6: =Revenue!L14 -> 13385.314 | N6: From Revenue Sheet
B7: COGS | C7: ='COGS & OpEx'!C14 -> 418 | D7: ='COGS & OpEx'!D14 -> 480 | E7: ='COGS & OpEx'!E14 -> 511 | F7: ='COGS & OpEx'!F14 -> 578 | G7: ='COGS & OpEx'!G14 -> 650 | H7: ='COGS & OpEx'!H14 -> 716.96652 | I7: ='COGS & OpEx'!I14 -> 805.18127 | J7: ='COGS & OpEx'!J14 -> 906.16947 | ... L7: ='COGS & OpEx'!L14 -> 1110.9811 | N7: From COGS and OpEx Sheet
B8: Gross profit | C8: =C6-C7 -> 3968 | D8: =D6-D7 -> 4525 | E8: =E6-E7 -> 4986 | F8: =F6-F7 -> 5553 | G8: =G6-G7 -> 6556 | H8: =H6-H7 -> 7619.8535 | I8: =I6-I7 -> 8895.7979 | J8: =J6-J7 -> 10011.535 | ... L8: =L6-L7 -> 12274.333
B9: OpEx | C9: ='COGS & OpEx'!C18 -> 3350 | D9: ='COGS & OpEx'!D18 -> 3536 | E9: ='COGS & OpEx'!E18 -> 3858 | F9: ='COGS & OpEx'!F18 -> 4199 | G9: ='COGS & OpEx'!G18 -> 4978 | H9: ='COGS & OpEx'!H18 -> 5418.933 | I9: ='COGS & OpEx'!I18 -> 6305.6365 | J9: ='COGS & OpEx'!J18 -> 6987.3308 | ... L9: ='COGS & OpEx'!L18 -> 8298.8948 | N9: From COGS and OpEx Sheet
B10: EBIT | C10: =C8-C9 -> 618 | D10: =D8-D9 -> 989 | E10: =E8-E9 -> 1128 | F10: =F8-F9 -> 1354 | G10: =G8-G9 -> 1578 | H10: =H8-H9 -> 2200.9205 | I10: =I8-I9 -> 2590.1614 | J10: =J8-J9 -> 3024.2041 | ... L10: =L8-L9 -> 3975.4383
C13: Drivers
C14: =C5 -> 2022 | D14: =D5 -> 2023 | E14: =E5 -> 2024 | F14: =F5 -> 2025 | G14: =G5 -> 2026 | H14: =H5 -> 2027 | I14: =I5 -> 2028 | J14: =J5 -> 2029 | ... L14: =L5 -> 2031
B15: Tax rate | C15: =Statement!M84 -> 0.12035398 | D15: =Statement!N84 -> 0.13002114 | E15: =Statement!O84 -> 0.20246479 | F15: =Statement!P84 -> 0.19653179 | G15: =Statement!Q84 -> 0.29881472 | H15: =Overview!$C$26 -> 0.21 | I15: =Overview!$C$26 -> 0.21 | J15: =Overview!$C$26 -> 0.21 | K15: =Overview!$C$26 -> 0.21 | L15: =Overview!$C$26 -> 0.21 | N15: From Statements and Overview sheet
C18: Cash Flow Statement
B19: $ (thousand) | C19: =C5 -> 2022 | D19: =D5 -> 2023 | E19: =E5 -> 2024 | F19: =F5 -> 2025 | G19: =G5 -> 2026 | H19: =H5 -> 2027 | I19: =I5 -> 2028 | J19: =J5 -> 2029 | ... L19: =L5 -> 2031
B20: D&A | C20: ='WC & Investments'!C42 -> 148 | D20: ='WC & Investments'!D42 -> 150 | E20: ='WC & Investments'!E42 -> 139 | F20: ='WC & Investments'!F42 -> 180 | G20: ='WC & Investments'!G42 -> 195 | H20: ='WC & Investments'!H42 -> 216.75732 | I20: ='WC & Investments'!I42 -> 271.62742 | J20: ='WC & Investments'!J42 -> 327.53113 | ... L20: ='WC & Investments'!L42 -> 401.55943 | N20: From WC & Investments Sheet
B21: CapEx | C21: ='WC & Investments'!C45 -> 67 | D21: ='WC & Investments'!D45 -> 46 | E21: ='WC & Investments'!E45 -> 61 | F21: ='WC & Investments'!F45 -> 102 | G21: ='WC & Investments'!G45 -> 76 | H21: ='WC & Investments'!H45 -> 83.3682 | I21: ='WC & Investments'!I45 -> 106.71077 | J21: ='WC & Investments'!J45 -> 141.93016 | ... L21: ='WC & Investments'!L45 -> 160.62377 | N21: From WC & Investments Sheet
B22: Change in NWC | C22: ='WC & Investments'!C35 -> 217 | D22: ='WC & Investments'!D35 -> 692 | E22: ='WC & Investments'!E35 -> -451 | F22: ='WC & Investments'!F35 -> -458 | G22: ='WC & Investments'!G35 -> -501 | H22: ='WC & Investments'!H35 -> 188.79974 | I22: ='WC & Investments'!I35 -> -654.86432 | J22: ='WC & Investments'!J35 -> -1801.8876 | ... L22: ='WC & Investments'!L35 -> -919.8881 | N22: From WC & Investments Sheet
C25: FCFF
B26: $ (thousand) | C26: =C5 -> 2022 | D26: =D5 -> 2023 | E26: =E5 -> 2024 | F26: =F5 -> 2025 | G26: =G5 -> 2026 | H26: =H5 -> 2027 | I26: =I5 -> 2028 | J26: =J5 -> 2029 | ... L26: =L5 -> 2031
B27: NOPAT | C27: =C10*(1-C15) -> 543.62124 | D27: =D10*(1-D15) -> 860.40909 | E27: =E10*(1-E15) -> 899.61972 | F27: =F10*(1-F15) -> 1087.896 | G27: =G10*(1-G15) -> 1106.4704 | H27: =H10*(1-H15) -> 1738.7272 | I27: =I10*(1-I15) -> 2046.2275 | J27: =J10*(1-J15) -> 2389.1213 | ... L27: =L10*(1-L15) -> 3140.5963
B28: FCFF | C28: =C27+C20-C21+C22 -> 841.62124 | D28: =D27+D20-D21+D22 -> 1656.4091 | E28: =E27+E20-E21+E22 -> 526.61972 | F28: =F27+F20-F21+F22 -> 707.89595 | G28: =G27+G20-G21+G22 -> 724.47037 | H28: =H27+H20-H21+H22 -> 2060.916 | I28: =I27+I20-I21+I22 -> 1556.2799 | J28: =J27+J20-J21+J22 -> 772.8346 | ... L28: =L27+L20-L21+L22 -> 2461.6438
C31: Margins
B32: % | C32: =C5 -> 2022 | D32: =D5 -> 2023 | E32: =E5 -> 2024 | F32: =F5 -> 2025 | G32: =G5 -> 2026 | H32: =H5 -> 2027 | I32: =I5 -> 2028 | J32: =J5 -> 2029 | ... L32: =L5 -> 2031
B33: Gross margin | C33: =Statement!M102 -> 0.90469676 | D33: =Statement!N102 -> 0.9040959 | E33: =Statement!O102 -> 0.9070402 | F33: =Statement!P102 -> 0.905725 | G33: =Statement!Q102 -> 0.90979739 | H33: =H8/H6 -> 0.914 | I33: =I8/I6 -> 0.917 | J33: =J8/J6 -> 0.917 | K33: =K8/K6 -> 0.917 | L33: =L8/L6 -> 0.917
B34: Operating margin | C34: =Statement!M103 -> 0.14090287 | D34: =Statement!N103 -> 0.1976024 | E34: =Statement!O103 -> 0.20520284 | F34: =Statement!P103 -> 0.22084489 | G34: =Statement!Q103 -> 0.21898418 | H34: =H10/H6 -> 0.264 | I34: =I10/I6 -> 0.267 | J34: =J10/J6 -> 0.277 | K34: =K10/K6 -> 0.297 | L34: =L10/L6 -> 0.297

Sheet Valuation ->
H5: Links
H6: Overview'!B3
H7: Financials ->'!B13
H8: Analysis ->'!B13
H9: Forecast ->'!B13
H10: Valuation ->'!B13
B13: Valuation ->

Sheet WACC
B1: WACC
B4: Inputs
B5: Shares Outstanding | C5: =Statement!AC79 -> 210
B6: Price | C6: =Overview!C5 -> 233.54
B7: Equity | C7: =C5*C6 -> 49043.4
B8: Debt | C8: =Statement!AC109 -> 3478
B9: Risk free rate | C9: =Overview!F27 -> 0.05244
B10: Beta | C10: =Overview!C13 -> 1.3195
B11: Market risk premium | C11: =[1]Sheet1!$C$12 -> 0.045
B12: Tax rate | C12: =Overview!C26 -> 0.21
B13: Cost of debt | C13: =Overview!C27 -> 0.061
B15: Calculations
B16: Debt/(Debt+Equity) | C16: =C8/(C8+C7) -> 0.066220626
B17: Equity/(Debt+Equity) | C17: =C7/(C8+C7) -> 0.93377937
B18: Cost of debt with tax | C18: =C13*(1-C12) -> 0.04819
B19: Cost of equity | C19: =C9+C10*C11 -> 0.1118175
B20: WACC | C20: =(C17*C19)+(C16*C18) -> 0.10760405

Sheet DCF
B1: DCF
C3: History | H3: Forecast
C5: PV of FCF
B6: $ (thousand) | C6: =Revenue!C5 -> 2022 | D6: =Revenue!D5 -> 2023 | E6: =Revenue!E5 -> 2024 | F6: =Revenue!F5 -> 2025 | G6: =Revenue!G5 -> 2026 | H6: =Revenue!H5 -> 2027 | I6: =Revenue!I5 -> 2028 | J6: =Revenue!J5 -> 2029 | ... L6: =Revenue!L5 -> 2031
B7: FCFF | C7: ='FCF & Other'!C28 -> 841.62124 | D7: ='FCF & Other'!D28 -> 1656.4091 | E7: ='FCF & Other'!E28 -> 526.61972 | F7: ='FCF & Other'!F28 -> 707.89595 | G7: ='FCF & Other'!G28 -> 724.47037 | H7: ='FCF & Other'!H28 -> 2060.916 | I7: ='FCF & Other'!I28 -> 1556.2799 | J7: ='FCF & Other'!J28 -> 772.8346 | ... L7: ='FCF & Other'!L28 -> 2461.6438
B8: Perpetual cashflow | C8: 0 | D8: 0 | E8: 0 | F8: 0 | G8: 0 | H8: 0 | I8: 0 | J8: 0 | K8: 0 | L8: =L7*(1+C14)/(C15-C14) -> 28661.652
B9: Period | H9: 1 | I9: 2 | J9: 3 | K9: 4 | L9: 5
B10: PV of FCFF | H10: =H7/(1+$C$15)^H9 -> 1860.6975 | I10: =I7/(1+$C$15)^I9 -> 1268.5823 | J10: =J7/(1+$C$15)^J9 -> 568.76512 | K10: =K7/(1+$C$15)^K9 -> 1416.2888 | L10: =L7/(1+$C$15)^L9 -> 1476.7349
B11: PV of Perpetual cashflow | L11: =L8/(1+C15)^L9 -> 17194.064
B13: Input parameters
B14: Perpetual growth | C14: 0.02
B15: WACC | C15: =IF(Overview!C28>0,Overview!C28,WACC!C20) -> 0.10760405
B18: Result
B19: Total PV of Unlevered FCF | C19: =SUM(H10:L10) -> 6591.0686
B20: PV of Perpetual cashflow | C20: =L11 -> 17194.064
B21: Enterprise value | C21: =C19+C20 -> 23785.133
B22: (+) Cash | C22: =Statement!AC108 -> 4357
B23: (-) Debt | C23: =Statement!AC109 -> 3478
B24: Equity value | C24: =C21+C22-C23 -> 24664.133
B25: Shares outstanding | C25: =Statement!AC79 -> 210
B26: Price per share | C26: =C24/C25 -> 117.44825

Sheet Multiples
B1: Multiples valuations
C2: History | H2: Forecast
C4: Revenues, earnings cash
B5: Revenues (thousand) | C5: =Revenue!C5 -> 2022 | D5: =Revenue!D5 -> 2023 | E5: =Revenue!E5 -> 2024 | F5: =Revenue!F5 -> 2025 | G5: =Revenue!G5 -> 2026 | H5: =Revenue!H5 -> 2027 | I5: =Revenue!I5 -> 2028 | J5: =Revenue!J5 -> 2029 | ... L5: =Revenue!L5 -> 2031
B6: Revenue | C6: =Revenue!C14 -> 4386 | D6: =Revenue!D14 -> 5005 | E6: =Revenue!E14 -> 5497 | F6: =Revenue!F14 -> 6131 | G6: =Revenue!G14 -> 7206 | H6: =Revenue!H14 -> 8336.82 | I6: =Revenue!I14 -> 9700.9792 | J6: =Revenue!J14 -> 10917.704 | ... L6: =Revenue!L14 -> 13385.314
B7: EBIT | C7: ='FCF & Other'!C10 -> 618 | D7: ='FCF & Other'!D10 -> 989 | E7: ='FCF & Other'!E10 -> 1128 | F7: ='FCF & Other'!F10 -> 1354 | G7: ='FCF & Other'!G10 -> 1578 | H7: ='FCF & Other'!H10 -> 2200.9205 | I7: ='FCF & Other'!I10 -> 2590.1614 | J7: ='FCF & Other'!J10 -> 3024.2041 | ... L7: ='FCF & Other'!L10 -> 3975.4383
B8: FCFF | C8: ='FCF & Other'!C28 -> 841.62124 | D8: ='FCF & Other'!D28 -> 1656.4091 | E8: ='FCF & Other'!E28 -> 526.61972 | F8: ='FCF & Other'!F28 -> 707.89595 | G8: ='FCF & Other'!G28 -> 724.47037 | H8: ='FCF & Other'!H28 -> 2060.916 | I8: ='FCF & Other'!I28 -> 1556.2799 | J8: ='FCF & Other'!J28 -> 772.8346 | ... L8: ='FCF & Other'!L28 -> 2461.6438
B9: PV of FCFF | H9: =DCF!H10 -> 1860.6975 | I9: =DCF!I10 -> 1268.5823 | J9: =DCF!J10 -> 568.76512 | K9: =DCF!K10 -> 1416.2888 | L9: =DCF!L10 -> 1476.7349
C11: Growth rates
B12: % Growth | C12: =C5 -> 2022 | D12: =D5 -> 2023 | E12: =E5 -> 2024 | F12: =F5 -> 2025 | G12: =G5 -> 2026 | H12: =H5 -> 2027 | I12: =I5 -> 2028 | J12: =J5 -> 2029 | ... L12: =L5 -> 2031
B13: Revenue | D13: =(D6-C6)/C6 -> 0.14113087 | E13: =(E6-D6)/D6 -> 0.098301698 | F13: =(F6-E6)/E6 -> 0.11533564 | G13: =(G6-F6)/F6 -> 0.17533844 | H13: =(H6-G6)/G6 -> 0.15692756 | I13: =(I6-H6)/H6 -> 0.16363064 | J13: =(J6-I6)/I6 -> 0.12542293 | K13: =(K6-J6)/J6 -> 0.12221823 | L13: =(L6-K6)/K6 -> 0.092496163
B14: EBIT | D14: =IF(C7=0, IF(D7=0,0,IF(D7>0,1,-1)), (D7-C7)/ABS(C7) ) -> 0.60032362 | E14: =IF(D7=0, IF(E7=0,0,IF(E7>0,1,-1)), (E7-D7)/ABS(D7) ) -> 0.14054601 | F14: =IF(E7=0, IF(F7=0,0,IF(F7>0,1,-1)), (F7-E7)/ABS(E7) ) -> 0.20035461 | G14: =IF(F7=0, IF(G7=0,0,IF(G7>0,1,-1)), (G7-F7)/ABS(F7) ) -> 0.16543575 | H14: =IF(G7=0, IF(H7=0,0,IF(H7>0,1,-1)), (H7-G7)/ABS(G7) ) -> 0.39475316 | I14: =IF(H7=0, IF(I7=0,0,IF(I7>0,1,-1)), (I7-H7)/ABS(H7) ) -> 0.17685372 | J14: =IF(I7=0, IF(J7=0,0,IF(J7>0,1,-1)), (J7-I7)/ABS(I7) ) -> 0.1675736 | K14: =IF(J7=0, IF(K7=0,0,IF(K7>0,1,-1)), (K7-J7)/ABS(J7) ) -> 0.20324481 | L14: =IF(K7=0, IF(L7=0,0,IF(L7>0,1,-1)), (L7-K7)/ABS(K7) ) -> 0.092496163
B15: FCFF | D15: =IF(C8=0, IF(D8=0,0,IF(D8>0,1,-1)), (D8-C8)/ABS(C8) ) -> 0.96811703 | E15: =IF(D8=0, IF(E8=0,0,IF(E8>0,1,-1)), (E8-D8)/ABS(D8) ) -> -0.68207146 | F15: =IF(E8=0, IF(F8=0,0,IF(F8>0,1,-1)), (F8-E8)/ABS(E8) ) -> 0.34422607 | G15: =IF(F8=0, IF(G8=0,0,IF(G8>0,1,-1)), (G8-F8)/ABS(F8) ) -> 0.023413631 | H15: =IF(G8=0, IF(H8=0,0,IF(H8>0,1,-1)), (H8-G8)/ABS(G8) ) -> 1.844721 | I15: =IF(H8=0, IF(I8=0,0,IF(I8>0,1,-1)), (I8-H8)/ABS(H8) ) -> -0.24486013 | J15: =IF(I8=0, IF(J8=0,0,IF(J8>0,1,-1)), (J8-I8)/ABS(I8) ) -> -0.50340899 | K15: =IF(J8=0, IF(K8=0,0,IF(K8>0,1,-1)), (K8-J8)/ABS(J8) ) -> 1.758058 | L15: =IF(K8=0, IF(L8=0,0,IF(L8>0,1,-1)), (L8-K8)/ABS(K8) ) -> 0.15487575
C17: Shares
C18: =C5 -> 2022 | D18: =D5 -> 2023 | E18: =E5 -> 2024 | F18: =F5 -> 2025 | G18: =G5 -> 2026 | H18: =H5 -> 2027 | I18: =I5 -> 2028 | J18: =J5 -> 2029 | ... L18: =L5 -> 2031
B19: Avg diluted shares | C19: =Statement!M23 -> 222 | D19: =Statement!N23 -> 218 | E19: =Statement!O23 -> 216 | F19: =Statement!P23 -> 217 | G19: =Statement!Q23 -> 215 | H19: =G19*(1+H20) -> 213.28 | I19: =H19*(1+I20) -> 211.36048 | J19: =I19*(1+J20) -> 210.30368 | K19: =J19*(1+K20) -> 209.25216 | L19: =K19*(1+L20) -> 209.25216
B20: Dilution rate | D20: =D19/C19-1 -> -0.018018018 | E20: =E19/D19-1 -> -0.0091743119 | F20: =F19/E19-1 -> 0.0046296296 | G20: =G19/F19-1 -> -0.0092165899 | H20: -0.008 | I20: -0.009 | J20: -0.005 | K20: -0.005 | L20: 0
C22: Historical price
C23: =C5 -> 2022 | D23: =D5 -> 2023 | E23: =E5 -> 2024 | F23: =F5 -> 2025 | G23: =G5 -> 2026 | H23: =H5 -> 2027 | I23: =I5 -> 2028 | J23: =J5 -> 2029 | ... L23: =L5 -> 2031
B24: Price | C24: =Statement!M117 -> 249.79 | D24: =Statement!N117 -> 215.16 | E24: =Statement!O117 -> 253.81 | F24: =Statement!P117 -> 311.21 | G24: =Statement!Q117 -> 252.87
C27: Historical ratios
C28: =C5 -> 2022 | D28: =D5 -> 2023 | E28: =E5 -> 2024 | F28: =F5 -> 2025 | G28: =G5 -> 2026 | H28: =H5 -> 2027 | I28: =I5 -> 2028 | J28: =J5 -> 2029 | ... L28: =L5 -> 2031
B29: PS | C29: =C24/(C6/C19) -> 12.643269 | D29: =D24/(D6/D19) -> 9.3716044 | E29: =E24/(E6/E19) -> 9.9732509 | F29: =F24/(F6/F19) -> 11.014936 | G29: =G24/(G6/G19) -> 7.5446919
B30: Market Cap | C30: =C24*C19 -> 55453.38 | D30: =D24*D19 -> 46904.88 | E30: =E24*E19 -> 54822.96 | F30: =F24*F19 -> 67532.57 | G30: =G24*G19 -> 54367.05
B31: Debt | C31: =Statement!M109 -> 2280 | D31: =Statement!N109 -> 2281 | E31: =Statement!O109 -> 2284 | F31: =Statement!P109 -> 2287 | G31: =Statement!Q109 -> 2483
B32: Cash | C32: =Statement!M108 -> 1809 | D32: =Statement!N108 -> 2174 | E32: =Statement!O108 -> 2480 | F32: =Statement!P108 -> 2153 | G32: =Statement!Q108 -> 2973
B33: EV | C33: =C30+C31-C32 -> 55924.38 | D33: =D30+D31-D32 -> 47011.88 | E33: =E30+E31-E32 -> 54626.96 | F33: =F30+F31-F32 -> 67666.57 | G33: =G30+G31-G32 -> 53877.05
B34: EV/EBIT | C34: =C33/C7 -> 90.492524 | D34: =D33/D7 -> 47.534762 | E34: =E33/E7 -> 48.428156 | F34: =F33/F7 -> 49.97531 | G34: =G33/G7 -> 34.142617
B35: EV/FCFF | C35: =C33/C8 -> 66.448394 | D35: =D33/D8 -> 28.381805 | E35: =E33/E8 -> 103.73132 | F35: =F33/F8 -> 95.588299 | G35: =G33/G8 -> 74.3675
B36: EV/Sales | C36: =C33/C6 -> 12.750657 | D36: =D33/D6 -> 9.392983 | E36: =E33/E6 -> 9.9375951 | F36: =F33/F6 -> 11.036792 | G36: =G33/G6 -> 7.476693
B39: EV/EBIT valuation
B40: Year 5 EBIT | C40: =L7 -> 3975.4383
B41: WACC | C41: =IF(Overview!C28>0,Overview!C28,WACC!C20) -> 0.10760405
B42: Applied EV/EBIT ratio | C42: 28
B43: Terminal EV | C43: =(C40*C42) -> 111312.27
B44: PV of Terminal EV | C44: =C43/(1+C41)^5 -> 66775.997
B45: Total EV | C45: =SUM(H9:K9)+C44 -> 71890.331
B46: (+) Cash | C46: =Statement!AC108 -> 4357
B47: (-) Debt | C47: =Statement!AC109 -> 3478
B48: Equity value | C48: =C45+C46-C47 -> 72769.331
B49: Shares outstanding | C49: =Statement!AC79 -> 210
B50: PV of price per share | C50: =C48/C49 -> 346.52062
B52: PS valuation
B53: Year 5 sales | C53: =L6 -> 13385.314
B54: Discount rate | C54: =IF(Overview!C29>0,Overview!C29,WACC!C19) -> 0.1118175
B55: Applied PS ratio | C55: 5
B56: Shares outstanding diluted | C56: =L19 -> 209.25216
B57: Price per share | C57: =(C53*C55)/C56 -> 319.83694
B58: PV of price per share | C58: =C57/(1+C54)^5 -> 188.26132
B60: EV/FCFF valuation
B61: Year 5 FCFF | C61: =L8 -> 2461.6438
B62: WACC | C62: =IF(Overview!C28>0,Overview!C28,WACC!C20) -> 0.10760405
B63: Applied EV/FCFF ratio | C63: 45
B64: Terminal EV | C64: =(C61*C63) -> 110773.97
B65: PV of Terminal EV | C65: =C64/(1+C62)^5 -> 66453.072
B66: Total EV | C66: =SUM(H9:K9)+C65 -> 71567.405
B67: (+) Cash | C67: =Statement!AC108 -> 4357
B68: (-) Debt | C68: =Statement!AC109 -> 3478
B69: Equity value | C69: =C66+C67-C68 -> 72446.405
B70: Shares outstanding | C70: =Statement!AC79 -> 210
B71: PV of price per share | C71: =C69/C70 -> 344.98288
B73: EV/Sales valuation
B74: Year 5 Sales | C74: =L6 -> 13385.314
B75: WACC | C75: =IF(Overview!C28>0,Overview!C28,WACC!C20) -> 0.10760405
B76: Applied EV/Sales ratio | C76: 5
B77: Terminal EV | C77: =(C74*C76) -> 66926.571
B78: PV of Terminal EV | C78: =C77/(1+C75)^5 -> 40149.108
B79: Total EV | C79: =SUM(H9:K9)+C78 -> 45263.442
B80: (+) Cash | C80: =Statement!AC108 -> 4357
B81: (-) Debt | C81: =Statement!AC109 -> 3478
B82: Equity value | C82: =C79+C80-C81 -> 46142.442
B83: Shares outstanding | C83: =Statement!AC79 -> 210
B84: PV of price per share | C84: =C82/C83 -> 219.72591

Sheet AVG target price
B1: AVG target price
B4: AVG target price
B5: DCF price | C5: =DCF!C26 -> 117.44825
B6: EV/EBIT price | C6: =Multiples!C50 -> 346.52062
B7: PS price | C7: =Multiples!C58 -> 188.26132
B8: EV/FCFF price | C8: =Multiples!C71 -> 344.98288
B9: EV/Sales price | C9: =Multiples!C84 -> 219.72591
B10: AVG price | C10: =AVERAGE(C5:C9) -> 243.3878
B11: Current price | C11: =Overview!C5 -> 233.54
B12: Upside/Downside | C12: =(C10-C11)/C11 -> 0.042167502

Sheet DDM
B1: Dividend discount model
C2: History | H2: Forecast
C4: Revenues, earnings cash
B5: Revenues (thousand) | C5: =Revenue!C5 -> 2022 | D5: =Revenue!D5 -> 2023 | E5: =Revenue!E5 -> 2024 | F5: =Revenue!F5 -> 2025 | G5: =Revenue!G5 -> 2026 | H5: =Revenue!H5 -> 2027 | I5: =Revenue!I5 -> 2028 | J5: =Revenue!J5 -> 2029 | ... L5: =Revenue!L5 -> 2031
B6: EPS | C6: =Statement!M27 -> 2.24 | D6: =Statement!N27 -> 3.78 | E6: =Statement!O27 -> 4.19 | F6: =Statement!P27 -> 5.12 | G6: =Statement!Q27 -> 5.23
B7: Dividend per share | C7: =Statement!M83 -> 0 | D7: =Statement!N83 -> 0 | E7: =Statement!O83 -> 0 | F7: =Statement!P83 -> 0 | G7: =Statement!Q83 -> 0
C9: Growth rates
B10: % Growth | C10: =C5 -> 2022 | D10: =D5 -> 2023 | E10: =E5 -> 2024 | F10: =F5 -> 2025 | G10: =G5 -> 2026 | H10: =H5 -> 2027 | I10: =I5 -> 2028 | J10: =J5 -> 2029 | ... L10: =L5 -> 2031
B11: EPS | D11: =(D6-C6)/C6 -> 0.6875 | E11: =(E6-D6)/D6 -> 0.10846561 | F11: =(F6-E6)/E6 -> 0.22195704 | G11: =(G6-F6)/F6 -> 0.021484375
B12: Dividend | D12: =IF(C7=0, IF(D7=0,0,IF(D7>0,1,-1)), (D7-C7)/ABS(C7) ) -> 0 | E12: =IF(D7=0, IF(E7=0,0,IF(E7>0,1,-1)), (E7-D7)/ABS(D7) ) -> 0 | F12: =IF(E7=0, IF(F7=0,0,IF(F7>0,1,-1)), (F7-E7)/ABS(E7) ) -> 0 | G12: =IF(F7=0, IF(G7=0,0,IF(G7>0,1,-1)), (G7-F7)/ABS(F7) ) -> 0
C14: Ratios
B15: % | C15: =C5 -> 2022 | D15: =D5 -> 2023 | E15: =E5 -> 2024 | F15: =F5 -> 2025 | G15: =G5 -> 2026 | H15: =H5 -> 2027 | I15: =I5 -> 2028 | J15: =J5 -> 2029 | ... L15: =L5 -> 2031
B16: Payout | C16: =C7/C6 -> 0 | D16: =D7/D6 -> 0 | E16: =E7/E6 -> 0 | F16: =F7/F6 -> 0 | G16: =G7/G6 -> 0
B20: DDM valuation
B21: Latest dividend | C21: =G7 -> 0
B22: Year 1 growth rate | C22: 0
B23: Year 1 dividend | C23: =C21*(1+C22) -> 0
B24: Discount rate | C24: =IF(Overview!C29>0,Overview!C29,WACC!C19) -> 0.1118175
B25: Perpetual dividend growth | C25: 0
B26: PV of price per share | C26: =C23/(C24-C25) -> 0

Sheet Reverse DCF
B1: Reverse DCF
C3: History | H3: Forecast
C5: PV of FCF
B6: $ (thousand) | C6: =Revenue!C5 -> 2022 | D6: =Revenue!D5 -> 2023 | E6: =Revenue!E5 -> 2024 | F6: =Revenue!F5 -> 2025 | G6: =Revenue!G5 -> 2026 | H6: =Revenue!H5 -> 2027 | I6: =Revenue!I5 -> 2028 | J6: =Revenue!J5 -> 2029 | ... L6: =Revenue!L5 -> 2031
B7: FCFF | C7: ='FCF & Other'!C28 -> 841.62124 | D7: ='FCF & Other'!D28 -> 1656.4091 | E7: ='FCF & Other'!E28 -> 526.61972 | F7: ='FCF & Other'!F28 -> 707.89595 | G7: ='FCF & Other'!G28 -> 724.47037 | H7: =G7*(1+$C$17) -> 1061.3491 | I7: =H7*(1+$C$17) -> 1554.8764 | J7: =I7*(1+$C$17) -> 2277.8939 | K7: =J7*(1+$C$17) -> 3337.1146 | L7: =K7*(1+$C$17) -> 4888.8729
B8: Perpetual cashflow | L8: =L7*(1+C20)/(C21-C20) -> 56922.603
B9: Period | H9: 1 | I9: 2 | J9: 3 | K9: 4 | L9: 5
B10: PV of FCFF | H10: =H7/(1+$C$21)^H9 -> 958.23872 | I10: =I7/(1+$C$21)^I9 -> 1267.4382 | J10: =J7/(1+$C$21)^J9 -> 1676.4087 | K10: =K7/(1+$C$21)^K9 -> 2217.3436 | L10: =L7/(1+$C$21)^L9 -> 2932.8245
B11: PV of Perpetual cashflow | L11: =L8/(1+C21)^L9 -> 34147.749
B14: Growth adjustment
B15: Current Price | C15: =Overview!C5 -> 233.54
B16: Calculated Price | C16: =C36 -> 210.90432
B17: FCFF Growth | C17: 0.465 | E17: Modify until Calculated Price is very close to Current Price
B19: Input parameters
B20: Perpetual growth | C20: 0.02
B21: WACC | C21: =IF(Overview!C28>0,Overview!C28,WACC!C20) -> 0.10760405
B22: Shares outstanding | C22: =Statement!AC76 -> 209
B23: Market cap | C23: =C15*C22 -> 48809.86
B24: Cash | C24: =Statement!AC108 -> 4357
B25: Debt | C25: =Statement!AC109 -> 3478
B26: Enterprise Value | C26: =C23+C25-C24 -> 47930.86
B28: Result
B29: Total PV of Unlevered FCF | C29: =SUM(H10:L10) -> 9052.2537
B30: PV of Perpetual cashflow | C30: =L11 -> 34147.749
B31: Enterprise value | C31: =C29+C30 -> 43200.003
B32: (+) Cash | C32: =C24 -> 4357
B33: (-) Debt | C33: =C25 -> 3478
B34: Equity value | C34: =C31+C32-C33 -> 44079.003
B35: Shares outstanding | C35: =C22 -> 209
B36: Price per share | C36: =C34/C35 -> 210.90432
