Workbook

Sheet Overview
B2: Automatic Data | E2: At a glance | H2: Valuation | K2: Links
B3: Company | C3: #VALUE! | E3: Market capitalization | F3: =Statement!AC154 -> 2662186.8 | H3: ='AVG target price'!B5 -> DCF price | I3: ='AVG target price'!C5 -> 93.81546 | K3: Financials ->'!B13
B4: Ticker | C4: {=_FV(C3,"Ticker symbol",TRUE)} -> AMZN | E4: Enterprise value | F4: =Statement!AC155 -> 2721085.8 | H4: ='AVG target price'!B6 -> EV/EBIT price | I4: ='AVG target price'!C6 -> 385.51692 | K4: Analysis ->'!B13
B5: Price | C5: {=_FV(C3,"Price",TRUE)} -> 243.79 | E5: EPS | F5: =Statement!AC27 -> 6.6066633 | H5: ='AVG target price'!B7 -> PS price | I5: ='AVG target price'!C7 -> 284.18338 | K5: Forecast ->'!B13
B6: Price Extended Hours | C6: {=_FV(C3,"Price (Extended hours)",TRUE)} -> 231.2492 | E6: PE | F6: =Statement!AC151 -> 36.900624 | H6: ='AVG target price'!B8 -> EV/FCFF price | I6: ='AVG target price'!C8 -> 278.1761 | K6: Valuation ->'!B13
B7: Day change | C7: {=_FV(C3,"Change")} -> -10.81 | E7: PS | F7: =Statement!AC152 -> 3.3298702 | H7: ='AVG target price'!B9 -> EV/Sales price | I7: ='AVG target price'!C9 -> 282.71146
B8: Day change extended | C8: {=_FV(C3,"Change (extended hours)",TRUE)} -> -12.5408 | E8: FCF Yield | F8: =Statement!AC162 -> -0.025079006 | H8: ='AVG target price'!B10 -> AVG price | I8: ='AVG target price'!C10 -> 264.88067
B9: Day change % | C9: {=_FV(C3,"Change (%)",TRUE)} -> -0.042459 | E9: Earnings Yield | F9: =Statement!AC163 -> 0.027099813 | H9: ='AVG target price'!B12 -> Upside/Downside | I9: ='AVG target price'!C12 -> 0.086511614
B10: Day change extended % | C10: {=_FV(C3,"Change % (extended hours)",TRUE)} -> -0.051441 | E10: Buyback Yield | F10: =Statement!AC165 -> 0
B11: 52 week high | C11: {=_FV(C3,"52 week high",TRUE)} -> 287.2 | E11: Dividend Yield | F11: =Statement!AC164 -> 0 | H11: DDM price | I11: =DDM!C26 -> 0
B12: 52 week low | C12: {=_FV(C3,"52 week low",TRUE)} -> 196 | E12: ROA | F12: =Statement!AC124 -> 0.057878059
B13: Beta | C13: {=_FV(C3,"Beta")} -> 1.4919 | E13: ROE | F13: =Statement!AC126 -> 0.11728306 | H13: Reverse DCF rate | I13: ='Reverse DCF'!C17 -> 0.03
B14: Avg volume | C14: {=_FV(C3,"Volume average",TRUE)} -> 35430230 | E14: ROIC | F14: =Statement!AC141 -> 0.10099664 | H14: Reverse DCF price | I14: ='Reverse DCF'!C16 -> -30.998311
E15: Net Cash/Market Cap | F15: =Statement!AC177 -> -0.022124293
E16: Net Cash/Share | F16: =Statement!AC176 -> -5.4606898 | H16: Discount rates used
B17: Unit data and other info | E17: Insider Ownership | F17: =Statement!AC172 -> 0.093864469 | H17: WACC | I17: =DCF!C15 -> 0.11325171
B18: Units | C18: M | E18: Net Trade Cycle | F18: =Statement!AC145 -> -38.849641 | H18: Cost of Equity | I18: =Multiples!C54 -> 0.1175855
B19: Units conversion | C19: 1000000 | E19: Net Debt/Equity | F19: =Statement!AC147 -> 0.095989087
B20: Has operating lease | C20: Yes | E20: Quick Ratio | F20: =Statement!AC148 -> 0.82357684
B21: Has finance lease | C21: No
B22: Has debt | C22: Yes
B25: Constants | E25: 10 Year Bond Yield
B26: Default tax rate | C26: 0.21 | E26: #VALUE! | F26: {=_FV(E26,"Price")} -> 50.45
B27: Cost of debt | C27: 0.059 | E27: Percentage | F27: =F26/1000 -> 0.05045
B28: Manual WACC | C28: 0
B29: Manual Cost of Equity | C29: 0
B33: Info
B35: Mission: | C35: Be Earth's most customer-centric company
B36: Auditor: | C36: Ernst & Young
B42: Notes
B44: Date: | C44: 18.09.2026 | E44: Q3 2026
B45: -
B52: Adjustments
B54: Date: | C54: 30.06.2026 | E54: Q2 2026
B55: - | C55: Other income/expense | E55: Taken out 50486 due to paper gains from Anthropic
B57: Date: | C57: 31.03.2026 | E57: Q1 2026
B58: - | C58: Other income/expense | E58: Taken out 12328 due to paper gains from Anthropic
B60: Date: | C60: 30.09.2025 | E60: Q3 2025
B61: - | C61: Other income/expense | E61: Taken out 9000 due to paper gains from Anthropic
B63: Date: | C63: 31.12.2025 | E63: FY 2025
B64: - | C64: Other income/expense | E64: Taken out 13000 due to paper gains from Anthropic
B66: Date: | C66: 31.12.2022 | E66: FY 2022
B67: - | C67: Other income/expense | E67: Added 13870 due to Rivian paper loss and recalculated net income lines
B69: Date: | C69: 31.12.2021 | E69: FY 2021
B70: - | C70: Other income/expense | E70: Taken out 11526 due to paper gains from Rivian and recalculate income lines

Sheet Financials ->
H5: Links
H6: Overview'!B3
H7: Financials ->'!B13
H8: Analysis ->'!B13
H9: Forecast ->'!B13
H10: Valuation ->'!B13
B13: Financials ->

Sheet Statement
B2: Date | M2: 31.12.2021 | N2: 31.12.2022 | O2: 31.12.2023 | P2: 31.12.2024 | Q2: 31.12.2025 | T2: 31.12.2024 | U2: 31.03.2025 | V2: 30.06.2025 | W2: 30.09.2025 | X2: 31.12.2025 | Y2: 31.03.2026 | Z2: 30.06.2026 | AA2: 30.09.2026
B3: FY | M3: 2021 | N3: 2022 | O3: 2023 | P3: 2024 | Q3: 2025 | T3: Q4 2024 | U3: Q1 2025 | V3: Q2 2025 | W3: Q3 2025 | X3: Q4 2025 | Y3: Q1 2026 | Z3: Q2 2026 | AA3: Q3 2026 | AC3: TTM/YTD
B4: Income statement
B5: Revenue | M5: 469822 | N5: 513983 | O5: 574785 | P5: 637959 | Q5: 716924 | T5: 187792 | U5: 155667 | V5: 167702 | W5: 180169 | X5: 213386 | Y5: 181519 | Z5: 200606 | AA5: 201944 | AC5: =SUM(X5:AA5) -> 797455
B6: COGS | M6: =272344+75111 -> 347455 | N6: =288831+84299 -> 373130 | O6: =304739+90619 -> 395358 | P6: =326288+98505 -> 424793 | Q6: =356414+109074 -> 465488 | T6: =98893+27962 -> 126855 | U6: =76976+24593 -> 101569 | V6: =80809+25976 -> 106785 | W6: =88670+27679 -> 116349 | X6: =109959+30826 -> 140785 | Y6: =87463+27289 -> 114752 | Z6: =95778+29633 -> 125411 | AA6: =94573+29997 -> 124570 | AC6: =SUM(X6:AA6) -> 505518
B7: Gross Profit | C7: =C5-C6 -> 0 | D7: =D5-D6 -> 0 | E7: =E5-E6 -> 0 | F7: =F5-F6 -> 0 | G7: =G5-G6 -> 0 | H7: =H5-H6 -> 0 | I7: =I5-I6 -> 0 | J7: =J5-J6 -> 0 | ... Q7: =Q5-Q6 -> 251436 | T7: =T5-T6 -> 60937 | U7: =U5-U6 -> 54098 | V7: =V5-V6 -> 60917 | W7: =W5-W6 -> 63820 | X7: =X5-X6 -> 72601 | Y7: =Y5-Y6 -> 66767 | Z7: =Z5-Z6 -> 75195 | AA7: =AA5-AA6 -> 77374 | AC7: =SUM(X7:AA7) -> 291937
B8: Tech and infra | M8: 56052 | N8: 73213 | O8: 85622 | P8: 88544 | Q8: 108521 | T8: 23571 | U8: 22994 | V8: 27166 | W8: 28962 | X8: 29399 | Y8: 29567 | Z8: 33158 | AA8: 34814 | AC8: =SUM(X8:AA8) -> 126938
B9: Sales and marketing | M9: 32551 | N9: 42238 | O9: 44370 | P9: 43907 | Q9: 47129 | T9: 13124 | U9: 9763 | V9: 11416 | W9: 11686 | X9: 14264 | Y9: 10314 | Z9: 11698 | AA9: 11649 | AC9: =SUM(X9:AA9) -> 47925
B10: General and administrative | M10: 8823 | N10: 11891 | O10: 11816 | P10: 11359 | Q10: 11172 | T10: 2863 | U10: 2628 | V10: 2965 | W10: 2875 | X10: 2704 | Y10: 2587 | Z10: 2788 | AA10: 2701 | AC10: =SUM(X10:AA10) -> 10780
B11: Other expenses/income | M11: 62 | N11: 1263 | O11: 767 | P11: 763 | Q11: 4639 | T11: 176 | U11: 308 | V11: 199 | W11: 2875 | X11: 1257 | Y11: 447 | Z11: 90 | AA11: 134 | AC11: =SUM(X11:AA11) -> 1928
B12: OpEx | M12: =SUM(M8:M11) -> 97488 | N12: =SUM(N8:N11) -> 128605 | O12: =SUM(O8:O11) -> 142575 | P12: =SUM(P8:P11) -> 144573 | Q12: =SUM(Q8:Q11) -> 171461 | T12: =SUM(T8:T11) -> 39734 | U12: =SUM(U8:U11) -> 35693 | V12: =SUM(V8:V11) -> 41746 | W12: =SUM(W8:W11) -> 46398 | X12: =SUM(X8:X11) -> 47624 | Y12: =SUM(Y8:Y11) -> 42915 | Z12: =SUM(Z8:Z11) -> 47734 | AA12: =SUM(AA8:AA11) -> 49298 | AC12: =SUM(X12:AA12) -> 187571
B13: Operating income | M13: 24879 | N13: 12248 | O13: 36852 | P13: 68593 | Q13: 79975 | T13: 21203 | U13: 18405 | V13: 19171 | W13: 17422 | X13: 24977 | Y13: 23852 | Z13: 27461 | AA13: 28076 | AC13: =SUM(X13:AA13) -> 104366
B14: Interest income/expense | M14: =448-1809 -> -1361 | N14: =989-2367 -> -1378 | O14: =2949-3182 -> -233 | P14: =4677-2406 -> 2271 | Q14: =4381-2274 -> 2107 | T14: =1248-570 -> 678 | U14: =1066-541 -> 525 | V14: =1085-516 -> 569 | W14: =1100-538 -> 562 | X14: =1130-679 -> 451 | Y14: =1135-800 -> 335 | Z14: =1295-1314 -> -19 | AA14: =1187-1691 -> -504 | AC14: =SUM(X14:AA14) -> 263
B15: Other income/expense | M15: =14633-11526 -> 3107 | N15: =-16806+13870 -> -2936 | O15: 938 | P15: -2250 | Q15: 2229 | T15: 468 | U15: 2749 | V15: 1117 | W15: =10186-9000 -> 1186 | X15: 1177 | Y15: =15647-12328 -> 3319 | Z15: =53415-50486 -> 2929 | AA15: -703 | AC15: =SUM(X15:AA15) -> 6722
B16: Income before taxes | M16: =38151-11526 -> 26625 | N16: =-5936+13870 -> 7934 | O16: 37557 | P16: 68614 | Q16: 84311 | T16: 22349 | U16: 21679 | V16: 20857 | W16: =28170-9000 -> 19170 | X16: 26605 | Y16: =39834-12328 -> 27506 | Z16: =80857-50486 -> 30371 | AA16: 26869 | AC16: =SUM(X16:AA16) -> 111351
B17: Income tax expense/benefit | M17: -4791 | N17: 3217 | O17: -7120 | P17: -9265 | Q17: -19087 | T17: -2325 | U17: -4553 | V17: -2678 | W17: -6910 | X17: -4946 | Y17: -9560 | Z17: -18199 | AA17: -6180 | AC17: =SUM(X17:AA17) -> -38885
B18: Non-controlling interest | M18: 0 | N18: 0 | O18: 0 | P18: 0 | Q18: 0 | T18: 0 | U18: 0 | V18: 0 | W18: 0 | X18: 0 | Y18: 0 | Z18: 0 | AA18: 0 | AC18: =SUM(X18:AA18) -> 0
B19: Net income | M19: =33364-11526 -> 21838 | N19: =-2722+13870 -> 11148 | O19: 30425 | P19: 59248 | Q19: 64670 | T19: 20004 | U19: 17127 | V19: 18164 | W19: =21187-9000 -> 12187 | X19: 21192 | Y19: =30255-12328 -> 17927 | Z19: =62647-50486 -> 12161 | AA19: 20685 | AC19: =SUM(X19:AA19) -> 71965
B20: Basic Shares outstanding avg | M20: 10117 | N20: 10189 | O20: 10304 | P20: 10473 | Q20: 10656 | T20: 10552 | U20: 10603 | V20: 10637 | W20: 10674 | X20: 10709 | Y20: 10743 | Z20: 10769 | AA20: 10797 | AC20: =AVERAGE(X20:AA20) -> 10754.5
B21: Basic Shares outstanding avg adjusted | C21: =C20*C$86 -> 0 | D21: =D20*D$86 -> 0 | E21: =E20*E$86 -> 0 | F21: =F20*F$86 -> 0 | G21: =G20*G$86 -> 0 | H21: =H20*H$86 -> 0 | I21: =I20*I$86 -> 0 | J21: =J20*J$86 -> 0 | ... Q21: =Q20*Q$86 -> 10656 | T21: =T20*T$86 -> 10552 | U21: =U20*U$86 -> 10603 | V21: =V20*V$86 -> 10637 | W21: =W20*W$86 -> 10674 | X21: =X20*X$86 -> 10709 | Y21: =Y20*Y$86 -> 10743 | Z21: =Z20*Z$86 -> 10769 | AA21: =AA20*AA$86 -> 10797 | AC21: =AC20*AC$86 -> 10754.5
B22: Diluted Shares outstanding avg | M22: 10296 | N22: 10189 | O22: 10492 | P22: 10721 | Q22: 10827 | T22: 10771 | U22: 10793 | V22: 10806 | W22: 10845 | X22: 10863 | Y22: 10874 | Z22: 10903 | AA22: 10929 | AC22: =AVERAGE(X22:AA22) -> 10892.25
B23: Diluted Shares outstanding avg adjusted | C23: =C22*C$86 -> 0 | D23: =D22*D$86 -> 0 | E23: =E22*E$86 -> 0 | F23: =F22*F$86 -> 0 | G23: =G22*G$86 -> 0 | H23: =H22*H$86 -> 0 | I23: =I22*I$86 -> 0 | J23: =J22*J$86 -> 0 | ... Q23: =Q22*Q$86 -> 10827 | T23: =T22*T$86 -> 10771 | U23: =U22*U$86 -> 10793 | V23: =V22*V$86 -> 10806 | W23: =W22*W$86 -> 10845 | X23: =X22*X$86 -> 10863 | Y23: =Y22*Y$86 -> 10874 | Z23: =Z22*Z$86 -> 10903 | AA23: =AA22*AA$86 -> 10929 | AC23: =AC22*AC$86 -> 10892.25
B24: Basic EPS | M24: =M19/M20 -> 2.158545 | N24: =N19/N20 -> 1.0941211 | O24: 2.95 | P24: 5.66 | Q24: =Q19/Q20 -> 6.0688814 | T24: 1.9 | U24: 1.62 | V24: 1.71 | W24: =W19/W20 -> 1.1417463 | X24: 1.98 | Y24: =Y19/Y20 -> 1.6687145 | Z24: =Z19/Z20 -> 1.1292599 | AA24: =AA19/AA20 -> 1.9158099 | AC24: =SUM(X24:AA24) -> 6.6937844
B25: Basic EPS adjusted | M25: =M24/M$86 -> 2.158545 | N25: =N24/N$86 -> 1.0941211 | O25: =O24/O$86 -> 2.95 | P25: =P24/P$86 -> 5.66 | Q25: =Q24/Q$86 -> 6.0688814 | T25: =T24/T$86 -> 1.9 | U25: =U24/U$86 -> 1.62 | V25: =V24/V$86 -> 1.71 | W25: =W24/W$86 -> 1.1417463 | X25: =X24/X$86 -> 1.98 | Y25: =Y24/Y$86 -> 1.6687145 | Z25: =Z24/Z$86 -> 1.1292599 | AA25: =AA24/AA$86 -> 1.9158099 | AC25: =AC24/AC$86 -> 6.6937844
B26: Diluted EPS | M26: =M19/M22 -> 2.1210179 | N26: =N19/N22 -> 1.0941211 | O26: 2.9 | P26: 5.53 | Q26: =Q19/Q22 -> 5.9730304 | T26: 1.86 | U26: 1.59 | V26: 1.68 | W26: =W19/W22 -> 1.1237437 | X26: 1.95 | Y26: =Y19/Y22 -> 1.6486114 | Z26: =Z19/Z22 -> 1.1153811 | AA26: =AA19/AA22 -> 1.8926709 | AC26: =SUM(X26:AA26) -> 6.6066633
B27: Diluted EPS adjusted | M27: =M26/M$86 -> 2.1210179 | N27: =N26/N$86 -> 1.0941211 | O27: =O26/O$86 -> 2.9 | P27: =P26/P$86 -> 5.53 | Q27: =Q26/Q$86 -> 5.9730304 | T27: =T26/T$86 -> 1.86 | U27: =U26/U$86 -> 1.59 | V27: =V26/V$86 -> 1.68 | W27: =W26/W$86 -> 1.1237437 | X27: =X26/X$86 -> 1.95 | Y27: =Y26/Y$86 -> 1.6486114 | Z27: =Z26/Z$86 -> 1.1153811 | AA27: =AA26/AA$86 -> 1.8926709 | AC27: =AC26/AC$86 -> 6.6066633
B29: Balance sheet
B30: Cash and cash equivalents | M30: =36220+59829 -> 96049 | N30: =53888+16138 -> 70026 | O30: =73387+13393 -> 86780 | P30: =78779+22423 -> 101202 | Q30: =86810+36219 -> 123029 | T30: =78779+22423 -> 101202 | U30: =66207+28358 -> 94565 | V30: =57741+35439 -> 93180 | W30: =66922+27275 -> 94197 | X30: =86810+36219 -> 123029 | Y30: =101816+41273 -> 143089 | Z30: =78213+44775 -> 122988 | AA30: =55783+58443 -> 114226 | AC30: =AA30 -> 114226
B31: Acc receivable | M31: 32891 | N31: 42360 | O31: 52253 | P31: 55451 | Q31: 67729 | T31: 55451 | U31: 54216 | V31: 57415 | W31: 61175 | X31: 67729 | Y31: 75532 | Z31: 88092 | AA31: 98242 | AC31: =AA31 -> 98242
B32: Inventory | M32: 32640 | N32: 34405 | O32: 33318 | P32: 34214 | Q32: 38325 | T32: 34214 | U32: 35864 | V32: 40825 | W32: 41494 | X32: 38325 | Y32: 36534 | Z32: 38184 | AA32: 42632 | AC32: =AA32 -> 42632
B33: Current assets | M33: 161580 | N33: 146791 | O33: 172351 | P33: 190867 | Q33: 229083 | T33: 190867 | U33: 184645 | V33: 191420 | W33: 196866 | X33: 229083 | Y33: 255155 | Z33: 249264 | AA33: 255100 | AC33: =AA33 -> 255100
B34: PP&E | M34: 160281 | N34: 186715 | O34: 204177 | P34: 252665 | Q34: 357025 | T34: 252665 | U34: 272781 | V34: 297616 | W34: 324435 | X34: 357025 | Y34: 397458 | Z34: 446046 | AA34: 508862 | AC34: =AA34 -> 508862
B35: Marketable securities and investments | M35: 0 | N35: 0 | O35: 0 | P35: 0 | Q35: 0 | T35: 0 | U35: 0 | V35: 0 | W35: 0 | X35: 0 | Y35: 0 | Z35: 0 | AA35: 0 | AC35: =AA35 -> 0
B36: Goodwill | M36: 15371 | N36: 20288 | O36: 22789 | P36: 23074 | Q36: 23273 | T36: 23074 | U36: 23089 | V36: 23155 | W36: 23260 | X36: 23273 | Y36: 23449 | Z36: 23504 | AA36: 23743 | AC36: =AA36 -> 23743
B37: Long term assets | M37: =M38-M33 -> 258969 | N37: =N38-N33 -> 315884 | O37: =O38-O33 -> 355503 | P37: =P38-P33 -> 434027 | Q37: =Q38-Q33 -> 588959 | T37: =T38-T33 -> 434027 | U37: =U38-U33 -> 458611 | V37: =V38-V33 -> 490750 | W37: =W38-W33 -> 531055 | X37: =X38-X33 -> 588959 | Y37: =Y38-Y33 -> 661475 | Z37: =Z38-Z33 -> 846425 | AA37: =AA38-AA33 -> 988290 | AC37: =AA37 -> 988290
B38: Total assets | M38: 420549 | N38: 462675 | O38: 527854 | P38: 624894 | Q38: 818042 | T38: 624894 | U38: 643256 | V38: 682170 | W38: 727921 | X38: 818042 | Y38: 916630 | Z38: 1095689 | AA38: 1243390 | AC38: =AA38 -> 1243390
B39: Acc payable | M39: 78664 | N39: 79600 | O39: 84981 | P39: 94363 | Q39: 121909 | T39: 94363 | U39: 89241 | V39: 98285 | W39: 106032 | X39: 121909 | Y39: 124749 | Z39: 147440 | AA39: 158715 | AC39: =AA39 -> 158715
B40: Debt | M40: 0 | N40: 0 | O40: 0 | P40: 0 | Q40: 0 | T40: 0 | U40: 0 | V40: 0 | W40: 0 | X40: 0 | Y40: 0 | Z40: 0 | AA40: 0 | AC40: =AA40 -> 0
B41: Current liabilities | M41: 142266 | N41: 155393 | O41: 164917 | P41: 179431 | Q41: 218005 | T41: 179431 | U41: 176171 | V41: 186921 | W41: 195196 | X41: 218005 | Y41: 216756 | Z41: 241274 | AA41: 257982 | AC41: =AA41 -> 257982
B42: Debt | M42: 48744 | N42: 67150 | O42: 58314 | P42: 52623 | Q42: 65648 | T42: 52623 | U42: 53374 | V42: 50718 | W42: 50742 | X42: 65648 | Y42: 119074 | Z42: 128894 | AA42: 173125 | AC42: =AA42 -> 173125
B43: Long term liabilities | M43: =M44-M41 -> 140038 | N43: =N44-N41 -> 161239 | O43: =O44-O41 -> 161062 | P43: =P44-P41 -> 159493 | Q43: =Q44-Q41 -> 188972 | T43: =T44-T41 -> 159493 | U43: =U44-U41 -> 161218 | V43: =V44-V41 -> 161474 | W43: =W44-W41 -> 163094 | X43: =X44-X41 -> 188972 | Y43: =Y44-Y41 -> 257960 | Z43: =Z44-Z41 -> 302795 | AA43: =AA44-AA41 -> 371807 | AC43: =AA43 -> 371807
B44: Total liabilities | M44: =M51-M50 -> 282304 | N44: =N51-N50 -> 316632 | O44: =O51-O50 -> 325979 | P44: =P51-P50 -> 338924 | Q44: =Q51-Q50 -> 406977 | T44: =T51-T50 -> 338924 | U44: =U51-U50 -> 337389 | V44: =V51-V50 -> 348395 | W44: =W51-W50 -> 358290 | X44: =X51-X50 -> 406977 | Y44: =Y51-Y50 -> 474716 | Z44: =Z51-Z50 -> 544069 | AA44: =AA51-AA50 -> 629789 | AC44: =AA44 -> 629789
B45: Treasury stock | M45: -1837 | N45: -7837 | O45: -7837 | P45: -7837 | Q45: -7837 | T45: -7837 | U45: -7837 | V45: -7837 | W45: -7837 | X45: -7837 | Y45: -7837 | Z45: -7837 | AA45: -7837 | AC45: =AA45 -> -7837
B46: Preferred stock | M46: 0 | N46: 0 | O46: 0 | P46: 0 | Q46: 0 | T46: 0 | U46: 0 | V46: 0 | W46: 0 | X46: 0 | Y46: 0 | Z46: 0 | AA46: 0 | AC46: =AA46 -> 0
B47: Paid in capital | M47: 55437 | N47: 75066 | O47: 99025 | P47: 120864 | Q47: 140024 | T47: 120864 | U47: 124514 | V47: 130923 | W47: 135679 | X47: 140024 | Y47: 143979 | Z47: 149619 | AA47: 154924 | AC47: =AA47 -> 154924
B48: Accumulated income/loss | M48: 85915 | N48: 83193 | O48: 113618 | P48: 172866 | Q48: 250536 | T48: 172866 | U48: 189993 | V48: 208157 | W48: 229344 | X48: 250536 | Y48: 280791 | Z48: 343438 | AA48: 364123 | AC48: =AA48 -> 364123
B49: Non-controlling interest | M49: 0 | N49: 0 | O49: 0 | P49: 0 | Q49: 0 | T49: 0 | U49: 0 | V49: 0 | W49: 0 | X49: 0 | Y49: 0 | Z49: 0 | AA49: 0 | AC49: =AA49 -> 0
B50: Stockholder equity | M50: 138245 | N50: 146043 | O50: 201875 | P50: 285970 | Q50: 411065 | T50: 285970 | U50: 305867 | V50: 333775 | W50: 369631 | X50: 411065 | Y50: 441914 | Z50: 551620 | AA50: 613601 | AC50: =AA50 -> 613601
B51: Total liabilities and equity | M51: 420549 | N51: 462675 | O51: 527854 | P51: 624894 | Q51: 818042 | T51: 624894 | U51: 643256 | V51: 682170 | W51: 727921 | X51: 818042 | Y51: 916630 | Z51: 1095689 | AA51: 1243390 | AC51: =AA51 -> 1243390
B53: Cashflow statement
B54: D&A | M54: 34433 | N54: 41921 | O54: 48663 | P54: 52795 | Q54: 65756 | T54: 15631 | U54: 14262 | V54: 15227 | W54: 16796 | X54: 19471 | Y54: 18945 | Z54: 19988 | AA54: 20949 | AC54: =SUM(X54:AA54) -> 79353
B55: Stock-based compensation | M55: 12757 | N55: 19621 | O55: 24023 | P55: 22011 | Q55: 19467 | T55: 4995 | U55: 3689 | V55: 6534 | W55: 4847 | X55: 4397 | Y55: 4032 | Z55: 6038 | AA55: 5406 | AC55: =SUM(X55:AA55) -> 19873
B56: Change in accounts receivable | M56: -9145 | N56: -8622 | O56: -8348 | P56: -3249 | Q56: -7333 | T56: -4023 | U56: 1247 | V56: -1125 | W56: -1977 | X56: -5478 | Y56: -5750 | Z56: -8204 | AA56: -2127 | AC56: =SUM(X56:AA56) -> -21559
B57: Change in inventory | M57: -9487 | N57: -2592 | O57: 1449 | P57: -1884 | Q57: -3002 | T57: 934 | U57: -1222 | V57: -4045 | W57: -827 | X57: 3101 | Y57: 1622 | Z57: -1818 | AA57: -4516 | AC57: =SUM(X57:AA57) -> -1611
B58: Change in accounts payable | M58: 3602 | N58: 2945 | O58: 5473 | P58: 2972 | Q58: 11231 | T58: 8726 | U58: -9043 | V58: 7058 | W58: 2151 | X58: 11065 | Y58: -8737 | Z58: 9442 | AA58: 1502 | AC58: =SUM(X58:AA58) -> 13272
B59: Change in other operating NWC | M59: =-9018+2123+2314 -> -4581 | N59: =-13275-1558+2216 -> -12617 | O59: =-12265-2428+4578 -> -10115 | P59: =-14483-2904+4007 -> -13380 | Q59: =-15632-5019-214 -> -20865 | T59: =-4190+4042+1611 -> 1463 | U59: =-3402-4061+728 -> -6735 | V59: =-2971-4952-119 -> -8042 | W59: =-4039-1999-632 -> -6670 | X59: =-5220+5993-191 -> 582 | Y59: =-3811-8045+355 -> -11501 | Z59: =-4717-2018-281 -> -7016 | AA59: =-4637-3848+3281 -> -5204 | AC59: =SUM(X59:AA59) -> -23139
B60: Operating cashflow | M60: 46327 | N60: 46752 | O60: 84946 | P60: 115877 | Q60: 139514 | T60: 45636 | U60: 17015 | V60: 32515 | W60: 35525 | X60: 54459 | Y60: 26032 | Z60: 45387 | AA60: 42422 | AC60: =SUM(X60:AA60) -> 168300
B61: CapEx | M61: -61053 | N61: -63645 | O61: -52729 | P61: -82999 | Q61: -131819 | T61: -27834 | U61: -25019 | V61: -32183 | W61: -35095 | X61: -39522 | Y61: -44203 | Z61: -54208 | AA61: -77259 | AC61: =SUM(X61:AA61) -> -215192
B62: Capitalized software | M62: 0 | N62: 0 | O62: 0 | P62: 0 | Q62: 0 | T62: 0 | U62: 0 | V62: 0 | W62: 0 | X62: 0 | Y62: 0 | Z62: 0 | AA62: 0 | AC62: =SUM(X62:AA62) -> 0
B63: Investing cashflow | M63: -58154 | N63: -37601 | O63: -49833 | P63: -94342 | Q63: -142545 | T63: -37443 | U63: -29803 | V63: -39424 | W63: -26073 | X63: -47245 | Y63: -64212 | Z63: -79245 | AA63: -113642 | AC63: =SUM(X63:AA63) -> -304344
B64: Repurchase stock | M64: 0 | N64: -6000 | O64: 0 | P64: 0 | Q64: 0 | T64: 0 | U64: 0 | V64: 0 | W64: 0 | X64: 0 | Y64: 0 | Z64: 0 | AA64: 0 | AC64: =SUM(X64:AA64) -> 0
B65: Dividends | M65: 0 | N65: 0 | O65: 0 | P65: 0 | Q65: 0 | T65: 0 | U65: 0 | V65: 0 | W65: 0 | X65: 0 | Y65: 0 | Z65: 0 | AA65: 0 | AC65: =SUM(X65:AA65) -> 0
B66: Dividends to minority interest | M66: 0 | N66: 0 | O66: 0 | P66: 0 | Q66: 0 | T66: 0 | U66: 0 | V66: 0 | W66: 0 | X66: 0 | Y66: 0 | Z66: 0 | AA66: 0 | AC66: =SUM(X66:AA66) -> 0
B67: Financing cashflow | M67: 6291 | N67: 9718 | O67: -15879 | P67: -11812 | Q67: 9661 | T67: -3308 | U67: -47 | V67: -2539 | W67: -44 | X67: 12291 | Y67: 52767 | Z67: 10146 | AA67: 48935 | AC67: =SUM(X67:AA67) -> 124139
B69: Sanity checks
B70: Calculated Net Income | C70: =C5-C6-C12+C14+C15+C17-C18 -> 0 | D70: =D5-D6-D12+D14+D15+D17-D18 -> 0 | E70: =E5-E6-E12+E14+E15+E17-E18 -> 0 | F70: =F5-F6-F12+F14+F15+F17-F18 -> 0 | G70: =G5-G6-G12+G14+G15+G17-G18 -> 0 | H70: =H5-H6-H12+H14+H15+H17-H18 -> 0 | I70: =I5-I6-I12+I14+I15+I17-I18 -> 0 | J70: =J5-J6-J12+J14+J15+J17-J18 -> 0 | ... Q70: =Q5-Q6-Q12+Q14+Q15+Q17-Q18 -> 65224 | T70: =T5-T6-T12+T14+T15+T17-T18 -> 20024 | U70: =U5-U6-U12+U14+U15+U17-U18 -> 17126 | V70: =V5-V6-V12+V14+V15+V17-V18 -> 18179 | W70: =W5-W6-W12+W14+W15+W17-W18 -> 12260 | X70: =X5-X6-X12+X14+X15+X17-X18 -> 21659 | Y70: =Y5-Y6-Y12+Y14+Y15+Y17-Y18 -> 17946 | Z70: =Z5-Z6-Z12+Z14+Z15+Z17-Z18 -> 12172 | AA70: =AA5-AA6-AA12+AA14+AA15+AA17-AA18 -> 20689 | AC70: =AC5-AC6-AC12+AC14+AC15+AC17-AC18 -> 72466
B71: Check Net Income | C71: =C19-C70 -> 0 | D71: =D19-D70 -> 0 | E71: =E19-E70 -> 0 | F71: =F19-F70 -> 0 | G71: =G19-G70 -> 0 | H71: =H19-H70 -> 0 | I71: =I19-I70 -> 0 | J71: =J19-J70 -> 0 | ... Q71: =Q19-Q70 -> -554 | T71: =T19-T70 -> -20 | U71: =U19-U70 -> 1 | V71: =V19-V70 -> -15 | W71: =W19-W70 -> -73 | X71: =X19-X70 -> -467 | Y71: =Y19-Y70 -> -19 | Z71: =Z19-Z70 -> -11 | AA71: =AA19-AA70 -> -4 | AC71: =AC19-AC70 -> -501
B72: Check balance | C72: =C38-(C44+C113) -> 0 | D72: =D38-(D44+D113) -> 0 | E72: =E38-(E44+E113) -> 0 | F72: =F38-(F44+F113) -> 0 | G72: =G38-(G44+G113) -> 0 | H72: =H38-(H44+H113) -> 0 | I72: =I38-(I44+I113) -> 0 | J72: =J38-(J44+J113) -> 0 | ... Q72: =Q38-(Q44+Q113) -> 0 | T72: =T38-(T44+T113) -> 0 | U72: =U38-(U44+U113) -> 0 | V72: =V38-(V44+V113) -> 0 | W72: =W38-(W44+W113) -> 0 | X72: =X38-(X44+X113) -> 0 | Y72: =Y38-(Y44+Y113) -> 0 | Z72: =Z38-(Z44+Z113) -> 0 | AA72: =AA38-(AA44+AA113) -> 0 | AC72: =AC38-(AC44+AC113) -> 0
B74: Other data
B75: Shares outstanding | M75: 10177 | N75: 10247 | O75: 10388 | P75: 10598 | Q75: 10735 | T75: 10598 | U75: 10616 | V75: 10665 | W75: 10690 | X75: 10735 | Y75: 10757 | Z75: 10786 | AA75: 10786 | AC75: =AA75 -> 10786
B76: Split adjusted shares outstanding | M76: =M75*M86 -> 10177 | N76: =N75*N86 -> 10247 | O76: =O75*O86 -> 10388 | P76: =P75*P86 -> 10598 | Q76: =Q75*Q86 -> 10735 | T76: =T75*T86 -> 10598 | U76: =U75*U86 -> 10616 | V76: =V75*V86 -> 10665 | W76: =W75*W86 -> 10690 | X76: =X75*X86 -> 10735 | Y76: =Y75*Y86 -> 10757 | Z76: =Z75*Z86 -> 10786 | AA76: =AA75*AA86 -> 10786 | AC76: =AA76 -> 10786
B77: Dilutive shares | M77: 179 | N77: 0 | O77: 188 | P77: 248 | Q77: 171 | T77: 248 | U77: 190 | V77: 169 | W77: 171 | X77: 171 | Y77: 131 | Z77: 134 | AA77: 134 | AC77: =AA77 -> 134
B78: Split adjusted dilutive shares | M78: =M77*M86 -> 179 | N78: =N77*N86 -> 0 | O78: =O77*O86 -> 188 | P78: =P77*P86 -> 248 | Q78: =Q77*Q86 -> 171 | T78: =T77*T86 -> 248 | U78: =U77*U86 -> 190 | V78: =V77*V86 -> 169 | W78: =W77*W86 -> 171 | X78: =X77*X86 -> 171 | Y78: =Y77*Y86 -> 131 | Z78: =Z77*Z86 -> 134 | AA78: =AA77*AA86 -> 134 | AC78: =AA78 -> 134
B79: Split adjusted diluted shares | M79: =M76+M78 -> 10356 | N79: =N76+N78 -> 10247 | O79: =O76+O78 -> 10576 | P79: =P76+P78 -> 10846 | Q79: =Q76+Q78 -> 10906 | T79: =T76+T78 -> 10846 | U79: =U76+U78 -> 10806 | V79: =V76+V78 -> 10834 | W79: =W76+W78 -> 10861 | X79: =X76+X78 -> 10906 | Y79: =Y76+Y78 -> 10888 | Z79: =Z76+Z78 -> 10920 | AA79: =AA76+AA78 -> 10920 | AC79: =AA79 -> 10920
B80: Shares held by insiders | M80: 1415 | N80: 1294 | O80: 1262 | P80: 1126 | Q80: 1025 | AC80: =Q80 -> 1025
B81: Split adjusted shares held by insiders | M81: =M80*M86 -> 1415 | N81: =N80*N86 -> 1294 | O81: =O80*O86 -> 1262 | P81: =P80*P86 -> 1126 | Q81: =Q80*Q86 -> 1025 | AC81: =Q81 -> 1025
B82: Dividends per share | M82: 0 | N82: 0 | O82: 0 | P82: 0 | Q82: 0 | T82: 0 | U82: 0 | V82: 0 | W82: 0 | X82: 0 | Y82: 0 | Z82: 0 | AA82: 0 | AC82: =SUM(X82:AA82) -> 0
B83: Split adjusted dividends per share | M83: =M82/M86 -> 0 | N83: =N82/N86 -> 0 | O83: =O82/O86 -> 0 | P83: =P82/P86 -> 0 | Q83: =Q82/Q86 -> 0 | T83: =T82/T86 -> 0 | U83: =U82/U86 -> 0 | V83: =V82/V86 -> 0 | W83: =W82/W86 -> 0 | X83: =X82/X86 -> 0 | Y83: =Y82/Y86 -> 0 | Z83: =Z82/Z86 -> 0 | AA83: =AA82/AA86 -> 0 | AC83: =SUM(X83:AA83) -> 0
B84: Tax rate | C84: =IF(AND(C16>0,C17<0),-(C17)/C16,0) -> 0 | D84: =IF(AND(D16>0,D17<0),-(D17)/D16,0) -> 0 | E84: =IF(AND(E16>0,E17<0),-(E17)/E16,0) -> 0 | F84: =IF(AND(F16>0,F17<0),-(F17)/F16,0) -> 0 | G84: =IF(AND(G16>0,G17<0),-(G17)/G16,0) -> 0 | H84: =IF(AND(H16>0,H17<0),-(H17)/H16,0) -> 0 | I84: =IF(AND(I16>0,I17<0),-(I17)/I16,0) -> 0 | J84: =IF(AND(J16>0,J17<0),-(J17)/J16,0) -> 0 | ... Q84: =IF(AND(Q16>0,Q17<0),-(Q17)/Q16,0) -> 0.22638802 | T84: =IF(AND(T16>0,T17<0),-(T17)/T16,0) -> 0.1040315 | U84: =IF(AND(U16>0,U17<0),-(U17)/U16,0) -> 0.21001891 | V84: =IF(AND(V16>0,V17<0),-(V17)/V16,0) -> 0.12839814 | W84: =IF(AND(W16>0,W17<0),-(W17)/W16,0) -> 0.36045905 | X84: =IF(AND(X16>0,X17<0),-(X17)/X16,0) -> 0.18590491 | Y84: =IF(AND(Y16>0,Y17<0),-(Y17)/Y16,0) -> 0.34756053 | Z84: =IF(AND(Z16>0,Z17<0),-(Z17)/Z16,0) -> 0.59922294 | AA84: =IF(AND(AA16>0,AA17<0),-(AA17)/AA16,0) -> 0.23000484 | AC84: =IF(AND(AC16>0,AC17<0),-(AC17)/AC16,0) -> 0.34921105
B85: Employees | M85: 1608000 | N85: 1541000 | O85: 1525000 | P85: 1556000 | Q85: 1576000 | AC85: =Q85 -> 1576000
B86: Stock split factor | M86: 1 | N86: 1 | O86: 1 | P86: 1 | Q86: 1 | T86: 1 | U86: 1 | V86: 1 | W86: 1 | X86: 1 | Y86: 1 | Z86: 1 | AA86: 1 | AC86: 1
B89: Growth rates Income Statement
B90: Revenue | M90: =IF(L5=0, IF(M5=0,0,IF(M5>0,1,-1)), (M5-L5)/ABS(L5) ) -> 1 | N90: =IF(M5=0, IF(N5=0,0,IF(N5>0,1,-1)), (N5-M5)/ABS(M5) ) -> 0.093995173 | O90: =IF(N5=0, IF(O5=0,0,IF(O5>0,1,-1)), (O5-N5)/ABS(N5) ) -> 0.11829574 | P90: =IF(O5=0, IF(P5=0,0,IF(P5>0,1,-1)), (P5-O5)/ABS(O5) ) -> 0.10990892 | Q90: =IF(P5=0, IF(Q5=0,0,IF(Q5>0,1,-1)), (Q5-P5)/ABS(P5) ) -> 0.12377755 | T90: =IF(S5=0, IF(T5=0,0,IF(T5>0,1,-1)), (T5-S5)/ABS(S5) ) -> 1 | U90: =IF(T5=0, IF(U5=0,0,IF(U5>0,1,-1)), (U5-T5)/ABS(T5) ) -> -0.17106693 | V90: =IF(U5=0, IF(V5=0,0,IF(V5>0,1,-1)), (V5-U5)/ABS(U5) ) -> 0.077312468 | W90: =IF(V5=0, IF(W5=0,0,IF(W5>0,1,-1)), (W5-V5)/ABS(V5) ) -> 0.074340199 | X90: =IF(W5=0, IF(X5=0,0,IF(X5>0,1,-1)), (X5-W5)/ABS(W5) ) -> 0.18436579 | Y90: =IF(X5=0, IF(Y5=0,0,IF(Y5>0,1,-1)), (Y5-X5)/ABS(X5) ) -> -0.14933969 | Z90: =IF(Y5=0, IF(Z5=0,0,IF(Z5>0,1,-1)), (Z5-Y5)/ABS(Y5) ) -> 0.10515153 | AA90: =IF(Z5=0, IF(AA5=0,0,IF(AA5>0,1,-1)), (AA5-Z5)/ABS(Z5) ) -> 0.0066697905
B91: COGS | M91: =IF(L6=0, IF(M6=0,0,IF(M6>0,1,-1)), (M6-L6)/ABS(L6) ) -> 1 | N91: =IF(M6=0, IF(N6=0,0,IF(N6>0,1,-1)), (N6-M6)/ABS(M6) ) -> 0.073894461 | O91: =IF(N6=0, IF(O6=0,0,IF(O6>0,1,-1)), (O6-N6)/ABS(N6) ) -> 0.059571731 | P91: =IF(O6=0, IF(P6=0,0,IF(P6>0,1,-1)), (P6-O6)/ABS(O6) ) -> 0.07445151 | Q91: =IF(P6=0, IF(Q6=0,0,IF(Q6>0,1,-1)), (Q6-P6)/ABS(P6) ) -> 0.095799601 | T91: =IF(S6=0, IF(T6=0,0,IF(T6>0,1,-1)), (T6-S6)/ABS(S6) ) -> 1 | U91: =IF(T6=0, IF(U6=0,0,IF(U6>0,1,-1)), (U6-T6)/ABS(T6) ) -> -0.19932994 | V91: =IF(U6=0, IF(V6=0,0,IF(V6>0,1,-1)), (V6-U6)/ABS(U6) ) -> 0.051354252 | W91: =IF(V6=0, IF(W6=0,0,IF(W6>0,1,-1)), (W6-V6)/ABS(V6) ) -> 0.089563141 | X91: =IF(W6=0, IF(X6=0,0,IF(X6>0,1,-1)), (X6-W6)/ABS(W6) ) -> 0.21002329 | Y91: =IF(X6=0, IF(Y6=0,0,IF(Y6>0,1,-1)), (Y6-X6)/ABS(X6) ) -> -0.18491317 | Z91: =IF(Y6=0, IF(Z6=0,0,IF(Z6>0,1,-1)), (Z6-Y6)/ABS(Y6) ) -> 0.09288727 | AA91: =IF(Z6=0, IF(AA6=0,0,IF(AA6>0,1,-1)), (AA6-Z6)/ABS(Z6) ) -> -0.0067059508
B92: Gross Profit | M92: =IF(L7=0, IF(M7=0,0,IF(M7>0,1,-1)), (M7-L7)/ABS(L7) ) -> 1 | N92: =IF(M7=0, IF(N7=0,0,IF(N7>0,1,-1)), (N7-M7)/ABS(M7) ) -> 0.15107014 | O92: =IF(N7=0, IF(O7=0,0,IF(O7>0,1,-1)), (O7-N7)/ABS(N7) ) -> 0.27385998 | P92: =IF(O7=0, IF(P7=0,0,IF(P7>0,1,-1)), (P7-O7)/ABS(O7) ) -> 0.18803747 | Q92: =IF(P7=0, IF(Q7=0,0,IF(Q7>0,1,-1)), (Q7-P7)/ABS(P7) ) -> 0.17953144 | T92: =IF(S7=0, IF(T7=0,0,IF(T7>0,1,-1)), (T7-S7)/ABS(S7) ) -> 1 | U92: =IF(T7=0, IF(U7=0,0,IF(U7>0,1,-1)), (U7-T7)/ABS(T7) ) -> -0.11223066 | V92: =IF(U7=0, IF(V7=0,0,IF(V7>0,1,-1)), (V7-U7)/ABS(U7) ) -> 0.12604902 | W92: =IF(V7=0, IF(W7=0,0,IF(W7>0,1,-1)), (W7-V7)/ABS(V7) ) -> 0.047655006 | X92: =IF(W7=0, IF(X7=0,0,IF(X7>0,1,-1)), (X7-W7)/ABS(W7) ) -> 0.1375901 | Y92: =IF(X7=0, IF(Y7=0,0,IF(Y7>0,1,-1)), (Y7-X7)/ABS(X7) ) -> -0.08035702 | Z92: =IF(Y7=0, IF(Z7=0,0,IF(Z7>0,1,-1)), (Z7-Y7)/ABS(Y7) ) -> 0.12623002 | AA92: =IF(Z7=0, IF(AA7=0,0,IF(AA7>0,1,-1)), (AA7-Z7)/ABS(Z7) ) -> 0.028977991
B93: Sales and marketing | M93: =IF(L8=0, IF(M8=0,0,IF(M8>0,1,-1)), (M8-L8)/ABS(L8) ) -> 1 | N93: =IF(M8=0, IF(N8=0,0,IF(N8>0,1,-1)), (N8-M8)/ABS(M8) ) -> 0.30616214 | O93: =IF(N8=0, IF(O8=0,0,IF(O8>0,1,-1)), (O8-N8)/ABS(N8) ) -> 0.16949176 | P93: =IF(O8=0, IF(P8=0,0,IF(P8>0,1,-1)), (P8-O8)/ABS(O8) ) -> 0.034126743 | Q93: =IF(P8=0, IF(Q8=0,0,IF(Q8>0,1,-1)), (Q8-P8)/ABS(P8) ) -> 0.22561664 | T93: =IF(S8=0, IF(T8=0,0,IF(T8>0,1,-1)), (T8-S8)/ABS(S8) ) -> 1 | U93: =IF(T8=0, IF(U8=0,0,IF(U8>0,1,-1)), (U8-T8)/ABS(T8) ) -> -0.024479233 | V93: =IF(U8=0, IF(V8=0,0,IF(V8>0,1,-1)), (V8-U8)/ABS(U8) ) -> 0.18143864 | W93: =IF(V8=0, IF(W8=0,0,IF(W8>0,1,-1)), (W8-V8)/ABS(V8) ) -> 0.066112052 | X93: =IF(W8=0, IF(X8=0,0,IF(X8>0,1,-1)), (X8-W8)/ABS(W8) ) -> 0.015088737 | Y93: =IF(X8=0, IF(Y8=0,0,IF(Y8>0,1,-1)), (Y8-X8)/ABS(X8) ) -> 0.0057144801 | Z93: =IF(Y8=0, IF(Z8=0,0,IF(Z8>0,1,-1)), (Z8-Y8)/ABS(Y8) ) -> 0.12145297 | AA93: =IF(Z8=0, IF(AA8=0,0,IF(AA8>0,1,-1)), (AA8-Z8)/ABS(Z8) ) -> 0.049942699
B94: R&D | M94: =IF(L9=0, IF(M9=0,0,IF(M9>0,1,-1)), (M9-L9)/ABS(L9) ) -> 1 | N94: =IF(M9=0, IF(N9=0,0,IF(N9>0,1,-1)), (N9-M9)/ABS(M9) ) -> 0.29759454 | O94: =IF(N9=0, IF(O9=0,0,IF(O9>0,1,-1)), (O9-N9)/ABS(N9) ) -> 0.050475875 | P94: =IF(O9=0, IF(P9=0,0,IF(P9>0,1,-1)), (P9-O9)/ABS(O9) ) -> -0.010434979 | Q94: =IF(P9=0, IF(Q9=0,0,IF(Q9>0,1,-1)), (Q9-P9)/ABS(P9) ) -> 0.073382376 | T94: =IF(S9=0, IF(T9=0,0,IF(T9>0,1,-1)), (T9-S9)/ABS(S9) ) -> 1 | U94: =IF(T9=0, IF(U9=0,0,IF(U9>0,1,-1)), (U9-T9)/ABS(T9) ) -> -0.2560957 | V94: =IF(U9=0, IF(V9=0,0,IF(V9>0,1,-1)), (V9-U9)/ABS(U9) ) -> 0.16931271 | W94: =IF(V9=0, IF(W9=0,0,IF(W9>0,1,-1)), (W9-V9)/ABS(V9) ) -> 0.023651016 | X94: =IF(W9=0, IF(X9=0,0,IF(X9>0,1,-1)), (X9-W9)/ABS(W9) ) -> 0.22060585 | Y94: =IF(X9=0, IF(Y9=0,0,IF(Y9>0,1,-1)), (Y9-X9)/ABS(X9) ) -> -0.27692092 | Z94: =IF(Y9=0, IF(Z9=0,0,IF(Z9>0,1,-1)), (Z9-Y9)/ABS(Y9) ) -> 0.13418654 | AA94: =IF(Z9=0, IF(AA9=0,0,IF(AA9>0,1,-1)), (AA9-Z9)/ABS(Z9) ) -> -0.0041887502
B95: General and administrative | M95: =IF(L10=0, IF(M10=0,0,IF(M10>0,1,-1)), (M10-L10)/ABS(L10) ) -> 1 | N95: =IF(M10=0, IF(N10=0,0,IF(N10>0,1,-1)), (N10-M10)/ABS(M10) ) -> 0.34772753 | O95: =IF(N10=0, IF(O10=0,0,IF(O10>0,1,-1)), (O10-N10)/ABS(N10) ) -> -0.0063072912 | P95: =IF(O10=0, IF(P10=0,0,IF(P10>0,1,-1)), (P10-O10)/ABS(O10) ) -> -0.038676371 | Q95: =IF(P10=0, IF(Q10=0,0,IF(Q10>0,1,-1)), (Q10-P10)/ABS(P10) ) -> -0.016462717 | T95: =IF(S10=0, IF(T10=0,0,IF(T10>0,1,-1)), (T10-S10)/ABS(S10) ) -> 1 | U95: =IF(T10=0, IF(U10=0,0,IF(U10>0,1,-1)), (U10-T10)/ABS(T10) ) -> -0.082081732 | V95: =IF(U10=0, IF(V10=0,0,IF(V10>0,1,-1)), (V10-U10)/ABS(U10) ) -> 0.1282344 | W95: =IF(V10=0, IF(W10=0,0,IF(W10>0,1,-1)), (W10-V10)/ABS(V10) ) -> -0.030354132 | X95: =IF(W10=0, IF(X10=0,0,IF(X10>0,1,-1)), (X10-W10)/ABS(W10) ) -> -0.059478261 | Y95: =IF(X10=0, IF(Y10=0,0,IF(Y10>0,1,-1)), (Y10-X10)/ABS(X10) ) -> -0.043269231 | Z95: =IF(Y10=0, IF(Z10=0,0,IF(Z10>0,1,-1)), (Z10-Y10)/ABS(Y10) ) -> 0.077696173 | AA95: =IF(Z10=0, IF(AA10=0,0,IF(AA10>0,1,-1)), (AA10-Z10)/ABS(Z10) ) -> -0.031205165
B96: OpEx | M96: =IF(L12=0, IF(M12=0,0,IF(M12>0,1,-1)), (M12-L12)/ABS(L12) ) -> 1 | N96: =IF(M12=0, IF(N12=0,0,IF(N12>0,1,-1)), (N12-M12)/ABS(M12) ) -> 0.319188 | O96: =IF(N12=0, IF(O12=0,0,IF(O12>0,1,-1)), (O12-N12)/ABS(N12) ) -> 0.10862719 | P96: =IF(O12=0, IF(P12=0,0,IF(P12>0,1,-1)), (P12-O12)/ABS(O12) ) -> 0.014013677 | Q96: =IF(P12=0, IF(Q12=0,0,IF(Q12>0,1,-1)), (Q12-P12)/ABS(P12) ) -> 0.18598217 | T96: =IF(S12=0, IF(T12=0,0,IF(T12>0,1,-1)), (T12-S12)/ABS(S12) ) -> 1 | U96: =IF(T12=0, IF(U12=0,0,IF(U12>0,1,-1)), (U12-T12)/ABS(T12) ) -> -0.10170131 | V96: =IF(U12=0, IF(V12=0,0,IF(V12>0,1,-1)), (V12-U12)/ABS(U12) ) -> 0.16958507 | W96: =IF(V12=0, IF(W12=0,0,IF(W12>0,1,-1)), (W12-V12)/ABS(V12) ) -> 0.11143583 | X96: =IF(W12=0, IF(X12=0,0,IF(X12>0,1,-1)), (X12-W12)/ABS(W12) ) -> 0.026423553 | Y96: =IF(X12=0, IF(Y12=0,0,IF(Y12>0,1,-1)), (Y12-X12)/ABS(X12) ) -> -0.098878717 | Z96: =IF(Y12=0, IF(Z12=0,0,IF(Z12>0,1,-1)), (Z12-Y12)/ABS(Y12) ) -> 0.11229174 | AA96: =IF(Z12=0, IF(AA12=0,0,IF(AA12>0,1,-1)), (AA12-Z12)/ABS(Z12) ) -> 0.032764906
B97: Operating income | M97: =IF(L13=0, IF(M13=0,0,IF(M13>0,1,-1)), (M13-L13)/ABS(L13) ) -> 1 | N97: =IF(M13=0, IF(N13=0,0,IF(N13>0,1,-1)), (N13-M13)/ABS(M13) ) -> -0.50769725 | O97: =IF(N13=0, IF(O13=0,0,IF(O13>0,1,-1)), (O13-N13)/ABS(N13) ) -> 2.0088178 | P97: =IF(O13=0, IF(P13=0,0,IF(P13>0,1,-1)), (P13-O13)/ABS(O13) ) -> 0.86131011 | Q97: =IF(P13=0, IF(Q13=0,0,IF(Q13>0,1,-1)), (Q13-P13)/ABS(P13) ) -> 0.1659353 | T97: =IF(S13=0, IF(T13=0,0,IF(T13>0,1,-1)), (T13-S13)/ABS(S13) ) -> 1 | U97: =IF(T13=0, IF(U13=0,0,IF(U13>0,1,-1)), (U13-T13)/ABS(T13) ) -> -0.13196246 | V97: =IF(U13=0, IF(V13=0,0,IF(V13>0,1,-1)), (V13-U13)/ABS(U13) ) -> 0.041619125 | W97: =IF(V13=0, IF(W13=0,0,IF(W13>0,1,-1)), (W13-V13)/ABS(V13) ) -> -0.091231548 | X97: =IF(W13=0, IF(X13=0,0,IF(X13>0,1,-1)), (X13-W13)/ABS(W13) ) -> 0.43364711 | Y97: =IF(X13=0, IF(Y13=0,0,IF(Y13>0,1,-1)), (Y13-X13)/ABS(X13) ) -> -0.045041438 | Z97: =IF(Y13=0, IF(Z13=0,0,IF(Z13>0,1,-1)), (Z13-Y13)/ABS(Y13) ) -> 0.15130807 | AA97: =IF(Z13=0, IF(AA13=0,0,IF(AA13>0,1,-1)), (AA13-Z13)/ABS(Z13) ) -> 0.022395397
B98: Income before taxes | M98: =IF(L16=0, IF(M16=0,0,IF(M16>0,1,-1)), (M16-L16)/ABS(L16) ) -> 1 | N98: =IF(M16=0, IF(N16=0,0,IF(N16>0,1,-1)), (N16-M16)/ABS(M16) ) -> -0.70200939 | O98: =IF(N16=0, IF(O16=0,0,IF(O16>0,1,-1)), (O16-N16)/ABS(N16) ) -> 3.7336778 | P98: =IF(O16=0, IF(P16=0,0,IF(P16>0,1,-1)), (P16-O16)/ABS(O16) ) -> 0.82692973 | Q98: =IF(P16=0, IF(Q16=0,0,IF(Q16>0,1,-1)), (Q16-P16)/ABS(P16) ) -> 0.22877255 | T98: =IF(S16=0, IF(T16=0,0,IF(T16>0,1,-1)), (T16-S16)/ABS(S16) ) -> 1 | U98: =IF(T16=0, IF(U16=0,0,IF(U16>0,1,-1)), (U16-T16)/ABS(T16) ) -> -0.02997897 | V98: =IF(U16=0, IF(V16=0,0,IF(V16>0,1,-1)), (V16-U16)/ABS(U16) ) -> -0.037916878 | W98: =IF(V16=0, IF(W16=0,0,IF(W16>0,1,-1)), (W16-V16)/ABS(V16) ) -> -0.080884116 | X98: =IF(W16=0, IF(X16=0,0,IF(X16>0,1,-1)), (X16-W16)/ABS(W16) ) -> 0.38784559 | Y98: =IF(X16=0, IF(Y16=0,0,IF(Y16>0,1,-1)), (Y16-X16)/ABS(X16) ) -> 0.033865815 | Z98: =IF(Y16=0, IF(Z16=0,0,IF(Z16>0,1,-1)), (Z16-Y16)/ABS(Y16) ) -> 0.10415909 | AA98: =IF(Z16=0, IF(AA16=0,0,IF(AA16>0,1,-1)), (AA16-Z16)/ABS(Z16) ) -> -0.11530737
B99: Net income | M99: =IF(L19=0, IF(M19=0,0,IF(M19>0,1,-1)), (M19-L19)/ABS(L19) ) -> 1 | N99: =IF(M19=0, IF(N19=0,0,IF(N19>0,1,-1)), (N19-M19)/ABS(M19) ) -> -0.48951369 | O99: =IF(N19=0, IF(O19=0,0,IF(O19>0,1,-1)), (O19-N19)/ABS(N19) ) -> 1.7291891 | P99: =IF(O19=0, IF(P19=0,0,IF(P19>0,1,-1)), (P19-O19)/ABS(O19) ) -> 0.94734593 | Q99: =IF(P19=0, IF(Q19=0,0,IF(Q19>0,1,-1)), (Q19-P19)/ABS(P19) ) -> 0.091513638 | T99: =IF(S19=0, IF(T19=0,0,IF(T19>0,1,-1)), (T19-S19)/ABS(S19) ) -> 1 | U99: =IF(T19=0, IF(U19=0,0,IF(U19>0,1,-1)), (U19-T19)/ABS(T19) ) -> -0.14382124 | V99: =IF(U19=0, IF(V19=0,0,IF(V19>0,1,-1)), (V19-U19)/ABS(U19) ) -> 0.060547673 | W99: =IF(V19=0, IF(W19=0,0,IF(W19>0,1,-1)), (W19-V19)/ABS(V19) ) -> -0.32905748 | X99: =IF(W19=0, IF(X19=0,0,IF(X19>0,1,-1)), (X19-W19)/ABS(W19) ) -> 0.73890211 | Y99: =IF(X19=0, IF(Y19=0,0,IF(Y19>0,1,-1)), (Y19-X19)/ABS(X19) ) -> -0.15406757 | Z99: =IF(Y19=0, IF(Z19=0,0,IF(Z19>0,1,-1)), (Z19-Y19)/ABS(Y19) ) -> -0.32163775 | AA99: =IF(Z19=0, IF(AA19=0,0,IF(AA19>0,1,-1)), (AA19-Z19)/ABS(Z19) ) -> 0.7009292
B101: Margins
B102: Gross margin | M102: =M7/M5 -> 0.26045396 | N102: =N7/N5 -> 0.27404214 | O102: =O7/O5 -> 0.31216368 | P102: =P7/P5 -> 0.33413746 | Q102: =Q7/Q5 -> 0.350715 | T102: =T7/T5 -> 0.32449199 | U102: =U7/U5 -> 0.34752388 | V102: =V7/V5 -> 0.36324552 | W102: =W7/W5 -> 0.35422298 | X102: =X7/X5 -> 0.34023319 | Y102: =Y7/Y5 -> 0.36782375 | Z102: =Z7/Z5 -> 0.37483924 | AA102: =AA7/AA5 -> 0.38314582 | AC102: =AC7/AC5 -> 0.36608586
B103: Operating margin | M103: =M13/M5 -> 0.052954098 | N103: =N13/N5 -> 0.023829582 | O103: =O13/O5 -> 0.064114408 | P103: =P13/P5 -> 0.10751945 | Q103: =Q13/Q5 -> 0.11155297 | T103: =T13/T5 -> 0.11290683 | U103: =U13/U5 -> 0.11823315 | V103: =V13/V5 -> 0.11431587 | W103: =W13/W5 -> 0.0966981 | X103: =X13/X5 -> 0.11705079 | Y103: =Y13/Y5 -> 0.13140222 | Z103: =Z13/Z5 -> 0.13689022 | AA103: =AA13/AA5 -> 0.13902864 | AC103: =AC13/AC5 -> 0.13087384
B104: Net margin | M104: =M112/M5 -> 0.046481433 | N104: =N112/N5 -> 0.021689433 | O104: =O112/O5 -> 0.052932836 | P104: =P112/P5 -> 0.092871172 | Q104: =Q112/Q5 -> 0.090204819 | T104: =T112/T5 -> 0.10652211 | U104: =U112/U5 -> 0.11002332 | V104: =V112/V5 -> 0.10831117 | W104: =W112/W5 -> 0.067642047 | X104: =X112/X5 -> 0.099312982 | Y104: =Y112/Y5 -> 0.098761011 | Z104: =Z112/Z5 -> 0.060621317 | AA104: =AA112/AA5 -> 0.10242939 | AC104: =AC112/AC5 -> 0.090243337
B106: Adjustments
B107: Tax rate | C107: =IF(AND(C84>=0,C13>=0),C84,0) -> 0 | D107: =IF(AND(D84>=0,D13>=0),D84,0) -> 0 | E107: =IF(AND(E84>=0,E13>=0),E84,0) -> 0 | F107: =IF(AND(F84>=0,F13>=0),F84,0) -> 0 | G107: =IF(AND(G84>=0,G13>=0),G84,0) -> 0 | H107: =IF(AND(H84>=0,H13>=0),H84,0) -> 0 | I107: =IF(AND(I84>=0,I13>=0),I84,0) -> 0 | J107: =IF(AND(J84>=0,J13>=0),J84,0) -> 0 | ... Q107: =IF(AND(Q84>=0,Q13>=0),Q84,0) -> 0.22638802 | T107: =IF(AND(T84>=0,T13>=0),T84,0) -> 0.1040315 | U107: =IF(AND(U84>=0,U13>=0),U84,0) -> 0.21001891 | V107: =IF(AND(V84>=0,V13>=0),V84,0) -> 0.12839814 | W107: =IF(AND(W84>=0,W13>=0),W84,0) -> 0.36045905 | X107: =IF(AND(X84>=0,X13>=0),X84,0) -> 0.18590491 | Y107: =IF(AND(Y84>=0,Y13>=0),Y84,0) -> 0.34756053 | Z107: =IF(AND(Z84>=0,Z13>=0),Z84,0) -> 0.59922294 | AA107: =IF(AND(AA84>=0,AA13>=0),AA84,0) -> 0.23000484 | AC107: =IF(AND(AC84>=0,AC13>=0),AC84,0) -> 0.34921105
B108: Cash | M108: =M30+M35 -> 96049 | N108: =N30+N35 -> 70026 | O108: =O30+O35 -> 86780 | P108: =P30+P35 -> 101202 | Q108: =Q30+Q35 -> 123029 | T108: =T30+T35 -> 101202 | U108: =U30+U35 -> 94565 | V108: =V30+V35 -> 93180 | W108: =W30+W35 -> 94197 | X108: =X30+X35 -> 123029 | Y108: =Y30+Y35 -> 143089 | Z108: =Z30+Z35 -> 122988 | AA108: =AA30+AA35 -> 114226 | AC108: =AA108 -> 114226
B109: Debt | C109: 0 | D109: 0 | E109: 0 | F109: 0 | G109: 0 | H109: 0 | I109: 0 | J109: 0 | K109: 0 | L109: 0 | M109: =M40+M42 -> 48744 | N109: =N40+N42 -> 67150 | O109: =O40+O42 -> 58314 | P109: =P40+P42 -> 52623 | Q109: =Q40+Q42 -> 65648 | T109: =T40+T42 -> 52623 | U109: =U40+U42 -> 53374 | V109: =V40+V42 -> 50718 | W109: =W40+W42 -> 50742 | X109: =X40+X42 -> 65648 | Y109: =Y40+Y42 -> 119074 | Z109: =Z40+Z42 -> 128894 | AA109: =AA40+AA42 -> 173125 | AC109: =AA109 -> 173125
...

Sheet Analysis ->
H5: Links
H6: Overview'!B3
H7: Financials ->'!B13
H8: Analysis ->'!B13
H9: Forecast ->'!B13
H10: Valuation ->'!B13
B13: Analysis ->

Sheet Basic
B1: TTM/YTD data
B4: Overview | E4: CAGR
B5: Price | C5: =Overview!C5 -> 243.79 | F5: 5Y | G5: 10Y
B6: Market capitalization | C6: =Statement!AC154 -> 2662186.8 | E6: Revenue | F6: =IF(Statement!M5<=0,"N/A",_xlfn.RRI(4,Statement!M5,Statement!Q5)) -> 0.11143724 | G6: =IF(Statement!H5<=0,"N/A",_xlfn.RRI(9,Statement!H5,Statement!Q5)) -> N/A
B7: Enterprise value | C7: =Statement!AC155 -> 2721085.8 | E7: Net income | F7: =IF(OR(Statement!M19<=0, Statement!Q19<=0), "N/A", _xlfn.RRI(4, Statement!M19, Statement!Q19)) -> 0.31181472 | G7: =IF(OR(Statement!H19<=0, Statement!Q19<=0), "N/A", _xlfn.RRI(9, Statement!H19, Statement!Q19)) -> N/A
B8: PE | C8: =Statement!AC151 -> 36.900624 | E8: EPS | F8: =IF(OR(Statement!M27<=0, Statement!Q27<=0), "N/A", _xlfn.RRI(4, Statement!M27, Statement!Q27)) -> 0.29542597 | G8: =IF(OR(Statement!H27<=0, Statement!Q27<=0), "N/A", _xlfn.RRI(9, Statement!H27, Statement!Q27)) -> N/A
B9: PS | C9: =Statement!AC152 -> 3.3298702 | E9: Dividend | F9: =IF(Statement!M83<=0,"N/A",_xlfn.RRI(4,Statement!M83,Statement!Q83)) -> N/A | G9: =IF(Statement!H83<=0,"N/A",_xlfn.RRI(9,Statement!H83,Statement!Q83)) -> N/A
B10: PB | C10: =Statement!AC153 -> 4.2853889 | E10: Price | F10: =IF(Statement!M118<=0,"N/A",_xlfn.RRI(4,Statement!M118,Statement!Q118)) -> 0.084729456 | G10: =IF(Statement!H118<=0,"N/A",_xlfn.RRI(9,Statement!H118,Statement!Q118)) -> N/A
B11: EV/Revenue | C11: =Statement!AC156 -> 3.4122124
B12: EV/EBIT | C12: =Statement!AC157 -> 26.072531
B15: Margins | E15: Earnings quality
B16: Gross margin | C16: =Statement!AC102 -> 0.36608586 | E16: Net income | F16: =Statement!AC19 -> 71965
B17: Operating margin | C17: =Statement!AC103 -> 0.13087384 | E17: Operating cash | F17: =Statement!AC60 -> 168300
B18: Net margin | C18: =Statement!AC104 -> 0.090243337 | E18: Cash accruals | F18: =IF(OR(F16<=0, F17<=0),"N/A",F16-F17) -> -96335
B21: DuPont Identity | E21: Performance indicators
B22: Profit Margin (Earnings/Revenue) | C22: =Statement!AC122 -> 0.090243337 | E22: ROA | F22: =C24 -> 0.057878059
B23: Asset Turnover (Revenue/Total assets) | C23: =Statement!AC123 -> 0.64135549 | E23: ROE | F23: =C26 -> 0.11728306
B24: ROA | C24: =Statement!AC124 -> 0.057878059 | E24: ROIC | F24: =Statement!AC141 -> 0.10099664
B25: Equity Multiplier (Total assets/Equity) | C25: =Statement!AC125 -> 2.026382
B26: ROE | C26: =Statement!AC126 -> 0.11728306
B29: Cash conversion cycle | E29: Liquidity ratios
B30: DSO | C30: =Statement!AC142 -> 44.96596 | E30: Debt/Equity | F30: =Statement!AC146 -> 0.28214589
B31: DIO | C31: =Statement!AC143 -> 30.781654 | E31: Net Debt/Equity | F31: =Statement!AC147 -> 0.095989087
B32: DPO | C32: =Statement!AC144 -> 114.59725 | E32: Current ratio | F32: =Statement!AC149 -> 0.98882868
B33: Net trade cycle | C33: =Statement!AC145 -> -38.849641 | E33: Quick ratio | F33: =Statement!AC148 -> 0.82357684
E34: Interest coverage | F34: =Statement!AC150 -> N/A
B37: Earnings yields | E37: Payout ratios
B38: Earnings yield | C38: =Statement!AC163 -> 0.027099813 | E38: Dividend payout ratio | F38: =Statement!AC169 -> 0
B39: FCF yield | C39: =Statement!AC162 -> -0.025079006 | E39: Buyback payout ratio | F39: =Statement!AC170 -> 0
B40: Dividend yield | C40: =Statement!AC164 -> 0 | E40: Full payout ratio | F40: =Statement!AC171 -> 0
B41: Buyback yield | C41: =Statement!AC165 -> 0
B42: Total shareholder yield | C42: =Statement!AC166 -> 0
B45: Ownership | E45: Cash holdings
B46: Insider ownership | C46: =Statement!AC172 -> 0.093864469 | E46: Cash per share | F46: =Statement!AC173 -> 10.59021
E47: Net cash per share | F47: =Statement!AC176 -> -5.4606898
E48: Net cash to market cap | F48: =Statement!AC177 -> -0.022124293
B51: Stock based compensation | E51: CapEx usage
B52: Stock based compensation % OCF | C52: =Statement!AC174 -> 0.11808081 | E52: Capex to Revenue | F52: =Statement!AC178 -> 0.26984846
B53: Stock based compensation % Revenue | C53: =Statement!AC175 -> 0.024920528 | E53: CapEx to OCF | F53: =Statement!AC179 -> 1.2786215
E54: CapEx to D&A | F54: =Statement!AC180 -> 2.7118319
B57: FCF ratios
B58: P/FCF | C58: =Statement!AC160 -> -39.873988
B59: EV/FCF | C59: =Statement!AC161 -> -26.953249
B60: FCFF/Sales | C60: =Statement!AC167 -> -0.12659744
B61: FCFE/Sales | C61: =Statement!AC168 -> -0.083722592

Sheet Yearly Analysis
C2: =Statement!M2 -> 31.12.2021 | D2: =Statement!N2 -> 31.12.2022 | E2: =Statement!O2 -> 31.12.2023 | F2: =Statement!P2 -> 31.12.2024 | G2: =Statement!Q2 -> 31.12.2025
C3: =Statement!M3 -> 2021 | D3: =Statement!N3 -> 2022 | E3: =Statement!O3 -> 2023 | F3: =Statement!P3 -> 2024 | G3: =Statement!Q3 -> 2025 | I3: =Statement!AC3 -> TTM/YTD
B5: Overview
B6: Price | C6: =Statement!M117 -> 166.72 | D6: =Statement!N117 -> 83.99 | E6: =Statement!O117 -> 151.94 | F6: =Statement!P117 -> 219.39 | G6: =Statement!Q117 -> 230.82 | I6: =Statement!AC117 -> 243.79
B7: Market capitalization | C7: =Statement!M154 -> 1726552.3 | D7: =Statement!N154 -> 860645.53 | E7: =Statement!O154 -> 1606917.4 | F7: =Statement!P154 -> 2379503.9 | G7: =Statement!Q154 -> 2517322.9 | I7: =Statement!AC154 -> 2662186.8
B8: Enterprise value | C8: =Statement!M155 -> 1679247.3 | D8: =Statement!N155 -> 857769.53 | E8: =Statement!O155 -> 1578451.4 | F8: =Statement!P155 -> 2330924.9 | G8: =Statement!Q155 -> 2459941.9 | I8: =Statement!AC155 -> 2721085.8
B9: PE | C9: =Statement!M151 -> 78.60377 | D9: =Statement!N151 -> 76.764811 | E9: =Statement!O151 -> 52.393103 | F9: =Statement!P151 -> 39.672694 | G9: =Statement!Q151 -> 38.643701 | I9: =Statement!AC151 -> 36.900624
B10: PS | C10: =Statement!M152 -> 3.6536159 | D10: =Statement!N152 -> 1.6649852 | E10: =Statement!O152 -> 2.7734796 | F10: =Statement!P152 -> 3.686883 | G10: =Statement!Q152 -> 3.4858481 | I10: =Statement!AC152 -> 3.3298702
B11: PB | C11: =Statement!M153 -> 12.273207 | D11: =Statement!N153 -> 5.8930968 | E11: =Statement!O153 -> 7.8184655 | F11: =Statement!P153 -> 8.1305564 | G11: =Statement!Q153 -> 6.0278854 | I11: =Statement!AC153 -> 4.2853889
B12: EV/Revenue | C12: =Statement!M156 -> 3.5742203 | D12: =Statement!N156 -> 1.6688675 | E12: =Statement!O156 -> 2.7461598 | F12: =Statement!P156 -> 3.6537222 | G12: =Statement!Q156 -> 3.431245 | I12: =Statement!AC156 -> 3.4122124
B13: EV/EBIT | C13: =Statement!M157 -> 67.496576 | D13: =Statement!N157 -> 70.033436 | E13: =Statement!O157 -> 42.832178 | F13: =Statement!P157 -> 33.981965 | G13: =Statement!Q157 -> 30.758886 | I13: =Statement!AC157 -> 26.072531
B15: Margins
B16: Gross margin | C16: =Statement!M102 -> 0.26045396 | D16: =Statement!N102 -> 0.27404214 | E16: =Statement!O102 -> 0.31216368 | F16: =Statement!P102 -> 0.33413746 | G16: =Statement!Q102 -> 0.350715 | I16: =Statement!AC102 -> 0.36608586
B17: Operating margin | C17: =Statement!M103 -> 0.052954098 | D17: =Statement!N103 -> 0.023829582 | E17: =Statement!O103 -> 0.064114408 | F17: =Statement!P103 -> 0.10751945 | G17: =Statement!Q103 -> 0.11155297 | I17: =Statement!AC103 -> 0.13087384
B18: Net margin | C18: =Statement!M104 -> 0.046481433 | D18: =Statement!N104 -> 0.021689433 | E18: =Statement!O104 -> 0.052932836 | F18: =Statement!P104 -> 0.092871172 | G18: =Statement!Q104 -> 0.090204819 | I18: =Statement!AC104 -> 0.090243337
B20: Earnings quality
B21: Net income | C21: =Statement!M19 -> 21838 | D21: =Statement!N19 -> 11148 | E21: =Statement!O19 -> 30425 | F21: =Statement!P19 -> 59248 | G21: =Statement!Q19 -> 64670 | I21: =Statement!AC19 -> 71965
B22: Operating cash | C22: =Statement!M60 -> 46327 | D22: =Statement!N60 -> 46752 | E22: =Statement!O60 -> 84946 | F22: =Statement!P60 -> 115877 | G22: =Statement!Q60 -> 139514 | I22: =Statement!AC60 -> 168300
B23: Cash accruals | C23: =IF(OR(C21<=0, C22<=0),"N/A",C21-C22) -> -24489 | D23: =IF(OR(D21<=0, D22<=0),"N/A",D21-D22) -> -35604 | E23: =IF(OR(E21<=0, E22<=0),"N/A",E21-E22) -> -54521 | F23: =IF(OR(F21<=0, F22<=0),"N/A",F21-F22) -> -56629 | G23: =IF(OR(G21<=0, G22<=0),"N/A",G21-G22) -> -74844 | I23: =IF(OR(I21<=0, I22<=0),"N/A",I21-I22) -> -96335
B25: DuPont Identity
B26: Profit Margin (Earnings/Revenue) | C26: =Statement!M122 -> 0.046481433 | D26: =Statement!N122 -> 0.021689433 | E26: =Statement!O122 -> 0.052932836 | F26: =Statement!P122 -> 0.092871172 | G26: =Statement!Q122 -> 0.090204819 | I26: =Statement!AC122 -> 0.090243337
B27: Asset Turnover (Revenue/Total assets) | C27: =Statement!M123 -> 1.1171635 | D27: =Statement!N123 -> 1.1108943 | E27: =Statement!O123 -> 1.0889091 | F27: =Statement!P123 -> 1.0209075 | G27: =Statement!Q123 -> 0.87639021 | I27: =Statement!AC123 -> 0.64135549
B28: ROA | C28: =Statement!M124 -> 0.051927362 | D28: =Statement!N124 -> 0.024094667 | E28: =Statement!O124 -> 0.057639044 | F28: =Statement!P124 -> 0.09481288 | G28: =Statement!Q124 -> 0.079054621 | I28: =Statement!AC124 -> 0.057878059
B29: Equity Multiplier (Total assets/Equity) | C29: =Statement!M125 -> 3.0420558 | D29: =Statement!N125 -> 3.1680738 | E29: =Statement!O125 -> 2.6147567 | F29: =Statement!P125 -> 2.1851733 | G29: =Statement!Q125 -> 1.9900551 | I29: =Statement!AC125 -> 2.026382
B30: ROE | C30: =Statement!M126 -> 0.15796593 | D30: =Statement!N126 -> 0.076333683 | E30: =Statement!O126 -> 0.15071207 | F30: =Statement!P126 -> 0.20718257 | G30: =Statement!Q126 -> 0.15732305 | I30: =Statement!AC126 -> 0.11728306
B32: Performance Indicators
B33: ROA | C33: =C28 -> 0.051927362 | D33: =D28 -> 0.024094667 | E33: =E28 -> 0.057639044 | F33: =F28 -> 0.09481288 | G33: =G28 -> 0.079054621 | I33: =I28 -> 0.057878059
B34: ROE | C34: =C30 -> 0.15796593 | D34: =D30 -> 0.076333683 | E34: =E30 -> 0.15071207 | F34: =F30 -> 0.20718257 | G34: =G30 -> 0.15732305 | I34: =I30 -> 0.11728306
B35: ROIC | C35: =Statement!M141 -> 0.22434772 | D35: =Statement!N141 -> 0.085550441 | E35: =Statement!O141 -> 0.17222666 | F35: =Statement!P141 -> 0.24992875 | G35: =Statement!Q141 -> 0.17492908 | I35: =Statement!AC141 -> 0.10099664
B37: Cash conversion cycle
B38: DSO | C38: =Statement!M142 -> 25.552688 | D38: =Statement!N142 -> 30.08154 | E38: =Statement!O142 -> 33.181703 | F38: =Statement!P142 -> 31.725573 | G38: =Statement!Q142 -> 34.482156 | I38: =Statement!AC142 -> 44.96596
B39: DIO | C39: =Statement!M143 -> 34.288181 | D39: =Statement!N143 -> 33.655361 | E39: =Statement!O143 -> 30.759641 | F39: =Statement!P143 -> 29.398107 | G39: =Statement!Q143 -> 30.051527 | I39: =Statement!AC143 -> 30.781654
B40: DPO | C40: =Statement!M144 -> 82.636197 | D40: =Statement!N144 -> 77.865623 | E40: =Statement!O144 -> 78.45564 | F40: =Statement!P144 -> 81.080656 | G40: =Statement!Q144 -> 95.591691 | I40: =Statement!AC144 -> 114.59725
B41: Net trade cycle | C41: =Statement!M145 -> -22.795328 | D41: =Statement!N145 -> -14.128722 | E41: =Statement!O145 -> -14.514297 | F41: =Statement!P145 -> -19.956976 | G41: =Statement!Q145 -> -31.058009 | I41: =Statement!AC145 -> -38.849641
B43: Liquidity ratios
B44: Debt/Equity | C44: =Statement!M146 -> 0.35259141 | D44: =Statement!N146 -> 0.45979609 | E44: =Statement!O146 -> 0.28886192 | F44: =Statement!P146 -> 0.18401581 | G44: =Statement!Q146 -> 0.15970224 | I44: =Statement!AC146 -> 0.28214589
B45: Net Debt/Equity | C45: =Statement!M147 -> -0.34218236 | D45: =Statement!N147 -> -0.01969283 | E45: =Statement!O147 -> -0.14100805 | F45: =Statement!P147 -> -0.16987446 | G45: =Statement!Q147 -> -0.13959106 | I45: =Statement!AC147 -> 0.095989087
B46: Quick ratio | C46: =Statement!M148 -> 0.9063304 | D46: =Statement!N148 -> 0.72323721 | E46: =Statement!O148 -> 0.84304832 | F46: =Statement!P148 -> 0.87305427 | G46: =Statement!Q148 -> 0.87501663 | I46: =Statement!AC148 -> 0.82357684
B47: Current ratio | C47: =Statement!M149 -> 1.1357598 | D47: =Statement!N149 -> 0.94464358 | E47: =Statement!O149 -> 1.0450772 | F47: =Statement!P149 -> 1.0637348 | G47: =Statement!Q149 -> 1.0508153 | I47: =Statement!AC149 -> 0.98882868
B48: Interest coverage | C48: =Statement!M150 -> 18.279941 | D48: =Statement!N150 -> 8.8882438 | E48: =Statement!O150 -> 158.16309 | F48: =Statement!P150 -> N/A | G48: =Statement!Q150 -> N/A | I48: =Statement!AC150 -> N/A
B50: Earnings yields
B51: Earnings yield | C51: =Statement!M163 -> 0.012722036 | D51: =Statement!N163 -> 0.013026802 | E51: =Statement!O163 -> 0.019086482 | F51: =Statement!P163 -> 0.025206254 | G51: =Statement!Q163 -> 0.025877439 | I51: =Statement!AC163 -> 0.027099813
B52: FCF yield | C52: =Statement!M162 -> -0.01591785 | D52: =Statement!N162 -> -0.042426294 | E52: =Statement!O162 -> 0.0050992041 | F52: =Statement!P162 -> 0.0045669183 | G52: =Statement!Q162 -> -0.0046763965 | I52: =Statement!AC162 -> -0.025079006
B53: Dividend yield | C53: =Statement!M164 -> 0 | D53: =Statement!N164 -> 0 | E53: =Statement!O164 -> 0 | F53: =Statement!P164 -> 0 | G53: =Statement!Q164 -> 0 | I53: =Statement!AC164 -> 0
B54: Buyback yield | C54: =Statement!M165 -> 0 | D54: =Statement!N165 -> 0.0069715113 | E54: =Statement!O165 -> 0 | F54: =Statement!P165 -> 0 | G54: =Statement!Q165 -> 0 | I54: =Statement!AC165 -> 0
B55: Total shareholder yield | C55: =Statement!M166 -> 0 | D55: =Statement!N166 -> 0.0069715113 | E55: =Statement!O166 -> 0 | F55: =Statement!P166 -> 0 | G55: =Statement!Q166 -> 0 | I55: =Statement!AC166 -> 0
B57: Payout ratios
B58: Dividend payout ratio | C58: =Statement!M169 -> 0 | D58: =Statement!N169 -> 0 | E58: =Statement!O169 -> 0 | F58: =Statement!P169 -> 0 | G58: =Statement!Q169 -> 0 | I58: =Statement!AC169 -> 0
B59: Buyback payout ratio | C59: =Statement!M170 -> 0 | D59: =Statement!N170 -> -0.16432053 | E59: =Statement!O170 -> 0 | F59: =Statement!P170 -> 0 | G59: =Statement!Q170 -> 0 | I59: =Statement!AC170 -> 0
B60: Full payout ratio | C60: =Statement!M171 -> 0 | D60: =Statement!N171 -> -0.16432053 | E60: =Statement!O171 -> 0 | F60: =Statement!P171 -> 0 | G60: =Statement!Q171 -> 0 | I60: =Statement!AC171 -> 0
B62: Ownership
B63: Insider ownership | C63: =Statement!M172 -> 0.13663577 | D63: =Statement!N172 -> 0.12628086 | E63: =Statement!O172 -> 0.11932678 | F63: =Statement!P172 -> 0.10381708 | G63: =Statement!Q172 -> 0.093984962 | I63: =Statement!AC172 -> 0.093864469
B65: Cash holdings
B66: Cash per share | C66: =Statement!M173 -> 9.4378501 | D66: =Statement!N173 -> 6.833805 | E66: =Statement!O173 -> 8.3538698 | F66: =Statement!P173 -> 9.5491602 | G66: =Statement!Q173 -> 11.46055 | I66: =Statement!AC173 -> 10.59021
B67: Net cash per share | C67: =Statement!M176 -> 4.6482264 | D67: =Statement!N176 -> 0.28066751 | E67: =Statement!O176 -> 2.7402772 | F67: =Statement!P176 -> 4.5837894 | G67: =Statement!Q176 -> 5.3452259 | I67: =Statement!AC176 -> -5.4606898
B68: Net cash to market cap | C68: =Statement!M177 -> 0.027398533 | D68: =Statement!N177 -> 0.0033416777 | E68: =Statement!O177 -> 0.017714662 | F68: =Statement!P177 -> 0.0204156 | G68: =Statement!Q177 -> 0.022794453 | I68: =Statement!AC177 -> -0.022124293
B70: Stock Based Compensation
B71: Stock based compensation % OCF | C71: =Statement!M174 -> 0.27536858 | D71: =Statement!N174 -> 0.41968258 | E71: =Statement!O174 -> 0.28280319 | F71: =Statement!P174 -> 0.18995141 | G71: =Statement!Q174 -> 0.13953438 | I71: =Statement!AC174 -> 0.11808081
B72: Stock based compensation % Revenue | C72: =Statement!M175 -> 0.027152837 | D72: =Statement!N175 -> 0.038174414 | E72: =Statement!O175 -> 0.041794758 | F72: =Statement!P175 -> 0.034502217 | G72: =Statement!Q175 -> 0.027153506 | I72: =Statement!AC175 -> 0.024920528
B74: CapEx Usage
B75: Capex to Revenue | C75: =Statement!M178 -> 0.12994921 | D75: =Statement!N178 -> 0.12382705 | E75: =Statement!O178 -> 0.09173691 | F75: =Statement!P178 -> 0.13010084 | G75: =Statement!Q178 -> 0.18386747 | I75: =Statement!AC178 -> 0.26984846
B76: CapEx to OCF | C76: =Statement!M179 -> 1.3178708 | D76: =Statement!N179 -> 1.3613321 | E76: =Statement!O179 -> 0.62073553 | F76: =Statement!P179 -> 0.71626811 | G76: =Statement!Q179 -> 0.94484425 | I76: =Statement!AC179 -> 1.2786215
B77: CapEx to D&A | C77: =Statement!M180 -> 1.7730956 | D77: =Statement!N180 -> 1.5182128 | E77: =Statement!O180 -> 1.0835542 | F77: =Statement!P180 -> 1.5720996 | G77: =Statement!Q180 -> 2.0046688 | I77: =Statement!AC180 -> 2.7118319
B79: Growth rates
B80: Revenue | C80: =Statement!M90 -> 1 | D80: =Statement!N90 -> 0.093995173 | E80: =Statement!O90 -> 0.11829574 | F80: =Statement!P90 -> 0.10990892 | G80: =Statement!Q90 -> 0.12377755
B81: COGS | C81: =Statement!M91 -> 1 | D81: =Statement!N91 -> 0.073894461 | E81: =Statement!O91 -> 0.059571731 | F81: =Statement!P91 -> 0.07445151 | G81: =Statement!Q91 -> 0.095799601
B82: Gross Profit | C82: =Statement!M92 -> 1 | D82: =Statement!N92 -> 0.15107014 | E82: =Statement!O92 -> 0.27385998 | F82: =Statement!P92 -> 0.18803747 | G82: =Statement!Q92 -> 0.17953144
B83: OpEx | C83: =Statement!M96 -> 1 | D83: =Statement!N96 -> 0.319188 | E83: =Statement!O96 -> 0.10862719 | F83: =Statement!P96 -> 0.014013677 | G83: =Statement!Q96 -> 0.18598217
B84: Operating Income | C84: =Statement!M97 -> 1 | D84: =Statement!N97 -> -0.50769725 | E84: =Statement!O97 -> 2.0088178 | F84: =Statement!P97 -> 0.86131011 | G84: =Statement!Q97 -> 0.1659353
B85: Net Income | C85: =Statement!M99 -> 1 | D85: =Statement!N99 -> -0.48951369 | E85: =Statement!O99 -> 1.7291891 | F85: =Statement!P99 -> 0.94734593 | G85: =Statement!Q99 -> 0.091513638
B87: FCF ratios
B88: P/FCF | C88: =Statement!M160 -> -62.822556 | D88: =Statement!N160 -> -23.570289 | E88: =Statement!O160 -> 196.10904 | F88: =Statement!P160 -> 218.96604 | G88: =Statement!Q160 -> -213.83987 | I88: =Statement!AC160 -> -39.873988
B89: EV/FCF | C89: =Statement!M161 -> -65.014485 | D89: =Statement!N161 -> -28.251417 | E89: =Statement!O161 -> 110.7013 | F89: =Statement!P161 -> 171.57023 | G89: =Statement!Q161 -> -101.80875 | I89: =Statement!AC161 -> -26.953249
B90: FCFF/Sales | C90: =Statement!M167 -> -0.054975753 | D90: =Statement!N167 -> -0.059071993 | E90: =Statement!O167 -> 0.024806933 | F90: =Statement!P167 -> 0.021295782 | G90: =Statement!Q167 -> -0.033702849 | I90: =Statement!AC167 -> -0.12659744
B91: FCFE/Sales | C91: =Statement!M168 -> -0.058496622 | D91: =Statement!N168 -> -0.07104126 | E91: =Statement!O168 -> 0.014255765 | F91: =Statement!P168 -> 0.01703401 | G91: =Statement!Q168 -> -0.016420151 | I91: =Statement!AC168 -> -0.083722592
B93: Other standard growth rates
B94: Dividends | C94: =Statement!M216 -> 0 | D94: =Statement!N216 -> 0 | E94: =Statement!O216 -> 0 | F94: =Statement!P216 -> 0 | G94: =Statement!Q216 -> 0
B97: Growth rates breakdown
B98: =Statement!B202 -> Online Stores | C98: =Statement!M202 -> 1 | D98: =Statement!N202 -> -0.0093256783 | E98: =Statement!O202 -> 0.053944474 | F98: =Statement!P202 -> 0.065367962 | G98: =Statement!Q202 -> 0.090102781
B99: =Statement!B203 -> Physical Stores | C99: =Statement!M203 -> 1 | D99: =Statement!N203 -> 0.11057101 | E99: =Statement!O203 -> 0.056267468 | F99: =Statement!P203 -> 0.059161258 | G99: =Statement!Q203 -> 0.063445675
B100: =Statement!B204 -> Third party seller services | C100: =Statement!M204 -> 1 | D100: =Statement!N204 -> 0.13882708 | E100: =Statement!O204 -> 0.1897533 | F100: =Statement!P204 -> 0.1149065 | G100: =Statement!Q204 -> 0.10257067
B101: =Statement!B205 -> Advertising services | C101: =Statement!M205 -> 1 | D101: =Statement!N205 -> 0.21113607 | E101: =Statement!O205 -> 0.24290522 | F101: =Statement!P205 -> 0.19843943 | G101: =Statement!Q205 -> 0.22095919
B102: =Statement!B206 -> Subscription services | C102: =Statement!M206 -> 1 | D102: =Statement!N206 -> 0.10859985 | E102: =Statement!O206 -> 0.1417173 | F102: =Statement!P206 -> 0.10358377 | G102: =Statement!Q206 -> 0.11819985
B103: =Statement!B207 -> Other | C103: =Statement!M207 -> 1 | D103: =Statement!N207 -> 0.95174632 | E103: =Statement!O207 -> 0.16741229 | F103: =Statement!P207 -> 0.094191206 | G103: =Statement!Q207 -> 0.094009217
B104: =Statement!B208 -> Retail | C104: =Statement!M208 -> 1 | D104: =Statement!N208 -> 0.06443992 | E104: =Statement!O208 -> 0.11556235 | F104: =Statement!P208 -> 0.095810573 | G104: =Statement!Q208 -> 0.1089662
B105: =Statement!B209 -> AWS | C105: =Statement!M209 -> 1 | D105: =Statement!N209 -> 0.28767564 | E105: =Statement!O209 -> 0.13310278 | F105: =Statement!P209 -> 0.18509867 | G105: =Statement!Q209 -> 0.1968184

Sheet Quarter analysis
C3: Latest 2 quarters | F3: YoY
C4: =Statement!Z2 -> 30.06.2026 | D4: =Statement!AA2 -> 30.09.2026 | F4: =Statement!W2 -> 30.09.2025 | G4: =Statement!AA2 -> 30.09.2026
B5: Income statement growth | C5: =Statement!Z3 -> Q2 2026 | D5: =Statement!AA3 -> Q3 2026 | F5: =Statement!W3 -> Q3 2025 | G5: =Statement!AA3 -> Q3 2026
B6: Revenue | C6: =Statement!Z5 -> 200606 | D6: =Statement!AA5 -> 201944 | F6: =Statement!W5 -> 180169 | G6: =Statement!AA5 -> 201944
B7: Growth | C7: =Statement!AA90 -> 0.0066697905 | F7: =IF(F6=0, IF(G6=0,0,IF(G6>0,1,-1)), (G6-F6)/ABS(F6) ) -> 0.12085875
B8: COGS | C8: =Statement!Z6 -> 125411 | D8: =Statement!AA6 -> 124570 | F8: =Statement!W6 -> 116349 | G8: =Statement!AA6 -> 124570
B9: Growth | C9: =Statement!AA91 -> -0.0067059508 | F9: =IF(F8=0, IF(G8=0,0,IF(G8>0,1,-1)), (G8-F8)/ABS(F8) ) -> 0.070658106
B10: Gross Profit | C10: =Statement!Z7 -> 75195 | D10: =Statement!AA7 -> 77374 | F10: =Statement!W7 -> 63820 | G10: =Statement!AA7 -> 77374
B11: Growth | C11: =Statement!AA92 -> 0.028977991 | F11: =IF(F10=0, IF(G10=0,0,IF(G10>0,1,-1)), (G10-F10)/ABS(F10) ) -> 0.21237856
B12: OpEx | C12: =Statement!Z12 -> 47734 | D12: =Statement!AA12 -> 49298 | F12: =Statement!W12 -> 46398 | G12: =Statement!AA12 -> 49298
B13: Growth | C13: =Statement!AA96 -> 0.032764906 | F13: =IF(F12=0, IF(G12=0,0,IF(G12>0,1,-1)), (G12-F12)/ABS(F12) ) -> 0.062502694
B14: Operating profit | C14: =Statement!Z13 -> 27461 | D14: =Statement!AA13 -> 28076 | F14: =Statement!W13 -> 17422 | G14: =Statement!AA13 -> 28076
B15: Growth | C15: =Statement!AA97 -> 0.022395397 | F15: =IF(F14=0, IF(G14=0,0,IF(G14>0,1,-1)), (G14-F14)/ABS(F14) ) -> 0.61152566
B16: Net income | C16: =Statement!Z19 -> 12161 | D16: =Statement!AA19 -> 20685 | F16: =Statement!W19 -> 12187 | G16: =Statement!AA19 -> 20685
B17: Growth | C17: =Statement!AA99 -> 0.7009292 | F17: =IF(F16=0, IF(G16=0,0,IF(G16>0,1,-1)), (G16-F16)/ABS(F16) ) -> 0.6973004
B18: Diluted shares outstanding | C18: =Statement!Z23 -> 10903 | D18: =Statement!AA23 -> 10929 | F18: =Statement!W23 -> 10845 | G18: =Statement!AA23 -> 10929
B19: Growth | C19: =IF(C18=0, IF(D18=0,0,IF(D18>0,1,-1)), (D18-C18)/ABS(C18) ) -> 0.0023846648 | F19: =IF(F18=0, IF(G18=0,0,IF(G18>0,1,-1)), (G18-F18)/ABS(F18) ) -> 0.0077455048
B20: Diluted EPS | C20: =Statement!Z27 -> 1.1153811 | D20: =Statement!AA27 -> 1.8926709 | F20: =Statement!W27 -> 1.1237437 | G20: =Statement!AA27 -> 1.8926709
B21: Growth | C21: =IF(C20=0, IF(D20=0,0,IF(D20>0,1,-1)), (D20-C20)/ABS(C20) ) -> 0.6968827 | F21: =IF(F20=0, IF(G20=0,0,IF(G20>0,1,-1)), (G20-F20)/ABS(F20) ) -> 0.684255
B23: Revenue breakdown | C23: =C5 -> Q2 2026 | D23: =D5 -> Q3 2026 | F23: =F5 -> Q3 2025 | G23: =G5 -> Q3 2026
B24: =Statement!B202 -> Online Stores | C24: =Statement!Z188 -> 70432 | D24: =Statement!AA188 -> 68470 | F24: =Statement!W188 -> 67407 | G24: =Statement!AA188 -> 68470
B25: Growth | C25: =IF(C24=0, IF(D24=0,0,IF(D24>0,1,-1)), (D24-C24)/ABS(C24) ) -> -0.027856656 | F25: =IF(F24=0, IF(G24=0,0,IF(G24>0,1,-1)), (G24-F24)/ABS(F24) ) -> 0.015769876
B26: =Statement!B203 -> Physical Stores | C26: =Statement!Z189 -> 5794 | D26: =Statement!AA189 -> 5710 | F26: =Statement!W189 -> 5578 | G26: =Statement!AA189 -> 5710
B27: Growth | C27: =IF(C26=0, IF(D26=0,0,IF(D26>0,1,-1)), (D26-C26)/ABS(C26) ) -> -0.014497756 | F27: =IF(F26=0, IF(G26=0,0,IF(G26>0,1,-1)), (G26-F26)/ABS(F26) ) -> 0.023664396
B28: =Statement!B204 -> Third party seller services | C28: =Statement!Z190 -> 46780 | D28: =Statement!AA190 -> 46492 | F28: =Statement!W190 -> 42486 | G28: =Statement!AA190 -> 46492
B29: Growth | C29: =IF(C28=0, IF(D28=0,0,IF(D28>0,1,-1)), (D28-C28)/ABS(C28) ) -> -0.0061564771 | F29: =IF(F28=0, IF(G28=0,0,IF(G28>0,1,-1)), (G28-F28)/ABS(F28) ) -> 0.094289884
B30: =Statement!B205 -> Advertising services | C30: =Statement!Z191 -> 19809 | D30: =Statement!AA191 -> 19637 | F30: =Statement!W191 -> 17703 | G30: =Statement!AA191 -> 19637
B31: Growth | C31: =IF(C30=0, IF(D30=0,0,IF(D30>0,1,-1)), (D30-C30)/ABS(C30) ) -> -0.0086829219 | F31: =IF(F30=0, IF(G30=0,0,IF(G30>0,1,-1)), (G30-F30)/ABS(F30) ) -> 0.10924702
B32: =Statement!B206 -> Subscription services | C32: =Statement!Z192 -> 13730 | D32: =Statement!AA192 -> 14006 | F32: =Statement!W192 -> 12574 | G32: =Statement!AA192 -> 14006
B33: Growth | C33: =IF(C32=0, IF(D32=0,0,IF(D32>0,1,-1)), (D32-C32)/ABS(C32) ) -> 0.020101966 | F33: =IF(F32=0, IF(G32=0,0,IF(G32>0,1,-1)), (G32-F32)/ABS(F32) ) -> 0.1138858
B34: =Statement!B207 -> Other | C34: =Statement!Z193 -> 1829 | D34: =Statement!AA193 -> 1645 | F34: =Statement!W193 -> 1415 | G34: =Statement!AA193 -> 1645
B35: Growth | C35: =IF(C34=0, IF(D34=0,0,IF(D34>0,1,-1)), (D34-C34)/ABS(C34) ) -> -0.10060142 | F35: =IF(F34=0, IF(G34=0,0,IF(G34>0,1,-1)), (G34-F34)/ABS(F34) ) -> 0.16254417
B36: =Statement!B208 -> Retail | C36: =Statement!Z194 -> 158374 | D36: =Statement!AA194 -> 155960 | F36: =Statement!W194 -> 147163 | G36: =Statement!AA194 -> 155960
B37: Growth | C37: =IF(C36=0, IF(D36=0,0,IF(D36>0,1,-1)), (D36-C36)/ABS(C36) ) -> -0.015242401 | F37: =IF(F36=0, IF(G36=0,0,IF(G36>0,1,-1)), (G36-F36)/ABS(F36) ) -> 0.059777254
B38: =Statement!B209 -> AWS | C38: =Statement!Z195 -> 42232 | D38: =Statement!AA195 -> 45984 | F38: =Statement!W195 -> 33006 | G38: =Statement!AA195 -> 45984
B39: Growth | C39: =IF(C38=0, IF(D38=0,0,IF(D38>0,1,-1)), (D38-C38)/ABS(C38) ) -> 0.088842584 | F39: =IF(F38=0, IF(G38=0,0,IF(G38>0,1,-1)), (G38-F38)/ABS(F38) ) -> 0.39320124

Sheet Graphs Year
C63: =Statement!H2 -> 0 | D63: =Statement!I2 -> 0 | E63: =Statement!J2 -> 0 | F63: =Statement!K2 -> 0 | G63: =Statement!L2 -> 0 | H63: =Statement!M2 -> 31.12.2021 | I63: =Statement!N2 -> 31.12.2022 | J63: =Statement!O2 -> 31.12.2023 | ... L63: =Statement!Q2 -> 31.12.2025
C64: =Statement!H3 -> 0 | D64: =Statement!I3 -> 0 | E64: =Statement!J3 -> 0 | F64: =Statement!K3 -> 0 | G64: =Statement!L3 -> 0 | H64: =Statement!M3 -> 2021 | I64: =Statement!N3 -> 2022 | J64: =Statement!O3 -> 2023 | ... L64: =Statement!Q3 -> 2025
B65: Revenue | C65: =Statement!H5 -> 0 | D65: =Statement!I5 -> 0 | E65: =Statement!J5 -> 0 | F65: =Statement!K5 -> 0 | G65: =Statement!L5 -> 0 | H65: =Statement!M5 -> 469822 | I65: =Statement!N5 -> 513983 | J65: =Statement!O5 -> 574785 | ... L65: =Statement!Q5 -> 716924
B66: Operating income | C66: =Statement!H13 -> 0 | D66: =Statement!I13 -> 0 | E66: =Statement!J13 -> 0 | F66: =Statement!K13 -> 0 | G66: =Statement!L13 -> 0 | H66: =Statement!M13 -> 24879 | I66: =Statement!N13 -> 12248 | J66: =Statement!O13 -> 36852 | ... L66: =Statement!Q13 -> 79975
B67: Net income | C67: =Statement!H19 -> 0 | D67: =Statement!I19 -> 0 | E67: =Statement!J19 -> 0 | F67: =Statement!K19 -> 0 | G67: =Statement!L19 -> 0 | H67: =Statement!M19 -> 21838 | I67: =Statement!N19 -> 11148 | J67: =Statement!O19 -> 30425 | ... L67: =Statement!Q19 -> 64670
B68: FCFE | C68: =Statement!H158 -> 0 | D68: =Statement!I158 -> 0 | E68: =Statement!J158 -> 0 | F68: =Statement!K158 -> 0 | G68: =Statement!L158 -> 0 | H68: =Statement!M158 -> -27483 | I68: =Statement!N158 -> -36514 | J68: =Statement!O158 -> 8194 | ... L68: =Statement!Q158 -> -11772
B69: FCFF | C69: =Statement!H159 -> 0 | D69: =Statement!I159 -> 0 | E69: =Statement!J159 -> 0 | F69: =Statement!K159 -> 0 | G69: =Statement!L159 -> 0 | H69: =Statement!M159 -> -25828.818 | I69: =Statement!N159 -> -30362 | J69: =Statement!O159 -> 14258.653 | ... L69: =Statement!Q159 -> -24162.382
B70: Gross margin | C70: =Statement!H102 -> 0 | D70: =Statement!I102 -> 0 | E70: =Statement!J102 -> 0 | F70: =Statement!K102 -> 0 | G70: =Statement!L102 -> 0 | H70: =Statement!M102 -> 0.26045396 | I70: =Statement!N102 -> 0.27404214 | J70: =Statement!O102 -> 0.31216368 | ... L70: =Statement!Q102 -> 0.350715
B71: Operating margin | C71: =Statement!H103 -> 0 | D71: =Statement!I103 -> 0 | E71: =Statement!J103 -> 0 | F71: =Statement!K103 -> 0 | G71: =Statement!L103 -> 0 | H71: =Statement!M103 -> 0.052954098 | I71: =Statement!N103 -> 0.023829582 | J71: =Statement!O103 -> 0.064114408 | ... L71: =Statement!Q103 -> 0.11155297
B72: Net margin | C72: =Statement!H104 -> 0 | D72: =Statement!I104 -> 0 | E72: =Statement!J104 -> 0 | F72: =Statement!K104 -> 0 | G72: =Statement!L104 -> 0 | H72: =Statement!M104 -> 0.046481433 | I72: =Statement!N104 -> 0.021689433 | J72: =Statement!O104 -> 0.052932836 | ... L72: =Statement!Q104 -> 0.090204819
B73: ="Revenue "&Statement!B188 -> Revenue Online Stores | C73: =Statement!H188 -> 0 | D73: =Statement!I188 -> 0 | E73: =Statement!J188 -> 0 | F73: =Statement!K188 -> 0 | G73: =Statement!L188 -> 0 | H73: =Statement!M188 -> 222075 | I73: =Statement!N188 -> 220004 | J73: =Statement!O188 -> 231872 | ... L73: =Statement!Q188 -> 269287
B74: ="Revenue "&Statement!B189 -> Revenue Physical Stores | C74: =Statement!H189 -> 0 | D74: =Statement!I189 -> 0 | E74: =Statement!J189 -> 0 | F74: =Statement!K189 -> 0 | G74: =Statement!L189 -> 0 | H74: =Statement!M189 -> 17075 | I74: =Statement!N189 -> 18963 | J74: =Statement!O189 -> 20030 | ... L74: =Statement!Q189 -> 22561
B75: ="Revenue "&Statement!B190 -> Revenue Third party seller services | C75: =Statement!H190 -> 0 | D75: =Statement!I190 -> 0 | E75: =Statement!J190 -> 0 | F75: =Statement!K190 -> 0 | G75: =Statement!L190 -> 0 | H75: =Statement!M190 -> 103366 | I75: =Statement!N190 -> 117716 | J75: =Statement!O190 -> 140053 | ... L75: =Statement!Q190 -> 172162
B76: ="Revenue "&Statement!B191 -> Revenue Advertising services | C76: =Statement!H191 -> 0 | D76: =Statement!I191 -> 0 | E76: =Statement!J191 -> 0 | F76: =Statement!K191 -> 0 | G76: =Statement!L191 -> 0 | H76: =Statement!M191 -> 31160 | I76: =Statement!N191 -> 37739 | J76: =Statement!O191 -> 46906 | ... L76: =Statement!Q191 -> 68635
B77: ="Revenue "&Statement!B192 -> Revenue Subscription services | C77: =Statement!H192 -> 0 | D77: =Statement!I192 -> 0 | E77: =Statement!J192 -> 0 | F77: =Statement!K192 -> 0 | G77: =Statement!L192 -> 0 | H77: =Statement!M192 -> 31768 | I77: =Statement!N192 -> 35218 | J77: =Statement!O192 -> 40209 | ... L77: =Statement!Q192 -> 49619
B78: ="Revenue "&Statement!B193 -> Revenue Other | C78: =Statement!H193 -> 0 | D78: =Statement!I193 -> 0 | E78: =Statement!J193 -> 0 | F78: =Statement!K193 -> 0 | G78: =Statement!L193 -> 0 | H78: =Statement!M193 -> 2176 | I78: =Statement!N193 -> 4247 | J78: =Statement!O193 -> 4958 | ... L78: =Statement!Q193 -> 5935
B79: ="Revenue "&Statement!B194 -> Revenue Retail | C79: =Statement!H194 -> 0 | D79: =Statement!I194 -> 0 | E79: =Statement!J194 -> 0 | F79: =Statement!K194 -> 0 | G79: =Statement!L194 -> 0 | H79: =Statement!M194 -> 407620 | I79: =Statement!N194 -> 433887 | J79: =Statement!O194 -> 484028 | ... L79: =Statement!Q194 -> 588199
B80: ="Revenue "&Statement!B195 -> Revenue AWS | C80: =Statement!H195 -> 0 | D80: =Statement!I195 -> 0 | E80: =Statement!J195 -> 0 | F80: =Statement!K195 -> 0 | G80: =Statement!L195 -> 0 | H80: =Statement!M195 -> 62202 | I80: =Statement!N195 -> 80096 | J80: =Statement!O195 -> 90757 | ... L80: =Statement!Q195 -> 128725
B81: ROA | C81: =Statement!H124 -> 0 | D81: =Statement!I124 -> 0 | E81: =Statement!J124 -> 0 | F81: =Statement!K124 -> 0 | G81: =Statement!L124 -> 0 | H81: =Statement!M124 -> 0.051927362 | I81: =Statement!N124 -> 0.024094667 | J81: =Statement!O124 -> 0.057639044 | ... L81: =Statement!Q124 -> 0.079054621
B82: ROE | C82: =Statement!H126 -> 0 | D82: =Statement!I126 -> 0 | E82: =Statement!J126 -> 0 | F82: =Statement!K126 -> 0 | G82: =Statement!L126 -> 0 | H82: =Statement!M126 -> 0.15796593 | I82: =Statement!N126 -> 0.076333683 | J82: =Statement!O126 -> 0.15071207 | ... L82: =Statement!Q126 -> 0.15732305
B83: ROIC | C83: =Statement!H141 -> 0 | D83: =Statement!I141 -> 0 | E83: =Statement!J141 -> 0 | F83: =Statement!K141 -> 0 | G83: =Statement!L141 -> 0 | H83: =Statement!M141 -> 0.22434772 | I83: =Statement!N141 -> 0.085550441 | J83: =Statement!O141 -> 0.17222666 | ... L83: =Statement!Q141 -> 0.17492908
B84: Price 5y | C84: =Statement!H220 -> 0 | D84: =Statement!I220 -> 0 | E84: =Statement!J220 -> 0 | F84: =Statement!K220 -> 0 | G84: =Statement!L220 -> 0 | H84: =Statement!M220 -> 100 | I84: =Statement!N220 -> 50.377879 | J84: =Statement!O220 -> 91.134837 | ... L84: =Statement!Q220 -> 138.4477
B85: Revenue 5y | C85: =Statement!H221 -> 0 | D85: =Statement!I221 -> 0 | E85: =Statement!J221 -> 0 | F85: =Statement!K221 -> 0 | G85: =Statement!L221 -> 0 | H85: =Statement!M221 -> 100 | I85: =Statement!N221 -> 109.39952 | J85: =Statement!O221 -> 122.34101 | ... L85: =Statement!Q221 -> 152.59481
B86: EPS 5y | C86: =Statement!H222 -> 0 | D86: =Statement!I222 -> 0 | E86: =Statement!J222 -> 0 | F86: =Statement!K222 -> 0 | G86: =Statement!L222 -> 0 | H86: =Statement!M222 -> 100 | I86: =Statement!N222 -> 51.584719 | J86: =Statement!O222 -> 136.72681 | ... L86: =Statement!Q222 -> 281.61151

Sheet Graphs Quarter
C55: =Statement!T2 -> 31.12.2024 | D55: =Statement!U2 -> 31.03.2025 | E55: =Statement!V2 -> 30.06.2025 | F55: =Statement!W2 -> 30.09.2025 | G55: =Statement!X2 -> 31.12.2025 | H55: =Statement!Y2 -> 31.03.2026 | I55: =Statement!Z2 -> 30.06.2026 | J55: =Statement!AA2 -> 30.09.2026
C56: =Statement!T3 -> Q4 2024 | D56: =Statement!U3 -> Q1 2025 | E56: =Statement!V3 -> Q2 2025 | F56: =Statement!W3 -> Q3 2025 | G56: =Statement!X3 -> Q4 2025 | H56: =Statement!Y3 -> Q1 2026 | I56: =Statement!Z3 -> Q2 2026 | J56: =Statement!AA3 -> Q3 2026
B57: Revenue | C57: =Statement!T5 -> 187792 | D57: =Statement!U5 -> 155667 | E57: =Statement!V5 -> 167702 | F57: =Statement!W5 -> 180169 | G57: =Statement!X5 -> 213386 | H57: =Statement!Y5 -> 181519 | I57: =Statement!Z5 -> 200606 | J57: =Statement!AA5 -> 201944
B58: Operating income | C58: =Statement!T13 -> 21203 | D58: =Statement!U13 -> 18405 | E58: =Statement!V13 -> 19171 | F58: =Statement!W13 -> 17422 | G58: =Statement!X13 -> 24977 | H58: =Statement!Y13 -> 23852 | I58: =Statement!Z13 -> 27461 | J58: =Statement!AA13 -> 28076
B59: Net income | C59: =Statement!T19 -> 20004 | D59: =Statement!U19 -> 17127 | E59: =Statement!V19 -> 18164 | F59: =Statement!W19 -> 12187 | G59: =Statement!X19 -> 21192 | H59: =Statement!Y19 -> 17927 | I59: =Statement!Z19 -> 12161 | J59: =Statement!AA19 -> 20685
B60: Gross margin | C60: =Statement!T102 -> 0.32449199 | D60: =Statement!U102 -> 0.34752388 | E60: =Statement!V102 -> 0.36324552 | F60: =Statement!W102 -> 0.35422298 | G60: =Statement!X102 -> 0.34023319 | H60: =Statement!Y102 -> 0.36782375 | I60: =Statement!Z102 -> 0.37483924 | J60: =Statement!AA102 -> 0.38314582
B61: Operating margin | C61: =Statement!T103 -> 0.11290683 | D61: =Statement!U103 -> 0.11823315 | E61: =Statement!V103 -> 0.11431587 | F61: =Statement!W103 -> 0.0966981 | G61: =Statement!X103 -> 0.11705079 | H61: =Statement!Y103 -> 0.13140222 | I61: =Statement!Z103 -> 0.13689022 | J61: =Statement!AA103 -> 0.13902864
B62: Net margin | C62: =Statement!T104 -> 0.10652211 | D62: =Statement!U104 -> 0.11002332 | E62: =Statement!V104 -> 0.10831117 | F62: =Statement!W104 -> 0.067642047 | G62: =Statement!X104 -> 0.099312982 | H62: =Statement!Y104 -> 0.098761011 | I62: =Statement!Z104 -> 0.060621317 | J62: =Statement!AA104 -> 0.10242939
B63: ="Revenue "&Statement!B188 -> Revenue Online Stores | C63: =Statement!T188 -> 0 | D63: =Statement!U188 -> 57407 | E63: =Statement!V188 -> 61485 | F63: =Statement!W188 -> 67407 | G63: =Statement!X188 -> 82988 | H63: =Statement!Y188 -> 64254 | I63: =Statement!Z188 -> 70432 | J63: =Statement!AA188 -> 68470
B64: ="Revenue "&Statement!B189 -> Revenue Physical Stores | C64: =Statement!T189 -> 0 | D64: =Statement!U189 -> 5533 | E64: =Statement!V189 -> 5595 | F64: =Statement!W189 -> 5578 | G64: =Statement!X189 -> 5855 | H64: =Statement!Y189 -> 5785 | I64: =Statement!Z189 -> 5794 | J64: =Statement!AA189 -> 5710
B65: ="Revenue "&Statement!B190 -> Revenue Third party seller services | C65: =Statement!T190 -> 0 | D65: =Statement!U190 -> 36512 | E65: =Statement!V190 -> 40348 | F65: =Statement!W190 -> 42486 | G65: =Statement!X190 -> 52816 | H65: =Statement!Y190 -> 41578 | I65: =Statement!Z190 -> 46780 | J65: =Statement!AA190 -> 46492
B66: ="Revenue "&Statement!B191 -> Revenue Advertising services | C66: =Statement!T191 -> 0 | D66: =Statement!U191 -> 13921 | E66: =Statement!V191 -> 15694 | F66: =Statement!W191 -> 17703 | G66: =Statement!X191 -> 21317 | H66: =Statement!Y191 -> 17243 | I66: =Statement!Z191 -> 19809 | J66: =Statement!AA191 -> 19637
B67: ="Revenue "&Statement!B192 -> Revenue Subscription services | C67: =Statement!T192 -> 0 | D67: =Statement!U192 -> 11715 | E67: =Statement!V192 -> 12208 | F67: =Statement!W192 -> 12574 | G67: =Statement!X192 -> 13122 | H67: =Statement!Y192 -> 13427 | I67: =Statement!Z192 -> 13730 | J67: =Statement!AA192 -> 14006
B68: ="Revenue "&Statement!B193 -> Revenue Other | C68: =Statement!T193 -> 0 | D68: =Statement!U193 -> 1312 | E68: =Statement!V193 -> 1499 | F68: =Statement!W193 -> 1415 | G68: =Statement!X193 -> 1709 | H68: =Statement!Y193 -> 1645 | I68: =Statement!Z193 -> 1829 | J68: =Statement!AA193 -> 1645
B69: ="Revenue "&Statement!B194 -> Revenue Retail | C69: =Statement!T194 -> 0 | D69: =Statement!U194 -> 126400 | E69: =Statement!V194 -> 136829 | F69: =Statement!W194 -> 147163 | G69: =Statement!X194 -> 177807 | H69: =Statement!Y194 -> 143932 | I69: =Statement!Z194 -> 158374 | J69: =Statement!AA194 -> 155960
B70: ="Revenue "&Statement!B195 -> Revenue AWS | C70: =Statement!T195 -> 0 | D70: =Statement!U195 -> 29267 | E70: =Statement!V195 -> 30837 | F70: =Statement!W195 -> 33006 | G70: =Statement!X195 -> 35615 | H70: =Statement!Y195 -> 37587 | I70: =Statement!Z195 -> 42232 | J70: =Statement!AA195 -> 45984
B71: FCFE | C71: =Statement!T158 -> 12807 | D71: =Statement!U158 -> -11693 | E71: =Statement!V158 -> -6202 | F71: =Statement!W158 -> -4417 | G71: =Statement!X158 -> 10540 | H71: =Statement!Y158 -> -22203 | I71: =Statement!Z158 -> -14859 | J71: =Statement!AA158 -> -40243

Sheet Forecast ->
H5: Links
H6: Overview'!B3
H7: Financials ->'!B13
H8: Analysis ->'!B13
H9: Forecast ->'!B13
H10: Valuation ->'!B13
B13: Forecast ->

Sheet Revenue
B1: Revenue forecast
C2: History | H2: Forecast | S2: History | AA2: Forecast | AE2: TTM
C4: Revenues | S4: Revenues
B5: Revenues (thousand) | C5: =Statement!M3 -> 2021 | D5: =Statement!N3 -> 2022 | E5: =Statement!O3 -> 2023 | F5: =Statement!P3 -> 2024 | G5: =Statement!Q3 -> 2025 | H5: =G5+1 -> 2026 | I5: =H5+1 -> 2027 | J5: =I5+1 -> 2028 | K5: =J5+1 -> 2029 | L5: =K5+1 -> 2030 | R5: =B5 -> Revenues (thousand) | S5: =Statement!T3 -> Q4 2024 | T5: =Statement!U3 -> Q1 2025 | U5: =Statement!V3 -> Q2 2025 | V5: =Statement!W3 -> Q3 2025 | W5: =Statement!X3 -> Q4 2025 | X5: =Statement!Y3 -> Q1 2026 | Y5: =Statement!Z3 -> Q2 2026 | Z5: =Statement!AA3 -> Q3 2026 | AA5: FQ1 | AB5: FQ2 | AC5: FQ3 | AE5: FQ1
B6: =Statement!B188 -> Online Stores | C6: =Statement!M188 -> 222075 | D6: =Statement!N188 -> 220004 | E6: =Statement!O188 -> 231872 | F6: =Statement!P188 -> 247029 | G6: =Statement!Q188 -> 269287 | H6: =G6*(1+H18) -> 292176.4 | I6: =H6*(1+I18) -> 312628.74 | J6: =I6*(1+J18) -> 334512.75 | K6: =J6*(1+K18) -> 357928.65 | L6: =K6*(1+L18) -> 382983.65 | N6: Online Stores Growth Rate | Q6: Online Stores Growth Rate | R6: =B6 -> Online Stores | S6: =Statement!T188 -> 0 | T6: =Statement!U188 -> 57407 | U6: =Statement!V188 -> 61485 | V6: =Statement!W188 -> 67407 | W6: =Statement!X188 -> 82988 | X6: =Statement!Y188 -> 64254 | Y6: =Statement!Z188 -> 70432 | Z6: =Statement!AA188 -> 68470 | AA6: =Z6*(1+AA18) -> 89011 | AE6: =SUM(X6:AA6) -> 292167
B7: =Statement!B189 -> Physical Stores | C7: =Statement!M189 -> 17075 | D7: =Statement!N189 -> 18963 | E7: =Statement!O189 -> 20030 | F7: =Statement!P189 -> 21215 | G7: =Statement!Q189 -> 22561 | H7: =G7*(1+H19) -> 23576.245 | I7: =H7*(1+I19) -> 24566.447 | J7: =I7*(1+J19) -> 25549.105 | K7: =J7*(1+K19) -> 26571.069 | L7: =K7*(1+L19) -> 27633.912 | N7: Physical Stores Growth Rate | Q7: Physical Stores Growth Rate | R7: =B7 -> Physical Stores | S7: =Statement!T189 -> 0 | T7: =Statement!U189 -> 5533 | U7: =Statement!V189 -> 5595 | V7: =Statement!W189 -> 5578 | W7: =Statement!X189 -> 5855 | X7: =Statement!Y189 -> 5785 | Y7: =Statement!Z189 -> 5794 | Z7: =Statement!AA189 -> 5710 | AA7: =Z7*(1+AA19) -> 6566.5 | AE7: =SUM(X7:AA7) -> 23855.5
B8: =Statement!B190 -> Third party seller services | C8: =Statement!M190 -> 103366 | D8: =Statement!N190 -> 117716 | E8: =Statement!O190 -> 140053 | F8: =Statement!P190 -> 156146 | G8: =Statement!Q190 -> 172162 | H8: =G8*(1+H20) -> 189378.2 | I8: =H8*(1+I20) -> 208316.02 | J8: =I8*(1+J20) -> 229147.62 | K8: =J8*(1+K20) -> 249770.91 | L8: =K8*(1+L20) -> 272250.29 | N8: Third party Growth Rate | Q8: Third party Growth Rate | R8: =B8 -> Third party seller services | S8: =Statement!T190 -> 0 | T8: =Statement!U190 -> 36512 | U8: =Statement!V190 -> 40348 | V8: =Statement!W190 -> 42486 | W8: =Statement!X190 -> 52816 | X8: =Statement!Y190 -> 41578 | Y8: =Statement!Z190 -> 46780 | Z8: =Statement!AA190 -> 46492 | AA8: =Z8*(1+AA20) -> 55790.4 | AE8: =SUM(X8:AA8) -> 190640.4
B9: =Statement!B191 -> Advertising services | C9: =Statement!M191 -> 31160 | D9: =Statement!N191 -> 37739 | E9: =Statement!O191 -> 46906 | F9: =Statement!P191 -> 56214 | G9: =Statement!Q191 -> 68635 | H9: =G9*(1+H21) -> 78930.25 | I9: =H9*(1+I21) -> 93137.695 | J9: =I9*(1+J21) -> 110833.86 | K9: =J9*(1+K21) -> 129675.61 | L9: =K9*(1+L21) -> 149126.95 | N9: Advertising Growth Rate | Q9: Advertising Growth Rate | R9: =B9 -> Advertising services | S9: =Statement!T191 -> 0 | T9: =Statement!U191 -> 13921 | U9: =Statement!V191 -> 15694 | V9: =Statement!W191 -> 17703 | W9: =Statement!X191 -> 21317 | X9: =Statement!Y191 -> 17243 | Y9: =Statement!Z191 -> 19809 | Z9: =Statement!AA191 -> 19637 | AA9: =Z9*(1+AA21) -> 20618.85 | AE9: =SUM(X9:AA9) -> 77307.85
B10: =Statement!B192 -> Subscription services | C10: =Statement!M192 -> 31768 | D10: =Statement!N192 -> 35218 | E10: =Statement!O192 -> 40209 | F10: =Statement!P192 -> 44374 | G10: =Statement!Q192 -> 49619 | H10: =G10*(1+H22) -> 54580.9 | I10: =H10*(1+I22) -> 60584.799 | J10: =I10*(1+J22) -> 67854.975 | K10: =J10*(1+K22) -> 74640.472 | L10: =K10*(1+L22) -> 81358.115 | N10: Subscription Growth Rate | Q10: Subscription Growth Rate | R10: =B10 -> Subscription services | S10: =Statement!T192 -> 0 | T10: =Statement!U192 -> 11715 | U10: =Statement!V192 -> 12208 | V10: =Statement!W192 -> 12574 | W10: =Statement!X192 -> 13122 | X10: =Statement!Y192 -> 13427 | Y10: =Statement!Z192 -> 13730 | Z10: =Statement!AA192 -> 14006 | AA10: =Z10*(1+AA22) -> 14706.3 | AE10: =SUM(X10:AA10) -> 55869.3
B11: =Statement!B193 -> Other | C11: =Statement!M193 -> 2176 | D11: =Statement!N193 -> 4247 | E11: =Statement!O193 -> 4958 | F11: =Statement!P193 -> 5425 | G11: =Statement!Q193 -> 5935 | H11: =G11*(1+H23) -> 6409.8 | I11: =H11*(1+I23) -> 6858.486 | J11: =I11*(1+J23) -> 7407.1649 | K11: =J11*(1+K23) -> 7925.6664 | L11: =K11*(1+L23) -> 8480.4631 | N11: Other Growth Rate | Q11: Other Growth Rate | R11: =B11 -> Other | S11: =Statement!T193 -> 0 | T11: =Statement!U193 -> 1312 | U11: =Statement!V193 -> 1499 | V11: =Statement!W193 -> 1415 | W11: =Statement!X193 -> 1709 | X11: =Statement!Y193 -> 1645 | Y11: =Statement!Z193 -> 1829 | Z11: =Statement!AA193 -> 1645 | AA11: =Z11*(1+AA23) -> 1809.5 | AE11: =SUM(X11:AA11) -> 6928.5
B12: =Statement!B194 -> Retail | C12: =Statement!M194 -> 407620 | D12: =Statement!N194 -> 433887 | E12: =Statement!O194 -> 484028 | F12: =Statement!P194 -> 530403 | G12: =Statement!Q194 -> 588199 | H12: =SUM(H6:H11) -> 645051.79 | I12: =SUM(I6:I11) -> 706092.19 | J12: =SUM(J6:J11) -> 775305.48 | K12: =SUM(K6:K11) -> 846512.38 | L12: =SUM(L6:L11) -> 921833.39 | N12: SUM of all the above | Q12: SUM of all the above | R12: =B12 -> Retail | S12: =Statement!T194 -> 0 | T12: =Statement!U194 -> 126400 | U12: =Statement!V194 -> 136829 | V12: =Statement!W194 -> 147163 | W12: =Statement!X194 -> 177807 | X12: =Statement!Y194 -> 143932 | Y12: =Statement!Z194 -> 158374 | Z12: =Statement!AA194 -> 155960 | AA12: =SUM(AA6:AA11) -> 188502.55 | AE12: =SUM(X12:AA12) -> 646768.55
B13: =Statement!B195 -> AWS | C13: =Statement!M195 -> 62202 | D13: =Statement!N195 -> 80096 | E13: =Statement!O195 -> 90757 | F13: =Statement!P195 -> 107556 | G13: =Statement!Q195 -> 128725 | H13: =G13*(1+H25) -> 181502.25 | I13: =H13*(1+I25) -> 245028.04 | J13: =I13*(1+J25) -> 301384.49 | K13: =J13*(1+K25) -> 355633.69 | L13: =K13*(1+L25) -> 405422.41 | N13: AWS Growth Rate | Q13: AWS Growth Rate | R13: =B13 -> AWS | S13: =Statement!T195 -> 0 | T13: =Statement!U195 -> 29267 | U13: =Statement!V195 -> 30837 | V13: =Statement!W195 -> 33006 | W13: =Statement!X195 -> 35615 | X13: =Statement!Y195 -> 37587 | Y13: =Statement!Z195 -> 42232 | Z13: =Statement!AA195 -> 45984 | AA13: =Z13*(1+AA25) -> 55180.8 | AE13: =SUM(X13:AA13) -> 180983.8
B14: Total | C14: =Statement!M5 -> 469822 | D14: =Statement!N5 -> 513983 | E14: =Statement!O5 -> 574785 | F14: =Statement!P5 -> 637959 | G14: =Statement!Q5 -> 716924 | H14: =SUM(H12:H13) -> 826554.04 | I14: =SUM(I12:I13) -> 951120.23 | J14: =SUM(J12:J13) -> 1076690 | K14: =SUM(K12:K13) -> 1202146.1 | L14: =SUM(L12:L13) -> 1327255.8 | N14: SUM of Retail and AWS | Q14: SUM of Retail and AWS | R14: Total | S14: =Statement!T5 -> 187792 | T14: =Statement!U5 -> 155667 | U14: =Statement!V5 -> 167702 | V14: =Statement!W5 -> 180169 | W14: =Statement!X5 -> 213386 | X14: =Statement!Y5 -> 181519 | Y14: =Statement!Z5 -> 200606 | Z14: =Statement!AA5 -> 201944 | AA14: =SUM(AA12:AA13) -> 243683.35 | AE14: =SUM(X14:AA14) -> 827752.35
C16: Growth rates | S16: Growth rates
B17: Revenue growth % | C17: =C5 -> 2021 | D17: =D5 -> 2022 | E17: =E5 -> 2023 | F17: =F5 -> 2024 | G17: =G5 -> 2025 | H17: =H5 -> 2026 | I17: =I5 -> 2027 | J17: =J5 -> 2028 | ... L17: =L5 -> 2030 | R17: Revenue growth % | S17: =S5 -> Q4 2024 | T17: =T5 -> Q1 2025 | U17: =U5 -> Q2 2025 | V17: =V5 -> Q3 2025 | W17: =W5 -> Q4 2025 | X17: =X5 -> Q1 2026 | Y17: =Y5 -> Q2 2026 | Z17: =Z5 -> Q3 2026 | ... AC17: =AC5 -> FQ3
B18: =B6 -> Online Stores | D18: =D6/C6-1 -> -0.0093256783 | E18: =E6/D6-1 -> 0.053944474 | F18: =F6/E6-1 -> 0.065367962 | G18: =G6/F6-1 -> 0.090102781 | H18: 0.085 | I18: 0.07 | J18: 0.07 | K18: 0.07 | L18: 0.07 | R18: =R6 -> Online Stores | T18: =T6/S6-1 -> #DIV/0! | U18: =U6/T6-1 -> 0.071036633 | V18: =V6/U6-1 -> 0.096316175 | W18: =W6/V6-1 -> 0.2311481 | X18: =X6/W6-1 -> -0.22574348 | Y18: =Y6/X6-1 -> 0.096149656 | Z18: =Z6/Y6-1 -> -0.027856656 | AA18: 0.3
B19: =B7 -> Physical Stores | D19: =D7/C7-1 -> 0.11057101 | E19: =E7/D7-1 -> 0.056267468 | F19: =F7/E7-1 -> 0.059161258 | G19: =G7/F7-1 -> 0.063445675 | H19: 0.045 | I19: 0.042 | J19: 0.04 | K19: 0.04 | L19: 0.04 | R19: =R7 -> Physical Stores | T19: =T7/S7-1 -> #DIV/0! | U19: =U7/T7-1 -> 0.011205494 | V19: =V7/U7-1 -> -0.0030384272 | W19: =W7/V7-1 -> 0.049659376 | X19: =X7/W7-1 -> -0.011955594 | Y19: =Y7/X7-1 -> 0.0015557476 | Z19: =Z7/Y7-1 -> -0.014497756 | AA19: 0.15
B20: =B8 -> Third party seller services | D20: =D8/C8-1 -> 0.13882708 | E20: =E8/D8-1 -> 0.1897533 | F20: =F8/E8-1 -> 0.1149065 | G20: =G8/F8-1 -> 0.10257067 | H20: 0.1 | I20: 0.1 | J20: 0.1 | K20: 0.09 | L20: 0.09 | R20: =R8 -> Third party seller services | T20: =T8/S8-1 -> #DIV/0! | U20: =U8/T8-1 -> 0.10506135 | V20: =V8/U8-1 -> 0.052988996 | W20: =W8/V8-1 -> 0.24313892 | X20: =X8/W8-1 -> -0.21277643 | Y20: =Y8/X8-1 -> 0.12511424 | Z20: =Z8/Y8-1 -> -0.0061564771 | AA20: 0.2
B21: =B9 -> Advertising services | D21: =D9/C9-1 -> 0.21113607 | E21: =E9/D9-1 -> 0.24290522 | F21: =F9/E9-1 -> 0.19843943 | G21: =G9/F9-1 -> 0.22095919 | H21: 0.15 | I21: 0.18 | J21: 0.19 | K21: 0.17 | L21: 0.15 | R21: =R9 -> Advertising services | T21: =T9/S9-1 -> #DIV/0! | U21: =U9/T9-1 -> 0.12736154 | V21: =V9/U9-1 -> 0.1280107 | W21: =W9/V9-1 -> 0.20414619 | X21: =X9/W9-1 -> -0.19111507 | Y21: =Y9/X9-1 -> 0.14881401 | Z21: =Z9/Y9-1 -> -0.0086829219 | AA21: 0.05
B22: =B10 -> Subscription services | D22: =D10/C10-1 -> 0.10859985 | E22: =E10/D10-1 -> 0.1417173 | F22: =F10/E10-1 -> 0.10358377 | G22: =G10/F10-1 -> 0.11819985 | H22: 0.1 | I22: 0.11 | J22: 0.12 | K22: 0.1 | L22: 0.09 | R22: =R10 -> Subscription services | T22: =T10/S10-1 -> #DIV/0! | U22: =U10/T10-1 -> 0.0420828 | V22: =V10/U10-1 -> 0.029980341 | W22: =W10/V10-1 -> 0.043581995 | X22: =X10/W10-1 -> 0.023243408 | Y22: =Y10/X10-1 -> 0.022566471 | Z22: =Z10/Y10-1 -> 0.020101966 | AA22: 0.05
B23: =B11 -> Other | D23: =D11/C11-1 -> 0.95174632 | E23: =E11/D11-1 -> 0.16741229 | F23: =F11/E11-1 -> 0.094191206 | G23: =G11/F11-1 -> 0.094009217 | H23: 0.08 | I23: 0.07 | J23: 0.08 | K23: 0.07 | L23: 0.07 | R23: =R11 -> Other | T23: =T11/S11-1 -> #DIV/0! | U23: =U11/T11-1 -> 0.14253049 | V23: =V11/U11-1 -> -0.056037358 | W23: =W11/V11-1 -> 0.20777385 | X23: =X11/W11-1 -> -0.0374488 | Y23: =Y11/X11-1 -> 0.1118541 | Z23: =Z11/Y11-1 -> -0.10060142 | AA23: 0.1
B24: =B12 -> Retail | D24: =D12/C12-1 -> 0.06443992 | E24: =E12/D12-1 -> 0.11556235 | F24: =F12/E12-1 -> 0.095810573 | G24: =G12/F12-1 -> 0.1089662 | H24: =H12/G12-1 -> 0.096655707 | I24: =I12/H12-1 -> 0.094628681 | J24: =J12/I12-1 -> 0.09802302 | K24: =K12/J12-1 -> 0.091843666 | L24: =L12/K12-1 -> 0.088978039 | R24: =R12 -> Retail | T24: =T12/S12-1 -> #DIV/0! | U24: =U12/T12-1 -> 0.082507911 | V24: =V12/U12-1 -> 0.075524925 | W24: =W12/V12-1 -> 0.20823169 | X24: =X12/W12-1 -> -0.19051556 | Y24: =Y12/X12-1 -> 0.10033905 | Z24: =Z12/Y12-1 -> -0.015242401 | AA24: =AA12/Z12-1 -> 0.20865959
B25: =B13 -> AWS | D25: =D13/C13-1 -> 0.28767564 | E25: =E13/D13-1 -> 0.13310278 | F25: =F13/E13-1 -> 0.18509867 | G25: =G13/F13-1 -> 0.1968184 | H25: 0.41 | I25: 0.35 | J25: 0.23 | K25: 0.18 | L25: 0.14 | R25: =R13 -> AWS | T25: =T13/S13-1 -> #DIV/0! | U25: =U13/T13-1 -> 0.053644036 | V25: =V13/U13-1 -> 0.070337581 | W25: =W13/V13-1 -> 0.079046234 | X25: =X13/W13-1 -> 0.055369928 | Y25: =Y13/X13-1 -> 0.12357996 | Z25: =Z13/Y13-1 -> 0.088842584 | AA25: 0.2
B26: =B14 -> Total | D26: =D14/C14-1 -> 0.093995173 | E26: =E14/D14-1 -> 0.11829574 | F26: =F14/E14-1 -> 0.10990892 | G26: =G14/F14-1 -> 0.12377755 | H26: =H14/G14-1 -> 0.15291724 | I26: =I14/H14-1 -> 0.15070544 | J26: =J14/I14-1 -> 0.13202299 | K26: =K14/J14-1 -> 0.11652018 | L26: =L14/K14-1 -> 0.10407199 | R26: =R14 -> Total | T26: =T14/S14-1 -> -0.17106693 | U26: =U14/T14-1 -> 0.077312468 | V26: =V14/U14-1 -> 0.074340199 | W26: =W14/V14-1 -> 0.18436579 | X26: =X14/W14-1 -> -0.14933969 | Y26: =Y14/X14-1 -> 0.10515153 | Z26: =Z14/Y14-1 -> 0.0066697905 | AA26: =AA14/Z14-1 -> 0.20668775

Sheet COGS & OpEx
B1: COGS & OpEx forecast
C2: History | H2: Forecast | P2: History | X2: Forecast | AB2: TTM
C4: Revenues | P4: Revenues
B5: =Revenue!B5 -> Revenues (thousand) | C5: =Revenue!C5 -> 2021 | D5: =Revenue!D5 -> 2022 | E5: =Revenue!E5 -> 2023 | F5: =Revenue!F5 -> 2024 | G5: =Revenue!G5 -> 2025 | H5: =G5+1 -> 2026 | I5: =H5+1 -> 2027 | J5: =I5+1 -> 2028 | K5: =J5+1 -> 2029 | L5: =K5+1 -> 2030 | O5: Revenues (thousand) | P5: =Revenue!S5 -> Q4 2024 | Q5: =Revenue!T5 -> Q1 2025 | R5: =Revenue!U5 -> Q2 2025 | S5: =Revenue!V5 -> Q3 2025 | T5: =Revenue!W5 -> Q4 2025 | U5: =Revenue!X5 -> Q1 2026 | V5: =Revenue!Y5 -> Q2 2026 | W5: =Revenue!Z5 -> Q3 2026 | X5: FQ1 | Y5: FQ2 | Z5: FQ3 | AB5: =Revenue!AE5 -> FQ1
B6: Revenue | C6: =Revenue!C14 -> 469822 | D6: =Revenue!D14 -> 513983 | E6: =Revenue!E14 -> 574785 | F6: =Revenue!F14 -> 637959 | G6: =Revenue!G14 -> 716924 | H6: =Revenue!H14 -> 826554.04 | I6: =Revenue!I14 -> 951120.23 | J6: =Revenue!J14 -> 1076690 | ... L6: =Revenue!L14 -> 1327255.8 | O6: Revenue | P6: =Revenue!S14 -> 187792 | Q6: =Revenue!T14 -> 155667 | R6: =Revenue!U14 -> 167702 | S6: =Revenue!V14 -> 180169 | T6: =Revenue!W14 -> 213386 | U6: =Revenue!X14 -> 181519 | V6: =Revenue!Y14 -> 200606 | W6: =Revenue!Z14 -> 201944 | X6: =Revenue!AA14 -> 243683.35 | AB6: =Revenue!AE14 -> 827752.35
B7: Retail | C7: =Revenue!C12 -> 407620 | D7: =Revenue!D12 -> 433887 | E7: =Revenue!E12 -> 484028 | F7: =Revenue!F12 -> 530403 | G7: =Revenue!G12 -> 588199 | H7: =Revenue!H12 -> 645051.79 | I7: =Revenue!I12 -> 706092.19 | J7: =Revenue!J12 -> 775305.48 | ... L7: =Revenue!L12 -> 921833.39 | O7: Retail | P7: =Revenue!S12 -> 0 | Q7: =Revenue!T12 -> 126400 | R7: =Revenue!U12 -> 136829 | S7: =Revenue!V12 -> 147163 | T7: =Revenue!W12 -> 177807 | U7: =Revenue!X12 -> 143932 | V7: =Revenue!Y12 -> 158374 | W7: =Revenue!Z12 -> 155960 | X7: =Revenue!AA12 -> 188502.55 | AB7: =Revenue!AE12 -> 646768.55
B8: Retail Store | C8: =SUM(Revenue!C6:C8) -> 342516 | D8: =SUM(Revenue!D6:D8) -> 356683 | E8: =SUM(Revenue!E6:E8) -> 391955 | F8: =SUM(Revenue!F6:F8) -> 424390 | G8: =SUM(Revenue!G6:G8) -> 464010 | H8: =SUM(Revenue!H6:H8) -> 505130.84 | I8: =SUM(Revenue!I6:I8) -> 545511.21 | J8: =SUM(Revenue!J6:J8) -> 589209.48 | ... L8: =SUM(Revenue!L6:L8) -> 682867.85 | O8: Retail Store | P8: =SUM(Revenue!S6:S8) -> 0 | Q8: =SUM(Revenue!T6:T8) -> 99452 | R8: =SUM(Revenue!U6:U8) -> 107428 | S8: =SUM(Revenue!V6:V8) -> 115471 | T8: =SUM(Revenue!W6:W8) -> 141659 | U8: =SUM(Revenue!X6:X8) -> 111617 | V8: =SUM(Revenue!Y6:Y8) -> 123006 | W8: =SUM(Revenue!Z6:Z8) -> 120672 | X8: =SUM(Revenue!AA6:AA8) -> 151367.9 | AB8: =SUM(Revenue!AE6:AE8) -> 506662.9
C12: COGS and OpEx | P12: COGS & OpEx | AB12: =AB4 -> 0
B13: Expenses (tnousand) | C13: =C5 -> 2021 | D13: =D5 -> 2022 | E13: =E5 -> 2023 | F13: =F5 -> 2024 | G13: =G5 -> 2025 | H13: =H5 -> 2026 | I13: =I5 -> 2027 | J13: =J5 -> 2028 | ... L13: =L5 -> 2030 | O13: Expenses (thousand) | P13: =P5 -> Q4 2024 | Q13: =Q5 -> Q1 2025 | R13: =R5 -> Q2 2025 | S13: =S5 -> Q3 2025 | T13: =T5 -> Q4 2025 | U13: =U5 -> Q1 2026 | V13: =V5 -> Q2 2026 | W13: =W5 -> Q3 2026 | ... Z13: =Z5 -> FQ3 | AB13: =AB5 -> FQ1
B14: =Statement!B197 -> Cost of Sales COGS | C14: =Statement!M197 -> 272344 | D14: =Statement!N197 -> 288831 | E14: =Statement!O197 -> 304739 | F14: =Statement!P197 -> 326288 | G14: =Statement!Q197 -> 356414 | H14: =H7*H25 -> 393481.59 | I14: =I7*I25 -> 423655.31 | J14: =J7*J25 -> 480689.4 | K14: =K7*K25 -> 533302.8 | L14: =L7*L25 -> 562318.37 | O14: =B14 -> Cost of Sales COGS | P14: =Statement!T197 -> 98893 | Q14: =Statement!U197 -> 76976 | R14: =Statement!V197 -> 80809 | S14: =Statement!W197 -> 88670 | T14: =Statement!X197 -> 109959 | U14: =Statement!Y197 -> 87463 | V14: =Statement!Z197 -> 95778 | W14: =Statement!AA197 -> 94573 | X14: =X25*X$7 -> 113101.53 | AB14: =SUM(U14:X14) -> 390915.53
B15: =Statement!B198 -> Fulfillment COGS | C15: =Statement!M198 -> 75111 | D15: =Statement!N198 -> 84299 | E15: =Statement!O198 -> 90619 | F15: =Statement!P198 -> 98505 | G15: =Statement!Q198 -> 109074 | H15: =H8*H26 -> 136385.33 | I15: =I8*I26 -> 130922.69 | J15: =J8*J26 -> 135518.18 | K15: =K8*K26 -> 158567.66 | L15: =L8*L26 -> 163888.29 | O15: =B15 -> Fulfillment COGS | P15: =Statement!T198 -> 27962 | Q15: =Statement!U198 -> 24593 | R15: =Statement!V198 -> 25976 | S15: =Statement!W198 -> 27679 | T15: =Statement!X198 -> 30826 | U15: =Statement!Y198 -> 27289 | V15: =Statement!Z198 -> 29633 | W15: =Statement!AA198 -> 29997 | X15: =X26*X$8 -> 34814.617 | AB15: =SUM(U15:X15) -> 121733.62
B16: COGS | C16: =Statement!M6 -> 347455 | D16: =Statement!N6 -> 373130 | E16: =Statement!O6 -> 395358 | F16: =Statement!P6 -> 424793 | G16: =Statement!Q6 -> 465488 | H16: =SUM(H14:H15) -> 529866.92 | I16: =SUM(I14:I15) -> 554578 | J16: =SUM(J14:J15) -> 616207.58 | K16: =SUM(K14:K15) -> 691870.45 | L16: =SUM(L14:L15) -> 726206.65 | O16: =B16 -> COGS | P16: =Statement!T6 -> 126855 | Q16: =Statement!U6 -> 101569 | R16: =Statement!V6 -> 106785 | S16: =Statement!W6 -> 116349 | T16: =Statement!X6 -> 140785 | U16: =Statement!Y6 -> 114752 | V16: =Statement!Z6 -> 125411 | W16: =Statement!AA6 -> 124570 | X16: =SUM(X14:X15) -> 147916.15 | AB16: =SUM(AB14:AB15) -> 512649.15
B17: =Statement!B8 -> Tech and infra | C17: =Statement!M8 -> 56052 | D17: =Statement!N8 -> 73213 | E17: =Statement!O8 -> 85622 | F17: =Statement!P8 -> 88544 | G17: =Statement!Q8 -> 108521 | H17: =H6*H28 -> 148779.73 | I17: =I6*I28 -> 142668.03 | J17: =J6*J28 -> 172270.39 | K17: =K6*K28 -> 168300.45 | L17: =L6*L28 -> 199088.37 | O17: =B17 -> Tech and infra | P17: =Statement!T8 -> 23571 | Q17: =Statement!U8 -> 22994 | R17: =Statement!V8 -> 27166 | S17: =Statement!W8 -> 28962 | T17: =Statement!X8 -> 29399 | U17: =Statement!Y8 -> 29567 | V17: =Statement!Z8 -> 33158 | W17: =Statement!AA8 -> 34814 | X17: =X28*X$6 -> 46299.836 | AB17: =SUM(U17:X17) -> 143838.84
B18: =Statement!B9 -> Sales and marketing | C18: =Statement!M9 -> 32551 | D18: =Statement!N9 -> 42238 | E18: =Statement!O9 -> 44370 | F18: =Statement!P9 -> 43907 | G18: =Statement!Q9 -> 47129 | H18: =H6*H29 -> 66124.323 | I18: =I6*I29 -> 66578.416 | J18: =J6*J29 -> 64601.398 | K18: =K6*K29 -> 96171.686 | L18: =L6*L29 -> 86271.627 | O18: =B18 -> Sales and marketing | P18: =Statement!T9 -> 13124 | Q18: =Statement!U9 -> 9763 | R18: =Statement!V9 -> 11416 | S18: =Statement!W9 -> 11686 | T18: =Statement!X9 -> 14264 | U18: =Statement!Y9 -> 10314 | V18: =Statement!Z9 -> 11698 | W18: =Statement!AA9 -> 11649 | X18: =X29*X$6 -> 19494.668 | AB18: =SUM(U18:X18) -> 53155.668
B19: =Statement!B10 -> General and administrative | C19: =Statement!M10 -> 8823 | D19: =Statement!N10 -> 11891 | E19: =Statement!O10 -> 11816 | F19: =Statement!P10 -> 11359 | G19: =Statement!Q10 -> 11172 | H19: =H6*H30 -> 16531.081 | I19: =I6*I30 -> 14266.803 | J19: =J6*J30 -> 21533.799 | K19: =K6*K30 -> 24042.921 | L19: =L6*L30 -> 26545.116 | O19: =B19 -> General and administrative | P19: =Statement!T10 -> 2863 | Q19: =Statement!U10 -> 2628 | R19: =Statement!V10 -> 2965 | S19: =Statement!W10 -> 2875 | T19: =Statement!X10 -> 2704 | U19: =Statement!Y10 -> 2587 | V19: =Statement!Z10 -> 2788 | W19: =Statement!AA10 -> 2701 | X19: =X30*X$6 -> 4873.667 | AB19: =SUM(U19:X19) -> 12949.667
B20: OpEx | C20: =Statement!M12 -> 97488 | D20: =Statement!N12 -> 128605 | E20: =Statement!O12 -> 142575 | F20: =Statement!P12 -> 144573 | G20: =Statement!Q12 -> 171461 | H20: =SUM(H17:H19) -> 231435.13 | I20: =SUM(I17:I19) -> 223513.25 | J20: =SUM(J17:J19) -> 258405.59 | K20: =SUM(K17:K19) -> 288515.06 | L20: =SUM(L17:L19) -> 311905.11 | O20: =B20 -> OpEx | P20: =Statement!T12 -> 39734 | Q20: =Statement!U12 -> 35693 | R20: =Statement!V12 -> 41746 | S20: =Statement!W12 -> 46398 | T20: =Statement!X12 -> 47624 | U20: =Statement!Y12 -> 42915 | V20: =Statement!Z12 -> 47734 | W20: =Statement!AA12 -> 49298 | X20: =SUM(X17:X19) -> 70668.171 | AB20: =SUM(U20:X20) -> 210615.17
C23: Expenses % of Revenue | P23: Expenses % of Revenue
B24: % of revenue | C24: =C5 -> 2021 | D24: =D5 -> 2022 | E24: =E5 -> 2023 | F24: =F5 -> 2024 | G24: =G5 -> 2025 | H24: =H5 -> 2026 | I24: =I5 -> 2027 | J24: =J5 -> 2028 | ... L24: =L5 -> 2030 | O24: % of revenue | P24: =P5 -> Q4 2024 | Q24: =Q5 -> Q1 2025 | R24: =R5 -> Q2 2025 | S24: =S5 -> Q3 2025 | T24: =T5 -> Q4 2025 | U24: =U5 -> Q1 2026 | V24: =V5 -> Q2 2026 | W24: =W5 -> Q3 2026 | ... Z24: =Z5 -> FQ3
B25: =B14 -> Cost of Sales COGS | C25: =C14/C$7 -> 0.66813208 | D25: =D14/D$7 -> 0.66568254 | E25: =E14/E$7 -> 0.62958961 | F25: =F14/F$7 -> 0.61516997 | G25: =G14/G$7 -> 0.60594119 | H25: 0.61 | I25: 0.6 | J25: 0.62 | K25: 0.63 | L25: 0.61 | O25: =O14 -> Cost of Sales COGS | P25: =P14/P$7 -> #DIV/0! | Q25: =Q14/Q$7 -> 0.60898734 | R25: =R14/R$7 -> 0.59058387 | S25: =S14/S$7 -> 0.60252917 | T25: =T14/T$7 -> 0.61841772 | U25: =U14/U$7 -> 0.6076689 | V25: =V14/V$7 -> 0.60475836 | W25: =W14/W$7 -> 0.60639266 | X25: 0.6
B26: =B15 -> Fulfillment COGS | C26: =C15/C$8 -> 0.21929195 | D26: =D15/D$8 -> 0.23634151 | E26: =E15/E$8 -> 0.23119746 | F26: =F15/F$8 -> 0.23210962 | G26: =G15/G$8 -> 0.23506821 | H26: 0.27 | I26: 0.24 | J26: 0.23 | K26: 0.25 | L26: 0.24 | O26: =O15 -> Fulfillment COGS | P26: =P15/P$8 -> #DIV/0! | Q26: =Q15/Q$8 -> 0.24728512 | R26: =R15/R$8 -> 0.24179916 | S26: =S15/S$8 -> 0.23970521 | T26: =T15/T$8 -> 0.21760707 | U26: =U15/U$8 -> 0.24448785 | V26: =V15/V$8 -> 0.24090695 | W26: =W15/W$8 -> 0.24858294 | X26: 0.23
B27: =B16 -> COGS | C27: =C16/C$6 -> 0.73954604 | D27: =D16/D$6 -> 0.72595786 | E27: =E16/E$6 -> 0.68783632 | F27: =F16/F$6 -> 0.66586254 | G27: =G16/G$6 -> 0.649285 | H27: =H16/H$6 -> 0.64105539 | I27: =I16/I$6 -> 0.58307876 | J27: =J16/J$6 -> 0.57231664 | ... L27: =L16/L$6 -> 0.54714898 | O27: =O16 -> COGS | P27: =P16/P$6 -> 0.67550801 | Q27: =Q16/Q$6 -> 0.65247612 | R27: =R16/R$6 -> 0.63675448 | S27: =S16/S$6 -> 0.64577702 | T27: =T16/T$6 -> 0.65976681 | U27: =U16/U$6 -> 0.63217625 | V27: =V16/V$6 -> 0.62516076 | W27: =W16/W$6 -> 0.61685418 | X27: =X16/X$6 -> 0.60700145
B28: =B17 -> Tech and infra | C28: =C17/C$6 -> 0.11930476 | D28: =D17/D$6 -> 0.14244245 | E28: =E17/E$6 -> 0.14896353 | F28: =F17/F$6 -> 0.13879262 | G28: =G17/G$6 -> 0.1513703 | H28: 0.18 | I28: 0.15 | J28: 0.16 | K28: 0.14 | L28: 0.15 | O28: =O17 -> Tech and infra | P28: =P17/P$6 -> 0.12551653 | Q28: =Q17/Q$6 -> 0.14771275 | R28: =R17/R$6 -> 0.16198972 | S28: =S17/S$6 -> 0.16074907 | T28: =T17/T$6 -> 0.1377738 | U28: =U17/U$6 -> 0.16288653 | V28: =V17/V$6 -> 0.16528917 | W28: =W17/W$6 -> 0.17239433 | X28: 0.19
B29: =B18 -> Sales and marketing | C29: =C18/C$6 -> 0.069283686 | D29: =D18/D$6 -> 0.082177815 | E29: =E18/E$6 -> 0.077194081 | F29: =F18/F$6 -> 0.068824172 | G29: =G18/G$6 -> 0.065737791 | H29: 0.08 | I29: 0.07 | J29: 0.06 | K29: 0.08 | L29: 0.065 | O29: =O18 -> Sales and marketing | P29: =P18/P$6 -> 0.069885831 | Q29: =Q18/Q$6 -> 0.06271721 | R29: =R18/R$6 -> 0.06807313 | S29: =S18/S$6 -> 0.064861325 | T29: =T18/T$6 -> 0.066845997 | U29: =U18/U$6 -> 0.056820498 | V29: =V18/V$6 -> 0.058313311 | W29: =W18/W$6 -> 0.057684309 | X29: 0.08
B30: =B19 -> General and administrative | C30: =C19/C$6 -> 0.018779453 | D30: =D19/D$6 -> 0.023135006 | E30: =E19/E$6 -> 0.020557252 | F30: =F19/F$6 -> 0.017805219 | G30: =G19/G$6 -> 0.015583242 | H30: 0.02 | I30: 0.015 | J30: 0.02 | K30: 0.02 | L30: 0.02 | O30: =O19 -> General and administrative | P30: =P19/P$6 -> 0.015245591 | Q30: =Q19/Q$6 -> 0.016882191 | R30: =R19/R$6 -> 0.017680171 | S30: =S19/S$6 -> 0.01595724 | T30: =T19/T$6 -> 0.012671872 | U30: =U19/U$6 -> 0.014251952 | V30: =V19/V$6 -> 0.013897889 | W30: =W19/W$6 -> 0.013374995 | X30: 0.02
B31: =B20 -> OpEx | C31: =C20/C$6 -> 0.20749986 | D31: =D20/D$6 -> 0.25021256 | E31: =E20/E$6 -> 0.24804927 | F31: =F20/F$6 -> 0.22661801 | G31: =G20/G$6 -> 0.23916203 | H31: =H20/H$6 -> 0.28 | I31: =I20/I$6 -> 0.235 | J31: =J20/J$6 -> 0.24 | ... L31: =L20/L$6 -> 0.235 | O31: =O20 -> OpEx | P31: =P20/P$6 -> 0.21158516 | Q31: =Q20/Q$6 -> 0.22929073 | R31: =R20/R$6 -> 0.24892965 | S31: =S20/S$6 -> 0.25752488 | T31: =T20/T$6 -> 0.2231824 | U31: =U20/U$6 -> 0.23642153 | V31: =V20/V$6 -> 0.23794901 | W31: =W20/W$6 -> 0.24411718 | X31: =X20/X$6 -> 0.29

Sheet WC & Investments
B1: Working Capital, Capex, D&A
C3: History | H3: Forecast
C5: Revenues
B6: Revenues (thousand) | C6: =Revenue!C5 -> 2021 | D6: =Revenue!D5 -> 2022 | E6: =Revenue!E5 -> 2023 | F6: =Revenue!F5 -> 2024 | G6: =Revenue!G5 -> 2025 | H6: =G6+1 -> 2026 | I6: =H6+1 -> 2027 | J6: =I6+1 -> 2028 | K6: =J6+1 -> 2029 | L6: =K6+1 -> 2030
B7: Revenue | C7: =Revenue!C14 -> 469822 | D7: =Revenue!D14 -> 513983 | E7: =Revenue!E14 -> 574785 | F7: =Revenue!F14 -> 637959 | G7: =Revenue!G14 -> 716924 | H7: =Revenue!H14 -> 826554.04 | I7: =Revenue!I14 -> 951120.23 | J7: =Revenue!J14 -> 1076690 | ... L7: =Revenue!L14 -> 1327255.8
B8: COGS | C8: ='COGS & OpEx'!C16 -> 347455 | D8: ='COGS & OpEx'!D16 -> 373130 | E8: ='COGS & OpEx'!E16 -> 395358 | F8: ='COGS & OpEx'!F16 -> 424793 | G8: ='COGS & OpEx'!G16 -> 465488 | H8: ='COGS & OpEx'!H16 -> 529866.92 | I8: ='COGS & OpEx'!I16 -> 554578 | J8: ='COGS & OpEx'!J16 -> 616207.58 | ... L8: ='COGS & OpEx'!L16 -> 726206.65
C11: Working Capital
B12: $ (thousand) | C12: =C6 -> 2021 | D12: =D6 -> 2022 | E12: =E6 -> 2023 | F12: =F6 -> 2024 | G12: =G6 -> 2025 | H12: =H6 -> 2026 | I12: =I6 -> 2027 | J12: =J6 -> 2028 | ... L12: =L6 -> 2030
B13: Accounts receivable | C13: =Statement!M31 -> 32891 | D13: =Statement!N31 -> 42360 | E13: =Statement!O31 -> 52253 | F13: =Statement!P31 -> 55451 | G13: =Statement!Q31 -> 67729 | H13: =H20*H7/365 -> 86052.201 | I13: =I20*I7/365 -> 99020.736 | J13: =J20*J7/365 -> 112093.75 | K13: =K20*K7/365 -> 125154.93 | L13: =L20*L7/365 -> 138180.06
B14: Inventory | C14: =Statement!M32 -> 32640 | D14: =Statement!N32 -> 34405 | E14: =Statement!O32 -> 33318 | F14: =Statement!P32 -> 34214 | G14: =Statement!Q32 -> 38325 | H14: =H21*H8/365 -> 39195.635 | I14: =I21*I8/365 -> 41023.578 | J14: =J21*J8/365 -> 45582.478 | K14: =K21*K8/365 -> 51179.458 | L14: =L21*L8/365 -> 53719.396
B15: Accounts payable | C15: =Statement!M39 -> 78664 | D15: =Statement!N39 -> 79600 | E15: =Statement!O39 -> 84981 | F15: =Statement!P39 -> 94363 | G15: =Statement!Q39 -> 121909 | H15: =H22*H8/365 -> 145169.02 | I15: =I22*I8/365 -> 151939.18 | J15: =J22*J8/365 -> 168823.99 | K15: =K22*K8/365 -> 189553.55 | L15: =L22*L8/365 -> 198960.73
C18: WC metrics and drivers
B19: Days | C19: =C6 -> 2021 | D19: =D6 -> 2022 | E19: =E6 -> 2023 | F19: =F6 -> 2024 | G19: =G6 -> 2025 | H19: =H6 -> 2026 | I19: =I6 -> 2027 | J19: =J6 -> 2028 | ... L19: =L6 -> 2030
B20: DSO | C20: =C13/C7*365 -> 25.552688 | D20: =D13/D7*365 -> 30.08154 | E20: =E13/E7*365 -> 33.181703 | F20: =F13/F7*365 -> 31.725573 | G20: =G13/G7*365 -> 34.482156 | H20: 38 | I20: 38 | J20: 38 | K20: 38 | L20: 38
B21: DIO | C21: =C14/C8*365 -> 34.288181 | D21: =D14/D8*365 -> 33.655361 | E21: =E14/E8*365 -> 30.759641 | F21: =F14/F8*365 -> 29.398107 | G21: =G14/G8*365 -> 30.051527 | H21: 27 | I21: 27 | J21: 27 | K21: 27 | L21: 27
B22: DPO | C22: =C15/C8*365 -> 82.636197 | D22: =D15/D8*365 -> 77.865623 | E22: =E15/E8*365 -> 78.45564 | F22: =F15/F8*365 -> 81.080656 | G22: =G15/G8*365 -> 95.591691 | H22: 100 | I22: 100 | J22: 100 | K22: 100 | L22: 100
B23: Net trade cycle | C23: =C20+C21-C22 -> -22.795328 | D23: =D20+D21-D22 -> -14.128722 | E23: =E20+E21-E22 -> -14.514297 | F23: =F20+F21-F22 -> -19.956976 | G23: =G20+G21-G22 -> -31.058009 | H23: =H20+H21-H22 -> -35 | I23: =I20+I21-I22 -> -35 | J23: =J20+J21-J22 -> -35 | ... L23: =L20+L21-L22 -> -35
C26: Change in SIP NWC
B27: $ (thousand) | C27: =C6 -> 2021 | D27: =D6 -> 2022 | E27: =E6 -> 2023 | F27: =F6 -> 2024 | G27: =G6 -> 2025 | H27: =H6 -> 2026 | I27: =I6 -> 2027 | J27: =J6 -> 2028 | ... L27: =L6 -> 2030
B28: Change in acc receivable | C28: =Statement!M56 -> -9145 | D28: =Statement!N56 -> -8622 | E28: =Statement!O56 -> -8348 | F28: =Statement!P56 -> -3249 | G28: =Statement!Q56 -> -7333 | H28: =-(H13-G13) -> -18323.201 | I28: =-(I13-H13) -> -12968.535 | J28: =-(J13-I13) -> -13073.014 | K28: =-(K13-J13) -> -13061.184 | L28: =-(L13-K13) -> -13025.122
B29: Change in inventory | C29: =Statement!M57 -> -9487 | D29: =Statement!N57 -> -2592 | E29: =Statement!O57 -> 1449 | F29: =Statement!P57 -> -1884 | G29: =Statement!Q57 -> -3002 | H29: =-(H14-G14) -> -870.63508 | I29: =-(I14-H14) -> -1827.9433 | J29: =-(J14-I14) -> -4558.8999 | K29: =-(K14-J14) -> -5596.9799 | L29: =-(L14-K14) -> -2539.9379
B30: Change in acc payable | C30: =Statement!M58 -> 3602 | D30: =Statement!N58 -> 2945 | E30: =Statement!O58 -> 5473 | F30: =Statement!P58 -> 2972 | G30: =Statement!Q58 -> 11231 | H30: =H15-G15 -> 23260.019 | I30: =I15-H15 -> 6770.1605 | J30: =J15-I15 -> 16884.815 | K30: =K15-J15 -> 20729.555 | L30: =L15-K15 -> 9407.1775
C33: Total change in NWC and less SIP
B34: $ (thousand) | C34: =C6 -> 2021 | D34: =D6 -> 2022 | E34: =E6 -> 2023 | F34: =F6 -> 2024 | G34: =G6 -> 2025 | H34: =H6 -> 2026 | I34: =I6 -> 2027 | J34: =J6 -> 2028 | ... L34: =L6 -> 2030
B35: Total change in NWC | C35: =Statement!M56+Statement!M57+Statement!M58+Statement!M59 -> -19611 | D35: =Statement!N56+Statement!N57+Statement!N58+Statement!N59 -> -20886 | E35: =Statement!O56+Statement!O57+Statement!O58+Statement!O59 -> -11541 | F35: =Statement!P56+Statement!P57+Statement!P58+Statement!P59 -> -15541 | G35: =Statement!Q56+Statement!Q57+Statement!Q58+Statement!Q59 -> -19969 | H35: =H36+H28+H29+H30 -> -8332.1283 | I35: =I36+I28+I29+I30 -> -27048.722 | J35: =J36+J28+J29+J30 -> -16897.449 | K35: =K36+K28+K29+K30 -> -21971.53 | L35: =L36+L28+L29+L30 -> -26066.72
B36: Change in NWC less SIP | C36: =C35-C28-C29-C30 -> -4581 | D36: =D35-D28-D29-D30 -> -12617 | E36: =E35-E28-E29-E30 -> -10115 | F36: =F35-F28-F29-F30 -> -13380 | G36: =G35-G28-G29-G30 -> -20865 | H36: =H7*H37 -> -12398.311 | I36: =I7*I37 -> -19022.405 | J36: =J7*J37 -> -16150.349 | K36: =K7*K37 -> -24042.921 | L36: =L7*L37 -> -19908.837
B37: % of revenue | C37: =C36/C7 -> -0.0097505013 | D37: =D36/D7 -> -0.024547504 | E37: =E36/E7 -> -0.017597884 | F37: =F36/F7 -> -0.020973135 | G37: =G36/G7 -> -0.029103503 | H37: -0.015 | I37: -0.02 | J37: -0.015 | K37: -0.02 | L37: -0.015
C40: Investments
B41: $ (thousand) | C41: =C6 -> 2021 | D41: =D6 -> 2022 | E41: =E6 -> 2023 | F41: =F6 -> 2024 | G41: =G6 -> 2025 | H41: =H6 -> 2026 | I41: =I6 -> 2027 | J41: =J6 -> 2028 | ... L41: =L6 -> 2030
B42: D&A | C42: =Statement!M54 -> 34433 | D42: =Statement!N54 -> 41921 | E42: =Statement!O54 -> 48663 | F42: =Statement!P54 -> 52795 | G42: =Statement!Q54 -> 65756 | H42: =H7*H43 -> 90920.944 | I42: =I7*I43 -> 123645.63 | J42: =J7*J43 -> 139969.7 | K42: =K7*K43 -> 144257.53 | L42: =L7*L43 -> 132725.58
B43: % of Revenue | C43: =C42/C7 -> 0.073289459 | D43: =D42/D7 -> 0.081561063 | E43: =E42/E7 -> 0.084662961 | F43: =F42/F7 -> 0.082756102 | G43: =G42/G7 -> 0.091719624 | H43: 0.11 | I43: 0.13 | J43: 0.13 | K43: 0.12 | L43: 0.1
B44: % of CapEx | C44: =C42/C45 -> 0.56398539 | D44: =D42/D45 -> 0.65866918 | E44: =E42/E45 -> 0.92288873 | F44: =F42/F45 -> 0.636092 | G44: =G42/G45 -> 0.49883552 | H44: =H42/H45 -> 0.40740741 | I44: =I42/I45 -> 0.56521739 | J44: =J42/J45 -> 0.65 | ... L44: =L42/L45 -> 0.71428571
B45: CapEx | C45: =-Statement!M111 -> 61053 | D45: =-Statement!N111 -> 63645 | E45: =-Statement!O111 -> 52729 | F45: =-Statement!P111 -> 82999 | G45: =-Statement!Q111 -> 131819 | H45: =H7*H46 -> 223169.59 | I45: =I7*I46 -> 218757.65 | J45: =J7*J46 -> 215337.99 | K45: =K7*K46 -> 204364.83 | L45: =L7*L46 -> 185815.81
B46: % of Revenue | C46: =C45/C7 -> 0.12994921 | D46: =D45/D7 -> 0.12382705 | E46: =E45/E7 -> 0.09173691 | F46: =F45/F7 -> 0.13010084 | G46: =G45/G7 -> 0.18386747 | H46: 0.27 | I46: 0.23 | J46: 0.2 | K46: 0.17 | L46: 0.14

Sheet FCF & Other
B1: Results
C2: History | H2: Forecast
C4: Income statement
B5: $ (thousand) | C5: =Revenue!C5 -> 2021 | D5: =Revenue!D5 -> 2022 | E5: =Revenue!E5 -> 2023 | F5: =Revenue!F5 -> 2024 | G5: =Revenue!G5 -> 2025 | H5: =G5+1 -> 2026 | I5: =H5+1 -> 2027 | J5: =I5+1 -> 2028 | K5: =J5+1 -> 2029 | L5: =K5+1 -> 2030
B6: Revenue | C6: =Revenue!C14 -> 469822 | D6: =Revenue!D14 -> 513983 | E6: =Revenue!E14 -> 574785 | F6: =Revenue!F14 -> 637959 | G6: =Revenue!G14 -> 716924 | H6: =Revenue!H14 -> 826554.04 | I6: =Revenue!I14 -> 951120.23 | J6: =Revenue!J14 -> 1076690 | ... L6: =Revenue!L14 -> 1327255.8 | N6: From Revenue Sheet
B7: COGS | C7: ='COGS & OpEx'!C16 -> 347455 | D7: ='COGS & OpEx'!D16 -> 373130 | E7: ='COGS & OpEx'!E16 -> 395358 | F7: ='COGS & OpEx'!F16 -> 424793 | G7: ='COGS & OpEx'!G16 -> 465488 | H7: ='COGS & OpEx'!H16 -> 529866.92 | I7: ='COGS & OpEx'!I16 -> 554578 | J7: ='COGS & OpEx'!J16 -> 616207.58 | ... L7: ='COGS & OpEx'!L16 -> 726206.65 | N7: From COGS and OpEx Sheet
B8: Gross profit | C8: =C6-C7 -> 122367 | D8: =D6-D7 -> 140853 | E8: =E6-E7 -> 179427 | F8: =F6-F7 -> 213166 | G8: =G6-G7 -> 251436 | H8: =H6-H7 -> 296687.12 | I8: =I6-I7 -> 396542.22 | J8: =J6-J7 -> 460482.39 | ... L8: =L6-L7 -> 601049.15
B9: OpEx | C9: ='COGS & OpEx'!C20 -> 97488 | D9: ='COGS & OpEx'!D20 -> 128605 | E9: ='COGS & OpEx'!E20 -> 142575 | F9: ='COGS & OpEx'!F20 -> 144573 | G9: ='COGS & OpEx'!G20 -> 171461 | H9: ='COGS & OpEx'!H20 -> 231435.13 | I9: ='COGS & OpEx'!I20 -> 223513.25 | J9: ='COGS & OpEx'!J20 -> 258405.59 | ... L9: ='COGS & OpEx'!L20 -> 311905.11 | N9: From COGS and OpEx Sheet
B10: EBIT | C10: =C8-C9 -> 24879 | D10: =D8-D9 -> 12248 | E10: =E8-E9 -> 36852 | F10: =F8-F9 -> 68593 | G10: =G8-G9 -> 79975 | H10: =H8-H9 -> 65251.99 | I10: =I8-I9 -> 173028.97 | J10: =J8-J9 -> 202076.8 | ... L10: =L8-L9 -> 289144.03
C13: Drivers
C14: =C5 -> 2021 | D14: =D5 -> 2022 | E14: =E5 -> 2023 | F14: =F5 -> 2024 | G14: =G5 -> 2025 | H14: =H5 -> 2026 | I14: =I5 -> 2027 | J14: =J5 -> 2028 | ... L14: =L5 -> 2030
B15: Tax rate | C15: =Statement!M84 -> 0.17994366 | D15: =Statement!N84 -> 0 | E15: =Statement!O84 -> 0.18957851 | F15: =Statement!P84 -> 0.13503075 | G15: =Statement!Q84 -> 0.22638802 | H15: =Overview!$C$26 -> 0.21 | I15: =Overview!$C$26 -> 0.21 | J15: =Overview!$C$26 -> 0.21 | K15: =Overview!$C$26 -> 0.21 | L15: =Overview!$C$26 -> 0.21 | N15: From Statements and Overview sheet
C18: Cash Flow Statement
B19: $ (thousand) | C19: =C5 -> 2021 | D19: =D5 -> 2022 | E19: =E5 -> 2023 | F19: =F5 -> 2024 | G19: =G5 -> 2025 | H19: =H5 -> 2026 | I19: =I5 -> 2027 | J19: =J5 -> 2028 | ... L19: =L5 -> 2030
B20: D&A | C20: ='WC & Investments'!C42 -> 34433 | D20: ='WC & Investments'!D42 -> 41921 | E20: ='WC & Investments'!E42 -> 48663 | F20: ='WC & Investments'!F42 -> 52795 | G20: ='WC & Investments'!G42 -> 65756 | H20: ='WC & Investments'!H42 -> 90920.944 | I20: ='WC & Investments'!I42 -> 123645.63 | J20: ='WC & Investments'!J42 -> 139969.7 | ... L20: ='WC & Investments'!L42 -> 132725.58 | N20: From WC & Investments Sheet
B21: CapEx | C21: ='WC & Investments'!C45 -> 61053 | D21: ='WC & Investments'!D45 -> 63645 | E21: ='WC & Investments'!E45 -> 52729 | F21: ='WC & Investments'!F45 -> 82999 | G21: ='WC & Investments'!G45 -> 131819 | H21: ='WC & Investments'!H45 -> 223169.59 | I21: ='WC & Investments'!I45 -> 218757.65 | J21: ='WC & Investments'!J45 -> 215337.99 | ... L21: ='WC & Investments'!L45 -> 185815.81 | N21: From WC & Investments Sheet
B22: Change in NWC | C22: ='WC & Investments'!C35 -> -19611 | D22: ='WC & Investments'!D35 -> -20886 | E22: ='WC & Investments'!E35 -> -11541 | F22: ='WC & Investments'!F35 -> -15541 | G22: ='WC & Investments'!G35 -> -19969 | H22: ='WC & Investments'!H35 -> -8332.1283 | I22: ='WC & Investments'!I35 -> -27048.722 | J22: ='WC & Investments'!J35 -> -16897.449 | ... L22: ='WC & Investments'!L35 -> -26066.72 | N22: From WC & Investments Sheet
C25: FCFF
B26: $ (thousand) | C26: =C5 -> 2021 | D26: =D5 -> 2022 | E26: =E5 -> 2023 | F26: =F5 -> 2024 | G26: =G5 -> 2025 | H26: =H5 -> 2026 | I26: =I5 -> 2027 | J26: =J5 -> 2028 | ... L26: =L5 -> 2030
B27: NOPAT | C27: =C10*(1-C15) -> 20402.182 | D27: =D10*(1-D15) -> 12248 | E27: =E10*(1-E15) -> 29865.653 | F27: =F10*(1-F15) -> 59330.836 | G27: =G10*(1-G15) -> 61869.618 | H27: =H10*(1-H15) -> 51549.072 | I27: =I10*(1-I15) -> 136692.89 | J27: =J10*(1-J15) -> 159640.67 | ... L27: =L10*(1-L15) -> 228423.79
B28: FCFF | C28: =C27+C20-C21+C22 -> -25828.818 | D28: =D27+D20-D21+D22 -> -30362 | E28: =E27+E20-E21+E22 -> 14258.653 | F28: =F27+F20-F21+F22 -> 13585.836 | G28: =G27+G20-G21+G22 -> -24162.382 | H28: =H27+H20-H21+H22 -> -89031.703 | I28: =I27+I20-I21+I22 -> 14532.141 | J28: =J27+J20-J21+J22 -> 67374.922 | ... L28: =L27+L20-L21+L22 -> 149266.84
C31: Margins
B32: % | C32: =C5 -> 2021 | D32: =D5 -> 2022 | E32: =E5 -> 2023 | F32: =F5 -> 2024 | G32: =G5 -> 2025 | H32: =H5 -> 2026 | I32: =I5 -> 2027 | J32: =J5 -> 2028 | ... L32: =L5 -> 2030
B33: Gross margin | C33: =Statement!M102 -> 0.26045396 | D33: =Statement!N102 -> 0.27404214 | E33: =Statement!O102 -> 0.31216368 | F33: =Statement!P102 -> 0.33413746 | G33: =Statement!Q102 -> 0.350715 | H33: =H8/H6 -> 0.35894461 | I33: =I8/I6 -> 0.41692124 | J33: =J8/J6 -> 0.42768336 | K33: =K8/K6 -> 0.42447056 | L33: =L8/L6 -> 0.45285102
B34: Operating margin | C34: =Statement!M103 -> 0.052954098 | D34: =Statement!N103 -> 0.023829582 | E34: =Statement!O103 -> 0.064114408 | F34: =Statement!P103 -> 0.10751945 | G34: =Statement!Q103 -> 0.11155297 | H34: =H10/H6 -> 0.078944615 | I34: =I10/I6 -> 0.18192124 | J34: =J10/J6 -> 0.18768336 | K34: =K10/K6 -> 0.18447056 | L34: =L10/L6 -> 0.21785102

Sheet Valuation ->
H5: Links
H6: Overview'!B3
H7: Financials ->'!B13
H8: Analysis ->'!B13
H9: Forecast ->'!B13
H10: Valuation ->'!B13
B13: Valuation ->

Sheet WACC
B1: WACC
B4: Inputs
B5: Shares Outstanding | C5: =Statement!AC79 -> 10920
B6: Price | C6: =Overview!C5 -> 243.79
B7: Equity | C7: =C5*C6 -> 2662186.8
B8: Debt | C8: =Statement!AC109 -> 173125
B9: Risk free rate | C9: =Overview!F27 -> 0.05045
B10: Beta | C10: =Overview!C13 -> 1.4919
B11: Market risk premium | C11: =[1]Sheet1!$C$12 -> 0.045
B12: Tax rate | C12: =Overview!C26 -> 0.21
B13: Cost of debt | C13: =Overview!C27 -> 0.059
B15: Calculations
B16: Debt/(Debt+Equity) | C16: =C8/(C8+C7) -> 0.061060304
B17: Equity/(Debt+Equity) | C17: =C7/(C8+C7) -> 0.9389397
B18: Cost of debt with tax | C18: =C13*(1-C12) -> 0.04661
B19: Cost of equity | C19: =C9+C10*C11 -> 0.1175855
B20: WACC | C20: =(C17*C19)+(C16*C18) -> 0.11325171

Sheet DCF
B1: DCF
C3: History | H3: Forecast
C5: PV of FCF
B6: $ (thousand) | C6: =Revenue!C5 -> 2021 | D6: =Revenue!D5 -> 2022 | E6: =Revenue!E5 -> 2023 | F6: =Revenue!F5 -> 2024 | G6: =Revenue!G5 -> 2025 | H6: =Revenue!H5 -> 2026 | I6: =Revenue!I5 -> 2027 | J6: =Revenue!J5 -> 2028 | ... L6: =Revenue!L5 -> 2030
B7: FCFF | C7: ='FCF & Other'!C28 -> -25828.818 | D7: ='FCF & Other'!D28 -> -30362 | E7: ='FCF & Other'!E28 -> 14258.653 | F7: ='FCF & Other'!F28 -> 13585.836 | G7: ='FCF & Other'!G28 -> -24162.382 | H7: ='FCF & Other'!H28 -> -89031.703 | I7: ='FCF & Other'!I28 -> 14532.141 | J7: ='FCF & Other'!J28 -> 67374.922 | ... L7: ='FCF & Other'!L28 -> 149266.84
B8: Perpetual cashflow | C8: 0 | D8: 0 | E8: 0 | F8: 0 | G8: 0 | H8: 0 | I8: 0 | J8: 0 | K8: 0 | L8: =L7*(1+C14)/(C15-C14) -> 1632701
B9: Period | H9: 1 | I9: 2 | J9: 3 | K9: 4 | L9: 5
B10: PV of FCFF | H10: =H7/(1+$C$15)^H9 -> -79974.458 | I10: =I7/(1+$C$15)^I9 -> 11725.81 | J10: =J7/(1+$C$15)^J9 -> 48833.535 | K10: =K7/(1+$C$15)^K9 -> 60622.272 | L10: =L7/(1+$C$15)^L9 -> 87296.426
B11: PV of Perpetual cashflow | L11: =L8/(1+C15)^L9 -> 954860.24
B13: Input parameters
B14: Perpetual growth | C14: 0.02
B15: WACC | C15: =IF(Overview!C28>0,Overview!C28,WACC!C20) -> 0.11325171
B18: Result
B19: Total PV of Unlevered FCF | C19: =SUM(H10:L10) -> 128503.58
B20: PV of Perpetual cashflow | C20: =L11 -> 954860.24
B21: Enterprise value | C21: =C19+C20 -> 1083363.8
B22: (+) Cash | C22: =Statement!AC108 -> 114226
B23: (-) Debt | C23: =Statement!AC109 -> 173125
B24: Equity value | C24: =C21+C22-C23 -> 1024464.8
B25: Shares outstanding | C25: =Statement!AC79 -> 10920
B26: Price per share | C26: =C24/C25 -> 93.81546

Sheet Multiples
B1: Multiples valuations
C2: History | H2: Forecast
C4: Revenues, earnings cash
B5: Revenues (thousand) | C5: =Revenue!C5 -> 2021 | D5: =Revenue!D5 -> 2022 | E5: =Revenue!E5 -> 2023 | F5: =Revenue!F5 -> 2024 | G5: =Revenue!G5 -> 2025 | H5: =Revenue!H5 -> 2026 | I5: =Revenue!I5 -> 2027 | J5: =Revenue!J5 -> 2028 | ... L5: =Revenue!L5 -> 2030
B6: Revenue | C6: =Revenue!C14 -> 469822 | D6: =Revenue!D14 -> 513983 | E6: =Revenue!E14 -> 574785 | F6: =Revenue!F14 -> 637959 | G6: =Revenue!G14 -> 716924 | H6: =Revenue!H14 -> 826554.04 | I6: =Revenue!I14 -> 951120.23 | J6: =Revenue!J14 -> 1076690 | ... L6: =Revenue!L14 -> 1327255.8
B7: EBIT | C7: ='FCF & Other'!C10 -> 24879 | D7: ='FCF & Other'!D10 -> 12248 | E7: ='FCF & Other'!E10 -> 36852 | F7: ='FCF & Other'!F10 -> 68593 | G7: ='FCF & Other'!G10 -> 79975 | H7: ='FCF & Other'!H10 -> 65251.99 | I7: ='FCF & Other'!I10 -> 173028.97 | J7: ='FCF & Other'!J10 -> 202076.8 | ... L7: ='FCF & Other'!L10 -> 289144.03
B8: FCFF | C8: ='FCF & Other'!C28 -> -25828.818 | D8: ='FCF & Other'!D28 -> -30362 | E8: ='FCF & Other'!E28 -> 14258.653 | F8: ='FCF & Other'!F28 -> 13585.836 | G8: ='FCF & Other'!G28 -> -24162.382 | H8: ='FCF & Other'!H28 -> -89031.703 | I8: ='FCF & Other'!I28 -> 14532.141 | J8: ='FCF & Other'!J28 -> 67374.922 | ... L8: ='FCF & Other'!L28 -> 149266.84
B9: PV of FCFF | H9: =DCF!H10 -> -79974.458 | I9: =DCF!I10 -> 11725.81 | J9: =DCF!J10 -> 48833.535 | K9: =DCF!K10 -> 60622.272 | L9: =DCF!L10 -> 87296.426
C11: Growth rates
B12: % Growth | C12: =C5 -> 2021 | D12: =D5 -> 2022 | E12: =E5 -> 2023 | F12: =F5 -> 2024 | G12: =G5 -> 2025 | H12: =H5 -> 2026 | I12: =I5 -> 2027 | J12: =J5 -> 2028 | ... L12: =L5 -> 2030
B13: Revenue | D13: =(D6-C6)/C6 -> 0.093995173 | E13: =(E6-D6)/D6 -> 0.11829574 | F13: =(F6-E6)/E6 -> 0.10990892 | G13: =(G6-F6)/F6 -> 0.12377755 | H13: =(H6-G6)/G6 -> 0.15291724 | I13: =(I6-H6)/H6 -> 0.15070544 | J13: =(J6-I6)/I6 -> 0.13202299 | K13: =(K6-J6)/J6 -> 0.11652018 | L13: =(L6-K6)/K6 -> 0.10407199
B14: EBIT | D14: =IF(C7=0, IF(D7=0,0,IF(D7>0,1,-1)), (D7-C7)/ABS(C7) ) -> -0.50769725 | E14: =IF(D7=0, IF(E7=0,0,IF(E7>0,1,-1)), (E7-D7)/ABS(D7) ) -> 2.0088178 | F14: =IF(E7=0, IF(F7=0,0,IF(F7>0,1,-1)), (F7-E7)/ABS(E7) ) -> 0.86131011 | G14: =IF(F7=0, IF(G7=0,0,IF(G7>0,1,-1)), (G7-F7)/ABS(F7) ) -> 0.1659353 | H14: =IF(G7=0, IF(H7=0,0,IF(H7>0,1,-1)), (H7-G7)/ABS(G7) ) -> -0.18409515 | I14: =IF(H7=0, IF(I7=0,0,IF(I7>0,1,-1)), (I7-H7)/ABS(H7) ) -> 1.6517041 | J14: =IF(I7=0, IF(J7=0,0,IF(J7>0,1,-1)), (J7-I7)/ABS(I7) ) -> 0.1678784 | K14: =IF(J7=0, IF(K7=0,0,IF(K7>0,1,-1)), (K7-J7)/ABS(J7) ) -> 0.097407345 | L14: =IF(K7=0, IF(L7=0,0,IF(L7>0,1,-1)), (L7-K7)/ABS(K7) ) -> 0.30385689
B15: FCFF | D15: =IF(C8=0, IF(D8=0,0,IF(D8>0,1,-1)), (D8-C8)/ABS(C8) ) -> -0.17550867 | E15: =IF(D8=0, IF(E8=0,0,IF(E8>0,1,-1)), (E8-D8)/ABS(D8) ) -> 1.4696217 | F15: =IF(E8=0, IF(F8=0,0,IF(F8>0,1,-1)), (F8-E8)/ABS(E8) ) -> -0.04718659 | G15: =IF(F8=0, IF(G8=0,0,IF(G8>0,1,-1)), (G8-F8)/ABS(F8) ) -> -2.778498 | H15: =IF(G8=0, IF(H8=0,0,IF(H8>0,1,-1)), (H8-G8)/ABS(G8) ) -> -2.6847238 | I15: =IF(H8=0, IF(I8=0,0,IF(I8>0,1,-1)), (I8-H8)/ABS(H8) ) -> 1.1632243 | J15: =IF(I8=0, IF(J8=0,0,IF(J8>0,1,-1)), (J8-I8)/ABS(I8) ) -> 3.6362694 | K15: =IF(J8=0, IF(K8=0,0,IF(K8>0,1,-1)), (K8-J8)/ABS(J8) ) -> 0.38199801 | L15: =IF(K8=0, IF(L8=0,0,IF(L8>0,1,-1)), (L8-K8)/ABS(K8) ) -> 0.60308898
C17: Shares
C18: =C5 -> 2021 | D18: =D5 -> 2022 | E18: =E5 -> 2023 | F18: =F5 -> 2024 | G18: =G5 -> 2025 | H18: =H5 -> 2026 | I18: =I5 -> 2027 | J18: =J5 -> 2028 | ... L18: =L5 -> 2030
B19: Avg diluted shares | C19: =Statement!M23 -> 10296 | D19: =Statement!N23 -> 10189 | E19: =Statement!O23 -> 10492 | F19: =Statement!P23 -> 10721 | G19: =Statement!Q23 -> 10827 | H19: =G19*(1+H20) -> 10935.27 | I19: =H19*(1+I20) -> 11044.623 | J19: =I19*(1+J20) -> 11044.623 | K19: =J19*(1+K20) -> 10934.176 | L19: =K19*(1+L20) -> 10715.493
B20: Dilution rate | D20: =D19/C19-1 -> -0.010392385 | E20: =E19/D19-1 -> 0.029737953 | F20: =F19/E19-1 -> 0.021826153 | G20: =G19/F19-1 -> 0.0098871374 | H20: 0.01 | I20: 0.01 | J20: 0 | K20: -0.01 | L20: -0.02
C22: Historical price
C23: =C5 -> 2021 | D23: =D5 -> 2022 | E23: =E5 -> 2023 | F23: =F5 -> 2024 | G23: =G5 -> 2025 | H23: =H5 -> 2026 | I23: =I5 -> 2027 | J23: =J5 -> 2028 | ... L23: =L5 -> 2030
B24: Price | C24: =Statement!M117 -> 166.72 | D24: =Statement!N117 -> 83.99 | E24: =Statement!O117 -> 151.94 | F24: =Statement!P117 -> 219.39 | G24: =Statement!Q117 -> 230.82
C27: Historical ratios
C28: =C5 -> 2021 | D28: =D5 -> 2022 | E28: =E5 -> 2023 | F28: =F5 -> 2024 | G28: =G5 -> 2025 | H28: =H5 -> 2026 | I28: =I5 -> 2027 | J28: =J5 -> 2028 | ... L28: =L5 -> 2030
B29: PS | C29: =C24/(C6/C19) -> 3.6536159 | D29: =D24/(D6/D19) -> 1.6649852 | E29: =E24/(E6/E19) -> 2.7734796 | F29: =F24/(F6/F19) -> 3.686883 | G29: =G24/(G6/G19) -> 3.4858481
B30: Market Cap | C30: =C24*C19 -> 1716549.1 | D30: =D24*D19 -> 855774.11 | E30: =E24*E19 -> 1594154.5 | F30: =F24*F19 -> 2352080.2 | G30: =G24*G19 -> 2499088.1
B31: Debt | C31: =Statement!M109 -> 48744 | D31: =Statement!N109 -> 67150 | E31: =Statement!O109 -> 58314 | F31: =Statement!P109 -> 52623 | G31: =Statement!Q109 -> 65648
B32: Cash | C32: =Statement!M108 -> 96049 | D32: =Statement!N108 -> 70026 | E32: =Statement!O108 -> 86780 | F32: =Statement!P108 -> 101202 | G32: =Statement!Q108 -> 123029
B33: EV | C33: =C30+C31-C32 -> 1669244.1 | D33: =D30+D31-D32 -> 852898.11 | E33: =E30+E31-E32 -> 1565688.5 | F33: =F30+F31-F32 -> 2303501.2 | G33: =G30+G31-G32 -> 2441707.1
B34: EV/EBIT | C34: =C33/C7 -> 67.094502 | D34: =D33/D7 -> 69.635705 | E34: =E33/E7 -> 42.485848 | F34: =F33/F7 -> 33.582161 | G34: =G33/G7 -> 30.53088
B35: EV/FCFF | C35: =C33/C8 -> -64.627197 | D35: =D33/D8 -> -28.090973 | E35: =E33/E8 -> 109.8062 | F35: =F33/F8 -> 169.55167 | G35: =G33/G8 -> -101.05408
B36: EV/Sales | C36: =C33/C6 -> 3.5529288 | D36: =D33/D6 -> 1.6593897 | E36: =E33/E6 -> 2.723955 | F36: =F33/F6 -> 3.6107355 | G36: =G33/G6 -> 3.4058103
B39: EV/EBIT valuation
B40: Year 5 EBIT | C40: =L7 -> 289144.03
B41: WACC | C41: =IF(Overview!C28>0,Overview!C28,WACC!C20) -> 0.11325171
B42: Applied EV/EBIT ratio | C42: 25
B43: Terminal EV | C43: =(C40*C42) -> 7228600.9
B44: PV of Terminal EV | C44: =C43/(1+C41)^5 -> 4227536.7
B45: Total EV | C45: =SUM(H9:K9)+C44 -> 4268743.8
B46: (+) Cash | C46: =Statement!AC108 -> 114226
B47: (-) Debt | C47: =Statement!AC109 -> 173125
B48: Equity value | C48: =C45+C46-C47 -> 4209844.8
B49: Shares outstanding | C49: =Statement!AC79 -> 10920
B50: PV of price per share | C50: =C48/C49 -> 385.51692
B52: PS valuation
B53: Year 5 sales | C53: =L6 -> 1327255.8
B54: Discount rate | C54: =IF(Overview!C29>0,Overview!C29,WACC!C19) -> 0.1175855
B55: Applied PS ratio | C55: 4
B56: Shares outstanding diluted | C56: =L19 -> 10715.493
B57: Price per share | C57: =(C53*C55)/C56 -> 495.45301
B58: PV of price per share | C58: =C57/(1+C54)^5 -> 284.18338
B60: EV/FCFF valuation
B61: Year 5 FCFF | C61: =L8 -> 149266.84
B62: WACC | C62: =IF(Overview!C28>0,Overview!C28,WACC!C20) -> 0.11325171
B63: Applied EV/FCFF ratio | C63: 35
B64: Terminal EV | C64: =(C61*C63) -> 5224339.2
B65: PV of Terminal EV | C65: =C64/(1+C62)^5 -> 3055374.9
B66: Total EV | C66: =SUM(H9:K9)+C65 -> 3096582.1
B67: (+) Cash | C67: =Statement!AC108 -> 114226
B68: (-) Debt | C68: =Statement!AC109 -> 173125
B69: Equity value | C69: =C66+C67-C68 -> 3037683.1
B70: Shares outstanding | C70: =Statement!AC79 -> 10920
B71: PV of price per share | C71: =C69/C70 -> 278.1761
B73: EV/Sales valuation
B74: Year 5 Sales | C74: =L6 -> 1327255.8
B75: WACC | C75: =IF(Overview!C28>0,Overview!C28,WACC!C20) -> 0.11325171
B76: Applied EV/Sales ratio | C76: 4
B77: Terminal EV | C77: =(C74*C76) -> 5309023.2
B78: PV of Terminal EV | C78: =C77/(1+C75)^5 -> 3104901
B79: Total EV | C79: =SUM(H9:K9)+C78 -> 3146108.2
B80: (+) Cash | C80: =Statement!AC108 -> 114226
B81: (-) Debt | C81: =Statement!AC109 -> 173125
B82: Equity value | C82: =C79+C80-C81 -> 3087209.2
B83: Shares outstanding | C83: =Statement!AC79 -> 10920
B84: PV of price per share | C84: =C82/C83 -> 282.71146

Sheet AVG target price
B1: AVG target price
B4: AVG target price
B5: DCF price | C5: =DCF!C26 -> 93.81546
B6: EV/EBIT price | C6: =Multiples!C50 -> 385.51692
B7: PS price | C7: =Multiples!C58 -> 284.18338
B8: EV/FCFF price | C8: =Multiples!C71 -> 278.1761
B9: EV/Sales price | C9: =Multiples!C84 -> 282.71146
B10: AVG price | C10: =AVERAGE(C5:C9) -> 264.88067
B11: Current price | C11: =Overview!C5 -> 243.79
B12: Upside/Downside | C12: =(C10-C11)/C11 -> 0.086511614

Sheet DDM
B1: Dividend discount model
C2: History | H2: Forecast
C4: Revenues, earnings cash
B5: Revenues (thousand) | C5: =[2]Revenue!C5 -> 2021 | D5: =[2]Revenue!D5 -> 2022 | E5: =[2]Revenue!E5 -> 2023 | F5: =[2]Revenue!F5 -> 2024 | G5: =[2]Revenue!G5 -> 2025 | H5: =[2]Revenue!H5 -> 2026 | I5: =[2]Revenue!I5 -> 2027 | J5: =[2]Revenue!J5 -> 2028 | ... L5: =[2]Revenue!L5 -> 2030
B6: EPS | C6: =Statement!M27 -> 2.1210179 | D6: =Statement!N27 -> 1.0941211 | E6: =Statement!O27 -> 2.9 | F6: =Statement!P27 -> 5.53 | G6: =Statement!Q27 -> 5.9730304
B7: Dividend per share | C7: =Statement!M83 -> 0 | D7: =Statement!N83 -> 0 | E7: =Statement!O83 -> 0 | F7: =Statement!P83 -> 0 | G7: =Statement!Q83 -> 0
C9: Growth rates
B10: % Growth | C10: =C5 -> 2021 | D10: =D5 -> 2022 | E10: =E5 -> 2023 | F10: =F5 -> 2024 | G10: =G5 -> 2025 | H10: =H5 -> 2026 | I10: =I5 -> 2027 | J10: =J5 -> 2028 | ... L10: =L5 -> 2030
B11: EPS | D11: =(D6-C6)/C6 -> -0.48415281 | E11: =(E6-D6)/D6 -> 1.6505292 | F11: =(F6-E6)/E6 -> 0.90689655 | G11: =(G6-F6)/F6 -> 0.080113994
B12: Dividend | D12: =IF(C7=0, IF(D7=0,0,IF(D7>0,1,-1)), (D7-C7)/ABS(C7) ) -> 0 | E12: =IF(D7=0, IF(E7=0,0,IF(E7>0,1,-1)), (E7-D7)/ABS(D7) ) -> 0 | F12: =IF(E7=0, IF(F7=0,0,IF(F7>0,1,-1)), (F7-E7)/ABS(E7) ) -> 0 | G12: =IF(F7=0, IF(G7=0,0,IF(G7>0,1,-1)), (G7-F7)/ABS(F7) ) -> 0
C14: Ratios
B15: % | C15: =C5 -> 2021 | D15: =D5 -> 2022 | E15: =E5 -> 2023 | F15: =F5 -> 2024 | G15: =G5 -> 2025 | H15: =H5 -> 2026 | I15: =I5 -> 2027 | J15: =J5 -> 2028 | ... L15: =L5 -> 2030
B16: Payout | C16: =C7/C6 -> 0 | D16: =D7/D6 -> 0 | E16: =E7/E6 -> 0 | F16: =F7/F6 -> 0 | G16: =G7/G6 -> 0
B20: DDM valuation
B21: Latest dividend | C21: =G7 -> 0
B22: Year 1 growth rate | C22: 0
B23: Year 1 dividend | C23: =C21*(1+C22) -> 0
B24: Discount rate | C24: =IF(Overview!C29>0,Overview!C29,WACC!C19) -> 0.1175855
B25: Perpetual dividend growth | C25: 0
B26: PV of price per share | C26: =C23/(C24-C25) -> 0

Sheet Reverse DCF
B1: Reverse DCF
C3: History | H3: Forecast
C5: PV of FCF
B6: $ (thousand) | C6: =Revenue!C5 -> 2021 | D6: =Revenue!D5 -> 2022 | E6: =Revenue!E5 -> 2023 | F6: =Revenue!F5 -> 2024 | G6: =Revenue!G5 -> 2025 | H6: =Revenue!H5 -> 2026 | I6: =Revenue!I5 -> 2027 | J6: =Revenue!J5 -> 2028 | ... L6: =Revenue!L5 -> 2030
B7: FCFF | C7: ='FCF & Other'!C28 -> -25828.818 | D7: ='FCF & Other'!D28 -> -30362 | E7: ='FCF & Other'!E28 -> 14258.653 | F7: ='FCF & Other'!F28 -> 13585.836 | G7: ='FCF & Other'!G28 -> -24162.382 | H7: =G7*(1+$C$17) -> -24887.253 | I7: =H7*(1+$C$17) -> -25633.871 | J7: =I7*(1+$C$17) -> -26402.887 | K7: =J7*(1+$C$17) -> -27194.973 | L7: =K7*(1+$C$17) -> -28010.823
B8: Perpetual cashflow | L8: =L7*(1+C20)/(C21-C20) -> -306386.21
B9: Period | H9: 1 | I9: 2 | J9: 3 | K9: 4 | L9: 5
B10: PV of FCFF | H10: =H7/(1+$C$21)^H9 -> -22355.459 | I10: =I7/(1+$C$21)^I9 -> -20683.662 | J10: =J7/(1+$C$21)^J9 -> -19136.887 | K10: =K7/(1+$C$21)^K9 -> -17705.783 | L10: =L7/(1+$C$21)^L9 -> -16381.701
B11: PV of Perpetual cashflow | L11: =L8/(1+C21)^L9 -> -179185.29
B14: Growth adjustment
B15: Current Price | C15: =Overview!C5 -> 243.79
B16: Calculated Price | C16: =C36 -> -30.998311
B17: FCFF Growth | C17: 0.03 | E17: Modify until Calculated Price is very close to Current Price
B19: Input parameters
B20: Perpetual growth | C20: 0.02
B21: WACC | C21: =IF(Overview!C28>0,Overview!C28,WACC!C20) -> 0.11325171
B22: Shares outstanding | C22: =Statement!AC76 -> 10786
B23: Market cap | C23: =C15*C22 -> 2629518.9
B24: Cash | C24: =Statement!AC108 -> 114226
B25: Debt | C25: =Statement!AC109 -> 173125
B26: Enterprise Value | C26: =C23+C25-C24 -> 2688417.9
B28: Result
B29: Total PV of Unlevered FCF | C29: =SUM(H10:L10) -> -96263.493
B30: PV of Perpetual cashflow | C30: =L11 -> -179185.29
B31: Enterprise value | C31: =C29+C30 -> -275448.78
B32: (+) Cash | C32: =C24 -> 114226
B33: (-) Debt | C33: =C25 -> 173125
B34: Equity value | C34: =C31+C32-C33 -> -334347.78
B35: Shares outstanding | C35: =C22 -> 10786
B36: Price per share | C36: =C34/C35 -> -30.998311
