Workbook

Sheet Overview
B2: Ticker | C2: PHR
B3: Price | C3: =[1]Sheet1!$C$7 -> 9.05
B4: Cost of operating lease debt | C4: 0.075
B5: Cost of financial lease debt | C5: 0.078
B8: Units | C8: K
B10: Market cap | C10: =C3*'Statement Q'!J147 -> 549905.15
B11: Net debt | C11: =(Statements!S48+Statements!S49+Statements!S56+Statements!S57)-Statements!S26 -> 28619
B12: EV | C12: =C10+C11 -> 578524.15
B14: PE | C14: =C3/'Statement Q'!N25 -> 239.06756
B15: PS | C15: =$C$3/('Statement Q'!$N$5/'Statement Q'!$N$23) -> 1.147108
B19: Shares held by insiders | C19: 3302
B20: Total shares | C20: ='Statement Q'!J147 -> 60763
B21: Insider % | C21: =C19/C20 -> 0.054342281
B23: ROIC = NOPAT/Invested capital
B24: NOPAT = EBIT * (1-tax rate)
B25: Invested capital = (Total assets - Cash and equivalents) -non-interest bearing current liabilities
B26: NIBCL usually are accounts payable and accrued expenses and other operating items that do not have interest attached
B27: NIBCL does not include any sort of debt
B29: NOPAT | C29: =Statements!S14*(1-'Statement Y'!G151) -> -6290.232
B30: Assets les cash | C30: =Statements!S46-Statements!S26-Statements!S27 -> 556961
B31: NIBCL | C31: =SUM(Statements!S50:S54)+Statements!S47 -> 174016
B32: Invested capital | C32: =C30-C31 -> 382945
B33: ROIC | C33: =C29/C32 -> -0.016425941
A37: Info
A39: Mission: | B39: Address 3 challenges in healthcare: access to care, affordability of care, health patient outcomes
A40: Auditor: | B40: KPMG
A44: Notes
A46: Date: | B46: 30.03.2026 | C46: Q4 2026
B47: Revenue outlook for FY 2027 will be in the range 510-520 million
B48: Network solution clients commiting lower spend levels for second half of fiscal 2027
B49: AccessOne will contribute about 37 million to the total revenue range
B50: Adjusted EBITDA in the range 125 to 135 million
B51: AHSC growth in the mid single digit percentage range
B52: Total revenue per AHSC in low single digit percentage range
B53: TAM of 24B
B54: It is expected that subscription growth will be slower than the other 2 revenue streams
B55: Got a $250k revolving credit maturing on 13.03.2031

Sheet Financials ->
B13: Financials ->

Sheet Statement Y
B2: Date | C2: 31.01.2021 | D2: 31.01.2022 | E2: 31.01.2023 | F2: 31.01.2024 | G2: 31.01.2025 | H2: 31.01.2026
B3: FY | C3: =2021 -> 2021 | D3: =C3+1 -> 2022 | E3: =D3+1 -> 2023 | F3: =E3+1 -> 2024 | G3: =F3+1 -> 2025 | H3: =G3+1 -> 2026 | I3: =H3+1 -> 2027 | J3: =I3+1 -> 2028 | K3: =J3+1 -> 2029
B4: Income statement
B5: Revenue | C5: 148677 | D5: 213233 | E5: 280910 | F5: 356299 | G5: 419813 | H5: 480591
B6: COGS | C6: 52386 | D6: 81388 | E6: 109267 | F6: 124011 | G6: 134934 | H6: 154123
B7: Gross Profit | C7: =C5-C6 -> 96291 | D7: =D5-D6 -> 131845 | E7: =E5-E6 -> 171643 | F7: =F5-F6 -> 232288 | G7: =G5-G6 -> 284879 | H7: =H5-H6 -> 326468 | I7: =I5-I6 -> 0 | J7: =J5-J6 -> 0 | K7: =K5-K6 -> 0
B8: Sales and marketing | C8: 42972 | D8: 106421 | E8: 151263 | F8: 147008 | G8: 121129 | H8: 100243
B9: R&D | C9: 22622 | D9: 52265 | E9: 91244 | F9: 112346 | G9: 117364 | H9: 121481
B10: General and administrative | C10: 40460 | D10: 68674 | E10: 80384 | F10: 79926 | G10: 76597 | H10: 79903
B11: Depreciation | C11: 9770 | D11: 14985 | E11: 17988 | F11: 17584 | G11: 14183 | H11: 12972
B12: Amortization | C12: 6138 | D12: 6317 | E12: 7316 | F12: 11903 | G12: 13703 | H12: 18481
B13: OpEx | C13: =SUM(C8:C12) -> 121962 | D13: =SUM(D8:D12) -> 248662 | E13: =SUM(E8:E12) -> 348195 | F13: =SUM(F8:F12) -> 368767 | G13: =SUM(G8:G12) -> 342976 | H13: =SUM(H8:H12) -> 333080 | I13: =SUM(I8:I12) -> 0 | J13: =SUM(J8:J12) -> 0 | K13: =SUM(K8:K12) -> 0
B14: Operating income | C14: -25671 | D14: -116817 | E14: -176552 | F14: -136479 | G14: -58097 | H14: -6612
B15: Other income/expense | C15: 1 | D15: -78 | E15: -175 | F15: 44 | G15: 1956 | H15: 2953
B16: Extinguishment of debt | C16: 0 | D16: 0 | E16: 0 | F16: -1118 | G16: 0 | H16: -501
B17: Interest expense | C17: 0 | D17: 0 | E17: 0 | F17: 0 | G17: 0 | H17: -6953
B18: Interest income | C18: -1573 | D18: -1084 | E18: 1064 | F18: 2211 | G18: 330 | H18: 2173
B19: Income before taxes | C19: -27243 | D19: -117979 | E19: -175663 | F19: -135342 | G19: -55811 | H19: -8940
B20: Income tax expense/benefit | C20: -49 | D20: -182 | E20: -483 | F20: -1543 | G20: -2716 | H20: 11246
B21: Net income | C21: -27292 | D21: -118161 | E21: -176146 | F21: -136885 | G21: -58527 | H21: 2306
B22: Basic Shares outstanding avg | C22: 39520 | D22: 49888 | E22: 52440 | F22: 54561 | G22: 57590 | H22: 59738
B23: Diluted Shares outstanding avg | C23: 39520 | D23: 49888 | E23: 52440 | F23: 54561 | G23: 57590 | H23: 61495
B24: Basic EPS | C24: -0.69 | D24: -2.37 | E24: -3.36 | F24: -2.51 | G24: -1.02 | H24: 0.04
B25: Diluted EPS | C25: -0.69 | D25: -2.37 | E25: -3.36 | F25: -2.51 | G25: -1.02 | H25: 0.04
B27: Balance sheet
B28: Cash and cash equivalents | C28: 218781 | D28: 313812 | E28: 176683 | F28: 87520 | G28: 84220 | H28: 73830
B29: Settlement assets | C29: 15488 | D29: 19590 | E29: 22599 | F29: 28072 | G29: 29176 | H29: 32999
B30: Acc receivable | C30: 29052 | D30: 40262 | E30: 51394 | F30: 64863 | G30: 73617 | H30: 97453
B31: Cardholder receivables | C31: 0 | D31: 0 | E31: 0 | F31: 0 | G31: 0 | H31: 38330
B32: Deferred purchase receivables | C32: 0 | D32: 0 | E32: 0 | F32: 0 | G32: 0 | H32: 18003
B33: Accrued interest receivables | C33: 0 | D33: 0 | E33: 0 | F33: 0 | G33: 0 | H33: 840
B34: Deferred contract acquisition costs | C34: 1693 | D34: 1642 | E34: 1056 | F34: 768 | G34: 401 | H34: 410
B35: Prepaid expenses & Other current | C35: 7254 | D35: 11043 | E35: 10709 | F35: 14461 | G35: 15871 | H35: 17978
B36: Current assets | C36: 272268 | D36: 386349 | E36: 262441 | F36: 195684 | G36: 203285 | H36: 279843
B37: PP&E | C37: 26660 | D37: 34645 | E37: 21670 | F37: 16902 | G37: 23651 | H37: 20332
B38: Capitalized internal use software | C38: 10476 | D38: 17643 | E38: 35150 | F38: 46139 | G38: 52763 | H38: 54270
B39: Operating lease right of use | C39: 2654 | D39: 2337 | E39: 569 | F39: 266 | G39: 1477 | H39: 2002
... B46: Deferred purchase receivables | C46: 0 | D46: 0 | E46: 0 | F46: 0 | G46: 0 | H46: 5422
B47: Long term assets | C47: =SUM(C37:C44) -> 54398 | D47: =SUM(D37:D44) -> 108127 | E47: =SUM(E37:E44) -> 107616 | F47: =SUM(F37:F44) -> 174642 | G47: =SUM(G37:G44) -> 185130 | H47: =SUM(H37:H44) -> 330802 | I47: =SUM(I37:I44) -> 0 | J47: =SUM(J37:J44) -> 0 | K47: =SUM(K37:K44) -> 0
B48: Total assets | C48: 326666 | D48: 494476 | E48: 370057 | F48: 370326 | G48: 388415 | H48: 663790
B49: Settlement obligations | C49: 15488 | D49: 19590 | E49: 22599 | F49: 28072 | G49: 29176 | H49: 32999
B50: Current portion of finance lease | C50: 4864 | D50: 5821 | E50: 5172 | F50: 6056 | G50: 8043 | H50: 7971
B51: Current portion of operating lease | C51: 1087 | D51: 1281 | E51: 934 | F51: 393 | G51: 964 | H51: 1254
B52: Acc payable | C52: 4389 | D52: 5119 | E52: 10836 | F52: 8480 | G52: 5622 | H52: 11477
B53: Accrued expenses | C53: 18324 | D53: 20128 | E53: 21810 | F53: 37130 | G53: 37460 | H53: 41257
B54: Dues to healthcare providers | C54: 0 | D54: 0 | E54: 0 | F54: 0 | G54: 0 | H54: 38056
B55: Deferred revenue | C55: 10838 | D55: 16493 | E55: 17688 | F55: 24113 | G55: 32758 | H55: 49522
B56: Other current liabilities | C56: 0 | D56: 0 | E56: 0 | F56: 5875 | G56: 0 | H56: 705
B57: Current liabilities | C57: 54990 | D57: 68432 | E57: 79039 | F57: 110119 | G57: 114023 | H57: 183241
B58: Long term finance lease | C58: 6471 | D58: 7423 | E58: 2725 | F58: 5400 | G58: 8150 | H58: 92117
B59: Operating lease | C59: 1899 | D59: 1276 | E59: 349 | F59: 134 | G59: 646 | H59: 1107
... B63: Other liabilities | C63: 0 | D63: 0 | E63: 0 | F63: 2857 | G63: 185 | H63: 47
B64: Long term liabilities | C64: =SUM(C58:C63) -> 8370 | D64: =SUM(D58:D63) -> 8764 | E64: =SUM(E58:E63) -> 3199 | F64: =SUM(F58:F63) -> 8758 | G64: =SUM(G58:G63) -> 9584 | H64: =SUM(H58:H58) -> 92117 | I64: =SUM(I58:I58) -> 0 | J64: =SUM(J58:J58) -> 0 | K64: =SUM(K58:K58) -> 0
B65: Total liabilities | C65: 63360 | D65: 77196 | E65: 82238 | F65: 118877 | G65: 123607 | H65: 326583
B66: Preferred stock par value | C66: 0 | D66: 0 | E66: 0 | F66: 0 | G66: 0 | H66: 0
B67: Common stock par value | C67: 449 | D67: 521 | E67: 542 | F67: 577 | G67: 601 | H67: 620
B68: Additional paid-in capital | C68: 579599 | D68: 860657 | E68: 926957 | F68: 1039361 | G68: 1111274 | H68: 1181679
B69: Retained earnings | C69: -311777 | D69: -429938 | E69: -606084 | F69: -742969 | G69: -801496 | H69: -799190
B70: Other comprehensive loss | C70: 0 | D70: 0 | E70: 0 | F70: 0 | G70: -51 | H70: -382
B71: Treasury stock par value | C71: -4965 | D71: -13960 | E71: -33596 | F71: -45520 | G71: -45520 | H71: -45520
B72: Stockholder equity | C72: 263306 | D72: 417280 | E72: 287819 | F72: 251449 | G72: 264808 | H72: 337207
B73: Total liabilities and equity | C73: 326666 | D73: 494476 | E73: 370057 | F73: 370326 | G73: 388415 | H73: 663790
B75: Cashflow statement
B76: Net income | C76: =C21 -> -27292 | D76: =D21 -> -118161 | E76: =E21 -> -176146 | F76: =F21 -> -136885 | G76: =G21 -> -58527 | H76: =H21 -> 2306 | I76: =I21 -> 0 | J76: =J21 -> 0 | K76: =K21 -> 0
B77: D&A | C77: 15908 | D77: 21302 | E77: 25304 | F77: 29487 | G77: 27886 | H77: 31453
B78: Stock-based compensation | C78: 13489 | D78: 36144 | E78: 58775 | F78: 71613 | G78: 66975 | H78: 67452
B79: Amortization of deferred financing | C79: 389 | D79: 288 | E79: 310 | F79: 321 | G79: 236 | H79: 2977
B80: Loss exstinguishment of debt | C80: 0 | D80: 0 | E80: 0 | F80: 1118 | G80: 0 | H80: 501
B81: Non-cash gain on settlement | C81: 0 | D81: 0 | E81: 0 | F81: 0 | G81: -2345 | H81: 0
B82: Cost of Phreesia HW purchased | C82: 762 | D82: 672 | E82: 1598 | F82: 1619 | G82: 1873 | H82: 1022
B83: Deferred contract acquisition | C83: 2025 | D83: 2211 | E83: 1696 | F83: 1056 | G83: 1815 | H83: 570
B84: Non-cash operating lease | C84: 1766 | D84: 1004 | E84: 1768 | F84: 702 | G84: 747 | H84: 914
B85: Change fair value contingent liabilities | C85: 0 | D85: 258 | E85: 0 | F85: 0 | G85: 0 | H85: 0
B86: Deferred taxes | C86: -65 | D86: 143 | E86: 434 | F86: 228 | G86: 214 | H86: -13271
B87: Unrialized gains/losses fair value option | C87: 0 | D87: 0 | E87: 0 | F87: 0 | G87: 0 | H87: -1020
B88: Change acc receivable | C88: -6619 | D88: -10216 | E88: -11132 | F88: -11205 | G88: -8812 | H88: -23397
... B125: End cash | C125: 218781 | D125: 313812 | E125: 176683 | F125: 87520 | G125: 84220 | H125: 73830
B127: Sanity checks
B128: Calculated Net Income | C128: =C5-C6-C13+C15+C16+C17+C18+C20 -> -27292 | D128: =D5-D6-D13+D15+D16+D17+D18+D20 -> -118161 | E128: =E5-E6-E13+E15+E16+E17+E18+E20 -> -176146 | F128: =F5-F6-F13+F15+F16+F17+F18+F20 -> -136885 | G128: =G5-G6-G13+G15+G16+G17+G18+G20 -> -58527 | H128: =H5-H6-H13+H15+H16+H17+H18+H20 -> 2306 | I128: =I5-I6-I13+I15+I16+I17+I18+I20 -> 0 | J128: =J5-J6-J13+J15+J16+J17+J18+J20 -> 0 | K128: =K5-K6-K13+K15+K16+K17+K18+K20 -> 0
B129: Check Net Income | C129: =C21-C128 -> 0 | D129: =D21-D128 -> 0 | E129: =E21-E128 -> 0 | F129: =F21-F128 -> 0 | G129: =G21-G128 -> 0 | H129: =H21-H128 -> 0 | I129: =I21-I128 -> 0 | J129: =J21-J128 -> 0 | K129: =K21-K128 -> 0
B130: Calculated Assets | C130: =SUM(C28:C35)+SUM(C37:C46) -> 326666 | D130: =SUM(D28:D35)+SUM(D37:D46) -> 494476 | E130: =SUM(E28:E35)+SUM(E37:E46) -> 370057 | F130: =SUM(F28:F35)+SUM(F37:F46) -> 370326 | G130: =SUM(G28:G35)+SUM(G37:G46) -> 388415 | H130: =SUM(H28:H35)+SUM(H37:H46) -> 663790 | I130: =SUM(I28:I35)+SUM(I37:I46) -> 0 | J130: =SUM(J28:J35)+SUM(J37:J46) -> 0 | K130: =SUM(K28:K35)+SUM(K37:K46) -> 0
B131: Check Assets | C131: =C48-C130 -> 0 | D131: =D48-D130 -> 0 | E131: =E48-E130 -> 0 | F131: =F48-F130 -> 0 | G131: =G48-G130 -> 0 | H131: =H48-H130 -> 0 | I131: =I48-I130 -> 0 | J131: =J48-J130 -> 0 | K131: =K48-K130 -> 0
B132: Calculated Liabilities | C132: =SUM(C49:C56)+SUM(C58:C63) -> 63360 | D132: =SUM(D49:D56)+SUM(D58:D63) -> 77196 | E132: =SUM(E49:E56)+SUM(E58:E63) -> 82238 | F132: =SUM(F49:F56)+SUM(F58:F63) -> 118877 | G132: =SUM(G49:G56)+SUM(G58:G63) -> 123607 | H132: =SUM(H49:H56)+SUM(H58:H63) -> 326583 | I132: =SUM(I49:I56)+SUM(I58:I63) -> 0 | J132: =SUM(J49:J56)+SUM(J58:J63) -> 0 | K132: =SUM(K49:K56)+SUM(K58:K63) -> 0
B133: Check Liabilities | C133: =C65-C132 -> 0 | D133: =D65-D132 -> 0 | E133: =E65-E132 -> 0 | F133: =F65-F132 -> 0 | G133: =G65-G132 -> 0 | H133: =H65-H132 -> 0 | I133: =I65-I132 -> 0 | J133: =J65-J132 -> 0 | K133: =K65-K132 -> 0
B134: Calculated Stockholder Equity | C134: =SUM(C66:C71) -> 263306 | D134: =SUM(D66:D71) -> 417280 | E134: =SUM(E66:E71) -> 287819 | F134: =SUM(F66:F71) -> 251449 | G134: =SUM(G66:G71) -> 264808 | H134: =SUM(H66:H71) -> 337207 | I134: =SUM(I66:I71) -> 0 | J134: =SUM(J66:J71) -> 0 | K134: =SUM(K66:K71) -> 0
B135: Check Stockholder Equity | C135: =C72-C134 -> 0 | D135: =D72-D134 -> 0 | E135: =E72-E134 -> 0 | F135: =F72-F134 -> 0 | G135: =G72-G134 -> 0 | H135: =H72-H134 -> 0 | I135: =I72-I134 -> 0 | J135: =J72-J134 -> 0 | K135: =K72-K134 -> 0
B136: Check balance | C136: =C48-(C65+C72) -> 0 | D136: =D48-(D65+D72) -> 0 | E136: =E48-(E65+E72) -> 0 | F136: =F48-(F65+F72) -> 0 | G136: =G48-(G65+G72) -> 0 | H136: =H48-(H65+H72) -> 0 | I136: =I48-(I65+I72) -> 0 | J136: =J48-(J65+J72) -> 0 | K136: =K48-(K65+K72) -> 0
B137: Calculated Operating Cashflow | C137: =SUM(C76:C97) -> 2890 | D137: =SUM(D76:D97) -> -74710 | E137: =SUM(E76:E97) -> -90123 | F137: =SUM(F76:F97) -> -32378 | G137: =SUM(G76:G97) -> 32381 | H137: =SUM(H76:H97) -> 78814 | I137: =SUM(I76:I97) -> 0 | J137: =SUM(J76:J97) -> 0 | K137: =SUM(K76:K97) -> 0
B138: Check Operating Cashflow | C138: =C98-C137 -> 0 | D138: =D98-D137 -> 0 | E138: =E98-E137 -> 0 | F138: =F98-F137 -> 0 | G138: =G98-G137 -> 0 | H138: =H98-H137 -> 0 | I138: =I98-I137 -> 0 | J138: =J98-J137 -> 0 | K138: =K98-K137 -> 0
B139: Calculated Investing Cashflow | C139: =SUM(C99:C101) -> -25085 | D139: =SUM(D99:D101) -> -65228 | E139: =SUM(E99:E101) -> -26203 | F139: =SUM(F99:F101) -> -39670 | G139: =SUM(G99:G101) -> -24089 | H139: =SUM(H99:H102) -> -161879 | I139: =SUM(I99:I101) -> 0 | J139: =SUM(J99:J101) -> 0 | K139: =SUM(K99:K101) -> 0
B140: Check Investing Cashflow | C140: =C103-C139 -> 0 | D140: =D103-D139 -> 0 | E140: =E103-E139 -> 0 | F140: =F103-F139 -> 0 | G140: =G103-G139 -> 0 | H140: =H103-H139 -> 0 | I140: =I103-I139 -> 0 | J140: =J103-J139 -> 0 | K140: =K103-K139 -> 0
B141: Calculated Financing Cashflow | C141: =SUM(C104:C120) -> 150661 | D141: =SUM(D104:D120) -> 234969 | E141: =SUM(E104:E120) -> -20803 | F141: =SUM(F104:F120) -> -17115 | G141: =SUM(G104:G120) -> -11486 | H141: =SUM(H104:H120) -> 72851 | I141: =SUM(I104:I120) -> 0 | J141: =SUM(J104:J120) -> 0 | K141: =SUM(K104:K120) -> 0
B142: Check Financing Cashflow | C142: =C121-C141 -> 0 | D142: =D121-D141 -> 0 | E142: =E121-E141 -> 0 | F142: =F121-F141 -> 0 | G142: =G121-G141 -> 0 | H142: =H121-H141 -> 0 | I142: =I121-I141 -> 0 | J142: =J121-J141 -> 0 | K142: =K121-K141 -> 0
B143: Calculated End Cash | C143: =C98+C103+C121+C124+C122 -> 218781 | D143: =D98+D103+D121+D124+D122 -> 313812 | E143: =E98+E103+E121+E124+E122 -> 176683 | F143: =F98+F103+F121+F124+F122 -> 87520 | G143: =G98+G103+G121+G124+G122 -> 84220 | H143: =H98+H103+H121+H124+H122 -> 73830 | I143: =I98+I103+I121+I124+I122 -> 0 | J143: =J98+J103+J121+J124+J122 -> 0 | K143: =K98+K103+K121+K124+K122 -> 0
B144: Check End Cash | C144: =C125-C143 -> 0 | D144: =D125-D143 -> 0 | E144: =E125-E143 -> 0 | F144: =F125-F143 -> 0 | G144: =G125-G143 -> 0 | H144: =H125-H143 -> 0 | I144: =I125-I143 -> 0 | J144: =J125-J143 -> 0 | K144: =K125-K143 -> 0
B146: Other data
B147: Shares outstanding | C147: 44900 | D147: 51946 | E147: 53355 | F147: 56387 | G147: 58772 | H147: 60763
B148: Dividends per share | C148: 0 | D148: 0 | E148: 0 | F148: 0 | G148: 0 | H148: 0
B149: Depreciation | C149: =C11 -> 9770 | D149: =D11 -> 14985 | E149: =E11 -> 17988 | F149: =F11 -> 17584 | G149: =G11 -> 14183 | H149: =H11 -> 12972
B150: Amortization | C150: =C12 -> 6138 | D150: =D12 -> 6317 | E150: =E12 -> 7316 | F150: =F12 -> 11903 | G150: =G12 -> 13703 | H150: =H12 -> 18481
...

Sheet Statement Q
B2: Date | C2: 30.04.2024 | D2: 31.07.2024 | E2: 31.10.2024 | F2: 31.01.2025 | G2: 30.04.2025 | H2: 31.07.2025 | I2: 31.10.2025 | J2: 31.01.2026
B3: Q | C3: Q1 2025 | D3: Q2 2025 | E3: Q3 2025 | F3: Q4 2025 | G3: Q1 2026 | H3: Q2 2026 | I3: Q3 2026 | J3: Q4 2026 | P3: =I3 -> Q3 2026 | Q3: =J3 -> Q4 2026 | R3: Growth Rate
B4: Income statement | N4: TTM | P4: Quarter compare
B5: Revenue | C5: 101217 | D5: 102115 | E5: 106800 | F5: 109681 | G5: 115936 | H5: 117255 | I5: 120333 | J5: 127067 | N5: =SUM(G5:J5) -> 480591 | P5: =I5 -> 120333 | Q5: =J5 -> 127067 | R5: =IF(P5=0, IF(Q5=0,0,IF(Q5>0,1,-1)), (Q5-P5)/ABS(P5) ) -> 0.055961374
B6: COGS | C6: 34020 | D6: 32811 | E6: 34537 | F6: 33566 | G6: 38065 | H6: 37641 | I6: 38027 | J6: 40390 | N6: =SUM(G6:J6) -> 154123 | P6: =I6 -> 38027 | Q6: =J6 -> 40390 | R6: =IF(P6=0, IF(Q6=0,0,IF(Q6>0,1,-1)), (Q6-P6)/ABS(P6) ) -> 0.062140058
B7: Gross Profit | C7: =C5-C6 -> 67197 | D7: =D5-D6 -> 69304 | E7: =E5-E6 -> 72263 | F7: =F5-F6 -> 76115 | G7: =G5-G6 -> 77871 | H7: =H5-H6 -> 79614 | I7: =I5-I6 -> 82306 | J7: =J5-J6 -> 86677 | N7: =SUM(G7:J7) -> 326468 | P7: =I7 -> 82306 | Q7: =J7 -> 86677 | R7: =IF(P7=0, IF(Q7=0,0,IF(Q7>0,1,-1)), (Q7-P7)/ABS(P7) ) -> 0.053106699
B8: Sales and marketing | C8: 32011 | D8: 30184 | E8: 30071 | F8: 28863 | G8: 26043 | H8: 25396 | I8: 24148 | J8: 24656 | N8: =SUM(G8:J8) -> 100243 | P8: =I8 -> 24148 | Q8: =J8 -> 24656 | R8: =IF(P8=0, IF(Q8=0,0,IF(Q8>0,1,-1)), (Q8-P8)/ABS(P8) ) -> 0.021036939
B9: R&D | C9: 28881 | D9: 29542 | E9: 29315 | F9: 29626 | G9: 31829 | H9: 29274 | I9: 29453 | J9: 30925 | N9: =SUM(G9:J9) -> 121481 | P9: =I9 -> 29453 | Q9: =J9 -> 30925 | R9: =IF(P9=0, IF(Q9=0,0,IF(Q9>0,1,-1)), (Q9-P9)/ABS(P9) ) -> 0.049977931
B10: General and administrative | C10: 19052 | D10: 19497 | E10: 19633 | F10: 18415 | G10: 16408 | H10: 19042 | I10: 17488 | J10: 26965 | N10: =SUM(G10:J10) -> 79903 | P10: =I10 -> 17488 | Q10: =J10 -> 26965 | R10: =IF(P10=0, IF(Q10=0,0,IF(Q10>0,1,-1)), (Q10-P10)/ABS(P10) ) -> 0.54191446
B11: Depreciation | C11: 3524 | D11: 3921 | E11: 3566 | F11: 3172 | G11: 2986 | H11: 3279 | I11: 3199 | J11: 3508 | N11: =SUM(G11:J11) -> 12972 | P11: =I11 -> 3199 | Q11: =J11 -> 3508 | R11: =IF(P11=0, IF(Q11=0,0,IF(Q11>0,1,-1)), (Q11-P11)/ABS(P11) ) -> 0.096592685
B12: Amortization | C12: 3149 | D12: 3382 | E12: 3521 | F12: 3651 | G12: 3892 | H12: 4130 | I12: 4279 | J12: 6180 | N12: =SUM(G12:J12) -> 18481 | P12: =I12 -> 4279 | Q12: =J12 -> 6180 | R12: =IF(P12=0, IF(Q12=0,0,IF(Q12>0,1,-1)), (Q12-P12)/ABS(P12) ) -> 0.44426268
B13: OpEx | C13: =SUM(C8:C12) -> 86617 | D13: =SUM(D8:D12) -> 86526 | E13: =SUM(E8:E12) -> 86106 | F13: =SUM(F8:F12) -> 83727 | G13: =SUM(G8:G12) -> 81158 | H13: =SUM(H8:H12) -> 81121 | I13: =SUM(I8:I12) -> 78567 | J13: =SUM(J8:J12) -> 92234 | N13: =SUM(G13:J13) -> 333080 | P13: =I13 -> 78567 | Q13: =J13 -> 92234 | R13: =IF(P13=0, IF(Q13=0,0,IF(Q13>0,1,-1)), (Q13-P13)/ABS(P13) ) -> 0.17395344
B14: Operating income | C14: -19420 | D14: -17222 | E14: -13843 | F14: -7612 | G14: -3287 | H14: -1507 | I14: 3739 | J14: -5557 | N14: =SUM(G14:J14) -> -6612 | P14: =I14 -> 3739 | Q14: =J14 -> -5557 | R14: =IF(P14=0, IF(Q14=0,0,IF(Q14>0,1,-1)), (Q14-P14)/ABS(P14) ) -> -2.4862263
B15: Other income/expense | C15: -31 | D15: -86 | E15: -144 | F15: 2217 | G15: 338 | H15: 336 | I15: 1006 | J15: 1273 | N15: =SUM(G15:J15) -> 2953 | P15: =I15 -> 1006 | Q15: =J15 -> 1273 | R15: =IF(P15=0, IF(Q15=0,0,IF(Q15>0,1,-1)), (Q15-P15)/ABS(P15) ) -> 0.26540755
B16: Extinguishment of debt | C16: 0 | D16: 0 | E16: 0 | F16: 0 | G16: 0 | H16: 0 | I16: 0 | J16: -501 | N16: =SUM(G16:J16) -> -501 | P16: =I16 -> 0 | Q16: =J16 -> -501 | R16: =IF(P16=0, IF(Q16=0,0,IF(Q16>0,1,-1)), (Q16-P16)/ABS(P16) ) -> -1
B17: Interest expense | C17: 0 | D17: 0 | E17: 0 | F17: 0 | G17: 0 | H17: 0 | I17: 0 | J17: -5807 | N17: =SUM(G17:J17) -> -5807 | P17: =I17 -> 0 | Q17: =J17 -> -5807 | R17: =IF(P17=0, IF(Q17=0,0,IF(Q17>0,1,-1)), (Q17-P17)/ABS(P17) ) -> -1
B18: Interest income | C18: 239 | D18: 46 | E18: 26 | F18: 19 | G18: -230 | H18: 608 | I18: 380 | J18: 269 | N18: =SUM(G18:J18) -> 1027 | P18: =I18 -> 380 | Q18: =J18 -> 269 | R18: =IF(P18=0, IF(Q18=0,0,IF(Q18>0,1,-1)), (Q18-P18)/ABS(P18) ) -> -0.29210526
B19: Income before taxes | C19: -19212 | D19: -17262 | E19: -13961 | F19: -5376 | G19: -3179 | H19: -563 | I19: 5125 | J19: -10323 | N19: =SUM(G19:J19) -> -8940 | P19: =I19 -> 5125 | Q19: =J19 -> -10323 | R19: =IF(P19=0, IF(Q19=0,0,IF(Q19>0,1,-1)), (Q19-P19)/ABS(P19) ) -> -3.0142439
B20: Income tax expense/benefit | C20: -510 | D20: -750 | E20: -442 | F20: -1014 | G20: -735 | H20: 1217 | I20: -854 | J20: 11618 | N20: =SUM(G20:J20) -> 11246 | P20: =I20 -> -854 | Q20: =J20 -> 11618 | R20: =IF(P20=0, IF(Q20=0,0,IF(Q20>0,1,-1)), (Q20-P20)/ABS(P20) ) -> 14.604215
B21: Net income | C21: -19722 | D21: -18012 | E21: -14403 | F21: -6390 | G21: -3914 | H21: 654 | I21: 4271 | J21: 1295 | N21: =SUM(G21:J21) -> 2306 | P21: =I21 -> 4271 | Q21: =J21 -> 1295 | R21: =IF(P21=0, IF(Q21=0,0,IF(Q21>0,1,-1)), (Q21-P21)/ABS(P21) ) -> -0.69679232
B22: Basic Shares outstanding avg | C22: 56666 | D22: 57503 | E22: 57892 | F22: 58278 | G22: 58921 | H22: 59592 | I22: 60009 | J22: 60404 | N22: =AVERAGE(G22:J22) -> 59731.5 | P22: =I22 -> 60009 | Q22: =J22 -> 60404 | R22: =IF(P22=0, IF(Q22=0,0,IF(Q22>0,1,-1)), (Q22-P22)/ABS(P22) ) -> 0.006582346
B23: Diluted Shares outstanding avg | C23: 56666 | D23: 57503 | E23: 57892 | F23: 58278 | G23: 58921 | H23: 61686 | I23: 61560 | J23: 61497 | N23: =AVERAGE((G23:J23)) -> 60916 | P23: =I23 -> 61560 | Q23: =J23 -> 61497 | R23: =IF(P23=0, IF(Q23=0,0,IF(Q23>0,1,-1)), (Q23-P23)/ABS(P23) ) -> -0.0010233918
B24: Basic EPS | C24: -0.35 | D24: -0.31 | E24: -0.25 | F24: -0.11 | G24: -0.07 | H24: 0.01 | I24: 0.07 | J24: 0.02 | N24: =N21/N22 -> 0.038606096 | P24: =I24 -> 0.07 | Q24: =J24 -> 0.02 | R24: =IF(P24=0, IF(Q24=0,0,IF(Q24>0,1,-1)), (Q24-P24)/ABS(P24) ) -> -0.71428571
B25: Diluted EPS | C25: -0.35 | D25: -0.31 | E25: -0.25 | F25: -0.11 | G25: -0.07 | H25: 0.01 | I25: 0.07 | J25: 0.02 | N25: =N21/N23 -> 0.037855407 | P25: =I25 -> 0.07 | Q25: =J25 -> 0.02 | R25: =IF(P25=0, IF(Q25=0,0,IF(Q25>0,1,-1)), (Q25-P25)/ABS(P25) ) -> -0.71428571
B27: Balance sheet
B28: Cash and cash equivalents | G28: 90871 | H28: 98266 | I28: 106371 | J28: 73830
B29: Settlement assets | G29: 33006 | H29: 28875 | I29: 25391 | J29: 32999
B30: Acc receivable | G30: 75099 | H30: 76842 | I30: 88257 | J30: 97453
B31: Cardholder receivables | G31: 0 | H31: 0 | I31: 0 | J31: 38330
B32: Deferred purchase receivables | G32: 0 | H32: 0 | I32: 0 | J32: 18003
B33: Accrued interest receivables | G33: 0 | H33: 0 | I33: 0 | J33: 840
B34: Deferred contract acquisition costs | G34: 414 | H34: 431 | I34: 427 | J34: 410
B35: Prepaid expenses & Other current | G35: 16019 | H35: 18227 | I35: 20460 | J35: 17978
B36: Current assets | G36: 215409 | H36: 222641 | I36: 240906 | J36: 279843
B37: PP&E | G37: 23492 | H37: 22769 | I37: 21111 | J37: 20332
B38: Capitalized internal use software | G38: 53531 | H38: 53881 | I38: 54093 | J38: 54270
B39: Operating lease right of use | G39: 1262 | H39: 1043 | I39: 820 | J39: 2002
... B46: Deferred purchase receivables | G46: 0 | H46: 0 | I46: 0 | J46: 5422
B47: Long term assets | C47: =SUM(C37:C44) -> 0 | D47: =SUM(D37:D44) -> 0 | E47: =SUM(E37:E44) -> 0 | F47: =SUM(F37:F44) -> 0 | G47: =SUM(G37:G44) -> 184986 | H47: =SUM(H37:H44) -> 185988 | I47: =SUM(I37:I44) -> 182566 | J47: =SUM(J37:J44) -> 330802
B48: Total assets | G48: 400395 | H48: 408629 | I48: 423472 | J48: 663790
B49: Settlement obligations | G49: 33006 | H49: 28875 | I49: 25391 | J49: 32999
B50: Current portion of finance lease | G50: 8348 | H50: 7096 | I50: 6199 | J50: 7971
B51: Current portion of operating lease | G51: 957 | H51: 941 | I51: 746 | J51: 1254
B52: Acc payable | G52: 3204 | H52: 6527 | I52: 6218 | J52: 11477
B53: Accrued expenses | G53: 34059 | H53: 34783 | I53: 30517 | J53: 41257
B54: Dues to healthcare providers | G54: 0 | H54: 0 | I54: 0 | J54: 38056
B55: Deferred revenue | G55: 31146 | H55: 26913 | I55: 29712 | J55: 49522
B56: Other current liabilities | G56: 0 | H56: 0 | I56: 0 | J56: 705
B57: Current liabilities | G57: 110720 | H57: 105135 | I57: 98783 | J57: 183241
B58: Long term finance lease | G58: 6162 | H58: 4576 | I58: 3353 | J58: 92117
B59: Operating lease | G59: 401 | H59: 179 | I59: 132 | J59: 1107
... B63: Other liabilities | G63: 246 | H63: 45 | I63: 41 | J63: 47
B64: Long term liabilities | C64: =SUM(C58:C63) -> 0 | D64: =SUM(D58:D63) -> 0 | E64: =SUM(E58:E63) -> 0 | F64: =SUM(F58:F63) -> 0 | G64: =SUM(G58:G63) -> 7489 | H64: =SUM(H58:H63) -> 5507 | I64: =SUM(I58:I63) -> 4360 | J64: =SUM(J58:J58) -> 92117
B65: Total liabilities | G65: 118209 | H65: 110642 | I65: 103143 | J65: 326583
B66: Preferred stock par value | G66: 0 | H66: 0 | I66: 0 | J66: 0
B67: Common stock par value | G67: 608 | H67: 611 | I67: 616 | J67: 620
B68: Additional paid-in capital | G68: 1132124 | H68: 1147540 | I68: 1166078 | J68: 1181679
B69: Retained earnings | G69: -805410 | H69: -804756 | I69: -800485 | J69: -799190
B70: Other comprehensive loss | G70: 384 | H70: 112 | I70: -360 | J70: -382
B71: Treasury stock par value | G71: -45520 | H71: -45520 | I71: -45520 | J71: -45520
B72: Stockholder equity | G72: 282186 | H72: 297987 | I72: 320329 | J72: 337207
B73: Total liabilities and equity | G73: 400395 | H73: 408629 | I73: 423472 | J73: 663790
B75: Cashflow statement
B76: Net income | C76: =C21 -> -19722 | D76: =D21 -> -18012 | E76: =E21 -> -14403 | F76: =F21 -> -6390 | G76: =G21 -> -3914 | H76: 654 | I76: =I21 -> 4271 | J76: =J21 -> 1295
B77: D&A | C77: 6673 | D77: 7303 | E77: 7087 | F77: 6823 | G77: 6878 | H77: 7409 | I77: 7478 | J77: 9688 | N77: =SUM(G77:J77) -> 31453
B78: Stock-based compensation | C78: 16840 | D78: 16448 | E78: 16525 | F78: 17162 | G78: 17225 | H78: 16230 | I78: 15959 | J78: 18038
B79: Amortization of deferred financing | C79: 61 | D79: 51 | E79: 62 | F79: 62 | G79: 62 | H79: 62 | I79: 61 | J79: 2792
B80: Loss exstinguishment of debt | C80: 0 | D80: 0 | E80: 0 | F80: 0 | G80: 0 | H80: 0 | I80: 0 | J80: 501
B81: Non-cash gain on settlement | C81: 0 | D81: 0 | E81: 0 | F81: -2345 | G81: 0 | H81: 0 | I81: 0 | J81: 0
B82: Cost of Phreesia HW purchased | C82: 343 | D82: 334 | E82: 571 | F82: 625 | G82: 436 | H82: 157 | I82: 235 | J82: 194
B83: Deferred contract acquisition | C83: 192 | D83: 192 | E83: 1322 | F83: 109 | G83: 110 | H83: 242 | I83: 111 | J83: 107
B84: Non-cash operating lease | C84: 173 | D84: 188 | E84: 207 | F84: 179 | G84: 215 | H84: 218 | I84: 224 | J84: 257
B85: Change fair value contingent liabilities | C85: 0 | D85: 0 | E85: 0 | F85: 0 | G85: 0 | H85: 0 | I85: 0 | J85: 0
B86: Deferred taxes | C86: 63 | D86: 56 | E86: 57 | F86: 38 | G86: 85 | H86: -1583 | I86: 57 | J86: -11830
B87: Unrialized gains/losses fair value option | C87: 0 | D87: 0 | E87: 0 | F87: 0 | G87: 0 | H87: 0 | I87: 0 | J87: -1020
B88: Change acc receivable | C88: -1393 | D88: 4976 | E88: -10141 | F88: -2254 | G88: -1490 | H88: -1820 | I88: -11455 | J88: -8632 | L88: =C89+C90+C91+C92+C94+C95+C96+C97 -> -1015 | M88: =D89+D90+D91+D92+D94+D95+D96+D97 -> -1661 | N88: =E89+E90+E91+E92+E94+E95+E96+E97 -> -2450 | O88: =F89+F90+F91+F92+F94+F95+F96+F97 -> 10679 | P88: =G89+G90+G91+G92+G94+G95+G96+G97 -> -3018 | Q88: =H89+H90+H91+H92+H94+H95+H96+H97 -> -8802 | R88: =I89+I90+I91+I92+I94+I95+I96+I97 -> -2777 | S88: =J89+J90+J91+J92+J94+J95+J96+J97 -> 18643
B89: Collections principal on receivables | C89: 0 | D89: 0 | E89: 0 | F89: 0 | G89: 0 | H89: 0 | I89: 0 | J89: 13691
B90: Accrued interest receivable | C90: 0 | D90: 0 | E90: 0 | F90: 0 | G90: 0 | H90: 0 | I90: 0 | J90: -446
B91: Change prepaid expenses | C91: 414 | D91: 2867 | E91: 1005 | F91: -5713 | G91: -256 | H91: -2660 | I91: -1952 | J91: 3475
B92: Change deferred contract acquisition | C92: 0 | D92: -213 | E92: -552 | F92: -280 | G92: 0 | H92: -351 | I92: 0 | J92: 17
B93: Change acc payable | C93: -2936 | D93: 1186 | E93: 6948 | F93: -8432 | G93: -1739 | H93: 2068 | I93: 1303 | J93: 3629
B94: Change accrued expenses | C94: -1155 | D94: -1392 | E94: -3655 | F94: 6384 | G94: -891 | H94: -1289 | I94: -3452 | J94: 8526
B95: Payment of due to provider | C95: 0 | D95: 0 | E95: 0 | F95: 0 | G95: 0 | H95: 0 | I95: 0 | J95: -17588
B96: Change lease liabilities | C96: -219 | D96: -201 | E96: -202 | F96: -202 | G96: -252 | H96: -238 | I96: -242 | J96: -375
B97: Change deferred revenue | C97: -55 | D97: -2722 | E97: 954 | F97: 10490 | G97: -1619 | H97: -4264 | I97: 2869 | J97: 11343
B98: Operating cashflow | C98: -721 | D98: 11061 | E98: 5785 | F98: 16256 | G98: 14850 | H98: 14835 | I98: 15467 | J98: 33662
B99: Acquisitions | C99: 0 | D99: 0 | E99: 0 | F99: 0 | G99: 0 | H99: 0 | I99: 0 | J99: -153191
B100: Capitalized internal use software | C100: -4570 | D100: -2976 | E100: -3566 | F100: -4268 | G100: -3888 | H100: -3435 | I100: -3395 | J100: -2578
... B125: End cash | C125: 79527 | D125: 81798 | E125: 81740 | F125: 84220 | G125: 90871 | H125: 98266 | I125: 106371 | J125: 73830
B127: Sanity checks
B128: Calculated Net Income | C128: =C5-C6-C13+C15+C16+C17+C18+C20 -> -19722 | D128: =D5-D6-D13+D15+D16+D17+D18+D20 -> -18012 | E128: =E5-E6-E13+E15+E16+E17+E18+E20 -> -14403 | F128: =F5-F6-F13+F15+F16+F17+F18+F20 -> -6390 | G128: =G5-G6-G13+G15+G16+G17+G18+G20 -> -3914 | H128: =H5-H6-H13+H15+H16+H17+H18+H20 -> 654 | I128: =I5-I6-I13+I15+I16+I17+I18+I20 -> 4271 | J128: =J5-J6-J13+J15+J16+J17+J18+J20 -> 1295
B129: Check Net Income | C129: =C21-C128 -> 0 | D129: =D21-D128 -> 0 | E129: =E21-E128 -> 0 | F129: =F21-F128 -> 0 | G129: =G21-G128 -> 0 | H129: =H21-H128 -> 0 | I129: =I21-I128 -> 0 | J129: =J21-J128 -> 0
B130: Calculated Assets | C130: =SUM(C28:C35)+SUM(C37:C46) -> 0 | D130: =SUM(D28:D35)+SUM(D37:D46) -> 0 | E130: =SUM(E28:E35)+SUM(E37:E46) -> 0 | F130: =SUM(F28:F35)+SUM(F37:F46) -> 0 | G130: =SUM(G28:G35)+SUM(G37:G46) -> 400395 | H130: =SUM(H28:H35)+SUM(H37:H46) -> 408629 | I130: =SUM(I28:I35)+SUM(I37:I46) -> 423472 | J130: =SUM(J28:J35)+SUM(J37:J46) -> 663790
B131: Check Assets | C131: =C48-C130 -> 0 | D131: =D48-D130 -> 0 | E131: =E48-E130 -> 0 | F131: =F48-F130 -> 0 | G131: =G48-G130 -> 0 | H131: =H48-H130 -> 0 | I131: =I48-I130 -> 0 | J131: =J48-J130 -> 0
B132: Calculated Liabilities | C132: =SUM(C49:C56)+SUM(C58:C63) -> 0 | D132: =SUM(D49:D56)+SUM(D58:D63) -> 0 | E132: =SUM(E49:E56)+SUM(E58:E63) -> 0 | F132: =SUM(F49:F56)+SUM(F58:F63) -> 0 | G132: =SUM(G49:G56)+SUM(G58:G63) -> 118209 | H132: =SUM(H49:H56)+SUM(H58:H63) -> 110642 | I132: =SUM(I49:I56)+SUM(I58:I63) -> 103143 | J132: =SUM(J49:J56)+SUM(J58:J63) -> 326583
B133: Check Liabilities | C133: =C65-C132 -> 0 | D133: =D65-D132 -> 0 | E133: =E65-E132 -> 0 | F133: =F65-F132 -> 0 | G133: =G65-G132 -> 0 | H133: =H65-H132 -> 0 | I133: =I65-I132 -> 0 | J133: =J65-J132 -> 0
B134: Calculated Stockholder Equity | C134: =SUM(C66:C71) -> 0 | D134: =SUM(D66:D71) -> 0 | E134: =SUM(E66:E71) -> 0 | F134: =SUM(F66:F71) -> 0 | G134: =SUM(G66:G71) -> 282186 | H134: =SUM(H66:H71) -> 297987 | I134: =SUM(I66:I71) -> 320329 | J134: =SUM(J66:J71) -> 337207
B135: Check Stockholder Equity | C135: =C72-C134 -> 0 | D135: =D72-D134 -> 0 | E135: =E72-E134 -> 0 | F135: =F72-F134 -> 0 | G135: =G72-G134 -> 0 | H135: =H72-H134 -> 0 | I135: =I72-I134 -> 0 | J135: =J72-J134 -> 0
B136: Check balance | C136: =C48-(C65+C72) -> 0 | D136: =D48-(D65+D72) -> 0 | E136: =E48-(E65+E72) -> 0 | F136: =F48-(F65+F72) -> 0 | G136: =G48-(G65+G72) -> 0 | H136: =H48-(H65+H72) -> 0 | I136: =I48-(I65+I72) -> 0 | J136: =J48-(J65+J72) -> 0
B137: Calculated Operating Cashflow | C137: =SUM(C76:C97) -> -721 | D137: =SUM(D76:D97) -> 11061 | E137: =SUM(E76:E97) -> 5785 | F137: =SUM(F76:F97) -> 16256 | G137: =SUM(G76:G97) -> 14850 | H137: =SUM(H76:H97) -> 14835 | I137: =SUM(I76:I97) -> 15467 | J137: =SUM(J76:J97) -> 33662
...

Sheet Statements
B2: Date | C2: ='Statement Y'!C2 -> 31.01.2021 | D2: ='Statement Y'!D2 -> 31.01.2022 | E2: ='Statement Y'!E2 -> 31.01.2023 | F2: ='Statement Y'!F2 -> 31.01.2024 | G2: ='Statement Y'!G2 -> 31.01.2025 | H2: ='Statement Y'!H2 -> 31.01.2026 | J2: ='Statement Q'!C2 -> 30.04.2024 | K2: ='Statement Q'!D2 -> 31.07.2024 | L2: ='Statement Q'!E2 -> 31.10.2024 | M2: ='Statement Q'!F2 -> 31.01.2025 | N2: ='Statement Q'!G2 -> 30.04.2025 | O2: ='Statement Q'!H2 -> 31.07.2025 | P2: ='Statement Q'!I2 -> 31.10.2025 | Q2: ='Statement Q'!J2 -> 31.01.2026
B3: FY | C3: ='Statement Y'!C3 -> 2021 | D3: ='Statement Y'!D3 -> 2022 | E3: ='Statement Y'!E3 -> 2023 | F3: ='Statement Y'!F3 -> 2024 | G3: ='Statement Y'!G3 -> 2025 | H3: ='Statement Y'!H3 -> 2026 | J3: ='Statement Q'!C3 -> Q1 2025 | K3: ='Statement Q'!D3 -> Q2 2025 | L3: ='Statement Q'!E3 -> Q3 2025 | M3: ='Statement Q'!F3 -> Q4 2025 | N3: ='Statement Q'!G3 -> Q1 2026 | O3: ='Statement Q'!H3 -> Q2 2026 | P3: ='Statement Q'!I3 -> Q3 2026 | Q3: ='Statement Q'!J3 -> Q4 2026 | S3: TTM
B4: Income statement
B5: Revenue | C5: ='Statement Y'!C5 -> 148677 | D5: ='Statement Y'!D5 -> 213233 | E5: ='Statement Y'!E5 -> 280910 | F5: ='Statement Y'!F5 -> 356299 | G5: ='Statement Y'!G5 -> 419813 | H5: ='Statement Y'!H5 -> 480591 | J5: ='Statement Q'!C5 -> 101217 | K5: ='Statement Q'!D5 -> 102115 | L5: ='Statement Q'!E5 -> 106800 | M5: ='Statement Q'!F5 -> 109681 | N5: ='Statement Q'!G5 -> 115936 | O5: ='Statement Q'!H5 -> 117255 | P5: ='Statement Q'!I5 -> 120333 | Q5: ='Statement Q'!J5 -> 127067 | S5: =SUM(N5:Q5) -> 480591
B6: COGS | C6: ='Statement Y'!C6 -> 52386 | D6: ='Statement Y'!D6 -> 81388 | E6: ='Statement Y'!E6 -> 109267 | F6: ='Statement Y'!F6 -> 124011 | G6: ='Statement Y'!G6 -> 134934 | H6: ='Statement Y'!H6 -> 154123 | J6: ='Statement Q'!C6 -> 34020 | K6: ='Statement Q'!D6 -> 32811 | L6: ='Statement Q'!E6 -> 34537 | M6: ='Statement Q'!F6 -> 33566 | N6: ='Statement Q'!G6 -> 38065 | O6: ='Statement Q'!H6 -> 37641 | P6: ='Statement Q'!I6 -> 38027 | Q6: ='Statement Q'!J6 -> 40390 | S6: =SUM(N6:Q6) -> 154123
B7: Gross Profit | C7: ='Statement Y'!C7 -> 96291 | D7: ='Statement Y'!D7 -> 131845 | E7: ='Statement Y'!E7 -> 171643 | F7: ='Statement Y'!F7 -> 232288 | G7: ='Statement Y'!G7 -> 284879 | H7: ='Statement Y'!H7 -> 326468 | J7: ='Statement Q'!C7 -> 67197 | K7: ='Statement Q'!D7 -> 69304 | L7: ='Statement Q'!E7 -> 72263 | M7: ='Statement Q'!F7 -> 76115 | N7: ='Statement Q'!G7 -> 77871 | O7: ='Statement Q'!H7 -> 79614 | P7: ='Statement Q'!I7 -> 82306 | Q7: ='Statement Q'!J7 -> 86677 | S7: =SUM(N7:Q7) -> 326468
B8: Sales and marketing | C8: ='Statement Y'!C8 -> 42972 | D8: ='Statement Y'!D8 -> 106421 | E8: ='Statement Y'!E8 -> 151263 | F8: ='Statement Y'!F8 -> 147008 | G8: ='Statement Y'!G8 -> 121129 | H8: ='Statement Y'!H8 -> 100243 | J8: ='Statement Q'!C8 -> 32011 | K8: ='Statement Q'!D8 -> 30184 | L8: ='Statement Q'!E8 -> 30071 | M8: ='Statement Q'!F8 -> 28863 | N8: ='Statement Q'!G8 -> 26043 | O8: ='Statement Q'!H8 -> 25396 | P8: ='Statement Q'!I8 -> 24148 | Q8: ='Statement Q'!J8 -> 24656 | S8: =SUM(N8:Q8) -> 100243
B9: R&D | C9: ='Statement Y'!C9 -> 22622 | D9: ='Statement Y'!D9 -> 52265 | E9: ='Statement Y'!E9 -> 91244 | F9: ='Statement Y'!F9 -> 112346 | G9: ='Statement Y'!G9 -> 117364 | H9: ='Statement Y'!H9 -> 121481 | J9: ='Statement Q'!C9 -> 28881 | K9: ='Statement Q'!D9 -> 29542 | L9: ='Statement Q'!E9 -> 29315 | M9: ='Statement Q'!F9 -> 29626 | N9: ='Statement Q'!G9 -> 31829 | O9: ='Statement Q'!H9 -> 29274 | P9: ='Statement Q'!I9 -> 29453 | Q9: ='Statement Q'!J9 -> 30925 | S9: =SUM(N9:Q9) -> 121481
B10: General and administrative | C10: ='Statement Y'!C10 -> 40460 | D10: ='Statement Y'!D10 -> 68674 | E10: ='Statement Y'!E10 -> 80384 | F10: ='Statement Y'!F10 -> 79926 | G10: ='Statement Y'!G10 -> 76597 | H10: ='Statement Y'!H10 -> 79903 | J10: ='Statement Q'!C10 -> 19052 | K10: ='Statement Q'!D10 -> 19497 | L10: ='Statement Q'!E10 -> 19633 | M10: ='Statement Q'!F10 -> 18415 | N10: ='Statement Q'!G10 -> 16408 | O10: ='Statement Q'!H10 -> 19042 | P10: ='Statement Q'!I10 -> 17488 | Q10: ='Statement Q'!J10 -> 26965 | S10: =SUM(N10:Q10) -> 79903
B11: Depreciation | C11: ='Statement Y'!C11 -> 9770 | D11: ='Statement Y'!D11 -> 14985 | E11: ='Statement Y'!E11 -> 17988 | F11: ='Statement Y'!F11 -> 17584 | G11: ='Statement Y'!G11 -> 14183 | H11: ='Statement Y'!H11 -> 12972 | J11: ='Statement Q'!C11 -> 3524 | K11: ='Statement Q'!D11 -> 3921 | L11: ='Statement Q'!E11 -> 3566 | M11: ='Statement Q'!F11 -> 3172 | N11: ='Statement Q'!G11 -> 2986 | O11: ='Statement Q'!H11 -> 3279 | P11: ='Statement Q'!I11 -> 3199 | Q11: ='Statement Q'!J11 -> 3508 | S11: =SUM(N11:Q11) -> 12972
B12: Amortization | C12: ='Statement Y'!C12 -> 6138 | D12: ='Statement Y'!D12 -> 6317 | E12: ='Statement Y'!E12 -> 7316 | F12: ='Statement Y'!F12 -> 11903 | G12: ='Statement Y'!G12 -> 13703 | H12: ='Statement Y'!H12 -> 18481 | J12: ='Statement Q'!C12 -> 3149 | K12: ='Statement Q'!D12 -> 3382 | L12: ='Statement Q'!E12 -> 3521 | M12: ='Statement Q'!F12 -> 3651 | N12: ='Statement Q'!G12 -> 3892 | O12: ='Statement Q'!H12 -> 4130 | P12: ='Statement Q'!I12 -> 4279 | Q12: ='Statement Q'!J12 -> 6180 | S12: =SUM(N12:Q12) -> 18481
B13: OpEx | C13: ='Statement Y'!C13 -> 121962 | D13: ='Statement Y'!D13 -> 248662 | E13: ='Statement Y'!E13 -> 348195 | F13: ='Statement Y'!F13 -> 368767 | G13: ='Statement Y'!G13 -> 342976 | H13: ='Statement Y'!H13 -> 333080 | J13: ='Statement Q'!C13 -> 86617 | K13: ='Statement Q'!D13 -> 86526 | L13: ='Statement Q'!E13 -> 86106 | M13: ='Statement Q'!F13 -> 83727 | N13: ='Statement Q'!G13 -> 81158 | O13: ='Statement Q'!H13 -> 81121 | P13: ='Statement Q'!I13 -> 78567 | Q13: ='Statement Q'!J13 -> 92234 | S13: =SUM(N13:Q13) -> 333080
B14: Operating income | C14: ='Statement Y'!C14 -> -25671 | D14: ='Statement Y'!D14 -> -116817 | E14: ='Statement Y'!E14 -> -176552 | F14: ='Statement Y'!F14 -> -136479 | G14: ='Statement Y'!G14 -> -58097 | H14: ='Statement Y'!H14 -> -6612 | J14: ='Statement Q'!C14 -> -19420 | K14: ='Statement Q'!D14 -> -17222 | L14: ='Statement Q'!E14 -> -13843 | M14: ='Statement Q'!F14 -> -7612 | N14: ='Statement Q'!G14 -> -3287 | O14: ='Statement Q'!H14 -> -1507 | P14: ='Statement Q'!I14 -> 3739 | Q14: ='Statement Q'!J14 -> -5557 | S14: =SUM(N14:Q14) -> -6612
B15: EBITDA | C15: =C14+C73 -> -9763 | D15: =D14+D73 -> -95515 | E15: =E14+E73 -> -151248 | F15: =F14+F73 -> -106992 | G15: =G14+G73 -> -30211 | H15: =H14+H73 -> 24841 | J15: =J14+J73 -> -12747 | K15: =K14+K73 -> -9919 | L15: =L14+L73 -> -6756 | M15: =M14+M73 -> -789 | N15: =N14+N73 -> 3591 | O15: =O14+O73 -> 5902 | P15: =P14+P73 -> 11217 | Q15: =Q14+Q73 -> 4131 | S15: =SUM(N15:Q15) -> 24841
B16: Other income/expense | C16: ='Statement Y'!C15 -> 1 | D16: ='Statement Y'!D15 -> -78 | E16: ='Statement Y'!E15 -> -175 | F16: ='Statement Y'!F15 -> 44 | G16: ='Statement Y'!G15 -> 1956 | H16: ='Statement Y'!H15 -> 2953 | J16: ='Statement Q'!C15 -> -31 | K16: ='Statement Q'!D15 -> -86 | L16: ='Statement Q'!E15 -> -144 | M16: ='Statement Q'!F15 -> 2217 | N16: ='Statement Q'!G15 -> 338 | O16: ='Statement Q'!H15 -> 336 | P16: ='Statement Q'!I15 -> 1006 | Q16: ='Statement Q'!J15 -> 1273 | S16: =SUM(N16:Q16) -> 2953
B17: Extinguishment of debt | C17: ='Statement Y'!C16 -> 0 | D17: ='Statement Y'!D16 -> 0 | E17: ='Statement Y'!E16 -> 0 | F17: ='Statement Y'!F16 -> -1118 | G17: ='Statement Y'!G16 -> 0 | H17: ='Statement Y'!H16 -> -501 | J17: ='Statement Q'!C16 -> 0 | K17: ='Statement Q'!D16 -> 0 | L17: ='Statement Q'!E16 -> 0 | M17: ='Statement Q'!F16 -> 0 | N17: ='Statement Q'!G16 -> 0 | O17: ='Statement Q'!H16 -> 0 | P17: ='Statement Q'!I16 -> 0 | Q17: ='Statement Q'!J16 -> -501 | S17: =SUM(N17:Q17) -> -501
B18: Interest income | C18: ='Statement Y'!C18+'Statement Y'!C17 -> -1573 | D18: ='Statement Y'!D18+'Statement Y'!D17 -> -1084 | E18: ='Statement Y'!E18+'Statement Y'!E17 -> 1064 | F18: ='Statement Y'!F18+'Statement Y'!F17 -> 2211 | G18: ='Statement Y'!G18+'Statement Y'!G17 -> 330 | H18: ='Statement Y'!H18+'Statement Y'!H17 -> -4780 | J18: ='Statement Q'!C18+'Statement Q'!C17 -> 239 | K18: ='Statement Q'!D18+'Statement Q'!D17 -> 46 | L18: ='Statement Q'!E18+'Statement Q'!E17 -> 26 | M18: ='Statement Q'!F18+'Statement Q'!F17 -> 19 | N18: ='Statement Q'!G18+'Statement Q'!G17 -> -230 | O18: ='Statement Q'!H18+'Statement Q'!H17 -> 608 | P18: ='Statement Q'!I18+'Statement Q'!I17 -> 380 | Q18: ='Statement Q'!J18+'Statement Q'!J17 -> -5538 | S18: =SUM(N18:Q18) -> -4780
B19: Income before taxes | C19: ='Statement Y'!C19 -> -27243 | D19: ='Statement Y'!D19 -> -117979 | E19: ='Statement Y'!E19 -> -175663 | F19: ='Statement Y'!F19 -> -135342 | G19: ='Statement Y'!G19 -> -55811 | H19: ='Statement Y'!H19 -> -8940 | J19: ='Statement Q'!C19 -> -19212 | K19: ='Statement Q'!D19 -> -17262 | L19: ='Statement Q'!E19 -> -13961 | M19: ='Statement Q'!F19 -> -5376 | N19: ='Statement Q'!G19 -> -3179 | O19: ='Statement Q'!H19 -> -563 | P19: ='Statement Q'!I19 -> 5125 | Q19: ='Statement Q'!J19 -> -10323 | S19: =SUM(N19:Q19) -> -8940
B20: Income tax expense/benefit | C20: ='Statement Y'!C20 -> -49 | D20: ='Statement Y'!D20 -> -182 | E20: ='Statement Y'!E20 -> -483 | F20: ='Statement Y'!F20 -> -1543 | G20: ='Statement Y'!G20 -> -2716 | H20: ='Statement Y'!H20 -> 11246 | J20: ='Statement Q'!C20 -> -510 | K20: ='Statement Q'!D20 -> -750 | L20: ='Statement Q'!E20 -> -442 | M20: ='Statement Q'!F20 -> -1014 | N20: ='Statement Q'!G20 -> -735 | O20: ='Statement Q'!H20 -> 1217 | P20: ='Statement Q'!I20 -> -854 | Q20: ='Statement Q'!J20 -> 11618 | S20: =SUM(N20:Q20) -> 11246
B21: Net income | C21: ='Statement Y'!C21 -> -27292 | D21: ='Statement Y'!D21 -> -118161 | E21: ='Statement Y'!E21 -> -176146 | F21: ='Statement Y'!F21 -> -136885 | G21: ='Statement Y'!G21 -> -58527 | H21: ='Statement Y'!H21 -> 2306 | J21: ='Statement Q'!C21 -> -19722 | K21: ='Statement Q'!D21 -> -18012 | L21: ='Statement Q'!E21 -> -14403 | M21: ='Statement Q'!F21 -> -6390 | N21: ='Statement Q'!G21 -> -3914 | O21: ='Statement Q'!H21 -> 654 | P21: ='Statement Q'!I21 -> 4271 | Q21: ='Statement Q'!J21 -> 1295 | S21: =SUM(N21:Q21) -> 2306
B22: Diluted Shares outstanding avg | C22: ='Statement Y'!C23 -> 39520 | D22: ='Statement Y'!D23 -> 49888 | E22: ='Statement Y'!E23 -> 52440 | F22: ='Statement Y'!F23 -> 54561 | G22: ='Statement Y'!G23 -> 57590 | H22: ='Statement Y'!H23 -> 61495 | J22: ='Statement Q'!C23 -> 56666 | K22: ='Statement Q'!D23 -> 57503 | L22: ='Statement Q'!E23 -> 57892 | M22: ='Statement Q'!F23 -> 58278 | N22: ='Statement Q'!G23 -> 58921 | O22: ='Statement Q'!H23 -> 61686 | P22: ='Statement Q'!I23 -> 61560 | Q22: ='Statement Q'!J23 -> 61497 | S22: =AVERAGE(N22:Q22) -> 60916
B23: Diluted EPS | C23: ='Statement Y'!C25 -> -0.69 | D23: ='Statement Y'!D25 -> -2.37 | E23: ='Statement Y'!E25 -> -3.36 | F23: ='Statement Y'!F25 -> -2.51 | G23: ='Statement Y'!G25 -> -1.02 | H23: ='Statement Y'!H25 -> 0.04 | J23: ='Statement Q'!C25 -> -0.35 | K23: ='Statement Q'!D25 -> -0.31 | L23: ='Statement Q'!E25 -> -0.25 | M23: ='Statement Q'!F25 -> -0.11 | N23: ='Statement Q'!G25 -> -0.07 | O23: ='Statement Q'!H25 -> 0.01 | P23: ='Statement Q'!I25 -> 0.07 | Q23: ='Statement Q'!J25 -> 0.02 | S23: =S21/S22 -> 0.037855407
B25: Balance sheet
B26: Cash and cash equivalents | C26: ='Statement Y'!C28 -> 218781 | D26: ='Statement Y'!D28 -> 313812 | E26: ='Statement Y'!E28 -> 176683 | F26: ='Statement Y'!F28 -> 87520 | G26: ='Statement Y'!G28 -> 84220 | H26: ='Statement Y'!H28 -> 73830 | J26: ='Statement Q'!C28 -> 0 | K26: ='Statement Q'!D28 -> 0 | L26: ='Statement Q'!E28 -> 0 | M26: ='Statement Q'!F28 -> 0 | N26: ='Statement Q'!G28 -> 90871 | O26: ='Statement Q'!H28 -> 98266 | P26: ='Statement Q'!I28 -> 106371 | Q26: ='Statement Q'!J28 -> 73830 | S26: =Q26 -> 73830
B27: Settlement assets | C27: ='Statement Y'!C29 -> 15488 | D27: ='Statement Y'!D29 -> 19590 | E27: ='Statement Y'!E29 -> 22599 | F27: ='Statement Y'!F29 -> 28072 | G27: ='Statement Y'!G29 -> 29176 | H27: ='Statement Y'!H29 -> 32999 | J27: ='Statement Q'!C29 -> 0 | K27: ='Statement Q'!D29 -> 0 | L27: ='Statement Q'!E29 -> 0 | M27: ='Statement Q'!F29 -> 0 | N27: ='Statement Q'!G29 -> 33006 | O27: ='Statement Q'!H29 -> 28875 | P27: ='Statement Q'!I29 -> 25391 | Q27: ='Statement Q'!J29 -> 32999 | S27: =Q27 -> 32999
B28: Acc receivable | C28: ='Statement Y'!C30 -> 29052 | D28: ='Statement Y'!D30 -> 40262 | E28: ='Statement Y'!E30 -> 51394 | F28: ='Statement Y'!F30 -> 64863 | G28: ='Statement Y'!G30 -> 73617 | H28: ='Statement Y'!H30 -> 97453 | J28: ='Statement Q'!C30 -> 0 | K28: ='Statement Q'!D30 -> 0 | L28: ='Statement Q'!E30 -> 0 | M28: ='Statement Q'!F30 -> 0 | N28: ='Statement Q'!G30 -> 75099 | O28: ='Statement Q'!H30 -> 76842 | P28: ='Statement Q'!I30 -> 88257 | Q28: ='Statement Q'!J30 -> 97453 | S28: =Q28 -> 97453
B29: Cardholder receivables | C29: ='Statement Y'!C31 -> 0 | D29: ='Statement Y'!D31 -> 0 | E29: ='Statement Y'!E31 -> 0 | F29: ='Statement Y'!F31 -> 0 | G29: ='Statement Y'!G31 -> 0 | H29: ='Statement Y'!H31 -> 38330 | J29: ='Statement Q'!C31 -> 0 | K29: ='Statement Q'!D31 -> 0 | L29: ='Statement Q'!E31 -> 0 | M29: ='Statement Q'!F31 -> 0 | N29: ='Statement Q'!G31 -> 0 | O29: ='Statement Q'!H31 -> 0 | P29: ='Statement Q'!I31 -> 0 | Q29: ='Statement Q'!J31 -> 38330 | S29: =Q29 -> 38330
B30: Deferred purchase receivables | C30: ='Statement Y'!C32 -> 0 | D30: ='Statement Y'!D32 -> 0 | E30: ='Statement Y'!E32 -> 0 | F30: ='Statement Y'!F32 -> 0 | G30: ='Statement Y'!G32 -> 0 | H30: ='Statement Y'!H32 -> 18003 | J30: ='Statement Q'!C32 -> 0 | K30: ='Statement Q'!D32 -> 0 | L30: ='Statement Q'!E32 -> 0 | M30: ='Statement Q'!F32 -> 0 | N30: ='Statement Q'!G32 -> 0 | O30: ='Statement Q'!H32 -> 0 | P30: ='Statement Q'!I32 -> 0 | Q30: ='Statement Q'!J32 -> 18003 | S30: =Q30 -> 18003
B31: Accrued interest receivables | C31: ='Statement Y'!C33 -> 0 | D31: ='Statement Y'!D33 -> 0 | E31: ='Statement Y'!E33 -> 0 | F31: ='Statement Y'!F33 -> 0 | G31: ='Statement Y'!G33 -> 0 | H31: ='Statement Y'!H33 -> 840 | J31: ='Statement Q'!C33 -> 0 | K31: ='Statement Q'!D33 -> 0 | L31: ='Statement Q'!E33 -> 0 | M31: ='Statement Q'!F33 -> 0 | N31: ='Statement Q'!G33 -> 0 | O31: ='Statement Q'!H33 -> 0 | P31: ='Statement Q'!I33 -> 0 | Q31: ='Statement Q'!J33 -> 840 | S31: =Q31 -> 840
B32: Deferred contract acquisition costs | C32: ='Statement Y'!C34 -> 1693 | D32: ='Statement Y'!D34 -> 1642 | E32: ='Statement Y'!E34 -> 1056 | F32: ='Statement Y'!F34 -> 768 | G32: ='Statement Y'!G34 -> 401 | H32: ='Statement Y'!H34 -> 410 | J32: ='Statement Q'!C34 -> 0 | K32: ='Statement Q'!D34 -> 0 | L32: ='Statement Q'!E34 -> 0 | M32: ='Statement Q'!F34 -> 0 | N32: ='Statement Q'!G34 -> 414 | O32: ='Statement Q'!H34 -> 431 | P32: ='Statement Q'!I34 -> 427 | Q32: ='Statement Q'!J34 -> 410 | S32: =Q32 -> 410
B33: Prepaid expenses & Other current | C33: ='Statement Y'!C35 -> 7254 | D33: ='Statement Y'!D35 -> 11043 | E33: ='Statement Y'!E35 -> 10709 | F33: ='Statement Y'!F35 -> 14461 | G33: ='Statement Y'!G35 -> 15871 | H33: ='Statement Y'!H35 -> 17978 | J33: ='Statement Q'!C35 -> 0 | K33: ='Statement Q'!D35 -> 0 | L33: ='Statement Q'!E35 -> 0 | M33: ='Statement Q'!F35 -> 0 | N33: ='Statement Q'!G35 -> 16019 | O33: ='Statement Q'!H35 -> 18227 | P33: ='Statement Q'!I35 -> 20460 | Q33: ='Statement Q'!J35 -> 17978 | S33: =Q33 -> 17978
B34: Current assets | C34: ='Statement Y'!C36 -> 272268 | D34: ='Statement Y'!D36 -> 386349 | E34: ='Statement Y'!E36 -> 262441 | F34: ='Statement Y'!F36 -> 195684 | G34: ='Statement Y'!G36 -> 203285 | H34: ='Statement Y'!H36 -> 279843 | J34: ='Statement Q'!C36 -> 0 | K34: ='Statement Q'!D36 -> 0 | L34: ='Statement Q'!E36 -> 0 | M34: ='Statement Q'!F36 -> 0 | N34: ='Statement Q'!G36 -> 215409 | O34: ='Statement Q'!H36 -> 222641 | P34: ='Statement Q'!I36 -> 240906 | Q34: ='Statement Q'!J36 -> 279843 | S34: =Q34 -> 279843
B35: PP&E | C35: ='Statement Y'!C37 -> 26660 | D35: ='Statement Y'!D37 -> 34645 | E35: ='Statement Y'!E37 -> 21670 | F35: ='Statement Y'!F37 -> 16902 | G35: ='Statement Y'!G37 -> 23651 | H35: ='Statement Y'!H37 -> 20332 | J35: ='Statement Q'!C37 -> 0 | K35: ='Statement Q'!D37 -> 0 | L35: ='Statement Q'!E37 -> 0 | M35: ='Statement Q'!F37 -> 0 | N35: ='Statement Q'!G37 -> 23492 | O35: ='Statement Q'!H37 -> 22769 | P35: ='Statement Q'!I37 -> 21111 | Q35: ='Statement Q'!J37 -> 20332 | S35: =Q35 -> 20332
B36: Capitalized internal use software | C36: ='Statement Y'!C38 -> 10476 | D36: ='Statement Y'!D38 -> 17643 | E36: ='Statement Y'!E38 -> 35150 | F36: ='Statement Y'!F38 -> 46139 | G36: ='Statement Y'!G38 -> 52763 | H36: ='Statement Y'!H38 -> 54270 | J36: ='Statement Q'!C38 -> 0 | K36: ='Statement Q'!D38 -> 0 | L36: ='Statement Q'!E38 -> 0 | M36: ='Statement Q'!F38 -> 0 | N36: ='Statement Q'!G38 -> 53531 | O36: ='Statement Q'!H38 -> 53881 | P36: ='Statement Q'!I38 -> 54093 | Q36: ='Statement Q'!J38 -> 54270 | S36: =Q36 -> 54270
B37: Operating lease right of use | C37: ='Statement Y'!C39 -> 2654 | D37: ='Statement Y'!D39 -> 2337 | E37: ='Statement Y'!E39 -> 569 | F37: ='Statement Y'!F39 -> 266 | G37: ='Statement Y'!G39 -> 1477 | H37: ='Statement Y'!H39 -> 2002 | J37: ='Statement Q'!C39 -> 0 | K37: ='Statement Q'!D39 -> 0 | L37: ='Statement Q'!E39 -> 0 | M37: ='Statement Q'!F39 -> 0 | N37: ='Statement Q'!G39 -> 1262 | O37: ='Statement Q'!H39 -> 1043 | P37: ='Statement Q'!I39 -> 820 | Q37: ='Statement Q'!J39 -> 2002 | S37: =Q37 -> 2002
... B63: Total liabilities | C63: ='Statement Y'!C65 -> 63360 | D63: ='Statement Y'!D65 -> 77196 | E63: ='Statement Y'!E65 -> 82238 | F63: ='Statement Y'!F65 -> 118877 | G63: ='Statement Y'!G65 -> 123607 | H63: ='Statement Y'!H65 -> 326583 | J63: ='Statement Q'!C65 -> 0 | K63: ='Statement Q'!D65 -> 0 | L63: ='Statement Q'!E65 -> 0 | M63: ='Statement Q'!F65 -> 0 | N63: ='Statement Q'!G65 -> 118209 | O63: ='Statement Q'!H65 -> 110642 | P63: ='Statement Q'!I65 -> 103143 | Q63: ='Statement Q'!J65 -> 326583 | S63: =Q63 -> 326583
B64: Common stock par value | C64: ='Statement Y'!C67 -> 449 | D64: ='Statement Y'!D67 -> 521 | E64: ='Statement Y'!E67 -> 542 | F64: ='Statement Y'!F67 -> 577 | G64: ='Statement Y'!G67 -> 601 | H64: ='Statement Y'!H67 -> 620 | J64: ='Statement Q'!C67 -> 0 | K64: ='Statement Q'!D67 -> 0 | L64: ='Statement Q'!E67 -> 0 | M64: ='Statement Q'!F67 -> 0 | N64: ='Statement Q'!G67 -> 608 | O64: ='Statement Q'!H67 -> 611 | P64: ='Statement Q'!I67 -> 616 | Q64: ='Statement Q'!J67 -> 620 | S64: =Q64 -> 620
B65: Additional paid-in capital | C65: ='Statement Y'!C68 -> 579599 | D65: ='Statement Y'!D68 -> 860657 | E65: ='Statement Y'!E68 -> 926957 | F65: ='Statement Y'!F68 -> 1039361 | G65: ='Statement Y'!G68 -> 1111274 | H65: ='Statement Y'!H68 -> 1181679 | J65: ='Statement Q'!C68 -> 0 | K65: ='Statement Q'!D68 -> 0 | L65: ='Statement Q'!E68 -> 0 | M65: ='Statement Q'!F68 -> 0 | N65: ='Statement Q'!G68 -> 1132124 | O65: ='Statement Q'!H68 -> 1147540 | P65: ='Statement Q'!I68 -> 1166078 | Q65: ='Statement Q'!J68 -> 1181679 | S65: =Q65 -> 1181679
B66: Retained earnings | C66: ='Statement Y'!C69 -> -311777 | D66: ='Statement Y'!D69 -> -429938 | E66: ='Statement Y'!E69 -> -606084 | F66: ='Statement Y'!F69 -> -742969 | G66: ='Statement Y'!G69 -> -801496 | H66: ='Statement Y'!H69 -> -799190 | J66: ='Statement Q'!C69 -> 0 | K66: ='Statement Q'!D69 -> 0 | L66: ='Statement Q'!E69 -> 0 | M66: ='Statement Q'!F69 -> 0 | N66: ='Statement Q'!G69 -> -805410 | O66: ='Statement Q'!H69 -> -804756 | P66: ='Statement Q'!I69 -> -800485 | Q66: ='Statement Q'!J69 -> -799190 | S66: =Q66 -> -799190
B67: Treasury stock par value | C67: ='Statement Y'!C71 -> -4965 | D67: ='Statement Y'!D71 -> -13960 | E67: ='Statement Y'!E71 -> -33596 | F67: ='Statement Y'!F71 -> -45520 | G67: ='Statement Y'!G71 -> -45520 | H67: ='Statement Y'!H71 -> -45520 | J67: ='Statement Q'!C71 -> 0 | K67: ='Statement Q'!D71 -> 0 | L67: ='Statement Q'!E71 -> 0 | M67: ='Statement Q'!F71 -> 0 | N67: ='Statement Q'!G71 -> -45520 | O67: ='Statement Q'!H71 -> -45520 | P67: ='Statement Q'!I71 -> -45520 | Q67: ='Statement Q'!J71 -> -45520 | S67: =Q67 -> -45520
B68: Stockholder equity | C68: ='Statement Y'!C72 -> 263306 | D68: ='Statement Y'!D72 -> 417280 | E68: ='Statement Y'!E72 -> 287819 | F68: ='Statement Y'!F72 -> 251449 | G68: ='Statement Y'!G72 -> 264808 | H68: ='Statement Y'!H72 -> 337207 | J68: ='Statement Q'!C72 -> 0 | K68: ='Statement Q'!D72 -> 0 | L68: ='Statement Q'!E72 -> 0 | M68: ='Statement Q'!F72 -> 0 | N68: ='Statement Q'!G72 -> 282186 | O68: ='Statement Q'!H72 -> 297987 | P68: ='Statement Q'!I72 -> 320329 | Q68: ='Statement Q'!J72 -> 337207 | S68: =Q68 -> 337207
B69: Total liabilities and equity | C69: ='Statement Y'!C73 -> 326666 | D69: ='Statement Y'!D73 -> 494476 | E69: ='Statement Y'!E73 -> 370057 | F69: ='Statement Y'!F73 -> 370326 | G69: ='Statement Y'!G73 -> 388415 | H69: ='Statement Y'!H73 -> 663790 | J69: ='Statement Q'!C73 -> 0 | K69: ='Statement Q'!D73 -> 0 | L69: ='Statement Q'!E73 -> 0 | M69: ='Statement Q'!F73 -> 0 | N69: ='Statement Q'!G73 -> 400395 | O69: ='Statement Q'!H73 -> 408629 | P69: ='Statement Q'!I73 -> 423472 | Q69: ='Statement Q'!J73 -> 663790 | S69: =Q69 -> 663790
B71: Cashflow statement
B72: Net income | C72: ='Statement Y'!C76 -> -27292 | D72: ='Statement Y'!D76 -> -118161 | E72: ='Statement Y'!E76 -> -176146 | F72: ='Statement Y'!F76 -> -136885 | G72: ='Statement Y'!G76 -> -58527 | H72: ='Statement Y'!H76 -> 2306 | J72: ='Statement Q'!C76 -> -19722 | K72: ='Statement Q'!D76 -> -18012 | L72: ='Statement Q'!E76 -> -14403 | M72: ='Statement Q'!F76 -> -6390 | N72: ='Statement Q'!G76 -> -3914 | O72: ='Statement Q'!H76 -> 654 | P72: ='Statement Q'!I76 -> 4271 | Q72: ='Statement Q'!J76 -> 1295 | S72: =SUM(N72:Q72) -> 2306
B73: D&A | C73: ='Statement Y'!C77 -> 15908 | D73: ='Statement Y'!D77 -> 21302 | E73: ='Statement Y'!E77 -> 25304 | F73: ='Statement Y'!F77 -> 29487 | G73: ='Statement Y'!G77 -> 27886 | H73: ='Statement Y'!H77 -> 31453 | J73: ='Statement Q'!C77 -> 6673 | K73: ='Statement Q'!D77 -> 7303 | L73: ='Statement Q'!E77 -> 7087 | M73: ='Statement Q'!F77 -> 6823 | N73: ='Statement Q'!G77 -> 6878 | O73: ='Statement Q'!H77 -> 7409 | P73: ='Statement Q'!I77 -> 7478 | Q73: ='Statement Q'!J77 -> 9688 | S73: =SUM(N73:Q73) -> 31453
B74: Stock-based compensation | C74: ='Statement Y'!C78 -> 13489 | D74: ='Statement Y'!D78 -> 36144 | E74: ='Statement Y'!E78 -> 58775 | F74: ='Statement Y'!F78 -> 71613 | G74: ='Statement Y'!G78 -> 66975 | H74: ='Statement Y'!H78 -> 67452 | J74: ='Statement Q'!C78 -> 16840 | K74: ='Statement Q'!D78 -> 16448 | L74: ='Statement Q'!E78 -> 16525 | M74: ='Statement Q'!F78 -> 17162 | N74: ='Statement Q'!G78 -> 17225 | O74: ='Statement Q'!H78 -> 16230 | P74: ='Statement Q'!I78 -> 15959 | Q74: ='Statement Q'!J78 -> 18038 | S74: =SUM(N74:Q74) -> 67452
B75: Amortization of deferred financing | C75: ='Statement Y'!C79 -> 389 | D75: ='Statement Y'!D79 -> 288 | E75: ='Statement Y'!E79 -> 310 | F75: ='Statement Y'!F79 -> 321 | G75: ='Statement Y'!G79 -> 236 | H75: ='Statement Y'!H79 -> 2977 | J75: ='Statement Q'!C79 -> 61 | K75: ='Statement Q'!D79 -> 51 | L75: ='Statement Q'!E79 -> 62 | M75: ='Statement Q'!F79 -> 62 | N75: ='Statement Q'!G79 -> 62 | O75: ='Statement Q'!H79 -> 62 | P75: ='Statement Q'!I79 -> 61 | Q75: ='Statement Q'!J79 -> 2792 | S75: =SUM(N75:Q75) -> 2977
B76: Loss exstinguishment of debt | C76: ='Statement Y'!C80 -> 0 | D76: ='Statement Y'!D80 -> 0 | E76: ='Statement Y'!E80 -> 0 | F76: ='Statement Y'!F80 -> 1118 | G76: ='Statement Y'!G80 -> 0 | H76: ='Statement Y'!H80 -> 501 | J76: ='Statement Q'!C80 -> 0 | K76: ='Statement Q'!D80 -> 0 | L76: ='Statement Q'!E80 -> 0 | M76: ='Statement Q'!F80 -> 0 | N76: ='Statement Q'!G80 -> 0 | O76: ='Statement Q'!H80 -> 0 | P76: ='Statement Q'!I80 -> 0 | Q76: ='Statement Q'!J80 -> 501 | S76: =SUM(N76:Q76) -> 501
B77: Non-cash gain on settlement | C77: ='Statement Y'!C81 -> 0 | D77: ='Statement Y'!D81 -> 0 | E77: ='Statement Y'!E81 -> 0 | F77: ='Statement Y'!F81 -> 0 | G77: ='Statement Y'!G81 -> -2345 | H77: ='Statement Y'!H81 -> 0 | J77: ='Statement Q'!C81 -> 0 | K77: ='Statement Q'!D81 -> 0 | L77: ='Statement Q'!E81 -> 0 | M77: ='Statement Q'!F81 -> -2345 | N77: ='Statement Q'!G81 -> 0 | O77: ='Statement Q'!H81 -> 0 | P77: ='Statement Q'!I81 -> 0 | Q77: ='Statement Q'!J81 -> 0 | S77: =SUM(N77:Q77) -> 0
B78: Cost of Phreesia HW purchased | C78: ='Statement Y'!C82 -> 762 | D78: ='Statement Y'!D82 -> 672 | E78: ='Statement Y'!E82 -> 1598 | F78: ='Statement Y'!F82 -> 1619 | G78: ='Statement Y'!G82 -> 1873 | H78: ='Statement Y'!H82 -> 1022 | J78: ='Statement Q'!C82 -> 343 | K78: ='Statement Q'!D82 -> 334 | L78: ='Statement Q'!E82 -> 571 | M78: ='Statement Q'!F82 -> 625 | N78: ='Statement Q'!G82 -> 436 | O78: ='Statement Q'!H82 -> 157 | P78: ='Statement Q'!I82 -> 235 | Q78: ='Statement Q'!J82 -> 194 | S78: =SUM(N78:Q78) -> 1022
B79: Deferred contract acquisition | C79: ='Statement Y'!C83 -> 2025 | D79: ='Statement Y'!D83 -> 2211 | E79: ='Statement Y'!E83 -> 1696 | F79: ='Statement Y'!F83 -> 1056 | G79: ='Statement Y'!G83 -> 1815 | H79: ='Statement Y'!H83 -> 570 | J79: ='Statement Q'!C83 -> 192 | K79: ='Statement Q'!D83 -> 192 | L79: ='Statement Q'!E83 -> 1322 | M79: ='Statement Q'!F83 -> 109 | N79: ='Statement Q'!G83 -> 110 | O79: ='Statement Q'!H83 -> 242 | P79: ='Statement Q'!I83 -> 111 | Q79: ='Statement Q'!J83 -> 107 | S79: =SUM(N79:Q79) -> 570
B80: Non-cash operating lease | C80: ='Statement Y'!C84 -> 1766 | D80: ='Statement Y'!D84 -> 1004 | E80: ='Statement Y'!E84 -> 1768 | F80: ='Statement Y'!F84 -> 702 | G80: ='Statement Y'!G84 -> 747 | H80: ='Statement Y'!H84 -> 914 | J80: ='Statement Q'!C84 -> 173 | K80: ='Statement Q'!D84 -> 188 | L80: ='Statement Q'!E84 -> 207 | M80: ='Statement Q'!F84 -> 179 | N80: ='Statement Q'!G84 -> 215 | O80: ='Statement Q'!H84 -> 218 | P80: ='Statement Q'!I84 -> 224 | Q80: ='Statement Q'!J84 -> 257 | S80: =SUM(N80:Q80) -> 914
B81: Change fair value contingent liabilities | C81: ='Statement Y'!C85 -> 0 | D81: ='Statement Y'!D85 -> 258 | E81: ='Statement Y'!E85 -> 0 | F81: ='Statement Y'!F85 -> 0 | G81: ='Statement Y'!G85 -> 0 | H81: ='Statement Y'!H85 -> 0 | J81: ='Statement Q'!C85 -> 0 | K81: ='Statement Q'!D85 -> 0 | L81: ='Statement Q'!E85 -> 0 | M81: ='Statement Q'!F85 -> 0 | N81: ='Statement Q'!G85 -> 0 | O81: ='Statement Q'!H85 -> 0 | P81: ='Statement Q'!I85 -> 0 | Q81: ='Statement Q'!J85 -> 0 | S81: =SUM(N81:Q81) -> 0
B82: Deferred taxes | C82: ='Statement Y'!C86 -> -65 | D82: ='Statement Y'!D86 -> 143 | E82: ='Statement Y'!E86 -> 434 | F82: ='Statement Y'!F86 -> 228 | G82: ='Statement Y'!G86 -> 214 | H82: ='Statement Y'!H86 -> -13271 | J82: ='Statement Q'!C86 -> 63 | K82: ='Statement Q'!D86 -> 56 | L82: ='Statement Q'!E86 -> 57 | M82: ='Statement Q'!F86 -> 38 | N82: ='Statement Q'!G86 -> 85 | O82: ='Statement Q'!H86 -> -1583 | P82: ='Statement Q'!I86 -> 57 | Q82: ='Statement Q'!J86 -> -11830 | S82: =SUM(N82:Q82) -> -13271
B83: Unrialized gains/losses fair value option | C83: ='Statement Y'!C87 -> 0 | D83: ='Statement Y'!D87 -> 0 | E83: ='Statement Y'!E87 -> 0 | F83: ='Statement Y'!F87 -> 0 | G83: ='Statement Y'!G87 -> 0 | H83: ='Statement Y'!H87 -> -1020 | J83: ='Statement Q'!C87 -> 0 | K83: ='Statement Q'!D87 -> 0 | L83: ='Statement Q'!E87 -> 0 | M83: ='Statement Q'!F87 -> 0 | N83: ='Statement Q'!G87 -> 0 | O83: ='Statement Q'!H87 -> 0 | P83: ='Statement Q'!I87 -> 0 | Q83: ='Statement Q'!J87 -> -1020
B84: Change NWC | C84: =SUM('Statement Y'!C88:C97) -> -4092 | D84: =SUM('Statement Y'!D88:D97) -> -18571 | E84: =SUM('Statement Y'!E88:E97) -> -3862 | F84: =SUM('Statement Y'!F88:F97) -> -1637 | G84: =SUM('Statement Y'!G88:G97) -> -6493 | H84: =SUM('Statement Y'!H88:H97) -> -14090 | J84: =SUM('Statement Q'!C88:C97) -> -5344 | K84: =SUM('Statement Q'!D88:D97) -> 4501 | L84: =SUM('Statement Q'!E88:E97) -> -5643 | M84: =SUM('Statement Q'!F88:F97) -> -7 | N84: =SUM('Statement Q'!G88:G97) -> -6247 | O84: =SUM('Statement Q'!H88:H97) -> -8554 | P84: =SUM('Statement Q'!I88:I97) -> -12929 | Q84: =SUM('Statement Q'!J88:J97) -> 13640 | S84: =SUM(N84:Q84) -> -14090
B85: Operating cashflow | C85: ='Statement Y'!C98 -> 2890 | D85: ='Statement Y'!D98 -> -74710 | E85: ='Statement Y'!E98 -> -90123 | F85: ='Statement Y'!F98 -> -32378 | G85: ='Statement Y'!G98 -> 32381 | H85: ='Statement Y'!H98 -> 78814 | J85: ='Statement Q'!C98 -> -721 | K85: ='Statement Q'!D98 -> 11061 | L85: ='Statement Q'!E98 -> 5785 | M85: ='Statement Q'!F98 -> 16256 | N85: ='Statement Q'!G98 -> 14850 | O85: ='Statement Q'!H98 -> 14835 | P85: ='Statement Q'!I98 -> 15467 | Q85: ='Statement Q'!J98 -> 33662 | S85: =SUM(N85:Q85) -> 78814
B86: Acquisitions | C86: ='Statement Y'!C99 -> -6510 | D86: ='Statement Y'!D99 -> -34423 | E86: ='Statement Y'!E99 -> 0 | F86: ='Statement Y'!F99 -> -14573 | G86: ='Statement Y'!G99 -> 0 | H86: ='Statement Y'!H99 -> -153191 | J86: ='Statement Q'!C99 -> 0 | K86: ='Statement Q'!D99 -> 0 | L86: ='Statement Q'!E99 -> 0 | M86: ='Statement Q'!F99 -> 0 | N86: ='Statement Q'!G99 -> 0 | O86: ='Statement Q'!H99 -> 0 | P86: ='Statement Q'!I99 -> 0 | Q86: ='Statement Q'!J99 -> -153191 | S86: =SUM(N86:Q86) -> -153191
B87: Capitalized internal use software | C87: ='Statement Y'!C100 -> -7334 | D87: ='Statement Y'!D100 -> -12385 | E87: ='Statement Y'!E100 -> -21471 | F87: ='Statement Y'!F100 -> -19291 | G87: ='Statement Y'!G100 -> -15380 | H87: ='Statement Y'!H100 -> -13296 | J87: ='Statement Q'!C100 -> -4570 | K87: ='Statement Q'!D100 -> -2976 | L87: ='Statement Q'!E100 -> -3566 | M87: ='Statement Q'!F100 -> -4268 | N87: ='Statement Q'!G100 -> -3888 | O87: ='Statement Q'!H100 -> -3435 | P87: ='Statement Q'!I100 -> -3395 | Q87: ='Statement Q'!J100 -> -2578 | S87: =SUM(N87:Q87) -> -13296
B88: CapEx | C88: ='Statement Y'!C101 -> -11241 | D88: ='Statement Y'!D101 -> -18420 | E88: ='Statement Y'!E101 -> -4732 | F88: ='Statement Y'!F101 -> -5806 | G88: ='Statement Y'!G101 -> -8709 | H88: ='Statement Y'!H101 -> -11101 | J88: ='Statement Q'!C101 -> -876 | K88: ='Statement Q'!D101 -> -4427 | L88: ='Statement Q'!E101 -> -616 | M88: ='Statement Q'!F101 -> -2790 | N88: ='Statement Q'!G101 -> -3504 | O88: ='Statement Q'!H101 -> -1767 | P88: ='Statement Q'!I101 -> -3271 | Q88: ='Statement Q'!J101 -> -2559 | S88: =SUM(N88:Q88) -> -11101
B89: Investing cashflow | C89: ='Statement Y'!C103 -> -25085 | D89: ='Statement Y'!D103 -> -65228 | E89: ='Statement Y'!E103 -> -26203 | F89: ='Statement Y'!F103 -> -39670 | G89: ='Statement Y'!G103 -> -24089 | H89: ='Statement Y'!H103 -> -161879 | J89: ='Statement Q'!C103 -> -5446 | K89: ='Statement Q'!D103 -> -7403 | L89: ='Statement Q'!E103 -> -4182 | M89: ='Statement Q'!F103 -> -7058 | N89: ='Statement Q'!G103 -> -7392 | O89: ='Statement Q'!H103 -> -5202 | P89: ='Statement Q'!I103 -> -6666 | Q89: ='Statement Q'!J103 -> -142619 | S89: =SUM(N89:Q89) -> -161879
B90: Issuance common stock | C90: ='Statement Y'!C104 -> 174800 | D90: ='Statement Y'!D104 -> 245813 | E90: ='Statement Y'!E104 -> 1603 | F90: ='Statement Y'!F104 -> 955 | G90: ='Statement Y'!G104 -> 1012 | H90: ='Statement Y'!H104 -> 1454 | J90: ='Statement Q'!C104 -> 0 | K90: ='Statement Q'!D104 -> 0 | L90: ='Statement Q'!E104 -> 0 | M90: ='Statement Q'!F104 -> 0 | N90: ='Statement Q'!G104 -> 0 | O90: ='Statement Q'!H104 -> 0 | P90: ='Statement Q'!I104 -> 0 | Q90: ='Statement Q'!J104 -> 0 | S90: =SUM(N90:Q90) -> 0
B91: Financing cashflow | C91: ='Statement Y'!C121 -> 150661 | D91: ='Statement Y'!D121 -> 234969 | E91: ='Statement Y'!E121 -> -20803 | F91: ='Statement Y'!F121 -> -17115 | G91: ='Statement Y'!G121 -> -11486 | H91: ='Statement Y'!H121 -> 72851 | J91: ='Statement Q'!C121 -> -1825 | K91: ='Statement Q'!D121 -> -1381 | L91: ='Statement Q'!E121 -> -1651 | M91: ='Statement Q'!F121 -> -6629 | N91: ='Statement Q'!G121 -> -838 | O91: ='Statement Q'!H121 -> -2149 | P91: ='Statement Q'!I121 -> -667 | Q91: ='Statement Q'!J121 -> 76505 | S91: =SUM(N91:Q91) -> 72851
B92: Net increase/decrease in cash | C92: ='Statement Y'!C123 -> 128466 | D92: ='Statement Y'!D123 -> 95031 | E92: ='Statement Y'!E123 -> -137129 | F92: ='Statement Y'!F123 -> -89163 | G92: ='Statement Y'!G123 -> -3300 | H92: ='Statement Y'!H123 -> -10390 | J92: ='Statement Q'!C123 -> -7993 | K92: ='Statement Q'!D123 -> 2271 | L92: ='Statement Q'!E123 -> -58 | M92: ='Statement Q'!F123 -> 2480 | N92: ='Statement Q'!G123 -> 6651 | O92: ='Statement Q'!H123 -> 7395 | P92: ='Statement Q'!I123 -> 8105 | Q92: ='Statement Q'!J123 -> -32541 | S92: =SUM(N92:Q92) -> -10390
B93: Begin cash | C93: ='Statement Y'!C124 -> 90315 | D93: ='Statement Y'!D124 -> 218781 | E93: ='Statement Y'!E124 -> 313812 | F93: ='Statement Y'!F124 -> 176683 | G93: ='Statement Y'!G124 -> 87520 | H93: ='Statement Y'!H124 -> 84220 | J93: ='Statement Q'!C124 -> 87520 | K93: ='Statement Q'!D124 -> 79527 | L93: ='Statement Q'!E124 -> 81798 | M93: ='Statement Q'!F124 -> 81740 | N93: ='Statement Q'!G124 -> 84220 | O93: ='Statement Q'!H124 -> 90871 | P93: ='Statement Q'!I124 -> 98266 | Q93: ='Statement Q'!J124 -> 106371 | S93: =N93 -> 84220
B94: End cash | C94: ='Statement Y'!C125 -> 218781 | D94: ='Statement Y'!D125 -> 313812 | E94: ='Statement Y'!E125 -> 176683 | F94: ='Statement Y'!F125 -> 87520 | G94: ='Statement Y'!G125 -> 84220 | H94: ='Statement Y'!H125 -> 73830 | J94: ='Statement Q'!C125 -> 79527 | K94: ='Statement Q'!D125 -> 81798 | L94: ='Statement Q'!E125 -> 81740 | M94: ='Statement Q'!F125 -> 84220 | N94: ='Statement Q'!G125 -> 90871 | O94: ='Statement Q'!H125 -> 98266 | P94: ='Statement Q'!I125 -> 106371 | Q94: ='Statement Q'!J125 -> 73830 | S94: =Q94 -> 73830
B96: DuPont Identity
B97: Profit Margin (Earnings/Revenue) | C97: =C21/C5 -> -0.18356572 | D97: =D21/D5 -> -0.55414031 | E97: =E21/E5 -> -0.62705493 | F97: =F21/F5 -> -0.38418575 | G97: =G21/G5 -> -0.13941207 | H97: =H21/H5 -> 0.0047982588 | S97: =S21/S5 -> 0.0047982588
B98: Asset Turnover (Revenue/Total assets) | C98: =C5/C46 -> 0.4551346 | D98: =D5/D46 -> 0.43123023 | E98: =E5/E46 -> 0.75909927 | F98: =F5/F46 -> 0.96212256 | G98: =G5/G46 -> 1.0808362 | H98: =H5/H46 -> 0.72401061 | S98: =S5/S46 -> 0.72401061
B99: ROA | C99: =C97*C98 -> -0.083547109 | D99: =D97*D98 -> -0.23896205 | E99: =E97*E98 -> -0.47599694 | F99: =F97*F98 -> -0.36963378 | G99: =G97*G98 -> -0.15068162 | H99: =H97*H98 -> 0.0034739903 | S99: =S97*S98 -> 0.0034739903
B100: Equity Multiplier (Total assets/Equity) | C100: =C46/C68 -> 1.2406326 | D100: =D46/D68 -> 1.1849981 | E100: =E46/E68 -> 1.2857282 | F100: =F46/F68 -> 1.4727678 | G100: =G46/G68 -> 1.4667797 | H100: =H46/H68 -> 1.9684941 | S100: =S46/S68 -> 1.9684941
B101: ROE | C101: =C99*C100 -> -0.10365127 | D101: =D99*D100 -> -0.28316957 | E101: =E99*E100 -> -0.61200268 | F101: =F99*F100 -> -0.54438475 | G101: =G99*G100 -> -0.22101674 | H101: =H99*H100 -> 0.0068385294 | S101: =S99*S100 -> 0.0068385294
B103: Growth rates
B104: Revenue | D104: =(D5-C5)/C5 -> 0.434203 | E104: =(E5-D5)/D5 -> 0.31738521 | F104: =(F5-E5)/E5 -> 0.26837421 | G104: =(G5-F5)/F5 -> 0.17826039 | H104: =(H5-G5)/G5 -> 0.14477398 | K104: =(K5-J5)/J5 -> 0.0088720274 | L104: =(L5-K5)/K5 -> 0.045879645 | M104: =(M5-L5)/L5 -> 0.026975655 | N104: =(N5-M5)/M5 -> 0.057029021 | O104: =(O5-N5)/N5 -> 0.011376967 | P104: =(P5-O5)/O5 -> 0.02625048 | Q104: =(Q5-P5)/P5 -> 0.055961374
B105: COGS | D105: =(D6-C6)/C6 -> 0.5536212 | E105: =(E6-D6)/D6 -> 0.34254436 | F105: =(F6-E6)/E6 -> 0.13493552 | G105: =(G6-F6)/F6 -> 0.088080896 | H105: =(H6-G6)/G6 -> 0.14221027 | K105: =(K6-J6)/J6 -> -0.035537919 | L105: =(L6-K6)/K6 -> 0.05260431 | M105: =(M6-L6)/L6 -> -0.028114775 | N105: =(N6-M6)/M6 -> 0.13403444 | O105: =(O6-N6)/N6 -> -0.011138841 | P105: =(P6-O6)/O6 -> 0.010254775 | Q105: =(Q6-P6)/P6 -> 0.062140058
B106: Gross Profit | D106: =IF(C7=0, IF(D7=0,0,IF(D7>0,1,-1)), (D7-C7)/ABS(C7) ) -> 0.36923492 | E106: =IF(D7=0, IF(E7=0,0,IF(E7>0,1,-1)), (E7-D7)/ABS(D7) ) -> 0.30185445 | F106: =IF(E7=0, IF(F7=0,0,IF(F7>0,1,-1)), (F7-E7)/ABS(E7) ) -> 0.35332055 | G106: =IF(F7=0, IF(G7=0,0,IF(G7>0,1,-1)), (G7-F7)/ABS(F7) ) -> 0.22640429 | H106: =IF(G7=0, IF(H7=0,0,IF(H7>0,1,-1)), (H7-G7)/ABS(G7) ) -> 0.1459883 | K106: =IF(J7=0, IF(K7=0,0,IF(K7>0,1,-1)), (K7-J7)/ABS(J7) ) -> 0.031355566 | L106: =IF(K7=0, IF(L7=0,0,IF(L7>0,1,-1)), (L7-K7)/ABS(K7) ) -> 0.042695948 | M106: =IF(L7=0, IF(M7=0,0,IF(M7>0,1,-1)), (M7-L7)/ABS(L7) ) -> 0.053305288 | N106: =IF(M7=0, IF(N7=0,0,IF(N7>0,1,-1)), (N7-M7)/ABS(M7) ) -> 0.023070354 | O106: =IF(N7=0, IF(O7=0,0,IF(O7>0,1,-1)), (O7-N7)/ABS(N7) ) -> 0.022383172 | P106: =IF(O7=0, IF(P7=0,0,IF(P7>0,1,-1)), (P7-O7)/ABS(O7) ) -> 0.033813148 | Q106: =IF(P7=0, IF(Q7=0,0,IF(Q7>0,1,-1)), (Q7-P7)/ABS(P7) ) -> 0.053106699
B107: OpEx | D107: =IF(C13=0, IF(D13=0,0,IF(D13>0,1,-1)), (D13-C13)/ABS(C13) ) -> 1.0388482 | E107: =IF(D13=0, IF(E13=0,0,IF(E13>0,1,-1)), (E13-D13)/ABS(D13) ) -> 0.40027427 | F107: =IF(E13=0, IF(F13=0,0,IF(F13>0,1,-1)), (F13-E13)/ABS(E13) ) -> 0.059081836 | G107: =IF(F13=0, IF(G13=0,0,IF(G13>0,1,-1)), (G13-F13)/ABS(F13) ) -> -0.069938471 | H107: =IF(G13=0, IF(H13=0,0,IF(H13>0,1,-1)), (H13-G13)/ABS(G13) ) -> -0.028853331 | K107: =IF(J13=0, IF(K13=0,0,IF(K13>0,1,-1)), (K13-J13)/ABS(J13) ) -> -0.0010506021 | L107: =IF(K13=0, IF(L13=0,0,IF(L13>0,1,-1)), (L13-K13)/ABS(K13) ) -> -0.0048540323 | M107: =IF(L13=0, IF(M13=0,0,IF(M13>0,1,-1)), (M13-L13)/ABS(L13) ) -> -0.027628737 | N107: =IF(M13=0, IF(N13=0,0,IF(N13>0,1,-1)), (N13-M13)/ABS(M13) ) -> -0.030683053 | O107: =IF(N13=0, IF(O13=0,0,IF(O13>0,1,-1)), (O13-N13)/ABS(N13) ) -> -0.00045590084 | P107: =IF(O13=0, IF(P13=0,0,IF(P13>0,1,-1)), (P13-O13)/ABS(O13) ) -> -0.031483833 | Q107: =IF(P13=0, IF(Q13=0,0,IF(Q13>0,1,-1)), (Q13-P13)/ABS(P13) ) -> 0.17395344
B108: Operating income | D108: =IF(C14=0, IF(D14=0,0,IF(D14>0,1,-1)), (D14-C14)/ABS(C14) ) -> -3.5505434 | E108: =IF(D14=0, IF(E14=0,0,IF(E14>0,1,-1)), (E14-D14)/ABS(D14) ) -> -0.51135537 | F108: =IF(E14=0, IF(F14=0,0,IF(F14>0,1,-1)), (F14-E14)/ABS(E14) ) -> 0.22697562 | G108: =IF(F14=0, IF(G14=0,0,IF(G14>0,1,-1)), (G14-F14)/ABS(F14) ) -> 0.57431546 | H108: =IF(G14=0, IF(H14=0,0,IF(H14>0,1,-1)), (H14-G14)/ABS(G14) ) -> 0.88619034 | K108: =IF(J14=0, IF(K14=0,0,IF(K14>0,1,-1)), (K14-J14)/ABS(J14) ) -> 0.11318229 | L108: =IF(K14=0, IF(L14=0,0,IF(L14>0,1,-1)), (L14-K14)/ABS(K14) ) -> 0.19620253 | M108: =IF(L14=0, IF(M14=0,0,IF(M14>0,1,-1)), (M14-L14)/ABS(L14) ) -> 0.45011919 | N108: =IF(M14=0, IF(N14=0,0,IF(N14>0,1,-1)), (N14-M14)/ABS(M14) ) -> 0.56818182 | O108: =IF(N14=0, IF(O14=0,0,IF(O14>0,1,-1)), (O14-N14)/ABS(N14) ) -> 0.54152723 | P108: =IF(O14=0, IF(P14=0,0,IF(P14>0,1,-1)), (P14-O14)/ABS(O14) ) -> 3.4810883 | Q108: =IF(P14=0, IF(Q14=0,0,IF(Q14>0,1,-1)), (Q14-P14)/ABS(P14) ) -> -2.4862263
B109: Income before taxes | D109: =IF(C19=0, IF(D19=0,0,IF(D19>0,1,-1)), (D19-C19)/ABS(C19) ) -> -3.330617 | E109: =IF(D19=0, IF(E19=0,0,IF(E19>0,1,-1)), (E19-D19)/ABS(D19) ) -> -0.48893447 | F109: =IF(E19=0, IF(F19=0,0,IF(F19>0,1,-1)), (F19-E19)/ABS(E19) ) -> 0.2295361 | G109: =IF(F19=0, IF(G19=0,0,IF(G19>0,1,-1)), (G19-F19)/ABS(F19) ) -> 0.58762986 | H109: =IF(G19=0, IF(H19=0,0,IF(H19>0,1,-1)), (H19-G19)/ABS(G19) ) -> 0.83981652 | K109: =IF(J19=0, IF(K19=0,0,IF(K19>0,1,-1)), (K19-J19)/ABS(J19) ) -> 0.10149906 | L109: =IF(K19=0, IF(L19=0,0,IF(L19>0,1,-1)), (L19-K19)/ABS(K19) ) -> 0.19122929 | M109: =IF(L19=0, IF(M19=0,0,IF(M19>0,1,-1)), (M19-L19)/ABS(L19) ) -> 0.6149273 | N109: =IF(M19=0, IF(N19=0,0,IF(N19>0,1,-1)), (N19-M19)/ABS(M19) ) -> 0.40866815 | O109: =IF(N19=0, IF(O19=0,0,IF(O19>0,1,-1)), (O19-N19)/ABS(N19) ) -> 0.82290028 | P109: =IF(O19=0, IF(P19=0,0,IF(P19>0,1,-1)), (P19-O19)/ABS(O19) ) -> 10.10302 | Q109: =IF(P19=0, IF(Q19=0,0,IF(Q19>0,1,-1)), (Q19-P19)/ABS(P19) ) -> -3.0142439
B110: Net income | D110: =IF(C21=0, IF(D21=0,0,IF(D21>0,1,-1)), (D21-C21)/ABS(C21) ) -> -3.3295105 | E110: =IF(D21=0, IF(E21=0,0,IF(E21>0,1,-1)), (E21-D21)/ABS(D21) ) -> -0.49072875 | F110: =IF(E21=0, IF(F21=0,0,IF(F21>0,1,-1)), (F21-E21)/ABS(E21) ) -> 0.22288897 | G110: =IF(F21=0, IF(G21=0,0,IF(G21>0,1,-1)), (G21-F21)/ABS(F21) ) -> 0.57243672 | H110: =IF(G21=0, IF(H21=0,0,IF(H21>0,1,-1)), (H21-G21)/ABS(G21) ) -> 1.0394006 | K110: =IF(J21=0, IF(K21=0,0,IF(K21>0,1,-1)), (K21-J21)/ABS(J21) ) -> 0.086705202 | L110: =IF(K21=0, IF(L21=0,0,IF(L21>0,1,-1)), (L21-K21)/ABS(K21) ) -> 0.20036642 | M110: =IF(L21=0, IF(M21=0,0,IF(M21>0,1,-1)), (M21-L21)/ABS(L21) ) -> 0.55634243 | N110: =IF(M21=0, IF(N21=0,0,IF(N21>0,1,-1)), (N21-M21)/ABS(M21) ) -> 0.38748044 | O110: =IF(N21=0, IF(O21=0,0,IF(O21>0,1,-1)), (O21-N21)/ABS(N21) ) -> 1.1670925 | P110: =IF(O21=0, IF(P21=0,0,IF(P21>0,1,-1)), (P21-O21)/ABS(O21) ) -> 5.530581 | Q110: =IF(P21=0, IF(Q21=0,0,IF(Q21>0,1,-1)), (Q21-P21)/ABS(P21) ) -> -0.69679232
B111: Diluted Shares outstanding avg | D111: =(D22-C22)/C22 -> 0.26234818 | E111: =(E22-D22)/D22 -> 0.051154586 | F111: =(F22-E22)/E22 -> 0.040446224 | G111: =(G22-F22)/F22 -> 0.055515845 | H111: =(H22-G22)/G22 -> 0.067806911 | K111: =(K22-J22)/J22 -> 0.014770762 | L111: =(L22-K22)/K22 -> 0.0067648644 | M111: =(M22-L22)/L22 -> 0.0066675879 | N111: =(N22-M22)/M22 -> 0.011033323 | O111: =(O22-N22)/N22 -> 0.046927242 | P111: =(P22-O22)/O22 -> -0.0020426029 | Q111: =(Q22-P22)/P22 -> -0.0010233918
B112: Diluted EPS | D112: =IF(C23=0, IF(D23=0,0,IF(D23>0,1,-1)), (D23-C23)/ABS(C23) ) -> -2.4347826 | E112: =IF(D23=0, IF(E23=0,0,IF(E23>0,1,-1)), (E23-D23)/ABS(D23) ) -> -0.41772152 | F112: =IF(E23=0, IF(F23=0,0,IF(F23>0,1,-1)), (F23-E23)/ABS(E23) ) -> 0.25297619 | G112: =IF(F23=0, IF(G23=0,0,IF(G23>0,1,-1)), (G23-F23)/ABS(F23) ) -> 0.5936255 | H112: =IF(G23=0, IF(H23=0,0,IF(H23>0,1,-1)), (H23-G23)/ABS(G23) ) -> 1.0392157 | K112: =IF(J23=0, IF(K23=0,0,IF(K23>0,1,-1)), (K23-J23)/ABS(J23) ) -> 0.11428571 | L112: =IF(K23=0, IF(L23=0,0,IF(L23>0,1,-1)), (L23-K23)/ABS(K23) ) -> 0.19354839 | M112: =IF(L23=0, IF(M23=0,0,IF(M23>0,1,-1)), (M23-L23)/ABS(L23) ) -> 0.56 | N112: =IF(M23=0, IF(N23=0,0,IF(N23>0,1,-1)), (N23-M23)/ABS(M23) ) -> 0.36363636 | O112: =IF(N23=0, IF(O23=0,0,IF(O23>0,1,-1)), (O23-N23)/ABS(N23) ) -> 1.1428571 | P112: =IF(O23=0, IF(P23=0,0,IF(P23>0,1,-1)), (P23-O23)/ABS(O23) ) -> 6 | Q112: =IF(P23=0, IF(Q23=0,0,IF(Q23>0,1,-1)), (Q23-P23)/ABS(P23) ) -> -0.71428571
B114: Margins
B115: Gross margin | C115: =C7/C5 -> 0.64765229 | D115: =D7/D5 -> 0.61831424 | E115: =E7/E5 -> 0.61102488 | F115: =F7/F5 -> 0.65194682 | G115: =G7/G5 -> 0.67858547 | H115: =H7/H5 -> 0.67930527 | J115: =J7/J5 -> 0.66389045 | K115: =K7/K5 -> 0.6786858 | L115: =L7/L5 -> 0.67661985 | M115: =M7/M5 -> 0.69396705 | N115: =N7/N5 -> 0.6716723 | O115: =O7/O5 -> 0.67898171 | P115: =P7/P5 -> 0.68398527 | Q115: =Q7/Q5 -> 0.6821362 | S115: =S7/S5 -> 0.67930527
B116: Operating margin | C116: =C14/C5 -> -0.17266289 | D116: =D14/D5 -> -0.54783734 | E116: =E14/E5 -> -0.62850023 | F116: =F14/F5 -> -0.38304626 | G116: =G14/G5 -> -0.13838781 | H116: =H14/H5 -> -0.01375806 | J116: =J14/J5 -> -0.191865 | K116: =K14/K5 -> -0.16865299 | L116: =L14/L5 -> -0.1296161 | M116: =M14/M5 -> -0.069401264 | N116: =N14/N5 -> -0.028351849 | O116: =O14/O5 -> -0.01285233 | P116: =P14/P5 -> 0.031072108 | Q116: =Q14/Q5 -> -0.043732834 | S116: =S14/S5 -> -0.01375806
B117: Net margin | C117: =C21/C5 -> -0.18356572 | D117: =D21/D5 -> -0.55414031 | E117: =E21/E5 -> -0.62705493 | F117: =F21/F5 -> -0.38418575 | G117: =G21/G5 -> -0.13941207 | H117: =H21/H5 -> 0.0047982588 | J117: =J21/J5 -> -0.19484869 | K117: =K21/K5 -> -0.17638936 | L117: =L21/L5 -> -0.13485955 | M117: =M21/M5 -> -0.058259863 | N117: =N21/N5 -> -0.033760006 | O117: =O21/O5 -> 0.0055775873 | P117: =P21/P5 -> 0.035493173 | Q117: =Q21/Q5 -> 0.010191474 | S117: =S21/S5 -> 0.0047982588

Sheet Forecast ->
B13: Forecast ->

Sheet Revenue
B1: Revenue forecast
C2: History | H2: Forecast | S2: History | AA2: Forecast | AE2: TTM
C4: Revenues | S4: Revenues | AE4: Q2-Q3-Q4
B5: Revenues (million) | C5: ='Statement Y'!D3 -> 2022 | D5: ='Statement Y'!E3 -> 2023 | E5: ='Statement Y'!F3 -> 2024 | F5: ='Statement Y'!G3 -> 2025 | G5: ='Statement Y'!H3 -> 2026 | H5: =G5+1 -> 2027 | I5: =H5+1 -> 2028 | J5: =I5+1 -> 2029 | K5: =J5+1 -> 2030 | L5: =K5+1 -> 2031 | R5: Revenues (thousand) | S5: ='Statement Q'!C3 -> Q1 2025 | T5: ='Statement Q'!D3 -> Q2 2025 | U5: ='Statement Q'!E3 -> Q3 2025 | V5: ='Statement Q'!F3 -> Q4 2025 | W5: ='Statement Q'!G3 -> Q1 2026 | X5: ='Statement Q'!H3 -> Q2 2026 | Y5: ='Statement Q'!I3 -> Q3 2026 | Z5: ='Statement Q'!J3 -> Q4 2026 | AA5: FQ1 | AB5: FQ2 | AC5: FQ3 | AE5: FQ1
B6: ='Statement Y'!B182 -> Subscription and related services | C6: ='Statement Y'!D182 -> 95514 | D6: ='Statement Y'!E182 -> 128975 | E6: ='Statement Y'!F182 -> 165436 | F6: ='Statement Y'!G182 -> 196510 | G6: ='Statement Y'!H182 -> 219461 | H6: =H24*H26 -> 236161.98 | I6: =I24*I26 -> 255285.2 | J6: =J24*J26 -> 274214.6 | K6: =K24*K26 -> 304652.42 | L6: =L24*L26 -> 346328.87 | N6: AHSC * avg sub revenue per AHSC | Q6: AHSC * avg sub revenue per AHSC | R6: ='Statement Q'!B172 -> Subscription and related services | S6: ='Statement Q'!C172 -> 46742 | T6: ='Statement Q'!D172 -> 48612 | U6: ='Statement Q'!E172 -> 49363 | V6: ='Statement Q'!F172 -> 51793 | W6: ='Statement Q'!G172 -> 54355 | X6: ='Statement Q'!H172 -> 53702 | Y6: ='Statement Q'!I172 -> 55480 | Z6: ='Statement Q'!J172 -> 55924 | AA6: =AA24*AA26 -> 57025.703 | AE6: =SUM(X6:AA6) -> 222131.7
B7: ='Statement Y'!B183 -> Payment solutions | C7: ='Statement Y'!D183 -> 65201 | D7: ='Statement Y'!E183 -> 78368 | E7: ='Statement Y'!F183 -> 94610 | F7: ='Statement Y'!G183 -> 101740 | G7: ='Statement Y'!H183 -> 121459 | H7: =H20*H22*H23 -> 132935.44 | I7: =I20*I22*I23 -> 139763.93 | J7: =J20*J22*J23 -> 148905.4 | K7: =K20*K22*K23 -> 159800.92 | L7: =L20*L22*L23 -> 171621.91 | N7: pacient payment volume * facilitator * take rate | Q7: pacient payment volume * facilitator * take rate | R7: ='Statement Q'!B173 -> Payment solutions | S7: ='Statement Q'!C173 -> 27060 | T7: ='Statement Q'!D173 -> 25300 | U7: ='Statement Q'!E173 -> 24704 | V7: ='Statement Q'!F173 -> 24676 | W7: ='Statement Q'!G173 -> 29925 | X7: ='Statement Q'!H173 -> 28392 | Y7: ='Statement Q'!I173 -> 27422 | Z7: ='Statement Q'!J173 -> 35720 | AA7: =AA20*AA22*AA23 -> 44008.92 | AE7: =SUM(X7:AA7) -> 135542.92
B8: ='Statement Y'!B184 -> Network solutions | C8: ='Statement Y'!D184 -> 52518 | D8: ='Statement Y'!E184 -> 73567 | E8: ='Statement Y'!F184 -> 96253 | F8: ='Statement Y'!G184 -> 121563 | G8: ='Statement Y'!H184 -> 139671 | H8: =H28*H32 -> 142906.53 | I8: =I28*I32 -> 149029.79 | J8: =J28*J32 -> 168084.37 | K8: =K28*K32 -> 205674.75 | L8: =L28*L32 -> 268479.6 | N8: annual patient visits * revenue per visit | Q8: network solutions per AHSC * AHSC | R8: ='Statement Q'!B174 -> Network solutions | S8: ='Statement Q'!C174 -> 27415 | T8: ='Statement Q'!D174 -> 28203 | U8: ='Statement Q'!E174 -> 32733 | V8: ='Statement Q'!F174 -> 33212 | W8: ='Statement Q'!G174 -> 31656 | X8: ='Statement Q'!H174 -> 35161 | Y8: ='Statement Q'!I174 -> 37431 | Z8: ='Statement Q'!J174 -> 35423 | AA8: =AA24*AA28 -> 35391.119 | AE8: =SUM(X8:AA8) -> 143406.12
B9: Total | C9: ='Statement Y'!D5 -> 213233 | D9: ='Statement Y'!E5 -> 280910 | E9: ='Statement Y'!F5 -> 356299 | F9: ='Statement Y'!G5 -> 419813 | G9: ='Statement Y'!H5 -> 480591 | H9: =SUM(H6:H8) -> 512003.95 | I9: =SUM(I6:I8) -> 544078.91 | J9: =SUM(J6:J8) -> 591204.37 | K9: =SUM(K6:K8) -> 670128.09 | L9: =SUM(L6:L8) -> 786430.37 | N9: annual patient visits = ahsc * visit per ahsc | R9: Total | S9: ='Statement Q'!C5 -> 101217 | T9: ='Statement Q'!D5 -> 102115 | U9: ='Statement Q'!E5 -> 106800 | V9: ='Statement Q'!F5 -> 109681 | W9: ='Statement Q'!G5 -> 115936 | X9: ='Statement Q'!H5 -> 117255 | Y9: ='Statement Q'!I5 -> 120333 | Z9: ='Statement Q'!J5 -> 127067 | AA9: =SUM(AA6:AA8) -> 136425.74 | AE9: =SUM(X9:AA9) -> 501080.74
C11: Growth rates | S11: Growth rates
B12: Revenue growth % | C12: =C5 -> 2022 | D12: =D5 -> 2023 | E12: =E5 -> 2024 | F12: =F5 -> 2025 | G12: =G5 -> 2026 | H12: =H5 -> 2027 | I12: =I5 -> 2028 | J12: =J5 -> 2029 | ... L12: =L5 -> 2031 | R12: Revenue growth % | S12: =S5 -> Q1 2025 | T12: =T5 -> Q2 2025 | U12: =U5 -> Q3 2025 | V12: =V5 -> Q4 2025 | W12: =W5 -> Q1 2026 | X12: =X5 -> Q2 2026 | Y12: =Y5 -> Q3 2026 | Z12: =Z5 -> Q4 2026 | ... AC12: =AC5 -> FQ3
B13: =B6 -> Subscription and related services | D13: =D6/C6-1 -> 0.35032561 | E13: =E6/D6-1 -> 0.2826982 | F13: =F6/E6-1 -> 0.18783094 | G13: =G6/F6-1 -> 0.11679304 | H13: =H6/G6-1 -> 0.0761 | I13: =I6/H6-1 -> 0.080975 | J13: =J6/I6-1 -> 0.07415 | K13: =K6/J6-1 -> 0.111 | L13: =L6/K6-1 -> 0.1368 | R13: =R6 -> Subscription and related services | T13: =T6/S6-1 -> 0.040006846 | U13: =U6/T6-1 -> 0.01544886 | V13: =V6/U6-1 -> 0.049227154 | W13: =W6/V6-1 -> 0.049466144 | X13: =X6/W6-1 -> -0.012013614 | Y13: =Y6/X6-1 -> 0.033108637 | Z13: =Z6/Y6-1 -> 0.0080028839 | AA13: =AA6/Z6-1 -> 0.0197
B14: =B7 -> Payment solutions | D14: =D7/C7-1 -> 0.20194476 | E14: =E7/D7-1 -> 0.20725296 | F14: =F7/E7-1 -> 0.075362012 | G14: =G7/F7-1 -> 0.19381757 | H14: =H7/G7-1 -> 0.094488181 | I14: =I7/H7-1 -> 0.051366935 | J14: =J7/I7-1 -> 0.065406556 | K14: =K7/J7-1 -> 0.073170732 | L14: =L7/K7-1 -> 0.073973214 | R14: =R7 -> Payment solutions | T14: =T7/S7-1 -> -0.06504065 | U14: =U7/T7-1 -> -0.023557312 | V14: =V7/U7-1 -> -0.0011334197 | W14: =W7/V7-1 -> 0.21271681 | X14: =X7/W7-1 -> -0.05122807 | Y14: =Y7/X7-1 -> -0.034164553 | Z14: =Z7/Y7-1 -> 0.30260375 | AA14: =AA7/Z7-1 -> 0.23205263
B15: =B8 -> Network solutions | D15: =D8/C8-1 -> 0.40079592 | E15: =E8/D8-1 -> 0.30837196 | F15: =F8/E8-1 -> 0.26295284 | G15: =G8/F8-1 -> 0.1489598 | H15: =H8/G8-1 -> 0.023165375 | I15: =I8/H8-1 -> 0.042848 | J15: =J8/I8-1 -> 0.1278575 | K15: =K8/J8-1 -> 0.22364 | L15: =L8/K8-1 -> 0.30536 | R15: =R8 -> Network solutions | T15: =T8/S8-1 -> 0.028743389 | U15: =U8/T8-1 -> 0.16062121 | V15: =V8/U8-1 -> 0.01463355 | W15: =W8/V8-1 -> -0.046850536 | X15: =X8/W8-1 -> 0.11072151 | Y15: =Y8/X8-1 -> 0.064560166 | Z15: =Z8/Y8-1 -> -0.053645374 | AA15: =AA8/Z8-1 -> -0.0009
B16: Total | D16: =D9/C9-1 -> 0.31738521 | E16: =E9/D9-1 -> 0.26837421 | F16: =F9/E9-1 -> 0.17826039 | G16: =G9/F9-1 -> 0.14477398 | H16: =H9/G9-1 -> 0.065363174 | I16: =I9/H9-1 -> 0.062645926 | J16: =J9/I9-1 -> 0.086615102 | K16: =K9/J9-1 -> 0.13349652 | L16: =L9/K9-1 -> 0.17355231 | R16: Total | T16: =T9/S9-1 -> 0.0088720274 | U16: =U9/T9-1 -> 0.045879645 | V16: =V9/U9-1 -> 0.026975655 | W16: =W9/V9-1 -> 0.057029021 | X16: =X9/W9-1 -> 0.011376967 | Y16: =Y9/X9-1 -> 0.02625048 | Z16: =Z9/Y9-1 -> 0.055961374 | AA16: =AA9/Z9-1 -> 0.073652027
C18: Revenue drivers | S18: Growth rates
C19: =C12 -> 2022 | D19: =D12 -> 2023 | E19: =E12 -> 2024 | F19: =F12 -> 2025 | G19: =G12 -> 2026 | H19: =H12 -> 2027 | I19: =I12 -> 2028 | J19: =J12 -> 2029 | ... L19: =L12 -> 2031 | S19: =S12 -> Q1 2025 | T19: =T12 -> Q2 2025 | U19: =U12 -> Q3 2025 | V19: =V12 -> Q4 2025 | W19: =W12 -> Q1 2026 | X19: =X12 -> Q2 2026 | Y19: =Y12 -> Q3 2026 | Z19: =Z12 -> Q4 2026 | ... AC19: =AC12 -> FQ3
B20: ='Statement Y'!B175 -> Patient payment volume | C20: ='Statement Y'!D175 -> 2768000 | D20: ='Statement Y'!E175 -> 3284000 | E20: ='Statement Y'!F175 -> 3947000 | F20: ='Statement Y'!G175 -> 4420000 | G20: ='Statement Y'!H175 -> 4873000 | H20: =G20*(1+H21) -> 5360300 | I20: =H20*(1+I21) -> 5949933 | J20: =I20*(1+J21) -> 6485427 | K20: =J20*(1+K21) -> 7133969.7 | L20: =K20*(1+L21) -> 7847366.6 | R20: ='Statement Q'!B165 -> Patient payment volume | S20: ='Statement Q'!C165 -> 1166000 | T20: ='Statement Q'!D165 -> 1093000 | U20: ='Statement Q'!E165 -> 1081000 | V20: ='Statement Q'!F165 -> 1080000 | W20: ='Statement Q'!G165 -> 1314000 | X20: ='Statement Q'!H165 -> 1250000 | Y20: ='Statement Q'!I165 -> 1181000 | Z20: ='Statement Q'!J165 -> 1128000 | AA20: =Z20*(1+AA21) -> 1150560 | AE20: =SUM(X20:AA20) -> 4709560
B21: Patient payment volume growth | D21: =(D20-C20)/C20 -> 0.18641618 | E21: =(E20-D20)/D20 -> 0.20188794 | F21: =(F20-E20)/E20 -> 0.11983785 | G21: =(G20-F20)/F20 -> 0.10248869 | H21: 0.1 | I21: 0.11 | J21: 0.09 | K21: 0.1 | L21: 0.1 | R21: Patient payment volume growth | T21: =(T20-S20)/S20 -> -0.062607204 | U21: =(U20-T20)/T20 -> -0.010978957 | V21: =(V20-U20)/U20 -> -0.00092506938 | W21: =(W20-V20)/V20 -> 0.21666667 | X21: =(X20-W20)/W20 -> -0.04870624 | Y21: =(Y20-X20)/X20 -> -0.0552 | Z21: =(Z20-Y20)/Y20 -> -0.044877223 | AA21: 0.02
B22: ='Statement Y'!B176 -> Payment facilitator volume | C22: ='Statement Y'!D176 -> 0.79 | D22: ='Statement Y'!E176 -> 0.8 | E22: ='Statement Y'!F176 -> 0.82 | F22: ='Statement Y'!G176 -> 0.81 | G22: ='Statement Y'!H176 -> 0.83 | H22: 0.8 | I22: 0.81 | J22: 0.82 | K22: 0.8 | L22: 0.81 | R22: ='Statement Q'!B166 -> Payment facilitator volume | S22: ='Statement Q'!C166 -> 0.81 | T22: ='Statement Q'!D166 -> 0.81 | U22: ='Statement Q'!E166 -> 0.81 | V22: ='Statement Q'!F166 -> 0.82 | W22: ='Statement Q'!G166 -> 0.82 | X22: ='Statement Q'!H166 -> 0.82 | Y22: ='Statement Q'!I166 -> 0.85 | Z22: ='Statement Q'!J166 -> 0.84 | AA22: 0.85
B23: ='Statement Y'!B177 -> Take rate | C23: ='Statement Y'!D177 -> 0.0298 | D23: ='Statement Y'!E177 -> 0.0298 | E23: ='Statement Y'!F177 -> 0.0292 | F23: ='Statement Y'!G177 -> 0.0283 | G23: ='Statement Y'!H177 -> 0.030029991 | H23: 0.031 | I23: 0.029 | J23: 0.028 | K23: 0.028 | L23: 0.027 | R23: ='Statement Q'!B167 -> Take rate | S23: ='Statement Q'!C167 -> 0.029 | T23: ='Statement Q'!D167 -> 0.029 | U23: ='Statement Q'!E167 -> 0.028 | V23: ='Statement Q'!F167 -> 0.028 | W23: ='Statement Q'!G167 -> 0.028 | X23: ='Statement Q'!H167 -> 0.028 | Y23: ='Statement Q'!I167 -> 0.027 | Z23: ='Statement Q'!J167 -> 0.037698413 | AA23: 0.045
B24: ='Statement Y'!B173 -> AHSC | C24: ='Statement Y'!D173 -> 2074 | D24: ='Statement Y'!E173 -> 2856 | E24: ='Statement Y'!F173 -> 3601 | F24: ='Statement Y'!G173 -> 4203 | G24: ='Statement Y'!H173 -> 4514 | H24: =G24*(1+H25) -> 4762.27 | I24: =H24*(1+I25) -> 5071.8175 | J24: =I24*(1+J25) -> 5502.922 | K24: =J24*(1+K25) -> 6053.2142 | L24: =K24*(1+L25) -> 6779.6 | R24: ='Statement Q'!B163 -> AHSC | S24: ='Statement Q'!C163 -> 4065 | T24: ='Statement Q'!D163 -> 4169 | U24: ='Statement Q'!E163 -> 4237 | V24: ='Statement Q'!F163 -> 4341 | W24: ='Statement Q'!G163 -> 4411 | X24: ='Statement Q'!H163 -> 4467 | Y24: ='Statement Q'!I163 -> 4520 | Z24: ='Statement Q'!J163 -> 4658 | AA24: =Z24*(1+AA25) -> 4797.74 | AE24: =AVERAGE(X24:AA24) -> 4610.685
B25: AHSC Growth | D25: =(D24-C24)/C24 -> 0.37704918 | E25: =(E24-D24)/D24 -> 0.26085434 | F25: =(F24-E24)/E24 -> 0.16717578 | G25: =(G24-F24)/F24 -> 0.073994766 | H25: 0.055 | I25: 0.065 | J25: 0.085 | K25: 0.1 | L25: 0.12 | R25: AHSC Growth | T25: =(T24-S24)/S24 -> 0.025584256 | U25: =(U24-T24)/T24 -> 0.016310866 | V25: =(V24-U24)/U24 -> 0.024545669 | W25: =(W24-V24)/V24 -> 0.016125317 | X25: =(X24-W24)/W24 -> 0.012695534 | Y25: =(Y24-X24)/X24 -> 0.011864786 | Z25: =(Z24-Y24)/Y24 -> 0.030530973 | AA25: 0.03
B26: ='Statement Y'!B174 -> Avg subscription revenue per AHSC | C26: ='Statement Y'!D174 -> 46.053038 | D26: ='Statement Y'!E174 -> 45.159314 | E26: ='Statement Y'!F174 -> 45.941683 | F26: ='Statement Y'!G174 -> 46.754699 | G26: ='Statement Y'!H174 -> 48.617856 | H26: =G26*(1+H27) -> 49.590213 | I26: =H26*(1+I27) -> 50.334066 | J26: =I26*(1+J27) -> 49.830725 | K26: =J26*(1+K27) -> 50.329032 | L26: =K26*(1+L27) -> 51.083968 | R26: ='Statement Q'!B164 -> Avg subscription revenue per AHSC | S26: ='Statement Q'!C164 -> 11.498647 | T26: ='Statement Q'!D164 -> 11.66035 | U26: ='Statement Q'!E164 -> 11.65046 | V26: ='Statement Q'!F164 -> 11.931122 | W26: ='Statement Q'!G164 -> 12.322603 | X26: ='Statement Q'!H164 -> 12.021939 | Y26: ='Statement Q'!I164 -> 12.274336 | Z26: ='Statement Q'!J164 -> 12.006011 | AA26: =Z26*(1+AA27) -> 11.885951 | AE26: =SUM(X26:AA26) -> 48.188237
B27: Avg revenue AHSC growth | D27: =(D26-C26)/C26 -> -0.019406405 | E27: =(E26-D26)/D26 -> 0.017324646 | F27: =(F26-E26)/E26 -> 0.0176967 | G27: =(G26-F26)/F26 -> 0.03984961 | H27: 0.02 | I27: 0.015 | J27: -0.01 | K27: 0.01 | L27: 0.015 | R27: Avg revenue AHSC growth | T27: =(T26-S26)/S26 -> 0.014062804 | U27: =(U26-T26)/T26 -> -0.00084817115 | V27: =(V26-U26)/U26 -> 0.024090175 | W27: =(W26-V26)/V26 -> 0.032811728 | X27: =(X26-W26)/W26 -> -0.024399385 | Y27: =(Y26-X26)/X26 -> 0.020994752 | Z27: =(Z26-Y26)/Y26 -> -0.021860662 | AA27: -0.01
B28: ='Statement Y'!B178 -> Annual patient visits | D28: ='Statement Y'!E178 -> 120000 | E28: ='Statement Y'!F178 -> 150000 | F28: ='Statement Y'!G178 -> 170000 | G28: ='Statement Y'!H178 -> 180000 | H28: =H24*H30 -> 183253.5 | I28: =I24*I30 -> 187358.38 | J28: =J24*J30 -> 201251 | K28: =K24*K30 -> 228017.39 | L28: =L24*L30 -> 268148.45 | R28: ='Statement Q'!B168 -> Network solutions revenue per AHSC | S28: ='Statement Q'!C168 -> 6.7441574 | T28: ='Statement Q'!D168 -> 6.7649316 | U28: ='Statement Q'!E168 -> 7.7255133 | V28: ='Statement Q'!F168 -> 7.6507717 | W28: ='Statement Q'!G168 -> 7.1766039 | X28: ='Statement Q'!H168 -> 7.8712783 | Y28: ='Statement Q'!I168 -> 8.2811947 | Z28: ='Statement Q'!J168 -> 7.604766 | AA28: =Z28*(1+AA29) -> 7.376623 | AE28: =SUM(X28:AA28) -> 31.133862
B29: Annual patient visits growth | E29: =(E28-D28)/D28 -> 0.25 | F29: =(F28-E28)/E28 -> 0.13333333 | G29: =(G28-F28)/F28 -> 0.058823529 | H29: =(H28-G28)/G28 -> 0.018075 | I29: =(I28-H28)/H28 -> 0.0224 | J29: =(J28-I28)/I28 -> 0.07415 | K29: =(K28-J28)/J28 -> 0.133 | L29: =(L28-K28)/K28 -> 0.176 | R29: Nw solutions revenue growth | T29: =(T28-S28)/S28 -> 0.003080325 | U29: =(U28-T28)/T28 -> 0.14199429 | V29: =(V28-U28)/U28 -> -0.0096746482 | W29: =(W28-V28)/V28 -> -0.061976463 | X29: =(X28-W28)/W28 -> 0.096797082 | Y29: =(Y28-X28)/X28 -> 0.052077492 | Z29: =(Z28-Y28)/Y28 -> -0.081682501 | AA29: -0.03
B30: ='Statement Y'!B188 -> Patient visit per AHSC | D30: ='Statement Y'!E188 -> 42.016807 | E30: ='Statement Y'!F188 -> 41.655096 | F30: ='Statement Y'!G188 -> 40.4473 | G30: ='Statement Y'!H188 -> 39.875942 | H30: =G30*(1+H31) -> 38.480284 | I30: =H30*(1+I31) -> 36.941072 | J30: =I30*(1+J31) -> 36.571661 | K30: =J30*(1+K31) -> 37.668811 | L30: =K30*(1+L31) -> 39.552252
B31: Patient visit per AHSC growth | E31: =(E30-D30)/D30 -> -0.0086087198 | F31: =(F30-E30)/E30 -> -0.028995162 | G31: =(G30-F30)/F30 -> -0.014125987 | H31: -0.035 | I31: -0.04 | J31: -0.01 | K31: 0.03 | L31: 0.05
B32: ='Statement Y'!B189 -> Revenue per visit | D32: ='Statement Y'!E189 -> 0.61305833 | E32: ='Statement Y'!F189 -> 0.64168667 | F32: ='Statement Y'!G189 -> 0.71507647 | G32: ='Statement Y'!H189 -> 0.77595 | H32: =G32*(1+H33) -> 0.77982975 | I32: =H32*(1+I33) -> 0.79542634 | J32: =I32*(1+J33) -> 0.83519766 | K32: =J32*(1+K33) -> 0.90201348 | L32: =K32*(1+L33) -> 1.001235
B33: Revenue per visit growth | E33: =(E32-D32)/D32 -> 0.046697568 | F33: =(F32-E32)/E32 -> 0.11437016 | G33: =(G32-F32)/F32 -> 0.085128699 | H33: 0.005 | I33: 0.02 | J33: 0.05 | K33: 0.08 | L33: 0.11

Sheet COGS & OpEx
B1: COGS & OpEx forecast
C2: History | H2: Forecast | P2: History | X2: Forecast | AB2: TTM
C4: Revenues | P4: Revenues | AB4: =Revenue!AE4 -> Q2-Q3-Q4
B5: Revenues (million) | C5: =Revenue!C5 -> 2022 | D5: =Revenue!D5 -> 2023 | E5: =Revenue!E5 -> 2024 | F5: =Revenue!F5 -> 2025 | G5: =Revenue!G5 -> 2026 | H5: =Revenue!H5 -> 2027 | I5: =Revenue!I5 -> 2028 | J5: =Revenue!J5 -> 2029 | ... L5: =Revenue!L5 -> 2031 | O5: Revenues (thousand) | P5: =Revenue!S5 -> Q1 2025 | Q5: =Revenue!T5 -> Q2 2025 | R5: =Revenue!U5 -> Q3 2025 | S5: =Revenue!V5 -> Q4 2025 | T5: =Revenue!W5 -> Q1 2026 | U5: =Revenue!X5 -> Q2 2026 | V5: =Revenue!Y5 -> Q3 2026 | W5: =Revenue!Z5 -> Q4 2026 | X5: FQ1 | Y5: FQ2 | Z5: FQ3 | AB5: =Revenue!AE5 -> FQ1
B6: Revenue | C6: =Revenue!C9 -> 213233 | D6: =Revenue!D9 -> 280910 | E6: =Revenue!E9 -> 356299 | F6: =Revenue!F9 -> 419813 | G6: =Revenue!G9 -> 480591 | H6: =Revenue!H9 -> 512003.95 | I6: =Revenue!I9 -> 544078.91 | J6: =Revenue!J9 -> 591204.37 | ... L6: =Revenue!L9 -> 786430.37 | O6: Revenue | P6: =Revenue!S9 -> 101217 | Q6: =Revenue!T9 -> 102115 | R6: =Revenue!U9 -> 106800 | S6: =Revenue!V9 -> 109681 | T6: =Revenue!W9 -> 115936 | U6: =Revenue!X9 -> 117255 | V6: =Revenue!Y9 -> 120333 | W6: =Revenue!Z9 -> 127067 | X6: =Revenue!AA9 -> 136425.74 | Y6: =[2]Revenue!AB11 -> 0 | Z6: =[2]Revenue!AC11 -> 0 | AB6: =SUM(U6:X6) -> 501080.74
C9: COGS and OpEx | P9: COGS & OpEx | AB9: =AB4 -> Q2-Q3-Q4
B10: Expenses (million) | C10: =C5 -> 2022 | D10: =D5 -> 2023 | E10: =E5 -> 2024 | F10: =F5 -> 2025 | G10: =G5 -> 2026 | H10: =H5 -> 2027 | I10: =I5 -> 2028 | J10: =J5 -> 2029 | ... L10: =L5 -> 2031 | O10: Expenses (thousand) | P10: =P5 -> Q1 2025 | Q10: =Q5 -> Q2 2025 | R10: =R5 -> Q3 2025 | S10: =S5 -> Q4 2025 | T10: =T5 -> Q1 2026 | U10: =U5 -> Q2 2026 | V10: =V5 -> Q3 2026 | W10: =W5 -> Q4 2026 | ... Z10: =Z5 -> FQ3 | AB10: =AB5 -> FQ1
B11: COGS | C11: ='Statement Y'!D6 -> 81388 | D11: ='Statement Y'!E6 -> 109267 | E11: ='Statement Y'!F6 -> 124011 | F11: ='Statement Y'!G6 -> 134934 | G11: ='Statement Y'!H6 -> 154123 | H11: =H22*H$6 -> 158721.23 | I11: =I22*I$6 -> 157782.89 | J11: =J22*J$6 -> 165537.22 | K11: =K22*K$6 -> 187635.87 | L11: =L22*L$6 -> 228064.81 | O11: COGS | P11: ='Statement Q'!C6 -> 34020 | Q11: ='Statement Q'!D6 -> 32811 | R11: ='Statement Q'!E6 -> 34537 | S11: ='Statement Q'!F6 -> 33566 | T11: ='Statement Q'!G6 -> 38065 | U11: ='Statement Q'!H6 -> 37641 | V11: ='Statement Q'!I6 -> 38027 | W11: ='Statement Q'!J6 -> 40390 | X11: =X22*X$6 -> 43656.237 | AB11: =SUM(U11:X11) -> 159714.24
B12: ='Statement Y'!B8 -> Sales and marketing | C12: ='Statement Y'!D8 -> 106421 | D12: ='Statement Y'!E8 -> 151263 | E12: ='Statement Y'!F8 -> 147008 | F12: ='Statement Y'!G8 -> 121129 | G12: ='Statement Y'!H8 -> 100243 | H12: =H23*H$6 -> 107520.83 | I12: =I23*I$6 -> 119697.36 | J12: =J23*J$6 -> 124152.92 | K12: =K23*K$6 -> 134025.62 | L12: =L23*L$6 -> 157286.07 | O12: ='Statement Q'!B8 -> Sales and marketing | P12: ='Statement Q'!C8 -> 32011 | Q12: ='Statement Q'!D8 -> 30184 | R12: ='Statement Q'!E8 -> 30071 | S12: ='Statement Q'!F8 -> 28863 | T12: ='Statement Q'!G8 -> 26043 | U12: ='Statement Q'!H8 -> 25396 | V12: ='Statement Q'!I8 -> 24148 | W12: ='Statement Q'!J8 -> 24656 | X12: =X23*X$6 -> 25920.891 | AB12: =SUM(U12:X12) -> 100120.89
B13: ='Statement Y'!B9 -> R&D | C13: ='Statement Y'!D9 -> 52265 | D13: ='Statement Y'!E9 -> 91244 | E13: ='Statement Y'!F9 -> 112346 | F13: ='Statement Y'!G9 -> 117364 | G13: ='Statement Y'!H9 -> 121481 | H13: =H24*H$6 -> 133121.03 | I13: =I24*I$6 -> 141460.52 | J13: =J24*J$6 -> 147801.09 | K13: =K24*K$6 -> 147428.18 | L13: =L24*L$6 -> 165150.38 | O13: ='Statement Q'!B9 -> R&D | P13: ='Statement Q'!C9 -> 28881 | Q13: ='Statement Q'!D9 -> 29542 | R13: ='Statement Q'!E9 -> 29315 | S13: ='Statement Q'!F9 -> 29626 | T13: ='Statement Q'!G9 -> 31829 | U13: ='Statement Q'!H9 -> 29274 | V13: ='Statement Q'!I9 -> 29453 | W13: ='Statement Q'!J9 -> 30925 | X13: =X24*X$6 -> 32742.178 | AB13: =SUM(U13:X13) -> 122394.18
B14: ='Statement Y'!B10 -> General and administrative | C14: ='Statement Y'!D10 -> 68674 | D14: ='Statement Y'!E10 -> 80384 | E14: ='Statement Y'!F10 -> 79926 | F14: ='Statement Y'!G10 -> 76597 | G14: ='Statement Y'!H10 -> 79903 | H14: =H25*H$6 -> 79360.613 | I14: =I25*I$6 -> 89228.942 | J14: =J25*J$6 -> 94592.699 | K14: =K25*K$6 -> 113921.78 | L14: =L25*L$6 -> 125828.86 | O14: ='Statement Q'!B10 -> General and administrative | P14: ='Statement Q'!C10 -> 19052 | Q14: ='Statement Q'!D10 -> 19497 | R14: ='Statement Q'!E10 -> 19633 | S14: ='Statement Q'!F10 -> 18415 | T14: ='Statement Q'!G10 -> 16408 | U14: ='Statement Q'!H10 -> 19042 | V14: ='Statement Q'!I10 -> 17488 | W14: ='Statement Q'!J10 -> 26965 | X14: =X25*X$6 -> 25920.891 | AB14: =SUM(U14:X14) -> 89415.891
B15: ='Statement Y'!B11 -> Depreciation | C15: ='Statement Y'!D11 -> 14985 | D15: ='Statement Y'!E11 -> 17988 | E15: ='Statement Y'!F11 -> 17584 | F15: ='Statement Y'!G11 -> 14183 | G15: ='Statement Y'!H11 -> 12972 | H15: =H26*H$6 -> 12288.095 | I15: =I26*I$6 -> 13601.973 | J15: =J26*J$6 -> 13597.7 | K15: =K26*K$6 -> 13402.562 | L15: =L26*L$6 -> 13369.316 | O15: ='Statement Q'!B11 -> Depreciation | P15: ='Statement Q'!C11 -> 3524 | Q15: ='Statement Q'!D11 -> 3921 | R15: ='Statement Q'!E11 -> 3566 | S15: ='Statement Q'!F11 -> 3172 | T15: ='Statement Q'!G11 -> 2986 | U15: ='Statement Q'!H11 -> 3279 | V15: ='Statement Q'!I11 -> 3199 | W15: ='Statement Q'!J11 -> 3508 | X15: =X26*X$6 -> 4092.7723 | AB15: =SUM(U15:X15) -> 14078.772
B16: ='Statement Y'!B12 -> Amortization | C16: ='Statement Y'!D12 -> 6317 | D16: ='Statement Y'!E12 -> 7316 | E16: ='Statement Y'!F12 -> 11903 | F16: ='Statement Y'!G12 -> 13703 | G16: ='Statement Y'!H12 -> 18481 | H16: =H27*H$6 -> 20480.158 | I16: =I27*I$6 -> 20674.999 | J16: =J27*J$6 -> 18918.54 | K16: =K27*K$6 -> 17423.33 | L16: =L27*L$6 -> 17301.468 | O16: ='Statement Q'!B12 -> Amortization | P16: ='Statement Q'!C12 -> 3149 | Q16: ='Statement Q'!D12 -> 3382 | R16: ='Statement Q'!E12 -> 3521 | S16: ='Statement Q'!F12 -> 3651 | T16: ='Statement Q'!G12 -> 3892 | U16: ='Statement Q'!H12 -> 4130 | V16: ='Statement Q'!I12 -> 4279 | W16: ='Statement Q'!J12 -> 6180 | X16: =X27*X$6 -> 6821.2871 | AB16: =SUM(U16:X16) -> 21410.287
B17: OpEx | C17: ='Statement Y'!D13 -> 248662 | D17: ='Statement Y'!E13 -> 348195 | E17: ='Statement Y'!F13 -> 368767 | F17: ='Statement Y'!G13 -> 342976 | G17: ='Statement Y'!H13 -> 333080 | H17: =SUM(H12:H16) -> 352770.72 | I17: =SUM(I12:I16) -> 384663.79 | J17: =SUM(J12:J16) -> 399062.95 | K17: =SUM(K12:K16) -> 426201.47 | L17: =SUM(L12:L16) -> 478936.1 | O17: OpEx | P17: ='Statement Q'!C13 -> 86617 | Q17: ='Statement Q'!D13 -> 86526 | R17: ='Statement Q'!E13 -> 86106 | S17: ='Statement Q'!F13 -> 83727 | T17: ='Statement Q'!G13 -> 81158 | U17: ='Statement Q'!H13 -> 81121 | V17: ='Statement Q'!I13 -> 78567 | W17: ='Statement Q'!J13 -> 92234 | X17: =SUM(X12:X16) -> 95498.019 | AB17: =SUM(U17:X17) -> 347420.02
C20: Expenses % of Revenue | P20: Expenses % of Revenue
B21: % of revenue | C21: =C5 -> 2022 | D21: =D5 -> 2023 | E21: =E5 -> 2024 | F21: =F5 -> 2025 | G21: =G5 -> 2026 | H21: =H5 -> 2027 | I21: =I5 -> 2028 | J21: =J5 -> 2029 | ... L21: =L5 -> 2031 | O21: % of revenue | P21: =P5 -> Q1 2025 | Q21: =Q5 -> Q2 2025 | R21: =R5 -> Q3 2025 | S21: =S5 -> Q4 2025 | T21: =T5 -> Q1 2026 | U21: =U5 -> Q2 2026 | V21: =V5 -> Q3 2026 | W21: =W5 -> Q4 2026 | ... Z21: =Z5 -> FQ3
B22: =B11 -> COGS | C22: =C11/C$6 -> 0.38168576 | D22: =D11/D$6 -> 0.38897512 | E22: =E11/E$6 -> 0.34805318 | F22: =F11/F$6 -> 0.32141453 | G22: =G11/G$6 -> 0.32069473 | H22: 0.31 | I22: 0.29 | J22: 0.28 | K22: 0.28 | L22: 0.29 | O22: =O11 -> COGS | P22: =P11/P$6 -> 0.33610955 | Q22: =Q11/Q$6 -> 0.3213142 | R22: =R11/R$6 -> 0.32338015 | S22: =S11/S$6 -> 0.30603295 | T22: =T11/T$6 -> 0.3283277 | U22: =U11/U$6 -> 0.32101829 | V22: =V11/V$6 -> 0.31601473 | W22: =W11/W$6 -> 0.3178638 | X22: 0.32
B23: =B12 -> Sales and marketing | C23: =C12/C$6 -> 0.49908316 | D23: =D12/D$6 -> 0.53847496 | E23: =E12/E$6 -> 0.41259728 | F23: =F12/F$6 -> 0.28853085 | G23: =G12/G$6 -> 0.20858277 | H23: 0.21 | I23: 0.22 | J23: 0.21 | K23: 0.2 | L23: 0.2 | O23: =O12 -> Sales and marketing | P23: =P12/P$6 -> 0.3162611 | Q23: =Q12/Q$6 -> 0.29558831 | R23: =R12/R$6 -> 0.28156367 | S23: =S12/S$6 -> 0.26315406 | T23: =T12/T$6 -> 0.22463256 | U23: =U12/U$6 -> 0.21658778 | V23: =V12/V$6 -> 0.20067646 | W23: =W12/W$6 -> 0.19403937 | X23: 0.19
B24: =B13 -> R&D | C24: =C13/C$6 -> 0.24510746 | D24: =D13/D$6 -> 0.32481578 | E24: =E13/E$6 -> 0.31531382 | F24: =F13/F$6 -> 0.27956257 | G24: =G13/G$6 -> 0.25277419 | H24: 0.26 | I24: 0.26 | J24: 0.25 | K24: 0.22 | L24: 0.21 | O24: =O13 -> R&D | P24: =P13/P$6 -> 0.28533744 | Q24: =Q13/Q$6 -> 0.28930128 | R24: =R13/R$6 -> 0.27448502 | S24: =S13/S$6 -> 0.27011059 | T24: =T13/T$6 -> 0.2745394 | U24: =U13/U$6 -> 0.249661 | V24: =V13/V$6 -> 0.24476245 | W24: =W13/W$6 -> 0.24337554 | X24: 0.24
B25: =B14 -> General and administrative | C25: =C14/C$6 -> 0.32206084 | D25: =D14/D$6 -> 0.28615571 | E25: =E14/E$6 -> 0.22432283 | F25: =F14/F$6 -> 0.18245505 | G25: =G14/G$6 -> 0.16625988 | H25: 0.155 | I25: 0.164 | J25: 0.16 | K25: 0.17 | L25: 0.16 | O25: =O14 -> General and administrative | P25: =P14/P$6 -> 0.18822925 | Q25: =Q14/Q$6 -> 0.19093179 | R25: =R14/R$6 -> 0.18382959 | S25: =S14/S$6 -> 0.16789599 | T25: =T14/T$6 -> 0.14152636 | U25: =U14/U$6 -> 0.16239819 | V25: =V14/V$6 -> 0.14533004 | W25: =W14/W$6 -> 0.21221088 | X25: 0.19
B26: =B15 -> Depreciation | C26: =C15/C$6 -> 0.070275239 | D26: =D15/D$6 -> 0.064034744 | E26: =E15/E$6 -> 0.049351808 | F26: =F15/F$6 -> 0.03378409 | G26: =G15/G$6 -> 0.026991766 | H26: 0.024 | I26: 0.025 | J26: 0.023 | K26: 0.02 | L26: 0.017 | O26: =O15 -> Depreciation | P26: =P15/P$6 -> 0.034816286 | Q26: =Q15/Q$6 -> 0.038397885 | R26: =R15/R$6 -> 0.033389513 | S26: =S15/S$6 -> 0.028920232 | T26: =T15/T$6 -> 0.025755589 | U26: =U15/U$6 -> 0.027964692 | V26: =V15/V$6 -> 0.026584561 | W26: =W15/W$6 -> 0.027607483 | X26: 0.03
B27: =B16 -> Amortization | C27: =C16/C$6 -> 0.02962487 | D27: =D16/D$6 -> 0.026043929 | E27: =E16/E$6 -> 0.033407335 | F27: =F16/F$6 -> 0.032640723 | G27: =G16/G$6 -> 0.038454736 | H27: 0.04 | I27: 0.038 | J27: 0.032 | K27: 0.026 | L27: 0.022 | O27: =O16 -> Amortization | P27: =P16/P$6 -> 0.031111375 | Q27: =Q16/Q$6 -> 0.033119522 | R27: =R16/R$6 -> 0.032968165 | S27: =S16/S$6 -> 0.033287443 | T27: =T16/T$6 -> 0.033570246 | U27: =U16/U$6 -> 0.035222379 | V27: =V16/V$6 -> 0.035559655 | W27: =W16/W$6 -> 0.048635759 | X27: 0.05

Sheet WC & Investments
B1: Working Capital, Capex, D&A
C3: History | H3: Forecast
C5: Revenues
B6: Revenues (thousand) | C6: =Revenue!C5 -> 2022 | D6: =Revenue!D5 -> 2023 | E6: =Revenue!E5 -> 2024 | F6: =Revenue!F5 -> 2025 | G6: =Revenue!G5 -> 2026 | H6: =Revenue!H5 -> 2027 | I6: =Revenue!I5 -> 2028 | J6: =Revenue!J5 -> 2029 | ... L6: =Revenue!L5 -> 2031
B7: Revenue | C7: =Revenue!C9 -> 213233 | D7: =Revenue!D9 -> 280910 | E7: =Revenue!E9 -> 356299 | F7: =Revenue!F9 -> 419813 | G7: =Revenue!G9 -> 480591 | H7: =Revenue!H9 -> 512003.95 | I7: =Revenue!I9 -> 544078.91 | J7: =Revenue!J9 -> 591204.37 | ... L7: =Revenue!L9 -> 786430.37
B8: COGS | C8: ='COGS & OpEx'!C11 -> 81388 | D8: ='COGS & OpEx'!D11 -> 109267 | E8: ='COGS & OpEx'!E11 -> 124011 | F8: ='COGS & OpEx'!F11 -> 134934 | G8: ='COGS & OpEx'!G11 -> 154123 | H8: ='COGS & OpEx'!H11 -> 158721.23 | I8: ='COGS & OpEx'!I11 -> 157782.89 | J8: ='COGS & OpEx'!J11 -> 165537.22 | ... L8: ='COGS & OpEx'!L11 -> 228064.81
C11: Working Capital
B12: $ (thousand) | C12: =C6 -> 2022 | D12: =D6 -> 2023 | E12: =E6 -> 2024 | F12: =F6 -> 2025 | G12: =G6 -> 2026 | H12: =H6 -> 2027 | I12: =I6 -> 2028 | J12: =J6 -> 2029 | ... L12: =L6 -> 2031
B13: Accounts receivable | C13: =Statements!D28 -> 40262 | D13: =Statements!E28 -> 51394 | E13: =Statements!F28 -> 64863 | F13: =Statements!G28 -> 73617 | G13: =Statements!H28 -> 97453 | H13: =H20*H7/365 -> 98192.539 | I13: =I20*I7/365 -> 104343.9 | J13: =J20*J7/365 -> 113381.66 | K13: =K20*K7/365 -> 128517.72 | L13: =L20*L7/365 -> 150822.26
B14: Inventory | C14: 0 | D14: 0 | E14: 0 | F14: 0 | G14: 0 | H14: =H21*H8/365 -> 0 | I14: =I21*I8/365 -> 0 | J14: =J21*J8/365 -> 0 | K14: =K21*K8/365 -> 0 | L14: =L21*L8/365 -> 0
B15: Accounts payable | C15: =Statements!D50 -> 5119 | D15: =Statements!E50 -> 10836 | E15: =Statements!F50 -> 8480 | F15: =Statements!G50 -> 5622 | G15: =Statements!H50 -> 11477 | H15: =H22*H8/365 -> 11306.169 | I15: =I22*I8/365 -> 11239.329 | J15: =J22*J8/365 -> 11791.693 | K15: =K22*K8/365 -> 13365.842 | L15: =L22*L8/365 -> 16245.712
C18: WC metrics and drivers
B19: Days | C19: =C6 -> 2022 | D19: =D6 -> 2023 | E19: =E6 -> 2024 | F19: =F6 -> 2025 | G19: =G6 -> 2026 | H19: =H6 -> 2027 | I19: =I6 -> 2028 | J19: =J6 -> 2029 | ... L19: =L6 -> 2031
B20: DSO | C20: =C13/C7*365 -> 68.918179 | D20: =D13/D7*365 -> 66.778719 | E20: =E13/E7*365 -> 66.446987 | F20: =F13/F7*365 -> 64.005176 | G20: =G13/G7*365 -> 74.013756 | H20: 70 | I20: 70 | J20: 70 | K20: 70 | L20: 70
B21: DIO | C21: =C14/C8*365 -> 0 | D21: =D14/D8*365 -> 0 | E21: =E14/E8*365 -> 0 | F21: =F14/F8*365 -> 0 | G21: =G14/G8*365 -> 0 | H21: 0 | I21: 0 | J21: 0 | K21: 0 | L21: 0
B22: DPO | C22: =C15/C8*365 -> 22.957131 | D22: =D15/D8*365 -> 36.197022 | E22: =E15/E8*365 -> 24.959076 | F22: =F15/F8*365 -> 15.207657 | G22: =G15/G8*365 -> 27.180272 | H22: 26 | I22: 26 | J22: 26 | K22: 26 | L22: 26
B23: Net trade cycle | C23: =C20+C21-C22 -> 45.961047 | D23: =D20+D21-D22 -> 30.581697 | E23: =E20+E21-E22 -> 41.487911 | F23: =F20+F21-F22 -> 48.797519 | G23: =G20+G21-G22 -> 46.833484 | H23: =H20+H21-H22 -> 44 | I23: =I20+I21-I22 -> 44 | J23: =J20+J21-J22 -> 44 | ... L23: =L20+L21-L22 -> 44
C26: Change in SIP NWC
B27: $ (thousand) | C27: =C6 -> 2022 | D27: =D6 -> 2023 | E27: =E6 -> 2024 | F27: =F6 -> 2025 | G27: =G6 -> 2026 | H27: =H6 -> 2027 | I27: =I6 -> 2028 | J27: =J6 -> 2029 | ... L27: =L6 -> 2031
B28: Change in acc receivable | C28: ='Statement Y'!D88 -> -10216 | D28: ='Statement Y'!E88 -> -11132 | E28: ='Statement Y'!F88 -> -11205 | F28: ='Statement Y'!G88 -> -8812 | G28: ='Statement Y'!H88 -> -23397 | H28: =-(H13-G13) -> -739.53897 | I28: =-(I13-H13) -> -6151.3625 | J28: =-(J13-I13) -> -9037.7577 | K28: =-(K13-J13) -> -15136.057 | L28: =-(L13-K13) -> -22304.547
B29: Change in inventory | C29: 0 | D29: 0 | E29: 0 | F29: 0 | G29: 0 | H29: =-(H14-G14) -> 0 | I29: =-(I14-H14) -> 0 | J29: =-(J14-I14) -> 0 | K29: =-(K14-J14) -> 0 | L29: =-(L14-K14) -> 0
B30: Change in acc payable | C30: ='Statement Y'!D93 -> 2881 | D30: ='Statement Y'!E93 -> 4774 | E30: ='Statement Y'!F93 -> -1993 | F30: ='Statement Y'!G93 -> -3234 | G30: ='Statement Y'!H93 -> 5261 | H30: =H15-G15 -> -170.83051 | I30: =I15-H15 -> -66.840669 | J30: =J15-I15 -> 552.36374 | K30: =K15-J15 -> 1574.1499 | L30: =L15-K15 -> 2879.8699
C33: Total change in NWC and less SIP
B34: $ (thousand) | C34: =C6 -> 2022 | D34: =D6 -> 2023 | E34: =E6 -> 2024 | F34: =F6 -> 2025 | G34: =G6 -> 2026 | H34: =H6 -> 2027 | I34: =I6 -> 2028 | J34: =J6 -> 2029 | ... L34: =L6 -> 2031
B35: Total change in NWC | C35: =Statements!D84 -> -18571 | D35: =Statements!E84 -> -3862 | E35: =Statements!F84 -> -1637 | F35: =Statements!G84 -> -6493 | G35: =Statements!H84 -> -14090 | H35: =H36+H28+H29+H30 -> 6769.6898 | I35: =I36+I28+I29+I30 -> 1942.9805 | J35: =J36+J28+J29+J30 -> 382.67151 | K35: =K36+K28+K29+K30 -> -3509.9856 | L35: =L36+L28+L29+L30 -> -7628.2216
B36: Change in NWC less SIP | C36: =C35-C28-C29-C30 -> -11236 | D36: =D35-D28-D29-D30 -> 2496 | E36: =E35-E28-E29-E30 -> 11561 | F36: =F35-F28-F29-F30 -> 5553 | G36: =G35-G28-G29-G30 -> 4046 | H36: =H7*H37 -> 7680.0593 | I36: =I7*I37 -> 8161.1837 | J36: =J7*J37 -> 8868.0655 | K36: =K7*K37 -> 10051.921 | L36: =L7*L37 -> 11796.456
B37: % of revenue | C37: =C36/C7 -> -0.052693532 | D37: =D36/D7 -> 0.0088854081 | E37: =E36/E7 -> 0.032447467 | F37: =F36/F7 -> 0.013227318 | G37: =G36/G7 -> 0.008418801 | H37: 0.015 | I37: 0.015 | J37: 0.015 | K37: 0.015 | L37: 0.015
C40: Investments
B41: $ (thousand) | C41: =C6 -> 2022 | D41: =D6 -> 2023 | E41: =E6 -> 2024 | F41: =F6 -> 2025 | G41: =G6 -> 2026 | H41: =H6 -> 2027 | I41: =I6 -> 2028 | J41: =J6 -> 2029 | ... L41: =L6 -> 2031
B42: D&A | C42: =Statements!D73 -> 21302 | D42: =Statements!E73 -> 25304 | E42: =Statements!F73 -> 29487 | F42: =Statements!G73 -> 27886 | G42: =Statements!H73 -> 31453 | H42: ='COGS & OpEx'!H15+'COGS & OpEx'!H16 -> 32768.253 | I42: ='COGS & OpEx'!I15+'COGS & OpEx'!I16 -> 34276.972 | J42: ='COGS & OpEx'!J15+'COGS & OpEx'!J16 -> 32516.24 | K42: ='COGS & OpEx'!K15+'COGS & OpEx'!K16 -> 30825.892 | L42: ='COGS & OpEx'!L15+'COGS & OpEx'!L16 -> 30670.785
B43: % of Revenue | C43: =C42/C7 -> 0.099900109 | D43: =D42/D7 -> 0.090078673 | E43: =E42/E7 -> 0.082759143 | F43: =F42/F7 -> 0.066424813 | G43: =G42/G7 -> 0.065446502 | H43: =H42/H7 -> 0.064 | I43: =I42/I7 -> 0.063 | J43: =J42/J7 -> 0.055 | ... L43: =L42/L7 -> 0.039
B44: % of CapEx | C44: =C42/C45 -> 0.69151112 | D44: =D42/D45 -> 0.96569095 | E44: =E42/E45 -> 1.1749213 | F44: =F42/F45 -> 1.1576238 | G44: =G42/G45 -> 1.2892159 | H44: =H42/H45 -> 1.28 | I44: =I42/I45 -> 1.26 | J44: =J42/J45 -> 1.2222222 | ... L44: =L42/L45 -> 0.975
B45: CapEx | C45: =-(Statements!D88+Statements!D87) -> 30805 | D45: =-(Statements!E88+Statements!E87) -> 26203 | E45: =-(Statements!F88+Statements!F87) -> 25097 | F45: =-(Statements!G88+Statements!G87) -> 24089 | G45: =-(Statements!H88+Statements!H87) -> 24397 | H45: =H7*H46 -> 25600.198 | I45: =I7*I46 -> 27203.946 | J45: =J7*J46 -> 26604.196 | K45: =K7*K46 -> 30155.764 | L45: =L7*L46 -> 31457.215
B46: % of Revenue | C46: =C45/C7 -> 0.14446638 | D46: =D45/D7 -> 0.093278986 | E46: =E45/E7 -> 0.070438031 | F46: =F45/F7 -> 0.05738031 | G46: =G45/G7 -> 0.050764579 | H46: 0.05 | I46: 0.05 | J46: 0.045 | K46: 0.045 | L46: 0.04

Sheet FCF & Other
B1: Results
C2: History | H2: Forecast
C4: Income statement
B5: $ (thousand) | C5: =Revenue!C5 -> 2022 | D5: =Revenue!D5 -> 2023 | E5: =Revenue!E5 -> 2024 | F5: =Revenue!F5 -> 2025 | G5: =Revenue!G5 -> 2026 | H5: =Revenue!H5 -> 2027 | I5: =Revenue!I5 -> 2028 | J5: =Revenue!J5 -> 2029 | ... L5: =Revenue!L5 -> 2031
B6: Revenue | C6: =Revenue!C9 -> 213233 | D6: =Revenue!D9 -> 280910 | E6: =Revenue!E9 -> 356299 | F6: =Revenue!F9 -> 419813 | G6: =Revenue!G9 -> 480591 | H6: =Revenue!H9 -> 512003.95 | I6: =Revenue!I9 -> 544078.91 | J6: =Revenue!J9 -> 591204.37 | ... L6: =Revenue!L9 -> 786430.37 | N6: From Revenue Sheet
B7: COGS | C7: ='COGS & OpEx'!C11 -> 81388 | D7: ='COGS & OpEx'!D11 -> 109267 | E7: ='COGS & OpEx'!E11 -> 124011 | F7: ='COGS & OpEx'!F11 -> 134934 | G7: ='COGS & OpEx'!G11 -> 154123 | H7: ='COGS & OpEx'!H11 -> 158721.23 | I7: ='COGS & OpEx'!I11 -> 157782.89 | J7: ='COGS & OpEx'!J11 -> 165537.22 | ... L7: ='COGS & OpEx'!L11 -> 228064.81 | N7: From COGS and OpEx Sheet
B8: Gross profit | C8: =C6-C7 -> 131845 | D8: =D6-D7 -> 171643 | E8: =E6-E7 -> 232288 | F8: =F6-F7 -> 284879 | G8: =G6-G7 -> 326468 | H8: =H6-H7 -> 353282.73 | I8: =I6-I7 -> 386296.03 | J8: =J6-J7 -> 425667.14 | ... L8: =L6-L7 -> 558365.56
B9: ='COGS & OpEx'!B12 -> Sales and marketing | C9: ='COGS & OpEx'!C12 -> 106421 | D9: ='COGS & OpEx'!D12 -> 151263 | E9: ='COGS & OpEx'!E12 -> 147008 | F9: ='COGS & OpEx'!F12 -> 121129 | G9: ='COGS & OpEx'!G12 -> 100243 | H9: ='COGS & OpEx'!H12 -> 107520.83 | I9: ='COGS & OpEx'!I12 -> 119697.36 | ... L9: ='COGS & OpEx'!L12 -> 157286.07 | N9: From COGS and OpEx Sheet
B10: ='COGS & OpEx'!B13 -> R&D | C10: ='COGS & OpEx'!C13 -> 52265 | D10: ='COGS & OpEx'!D13 -> 91244 | E10: ='COGS & OpEx'!E13 -> 112346 | F10: ='COGS & OpEx'!F13 -> 117364 | G10: ='COGS & OpEx'!G13 -> 121481 | H10: ='COGS & OpEx'!H13 -> 133121.03 | I10: ='COGS & OpEx'!I13 -> 141460.52 | ... L10: ='COGS & OpEx'!L13 -> 165150.38 | N10: From COGS and OpEx Sheet
B11: ='COGS & OpEx'!B14 -> General and administrative | C11: ='COGS & OpEx'!C14 -> 68674 | D11: ='COGS & OpEx'!D14 -> 80384 | E11: ='COGS & OpEx'!E14 -> 79926 | F11: ='COGS & OpEx'!F14 -> 76597 | G11: ='COGS & OpEx'!G14 -> 79903 | H11: ='COGS & OpEx'!H14 -> 79360.613 | I11: ='COGS & OpEx'!I14 -> 89228.942 | ... L11: ='COGS & OpEx'!L14 -> 125828.86 | N11: From COGS and OpEx Sheet
B12: ='COGS & OpEx'!B15 -> Depreciation | C12: ='COGS & OpEx'!C15 -> 14985 | D12: ='COGS & OpEx'!D15 -> 17988 | E12: ='COGS & OpEx'!E15 -> 17584 | F12: ='COGS & OpEx'!F15 -> 14183 | G12: ='COGS & OpEx'!G15 -> 12972 | H12: ='COGS & OpEx'!H15 -> 12288.095 | I12: ='COGS & OpEx'!I15 -> 13601.973 | ... L12: ='COGS & OpEx'!L15 -> 13369.316 | N12: From COGS and OpEx Sheet
B13: ='COGS & OpEx'!B16 -> Amortization | C13: ='COGS & OpEx'!C16 -> 6317 | D13: ='COGS & OpEx'!D16 -> 7316 | E13: ='COGS & OpEx'!E16 -> 11903 | F13: ='COGS & OpEx'!F16 -> 13703 | G13: ='COGS & OpEx'!G16 -> 18481 | H13: ='COGS & OpEx'!H16 -> 20480.158 | I13: ='COGS & OpEx'!I16 -> 20674.999 | ... L13: ='COGS & OpEx'!L16 -> 17301.468 | N13: From COGS and OpEx Sheet
B14: OpEx | C14: ='COGS & OpEx'!C17 -> 248662 | D14: ='COGS & OpEx'!D17 -> 348195 | E14: ='COGS & OpEx'!E17 -> 368767 | F14: ='COGS & OpEx'!F17 -> 342976 | G14: ='COGS & OpEx'!G17 -> 333080 | H14: ='COGS & OpEx'!H17 -> 352770.72 | I14: ='COGS & OpEx'!I17 -> 384663.79 | J14: ='COGS & OpEx'!J17 -> 399062.95 | ... L14: ='COGS & OpEx'!L17 -> 478936.1 | N14: From COGS and OpEx Sheet
B15: Operating lease interest | C15: ='Statement Y'!D200 -> 191.775 | D15: ='Statement Y'!E200 -> 96.225 | E15: ='Statement Y'!F200 -> 39.525 | F15: ='Statement Y'!G200 -> 120.75 | G15: ='Statement Y'!H200 -> 177.075 | H15: 1318 | I15: 793 | J15: 292 | K15: 0 | L15: 0 | N15: From 10-K Leases note
B16: Operating lease amortization | C16: ='Statement Y'!D201 -> 1127.225 | D16: ='Statement Y'!E201 -> 1800.775 | E16: ='Statement Y'!F201 -> 747.475 | F16: ='Statement Y'!G201 -> 862.25 | G16: ='Statement Y'!H201 -> 776.925 | H16: =H15-H15*Overview!$C$4 -> 1219.15 | I16: =I15-I15*Overview!$C$4 -> 733.525 | J16: =J15-J15*Overview!$C$4 -> 270.1 | K16: =K15-K15*Overview!$C$4 -> 0 | L16: =L15-L15*Overview!$C$4 -> 0
B17: EBIT | C17: =C8-C14+C15-C16 -> -117752.45 | D17: =D8-D14+D15-D16 -> -178256.55 | E17: =E8-E14+E15-E16 -> -137186.95 | F17: =F8-F14+F15-F16 -> -58838.5 | G17: =G8-G14+G15-G16 -> -7211.85 | H17: =H8-H14+H15*Overview!$C$4 -> 610.85395 | I17: =I8-I14+I15*Overview!$C$4 -> 1691.7117 | J17: =J8-J14+J15*Overview!$C$4 -> 26626.096 | K17: =K8-K14+K15*Overview!$C$4 -> 56290.76 | L17: =L8-L14+L15*Overview!$C$4 -> 79429.468
C20: Drivers
C21: =C5 -> 2022 | D21: =D5 -> 2023 | E21: =E5 -> 2024 | F21: =F5 -> 2025 | G21: =G5 -> 2026 | H21: =H5 -> 2027 | I21: =I5 -> 2028 | J21: =J5 -> 2029 | ... L21: =L5 -> 2031
B22: Tax rate | C22: ='Statement Y'!D151 -> 0.0015426474 | D22: ='Statement Y'!E151 -> 0.002749583 | E22: ='Statement Y'!F151 -> 0.011400748 | F22: ='Statement Y'!G151 -> 0.048664242 | G22: 0 | H22: 0.21 | I22: 0.21 | J22: 0.21 | K22: 0.21 | L22: 0.21
C25: Cash Flow Statement
B26: $ (thousand) | C26: =C5 -> 2022 | D26: =D5 -> 2023 | E26: =E5 -> 2024 | F26: =F5 -> 2025 | G26: =G5 -> 2026 | H26: =H5 -> 2027 | I26: =I5 -> 2028 | J26: =J5 -> 2029 | ... L26: =L5 -> 2031
B27: D&A | C27: ='WC & Investments'!C42 -> 21302 | D27: ='WC & Investments'!D42 -> 25304 | E27: ='WC & Investments'!E42 -> 29487 | F27: ='WC & Investments'!F42 -> 27886 | G27: ='WC & Investments'!G42 -> 31453 | H27: ='WC & Investments'!H42 -> 32768.253 | I27: ='WC & Investments'!I42 -> 34276.972 | J27: ='WC & Investments'!J42 -> 32516.24 | ... L27: ='WC & Investments'!L42 -> 30670.785 | N27: From WC & Investments Sheet
B28: CapEx | C28: ='WC & Investments'!C45 -> 30805 | D28: ='WC & Investments'!D45 -> 26203 | E28: ='WC & Investments'!E45 -> 25097 | F28: ='WC & Investments'!F45 -> 24089 | G28: ='WC & Investments'!G45 -> 24397 | H28: ='WC & Investments'!H45 -> 25600.198 | I28: ='WC & Investments'!I45 -> 27203.946 | J28: ='WC & Investments'!J45 -> 26604.196 | ... L28: ='WC & Investments'!L45 -> 31457.215 | N28: From WC & Investments Sheet
B29: Change in NWC | C29: ='WC & Investments'!C35 -> -18571 | D29: ='WC & Investments'!D35 -> -3862 | E29: ='WC & Investments'!E35 -> -1637 | F29: ='WC & Investments'!F35 -> -6493 | G29: ='WC & Investments'!G35 -> -14090 | H29: ='WC & Investments'!H35 -> 6769.6898 | I29: ='WC & Investments'!I35 -> 1942.9805 | J29: ='WC & Investments'!J35 -> 382.67151 | ... L29: ='WC & Investments'!L35 -> -7628.2216 | N29: From WC & Investments Sheet
C32: UFCF
B33: $ (thousand) | C33: =C5 -> 2022 | D33: =D5 -> 2023 | E33: =E5 -> 2024 | F33: =F5 -> 2025 | G33: =G5 -> 2026 | H33: =H5 -> 2027 | I33: =I5 -> 2028 | J33: =J5 -> 2029 | ... L33: =L5 -> 2031
B34: NOPAT | C34: =C17*(1-C22) -> -117570.8 | D34: =D17*(1-D22) -> -177766.42 | E34: =E17*(1-E22) -> -135622.92 | F34: =F17*(1-F22) -> -55975.169 | G34: =G17*(1-G22) -> -7211.85 | H34: =H17*(1-H22) -> 482.57462 | I34: =I17*(1-I22) -> 1336.4523 | J34: =J17*(1-J22) -> 21034.616 | ... L34: =L17*(1-L22) -> 62749.279
B35: UFCF | C35: =C34+C27-C28+C29 -> -145644.8 | D35: =D34+D27-D28+D29 -> -182527.42 | E35: =E34+E27-E28+E29 -> -132869.92 | F35: =F34+F27-F28+F29 -> -58671.169 | G35: =G34+G27-G28+G29 -> -14245.85 | H35: =H34+H27-H28+H29 -> 14420.32 | I35: =I34+I27-I28+I29 -> 10352.459 | J35: =J34+J27-J28+J29 -> 27329.331 | ... L35: =L34+L27-L28+L29 -> 54334.627

Sheet Valuation ->
B13: Valuation ->

Sheet WACC
B1: WACC
B4: Inputs
B5: Shares Outstanding | C5: ='Statement Q'!N147 -> 60763
B6: Price | C6: =[1]Sheet1!$C$7 -> 9.05
B7: Equity | C7: =C5*C6 -> 549905.15
B8: Debt | C8: ='Statement Q'!N181 -> 102449
B9: Risk free rate | C9: =[1]Sheet1!$C$10/1000 -> 0.04542
B10: Beta | C10: =[1]Sheet1!$F$7 -> 0.8877
B11: Market risk premium | C11: 0.05
B12: Tax rate | C12: 0.21
B13: Cost of debt | C13: =Overview!C5 -> 0.078
B15: Calculations
B16: Debt/(Debt+Equity) | C16: =C8/(C8+C7) -> 0.15704507
B17: Equity/(Debt+Equity) | C17: =C7/(C8+C7) -> 0.84295493
B18: Cost of debt with tax | C18: =C13*(1-C12) -> 0.06162
B19: Cost of equity | C19: =C9+C10*C11 -> 0.089805
B20: WACC | C20: =(C17*C19)+(C16*C18) -> 0.085378685
B21: WACC set manually | C21: 0.1

Sheet DCF
B1: DCF
C3: History | H3: Forecast
C5: PV of FCF
B6: $ (thousand) | C6: =Revenue!C5 -> 2022 | D6: =Revenue!D5 -> 2023 | E6: =Revenue!E5 -> 2024 | F6: =Revenue!F5 -> 2025 | G6: =Revenue!G5 -> 2026 | H6: =Revenue!H5 -> 2027 | I6: =Revenue!I5 -> 2028 | J6: =Revenue!J5 -> 2029 | ... L6: =Revenue!L5 -> 2031
B7: UFCF | C7: ='FCF & Other'!C35 -> -145644.8 | D7: ='FCF & Other'!D35 -> -182527.42 | E7: ='FCF & Other'!E35 -> -132869.92 | F7: ='FCF & Other'!F35 -> -58671.169 | G7: ='FCF & Other'!G35 -> -14245.85 | H7: ='FCF & Other'!H35 -> 14420.32 | I7: ='FCF & Other'!I35 -> 10352.459 | J7: ='FCF & Other'!J35 -> 27329.331 | ... L7: ='FCF & Other'!L35 -> 54334.627
B8: Perpetual cashflow | C8: 0 | D8: 0 | E8: 0 | F8: 0 | G8: 0 | H8: 0 | I8: 0 | J8: 0 | K8: 0 | L8: =L7*(1+C14)/(C15-C14) -> 847697.08
B9: Period | H9: 1 | I9: 2 | J9: 3 | K9: 4 | L9: 5
B10: PV of UFCF | H10: =H7/(1+$C$15)^H9 -> 13285.98 | I10: =I7/(1+$C$15)^I9 -> 8787.8155 | J10: =J7/(1+$C$15)^J9 -> 21373.967 | K10: =K7/(1+$C$15)^K9 -> 29997.124 | L10: =L7/(1+$C$15)^L9 -> 36072.002
B11: PV of Perpetual cashflow | L11: =L8/(1+C15)^L9 -> 562774.28
B13: Input parameters
B14: Perpetual growth | C14: 0.02
B15: WACC | C15: =WACC!C20 -> 0.085378685
B18: Result
B19: Total PV of Unlevered FCF | C19: =SUM(H10:L10) -> 109516.89
B20: PV of Perpetual cashflow | C20: =L11 -> 562774.28
B21: Enterprise value | C21: =C19+C20 -> 672291.17
B22: (+) Cash | C22: ='Statement Q'!N182 -> 73830
B23: (-) Debt | C23: ='Statement Q'!N181 -> 102449
B24: Equity value | C24: =C21+C22-C23 -> 643672.17
B25: Shares outstanding | C25: ='Statement Q'!N147 -> 60763
B26: Price per share | C26: =C24/C25 -> 10.59316

Sheet Multiples
B1: Multiples valuations
C2: History | H2: Forecast
C4: Revenues, earnings cash
B5: Revenues (thousand) | C5: =Revenue!C5 -> 2022 | D5: =Revenue!D5 -> 2023 | E5: =Revenue!E5 -> 2024 | F5: =Revenue!F5 -> 2025 | G5: =Revenue!G5 -> 2026 | H5: =Revenue!H5 -> 2027 | I5: =Revenue!I5 -> 2028 | J5: =Revenue!J5 -> 2029 | ... L5: =Revenue!L5 -> 2031
B6: Revenue | C6: =Revenue!C9 -> 213233 | D6: =Revenue!D9 -> 280910 | E6: =Revenue!E9 -> 356299 | F6: =Revenue!F9 -> 419813 | G6: =Revenue!G9 -> 480591 | H6: =Revenue!H9 -> 512003.95 | I6: =Revenue!I9 -> 544078.91 | J6: =Revenue!J9 -> 591204.37 | ... L6: =Revenue!L9 -> 786430.37
B7: EBIT | C7: ='FCF & Other'!C17 -> -117752.45 | D7: ='FCF & Other'!D17 -> -178256.55 | E7: ='FCF & Other'!E17 -> -137186.95 | F7: ='FCF & Other'!F17 -> -58838.5 | G7: ='FCF & Other'!G17 -> -7211.85 | H7: ='FCF & Other'!H17 -> 610.85395 | I7: ='FCF & Other'!I17 -> 1691.7117 | J7: ='FCF & Other'!J17 -> 26626.096 | ... L7: ='FCF & Other'!L17 -> 79429.468
B8: UFCF | C8: ='FCF & Other'!C35 -> -145644.8 | D8: ='FCF & Other'!D35 -> -182527.42 | E8: ='FCF & Other'!E35 -> -132869.92 | F8: ='FCF & Other'!F35 -> -58671.169 | G8: ='FCF & Other'!G35 -> -14245.85 | H8: ='FCF & Other'!H35 -> 14420.32 | I8: ='FCF & Other'!I35 -> 10352.459 | J8: ='FCF & Other'!J35 -> 27329.331 | ... L8: ='FCF & Other'!L35 -> 54334.627
C10: Growth rates
B11: % Growth | C11: =C5 -> 2022 | D11: =D5 -> 2023 | E11: =E5 -> 2024 | F11: =F5 -> 2025 | G11: =G5 -> 2026 | H11: =H5 -> 2027 | I11: =I5 -> 2028 | J11: =J5 -> 2029 | ... L11: =L5 -> 2031
B12: Revenue | D12: =(D6-C6)/C6 -> 0.31738521 | E12: =(E6-D6)/D6 -> 0.26837421 | F12: =(F6-E6)/E6 -> 0.17826039 | G12: =(G6-F6)/F6 -> 0.14477398 | H12: =(H6-G6)/G6 -> 0.065363174 | I12: =(I6-H6)/H6 -> 0.062645926 | J12: =(J6-I6)/I6 -> 0.086615102 | K12: =(K6-J6)/J6 -> 0.13349652 | L12: =(L6-K6)/K6 -> 0.17355231
B13: EBIT | D13: =(D7-C7)/C7 -> 0.51382455 | E13: =(E7-D7)/D7 -> -0.23039602 | F13: =(F7-E7)/E7 -> -0.57110716 | G13: =(G7-F7)/F7 -> -0.87742974 | H13: =(H7-G7)/G7 -> -1.0847014 | I13: =(I7-H7)/H7 -> 1.769421 | J13: =(J7-I7)/I7 -> 14.739145 | K13: =(K7-J7)/J7 -> 1.1141199 | L13: =(L7-K7)/K7 -> 0.41105695
B14: UFCF | D14: =(D8-C8)/C8 -> 0.25323678 | E14: =(E8-D8)/D8 -> -0.27205503 | F14: =(F8-E8)/E8 -> -0.5584315 | G14: =(G8-F8)/F8 -> -0.75719165 | H14: =(H8-G8)/G8 -> -2.0122471 | I14: =(I8-H8)/H8 -> -0.28209229 | J14: =(J8-I8)/I8 -> 1.639888 | K14: =(K8-J8)/J8 -> 0.52326605 | L14: =(L8-K8)/K8 -> 0.30518455
C16: Shares
C17: =C5 -> 2022 | D17: =D5 -> 2023 | E17: =E5 -> 2024 | F17: =F5 -> 2025 | G17: =G5 -> 2026 | H17: =H5 -> 2027 | I17: =I5 -> 2028 | J17: =J5 -> 2029 | ... L17: =L5 -> 2031
B18: Avg diluted shares | C18: =Statements!D22 -> 49888 | D18: =Statements!E22 -> 52440 | E18: =Statements!F22 -> 54561 | F18: =Statements!G22 -> 57590 | G18: =Statements!H22 -> 61495 | H18: =G18*(1+H19) -> 66107.125 | I18: =H18*(1+I19) -> 71395.695 | J18: =I18*(1+J19) -> 77821.308 | K18: =J18*(1+K19) -> 84825.225 | L18: =K18*(1+L19) -> 92459.496
B19: Dilution rate | D19: =D18/C18-1 -> 0.051154586 | E19: =E18/D18-1 -> 0.040446224 | F19: =F18/E18-1 -> 0.055515845 | G19: =G18/F18-1 -> 0.067806911 | H19: 0.075 | I19: 0.08 | J19: 0.09 | K19: 0.09 | L19: 0.09
C21: Historical price
C22: =C5 -> 2022 | D22: =D5 -> 2023 | E22: =E5 -> 2024 | F22: =F5 -> 2025 | G22: =G5 -> 2026 | H22: =H5 -> 2027 | I22: =I5 -> 2028 | J22: =J5 -> 2029 | ... L22: =L5 -> 2031
B23: Price | C23: ='Statement Y'!D194 -> 28.44 | D23: ='Statement Y'!E194 -> 36.19 | E23: ='Statement Y'!F194 -> 25.61 | F23: ='Statement Y'!G194 -> 29 | G23: ='Statement Y'!H194 -> 13.43
C26: Historical ratios
C27: =C5 -> 2022 | D27: =D5 -> 2023 | E27: =E5 -> 2024 | F27: =F5 -> 2025 | G27: =G5 -> 2026 | H27: =H5 -> 2027 | I27: =I5 -> 2028 | J27: =J5 -> 2029 | ... L27: =L5 -> 2031
B28: PS | C28: =C23/(C6/C18) -> 6.6538234 | D28: =D23/(D6/D18) -> 6.7559133 | E28: =E23/(E6/E18) -> 3.9217264 | F28: =F23/(F6/F18) -> 3.9782236 | G28: =G23/(G6/G18) -> 1.718463
B29: Market Cap | C29: =C23*C18 -> 1418814.7 | D29: =D23*D18 -> 1897803.6 | E29: =E23*E18 -> 1397307.2 | F29: =F23*F18 -> 1670110 | G29: =G23*G18 -> 825877.85
B30: Debt | C30: =Statements!D48+Statements!D56 -> 13244 | D30: =Statements!E48+Statements!E56 -> 7897 | E30: =Statements!F48+Statements!F56 -> 11456 | F30: =Statements!G48+Statements!G56 -> 16193 | G30: =Statements!H48+Statements!H56 -> 100088
B31: Cash | C31: =Statements!D26 -> 313812 | D31: =Statements!E26 -> 176683 | E31: =Statements!F26 -> 87520 | F31: =Statements!G26 -> 84220 | G31: =Statements!H26 -> 73830
B32: EV | C32: =C29+C30-C31 -> 1118246.7 | D32: =D29+D30-D31 -> 1729017.6 | E32: =E29+E30-E31 -> 1321243.2 | F32: =F29+F30-F31 -> 1602083 | G32: =G29+G30-G31 -> 852135.85
B33: EV/EBIT | C33: =C32/C7 -> -9.4965898 | D33: =D32/D7 -> -9.6996021 | E33: =E32/E7 -> -9.6309686 | F33: =F32/F7 -> -27.228481 | G33: =G32/G7 -> -118.15773
B34: EV/UFCF | C34: =C32/C8 -> -7.6779035 | D34: =D32/D8 -> -9.4726459 | E34: =E32/E8 -> -9.9438853 | F34: =F32/F8 -> -27.306137 | G34: =G32/G8 -> -59.816427
B37: EV/EBIT valuation
B38: Year 5 EBIT | C38: =L7 -> 79429.468
B39: WACC | C39: =WACC!C20 -> 0.085378685
B40: Applied EV/EBIT ratio | C40: 30
B41: Shares outstanding diluted | C41: =L18 -> 92459.496
B42: EV | C42: =(C38*C40)-G30+G31 -> 2356626
B43: Price per share | C43: =C42/C41 -> 25.488199
B44: PV of price per share | C44: =C43/(1+C48)^5 -> 16.92126
B46: PS valuation
B47: Year 5 sales | C47: =L6 -> 786430.37
B48: WACC | C48: =WACC!C20 -> 0.085378685
B49: Applied PS ratio | C49: 3.5
B50: Shares outstanding diluted | C50: =L18 -> 92459.496
B51: Price per share | C51: =(C47*C49)/C50 -> 29.769861
B52: PV of price per share | C52: =C51/(1+C48)^5 -> 19.763796
B54: EV/UFCF valuation
B55: Year 5 UFCF | C55: =L8 -> 54334.627
B56: WACC | C56: =WACC!C20 -> 0.085378685
B57: Applied EV/UFCF ratio | C57: 25
B58: Shares outstanding diluted | C58: =L18 -> 92459.496
B59: EV | C59: =(C55*C57)-G30+G31 -> 1332107.7
B60: Price per share | C60: =C59/C58 -> 14.407473
B61: PV of price per share | C61: =C60/(1+C56)^5 -> 9.5649207

Sheet AVG target price
B1: AVG target price
B4: AVG target price
B5: DCF price | C5: =DCF!C26 -> 10.59316
B6: EV/EBIT price | C6: =Multiples!C44 -> 16.92126
B7: PS price | C7: =Multiples!C52 -> 19.763796
B8: EV/UFCF price | C8: =Multiples!C61 -> 9.5649207
B9: AVG price | C9: =AVERAGE(C5:C8) -> 14.210784
B10: Current price | C10: =Overview!C3 -> 9.05
B11: Upside/Downside | C11: =(C9-C10)/C10 -> 0.5702524

Sheet Reverse DCF
B1: Reverse DCF
C3: History | H3: Forecast
C5: PV of FCF
B6: $ (thousand) | C6: =Revenue!C5 -> 2022 | D6: =Revenue!D5 -> 2023 | E6: =Revenue!E5 -> 2024 | F6: =Revenue!F5 -> 2025 | G6: =Revenue!G5 -> 2026 | H6: =Revenue!H5 -> 2027 | I6: =Revenue!I5 -> 2028 | J6: =Revenue!J5 -> 2029 | ... L6: =Revenue!L5 -> 2031
B7: UFCF | C7: ='FCF & Other'!C35 -> -145644.8 | D7: ='FCF & Other'!D35 -> -182527.42 | E7: ='FCF & Other'!E35 -> -132869.92 | F7: ='FCF & Other'!F35 -> -58671.169 | G7: 1000 | H7: =G7*(1+$C$17) -> 2250 | I7: =H7*(1+$C$17) -> 5062.5 | J7: =I7*(1+$C$17) -> 11390.625 | K7: =J7*(1+$C$17) -> 25628.906 | L7: =K7*(1+$C$17) -> 57665.039
B8: Perpetual cashflow | L8: =L7*(1+C20)/(C21-C20) -> 899656.21
B9: Period | H9: 1 | I9: 2 | J9: 3 | K9: 4 | L9: 5
B10: PV of UFCF | H10: =H7/(1+$C$21)^H9 -> 2073.0092 | I10: =I7/(1+$C$21)^I9 -> 4297.3671 | J10: =J7/(1+$C$21)^J9 -> 8908.4816 | K10: =K7/(1+$C$21)^K9 -> 18467.364 | L10: =L7/(1+$C$21)^L9 -> 38283.016
B11: PV of Perpetual cashflow | L11: =L8/(1+C21)^L9 -> 597269.23
B14: Growth adjustment
B15: Current Price | C15: =Overview!C3 -> 9.05
B16: Calculated Price | C16: =C36 -> 10.582764
B17: UFCF Growth | C17: 1.25 | E17: Modify until Calculated Price is very close to Current Price
B19: Input parameters
B20: Perpetual growth | C20: 0.02
B21: WACC | C21: =WACC!C20 -> 0.085378685
B22: Shares outstanding | C22: ='Statement Q'!N147 -> 60763
B23: Market cap | C23: =C15*C22 -> 549905.15
B24: Cash | C24: =Statements!S26 -> 73830
B25: Debt | C25: =Statements!S48+Statements!S56 -> 100088
B26: Enterprise Value | C26: =C23+C25-C24 -> 576163.15
B28: Result
B29: Total PV of Unlevered FCF | C29: =SUM(H10:L10) -> 72029.239
B30: PV of Perpetual cashflow | C30: =L11 -> 597269.23
B31: Enterprise value | C31: =C29+C30 -> 669298.47
B32: (+) Cash | C32: =C24 -> 73830
B33: (-) Debt | C33: =C25 -> 100088
B34: Equity value | C34: =C31+C32-C33 -> 643040.47
B35: Shares outstanding | C35: =C22 -> 60763
B36: Price per share | C36: =C34/C35 -> 10.582764
C39: Compare Metrics and growth rates
C40: =C6 -> 2022 | D40: =D6 -> 2023 | E40: =E6 -> 2024 | F40: =F6 -> 2025 | G40: =G6 -> 2026 | H40: =H6 -> 2027 | I40: =I6 -> 2028 | J40: =J6 -> 2029 | ... L40: =L6 -> 2031
B41: UFCF | C41: =C7 -> -145644.8 | D41: =D7 -> -182527.42 | E41: =E7 -> -132869.92 | F41: =F7 -> -58671.169 | G41: =G7 -> 1000 | H41: =H7 -> 2250 | I41: =I7 -> 5062.5 | J41: =J7 -> 11390.625 | ... L41: =L7 -> 57665.039
B42: EBIT | C42: ='FCF & Other'!C17 -> -117752.45 | D42: ='FCF & Other'!D17 -> -178256.55 | E42: ='FCF & Other'!E17 -> -137186.95 | F42: ='FCF & Other'!F17 -> -58838.5 | G42: ='FCF & Other'!G17 -> -7211.85 | H42: =H41/H43 -> 2500 | I42: =I41/I43 -> 5625 | J42: =J41/J43 -> 12656.25 | K42: =K41/K43 -> 28476.562 | L42: =L41/L43 -> 64072.266
B43: UFCF to EBIT margin | C43: =C41/C42 -> 1.2368728 | D43: =D41/D42 -> 1.0239591 | E43: =E41/E42 -> 0.96853175 | F43: =F41/F42 -> 0.9971561 | G43: =G41/G42 -> -0.13866068 | H43: 0.9 | I43: 0.9 | J43: 0.9 | K43: 0.9 | L43: 0.9
B44: Revenue | C44: =Revenue!C9 -> 213233 | D44: =Revenue!D9 -> 280910 | E44: =Revenue!E9 -> 356299 | F44: =Revenue!F9 -> 419813 | G44: =Revenue!G9 -> 480591 | H44: =H41/H45 -> 450000 | I44: =I41/I45 -> 506250 | J44: =J41/J45 -> 569531.25 | K44: =K41/K45 -> 640722.66 | L44: =L41/L45 -> 720812.99
B45: UFCF to Revenue margin | C45: =C41/C44 -> -0.68303124 | D45: =D41/D44 -> -0.64977188 | E45: =E41/E44 -> -0.37291689 | F45: =F41/F44 -> -0.13975548 | G45: =G41/G44 -> 0.0020807714 | H45: 0.005 | I45: 0.01 | J45: 0.02 | K45: 0.04 | L45: 0.08
B46: UFCF growth | D46: =D41/C41-1 -> 0.25323678 | E46: =E41/D41-1 -> -0.27205503 | F46: =F41/E41-1 -> -0.5584315 | G46: =G41/F41-1 -> -1.0170441 | H46: =H41/G41-1 -> 1.25 | I46: =I41/H41-1 -> 1.25 | J46: =J41/I41-1 -> 1.25 | K46: =K41/J41-1 -> 1.25 | L46: =L41/K41-1 -> 1.25
B47: EBIT growth | D47: =D42/C42-1 -> 0.51382455 | E47: =E42/D42-1 -> -0.23039602 | F47: =F42/E42-1 -> -0.57110716 | G47: =G42/F42-1 -> -0.87742974 | H47: =H42/G42-1 -> -1.3466517 | I47: =I42/H42-1 -> 1.25 | J47: =J42/I42-1 -> 1.25 | K47: =K42/J42-1 -> 1.25 | L47: =L42/K42-1 -> 1.25
B48: Revenue growth | D48: =D44/C44-1 -> 0.31738521 | E48: =E44/D44-1 -> 0.26837421 | F48: =F44/E44-1 -> 0.17826039 | G48: =G44/F44-1 -> 0.14477398 | H48: =H44/G44-1 -> -0.063652877 | I48: =I44/H44-1 -> 0.125 | J48: =J44/I44-1 -> 0.125 | K48: =K44/J44-1 -> 0.125 | L48: =L44/K44-1 -> 0.125
B49: EBIT margin | C49: =C42/C44 -> -0.55222433 | D49: =D42/D44 -> -0.63456819 | E49: =E42/E44 -> -0.38503322 | F49: =F42/F44 -> -0.14015407 | G49: =G42/G44 -> -0.015006211 | H49: =H42/H44 -> 0.0055555556 | I49: =I42/I44 -> 0.011111111 | J49: =J42/J44 -> 0.022222222 | ... L49: =L42/L44 -> 0.088888889
