Workbook

Sheet Overview
B2: Automatic Data | E2: At a glance | H2: Valuation | K2: Links
B3: Company | C3: #VALUE! | E3: Market capitalization | F3: =Statement!AC149 -> 7169450.9 | H3: ='AVG target price'!B5 -> DCF price | I3: ='AVG target price'!C5 -> 147.1741 | K3: Financials ->'!B13
B4: Ticker | C4: {=_FV(C3,"Ticker symbol",TRUE)} -> DUOL | E4: Enterprise value | F4: =Statement!AC150 -> 5752891.9 | H4: ='AVG target price'!B6 -> EV/EBIT price | I4: ='AVG target price'!C6 -> 198.02442 | K4: Analysis ->'!B13
B5: Price | C5: {=_FV(C3,"Price",TRUE)} -> 143.04 | E5: EPS | F5: =Statement!AC26 -> 3.1405969 | H5: ='AVG target price'!B7 -> PS price | I5: ='AVG target price'!C7 -> 159.74574 | K5: Forecast ->'!B13
B6: Price Extended Hours | C6: {=_FV(C3,"Price (Extended hours)",TRUE)} -> 142.69 | E6: PE | F6: =Statement!AC146 -> 45.545482 | H6: ='AVG target price'!B8 -> EV/FCFF price | I6: ='AVG target price'!C8 -> 203.55142 | K6: Valuation ->'!B13
B7: Day change | C7: {=_FV(C3,"Change")} -> 1.65 | E7: PS | F7: =Statement!AC147 -> 6.1427774 | H7: ='AVG target price'!B9 -> EV/Sales | I7: ='AVG target price'!C9 -> 203.9738
B8: Day change extended | C8: {=_FV(C3,"Change (extended hours)",TRUE)} -> -0.35 | E8: FCF Yield | F8: =Statement!AC157 -> 0.03526351 | H8: ='AVG target price'!B10 -> AVG price | I8: ='AVG target price'!C10 -> 182.4939
B9: Day change % | C9: {=_FV(C3,"Change (%)",TRUE)} -> 0.01167 | E9: Earnings Yield | F9: =Statement!AC158 -> 0.021956075 | H9: ='AVG target price'!B12 -> Upside/Downside | I9: ='AVG target price'!C12 -> 0.27582424
B10: Day change extended % | C10: {=_FV(C3,"Change % (extended hours)",TRUE)} -> -0.002447 | E10: Buyback Yield | F10: =Statement!AC160 -> 0.0097082749
B11: 52 week high | C11: {=_FV(C3,"52 week high",TRUE)} -> 322.09 | E11: Dividend Yield | F11: =Statement!AC159 -> 0 | H11: DDM price | I11: =DDM!C26 -> 0
B12: 52 week low | C12: {=_FV(C3,"52 week low",TRUE)} -> 87.89 | E12: ROA | F12: =Statement!AC123 -> 0.07428664
B13: Beta | C13: {=_FV(C3,"Beta")} -> 1.066 | E13: ROE | F13: =Statement!AC125 -> 0.10928737 | H13: Reverse DCF rate | I13: ='Reverse DCF'!C17 -> 0.29
B14: Avg volume | C14: {=_FV(C3,"Volume average",TRUE)} -> 930380 | E14: ROIC | F14: =Statement!AC136 -> -17.586668 | H14: Reverse DCF price | I14: ='Reverse DCF'!C16 -> 154.01938
E15: Net Cash/Market Cap | F15: =Statement!AC172 -> 0.19758264
E16: Net Cash/Share | F16: =Statement!AC171 -> 30.277412 | H16: Discount rates used
B17: Unit data and other info | E17: Insider Ownership | F17: =Statement!AC167 -> 0.1452057 | H17: WACC | I17: =DCF!C15 -> 0.0975
B18: Units | C18: K | E18: Net Trade Cycle | F18: =Statement!AC140 -> 22.829227 | H18: Cost of Equity | I18: =Multiples!C54 -> 0.0975
B19: Units conversion | C19: 1000 | E19: Net Debt/Equity | F19: =Statement!AC142 -> -1.0048356
B20: Has operating lease | C20: Yes | E20: Quick Ratio | F20: =Statement!AC143 -> 2.6781752
B21: Has finance lease | C21: No
B22: Has debt | C22: No
B25: Constants | E25: 10 Year Bond Yield
B26: Default tax rate | C26: 0.21 | E26: #VALUE! | F26: {=_FV(E26,"Price")} -> 49.53
B27: Cost of debt | C27: 0 | E27: Percentage | F27: =F26/1000 -> 0.04953
B28: Manual WACC | C28: 0
B29: Manual Cost of Equity | C29: 0
B33: Info
B35: Mission: | C35: Develop the best education in the world and make it universally available
B36: Auditor: | C36: Deloitte
B42: Notes
B44: Date: | C44: 04.08.2026 | E44: Q2 2027
B45: - | C45: FY2027 revenue expected as 1285
B46: - | C46: Gross margin expected at 71% in Q3 and 71.6% in FY2027
B47: - | C47: Stock based compensation expected at about 15% of revenue
B53: Adjustments
B58: Date: | C58: 31.12.2025 | E58: FY 2025
B59: - | C59: Tax expense/benefit | E59: Taken out 256.7M to account for a big tax benefit
B60: - | C60: Net income, both EPS | E60: Adjusted these values to account for the tax change
B62: Date: | C62: 30.09.2025 | E62: Q3 2025
B63: - | C63: Tax expense/benefit | E63: Taken out 256.7M to account for a big tax benefit
B64: - | C64: Net income, both EPS | E64: Adjusted these values to account for the tax change

Sheet Financials ->
H5: Links
H6: Overview'!B3
H7: Financials ->'!B13
H8: Analysis ->'!B13
H9: Forecast ->'!B13
H10: Valuation ->'!B13
B13: Financials ->

Sheet Statement
B2: Date | M2: 31.12.2021 | N2: 30.09.2022 | O2: 31.12.2023 | P2: 31.12.2024 | Q2: 31.12.2025 | T2: 30.09.2024 | U2: 31.12.2024 | V2: 31.03.2025 | W2: 30.06.2025 | X2: 30.09.2025 | Y2: 31.12.2025 | Z2: 31.03.2026 | AA2: 30.06.2026
B3: FY | M3: 2021 | N3: 2022 | O3: 2023 | P3: 2024 | Q3: 2025 | T3: Q3 2024 | U3: Q4 2024 | V3: Q1 2025 | W3: Q2 2025 | X3: Q3 2025 | Y3: Q4 2025 | Z3: Q1 2026 | AA3: Q2 2026 | AC3: TTM/YTD
B4: Income statement
B5: Revenue | M5: 250772 | N5: 369495 | O5: 531109 | P5: 748024 | Q5: 1037589 | T5: 192594 | U5: 209550 | V5: 230743 | W5: 252265 | X5: 271713 | Y5: 282868 | Z5: 291967 | AA5: 298454 | AC5: =SUM(X5:AA5) -> 1145002
B6: COGS | M6: 69186 | N6: 99431 | O6: 142105 | P6: 203645 | Q6: 288132 | T6: 52180 | U6: 58925 | V6: 66647 | W6: 69684 | X6: 74802 | Y6: 76999 | Z6: 78871 | AA6: 81714 | AC6: =SUM(X6:AA6) -> 312386
B7: Gross Profit | C7: =C5-C6 -> 0 | D7: =D5-D6 -> 0 | E7: =E5-E6 -> 0 | F7: =F5-F6 -> 0 | G7: =G5-G6 -> 0 | H7: =H5-H6 -> 0 | I7: =I5-I6 -> 0 | J7: =J5-J6 -> 0 | ... Q7: =Q5-Q6 -> 749457 | T7: =T5-T6 -> 140414 | U7: =U5-U6 -> 150625 | V7: =V5-V6 -> 164096 | W7: =W5-W6 -> 182581 | X7: =X5-X6 -> 196911 | Y7: =Y5-Y6 -> 205869 | Z7: =Z5-Z6 -> 213096 | AA7: =AA5-AA6 -> 216740 | AC7: =SUM(X7:AA7) -> 832616
B8: R&D | M8: 103833 | N8: 150444 | O8: 194352 | P8: 235298 | Q8: 306323 | T8: 62878 | U8: 66395 | V8: 70390 | W8: 73670 | X8: 82707 | Y8: 79556 | Z8: 82974 | AA8: 92195 | AC8: =SUM(X8:AA8) -> 337432
B9: Sales and marketing | M9: 59170 | N9: 66967 | O9: 75788 | P9: 90494 | Q9: 125677 | T9: 25574 | U9: 24815 | V9: 26662 | W9: 29563 | X9: 35081 | Y9: 34371 | Z9: 39249 | AA9: 40007 | AC9: =SUM(X9:AA9) -> 148708
B10: General and administrative | M10: 78590 | N10: 117848 | O10: 132123 | P10: 155992 | Q10: 181887 | T10: 38388 | U10: 45533 | V10: 43450 | W10: 45985 | X10: 43964 | Y10: 48488 | Z10: 46346 | AA10: 50593 | AC10: =SUM(X10:AA10) -> 189391
B11: OpEx | C11: =SUM(C8:C10) -> 0 | D11: =SUM(D8:D10) -> 0 | E11: =SUM(E8:E10) -> 0 | F11: =SUM(F8:F10) -> 0 | G11: =SUM(G8:G10) -> 0 | H11: =SUM(H8:H10) -> 0 | I11: =SUM(I8:I10) -> 0 | J11: =SUM(J8:J10) -> 0 | ... Q11: =SUM(Q8:Q10) -> 613887 | T11: =SUM(T8:T10) -> 126840 | U11: =SUM(U8:U10) -> 136743 | V11: =SUM(V8:V10) -> 140502 | W11: =SUM(W8:W10) -> 149218 | X11: =SUM(X8:X10) -> 161752 | Y11: =SUM(Y8:Y10) -> 162415 | Z11: =SUM(Z8:Z10) -> 168569 | AA11: =SUM(AA8:AA10) -> 182795 | AC11: =SUM(X11:AA11) -> 675531
B12: Operating income | M12: -60007 | N12: -65195 | O12: -13259 | P12: 62595 | Q12: 135570 | T12: 13574 | U12: 13882 | V12: 23594 | W12: 33363 | X12: 35159 | Y12: 43454 | Z12: 44527 | AA12: 33945 | AC12: =SUM(X12:AA12) -> 157085
B13: Interest income/expense | M13: 19 | N13: 7235 | O13: 31091 | P13: 42697 | Q13: 45231 | T13: 11246 | U13: 10697 | V13: 10415 | W13: 11427 | X13: 11793 | Y13: 11596 | Z13: 11811 | AA13: 11831 | AC13: =SUM(X13:AA13) -> 47031
B14: Other income/expense | M14: =318-288 -> 30 | N14: =131-807 -> -676 | O14: =590-645 -> -55 | P14: =1267-4253 -> -2986 | Q14: =3382-1773 -> 1609 | T14: 569 | U14: -2227 | V14: 1001 | W14: 1660 | X14: -503 | Y14: -549 | Z14: -786 | AA14: -410 | AC14: =SUM(X14:AA14) -> -2248
B15: Income before taxes | M15: -59958 | N15: 58636 | O15: 17777 | P15: 102306 | Q15: 182410 | T15: 25389 | U15: 22352 | V15: 35010 | W15: 46450 | X15: 46449 | Y15: 54501 | Z15: 55552 | AA15: 45366 | AC15: =SUM(X15:AA15) -> 201868
B16: Income tax expense/benefit | M16: -177 | N16: -938 | O16: -1710 | P16: -13732 | Q16: -25045 | T16: -2029 | U16: -8445 | V16: 125 | W16: -1669 | X16: =245746-256700 -> -10954 | Y16: -12547 | Z16: -12092 | AA16: -12208 | AC16: =SUM(X16:AA16) -> -47801
B17: Non-controlling interest | M17: 0 | N17: 0 | O17: 0 | P17: 0 | Q17: 0 | T17: 0 | U17: 0 | V17: 0 | W17: 0 | X17: 0 | Y17: 0 | Z17: 0 | AA17: 0 | AC17: =SUM(X17:AA17) -> 0
B18: Net income | M18: -60135 | N18: -59574 | O18: 16067 | P18: 88574 | Q18: 157365 | T18: 23360 | U18: 13907 | V18: 35135 | W18: 44781 | X18: 35495 | Y18: 41954 | Z18: 43460 | AA18: 33158 | AC18: =SUM(X18:AA18) -> 154067
B19: Basic Shares outstanding avg | M19: 23433 | N19: 39470 | O19: 41451 | P19: 43504 | Q19: 45753.039 | T19: 43707 | U19: 43504 | V19: 45148 | W19: 45610 | X19: 45950 | Y19: 45753.039 | Z19: 46793 | AA19: 46701.408 | AC19: =AVERAGE(X19:AA19) -> 46299.362
B20: Basic Shares outstanding avg adjusted | C20: =C19*C$85 -> 0 | D20: =D19*D$85 -> 0 | E20: =E19*E$85 -> 0 | F20: =F19*F$85 -> 0 | G20: =G19*G$85 -> 0 | H20: =H19*H$85 -> 0 | I20: =I19*I$85 -> 0 | J20: =J19*J$85 -> 0 | ... Q20: =Q19*Q$85 -> 45753.039 | T20: =T19*T$85 -> 43707 | U20: =U19*U$85 -> 43504 | V20: =V19*V$85 -> 45148 | W20: =W19*W$85 -> 45610 | X20: =X19*X$85 -> 45950 | Y20: =Y19*Y$85 -> 45753.039 | Z20: =Z19*Z$85 -> 46793 | AA20: =AA19*AA$85 -> 46701.408 | AC20: =AC19*AC$85 -> 46299.362
B21: Diluted Shares outstanding avg | M21: 23433 | N21: 39470 | O21: 46522 | P21: 47101 | Q21: 48315.636 | T21: 47969 | U21: 47101 | V21: 48497 | W21: 49000 | X21: 49144 | Y21: 48315.636 | Z21: 48987 | AA21: 50239.394 | AC21: =AVERAGE(X21:AA21) -> 49171.507
B22: Diluted Shares outstanding avg adjusted | C22: =C21*C$85 -> 0 | D22: =D21*D$85 -> 0 | E22: =E21*E$85 -> 0 | F22: =F21*F$85 -> 0 | G22: =G21*G$85 -> 0 | H22: =H21*H$85 -> 0 | I22: =I21*I$85 -> 0 | J22: =J21*J$85 -> 0 | ... Q22: =Q21*Q$85 -> 48315.636 | T22: =T21*T$85 -> 47969 | U22: =U21*U$85 -> 47101 | V22: =V21*V$85 -> 48497 | W22: =W21*W$85 -> 49000 | X22: =X21*X$85 -> 49144 | Y22: =Y21*Y$85 -> 48315.636 | Z22: =Z21*Z$85 -> 48987 | AA22: =AA21*AA$85 -> 50239.394 | AC22: =AC21*AC$85 -> 49171.507
B23: Basic EPS | M23: -2.57 | N23: -1.51 | O23: 0.39 | P23: 2.04 | Q23: 3.4394437 | T23: 0.53 | U23: 0.31967175 | V23: 0.78 | W23: 0.98 | X23: 0.77247008 | Y23: 0.91696642 | Z23: 0.93 | AA23: 0.71 | AC23: =SUM(X23:AA23) -> 3.3294365
B24: Basic EPS adjusted | M24: =M23/M$85 -> -2.57 | N24: =N23/N$85 -> -1.51 | O24: =O23/O$85 -> 0.39 | P24: =P23/P$85 -> 2.04 | Q24: =Q23/Q$85 -> 3.4394437 | T24: =T23/T$85 -> 0.53 | U24: =U23/U$85 -> 0.31967175 | V24: =V23/V$85 -> 0.78 | W24: =W23/W$85 -> 0.98 | X24: =X23/X$85 -> 0.77247008 | Y24: =Y23/Y$85 -> 0.91696642 | Z24: =Z23/Z$85 -> 0.93 | AA24: =AA23/AA$85 -> 0.71 | AC24: =AC23/AC$85 -> 3.3294365
B25: Diluted EPS | M25: -2.57 | N25: -1.51 | O25: 0.35 | P25: 1.88 | Q25: 3.2570202 | T25: 0.49 | U25: 0.29525912 | V25: 0.72 | W25: 0.91 | X25: 0.72226518 | Y25: 0.86833174 | Z25: 0.89 | AA25: 0.66 | AC25: =SUM(X25:AA25) -> 3.1405969
B26: Diluted EPS adjusted | M26: =M25/M$85 -> -2.57 | N26: =N25/N$85 -> -1.51 | O26: =O25/O$85 -> 0.35 | P26: =P25/P$85 -> 1.88 | Q26: =Q25/Q$85 -> 3.2570202 | T26: =T25/T$85 -> 0.49 | U26: =U25/U$85 -> 0.29525912 | V26: =V25/V$85 -> 0.72 | W26: =W25/W$85 -> 0.91 | X26: =X25/X$85 -> 0.72226518 | Y26: =Y25/Y$85 -> 0.86833174 | Z26: =Z25/Z$85 -> 0.89 | AA26: =AA25/AA$85 -> 0.66 | AC26: =AC25/AC$85 -> 3.1405969
B28: Balance sheet
B29: Cash and cash equivalents | M29: 553922 | N29: 608180 | O29: 747610 | P29: =785791+91854 -> 877645 | Q29: =1036389+104078 -> 1140467 | T29: =854409+26354 -> 880763 | U29: =785791+91854 -> 877645 | V29: =883996+115284 -> 999280 | W29: =976231+121652 -> 1097883 | X29: =1011542+109912 -> 1121454 | Y29: =1036389+104078 -> 1140467 | Z29: =1138561+113049 -> 1251610 | AA29: =1180887+132979 -> 1313866 | AC29: =AA29 -> 1313866
B30: Acc receivable | M30: 33163 | N30: 46728 | O30: 88975 | P30: 128923 | Q30: 162827 | T30: 94215 | U30: 128923 | V30: 114183 | W30: 112919 | X30: 124489 | Y30: 162827 | Z30: 125086 | AA30: 130979 | AC30: =AA30 -> 130979
B31: Inventory | M31: 0 | N31: 0 | O31: 0 | P31: 0 | Q31: 0 | T31: 0 | U31: 0 | V31: 0 | W31: 0 | X31: 0 | Y31: 0 | Z31: 0 | AA31: 0 | AC31: =AA31 -> 0
B32: Current assets | M32: 619271 | N32: 697183 | O32: 897798 | P32: 1101588 | Q32: 1436606 | T32: 1058437 | U32: 1101588 | V32: 1219657 | W32: 1323990 | X32: 1367105 | Y32: 1436606 | Z32: 1505959 | AA32: 1671114 | AC32: =AA32 -> 1671114
B33: PP&E | M33: 8211 | N33: 12969 | O33: 11792 | P33: 18943 | Q33: 36297 | T33: 19495 | U33: 18943 | V33: 19161 | W33: 19685 | X33: 24626 | Y33: 36297 | Z33: 36966 | AA33: 42619 | AC33: =AA33 -> 42619
B34: Marketable securities and investments | M34: 0 | N34: 0 | O34: 0 | P34: 98292 | Q34: 135098 | T34: 55328 | U34: 98292 | V34: 83342 | W34: 75362 | X34: 98735 | Y34: 135098 | Z34: 140211 | AA34: 102693 | AC34: =AA34 -> 102693
B35: Goodwill | M35: 0 | N35: 4050 | O35: 4050 | P35: 10538 | Q35: 35335 | T35: 10538 | U35: 10538 | V35: 10538 | W35: 10538 | X35: 35335 | Y35: 35335 | Z35: 35335 | AA35: 35335 | AC35: =AA35 -> 35335
B36: Long term assets | M36: =M37-M32 -> 42040 | N36: =N37-N32 -> 50164 | O36: =O37-O32 -> 56159 | P36: =P37-P32 -> 200140 | Q36: =Q37-Q32 -> 555576 | T36: =T37-T32 -> 161112 | U36: =U37-U32 -> 200140 | V36: =V37-V32 -> 183489 | W36: =W37-W32 -> 218569 | X36: =X37-X32 -> 518533 | Y36: =Y37-Y32 -> 555576 | Z36: =Z37-Z32 -> 552035 | AA36: =AA37-AA32 -> 402839 | AC36: =AA36 -> 402839
B37: Total assets | M37: 661311 | N37: 747347 | O37: 953957 | P37: 1301728 | Q37: 1992182 | T37: 1219549 | U37: 1301728 | V37: 1403146 | W37: 1542559 | X37: 1885638 | Y37: 1992182 | Z37: 2057994 | AA37: 2073953 | AC37: =AA37 -> 2073953
B38: Acc payable | M38: 7818 | N38: 1177 | O38: 2447 | P38: 6381 | Q38: 7998 | T38: 3649 | U38: 6381 | V38: 2546 | W38: 7729 | X38: 3568 | Y38: 7998 | Z38: 7486 | AA38: 16196 | AC38: =AA38 -> 16196
B39: Debt | M39: 0 | N39: 0 | O39: 0 | P39: 0 | Q39: 0 | T39: 0 | U39: 0 | V39: 0 | W39: 0 | X39: 0 | Y39: 0 | Z39: 0 | AA39: 0 | AC39: =AA39 -> 0
B40: Current liabilities | M40: 119131 | N40: 181766 | O40: 277362 | P40: 422231 | Q40: 551148 | T40: 342133 | U40: 422231 | V40: 454485 | W40: 471383 | X40: 484540 | Y40: 551148 | Z40: 574114 | AA40: 577833 | AC40: =AA40 -> 577833
B41: Debt | M41: 0 | N41: 0 | O41: 0 | P41: 0 | Q41: 0 | T41: 0 | U41: 0 | V41: 0 | W41: 0 | X41: 0 | Y41: 0 | Z41: 0 | AA41: 0 | AC41: =AA41 -> 0
B42: Long term liabilities | M42: =M43-M40 -> 29124 | N42: =N43-N40 -> 23503 | O42: =O43-O40 -> 21094 | P42: =P43-P40 -> 54947 | Q42: =Q43-Q40 -> 94028 | T42: =T43-T40 -> 54963 | U42: =U43-U40 -> 54947 | V42: =V43-V40 -> 54835 | W42: =W43-W40 -> 94145 | X42: =X43-X40 -> 93559 | Y42: =Y43-Y40 -> 94028 | Z42: =Z43-Z40 -> 92116 | AA42: =AA43-AA40 -> 86378 | AC42: =AA42 -> 86378
B43: Total liabilities | M43: 148255 | N43: 205269 | O43: 298456 | P43: 477178 | Q43: 645176 | T43: 397096 | U43: 477178 | V43: 509320 | W43: 565528 | X43: 578099 | Y43: 645176 | Z43: 666230 | AA43: 664211 | AC43: =AA43 -> 664211
B44: Treasury stock | M44: 0 | N44: 0 | O44: 0 | P44: 0 | Q44: 0 | T44: 0 | U44: 0 | V44: 0 | W44: 0 | X44: 0 | Y44: 0 | Z44: -4499 | AA44: -1425 | AC44: =AA44 -> -1425
B45: Preferred stock | M45: 0 | N45: 0 | O45: 0 | P45: 0 | Q45: 0 | T45: 0 | U45: 0 | V45: 0 | W45: 0 | X45: 0 | Y45: 0 | Z45: 0 | AA45: 0 | AC45: =AA45 -> 0
B46: Paid in capital | M46: 683966 | N46: 772562 | O46: 869918 | P46: 950393 | Q46: 1058783 | T46: 962203 | U46: 950393 | V46: 984534 | W46: 1022958 | X46: 1061270 | Y46: 1058783 | Z46: 1064580 | AA46: 1046326 | AC46: =AA46 -> 1046326
B47: Accumulated income/loss | M47: -170914 | N47: -230488 | O47: -214421 | P47: -125847 | Q47: 288218 | T47: -139754 | U47: -125847 | V47: -90712 | W47: -45931 | X47: 246264 | Y47: 288218 | Z47: 331678 | AA47: 364836 | AC47: =AA47 -> 364836
B48: Non-controlling interest | M48: 0 | N48: 0 | O48: 0 | P48: 0 | Q48: 0 | T48: 0 | U48: 0 | V48: 0 | W48: 0 | X48: 0 | Y48: 0 | Z48: 0 | AA48: 0 | AC48: =AA48 -> 0
B49: Stockholder equity | M49: 513056 | N49: 542078 | O49: 655501 | P49: 824550 | Q49: 1347006 | T49: 822453 | U49: 824550 | V49: 893826 | W49: 977031 | X49: 1307539 | Y49: 1347006 | Z49: 1391764 | AA49: 1409742 | AC49: =AA49 -> 1409742
B50: Total liabilities and equity | M50: 661311 | N50: 747347 | O50: 953957 | P50: 1301728 | Q50: 1992182 | T50: 1219549 | U50: 1301728 | V50: 1403146 | W50: 1542559 | X50: 1885638 | Y50: 1992182 | Z50: 2057994 | AA50: 2073953 | AC50: =AA50 -> 2073953
B52: Cashflow statement
B53: D&A | M53: 2726 | N53: 4870 | O53: 7095 | P53: 10854 | Q53: 14391 | T53: 2876 | U53: 3661 | V53: 3590 | W53: 3440 | X53: 3553 | Y53: 3808 | Z53: 4191 | AA53: 4247 | AC53: =SUM(X53:AA53) -> 15799
B54: Stock-based compensation | M54: 40804 | N54: 73820 | O54: 95221 | P54: 110477 | Q54: 137437 | T54: 28959 | U54: 29787 | V54: 31018 | W54: 34592 | X54: 35565 | Y54: 36262 | Z54: 34647 | AA54: 38210 | AC54: =SUM(X54:AA54) -> 144684
B55: Change in accounts receivable | M55: -12713 | N55: -13565 | O55: -42247 | P55: -39917 | Q55: -33904 | T55: -16462 | U55: -34708 | V55: 14740 | W55: 1264 | X55: -11570 | Y55: -38338 | Z55: 37741 | AA55: -5893 | AC55: =SUM(X55:AA55) -> -18060
B56: Change in inventory | M56: 0 | N56: 0 | O56: 0 | P56: 0 | Q56: 0 | T56: 0 | U56: 0 | V56: 0 | W56: 0 | X56: 0 | Y56: 0 | Z56: 0 | AA56: 0 | AC56: =SUM(X56:AA56) -> 0
B57: Change in accounts payable | M57: 5622 | N57: -6655 | O57: 1261 | P57: 3934 | Q57: 1617 | T57: -214 | U57: 3412 | V57: -3843 | W57: 4436 | X57: -3406 | Y57: 4430 | Z57: -2405 | AA57: 8593 | AC57: =SUM(X57:AA57) -> 7212
B58: Change in other operating NWC | M58: 32866 | N58: 54760 | O58: 75884 | P58: 111904 | Q58: 81253 | T58: 17760 | U58: 67586 | V58: 25541 | W58: 2629 | X58: 7829 | Y58: 45254 | Z58: 23962 | AA58: -2109 | AC58: =SUM(X58:AA58) -> 74936
B59: Operating cashflow | M59: 9170 | N59: 53656 | O59: 153614 | P59: 285513 | Q59: 387823 | T59: 56267 | U59: 83344 | V59: 105631 | W59: 90675 | X59: 84239 | Y59: 107278 | Z59: 150771 | AA59: 88260 | AC59: =SUM(X59:AA59) -> 430548
B60: CapEx | M60: -3586 | N60: -5562 | O60: -3191 | P60: -12116 | Q60: -18096 | T60: -3178 | U60: -1961 | V60: -1309 | W60: -1198 | X60: -4862 | Y60: -10727 | Z60: -132 | AA60: -6896 | AC60: =SUM(X60:AA60) -> -22617
B61: Capitalized software | M61: -2620 | N61: -4562 | O61: -10493 | P61: -9024 | Q61: -9303 | T61: -1845 | U61: -479 | V61: -1310 | W61: -3153 | X61: -2021 | Y61: -2819 | Z61: -2853 | AA61: -2734 | AC61: =SUM(X61:AA61) -> -10427
B62: Investing cashflow | M62: -6206 | N62: -14174 | O62: -13584 | P62: -217330 | Q62: -107678 | T62: -93288 | U62: -110365 | V62: -10549 | W62: -2272 | X62: -51675 | Y62: -43182 | Z62: -16749 | AA62: 25218 | AC62: =SUM(X62:AA62) -> -86388
B63: Repurchase stock | M63: -868 | N63: 0 | O63: 0 | P63: 0 | Q63: 0 | T63: 0 | U63: 0 | V63: 0 | W63: 0 | X63: 0 | Y63: 0 | Z63: -24331 | AA63: -45272 | AC63: =SUM(X63:AA63) -> -69603
B64: Dividends | M64: 0 | N64: 0 | O64: 0 | P64: 0 | Q64: 0 | T64: 0 | U64: 0 | V64: 0 | W64: 0 | X64: 0 | Y64: 0 | Z64: 0 | AA64: 0 | AC64: =SUM(X64:AA64) -> 0
... B66: Financing cashflow | M66: 430468 | N66: 14776 | O66: 2135 | P66: -30002 | Q66: -29547 | T66: 3190 | U66: -41597 | V66: 3123 | W66: 3832 | X66: 2747 | Y66: -39249 | Z66: -31850 | AA66: -54214 | AC66: =SUM(X66:AA66) -> -122566
B68: Sanity checks
B69: Calculated Net Income | C69: =C5-C6-C11+C13+C14+C16-C17 -> 0 | D69: =D5-D6-D11+D13+D14+D16-D17 -> 0 | E69: =E5-E6-E11+E13+E14+E16-E17 -> 0 | F69: =F5-F6-F11+F13+F14+F16-F17 -> 0 | G69: =G5-G6-G11+G13+G14+G16-G17 -> 0 | H69: =H5-H6-H11+H13+H14+H16-H17 -> 0 | I69: =I5-I6-I11+I13+I14+I16-I17 -> 0 | J69: =J5-J6-J11+J13+J14+J16-J17 -> 0 | ... Q69: =Q5-Q6-Q11+Q13+Q14+Q16-Q17 -> 157365 | T69: =T5-T6-T11+T13+T14+T16-T17 -> 23360 | U69: =U5-U6-U11+U13+U14+U16-U17 -> 13907 | V69: =V5-V6-V11+V13+V14+V16-V17 -> 35135 | W69: =W5-W6-W11+W13+W14+W16-W17 -> 44781 | X69: =X5-X6-X11+X13+X14+X16-X17 -> 35495 | Y69: =Y5-Y6-Y11+Y13+Y14+Y16-Y17 -> 41954 | Z69: =Z5-Z6-Z11+Z13+Z14+Z16-Z17 -> 43460 | AA69: =AA5-AA6-AA11+AA13+AA14+AA16-AA17 -> 33158 | AC69: =AC5-AC6-AC11+AC13+AC14+AC16-AC17 -> 154067
B70: Check Net Income | C70: =C18-C69 -> 0 | D70: =D18-D69 -> 0 | E70: =E18-E69 -> 0 | F70: =F18-F69 -> 0 | G70: =G18-G69 -> 0 | H70: =H18-H69 -> 0 | I70: =I18-I69 -> 0 | J70: =J18-J69 -> 0 | ... Q70: =Q18-Q69 -> 0 | T70: =T18-T69 -> 0 | U70: =U18-U69 -> 0 | V70: =V18-V69 -> 0 | W70: =W18-W69 -> 0 | X70: =X18-X69 -> 0 | Y70: =Y18-Y69 -> 0 | Z70: =Z18-Z69 -> 0 | AA70: =AA18-AA69 -> 0 | AC70: =AC18-AC69 -> 0
B71: Check balance | C71: =C37-(C43+C112) -> 0 | D71: =D37-(D43+D112) -> 0 | E71: =E37-(E43+E112) -> 0 | F71: =F37-(F43+F112) -> 0 | G71: =G37-(G43+G112) -> 0 | H71: =H37-(H43+H112) -> 0 | I71: =I37-(I43+I112) -> 0 | J71: =J37-(J43+J112) -> 0 | ... Q71: =Q37-(Q43+Q112) -> 0 | T71: =T37-(T43+T112) -> 0 | U71: =U37-(U43+U112) -> 0 | V71: =V37-(V43+V112) -> 0 | W71: =W37-(W43+W112) -> 0 | X71: =X37-(X43+X112) -> 0 | Y71: =Y37-(Y43+Y112) -> 0 | Z71: =Z37-(Z43+Z112) -> 0 | AA71: =AA37-(AA43+AA112) -> 0 | AC71: =AC37-(AC43+AC112) -> 0
B73: Other data
B74: Shares outstanding | M74: 38625 | N74: 40636 | O74: 42876 | P74: 45243 | Q74: 47400 | T74: 43984 | U74: 45243 | V74: 45455 | W74: 45822 | X74: 46228 | Y74: 47400 | Z74: 46593 | AA74: 46786 | AC74: =AA74 -> 46786
B75: Split adjusted shares outstanding | M75: =M74*M85 -> 38625 | N75: =N74*N85 -> 40636 | O75: =O74*O85 -> 42876 | P75: =P74*P85 -> 45243 | Q75: =Q74*Q85 -> 47400 | T75: =T74*T85 -> 43984 | U75: =U74*U85 -> 45243 | V75: =V74*V85 -> 45455 | W75: =W74*W85 -> 45822 | X75: =X74*X85 -> 46228 | Y75: =Y74*Y85 -> 47400 | Z75: =Z74*Z85 -> 46593 | AA75: =AA74*AA85 -> 46786 | AC75: =AA75 -> 46786
B76: Dilutive shares | M76: 0 | N76: 0 | O76: =2027+2774+270 -> 5071 | P76: =1802+1435+360 -> 3597 | Q76: =1406+769+360 -> 2535 | T76: =1938+2054+270 -> 4262 | U76: =1802+1435+360 -> 3597 | V76: =1644+1165+540 -> 3349 | W76: =1638+1032+720 -> 3390 | X76: =1547+927+720 -> 3194 | Y76: =1406+769+360 -> 2535 | Z76: =1486+528+180 -> 2194 | AA76: =519+2817 -> 3336 | AC76: =AA76 -> 3336
B77: Split adjusted dilutive shares | M77: =M76*M85 -> 0 | N77: =N76*N85 -> 0 | O77: =O76*O85 -> 5071 | P77: =P76*P85 -> 3597 | Q77: =Q76*Q85 -> 2535 | T77: =T76*T85 -> 4262 | U77: =U76*U85 -> 3597 | V77: =V76*V85 -> 3349 | W77: =W76*W85 -> 3390 | X77: =X76*X85 -> 3194 | Y77: =Y76*Y85 -> 2535 | Z77: =Z76*Z85 -> 2194 | AA77: =AA76*AA85 -> 3336 | AC77: =AA77 -> 3336
B78: Split adjusted diluted shares | M78: =M75+M77 -> 38625 | N78: =N75+N77 -> 40636 | O78: =O75+O77 -> 47947 | P78: =P75+P77 -> 48840 | Q78: =Q75+Q77 -> 49935 | T78: =T75+T77 -> 48246 | U78: =U75+U77 -> 48840 | V78: =V75+V77 -> 48804 | W78: =W75+W77 -> 49212 | X78: =X75+X77 -> 49422 | Y78: =Y75+Y77 -> 49935 | Z78: =Z75+Z77 -> 48787 | AA78: =AA75+AA77 -> 50122 | AC78: =AA78 -> 50122
B79: Shares held by insiders | M79: 8651 | N79: 8145 | O79: 7885 | P79: 7122 | Q79: =520+6758 -> 7278 | AC79: =Q79 -> 7278
B80: Split adjusted shares held by insiders | M80: =M79*M85 -> 8651 | N80: =N79*N85 -> 8145 | O80: =O79*O85 -> 7885 | P80: =P79*P85 -> 7122 | Q80: =Q79*Q85 -> 7278 | AC80: =Q80 -> 7278
B81: Dividends per share | M81: 0 | N81: 0 | O81: 0 | P81: 0 | Q81: 0 | T81: 0 | U81: 0 | V81: 0 | W81: 0 | X81: 0 | Y81: 0 | Z81: 0 | AA81: 0 | AC81: =SUM(X81:AA81) -> 0
B82: Split adjusted dividends per share | M82: =M81/M85 -> 0 | N82: =N81/N85 -> 0 | O82: =O81/O85 -> 0 | P82: =P81/P85 -> 0 | Q82: =Q81/Q85 -> 0 | T82: =T81/T85 -> 0 | U82: =U81/U85 -> 0 | V82: =V81/V85 -> 0 | W82: =W81/W85 -> 0 | X82: =X81/X85 -> 0 | Y82: =Y81/Y85 -> 0 | Z82: =Z81/Z85 -> 0 | AA82: =AA81/AA85 -> 0 | AC82: =SUM(X82:AA82) -> 0
B83: Tax rate | C83: =IF(AND(C15>0,C16<0),-(C16)/C15,0) -> 0 | D83: =IF(AND(D15>0,D16<0),-(D16)/D15,0) -> 0 | E83: =IF(AND(E15>0,E16<0),-(E16)/E15,0) -> 0 | F83: =IF(AND(F15>0,F16<0),-(F16)/F15,0) -> 0 | G83: =IF(AND(G15>0,G16<0),-(G16)/G15,0) -> 0 | H83: =IF(AND(H15>0,H16<0),-(H16)/H15,0) -> 0 | I83: =IF(AND(I15>0,I16<0),-(I16)/I15,0) -> 0 | J83: =IF(AND(J15>0,J16<0),-(J16)/J15,0) -> 0 | ... Q83: =IF(AND(Q15>0,Q16<0),-(Q16)/Q15,0) -> 0.13730059 | T83: =IF(AND(T15>0,T16<0),-(T16)/T15,0) -> 0.079916499 | U83: =IF(AND(U15>0,U16<0),-(U16)/U15,0) -> 0.37781854 | V83: =IF(AND(V15>0,V16<0),-(V16)/V15,0) -> 0 | W83: =IF(AND(W15>0,W16<0),-(W16)/W15,0) -> 0.035931109 | X83: =IF(AND(X15>0,X16<0),-(X16)/X15,0) -> 0.23582854 | Y83: =IF(AND(Y15>0,Y16<0),-(Y16)/Y15,0) -> 0.23021596 | Z83: =IF(AND(Z15>0,Z16<0),-(Z16)/Z15,0) -> 0.21766993 | AA83: =IF(AND(AA15>0,AA16<0),-(AA16)/AA15,0) -> 0.26910021 | AC83: =IF(AND(AC15>0,AC16<0),-(AC16)/AC15,0) -> 0.23679335
B84: Employees | M84: 500 | N84: 600 | O84: 720 | P84: 830 | Q84: 900 | AC84: =Q84 -> 900
B85: Stock split factor | M85: 1 | N85: 1 | O85: 1 | P85: 1 | Q85: 1 | T85: 1 | U85: 1 | V85: 1 | W85: 1 | X85: 1 | Y85: 1 | Z85: 1 | AA85: 1 | AC85: 1
B88: Growth rates Income Statement
B89: Revenue | M89: =IF(L5=0, IF(M5=0,0,IF(M5>0,1,-1)), (M5-L5)/ABS(L5) ) -> 1 | N89: =IF(M5=0, IF(N5=0,0,IF(N5>0,1,-1)), (N5-M5)/ABS(M5) ) -> 0.47343005 | O89: =IF(N5=0, IF(O5=0,0,IF(O5>0,1,-1)), (O5-N5)/ABS(N5) ) -> 0.43739157 | P89: =IF(O5=0, IF(P5=0,0,IF(P5>0,1,-1)), (P5-O5)/ABS(O5) ) -> 0.40841899 | Q89: =IF(P5=0, IF(Q5=0,0,IF(Q5>0,1,-1)), (Q5-P5)/ABS(P5) ) -> 0.38710656 | T89: =IF(S5=0, IF(T5=0,0,IF(T5>0,1,-1)), (T5-S5)/ABS(S5) ) -> 1 | U89: =IF(T5=0, IF(U5=0,0,IF(U5>0,1,-1)), (U5-T5)/ABS(T5) ) -> 0.088040126 | V89: =IF(U5=0, IF(V5=0,0,IF(V5>0,1,-1)), (V5-U5)/ABS(U5) ) -> 0.10113577 | W89: =IF(V5=0, IF(W5=0,0,IF(W5>0,1,-1)), (W5-V5)/ABS(V5) ) -> 0.093272602 | X89: =IF(W5=0, IF(X5=0,0,IF(X5>0,1,-1)), (X5-W5)/ABS(W5) ) -> 0.077093533 | Y89: =IF(X5=0, IF(Y5=0,0,IF(Y5>0,1,-1)), (Y5-X5)/ABS(X5) ) -> 0.041054348 | Z89: =IF(Y5=0, IF(Z5=0,0,IF(Z5>0,1,-1)), (Z5-Y5)/ABS(Y5) ) -> 0.032166947 | AA89: =IF(Z5=0, IF(AA5=0,0,IF(AA5>0,1,-1)), (AA5-Z5)/ABS(Z5) ) -> 0.022218264
B90: COGS | M90: =IF(L6=0, IF(M6=0,0,IF(M6>0,1,-1)), (M6-L6)/ABS(L6) ) -> 1 | N90: =IF(M6=0, IF(N6=0,0,IF(N6>0,1,-1)), (N6-M6)/ABS(M6) ) -> 0.43715492 | O90: =IF(N6=0, IF(O6=0,0,IF(O6>0,1,-1)), (O6-N6)/ABS(N6) ) -> 0.42918205 | P90: =IF(O6=0, IF(P6=0,0,IF(P6>0,1,-1)), (P6-O6)/ABS(O6) ) -> 0.43306006 | Q90: =IF(P6=0, IF(Q6=0,0,IF(Q6>0,1,-1)), (Q6-P6)/ABS(P6) ) -> 0.41487392 | T90: =IF(S6=0, IF(T6=0,0,IF(T6>0,1,-1)), (T6-S6)/ABS(S6) ) -> 1 | U90: =IF(T6=0, IF(U6=0,0,IF(U6>0,1,-1)), (U6-T6)/ABS(T6) ) -> 0.12926409 | V90: =IF(U6=0, IF(V6=0,0,IF(V6>0,1,-1)), (V6-U6)/ABS(U6) ) -> 0.13104794 | W90: =IF(V6=0, IF(W6=0,0,IF(W6>0,1,-1)), (W6-V6)/ABS(V6) ) -> 0.045568443 | X90: =IF(W6=0, IF(X6=0,0,IF(X6>0,1,-1)), (X6-W6)/ABS(W6) ) -> 0.073445841 | Y90: =IF(X6=0, IF(Y6=0,0,IF(Y6>0,1,-1)), (Y6-X6)/ABS(X6) ) -> 0.029370872 | Z90: =IF(Y6=0, IF(Z6=0,0,IF(Z6>0,1,-1)), (Z6-Y6)/ABS(Y6) ) -> 0.024312004 | AA90: =IF(Z6=0, IF(AA6=0,0,IF(AA6>0,1,-1)), (AA6-Z6)/ABS(Z6) ) -> 0.036046202
B91: Gross Profit | M91: =IF(L7=0, IF(M7=0,0,IF(M7>0,1,-1)), (M7-L7)/ABS(L7) ) -> 1 | N91: =IF(M7=0, IF(N7=0,0,IF(N7>0,1,-1)), (N7-M7)/ABS(M7) ) -> 0.48725122 | O91: =IF(N7=0, IF(O7=0,0,IF(O7>0,1,-1)), (O7-N7)/ABS(N7) ) -> 0.44041412 | P91: =IF(O7=0, IF(P7=0,0,IF(P7>0,1,-1)), (P7-O7)/ABS(O7) ) -> 0.39941749 | Q91: =IF(P7=0, IF(Q7=0,0,IF(Q7>0,1,-1)), (Q7-P7)/ABS(P7) ) -> 0.37671916 | T91: =IF(S7=0, IF(T7=0,0,IF(T7>0,1,-1)), (T7-S7)/ABS(S7) ) -> 1 | U91: =IF(T7=0, IF(U7=0,0,IF(U7>0,1,-1)), (U7-T7)/ABS(T7) ) -> 0.072720669 | V91: =IF(U7=0, IF(V7=0,0,IF(V7>0,1,-1)), (V7-U7)/ABS(U7) ) -> 0.089434025 | W91: =IF(V7=0, IF(W7=0,0,IF(W7>0,1,-1)), (W7-V7)/ABS(V7) ) -> 0.11264747 | X91: =IF(W7=0, IF(X7=0,0,IF(X7>0,1,-1)), (X7-W7)/ABS(W7) ) -> 0.078485713 | Y91: =IF(X7=0, IF(Y7=0,0,IF(Y7>0,1,-1)), (Y7-X7)/ABS(X7) ) -> 0.045492634 | Z91: =IF(Y7=0, IF(Z7=0,0,IF(Z7>0,1,-1)), (Z7-Y7)/ABS(Y7) ) -> 0.035104848 | AA91: =IF(Z7=0, IF(AA7=0,0,IF(AA7>0,1,-1)), (AA7-Z7)/ABS(Z7) ) -> 0.017100274
B92: Sales and marketing | M92: =IF(L8=0, IF(M8=0,0,IF(M8>0,1,-1)), (M8-L8)/ABS(L8) ) -> 1 | N92: =IF(M8=0, IF(N8=0,0,IF(N8>0,1,-1)), (N8-M8)/ABS(M8) ) -> 0.44890353 | O92: =IF(N8=0, IF(O8=0,0,IF(O8>0,1,-1)), (O8-N8)/ABS(N8) ) -> 0.29185611 | P92: =IF(O8=0, IF(P8=0,0,IF(P8>0,1,-1)), (P8-O8)/ABS(O8) ) -> 0.21067959 | Q92: =IF(P8=0, IF(Q8=0,0,IF(Q8>0,1,-1)), (Q8-P8)/ABS(P8) ) -> 0.30185127 | T92: =IF(S8=0, IF(T8=0,0,IF(T8>0,1,-1)), (T8-S8)/ABS(S8) ) -> 1 | U92: =IF(T8=0, IF(U8=0,0,IF(U8>0,1,-1)), (U8-T8)/ABS(T8) ) -> 0.055933713 | V92: =IF(U8=0, IF(V8=0,0,IF(V8>0,1,-1)), (V8-U8)/ABS(U8) ) -> 0.060170194 | W92: =IF(V8=0, IF(W8=0,0,IF(W8>0,1,-1)), (W8-V8)/ABS(V8) ) -> 0.046597528 | X92: =IF(W8=0, IF(X8=0,0,IF(X8>0,1,-1)), (X8-W8)/ABS(W8) ) -> 0.12266866 | Y92: =IF(X8=0, IF(Y8=0,0,IF(Y8>0,1,-1)), (Y8-X8)/ABS(X8) ) -> -0.038098347 | Z92: =IF(Y8=0, IF(Z8=0,0,IF(Z8>0,1,-1)), (Z8-Y8)/ABS(Y8) ) -> 0.042963447 | AA92: =IF(Z8=0, IF(AA8=0,0,IF(AA8>0,1,-1)), (AA8-Z8)/ABS(Z8) ) -> 0.1111312
B93: R&D | M93: =IF(L9=0, IF(M9=0,0,IF(M9>0,1,-1)), (M9-L9)/ABS(L9) ) -> 1 | N93: =IF(M9=0, IF(N9=0,0,IF(N9>0,1,-1)), (N9-M9)/ABS(M9) ) -> 0.13177286 | O93: =IF(N9=0, IF(O9=0,0,IF(O9>0,1,-1)), (O9-N9)/ABS(N9) ) -> 0.13172159 | P93: =IF(O9=0, IF(P9=0,0,IF(P9>0,1,-1)), (P9-O9)/ABS(O9) ) -> 0.19404127 | Q93: =IF(P9=0, IF(Q9=0,0,IF(Q9>0,1,-1)), (Q9-P9)/ABS(P9) ) -> 0.38878821 | T93: =IF(S9=0, IF(T9=0,0,IF(T9>0,1,-1)), (T9-S9)/ABS(S9) ) -> 1 | U93: =IF(T9=0, IF(U9=0,0,IF(U9>0,1,-1)), (U9-T9)/ABS(T9) ) -> -0.02967858 | V93: =IF(U9=0, IF(V9=0,0,IF(V9>0,1,-1)), (V9-U9)/ABS(U9) ) -> 0.074430788 | W93: =IF(V9=0, IF(W9=0,0,IF(W9>0,1,-1)), (W9-V9)/ABS(V9) ) -> 0.10880654 | X93: =IF(W9=0, IF(X9=0,0,IF(X9>0,1,-1)), (X9-W9)/ABS(W9) ) -> 0.18665223 | Y93: =IF(X9=0, IF(Y9=0,0,IF(Y9>0,1,-1)), (Y9-X9)/ABS(X9) ) -> -0.020238876 | Z93: =IF(Y9=0, IF(Z9=0,0,IF(Z9>0,1,-1)), (Z9-Y9)/ABS(Y9) ) -> 0.14192197 | AA93: =IF(Z9=0, IF(AA9=0,0,IF(AA9>0,1,-1)), (AA9-Z9)/ABS(Z9) ) -> 0.019312594
B94: General and administrative | M94: =IF(L10=0, IF(M10=0,0,IF(M10>0,1,-1)), (M10-L10)/ABS(L10) ) -> 1 | N94: =IF(M10=0, IF(N10=0,0,IF(N10>0,1,-1)), (N10-M10)/ABS(M10) ) -> 0.4995292 | O94: =IF(N10=0, IF(O10=0,0,IF(O10>0,1,-1)), (O10-N10)/ABS(N10) ) -> 0.12113061 | P94: =IF(O10=0, IF(P10=0,0,IF(P10>0,1,-1)), (P10-O10)/ABS(O10) ) -> 0.18065742 | Q94: =IF(P10=0, IF(Q10=0,0,IF(Q10>0,1,-1)), (Q10-P10)/ABS(P10) ) -> 0.1660021 | T94: =IF(S10=0, IF(T10=0,0,IF(T10>0,1,-1)), (T10-S10)/ABS(S10) ) -> 1 | U94: =IF(T10=0, IF(U10=0,0,IF(U10>0,1,-1)), (U10-T10)/ABS(T10) ) -> 0.18612587 | V94: =IF(U10=0, IF(V10=0,0,IF(V10>0,1,-1)), (V10-U10)/ABS(U10) ) -> -0.045747041 | W94: =IF(V10=0, IF(W10=0,0,IF(W10>0,1,-1)), (W10-V10)/ABS(V10) ) -> 0.058342923 | X94: =IF(W10=0, IF(X10=0,0,IF(X10>0,1,-1)), (X10-W10)/ABS(W10) ) -> -0.043949114 | Y94: =IF(X10=0, IF(Y10=0,0,IF(Y10>0,1,-1)), (Y10-X10)/ABS(X10) ) -> 0.10290237 | Z94: =IF(Y10=0, IF(Z10=0,0,IF(Z10>0,1,-1)), (Z10-Y10)/ABS(Y10) ) -> -0.044175879 | AA94: =IF(Z10=0, IF(AA10=0,0,IF(AA10>0,1,-1)), (AA10-Z10)/ABS(Z10) ) -> 0.091636819
B95: OpEx | M95: =IF(L11=0, IF(M11=0,0,IF(M11>0,1,-1)), (M11-L11)/ABS(L11) ) -> 1 | N95: =IF(M11=0, IF(N11=0,0,IF(N11>0,1,-1)), (N11-M11)/ABS(M11) ) -> 0.38770163 | O95: =IF(N11=0, IF(O11=0,0,IF(O11>0,1,-1)), (O11-N11)/ABS(N11) ) -> 0.19985742 | P95: =IF(O11=0, IF(P11=0,0,IF(P11>0,1,-1)), (P11-O11)/ABS(O11) ) -> 0.1976841 | Q95: =IF(P11=0, IF(Q11=0,0,IF(Q11>0,1,-1)), (Q11-P11)/ABS(P11) ) -> 0.27419549 | T95: =IF(S11=0, IF(T11=0,0,IF(T11>0,1,-1)), (T11-S11)/ABS(S11) ) -> 1 | U95: =IF(T11=0, IF(U11=0,0,IF(U11>0,1,-1)), (U11-T11)/ABS(T11) ) -> 0.07807474 | V95: =IF(U11=0, IF(V11=0,0,IF(V11>0,1,-1)), (V11-U11)/ABS(U11) ) -> 0.027489524 | W95: =IF(V11=0, IF(W11=0,0,IF(W11>0,1,-1)), (W11-V11)/ABS(V11) ) -> 0.062034704 | X95: =IF(W11=0, IF(X11=0,0,IF(X11>0,1,-1)), (X11-W11)/ABS(W11) ) -> 0.083997909 | Y95: =IF(X11=0, IF(Y11=0,0,IF(Y11>0,1,-1)), (Y11-X11)/ABS(X11) ) -> 0.0040988674 | Z95: =IF(Y11=0, IF(Z11=0,0,IF(Z11>0,1,-1)), (Z11-Y11)/ABS(Y11) ) -> 0.037890589 | AA95: =IF(Z11=0, IF(AA11=0,0,IF(AA11>0,1,-1)), (AA11-Z11)/ABS(Z11) ) -> 0.084392741
B96: Operating income | M96: =IF(L12=0, IF(M12=0,0,IF(M12>0,1,-1)), (M12-L12)/ABS(L12) ) -> -1 | N96: =IF(M12=0, IF(N12=0,0,IF(N12>0,1,-1)), (N12-M12)/ABS(M12) ) -> -0.08645658 | O96: =IF(N12=0, IF(O12=0,0,IF(O12>0,1,-1)), (O12-N12)/ABS(N12) ) -> 0.79662551 | P96: =IF(O12=0, IF(P12=0,0,IF(P12>0,1,-1)), (P12-O12)/ABS(O12) ) -> 5.7209443 | Q96: =IF(P12=0, IF(Q12=0,0,IF(Q12>0,1,-1)), (Q12-P12)/ABS(P12) ) -> 1.1658279 | T96: =IF(S12=0, IF(T12=0,0,IF(T12>0,1,-1)), (T12-S12)/ABS(S12) ) -> 1 | U96: =IF(T12=0, IF(U12=0,0,IF(U12>0,1,-1)), (U12-T12)/ABS(T12) ) -> 0.022690438 | V96: =IF(U12=0, IF(V12=0,0,IF(V12>0,1,-1)), (V12-U12)/ABS(U12) ) -> 0.69961101 | W96: =IF(V12=0, IF(W12=0,0,IF(W12>0,1,-1)), (W12-V12)/ABS(V12) ) -> 0.41404594 | X96: =IF(W12=0, IF(X12=0,0,IF(X12>0,1,-1)), (X12-W12)/ABS(W12) ) -> 0.053832089 | Y96: =IF(X12=0, IF(Y12=0,0,IF(Y12>0,1,-1)), (Y12-X12)/ABS(X12) ) -> 0.23592821 | Z96: =IF(Y12=0, IF(Z12=0,0,IF(Z12>0,1,-1)), (Z12-Y12)/ABS(Y12) ) -> 0.024692779 | AA96: =IF(Z12=0, IF(AA12=0,0,IF(AA12>0,1,-1)), (AA12-Z12)/ABS(Z12) ) -> -0.23765356
B97: Income before taxes | M97: =IF(L15=0, IF(M15=0,0,IF(M15>0,1,-1)), (M15-L15)/ABS(L15) ) -> -1 | N97: =IF(M15=0, IF(N15=0,0,IF(N15>0,1,-1)), (N15-M15)/ABS(M15) ) -> 1.9779512 | O97: =IF(N15=0, IF(O15=0,0,IF(O15>0,1,-1)), (O15-N15)/ABS(N15) ) -> -0.69682448 | P97: =IF(O15=0, IF(P15=0,0,IF(P15>0,1,-1)), (P15-O15)/ABS(O15) ) -> 4.7549643 | Q97: =IF(P15=0, IF(Q15=0,0,IF(Q15>0,1,-1)), (Q15-P15)/ABS(P15) ) -> 0.78298438 | T97: =IF(S15=0, IF(T15=0,0,IF(T15>0,1,-1)), (T15-S15)/ABS(S15) ) -> 1 | U97: =IF(T15=0, IF(U15=0,0,IF(U15>0,1,-1)), (U15-T15)/ABS(T15) ) -> -0.11961873 | V97: =IF(U15=0, IF(V15=0,0,IF(V15>0,1,-1)), (V15-U15)/ABS(U15) ) -> 0.56630279 | W97: =IF(V15=0, IF(W15=0,0,IF(W15>0,1,-1)), (W15-V15)/ABS(V15) ) -> 0.32676378 | X97: =IF(W15=0, IF(X15=0,0,IF(X15>0,1,-1)), (X15-W15)/ABS(W15) ) -> -2.1528525e-05 | Y97: =IF(X15=0, IF(Y15=0,0,IF(Y15>0,1,-1)), (Y15-X15)/ABS(X15) ) -> 0.17335142 | Z97: =IF(Y15=0, IF(Z15=0,0,IF(Z15>0,1,-1)), (Z15-Y15)/ABS(Y15) ) -> 0.01928405 | AA97: =IF(Z15=0, IF(AA15=0,0,IF(AA15>0,1,-1)), (AA15-Z15)/ABS(Z15) ) -> -0.18335974
B98: Net income | M98: =IF(L18=0, IF(M18=0,0,IF(M18>0,1,-1)), (M18-L18)/ABS(L18) ) -> -1 | N98: =IF(M18=0, IF(N18=0,0,IF(N18>0,1,-1)), (N18-M18)/ABS(M18) ) -> 0.0093290097 | O98: =IF(N18=0, IF(O18=0,0,IF(O18>0,1,-1)), (O18-N18)/ABS(N18) ) -> 1.2696982 | P98: =IF(O18=0, IF(P18=0,0,IF(P18>0,1,-1)), (P18-O18)/ABS(O18) ) -> 4.5127902 | Q98: =IF(P18=0, IF(Q18=0,0,IF(Q18>0,1,-1)), (Q18-P18)/ABS(P18) ) -> 0.77665003 | T98: =IF(S18=0, IF(T18=0,0,IF(T18>0,1,-1)), (T18-S18)/ABS(S18) ) -> 1 | U98: =IF(T18=0, IF(U18=0,0,IF(U18>0,1,-1)), (U18-T18)/ABS(T18) ) -> -0.4046661 | V98: =IF(U18=0, IF(V18=0,0,IF(V18>0,1,-1)), (V18-U18)/ABS(U18) ) -> 1.5264255 | W98: =IF(V18=0, IF(W18=0,0,IF(W18>0,1,-1)), (W18-V18)/ABS(V18) ) -> 0.27454106 | X98: =IF(W18=0, IF(X18=0,0,IF(X18>0,1,-1)), (X18-W18)/ABS(W18) ) -> -0.20736473 | Y98: =IF(X18=0, IF(Y18=0,0,IF(Y18>0,1,-1)), (Y18-X18)/ABS(X18) ) -> 0.18196929 | Z98: =IF(Y18=0, IF(Z18=0,0,IF(Z18>0,1,-1)), (Z18-Y18)/ABS(Y18) ) -> 0.035896458 | AA98: =IF(Z18=0, IF(AA18=0,0,IF(AA18>0,1,-1)), (AA18-Z18)/ABS(Z18) ) -> -0.23704556
B100: Margins
B101: Gross margin | M101: =M7/M5 -> 0.72410795 | N101: =N7/N5 -> 0.73090028 | O101: =O7/O5 -> 0.73243722 | P101: =P7/P5 -> 0.72775606 | Q101: =Q7/Q5 -> 0.72230623 | T101: =T7/T5 -> 0.72906736 | U101: =U7/U5 -> 0.7188022 | V101: =V7/V5 -> 0.7111635 | W101: =W7/W5 -> 0.72376667 | X101: =X7/X5 -> 0.72470217 | Y101: =Y7/Y5 -> 0.72779176 | Z101: =Z7/Z5 -> 0.72986331 | AA101: =AA7/AA5 -> 0.72620906 | AC101: =AC7/AC5 -> 0.72717428
B102: Operating margin | M102: =M12/M5 -> -0.23928908 | N102: =N12/N5 -> -0.17644352 | O102: =O12/O5 -> -0.024964744 | P102: =P12/P5 -> 0.08368047 | Q102: =Q12/Q5 -> 0.13065867 | T102: =T12/T5 -> 0.07047987 | U102: =U12/U5 -> 0.066246719 | V102: =V12/V5 -> 0.10225229 | W102: =W12/W5 -> 0.13225378 | X102: =X12/X5 -> 0.12939756 | Y102: =Y12/Y5 -> 0.15361936 | Z102: =Z12/Z5 -> 0.15250696 | AA102: =AA12/AA5 -> 0.11373612 | AC102: =AC12/AC5 -> 0.1371919
B103: Net margin | M103: =M111/M5 -> -0.2397995 | N103: =N111/N5 -> -0.16123087 | O103: =O111/O5 -> 0.030251794 | P103: =P111/P5 -> 0.11841064 | Q103: =Q111/Q5 -> 0.1516641 | T103: =T111/T5 -> 0.12129142 | U103: =U111/U5 -> 0.066366022 | V103: =V111/V5 -> 0.15226897 | W103: =W111/W5 -> 0.17751571 | X103: =X111/X5 -> 0.13063416 | Y103: =Y111/Y5 -> 0.14831653 | Z103: =Z111/Z5 -> 0.14885244 | AA103: =AA111/AA5 -> 0.1110992 | AC103: =AC111/AC5 -> 0.1345561
B105: Adjustments
B106: Tax rate | C106: =IF(AND(C83>=0,C12>=0),C83,0) -> 0 | D106: =IF(AND(D83>=0,D12>=0),D83,0) -> 0 | E106: =IF(AND(E83>=0,E12>=0),E83,0) -> 0 | F106: =IF(AND(F83>=0,F12>=0),F83,0) -> 0 | G106: =IF(AND(G83>=0,G12>=0),G83,0) -> 0 | H106: =IF(AND(H83>=0,H12>=0),H83,0) -> 0 | I106: =IF(AND(I83>=0,I12>=0),I83,0) -> 0 | J106: =IF(AND(J83>=0,J12>=0),J83,0) -> 0 | ... Q106: =IF(AND(Q83>=0,Q12>=0),Q83,0) -> 0.13730059 | T106: =IF(AND(T83>=0,T12>=0),T83,0) -> 0.079916499 | U106: =IF(AND(U83>=0,U12>=0),U83,0) -> 0.37781854 | V106: =IF(AND(V83>=0,V12>=0),V83,0) -> 0 | W106: =IF(AND(W83>=0,W12>=0),W83,0) -> 0.035931109 | X106: =IF(AND(X83>=0,X12>=0),X83,0) -> 0.23582854 | Y106: =IF(AND(Y83>=0,Y12>=0),Y83,0) -> 0.23021596 | Z106: =IF(AND(Z83>=0,Z12>=0),Z83,0) -> 0.21766993 | AA106: =IF(AND(AA83>=0,AA12>=0),AA83,0) -> 0.26910021 | AC106: =IF(AND(AC83>=0,AC12>=0),AC83,0) -> 0.23679335
B107: Cash | M107: =M29+M34 -> 553922 | N107: =N29+N34 -> 608180 | O107: =O29+O34 -> 747610 | P107: =P29+P34 -> 975937 | Q107: =Q29+Q34 -> 1275565 | T107: =T29+T34 -> 936091 | U107: =U29+U34 -> 975937 | V107: =V29+V34 -> 1082622 | W107: =W29+W34 -> 1173245 | X107: =X29+X34 -> 1220189 | Y107: =Y29+Y34 -> 1275565 | Z107: =Z29+Z34 -> 1391821 | AA107: =AA29+AA34 -> 1416559 | AC107: =AA107 -> 1416559
B108: Debt | C108: 0 | D108: 0 | E108: 0 | F108: 0 | G108: 0 | H108: 0 | I108: 0 | J108: 0 | K108: 0 | L108: 0 | M108: =M39+M41 -> 0 | N108: =N39+N41 -> 0 | O108: =O39+O41 -> 0 | P108: =P39+P41 -> 0 | Q108: =Q39+Q41 -> 0 | T108: =T39+T41 -> 0 | U108: =U39+U41 -> 0 | V108: =V39+V41 -> 0 | W108: =W39+W41 -> 0 | X108: =X39+X41 -> 0 | Y108: =Y39+Y41 -> 0 | Z108: =Z39+Z41 -> 0 | AA108: =AA39+AA41 -> 0 | AC108: =AA108 -> 0
B109: NOPAT | M109: =M12*(1-M106) -> -60007 | N109: =N12*(1-N106) -> -65195 | O109: =O12*(1-O106) -> -13259 | P109: =P12*(1-P106) -> 54193.2 | Q109: =Q12*(1-Q106) -> 116956.16 | AC109: =AC12*(1-AC106) -> 119888.32
B110: Capex | M110: =M60+M61 -> -6206 | N110: =N60+N61 -> -10124 | O110: =O60+O61 -> -13684 | P110: =P60+P61 -> -21140 | Q110: =Q60+Q61 -> -27399 | T110: =T60+T61 -> -5023 | U110: =U60+U61 -> -2440 | V110: =V60+V61 -> -2619 | W110: =W60+W61 -> -4351 | X110: =X60+X61 -> -6883 | Y110: =Y60+Y61 -> -13546 | Z110: =Z60+Z61 -> -2985 | AA110: =AA60+AA61 -> -9630 | AC110: =AC60+AC61 -> -33044
...

Sheet Analysis ->
H5: Links
H6: Overview'!B3
H7: Financials ->'!B13
H8: Analysis ->'!B13
H9: Forecast ->'!B13
H10: Valuation ->'!B13
B13: Analysis ->

Sheet Basic
B1: TTM/YTD data
B4: Overview | E4: CAGR
B5: Price | C5: =Overview!C5 -> 143.04 | F5: 5Y | G5: 10Y
B6: Market capitalization | C6: =Statement!AC149 -> 7169450.9 | E6: Revenue | F6: =IF(Statement!M5<=0,"N/A",_xlfn.RRI(4,Statement!M5,Statement!Q5)) -> 0.42622019 | G6: =IF(Statement!H5<=0,"N/A",_xlfn.RRI(9,Statement!H5,Statement!Q5)) -> N/A
B7: Enterprise value | C7: =Statement!AC150 -> 5752891.9 | E7: Net income | F7: =IF(OR(Statement!M18<=0, Statement!Q18<=0), "N/A", _xlfn.RRI(4, Statement!M18, Statement!Q18)) -> N/A | G7: =IF(OR(Statement!H18<=0, Statement!Q18<=0), "N/A", _xlfn.RRI(9, Statement!H18, Statement!Q18)) -> N/A
B8: PE | C8: =Statement!AC146 -> 45.545482 | E8: EPS | F8: =IF(OR(Statement!M26<=0, Statement!Q26<=0), "N/A", _xlfn.RRI(4, Statement!M26, Statement!Q26)) -> N/A | G8: =IF(OR(Statement!H26<=0, Statement!Q26<=0), "N/A", _xlfn.RRI(9, Statement!H26, Statement!Q26)) -> N/A
B9: PS | C9: =Statement!AC147 -> 6.1427774 | E9: Dividend | F9: =IF(Statement!M82<=0,"N/A",_xlfn.RRI(4,Statement!M82,Statement!Q82)) -> N/A | G9: =IF(Statement!H82<=0,"N/A",_xlfn.RRI(9,Statement!H82,Statement!Q82)) -> N/A
B10: PB | C10: =Statement!AC148 -> 4.747159 | E10: Price | F10: =IF(Statement!M117<=0,"N/A",_xlfn.RRI(4,Statement!M117,Statement!Q117)) -> 0.12501941 | G10: =IF(Statement!H117<=0,"N/A",_xlfn.RRI(9,Statement!H117,Statement!Q117)) -> N/A
B11: EV/Revenue | C11: =Statement!AC151 -> 5.0243509
B12: EV/EBIT | C12: =Statement!AC152 -> 36.622796
B15: Margins | E15: Earnings quality
B16: Gross margin | C16: =Statement!AC101 -> 0.72717428 | E16: Net income | F16: =Statement!AC18 -> 154067
B17: Operating margin | C17: =Statement!AC102 -> 0.1371919 | E17: Operating cash | F17: =Statement!AC59 -> 430548
B18: Net margin | C18: =Statement!AC103 -> 0.1345561 | E18: Cash accruals | F18: =IF(OR(F16<=0, F17<=0),"N/A",F16-F17) -> -276481
B21: DuPont Identity | E21: Performance indicators
B22: Profit Margin (Earnings/Revenue) | C22: =Statement!AC121 -> 0.1345561 | E22: ROA | F22: =C24 -> 0.07428664
B23: Asset Turnover (Revenue/Total assets) | C23: =Statement!AC122 -> 0.55208676 | E23: ROE | F23: =C26 -> 0.10928737
B24: ROA | C24: =Statement!AC123 -> 0.07428664 | E24: ROIC | F24: =Statement!AC136 -> -17.586668
B25: Equity Multiplier (Total assets/Equity) | C25: =Statement!AC124 -> 1.4711578
B26: ROE | C26: =Statement!AC125 -> 0.10928737
B29: Cash conversion cycle | E29: Liquidity ratios
B30: DSO | C30: =Statement!AC137 -> 41.753058 | E30: Debt/Equity | F30: =Statement!AC141 -> 0
B31: DIO | C31: =Statement!AC138 -> 0 | E31: Net Debt/Equity | F31: =Statement!AC142 -> -1.0048356
B32: DPO | C32: =Statement!AC139 -> 18.923831 | E32: Current ratio | F32: =Statement!AC144 -> 2.8920363
B33: Net trade cycle | C33: =Statement!AC140 -> 22.829227 | E33: Quick ratio | F33: =Statement!AC143 -> 2.6781752
E34: Interest coverage | F34: =Statement!AC145 -> N/A
B37: Earnings yields | E37: Payout ratios
B38: Earnings yield | C38: =Statement!AC158 -> 0.021956075 | E38: Dividend payout ratio | F38: =Statement!AC164 -> 0
B39: FCF yield | C39: =Statement!AC157 -> 0.03526351 | E39: Buyback payout ratio | F39: =Statement!AC165 -> 0.27530654
B40: Dividend yield | C40: =Statement!AC159 -> 0 | E40: Full payout ratio | F40: =Statement!AC166 -> 0.27530654
B41: Buyback yield | C41: =Statement!AC160 -> 0.0097082749
B42: Total shareholder yield | C42: =Statement!AC161 -> 0.0097082749
B45: Ownership | E45: Cash holdings
B46: Insider ownership | C46: =Statement!AC167 -> 0.1452057 | E46: Cash per share | F46: =Statement!AC168 -> 30.277412
E47: Net cash per share | F47: =Statement!AC171 -> 30.277412
E48: Net cash to market cap | F48: =Statement!AC172 -> 0.19758264
B51: Stock based compensation | E51: CapEx usage
B52: Stock based compensation % OCF | C52: =Statement!AC169 -> 0.33604616 | E52: Capex to Revenue | F52: =Statement!AC173 -> 0.028859338
B53: Stock based compensation % Revenue | C53: =Statement!AC170 -> 0.12636135 | E53: CapEx to OCF | F53: =Statement!AC174 -> 0.076748702
E54: CapEx to D&A | F54: =Statement!AC175 -> 2.0915248

Sheet Yearly Analysis
C2: =Statement!M2 -> 31.12.2021 | D2: =Statement!N2 -> 30.09.2022 | E2: =Statement!O2 -> 31.12.2023 | F2: =Statement!P2 -> 31.12.2024 | G2: =Statement!Q2 -> 31.12.2025
C3: =Statement!M3 -> 2021 | D3: =Statement!N3 -> 2022 | E3: =Statement!O3 -> 2023 | F3: =Statement!P3 -> 2024 | G3: =Statement!Q3 -> 2025 | I3: =Statement!AC3 -> TTM/YTD
B5: Overview
B6: Price | C6: =Statement!M116 -> 110.58 | D6: =Statement!N116 -> 71.13 | E6: =Statement!O116 -> 226.85 | F6: =Statement!P116 -> 325.2 | G6: =Statement!Q116 -> 177.14 | I6: =Statement!AC116 -> 143.04
B7: Market capitalization | C7: =Statement!M149 -> 4271152.5 | D7: =Statement!N149 -> 2890438.7 | E7: =Statement!O149 -> 10876777 | F7: =Statement!P149 -> 15882768 | G7: =Statement!Q149 -> 8845485.9 | I7: =Statement!AC149 -> 7169450.9
B8: Enterprise value | C8: =Statement!M150 -> 3717230.5 | D8: =Statement!N150 -> 2282258.7 | E8: =Statement!O150 -> 10129167 | F8: =Statement!P150 -> 14906831 | G8: =Statement!Q150 -> 7569920.9 | I8: =Statement!AC150 -> 5752891.9
B9: PE | C9: =Statement!M146 -> -43.027237 | D9: =Statement!N146 -> -47.10596 | E9: =Statement!O146 -> 648.14286 | F9: =Statement!P146 -> 172.97872 | G9: =Statement!Q146 -> 54.387137 | I9: =Statement!AC146 -> 45.545482
B10: PS | C10: =Statement!M147 -> 10.332976 | D10: =Statement!N147 -> 7.5982113 | E10: =Statement!O147 -> 19.870715 | F10: =Statement!P147 -> 20.476944 | G10: =Statement!Q147 -> 8.248576 | I10: =Statement!AC147 -> 6.1427774
B11: PB | C11: =Statement!M148 -> 8.3249246 | D11: =Statement!N148 -> 5.3321453 | E11: =Statement!O148 -> 14.838148 | F11: =Statement!P148 -> 17.843701 | G11: =Statement!Q148 -> 6.2334065 | I11: =Statement!AC148 -> 4.747159
B12: EV/Revenue | C12: =Statement!M151 -> 14.823148 | D12: =Statement!N151 -> 6.1766971 | E12: =Statement!O151 -> 19.071729 | F12: =Statement!P151 -> 19.928279 | G12: =Statement!Q151 -> 7.2956835 | I12: =Statement!AC151 -> 5.0243509
B13: EV/EBIT | C13: =Statement!M152 -> -61.946615 | D13: =Statement!N152 -> -35.006652 | E13: =Statement!O152 -> -763.94652 | F13: =Statement!P152 -> 238.14731 | G13: =Statement!Q152 -> 55.837729 | I13: =Statement!AC152 -> 36.622796
B15: Margins
B16: Gross margin | C16: =Statement!M101 -> 0.72410795 | D16: =Statement!N101 -> 0.73090028 | E16: =Statement!O101 -> 0.73243722 | F16: =Statement!P101 -> 0.72775606 | G16: =Statement!Q101 -> 0.72230623 | I16: =Statement!AC101 -> 0.72717428
B17: Operating margin | C17: =Statement!M102 -> -0.23928908 | D17: =Statement!N102 -> -0.17644352 | E17: =Statement!O102 -> -0.024964744 | F17: =Statement!P102 -> 0.08368047 | G17: =Statement!Q102 -> 0.13065867 | I17: =Statement!AC102 -> 0.1371919
B18: Net margin | C18: =Statement!M103 -> -0.2397995 | D18: =Statement!N103 -> -0.16123087 | E18: =Statement!O103 -> 0.030251794 | F18: =Statement!P103 -> 0.11841064 | G18: =Statement!Q103 -> 0.1516641 | I18: =Statement!AC103 -> 0.1345561
B20: Earnings quality
B21: Net income | C21: =Statement!M18 -> -60135 | D21: =Statement!N18 -> -59574 | E21: =Statement!O18 -> 16067 | F21: =Statement!P18 -> 88574 | G21: =Statement!Q18 -> 157365 | I21: =Statement!AC18 -> 154067
B22: Operating cash | C22: =Statement!M59 -> 9170 | D22: =Statement!N59 -> 53656 | E22: =Statement!O59 -> 153614 | F22: =Statement!P59 -> 285513 | G22: =Statement!Q59 -> 387823 | I22: =Statement!AC59 -> 430548
B23: Cash accruals | C23: =IF(OR(C21<=0, C22<=0),"N/A",C21-C22) -> N/A | D23: =IF(OR(D21<=0, D22<=0),"N/A",D21-D22) -> N/A | E23: =IF(OR(E21<=0, E22<=0),"N/A",E21-E22) -> -137547 | F23: =IF(OR(F21<=0, F22<=0),"N/A",F21-F22) -> -196939 | G23: =IF(OR(G21<=0, G22<=0),"N/A",G21-G22) -> -230458 | I23: =IF(OR(I21<=0, I22<=0),"N/A",I21-I22) -> -276481
B25: DuPont Identity
B26: Profit Margin (Earnings/Revenue) | C26: =Statement!M121 -> -0.2397995 | D26: =Statement!N121 -> -0.16123087 | E26: =Statement!O121 -> 0.030251794 | F26: =Statement!P121 -> 0.11841064 | G26: =Statement!Q121 -> 0.1516641 | I26: =Statement!AC121 -> 0.1345561
B27: Asset Turnover (Revenue/Total assets) | C27: =Statement!M122 -> 0.37920434 | D27: =Statement!N122 -> 0.49440889 | E27: =Statement!O122 -> 0.55674312 | F27: =Statement!P122 -> 0.57463925 | G27: =Statement!Q122 -> 0.52083043 | I27: =Statement!AC122 -> 0.55208676
B28: ROA | C28: =Statement!M123 -> -0.09093301 | D28: =Statement!N123 -> -0.079713975 | E28: =Statement!O123 -> 0.016842478 | F28: =Statement!P123 -> 0.068043401 | G28: =Statement!Q123 -> 0.078991277 | I28: =Statement!AC123 -> 0.07428664
B29: Equity Multiplier (Total assets/Equity) | C29: =Statement!M124 -> 1.2889646 | D29: =Statement!N124 -> 1.3786706 | E29: =Statement!O124 -> 1.4553098 | F29: =Statement!P124 -> 1.5787132 | G29: =Statement!Q124 -> 1.4789704 | I29: =Statement!AC124 -> 1.4711578
B30: ROE | C30: =Statement!M125 -> -0.11720943 | D30: =Statement!N125 -> -0.10989931 | E30: =Statement!O125 -> 0.024511023 | F30: =Statement!P125 -> 0.10742102 | G30: =Statement!Q125 -> 0.11682576 | I30: =Statement!AC125 -> 0.10928737
B32: Performance Indicators
B33: ROA | C33: =C28 -> -0.09093301 | D33: =D28 -> -0.079713975 | E33: =E28 -> 0.016842478 | F33: =F28 -> 0.068043401 | G33: =G28 -> 0.078991277 | I33: =I28 -> 0.07428664
B34: ROE | C34: =C30 -> -0.11720943 | D34: =D30 -> -0.10989931 | E34: =E30 -> 0.024511023 | F34: =F30 -> 0.10742102 | G34: =G30 -> 0.11682576 | I34: =I30 -> 0.10928737
B35: ROIC | C35: =Statement!M136 -> 1.4683845 | D35: =Statement!N136 -> 0.98627878 | E35: =Statement!O136 -> 0.14394902 | F35: =Statement!P136 -> -0.3579779 | G35: =Statement!Q136 -> 1.6371014 | I35: =Statement!AC136 -> -17.586668
B37: Cash conversion cycle
B38: DSO | C38: =Statement!M137 -> 48.268926 | D38: =Statement!N137 -> 46.159542 | E38: =Statement!O137 -> 61.147288 | F38: =Statement!P137 -> 62.908269 | G38: =Statement!Q137 -> 57.278802 | I38: =Statement!AC137 -> 41.753058
B39: DIO | C39: =Statement!M138 -> 0 | D39: =Statement!N138 -> 0 | E39: =Statement!O138 -> 0 | F39: =Statement!P138 -> 0 | G39: =Statement!Q138 -> 0 | I39: =Statement!AC138 -> 0
B40: DPO | C40: =Statement!M139 -> 41.244905 | D40: =Statement!N139 -> 4.3206344 | E40: =Statement!O139 -> 6.2851765 | F40: =Statement!P139 -> 11.436888 | G40: =Statement!Q139 -> 10.13171 | I40: =Statement!AC139 -> 18.923831
B41: Net trade cycle | C41: =Statement!M140 -> 7.0240205 | D41: =Statement!N140 -> 41.838908 | E41: =Statement!O140 -> 54.862112 | F41: =Statement!P140 -> 51.471381 | G41: =Statement!Q140 -> 47.147092 | I41: =Statement!AC140 -> 22.829227
B43: Liquidity ratios
B44: Debt/Equity | C44: =Statement!M141 -> 0 | D44: =Statement!N141 -> 0 | E44: =Statement!O141 -> 0 | F44: =Statement!P141 -> 0 | G44: =Statement!Q141 -> 0 | I44: =Statement!AC141 -> 0
B45: Net Debt/Equity | C45: =Statement!M142 -> -1.0796521 | D45: =Statement!N142 -> -1.1219419 | E45: =Statement!O142 -> -1.1405169 | F45: =Statement!P142 -> -1.1835995 | G45: =Statement!Q142 -> -0.94696312 | I45: =Statement!AC142 -> -1.0048356
B46: Quick ratio | C46: =Statement!M143 -> 4.9280624 | D46: =Statement!N143 -> 3.6030281 | E46: =Statement!O143 -> 3.0162207 | F46: =Statement!P143 -> 2.6167193 | G46: =Statement!Q143 -> 2.6098108 | I46: =Statement!AC143 -> 2.6781752
B47: Current ratio | C47: =Statement!M144 -> 5.1982356 | D47: =Statement!N144 -> 3.8356073 | E47: =Statement!O144 -> 3.2369178 | F47: =Statement!P144 -> 2.60897 | G47: =Statement!Q144 -> 2.6065703 | I47: =Statement!AC144 -> 2.8920363
B48: Interest coverage | C48: =Statement!M145 -> N/A | D48: =Statement!N145 -> N/A | E48: =Statement!O145 -> N/A | F48: =Statement!P145 -> N/A | G48: =Statement!Q145 -> N/A | I48: =Statement!AC145 -> N/A
B50: Earnings yields
B51: Earnings yield | C51: =Statement!M158 -> -0.023241092 | D51: =Statement!N158 -> -0.021228736 | E51: =Statement!O158 -> 0.0015428697 | F51: =Statement!P158 -> 0.0057810578 | G51: =Statement!Q158 -> 0.018386701 | I51: =Statement!AC158 -> 0.021956075
B52: FCF yield | C52: =Statement!M157 -> -0.0088594355 | D52: =Statement!N157 -> -0.010478686 | E52: =Statement!O157 -> 0.0041105008 | F52: =Statement!P157 -> 0.0096894949 | G52: =Statement!Q157 -> 0.02520913 | I52: =Statement!AC157 -> 0.03526351
B53: Dividend yield | C53: =Statement!M159 -> 0 | D53: =Statement!N159 -> 0 | E53: =Statement!O159 -> 0 | F53: =Statement!P159 -> 0 | G53: =Statement!Q159 -> 0 | I53: =Statement!AC159 -> 0
B54: Buyback yield | C54: =Statement!M160 -> 0.00020322384 | D54: =Statement!N160 -> 0 | E54: =Statement!O160 -> 0 | F54: =Statement!P160 -> 0 | G54: =Statement!Q160 -> 0 | I54: =Statement!AC160 -> 0.0097082749
B55: Total shareholder yield | C55: =Statement!M161 -> 0.00020322384 | D55: =Statement!N161 -> 0 | E55: =Statement!O161 -> 0 | F55: =Statement!P161 -> 0 | G55: =Statement!Q161 -> 0 | I55: =Statement!AC161 -> 0.0097082749
B57: Payout ratios
B58: Dividend payout ratio | C58: =Statement!M164 -> 0 | D58: =Statement!N164 -> 0 | E58: =Statement!O164 -> 0 | F58: =Statement!P164 -> 0 | G58: =Statement!Q164 -> 0 | I58: =Statement!AC164 -> 0
B59: Buyback payout ratio | C59: =Statement!M165 -> -0.022938689 | D59: =Statement!N165 -> 0 | E59: =Statement!O165 -> 0 | F59: =Statement!P165 -> 0 | G59: =Statement!Q165 -> 0 | I59: =Statement!AC165 -> 0.27530654
B60: Full payout ratio | C60: =Statement!M166 -> -0.022938689 | D60: =Statement!N166 -> 0 | E60: =Statement!O166 -> 0 | F60: =Statement!P166 -> 0 | G60: =Statement!Q166 -> 0 | I60: =Statement!AC166 -> 0.27530654
B62: Ownership
B63: Insider ownership | C63: =Statement!M167 -> 0.22397411 | D63: =Statement!N167 -> 0.20043804 | E63: =Statement!O167 -> 0.16445242 | F63: =Statement!P167 -> 0.1458231 | G63: =Statement!Q167 -> 0.14574947 | I63: =Statement!AC167 -> 0.1452057
B65: Cash holdings
B66: Cash per share | C66: =Statement!M168 -> 14.341023 | D66: =Statement!N168 -> 14.966532 | E66: =Statement!O168 -> 17.436561 | F66: =Statement!P168 -> 21.571005 | G66: =Statement!Q168 -> 26.910654 | I66: =Statement!AC168 -> 30.277412
B67: Net cash per share | C67: =Statement!M171 -> 14.341023 | D67: =Statement!N171 -> 14.966532 | E67: =Statement!O171 -> 17.436561 | F67: =Statement!P171 -> 21.571005 | G67: =Statement!Q171 -> 26.910654 | I67: =Statement!AC171 -> 30.277412
B68: Net cash to market cap | C68: =Statement!M172 -> 0.12968912 | D68: =Statement!N172 -> 0.21041097 | E68: =Statement!O172 -> 0.068734516 | F68: =Statement!P172 -> 0.061446279 | G68: =Statement!Q172 -> 0.14420519 | I68: =Statement!AC172 -> 0.19758264
B70: Stock Based Compensation
B71: Stock based compensation % OCF | C71: =Statement!M169 -> 4.4497274 | D71: =Statement!N169 -> 1.3758014 | E71: =Statement!O169 -> 0.61987189 | F71: =Statement!P169 -> 0.3869421 | G71: =Statement!Q169 -> 0.35438074 | I71: =Statement!AC169 -> 0.33604616
B72: Stock based compensation % Revenue | C72: =Statement!M170 -> 0.16271354 | D72: =Statement!N170 -> 0.19978619 | E72: =Statement!O170 -> 0.17928711 | F72: =Statement!P170 -> 0.14769179 | G72: =Statement!Q170 -> 0.13245803 | I72: =Statement!AC170 -> 0.12636135
B74: CapEx Usage
B75: Capex to Revenue | C75: =Statement!M173 -> 0.024747579 | D75: =Statement!N173 -> 0.027399559 | E75: =Statement!O173 -> 0.025764956 | F75: =Statement!P173 -> 0.028261125 | G75: =Statement!Q173 -> 0.026406409 | I75: =Statement!AC173 -> 0.028859338
B76: CapEx to OCF | C76: =Statement!M174 -> 0.67677208 | D76: =Statement!N174 -> 0.18868347 | E76: =Statement!O174 -> 0.089080422 | F76: =Statement!P174 -> 0.074042163 | G76: =Statement!Q174 -> 0.070648208 | I76: =Statement!AC174 -> 0.076748702
B77: CapEx to D&A | C77: =Statement!M175 -> 2.2765957 | D77: =Statement!N175 -> 2.0788501 | E77: =Statement!O175 -> 1.9286822 | F77: =Statement!P175 -> 1.9476691 | G77: =Statement!Q175 -> 1.9038983 | I77: =Statement!AC175 -> 2.0915248
B79: Growth rates
B80: Revenue | C80: =Statement!M89 -> 1 | D80: =Statement!N89 -> 0.47343005 | E80: =Statement!O89 -> 0.43739157 | F80: =Statement!P89 -> 0.40841899 | G80: =Statement!Q89 -> 0.38710656
B81: COGS | C81: =Statement!M90 -> 1 | D81: =Statement!N90 -> 0.43715492 | E81: =Statement!O90 -> 0.42918205 | F81: =Statement!P90 -> 0.43306006 | G81: =Statement!Q90 -> 0.41487392
B82: Gross Profit | C82: =Statement!M91 -> 1 | D82: =Statement!N91 -> 0.48725122 | E82: =Statement!O91 -> 0.44041412 | F82: =Statement!P91 -> 0.39941749 | G82: =Statement!Q91 -> 0.37671916
B83: OpEx | C83: =Statement!M95 -> 1 | D83: =Statement!N95 -> 0.38770163 | E83: =Statement!O95 -> 0.19985742 | F83: =Statement!P95 -> 0.1976841 | G83: =Statement!Q95 -> 0.27419549
B84: Operating Income | C84: =Statement!M96 -> -1 | D84: =Statement!N96 -> -0.08645658 | E84: =Statement!O96 -> 0.79662551 | F84: =Statement!P96 -> 5.7209443 | G84: =Statement!Q96 -> 1.1658279
B85: Net Income | C85: =Statement!M98 -> -1 | D85: =Statement!N98 -> 0.0093290097 | E85: =Statement!O98 -> 1.2696982 | F85: =Statement!P98 -> 4.5127902 | G85: =Statement!Q98 -> 0.77665003
B88: Growth rates breakdown
B89: =Statement!B191&" Revenue" -> Subscription Revenue | C89: =Statement!M191 -> 1 | D89: =Statement!N191 -> 0.51361388 | E89: =Statement!O191 -> 0.47961113 | F89: =Statement!P191 -> 0.50124789 | G89: =Statement!Q191 -> 0.43769125
B90: =Statement!B192&" Revenue" -> Advertising Revenue | C90: =Statement!M192 -> 1 | D90: =Statement!N192 -> 0.16181398 | E90: =Statement!O192 -> 0.1146185 | F90: =Statement!P192 -> 0.1012676 | G90: =Statement!Q192 -> 0.45200066
B91: =Statement!B193&" Revenue" -> English test Revenue | C91: =Statement!M193 -> 1 | D91: =Statement!N193 -> 0.3268716 | E91: =Statement!O193 -> 0.25961245 | F91: =Statement!P193 -> 0.10744443 | G91: =Statement!Q193 -> -0.079623138
B92: =Statement!B194&" Revenue" -> In-App purchases Revenue | C92: =Statement!M194 -> 1 | D92: =Statement!N194 -> 1.6809834 | E92: =Statement!O194 -> 0.87027348 | F92: =Statement!P194 -> 0.11478672 | G92: =Statement!Q194 -> 0.047240835
B93: =Statement!B195&" Revenue" -> Other Revenue | C93: =Statement!M195 -> 1 | D93: =Statement!N195 -> 6.9113924 | E93: =Statement!O195 -> 0.0912 | F93: =Statement!P195 -> 0.89589443 | G93: =Statement!Q195 -> 0.49806651
B95: Other growth rates
B96: Dividends | C96: =Statement!M199 -> 0 | D96: =Statement!N199 -> 0 | E96: =Statement!O199 -> 0 | F96: =Statement!P199 -> 0 | G96: =Statement!Q199 -> 0

Sheet Quarter analysis
C3: Latest 2 quarters | F3: YoY
C4: =Statement!Z2 -> 31.03.2026 | D4: =Statement!AA2 -> 30.06.2026 | F4: =Statement!W2 -> 30.06.2025 | G4: =Statement!AA2 -> 30.06.2026
B5: Income statement growth | C5: =Statement!Z3 -> Q1 2026 | D5: =Statement!AA3 -> Q2 2026 | F5: =Statement!W3 -> Q2 2025 | G5: =Statement!AA3 -> Q2 2026
B6: Revenue | C6: =Statement!Z5 -> 291967 | D6: =Statement!AA5 -> 298454 | F6: =Statement!W5 -> 252265 | G6: =Statement!AA5 -> 298454
B7: Growth | C7: =Statement!AA89 -> 0.022218264 | F7: =IF(F6=0, IF(G6=0,0,IF(G6>0,1,-1)), (G6-F6)/ABS(F6) ) -> 0.18309714
B8: COGS | C8: =Statement!Z6 -> 78871 | D8: =Statement!AA6 -> 81714 | F8: =Statement!W6 -> 69684 | G8: =Statement!AA6 -> 81714
B9: Growth | C9: =Statement!AA90 -> 0.036046202 | F9: =IF(F8=0, IF(G8=0,0,IF(G8>0,1,-1)), (G8-F8)/ABS(F8) ) -> 0.17263647
B10: Gross Profit | C10: =Statement!Z7 -> 213096 | D10: =Statement!AA7 -> 216740 | F10: =Statement!W7 -> 182581 | G10: =Statement!AA7 -> 216740
B11: Growth | C11: =Statement!AA91 -> 0.017100274 | F11: =IF(F10=0, IF(G10=0,0,IF(G10>0,1,-1)), (G10-F10)/ABS(F10) ) -> 0.18708957
B12: OpEx | C12: =Statement!Z11 -> 168569 | D12: =Statement!AA11 -> 182795 | F12: =Statement!W11 -> 149218 | G12: =Statement!AA11 -> 182795
B13: Growth | C13: =Statement!AA95 -> 0.084392741 | F13: =IF(F12=0, IF(G12=0,0,IF(G12>0,1,-1)), (G12-F12)/ABS(F12) ) -> 0.22501977
B14: Operating profit | C14: =Statement!Z12 -> 44527 | D14: =Statement!AA12 -> 33945 | F14: =Statement!W12 -> 33363 | G14: =Statement!AA12 -> 33945
B15: Growth | C15: =Statement!AA96 -> -0.23765356 | F15: =IF(F14=0, IF(G14=0,0,IF(G14>0,1,-1)), (G14-F14)/ABS(F14) ) -> 0.017444474
B16: Net income | C16: =Statement!Z18 -> 43460 | D16: =Statement!AA18 -> 33158 | F16: =Statement!W18 -> 44781 | G16: =Statement!AA18 -> 33158
B17: Growth | C17: =Statement!AA98 -> -0.23704556 | F17: =IF(F16=0, IF(G16=0,0,IF(G16>0,1,-1)), (G16-F16)/ABS(F16) ) -> -0.25955204
B18: Diluted shares outstanding | C18: =Statement!Z22 -> 48987 | D18: =Statement!AA22 -> 50239.394 | F18: =Statement!W22 -> 49000 | G18: =Statement!AA22 -> 50239.394
B19: Growth | C19: =IF(C18=0, IF(D18=0,0,IF(D18>0,1,-1)), (D18-C18)/ABS(C18) ) -> 0.025565843 | F19: =IF(F18=0, IF(G18=0,0,IF(G18>0,1,-1)), (G18-F18)/ABS(F18) ) -> 0.025293754
B20: Diluted EPS | C20: =Statement!Z26 -> 0.89 | D20: =Statement!AA26 -> 0.66 | F20: =Statement!W26 -> 0.91 | G20: =Statement!AA26 -> 0.66
B21: Growth | C21: =IF(C20=0, IF(D20=0,0,IF(D20>0,1,-1)), (D20-C20)/ABS(C20) ) -> -0.25842697 | F21: =IF(F20=0, IF(G20=0,0,IF(G20>0,1,-1)), (G20-F20)/ABS(F20) ) -> -0.27472527
B23: Revenue breakdown | C23: =C5 -> Q1 2026 | D23: =D5 -> Q2 2026 | F23: =F5 -> Q2 2025 | G23: =G5 -> Q2 2026
B24: =Statement!B183 -> Subscription | C24: =Statement!Z183 -> 250908 | D24: =Statement!AA183 -> 258035 | F24: =Statement!W183 -> 210678 | G24: =Statement!AA183 -> 258035
B25: Growth | C25: =IF(C24=0, IF(D24=0,0,IF(D24>0,1,-1)), (D24-C24)/ABS(C24) ) -> 0.028404834 | F25: =IF(F24=0, IF(G24=0,0,IF(G24>0,1,-1)), (G24-F24)/ABS(F24) ) -> 0.22478379
B26: =Statement!B184 -> Advertising | C26: =Statement!Z184 -> 20614 | D26: =Statement!AA184 -> 21052 | F26: =Statement!W184 -> 20603 | G26: =Statement!AA184 -> 21052
B27: Growth | C27: =IF(C26=0, IF(D26=0,0,IF(D26>0,1,-1)), (D26-C26)/ABS(C26) ) -> 0.021247696 | F27: =IF(F26=0, IF(G26=0,0,IF(G26>0,1,-1)), (G26-F26)/ABS(F26) ) -> 0.021792943
B28: =Statement!B185 -> English test | C28: =Statement!Z185 -> 11317 | D28: =Statement!AA185 -> 10109 | F28: =Statement!W185 -> 10088 | G28: =Statement!AA185 -> 10109
B29: Growth | C29: =IF(C28=0, IF(D28=0,0,IF(D28>0,1,-1)), (D28-C28)/ABS(C28) ) -> -0.10674207 | F29: =IF(F28=0, IF(G28=0,0,IF(G28>0,1,-1)), (G28-F28)/ABS(F28) ) -> 0.0020816812
B30: =Statement!B186 -> In-App purchases | C30: =Statement!Z186 -> 8446 | D30: =Statement!AA186 -> 8002 | F30: =Statement!W186 -> 10390 | G30: =Statement!AA186 -> 8002
B31: Growth | C31: =IF(C30=0, IF(D30=0,0,IF(D30>0,1,-1)), (D30-C30)/ABS(C30) ) -> -0.052569264 | F31: =IF(F30=0, IF(G30=0,0,IF(G30>0,1,-1)), (G30-F30)/ABS(F30) ) -> -0.22983638
B32: =Statement!B187 -> Other | C32: =Statement!Z187 -> 682 | D32: =Statement!AA187 -> 1256 | F32: =Statement!W187 -> 506 | G32: =Statement!AA187 -> 1256
B33: Growth | C33: =IF(C32=0, IF(D32=0,0,IF(D32>0,1,-1)), (D32-C32)/ABS(C32) ) -> 0.84164223 | F33: =IF(F32=0, IF(G32=0,0,IF(G32>0,1,-1)), (G32-F32)/ABS(F32) ) -> 1.4822134
B35: Metrics growth | C35: =C5 -> Q1 2026 | D35: =D5 -> Q2 2026 | F35: =F5 -> Q2 2025 | G35: =G5 -> Q2 2026
B36: =Statement!B209 -> DAU | C36: =Statement!Z209 -> 56500 | D36: =Statement!AA209 -> 58700 | F36: =Statement!W209 -> 47700 | G36: =Statement!AA209 -> 58700
B37: Growth | C37: =IF(C36=0, IF(D36=0,0,IF(D36>0,1,-1)), (D36-C36)/ABS(C36) ) -> 0.038938053 | F37: =IF(F36=0, IF(G36=0,0,IF(G36>0,1,-1)), (G36-F36)/ABS(F36) ) -> 0.23060797
B38: =Statement!B210 -> MAU | C38: =Statement!Z210 -> 137800 | D38: =Statement!AA210 -> 140600 | F38: =Statement!W210 -> 128300 | G38: =Statement!AA210 -> 140600
B39: Growth | C39: =IF(C38=0, IF(D38=0,0,IF(D38>0,1,-1)), (D38-C38)/ABS(C38) ) -> 0.020319303 | F39: =IF(F38=0, IF(G38=0,0,IF(G38>0,1,-1)), (G38-F38)/ABS(F38) ) -> 0.095869057
B40: =Statement!B211 -> Paid subscriberrs | C40: =Statement!Z211 -> 12500 | D40: =Statement!AA211 -> 12700 | F40: =Statement!W211 -> 10900 | G40: =Statement!AA211 -> 12700
B41: Growth | C41: =IF(C40=0, IF(D40=0,0,IF(D40>0,1,-1)), (D40-C40)/ABS(C40) ) -> 0.016 | F41: =IF(F40=0, IF(G40=0,0,IF(G40>0,1,-1)), (G40-F40)/ABS(F40) ) -> 0.16513761
B42: =Statement!B212 -> Free users | C42: =Statement!Z212 -> 125300 | D42: =Statement!AA212 -> 127900 | F42: =Statement!W212 -> 117400 | G42: =Statement!AA212 -> 127900
B43: Growth | C43: =IF(C42=0, IF(D42=0,0,IF(D42>0,1,-1)), (D42-C42)/ABS(C42) ) -> 0.0207502 | F43: =IF(F42=0, IF(G42=0,0,IF(G42>0,1,-1)), (G42-F42)/ABS(F42) ) -> 0.089437819
B44: =Statement!B213 -> Average revenue per paid user | C44: =Statement!Z213 -> 20.07264 | D44: =Statement!AA213 -> 20.317717 | F44: =Statement!W213 -> 19.328257 | G44: =Statement!AA213 -> 20.317717
B45: Growth | C45: =IF(C44=0, IF(D44=0,0,IF(D44>0,1,-1)), (D44-C44)/ABS(C44) ) -> 0.012209482 | F45: =IF(F44=0, IF(G44=0,0,IF(G44>0,1,-1)), (G44-F44)/ABS(F44) ) -> 0.05119239
B46: =Statement!B214 -> DAU to MAU ratio | C46: =Statement!Z214 -> 0.41001451 | D46: =Statement!AA214 -> 0.41749644 | F46: =Statement!W214 -> 0.37178488 | G46: =Statement!AA214 -> 0.41749644
B47: Growth | C47: =IF(C46=0, IF(D46=0,0,IF(D46>0,1,-1)), (D46-C46)/ABS(C46) ) -> 0.018247964 | F47: =IF(F46=0, IF(G46=0,0,IF(G46>0,1,-1)), (G46-F46)/ABS(F46) ) -> 0.12295165
B48: =Statement!B215 -> Subscribers to MAU ratio | C48: =Statement!Z215 -> 0.090711176 | D48: =Statement!AA215 -> 0.090327169 | F48: =Statement!W215 -> 0.084957132 | G48: =Statement!AA215 -> 0.090327169
B49: Growth | C49: =IF(C48=0, IF(D48=0,0,IF(D48>0,1,-1)), (D48-C48)/ABS(C48) ) -> -0.0042332859 | F49: =IF(F48=0, IF(G48=0,0,IF(G48>0,1,-1)), (G48-F48)/ABS(F48) ) -> 0.063208791
B50: =Statement!B216 -> Ad revenue per free user | C50: =Statement!Z216 -> 0.16451716 | D50: =Statement!AA216 -> 0.16459734 | F50: =Statement!W216 -> 0.17549404 | G50: =Statement!AA216 -> 0.16459734
B51: Growth | C51: =IF(C50=0, IF(D50=0,0,IF(D50>0,1,-1)), (D50-C50)/ABS(C50) ) -> 0.00048738293 | F51: =IF(F50=0, IF(G50=0,0,IF(G50>0,1,-1)), (G50-F50)/ABS(F50) ) -> -0.062091544
B52: =Statement!B217 -> In-app purchases % of DAU | C52: =Statement!Z217 -> 0.14948673 | D52: =Statement!AA217 -> 0.13632027 | F52: =Statement!W217 -> 0.21781971 | G52: =Statement!AA217 -> 0.13632027
B53: Growth | C53: =IF(C52=0, IF(D52=0,0,IF(D52>0,1,-1)), (D52-C52)/ABS(C52) ) -> -0.088077741 | F53: =IF(F52=0, IF(G52=0,0,IF(G52>0,1,-1)), (G52-F52)/ABS(F52) ) -> -0.37416006

Sheet Graphs Year
C55: =Statement!H2 -> 0 | D55: =Statement!I2 -> 0 | E55: =Statement!J2 -> 0 | F55: =Statement!K2 -> 0 | G55: =Statement!L2 -> 0 | H55: =Statement!M2 -> 31.12.2021 | I55: =Statement!N2 -> 30.09.2022 | J55: =Statement!O2 -> 31.12.2023 | ... L55: =Statement!Q2 -> 31.12.2025
C56: =Statement!H3 -> 0 | D56: =Statement!I3 -> 0 | E56: =Statement!J3 -> 0 | F56: =Statement!K3 -> 0 | G56: =Statement!L3 -> 0 | H56: =Statement!M3 -> 2021 | I56: =Statement!N3 -> 2022 | J56: =Statement!O3 -> 2023 | ... L56: =Statement!Q3 -> 2025
B57: Revenue | C57: =Statement!H5 -> 0 | D57: =Statement!I5 -> 0 | E57: =Statement!J5 -> 0 | F57: =Statement!K5 -> 0 | G57: =Statement!L5 -> 0 | H57: =Statement!M5 -> 250772 | I57: =Statement!N5 -> 369495 | J57: =Statement!O5 -> 531109 | ... L57: =Statement!Q5 -> 1037589
B58: Operating income | C58: =Statement!H12 -> 0 | D58: =Statement!I12 -> 0 | E58: =Statement!J12 -> 0 | F58: =Statement!K12 -> 0 | G58: =Statement!L12 -> 0 | H58: =Statement!M12 -> -60007 | I58: =Statement!N12 -> -65195 | J58: =Statement!O12 -> -13259 | ... L58: =Statement!Q12 -> 135570
B59: Net income | C59: =Statement!H18 -> 0 | D59: =Statement!I18 -> 0 | E59: =Statement!J18 -> 0 | F59: =Statement!K18 -> 0 | G59: =Statement!L18 -> 0 | H59: =Statement!M18 -> -60135 | I59: =Statement!N18 -> -59574 | J59: =Statement!O18 -> 16067 | ... L59: =Statement!Q18 -> 157365
B60: FCFE | C60: =Statement!H153 -> 0 | D60: =Statement!I153 -> 0 | E60: =Statement!J153 -> 0 | F60: =Statement!K153 -> 0 | G60: =Statement!L153 -> 0 | H60: =Statement!M153 -> -37840 | I60: =Statement!N153 -> -30288 | J60: =Statement!O153 -> 44709 | ... L60: =Statement!Q153 -> 222987
B61: FCFF | C61: =Statement!H154 -> 0 | D61: =Statement!I154 -> 0 | E61: =Statement!J154 -> 0 | F61: =Statement!K154 -> 0 | G61: =Statement!L154 -> 0 | H61: =Statement!M154 -> -37712 | I61: =Statement!N154 -> -35909 | J61: =Statement!O154 -> 15050 | ... L61: =Statement!Q154 -> 152914.16
B62: Gross margin | C62: =Statement!H101 -> 0 | D62: =Statement!I101 -> 0 | E62: =Statement!J101 -> 0 | F62: =Statement!K101 -> 0 | G62: =Statement!L101 -> 0 | H62: =Statement!M101 -> 0.72410795 | I62: =Statement!N101 -> 0.73090028 | J62: =Statement!O101 -> 0.73243722 | ... L62: =Statement!Q101 -> 0.72230623
B63: Operating margin | C63: =Statement!H102 -> 0 | D63: =Statement!I102 -> 0 | E63: =Statement!J102 -> 0 | F63: =Statement!K102 -> 0 | G63: =Statement!L102 -> 0 | H63: =Statement!M102 -> -0.23928908 | I63: =Statement!N102 -> -0.17644352 | J63: =Statement!O102 -> -0.024964744 | ... L63: =Statement!Q102 -> 0.13065867
B64: Net margin | C64: =Statement!H103 -> 0 | D64: =Statement!I103 -> 0 | E64: =Statement!J103 -> 0 | F64: =Statement!K103 -> 0 | G64: =Statement!L103 -> 0 | H64: =Statement!M103 -> -0.2397995 | I64: =Statement!N103 -> -0.16123087 | J64: =Statement!O103 -> 0.030251794 | ... L64: =Statement!Q103 -> 0.1516641
B65: ="Revenue "&Statement!B183 -> Revenue Subscription | C65: =Statement!H183 -> 0 | D65: =Statement!I183 -> 0 | E65: =Statement!J183 -> 0 | F65: =Statement!K183 -> 0 | G65: =Statement!L183 -> 0 | H65: =Statement!M183 -> 180698 | I65: =Statement!N183 -> 273507 | J65: =Statement!O183 -> 404684 | ... L65: =Statement!Q183 -> 873442
B66: ="Revenue "&Statement!B184 -> Revenue Advertising | C66: =Statement!H184 -> 0 | D66: =Statement!I184 -> 0 | E66: =Statement!J184 -> 0 | F66: =Statement!K184 -> 0 | G66: =Statement!L184 -> 0 | H66: =Statement!M184 -> 38501 | I66: =Statement!N184 -> 44731 | J66: =Statement!O184 -> 49858 | ... L66: =Statement!Q184 -> 79725
B67: ="Revenue "&Statement!B185 -> Revenue English test | C67: =Statement!H185 -> 0 | D67: =Statement!I185 -> 0 | E67: =Statement!J185 -> 0 | F67: =Statement!K185 -> 0 | G67: =Statement!L185 -> 0 | H67: =Statement!M185 -> 24658 | I67: =Statement!N185 -> 32718 | J67: =Statement!O185 -> 41212 | ... L67: =Statement!Q185 -> 42006
B68: ="Revenue "&Statement!B186 -> Revenue In-App purchases | C68: =Statement!H186 -> 0 | D68: =Statement!I186 -> 0 | E68: =Statement!J186 -> 0 | F68: =Statement!K186 -> 0 | G68: =Statement!L186 -> 0 | H68: =Statement!M186 -> 6915 | I68: =Statement!N186 -> 18539 | J68: =Statement!O186 -> 34673 | ... L68: =Statement!Q186 -> 40479
B69: ="Revenue "&Statement!B187 -> Revenue Other | C69: =Statement!H187 -> 0 | D69: =Statement!I187 -> 0 | E69: =Statement!J187 -> 0 | F69: =Statement!K187 -> 0 | G69: =Statement!L187 -> 0 | H69: =Statement!M187 -> 79 | I69: =Statement!N187 -> 625 | J69: =Statement!O187 -> 682 | ... L69: =Statement!Q187 -> 1937
B70: ROA | C70: =Statement!H123 -> 0 | D70: =Statement!I123 -> 0 | E70: =Statement!J123 -> 0 | F70: =Statement!K123 -> 0 | G70: =Statement!L123 -> 0 | H70: =Statement!M123 -> -0.09093301 | I70: =Statement!N123 -> -0.079713975 | J70: =Statement!O123 -> 0.016842478 | ... L70: =Statement!Q123 -> 0.078991277
B71: ROE | C71: =Statement!H125 -> 0 | D71: =Statement!I125 -> 0 | E71: =Statement!J125 -> 0 | F71: =Statement!K125 -> 0 | G71: =Statement!L125 -> 0 | H71: =Statement!M125 -> -0.11720943 | I71: =Statement!N125 -> -0.10989931 | J71: =Statement!O125 -> 0.024511023 | ... L71: =Statement!Q125 -> 0.11682576
B72: ROIC | C72: =Statement!H136 -> 0 | D72: =Statement!I136 -> 0 | E72: =Statement!J136 -> 0 | F72: =Statement!K136 -> 0 | G72: =Statement!L136 -> 0 | H72: =Statement!M136 -> 1.4683845 | I72: =Statement!N136 -> 0.98627878 | J72: =Statement!O136 -> 0.14394902 | ... L72: =Statement!Q136 -> 1.6371014
B73: Price 5y | C73: =Statement!H203 -> 0 | D73: =Statement!I203 -> 0 | E73: =Statement!J203 -> 0 | F73: =Statement!K203 -> 0 | G73: =Statement!L203 -> 0 | H73: =Statement!M203 -> 100 | I73: =Statement!N203 -> 64.324471 | J73: =Statement!O203 -> 205.1456 | ... L73: =Statement!Q203 -> 160.19172
B74: Revenue 5y | C74: =Statement!H204 -> 0 | D74: =Statement!I204 -> 0 | E74: =Statement!J204 -> 0 | F74: =Statement!K204 -> 0 | G74: =Statement!L204 -> 0 | H74: =Statement!M204 -> 100 | I74: =Statement!N204 -> 147.343 | J74: =Statement!O204 -> 211.78959 | ... L74: =Statement!Q204 -> 413.75792
B75: EPS 5y | C75: =Statement!H205 -> 0 | D75: =Statement!I205 -> 0 | E75: =Statement!J205 -> 0 | F75: =Statement!K205 -> 0 | G75: =Statement!L205 -> 0 | H75: =Statement!M205 -> 100 | I75: =Statement!N205 -> 141.24514 | J75: =Statement!O205 -> 213.61868 | ... L75: =Statement!Q205 -> 326.7323

Sheet Graphs Quarter
C55: =Statement!T2 -> 30.09.2024 | D55: =Statement!U2 -> 31.12.2024 | E55: =Statement!V2 -> 31.03.2025 | F55: =Statement!W2 -> 30.06.2025 | G55: =Statement!X2 -> 30.09.2025 | H55: =Statement!Y2 -> 31.12.2025 | I55: =Statement!Z2 -> 31.03.2026 | J55: =Statement!AA2 -> 30.06.2026
C56: =Statement!T3 -> Q3 2024 | D56: =Statement!U3 -> Q4 2024 | E56: =Statement!V3 -> Q1 2025 | F56: =Statement!W3 -> Q2 2025 | G56: =Statement!X3 -> Q3 2025 | H56: =Statement!Y3 -> Q4 2025 | I56: =Statement!Z3 -> Q1 2026 | J56: =Statement!AA3 -> Q2 2026
B57: Revenue | C57: =Statement!T5 -> 192594 | D57: =Statement!U5 -> 209550 | E57: =Statement!V5 -> 230743 | F57: =Statement!W5 -> 252265 | G57: =Statement!X5 -> 271713 | H57: =Statement!Y5 -> 282868 | I57: =Statement!Z5 -> 291967 | J57: =Statement!AA5 -> 298454
B58: Operating income | C58: =Statement!T12 -> 13574 | D58: =Statement!U12 -> 13882 | E58: =Statement!V12 -> 23594 | F58: =Statement!W12 -> 33363 | G58: =Statement!X12 -> 35159 | H58: =Statement!Y12 -> 43454 | I58: =Statement!Z12 -> 44527 | J58: =Statement!AA12 -> 33945
B59: Net income | C59: =Statement!T18 -> 23360 | D59: =Statement!U18 -> 13907 | E59: =Statement!V18 -> 35135 | F59: =Statement!W18 -> 44781 | G59: =Statement!X18 -> 35495 | H59: =Statement!Y18 -> 41954 | I59: =Statement!Z18 -> 43460 | J59: =Statement!AA18 -> 33158
B60: Gross margin | C60: =Statement!T101 -> 0.72906736 | D60: =Statement!U101 -> 0.7188022 | E60: =Statement!V101 -> 0.7111635 | F60: =Statement!W101 -> 0.72376667 | G60: =Statement!X101 -> 0.72470217 | H60: =Statement!Y101 -> 0.72779176 | I60: =Statement!Z101 -> 0.72986331 | J60: =Statement!AA101 -> 0.72620906
B61: Operating margin | C61: =Statement!T102 -> 0.07047987 | D61: =Statement!U102 -> 0.066246719 | E61: =Statement!V102 -> 0.10225229 | F61: =Statement!W102 -> 0.13225378 | G61: =Statement!X102 -> 0.12939756 | H61: =Statement!Y102 -> 0.15361936 | I61: =Statement!Z102 -> 0.15250696 | J61: =Statement!AA102 -> 0.11373612
B62: Net margin | C62: =Statement!T103 -> 0.12129142 | D62: =Statement!U103 -> 0.066366022 | E62: =Statement!V103 -> 0.15226897 | F62: =Statement!W103 -> 0.17751571 | G62: =Statement!X103 -> 0.13063416 | H62: =Statement!Y103 -> 0.14831653 | I62: =Statement!Z103 -> 0.14885244 | J62: =Statement!AA103 -> 0.1110992
B63: ="Revenue "&Statement!B183 -> Revenue Subscription | C63: =Statement!T183 -> 157617 | D63: =Statement!U183 -> 174317 | E63: =Statement!V183 -> 190987 | F63: =Statement!W183 -> 210678 | G63: =Statement!X183 -> 229491 | H63: =Statement!Y183 -> 242286 | I63: =Statement!Z183 -> 250908 | J63: =Statement!AA183 -> 258035
B64: ="Revenue "&Statement!B184 -> Revenue Advertising | C64: =Statement!T184 -> 14405 | D64: =Statement!U184 -> 14292 | E64: =Statement!V184 -> 17882 | F64: =Statement!W184 -> 20603 | G64: =Statement!X184 -> 21019 | H64: =Statement!Y184 -> 20221 | I64: =Statement!Z184 -> 20614 | J64: =Statement!AA184 -> 21052
B65: ="Revenue "&Statement!B185 -> Revenue English test | C65: =Statement!T185 -> 10772 | D65: =Statement!U185 -> 11415 | E65: =Statement!V185 -> 11986 | F65: =Statement!W185 -> 10088 | G65: =Statement!X185 -> 9649 | H65: =Statement!Y185 -> 10283 | I65: =Statement!Z185 -> 11317 | J65: =Statement!AA185 -> 10109
B66: ="Revenue "&Statement!B186 -> Revenue In-App purchases | C66: =Statement!T186 -> 9411 | D66: =Statement!U186 -> 9142 | E66: =Statement!V186 -> 9442 | F66: =Statement!W186 -> 10390 | G66: =Statement!X186 -> 11096 | H66: =Statement!Y186 -> 9551 | I66: =Statement!Z186 -> 8446 | J66: =Statement!AA186 -> 8002
B67: ="Revenue "&Statement!B187 -> Revenue Other | C67: =Statement!T187 -> 389 | D67: =Statement!U187 -> 384 | E67: =Statement!V187 -> 446 | F67: =Statement!W187 -> 506 | G67: =Statement!X187 -> 458 | H67: =Statement!Y187 -> 527 | I67: =Statement!Z187 -> 682 | J67: =Statement!AA187 -> 1256
B68: FCFE | C68: =Statement!T153 -> 22285 | D68: =Statement!U153 -> 51117 | E68: =Statement!V153 -> 71994 | F68: =Statement!W153 -> 51732 | G68: =Statement!X153 -> 41791 | H68: =Statement!Y153 -> 57470 | I68: =Statement!Z153 -> 113139 | J68: =Statement!AA153 -> 40420

Sheet Forecast ->
H5: Links
H6: Overview'!B3
H7: Financials ->'!B13
H8: Analysis ->'!B13
H9: Forecast ->'!B13
H10: Valuation ->'!B13
B13: Forecast ->

Sheet Revenue
B1: Revenue forecast
C2: History | H2: Forecast | S2: History | AA2: Forecast | AE2: TTM/YTD
C4: Revenues | S4: Revenues
B5: Revenues (thousand) | C5: =Statement!M3 -> 2021 | D5: =Statement!N3 -> 2022 | E5: =Statement!O3 -> 2023 | F5: =Statement!P3 -> 2024 | G5: =Statement!Q3 -> 2025 | H5: =G5+1 -> 2026 | I5: =H5+1 -> 2027 | J5: =I5+1 -> 2028 | K5: =J5+1 -> 2029 | L5: =K5+1 -> 2030 | R5: =B5 -> Revenues (thousand) | S5: =Statement!T3 -> Q3 2024 | T5: =Statement!U3 -> Q4 2024 | U5: =Statement!V3 -> Q1 2025 | V5: =Statement!W3 -> Q2 2025 | W5: =Statement!X3 -> Q3 2025 | X5: =Statement!Y3 -> Q4 2025 | Y5: =Statement!Z3 -> Q1 2026 | Z5: =Statement!AA3 -> Q2 2026 | AA5: FQ1 | AB5: FQ2 | AC5: FQ3 | AE5: FQ1
B6: =Statement!B183 -> Subscription | C6: =Statement!M183 -> 180698 | D6: =Statement!N183 -> 273507 | E6: =Statement!O183 -> 404684 | F6: =Statement!P183 -> 607531 | G6: =Statement!Q183 -> 873442 | H6: =H37*H34 -> 1024390.1 | I6: =I37*I34 -> 1165141.3 | J6: =J37*J34 -> 1488468 | K6: =K37*K34 -> 2031452.9 | L6: =L37*L34 -> 2773542.7 | N6: Avg revenue/Paid user * Paid subscribers | Q6: Avg revenue/Paid user * Paid subscribers | R6: =B6 -> Subscription | S6: =Statement!T183 -> 157617 | T6: =Statement!U183 -> 174317 | U6: =Statement!V183 -> 190987 | V6: =Statement!W183 -> 210678 | W6: =Statement!X183 -> 229491 | X6: =Statement!Y183 -> 242286 | Y6: =Statement!Z183 -> 250908 | Z6: =Statement!AA183 -> 258035 | AA6: =AA37*AA34 -> 258876.8 | AE6: =SUM(X6:AA6) -> 1010105.8
B7: =Statement!B184 -> Advertising | C7: =Statement!M184 -> 38501 | D7: =Statement!N184 -> 44731 | E7: =Statement!O184 -> 49858 | F7: =Statement!P184 -> 54907 | G7: =Statement!Q184 -> 79725 | H7: =H35*H31 -> 101116.2 | I7: =I35*I31 -> 124816.88 | J7: =J35*J31 -> 150067.49 | K7: =K35*K31 -> 188412.22 | L7: =L35*L31 -> 232290.48 | N7: Free users * Ad revenue/Free user | Q7: Free users * Ad revenue/Free user | R7: =B7 -> Advertising | S7: =Statement!T184 -> 14405 | T7: =Statement!U184 -> 14292 | U7: =Statement!V184 -> 17882 | V7: =Statement!W184 -> 20603 | W7: =Statement!X184 -> 21019 | X7: =Statement!Y184 -> 20221 | Y7: =Statement!Z184 -> 20614 | Z7: =Statement!AA184 -> 21052 | AA7: =AA35*AA31 -> 22657.627 | AE7: =SUM(X7:AA7) -> 84544.627
B8: =Statement!B185 -> English test | C8: =Statement!M185 -> 24658 | D8: =Statement!N185 -> 32718 | E8: =Statement!O185 -> 41212 | F8: =Statement!P185 -> 45640 | G8: =Statement!Q185 -> 42006 | H8: =G8*(1+H25) -> 39905.7 | I8: =H8*(1+I25) -> 39107.586 | J8: =I8*(1+J25) -> 40280.814 | K8: =J8*(1+K25) -> 42697.662 | L8: =K8*(1+L25) -> 46113.475 | N8: English test growth rate | Q8: English test growth rate | R8: =B8 -> English test | S8: =Statement!T185 -> 10772 | T8: =Statement!U185 -> 11415 | U8: =Statement!V185 -> 11986 | V8: =Statement!W185 -> 10088 | W8: =Statement!X185 -> 9649 | X8: =Statement!Y185 -> 10283 | Y8: =Statement!Z185 -> 11317 | Z8: =Statement!AA185 -> 10109 | AA8: =Z8*(1+AA25) -> 10614.45 | AE8: =SUM(X8:AA8) -> 42323.45
B9: =Statement!B186 -> In-App purchases | C9: =Statement!M186 -> 6915 | D9: =Statement!N186 -> 18539 | E9: =Statement!O186 -> 34673 | F9: =Statement!P186 -> 38653 | G9: =Statement!Q186 -> 40479 | H9: =H27*H36 -> 44900.4 | I9: =I27*I36 -> 51382.5 | J9: =J27*J36 -> 60236.1 | K9: =K27*K36 -> 82874.834 | L9: =L27*L36 -> 106079.79 | N9: DAU * In-app purchases % of DAU | Q9: DAU * In-app purchases % of DAU | R9: =B9 -> In-App purchases | S9: =Statement!T186 -> 9411 | T9: =Statement!U186 -> 9142 | U9: =Statement!V186 -> 9442 | V9: =Statement!W186 -> 10390 | W9: =Statement!X186 -> 11096 | X9: =Statement!Y186 -> 9551 | Y9: =Statement!Z186 -> 8446 | Z9: =Statement!AA186 -> 8002 | AA9: =AA27*AA36 -> 7607.52 | AE9: =SUM(X9:AA9) -> 33606.52
B10: =Statement!B187 -> Other | C10: =Statement!M187 -> 79 | D10: =Statement!N187 -> 625 | E10: =Statement!O187 -> 682 | F10: =Statement!P187 -> 1293 | G10: =Statement!Q187 -> 1937 | H10: =G10*(1+H26) -> 2808.65 | I10: =H10*(1+I26) -> 3791.6775 | J10: =I10*(1+J26) -> 4929.1808 | K10: =J10*(1+K26) -> 6161.4759 | L10: =K10*(1+L26) -> 7393.7711 | N10: Other growth rate | Q10: Other growth rate | R10: =B10 -> Other | S10: =Statement!T187 -> 389 | T10: =Statement!U187 -> 384 | U10: =Statement!V187 -> 446 | V10: =Statement!W187 -> 506 | W10: =Statement!X187 -> 458 | X10: =Statement!Y187 -> 527 | Y10: =Statement!Z187 -> 682 | Z10: =Statement!AA187 -> 1256 | AA10: =Z10*(1+AA26) -> 1142.96 | AE10: =SUM(X10:AA10) -> 3607.96
B11: Total | C11: =Statement!M5 -> 250772 | D11: =Statement!N5 -> 369495 | E11: =Statement!O5 -> 531109 | F11: =Statement!P5 -> 748024 | G11: =Statement!Q5 -> 1037589 | H11: =SUM(H6:H10) -> 1213121 | I11: =SUM(I6:I10) -> 1384239.9 | J11: =SUM(J6:J10) -> 1743981.6 | K11: =SUM(K6:K10) -> 2351599.1 | L11: =SUM(L6:L10) -> 3165420.2 | R11: Total | S11: =Statement!T5 -> 192594 | T11: =Statement!U5 -> 209550 | U11: =Statement!V5 -> 230743 | V11: =Statement!W5 -> 252265 | W11: =Statement!X5 -> 271713 | X11: =Statement!Y5 -> 282868 | Y11: =Statement!Z5 -> 291967 | Z11: =Statement!AA5 -> 298454 | AA11: =SUM(AA6:AA10) -> 300899.36 | AE11: =SUM(X11:AA11) -> 1174188.4
C13: Growth rates | S13: Growth rates
B14: Revenue growth % | C14: =C5 -> 2021 | D14: =D5 -> 2022 | E14: =E5 -> 2023 | F14: =F5 -> 2024 | G14: =G5 -> 2025 | H14: =H5 -> 2026 | I14: =I5 -> 2027 | J14: =J5 -> 2028 | ... L14: =L5 -> 2030 | R14: Revenue growth % | S14: =S5 -> Q3 2024 | T14: =T5 -> Q4 2024 | U14: =U5 -> Q1 2025 | V14: =V5 -> Q2 2025 | W14: =W5 -> Q3 2025 | X14: =X5 -> Q4 2025 | Y14: =Y5 -> Q1 2026 | Z14: =Z5 -> Q2 2026 | ... AC14: =AC5 -> FQ3
B15: =B6 -> Subscription | D15: =D6/C6-1 -> 0.51361388 | E15: =E6/D6-1 -> 0.47961113 | F15: =F6/E6-1 -> 0.50124789 | G15: =G6/F6-1 -> 0.43769125 | H15: =H6/G6-1 -> 0.17281981 | I15: =I6/H6-1 -> 0.1374 | J15: =J6/I6-1 -> 0.2775 | K15: =K6/J6-1 -> 0.36479452 | L15: =L6/K6-1 -> 0.3653 | R15: =R6 -> Subscription | T15: =T6/S6-1 -> 0.10595304 | U15: =U6/T6-1 -> 0.095630375 | V15: =V6/U6-1 -> 0.10310126 | W15: =W6/V6-1 -> 0.089297411 | X15: =X6/W6-1 -> 0.05575382 | Y15: =Y6/X6-1 -> 0.035586043 | Z15: =Z6/Y6-1 -> 0.028404834 | AA15: =AA6/Z6-1 -> 0.0032623481
B16: =B7 -> Advertising | D16: =D7/C7-1 -> 0.16181398 | E16: =E7/D7-1 -> 0.1146185 | F16: =F7/E7-1 -> 0.1012676 | G16: =G7/F7-1 -> 0.45200066 | H16: =H7/G7-1 -> 0.26831237 | I16: =I7/H7-1 -> 0.23439052 | J16: =J7/I7-1 -> 0.20230118 | K16: =K7/J7-1 -> 0.2555166 | L16: =L7/K7-1 -> 0.23288436 | R16: =R7 -> Advertising | T16: =T7/S7-1 -> -0.0078444984 | U16: =U7/T7-1 -> 0.25118948 | V16: =V7/U7-1 -> 0.15216419 | W16: =W7/V7-1 -> 0.020191234 | X16: =X7/W7-1 -> -0.03796565 | Y16: =Y7/X7-1 -> 0.019435241 | Z16: =Z7/Y7-1 -> 0.021247696 | AA16: =AA7/Z7-1 -> 0.07626958
B17: =B8 -> English test | D17: =D8/C8-1 -> 0.3268716 | E17: =E8/D8-1 -> 0.25961245 | F17: =F8/E8-1 -> 0.10744443 | G17: =G8/F8-1 -> -0.079623138 | H17: =H8/G8-1 -> -0.05 | I17: =I8/H8-1 -> -0.02 | J17: =J8/I8-1 -> 0.03 | K17: =K8/J8-1 -> 0.06 | L17: =L8/K8-1 -> 0.08 | R17: =R8 -> English test | T17: =T8/S8-1 -> 0.059691794 | U17: =U8/T8-1 -> 0.050021901 | V17: =V8/U8-1 -> -0.15835141 | W17: =W8/V8-1 -> -0.04351705 | X17: =X8/W8-1 -> 0.065706291 | Y17: =Y8/X8-1 -> 0.10055431 | Z17: =Z8/Y8-1 -> -0.10674207 | AA17: =AA8/Z8-1 -> 0.05
B18: =B9 -> In-App purchases | D18: =D9/C9-1 -> 1.6809834 | E18: =E9/D9-1 -> 0.87027348 | F18: =F9/E9-1 -> 0.11478672 | G18: =G9/F9-1 -> 0.047240835 | H18: =H9/G9-1 -> 0.10922701 | I18: =I9/H9-1 -> 0.1443662 | J18: =J9/I9-1 -> 0.17230769 | K18: =K9/J9-1 -> 0.37583333 | L18: =L9/K9-1 -> 0.28 | R18: =R9 -> In-App purchases | T18: =T9/S9-1 -> -0.028583572 | U18: =U9/T9-1 -> 0.032815576 | V18: =V9/U9-1 -> 0.10040246 | W18: =W9/V9-1 -> 0.067949952 | X18: =X9/W9-1 -> -0.13923937 | Y18: =Y9/X9-1 -> -0.11569469 | Z18: =Z9/Y9-1 -> -0.052569264 | AA18: =AA9/Z9-1 -> -0.049297676
B19: =B10 -> Other | D19: =D10/C10-1 -> 6.9113924 | E19: =E10/D10-1 -> 0.0912 | F19: =F10/E10-1 -> 0.89589443 | G19: =G10/F10-1 -> 0.49806651 | H19: =H10/G10-1 -> 0.45 | I19: =I10/H10-1 -> 0.35 | J19: =J10/I10-1 -> 0.3 | K19: =K10/J10-1 -> 0.25 | L19: =L10/K10-1 -> 0.2 | R19: =R10 -> Other | T19: =T10/S10-1 -> -0.01285347 | U19: =U10/T10-1 -> 0.16145833 | V19: =V10/U10-1 -> 0.13452915 | W19: =W10/V10-1 -> -0.09486166 | X19: =X10/W10-1 -> 0.15065502 | Y19: =Y10/X10-1 -> 0.29411765 | Z19: =Z10/Y10-1 -> 0.84164223 | AA19: =AA10/Z10-1 -> -0.09
B20: =B11 -> Total | D20: =D11/C11-1 -> 0.47343005 | E20: =E11/D11-1 -> 0.43739157 | F20: =F11/E11-1 -> 0.40841899 | G20: =G11/F11-1 -> 0.38710656 | H20: =H11/G11-1 -> 0.16917299 | I20: =I11/H11-1 -> 0.14105673 | J20: =J11/I11-1 -> 0.25988388 | K20: =K11/J11-1 -> 0.34840826 | L20: =L11/K11-1 -> 0.34607135 | R20: =R11 -> Total | T20: =T11/S11-1 -> 0.088040126 | U20: =U11/T11-1 -> 0.10113577 | V20: =V11/U11-1 -> 0.093272602 | W20: =W11/V11-1 -> 0.077093533 | X20: =X11/W11-1 -> 0.041054348 | Y20: =Y11/X11-1 -> 0.032166947 | Z20: =Z11/Y11-1 -> 0.022218264 | AA20: =AA11/Z11-1 -> 0.0081934141
C23: Drivers and metrics | S23: Drivers and metrics | AE23: =AE2 -> TTM/YTD
B24: Metric (thousand) | C24: =C5 -> 2021 | D24: =D5 -> 2022 | E24: =E5 -> 2023 | F24: =F5 -> 2024 | G24: =G5 -> 2025 | H24: =H5 -> 2026 | I24: =I5 -> 2027 | J24: =J5 -> 2028 | ... L24: =L5 -> 2030 | R24: Metric (thousand) | S24: =S5 -> Q3 2024 | T24: =T5 -> Q4 2024 | U24: =U5 -> Q1 2025 | V24: =V5 -> Q2 2025 | W24: =W5 -> Q3 2025 | X24: =X5 -> Q4 2025 | Y24: =Y5 -> Q1 2026 | Z24: =Z5 -> Q2 2026 | ... AC24: =AC5 -> FQ3 | AE24: =AE5 -> FQ1
B25: English test growth rate | D25: =D17 -> 0.3268716 | E25: =E17 -> 0.25961245 | F25: =F17 -> 0.10744443 | G25: =G17 -> -0.079623138 | H25: -0.05 | I25: -0.02 | J25: 0.03 | K25: 0.06 | L25: 0.08 | R25: English test growth rate | T25: =T17 -> 0.059691794 | U25: =U17 -> 0.050021901 | V25: =V17 -> -0.15835141 | W25: =W17 -> -0.04351705 | X25: =X17 -> 0.065706291 | Y25: =Y17 -> 0.10055431 | Z25: =Z17 -> -0.10674207 | AA25: 0.05
B26: Other growth rate | D26: =D19 -> 6.9113924 | E26: =E19 -> 0.0912 | F26: =F19 -> 0.89589443 | G26: =G19 -> 0.49806651 | H26: 0.45 | I26: 0.35 | J26: 0.3 | K26: 0.25 | L26: 0.2 | R26: Other growth rate | T26: =T19 -> -0.01285347 | U26: =U19 -> 0.16145833 | V26: =V19 -> 0.13452915 | W26: =W19 -> -0.09486166 | X26: =X19 -> 0.15065502 | Y26: =Y19 -> 0.29411765 | Z26: =Z19 -> 0.84164223 | AA26: -0.09
B27: DAU | C27: =Statement!M209 -> 9600 | D27: =Statement!N209 -> 16300 | E27: =Statement!O209 -> 26900 | F27: =Statement!P209 -> 40500 | G27: =Statement!Q209 -> 52700 | H27: =G27*(1+H29) -> 63240 | I27: =H27*(1+I29) -> 79050 | J27: =I27*(1+J29) -> 100393.5 | K27: =J27*(1+K29) -> 127499.74 | L27: =K27*(1+L29) -> 163199.67 | N27: DAU growth rate | Q27: DAU growth rate | R27: DAU | S27: =Statement!T209 -> 37200 | T27: =Statement!U209 -> 40500 | U27: =Statement!V209 -> 46600 | V27: =Statement!W209 -> 47700 | W27: =Statement!X209 -> 50500 | X27: =Statement!Y209 -> 52700 | Y27: =Statement!Z209 -> 56500 | Z27: =Statement!AA209 -> 58700 | AA27: =Z27*(1+AA29) -> 63396 | AE27: =AA27 -> 63396
B28: MAU | C28: =Statement!M210 -> 40500 | D28: =Statement!N210 -> 60700 | E28: =Statement!O210 -> 88400 | F28: =Statement!P210 -> 116700 | G28: =Statement!Q210 -> 133100 | H28: =G28*(1+H30) -> 158389 | I28: =H28*(1+I30) -> 191650.69 | J28: =I28*(1+J30) -> 234772.1 | K28: =J28*(1+K30) -> 288769.68 | L28: =K28*(1+L30) -> 355186.7 | N28: MAU growth rate | Q28: MAU growth rate | R28: MAU | S28: =Statement!T210 -> 113100 | T28: =Statement!U210 -> 116700 | U28: =Statement!V210 -> 130200 | V28: =Statement!W210 -> 128300 | W28: =Statement!X210 -> 135300 | X28: =Statement!Y210 -> 133100 | Y28: =Statement!Z210 -> 137800 | Z28: =Statement!AA210 -> 140600 | AA28: =Z28*(1+AA30) -> 146224 | AE28: =AA28 -> 146224
B29: DAU growth rate | D29: =D27/C27-1 -> 0.69791667 | E29: =E27/D27-1 -> 0.65030675 | F29: =F27/E27-1 -> 0.50557621 | G29: =G27/F27-1 -> 0.30123457 | H29: 0.2 | I29: 0.25 | J29: 0.27 | K29: 0.27 | L29: 0.28 | R29: DAU growth rate | T29: =T27/S27-1 -> 0.088709677 | U29: =U27/T27-1 -> 0.15061728 | V29: =V27/U27-1 -> 0.02360515 | W29: =W27/V27-1 -> 0.05870021 | X29: =X27/W27-1 -> 0.043564356 | Y29: =Y27/X27-1 -> 0.072106262 | Z29: =Z27/Y27-1 -> 0.038938053 | AA29: 0.08
B30: MAU growth rate | D30: =D28/C28-1 -> 0.49876543 | E30: =E28/D28-1 -> 0.45634267 | F30: =F28/E28-1 -> 0.32013575 | G30: =G28/F28-1 -> 0.14053128 | H30: 0.19 | I30: 0.21 | J30: 0.225 | K30: 0.23 | L30: 0.23 | R30: MAU growth rate | T30: =T28/S28-1 -> 0.031830239 | U30: =U28/T28-1 -> 0.11568123 | V30: =V28/U28-1 -> -0.014592934 | W30: =W28/V28-1 -> 0.054559626 | X30: =X28/W28-1 -> -0.016260163 | Y30: =Y28/X28-1 -> 0.035311796 | Z30: =Z28/Y28-1 -> 0.020319303 | AA30: 0.04
B31: Ad revenue/Free user | C31: =Statement!M216 -> 1.0131842 | D31: =Statement!N216 -> 0.79169912 | E31: =Statement!O216 -> 0.609511 | F31: =Statement!P216 -> 0.51219216 | G31: =Statement!Q216 -> 0.65942928 | H31: 0.7 | I31: 0.71 | J31: 0.7 | K31: 0.72 | L31: 0.73 | R31: Ad revenue/Free user | S31: =Statement!T216 -> 0.13784689 | T31: =Statement!U216 -> 0.1333209 | U31: =Statement!V216 -> 0.14914095 | V31: =Statement!W216 -> 0.17549404 | W31: =Statement!X216 -> 0.16978191 | X31: =Statement!Y216 -> 0.16725393 | Y31: =Statement!Z216 -> 0.16451716 | Z31: =Statement!AA216 -> 0.16459734 | AA31: 0.17 | AE31: =AE7/AE35 -> 0.63433768
B32: Subscribers to MAU ratio | C32: =Statement!M215 -> 0.061728395 | D32: =Statement!N215 -> 0.069192751 | E32: =Statement!O215 -> 0.074660633 | F32: =Statement!P215 -> 0.081405313 | G32: =Statement!Q215 -> 0.091660406 | H32: =G32*(1+H33) -> 0.087993989 | I32: =H32*(1+I33) -> 0.08271435 | J32: =I32*(1+J33) -> 0.086850068 | K32: =J32*(1+K33) -> 0.093798073 | L32: =K32*(1+L33) -> 0.10411586 | N32: Subscribers to MAU growth | Q32: Subscribers to MAU growth | R32: Subscribers to MAU ratio | S32: =Statement!T215 -> 0.076038904 | T32: =Statement!U215 -> 0.081405313 | U32: =Statement!V215 -> 0.079109063 | V32: =Statement!W215 -> 0.084957132 | W32: =Statement!X215 -> 0.084996305 | X32: =Statement!Y215 -> 0.091660406 | Y32: =Statement!Z215 -> 0.090711176 | Z32: =Statement!AA215 -> 0.090327169 | AA32: =Z32*(1+AA33) -> 0.088520626
B33: Subscribers to MAU growth | D33: =D32/C32-1 -> 0.12092257 | E33: =E32/D32-1 -> 0.079023917 | F33: =F32/E32-1 -> 0.090337826 | G33: =G32/F32-1 -> 0.12597572 | H33: -0.04 | I33: -0.06 | J33: 0.05 | K33: 0.08 | L33: 0.11 | R33: Subscribers to MAU growth | T33: -1 | U33: =U32/T32-1 -> -0.028207616 | V33: =V32/U32-1 -> 0.073924131 | W33: =W32/V32-1 -> 0.00046108885 | X33: =X32/W32-1 -> 0.078404599 | Y33: =Y32/X32-1 -> -0.010355945 | Z33: =Z32/Y32-1 -> -0.0042332859 | AA33: -0.02
B34: Paid subscribers | C34: =Statement!M211 -> 2500 | D34: =Statement!N211 -> 4200 | E34: =Statement!O211 -> 6600 | F34: =Statement!P211 -> 9500 | G34: =Statement!Q211 -> 12200 | H34: =H32*H28 -> 13937.28 | I34: =I32*I28 -> 15852.262 | J34: =J32*J28 -> 20389.972 | K34: =K32*K28 -> 27086.039 | L34: =L32*L28 -> 36980.569 | N34: Subscribers to MAU ratio * MAU | Q34: Subscribers to MAU ratio * MAU | R34: Paid subscribers | S34: =Statement!T211 -> 8600 | T34: =Statement!U211 -> 9500 | U34: =Statement!V211 -> 10300 | V34: =Statement!W211 -> 10900 | W34: =Statement!X211 -> 11500 | X34: =Statement!Y211 -> 12200 | Y34: =Statement!Z211 -> 12500 | Z34: =Statement!AA211 -> 12700 | AA34: =AA32*AA28 -> 12943.84 | AE34: =AA34 -> 12943.84
B35: Free users | C35: =Statement!M212 -> 38000 | D35: =Statement!N212 -> 56500 | E35: =Statement!O212 -> 81800 | F35: =Statement!P212 -> 107200 | G35: =Statement!Q212 -> 120900 | H35: =H28-H34 -> 144451.72 | I35: =I28-I34 -> 175798.43 | J35: =J28-J34 -> 214382.12 | K35: =K28-K34 -> 261683.64 | L35: =L28-L34 -> 318206.13 | N35: MAU - Paid subscribers | Q35: MAU - Paid subscribers | R35: Free users | S35: =Statement!T212 -> 104500 | T35: =Statement!U212 -> 107200 | U35: =Statement!V212 -> 119900 | V35: =Statement!W212 -> 117400 | W35: =Statement!X212 -> 123800 | X35: =Statement!Y212 -> 120900 | Y35: =Statement!Z212 -> 125300 | Z35: =Statement!AA212 -> 127900 | AA35: =AA28-AA34 -> 133280.16 | AE35: =AA35 -> 133280.16
B36: In-App purchases % of DAU | C36: =Statement!M217 -> 0.7203125 | D36: =Statement!N217 -> 1.137362 | E36: =Statement!O217 -> 1.2889591 | F36: =Statement!P217 -> 0.95439506 | G36: =Statement!Q217 -> 0.76810247 | H36: 0.71 | I36: 0.65 | J36: 0.6 | K36: 0.65 | L36: 0.65 | R36: In-App purchases % of DAU | S36: =Statement!T217 -> 0.25298387 | T36: =Statement!U217 -> 0.2257284 | U36: =Statement!V217 -> 0.20261803 | V36: =Statement!W217 -> 0.21781971 | W36: =Statement!X217 -> 0.21972277 | X36: =Statement!Y217 -> 0.1812334 | Y36: =Statement!Z217 -> 0.14948673 | Z36: =Statement!AA217 -> 0.13632027 | AA36: 0.12
B37: Avg revenue/Paid user | C37: =Statement!M213 -> 72.2792 | D37: =Statement!N213 -> 65.120714 | E37: =Statement!O213 -> 61.315758 | F37: =Statement!P213 -> 63.950632 | G37: =Statement!Q213 -> 71.593607 | H37: 73.5 | I37: 73.5 | J37: 73 | K37: 75 | L37: 75 | R37: Avg revenue/Paid user | S37: =Statement!T213 -> 18.327558 | T37: =Statement!U213 -> 18.349158 | U37: =Statement!V213 -> 18.542427 | V37: =Statement!W213 -> 19.328257 | W37: =Statement!X213 -> 19.955739 | X37: =Statement!Y213 -> 19.859508 | Y37: =Statement!Z213 -> 20.07264 | Z37: =Statement!AA213 -> 20.317717 | AA37: 20
B38: DAU to MAU ratio | C38: =Statement!M214 -> 0.23703704 | D38: =Statement!N214 -> 0.26853377 | E38: =Statement!O214 -> 0.30429864 | F38: =Statement!P214 -> 0.3470437 | G38: =Statement!Q214 -> 0.3959429 | H38: 0.44 | I38: =I27/I28 -> 0.41246916 | J38: =J27/J28 -> 0.42762109 | K38: =K27/K28 -> 0.44152747 | L38: =L27/L28 -> 0.45947574 | N38: DAU/MAU | Q38: DAU/MAU | R38: DAU to MAU ratio | S38: =Statement!T214 -> 0.32891247 | T38: =Statement!U214 -> 0.3470437 | U38: =Statement!V214 -> 0.35791091 | V38: =Statement!W214 -> 0.37178488 | W38: =Statement!X214 -> 0.37324464 | X38: =Statement!Y214 -> 0.3959429 | Y38: =Statement!Z214 -> 0.41001451 | Z38: =Statement!AA214 -> 0.41749644 | AA38: =AA27/AA28 -> 0.433554
C40: Growth rates for metrics | S40: Growth rates for metrics
B41: Metrics growth % | C41: =C5 -> 2021 | D41: =D5 -> 2022 | E41: =E5 -> 2023 | F41: =F5 -> 2024 | G41: =G5 -> 2025 | H41: =H5 -> 2026 | I41: =I5 -> 2027 | J41: =J5 -> 2028 | ... L41: =L5 -> 2030 | R41: Metrics growth % | S41: =S5 -> Q3 2024 | T41: =T5 -> Q4 2024 | U41: =U5 -> Q1 2025 | V41: =V5 -> Q2 2025 | W41: =W5 -> Q3 2025 | X41: =X5 -> Q4 2025 | Y41: =Y5 -> Q1 2026 | Z41: =Z5 -> Q2 2026 | ... AC41: =AC5 -> FQ3
B42: Ad revenue/Free user | D42: =D31/C31-1 -> -0.21860299 | E42: =E31/D31-1 -> -0.23012292 | F42: =F31/E31-1 -> -0.15966707 | G42: =G31/F31-1 -> 0.2874646 | H42: =H31/G31-1 -> 0.061523989 | I42: =I31/H31-1 -> 0.014285714 | J42: =J31/I31-1 -> -0.014084507 | K42: =K31/J31-1 -> 0.028571429 | L42: =L31/K31-1 -> 0.013888889 | R42: Ad revenue/Free user | T42: =T31/S31-1 -> -0.03283349 | U42: =U31/T31-1 -> 0.11866148 | V42: =V31/U31-1 -> 0.1766992 | W42: =W31/V31-1 -> -0.032548862 | X42: =X31/W31-1 -> -0.014889557 | Y42: =Y31/X31-1 -> -0.016362964 | Z42: =Z31/Y31-1 -> 0.00048738293 | AA42: =AA31/Z31-1 -> 0.032823485
B43: Paid subscribers | D43: =D34/C34-1 -> 0.68 | E43: =E34/D34-1 -> 0.57142857 | F43: =F34/E34-1 -> 0.43939394 | G43: =G34/F34-1 -> 0.28421053 | H43: =H34/G34-1 -> 0.1424 | I43: =I34/H34-1 -> 0.1374 | J43: =J34/I34-1 -> 0.28625 | K43: =K34/J34-1 -> 0.3284 | L43: =L34/K34-1 -> 0.3653 | R43: Paid subscribers | T43: =T34/S34-1 -> 0.10465116 | U43: =U34/T34-1 -> 0.084210526 | V43: =V34/U34-1 -> 0.058252427 | W43: =W34/V34-1 -> 0.055045872 | X43: =X34/W34-1 -> 0.060869565 | Y43: =Y34/X34-1 -> 0.024590164 | Z43: =Z34/Y34-1 -> 0.016 | AA43: =AA34/Z34-1 -> 0.0192
B44: Free users | D44: =D35/C35-1 -> 0.48684211 | E44: =E35/D35-1 -> 0.44778761 | F44: =F35/E35-1 -> 0.31051345 | G44: =G35/F35-1 -> 0.12779851 | H44: =H35/G35-1 -> 0.19480331 | I44: =I35/H35-1 -> 0.21700474 | J44: =J35/I35-1 -> 0.21947691 | K44: =K35/J35-1 -> 0.22064114 | L44: =L35/K35-1 -> 0.21599553 | R44: Free users | T44: =T35/S35-1 -> 0.025837321 | U44: =U35/T35-1 -> 0.11847015 | V44: =V35/U35-1 -> -0.020850709 | W44: =W35/V35-1 -> 0.05451448 | X44: =X35/W35-1 -> -0.023424879 | Y44: =Y35/X35-1 -> 0.036393714 | Z44: =Z35/Y35-1 -> 0.0207502 | AA44: =AA35/Z35-1 -> 0.042065364
B45: In-App purchases % of DAU | D45: =D36/C36-1 -> 0.57898407 | E45: =E36/D36-1 -> 0.13328839 | F45: =F36/E36-1 -> -0.25956141 | G45: =G36/F36-1 -> -0.19519442 | H45: =H36/G36-1 -> -0.075644161 | I45: =I36/H36-1 -> -0.084507042 | J45: =J36/I36-1 -> -0.076923077 | K45: =K36/J36-1 -> 0.083333333 | L45: =L36/K36-1 -> 0 | R45: In-App purchases % of DAU | T45: =T36/S36-1 -> -0.10773602 | U45: =U36/T36-1 -> -0.10238131 | V45: =V36/U36-1 -> 0.0750263 | W45: =W36/V36-1 -> 0.0087368852 | X45: =X36/W36-1 -> -0.17517245 | Y45: =Y36/X36-1 -> -0.17517009 | Z45: =Z36/Y36-1 -> -0.088077741 | AA45: =AA36/Z36-1 -> -0.11972007
B46: Avg revenue/Paid user | D46: =D37/C37-1 -> -0.09903936 | E46: =E37/D37-1 -> -0.058429284 | F46: =F37/E37-1 -> 0.042972216 | G46: =G37/F37-1 -> 0.11951367 | H46: =H37/G37-1 -> 0.026627984 | I46: =I37/H37-1 -> 0 | J46: =J37/I37-1 -> -0.0068027211 | K46: =K37/J37-1 -> 0.02739726 | L46: =L37/K37-1 -> 0 | R46: Avg revenue/Paid user | T46: =T37/S37-1 -> 0.0011785397 | U46: =U37/T37-1 -> 0.01053287 | V46: =V37/U37-1 -> 0.042380088 | W46: =W37/V37-1 -> 0.032464503 | X46: =X37/W37-1 -> -0.0048222185 | Y46: =Y37/X37-1 -> 0.010731978 | Z46: =Z37/Y37-1 -> 0.012209482 | AA46: =AA37/Z37-1 -> -0.015637414
B47: DAU to MAU ratio | D47: =D38/C38-1 -> 0.13287685 | E47: =E38/D38-1 -> 0.13318574 | F47: =F38/E38-1 -> 0.14047075 | G47: =G38/F38-1 -> 0.14090213 | H47: =H38/G38-1 -> 0.11127135 | I47: =I38/H38-1 -> -0.06257008 | J47: =J38/I38-1 -> 0.036734694 | K47: =K38/J38-1 -> 0.032520325 | L47: =L38/K38-1 -> 0.040650407 | R47: DAU to MAU ratio | T47: =T38/S38-1 -> 0.055124803 | U47: =U38/T38-1 -> 0.031313649 | V47: =V38/U38-1 -> 0.038763761 | W47: =W38/V38-1 -> 0.0039263629 | X47: =X38/W38-1 -> 0.060813354 | Y47: =Y38/X38-1 -> 0.035539503 | Z47: =Z38/Y38-1 -> 0.018247964 | AA47: =AA38/Z38-1 -> 0.038461538

Sheet COGS & OpEx
B1: COGS & OpEx forecast
C2: History | H2: Forecast | P2: History | X2: Forecast | AB2: TTM
C4: Revenues | P4: Revenues
B5: =Revenue!B5 -> Revenues (thousand) | C5: =Revenue!C5 -> 2021 | D5: =Revenue!D5 -> 2022 | E5: =Revenue!E5 -> 2023 | F5: =Revenue!F5 -> 2024 | G5: =Revenue!G5 -> 2025 | H5: =G5+1 -> 2026 | I5: =H5+1 -> 2027 | J5: =I5+1 -> 2028 | K5: =J5+1 -> 2029 | L5: =K5+1 -> 2030 | O5: Revenues (thousand) | P5: =Revenue!S5 -> Q3 2024 | Q5: =Revenue!T5 -> Q4 2024 | R5: =Revenue!U5 -> Q1 2025 | S5: =Revenue!V5 -> Q2 2025 | T5: =Revenue!W5 -> Q3 2025 | U5: =Revenue!X5 -> Q4 2025 | V5: =Revenue!Y5 -> Q1 2026 | W5: =Revenue!Z5 -> Q2 2026 | X5: FQ1 | Y5: FQ2 | Z5: FQ3 | AB5: =Revenue!AE5 -> FQ1
B6: Revenue | C6: =Revenue!C11 -> 250772 | D6: =Revenue!D11 -> 369495 | E6: =Revenue!E11 -> 531109 | F6: =Revenue!F11 -> 748024 | G6: =Revenue!G11 -> 1037589 | H6: =Revenue!H11 -> 1213121 | I6: =Revenue!I11 -> 1384239.9 | J6: =Revenue!J11 -> 1743981.6 | ... L6: =Revenue!L11 -> 3165420.2 | O6: Revenue | P6: =Revenue!S11 -> 192594 | Q6: =Revenue!T11 -> 209550 | R6: =Revenue!U11 -> 230743 | S6: =Revenue!V11 -> 252265 | T6: =Revenue!W11 -> 271713 | U6: =Revenue!X11 -> 282868 | V6: =Revenue!Y11 -> 291967 | W6: =Revenue!Z11 -> 298454 | X6: =Revenue!AA11 -> 300899.36 | AB6: =Revenue!AE11 -> 1174188.4
C9: COGS and OpEx | P9: COGS & OpEx | AB9: =AB4 -> 0
B10: Expenses (tnousand) | C10: =C5 -> 2021 | D10: =D5 -> 2022 | E10: =E5 -> 2023 | F10: =F5 -> 2024 | G10: =G5 -> 2025 | H10: =H5 -> 2026 | I10: =I5 -> 2027 | J10: =J5 -> 2028 | ... L10: =L5 -> 2030 | O10: Expenses (thousand) | P10: =P5 -> Q3 2024 | Q10: =Q5 -> Q4 2024 | R10: =R5 -> Q1 2025 | S10: =S5 -> Q2 2025 | T10: =T5 -> Q3 2025 | U10: =U5 -> Q4 2025 | V10: =V5 -> Q1 2026 | W10: =W5 -> Q2 2026 | ... Z10: =Z5 -> FQ3 | AB10: =AB5 -> FQ1
B11: COGS | C11: =Statement!M6 -> 69186 | D11: =Statement!N6 -> 99431 | E11: =Statement!O6 -> 142105 | F11: =Statement!P6 -> 203645 | G11: =Statement!Q6 -> 288132 | H11: =H6*H20 -> 339673.89 | I11: =I6*I20 -> 380665.98 | J11: =J6*J20 -> 488314.84 | K11: =K6*K20 -> 630228.57 | L11: =L6*L20 -> 873655.98 | O11: =B11 -> COGS | P11: =Statement!T6 -> 52180 | Q11: =Statement!U6 -> 58925 | R11: =Statement!V6 -> 66647 | S11: =Statement!W6 -> 69684 | T11: =Statement!X6 -> 74802 | U11: =Statement!Y6 -> 76999 | V11: =Statement!Z6 -> 78871 | W11: =Statement!AA6 -> 81714 | X11: =X6*X20 -> 84251.82 | AB11: =SUM(U11:X11) -> 321835.82
B12: =Statement!B8 -> R&D | C12: =Statement!M8 -> 103833 | D12: =Statement!N8 -> 150444 | E12: =Statement!O8 -> 194352 | F12: =Statement!P8 -> 235298 | G12: =Statement!Q8 -> 306323 | H12: =H6*H21 -> 424592.36 | I12: =I6*I21 -> 415271.98 | J12: =J6*J21 -> 523194.47 | K12: =K6*K21 -> 728995.73 | L12: =L6*L21 -> 917971.86 | O12: =B12 -> R&D | P12: =Statement!T8 -> 62878 | Q12: =Statement!U8 -> 66395 | R12: =Statement!V8 -> 70390 | S12: =Statement!W8 -> 73670 | T12: =Statement!X8 -> 82707 | U12: =Statement!Y8 -> 79556 | V12: =Statement!Z8 -> 82974 | W12: =Statement!AA8 -> 92195 | X12: =X21*X$6 -> 89066.21 | AB12: =SUM(U12:X12) -> 343791.21
B13: =Statement!B9 -> Sales and marketing | C13: =Statement!M9 -> 59170 | D13: =Statement!N9 -> 66967 | E13: =Statement!O9 -> 75788 | F13: =Statement!P9 -> 90494 | G13: =Statement!Q9 -> 125677 | H13: =H6*H22 -> 157705.73 | I13: =I6*I22 -> 173029.99 | J13: =J6*J22 -> 209277.79 | K13: =K6*K22 -> 270433.9 | L13: =L6*L22 -> 348196.22 | O13: =B13 -> Sales and marketing | P13: =Statement!T9 -> 25574 | Q13: =Statement!U9 -> 24815 | R13: =Statement!V9 -> 26662 | S13: =Statement!W9 -> 29563 | T13: =Statement!X9 -> 35081 | U13: =Statement!Y9 -> 34371 | V13: =Statement!Z9 -> 39249 | W13: =Statement!AA9 -> 40007 | X13: =X22*X$6 -> 34603.426 | AB13: =SUM(U13:X13) -> 148230.43
B14: =Statement!B10 -> General and administrative | C14: =Statement!M10 -> 78590 | D14: =Statement!N10 -> 117848 | E14: =Statement!O10 -> 132123 | F14: =Statement!P10 -> 155992 | G14: =Statement!Q10 -> 181887 | H14: =H6*H23 -> 218361.79 | I14: =I6*I23 -> 235320.79 | J14: =J6*J23 -> 279037.05 | K14: =K6*K23 -> 411529.85 | L14: =L6*L23 -> 538121.44 | O14: =B14 -> General and administrative | P14: =Statement!T10 -> 38388 | Q14: =Statement!U10 -> 45533 | R14: =Statement!V10 -> 43450 | S14: =Statement!W10 -> 45985 | T14: =Statement!X10 -> 43964 | U14: =Statement!Y10 -> 48488 | V14: =Statement!Z10 -> 46346 | W14: =Statement!AA10 -> 50593 | X14: =X23*X$6 -> 55666.381 | AB14: =SUM(U14:X14) -> 201093.38
B15: OpEx | C15: =Statement!M11 -> 241593 | D15: =Statement!N11 -> 335259 | E15: =Statement!O11 -> 402263 | F15: =Statement!P11 -> 481784 | G15: =Statement!Q11 -> 613887 | H15: =SUM(H12:H14) -> 800659.88 | I15: =SUM(I12:I14) -> 823622.75 | J15: =SUM(J12:J14) -> 1011509.3 | K15: =SUM(K12:K14) -> 1410959.5 | L15: =SUM(L12:L14) -> 1804289.5 | O15: =B15 -> OpEx | P15: =Statement!T11 -> 126840 | Q15: =Statement!U11 -> 136743 | R15: =Statement!V11 -> 140502 | S15: =Statement!W11 -> 149218 | T15: =Statement!X11 -> 161752 | U15: =Statement!Y11 -> 162415 | V15: =Statement!Z11 -> 168569 | W15: =Statement!AA11 -> 182795 | X15: =SUM(X12:X14) -> 179336.02 | AB15: =SUM(U15:X15) -> 693115.02
C18: Expenses % of Revenue | P18: Expenses % of Revenue
B19: % of revenue | C19: =C5 -> 2021 | D19: =D5 -> 2022 | E19: =E5 -> 2023 | F19: =F5 -> 2024 | G19: =G5 -> 2025 | H19: =H5 -> 2026 | I19: =I5 -> 2027 | J19: =J5 -> 2028 | ... L19: =L5 -> 2030 | O19: % of revenue | P19: =P5 -> Q3 2024 | Q19: =Q5 -> Q4 2024 | R19: =R5 -> Q1 2025 | S19: =S5 -> Q2 2025 | T19: =T5 -> Q3 2025 | U19: =U5 -> Q4 2025 | V19: =V5 -> Q1 2026 | W19: =W5 -> Q2 2026 | ... Z19: =Z5 -> FQ3
B20: =B11 -> COGS | C20: =C11/C$6 -> 0.27589205 | D20: =D11/D$6 -> 0.26909972 | E20: =E11/E$6 -> 0.26756278 | F20: =F11/F$6 -> 0.27224394 | G20: =G11/G$6 -> 0.27769377 | H20: 0.28 | I20: 0.275 | J20: 0.28 | K20: 0.268 | L20: 0.276 | O20: =O11 -> COGS | P20: =P11/P$6 -> 0.27093264 | Q20: =Q11/Q$6 -> 0.2811978 | R20: =R11/R$6 -> 0.2888365 | S20: =S11/S$6 -> 0.27623333 | T20: =T11/T$6 -> 0.27529783 | U20: =U11/U$6 -> 0.27220824 | V20: =V11/V$6 -> 0.27013669 | W20: =W11/W$6 -> 0.27379094 | X20: 0.28
B21: =B12 -> R&D | C21: =C12/C$6 -> 0.4140534 | D21: =D12/D$6 -> 0.40716113 | E21: =E12/E$6 -> 0.36593618 | F21: =F12/F$6 -> 0.31455943 | G21: =G12/G$6 -> 0.29522576 | H21: 0.35 | I21: 0.3 | J21: 0.3 | K21: 0.31 | L21: 0.29 | O21: =O12 -> R&D | P21: =P12/P$6 -> 0.32647954 | Q21: =Q12/Q$6 -> 0.31684562 | R21: =R12/R$6 -> 0.30505801 | S21: =S12/S$6 -> 0.29203417 | T21: =T12/T$6 -> 0.30439103 | U21: =U12/U$6 -> 0.28124779 | V21: =V12/V$6 -> 0.28418965 | W21: =W12/W$6 -> 0.30890858 | X21: 0.296
B22: =B13 -> Sales and marketing | C22: =C13/C$6 -> 0.23595138 | D22: =D13/D$6 -> 0.18123926 | E22: =E13/E$6 -> 0.14269764 | F22: =F13/F$6 -> 0.1209774 | G22: =G13/G$6 -> 0.12112407 | H22: 0.13 | I22: 0.125 | J22: 0.12 | K22: 0.115 | L22: 0.11 | O22: =O13 -> Sales and marketing | P22: =P13/P$6 -> 0.13278711 | Q22: =Q13/Q$6 -> 0.11842042 | R22: =R13/R$6 -> 0.11554847 | S22: =S13/S$6 -> 0.11719026 | T22: =T13/T$6 -> 0.1291105 | U22: =U13/U$6 -> 0.12150897 | V22: =V13/V$6 -> 0.13442958 | W22: =W13/W$6 -> 0.13404746 | X22: 0.115
B23: =B14 -> General and administrative | C23: =C14/C$6 -> 0.31339224 | D23: =D14/D$6 -> 0.31894342 | E23: =E14/E$6 -> 0.24876814 | F23: =F14/F$6 -> 0.20853876 | G23: =G14/G$6 -> 0.17529773 | H23: 0.18 | I23: 0.17 | J23: 0.16 | K23: 0.175 | L23: 0.17 | O23: =O14 -> General and administrative | P23: =P14/P$6 -> 0.19932085 | Q23: =Q14/Q$6 -> 0.21728943 | R23: =R14/R$6 -> 0.18830474 | S23: =S14/S$6 -> 0.18228847 | T23: =T14/T$6 -> 0.16180308 | U23: =U14/U$6 -> 0.17141564 | V23: =V14/V$6 -> 0.15873712 | W23: =W14/W$6 -> 0.16951691 | X23: 0.185
B24: =B15 -> OpEx | C24: =C15/C$6 -> 0.96339703 | D24: =D15/D$6 -> 0.90734381 | E24: =E15/E$6 -> 0.75740196 | F24: =F15/F$6 -> 0.64407559 | G24: =G15/G$6 -> 0.59164756 | H24: =H15/H$6 -> 0.66 | I24: =I15/I$6 -> 0.595 | J24: =J15/J$6 -> 0.58 | ... L24: =L15/L$6 -> 0.57 | O24: =O15 -> OpEx | P24: =P15/P$6 -> 0.65858749 | Q24: =Q15/Q$6 -> 0.65255548 | R24: =R15/R$6 -> 0.60891121 | S24: =S15/S$6 -> 0.59151289 | T24: =T15/T$6 -> 0.5953046 | U24: =U15/U$6 -> 0.57417241 | V24: =V15/V$6 -> 0.57735635 | W24: =W15/W$6 -> 0.61247294 | X24: =X15/X$6 -> 0.596

Sheet WC & Investments
B1: Working Capital, Capex, D&A
C3: History | H3: Forecast
C5: Revenues
B6: Revenues (thousand) | C6: =Revenue!C5 -> 2021 | D6: =Revenue!D5 -> 2022 | E6: =Revenue!E5 -> 2023 | F6: =Revenue!F5 -> 2024 | G6: =Revenue!G5 -> 2025 | H6: =G6+1 -> 2026 | I6: =H6+1 -> 2027 | J6: =I6+1 -> 2028 | K6: =J6+1 -> 2029 | L6: =K6+1 -> 2030
B7: Revenue | C7: =Revenue!C11 -> 250772 | D7: =Revenue!D11 -> 369495 | E7: =Revenue!E11 -> 531109 | F7: =Revenue!F11 -> 748024 | G7: =Revenue!G11 -> 1037589 | H7: =Revenue!H11 -> 1213121 | I7: =Revenue!I11 -> 1384239.9 | J7: =Revenue!J11 -> 1743981.6 | ... L7: =Revenue!L11 -> 3165420.2
B8: COGS | C8: ='COGS & OpEx'!C11 -> 69186 | D8: ='COGS & OpEx'!D11 -> 99431 | E8: ='COGS & OpEx'!E11 -> 142105 | F8: ='COGS & OpEx'!F11 -> 203645 | G8: ='COGS & OpEx'!G11 -> 288132 | H8: ='COGS & OpEx'!H11 -> 339673.89 | I8: ='COGS & OpEx'!I11 -> 380665.98 | J8: ='COGS & OpEx'!J11 -> 488314.84 | ... L8: ='COGS & OpEx'!L11 -> 873655.98
C11: Working Capital
B12: $ (thousand) | C12: =C6 -> 2021 | D12: =D6 -> 2022 | E12: =E6 -> 2023 | F12: =F6 -> 2024 | G12: =G6 -> 2025 | H12: =H6 -> 2026 | I12: =I6 -> 2027 | J12: =J6 -> 2028 | ... L12: =L6 -> 2030
B13: Accounts receivable | C13: =Statement!M30 -> 33163 | D13: =Statement!N30 -> 46728 | E13: =Statement!O30 -> 88975 | F13: =Statement!P30 -> 128923 | G13: =Statement!Q30 -> 162827 | H13: =H20*H7/365 -> 149562.87 | I13: =I20*I7/365 -> 170659.72 | J13: =J20*J7/365 -> 215011.43 | K13: =K20*K7/365 -> 289923.18 | L13: =L20*L7/365 -> 390257.29
B14: Inventory | C14: =Statement!M31 -> 0 | D14: =Statement!N31 -> 0 | E14: =Statement!O31 -> 0 | F14: =Statement!P31 -> 0 | G14: =Statement!Q31 -> 0 | H14: =H21*H8/365 -> 0 | I14: =I21*I8/365 -> 0 | J14: =J21*J8/365 -> 0 | K14: =K21*K8/365 -> 0 | L14: =L21*L8/365 -> 0
B15: Accounts payable | C15: =Statement!M38 -> 7818 | D15: =Statement!N38 -> 1177 | E15: =Statement!O38 -> 2447 | F15: =Statement!P38 -> 6381 | G15: =Statement!Q38 -> 7998 | H15: =H22*H8/365 -> 14889.814 | I15: =I22*I8/365 -> 16686.728 | J15: =J22*J8/365 -> 21405.582 | K15: =K22*K8/365 -> 27626.458 | L15: =L22*L8/365 -> 38297.248
C18: WC metrics and drivers
B19: Days | C19: =C6 -> 2021 | D19: =D6 -> 2022 | E19: =E6 -> 2023 | F19: =F6 -> 2024 | G19: =G6 -> 2025 | H19: =H6 -> 2026 | I19: =I6 -> 2027 | J19: =J6 -> 2028 | ... L19: =L6 -> 2030
B20: DSO | C20: =C13/C7*365 -> 48.268926 | D20: =D13/D7*365 -> 46.159542 | E20: =E13/E7*365 -> 61.147288 | F20: =F13/F7*365 -> 62.908269 | G20: =G13/G7*365 -> 57.278802 | H20: 45 | I20: 45 | J20: 45 | K20: 45 | L20: 45
B21: DIO | C21: =C14/C8*365 -> 0 | D21: =D14/D8*365 -> 0 | E21: =E14/E8*365 -> 0 | F21: =F14/F8*365 -> 0 | G21: =G14/G8*365 -> 0 | H21: 0 | I21: 0 | J21: 0 | K21: 0 | L21: 0
B22: DPO | C22: =C15/C8*365 -> 41.244905 | D22: =D15/D8*365 -> 4.3206344 | E22: =E15/E8*365 -> 6.2851765 | F22: =F15/F8*365 -> 11.436888 | G22: =G15/G8*365 -> 10.13171 | H22: 16 | I22: 16 | J22: 16 | K22: 16 | L22: 16
B23: Net trade cycle | C23: =C20+C21-C22 -> 7.0240205 | D23: =D20+D21-D22 -> 41.838908 | E23: =E20+E21-E22 -> 54.862112 | F23: =F20+F21-F22 -> 51.471381 | G23: =G20+G21-G22 -> 47.147092 | H23: =H20+H21-H22 -> 29 | I23: =I20+I21-I22 -> 29 | J23: =J20+J21-J22 -> 29 | ... L23: =L20+L21-L22 -> 29
C26: Change in SIP NWC
B27: $ (thousand) | C27: =C6 -> 2021 | D27: =D6 -> 2022 | E27: =E6 -> 2023 | F27: =F6 -> 2024 | G27: =G6 -> 2025 | H27: =H6 -> 2026 | I27: =I6 -> 2027 | J27: =J6 -> 2028 | ... L27: =L6 -> 2030
B28: Change in acc receivable | C28: =Statement!M55 -> -12713 | D28: =Statement!N55 -> -13565 | E28: =Statement!O55 -> -42247 | F28: =Statement!P55 -> -39917 | G28: =Statement!Q55 -> -33904 | H28: =-(H13-G13) -> 13264.133 | I28: =-(I13-H13) -> -21096.849 | J28: =-(J13-I13) -> -44351.709 | K28: =-(K13-J13) -> -74911.756 | L28: =-(L13-K13) -> -100334.11
B29: Change in inventory | C29: =Statement!M56 -> 0 | D29: =Statement!N56 -> 0 | E29: =Statement!O56 -> 0 | F29: =Statement!P56 -> 0 | G29: =Statement!Q56 -> 0 | H29: =-(H14-G14) -> 0 | I29: =-(I14-H14) -> 0 | J29: =-(J14-I14) -> 0 | K29: =-(K14-J14) -> 0 | L29: =-(L14-K14) -> 0
B30: Change in acc payable | C30: =Statement!M57 -> 5622 | D30: =Statement!N57 -> -6655 | E30: =Statement!O57 -> 1261 | F30: =Statement!P57 -> 3934 | G30: =Statement!Q57 -> 1617 | H30: =H15-G15 -> 6891.8143 | I30: =I15-H15 -> 1796.9135 | J30: =J15-I15 -> 4718.8541 | K30: =K15-J15 -> 6220.8759 | L30: =L15-K15 -> 10670.791
C33: Total change in NWC and less SIP
B34: $ (thousand) | C34: =C6 -> 2021 | D34: =D6 -> 2022 | E34: =E6 -> 2023 | F34: =F6 -> 2024 | G34: =G6 -> 2025 | H34: =H6 -> 2026 | I34: =I6 -> 2027 | J34: =J6 -> 2028 | ... L34: =L6 -> 2030
B35: Total change in NWC | C35: =Statement!M55+Statement!M56+Statement!M57+Statement!M58 -> 25775 | D35: =Statement!N55+Statement!N56+Statement!N57+Statement!N58 -> 34540 | E35: =Statement!O55+Statement!O56+Statement!O57+Statement!O58 -> 34898 | F35: =Statement!P55+Statement!P56+Statement!P57+Statement!P58 -> 75921 | G35: =Statement!Q55+Statement!Q56+Statement!Q57+Statement!Q58 -> 48966 | H35: =H36+H28+H29+H30 -> 141468.05 | I35: =I36+I28+I29+I30 -> 119124.06 | J35: =J36+J28+J29+J30 -> 134765.3 | K35: =K36+K28+K29+K30 -> 166469.03 | L35: =L36+L28+L29+L30 -> 226878.71
B36: Change in NWC less SIP | C36: =C35-C28-C29-C30 -> 32866 | D36: =D35-D28-D29-D30 -> 54760 | E36: =E35-E28-E29-E30 -> 75884 | F36: =F35-F28-F29-F30 -> 111904 | G36: =G35-G28-G29-G30 -> 81253 | H36: =H7*H37 -> 121312.1 | I36: =I7*I37 -> 138423.99 | J36: =J7*J37 -> 174398.16 | K36: =K7*K37 -> 235159.91 | L36: =L7*L37 -> 316542.02
B37: % of revenue | C37: =C36/C7 -> 0.13105929 | D37: =D36/D7 -> 0.14820228 | E37: =E36/E7 -> 0.14287839 | F37: =F36/F7 -> 0.14959948 | G37: =G36/G7 -> 0.078309427 | H37: 0.1 | I37: 0.1 | J37: 0.1 | K37: 0.1 | L37: 0.1
C40: Investments
B41: $ (thousand) | C41: =C6 -> 2021 | D41: =D6 -> 2022 | E41: =E6 -> 2023 | F41: =F6 -> 2024 | G41: =G6 -> 2025 | H41: =H6 -> 2026 | I41: =I6 -> 2027 | J41: =J6 -> 2028 | ... L41: =L6 -> 2030
B42: D&A | C42: =Statement!M53 -> 2726 | D42: =Statement!N53 -> 4870 | E42: =Statement!O53 -> 7095 | F42: =Statement!P53 -> 10854 | G42: =Statement!Q53 -> 14391 | H42: =H7*H43 -> 15770.573 | I42: =I7*I43 -> 15226.639 | J42: =J7*J43 -> 17439.816 | K42: =K7*K43 -> 23515.991 | L42: =L7*L43 -> 31654.202
B43: % of Revenue | C43: =C42/C7 -> 0.010870432 | D43: =D42/D7 -> 0.013180151 | E43: =E42/E7 -> 0.01335884 | F43: =F42/F7 -> 0.01451023 | G43: =G42/G7 -> 0.013869654 | H43: 0.013 | I43: 0.011 | J43: 0.01 | K43: 0.01 | L43: 0.01
B44: % of CapEx | C44: =C42/C45 -> 0.43925234 | D44: =D42/D45 -> 0.48103516 | E44: =E42/E45 -> 0.51848875 | F44: =F42/F45 -> 0.51343425 | G44: =G42/G45 -> 0.52523815 | H44: =H42/H45 -> 0.46428571 | I44: =I42/I45 -> 0.42307692 | J44: =J42/J45 -> 0.4 | ... L44: =L42/L45 -> 0.45454545
B45: CapEx | C45: =-Statement!M110 -> 6206 | D45: =-Statement!N110 -> 10124 | E45: =-Statement!O110 -> 13684 | F45: =-Statement!P110 -> 21140 | G45: =-Statement!Q110 -> 27399 | H45: =H7*H46 -> 33967.389 | I45: =I7*I46 -> 35990.238 | J45: =J7*J46 -> 43599.539 | K45: =K7*K46 -> 54086.78 | L45: =L7*L46 -> 69639.245
B46: % of Revenue | C46: =C45/C7 -> 0.024747579 | D46: =D45/D7 -> 0.027399559 | E46: =E45/E7 -> 0.025764956 | F46: =F45/F7 -> 0.028261125 | G46: =G45/G7 -> 0.026406409 | H46: 0.028 | I46: 0.026 | J46: 0.025 | K46: 0.023 | L46: 0.022

Sheet FCF & Other
B1: Results
C2: History | H2: Forecast
C4: Income statement
B5: $ (thousand) | C5: =Revenue!C5 -> 2021 | D5: =Revenue!D5 -> 2022 | E5: =Revenue!E5 -> 2023 | F5: =Revenue!F5 -> 2024 | G5: =Revenue!G5 -> 2025 | H5: =G5+1 -> 2026 | I5: =H5+1 -> 2027 | J5: =I5+1 -> 2028 | K5: =J5+1 -> 2029 | L5: =K5+1 -> 2030
B6: Revenue | C6: =Revenue!C11 -> 250772 | D6: =Revenue!D11 -> 369495 | E6: =Revenue!E11 -> 531109 | F6: =Revenue!F11 -> 748024 | G6: =Revenue!G11 -> 1037589 | H6: =Revenue!H11 -> 1213121 | I6: =Revenue!I11 -> 1384239.9 | J6: =Revenue!J11 -> 1743981.6 | ... L6: =Revenue!L11 -> 3165420.2 | N6: From Revenue Sheet
B7: COGS | C7: ='COGS & OpEx'!C11 -> 69186 | D7: ='COGS & OpEx'!D11 -> 99431 | E7: ='COGS & OpEx'!E11 -> 142105 | F7: ='COGS & OpEx'!F11 -> 203645 | G7: ='COGS & OpEx'!G11 -> 288132 | H7: ='COGS & OpEx'!H11 -> 339673.89 | I7: ='COGS & OpEx'!I11 -> 380665.98 | J7: ='COGS & OpEx'!J11 -> 488314.84 | ... L7: ='COGS & OpEx'!L11 -> 873655.98 | N7: From COGS and OpEx Sheet
B8: Gross profit | C8: =C6-C7 -> 181586 | D8: =D6-D7 -> 270064 | E8: =E6-E7 -> 389004 | F8: =F6-F7 -> 544379 | G8: =G6-G7 -> 749457 | H8: =H6-H7 -> 873447.14 | I8: =I6-I7 -> 1003573.9 | J8: =J6-J7 -> 1255666.7 | ... L8: =L6-L7 -> 2291764.2
B9: OpEx | C9: ='COGS & OpEx'!C15 -> 241593 | D9: ='COGS & OpEx'!D15 -> 335259 | E9: ='COGS & OpEx'!E15 -> 402263 | F9: ='COGS & OpEx'!F15 -> 481784 | G9: ='COGS & OpEx'!G15 -> 613887 | H9: ='COGS & OpEx'!H15 -> 800659.88 | I9: ='COGS & OpEx'!I15 -> 823622.75 | J9: ='COGS & OpEx'!J15 -> 1011509.3 | ... L9: ='COGS & OpEx'!L15 -> 1804289.5 | N9: From COGS and OpEx Sheet
B10: EBIT | C10: =C8-C9 -> -60007 | D10: =D8-D9 -> -65195 | E10: =E8-E9 -> -13259 | F10: =F8-F9 -> 62595 | G10: =G8-G9 -> 135570 | H10: =H8-H9 -> 72787.262 | I10: =I8-I9 -> 179951.19 | J10: =J8-J9 -> 244157.42 | ... L10: =L8-L9 -> 487474.71
C13: Drivers
C14: =C5 -> 2021 | D14: =D5 -> 2022 | E14: =E5 -> 2023 | F14: =F5 -> 2024 | G14: =G5 -> 2025 | H14: =H5 -> 2026 | I14: =I5 -> 2027 | J14: =J5 -> 2028 | ... L14: =L5 -> 2030
B15: Tax rate | C15: =Statement!M83 -> 0 | D15: =Statement!N83 -> 0.015996998 | E15: =Statement!O83 -> 0.096191708 | F15: =Statement!P83 -> 0.13422478 | G15: =Statement!Q83 -> 0.13730059 | H15: =Overview!$C$26 -> 0.21 | I15: =Overview!$C$26 -> 0.21 | J15: =Overview!$C$26 -> 0.21 | K15: =Overview!$C$26 -> 0.21 | L15: =Overview!$C$26 -> 0.21 | N15: From Statements and Overview sheet
C18: Cash Flow Statement
B19: $ (thousand) | C19: =C5 -> 2021 | D19: =D5 -> 2022 | E19: =E5 -> 2023 | F19: =F5 -> 2024 | G19: =G5 -> 2025 | H19: =H5 -> 2026 | I19: =I5 -> 2027 | J19: =J5 -> 2028 | ... L19: =L5 -> 2030
B20: D&A | C20: ='WC & Investments'!C42 -> 2726 | D20: ='WC & Investments'!D42 -> 4870 | E20: ='WC & Investments'!E42 -> 7095 | F20: ='WC & Investments'!F42 -> 10854 | G20: ='WC & Investments'!G42 -> 14391 | H20: ='WC & Investments'!H42 -> 15770.573 | I20: ='WC & Investments'!I42 -> 15226.639 | J20: ='WC & Investments'!J42 -> 17439.816 | ... L20: ='WC & Investments'!L42 -> 31654.202 | N20: From WC & Investments Sheet
B21: CapEx | C21: ='WC & Investments'!C45 -> 6206 | D21: ='WC & Investments'!D45 -> 10124 | E21: ='WC & Investments'!E45 -> 13684 | F21: ='WC & Investments'!F45 -> 21140 | G21: ='WC & Investments'!G45 -> 27399 | H21: ='WC & Investments'!H45 -> 33967.389 | I21: ='WC & Investments'!I45 -> 35990.238 | J21: ='WC & Investments'!J45 -> 43599.539 | ... L21: ='WC & Investments'!L45 -> 69639.245 | N21: From WC & Investments Sheet
B22: Change in NWC | C22: ='WC & Investments'!C35 -> 25775 | D22: ='WC & Investments'!D35 -> 34540 | E22: ='WC & Investments'!E35 -> 34898 | F22: ='WC & Investments'!F35 -> 75921 | G22: ='WC & Investments'!G35 -> 48966 | H22: ='WC & Investments'!H35 -> 141468.05 | I22: ='WC & Investments'!I35 -> 119124.06 | J22: ='WC & Investments'!J35 -> 134765.3 | ... L22: ='WC & Investments'!L35 -> 226878.71 | N22: From WC & Investments Sheet
C25: FCFF
B26: $ (thousand) | C26: =C5 -> 2021 | D26: =D5 -> 2022 | E26: =E5 -> 2023 | F26: =F5 -> 2024 | G26: =G5 -> 2025 | H26: =H5 -> 2026 | I26: =I5 -> 2027 | J26: =J5 -> 2028 | ... L26: =L5 -> 2030
B27: NOPAT | C27: =C10*(1-C15) -> -60007 | D27: =D10*(1-D15) -> -64152.076 | E27: =E10*(1-E15) -> -11983.594 | F27: =F10*(1-F15) -> 54193.2 | G27: =G10*(1-G15) -> 116956.16 | H27: =H10*(1-H15) -> 57501.937 | I27: =I10*(1-I15) -> 142161.44 | J27: =J10*(1-J15) -> 192884.36 | ... L27: =L10*(1-L15) -> 385105.02
B28: FCFF | C28: =C27+C20-C21+C22 -> -37712 | D28: =D27+D20-D21+D22 -> -34866.076 | E28: =E27+E20-E21+E22 -> 16325.406 | F28: =F27+F20-F21+F22 -> 119828.2 | G28: =G27+G20-G21+G22 -> 152914.16 | H28: =H27+H20-H21+H22 -> 180773.17 | I28: =I27+I20-I21+I22 -> 240521.9 | J28: =J27+J20-J21+J22 -> 301489.94 | ... L28: =L27+L20-L21+L22 -> 573998.69
C31: Margins
B32: % | C32: =C5 -> 2021 | D32: =D5 -> 2022 | E32: =E5 -> 2023 | F32: =F5 -> 2024 | G32: =G5 -> 2025 | H32: =H5 -> 2026 | I32: =I5 -> 2027 | J32: =J5 -> 2028 | ... L32: =L5 -> 2030
B33: Gross margin | C33: =Statement!M101 -> 0.72410795 | D33: =Statement!N101 -> 0.73090028 | E33: =Statement!O101 -> 0.73243722 | F33: =Statement!P101 -> 0.72775606 | G33: =Statement!Q101 -> 0.72230623 | H33: =H8/H6 -> 0.72 | I33: =I8/I6 -> 0.725 | J33: =J8/J6 -> 0.72 | K33: =K8/K6 -> 0.732 | L33: =L8/L6 -> 0.724
B34: Operating margin | C34: =Statement!M102 -> -0.23928908 | D34: =Statement!N102 -> -0.17644352 | E34: =Statement!O102 -> -0.024964744 | F34: =Statement!P102 -> 0.08368047 | G34: =Statement!Q102 -> 0.13065867 | H34: =H10/H6 -> 0.06 | I34: =I10/I6 -> 0.13 | J34: =J10/J6 -> 0.14 | K34: =K10/K6 -> 0.132 | L34: =L10/L6 -> 0.154

Sheet Valuation ->
H5: Links
H6: Overview'!B3
H7: Financials ->'!B13
H8: Analysis ->'!B13
H9: Forecast ->'!B13
H10: Valuation ->'!B13
B13: Valuation ->

Sheet WACC
B1: WACC
B4: Inputs
B5: Shares Outstanding | C5: =Statement!AC78 -> 50122
B6: Price | C6: =Overview!C5 -> 143.04
B7: Equity | C7: =C5*C6 -> 7169450.9
B8: Debt | C8: =Statement!AC108 -> 0
B9: Risk free rate | C9: =Overview!F27 -> 0.04953
B10: Beta | C10: =Overview!C13 -> 1.066
B11: Market risk premium | C11: =[1]Sheet1!$C$12 -> 0.045
B12: Tax rate | C12: =Overview!C26 -> 0.21
B13: Cost of debt | C13: =Overview!C27 -> 0
B15: Calculations
B16: Debt/(Debt+Equity) | C16: =C8/(C8+C7) -> 0
B17: Equity/(Debt+Equity) | C17: =C7/(C8+C7) -> 1
B18: Cost of debt with tax | C18: =C13*(1-C12) -> 0
B19: Cost of equity | C19: =C9+C10*C11 -> 0.0975
B20: WACC | C20: =(C17*C19)+(C16*C18) -> 0.0975

Sheet DCF
B1: DCF
C3: History | H3: Forecast
C5: PV of FCF
B6: $ (thousand) | C6: =Revenue!C5 -> 2021 | D6: =Revenue!D5 -> 2022 | E6: =Revenue!E5 -> 2023 | F6: =Revenue!F5 -> 2024 | G6: =Revenue!G5 -> 2025 | H6: =Revenue!H5 -> 2026 | I6: =Revenue!I5 -> 2027 | J6: =Revenue!J5 -> 2028 | ... L6: =Revenue!L5 -> 2030
B7: FCFF | C7: ='FCF & Other'!C28 -> -37712 | D7: ='FCF & Other'!D28 -> -34866.076 | E7: ='FCF & Other'!E28 -> 16325.406 | F7: ='FCF & Other'!F28 -> 119828.2 | G7: ='FCF & Other'!G28 -> 152914.16 | H7: ='FCF & Other'!H28 -> 180773.17 | I7: ='FCF & Other'!I28 -> 240521.9 | J7: ='FCF & Other'!J28 -> 301489.94 | ... L7: ='FCF & Other'!L28 -> 573998.69
B8: Perpetual cashflow | C8: 0 | D8: 0 | E8: 0 | F8: 0 | G8: 0 | H8: 0 | I8: 0 | J8: 0 | K8: 0 | L8: =L7*(1+C14)/(C15-C14) -> 7554563.4
B9: Period | H9: 1 | I9: 2 | J9: 3 | K9: 4 | L9: 5
B10: PV of FCFF | H10: =H7/(1+$C$15)^H9 -> 164713.6 | I10: =I7/(1+$C$15)^I9 -> 199685.06 | J10: =J7/(1+$C$15)^J9 -> 228065.31 | K10: =K7/(1+$C$15)^K9 -> 262692.12 | L10: =L7/(1+$C$15)^L9 -> 360485.88
B11: PV of Perpetual cashflow | L11: =L8/(1+C15)^L9 -> 4744459.3
B13: Input parameters
B14: Perpetual growth | C14: 0.02
B15: WACC | C15: =IF(Overview!C28>0,Overview!C28,WACC!C20) -> 0.0975
B18: Result
B19: Total PV of Unlevered FCF | C19: =SUM(H10:L10) -> 1215642
B20: PV of Perpetual cashflow | C20: =L11 -> 4744459.3
B21: Enterprise value | C21: =C19+C20 -> 5960101.2
B22: (+) Cash | C22: =Statement!AC107 -> 1416559
B23: (-) Debt | C23: =Statement!AC108 -> 0
B24: Equity value | C24: =C21+C22-C23 -> 7376660.2
B25: Shares outstanding | C25: =Statement!AC78 -> 50122
B26: Price per share | C26: =C24/C25 -> 147.1741

Sheet Multiples
B1: Multiples valuations
C2: History | H2: Forecast
C4: Revenues, earnings cash
B5: Revenues (thousand) | C5: =Revenue!C5 -> 2021 | D5: =Revenue!D5 -> 2022 | E5: =Revenue!E5 -> 2023 | F5: =Revenue!F5 -> 2024 | G5: =Revenue!G5 -> 2025 | H5: =Revenue!H5 -> 2026 | I5: =Revenue!I5 -> 2027 | J5: =Revenue!J5 -> 2028 | ... L5: =Revenue!L5 -> 2030
B6: Revenue | C6: =Revenue!C11 -> 250772 | D6: =Revenue!D11 -> 369495 | E6: =Revenue!E11 -> 531109 | F6: =Revenue!F11 -> 748024 | G6: =Revenue!G11 -> 1037589 | H6: =Revenue!H11 -> 1213121 | I6: =Revenue!I11 -> 1384239.9 | J6: =Revenue!J11 -> 1743981.6 | ... L6: =Revenue!L11 -> 3165420.2
B7: EBIT | C7: ='FCF & Other'!C10 -> -60007 | D7: ='FCF & Other'!D10 -> -65195 | E7: ='FCF & Other'!E10 -> -13259 | F7: ='FCF & Other'!F10 -> 62595 | G7: ='FCF & Other'!G10 -> 135570 | H7: ='FCF & Other'!H10 -> 72787.262 | I7: ='FCF & Other'!I10 -> 179951.19 | J7: ='FCF & Other'!J10 -> 244157.42 | ... L7: ='FCF & Other'!L10 -> 487474.71
B8: FCFF | C8: ='FCF & Other'!C28 -> -37712 | D8: ='FCF & Other'!D28 -> -34866.076 | E8: ='FCF & Other'!E28 -> 16325.406 | F8: ='FCF & Other'!F28 -> 119828.2 | G8: ='FCF & Other'!G28 -> 152914.16 | H8: ='FCF & Other'!H28 -> 180773.17 | I8: ='FCF & Other'!I28 -> 240521.9 | J8: ='FCF & Other'!J28 -> 301489.94 | ... L8: ='FCF & Other'!L28 -> 573998.69
B9: PV of FCFF | H9: =DCF!H10 -> 164713.6 | I9: =DCF!I10 -> 199685.06 | J9: =DCF!J10 -> 228065.31 | K9: =DCF!K10 -> 262692.12 | L9: =DCF!L10 -> 360485.88
C11: Growth rates
B12: % Growth | C12: =C5 -> 2021 | D12: =D5 -> 2022 | E12: =E5 -> 2023 | F12: =F5 -> 2024 | G12: =G5 -> 2025 | H12: =H5 -> 2026 | I12: =I5 -> 2027 | J12: =J5 -> 2028 | ... L12: =L5 -> 2030
B13: Revenue | D13: =(D6-C6)/C6 -> 0.47343005 | E13: =(E6-D6)/D6 -> 0.43739157 | F13: =(F6-E6)/E6 -> 0.40841899 | G13: =(G6-F6)/F6 -> 0.38710656 | H13: =(H6-G6)/G6 -> 0.16917299 | I13: =(I6-H6)/H6 -> 0.14105673 | J13: =(J6-I6)/I6 -> 0.25988388 | K13: =(K6-J6)/J6 -> 0.34840826 | L13: =(L6-K6)/K6 -> 0.34607135
B14: EBIT | D14: =IF(C7=0, IF(D7=0,0,IF(D7>0,1,-1)), (D7-C7)/ABS(C7) ) -> -0.08645658 | E14: =IF(D7=0, IF(E7=0,0,IF(E7>0,1,-1)), (E7-D7)/ABS(D7) ) -> 0.79662551 | F14: =IF(E7=0, IF(F7=0,0,IF(F7>0,1,-1)), (F7-E7)/ABS(E7) ) -> 5.7209443 | G14: =IF(F7=0, IF(G7=0,0,IF(G7>0,1,-1)), (G7-F7)/ABS(F7) ) -> 1.1658279 | H14: =IF(G7=0, IF(H7=0,0,IF(H7>0,1,-1)), (H7-G7)/ABS(G7) ) -> -0.463102 | I14: =IF(H7=0, IF(I7=0,0,IF(I7>0,1,-1)), (I7-H7)/ABS(H7) ) -> 1.4722896 | J14: =IF(I7=0, IF(J7=0,0,IF(J7>0,1,-1)), (J7-I7)/ABS(I7) ) -> 0.35679802 | K14: =IF(J7=0, IF(K7=0,0,IF(K7>0,1,-1)), (K7-J7)/ABS(J7) ) -> 0.27135636 | L14: =IF(K7=0, IF(L7=0,0,IF(L7>0,1,-1)), (L7-K7)/ABS(K7) ) -> 0.57041657
B15: FCFF | D15: =IF(C8=0, IF(D8=0,0,IF(D8>0,1,-1)), (D8-C8)/ABS(C8) ) -> 0.075464688 | E15: =IF(D8=0, IF(E8=0,0,IF(E8>0,1,-1)), (E8-D8)/ABS(D8) ) -> 1.4682318 | F15: =IF(E8=0, IF(F8=0,0,IF(F8>0,1,-1)), (F8-E8)/ABS(E8) ) -> 6.3399829 | G15: =IF(F8=0, IF(G8=0,0,IF(G8>0,1,-1)), (G8-F8)/ABS(F8) ) -> 0.27611163 | H15: =IF(G8=0, IF(H8=0,0,IF(H8>0,1,-1)), (H8-G8)/ABS(G8) ) -> 0.18218727 | I15: =IF(H8=0, IF(I8=0,0,IF(I8>0,1,-1)), (I8-H8)/ABS(H8) ) -> 0.33051766 | J15: =IF(I8=0, IF(J8=0,0,IF(J8>0,1,-1)), (J8-I8)/ABS(I8) ) -> 0.25348229 | K15: =IF(J8=0, IF(K8=0,0,IF(K8>0,1,-1)), (K8-J8)/ABS(J8) ) -> 0.26413175 | L15: =IF(K8=0, IF(L8=0,0,IF(L8>0,1,-1)), (L8-K8)/ABS(K8) ) -> 0.50607201
C17: Shares
C18: =C5 -> 2021 | D18: =D5 -> 2022 | E18: =E5 -> 2023 | F18: =F5 -> 2024 | G18: =G5 -> 2025 | H18: =H5 -> 2026 | I18: =I5 -> 2027 | J18: =J5 -> 2028 | ... L18: =L5 -> 2030
B19: Avg diluted shares | C19: =Statement!M22 -> 23433 | D19: =Statement!N22 -> 39470 | E19: =Statement!O22 -> 46522 | F19: =Statement!P22 -> 47101 | G19: =Statement!Q22 -> 48315.636 | H19: =G19*(1+H20) -> 50248.261 | I19: =H19*(1+I20) -> 52258.192 | J19: =I19*(1+J20) -> 53825.938 | K19: =J19*(1+K20) -> 54902.456 | L19: =K19*(1+L20) -> 56000.505
B20: Dilution rate | D20: =D19/C19-1 -> 0.68437673 | E20: =E19/D19-1 -> 0.17866734 | F20: =F19/E19-1 -> 0.012445725 | G20: =G19/F19-1 -> 0.025787901 | H20: 0.04 | I20: 0.04 | J20: 0.03 | K20: 0.02 | L20: 0.02
C22: Historical price
C23: =C5 -> 2021 | D23: =D5 -> 2022 | E23: =E5 -> 2023 | F23: =F5 -> 2024 | G23: =G5 -> 2025 | H23: =H5 -> 2026 | I23: =I5 -> 2027 | J23: =J5 -> 2028 | ... L23: =L5 -> 2030
B24: Price | C24: =Statement!M116 -> 110.58 | D24: =Statement!N116 -> 71.13 | E24: =Statement!O116 -> 226.85 | F24: =Statement!P116 -> 325.2 | G24: =Statement!Q116 -> 177.14
C27: Historical ratios
C28: =C5 -> 2021 | D28: =D5 -> 2022 | E28: =E5 -> 2023 | F28: =F5 -> 2024 | G28: =G5 -> 2025 | H28: =H5 -> 2026 | I28: =I5 -> 2027 | J28: =J5 -> 2028 | ... L28: =L5 -> 2030
B29: PS | C29: =C24/(C6/C19) -> 10.332976 | D29: =D24/(D6/D19) -> 7.5982113 | E29: =E24/(E6/E19) -> 19.870715 | F29: =F24/(F6/F19) -> 20.476944 | G29: =G24/(G6/G19) -> 8.248576
B30: Market Cap | C30: =C24*C19 -> 2591221.1 | D30: =D24*D19 -> 2807501.1 | E30: =E24*E19 -> 10553516 | F30: =F24*F19 -> 15317245 | G30: =G24*G19 -> 8558631.8
B31: Debt | C31: =Statement!M108 -> 0 | D31: =Statement!N108 -> 0 | E31: =Statement!O108 -> 0 | F31: =Statement!P108 -> 0 | G31: =Statement!Q108 -> 0
B32: Cash | C32: =Statement!M107 -> 553922 | D32: =Statement!N107 -> 608180 | E32: =Statement!O107 -> 747610 | F32: =Statement!P107 -> 975937 | G32: =Statement!Q107 -> 1275565
B33: EV | C33: =C30+C31-C32 -> 2037299.1 | D33: =D30+D31-D32 -> 2199321.1 | E33: =E30+E31-E32 -> 9805905.7 | F33: =F30+F31-F32 -> 14341308 | G33: =G30+G31-G32 -> 7283066.8
B34: EV/EBIT | C34: =C33/C7 -> -33.951025 | D34: =D33/D7 -> -33.734506 | E34: =E33/E7 -> -739.56601 | F34: =F33/F7 -> 229.11268 | G34: =G33/G7 -> 53.721817
B35: EV/FCFF | C35: =C33/C8 -> -54.022569 | D35: =D33/D8 -> -63.079112 | E35: =E33/E8 -> 600.6531 | F35: =F33/F8 -> 119.68225 | G35: =G33/G8 -> 47.628465
B36: EV/Sales | C36: =C33/C6 -> 8.1241093 | D36: =D33/D6 -> 5.9522351 | E36: =E33/E6 -> 18.463076 | F36: =F33/F6 -> 19.172257 | G36: =G33/G6 -> 7.0192212
B39: EV/EBIT valuation
B40: Year 5 EBIT | C40: =L7 -> 487474.71
B41: WACC | C41: =IF(Overview!C28>0,Overview!C28,WACC!C20) -> 0.0975
B42: Applied EV/EBIT ratio | C42: 25
B43: Terminal EV | C43: =(C40*C42) -> 12186868
B44: PV of Terminal EV | C44: =C43/(1+C41)^5 -> 7653665.1
B45: Total EV | C45: =SUM(H9:K9)+C44 -> 8508821.2
B46: (+) Cash | C46: =Statement!AC107 -> 1416559
B47: (-) Debt | C47: =Statement!AC108 -> 0
B48: Equity value | C48: =C45+C46-C47 -> 9925380.2
B49: Shares outstanding | C49: =Statement!AC78 -> 50122
B50: PV of price per share | C50: =C48/C49 -> 198.02442
B52: PS valuation
B53: Year 5 sales | C53: =L6 -> 3165420.2
B54: Discount rate | C54: =IF(Overview!C29>0,Overview!C29,WACC!C19) -> 0.0975
B55: Applied PS ratio | C55: 4.5
B56: Shares outstanding diluted | C56: =L19 -> 56000.505
B57: Price per share | C57: =(C53*C55)/C56 -> 254.36183
B58: PV of price per share | C58: =C57/(1+C54)^5 -> 159.74574
B60: EV/FCFF valuation
B61: Year 5 FCFF | C61: =L8 -> 573998.69
B62: WACC | C62: =IF(Overview!C28>0,Overview!C28,WACC!C20) -> 0.0975
B63: Applied EV/FCFF ratio | C63: 22
B64: Terminal EV | C64: =(C61*C63) -> 12627971
B65: PV of Terminal EV | C65: =C64/(1+C62)^5 -> 7930689.3
B66: Total EV | C66: =SUM(H9:K9)+C65 -> 8785845.4
B67: (+) Cash | C67: =Statement!AC107 -> 1416559
B68: (-) Debt | C68: =Statement!AC108 -> 0
B69: Equity value | C69: =C66+C67-C68 -> 10202404
B70: Shares outstanding | C70: =Statement!AC78 -> 50122
B71: PV of price per share | C71: =C69/C70 -> 203.55142
B73: EV/Sales valuation
B74: Year 5 Sales | C74: =L6 -> 3165420.2
B75: WACC | C75: =IF(Overview!C28>0,Overview!C28,WACC!C20) -> 0.0975
B76: Applied EV/Sales ratio | C76: 4
B77: Terminal EV | C77: =(C74*C76) -> 12661681
B78: PV of Terminal EV | C78: =C77/(1+C75)^5 -> 7951859.9
B79: Total EV | C79: =SUM(H9:K9)+C78 -> 8807016
B80: (+) Cash | C80: =Statement!AC107 -> 1416559
B81: (-) Debt | C81: =Statement!AC108 -> 0
B82: Equity value | C82: =C79+C80-C81 -> 10223575
B83: Shares outstanding | C83: =Statement!AC78 -> 50122
B84: PV of price per share | C84: =C82/C83 -> 203.9738

Sheet AVG target price
B1: AVG target price
B4: AVG target price
B5: DCF price | C5: =DCF!C26 -> 147.1741
B6: EV/EBIT price | C6: =Multiples!C50 -> 198.02442
B7: PS price | C7: =Multiples!C58 -> 159.74574
B8: EV/FCFF price | C8: =Multiples!C71 -> 203.55142
B9: EV/Sales | C9: =Multiples!C84 -> 203.9738
B10: AVG price | C10: =AVERAGE(C5:C9) -> 182.4939
B11: Current price | C11: =Overview!C5 -> 143.04
B12: Upside/Downside | C12: =(C10-C11)/C11 -> 0.27582424

Sheet DDM
B1: Dividend discount model
C2: History | H2: Forecast
C4: Revenues, earnings cash
B5: Revenues (thousand) | C5: =[2]Revenue!C5 -> 2021 | D5: =[2]Revenue!D5 -> 2022 | E5: =[2]Revenue!E5 -> 2023 | F5: =[2]Revenue!F5 -> 2024 | G5: =[2]Revenue!G5 -> 2025 | H5: =[2]Revenue!H5 -> 2026 | I5: =[2]Revenue!I5 -> 2027 | J5: =[2]Revenue!J5 -> 2028 | ... L5: =[2]Revenue!L5 -> 2030
B6: EPS | C6: =Statement!M26 -> -2.57 | D6: =Statement!N26 -> -1.51 | E6: =Statement!O26 -> 0.35 | F6: =Statement!P26 -> 1.88 | G6: =Statement!Q26 -> 3.2570202
B7: Dividend per share | C7: =Statement!M82 -> 0 | D7: =Statement!N82 -> 0 | E7: =Statement!O82 -> 0 | F7: =Statement!P82 -> 0 | G7: =Statement!Q82 -> 0
C9: Growth rates
B10: % Growth | C10: =C5 -> 2021 | D10: =D5 -> 2022 | E10: =E5 -> 2023 | F10: =F5 -> 2024 | G10: =G5 -> 2025 | H10: =H5 -> 2026 | I10: =I5 -> 2027 | J10: =J5 -> 2028 | ... L10: =L5 -> 2030
B11: EPS | D11: =(D6-C6)/C6 -> -0.41245136 | E11: =(E6-D6)/D6 -> -1.2317881 | F11: =(F6-E6)/E6 -> 4.3714286 | G11: =(G6-F6)/F6 -> 0.73245753
B12: Dividend | D12: =IF(C7=0, IF(D7=0,0,IF(D7>0,1,-1)), (D7-C7)/ABS(C7) ) -> 0 | E12: =IF(D7=0, IF(E7=0,0,IF(E7>0,1,-1)), (E7-D7)/ABS(D7) ) -> 0 | F12: =IF(E7=0, IF(F7=0,0,IF(F7>0,1,-1)), (F7-E7)/ABS(E7) ) -> 0 | G12: =IF(F7=0, IF(G7=0,0,IF(G7>0,1,-1)), (G7-F7)/ABS(F7) ) -> 0
C14: Ratios
B15: % | C15: =C5 -> 2021 | D15: =D5 -> 2022 | E15: =E5 -> 2023 | F15: =F5 -> 2024 | G15: =G5 -> 2025 | H15: =H5 -> 2026 | I15: =I5 -> 2027 | J15: =J5 -> 2028 | ... L15: =L5 -> 2030
B16: Payout | C16: =C7/C6 -> 0 | D16: =D7/D6 -> 0 | E16: =E7/E6 -> 0 | F16: =F7/F6 -> 0 | G16: =G7/G6 -> 0
B20: DDM valuation
B21: Latest dividend | C21: =G7 -> 0
B22: Year 1 growth rate | C22: 0
B23: Year 1 dividend | C23: =C21*(1+C22) -> 0
B24: Discount rate | C24: =IF(Overview!C29>0,Overview!C29,WACC!C19) -> 0.0975
B25: Perpetual dividend growth | C25: 0
B26: PV of price per share | C26: =C23/(C24-C25) -> 0

Sheet Reverse DCF
B1: Reverse DCF
C3: History | H3: Forecast
C5: PV of FCF
B6: $ (thousand) | C6: =Revenue!C5 -> 2021 | D6: =Revenue!D5 -> 2022 | E6: =Revenue!E5 -> 2023 | F6: =Revenue!F5 -> 2024 | G6: =Revenue!G5 -> 2025 | H6: =Revenue!H5 -> 2026 | I6: =Revenue!I5 -> 2027 | J6: =Revenue!J5 -> 2028 | ... L6: =Revenue!L5 -> 2030
B7: FCFF | C7: ='FCF & Other'!C28 -> -37712 | D7: ='FCF & Other'!D28 -> -34866.076 | E7: ='FCF & Other'!E28 -> 16325.406 | F7: ='FCF & Other'!F28 -> 119828.2 | G7: ='FCF & Other'!G28 -> 152914.16 | H7: =G7*(1+$C$17) -> 197259.27 | I7: =H7*(1+$C$17) -> 254464.45 | J7: =I7*(1+$C$17) -> 328259.14 | K7: =J7*(1+$C$17) -> 423454.3 | L7: =K7*(1+$C$17) -> 546256.04
B8: Perpetual cashflow | L8: =L7*(1+C20)/(C21-C20) -> 7189434.4
B9: Period | H9: 1 | I9: 2 | J9: 3 | K9: 4 | L9: 5
B10: PV of FCFF | H10: =H7/(1+$C$21)^H9 -> 179735.09 | I10: =I7/(1+$C$21)^I9 -> 211260.38 | J10: =J7/(1+$C$21)^J9 -> 248315.17 | K10: =K7/(1+$C$21)^K9 -> 291869.31 | L10: =L7/(1+$C$21)^L9 -> 343062.78
B11: PV of Perpetual cashflow | L11: =L8/(1+C21)^L9 -> 4515148.9
B14: Growth adjustment
B15: Current Price | C15: =Overview!C5 -> 143.04
B16: Calculated Price | C16: =C36 -> 154.01938
B17: FCFF Growth | C17: 0.29 | E17: Modify until Calculated Price is very close to Current Price
B19: Input parameters
B20: Perpetual growth | C20: 0.02
B21: WACC | C21: =IF(Overview!C28>0,Overview!C28,WACC!C20) -> 0.0975
B22: Shares outstanding | C22: =Statement!AC75 -> 46786
B23: Market cap | C23: =C15*C22 -> 6692269.4
B24: Cash | C24: =Statement!AC107 -> 1416559
B25: Debt | C25: =Statement!AC108 -> 0
B26: Enterprise Value | C26: =C23+C25-C24 -> 5275710.4
B28: Result
B29: Total PV of Unlevered FCF | C29: =SUM(H10:L10) -> 1274242.7
B30: PV of Perpetual cashflow | C30: =L11 -> 4515148.9
B31: Enterprise value | C31: =C29+C30 -> 5789391.6
B32: (+) Cash | C32: =C24 -> 1416559
B33: (-) Debt | C33: =C25 -> 0
B34: Equity value | C34: =C31+C32-C33 -> 7205950.6
B35: Shares outstanding | C35: =C22 -> 46786
B36: Price per share | C36: =C34/C35 -> 154.01938
