Workbook

Sheet Overview
B2: Automatic Data | E2: At a glance | H2: Valuation | K2: Links
B3: Company | C3: #VALUE! | E3: Market capitalization | F3: =Statement!AC153 -> 1035640.2 | H3: ='AVG target price'!B5 -> DCF price | I3: ='AVG target price'!C5 -> 928.67184 | K3: Financials ->'!B13
B4: Ticker | C4: {=_FV(C3,"Ticker symbol",TRUE)} -> MU | E4: Enterprise value | F4: =Statement!AC154 -> 967366.2 | H4: ='AVG target price'!B6 -> EV/EBIT price | I4: ='AVG target price'!C6 -> 1281.1934 | K4: Analysis ->'!B13
B5: Price | C5: {=_FV(C3,"Price",TRUE)} -> 903.7 | E5: EPS | F5: =Statement!AC26 -> 74.21 | H5: ='AVG target price'!B7 -> PS price | I5: ='AVG target price'!C7 -> 567.445 | K5: Forecast ->'!B13
B6: Price Extended Hours | C6: {=_FV(C3,"Price (Extended hours)",TRUE)} -> 904.75 | E6: PE | F6: =Statement!AC150 -> 12.177604 | H6: ='AVG target price'!B8 -> EV/FCFF price | I6: ='AVG target price'!C8 -> 1729.7038 | K6: Valuation ->'!B13
B7: Day change | C7: {=_FV(C3,"Change")} -> 26.15 | E7: PS | F7: =Statement!AC151 -> 7.7554217 | H7: ='AVG target price'!B9 -> EV/Sales price | I7: ='AVG target price'!C9 -> 912.37103
B8: Day change extended | C8: {=_FV(C3,"Change (extended hours)",TRUE)} -> 1.05 | E8: FCF Yield | F8: =Statement!AC161 -> 0.055646739 | H8: ='AVG target price'!B10 -> AVG price | I8: ='AVG target price'!C10 -> 1083.877
B9: Day change % | C9: {=_FV(C3,"Change (%)",TRUE)} -> 0.029799 | E9: Earnings Yield | F9: =Statement!AC162 -> 0.082117959 | H9: ='AVG target price'!B12 -> Upside/Downside | I9: ='AVG target price'!C12 -> 0.19937703
B10: Day change extended % | C10: {=_FV(C3,"Change % (extended hours)",TRUE)} -> 0.001162 | E10: Buyback Yield | F10: =Statement!AC164 -> 0.0006276311
B11: 52 week high | C11: {=_FV(C3,"52 week high",TRUE)} -> 1255 | E11: Dividend Yield | F11: =Statement!AC163 -> 0.00062520748 | H11: DDM price | I11: =DDM!C26 -> 5.1961126
B12: 52 week low | C12: {=_FV(C3,"52 week low",TRUE)} -> 192.59 | E12: ROA | F12: =Statement!AC123 -> 0.43376317
B13: Beta | C13: {=_FV(C3,"Beta")} -> 2.3616 | E13: ROE | F13: =Statement!AC125 -> 0.61403547 | H13: Reverse DCF rate | I13: ='Reverse DCF'!C17 -> 0.24
B14: Avg volume | C14: {=_FV(C3,"Volume average",TRUE)} -> 26399323 | E14: ROIC | F14: =Statement!AC140 -> 1.2071782 | H14: Reverse DCF price | I14: ='Reverse DCF'!C16 -> 881.76467
E15: Net Cash/Market Cap | F15: =Statement!AC176 -> 0.06592444
E16: Net Cash/Share | F16: =Statement!AC175 -> 60.472985 | H16: Discount rates used
B17: Unit data and other info | E17: Insider Ownership | F17: =Statement!AC171 -> 0.002617801 | H17: WACC | I17: =DCF!C15 -> 0.15559907
B18: Units | C18: M | E18: Net Trade Cycle | F18: =Statement!AC144 -> -74.647977 | H18: Cost of Equity | I18: =Multiples!C54 -> 0.156152
B19: Units conversion | C19: 1000000 | E19: Net Debt/Equity | F19: =Statement!AC146 -> -0.49338768
B20: Has operating lease | C20: Yes | E20: Quick Ratio | F20: =Statement!AC147 -> 3.9898843
B21: Has finance lease | C21: No
B22: Has debt | C22: Yes
B25: Constants | E25: 10 Year Bond Yield
B26: Default tax rate | C26: 0.21 | E26: #VALUE! | F26: {=_FV(E26,"Price")} -> 49.88
B27: Cost of debt | C27: 0.057 | E27: Percentage | F27: =F26/1000 -> 0.04988
B28: Manual WACC | C28: 0
B29: Manual Cost of Equity | C29: 0
B33: Info
B35: Mission: | C35: Transform how the world uses information to enrich life for all
B36: Auditor: | C36: PwC
B37: Business units: | C37: Cloud memory business unit (CMBU) - memory for large hyperscalers and HBM for datacenter customers
C38: Core datacenter business unit (CDBU) - memory for mid-tier cloud, enterprise and OEM datacenter customers and storage for all datacenter customers
C39: Mobile and client business unit (MCBU) - memory and storage for mobile and client
C40: Automotive and embedded business unit (AEBU) - memory and storage for automotive, industrial and consumer
B46: Notes
B48: Date: | C48: 30.09.2026 | E48: Q4 2026
B49: - | C49: In Q1 2027 gross margin will be 85.95% and Opex $2.35B
B50: - | C50: 26 signed agreements with customers in datacenter consumer and automotive fields representing more than 35% of revenue through 2030
B51: - | C51: Cloud memory revenue increased because of higher pricing and higher bit shipments
B52: - | C52: Datacenter revenue increased because of higher pricing and higher bit shipments
B53: - | C53: Mobile and client revenue increased because of higher pricing though they had lower bit shipments
B54: - | C54: Automotive revenue increaeed because of higher pricing and higher bit shipments
B57: Date: | C57: 17.06.2026 | E57: Q3 2026
B58: - | C58: Tight supply conditions to persist beyond calendar year 2027
B59: - | C59: 16 signed agreements with customers in datacenter consumer and automotive fields
C60: DRAM volume of agreements: 20%
C61: NAND volume of agreements: 25%
C62: Agreements until end of 2030
C63: 14 of the SCAs have planned revenue of 100B until end of term
B64: - | C64: Cloud memory revenue increased because of higher pricing and higher bit shipments
B65: - | C65: Datacenter revenue increased because of higher pricing
B66: - | C66: Mobile and client revenue increased because of higher pricing though they had lower bit shipments
B67: - | C67: Automotive revenue increaeed because of higher pricing and higher bit shipments
B68: - | C68: Q4 gross margin expected at 86% and OpEx at 1.65B and CapEx at 10B
B69: - | C69: CapEx in fiscal 2027 will increase above 2026 with 50% YoY each quarter and OpEx will increase in fiscal 2027 with about 1B
B71: Date: | C71: 10.12.2025 | E71: Q1 2026
B72: - | C72: HBM TAM to be 100B in 2028
B78: Adjustments
B80: Date: | C80: 30.04.2026 | E80: Q1 2027

Sheet Financials ->
H5: Links
H6: Overview'!B3
H7: Financials ->'!B13
H8: Analysis ->'!B13
H9: Forecast ->'!B13
H10: Valuation ->'!B13
B13: Financials ->

Sheet Statement
B2: Date | L2: 02.09.2021 | M2: 01.09.2022 | N2: 31.08.2023 | O2: 29.08.2024 | P2: 28.08.2025 | Q2: 03.09.2025 | T2: 28.11.2024 | U2: 27.02.2025 | V2: 29.05.2025 | W2: 28.08.2025 | X2: 27.11.2025 | Y2: 26.02.2026 | Z2: 28.05.2026 | AA2: 03.09.2026
B3: FY | L3: 2021 | M3: 2022 | N3: 2023 | O3: 2024 | P3: 2025 | Q3: 2026 | T3: Q1 2025 | U3: Q2 2025 | V3: Q3 2025 | W3: Q4 2025 | X3: Q1 2026 | Y3: Q2 2026 | Z3: Q3 2026 | AA3: Q4 2026 | AC3: TTM/YTD
B4: Income statement
B5: Revenue | L5: 27705 | M5: 30758 | N5: 15540 | O5: 25111 | P5: 37378 | Q5: 133188 | T5: 8709 | U5: 8053 | V5: 9301 | W5: 11315 | X5: 13643 | Y5: 23860 | Z5: 41456 | AA5: 54229 | AC5: =SUM(X5:AA5) -> 133188
B6: COGS | L6: 17282 | M6: 16860 | N6: 16956 | O6: 19498 | P6: 22505 | Q6: 25684 | T6: 5361 | U6: 5090 | V6: 5793 | W6: 6261 | X6: 5997 | Y6: 6105 | Z6: 6400 | AA6: 7182 | AC6: =SUM(X6:AA6) -> 25684
B7: Gross Profit | C7: =C5-C6 -> 0 | D7: =D5-D6 -> 0 | E7: =E5-E6 -> 0 | F7: =F5-F6 -> 0 | G7: =G5-G6 -> 0 | H7: =H5-H6 -> 0 | I7: =I5-I6 -> 0 | J7: =J5-J6 -> 0 | ... Q7: =Q5-Q6 -> 107504 | T7: =T5-T6 -> 3348 | U7: =U5-U6 -> 2963 | V7: =V5-V6 -> 3508 | W7: =W5-W6 -> 5054 | X7: =X5-X6 -> 7646 | Y7: =Y5-Y6 -> 17755 | Z7: =Z5-Z6 -> 35056 | AA7: =AA5-AA6 -> 47047 | AC7: =SUM(X7:AA7) -> 107504
B8: R&D | L8: 2663 | M8: 3116 | N8: 3114 | O8: 3430 | P8: 3798 | Q8: 5650 | T8: 888 | U8: 898 | V8: 965 | W8: 1047 | X8: 1171 | Y8: 1250 | Z8: 1316 | AA8: 1913 | AC8: =SUM(X8:AA8) -> 5650
B9: Sales and marketing | L9: 894 | M9: 1066 | N9: 920 | O9: 1129 | P9: 1205 | Q9: 1947 | T9: 288 | U9: 285 | V9: 318 | W9: 314 | X9: 337 | Y9: 344 | Z9: 407 | AA9: 859 | AC9: =SUM(X9:AA9) -> 1947
B10: Other income/expense | L10: =488+95 -> 583 | M10: =48-34 -> 14 | N10: =171+124 -> 295 | O10: -250 | P10: 100 | Q10: 567 | T10: -2 | U10: 7 | V10: 56 | W10: 39 | X10: 2 | Y10: 26 | Z10: 15 | AA10: 524 | AC10: =SUM(X10:AA10) -> 567
B11: OpEx | C11: =SUM(C8:C10) -> 0 | D11: =SUM(D8:D10) -> 0 | E11: =SUM(E8:E10) -> 0 | F11: =SUM(F8:F10) -> 0 | G11: =SUM(G8:G10) -> 0 | H11: =SUM(H8:H10) -> 0 | I11: =SUM(I8:I10) -> 0 | J11: =SUM(J8:J10) -> 0 | ... Q11: =SUM(Q8:Q10) -> 8164 | T11: =SUM(T8:T10) -> 1174 | U11: =SUM(U8:U10) -> 1190 | V11: =SUM(V8:V10) -> 1339 | W11: =SUM(W8:W10) -> 1400 | X11: =SUM(X8:X10) -> 1510 | Y11: =SUM(Y8:Y10) -> 1620 | Z11: =SUM(Z8:Z10) -> 1738 | AA11: =SUM(AA8:AA10) -> 3296 | AC11: =SUM(X11:AA11) -> 8164
B12: Operating income | L12: 6283 | M12: 9702 | N12: -5745 | O12: 1304 | P12: 9770 | Q12: 99340 | T12: 2174 | U12: 1773 | V12: 2169 | W12: 3654 | X12: 6136 | Y12: 16135 | Z12: 33318 | AA12: 43751 | AC12: =SUM(X12:AA12) -> 99340
B13: Interest income/expense | L13: =37-183 -> -146 | M13: =96-189 -> -93 | N13: =468-388 -> 80 | O13: =529-562 -> -33 | P13: =496-477 -> 19 | Q13: =1084-106 -> 978 | T13: =107-118 -> -11 | U13: =108-112 -> -4 | V13: =135-123 -> 12 | W13: =146-124 -> 22 | X13: =139-74 -> 65 | Y13: =155-32 -> 123 | Z13: 215 | AA13: 575 | AC13: =SUM(X13:AA13) -> 978
B14: Other income/expense | L14: 81 | M14: -38 | N14: 7 | O14: -31 | P14: -135 | Q14: -647 | T14: -11 | U14: -11 | V14: -68 | W14: -45 | X14: -140 | Y14: -98 | Z14: -321 | AA14: -88 | AC14: =SUM(X14:AA14) -> -647
B15: Income before taxes | L15: 6218 | M15: 9571 | N15: -5658 | O15: 1240 | P15: 9654 | Q15: 99671 | T15: 2152 | U15: 1758 | V15: 2113 | W15: 3631 | X15: 6061 | Y15: 16160 | Z15: 33212 | AA15: 44238 | AC15: =SUM(X15:AA15) -> 99671
B16: Income tax expense/benefit | L16: -394 | M16: -888 | N16: -177 | O16: -451 | P16: -1124 | Q16: -14761 | T16: -283 | U16: -177 | V16: -235 | W16: -429 | X16: -829 | Y16: -2371 | Z16: -4978 | AA16: -6583 | AC16: =SUM(X16:AA16) -> -14761
B17: Non-controlling interest | L17: 0 | M17: 0 | N17: 0 | O17: 0 | P17: 0 | Q17: 0 | T17: 0 | U17: 0 | V17: 0 | W17: 0 | X17: 0 | Y17: 0 | Z17: 0 | AA17: 0 | AC17: =SUM(X17:AA17) -> 0
B18: Net income | L18: 5861 | M18: 8687 | N18: -5833 | O18: 778 | P18: 8539 | Q18: 84969 | T18: 1870 | U18: 1583 | V18: 1885 | W18: 3201 | X18: 5240 | Y18: 13785 | Z18: 28243 | AA18: 37701 | AC18: =SUM(X18:AA18) -> 84969
B19: Basic Shares outstanding avg | L19: 1120 | M19: 1112 | N19: 1093 | O19: 1105 | P19: 1116 | Q19: 1127 | T19: 1111 | U19: 1115 | V19: 1118 | W19: 1120 | X19: 1125 | Y19: 1126 | Z19: 1128 | AA19: 1130 | AC19: =AVERAGE(X19:AA19) -> 1127.25
B20: Basic Shares outstanding avg adjusted | C20: =C19*C$85 -> 0 | D20: =D19*D$85 -> 0 | E20: =E19*E$85 -> 0 | F20: =F19*F$85 -> 0 | G20: =G19*G$85 -> 0 | H20: =H19*H$85 -> 0 | I20: =I19*I$85 -> 0 | J20: =J19*J$85 -> 0 | ... Q20: =Q19*Q$85 -> 1127 | T20: =T19*T$85 -> 1111 | U20: =U19*U$85 -> 1115 | V20: =V19*V$85 -> 1118 | W20: =W19*W$85 -> 1120 | X20: =X19*X$85 -> 1125 | Y20: =Y19*Y$85 -> 1126 | Z20: =Z19*Z$85 -> 1128 | AA20: =AA19*AA$85 -> 1130 | AC20: =AC19*AC$85 -> 1127.25
B21: Diluted Shares outstanding avg | L21: 1141 | M21: 1122 | N21: 1093 | O21: 1118 | P21: 1125 | Q21: 1143 | T21: 1122 | U21: 1123 | V21: 1125 | W21: 1131 | X21: 1138 | Y21: 1142 | Z21: 1145 | AA21: 1147 | AC21: =AVERAGE(X21:AA21) -> 1143
B22: Diluted Shares outstanding avg adjusted | C22: =C21*C$85 -> 0 | D22: =D21*D$85 -> 0 | E22: =E21*E$85 -> 0 | F22: =F21*F$85 -> 0 | G22: =G21*G$85 -> 0 | H22: =H21*H$85 -> 0 | I22: =I21*I$85 -> 0 | J22: =J21*J$85 -> 0 | ... Q22: =Q21*Q$85 -> 1143 | T22: =T21*T$85 -> 1122 | U22: =U21*U$85 -> 1123 | V22: =V21*V$85 -> 1125 | W22: =W21*W$85 -> 1131 | X22: =X21*X$85 -> 1138 | Y22: =Y21*Y$85 -> 1142 | Z22: =Z21*Z$85 -> 1145 | AA22: =AA21*AA$85 -> 1147 | AC22: =AC21*AC$85 -> 1143
B23: Basic EPS | L23: 5.23 | M23: 7.81 | N23: -5.34 | O23: 0.7 | P23: 7.65 | Q23: 75.38 | T23: 1.68 | U23: 1.42 | V23: 1.69 | W23: 2.86 | X23: 4.66 | Y23: 12.25 | Z23: 25.03 | AA23: 33.36 | AC23: =SUM(X23:AA23) -> 75.3
B24: Basic EPS adjusted | L24: =L23/L$85 -> 5.23 | M24: =M23/M$85 -> 7.81 | N24: =N23/N$85 -> -5.34 | O24: =O23/O$85 -> 0.7 | P24: =P23/P$85 -> 7.65 | Q24: =Q23/Q$85 -> 75.38 | T24: =T23/T$85 -> 1.68 | U24: =U23/U$85 -> 1.42 | V24: =V23/V$85 -> 1.69 | W24: =W23/W$85 -> 2.86 | X24: =X23/X$85 -> 4.66 | Y24: =Y23/Y$85 -> 12.25 | Z24: =Z23/Z$85 -> 25.03 | AA24: =AA23/AA$85 -> 33.36 | AC24: =AC23/AC$85 -> 75.3
B25: Diluted EPS | L25: 5.14 | M25: 7.75 | N25: -5.34 | O25: 0.7 | P25: 7.59 | Q25: 74.33 | T25: 1.67 | U25: 1.41 | V25: 1.68 | W25: 2.83 | X25: 4.6 | Y25: 12.07 | Z25: 24.67 | AA25: 32.87 | AC25: =SUM(X25:AA25) -> 74.21
B26: Diluted EPS adjusted | L26: =L25/L$85 -> 5.14 | M26: =M25/M$85 -> 7.75 | N26: =N25/N$85 -> -5.34 | O26: =O25/O$85 -> 0.7 | P26: =P25/P$85 -> 7.59 | Q26: =Q25/Q$85 -> 74.33 | T26: =T25/T$85 -> 1.67 | U26: =U25/U$85 -> 1.41 | V26: =V25/V$85 -> 1.68 | W26: =W25/W$85 -> 2.83 | X26: =X25/X$85 -> 4.6 | Y26: =Y25/Y$85 -> 12.07 | Z26: =Z25/Z$85 -> 24.67 | AA26: =AA25/AA$85 -> 32.87 | AC26: =AC25/AC$85 -> 74.21
B28: Balance sheet
B29: Cash and cash equivalents | L29: =7763+870 -> 8633 | M29: =8262+1069 -> 9331 | N29: =8577+1017 -> 9594 | O29: =7041+1065 -> 8106 | P29: =9642+665 -> 10307 | Q29: =38364+5070 -> 43434 | T29: =6693+895 -> 7588 | U29: =7552+663 -> 8215 | V29: =10163+648 -> 10811 | W29: =9642+665 -> 10307 | X29: =9731+587 -> 10318 | Y29: =13908+681 -> 14589 | Z29: =24995+1027 -> 26022 | AA29: =38364+5070 -> 43434 | AC29: =AA29 -> 43434
B30: Acc receivable | L30: 5311 | M30: 5130 | N30: 2443 | O30: 6615 | P30: 9265 | Q30: 36197 | T30: 7423 | U30: 6504 | V30: 7436 | W30: 9265 | X30: 10184 | Y30: 17314 | Z30: 31025 | AA30: 36197 | AC30: =AA30 -> 36197
B31: Inventory | L31: 4487 | M31: 6663 | N31: 8387 | O31: 8875 | P31: 8355 | Q31: 10372 | T31: 8705 | U31: 9007 | V31: 8727 | W31: 8355 | X31: 8205 | Y31: 8267 | Z31: 8567 | AA31: 10372 | AC31: =AA31 -> 10372
B32: Current assets | L32: 19907 | M32: 21781 | N32: 21244 | O32: 24372 | P32: 28841 | Q32: 91070 | T32: 24493 | U32: 24689 | V32: 27919 | W32: 28841 | X32: 29665 | Y32: 41413 | Z32: 66737 | AA32: 91070 | AC32: =AA32 -> 91070
B33: PP&E | L33: 33213 | M33: 38549 | N33: 37928 | O33: 39749 | P33: 46590 | Q33: 63310 | T33: 41476 | U33: 42528 | V33: 44773 | W33: 46590 | X33: 48477 | Y33: 51408 | Z33: 56426 | AA33: 63310 | AC33: =AA33 -> 63310
B34: Marketable securities and investments | L34: 1765 | M34: 1647 | N34: 844 | O34: 1046 | P34: 1629 | Q34: 30019 | T34: 1156 | U34: 1375 | V34: 1402 | W34: 1629 | X34: 1697 | Y34: 2038 | Z34: 4106 | AA34: 30019 | AC34: =AA34 -> 30019
B35: Goodwill | L35: 1228 | M35: 1228 | N35: 1150 | O35: 1150 | P35: 1150 | Q35: 1150 | T35: 1150 | U35: 1150 | V35: 1150 | W35: 1150 | X35: 1150 | Y35: 1150 | Z35: 1150 | AA35: 1150 | AC35: =AA35 -> 1150
B36: Long term assets | L36: =L37-L32 -> 38942 | M36: =M37-M32 -> 44502 | N36: =N37-N32 -> 43010 | O36: =O37-O32 -> 45044 | P36: =P37-P32 -> 53957 | Q36: =Q37-Q32 -> 104818 | T36: =T37-T32 -> 46968 | U36: =U37-U32 -> 48364 | V36: =V37-V32 -> 50478 | W36: =W37-W32 -> 53957 | X36: =X37-X32 -> 56306 | Y36: =Y37-Y32 -> 60096 | Z36: =Z37-Z32 -> 67375 | AA36: =AA37-AA32 -> 104818 | AC36: =AA36 -> 104818
B37: Total assets | L37: 58849 | M37: 66283 | N37: 64254 | O37: 69416 | P37: 82798 | Q37: 195888 | T37: 71461 | U37: 73053 | V37: 78397 | W37: 82798 | X37: 85971 | Y37: 101509 | Z37: 134112 | AA37: 195888 | AC37: =AA37 -> 195888
B38: Acc payable | L38: 5325 | M38: 6090 | N38: 3958 | O38: 7299 | P38: 9649 | Q38: 22605 | T38: 7126 | U38: 6176 | V38: 8761 | W38: 9649 | X38: 9769 | Y38: 10997 | Z38: 15521 | AA38: 22605 | AC38: =AA38 -> 22605
B39: Debt | L39: 155 | M39: 103 | N39: 278 | O39: 431 | P39: 560 | Q39: 491 | T39: 533 | U39: 504 | V39: 538 | W39: 560 | X39: 569 | Y39: 585 | Z39: 582 | AA39: 491 | AC39: =AA39 -> 491
B40: Current liabilities | L40: 6424 | M40: 7539 | N40: 4765 | O40: 9248 | P40: 11454 | Q40: 27482 | T40: 9015 | U40: 7877 | V40: 10135 | W40: 11454 | X40: 12060 | Y40: 14296 | Z40: 19488 | AA40: 27482 | AC40: =AA40 -> 27482
B41: Debt | L41: 6621 | M41: 6803 | N41: 13052 | O41: 12966 | P41: 14017 | Q41: 4688 | T41: 13252 | U41: 13851 | V41: 15003 | W41: 14017 | X41: 11187 | Y41: 9557 | Z41: 5140 | AA41: 4688 | AC41: =AA41 -> 4688
B42: Long term liabilities | L42: =L43-L40 -> 8492 | M42: =M43-M40 -> 8837 | N42: =N43-N40 -> 15369 | O42: =O43-O40 -> 15037 | P42: =P43-P40 -> 17179 | Q42: =Q43-Q40 -> 30028 | T42: =T43-T40 -> 15649 | U42: =U43-U40 -> 16543 | V42: =V43-V40 -> 17514 | W42: =W43-W40 -> 17179 | X42: =X43-X40 -> 15105 | Y42: =Y43-Y40 -> 14754 | Z42: =Z43-Z40 -> 13900 | AA42: =AA43-AA40 -> 30028 | AC42: =AA42 -> 30028
B43: Total liabilities | L43: 14916 | M43: 16376 | N43: 20134 | O43: 24285 | P43: 28633 | Q43: 57510 | T43: 24664 | U43: 24420 | V43: 27649 | W43: 28633 | X43: 27165 | Y43: 29050 | Z43: 33388 | AA43: 57510 | AC43: =AA43 -> 57510
B44: Treasury stock | L44: -4695 | M44: -7127 | N44: -7552 | O44: -7852 | P44: -7852 | Q44: -8502 | T44: -7852 | U44: -7852 | V44: -7852 | W44: -7852 | X44: -8152 | Y44: -8502 | Z44: -8502 | AA44: -8502 | AC44: =AA44 -> -8502
B45: Preferred stock | L45: 0 | M45: 0 | N45: 0 | O45: 0 | P45: 0 | Q45: 0 | T45: 0 | U45: 0 | V45: 0 | W45: 0 | X45: 0 | Y45: 0 | Z45: 0 | AA45: 0 | AC45: =AA45 -> 0
B46: Paid in capital | L46: 9453 | M46: 10197 | N46: 11036 | O46: 12115 | P46: 13339 | Q46: 14974 | T46: 12317 | U46: 12711 | V46: 12960 | W46: 13339 | X46: 13610 | Y46: 14092 | Z46: 14442 | AA46: 14974 | AC46: =AA46 -> 14974
B47: Accumulated income/loss | L47: 39051 | M47: 47274 | N47: 40824 | O47: 40877 | P47: 48583 | Q47: 131851 | T47: 42427 | U47: 43839 | V47: 45559 | W47: 48583 | X47: 53344 | Y47: 66824 | Z47: 94682 | AA47: 131851 | AC47: =AA47 -> 131851
B48: Non-controlling interest | L48: 0 | M48: 0 | N48: 0 | O48: 0 | P48: 0 | Q48: 0 | T48: 0 | U48: 0 | V48: 0 | W48: 0 | X48: 0 | Y48: 0 | Z48: 0 | AA48: 0 | AC48: =AA48 -> 0
B49: Stockholder equity | L49: 43933 | M49: 49907 | N49: 44120 | O49: 45131 | P49: 54165 | Q49: 138378 | T49: 46797 | U49: 48633 | V49: 50748 | W49: 54165 | X49: 58806 | Y49: 72459 | Z49: 100724 | AA49: 138378 | AC49: =AA49 -> 138378
B50: Total liabilities and equity | L50: 58849 | M50: 66283 | N50: 64254 | O50: 69416 | P50: 82798 | Q50: 195888 | T50: 71461 | U50: 73053 | V50: 78397 | W50: 82798 | X50: 85971 | Y50: 101509 | Z50: 134112 | AA50: 195888 | AC50: =AA50 -> 195888
B52: Cashflow statement
B53: D&A | L53: 6214 | M53: 7116 | N53: 7756 | O53: 7780 | P53: 8352 | Q53: 9503 | T53: 2030 | U53: 2079 | V53: 2094 | W53: 2149 | X53: 2212 | Y53: 2286 | Z53: 2364 | AA53: 2641 | AC53: =SUM(X53:AA53) -> 9503
B54: Stock-based compensation | L54: 378 | M54: 514 | N54: 596 | O54: 833 | P54: 972 | Q54: 1333 | T54: 220 | U54: 249 | V54: 253 | W54: 250 | X54: 290 | Y54: 309 | Z54: 355 | AA54: 379 | AC54: =SUM(X54:AA54) -> 1333
B55: Change in accounts receivable | L55: -1446 | M55: 190 | N55: 2763 | O55: -3581 | P55: -1776 | Q55: -25206 | T55: -817 | U55: 1155 | V55: -461 | W55: -1653 | X55: -871 | Y55: -7427 | Z55: -11655 | AA55: -5253 | AC55: =SUM(X55:AA55) -> -25206
B56: Change in inventory | L56: 866 | M56: -2179 | N56: -3555 | O56: -488 | P56: 520 | Q56: -2017 | T56: 170 | U56: -302 | V56: 280 | W56: 372 | X56: 150 | Y56: -62 | Z56: -300 | AA56: -1805 | AC56: =SUM(X56:AA56) -> -2017
B57: Change in accounts payable | L57: 210 | M57: 744 | N57: -1302 | O57: 1915 | P57: 862 | Q57: 8707 | T57: -241 | U57: -473 | V57: 752 | W57: 824 | X57: 156 | Y57: 772 | Z57: 2401 | AA57: 5378 | AC57: =SUM(X57:AA57) -> 8707
B58: Change in other operating NWC | L58: 0 | M58: 0 | N58: =19-817 -> -798 | O58: =989+281 -> 1270 | P58: =-272+328 -> 56 | Q58: =3141+9633 -> 12774 | T58: =132-161 -> -29 | U58: -97 | V58: -296 | W58: 478 | X58: =449+547 -> 996 | Y58: 2579 | Z58: 3767 | AA58: 5432 | AC58: =SUM(X58:AA58) -> 12774
B59: Operating cashflow | L59: 12468 | M59: 15181 | N59: 1559 | O59: 8507 | P59: 17525 | Q59: 89675 | T59: 3244 | U59: 3942 | V59: 4609 | W59: 5730 | X59: 8411 | Y59: 11903 | Z59: 25388 | AA59: 43973 | AC59: =SUM(X59:AA59) -> 89675
B60: CapEx | L60: -10030 | M60: -12067 | N60: -7676 | O60: -8386 | P60: -15857 | Q60: -30712 | T60: -3206 | U60: -4055 | V60: -2938 | W60: -5658 | X60: -5389 | Y60: -6387 | Z60: -7826 | AA60: -11110 | AC60: =SUM(X60:AA60) -> -30712
B61: Capitalized software | L61: 0 | M61: 0 | N61: 0 | O61: 0 | P61: 0 | Q61: 0 | T61: 0 | U61: 0 | V61: 0 | W61: 0 | X61: 0 | Y61: 0 | Z61: 0 | AA61: 0 | AC61: =SUM(X61:AA61) -> 0
B62: Investing cashflow | L62: -10589 | M62: -11585 | N62: -6191 | O62: -8309 | P62: -14087 | Q62: -61641 | T62: -3148 | U62: -3152 | V62: -2589 | W62: -5198 | X62: -4594 | Y62: -5525 | Z62: -9569 | AA62: -41953 | AC62: =SUM(X62:AA62) -> -61641
B63: Repurchase stock | L63: =-1200-94 -> -1294 | M63: =-2432-125 -> -2557 | N63: -425 | O63: -300 | P63: 0 | Q63: -650 | T63: -207 | U63: -45 | V63: -38 | W63: 290 | X63: -367 | Y63: -283 | Z63: 0 | AA63: 0 | AC63: =SUM(X63:AA63) -> -650
B64: Dividends | L64: 0 | M64: -461 | N64: -504 | O64: -513 | P64: -522 | Q64: -610 | T64: -131 | U64: -130 | V64: -131 | W64: -130 | X64: -134 | Y64: -132 | Z64: -171 | AA64: -173 | AC64: =SUM(X64:AA64) -> -610
B65: Dividends to minority interest | L65: 0 | M65: 0 | N65: 0 | O65: 0 | P65: 0 | Q65: 0 | T65: 0 | U65: 0 | V65: 0 | W65: 0 | X65: 0 | Y65: 0 | Z65: 0 | AA65: 0 | AC65: =SUM(X65:AA65) -> 0
B66: Financing cashflow | L66: -1781 | M66: -2980 | N66: 4983 | O66: -1842 | P66: -850 | Q66: 630 | T66: -422 | U66: 96 | V66: 540 | W66: -1064 | X66: -3745 | Y66: -2167 | Z66: -4734 | AA66: 11276 | AC66: =SUM(X66:AA66) -> 630
B68: Sanity checks
B69: Calculated Net Income | C69: =C5-C6-C11+C13+C14+C16-C17 -> 0 | D69: =D5-D6-D11+D13+D14+D16-D17 -> 0 | E69: =E5-E6-E11+E13+E14+E16-E17 -> 0 | F69: =F5-F6-F11+F13+F14+F16-F17 -> 0 | G69: =G5-G6-G11+G13+G14+G16-G17 -> 0 | H69: =H5-H6-H11+H13+H14+H16-H17 -> 0 | I69: =I5-I6-I11+I13+I14+I16-I17 -> 0 | J69: =J5-J6-J11+J13+J14+J16-J17 -> 0 | ... Q69: =Q5-Q6-Q11+Q13+Q14+Q16-Q17 -> 84910 | T69: =T5-T6-T11+T13+T14+T16-T17 -> 1869 | U69: =U5-U6-U11+U13+U14+U16-U17 -> 1581 | V69: =V5-V6-V11+V13+V14+V16-V17 -> 1878 | W69: =W5-W6-W11+W13+W14+W16-W17 -> 3202 | X69: =X5-X6-X11+X13+X14+X16-X17 -> 5232 | Y69: =Y5-Y6-Y11+Y13+Y14+Y16-Y17 -> 13789 | Z69: =Z5-Z6-Z11+Z13+Z14+Z16-Z17 -> 28234 | AA69: =AA5-AA6-AA11+AA13+AA14+AA16-AA17 -> 37655 | AC69: =AC5-AC6-AC11+AC13+AC14+AC16-AC17 -> 84910
B70: Check Net Income | C70: =C18-C69 -> 0 | D70: =D18-D69 -> 0 | E70: =E18-E69 -> 0 | F70: =F18-F69 -> 0 | G70: =G18-G69 -> 0 | H70: =H18-H69 -> 0 | I70: =I18-I69 -> 0 | J70: =J18-J69 -> 0 | ... Q70: =Q18-Q69 -> 59 | T70: =T18-T69 -> 1 | U70: =U18-U69 -> 2 | V70: =V18-V69 -> 7 | W70: =W18-W69 -> -1 | X70: =X18-X69 -> 8 | Y70: =Y18-Y69 -> -4 | Z70: =Z18-Z69 -> 9 | AA70: =AA18-AA69 -> 46 | AC70: =AC18-AC69 -> 59
B71: Check balance | C71: =C37-(C43+C112) -> 0 | D71: =D37-(D43+D112) -> 0 | E71: =E37-(E43+E112) -> 0 | F71: =F37-(F43+F112) -> 0 | G71: =G37-(G43+G112) -> 0 | H71: =H37-(H43+H112) -> 0 | I71: =I37-(I43+I112) -> 0 | J71: =J37-(J43+J112) -> 0 | ... Q71: =Q37-(Q43+Q112) -> 0 | T71: =T37-(T43+T112) -> 0 | U71: =U37-(U43+U112) -> 0 | V71: =V37-(V43+V112) -> 0 | W71: =W37-(W43+W112) -> 0 | X71: =X37-(X43+X112) -> 0 | Y71: =Y37-(Y43+Y112) -> 0 | Z71: =Z37-(Z43+Z112) -> 0 | AA71: =AA37-(AA43+AA112) -> 0 | AC71: =AC37-(AC43+AC112) -> 0
B73: Other data
B74: Shares outstanding | L74: 1119 | M74: 1087 | N74: 1098 | O74: 1109 | P74: 1122 | Q74: 1129 | T74: 1114 | U74: 1118 | V74: 1119 | W74: 1122 | X74: 1126 | Y74: 1128 | Z74: 1129 | AA74: 1129 | AC74: =AA74 -> 1129
B75: Split adjusted shares outstanding | L75: =L74*L85 -> 1119 | M75: =M74*M85 -> 1087 | N75: =N74*N85 -> 1098 | O75: =O74*O85 -> 1109 | P75: =P74*P85 -> 1122 | Q75: =Q74*Q85 -> 1129 | T75: =T74*T85 -> 1114 | U75: =U74*U85 -> 1118 | V75: =V74*V85 -> 1119 | W75: =W74*W85 -> 1122 | X75: =X74*X85 -> 1126 | Y75: =Y74*Y85 -> 1128 | Z75: =Z74*Z85 -> 1129 | AA75: =AA74*AA85 -> 1129 | AC75: =AA75 -> 1129
B76: Dilutive shares | L76: 21 | M76: 10 | N76: 0 | O76: 13 | P76: 9 | Q76: 17 | T76: 11 | U76: 8 | V76: 7 | W76: 9 | X76: 13 | Y76: 16 | Z76: 17 | AA76: 17 | AC76: =AA76 -> 17
B77: Split adjusted dilutive shares | L77: =L76*L85 -> 21 | M77: =M76*M85 -> 10 | N77: =N76*N85 -> 0 | O77: =O76*O85 -> 13 | P77: =P76*P85 -> 9 | Q77: =Q76*Q85 -> 17 | T77: =T76*T85 -> 11 | U77: =U76*U85 -> 8 | V77: =V76*V85 -> 7 | W77: =W76*W85 -> 9 | X77: =X76*X85 -> 13 | Y77: =Y76*Y85 -> 16 | Z77: =Z76*Z85 -> 17 | AA77: =AA76*AA85 -> 17 | AC77: =AA77 -> 17
B78: Split adjusted diluted shares | L78: =L75+L77 -> 1140 | M78: =M75+M77 -> 1097 | N78: =N75+N77 -> 1098 | O78: =O75+O77 -> 1122 | P78: =P75+P77 -> 1131 | Q78: =Q75+Q77 -> 1146 | T78: =T75+T77 -> 1125 | U78: =U75+U77 -> 1126 | V78: =V75+V77 -> 1126 | W78: =W75+W77 -> 1131 | X78: =X75+X77 -> 1139 | Y78: =Y75+Y77 -> 1144 | Z78: =Z75+Z77 -> 1146 | AA78: =AA75+AA77 -> 1146 | AC78: =AA78 -> 1146
B79: Shares held by insiders | L79: 4 | M79: 4 | N79: 4 | O79: 3 | P79: 3 | Q79: 3 | AC79: =Q79 -> 3
B80: Split adjusted shares held by insiders | L80: =L79*L85 -> 4 | M80: =M79*M85 -> 4 | N80: =N79*N85 -> 4 | O80: =O79*O85 -> 3 | P80: =P79*P85 -> 3 | Q80: =Q79*Q85 -> 3 | AC80: =Q80 -> 3
B81: Dividends per share | L81: 0.1 | M81: 0.315 | N81: 0.46 | O81: 0.46 | P81: 0.46 | Q81: 0.57 | T81: 0.115 | U81: 0.115 | V81: 0.115 | W81: 0.115 | X81: 0.115 | Y81: 0.15 | Z81: 0.15 | AA81: 0.15 | AC81: =SUM(X81:AA81) -> 0.565
B82: Split adjusted dividends per share | L82: =L81/L85 -> 0.1 | M82: =M81/M85 -> 0.315 | N82: =N81/N85 -> 0.46 | O82: =O81/O85 -> 0.46 | P82: =P81/P85 -> 0.46 | Q82: =Q81/Q85 -> 0.57 | T82: =T81/T85 -> 0.115 | U82: =U81/U85 -> 0.115 | V82: =V81/V85 -> 0.115 | W82: =W81/W85 -> 0.115 | X82: =X81/X85 -> 0.115 | Y82: =Y81/Y85 -> 0.15 | Z82: =Z81/Z85 -> 0.15 | AA82: =AA81/AA85 -> 0.15 | AC82: =SUM(X82:AA82) -> 0.565
B83: Tax rate | C83: =IF(AND(C15>0,C16<0),-(C16)/C15,0) -> 0 | D83: =IF(AND(D15>0,D16<0),-(D16)/D15,0) -> 0 | E83: =IF(AND(E15>0,E16<0),-(E16)/E15,0) -> 0 | F83: =IF(AND(F15>0,F16<0),-(F16)/F15,0) -> 0 | G83: =IF(AND(G15>0,G16<0),-(G16)/G15,0) -> 0 | H83: =IF(AND(H15>0,H16<0),-(H16)/H15,0) -> 0 | I83: =IF(AND(I15>0,I16<0),-(I16)/I15,0) -> 0 | J83: =IF(AND(J15>0,J16<0),-(J16)/J15,0) -> 0 | ... Q83: =IF(AND(Q15>0,Q16<0),-(Q16)/Q15,0) -> 0.14809724 | T83: =IF(AND(T15>0,T16<0),-(T16)/T15,0) -> 0.13150558 | U83: =IF(AND(U15>0,U16<0),-(U16)/U15,0) -> 0.10068259 | V83: =IF(AND(V15>0,V16<0),-(V16)/V15,0) -> 0.11121628 | W83: =IF(AND(W15>0,W16<0),-(W16)/W15,0) -> 0.11814927 | X83: =IF(AND(X15>0,X16<0),-(X16)/X15,0) -> 0.13677611 | Y83: =IF(AND(Y15>0,Y16<0),-(Y16)/Y15,0) -> 0.1467203 | Z83: =IF(AND(Z15>0,Z16<0),-(Z16)/Z15,0) -> 0.14988558 | AA83: =IF(AND(AA15>0,AA16<0),-(AA16)/AA15,0) -> 0.14880872 | AC83: =IF(AND(AC15>0,AC16<0),-(AC16)/AC15,0) -> 0.14809724
B84: Employees | L84: 47500 | M84: 51000 | N84: 54000 | O84: 57000 | P84: 60000 | Q84: 60000 | AC84: =Q84 -> 60000
B85: Stock split factor | L85: 1 | M85: 1 | N85: 1 | O85: 1 | P85: 1 | Q85: 1 | T85: 1 | U85: 1 | V85: 1 | W85: 1 | X85: 1 | Y85: 1 | Z85: 1 | AA85: 1 | AC85: 1
B88: Growth rates Income Statement
B89: Revenue | L89: =IF(K5=0, IF(L5=0,0,IF(L5>0,1,-1)), (L5-K5)/ABS(K5) ) -> 1 | M89: =IF(L5=0, IF(M5=0,0,IF(M5>0,1,-1)), (M5-L5)/ABS(L5) ) -> 0.11019672 | N89: =IF(M5=0, IF(N5=0,0,IF(N5>0,1,-1)), (N5-M5)/ABS(M5) ) -> -0.49476559 | O89: =IF(N5=0, IF(O5=0,0,IF(O5>0,1,-1)), (O5-N5)/ABS(N5) ) -> 0.61589447 | P89: =IF(O5=0, IF(P5=0,0,IF(P5>0,1,-1)), (P5-O5)/ABS(O5) ) -> 0.48851101 | Q89: =IF(P5=0, IF(Q5=0,0,IF(Q5>0,1,-1)), (Q5-P5)/ABS(P5) ) -> 2.5632725 | T89: =IF(S5=0, IF(T5=0,0,IF(T5>0,1,-1)), (T5-S5)/ABS(S5) ) -> 1 | U89: =IF(T5=0, IF(U5=0,0,IF(U5>0,1,-1)), (U5-T5)/ABS(T5) ) -> -0.075324377 | V89: =IF(U5=0, IF(V5=0,0,IF(V5>0,1,-1)), (V5-U5)/ABS(U5) ) -> 0.1549733 | W89: =IF(V5=0, IF(W5=0,0,IF(W5>0,1,-1)), (W5-V5)/ABS(V5) ) -> 0.21653586 | X89: =IF(W5=0, IF(X5=0,0,IF(X5>0,1,-1)), (X5-W5)/ABS(W5) ) -> 0.20574459 | Y89: =IF(X5=0, IF(Y5=0,0,IF(Y5>0,1,-1)), (Y5-X5)/ABS(X5) ) -> 0.74888221 | Z89: =IF(Y5=0, IF(Z5=0,0,IF(Z5>0,1,-1)), (Z5-Y5)/ABS(Y5) ) -> 0.73746857 | AA89: =IF(Z5=0, IF(AA5=0,0,IF(AA5>0,1,-1)), (AA5-Z5)/ABS(Z5) ) -> 0.3081098
B90: COGS | L90: =IF(K6=0, IF(L6=0,0,IF(L6>0,1,-1)), (L6-K6)/ABS(K6) ) -> 1 | M90: =IF(L6=0, IF(M6=0,0,IF(M6>0,1,-1)), (M6-L6)/ABS(L6) ) -> -0.02441847 | N90: =IF(M6=0, IF(N6=0,0,IF(N6>0,1,-1)), (N6-M6)/ABS(M6) ) -> 0.0056939502 | O90: =IF(N6=0, IF(O6=0,0,IF(O6>0,1,-1)), (O6-N6)/ABS(N6) ) -> 0.14991743 | P90: =IF(O6=0, IF(P6=0,0,IF(P6>0,1,-1)), (P6-O6)/ABS(O6) ) -> 0.15422095 | Q90: =IF(P6=0, IF(Q6=0,0,IF(Q6>0,1,-1)), (Q6-P6)/ABS(P6) ) -> 0.1412575 | T90: =IF(S6=0, IF(T6=0,0,IF(T6>0,1,-1)), (T6-S6)/ABS(S6) ) -> 1 | U90: =IF(T6=0, IF(U6=0,0,IF(U6>0,1,-1)), (U6-T6)/ABS(T6) ) -> -0.05055027 | V90: =IF(U6=0, IF(V6=0,0,IF(V6>0,1,-1)), (V6-U6)/ABS(U6) ) -> 0.13811395 | W90: =IF(V6=0, IF(W6=0,0,IF(W6>0,1,-1)), (W6-V6)/ABS(V6) ) -> 0.080787157 | X90: =IF(W6=0, IF(X6=0,0,IF(X6>0,1,-1)), (X6-W6)/ABS(W6) ) -> -0.042165788 | Y90: =IF(X6=0, IF(Y6=0,0,IF(Y6>0,1,-1)), (Y6-X6)/ABS(X6) ) -> 0.018009005 | Z90: =IF(Y6=0, IF(Z6=0,0,IF(Z6>0,1,-1)), (Z6-Y6)/ABS(Y6) ) -> 0.048321048 | AA90: =IF(Z6=0, IF(AA6=0,0,IF(AA6>0,1,-1)), (AA6-Z6)/ABS(Z6) ) -> 0.1221875
B91: Gross Profit | L91: =IF(K7=0, IF(L7=0,0,IF(L7>0,1,-1)), (L7-K7)/ABS(K7) ) -> 1 | M91: =IF(L7=0, IF(M7=0,0,IF(M7>0,1,-1)), (M7-L7)/ABS(L7) ) -> 0.33339729 | N91: =IF(M7=0, IF(N7=0,0,IF(N7>0,1,-1)), (N7-M7)/ABS(M7) ) -> -1.1018852 | O91: =IF(N7=0, IF(O7=0,0,IF(O7>0,1,-1)), (O7-N7)/ABS(N7) ) -> 4.9639831 | P91: =IF(O7=0, IF(P7=0,0,IF(P7>0,1,-1)), (P7-O7)/ABS(O7) ) -> 1.6497417 | Q91: =IF(P7=0, IF(Q7=0,0,IF(Q7>0,1,-1)), (Q7-P7)/ABS(P7) ) -> 6.2281315 | T91: =IF(S7=0, IF(T7=0,0,IF(T7>0,1,-1)), (T7-S7)/ABS(S7) ) -> 1 | U91: =IF(T7=0, IF(U7=0,0,IF(U7>0,1,-1)), (U7-T7)/ABS(T7) ) -> -0.11499403 | V91: =IF(U7=0, IF(V7=0,0,IF(V7>0,1,-1)), (V7-U7)/ABS(U7) ) -> 0.1839352 | W91: =IF(V7=0, IF(W7=0,0,IF(W7>0,1,-1)), (W7-V7)/ABS(V7) ) -> 0.44070696 | X91: =IF(W7=0, IF(X7=0,0,IF(X7>0,1,-1)), (X7-W7)/ABS(W7) ) -> 0.5128611 | Y91: =IF(X7=0, IF(Y7=0,0,IF(Y7>0,1,-1)), (Y7-X7)/ABS(X7) ) -> 1.3221292 | Z91: =IF(Y7=0, IF(Z7=0,0,IF(Z7>0,1,-1)), (Z7-Y7)/ABS(Y7) ) -> 0.97442974 | AA91: =IF(Z7=0, IF(AA7=0,0,IF(AA7>0,1,-1)), (AA7-Z7)/ABS(Z7) ) -> 0.34205272
B92: R&D | L92: =IF(K8=0, IF(L8=0,0,IF(L8>0,1,-1)), (L8-K8)/ABS(K8) ) -> 1 | M92: =IF(L8=0, IF(M8=0,0,IF(M8>0,1,-1)), (M8-L8)/ABS(L8) ) -> 0.1701089 | N92: =IF(M8=0, IF(N8=0,0,IF(N8>0,1,-1)), (N8-M8)/ABS(M8) ) -> -0.00064184852 | O92: =IF(N8=0, IF(O8=0,0,IF(O8>0,1,-1)), (O8-N8)/ABS(N8) ) -> 0.1014772 | P92: =IF(O8=0, IF(P8=0,0,IF(P8>0,1,-1)), (P8-O8)/ABS(O8) ) -> 0.10728863 | Q92: =IF(P8=0, IF(Q8=0,0,IF(Q8>0,1,-1)), (Q8-P8)/ABS(P8) ) -> 0.48762507 | T92: =IF(S8=0, IF(T8=0,0,IF(T8>0,1,-1)), (T8-S8)/ABS(S8) ) -> 1 | U92: =IF(T8=0, IF(U8=0,0,IF(U8>0,1,-1)), (U8-T8)/ABS(T8) ) -> 0.011261261 | V92: =IF(U8=0, IF(V8=0,0,IF(V8>0,1,-1)), (V8-U8)/ABS(U8) ) -> 0.074610245 | W92: =IF(V8=0, IF(W8=0,0,IF(W8>0,1,-1)), (W8-V8)/ABS(V8) ) -> 0.084974093 | X92: =IF(W8=0, IF(X8=0,0,IF(X8>0,1,-1)), (X8-W8)/ABS(W8) ) -> 0.11843362 | Y92: =IF(X8=0, IF(Y8=0,0,IF(Y8>0,1,-1)), (Y8-X8)/ABS(X8) ) -> 0.067463706 | Z92: =IF(Y8=0, IF(Z8=0,0,IF(Z8>0,1,-1)), (Z8-Y8)/ABS(Y8) ) -> 0.0528 | AA92: =IF(Z8=0, IF(AA8=0,0,IF(AA8>0,1,-1)), (AA8-Z8)/ABS(Z8) ) -> 0.45364742
B93: Sales and marketing | L93: =IF(K9=0, IF(L9=0,0,IF(L9>0,1,-1)), (L9-K9)/ABS(K9) ) -> 1 | M93: =IF(L9=0, IF(M9=0,0,IF(M9>0,1,-1)), (M9-L9)/ABS(L9) ) -> 0.19239374 | N93: =IF(M9=0, IF(N9=0,0,IF(N9>0,1,-1)), (N9-M9)/ABS(M9) ) -> -0.1369606 | O93: =IF(N9=0, IF(O9=0,0,IF(O9>0,1,-1)), (O9-N9)/ABS(N9) ) -> 0.22717391 | P93: =IF(O9=0, IF(P9=0,0,IF(P9>0,1,-1)), (P9-O9)/ABS(O9) ) -> 0.067316209 | Q93: =IF(P9=0, IF(Q9=0,0,IF(Q9>0,1,-1)), (Q9-P9)/ABS(P9) ) -> 0.61576763 | T93: =IF(S9=0, IF(T9=0,0,IF(T9>0,1,-1)), (T9-S9)/ABS(S9) ) -> 1 | U93: =IF(T9=0, IF(U9=0,0,IF(U9>0,1,-1)), (U9-T9)/ABS(T9) ) -> -0.010416667 | V93: =IF(U9=0, IF(V9=0,0,IF(V9>0,1,-1)), (V9-U9)/ABS(U9) ) -> 0.11578947 | W93: =IF(V9=0, IF(W9=0,0,IF(W9>0,1,-1)), (W9-V9)/ABS(V9) ) -> -0.012578616 | X93: =IF(W9=0, IF(X9=0,0,IF(X9>0,1,-1)), (X9-W9)/ABS(W9) ) -> 0.073248408 | Y93: =IF(X9=0, IF(Y9=0,0,IF(Y9>0,1,-1)), (Y9-X9)/ABS(X9) ) -> 0.020771513 | Z93: =IF(Y9=0, IF(Z9=0,0,IF(Z9>0,1,-1)), (Z9-Y9)/ABS(Y9) ) -> 0.18313953 | AA93: =IF(Z9=0, IF(AA9=0,0,IF(AA9>0,1,-1)), (AA9-Z9)/ABS(Z9) ) -> 1.1105651
B94: Other income/expense | L94: =IF(K10=0, IF(L10=0,0,IF(L10>0,1,-1)), (L10-K10)/ABS(K10) ) -> 1 | M94: =IF(L10=0, IF(M10=0,0,IF(M10>0,1,-1)), (M10-L10)/ABS(L10) ) -> -0.97598628 | N94: =IF(M10=0, IF(N10=0,0,IF(N10>0,1,-1)), (N10-M10)/ABS(M10) ) -> 20.071429 | O94: =IF(N10=0, IF(O10=0,0,IF(O10>0,1,-1)), (O10-N10)/ABS(N10) ) -> -1.8474576 | P94: =IF(O10=0, IF(P10=0,0,IF(P10>0,1,-1)), (P10-O10)/ABS(O10) ) -> 1.4 | Q94: =IF(P10=0, IF(Q10=0,0,IF(Q10>0,1,-1)), (Q10-P10)/ABS(P10) ) -> 4.67 | T94: =IF(S10=0, IF(T10=0,0,IF(T10>0,1,-1)), (T10-S10)/ABS(S10) ) -> -1 | U94: =IF(T10=0, IF(U10=0,0,IF(U10>0,1,-1)), (U10-T10)/ABS(T10) ) -> 4.5 | V94: =IF(U10=0, IF(V10=0,0,IF(V10>0,1,-1)), (V10-U10)/ABS(U10) ) -> 7 | W94: =IF(V10=0, IF(W10=0,0,IF(W10>0,1,-1)), (W10-V10)/ABS(V10) ) -> -0.30357143 | X94: =IF(W10=0, IF(X10=0,0,IF(X10>0,1,-1)), (X10-W10)/ABS(W10) ) -> -0.94871795 | Y94: =IF(X10=0, IF(Y10=0,0,IF(Y10>0,1,-1)), (Y10-X10)/ABS(X10) ) -> 12 | Z94: =IF(Y10=0, IF(Z10=0,0,IF(Z10>0,1,-1)), (Z10-Y10)/ABS(Y10) ) -> -0.42307692 | AA94: =IF(Z10=0, IF(AA10=0,0,IF(AA10>0,1,-1)), (AA10-Z10)/ABS(Z10) ) -> 33.933333
B95: OpEx | L95: =IF(K11=0, IF(L11=0,0,IF(L11>0,1,-1)), (L11-K11)/ABS(K11) ) -> 1 | M95: =IF(L11=0, IF(M11=0,0,IF(M11>0,1,-1)), (M11-L11)/ABS(L11) ) -> 0.01352657 | N95: =IF(M11=0, IF(N11=0,0,IF(N11>0,1,-1)), (N11-M11)/ABS(M11) ) -> 0.031696854 | O95: =IF(N11=0, IF(O11=0,0,IF(O11>0,1,-1)), (O11-N11)/ABS(N11) ) -> -0.0046200046 | P95: =IF(O11=0, IF(P11=0,0,IF(P11>0,1,-1)), (P11-O11)/ABS(O11) ) -> 0.18426549 | Q95: =IF(P11=0, IF(Q11=0,0,IF(Q11>0,1,-1)), (Q11-P11)/ABS(P11) ) -> 0.59984323 | T95: =IF(S11=0, IF(T11=0,0,IF(T11>0,1,-1)), (T11-S11)/ABS(S11) ) -> 1 | U95: =IF(T11=0, IF(U11=0,0,IF(U11>0,1,-1)), (U11-T11)/ABS(T11) ) -> 0.01362862 | V95: =IF(U11=0, IF(V11=0,0,IF(V11>0,1,-1)), (V11-U11)/ABS(U11) ) -> 0.12521008 | W95: =IF(V11=0, IF(W11=0,0,IF(W11>0,1,-1)), (W11-V11)/ABS(V11) ) -> 0.045556385 | X95: =IF(W11=0, IF(X11=0,0,IF(X11>0,1,-1)), (X11-W11)/ABS(W11) ) -> 0.078571429 | Y95: =IF(X11=0, IF(Y11=0,0,IF(Y11>0,1,-1)), (Y11-X11)/ABS(X11) ) -> 0.072847682 | Z95: =IF(Y11=0, IF(Z11=0,0,IF(Z11>0,1,-1)), (Z11-Y11)/ABS(Y11) ) -> 0.072839506 | AA95: =IF(Z11=0, IF(AA11=0,0,IF(AA11>0,1,-1)), (AA11-Z11)/ABS(Z11) ) -> 0.89643268
B96: Operating income | L96: =IF(K12=0, IF(L12=0,0,IF(L12>0,1,-1)), (L12-K12)/ABS(K12) ) -> 1 | M96: =IF(L12=0, IF(M12=0,0,IF(M12>0,1,-1)), (M12-L12)/ABS(L12) ) -> 0.5441668 | N96: =IF(M12=0, IF(N12=0,0,IF(N12>0,1,-1)), (N12-M12)/ABS(M12) ) -> -1.5921459 | O96: =IF(N12=0, IF(O12=0,0,IF(O12>0,1,-1)), (O12-N12)/ABS(N12) ) -> 1.22698 | P96: =IF(O12=0, IF(P12=0,0,IF(P12>0,1,-1)), (P12-O12)/ABS(O12) ) -> 6.4923313 | Q96: =IF(P12=0, IF(Q12=0,0,IF(Q12>0,1,-1)), (Q12-P12)/ABS(P12) ) -> 9.1678608 | T96: =IF(S12=0, IF(T12=0,0,IF(T12>0,1,-1)), (T12-S12)/ABS(S12) ) -> 1 | U96: =IF(T12=0, IF(U12=0,0,IF(U12>0,1,-1)), (U12-T12)/ABS(T12) ) -> -0.18445262 | V96: =IF(U12=0, IF(V12=0,0,IF(V12>0,1,-1)), (V12-U12)/ABS(U12) ) -> 0.22335025 | W96: =IF(V12=0, IF(W12=0,0,IF(W12>0,1,-1)), (W12-V12)/ABS(V12) ) -> 0.6846473 | X96: =IF(W12=0, IF(X12=0,0,IF(X12>0,1,-1)), (X12-W12)/ABS(W12) ) -> 0.67925561 | Y96: =IF(X12=0, IF(Y12=0,0,IF(Y12>0,1,-1)), (Y12-X12)/ABS(X12) ) -> 1.6295632 | Z96: =IF(Y12=0, IF(Z12=0,0,IF(Z12>0,1,-1)), (Z12-Y12)/ABS(Y12) ) -> 1.064952 | AA96: =IF(Z12=0, IF(AA12=0,0,IF(AA12>0,1,-1)), (AA12-Z12)/ABS(Z12) ) -> 0.31313404
B97: Income before taxes | L97: =IF(K15=0, IF(L15=0,0,IF(L15>0,1,-1)), (L15-K15)/ABS(K15) ) -> 1 | M97: =IF(L15=0, IF(M15=0,0,IF(M15>0,1,-1)), (M15-L15)/ABS(L15) ) -> 0.53924091 | N97: =IF(M15=0, IF(N15=0,0,IF(N15>0,1,-1)), (N15-M15)/ABS(M15) ) -> -1.5911608 | O97: =IF(N15=0, IF(O15=0,0,IF(O15>0,1,-1)), (O15-N15)/ABS(N15) ) -> 1.2191587 | P97: =IF(O15=0, IF(P15=0,0,IF(P15>0,1,-1)), (P15-O15)/ABS(O15) ) -> 6.7854839 | Q97: =IF(P15=0, IF(Q15=0,0,IF(Q15>0,1,-1)), (Q15-P15)/ABS(P15) ) -> 9.3243215 | T97: =IF(S15=0, IF(T15=0,0,IF(T15>0,1,-1)), (T15-S15)/ABS(S15) ) -> 1 | U97: =IF(T15=0, IF(U15=0,0,IF(U15>0,1,-1)), (U15-T15)/ABS(T15) ) -> -0.1830855 | V97: =IF(U15=0, IF(V15=0,0,IF(V15>0,1,-1)), (V15-U15)/ABS(U15) ) -> 0.20193402 | W97: =IF(V15=0, IF(W15=0,0,IF(W15>0,1,-1)), (W15-V15)/ABS(V15) ) -> 0.71840984 | X97: =IF(W15=0, IF(X15=0,0,IF(X15>0,1,-1)), (X15-W15)/ABS(W15) ) -> 0.66923712 | Y97: =IF(X15=0, IF(Y15=0,0,IF(Y15>0,1,-1)), (Y15-X15)/ABS(X15) ) -> 1.6662267 | Z97: =IF(Y15=0, IF(Z15=0,0,IF(Z15>0,1,-1)), (Z15-Y15)/ABS(Y15) ) -> 1.055198 | AA97: =IF(Z15=0, IF(AA15=0,0,IF(AA15>0,1,-1)), (AA15-Z15)/ABS(Z15) ) -> 0.33198844
B98: Net income | L98: =IF(K18=0, IF(L18=0,0,IF(L18>0,1,-1)), (L18-K18)/ABS(K18) ) -> 1 | M98: =IF(L18=0, IF(M18=0,0,IF(M18>0,1,-1)), (M18-L18)/ABS(L18) ) -> 0.48217028 | N98: =IF(M18=0, IF(N18=0,0,IF(N18>0,1,-1)), (N18-M18)/ABS(M18) ) -> -1.6714631 | O98: =IF(N18=0, IF(O18=0,0,IF(O18>0,1,-1)), (O18-N18)/ABS(N18) ) -> 1.1333791 | P98: =IF(O18=0, IF(P18=0,0,IF(P18>0,1,-1)), (P18-O18)/ABS(O18) ) -> 9.9755784 | Q98: =IF(P18=0, IF(Q18=0,0,IF(Q18>0,1,-1)), (Q18-P18)/ABS(P18) ) -> 8.9506968 | T98: =IF(S18=0, IF(T18=0,0,IF(T18>0,1,-1)), (T18-S18)/ABS(S18) ) -> 1 | U98: =IF(T18=0, IF(U18=0,0,IF(U18>0,1,-1)), (U18-T18)/ABS(T18) ) -> -0.15347594 | V98: =IF(U18=0, IF(V18=0,0,IF(V18>0,1,-1)), (V18-U18)/ABS(U18) ) -> 0.19077701 | W98: =IF(V18=0, IF(W18=0,0,IF(W18>0,1,-1)), (W18-V18)/ABS(V18) ) -> 0.69814324 | X98: =IF(W18=0, IF(X18=0,0,IF(X18>0,1,-1)), (X18-W18)/ABS(W18) ) -> 0.63698844 | Y98: =IF(X18=0, IF(Y18=0,0,IF(Y18>0,1,-1)), (Y18-X18)/ABS(X18) ) -> 1.6307252 | Z98: =IF(Y18=0, IF(Z18=0,0,IF(Z18>0,1,-1)), (Z18-Y18)/ABS(Y18) ) -> 1.0488212 | AA98: =IF(Z18=0, IF(AA18=0,0,IF(AA18>0,1,-1)), (AA18-Z18)/ABS(Z18) ) -> 0.33487944
B100: Margins
B101: Gross margin | L101: =L7/L5 -> 0.37621368 | M101: =M7/M5 -> 0.45184993 | N101: =N7/N5 -> -0.091119691 | O101: =O7/O5 -> 0.22352754 | P101: =P7/P5 -> 0.39790786 | Q101: =Q7/Q5 -> 0.8071598 | T101: =T7/T5 -> 0.3844299 | U101: =U7/U5 -> 0.36793741 | V101: =V7/V5 -> 0.37716375 | W101: =W7/W5 -> 0.44666372 | X101: =X7/X5 -> 0.56043392 | Y101: =Y7/Y5 -> 0.74413244 | Z101: =Z7/Z5 -> 0.84561945 | AA101: =AA7/AA5 -> 0.86756164 | AC101: =AC7/AC5 -> 0.8071598
B102: Operating margin | L102: =L12/L5 -> 0.22678217 | M102: =M12/M5 -> 0.31543013 | N102: =N12/N5 -> -0.36969112 | O102: =O12/O5 -> 0.051929433 | P102: =P12/P5 -> 0.2613837 | Q102: =Q12/Q5 -> 0.74586299 | T102: =T12/T5 -> 0.24962682 | U102: =U12/U5 -> 0.2201664 | V102: =V12/V5 -> 0.23320073 | W102: =W12/W5 -> 0.32293416 | X102: =X12/X5 -> 0.44975445 | Y102: =Y12/Y5 -> 0.67623638 | Z102: =Z12/Z5 -> 0.80369548 | AA102: =AA12/AA5 -> 0.80678235 | AC102: =AC12/AC5 -> 0.74586299
B103: Net margin | L103: =L111/L5 -> 0.21155026 | M103: =M111/M5 -> 0.28243059 | N103: =N111/N5 -> -0.37535393 | O103: =O111/O5 -> 0.030982438 | P103: =P111/P5 -> 0.22844989 | Q103: =Q111/Q5 -> 0.63796288 | T103: =T111/T5 -> 0.2147204 | U103: =U111/U5 -> 0.19657271 | V103: =V111/V5 -> 0.20266638 | W103: =W111/W5 -> 0.28289881 | X103: =X111/X5 -> 0.38407975 | Y103: =Y111/Y5 -> 0.57774518 | Z103: =Z111/Z5 -> 0.68127653 | AA103: =AA111/AA5 -> 0.69521843 | AC103: =AC111/AC5 -> 0.63796288
B105: Adjustments
B106: Tax rate | C106: =IF(AND(C83>=0,C12>=0),C83,0) -> 0 | D106: =IF(AND(D83>=0,D12>=0),D83,0) -> 0 | E106: =IF(AND(E83>=0,E12>=0),E83,0) -> 0 | F106: =IF(AND(F83>=0,F12>=0),F83,0) -> 0 | G106: =IF(AND(G83>=0,G12>=0),G83,0) -> 0 | H106: =IF(AND(H83>=0,H12>=0),H83,0) -> 0 | I106: =IF(AND(I83>=0,I12>=0),I83,0) -> 0 | J106: =IF(AND(J83>=0,J12>=0),J83,0) -> 0 | ... Q106: =IF(AND(Q83>=0,Q12>=0),Q83,0) -> 0.14809724 | T106: =IF(AND(T83>=0,T12>=0),T83,0) -> 0.13150558 | U106: =IF(AND(U83>=0,U12>=0),U83,0) -> 0.10068259 | V106: =IF(AND(V83>=0,V12>=0),V83,0) -> 0.11121628 | W106: =IF(AND(W83>=0,W12>=0),W83,0) -> 0.11814927 | X106: =IF(AND(X83>=0,X12>=0),X83,0) -> 0.13677611 | Y106: =IF(AND(Y83>=0,Y12>=0),Y83,0) -> 0.1467203 | Z106: =IF(AND(Z83>=0,Z12>=0),Z83,0) -> 0.14988558 | AA106: =IF(AND(AA83>=0,AA12>=0),AA83,0) -> 0.14880872 | AC106: =IF(AND(AC83>=0,AC12>=0),AC83,0) -> 0.14809724
B107: Cash | L107: =L29+L34 -> 10398 | M107: =M29+M34 -> 10978 | N107: =N29+N34 -> 10438 | O107: =O29+O34 -> 9152 | P107: =P29+P34 -> 11936 | Q107: =Q29+Q34 -> 73453 | T107: =T29+T34 -> 8744 | U107: =U29+U34 -> 9590 | V107: =V29+V34 -> 12213 | W107: =W29+W34 -> 11936 | X107: =X29+X34 -> 12015 | Y107: =Y29+Y34 -> 16627 | Z107: =Z29+Z34 -> 30128 | AA107: =AA29+AA34 -> 73453 | AC107: =AA107 -> 73453
B108: Debt | C108: 0 | D108: 0 | E108: 0 | F108: 0 | G108: 0 | H108: 0 | I108: 0 | J108: 0 | K108: 0 | L108: =L39+L41 -> 6776 | M108: =M39+M41 -> 6906 | N108: =N39+N41 -> 13330 | O108: =O39+O41 -> 13397 | P108: =P39+P41 -> 14577 | Q108: =Q39+Q41 -> 5179 | T108: =T39+T41 -> 13785 | U108: =U39+U41 -> 14355 | V108: =V39+V41 -> 15541 | W108: =W39+W41 -> 14577 | X108: =X39+X41 -> 11756 | Y108: =Y39+Y41 -> 10142 | Z108: =Z39+Z41 -> 5722 | AA108: =AA39+AA41 -> 5179 | AC108: =AA108 -> 5179
B109: NOPAT | L109: =L12*(1-L106) -> 5884.8813 | M109: =M12*(1-M106) -> 8801.8458 | N109: =N12*(1-N106) -> -5745 | O109: =O12*(1-O106) -> 829.72258 | P109: =P12*(1-P106) -> 8632.4943 | Q109: =Q12*(1-Q106) -> 84628.02 | AC109: =AC12*(1-AC106) -> 84628.02
...

Sheet Analysis ->
H5: Links
H6: Overview'!B3
H7: Financials ->'!B13
H8: Analysis ->'!B13
H9: Forecast ->'!B13
H10: Valuation ->'!B13
B13: Analysis ->

Sheet Basic
B1: TTM/YTD data
B4: Overview | E4: CAGR
B5: Price | C5: =Overview!C5 -> 903.7 | F5: 5Y | G5: 10Y
B6: Market capitalization | C6: =Statement!AC153 -> 1035640.2 | E6: Revenue | F6: =IF(Statement!M5<=0,"N/A",_xlfn.RRI(4,Statement!M5,Statement!Q5)) -> 0.4425363 | G6: =IF(Statement!H5<=0,"N/A",_xlfn.RRI(9,Statement!H5,Statement!Q5)) -> N/A
B7: Enterprise value | C7: =Statement!AC154 -> 967366.2 | E7: Net income | F7: =IF(OR(Statement!M18<=0, Statement!Q18<=0), "N/A", _xlfn.RRI(4, Statement!M18, Statement!Q18)) -> 0.7684699 | G7: =IF(OR(Statement!H18<=0, Statement!Q18<=0), "N/A", _xlfn.RRI(9, Statement!H18, Statement!Q18)) -> N/A
B8: PE | C8: =Statement!AC150 -> 12.177604 | E8: EPS | F8: =IF(OR(Statement!M26<=0, Statement!Q26<=0), "N/A", _xlfn.RRI(4, Statement!M26, Statement!Q26)) -> 0.7598093 | G8: =IF(OR(Statement!H26<=0, Statement!Q26<=0), "N/A", _xlfn.RRI(9, Statement!H26, Statement!Q26)) -> N/A
B9: PS | C9: =Statement!AC151 -> 7.7554217 | E9: Dividend | F9: =IF(Statement!M82<=0,"N/A",_xlfn.RRI(4,Statement!M82,Statement!Q82)) -> 0.15982129 | G9: =IF(Statement!H82<=0,"N/A",_xlfn.RRI(9,Statement!H82,Statement!Q82)) -> N/A
B10: PB | C10: =Statement!AC152 -> 7.3731178 | E10: Price | F10: =IF(Statement!M117<=0,"N/A",_xlfn.RRI(4,Statement!M117,Statement!Q117)) -> 1.0220966 | G10: =IF(Statement!H117<=0,"N/A",_xlfn.RRI(9,Statement!H117,Statement!Q117)) -> N/A
B11: EV/Revenue | C11: =Statement!AC155 -> 7.2631633
B12: EV/EBIT | C12: =Statement!AC156 -> 9.7379324
B15: Margins | E15: Earnings quality
B16: Gross margin | C16: =Statement!AC101 -> 0.8071598 | E16: Net income | F16: =Statement!AC18 -> 84969
B17: Operating margin | C17: =Statement!AC102 -> 0.74586299 | E17: Operating cash | F17: =Statement!AC59 -> 89675
B18: Net margin | C18: =Statement!AC103 -> 0.63796288 | E18: Cash accruals | F18: =IF(OR(F16<=0, F17<=0),"N/A",F16-F17) -> -4706
B21: DuPont Identity | E21: Performance indicators
B22: Profit Margin (Earnings/Revenue) | C22: =Statement!AC121 -> 0.63796288 | E22: ROA | F22: =C24 -> 0.43376317
B23: Asset Turnover (Revenue/Total assets) | C23: =Statement!AC122 -> 0.67991914 | E23: ROE | F23: =C26 -> 0.61403547
B24: ROA | C24: =Statement!AC123 -> 0.43376317 | E24: ROIC | F24: =Statement!AC140 -> 1.2071782
B25: Equity Multiplier (Total assets/Equity) | C25: =Statement!AC124 -> 1.4156007
B26: ROE | C26: =Statement!AC125 -> 0.61403547
B29: Cash conversion cycle | E29: Liquidity ratios
B30: DSO | C30: =Statement!AC141 -> 99.197413 | E30: Debt/Equity | F30: =Statement!AC145 -> 0.03742647
B31: DIO | C31: =Statement!AC142 -> 147.39838 | E31: Net Debt/Equity | F31: =Statement!AC146 -> -0.49338768
B32: DPO | C32: =Statement!AC143 -> 321.24377 | E32: Current ratio | F32: =Statement!AC148 -> 3.3138054
B33: Net trade cycle | C33: =Statement!AC144 -> -74.647977 | E33: Quick ratio | F33: =Statement!AC147 -> 3.9898843
E34: Interest coverage | F34: =Statement!AC149 -> N/A
B37: Earnings yields | E37: Payout ratios
B38: Earnings yield | C38: =Statement!AC162 -> 0.082117959 | E38: Dividend payout ratio | F38: =Statement!AC168 -> 0.010584765
B39: FCF yield | C39: =Statement!AC161 -> 0.055646739 | E39: Buyback payout ratio | F39: =Statement!AC169 -> 0.011278848
B40: Dividend yield | C40: =Statement!AC163 -> 0.00062520748 | E40: Full payout ratio | F40: =Statement!AC170 -> 0.021863613
B41: Buyback yield | C41: =Statement!AC164 -> 0.0006276311
B42: Total shareholder yield | C42: =Statement!AC165 -> 0.0012166388
B45: Ownership | E45: Cash holdings
B46: Insider ownership | C46: =Statement!AC171 -> 0.002617801 | E46: Cash per share | F46: =Statement!AC172 -> 65.06023
E47: Net cash per share | F47: =Statement!AC175 -> 60.472985
E48: Net cash to market cap | F48: =Statement!AC176 -> 0.06592444
B51: Stock based compensation | E51: CapEx usage
B52: Stock based compensation % OCF | C52: =Statement!AC173 -> 0.01486479 | E52: Capex to Revenue | F52: =Statement!AC177 -> 0.23059134
B53: Stock based compensation % Revenue | C53: =Statement!AC174 -> 0.010008409 | E53: CapEx to OCF | F53: =Statement!AC178 -> 0.34248118
E54: CapEx to D&A | F54: =Statement!AC179 -> 3.2318215

Sheet Yearly Analysis
C2: =Statement!M2 -> 01.09.2022 | D2: =Statement!N2 -> 31.08.2023 | E2: =Statement!O2 -> 29.08.2024 | F2: =Statement!P2 -> 28.08.2025 | G2: =Statement!Q2 -> 03.09.2025
C3: =Statement!M3 -> 2022 | D3: =Statement!N3 -> 2023 | E3: =Statement!O3 -> 2024 | F3: =Statement!P3 -> 2025 | G3: =Statement!Q3 -> 2026 | I3: =Statement!AC3 -> TTM/YTD
B5: Overview
B6: Price | C6: =Statement!M116 -> 57.31 | D6: =Statement!N116 -> 68.09 | E6: =Statement!O116 -> 95.57 | F6: =Statement!P116 -> 122 | G6: =Statement!Q116 -> 958.16 | I6: =Statement!AC116 -> 903.7
B7: Market capitalization | C7: =Statement!M153 -> 62869.07 | D7: =Statement!N153 -> 74762.82 | E7: =Statement!O153 -> 107229.54 | F7: =Statement!P153 -> 137982 | G7: =Statement!Q153 -> 1098051.4 | I7: =Statement!AC153 -> 1035640.2
B8: Enterprise value | C8: =Statement!M154 -> 58797.07 | D8: =Statement!N154 -> 77654.82 | E8: =Statement!O154 -> 111474.54 | F8: =Statement!P154 -> 140623 | G8: =Statement!Q154 -> 1029777.4 | I8: =Statement!AC154 -> 967366.2
B9: PE | C9: =Statement!M150 -> 7.3948387 | D9: =Statement!N150 -> -12.750936 | E9: =Statement!O150 -> 136.52857 | F9: =Statement!P150 -> 16.073781 | G9: =Statement!Q150 -> 12.890623 | I9: =Statement!AC150 -> 12.177604
B10: PS | C10: =Statement!M151 -> 2.0905722 | D10: =Statement!N151 -> 4.7890843 | E10: =Statement!O151 -> 4.2549982 | F10: =Statement!P151 -> 3.6719461 | G10: =Statement!Q151 -> 8.2227894 | I10: =Statement!AC151 -> 7.7554217
B11: PB | C11: =Statement!M152 -> 1.2482411 | D11: =Statement!N152 -> 1.6945335 | E11: =Statement!O152 -> 2.348433 | F11: =Statement!P152 -> 2.527167 | G11: =Statement!Q152 -> 7.8174467 | I11: =Statement!AC152 -> 7.3731178
B12: EV/Revenue | C12: =Statement!M155 -> 1.9116025 | D12: =Statement!N155 -> 4.9970927 | E12: =Statement!O155 -> 4.4392712 | F12: =Statement!P155 -> 3.7621863 | G12: =Statement!Q155 -> 7.7317578 | I12: =Statement!AC155 -> 7.2631633
B13: EV/EBIT | C13: =Statement!M156 -> 6.0603041 | D13: =Statement!N156 -> -13.51694 | E13: =Statement!O156 -> 85.48661 | F13: =Statement!P156 -> 14.393347 | G13: =Statement!Q156 -> 10.36619 | I13: =Statement!AC156 -> 9.7379324
B15: Margins
B16: Gross margin | C16: =Statement!M101 -> 0.45184993 | D16: =Statement!N101 -> -0.091119691 | E16: =Statement!O101 -> 0.22352754 | F16: =Statement!P101 -> 0.39790786 | G16: =Statement!Q101 -> 0.8071598 | I16: =Statement!AC101 -> 0.8071598
B17: Operating margin | C17: =Statement!M102 -> 0.31543013 | D17: =Statement!N102 -> -0.36969112 | E17: =Statement!O102 -> 0.051929433 | F17: =Statement!P102 -> 0.2613837 | G17: =Statement!Q102 -> 0.74586299 | I17: =Statement!AC102 -> 0.74586299
B18: Net margin | C18: =Statement!M103 -> 0.28243059 | D18: =Statement!N103 -> -0.37535393 | E18: =Statement!O103 -> 0.030982438 | F18: =Statement!P103 -> 0.22844989 | G18: =Statement!Q103 -> 0.63796288 | I18: =Statement!AC103 -> 0.63796288
B20: Earnings quality
B21: Net income | C21: =Statement!M18 -> 8687 | D21: =Statement!N18 -> -5833 | E21: =Statement!O18 -> 778 | F21: =Statement!P18 -> 8539 | G21: =Statement!Q18 -> 84969 | I21: =Statement!AC18 -> 84969
B22: Operating cash | C22: =Statement!M59 -> 15181 | D22: =Statement!N59 -> 1559 | E22: =Statement!O59 -> 8507 | F22: =Statement!P59 -> 17525 | G22: =Statement!Q59 -> 89675 | I22: =Statement!AC59 -> 89675
B23: Cash accruals | C23: =IF(OR(C21<=0, C22<=0),"N/A",C21-C22) -> -6494 | D23: =IF(OR(D21<=0, D22<=0),"N/A",D21-D22) -> N/A | E23: =IF(OR(E21<=0, E22<=0),"N/A",E21-E22) -> -7729 | F23: =IF(OR(F21<=0, F22<=0),"N/A",F21-F22) -> -8986 | G23: =IF(OR(G21<=0, G22<=0),"N/A",G21-G22) -> -4706 | I23: =IF(OR(I21<=0, I22<=0),"N/A",I21-I22) -> -4706
B25: DuPont Identity
B26: Profit Margin (Earnings/Revenue) | C26: =Statement!M121 -> 0.28243059 | D26: =Statement!N121 -> -0.37535393 | E26: =Statement!O121 -> 0.030982438 | F26: =Statement!P121 -> 0.22844989 | G26: =Statement!Q121 -> 0.63796288 | I26: =Statement!AC121 -> 0.63796288
B27: Asset Turnover (Revenue/Total assets) | C27: =Statement!M122 -> 0.46404055 | D27: =Statement!N122 -> 0.24185265 | E27: =Statement!O122 -> 0.36174657 | F27: =Statement!P122 -> 0.45143603 | G27: =Statement!Q122 -> 0.67991914 | I27: =Statement!AC122 -> 0.67991914
B28: ROA | C28: =Statement!M123 -> 0.13105925 | D28: =Statement!N123 -> -0.090780341 | E28: =Statement!O123 -> 0.011207791 | F28: =Statement!P123 -> 0.10313051 | G28: =Statement!Q123 -> 0.43376317 | I28: =Statement!AC123 -> 0.43376317
B29: Equity Multiplier (Total assets/Equity) | C29: =Statement!M124 -> 1.3281303 | D29: =Statement!N124 -> 1.4563463 | E29: =Statement!O124 -> 1.5381002 | F29: =Statement!P124 -> 1.5286255 | G29: =Statement!Q124 -> 1.4156007 | I29: =Statement!AC124 -> 1.4156007
B30: ROE | C30: =Statement!M125 -> 0.17406376 | D30: =Statement!N125 -> -0.13220762 | E30: =Statement!O125 -> 0.017238705 | F30: =Statement!P125 -> 0.15764793 | G30: =Statement!Q125 -> 0.61403547 | I30: =Statement!AC125 -> 0.61403547
B32: Performance Indicators
B33: ROA | C33: =C28 -> 0.13105925 | D33: =D28 -> -0.090780341 | E33: =E28 -> 0.011207791 | F33: =F28 -> 0.10313051 | G33: =G28 -> 0.43376317 | I33: =I28 -> 0.43376317
B34: ROE | C34: =C30 -> 0.17406376 | D34: =D30 -> -0.13220762 | E34: =E30 -> 0.017238705 | F34: =F30 -> 0.15764793 | G34: =G30 -> 0.61403547 | I34: =I30 -> 0.61403547
B35: ROIC | C35: =Statement!M140 -> 0.19203329 | D35: =Statement!N140 -> -0.12220284 | E35: =Statement!O140 -> 0.016804168 | F35: =Statement!P140 -> 0.15196448 | G35: =Statement!Q140 -> 1.2071782 | I35: =Statement!AC140 -> 1.2071782
B37: Cash conversion cycle
B38: DSO | C38: =Statement!M141 -> 60.876845 | D38: =Statement!N141 -> 57.380631 | E38: =Statement!O141 -> 96.152085 | F38: =Statement!P141 -> 90.473674 | G38: =Statement!Q141 -> 99.197413 | I38: =Statement!AC141 -> 99.197413
B39: DIO | C39: =Statement!M142 -> 144.24644 | D39: =Statement!N142 -> 180.54111 | E39: =Statement!O142 -> 166.13883 | F39: =Statement!P142 -> 135.50655 | G39: =Statement!Q142 -> 147.39838 | I39: =Statement!AC142 -> 147.39838
B40: DPO | C40: =Statement!M143 -> 131.84164 | D40: =Statement!N143 -> 85.201109 | E40: =Statement!O143 -> 136.63632 | F40: =Statement!P143 -> 156.49345 | G40: =Statement!Q143 -> 321.24377 | I40: =Statement!AC143 -> 321.24377
B41: Net trade cycle | C41: =Statement!M144 -> 73.281649 | D41: =Statement!N144 -> 152.72063 | E41: =Statement!O144 -> 125.6546 | F41: =Statement!P144 -> 69.486783 | G41: =Statement!Q144 -> -74.647977 | I41: =Statement!AC144 -> -74.647977
B43: Liquidity ratios
B44: Debt/Equity | C44: =Statement!M145 -> 0.13837738 | D44: =Statement!N145 -> 0.30213055 | E44: =Statement!O145 -> 0.29684696 | F44: =Statement!P145 -> 0.26912213 | G44: =Statement!Q145 -> 0.03742647 | I44: =Statement!AC145 -> 0.03742647
B45: Net Debt/Equity | C45: =Statement!M146 -> -0.081591761 | D45: =Statement!N146 -> 0.065548504 | E45: =Statement!O146 -> 0.094059516 | F45: =Statement!P146 -> 0.048758423 | G45: =Statement!Q146 -> -0.49338768 | I45: =Statement!AC146 -> -0.49338768
B46: Quick ratio | C46: =Statement!M147 -> 2.1366229 | D46: =Statement!N147 -> 2.7032529 | E46: =Statement!O147 -> 1.7049092 | F46: =Statement!P147 -> 1.8509691 | G46: =Statement!Q147 -> 3.9898843 | I46: =Statement!AC147 -> 3.9898843
B47: Current ratio | C47: =Statement!M148 -> 2.88911 | D47: =Statement!N148 -> 4.4583421 | E47: =Statement!O148 -> 2.6353806 | F47: =Statement!P148 -> 2.517985 | G47: =Statement!Q148 -> 3.3138054 | I47: =Statement!AC148 -> 3.3138054
B48: Interest coverage | C48: =Statement!M149 -> 104.32258 | D48: =Statement!N149 -> N/A | E48: =Statement!O149 -> 39.515152 | F48: =Statement!P149 -> N/A | G48: =Statement!Q149 -> N/A | I48: =Statement!AC149 -> N/A
B50: Earnings yields
B51: Earnings yield | C51: =Statement!M162 -> 0.13522945 | D51: =Statement!N162 -> -0.078425613 | E51: =Statement!O162 -> 0.0073244742 | F51: =Statement!P162 -> 0.062213115 | G51: =Statement!Q162 -> 0.07757577 | I51: =Statement!AC162 -> 0.082117959
B52: FCF yield | C52: =Statement!M161 -> 0.041355789 | D52: =Statement!N161 -> -0.089790621 | E52: =Statement!O161 -> -0.0066399613 | F52: =Statement!P161 -> 0.0050441362 | G52: =Statement!Q161 -> 0.052483884 | I52: =Statement!AC161 -> 0.055646739
B53: Dividend yield | C53: =Statement!M163 -> 0.005496423 | D53: =Statement!N163 -> 0.0067557644 | E53: =Statement!O163 -> 0.0048132259 | F53: =Statement!P163 -> 0.0037704918 | G53: =Statement!Q163 -> 0.00059489021 | I53: =Statement!AC163 -> 0.00062520748
B54: Buyback yield | C54: =Statement!M164 -> 0.040671828 | D54: =Statement!N164 -> 0.0056846438 | E54: =Statement!O164 -> 0.0027977365 | F54: =Statement!P164 -> 0 | G54: =Statement!Q164 -> 0.00059195774 | I54: =Statement!AC164 -> 0.0006276311
B55: Total shareholder yield | C55: =Statement!M165 -> 0.048004528 | D55: =Statement!N165 -> 0.012425963 | E55: =Statement!O165 -> 0.007581866 | F55: =Statement!P165 -> 0.0037831021 | G55: =Statement!Q165 -> 0.0011474873 | I55: =Statement!AC165 -> 0.0012166388
B57: Payout ratios
B58: Dividend payout ratio | C58: =Statement!M168 -> 0.17730769 | D58: =Statement!N168 -> -0.075078206 | E58: =Statement!O168 -> -0.72050562 | F58: =Statement!P168 -> 0.75 | G58: =Statement!Q168 -> 0.010584765 | I58: =Statement!AC168 -> 0.010584765
B59: Buyback payout ratio | C59: =Statement!M169 -> 0.98346154 | D59: =Statement!N169 -> -0.063309996 | E59: =Statement!O169 -> -0.42134831 | F59: =Statement!P169 -> 0 | G59: =Statement!Q169 -> 0.011278848 | I59: =Statement!AC169 -> 0.011278848
B60: Full payout ratio | C60: =Statement!M170 -> 1.1607692 | D60: =Statement!N170 -> -0.1383882 | E60: =Statement!O170 -> -1.1418539 | F60: =Statement!P170 -> 0.75 | G60: =Statement!Q170 -> 0.021863613 | I60: =Statement!AC170 -> 0.021863613
B62: Ownership
B63: Insider ownership | C63: =Statement!M171 -> 0.0036463081 | D63: =Statement!N171 -> 0.0036429872 | E63: =Statement!O171 -> 0.0026737968 | F63: =Statement!P171 -> 0.0026525199 | G63: =Statement!Q171 -> 0.002617801 | I63: =Statement!AC171 -> 0.002617801
B65: Cash holdings
B66: Cash per share | C66: =Statement!M172 -> 10.099356 | D66: =Statement!N172 -> 9.5063752 | E66: =Statement!O172 -> 8.2524797 | F66: =Statement!P172 -> 10.638146 | G66: =Statement!Q172 -> 65.06023 | I66: =Statement!AC172 -> 65.06023
B67: Net cash per share | C67: =Statement!M175 -> 3.7460902 | D67: =Statement!N175 -> -2.6338798 | E67: =Statement!O175 -> -3.8277728 | F67: =Statement!P175 -> -2.3538324 | G67: =Statement!Q175 -> 60.472985 | I67: =Statement!AC175 -> 60.472985
B68: Net cash to market cap | C68: =Statement!M176 -> 0.064769528 | D68: =Statement!N176 -> -0.038682329 | E68: =Statement!O176 -> -0.039587972 | F68: =Statement!P176 -> -0.019140178 | G68: =Statement!Q176 -> 0.062177419 | I68: =Statement!AC176 -> 0.06592444
B70: Stock Based Compensation
B71: Stock based compensation % OCF | C71: =Statement!M173 -> 0.033858112 | D71: =Statement!N173 -> 0.38229634 | E71: =Statement!O173 -> 0.097919361 | F71: =Statement!P173 -> 0.055463623 | G71: =Statement!Q173 -> 0.01486479 | I71: =Statement!AC173 -> 0.01486479
B72: Stock based compensation % Revenue | C72: =Statement!M174 -> 0.0167111 | D72: =Statement!N174 -> 0.038352638 | E72: =Statement!O174 -> 0.033172713 | F72: =Statement!P174 -> 0.026004602 | G72: =Statement!Q174 -> 0.010008409 | I72: =Statement!AC174 -> 0.010008409
B74: CapEx Usage
B75: Capex to Revenue | C75: =Statement!M177 -> 0.3923207 | D75: =Statement!N177 -> 0.49395109 | E75: =Statement!O177 -> 0.33395723 | F75: =Statement!P177 -> 0.42423351 | G75: =Statement!Q177 -> 0.23059134 | I75: =Statement!AC177 -> 0.23059134
B76: CapEx to OCF | C76: =Statement!M178 -> 0.79487517 | D76: =Statement!N178 -> 4.923669 | E76: =Statement!O178 -> 0.98577642 | F76: =Statement!P178 -> 0.90482168 | G76: =Statement!Q178 -> 0.34248118 | I76: =Statement!AC178 -> 0.34248118
B77: CapEx to D&A | C77: =Statement!M179 -> 1.695756 | D77: =Statement!N179 -> 0.9896854 | E77: =Statement!O179 -> 1.077892 | F77: =Statement!P179 -> 1.8985872 | G77: =Statement!Q179 -> 3.2318215 | I77: =Statement!AC179 -> 3.2318215
B79: Growth rates
B80: Revenue | C80: =Statement!M89 -> 0.11019672 | D80: =Statement!N89 -> -0.49476559 | E80: =Statement!O89 -> 0.61589447 | F80: =Statement!P89 -> 0.48851101 | G80: =Statement!Q89 -> 2.5632725
B81: COGS | C81: =Statement!M90 -> -0.02441847 | D81: =Statement!N90 -> 0.0056939502 | E81: =Statement!O90 -> 0.14991743 | F81: =Statement!P90 -> 0.15422095 | G81: =Statement!Q90 -> 0.1412575
B82: Gross Profit | C82: =Statement!M91 -> 0.33339729 | D82: =Statement!N91 -> -1.1018852 | E82: =Statement!O91 -> 4.9639831 | F82: =Statement!P91 -> 1.6497417 | G82: =Statement!Q91 -> 6.2281315
B83: OpEx | C83: =Statement!M95 -> 0.01352657 | D83: =Statement!N95 -> 0.031696854 | E83: =Statement!O95 -> -0.0046200046 | F83: =Statement!P95 -> 0.18426549 | G83: =Statement!Q95 -> 0.59984323
B84: Operating Income | C84: =Statement!M96 -> 0.5441668 | D84: =Statement!N96 -> -1.5921459 | E84: =Statement!O96 -> 1.22698 | F84: =Statement!P96 -> 6.4923313 | G84: =Statement!Q96 -> 9.1678608
B85: Net Income | C85: =Statement!M98 -> 0.48217028 | D85: =Statement!N98 -> -1.6714631 | E85: =Statement!O98 -> 1.1333791 | F85: =Statement!P98 -> 9.9755784 | G85: =Statement!Q98 -> 8.9506968
B88: Growth rates breakdown
B89: =Statement!B203 -> DRAM | C89: =Statement!M203 -> 0.11712161 | D89: =Statement!N203 -> -0.50960422 | E89: =Statement!O203 -> 0.60347969 | F89: =Statement!P203 -> 0.62347327 | G89: =Statement!Q203 -> 2.5229547
B90: =Statement!B204 -> NAND | C90: =Statement!M204 -> 0.1147424 | D90: =Statement!N204 -> -0.46152861 | E90: =Statement!O204 -> 0.71825963 | F90: =Statement!P204 -> 0.17656012 | G90: =Statement!Q204 -> 2.7380924
B91: =Statement!B205 -> Other | C91: =Statement!M205 -> -0.14871017 | D91: =Statement!N205 -> -0.36541889 | E91: =Statement!O205 -> -0.21067416 | F91: =Statement!P205 -> 0.056939502 | G91: =Statement!Q205 -> 1.4377104
B93: =Statement!B207 -> Cloud Memory | C93: =Statement!M207 -> 0 | D93: =Statement!N207 -> 1 | E93: =Statement!O207 -> 1.025641 | F93: =Statement!P207 -> 2.5664557 | G93: =Statement!Q207 -> 2.1858178
B94: =Statement!B208 -> Core Data Center | C94: =Statement!M208 -> 0 | D94: =Statement!N208 -> 1 | E94: =Statement!O208 -> 1.346516 | F94: =Statement!P208 -> 0.45044141 | G94: =Statement!Q208 -> 4.200166
B95: =Statement!B209 -> Mobile and Client | C95: =Statement!M209 -> 0 | D95: =Statement!N209 -> 1 | E95: =Statement!O209 -> 0.577901 | F95: =Statement!P209 -> 0.016456673 | G95: =Statement!Q209 -> 2.0863479
B96: =Statement!B210 -> Automotive and Embedded | C96: =Statement!M210 -> 0 | D96: =Statement!N210 -> 1 | E96: =Statement!O210 -> 0.11886929 | F96: =Statement!P210 -> 0.026344202 | G96: =Statement!Q210 -> 2.3423101
B98: Other growth rates
B99: Dividends | C99: =Statement!M214 -> -1 | D99: =Statement!N214 -> 0.093275488 | E99: =Statement!O214 -> 0.017857143 | F99: =Statement!P214 -> 0.01754386 | G99: =Statement!Q214 -> 0.16858238

Sheet Quarter analysis
C3: Latest 2 quarters | F3: YoY
C4: =Statement!Z2 -> 28.05.2026 | D4: =Statement!AA2 -> 03.09.2026 | F4: =Statement!W2 -> 28.08.2025 | G4: =Statement!AA2 -> 03.09.2026
B5: Income statement growth | C5: =Statement!Z3 -> Q3 2026 | D5: =Statement!AA3 -> Q4 2026 | F5: =Statement!W3 -> Q4 2025 | G5: =Statement!AA3 -> Q4 2026
B6: Revenue | C6: =Statement!Z5 -> 41456 | D6: =Statement!AA5 -> 54229 | F6: =Statement!W5 -> 11315 | G6: =Statement!AA5 -> 54229
B7: Growth | C7: =Statement!AA89 -> 0.3081098 | F7: =IF(F6=0, IF(G6=0,0,IF(G6>0,1,-1)), (G6-F6)/ABS(F6) ) -> 3.7926646
B8: COGS | C8: =Statement!Z6 -> 6400 | D8: =Statement!AA6 -> 7182 | F8: =Statement!W6 -> 6261 | G8: =Statement!AA6 -> 7182
B9: Growth | C9: =Statement!AA90 -> 0.1221875 | F9: =IF(F8=0, IF(G8=0,0,IF(G8>0,1,-1)), (G8-F8)/ABS(F8) ) -> 0.1471011
B10: Gross Profit | C10: =Statement!Z7 -> 35056 | D10: =Statement!AA7 -> 47047 | F10: =Statement!W7 -> 5054 | G10: =Statement!AA7 -> 47047
B11: Growth | C11: =Statement!AA91 -> 0.34205272 | F11: =IF(F10=0, IF(G10=0,0,IF(G10>0,1,-1)), (G10-F10)/ABS(F10) ) -> 8.3088643
B12: OpEx | C12: =Statement!Z11 -> 1738 | D12: =Statement!AA11 -> 3296 | F12: =Statement!W11 -> 1400 | G12: =Statement!AA11 -> 3296
B13: Growth | C13: =Statement!AA95 -> 0.89643268 | F13: =IF(F12=0, IF(G12=0,0,IF(G12>0,1,-1)), (G12-F12)/ABS(F12) ) -> 1.3542857
B14: Operating profit | C14: =Statement!Z12 -> 33318 | D14: =Statement!AA12 -> 43751 | F14: =Statement!W12 -> 3654 | G14: =Statement!AA12 -> 43751
B15: Growth | C15: =Statement!AA96 -> 0.31313404 | F15: =IF(F14=0, IF(G14=0,0,IF(G14>0,1,-1)), (G14-F14)/ABS(F14) ) -> 10.973454
B16: Net income | C16: =Statement!Z18 -> 28243 | D16: =Statement!AA18 -> 37701 | F16: =Statement!W18 -> 3201 | G16: =Statement!AA18 -> 37701
B17: Growth | C17: =Statement!AA98 -> 0.33487944 | F17: =IF(F16=0, IF(G16=0,0,IF(G16>0,1,-1)), (G16-F16)/ABS(F16) ) -> 10.777882
B18: Diluted shares outstanding | C18: =Statement!Z22 -> 1145 | D18: =Statement!AA22 -> 1147 | F18: =Statement!W22 -> 1131 | G18: =Statement!AA22 -> 1147
B19: Growth | C19: =IF(C18=0, IF(D18=0,0,IF(D18>0,1,-1)), (D18-C18)/ABS(C18) ) -> 0.0017467249 | F19: =IF(F18=0, IF(G18=0,0,IF(G18>0,1,-1)), (G18-F18)/ABS(F18) ) -> 0.014146773
B20: Diluted EPS | C20: =Statement!Z26 -> 24.67 | D20: =Statement!AA26 -> 32.87 | F20: =Statement!W26 -> 2.83 | G20: =Statement!AA26 -> 32.87
B21: Growth | C21: =IF(C20=0, IF(D20=0,0,IF(D20>0,1,-1)), (D20-C20)/ABS(C20) ) -> 0.33238752 | F21: =IF(F20=0, IF(G20=0,0,IF(G20>0,1,-1)), (G20-F20)/ABS(F20) ) -> 10.614841
B23: Revenue breakdown | C23: =C5 -> Q3 2026 | D23: =D5 -> Q4 2026 | F23: =F5 -> Q4 2025 | G23: =G5 -> Q4 2026
B24: =Statement!B187 -> DRAM | C24: =Statement!Z187 -> 31328 | D24: =Statement!AA187 -> 39771 | F24: =Statement!W187 -> 22178 | G24: =Statement!AA187 -> 39771
B25: Growth | C25: =IF(C24=0, IF(D24=0,0,IF(D24>0,1,-1)), (D24-C24)/ABS(C24) ) -> 0.26950332 | F25: =IF(F24=0, IF(G24=0,0,IF(G24>0,1,-1)), (G24-F24)/ABS(F24) ) -> 0.79326359
B26: =Statement!B188 -> NAND | C26: =Statement!Z188 -> 9943 | D26: =Statement!AA188 -> 14102 | F26: =Statement!W188 -> 6262 | G26: =Statement!AA188 -> 14102
B27: Growth | C27: =IF(C26=0, IF(D26=0,0,IF(D26>0,1,-1)), (D26-C26)/ABS(C26) ) -> 0.41828422 | F27: =IF(F26=0, IF(G26=0,0,IF(G26>0,1,-1)), (G26-F26)/ABS(F26) ) -> 1.2519962
B28: =Statement!B189 -> Other | C28: =Statement!Z189 -> 185 | D28: =Statement!AA189 -> 356 | F28: =Statement!W189 -> 229 | G28: =Statement!AA189 -> 356
B29: Growth | C29: =IF(C28=0, IF(D28=0,0,IF(D28>0,1,-1)), (D28-C28)/ABS(C28) ) -> 0.92432432 | F29: =IF(F28=0, IF(G28=0,0,IF(G28>0,1,-1)), (G28-F28)/ABS(F28) ) -> 0.55458515
B31: =Statement!B191 -> Cloud Memory | C31: =Statement!Z191 -> 13769 | D31: =Statement!AA191 -> 16283 | F31: =Statement!W191 -> 4543 | G31: =Statement!AA191 -> 16283
B32: Growth | C32: =IF(C31=0, IF(D31=0,0,IF(D31>0,1,-1)), (D31-C31)/ABS(C31) ) -> 0.18258407 | F32: =IF(F31=0, IF(G31=0,0,IF(G31>0,1,-1)), (G31-F31)/ABS(F31) ) -> 2.5841955
B33: =Statement!B192 -> Core Data Center | C33: =Statement!Z192 -> 11524 | D33: =Statement!AA192 -> 18002 | F33: =Statement!W192 -> 1577 | G33: =Statement!AA192 -> 18002
B34: Growth | C34: =IF(C33=0, IF(D33=0,0,IF(D33>0,1,-1)), (D33-C33)/ABS(C33) ) -> 0.5621312 | F34: =IF(F33=0, IF(G33=0,0,IF(G33>0,1,-1)), (G33-F33)/ABS(F33) ) -> 10.415346
B35: =Statement!B193 -> Mobile and Client | C35: =Statement!Z193 -> 11521 | D35: =Statement!AA193 -> 13114 | F35: =Statement!W193 -> 3760 | G35: =Statement!AA193 -> 13114
B36: Growth | C36: =IF(C35=0, IF(D35=0,0,IF(D35>0,1,-1)), (D35-C35)/ABS(C35) ) -> 0.13826925 | F36: =IF(F35=0, IF(G35=0,0,IF(G35>0,1,-1)), (G35-F35)/ABS(F35) ) -> 2.487766
B37: =Statement!B194 -> Automotive and Embedded | C37: =Statement!Z194 -> 4634 | D37: =Statement!AA194 -> 6824 | F37: =Statement!W194 -> 1434 | G37: =Statement!AA194 -> 6824
B38: Growth | C38: =IF(C37=0, IF(D37=0,0,IF(D37>0,1,-1)), (D37-C37)/ABS(C37) ) -> 0.47259387 | F38: =IF(F37=0, IF(G37=0,0,IF(G37>0,1,-1)), (G37-F37)/ABS(F37) ) -> 3.7587169

Sheet Graphs Year
C62: =Statement!H2 -> 0 | D62: =Statement!I2 -> 0 | E62: =Statement!J2 -> 0 | F62: =Statement!K2 -> 0 | G62: =Statement!L2 -> 02.09.2021 | H62: =Statement!M2 -> 01.09.2022 | I62: =Statement!N2 -> 31.08.2023 | J62: =Statement!O2 -> 29.08.2024 | ... L62: =Statement!Q2 -> 03.09.2025
C63: =Statement!H3 -> 0 | D63: =Statement!I3 -> 0 | E63: =Statement!J3 -> 0 | F63: =Statement!K3 -> 0 | G63: =Statement!L3 -> 2021 | H63: =Statement!M3 -> 2022 | I63: =Statement!N3 -> 2023 | J63: =Statement!O3 -> 2024 | ... L63: =Statement!Q3 -> 2026
B64: Revenue | C64: =Statement!H5 -> 0 | D64: =Statement!I5 -> 0 | E64: =Statement!J5 -> 0 | F64: =Statement!K5 -> 0 | G64: =Statement!L5 -> 27705 | H64: =Statement!M5 -> 30758 | I64: =Statement!N5 -> 15540 | J64: =Statement!O5 -> 25111 | ... L64: =Statement!Q5 -> 133188
B65: Operating income | C65: =Statement!H12 -> 0 | D65: =Statement!I12 -> 0 | E65: =Statement!J12 -> 0 | F65: =Statement!K12 -> 0 | G65: =Statement!L12 -> 6283 | H65: =Statement!M12 -> 9702 | I65: =Statement!N12 -> -5745 | J65: =Statement!O12 -> 1304 | ... L65: =Statement!Q12 -> 99340
B66: Net income | C66: =Statement!H18 -> 0 | D66: =Statement!I18 -> 0 | E66: =Statement!J18 -> 0 | F66: =Statement!K18 -> 0 | G66: =Statement!L18 -> 5861 | H66: =Statement!M18 -> 8687 | I66: =Statement!N18 -> -5833 | J66: =Statement!O18 -> 778 | ... L66: =Statement!Q18 -> 84969
B67: FCFE | C67: =Statement!H157 -> 0 | D67: =Statement!I157 -> 0 | E67: =Statement!J157 -> 0 | F67: =Statement!K157 -> 0 | G67: =Statement!L157 -> 2060 | H67: =Statement!M157 -> 2600 | I67: =Statement!N157 -> -6713 | J67: =Statement!O157 -> -712 | ... L67: =Statement!Q157 -> 57630
B68: FCFF | C68: =Statement!H158 -> 0 | D68: =Statement!I158 -> 0 | E68: =Statement!J158 -> 0 | F68: =Statement!K158 -> 0 | G68: =Statement!L158 -> 1698.8813 | H68: =Statement!M158 -> 2605.8458 | I68: =Statement!N158 -> -8557 | J68: =Statement!O158 -> -660.27742 | ... L68: =Statement!Q158 -> 57677.02
B69: Gross margin | C69: =Statement!H101 -> 0 | D69: =Statement!I101 -> 0 | E69: =Statement!J101 -> 0 | F69: =Statement!K101 -> 0 | G69: =Statement!L101 -> 0.37621368 | H69: =Statement!M101 -> 0.45184993 | I69: =Statement!N101 -> -0.091119691 | J69: =Statement!O101 -> 0.22352754 | ... L69: =Statement!Q101 -> 0.8071598
B70: Operating margin | C70: =Statement!H102 -> 0 | D70: =Statement!I102 -> 0 | E70: =Statement!J102 -> 0 | F70: =Statement!K102 -> 0 | G70: =Statement!L102 -> 0.22678217 | H70: =Statement!M102 -> 0.31543013 | I70: =Statement!N102 -> -0.36969112 | J70: =Statement!O102 -> 0.051929433 | ... L70: =Statement!Q102 -> 0.74586299
B71: Net margin | C71: =Statement!H103 -> 0 | D71: =Statement!I103 -> 0 | E71: =Statement!J103 -> 0 | F71: =Statement!K103 -> 0 | G71: =Statement!L103 -> 0.21155026 | H71: =Statement!M103 -> 0.28243059 | I71: =Statement!N103 -> -0.37535393 | J71: =Statement!O103 -> 0.030982438 | ... L71: =Statement!Q103 -> 0.63796288
B72: ="Revenue "&Statement!B187 -> Revenue DRAM | C72: =Statement!H187 -> 0 | D72: =Statement!I187 -> 0 | E72: =Statement!J187 -> 0 | F72: =Statement!K187 -> 0 | G72: =Statement!L187 -> 20039 | H72: =Statement!M187 -> 22386 | I72: =Statement!N187 -> 10978 | J72: =Statement!O187 -> 17603 | ... L72: =Statement!Q187 -> 100679
B73: ="Revenue "&Statement!B188 -> Revenue NAND | C73: =Statement!H188 -> 0 | D73: =Statement!I188 -> 0 | E73: =Statement!J188 -> 0 | F73: =Statement!K188 -> 0 | G73: =Statement!L188 -> 7007 | H73: =Statement!M188 -> 7811 | I73: =Statement!N188 -> 4206 | J73: =Statement!O188 -> 7227 | ... L73: =Statement!Q188 -> 31785
B74: ="Revenue "&Statement!B189 -> Revenue Other | C74: =Statement!H189 -> 0 | D74: =Statement!I189 -> 0 | E74: =Statement!J189 -> 0 | F74: =Statement!K189 -> 0 | G74: =Statement!L189 -> 659 | H74: =Statement!M189 -> 561 | I74: =Statement!N189 -> 356 | J74: =Statement!O189 -> 281 | ... L74: =Statement!Q189 -> 724
B75: ="Revenue "&Statement!B191 -> Revenue Cloud Memory | C75: =Statement!H191 -> 0 | D75: =Statement!I191 -> 0 | E75: =Statement!J191 -> 0 | F75: =Statement!K191 -> 0 | G75: =Statement!L191 -> 0 | H75: =Statement!M191 -> 0 | I75: =Statement!N191 -> 1872 | J75: =Statement!O191 -> 3792 | ... L75: =Statement!Q191 -> 43085
B76: ="Revenue "&Statement!B192 -> Revenue Core Data Center | C76: =Statement!H192 -> 0 | D76: =Statement!I192 -> 0 | E76: =Statement!J192 -> 0 | F76: =Statement!K192 -> 0 | G76: =Statement!L192 -> 0 | H76: =Statement!M192 -> 0 | I76: =Statement!N192 -> 2124 | J76: =Statement!O192 -> 4984 | ... L76: =Statement!Q192 -> 37592
B77: ="Revenue "&Statement!B193 -> Revenue Mobile and Client | C77: =Statement!H193 -> 0 | D77: =Statement!I193 -> 0 | E77: =Statement!J193 -> 0 | F77: =Statement!K193 -> 0 | G77: =Statement!L193 -> 0 | H77: =Statement!M193 -> 0 | I77: =Statement!N193 -> 7394 | J77: =Statement!O193 -> 11667 | ... L77: =Statement!Q193 -> 36601
B78: ="Revenue "&Statement!B194 -> Revenue Automotive and Embedded | C78: =Statement!H194 -> 0 | D78: =Statement!I194 -> 0 | E78: =Statement!J194 -> 0 | F78: =Statement!K194 -> 0 | G78: =Statement!L194 -> 0 | H78: =Statement!M194 -> 0 | I78: =Statement!N194 -> 4139 | J78: =Statement!O194 -> 4631 | ... L78: =Statement!Q194 -> 15886
B79: ROA | C79: =Statement!H123 -> 0 | D79: =Statement!I123 -> 0 | E79: =Statement!J123 -> 0 | F79: =Statement!K123 -> 0 | G79: =Statement!L123 -> 0.099593876 | H79: =Statement!M123 -> 0.13105925 | I79: =Statement!N123 -> -0.090780341 | J79: =Statement!O123 -> 0.011207791 | ... L79: =Statement!Q123 -> 0.43376317
B80: ROE | C80: =Statement!H125 -> 0 | D80: =Statement!I125 -> 0 | E80: =Statement!J125 -> 0 | F80: =Statement!K125 -> 0 | G80: =Statement!L125 -> 0.13340769 | H80: =Statement!M125 -> 0.17406376 | I80: =Statement!N125 -> -0.13220762 | J80: =Statement!O125 -> 0.017238705 | ... L80: =Statement!Q125 -> 0.61403547
B81: ROIC | C81: =Statement!H140 -> 0 | D81: =Statement!I140 -> 0 | E81: =Statement!J140 -> 0 | F81: =Statement!K140 -> 0 | G81: =Statement!L140 -> 0.14598698 | H81: =Statement!M140 -> 0.19203329 | I81: =Statement!N140 -> -0.12220284 | J81: =Statement!O140 -> 0.016804168 | ... L81: =Statement!Q140 -> 1.2071782
B82: Price 5y | C82: =Statement!H218 -> 0 | D82: =Statement!I218 -> 0 | E82: =Statement!J218 -> 0 | F82: =Statement!K218 -> 0 | G82: =Statement!L218 -> 100 | H82: =Statement!M218 -> 100 | I82: =Statement!N218 -> 118.80998 | J82: =Statement!O218 -> 166.75973 | ... L82: =Statement!Q218 -> 1671.8897
B83: Revenue 5y | C83: =Statement!H219 -> 0 | D83: =Statement!I219 -> 0 | E83: =Statement!J219 -> 0 | F83: =Statement!K219 -> 0 | G83: =Statement!L219 -> 100 | H83: =Statement!M219 -> 100 | I83: =Statement!N219 -> 50.523441 | J83: =Statement!O219 -> 81.640549 | ... L83: =Statement!Q219 -> 433.01905
B84: EPS 5y | C84: =Statement!H220 -> 0 | D84: =Statement!I220 -> 0 | E84: =Statement!J220 -> 0 | F84: =Statement!K220 -> 0 | G84: =Statement!L220 -> 100 | H84: =Statement!M220 -> 100 | I84: =Statement!N220 -> -68.903226 | J84: =Statement!O220 -> 9.0322581 | ... L84: =Statement!Q220 -> 959.09677

Sheet Graphs Quarter
C55: =Statement!T2 -> 28.11.2024 | D55: =Statement!U2 -> 27.02.2025 | E55: =Statement!V2 -> 29.05.2025 | F55: =Statement!W2 -> 28.08.2025 | G55: =Statement!X2 -> 27.11.2025 | H55: =Statement!Y2 -> 26.02.2026 | I55: =Statement!Z2 -> 28.05.2026 | J55: =Statement!AA2 -> 03.09.2026
C56: =Statement!T3 -> Q1 2025 | D56: =Statement!U3 -> Q2 2025 | E56: =Statement!V3 -> Q3 2025 | F56: =Statement!W3 -> Q4 2025 | G56: =Statement!X3 -> Q1 2026 | H56: =Statement!Y3 -> Q2 2026 | I56: =Statement!Z3 -> Q3 2026 | J56: =Statement!AA3 -> Q4 2026
B57: Revenue | C57: =Statement!T5 -> 8709 | D57: =Statement!U5 -> 8053 | E57: =Statement!V5 -> 9301 | F57: =Statement!W5 -> 11315 | G57: =Statement!X5 -> 13643 | H57: =Statement!Y5 -> 23860 | I57: =Statement!Z5 -> 41456 | J57: =Statement!AA5 -> 54229
B58: Operating income | C58: =Statement!T12 -> 2174 | D58: =Statement!U12 -> 1773 | E58: =Statement!V12 -> 2169 | F58: =Statement!W12 -> 3654 | G58: =Statement!X12 -> 6136 | H58: =Statement!Y12 -> 16135 | I58: =Statement!Z12 -> 33318 | J58: =Statement!AA12 -> 43751
B59: Net income | C59: =Statement!T18 -> 1870 | D59: =Statement!U18 -> 1583 | E59: =Statement!V18 -> 1885 | F59: =Statement!W18 -> 3201 | G59: =Statement!X18 -> 5240 | H59: =Statement!Y18 -> 13785 | I59: =Statement!Z18 -> 28243 | J59: =Statement!AA18 -> 37701
B60: Gross margin | C60: =Statement!T101 -> 0.3844299 | D60: =Statement!U101 -> 0.36793741 | E60: =Statement!V101 -> 0.37716375 | F60: =Statement!W101 -> 0.44666372 | G60: =Statement!X101 -> 0.56043392 | H60: =Statement!Y101 -> 0.74413244 | I60: =Statement!Z101 -> 0.84561945 | J60: =Statement!AA101 -> 0.86756164
B61: Operating margin | C61: =Statement!T102 -> 0.24962682 | D61: =Statement!U102 -> 0.2201664 | E61: =Statement!V102 -> 0.23320073 | F61: =Statement!W102 -> 0.32293416 | G61: =Statement!X102 -> 0.44975445 | H61: =Statement!Y102 -> 0.67623638 | I61: =Statement!Z102 -> 0.80369548 | J61: =Statement!AA102 -> 0.80678235
B62: Net margin | C62: =Statement!T103 -> 0.2147204 | D62: =Statement!U103 -> 0.19657271 | E62: =Statement!V103 -> 0.20266638 | F62: =Statement!W103 -> 0.28289881 | G62: =Statement!X103 -> 0.38407975 | H62: =Statement!Y103 -> 0.57774518 | I62: =Statement!Z103 -> 0.68127653 | J62: =Statement!AA103 -> 0.69521843
B63: ="Revenue "&Statement!B187 -> Revenue DRAM | C63: =Statement!T187 -> 6400 | D63: =Statement!U187 -> 6123 | E63: =Statement!V187 -> 7071 | F63: =Statement!W187 -> 22178 | G63: =Statement!X187 -> 10812 | H63: =Statement!Y187 -> 18768 | I63: =Statement!Z187 -> 31328 | J63: =Statement!AA187 -> 39771
B64: ="Revenue "&Statement!B188 -> Revenue NAND | C64: =Statement!T188 -> 2241 | D64: =Statement!U188 -> 1855 | E64: =Statement!V188 -> 2155 | F64: =Statement!W188 -> 6262 | G64: =Statement!X188 -> 2743 | H64: =Statement!Y188 -> 4997 | I64: =Statement!Z188 -> 9943 | J64: =Statement!AA188 -> 14102
B65: ="Revenue "&Statement!B189 -> Revenue Other | C65: =Statement!T189 -> 68 | D65: =Statement!U189 -> 75 | E65: =Statement!V189 -> 75 | F65: =Statement!W189 -> 229 | G65: =Statement!X189 -> 88 | H65: =Statement!Y189 -> 95 | I65: =Statement!Z189 -> 185 | J65: =Statement!AA189 -> 356
B66: ="Revenue "&Statement!B191 -> Revenue Cloud Memory | C66: =Statement!T191 -> 2658 | D66: =Statement!U191 -> 2947 | E66: =Statement!V191 -> 3386 | F66: =Statement!W191 -> 4543 | G66: =Statement!X191 -> 5284 | H66: =Statement!Y191 -> 7749 | I66: =Statement!Z191 -> 13769 | J66: =Statement!AA191 -> 16283
B67: ="Revenue "&Statement!B192 -> Revenue Core Data Center | C67: =Statement!T192 -> 2292 | D67: =Statement!U192 -> 1830 | E67: =Statement!V192 -> 1530 | F67: =Statement!W192 -> 1577 | G67: =Statement!X192 -> 2379 | H67: =Statement!Y192 -> 5687 | I67: =Statement!Z192 -> 11524 | J67: =Statement!AA192 -> 18002
B68: ="Revenue "&Statement!B193 -> Revenue Mobile and Client | C68: =Statement!T193 -> 2608 | D68: =Statement!U193 -> 2236 | E68: =Statement!V193 -> 3255 | F68: =Statement!W193 -> 3760 | G68: =Statement!X193 -> 4255 | H68: =Statement!Y193 -> 7711 | I68: =Statement!Z193 -> 11521 | J68: =Statement!AA193 -> 13114
B69: ="Revenue "&Statement!B194 -> Revenue Automotive and Embedded | C69: =Statement!T194 -> 1158 | D69: =Statement!U194 -> 1034 | E69: =Statement!V194 -> 1127 | F69: =Statement!W194 -> 1434 | G69: =Statement!X194 -> 1720 | H69: =Statement!Y194 -> 2708 | I69: =Statement!Z194 -> 4634 | J69: =Statement!AA194 -> 6824
B70: FCFE | C70: =Statement!T157 -> -182 | D70: =Statement!U157 -> -362 | E70: =Statement!V157 -> 1418 | F70: =Statement!W157 -> -178 | G70: =Statement!X157 -> 2732 | H70: =Statement!Y157 -> 5207 | I70: =Statement!Z157 -> 17207 | J70: =Statement!AA157 -> 32484

Sheet Forecast ->
H5: Links
H6: Overview'!B3
H7: Financials ->'!B13
H8: Analysis ->'!B13
H9: Forecast ->'!B13
H10: Valuation ->'!B13
B13: Forecast ->

Sheet Revenue
B1: Revenue forecast
C2: History | H2: Forecast | S2: History | AA2: Forecast | AE2: TTM
C4: Revenues | S4: Revenues
B5: Revenues (thousand) | C5: =Statement!M3 -> 2022 | D5: =Statement!N3 -> 2023 | E5: =Statement!O3 -> 2024 | F5: =Statement!P3 -> 2025 | G5: =Statement!Q3 -> 2026 | H5: =G5+1 -> 2027 | I5: =H5+1 -> 2028 | J5: =I5+1 -> 2029 | K5: =J5+1 -> 2030 | L5: =K5+1 -> 2031 | R5: =B5 -> Revenues (thousand) | S5: =Statement!T3 -> Q1 2025 | T5: =Statement!U3 -> Q2 2025 | U5: =Statement!V3 -> Q3 2025 | V5: =Statement!W3 -> Q4 2025 | W5: =Statement!X3 -> Q1 2026 | X5: =Statement!Y3 -> Q2 2026 | Y5: =Statement!Z3 -> Q3 2026 | Z5: =Statement!AA3 -> Q4 2026 | AA5: FQ1 | AB5: FQ2 | AC5: FQ3 | AE5: FQ1
B6: =Statement!B191 -> Cloud Memory | C6: =Statement!M191 -> 0 | D6: =Statement!N191 -> 1872 | E6: =Statement!O191 -> 3792 | F6: =Statement!P191 -> 13524 | G6: =Statement!Q191 -> 43085 | H6: =G6*(1+H14) -> 62473.25 | I6: =H6*(1+I14) -> 87462.55 | J6: =I6*(1+J14) -> 96208.805 | K6: =J6*(1+K14) -> 86587.924 | L6: =K6*(1+L14) -> 51952.755 | N6: Cloud growth rate | Q6: =N6 -> Cloud growth rate | R6: =B6 -> Cloud Memory | S6: =Statement!T191 -> 2658 | T6: =Statement!U191 -> 2947 | U6: =Statement!V191 -> 3386 | V6: =Statement!W191 -> 4543 | W6: =Statement!X191 -> 5284 | X6: =Statement!Y191 -> 7749 | Y6: =Statement!Z191 -> 13769 | Z6: =Statement!AA191 -> 16283 | AA6: =Z6*(1+AA14) -> 18725.45 | AE6: =SUM(X6:AA6) -> 56526.45
B7: =Statement!B192 -> Core Data Center | C7: =Statement!M192 -> 0 | D7: =Statement!N192 -> 2124 | E7: =Statement!O192 -> 4984 | F7: =Statement!P192 -> 7229 | G7: =Statement!Q192 -> 37592 | H7: =G7*(1+H15) -> 63906.4 | I7: =H7*(1+I15) -> 83078.32 | J7: =I7*(1+J15) -> 95540.068 | K7: =J7*(1+K15) -> 81209.058 | L7: =K7*(1+L15) -> 40604.529 | N7: Datacenter growth rate | Q7: =N7 -> Datacenter growth rate | R7: =B7 -> Core Data Center | S7: =Statement!T192 -> 2292 | T7: =Statement!U192 -> 1830 | U7: =Statement!V192 -> 1530 | V7: =Statement!W192 -> 1577 | W7: =Statement!X192 -> 2379 | X7: =Statement!Y192 -> 5687 | Y7: =Statement!Z192 -> 11524 | Z7: =Statement!AA192 -> 18002 | AA7: =Z7*(1+AA15) -> 19802.2 | AE7: =SUM(X7:AA7) -> 55015.2
B8: =Statement!B193 -> Mobile and Client | C8: =Statement!M193 -> 0 | D8: =Statement!N193 -> 7394 | E8: =Statement!O193 -> 11667 | F8: =Statement!P193 -> 11859 | G8: =Statement!Q193 -> 36601 | H8: =G8*(1+H16) -> 73202 | I8: =H8*(1+I16) -> 102482.8 | J8: =I8*(1+J16) -> 133227.64 | K8: =J8*(1+K16) -> 106582.11 | L8: =K8*(1+L16) -> 95923.901 | N8: Mobile growth rate | Q8: =N8 -> Mobile growth rate | R8: =B8 -> Mobile and Client | S8: =Statement!T193 -> 2608 | T8: =Statement!U193 -> 2236 | U8: =Statement!V193 -> 3255 | V8: =Statement!W193 -> 3760 | W8: =Statement!X193 -> 4255 | X8: =Statement!Y193 -> 7711 | Y8: =Statement!Z193 -> 11521 | Z8: =Statement!AA193 -> 13114 | AA8: =Z8*(1+AA16) -> 15736.8 | AE8: =SUM(X8:AA8) -> 48082.8
B9: =Statement!B194 -> Automotive and Embedded | C9: =Statement!M194 -> 0 | D9: =Statement!N194 -> 4139 | E9: =Statement!O194 -> 4631 | F9: =Statement!P194 -> 4753 | G9: =Statement!Q194 -> 15886 | H9: =G9*(1+H17) -> 31772 | I9: =H9*(1+I17) -> 44480.8 | J9: =I9*(1+J17) -> 48928.88 | K9: =J9*(1+K17) -> 44035.992 | L9: =K9*(1+L17) -> 30825.194 | N9: Automotive growth rate | Q9: =N9 -> Automotive growth rate | R9: =B9 -> Automotive and Embedded | S9: =Statement!T194 -> 1158 | T9: =Statement!U194 -> 1034 | U9: =Statement!V194 -> 1127 | V9: =Statement!W194 -> 1434 | W9: =Statement!X194 -> 1720 | X9: =Statement!Y194 -> 2708 | Y9: =Statement!Z194 -> 4634 | Z9: =Statement!AA194 -> 6824 | AA9: =Z9*(1+AA17) -> 7506.4 | AE9: =SUM(X9:AA9) -> 21672.4
B10: Total | C10: =Statement!M5 -> 30758 | D10: =Statement!N5 -> 15540 | E10: =Statement!O5 -> 25111 | F10: =Statement!P5 -> 37378 | G10: =Statement!Q5 -> 133188 | H10: =SUM(H6:H9) -> 231353.65 | I10: =SUM(I6:I9) -> 317504.47 | J10: =SUM(J6:J9) -> 373905.39 | K10: =SUM(K6:K9) -> 318415.09 | L10: =SUM(L6:L9) -> 219306.38 | R10: Total | S10: =Statement!T5 -> 8709 | T10: =Statement!U5 -> 8053 | U10: =Statement!V5 -> 9301 | V10: =Statement!W5 -> 11315 | W10: =Statement!X5 -> 13643 | X10: =Statement!Y5 -> 23860 | Y10: =Statement!Z5 -> 41456 | Z10: =Statement!AA5 -> 54229 | AA10: =SUM(AA6:AA9) -> 61770.85 | AE10: =SUM(X10:AA10) -> 181315.85
C12: Growth rates | S12: Growth rates
B13: Revenue growth % | C13: =C5 -> 2022 | D13: =D5 -> 2023 | E13: =E5 -> 2024 | F13: =F5 -> 2025 | G13: =G5 -> 2026 | H13: =H5 -> 2027 | I13: =I5 -> 2028 | J13: =J5 -> 2029 | ... L13: =L5 -> 2031 | R13: Revenue growth % | S13: =S5 -> Q1 2025 | T13: =T5 -> Q2 2025 | U13: =U5 -> Q3 2025 | V13: =V5 -> Q4 2025 | W13: =W5 -> Q1 2026 | X13: =X5 -> Q2 2026 | Y13: =Y5 -> Q3 2026 | Z13: =Z5 -> Q4 2026 | ... AC13: =AC5 -> FQ3
B14: =B6 -> Cloud Memory | D14: =D6/C6-1 -> #DIV/0! | E14: =E6/D6-1 -> 1.025641 | F14: =F6/E6-1 -> 2.5664557 | G14: =G6/F6-1 -> 2.1858178 | H14: 0.45 | I14: 0.4 | J14: 0.1 | K14: -0.1 | L14: -0.4 | R14: =R6 -> Cloud Memory | T14: =T6/S6-1 -> 0.10872837 | U14: =U6/T6-1 -> 0.14896505 | V14: =V6/U6-1 -> 0.34170112 | W14: =W6/V6-1 -> 0.16310808 | X14: =X6/W6-1 -> 0.46650265 | Y14: =Y6/X6-1 -> 0.77687444 | Z14: =Z6/Y6-1 -> 0.18258407 | AA14: 0.15
B15: =B7 -> Core Data Center | D15: =D7/C7-1 -> #DIV/0! | E15: =E7/D7-1 -> 1.346516 | F15: =F7/E7-1 -> 0.45044141 | G15: =G7/F7-1 -> 4.200166 | H15: 0.7 | I15: 0.3 | J15: 0.15 | K15: -0.15 | L15: -0.5 | R15: =R7 -> Core Data Center | T15: =T7/S7-1 -> -0.20157068 | U15: =U7/T7-1 -> -0.16393443 | V15: =V7/U7-1 -> 0.030718954 | W15: =W7/V7-1 -> 0.50856056 | X15: =X7/W7-1 -> 1.3905002 | Y15: =Y7/X7-1 -> 1.0263759 | Z15: =Z7/Y7-1 -> 0.5621312 | AA15: 0.1
B16: =B8 -> Mobile and Client | D16: =D8/C8-1 -> #DIV/0! | E16: =E8/D8-1 -> 0.577901 | F16: =F8/E8-1 -> 0.016456673 | G16: =G8/F8-1 -> 2.0863479 | H16: 1 | I16: 0.4 | J16: 0.3 | K16: -0.2 | L16: -0.1 | R16: =R8 -> Mobile and Client | T16: =T8/S8-1 -> -0.14263804 | U16: =U8/T8-1 -> 0.45572451 | V16: =V8/U8-1 -> 0.15514593 | W16: =W8/V8-1 -> 0.13164894 | X16: =X8/W8-1 -> 0.81222092 | Y16: =Y8/X8-1 -> 0.49409934 | Z16: =Z8/Y8-1 -> 0.13826925 | AA16: 0.2
B17: =B9 -> Automotive and Embedded | D17: =D9/C9-1 -> #DIV/0! | E17: =E9/D9-1 -> 0.11886929 | F17: =F9/E9-1 -> 0.026344202 | G17: =G9/F9-1 -> 2.3423101 | H17: 1 | I17: 0.4 | J17: 0.1 | K17: -0.1 | L17: -0.3 | R17: =R9 -> Automotive and Embedded | T17: =T9/S9-1 -> -0.10708117 | U17: =U9/T9-1 -> 0.089941973 | V17: =V9/U9-1 -> 0.27240461 | W17: =W9/V9-1 -> 0.19944212 | X17: =X9/W9-1 -> 0.5744186 | Y17: =Y9/X9-1 -> 0.711226 | Z17: =Z9/Y9-1 -> 0.47259387 | AA17: 0.1
B18: =B10 -> Total | D18: =D10/C10-1 -> -0.49476559 | E18: =E10/D10-1 -> 0.61589447 | F18: =F10/E10-1 -> 0.48851101 | G18: =G10/F10-1 -> 2.5632725 | H18: =H10/G10-1 -> 0.73704575 | I18: =I10/H10-1 -> 0.37237718 | J18: =J10/I10-1 -> 0.1776382 | K18: =K10/J10-1 -> -0.14840735 | L18: =L10/K10-1 -> -0.31125632 | R18: =R10 -> Total | T18: =T10/S10-1 -> -0.075324377 | U18: =U10/T10-1 -> 0.1549733 | V18: =V10/U10-1 -> 0.21653586 | W18: =W10/V10-1 -> 0.20574459 | X18: =X10/W10-1 -> 0.74888221 | Y18: =Y10/X10-1 -> 0.73746857 | Z18: =Z10/Y10-1 -> 0.3081098 | AA18: =AA10/Z10-1 -> 0.13907411

Sheet COGS & OpEx
B1: COGS & OpEx forecast
C2: History | H2: Forecast | P2: History | X2: Forecast | AB2: TTM
C4: Revenues | P4: Revenues
B5: =Revenue!B5 -> Revenues (thousand) | C5: =Revenue!C5 -> 2022 | D5: =Revenue!D5 -> 2023 | E5: =Revenue!E5 -> 2024 | F5: =Revenue!F5 -> 2025 | G5: =Revenue!G5 -> 2026 | H5: =G5+1 -> 2027 | I5: =H5+1 -> 2028 | J5: =I5+1 -> 2029 | K5: =J5+1 -> 2030 | L5: =K5+1 -> 2031 | O5: Revenues (thousand) | P5: =Revenue!S5 -> Q1 2025 | Q5: =Revenue!T5 -> Q2 2025 | R5: =Revenue!U5 -> Q3 2025 | S5: =Revenue!V5 -> Q4 2025 | T5: =Revenue!W5 -> Q1 2026 | U5: =Revenue!X5 -> Q2 2026 | V5: =Revenue!Y5 -> Q3 2026 | W5: =Revenue!Z5 -> Q4 2026 | X5: FQ1 | Y5: FQ2 | Z5: FQ3 | AB5: =Revenue!AE5 -> FQ1
B6: Revenue | C6: =Revenue!C10 -> 30758 | D6: =Revenue!D10 -> 15540 | E6: =Revenue!E10 -> 25111 | F6: =Revenue!F10 -> 37378 | G6: =Revenue!G10 -> 133188 | H6: =Revenue!H10 -> 231353.65 | I6: =Revenue!I10 -> 317504.47 | J6: =Revenue!J10 -> 373905.39 | ... L6: =Revenue!L10 -> 219306.38 | O6: Revenue | P6: =Revenue!S10 -> 8709 | Q6: =Revenue!T10 -> 8053 | R6: =Revenue!U10 -> 9301 | S6: =Revenue!V10 -> 11315 | T6: =Revenue!W10 -> 13643 | U6: =Revenue!X10 -> 23860 | V6: =Revenue!Y10 -> 41456 | W6: =Revenue!Z10 -> 54229 | X6: =Revenue!AA10 -> 61770.85 | AB6: =Revenue!AE10 -> 181315.85
C9: COGS and OpEx | P9: COGS & OpEx | AB9: =AB4 -> 0
B10: Expenses (tnousand) | C10: =C5 -> 2022 | D10: =D5 -> 2023 | E10: =E5 -> 2024 | F10: =F5 -> 2025 | G10: =G5 -> 2026 | H10: =H5 -> 2027 | I10: =I5 -> 2028 | J10: =J5 -> 2029 | ... L10: =L5 -> 2031 | O10: Expenses (thousand) | P10: =P5 -> Q1 2025 | Q10: =Q5 -> Q2 2025 | R10: =R5 -> Q3 2025 | S10: =S5 -> Q4 2025 | T10: =T5 -> Q1 2026 | U10: =U5 -> Q2 2026 | V10: =V5 -> Q3 2026 | W10: =W5 -> Q4 2026 | ... Z10: =Z5 -> FQ3 | AB10: =AB5 -> FQ1
B11: =Statement!B191 -> Cloud Memory | C11: =Statement!M196 -> 0 | D11: =Statement!N196 -> 1801 | E11: =Statement!O196 -> 2677 | F11: =Statement!P196 -> 5867 | G11: =Statement!Q196 -> 8865.11 | H11: =H6*H24 -> 11567.683 | I11: =I6*I24 -> 12700.179 | J11: =J6*J24 -> 14956.216 | K11: =K6*K24 -> 14328.679 | L11: =L6*L24 -> 9868.787 | O11: =B11 -> Cloud Memory | P11: =Statement!T196 -> 1293 | Q11: =Statement!U196 -> 1317 | R11: =Statement!V196 -> 1415 | S11: =Statement!W196 -> 1842 | T11: =Statement!X196 -> 1817 | U11: =Statement!Y196 -> 2002 | V11: =Statement!Z196 -> 2278 | W11: =Statement!AA196 -> 2768.11 | X11: =X24*X$6 -> 3088.5425 | AB11: =SUM(U11:X11) -> 10136.653
B12: =Statement!B192 -> Core Data Center | C12: =Statement!M197 -> 0 | D12: =Statement!N197 -> 1967 | E12: =Statement!O197 -> 3638 | F12: =Statement!P197 -> 3995 | G12: =Statement!Q197 -> 5955.2 | H12: =H6*H25 -> 9254.146 | I12: =I6*I25 -> 9525.1341 | J12: =J6*J25 -> 11217.162 | K12: =K6*K25 -> 11144.528 | L12: =L6*L25 -> 7675.7233 | O12: =B12 -> Core Data Center | P12: =Statement!T197 -> 1149 | Q12: =Statement!U197 -> 967 | R12: =Statement!V197 -> 956 | S12: =Statement!W197 -> 923 | T12: =Statement!X197 -> 1157 | U12: =Statement!Y197 -> 1461 | V12: =Statement!Z197 -> 1537 | W12: =Statement!AA197 -> 1800.2 | X12: =X25*X$6 -> 2161.9797 | AB12: =SUM(U12:X12) -> 6960.1797
B13: =Statement!B193 -> Mobile and Client | C13: =Statement!M198 -> 0 | D13: =Statement!N198 -> 9072 | E13: =Statement!O198 -> 10222 | F13: =Statement!P198 -> 8650 | G13: =Statement!Q198 -> 6401.4 | H13: =H6*H26 -> 10410.914 | I13: =I6*I26 -> 11112.656 | J13: =J6*J26 -> 13086.689 | K13: =K6*K26 -> 12736.603 | L13: =L6*L26 -> 8772.2552 | O13: =B13 -> Mobile and Client | P13: =Statement!T198 -> 1899 | Q13: =Statement!U198 -> 1894 | R13: =Statement!V198 -> 2467 | S13: =Statement!W198 -> 2390 | T13: =Statement!X198 -> 1970 | U13: =Statement!Y198 -> 1657 | V13: =Statement!Z198 -> 1463 | W13: =Statement!AA198 -> 1311.4 | X13: =X26*X$6 -> 1853.1255 | AB13: =SUM(U13:X13) -> 6284.5255
B14: =Statement!B194 -> Automotive and Embedded | C14: =Statement!M199 -> 0 | D14: =Statement!N199 -> 2905 | E14: =Statement!O199 -> 3598 | F14: =Statement!P199 -> 3566 | G14: =Statement!Q199 -> 3867.84 | H14: =H6*H27 -> 5783.8413 | I14: =I6*I27 -> 6350.0894 | J14: =J6*J27 -> 7478.1079 | K14: =K6*K27 -> 9552.4526 | L14: =L6*L27 -> 6579.1914 | O14: =B14 -> Automotive and Embedded | P14: =Statement!T199 -> 922 | Q14: =Statement!U199 -> 820 | R14: =Statement!V199 -> 837 | S14: =Statement!W199 -> 987 | T14: =Statement!X199 -> 942 | U14: =Statement!Y199 -> 859 | V14: =Statement!Z199 -> 975 | W14: =Statement!AA199 -> 1091.84 | X14: =X27*X$6 -> 1420.7296 | AB14: =SUM(U14:X14) -> 4346.5696
B15: COGS | C15: =Statement!M6 -> 16860 | D15: =Statement!N6 -> 16956 | E15: =Statement!O6 -> 19498 | F15: =Statement!P6 -> 22505 | G15: =Statement!Q6 -> 25684 | H15: =SUM(H11:H14) -> 37016.584 | I15: =SUM(I11:I14) -> 39688.059 | J15: =SUM(J11:J14) -> 46738.174 | K15: =SUM(K11:K14) -> 47762.263 | L15: =SUM(L11:L14) -> 32895.957 | O15: =B15 -> COGS | P15: =Statement!T6 -> 5361 | Q15: =Statement!U6 -> 5090 | R15: =Statement!V6 -> 5793 | S15: =Statement!W6 -> 6261 | T15: =Statement!X6 -> 5997 | U15: =Statement!Y6 -> 6105 | V15: =Statement!Z6 -> 6400 | W15: =Statement!AA6 -> 7182 | X15: =SUM(X11:X14) -> 8524.3773 | AB15: =SUM(AB11:AB14) -> 27727.927
B16: =Statement!B8 -> R&D | C16: =Statement!M8 -> 3116 | D16: =Statement!N8 -> 3114 | E16: =Statement!O8 -> 3430 | F16: =Statement!P8 -> 3798 | G16: =Statement!Q8 -> 5650 | H16: =H6*H29 -> 9716.8533 | I16: =I6*I29 -> 12700.179 | J16: =J6*J29 -> 14956.216 | K16: =K6*K29 -> 11144.528 | L16: =L6*L29 -> 6579.1914 | O16: =B16 -> R&D | P16: =Statement!T8 -> 888 | Q16: =Statement!U8 -> 898 | R16: =Statement!V8 -> 965 | S16: =Statement!W8 -> 1047 | T16: =Statement!X8 -> 1171 | U16: =Statement!Y8 -> 1250 | V16: =Statement!Z8 -> 1316 | W16: =Statement!AA8 -> 1913 | X16: =X29*X$6 -> 1482.5004 | AB16: =SUM(U16:X16) -> 5961.5004
B17: =Statement!B9 -> Sales and marketing | C17: =Statement!M9 -> 1066 | D17: =Statement!N9 -> 920 | E17: =Statement!O9 -> 1129 | F17: =Statement!P9 -> 1205 | G17: =Statement!Q9 -> 1947 | H17: =H6*H30 -> 3470.3047 | I17: =I6*I30 -> 6350.0894 | J17: =J6*J30 -> 7478.1079 | K17: =K6*K30 -> 4776.2263 | L17: =L6*L30 -> 6579.1914 | O17: =B17 -> Sales and marketing | P17: =Statement!T9 -> 288 | Q17: =Statement!U9 -> 285 | R17: =Statement!V9 -> 318 | S17: =Statement!W9 -> 314 | T17: =Statement!X9 -> 337 | U17: =Statement!Y9 -> 344 | V17: =Statement!Z9 -> 407 | W17: =Statement!AA9 -> 859 | X17: =X30*X$6 -> 803.02105 | AB17: =SUM(U17:X17) -> 2413.021
B18: =Statement!B10 -> Other income/expense | C18: =Statement!M10 -> 14 | D18: =Statement!N10 -> 295 | E18: =Statement!O10 -> -250 | F18: =Statement!P10 -> 100 | G18: =Statement!Q10 -> 567 | H18: 150 | I18: 150 | J18: 150 | K18: 150 | L18: 150 | O18: =B18 -> Other income/expense | P18: =Statement!T10 -> -2 | Q18: =Statement!U10 -> 7 | R18: =Statement!V10 -> 56 | S18: =Statement!W10 -> 39 | T18: =Statement!X10 -> 2 | U18: =Statement!Y10 -> 26 | V18: =Statement!Z10 -> 15 | W18: =Statement!AA10 -> 524 | X18: 150 | AB18: =SUM(U18:X18) -> 715
B19: OpEx | C19: =Statement!M11 -> 4196 | D19: =Statement!N11 -> 4329 | E19: =Statement!O11 -> 4309 | F19: =Statement!P11 -> 5103 | G19: =Statement!Q11 -> 8164 | H19: =SUM(H16:H18) -> 13337.158 | I19: =SUM(I16:I18) -> 19200.268 | J19: =SUM(J16:J18) -> 22584.324 | K19: =SUM(K16:K18) -> 16070.754 | L19: =SUM(L16:L18) -> 13308.383 | O19: =B19 -> OpEx | P19: =Statement!T11 -> 1174 | Q19: =Statement!U11 -> 1190 | R19: =Statement!V11 -> 1339 | S19: =Statement!W11 -> 1400 | T19: =Statement!X11 -> 1510 | U19: =Statement!Y11 -> 1620 | V19: =Statement!Z11 -> 1738 | W19: =Statement!AA11 -> 3296 | X19: =SUM(X16:X18) -> 2435.5214 | AB19: =SUM(U19:X19) -> 9089.5215
C22: Expenses % of Revenue | P22: Expenses % of Revenue
B23: % of revenue | C23: =C5 -> 2022 | D23: =D5 -> 2023 | E23: =E5 -> 2024 | F23: =F5 -> 2025 | G23: =G5 -> 2026 | H23: =H5 -> 2027 | I23: =I5 -> 2028 | J23: =J5 -> 2029 | ... L23: =L5 -> 2031 | O23: % of revenue | P23: =P5 -> Q1 2025 | Q23: =Q5 -> Q2 2025 | R23: =R5 -> Q3 2025 | S23: =S5 -> Q4 2025 | T23: =T5 -> Q1 2026 | U23: =U5 -> Q2 2026 | V23: =V5 -> Q3 2026 | W23: =W5 -> Q4 2026 | ... Z23: =Z5 -> FQ3
B24: =B11 -> Cloud Memory | C24: =C11/C$6 -> 0 | D24: =D11/D$6 -> 0.11589447 | E24: =E11/E$6 -> 0.10660667 | F24: =F11/F$6 -> 0.15696399 | G24: =G11/G$6 -> 0.066560876 | H24: 0.05 | I24: 0.04 | J24: 0.04 | K24: 0.045 | L24: 0.045 | O24: =O11 -> Cloud Memory | P24: =P11/P$6 -> 0.1484671 | Q24: =Q11/Q$6 -> 0.16354154 | R24: =R11/R$6 -> 0.15213418 | S24: =S11/S$6 -> 0.16279275 | T24: =T11/T$6 -> 0.13318185 | U24: =U11/U$6 -> 0.083906119 | V24: =V11/V$6 -> 0.054949826 | W24: =W11/W$6 -> 0.051044828 | X24: 0.05
B25: =B12 -> Core Data Center | C25: =C12/C$6 -> 0 | D25: =D12/D$6 -> 0.12657658 | E25: =E12/E$6 -> 0.14487675 | F25: =F12/F$6 -> 0.10688105 | G25: =G12/G$6 -> 0.044712737 | H25: 0.04 | I25: 0.03 | J25: 0.03 | K25: 0.035 | L25: 0.035 | O25: =O12 -> Core Data Center | P25: =P12/P$6 -> 0.13193248 | Q25: =Q12/Q$6 -> 0.12007947 | R25: =R12/R$6 -> 0.10278465 | S25: =S12/S$6 -> 0.081573133 | T25: =T12/T$6 -> 0.084805395 | U25: =U12/U$6 -> 0.061232188 | V25: =V12/V$6 -> 0.037075453 | W25: =W12/W$6 -> 0.03319626 | X25: 0.035
B26: =B13 -> Mobile and Client | C26: =C13/C$6 -> 0 | D26: =D13/D$6 -> 0.58378378 | E26: =E13/E$6 -> 0.4070726 | F26: =F13/F$6 -> 0.23141955 | G26: =G13/G$6 -> 0.048062889 | H26: 0.045 | I26: 0.035 | J26: 0.035 | K26: 0.04 | L26: 0.04 | O26: =O13 -> Mobile and Client | P26: =P13/P$6 -> 0.21805029 | Q26: =Q13/Q$6 -> 0.23519185 | R26: =R13/R$6 -> 0.2652403 | S26: =S13/S$6 -> 0.21122404 | T26: =T13/T$6 -> 0.14439639 | U26: =U13/U$6 -> 0.069446773 | V26: =V13/V$6 -> 0.035290428 | W26: =W13/W$6 -> 0.024182633 | X26: 0.03
B27: =B14 -> Automotive and Embedded | C27: =C14/C$6 -> 0 | D27: =D14/D$6 -> 0.18693694 | E27: =E14/E$6 -> 0.14328382 | F27: =F14/F$6 -> 0.095403713 | G27: =G14/G$6 -> 0.029040454 | H27: 0.025 | I27: 0.02 | J27: 0.02 | K27: 0.03 | L27: 0.03 | O27: =O14 -> Automotive and Embedded | P27: =P14/P$6 -> 0.10586749 | Q27: =Q14/Q$6 -> 0.10182541 | R27: =R14/R$6 -> 0.089990324 | S27: =S14/S$6 -> 0.087229342 | T27: =T14/T$6 -> 0.069046397 | U27: =U14/U$6 -> 0.036001676 | V27: =V14/V$6 -> 0.023518912 | W27: =W14/W$6 -> 0.020133877 | X27: 0.023
B28: =B15 -> COGS | C28: =C15/C$6 -> 0.54815007 | D28: =D15/D$6 -> 1.0911197 | E28: =E15/E$6 -> 0.77647246 | F28: =F15/F$6 -> 0.60209214 | G28: =G15/G$6 -> 0.1928402 | H28: =H15/H$6 -> 0.16 | I28: =I15/I$6 -> 0.125 | J28: =J15/J$6 -> 0.125 | ... L28: =L15/L$6 -> 0.15 | O28: =O15 -> COGS | P28: =P15/P$6 -> 0.6155701 | Q28: =Q15/Q$6 -> 0.63206259 | R28: =R15/R$6 -> 0.62283625 | S28: =S15/S$6 -> 0.55333628 | T28: =T15/T$6 -> 0.43956608 | U28: =U15/U$6 -> 0.25586756 | V28: =V15/V$6 -> 0.15438055 | W28: =W15/W$6 -> 0.13243836 | X28: =X15/X$6 -> 0.138
B29: =B16 -> R&D | C29: =C16/C$6 -> 0.10130698 | D29: =D16/D$6 -> 0.2003861 | E29: =E16/E$6 -> 0.13659352 | F29: =F16/F$6 -> 0.10161057 | G29: =G16/G$6 -> 0.042421239 | H29: 0.042 | I29: 0.04 | J29: 0.04 | K29: 0.035 | L29: 0.03 | O29: =O16 -> R&D | P29: =P16/P$6 -> 0.10196349 | Q29: =Q16/Q$6 -> 0.11151124 | R29: =R16/R$6 -> 0.10375228 | S29: =S16/S$6 -> 0.092532037 | T29: =T16/T$6 -> 0.085831562 | U29: =U16/U$6 -> 0.052388935 | V29: =V16/V$6 -> 0.0317445 | W29: =W16/W$6 -> 0.035276328 | X29: 0.024
B30: =B17 -> Sales and marketing | C30: =C17/C$6 -> 0.03465765 | D30: =D17/D$6 -> 0.059202059 | E30: =E17/E$6 -> 0.044960376 | F30: =F17/F$6 -> 0.032238215 | G30: =G17/G$6 -> 0.014618434 | H30: 0.015 | I30: 0.02 | J30: 0.02 | K30: 0.015 | L30: 0.03 | O30: =O17 -> Sales and marketing | P30: =P17/P$6 -> 0.033069239 | Q30: =Q17/Q$6 -> 0.035390538 | R30: =R17/R$6 -> 0.034189872 | S30: =S17/S$6 -> 0.027750773 | T30: =T17/T$6 -> 0.024701312 | U30: =U17/U$6 -> 0.014417435 | V30: =V17/V$6 -> 0.009817638 | W30: =W17/W$6 -> 0.015840233 | X30: 0.013
B31: =B19 -> OpEx | C31: =C19/C$6 -> 0.13641979 | D31: =D19/D$6 -> 0.27857143 | E31: =E19/E$6 -> 0.1715981 | F31: =F19/F$6 -> 0.13652416 | G31: =G19/G$6 -> 0.061296814 | H31: =H19/H$6 -> 0.057648358 | I31: =I19/I$6 -> 0.060472434 | J31: =J19/J$6 -> 0.060401171 | ... L31: =L19/L$6 -> 0.060683975 | O31: =O19 -> OpEx | P31: =P19/P$6 -> 0.13480308 | Q31: =Q19/Q$6 -> 0.14777102 | R31: =R19/R$6 -> 0.14396301 | S31: =S19/S$6 -> 0.12372956 | T31: =T19/T$6 -> 0.11067947 | U31: =U19/U$6 -> 0.06789606 | V31: =V19/V$6 -> 0.041923968 | W31: =W19/W$6 -> 0.060779288 | X31: =X19/X$6 -> 0.03942833

Sheet WC & Investments
B1: Working Capital, Capex, D&A
C3: History | H3: Forecast
C5: Revenues
B6: Revenues (thousand) | C6: =Revenue!C5 -> 2022 | D6: =Revenue!D5 -> 2023 | E6: =Revenue!E5 -> 2024 | F6: =Revenue!F5 -> 2025 | G6: =Revenue!G5 -> 2026 | H6: =G6+1 -> 2027 | I6: =H6+1 -> 2028 | J6: =I6+1 -> 2029 | K6: =J6+1 -> 2030 | L6: =K6+1 -> 2031
B7: Revenue | C7: =Revenue!C10 -> 30758 | D7: =Revenue!D10 -> 15540 | E7: =Revenue!E10 -> 25111 | F7: =Revenue!F10 -> 37378 | G7: =Revenue!G10 -> 133188 | H7: =Revenue!H10 -> 231353.65 | I7: =Revenue!I10 -> 317504.47 | J7: =Revenue!J10 -> 373905.39 | ... L7: =Revenue!L10 -> 219306.38
B8: COGS | C8: ='COGS & OpEx'!C15 -> 16860 | D8: ='COGS & OpEx'!D15 -> 16956 | E8: ='COGS & OpEx'!E15 -> 19498 | F8: ='COGS & OpEx'!F15 -> 22505 | G8: ='COGS & OpEx'!G15 -> 25684 | H8: ='COGS & OpEx'!H15 -> 37016.584 | I8: ='COGS & OpEx'!I15 -> 39688.059 | J8: ='COGS & OpEx'!J15 -> 46738.174 | ... L8: ='COGS & OpEx'!L15 -> 32895.957
C11: Working Capital
B12: $ (thousand) | C12: =C6 -> 2022 | D12: =D6 -> 2023 | E12: =E6 -> 2024 | F12: =F6 -> 2025 | G12: =G6 -> 2026 | H12: =H6 -> 2027 | I12: =I6 -> 2028 | J12: =J6 -> 2029 | ... L12: =L6 -> 2031
B13: Accounts receivable | C13: =Statement!M30 -> 5130 | D13: =Statement!N30 -> 2443 | E13: =Statement!O30 -> 6615 | F13: =Statement!P30 -> 9265 | G13: =Statement!Q30 -> 36197 | H13: =H20*H7/365 -> 53876.877 | I13: =I20*I7/365 -> 73939.397 | J13: =J20*J7/365 -> 87073.859 | K13: =K20*K7/365 -> 74151.458 | L13: =L20*L7/365 -> 51071.348
B14: Inventory | C14: =Statement!M31 -> 6663 | D14: =Statement!N31 -> 8387 | E14: =Statement!O31 -> 8875 | F14: =Statement!P31 -> 8355 | G14: =Statement!Q31 -> 10372 | H14: =H21*H8/365 -> 13183.989 | I14: =I21*I8/365 -> 14135.473 | J14: =J21*J8/365 -> 16646.473 | K14: =K21*K8/365 -> 17011.217 | L14: =L21*L8/365 -> 11716.368
B15: Accounts payable | C15: =Statement!M38 -> 6090 | D15: =Statement!N38 -> 3958 | E15: =Statement!O38 -> 7299 | F15: =Statement!P38 -> 9649 | G15: =Statement!Q38 -> 22605 | H15: =H22*H8/365 -> 15212.295 | I15: =I22*I8/365 -> 16310.161 | J15: =J22*J8/365 -> 19207.469 | K15: =K22*K8/365 -> 19628.327 | L15: =L22*L8/365 -> 13518.886
C18: WC metrics and drivers
B19: Days | C19: =C6 -> 2022 | D19: =D6 -> 2023 | E19: =E6 -> 2024 | F19: =F6 -> 2025 | G19: =G6 -> 2026 | H19: =H6 -> 2027 | I19: =I6 -> 2028 | J19: =J6 -> 2029 | ... L19: =L6 -> 2031
B20: DSO | C20: =C13/C7*365 -> 60.876845 | D20: =D13/D7*365 -> 57.380631 | E20: =E13/E7*365 -> 96.152085 | F20: =F13/F7*365 -> 90.473674 | G20: =G13/G7*365 -> 99.197413 | H20: 85 | I20: 85 | J20: 85 | K20: 85 | L20: 85
B21: DIO | C21: =C14/C8*365 -> 144.24644 | D21: =D14/D8*365 -> 180.54111 | E21: =E14/E8*365 -> 166.13883 | F21: =F14/F8*365 -> 135.50655 | G21: =G14/G8*365 -> 147.39838 | H21: 130 | I21: 130 | J21: 130 | K21: 130 | L21: 130
B22: DPO | C22: =C15/C8*365 -> 131.84164 | D22: =D15/D8*365 -> 85.201109 | E22: =E15/E8*365 -> 136.63632 | F22: =F15/F8*365 -> 156.49345 | G22: =G15/G8*365 -> 321.24377 | H22: 150 | I22: 150 | J22: 150 | K22: 150 | L22: 150
B23: Net trade cycle | C23: =C20+C21-C22 -> 73.281649 | D23: =D20+D21-D22 -> 152.72063 | E23: =E20+E21-E22 -> 125.6546 | F23: =F20+F21-F22 -> 69.486783 | G23: =G20+G21-G22 -> -74.647977 | H23: =H20+H21-H22 -> 65 | I23: =I20+I21-I22 -> 65 | J23: =J20+J21-J22 -> 65 | ... L23: =L20+L21-L22 -> 65
C26: Change in SIP NWC
B27: $ (thousand) | C27: =C6 -> 2022 | D27: =D6 -> 2023 | E27: =E6 -> 2024 | F27: =F6 -> 2025 | G27: =G6 -> 2026 | H27: =H6 -> 2027 | I27: =I6 -> 2028 | J27: =J6 -> 2029 | ... L27: =L6 -> 2031
B28: Change in acc receivable | C28: =Statement!M55 -> 190 | D28: =Statement!N55 -> 2763 | E28: =Statement!O55 -> -3581 | F28: =Statement!P55 -> -1776 | G28: =Statement!Q55 -> -25206 | H28: =-(H13-G13) -> -17679.877 | I28: =-(I13-H13) -> -20062.52 | J28: =-(J13-I13) -> -13134.462 | K28: =-(K13-J13) -> 12922.4 | L28: =-(L13-K13) -> 23080.11
B29: Change in inventory | C29: =Statement!M56 -> -2179 | D29: =Statement!N56 -> -3555 | E29: =Statement!O56 -> -488 | F29: =Statement!P56 -> 520 | G29: =Statement!Q56 -> -2017 | H29: =-(H14-G14) -> -2811.9888 | I29: =-(I14-H14) -> -951.48416 | J29: =-(J14-I14) -> -2511 | K29: =-(K14-J14) -> -364.74396 | L29: =-(L14-K14) -> 5294.8488
B30: Change in acc payable | C30: =Statement!M57 -> 744 | D30: =Statement!N57 -> -1302 | E30: =Statement!O57 -> 1915 | F30: =Statement!P57 -> 862 | G30: =Statement!Q57 -> 8707 | H30: =H15-G15 -> -7392.7052 | I30: =I15-H15 -> 1097.8663 | J30: =J15-I15 -> 2897.3077 | K30: =K15-J15 -> 420.85842 | L30: =L15-K15 -> -6109.4409
C33: Total change in NWC and less SIP
B34: $ (thousand) | C34: =C6 -> 2022 | D34: =D6 -> 2023 | E34: =E6 -> 2024 | F34: =F6 -> 2025 | G34: =G6 -> 2026 | H34: =H6 -> 2027 | I34: =I6 -> 2028 | J34: =J6 -> 2029 | ... L34: =L6 -> 2031
B35: Total change in NWC | C35: =Statement!M55+Statement!M56+Statement!M57+Statement!M58 -> -1245 | D35: =Statement!N55+Statement!N56+Statement!N57+Statement!N58 -> -2892 | E35: =Statement!O55+Statement!O56+Statement!O57+Statement!O58 -> -884 | F35: =Statement!P55+Statement!P56+Statement!P57+Statement!P58 -> -338 | G35: =Statement!Q55+Statement!Q56+Statement!Q57+Statement!Q58 -> -5742 | H35: =H36+H28+H29+H30 -> -16316.889 | I35: =I36+I28+I29+I30 -> -13566.048 | J35: =J36+J28+J29+J30 -> -1530.992 | K35: =K36+K28+K29+K30 -> 19346.816 | L35: =L36+L28+L29+L30 -> 24458.582
B36: Change in NWC less SIP | C36: =C35-C28-C29-C30 -> 0 | D36: =D35-D28-D29-D30 -> -798 | E36: =E35-E28-E29-E30 -> 1270 | F36: =F35-F28-F29-F30 -> 56 | G36: =G35-G28-G29-G30 -> 12774 | H36: =H7*H37 -> 11567.683 | I36: =I7*I37 -> 6350.0894 | J36: =J7*J37 -> 11217.162 | K36: =K7*K37 -> 6368.3017 | L36: =L7*L37 -> 2193.0638
B37: % of revenue | C37: =C36/C7 -> 0 | D37: =D36/D7 -> -0.051351351 | E37: =E36/E7 -> 0.050575445 | F37: =F36/F7 -> 0.0014982075 | G37: =G36/G7 -> 0.095909541 | H37: 0.05 | I37: 0.02 | J37: 0.03 | K37: 0.02 | L37: 0.01
C40: Investments
B41: $ (thousand) | C41: =C6 -> 2022 | D41: =D6 -> 2023 | E41: =E6 -> 2024 | F41: =F6 -> 2025 | G41: =G6 -> 2026 | H41: =H6 -> 2027 | I41: =I6 -> 2028 | J41: =J6 -> 2029 | ... L41: =L6 -> 2031
B42: D&A | C42: =Statement!M53 -> 7116 | D42: =Statement!N53 -> 7756 | E42: =Statement!O53 -> 7780 | F42: =Statement!P53 -> 8352 | G42: =Statement!Q53 -> 9503 | H42: =H7*H43 -> 23135.365 | I42: =I7*I43 -> 28575.402 | J42: =J7*J43 -> 29912.431 | K42: =K7*K43 -> 31841.509 | L42: =L7*L43 -> 32895.957
B43: % of Revenue | C43: =C42/C7 -> 0.23135444 | D43: =D42/D7 -> 0.4990991 | E43: =E42/E7 -> 0.30982438 | F43: =F42/F7 -> 0.22344695 | G43: =G42/G7 -> 0.071350272 | H43: 0.1 | I43: 0.09 | J43: 0.08 | K43: 0.1 | L43: 0.15
B44: % of CapEx | C44: =C42/C45 -> 0.58970747 | D44: =D42/D45 -> 1.0104221 | E44: =E42/E45 -> 0.9277367 | F44: =F42/F45 -> 0.52670745 | G44: =G42/G45 -> 0.30942303 | H44: =H42/H45 -> 0.4 | I44: =I42/I45 -> 0.3 | J44: =J42/J45 -> 0.32 | ... L44: =L42/L45 -> 0.88235294
B45: CapEx | C45: =-Statement!M110 -> 12067 | D45: =-Statement!N110 -> 7676 | E45: =-Statement!O110 -> 8386 | F45: =-Statement!P110 -> 15857 | G45: =-Statement!Q110 -> 30712 | H45: =H7*H46 -> 57838.412 | I45: =I7*I46 -> 95251.341 | J45: =J7*J46 -> 93476.348 | K45: =K7*K46 -> 63683.017 | L45: =L7*L46 -> 37282.084
B46: % of Revenue | C46: =C45/C7 -> 0.3923207 | D46: =D45/D7 -> 0.49395109 | E46: =E45/E7 -> 0.33395723 | F46: =F45/F7 -> 0.42423351 | G46: =G45/G7 -> 0.23059134 | H46: 0.25 | I46: 0.3 | J46: 0.25 | K46: 0.2 | L46: 0.17

Sheet FCF & Other
B1: Results
C2: History | H2: Forecast
C4: Income statement
B5: $ (thousand) | C5: =Revenue!C5 -> 2022 | D5: =Revenue!D5 -> 2023 | E5: =Revenue!E5 -> 2024 | F5: =Revenue!F5 -> 2025 | G5: =Revenue!G5 -> 2026 | H5: =G5+1 -> 2027 | I5: =H5+1 -> 2028 | J5: =I5+1 -> 2029 | K5: =J5+1 -> 2030 | L5: =K5+1 -> 2031
B6: Revenue | C6: =Revenue!C10 -> 30758 | D6: =Revenue!D10 -> 15540 | E6: =Revenue!E10 -> 25111 | F6: =Revenue!F10 -> 37378 | G6: =Revenue!G10 -> 133188 | H6: =Revenue!H10 -> 231353.65 | I6: =Revenue!I10 -> 317504.47 | J6: =Revenue!J10 -> 373905.39 | ... L6: =Revenue!L10 -> 219306.38 | N6: From Revenue Sheet
B7: COGS | C7: ='COGS & OpEx'!C15 -> 16860 | D7: ='COGS & OpEx'!D15 -> 16956 | E7: ='COGS & OpEx'!E15 -> 19498 | F7: ='COGS & OpEx'!F15 -> 22505 | G7: ='COGS & OpEx'!G15 -> 25684 | H7: ='COGS & OpEx'!H15 -> 37016.584 | I7: ='COGS & OpEx'!I15 -> 39688.059 | J7: ='COGS & OpEx'!J15 -> 46738.174 | ... L7: ='COGS & OpEx'!L15 -> 32895.957 | N7: From COGS and OpEx Sheet
B8: Gross profit | C8: =C6-C7 -> 13898 | D8: =D6-D7 -> -1416 | E8: =E6-E7 -> 5613 | F8: =F6-F7 -> 14873 | G8: =G6-G7 -> 107504 | H8: =H6-H7 -> 194337.07 | I8: =I6-I7 -> 277816.41 | J8: =J6-J7 -> 327167.22 | ... L8: =L6-L7 -> 186410.42
B9: OpEx | C9: ='COGS & OpEx'!C19 -> 4196 | D9: ='COGS & OpEx'!D19 -> 4329 | E9: ='COGS & OpEx'!E19 -> 4309 | F9: ='COGS & OpEx'!F19 -> 5103 | G9: ='COGS & OpEx'!G19 -> 8164 | H9: ='COGS & OpEx'!H19 -> 13337.158 | I9: ='COGS & OpEx'!I19 -> 19200.268 | J9: ='COGS & OpEx'!J19 -> 22584.324 | ... L9: ='COGS & OpEx'!L19 -> 13308.383 | N9: From COGS and OpEx Sheet
B10: EBIT | C10: =C8-C9 -> 9702 | D10: =D8-D9 -> -5745 | E10: =E8-E9 -> 1304 | F10: =F8-F9 -> 9770 | G10: =G8-G9 -> 99340 | H10: =H8-H9 -> 180999.91 | I10: =I8-I9 -> 258616.14 | J10: =J8-J9 -> 304582.9 | ... L10: =L8-L9 -> 173102.04
C13: Drivers
C14: =C5 -> 2022 | D14: =D5 -> 2023 | E14: =E5 -> 2024 | F14: =F5 -> 2025 | G14: =G5 -> 2026 | H14: =H5 -> 2027 | I14: =I5 -> 2028 | J14: =J5 -> 2029 | ... L14: =L5 -> 2031
B15: Tax rate | C15: =Statement!M83 -> 0.092780274 | D15: =Statement!N83 -> 0 | E15: =Statement!O83 -> 0.36370968 | F15: =Statement!P83 -> 0.11642842 | G15: =Statement!Q83 -> 0.14809724 | H15: =Overview!$C$26 -> 0.21 | I15: =Overview!$C$26 -> 0.21 | J15: =Overview!$C$26 -> 0.21 | K15: =Overview!$C$26 -> 0.21 | L15: =Overview!$C$26 -> 0.21 | N15: From Statements and Overview sheet
C18: Cash Flow Statement
B19: $ (thousand) | C19: =C5 -> 2022 | D19: =D5 -> 2023 | E19: =E5 -> 2024 | F19: =F5 -> 2025 | G19: =G5 -> 2026 | H19: =H5 -> 2027 | I19: =I5 -> 2028 | J19: =J5 -> 2029 | ... L19: =L5 -> 2031
B20: D&A | C20: ='WC & Investments'!C42 -> 7116 | D20: ='WC & Investments'!D42 -> 7756 | E20: ='WC & Investments'!E42 -> 7780 | F20: ='WC & Investments'!F42 -> 8352 | G20: ='WC & Investments'!G42 -> 9503 | H20: ='WC & Investments'!H42 -> 23135.365 | I20: ='WC & Investments'!I42 -> 28575.402 | J20: ='WC & Investments'!J42 -> 29912.431 | ... L20: ='WC & Investments'!L42 -> 32895.957 | N20: From WC & Investments Sheet
B21: CapEx | C21: ='WC & Investments'!C45 -> 12067 | D21: ='WC & Investments'!D45 -> 7676 | E21: ='WC & Investments'!E45 -> 8386 | F21: ='WC & Investments'!F45 -> 15857 | G21: ='WC & Investments'!G45 -> 30712 | H21: ='WC & Investments'!H45 -> 57838.412 | I21: ='WC & Investments'!I45 -> 95251.341 | J21: ='WC & Investments'!J45 -> 93476.348 | ... L21: ='WC & Investments'!L45 -> 37282.084 | N21: From WC & Investments Sheet
B22: Change in NWC | C22: ='WC & Investments'!C35 -> -1245 | D22: ='WC & Investments'!D35 -> -2892 | E22: ='WC & Investments'!E35 -> -884 | F22: ='WC & Investments'!F35 -> -338 | G22: ='WC & Investments'!G35 -> -5742 | H22: ='WC & Investments'!H35 -> -16316.889 | I22: ='WC & Investments'!I35 -> -13566.048 | J22: ='WC & Investments'!J35 -> -1530.992 | ... L22: ='WC & Investments'!L35 -> 24458.582 | N22: From WC & Investments Sheet
C25: FCFF
B26: $ (thousand) | C26: =C5 -> 2022 | D26: =D5 -> 2023 | E26: =E5 -> 2024 | F26: =F5 -> 2025 | G26: =G5 -> 2026 | H26: =H5 -> 2027 | I26: =I5 -> 2028 | J26: =J5 -> 2029 | ... L26: =L5 -> 2031
B27: NOPAT | C27: =C10*(1-C15) -> 8801.8458 | D27: =D10*(1-D15) -> -5745 | E27: =E10*(1-E15) -> 829.72258 | F27: =F10*(1-F15) -> 8632.4943 | G27: =G10*(1-G15) -> 84628.02 | H27: =H10*(1-H15) -> 142989.93 | I27: =I10*(1-I15) -> 204306.75 | J27: =J10*(1-J15) -> 240620.49 | ... L27: =L10*(1-L15) -> 136750.61
B28: FCFF | C28: =C27+C20-C21+C22 -> 2605.8458 | D28: =D27+D20-D21+D22 -> -8557 | E28: =E27+E20-E21+E22 -> -660.27742 | F28: =F27+F20-F21+F22 -> 789.4943 | G28: =G27+G20-G21+G22 -> 57677.02 | H28: =H27+H20-H21+H22 -> 91969.991 | I28: =I27+I20-I21+I22 -> 124064.77 | J28: =J27+J20-J21+J22 -> 175525.58 | ... L28: =L27+L20-L21+L22 -> 156823.07
C31: Margins
B32: % | C32: =C5 -> 2022 | D32: =D5 -> 2023 | E32: =E5 -> 2024 | F32: =F5 -> 2025 | G32: =G5 -> 2026 | H32: =H5 -> 2027 | I32: =I5 -> 2028 | J32: =J5 -> 2029 | ... L32: =L5 -> 2031
B33: Gross margin | C33: =Statement!M101 -> 0.45184993 | D33: =Statement!N101 -> -0.091119691 | E33: =Statement!O101 -> 0.22352754 | F33: =Statement!P101 -> 0.39790786 | G33: =Statement!Q101 -> 0.8071598 | H33: =H8/H6 -> 0.84 | I33: =I8/I6 -> 0.875 | J33: =J8/J6 -> 0.875 | K33: =K8/K6 -> 0.85 | L33: =L8/L6 -> 0.85
B34: Operating margin | C34: =Statement!M102 -> 0.31543013 | D34: =Statement!N102 -> -0.36969112 | E34: =Statement!O102 -> 0.051929433 | F34: =Statement!P102 -> 0.2613837 | G34: =Statement!Q102 -> 0.74586299 | H34: =H10/H6 -> 0.78235164 | I34: =I10/I6 -> 0.81452757 | J34: =J10/J6 -> 0.81459883 | K34: =K10/K6 -> 0.79952892 | L34: =L10/L6 -> 0.78931603

Sheet Valuation ->
H5: Links
H6: Overview'!B3
H7: Financials ->'!B13
H8: Analysis ->'!B13
H9: Forecast ->'!B13
H10: Valuation ->'!B13
B13: Valuation ->

Sheet WACC
B1: WACC
B4: Inputs
B5: Shares Outstanding | C5: =Statement!AC78 -> 1146
B6: Price | C6: =Overview!C5 -> 903.7
B7: Equity | C7: =C5*C6 -> 1035640.2
B8: Debt | C8: =Statement!AC108 -> 5179
B9: Risk free rate | C9: =Overview!F27 -> 0.04988
B10: Beta | C10: =Overview!C13 -> 2.3616
B11: Market risk premium | C11: =[1]Sheet1!$C$12 -> 0.045
B12: Tax rate | C12: =Overview!C26 -> 0.21
B13: Cost of debt | C13: =Overview!C27 -> 0.057
B15: Calculations
B16: Debt/(Debt+Equity) | C16: =C8/(C8+C7) -> 0.0049758882
B17: Equity/(Debt+Equity) | C17: =C7/(C8+C7) -> 0.99502411
B18: Cost of debt with tax | C18: =C13*(1-C12) -> 0.04503
B19: Cost of equity | C19: =C9+C10*C11 -> 0.156152
B20: WACC | C20: =(C17*C19)+(C16*C18) -> 0.15559907

Sheet DCF
B1: DCF
C3: History | H3: Forecast
C5: PV of FCF
B6: $ (thousand) | C6: =Revenue!C5 -> 2022 | D6: =Revenue!D5 -> 2023 | E6: =Revenue!E5 -> 2024 | F6: =Revenue!F5 -> 2025 | G6: =Revenue!G5 -> 2026 | H6: =Revenue!H5 -> 2027 | I6: =Revenue!I5 -> 2028 | J6: =Revenue!J5 -> 2029 | ... L6: =Revenue!L5 -> 2031
B7: FCFF | C7: ='FCF & Other'!C28 -> 2605.8458 | D7: ='FCF & Other'!D28 -> -8557 | E7: ='FCF & Other'!E28 -> -660.27742 | F7: ='FCF & Other'!F28 -> 789.4943 | G7: ='FCF & Other'!G28 -> 57677.02 | H7: ='FCF & Other'!H28 -> 91969.991 | I7: ='FCF & Other'!I28 -> 124064.77 | J7: ='FCF & Other'!J28 -> 175525.58 | ... L7: ='FCF & Other'!L28 -> 156823.07
B8: Perpetual cashflow | C8: 0 | D8: 0 | E8: 0 | F8: 0 | G8: 0 | H8: 0 | I8: 0 | J8: 0 | K8: 0 | L8: =L7*(1+C14)/(C15-C14) -> 1087859.3
B9: Period | H9: 1 | I9: 2 | J9: 3 | K9: 4 | L9: 5
B10: PV of FCFF | H10: =H7/(1+$C$15)^H9 -> 79586.418 | I10: =I7/(1+$C$15)^I9 -> 92903.932 | J10: =J7/(1+$C$15)^J9 -> 113741.48 | K10: =K7/(1+$C$15)^K9 -> 105772.03 | L10: =L7/(1+$C$15)^L9 -> 76098.136
B11: PV of Perpetual cashflow | L11: =L8/(1+C15)^L9 -> 527881.93
B13: Input parameters
B14: Perpetual growth | C14: 0.01
B15: WACC | C15: =IF(Overview!C28>0,Overview!C28,WACC!C20) -> 0.15559907
B18: Result
B19: Total PV of Unlevered FCF | C19: =SUM(H10:L10) -> 468101.99
B20: PV of Perpetual cashflow | C20: =L11 -> 527881.93
B21: Enterprise value | C21: =C19+C20 -> 995983.92
B22: (+) Cash | C22: =Statement!AC107 -> 73453
B23: (-) Debt | C23: =Statement!AC108 -> 5179
B24: Equity value | C24: =C21+C22-C23 -> 1064257.9
B25: Shares outstanding | C25: =Statement!AC78 -> 1146
B26: Price per share | C26: =C24/C25 -> 928.67184

Sheet Multiples
B1: Multiples valuations
C2: History | H2: Forecast
C4: Revenues, earnings cash
B5: Revenues (thousand) | C5: =Revenue!C5 -> 2022 | D5: =Revenue!D5 -> 2023 | E5: =Revenue!E5 -> 2024 | F5: =Revenue!F5 -> 2025 | G5: =Revenue!G5 -> 2026 | H5: =Revenue!H5 -> 2027 | I5: =Revenue!I5 -> 2028 | J5: =Revenue!J5 -> 2029 | ... L5: =Revenue!L5 -> 2031
B6: Revenue | C6: =Revenue!C10 -> 30758 | D6: =Revenue!D10 -> 15540 | E6: =Revenue!E10 -> 25111 | F6: =Revenue!F10 -> 37378 | G6: =Revenue!G10 -> 133188 | H6: =Revenue!H10 -> 231353.65 | I6: =Revenue!I10 -> 317504.47 | J6: =Revenue!J10 -> 373905.39 | ... L6: =Revenue!L10 -> 219306.38
B7: EBIT | C7: ='FCF & Other'!C10 -> 9702 | D7: ='FCF & Other'!D10 -> -5745 | E7: ='FCF & Other'!E10 -> 1304 | F7: ='FCF & Other'!F10 -> 9770 | G7: ='FCF & Other'!G10 -> 99340 | H7: ='FCF & Other'!H10 -> 180999.91 | I7: ='FCF & Other'!I10 -> 258616.14 | J7: ='FCF & Other'!J10 -> 304582.9 | ... L7: ='FCF & Other'!L10 -> 173102.04
B8: FCFF | C8: ='FCF & Other'!C28 -> 2605.8458 | D8: ='FCF & Other'!D28 -> -8557 | E8: ='FCF & Other'!E28 -> -660.27742 | F8: ='FCF & Other'!F28 -> 789.4943 | G8: ='FCF & Other'!G28 -> 57677.02 | H8: ='FCF & Other'!H28 -> 91969.991 | I8: ='FCF & Other'!I28 -> 124064.77 | J8: ='FCF & Other'!J28 -> 175525.58 | ... L8: ='FCF & Other'!L28 -> 156823.07
B9: PV of FCFF | H9: =DCF!H10 -> 79586.418 | I9: =DCF!I10 -> 92903.932 | J9: =DCF!J10 -> 113741.48 | K9: =DCF!K10 -> 105772.03 | L9: =DCF!L10 -> 76098.136
C11: Growth rates
B12: % Growth | C12: =C5 -> 2022 | D12: =D5 -> 2023 | E12: =E5 -> 2024 | F12: =F5 -> 2025 | G12: =G5 -> 2026 | H12: =H5 -> 2027 | I12: =I5 -> 2028 | J12: =J5 -> 2029 | ... L12: =L5 -> 2031
B13: Revenue | D13: =(D6-C6)/C6 -> -0.49476559 | E13: =(E6-D6)/D6 -> 0.61589447 | F13: =(F6-E6)/E6 -> 0.48851101 | G13: =(G6-F6)/F6 -> 2.5632725 | H13: =(H6-G6)/G6 -> 0.73704575 | I13: =(I6-H6)/H6 -> 0.37237718 | J13: =(J6-I6)/I6 -> 0.1776382 | K13: =(K6-J6)/J6 -> -0.14840735 | L13: =(L6-K6)/K6 -> -0.31125632
B14: EBIT | D14: =IF(C7=0, IF(D7=0,0,IF(D7>0,1,-1)), (D7-C7)/ABS(C7) ) -> -1.5921459 | E14: =IF(D7=0, IF(E7=0,0,IF(E7>0,1,-1)), (E7-D7)/ABS(D7) ) -> 1.22698 | F14: =IF(E7=0, IF(F7=0,0,IF(F7>0,1,-1)), (F7-E7)/ABS(E7) ) -> 6.4923313 | G14: =IF(F7=0, IF(G7=0,0,IF(G7>0,1,-1)), (G7-F7)/ABS(F7) ) -> 9.1678608 | H14: =IF(G7=0, IF(H7=0,0,IF(H7>0,1,-1)), (H7-G7)/ABS(G7) ) -> 0.82202444 | I14: =IF(H7=0, IF(I7=0,0,IF(I7>0,1,-1)), (I7-H7)/ABS(H7) ) -> 0.4288192 | J14: =IF(I7=0, IF(J7=0,0,IF(J7>0,1,-1)), (J7-I7)/ABS(I7) ) -> 0.17774123 | K14: =IF(J7=0, IF(K7=0,0,IF(K7>0,1,-1)), (K7-J7)/ABS(J7) ) -> -0.16416164 | L14: =IF(K7=0, IF(L7=0,0,IF(L7>0,1,-1)), (L7-K7)/ABS(K7) ) -> -0.32005408
B15: FCFF | D15: =IF(C8=0, IF(D8=0,0,IF(D8>0,1,-1)), (D8-C8)/ABS(C8) ) -> -4.2837707 | E15: =IF(D8=0, IF(E8=0,0,IF(E8>0,1,-1)), (E8-D8)/ABS(D8) ) -> 0.92283774 | F15: =IF(E8=0, IF(F8=0,0,IF(F8>0,1,-1)), (F8-E8)/ABS(E8) ) -> 2.1957009 | G15: =IF(F8=0, IF(G8=0,0,IF(G8>0,1,-1)), (G8-F8)/ABS(F8) ) -> 72.055651 | H15: =IF(G8=0, IF(H8=0,0,IF(H8>0,1,-1)), (H8-G8)/ABS(G8) ) -> 0.59456904 | I15: =IF(H8=0, IF(I8=0,0,IF(I8>0,1,-1)), (I8-H8)/ABS(H8) ) -> 0.34897008 | J15: =IF(I8=0, IF(J8=0,0,IF(J8>0,1,-1)), (J8-I8)/ABS(I8) ) -> 0.4147899 | K15: =IF(J8=0, IF(K8=0,0,IF(K8>0,1,-1)), (K8-J8)/ABS(J8) ) -> 0.074630512 | L15: =IF(K8=0, IF(L8=0,0,IF(L8>0,1,-1)), (L8-K8)/ABS(K8) ) -> -0.16859935
C17: Shares
C18: =C5 -> 2022 | D18: =D5 -> 2023 | E18: =E5 -> 2024 | F18: =F5 -> 2025 | G18: =G5 -> 2026 | H18: =H5 -> 2027 | I18: =I5 -> 2028 | J18: =J5 -> 2029 | ... L18: =L5 -> 2031
B19: Avg diluted shares | C19: =Statement!M22 -> 1122 | D19: =Statement!N22 -> 1093 | E19: =Statement!O22 -> 1118 | F19: =Statement!P22 -> 1125 | G19: =Statement!Q22 -> 1143 | H19: =G19*(1+H20) -> 1133.856 | I19: =H19*(1+I20) -> 1128.1867 | J19: =I19*(1+J20) -> 1122.5458 | K19: =J19*(1+K20) -> 1122.5458 | L19: =K19*(1+L20) -> 1122.5458
B20: Dilution rate | D20: =D19/C19-1 -> -0.025846702 | E20: =E19/D19-1 -> 0.022872827 | F20: =F19/E19-1 -> 0.0062611807 | G20: =G19/F19-1 -> 0.016 | H20: -0.008 | I20: -0.005 | J20: -0.005 | K20: 0 | L20: 0
C22: Historical price
C23: =C5 -> 2022 | D23: =D5 -> 2023 | E23: =E5 -> 2024 | F23: =F5 -> 2025 | G23: =G5 -> 2026 | H23: =H5 -> 2027 | I23: =I5 -> 2028 | J23: =J5 -> 2029 | ... L23: =L5 -> 2031
B24: Price | C24: =Statement!M116 -> 57.31 | D24: =Statement!N116 -> 68.09 | E24: =Statement!O116 -> 95.57 | F24: =Statement!P116 -> 122 | G24: =Statement!Q116 -> 958.16
C27: Historical ratios
C28: =C5 -> 2022 | D28: =D5 -> 2023 | E28: =E5 -> 2024 | F28: =F5 -> 2025 | G28: =G5 -> 2026 | H28: =H5 -> 2027 | I28: =I5 -> 2028 | J28: =J5 -> 2029 | ... L28: =L5 -> 2031
B29: PS | C29: =C24/(C6/C19) -> 2.0905722 | D29: =D24/(D6/D19) -> 4.7890843 | E29: =E24/(E6/E19) -> 4.2549982 | F29: =F24/(F6/F19) -> 3.6719461 | G29: =G24/(G6/G19) -> 8.2227894
B30: Market Cap | C30: =C24*C19 -> 64301.82 | D30: =D24*D19 -> 74422.37 | E30: =E24*E19 -> 106847.26 | F30: =F24*F19 -> 137250 | G30: =G24*G19 -> 1095176.9
B31: Debt | C31: =Statement!M108 -> 6906 | D31: =Statement!N108 -> 13330 | E31: =Statement!O108 -> 13397 | F31: =Statement!P108 -> 14577 | G31: =Statement!Q108 -> 5179
B32: Cash | C32: =Statement!M107 -> 10978 | D32: =Statement!N107 -> 10438 | E32: =Statement!O107 -> 9152 | F32: =Statement!P107 -> 11936 | G32: =Statement!Q107 -> 73453
B33: EV | C33: =C30+C31-C32 -> 60229.82 | D33: =D30+D31-D32 -> 77314.37 | E33: =E30+E31-E32 -> 111092.26 | F33: =F30+F31-F32 -> 139891 | G33: =G30+G31-G32 -> 1026902.9
B34: EV/EBIT | C34: =C33/C7 -> 6.2079798 | D34: =D33/D7 -> -13.45768 | E34: =E33/E7 -> 85.193451 | F34: =F33/F7 -> 14.318424 | G34: =G33/G7 -> 10.337255
B35: EV/FCFF | C35: =C33/C8 -> 23.113348 | D35: =D33/D8 -> -9.0352191 | E35: =E33/E8 -> -168.25088 | F35: =F33/F8 -> 177.19064 | G35: =G33/G8 -> 17.804368
B36: EV/Sales | C36: =C33/C6 -> 1.9581839 | D36: =D33/D6 -> 4.9751847 | E36: =E33/E6 -> 4.4240476 | F36: =F33/F6 -> 3.7426026 | G36: =G33/G6 -> 7.7101757
B39: EV/EBIT valuation
B40: Year 5 EBIT | C40: =L7 -> 173102.04
B41: WACC | C41: =IF(Overview!C28>0,Overview!C28,WACC!C20) -> 0.15559907
B42: Applied EV/EBIT ratio | C42: 12
B43: Terminal EV | C43: =(C40*C42) -> 2077224.5
B44: PV of Terminal EV | C44: =C43/(1+C41)^5 -> 1007969.8
B45: Total EV | C45: =SUM(H9:K9)+C44 -> 1399973.6
B46: (+) Cash | C46: =Statement!AC107 -> 73453
B47: (-) Debt | C47: =Statement!AC108 -> 5179
B48: Equity value | C48: =C45+C46-C47 -> 1468247.6
B49: Shares outstanding | C49: =Statement!AC78 -> 1146
B50: PV of price per share | C50: =C48/C49 -> 1281.1934
B52: PS valuation
B53: Year 5 sales | C53: =L6 -> 219306.38
B54: Discount rate | C54: =IF(Overview!C29>0,Overview!C29,WACC!C19) -> 0.156152
B55: Applied PS ratio | C55: 6
B56: Shares outstanding diluted | C56: =L19 -> 1122.5458
B57: Price per share | C57: =(C53*C55)/C56 -> 1172.1912
B58: PV of price per share | C58: =C57/(1+C54)^5 -> 567.445
B60: EV/FCFF valuation
B61: Year 5 FCFF | C61: =L8 -> 156823.07
B62: WACC | C62: =IF(Overview!C28>0,Overview!C28,WACC!C20) -> 0.15559907
B63: Applied EV/FCFF ratio | C63: 20
B64: Terminal EV | C64: =(C61*C63) -> 3136461.3
B65: PV of Terminal EV | C65: =C64/(1+C62)^5 -> 1521962.7
B66: Total EV | C66: =SUM(H9:K9)+C65 -> 1913966.6
B67: (+) Cash | C67: =Statement!AC107 -> 73453
B68: (-) Debt | C68: =Statement!AC108 -> 5179
B69: Equity value | C69: =C66+C67-C68 -> 1982240.6
B70: Shares outstanding | C70: =Statement!AC78 -> 1146
B71: PV of price per share | C71: =C69/C70 -> 1729.7038
B73: EV/Sales valuation
B74: Year 5 Sales | C74: =L6 -> 219306.38
B75: WACC | C75: =IF(Overview!C28>0,Overview!C28,WACC!C20) -> 0.15559907
B76: Applied EV/Sales ratio | C76: 5.5
B77: Terminal EV | C77: =(C74*C76) -> 1206185.1
B78: PV of Terminal EV | C78: =C77/(1+C75)^5 -> 585299.34
B79: Total EV | C79: =SUM(H9:K9)+C78 -> 977303.2
B80: (+) Cash | C80: =Statement!AC107 -> 73453
B81: (-) Debt | C81: =Statement!AC108 -> 5179
B82: Equity value | C82: =C79+C80-C81 -> 1045577.2
B83: Shares outstanding | C83: =Statement!AC78 -> 1146
B84: PV of price per share | C84: =C82/C83 -> 912.37103

Sheet AVG target price
B1: AVG target price
B4: AVG target price
B5: DCF price | C5: =DCF!C26 -> 928.67184
B6: EV/EBIT price | C6: =Multiples!C50 -> 1281.1934
B7: PS price | C7: =Multiples!C58 -> 567.445
B8: EV/FCFF price | C8: =Multiples!C71 -> 1729.7038
B9: EV/Sales price | C9: =Multiples!C84 -> 912.37103
B10: AVG price | C10: =AVERAGE(C5:C9) -> 1083.877
B11: Current price | C11: =Overview!C5 -> 903.7
B12: Upside/Downside | C12: =(C10-C11)/C11 -> 0.19937703

Sheet DDM
B1: Dividend discount model
C2: History | H2: Forecast
C4: Revenues, earnings cash
B5: Revenues (thousand) | C5: =[2]Revenue!C5 -> 2021 | D5: =[2]Revenue!D5 -> 2022 | E5: =[2]Revenue!E5 -> 2023 | F5: =[2]Revenue!F5 -> 2024 | G5: =[2]Revenue!G5 -> 2025 | H5: =[2]Revenue!H5 -> 2026 | I5: =[2]Revenue!I5 -> 2027 | J5: =[2]Revenue!J5 -> 2028 | ... L5: =[2]Revenue!L5 -> 2030
B6: EPS | C6: =Statement!M26 -> 7.75 | D6: =Statement!N26 -> -5.34 | E6: =Statement!O26 -> 0.7 | F6: =Statement!P26 -> 7.59 | G6: =Statement!Q26 -> 74.33
B7: Dividend per share | C7: =Statement!M82 -> 0.315 | D7: =Statement!N82 -> 0.46 | E7: =Statement!O82 -> 0.46 | F7: =Statement!P82 -> 0.46 | G7: =Statement!Q82 -> 0.57
C9: Growth rates
B10: % Growth | C10: =C5 -> 2021 | D10: =D5 -> 2022 | E10: =E5 -> 2023 | F10: =F5 -> 2024 | G10: =G5 -> 2025 | H10: =H5 -> 2026 | I10: =I5 -> 2027 | J10: =J5 -> 2028 | ... L10: =L5 -> 2030
B11: EPS | D11: =(D6-C6)/C6 -> -1.6890323 | E11: =(E6-D6)/D6 -> -1.1310861 | F11: =(F6-E6)/E6 -> 9.8428571 | G11: =(G6-F6)/F6 -> 8.7931489
B12: Dividend | D12: =IF(C7=0, IF(D7=0,0,IF(D7>0,1,-1)), (D7-C7)/ABS(C7) ) -> 0.46031746 | E12: =IF(D7=0, IF(E7=0,0,IF(E7>0,1,-1)), (E7-D7)/ABS(D7) ) -> 0 | F12: =IF(E7=0, IF(F7=0,0,IF(F7>0,1,-1)), (F7-E7)/ABS(E7) ) -> 0 | G12: =IF(F7=0, IF(G7=0,0,IF(G7>0,1,-1)), (G7-F7)/ABS(F7) ) -> 0.23913043
C14: Ratios
B15: % | C15: =C5 -> 2021 | D15: =D5 -> 2022 | E15: =E5 -> 2023 | F15: =F5 -> 2024 | G15: =G5 -> 2025 | H15: =H5 -> 2026 | I15: =I5 -> 2027 | J15: =J5 -> 2028 | ... L15: =L5 -> 2030
B16: Payout | C16: =C7/C6 -> 0.040645161 | D16: =D7/D6 -> -0.086142322 | E16: =E7/E6 -> 0.65714286 | F16: =F7/F6 -> 0.060606061 | G16: =G7/G6 -> 0.0076685053
B20: DDM valuation
B21: Latest dividend | C21: =G7 -> 0.57
B22: Year 1 growth rate | C22: 0.15
B23: Year 1 dividend | C23: =C21*(1+C22) -> 0.6555
B24: Discount rate | C24: =IF(Overview!C29>0,Overview!C29,WACC!C19) -> 0.156152
B25: Perpetual dividend growth | C25: 0.03
B26: PV of price per share | C26: =C23/(C24-C25) -> 5.1961126

Sheet Reverse DCF
B1: Reverse DCF
C3: History | H3: Forecast
C5: PV of FCF
B6: $ (thousand) | C6: =Revenue!C5 -> 2022 | D6: =Revenue!D5 -> 2023 | E6: =Revenue!E5 -> 2024 | F6: =Revenue!F5 -> 2025 | G6: =Revenue!G5 -> 2026 | H6: =Revenue!H5 -> 2027 | I6: =Revenue!I5 -> 2028 | J6: =Revenue!J5 -> 2029 | ... L6: =Revenue!L5 -> 2031
B7: FCFF | C7: ='FCF & Other'!C28 -> 2605.8458 | D7: ='FCF & Other'!D28 -> -8557 | E7: ='FCF & Other'!E28 -> -660.27742 | F7: ='FCF & Other'!F28 -> 789.4943 | G7: ='FCF & Other'!G28 -> 57677.02 | H7: =G7*(1+$C$17) -> 71519.505 | I7: =H7*(1+$C$17) -> 88684.186 | J7: =I7*(1+$C$17) -> 109968.39 | K7: =J7*(1+$C$17) -> 136360.8 | L7: =K7*(1+$C$17) -> 169087.4
B8: Perpetual cashflow | L8: =L7*(1+C20)/(C21-C20) -> 1172935.2
B9: Period | H9: 1 | I9: 2 | J9: 3 | K9: 4 | L9: 5
B10: PV of FCFF | H10: =H7/(1+$C$21)^H9 -> 61889.549 | I10: =I7/(1+$C$21)^I9 -> 66409.746 | J10: =J7/(1+$C$21)^J9 -> 71260.082 | K10: =K7/(1+$C$21)^K9 -> 76464.671 | L10: =L7/(1+$C$21)^L9 -> 82049.384
B11: PV of Perpetual cashflow | L11: =L8/(1+C21)^L9 -> 569164.89
B14: Growth adjustment
B15: Current Price | C15: =Overview!C5 -> 903.7
B16: Calculated Price | C16: =C36 -> 881.76467
B17: FCFF Growth | C17: 0.24 | E17: Modify until Calculated Price is very close to Current Price
B19: Input parameters
B20: Perpetual growth | C20: 0.01
B21: WACC | C21: =IF(Overview!C28>0,Overview!C28,WACC!C20) -> 0.15559907
B22: Shares outstanding | C22: =Statement!AC75 -> 1129
B23: Market cap | C23: =C15*C22 -> 1020277.3
B24: Cash | C24: =Statement!AC107 -> 73453
B25: Debt | C25: =Statement!AC108 -> 5179
B26: Enterprise Value | C26: =C23+C25-C24 -> 952003.3
B28: Result
B29: Total PV of Unlevered FCF | C29: =SUM(H10:L10) -> 358073.43
B30: PV of Perpetual cashflow | C30: =L11 -> 569164.89
B31: Enterprise value | C31: =C29+C30 -> 927238.32
B32: (+) Cash | C32: =C24 -> 73453
B33: (-) Debt | C33: =C25 -> 5179
B34: Equity value | C34: =C31+C32-C33 -> 995512.32
B35: Shares outstanding | C35: =C22 -> 1129
B36: Price per share | C36: =C34/C35 -> 881.76467
