Workbook

Sheet Overview
B2: Automatic Data | E2: At a glance | H2: Valuation | K2: Links
B3: Company | C3: #VALUE! | E3: Market capitalization | F3: =Statement!AC155 -> 5104177.2 | H3: ='AVG target price'!B5 -> DCF price | I3: ='AVG target price'!C5 -> 205.87576 | K3: Financials ->'!B13
B4: Ticker | C4: {=_FV(C3,"Ticker symbol",TRUE)} -> NVDA | E4: Enterprise value | F4: =Statement!AC156 -> 5038074.2 | H4: ='AVG target price'!B6 -> EV/EBIT price | I4: ='AVG target price'!C6 -> 439.1811 | K4: Analysis ->'!B13
B5: Price | C5: {=_FV(C3,"Price",TRUE)} -> 210.96 | E5: EPS | F5: =Statement!AC25 -> 7.91 | H5: ='AVG target price'!B7 -> PS price | I5: ='AVG target price'!C7 -> 372.92429 | K5: Forecast ->'!B13
B6: Price Extended Hours | C6: {=_FV(C3,"Price (Extended hours)",TRUE)} -> 211.1155 | E6: PE | F6: =Statement!AC152 -> 26.670038 | H6: ='AVG target price'!B8 -> EV/FCFF price | I6: ='AVG target price'!C8 -> 456.30962 | K6: Valuation ->'!B13
B7: Day change | C7: {=_FV(C3,"Change")} -> -1.25 | E7: PS | F7: =Statement!AC153 -> 16.98837 | H7: ='AVG target price'!B9 -> EV/Sales price | I7: ='AVG target price'!C9 -> 404.87388
B8: Day change extended | C8: {=_FV(C3,"Change (extended hours)",TRUE)} -> 0.1555 | E8: FCF Yield | F8: =Statement!AC163 -> 0.023463919 | H8: ='AVG target price'!B10 -> AVG price | I8: ='AVG target price'!C10 -> 375.83293
B9: Day change % | C9: {=_FV(C3,"Change (%)",TRUE)} -> -0.00589 | E9: Earnings Yield | F9: =Statement!AC164 -> 0.03749526 | H9: ='AVG target price'!B12 -> Upside/Downside | I9: ='AVG target price'!C12 -> 0.78153645
B10: Day change extended % | C10: {=_FV(C3,"Change % (extended hours)",TRUE)} -> 0.0007371 | E10: Buyback Yield | F10: =Statement!AC166 -> 0.010837202
B11: 52 week high | C11: {=_FV(C3,"52 week high",TRUE)} -> 243.37 | E11: Dividend Yield | F11: =Statement!AC165 -> 0.0013272658 | H11: DDM price | I11: =DDM!C26 -> 1.6842105
B12: 52 week low | C12: {=_FV(C3,"52 week low",TRUE)} -> 164.27 | E12: ROA | F12: =Statement!AC121 -> 0.60223498
B13: Beta | C13: {=_FV(C3,"Beta")} -> 2.1957 | E13: ROE | F13: =Statement!AC123 -> 0.84232523 | H13: Reverse DCF rate | I13: ='Reverse DCF'!C17 -> 0.5
B14: Avg volume | C14: {=_FV(C3,"Volume average",TRUE)} -> 107148374 | E14: ROIC | F14: =Statement!AC142 -> 1.0183874 | H14: Reverse DCF price | I14: ='Reverse DCF'!C16 -> 228.84689
E15: Net Cash/Market Cap | F15: =Statement!AC178 -> 0.012950765
E16: Net Cash/Share | F16: =Statement!AC177 -> 2.7428631 | H16: Discount rates used
B17: Unit data and other info | E17: Insider Ownership | F17: =Statement!AC173 -> 0.039553627 | H17: WACC | I17: =DCF!C15 -> 0.12
B18: Units | C18: M | E18: Net Trade Cycle | F18: =Statement!AC146 -> 154.5376 | H18: Cost of Equity | I18: =Multiples!C54 -> 0.12
B19: Units conversion | C19: 1000000 | E19: Net Debt/Equity | F19: =Statement!AC148 -> -0.28867956
B20: Has operating lease | C20: Yes | E20: Quick Ratio | F20: =Statement!AC149 -> 3.775727
B21: Has finance lease | C21: No
B22: Has debt | C22: Yes
B25: Constants | E25: 10 Year Bond Yield
B26: Default tax rate | C26: 0.21 | E26: #VALUE! | F26: {=_FV(E26,"Price")} -> 49.53
B27: Cost of debt | C27: 0.05 | E27: Percentage | F27: =F26/1000 -> 0.04953
B28: Manual WACC | C28: 0.12
B29: Manual Cost of Equity | C29: 0.12
B33: Info
B35: Mission: | C35: Pioneered accelerated computing to help solve the most challanging computational problems
B36: Auditor: | C36: PwC
B42: Notes
B44: Date: | C44: 21.08.2026 | E44: Q2 2027
B45: - | C45: Revenue expected to grow by 70% in FY 2028
B46: - | C46: CapEx by top 5 hyperscalers expected to reach $800B in 2026 and $1.3T in 2027
B47: - | C47: Gross margins will bottom in Q4 2027 to 71%-72% and will settle at 72%-73 in FY 2028
B48: - | C48: Opex for the full year expected to be in the low 50s
B54: Adjustments
B56: Date: | C56: 21.08.2026 | E56: Q2 2027

Sheet Financials ->
H5: Links
H6: Overview'!B3
H7: Financials ->'!B13
H8: Analysis ->'!B13
H9: Forecast ->'!B13
H10: Valuation ->'!B13
B13: Financials ->

Sheet Statement
B2: Date | M2: 30.01.2022 | N2: 29.01.2023 | O2: 28.01.2024 | P2: 26.01.2025 | Q2: 25.01.2026 | T2: 27.10.2024 | U2: 26.01.2025 | V2: 27.04.2025 | W2: 27.07.2025 | X2: 26.10.2025 | Y2: 25.01.2026 | Z2: 26.04.2026 | AA2: 26.07.2026
B3: FY | M3: 2022 | N3: 2023 | O3: 2024 | P3: 2025 | Q3: 2026 | T3: Q3 2025 | U3: Q4 2025 | V3: Q1 2026 | W3: Q2 2026 | X3: Q3 2026 | Y3: Q4 2026 | Z3: Q1 2027 | AA3: Q2 2027 | AC3: TTM/YTD
B4: Income statement
B5: Revenue | M5: 26914 | N5: 26974 | O5: 60922 | P5: 130497 | Q5: 215938 | T5: 35082 | U5: 39331 | V5: 44062 | W5: 46743 | X5: 57006 | Y5: 68127 | Z5: 81615 | AA5: 96221 | AC5: =SUM(X5:AA5) -> 302969
B6: COGS | M6: 9439 | N6: 11618 | O6: 16621 | P6: 32639 | Q6: 62475 | T6: 8926 | U6: 10608 | V6: 17394 | W6: 12890 | X6: 15157 | Y6: 17034 | Z6: 20458 | AA6: 24079 | AC6: =SUM(X6:AA6) -> 76728
B7: Gross Profit | C7: =C5-C6 -> 0 | D7: =D5-D6 -> 0 | E7: =E5-E6 -> 0 | F7: =F5-F6 -> 0 | G7: =G5-G6 -> 0 | H7: =H5-H6 -> 0 | I7: =I5-I6 -> 0 | J7: =J5-J6 -> 0 | ... Q7: =Q5-Q6 -> 153463 | T7: =T5-T6 -> 26156 | U7: =U5-U6 -> 28723 | V7: =V5-V6 -> 26668 | W7: =W5-W6 -> 33853 | X7: =X5-X6 -> 41849 | Y7: =Y5-Y6 -> 51093 | Z7: =Z5-Z6 -> 61157 | AA7: =AA5-AA6 -> 72142 | AC7: =SUM(X7:AA7) -> 226241
B8: R&D | M8: 5268 | N8: 7339 | O8: 8675 | P8: 12914 | Q8: 18497 | T8: 3390 | U8: 3714 | V8: 3989 | W8: 4291 | X8: 4705 | Y8: 5512 | Z8: 6321 | AA8: 7054 | AC8: =SUM(X8:AA8) -> 23592
B9: SG&A | M9: 2166 | N9: 2440 | O9: 2654 | P9: 3491 | Q9: 4579 | T9: 897 | U9: 975 | V9: 1041 | W9: 1122 | X9: 1134 | Y9: 1282 | Z9: 1300 | AA9: 1354 | AC9: =SUM(X9:AA9) -> 5070
B10: OpEx | C10: =SUM(C8:C9) -> 0 | D10: =SUM(D8:D9) -> 0 | E10: =SUM(E8:E9) -> 0 | F10: =SUM(F8:F9) -> 0 | G10: =SUM(G8:G9) -> 0 | H10: =SUM(H8:H9) -> 0 | I10: =SUM(I8:I9) -> 0 | J10: =SUM(J8:J9) -> 0 | ... M10: =SUM(M8:M9) -> 7434 | N10: =SUM(N8:N9)+1353 -> 11132 | O10: =SUM(O8:O9) -> 11329 | P10: =SUM(P8:P9) -> 16405 | Q10: =SUM(Q8:Q9) -> 23076 | T10: =SUM(T8:T9) -> 4287 | U10: =SUM(U8:U9) -> 4689 | V10: =SUM(V8:V9) -> 5030 | W10: =SUM(W8:W9) -> 5413 | X10: =SUM(X8:X9) -> 5839 | Y10: =SUM(Y8:Y9) -> 6794 | Z10: =SUM(Z8:Z9) -> 7621 | AA10: =SUM(AA8:AA9) -> 8408 | AC10: =SUM(X10:AA10) -> 28662
B11: Operating income | M11: 10041 | N11: 4224 | O11: 32972 | P11: 81453 | Q11: 130387 | T11: 21869 | U11: 24034 | V11: 21638 | W11: 28440 | X11: 36010 | Y11: 44299 | Z11: 53536 | AA11: 63734 | AC11: =SUM(X11:AA11) -> 197579
B12: Interest income/expense | M12: =29-236 -> -207 | N12: 5 | O12: =866-257 -> 609 | P12: =1786-247 -> 1539 | Q12: =2300-259 -> 2041 | T12: =472-61 -> 411 | U12: =511-61 -> 450 | V12: =515-63 -> 452 | W12: =592-62 -> 530 | X12: =624-61 -> 563 | Y12: =568-74 -> 494 | Z12: =540-102 -> 438 | AA12: 0 | AC12: =SUM(X12:AA12) -> 1495
B13: Other income/expense | M13: 107 | N13: -48 | O13: 237 | P13: 1034 | Q13: 9022 | T13: 36 | U13: 733 | V13: -180 | W13: 2236 | X13: 1363 | Y13: 5604 | Z13: 15939 | AA13: 7773 | AC13: =SUM(X13:AA13) -> 30679
B14: Income before taxes | M14: 9941 | N14: 4181 | O14: 33818 | P14: 84026 | Q14: 141450 | T14: 22316 | U14: 25217 | V14: 21910 | W14: 31206 | X14: 37936 | Y14: 50397 | Z14: 69903 | AA14: 71507 | AC14: =SUM(X14:AA14) -> 229743
B15: Income tax expense/benefit | M15: -189 | N15: 187 | O15: -4058 | P15: -11146 | Q15: -21383 | T15: -3007 | U15: -3126 | V15: -3135 | W15: -4784 | X15: -6026 | Y15: -7437 | Z15: -11582 | AA15: -11819 | AC15: =SUM(X15:AA15) -> -36864
B16: Non-controlling interest | M16: 0 | N16: 0 | O16: 0 | P16: 0 | Q16: 0 | T16: 0 | U16: 0 | V16: 0 | W16: 0 | X16: 0 | Y16: 0 | Z16: 0 | AA16: 0 | AC16: =SUM(X16:AA16) -> 0
B17: Net income | M17: 9752 | N17: 4368 | O17: 29760 | P17: 72880 | Q17: 120067 | T17: 19309 | U17: 22091 | V17: 18775 | W17: 26422 | X17: 31910 | Y17: 42960 | Z17: 58321 | AA17: 59688 | AC17: =SUM(X17:AA17) -> 192879
B18: Basic Shares outstanding avg | M18: 2496 | N18: 2487 | O18: 2469 | P18: 24555 | Q18: 24359 | T18: 24533 | U18: 24489 | V18: 24441 | W18: 24366 | X18: 24327 | Y18: 24304 | Z18: 24286 | AA18: 24190 | AC18: =AVERAGE(X18:AA18) -> 24276.75
B19: Basic Shares outstanding avg adjusted | C19: =C18*C$84 -> 0 | D19: =D18*D$84 -> 0 | E19: =E18*E$84 -> 0 | F19: =F18*F$84 -> 0 | G19: =G18*G$84 -> 0 | H19: =H18*H$84 -> 0 | I19: =I18*I$84 -> 0 | J19: =J18*J$84 -> 0 | ... Q19: =Q18*Q$84 -> 24359 | T19: =T18*T$84 -> 24533 | U19: =U18*U$84 -> 24489 | V19: =V18*V$84 -> 24441 | W19: =W18*W$84 -> 24366 | X19: =X18*X$84 -> 24327 | Y19: =Y18*Y$84 -> 24304 | Z19: =Z18*Z$84 -> 24286 | AA19: =AA18*AA$84 -> 24190 | AC19: =AC18*AC$84 -> 24276.75
B20: Diluted Shares outstanding avg | M20: 2535 | N20: 2507 | O20: 2494 | P20: 24804 | Q20: 24514 | T20: 24774 | U20: 24706 | V20: 24611 | W20: 24532 | X20: 24483 | Y20: 24432 | Z20: 24391 | AA20: 24285 | AC20: =AVERAGE(X20:AA20) -> 24397.75
B21: Diluted Shares outstanding avg adjusted | C21: =C20*C$84 -> 0 | D21: =D20*D$84 -> 0 | E21: =E20*E$84 -> 0 | F21: =F20*F$84 -> 0 | G21: =G20*G$84 -> 0 | H21: =H20*H$84 -> 0 | I21: =I20*I$84 -> 0 | J21: =J20*J$84 -> 0 | ... Q21: =Q20*Q$84 -> 24514 | T21: =T20*T$84 -> 24774 | U21: =U20*U$84 -> 24706 | V21: =V20*V$84 -> 24611 | W21: =W20*W$84 -> 24532 | X21: =X20*X$84 -> 24483 | Y21: =Y20*Y$84 -> 24432 | Z21: =Z20*Z$84 -> 24391 | AA21: =AA20*AA$84 -> 24285 | AC21: =AC20*AC$84 -> 24397.75
B22: Basic EPS | M22: 3.91 | N22: 1.76 | O22: 12.05 | P22: 2.97 | Q22: 4.93 | T22: 0.79 | U22: 0.9 | V22: 0.77 | W22: 1.08 | X22: 1.31 | Y22: 1.77 | Z22: 2.4 | AA22: 2.47 | AC22: =SUM(X22:AA22) -> 7.95
B23: Basic EPS adjusted | M23: =M22/M$84 -> 0.391 | N23: =N22/N$84 -> 0.176 | O23: =O22/O$84 -> 1.205 | P23: =P22/P$84 -> 2.97 | Q23: =Q22/Q$84 -> 4.93 | T23: =T22/T$84 -> 0.79 | U23: =U22/U$84 -> 0.9 | V23: =V22/V$84 -> 0.77 | W23: =W22/W$84 -> 1.08 | X23: =X22/X$84 -> 1.31 | Y23: =Y22/Y$84 -> 1.77 | Z23: =Z22/Z$84 -> 2.4 | AA23: =AA22/AA$84 -> 2.47 | AC23: =AC22/AC$84 -> 7.95
B24: Diluted EPS | M24: 3.85 | N24: 1.74 | O24: 11.93 | P24: 2.94 | Q24: 4.9 | T24: 0.78 | U24: 0.89 | V24: 0.76 | W24: 1.08 | X24: 1.3 | Y24: 1.76 | Z24: 2.39 | AA24: 2.46 | AC24: =SUM(X24:AA24) -> 7.91
B25: Diluted EPS adjusted | M25: =M24/M$84 -> 0.385 | N25: =N24/N$84 -> 0.174 | O25: =O24/O$84 -> 1.193 | P25: =P24/P$84 -> 2.94 | Q25: =Q24/Q$84 -> 4.9 | T25: =T24/T$84 -> 0.78 | U25: =U24/U$84 -> 0.89 | V25: =V24/V$84 -> 0.76 | W25: =W24/W$84 -> 1.08 | X25: =X24/X$84 -> 1.3 | Y25: =Y24/Y$84 -> 1.76 | Z25: =Z24/Z$84 -> 2.39 | AA25: =AA24/AA$84 -> 2.46 | AC25: =AC24/AC$84 -> 7.91
B27: Balance sheet
B28: Cash and cash equivalents | M28: =1990+19218 -> 21208 | N28: =3389+9907 -> 13296 | O28: =7280+18704 -> 25984 | P28: =8589+34621 -> 43210 | Q28: =10605+51951 -> 62556 | T28: =9107+29380 -> 38487 | U28: =8589+34621 -> 43210 | V28: =15234+38457 -> 53691 | W28: =11639+45152 -> 56791 | X28: =11486+49122 -> 60608 | Y28: =10605+39065+12886 -> 62556 | Z28: =13237+37098+30237 -> 80572 | AA28: =22443+34143+42783 -> 99369 | AC28: =AA28 -> 99369
B29: Acc receivable | M29: 4650 | N29: 3827 | O29: 9999 | P29: 23065 | Q29: 38466 | T29: 17693 | U29: 23065 | V29: 22132 | W29: 27808 | X29: 33391 | Y29: 38466 | Z29: 40710 | AA29: 63059 | AC29: =AA29 -> 63059
B30: Inventory | M30: 2605 | N30: 5159 | O30: 5282 | P30: 10080 | Q30: 21403 | T30: 7654 | U30: 10080 | V30: 11333 | W30: 14962 | X30: 19784 | Y30: 21403 | Z30: 25797 | AA30: 31575 | AC30: =AA30 -> 31575
B31: Current assets | M31: 28829 | N31: 23073 | O31: 44345 | P31: 80126 | Q31: 125605 | T31: 67640 | U31: 80126 | V31: 89935 | W31: 102219 | X31: 116492 | Y31: 125605 | Z31: 150995 | AA31: 197412 | AC31: =AA31 -> 197412
B32: PP&E | M32: 2778 | N32: 3807 | O32: 3914 | P32: 6283 | Q32: 10383 | T32: 5343 | U32: 6283 | V32: 7136 | W32: 9141 | X32: 9780 | Y32: 10383 | Z32: 12403 | AA32: 14285 | AC32: =AA32 -> 14285
B33: Marketable securities and investments | M33: 0 | N33: 0 | O33: 0 | P33: 0 | Q33: 0 | T33: 0 | U33: 0 | V33: 0 | W33: 0 | X33: 0 | Y33: 0 | Z33: 0 | AA33: 0 | AC33: =AA33 -> 0
B34: Goodwill | M34: 4349 | N34: 4372 | O34: 4430 | P34: 5188 | Q34: 20832 | T34: 4724 | U34: 5188 | V34: 5498 | W34: 5755 | X34: 6261 | Y34: 20832 | Z34: 20894 | AA34: 21125 | AC34: =AA34 -> 21125
B35: Long term assets | M35: =M36-M31 -> 15358 | N35: =N36-N31 -> 18109 | O35: =O36-O31 -> 21383 | P35: =P36-P31 -> 31475 | Q35: =Q36-Q31 -> 81198 | T35: =T36-T31 -> 28373 | U35: =U36-U31 -> 31475 | V35: =V36-V31 -> 35319 | W35: =W36-W31 -> 38521 | X35: =X36-X31 -> 44656 | Y35: =Y36-Y31 -> 81198 | Z35: =Z36-Z31 -> 108479 | AA35: =AA36-AA31 -> 122860 | AC35: =AA35 -> 122860
B36: Total assets | M36: 44187 | N36: 41182 | O36: 65728 | P36: 111601 | Q36: 206803 | T36: 96013 | U36: 111601 | V36: 125254 | W36: 140740 | X36: 161148 | Y36: 206803 | Z36: 259474 | AA36: 320272 | AC36: =AA36 -> 320272
B37: Acc payable | M37: 1783 | N37: 1193 | O37: 2699 | P37: 6310 | Q37: 9812 | T37: 5353 | U37: 6310 | V37: 7331 | W37: 9064 | X37: 8624 | Y37: 9812 | Z37: 13097 | AA37: 15059 | AC37: =AA37 -> 15059
B38: Debt | M38: 0 | N38: 1250 | O38: 1250 | P38: 0 | Q38: 999 | T38: 0 | U38: 0 | V38: 0 | W38: 0 | X38: 999 | Y38: 999 | Z38: 1000 | AA38: 1000 | AC38: =AA38 -> 1000
B39: Current liabilities | M39: 4335 | N39: 6563 | O39: 10631 | P39: 18047 | Q39: 32163 | T39: 16479 | U39: 18047 | V39: 26542 | W39: 24257 | X39: 26075 | Y39: 32163 | Z39: 43884 | AA39: 43019 | AC39: =AA39 -> 43019
B40: Debt | M40: 10946 | N40: 9703 | O40: 8459 | P40: 8463 | Q40: 7469 | T40: 8462 | U40: 8463 | V40: 8464 | W40: 8466 | X40: 7468 | Y40: 7569 | Z40: 7470 | AA40: 32266 | AC40: =AA40 -> 32266
B41: Long term liabilities | M41: =M42-M39 -> 13240 | N41: =N42-N39 -> 12518 | O41: =O42-O39 -> 12119 | P41: =P42-P39 -> 14227 | Q41: =Q42-Q39 -> 17347 | T41: =T42-T39 -> 13635 | U41: =U42-U39 -> 14227 | V41: =V42-V39 -> 14869 | W41: =W42-W39 -> 16352 | X41: =X42-X39 -> 16176 | Y41: =Y42-Y39 -> 17347 | Z41: =Z42-Z39 -> 20116 | AA41: =AA42-AA39 -> 48269 | AC41: =AA41 -> 48269
B42: Total liabilities | M42: 17575 | N42: 19081 | O42: 22750 | P42: 32274 | Q42: 49510 | T42: 30114 | U42: 32274 | V42: 41411 | W42: 40609 | X42: 42251 | Y42: 49510 | Z42: 64000 | AA42: 91288 | AC42: =AA42 -> 91288
B43: Treasury stock | M43: 0 | N43: 0 | O43: 0 | P43: 0 | Q43: 0 | T43: 0 | U43: 0 | V43: 0 | W43: 0 | X43: 0 | Y43: 0 | Z43: 0 | AA43: 0 | AC43: =AA43 -> 0
B44: Preferred stock | M44: 0 | N44: 0 | O44: 0 | P44: 0 | Q44: 0 | T44: 0 | U44: 0 | V44: 0 | W44: 0 | X44: 0 | Y44: 0 | Z44: 0 | AA44: 0 | AC44: =AA44 -> 0
B45: Paid in capital | M45: 10385 | N45: 11971 | O45: 13132 | P45: 11237 | Q45: 10118 | T45: 11821 | U45: 11237 | V45: 11475 | W45: 11200 | X45: 10626 | Y45: 10118 | Z45: 10275 | AA45: 9828 | AC45: =AA45 -> 9828
B46: Accumulated income/loss | M46: 16235 | N46: 10171 | O46: 29817 | P46: 68038 | Q46: 146973 | T46: 53950 | U46: 68038 | V46: 72158 | W46: 88737 | X46: 107908 | Y46: 146973 | Z46: 185038 | AA46: 219157 | AC46: =AA46 -> 219157
B47: Non-controlling interest | M47: 0 | N47: 0 | O47: 0 | P47: 0 | Q47: 0 | T47: 0 | U47: 0 | V47: 0 | W47: 0 | X47: 0 | Y47: 0 | Z47: 0 | AA47: 0 | AC47: =AA47 -> 0
B48: Stockholder equity | M48: 26612 | N48: 22101 | O48: 42978 | P48: 79327 | Q48: 157293 | T48: 65899 | U48: 79327 | V48: 83843 | W48: 100131 | X48: 118897 | Y48: 157293 | Z48: 195474 | AA48: 228984 | AC48: =AA48 -> 228984
B49: Total liabilities and equity | M49: 44187 | N49: 41182 | O49: 65728 | P49: 111601 | Q49: 206803 | T49: 96013 | U49: 111601 | V49: 125254 | W49: 140740 | X49: 161148 | Y49: 206803 | Z49: 259474 | AA49: 320272 | AC49: =AA49 -> 320272
B51: Cashflow statement
B52: D&A | M52: 1174 | N52: 1544 | O52: 1508 | P52: 1864 | Q52: 2843 | T52: 478 | U52: 543 | V52: 611 | W52: 668 | X52: 752 | Y52: 811 | Z52: 997 | AA52: 1127 | AC52: =SUM(X52:AA52) -> 3687
B53: Stock-based compensation | M53: 2004 | N53: 2709 | O53: 3549 | P53: 4737 | Q53: 6386 | T53: 1252 | U53: 1321 | V53: 1474 | W53: 1624 | X53: 1655 | Y53: 1633 | Z53: 1928 | AA53: 2026 | AC53: =SUM(X53:AA53) -> 7242
B54: Change in accounts receivable | M54: -2215 | N54: 822 | O54: -6172 | P54: -13063 | Q54: -15399 | T54: -3561 | U54: -5370 | V54: 933 | W54: -5675 | X54: -5583 | Y54: -5073 | Z54: -2243 | AA54: -22347 | AC54: =SUM(X54:AA54) -> -35246
B55: Change in inventory | M55: -774 | N55: -2554 | O55: -98 | P55: -4781 | Q55: -11324 | T55: -978 | U55: -2424 | V55: -1258 | W55: -3622 | X55: -4823 | Y55: -1621 | Z55: -4420 | AA55: -5784 | AC55: =SUM(X55:AA55) -> -16648
B56: Change in accounts payable | M56: 568 | N56: -551 | O56: 1531 | P56: 3357 | Q56: 3069 | T56: 1689 | U56: 867 | V56: 941 | W56: 1314 | X56: -223 | Y56: 1064 | Z56: 2210 | AA56: 1915 | AC56: =SUM(X56:AA56) -> 4966
B57: Change in other operating NWC | M57: =-1715+581+192 -> -942 | N57: =-1517+1341+252 -> 76 | O57: =-1522+2025+514 -> 1017 | P57: =-395+4278+1221 -> 5104 | Q57: =577+5257+1844 -> 7678 | T57: =-714+606+266 -> 158 | U57: =331+360+372 -> 1063 | V57: =560+7128+350 -> 8038 | W57: =387-4053+629 -> -3037 | X57: =-89+1129+332 -> 1372 | Y57: =-281+1053+533 -> 1305 | Z57: =-983+7763+1217 -> 7997 | AA57: -4492 | AC57: =SUM(X57:AA57) -> 6182
B58: Operating cashflow | M58: 9108 | N58: 5641 | O58: 28090 | P58: 64089 | Q58: 102718 | T58: 17629 | U58: 16628 | V58: 27414 | W58: 15365 | X58: 23750 | Y58: 36190 | Z58: 50344 | AA58: 24077 | AC58: =SUM(X58:AA58) -> 134361
B59: CapEx | M59: -976 | N59: -1833 | O59: -1069 | P59: =-3236 -> -3236 | Q59: -6042 | T59: -813 | U59: -1077 | V59: -1227 | W59: -1894 | X59: -1637 | Y59: -1284 | Z59: -1757 | AA59: -2677 | AC59: =SUM(X59:AA59) -> -7355
B60: Capitalized software | M60: 0 | N60: 0 | O60: 0 | P60: 0 | Q60: 0 | T60: 0 | U60: 0 | V60: 0 | W60: 0 | X60: 0 | Y60: 0 | Z60: 0 | AA60: 0 | AC60: =SUM(X60:AA60) -> 0
B61: Investing cashflow | M61: -9830 | N61: 7375 | O61: -10566 | P61: -20421 | Q61: -52228 | T61: -4345 | U61: -7198 | V61: -5216 | W61: -7126 | X61: -9025 | Y61: -30861 | Z61: -26429 | AA61: -8695 | AC61: =SUM(X61:AA61) -> -75010
B62: Repurchase stock | M62: 0 | N62: -10039 | O62: -9533 | P62: -33706 | Q62: -40086 | T62: -10998 | U62: -7810 | V62: -14095 | W62: -9721 | X62: -12456 | Y62: -3815 | Z62: -19312 | AA62: -19732 | AC62: =SUM(X62:AA62) -> -55315
B63: Dividends | M63: -399 | N63: -398 | O63: -395 | P63: -834 | Q63: -974 | T63: -245 | U63: -245 | V63: -244 | W63: -244 | X63: -243 | Y63: -243 | Z63: -243 | AA63: -6047 | AC63: =SUM(X63:AA63) -> -6776
B64: Dividends to minority interest | M64: 0 | N64: 0 | O64: 0 | P64: 0 | Q64: 0 | T64: 0 | U64: 0 | V64: 0 | W64: 0 | X64: 0 | Y64: 0 | Z64: 0 | AA64: 0 | AC64: =SUM(X64:AA64) -> 0
B65: Financing cashflow | M65: 1865 | N65: -11617 | O65: -13633 | P65: -42359 | Q65: -48474 | T65: -12748 | U65: -9948 | V65: -15553 | W65: -11834 | X65: -14878 | Y65: -6210 | Z65: -21283 | AA65: -6176 | AC65: =SUM(X65:AA65) -> -48547
B67: Sanity checks
B68: Calculated Net Income | C68: =C5-C6-C10+C12+C13+C15-C16 -> 0 | D68: =D5-D6-D10+D12+D13+D15-D16 -> 0 | E68: =E5-E6-E10+E12+E13+E15-E16 -> 0 | F68: =F5-F6-F10+F12+F13+F15-F16 -> 0 | G68: =G5-G6-G10+G12+G13+G15-G16 -> 0 | H68: =H5-H6-H10+H12+H13+H15-H16 -> 0 | I68: =I5-I6-I10+I12+I13+I15-I16 -> 0 | J68: =J5-J6-J10+J12+J13+J15-J16 -> 0 | ... Q68: =Q5-Q6-Q10+Q12+Q13+Q15-Q16 -> 120067 | T68: =T5-T6-T10+T12+T13+T15-T16 -> 19309 | U68: =U5-U6-U10+U12+U13+U15-U16 -> 22091 | V68: =V5-V6-V10+V12+V13+V15-V16 -> 18775 | W68: =W5-W6-W10+W12+W13+W15-W16 -> 26422 | X68: =X5-X6-X10+X12+X13+X15-X16 -> 31910 | Y68: =Y5-Y6-Y10+Y12+Y13+Y15-Y16 -> 42960 | Z68: =Z5-Z6-Z10+Z12+Z13+Z15-Z16 -> 58331 | AA68: =AA5-AA6-AA10+AA12+AA13+AA15-AA16 -> 59688 | AC68: =AC5-AC6-AC10+AC12+AC13+AC15-AC16 -> 192889
B69: Check Net Income | C69: =C17-C68 -> 0 | D69: =D17-D68 -> 0 | E69: =E17-E68 -> 0 | F69: =F17-F68 -> 0 | G69: =G17-G68 -> 0 | H69: =H17-H68 -> 0 | I69: =I17-I68 -> 0 | J69: =J17-J68 -> 0 | ... Q69: =Q17-Q68 -> 0 | T69: =T17-T68 -> 0 | U69: =U17-U68 -> 0 | V69: =V17-V68 -> 0 | W69: =W17-W68 -> 0 | X69: =X17-X68 -> 0 | Y69: =Y17-Y68 -> 0 | Z69: =Z17-Z68 -> -10 | AA69: =AA17-AA68 -> 0 | AC69: =AC17-AC68 -> -10
B70: Check balance | C70: =C36-(C42+C110) -> 0 | D70: =D36-(D42+D110) -> 0 | E70: =E36-(E42+E110) -> 0 | F70: =F36-(F42+F110) -> 0 | G70: =G36-(G42+G110) -> 0 | H70: =H36-(H42+H110) -> 0 | I70: =I36-(I42+I110) -> 0 | J70: =J36-(J42+J110) -> 0 | ... Q70: =Q36-(Q42+Q110) -> 0 | T70: =T36-(T42+T110) -> 0 | U70: =U36-(U42+U110) -> 0 | V70: =V36-(V42+V110) -> 0 | W70: =W36-(W42+W110) -> 0 | X70: =X36-(X42+X110) -> 0 | Y70: =Y36-(Y42+Y110) -> 0 | Z70: =Z36-(Z42+Z110) -> 0 | AA70: =AA36-(AA42+AA110) -> 0 | AC70: =AC36-(AC42+AC110) -> 0
B72: Other data
B73: Shares outstanding | M73: 2510 | N73: 2470 | O73: 2500 | P73: 24400 | Q73: 24300 | T73: 24490 | U73: 24400 | V73: 24400 | W73: 24300 | X73: 24300 | Y73: 24300 | Z73: 24200 | AA73: 24100 | AC73: =AA73 -> 24100
B74: Split adjusted shares outstanding | M74: =M73*M84 -> 25100 | N74: =N73*N84 -> 24700 | O74: =O73*O84 -> 25000 | P74: =P73*P84 -> 24400 | Q74: =Q73*Q84 -> 24300 | T74: =T73*T84 -> 24490 | U74: =U73*U84 -> 24400 | V74: =V73*V84 -> 24400 | W74: =W73*W84 -> 24300 | X74: =X73*X84 -> 24300 | Y74: =Y73*Y84 -> 24300 | Z74: =Z73*Z84 -> 24200 | AA74: =AA73*AA84 -> 24100 | AC74: =AA74 -> 24100
B75: Dilutive shares | M75: 39 | N75: 20 | O75: 25 | P75: 249 | Q75: 155 | T75: 241 | U75: 249 | V75: 170 | W75: 166 | X75: 156 | Y75: 155 | Z75: 105 | AA75: 95 | AC75: =AA75 -> 95
B76: Split adjusted dilutive shares | M76: =M75*M84 -> 390 | N76: =N75*N84 -> 200 | O76: =O75*O84 -> 250 | P76: =P75*P84 -> 249 | Q76: =Q75*Q84 -> 155 | T76: =T75*T84 -> 241 | U76: =U75*U84 -> 249 | V76: =V75*V84 -> 170 | W76: =W75*W84 -> 166 | X76: =X75*X84 -> 156 | Y76: =Y75*Y84 -> 155 | Z76: =Z75*Z84 -> 105 | AA76: =AA75*AA84 -> 95 | AC76: =AA76 -> 95
B77: Split adjusted diluted shares | M77: =M74+M76 -> 25490 | N77: =N74+N76 -> 24900 | O77: =O74+O76 -> 25250 | P77: =P74+P76 -> 24649 | Q77: =Q74+Q76 -> 24455 | T77: =T74+T76 -> 24731 | U77: =U74+U76 -> 24649 | V77: =V74+V76 -> 24570 | W77: =W74+W76 -> 24466 | X77: =X74+X76 -> 24456 | Y77: =Y74+Y76 -> 24455 | Z77: =Z74+Z76 -> 24305 | AA77: =AA74+AA76 -> 24195 | AC77: =AA77 -> 24195
B78: Shares held by insiders | M78: 101 | N78: 99 | O78: 104 | P78: 1020 | Q78: 957 | AC78: =Q78 -> 957
B79: Split adjusted shares held by insiders | M79: =M78*M84 -> 1010 | N79: =N78*N84 -> 990 | O79: =O78*O84 -> 1040 | P79: =P78*P84 -> 1020 | Q79: =Q78*Q84 -> 957 | AC79: =Q79 -> 957
B80: Dividends per share | M80: 0.16 | N80: 0.16 | O80: 0.16 | P80: 0.034 | Q80: 0.04 | T80: 0.01 | U80: 0.01 | V80: 0.01 | W80: 0.01 | X80: 0.01 | Y80: 0.01 | Z80: 0.01 | AA80: 0.25 | AC80: =SUM(X80:AA80) -> 0.28
B81: Split adjusted dividends per share | M81: =M80/M84 -> 0.016 | N81: =N80/N84 -> 0.016 | O81: =O80/O84 -> 0.016 | P81: =P80/P84 -> 0.034 | Q81: =Q80/Q84 -> 0.04 | T81: =T80/T84 -> 0.01 | U81: =U80/U84 -> 0.01 | V81: =V80/V84 -> 0.01 | W81: =W80/W84 -> 0.01 | X81: =X80/X84 -> 0.01 | Y81: =Y80/Y84 -> 0.01 | Z81: =Z80/Z84 -> 0.01 | AA81: =AA80/AA84 -> 0.25 | AC81: =SUM(X81:AA81) -> 0.28
B82: Tax rate | C82: =IF(AND(C14>0,C15<0),-(C15)/C14,0) -> 0 | D82: =IF(AND(D14>0,D15<0),-(D15)/D14,0) -> 0 | E82: =IF(AND(E14>0,E15<0),-(E15)/E14,0) -> 0 | F82: =IF(AND(F14>0,F15<0),-(F15)/F14,0) -> 0 | G82: =IF(AND(G14>0,G15<0),-(G15)/G14,0) -> 0 | H82: =IF(AND(H14>0,H15<0),-(H15)/H14,0) -> 0 | I82: =IF(AND(I14>0,I15<0),-(I15)/I14,0) -> 0 | J82: =IF(AND(J14>0,J15<0),-(J15)/J14,0) -> 0 | ... Q82: =IF(AND(Q14>0,Q15<0),-(Q15)/Q14,0) -> 0.15117002 | T82: =IF(AND(T14>0,T15<0),-(T15)/T14,0) -> 0.13474637 | U82: =IF(AND(U14>0,U15<0),-(U15)/U14,0) -> 0.12396399 | V82: =IF(AND(V14>0,V15<0),-(V15)/V14,0) -> 0.14308535 | W82: =IF(AND(W14>0,W15<0),-(W15)/W14,0) -> 0.15330385 | X82: =IF(AND(X14>0,X15<0),-(X15)/X14,0) -> 0.15884648 | Y82: =IF(AND(Y14>0,Y15<0),-(Y15)/Y14,0) -> 0.14756831 | Z82: =IF(AND(Z14>0,Z15<0),-(Z15)/Z14,0) -> 0.16568674 | AA82: =IF(AND(AA14>0,AA15<0),-(AA15)/AA14,0) -> 0.16528452 | AC82: =IF(AND(AC14>0,AC15<0),-(AC15)/AC14,0) -> 0.16045755
B83: Employees | M83: 22473 | N83: 26196 | O83: 29600 | P83: 36000 | Q83: 42000 | AC83: =Q83 -> 42000
B84: Stock split factor | M84: 10 | N84: 10 | O84: 10 | P84: 1 | Q84: 1 | T84: 1 | U84: 1 | V84: 1 | W84: 1 | X84: 1 | Y84: 1 | Z84: 1 | AA84: 1 | AC84: 1
B87: Growth rates Income Statement
B88: Revenue | M88: =IF(L5=0, IF(M5=0,0,IF(M5>0,1,-1)), (M5-L5)/ABS(L5) ) -> 1 | N88: =IF(M5=0, IF(N5=0,0,IF(N5>0,1,-1)), (N5-M5)/ABS(M5) ) -> 0.002229323 | O88: =IF(N5=0, IF(O5=0,0,IF(O5>0,1,-1)), (O5-N5)/ABS(N5) ) -> 1.2585453 | P88: =IF(O5=0, IF(P5=0,0,IF(P5>0,1,-1)), (P5-O5)/ABS(O5) ) -> 1.1420341 | Q88: =IF(P5=0, IF(Q5=0,0,IF(Q5>0,1,-1)), (Q5-P5)/ABS(P5) ) -> 0.65473536 | T88: =IF(S5=0, IF(T5=0,0,IF(T5>0,1,-1)), (T5-S5)/ABS(S5) ) -> 1 | U88: =IF(T5=0, IF(U5=0,0,IF(U5>0,1,-1)), (U5-T5)/ABS(T5) ) -> 0.12111624 | V88: =IF(U5=0, IF(V5=0,0,IF(V5>0,1,-1)), (V5-U5)/ABS(U5) ) -> 0.1202868 | W88: =IF(V5=0, IF(W5=0,0,IF(W5>0,1,-1)), (W5-V5)/ABS(V5) ) -> 0.060846081 | X88: =IF(W5=0, IF(X5=0,0,IF(X5>0,1,-1)), (X5-W5)/ABS(W5) ) -> 0.21956229 | Y88: =IF(X5=0, IF(Y5=0,0,IF(Y5>0,1,-1)), (Y5-X5)/ABS(X5) ) -> 0.19508473 | Z88: =IF(Y5=0, IF(Z5=0,0,IF(Z5>0,1,-1)), (Z5-Y5)/ABS(Y5) ) -> 0.19798318 | AA88: =IF(Z5=0, IF(AA5=0,0,IF(AA5>0,1,-1)), (AA5-Z5)/ABS(Z5) ) -> 0.1789622
B89: COGS | M89: =IF(L6=0, IF(M6=0,0,IF(M6>0,1,-1)), (M6-L6)/ABS(L6) ) -> 1 | N89: =IF(M6=0, IF(N6=0,0,IF(N6>0,1,-1)), (N6-M6)/ABS(M6) ) -> 0.23085073 | O89: =IF(N6=0, IF(O6=0,0,IF(O6>0,1,-1)), (O6-N6)/ABS(N6) ) -> 0.43062489 | P89: =IF(O6=0, IF(P6=0,0,IF(P6>0,1,-1)), (P6-O6)/ABS(O6) ) -> 0.96372059 | Q89: =IF(P6=0, IF(Q6=0,0,IF(Q6>0,1,-1)), (Q6-P6)/ABS(P6) ) -> 0.91412114 | T89: =IF(S6=0, IF(T6=0,0,IF(T6>0,1,-1)), (T6-S6)/ABS(S6) ) -> 1 | U89: =IF(T6=0, IF(U6=0,0,IF(U6>0,1,-1)), (U6-T6)/ABS(T6) ) -> 0.18843827 | V89: =IF(U6=0, IF(V6=0,0,IF(V6>0,1,-1)), (V6-U6)/ABS(U6) ) -> 0.63970588 | W89: =IF(V6=0, IF(W6=0,0,IF(W6>0,1,-1)), (W6-V6)/ABS(V6) ) -> -0.25893986 | X89: =IF(W6=0, IF(X6=0,0,IF(X6>0,1,-1)), (X6-W6)/ABS(W6) ) -> 0.17587277 | Y89: =IF(X6=0, IF(Y6=0,0,IF(Y6>0,1,-1)), (Y6-X6)/ABS(X6) ) -> 0.12383717 | Z89: =IF(Y6=0, IF(Z6=0,0,IF(Z6>0,1,-1)), (Z6-Y6)/ABS(Y6) ) -> 0.20100975 | AA89: =IF(Z6=0, IF(AA6=0,0,IF(AA6>0,1,-1)), (AA6-Z6)/ABS(Z6) ) -> 0.17699677
B90: Gross Profit | M90: =IF(L7=0, IF(M7=0,0,IF(M7>0,1,-1)), (M7-L7)/ABS(L7) ) -> 1 | N90: =IF(M7=0, IF(N7=0,0,IF(N7>0,1,-1)), (N7-M7)/ABS(M7) ) -> -0.12125894 | O90: =IF(N7=0, IF(O7=0,0,IF(O7>0,1,-1)), (O7-N7)/ABS(N7) ) -> 1.884931 | P90: =IF(O7=0, IF(P7=0,0,IF(P7>0,1,-1)), (P7-O7)/ABS(O7) ) -> 1.2089343 | Q90: =IF(P7=0, IF(Q7=0,0,IF(Q7>0,1,-1)), (Q7-P7)/ABS(P7) ) -> 0.5682213 | T90: =IF(S7=0, IF(T7=0,0,IF(T7>0,1,-1)), (T7-S7)/ABS(S7) ) -> 1 | U90: =IF(T7=0, IF(U7=0,0,IF(U7>0,1,-1)), (U7-T7)/ABS(T7) ) -> 0.098141918 | V90: =IF(U7=0, IF(V7=0,0,IF(V7>0,1,-1)), (V7-U7)/ABS(U7) ) -> -0.071545451 | W90: =IF(V7=0, IF(W7=0,0,IF(W7>0,1,-1)), (W7-V7)/ABS(V7) ) -> 0.26942403 | X90: =IF(W7=0, IF(X7=0,0,IF(X7>0,1,-1)), (X7-W7)/ABS(W7) ) -> 0.23619768 | Y90: =IF(X7=0, IF(Y7=0,0,IF(Y7>0,1,-1)), (Y7-X7)/ABS(X7) ) -> 0.22088939 | Z90: =IF(Y7=0, IF(Z7=0,0,IF(Z7>0,1,-1)), (Z7-Y7)/ABS(Y7) ) -> 0.19697415 | AA90: =IF(Z7=0, IF(AA7=0,0,IF(AA7>0,1,-1)), (AA7-Z7)/ABS(Z7) ) -> 0.17961967
B91: R&D | M91: =IF(L8=0, IF(M8=0,0,IF(M8>0,1,-1)), (M8-L8)/ABS(L8) ) -> 1 | N91: =IF(M8=0, IF(N8=0,0,IF(N8>0,1,-1)), (N8-M8)/ABS(M8) ) -> 0.39312832 | O91: =IF(N8=0, IF(O8=0,0,IF(O8>0,1,-1)), (O8-N8)/ABS(N8) ) -> 0.18204115 | P91: =IF(O8=0, IF(P8=0,0,IF(P8>0,1,-1)), (P8-O8)/ABS(O8) ) -> 0.48864553 | Q91: =IF(P8=0, IF(Q8=0,0,IF(Q8>0,1,-1)), (Q8-P8)/ABS(P8) ) -> 0.43232151 | T91: =IF(S8=0, IF(T8=0,0,IF(T8>0,1,-1)), (T8-S8)/ABS(S8) ) -> 1 | U91: =IF(T8=0, IF(U8=0,0,IF(U8>0,1,-1)), (U8-T8)/ABS(T8) ) -> 0.095575221 | V91: =IF(U8=0, IF(V8=0,0,IF(V8>0,1,-1)), (V8-U8)/ABS(U8) ) -> 0.074044157 | W91: =IF(V8=0, IF(W8=0,0,IF(W8>0,1,-1)), (W8-V8)/ABS(V8) ) -> 0.075708198 | X91: =IF(W8=0, IF(X8=0,0,IF(X8>0,1,-1)), (X8-W8)/ABS(W8) ) -> 0.096481007 | Y91: =IF(X8=0, IF(Y8=0,0,IF(Y8>0,1,-1)), (Y8-X8)/ABS(X8) ) -> 0.17151966 | Z91: =IF(Y8=0, IF(Z8=0,0,IF(Z8>0,1,-1)), (Z8-Y8)/ABS(Y8) ) -> 0.14677068 | AA91: =IF(Z8=0, IF(AA8=0,0,IF(AA8>0,1,-1)), (AA8-Z8)/ABS(Z8) ) -> 0.11596266
B92: SG&A | M92: =IF(L9=0, IF(M9=0,0,IF(M9>0,1,-1)), (M9-L9)/ABS(L9) ) -> 1 | N92: =IF(M9=0, IF(N9=0,0,IF(N9>0,1,-1)), (N9-M9)/ABS(M9) ) -> 0.12650046 | O92: =IF(N9=0, IF(O9=0,0,IF(O9>0,1,-1)), (O9-N9)/ABS(N9) ) -> 0.087704918 | P92: =IF(O9=0, IF(P9=0,0,IF(P9>0,1,-1)), (P9-O9)/ABS(O9) ) -> 0.31537302 | Q92: =IF(P9=0, IF(Q9=0,0,IF(Q9>0,1,-1)), (Q9-P9)/ABS(P9) ) -> 0.31165855 | T92: =IF(S9=0, IF(T9=0,0,IF(T9>0,1,-1)), (T9-S9)/ABS(S9) ) -> 1 | U92: =IF(T9=0, IF(U9=0,0,IF(U9>0,1,-1)), (U9-T9)/ABS(T9) ) -> 0.086956522 | V92: =IF(U9=0, IF(V9=0,0,IF(V9>0,1,-1)), (V9-U9)/ABS(U9) ) -> 0.067692308 | W92: =IF(V9=0, IF(W9=0,0,IF(W9>0,1,-1)), (W9-V9)/ABS(V9) ) -> 0.077809798 | X92: =IF(W9=0, IF(X9=0,0,IF(X9>0,1,-1)), (X9-W9)/ABS(W9) ) -> 0.010695187 | Y92: =IF(X9=0, IF(Y9=0,0,IF(Y9>0,1,-1)), (Y9-X9)/ABS(X9) ) -> 0.13051146 | Z92: =IF(Y9=0, IF(Z9=0,0,IF(Z9>0,1,-1)), (Z9-Y9)/ABS(Y9) ) -> 0.014040562 | AA92: =IF(Z9=0, IF(AA9=0,0,IF(AA9>0,1,-1)), (AA9-Z9)/ABS(Z9) ) -> 0.041538462
B93: OpEx | M93: =IF(L10=0, IF(M10=0,0,IF(M10>0,1,-1)), (M10-L10)/ABS(L10) ) -> 1 | N93: =IF(M10=0, IF(N10=0,0,IF(N10>0,1,-1)), (N10-M10)/ABS(M10) ) -> 0.49744418 | O93: =IF(N10=0, IF(O10=0,0,IF(O10>0,1,-1)), (O10-N10)/ABS(N10) ) -> 0.01769673 | P93: =IF(O10=0, IF(P10=0,0,IF(P10>0,1,-1)), (P10-O10)/ABS(O10) ) -> 0.44805367 | Q93: =IF(P10=0, IF(Q10=0,0,IF(Q10>0,1,-1)), (Q10-P10)/ABS(P10) ) -> 0.40664432 | T93: =IF(S10=0, IF(T10=0,0,IF(T10>0,1,-1)), (T10-S10)/ABS(S10) ) -> 1 | U93: =IF(T10=0, IF(U10=0,0,IF(U10>0,1,-1)), (U10-T10)/ABS(T10) ) -> 0.093771868 | V93: =IF(U10=0, IF(V10=0,0,IF(V10>0,1,-1)), (V10-U10)/ABS(U10) ) -> 0.072723395 | W93: =IF(V10=0, IF(W10=0,0,IF(W10>0,1,-1)), (W10-V10)/ABS(V10) ) -> 0.076143141 | X93: =IF(W10=0, IF(X10=0,0,IF(X10>0,1,-1)), (X10-W10)/ABS(W10) ) -> 0.078699427 | Y93: =IF(X10=0, IF(Y10=0,0,IF(Y10>0,1,-1)), (Y10-X10)/ABS(X10) ) -> 0.1635554 | Z93: =IF(Y10=0, IF(Z10=0,0,IF(Z10>0,1,-1)), (Z10-Y10)/ABS(Y10) ) -> 0.12172505 | AA93: =IF(Z10=0, IF(AA10=0,0,IF(AA10>0,1,-1)), (AA10-Z10)/ABS(Z10) ) -> 0.10326729
B94: Operating income | M94: =IF(L11=0, IF(M11=0,0,IF(M11>0,1,-1)), (M11-L11)/ABS(L11) ) -> 1 | N94: =IF(M11=0, IF(N11=0,0,IF(N11>0,1,-1)), (N11-M11)/ABS(M11) ) -> -0.57932477 | O94: =IF(N11=0, IF(O11=0,0,IF(O11>0,1,-1)), (O11-N11)/ABS(N11) ) -> 6.8058712 | P94: =IF(O11=0, IF(P11=0,0,IF(P11>0,1,-1)), (P11-O11)/ABS(O11) ) -> 1.4703688 | Q94: =IF(P11=0, IF(Q11=0,0,IF(Q11>0,1,-1)), (Q11-P11)/ABS(P11) ) -> 0.60076363 | T94: =IF(S11=0, IF(T11=0,0,IF(T11>0,1,-1)), (T11-S11)/ABS(S11) ) -> 1 | U94: =IF(T11=0, IF(U11=0,0,IF(U11>0,1,-1)), (U11-T11)/ABS(T11) ) -> 0.098998582 | V94: =IF(U11=0, IF(V11=0,0,IF(V11>0,1,-1)), (V11-U11)/ABS(U11) ) -> -0.099692103 | W94: =IF(V11=0, IF(W11=0,0,IF(W11>0,1,-1)), (W11-V11)/ABS(V11) ) -> 0.31435438 | X94: =IF(W11=0, IF(X11=0,0,IF(X11>0,1,-1)), (X11-W11)/ABS(W11) ) -> 0.2661744 | Y94: =IF(X11=0, IF(Y11=0,0,IF(Y11>0,1,-1)), (Y11-X11)/ABS(X11) ) -> 0.23018606 | Z94: =IF(Y11=0, IF(Z11=0,0,IF(Z11>0,1,-1)), (Z11-Y11)/ABS(Y11) ) -> 0.20851486 | AA94: =IF(Z11=0, IF(AA11=0,0,IF(AA11>0,1,-1)), (AA11-Z11)/ABS(Z11) ) -> 0.19048864
B95: Income before taxes | M95: =IF(L14=0, IF(M14=0,0,IF(M14>0,1,-1)), (M14-L14)/ABS(L14) ) -> 1 | N95: =IF(M14=0, IF(N14=0,0,IF(N14>0,1,-1)), (N14-M14)/ABS(M14) ) -> -0.57941857 | O95: =IF(N14=0, IF(O14=0,0,IF(O14>0,1,-1)), (O14-N14)/ABS(N14) ) -> 7.0884956 | P95: =IF(O14=0, IF(P14=0,0,IF(P14>0,1,-1)), (P14-O14)/ABS(O14) ) -> 1.4846531 | Q95: =IF(P14=0, IF(Q14=0,0,IF(Q14>0,1,-1)), (Q14-P14)/ABS(P14) ) -> 0.68340752 | T95: =IF(S14=0, IF(T14=0,0,IF(T14>0,1,-1)), (T14-S14)/ABS(S14) ) -> 1 | U95: =IF(T14=0, IF(U14=0,0,IF(U14>0,1,-1)), (U14-T14)/ABS(T14) ) -> 0.12999642 | V95: =IF(U14=0, IF(V14=0,0,IF(V14>0,1,-1)), (V14-U14)/ABS(U14) ) -> -0.13114169 | W95: =IF(V14=0, IF(W14=0,0,IF(W14>0,1,-1)), (W14-V14)/ABS(V14) ) -> 0.42428115 | X95: =IF(W14=0, IF(X14=0,0,IF(X14>0,1,-1)), (X14-W14)/ABS(W14) ) -> 0.21566365 | Y95: =IF(X14=0, IF(Y14=0,0,IF(Y14>0,1,-1)), (Y14-X14)/ABS(X14) ) -> 0.32847427 | Z95: =IF(Y14=0, IF(Z14=0,0,IF(Z14>0,1,-1)), (Z14-Y14)/ABS(Y14) ) -> 0.38704685 | AA95: =IF(Z14=0, IF(AA14=0,0,IF(AA14>0,1,-1)), (AA14-Z14)/ABS(Z14) ) -> 0.022946082
B96: Net income | M96: =IF(L17=0, IF(M17=0,0,IF(M17>0,1,-1)), (M17-L17)/ABS(L17) ) -> 1 | N96: =IF(M17=0, IF(N17=0,0,IF(N17>0,1,-1)), (N17-M17)/ABS(M17) ) -> -0.55209188 | O96: =IF(N17=0, IF(O17=0,0,IF(O17>0,1,-1)), (O17-N17)/ABS(N17) ) -> 5.8131868 | P96: =IF(O17=0, IF(P17=0,0,IF(P17>0,1,-1)), (P17-O17)/ABS(O17) ) -> 1.4489247 | Q96: =IF(P17=0, IF(Q17=0,0,IF(Q17>0,1,-1)), (Q17-P17)/ABS(P17) ) -> 0.64746158 | T96: =IF(S17=0, IF(T17=0,0,IF(T17>0,1,-1)), (T17-S17)/ABS(S17) ) -> 1 | U96: =IF(T17=0, IF(U17=0,0,IF(U17>0,1,-1)), (U17-T17)/ABS(T17) ) -> 0.14407789 | V96: =IF(U17=0, IF(V17=0,0,IF(V17>0,1,-1)), (V17-U17)/ABS(U17) ) -> -0.15010638 | W96: =IF(V17=0, IF(W17=0,0,IF(W17>0,1,-1)), (W17-V17)/ABS(V17) ) -> 0.40729694 | X96: =IF(W17=0, IF(X17=0,0,IF(X17>0,1,-1)), (X17-W17)/ABS(W17) ) -> 0.2077057 | Y96: =IF(X17=0, IF(Y17=0,0,IF(Y17>0,1,-1)), (Y17-X17)/ABS(X17) ) -> 0.34628643 | Z96: =IF(Y17=0, IF(Z17=0,0,IF(Z17>0,1,-1)), (Z17-Y17)/ABS(Y17) ) -> 0.35756518 | AA96: =IF(Z17=0, IF(AA17=0,0,IF(AA17>0,1,-1)), (AA17-Z17)/ABS(Z17) ) -> 0.023439241
B98: Margins
B99: Gross margin | M99: =M7/M5 -> 0.64929033 | N99: =N7/N5 -> 0.56928894 | O99: =O7/O5 -> 0.72717573 | P99: =P7/P5 -> 0.74988697 | Q99: =Q7/Q5 -> 0.71068084 | T99: =T7/T5 -> 0.74556753 | U99: =U7/U5 -> 0.73028908 | V99: =V7/V5 -> 0.60523807 | W99: =W7/W5 -> 0.72423678 | X99: =X7/X5 -> 0.73411571 | Y99: =Y7/Y5 -> 0.74996697 | Z99: =Z7/Z5 -> 0.74933529 | AA99: =AA7/AA5 -> 0.74975317 | AC99: =AC7/AC5 -> 0.74674637
B100: Operating margin | M100: =M11/M5 -> 0.37307721 | N100: =N11/N5 -> 0.15659524 | O100: =O11/O5 -> 0.54121664 | P100: =P11/P5 -> 0.62417527 | Q100: =Q11/Q5 -> 0.60381684 | T100: =T11/T5 -> 0.62336811 | U100: =U11/U5 -> 0.61107015 | V100: =V11/V5 -> 0.49108075 | W100: =W11/W5 -> 0.60843335 | X100: =X11/X5 -> 0.63168789 | Y100: =Y11/Y5 -> 0.65024146 | Z100: =Z11/Z5 -> 0.65595785 | AA100: =AA11/AA5 -> 0.662371 | AC100: =AC11/AC5 -> 0.65214263
B101: Net margin | M101: =M109/M5 -> 0.3623393 | N101: =N109/N5 -> 0.16193371 | O101: =O109/O5 -> 0.48849348 | P101: =P109/P5 -> 0.55848027 | Q101: =Q109/Q5 -> 0.55602534 | T101: =T109/T5 -> 0.55039621 | U101: =U109/U5 -> 0.56166891 | V101: =V109/V5 -> 0.42610413 | W101: =W109/W5 -> 0.56526111 | X101: =X109/X5 -> 0.55976564 | Y101: =Y109/Y5 -> 0.63058699 | Z101: =Z109/Z5 -> 0.71458678 | AA101: =AA109/AA5 -> 0.62032197 | AC101: =AC109/AC5 -> 0.63662949
B103: Adjustments
B104: Tax rate | C104: =IF(AND(C82>=0,C11>=0),C82,0) -> 0 | D104: =IF(AND(D82>=0,D11>=0),D82,0) -> 0 | E104: =IF(AND(E82>=0,E11>=0),E82,0) -> 0 | F104: =IF(AND(F82>=0,F11>=0),F82,0) -> 0 | G104: =IF(AND(G82>=0,G11>=0),G82,0) -> 0 | H104: =IF(AND(H82>=0,H11>=0),H82,0) -> 0 | I104: =IF(AND(I82>=0,I11>=0),I82,0) -> 0 | J104: =IF(AND(J82>=0,J11>=0),J82,0) -> 0 | ... Q104: =IF(AND(Q82>=0,Q11>=0),Q82,0) -> 0.15117002 | T104: =IF(AND(T82>=0,T11>=0),T82,0) -> 0.13474637 | U104: =IF(AND(U82>=0,U11>=0),U82,0) -> 0.12396399 | V104: =IF(AND(V82>=0,V11>=0),V82,0) -> 0.14308535 | W104: =IF(AND(W82>=0,W11>=0),W82,0) -> 0.15330385 | X104: =IF(AND(X82>=0,X11>=0),X82,0) -> 0.15884648 | Y104: =IF(AND(Y82>=0,Y11>=0),Y82,0) -> 0.14756831 | Z104: =IF(AND(Z82>=0,Z11>=0),Z82,0) -> 0.16568674 | AA104: =IF(AND(AA82>=0,AA11>=0),AA82,0) -> 0.16528452 | AC104: =IF(AND(AC82>=0,AC11>=0),AC82,0) -> 0.16045755
B105: Cash | M105: =M28+M33 -> 21208 | N105: =N28+N33 -> 13296 | O105: =O28+O33 -> 25984 | P105: =P28+P33 -> 43210 | Q105: =Q28+Q33 -> 62556 | T105: =T28+T33 -> 38487 | U105: =U28+U33 -> 43210 | V105: =V28+V33 -> 53691 | W105: =W28+W33 -> 56791 | X105: =X28+X33 -> 60608 | Y105: =Y28+Y33 -> 62556 | Z105: =Z28+Z33 -> 80572 | AA105: =AA28+AA33 -> 99369 | AC105: =AA105 -> 99369
B106: Debt | C106: 0 | D106: 0 | E106: 0 | F106: 0 | G106: 0 | H106: 0 | I106: 0 | J106: 0 | K106: 0 | L106: 0 | M106: =M38+M40 -> 10946 | N106: =N38+N40 -> 10953 | O106: =O38+O40 -> 9709 | P106: =P38+P40 -> 8463 | Q106: =Q38+Q40 -> 8468 | T106: =T38+T40 -> 8462 | U106: =U38+U40 -> 8463 | V106: =V38+V40 -> 8464 | W106: =W38+W40 -> 8466 | X106: =X38+X40 -> 8467 | Y106: =Y38+Y40 -> 8568 | Z106: =Z38+Z40 -> 8470 | AA106: =AA38+AA40 -> 33266 | AC106: =AA106 -> 33266
B107: NOPAT | M107: =M11*(1-M104) -> 9850.0988 | N107: =N11*(1-N104) -> 4224 | O107: =O11*(1-O104) -> 29015.516 | P107: =P11*(1-P104) -> 70648.307 | Q107: =Q11*(1-Q104) -> 110676.39 | AC107: =AC11*(1-AC104) -> 165875.96
B108: Capex | M108: =M59+M60 -> -976 | N108: =N59+N60 -> -1833 | O108: =O59+O60 -> -1069 | P108: =P59+P60 -> -3236 | Q108: =Q59+Q60 -> -6042 | T108: =T59+T60 -> -813 | U108: =U59+U60 -> -1077 | V108: =V59+V60 -> -1227 | W108: =W59+W60 -> -1894 | X108: =X59+X60 -> -1637 | Y108: =Y59+Y60 -> -1284 | Z108: =Z59+Z60 -> -1757 | AA108: =AA59+AA60 -> -2677 | AC108: =AC59+AC60 -> -7355
B109: Net income with non-controlling | M109: =M16+M17 -> 9752 | N109: =N16+N17 -> 4368 | O109: =O16+O17 -> 29760 | P109: =P16+P17 -> 72880 | Q109: =Q16+Q17 -> 120067 | T109: =T16+T17 -> 19309 | U109: =U16+U17 -> 22091 | V109: =V16+V17 -> 18775 | W109: =W16+W17 -> 26422 | X109: =X16+X17 -> 31910 | Y109: =Y16+Y17 -> 42960 | Z109: =Z16+Z17 -> 58321 | AA109: =AA16+AA17 -> 59688 | AC109: =AC16+AC17 -> 192879
...

Sheet Analysis ->
H5: Links
H6: Overview'!B3
H7: Financials ->'!B13
H8: Analysis ->'!B13
H9: Forecast ->'!B13
H10: Valuation ->'!B13
B13: Analysis ->

Sheet Basic
B1: TTM/YTD data
B4: Overview | E4: CAGR
B5: Price | C5: =Overview!C5 -> 210.96 | F5: 5Y | G5: 10Y
B6: Market capitalization | C6: =Statement!AC155 -> 5104177.2 | E6: Revenue | F6: =IF(Statement!M5<=0,"N/A",_xlfn.RRI(4,Statement!M5,Statement!Q5)) -> 0.68301391 | G6: =IF(Statement!H5<=0,"N/A",_xlfn.RRI(9,Statement!H5,Statement!Q5)) -> N/A
B7: Enterprise value | C7: =Statement!AC156 -> 5038074.2 | E7: Net income | F7: =IF(OR(Statement!M17<=0, Statement!Q17<=0), "N/A", _xlfn.RRI(4, Statement!M17, Statement!Q17)) -> 0.87319285 | G7: =IF(OR(Statement!H17<=0, Statement!Q17<=0), "N/A", _xlfn.RRI(9, Statement!H17, Statement!Q17)) -> N/A
B8: PE | C8: =Statement!AC152 -> 26.670038 | E8: EPS | F8: =IF(OR(Statement!M25<=0, Statement!Q25<=0), "N/A", _xlfn.RRI(4, Statement!M25, Statement!Q25)) -> 0.88879071 | G8: =IF(OR(Statement!H25<=0, Statement!Q25<=0), "N/A", _xlfn.RRI(9, Statement!H25, Statement!Q25)) -> N/A
B9: PS | C9: =Statement!AC153 -> 16.98837 | E9: Dividend | F9: =IF(Statement!M81<=0,"N/A",_xlfn.RRI(4,Statement!M81,Statement!Q81)) -> 0.25743343 | G9: =IF(Statement!H81<=0,"N/A",_xlfn.RRI(9,Statement!H81,Statement!Q81)) -> N/A
B10: PB | C10: =Statement!AC154 -> 22.203019 | E10: Price | F10: =IF(Statement!M115<=0,"N/A",_xlfn.RRI(4,Statement!M115,Statement!Q115)) -> 0.69306912 | G10: =IF(Statement!H115<=0,"N/A",_xlfn.RRI(9,Statement!H115,Statement!Q115)) -> N/A
B11: EV/Revenue | C11: =Statement!AC157 -> 16.629009
B12: EV/EBIT | C12: =Statement!AC158 -> 25.499037
B15: Margins | E15: Earnings quality
B16: Gross margin | C16: =Statement!AC99 -> 0.74674637 | E16: Net income | F16: =Statement!AC17 -> 192879
B17: Operating margin | C17: =Statement!AC100 -> 0.65214263 | E17: Operating cash | F17: =Statement!AC58 -> 134361
B18: Net margin | C18: =Statement!AC101 -> 0.63662949 | E18: Cash accruals | F18: =IF(OR(F16<=0, F17<=0),"N/A",F16-F17) -> 58518
B21: DuPont Identity | E21: Performance indicators
B22: Profit Margin (Earnings/Revenue) | C22: =Statement!AC119 -> 0.63662949 | E22: ROA | F22: =C24 -> 0.60223498
B23: Asset Turnover (Revenue/Total assets) | C23: =Statement!AC120 -> 0.94597405 | E23: ROE | F23: =C26 -> 0.84232523
B24: ROA | C24: =Statement!AC121 -> 0.60223498 | E24: ROIC | F24: =Statement!AC142 -> 1.0183874
B25: Equity Multiplier (Total assets/Equity) | C25: =Statement!AC122 -> 1.3986654
B26: ROE | C26: =Statement!AC123 -> 0.84232523
B29: Cash conversion cycle | E29: Liquidity ratios
B30: DSO | C30: =Statement!AC143 -> 75.969934 | E30: Debt/Equity | F30: =Statement!AC147 -> 0.14527653
B31: DIO | C31: =Statement!AC144 -> 150.20429 | E31: Net Debt/Equity | F31: =Statement!AC148 -> -0.28867956
B32: DPO | C32: =Statement!AC145 -> 71.636625 | E32: Current ratio | F32: =Statement!AC150 -> 4.5889491
B33: Net trade cycle | C33: =Statement!AC146 -> 154.5376 | E33: Quick ratio | F33: =Statement!AC149 -> 3.775727
E34: Interest coverage | F34: =Statement!AC151 -> N/A
B37: Earnings yields | E37: Payout ratios
B38: Earnings yield | C38: =Statement!AC164 -> 0.03749526 | E38: Dividend payout ratio | F38: =Statement!AC170 -> 0.056577937
B39: FCF yield | C39: =Statement!AC163 -> 0.023463919 | E39: Buyback payout ratio | F39: =Statement!AC171 -> 0.46186667
B40: Dividend yield | C40: =Statement!AC165 -> 0.0013272658 | E40: Full payout ratio | F40: =Statement!AC172 -> 0.51844461
B41: Buyback yield | C41: =Statement!AC166 -> 0.010837202
B42: Total shareholder yield | C42: =Statement!AC167 -> 0.012164742
B45: Ownership | E45: Cash holdings
B46: Insider ownership | C46: =Statement!AC173 -> 0.039553627 | E46: Cash per share | F46: =Statement!AC174 -> 4.123195
E47: Net cash per share | F47: =Statement!AC177 -> 2.7428631
E48: Net cash to market cap | F48: =Statement!AC178 -> 0.012950765
B51: Stock based compensation | E51: CapEx usage
B52: Stock based compensation % OCF | C52: =Statement!AC175 -> 0.053899569 | E52: Capex to Revenue | F52: =Statement!AC179 -> 0.024276411
B53: Stock based compensation % Revenue | C53: =Statement!AC176 -> 0.023903436 | E53: CapEx to OCF | F53: =Statement!AC180 -> 0.054740587
E54: CapEx to D&A | F54: =Statement!AC181 -> 1.9948468

Sheet Yearly Analysis
C2: =Statement!M2 -> 30.01.2022 | D2: =Statement!N2 -> 29.01.2023 | E2: =Statement!O2 -> 28.01.2024 | F2: =Statement!P2 -> 26.01.2025 | G2: =Statement!Q2 -> 25.01.2026
C3: =Statement!M3 -> 2022 | D3: =Statement!N3 -> 2023 | E3: =Statement!O3 -> 2024 | F3: =Statement!P3 -> 2025 | G3: =Statement!Q3 -> 2026 | I3: =Statement!AC3 -> TTM/YTD
B5: Overview
B6: Price | C6: =Statement!M114 -> 228.4 | D6: =Statement!N114 -> 203.6 | E6: =Statement!O114 -> 610.3 | F6: =Statement!P114 -> 142.62 | G6: =Statement!Q114 -> 187.67 | I6: =Statement!AC114 -> 210.96
B7: Market capitalization | C7: =Statement!M155 -> 582191.6 | D7: =Statement!N155 -> 506964 | E7: =Statement!O155 -> 1541007.5 | F7: =Statement!P155 -> 3515440.4 | G7: =Statement!Q155 -> 4589469.8 | I7: =Statement!AC155 -> 5104177.2
B8: Enterprise value | C8: =Statement!M156 -> 571929.6 | D8: =Statement!N156 -> 504621 | E8: =Statement!O156 -> 1524732.5 | F8: =Statement!P156 -> 3480693.4 | G8: =Statement!Q156 -> 4535381.8 | I8: =Statement!AC156 -> 5038074.2
B9: PE | C9: =Statement!M152 -> 59.324675 | D9: =Statement!N152 -> 117.01149 | E9: =Statement!O152 -> 51.156748 | F9: =Statement!P152 -> 48.510204 | G9: =Statement!Q152 -> 38.3 | I9: =Statement!AC152 -> 26.670038
B10: PS | C10: =Statement!M153 -> 21.512744 | D10: =Statement!N153 -> 18.922859 | E10: =Statement!O153 -> 24.984213 | F10: =Statement!P153 -> 27.108259 | G10: =Statement!Q153 -> 21.304923 | I10: =Statement!AC153 -> 16.98837
B11: PB | C11: =Statement!M154 -> 21.542312 | D11: =Statement!N154 -> 22.754265 | E11: =Statement!O154 -> 35.500721 | F11: =Statement!P154 -> 43.868141 | G11: =Statement!Q154 -> 28.992905 | I11: =Statement!AC154 -> 22.203019
B12: EV/Revenue | C12: =Statement!M157 -> 21.250264 | D12: =Statement!N157 -> 18.707681 | E12: =Statement!O157 -> 25.027617 | F12: =Statement!P157 -> 26.672593 | G12: =Statement!Q157 -> 21.003167 | I12: =Statement!AC157 -> 16.629009
B13: EV/EBIT | C13: =Statement!M158 -> 56.959426 | D13: =Statement!N158 -> 119.4652 | E13: =Statement!O158 -> 46.243252 | F13: =Statement!P158 -> 42.732538 | G13: =Statement!Q158 -> 34.784003 | I13: =Statement!AC158 -> 25.499037
B15: Margins
B16: Gross margin | C16: =Statement!M99 -> 0.64929033 | D16: =Statement!N99 -> 0.56928894 | E16: =Statement!O99 -> 0.72717573 | F16: =Statement!P99 -> 0.74988697 | G16: =Statement!Q99 -> 0.71068084 | I16: =Statement!AC99 -> 0.74674637
B17: Operating margin | C17: =Statement!M100 -> 0.37307721 | D17: =Statement!N100 -> 0.15659524 | E17: =Statement!O100 -> 0.54121664 | F17: =Statement!P100 -> 0.62417527 | G17: =Statement!Q100 -> 0.60381684 | I17: =Statement!AC100 -> 0.65214263
B18: Net margin | C18: =Statement!M101 -> 0.3623393 | D18: =Statement!N101 -> 0.16193371 | E18: =Statement!O101 -> 0.48849348 | F18: =Statement!P101 -> 0.55848027 | G18: =Statement!Q101 -> 0.55602534 | I18: =Statement!AC101 -> 0.63662949
B20: Earnings quality
B21: Net income | C21: =Statement!M17 -> 9752 | D21: =Statement!N17 -> 4368 | E21: =Statement!O17 -> 29760 | F21: =Statement!P17 -> 72880 | G21: =Statement!Q17 -> 120067 | I21: =Statement!AC17 -> 192879
B22: Operating cash | C22: =Statement!M58 -> 9108 | D22: =Statement!N58 -> 5641 | E22: =Statement!O58 -> 28090 | F22: =Statement!P58 -> 64089 | G22: =Statement!Q58 -> 102718 | I22: =Statement!AC58 -> 134361
B23: Cash accruals | C23: =IF(OR(C21<=0, C22<=0),"N/A",C21-C22) -> 644 | D23: =IF(OR(D21<=0, D22<=0),"N/A",D21-D22) -> -1273 | E23: =IF(OR(E21<=0, E22<=0),"N/A",E21-E22) -> 1670 | F23: =IF(OR(F21<=0, F22<=0),"N/A",F21-F22) -> 8791 | G23: =IF(OR(G21<=0, G22<=0),"N/A",G21-G22) -> 17349 | I23: =IF(OR(I21<=0, I22<=0),"N/A",I21-I22) -> 58518
B25: DuPont Identity
B26: Profit Margin (Earnings/Revenue) | C26: =Statement!M119 -> 0.3623393 | D26: =Statement!N119 -> 0.16193371 | E26: =Statement!O119 -> 0.48849348 | F26: =Statement!P119 -> 0.55848027 | G26: =Statement!Q119 -> 0.55602534 | I26: =Statement!AC119 -> 0.63662949
B27: Asset Turnover (Revenue/Total assets) | C27: =Statement!M120 -> 0.60909317 | D27: =Statement!N120 -> 0.6549949 | E27: =Statement!O120 -> 0.92688048 | F27: =Statement!P120 -> 1.1693175 | G27: =Statement!Q120 -> 1.0441725 | I27: =Statement!AC120 -> 0.94597405
B28: ROA | C28: =Statement!M121 -> 0.2206984 | D28: =Statement!N121 -> 0.10606576 | E28: =Statement!O121 -> 0.45277507 | F28: =Statement!P121 -> 0.65304074 | G28: =Statement!Q121 -> 0.58058636 | I28: =Statement!AC121 -> 0.60223498
B29: Equity Multiplier (Total assets/Equity) | C29: =Statement!M122 -> 1.6604164 | D29: =Statement!N122 -> 1.8633546 | E29: =Statement!O122 -> 1.5293406 | F29: =Statement!P122 -> 1.4068476 | G29: =Statement!Q122 -> 1.3147629 | I29: =Statement!AC122 -> 1.3986654
B30: ROE | C30: =Statement!M123 -> 0.36645123 | D30: =Statement!N123 -> 0.19763812 | E30: =Statement!O123 -> 0.6924473 | F30: =Statement!P123 -> 0.91872881 | G30: =Statement!Q123 -> 0.7633334 | I30: =Statement!AC123 -> 0.84232523
B32: Performance Indicators
B33: ROA | C33: =C28 -> 0.2206984 | D33: =D28 -> 0.10606576 | E33: =E28 -> 0.45277507 | F33: =F28 -> 0.65304074 | G33: =G28 -> 0.58058636 | I33: =I28 -> 0.60223498
B34: ROE | C34: =C30 -> 0.36645123 | D34: =D30 -> 0.19763812 | E34: =E30 -> 0.6924473 | F34: =F30 -> 0.91872881 | G34: =G30 -> 0.7633334 | I34: =I30 -> 0.84232523
B35: ROIC | C35: =Statement!M142 -> 0.60245252 | D35: =Statement!N142 -> 0.21378682 | E35: =Statement!O142 -> 1.0866014 | F35: =Statement!P142 -> 1.5847534 | G35: =Statement!Q142 -> 1.0723937 | I35: =Statement!AC142 -> 1.0183874
B37: Cash conversion cycle
B38: DSO | C38: =Statement!M143 -> 63.061975 | D38: =Statement!N143 -> 51.785238 | E38: =Statement!O143 -> 59.906684 | F38: =Statement!P143 -> 64.512786 | G38: =Statement!Q143 -> 65.01908 | I38: =Statement!AC143 -> 75.969934
B39: DIO | C39: =Statement!M144 -> 100.73366 | D39: =Statement!N144 -> 162.0791 | E39: =Statement!O144 -> 115.99362 | F39: =Statement!P144 -> 112.72404 | G39: =Statement!Q144 -> 125.04354 | I39: =Statement!AC144 -> 150.20429
B40: DPO | C40: =Statement!M145 -> 68.947452 | D40: =Statement!N145 -> 37.480203 | E40: =Statement!O145 -> 59.270501 | F40: =Statement!P145 -> 70.564356 | G40: =Statement!Q145 -> 57.32501 | I40: =Statement!AC145 -> 71.636625
B41: Net trade cycle | C41: =Statement!M146 -> 94.848181 | D41: =Statement!N146 -> 176.38414 | E41: =Statement!O146 -> 116.62981 | F41: =Statement!P146 -> 106.67247 | G41: =Statement!Q146 -> 132.73761 | I41: =Statement!AC146 -> 154.5376
B43: Liquidity ratios
B44: Debt/Equity | C44: =Statement!M147 -> 0.4113182 | D44: =Statement!N147 -> 0.49558843 | E44: =Statement!O147 -> 0.22590628 | F44: =Statement!P147 -> 0.10668499 | G44: =Statement!Q147 -> 0.053835835 | I44: =Statement!AC147 -> 0.14527653
B45: Net Debt/Equity | C45: =Statement!M148 -> -0.38561551 | D45: =Statement!N148 -> -0.1060133 | E45: =Statement!O148 -> -0.37868212 | F45: =Statement!P148 -> -0.43802236 | G45: =Statement!Q148 -> -0.34386781 | I45: =Statement!AC148 -> -0.28867956
B46: Quick ratio | C46: =Statement!M149 -> 5.9649366 | D46: =Statement!N149 -> 2.6090203 | E46: =Statement!O149 -> 3.3847239 | F46: =Statement!P149 -> 3.6723555 | G46: =Statement!Q149 -> 3.1409383 | I46: =Statement!AC149 -> 3.775727
B47: Current ratio | C47: =Statement!M150 -> 6.6502884 | D47: =Statement!N150 -> 3.5156179 | E47: =Statement!O150 -> 4.1712915 | F47: =Statement!P150 -> 4.4398515 | G47: =Statement!Q150 -> 3.9052638 | I47: =Statement!AC150 -> 4.5889491
B48: Interest coverage | C48: =Statement!M151 -> 48.507246 | D48: =Statement!N151 -> N/A | E48: =Statement!O151 -> N/A | F48: =Statement!P151 -> N/A | G48: =Statement!Q151 -> N/A | I48: =Statement!AC151 -> N/A
B50: Earnings yields
B51: Earnings yield | C51: =Statement!M164 -> 0.016856392 | D51: =Statement!N164 -> 0.008546169 | E51: =Statement!O164 -> 0.019547763 | F51: =Statement!P164 -> 0.02061422 | G51: =Statement!Q164 -> 0.026109661 | I51: =Statement!AC164 -> 0.03749526
B52: FCF yield | C52: =Statement!M163 -> 0.010525744 | D52: =Statement!N163 -> 0.0021678068 | E52: =Statement!O163 -> 0.015231594 | F52: =Statement!P163 -> 0.015962723 | G52: =Statement!Q163 -> 0.019673296 | I52: =Statement!AC163 -> 0.023463919
B53: Dividend yield | C53: =Statement!M165 -> 0.00070052539 | D53: =Statement!N165 -> 0.00078585462 | E53: =Statement!O165 -> 0.00026216615 | F53: =Statement!P165 -> 0.00023839574 | G53: =Statement!Q165 -> 0.00021314009 | I53: =Statement!AC165 -> 0.0013272658
B54: Buyback yield | C54: =Statement!M166 -> 0 | D54: =Statement!N166 -> 0.019802195 | E54: =Statement!O166 -> 0.0061862126 | F54: =Statement!P166 -> 0.0095879879 | G54: =Statement!Q166 -> 0.0087343422 | I54: =Statement!AC166 -> 0.010837202
B55: Total shareholder yield | C55: =Statement!M167 -> 0.00068534139 | D55: =Statement!N167 -> 0.020587261 | E55: =Statement!O167 -> 0.0064425384 | F55: =Statement!P167 -> 0.0098252271 | G55: =Statement!Q167 -> 0.0089465671 | I55: =Statement!AC167 -> 0.012164742
B57: Payout ratios
B58: Dividend payout ratio | C58: =Statement!M170 -> 0.065110966 | D58: =Statement!N170 -> 0.36214741 | E58: =Statement!O170 -> 0.016828562 | F58: =Statement!P170 -> 0.014862071 | G58: =Statement!Q170 -> 0.010787463 | I58: =Statement!AC170 -> 0.056577937
B59: Buyback payout ratio | C59: =Statement!M171 -> 0 | D59: =Statement!N171 -> 9.1346679 | E59: =Statement!O171 -> 0.40614349 | F59: =Statement!P171 -> 0.60064866 | G59: =Statement!Q171 -> 0.44396943 | I59: =Statement!AC171 -> 0.46186667
B60: Full payout ratio | C60: =Statement!M172 -> 0.065110966 | D60: =Statement!N172 -> 9.4968153 | E60: =Statement!O172 -> 0.42297205 | F60: =Statement!P172 -> 0.61551073 | G60: =Statement!Q172 -> 0.45475689 | I60: =Statement!AC172 -> 0.51844461
B62: Ownership
B63: Insider ownership | C63: =Statement!M173 -> 0.039623382 | D63: =Statement!N173 -> 0.039759036 | E63: =Statement!O173 -> 0.041188119 | F63: =Statement!P173 -> 0.041380989 | G63: =Statement!Q173 -> 0.039133102 | I63: =Statement!AC173 -> 0.039553627
B65: Cash holdings
B66: Cash per share | C66: =Statement!M174 -> 0.84494024 | D66: =Statement!N174 -> 0.5382996 | E66: =Statement!O174 -> 1.03936 | F66: =Statement!P174 -> 1.7709016 | G66: =Statement!Q174 -> 2.574321 | I66: =Statement!AC174 -> 4.123195
B67: Net cash per share | C67: =Statement!M177 -> 0.40884462 | D67: =Statement!N177 -> 0.0948583 | E67: =Statement!O177 -> 0.651 | F67: =Statement!P177 -> 1.4240574 | G67: =Statement!Q177 -> 2.2258436 | I67: =Statement!AC177 -> 2.7428631
B68: Net cash to market cap | C68: =Statement!M178 -> 0.0176265 | D68: =Statement!N178 -> 0.0046216299 | E68: =Statement!O178 -> 0.010561272 | F68: =Statement!P178 -> 0.0098841102 | G68: =Statement!Q178 -> 0.011785239 | I68: =Statement!AC178 -> 0.012950765
B70: Stock Based Compensation
B71: Stock based compensation % OCF | C71: =Statement!M175 -> 0.22002635 | D71: =Statement!N175 -> 0.480234 | E71: =Statement!O175 -> 0.12634389 | F71: =Statement!P175 -> 0.07391284 | G71: =Statement!Q175 -> 0.062170214 | I71: =Statement!AC175 -> 0.053899569
B72: Stock based compensation % Revenue | C72: =Statement!M176 -> 0.074459389 | D72: =Statement!N176 -> 0.10043004 | E72: =Statement!O176 -> 0.058254818 | F72: =Statement!P176 -> 0.036299685 | G72: =Statement!Q176 -> 0.029573303 | I72: =Statement!AC176 -> 0.023903436
B74: CapEx Usage
B75: Capex to Revenue | C75: =Statement!M179 -> 0.036263655 | D75: =Statement!N179 -> 0.067954326 | E75: =Statement!O179 -> 0.017547027 | F75: =Statement!P179 -> 0.024797505 | G75: =Statement!Q179 -> 0.027980254 | I75: =Statement!AC179 -> 0.024276411
B76: CapEx to OCF | C76: =Statement!M180 -> 0.10715854 | D76: =Statement!N180 -> 0.32494239 | E76: =Statement!O180 -> 0.038056248 | F76: =Statement!P180 -> 0.050492284 | G76: =Statement!Q180 -> 0.058821239 | I76: =Statement!AC180 -> 0.054740587
B77: CapEx to D&A | C77: =Statement!M181 -> 0.83134583 | D77: =Statement!N181 -> 1.1871762 | E77: =Statement!O181 -> 0.70888594 | F77: =Statement!P181 -> 1.7360515 | G77: =Statement!Q181 -> 2.1252198 | I77: =Statement!AC181 -> 1.9948468
B79: Growth rates
B80: Revenue | C80: =Statement!M88 -> 1 | D80: =Statement!N88 -> 0.002229323 | E80: =Statement!O88 -> 1.2585453 | F80: =Statement!P88 -> 1.1420341 | G80: =Statement!Q88 -> 0.65473536
B81: COGS | C81: =Statement!M89 -> 1 | D81: =Statement!N89 -> 0.23085073 | E81: =Statement!O89 -> 0.43062489 | F81: =Statement!P89 -> 0.96372059 | G81: =Statement!Q89 -> 0.91412114
B82: Gross Profit | C82: =Statement!M90 -> 1 | D82: =Statement!N90 -> -0.12125894 | E82: =Statement!O90 -> 1.884931 | F82: =Statement!P90 -> 1.2089343 | G82: =Statement!Q90 -> 0.5682213
B83: OpEx | C83: =Statement!M93 -> 1 | D83: =Statement!N93 -> 0.49744418 | E83: =Statement!O93 -> 0.01769673 | F83: =Statement!P93 -> 0.44805367 | G83: =Statement!Q93 -> 0.40664432
B84: Operating Income | C84: =Statement!M94 -> 1 | D84: =Statement!N94 -> -0.57932477 | E84: =Statement!O94 -> 6.8058712 | F84: =Statement!P94 -> 1.4703688 | G84: =Statement!Q94 -> 0.60076363
B85: Net Income | C85: =Statement!M96 -> 1 | D85: =Statement!N96 -> -0.55209188 | E85: =Statement!O96 -> 5.8131868 | F85: =Statement!P96 -> 1.4489247 | G85: =Statement!Q96 -> 0.64746158
B88: Growth rates breakdown
B89: HyperScale | C89: =Statement!M196 -> 0 | D89: =Statement!N196 -> 0 | E89: =Statement!O196 -> 0 | F89: =Statement!P196 -> 1 | G89: =Statement!Q196 -> 0.96364042
B90: AI Clouds | C90: =Statement!M197 -> 0 | D90: =Statement!N197 -> 0 | E90: =Statement!O197 -> 0 | F90: =Statement!P197 -> 1 | G90: =Statement!Q197 -> 0.43510344
B91: Data Center | C91: =Statement!M198 -> 0 | D91: =Statement!N198 -> 0 | E91: =Statement!O198 -> 0 | F91: =Statement!P198 -> 1 | G91: =Statement!Q198 -> 0.6819492
B92: Edge Computing | C92: =Statement!M199 -> 0 | D92: =Statement!N199 -> 0 | E92: =Statement!O199 -> 0 | F92: =Statement!P199 -> 1 | G92: =Statement!Q199 -> 0.45000327
B94: Other growth rates
B95: Dividends | C95: =Statement!M202 -> 0 | D95: =Statement!N203 -> -0.0025062657 | E95: =Statement!O203 -> -0.0075376884 | F95: =Statement!P203 -> 1.1113924 | G95: =Statement!Q203 -> 0.16786571

Sheet Quarter analysis
C3: Latest 2 quarters | F3: YoY
C4: =Statement!Z2 -> 26.04.2026 | D4: =Statement!AA2 -> 26.07.2026 | F4: =Statement!W2 -> 27.07.2025 | G4: =Statement!AA2 -> 26.07.2026
B5: Income statement growth | C5: =Statement!Z3 -> Q1 2027 | D5: =Statement!AA3 -> Q2 2027 | F5: =Statement!W3 -> Q2 2026 | G5: =Statement!AA3 -> Q2 2027
B6: Revenue | C6: =Statement!Z5 -> 81615 | D6: =Statement!AA5 -> 96221 | F6: =Statement!W5 -> 46743 | G6: =Statement!AA5 -> 96221
B7: Growth | C7: =Statement!AA88 -> 0.1789622 | F7: =IF(F6=0, IF(G6=0,0,IF(G6>0,1,-1)), (G6-F6)/ABS(F6) ) -> 1.0585114
B8: COGS | C8: =Statement!Z6 -> 20458 | D8: =Statement!AA6 -> 24079 | F8: =Statement!W6 -> 12890 | G8: =Statement!AA6 -> 24079
B9: Growth | C9: =Statement!AA89 -> 0.17699677 | F9: =IF(F8=0, IF(G8=0,0,IF(G8>0,1,-1)), (G8-F8)/ABS(F8) ) -> 0.86803724
B10: Gross Profit | C10: =Statement!Z7 -> 61157 | D10: =Statement!AA7 -> 72142 | F10: =Statement!W7 -> 33853 | G10: =Statement!AA7 -> 72142
B11: Growth | C11: =Statement!AA90 -> 0.17961967 | F11: =IF(F10=0, IF(G10=0,0,IF(G10>0,1,-1)), (G10-F10)/ABS(F10) ) -> 1.1310371
B12: OpEx | C12: =Statement!Z10 -> 7621 | D12: =Statement!AA10 -> 8408 | F12: =Statement!W10 -> 5413 | G12: =Statement!AA10 -> 8408
B13: Growth | C13: =Statement!AA93 -> 0.10326729 | F13: =IF(F12=0, IF(G12=0,0,IF(G12>0,1,-1)), (G12-F12)/ABS(F12) ) -> 0.55329762
B14: Operating profit | C14: =Statement!Z11 -> 53536 | D14: =Statement!AA11 -> 63734 | F14: =Statement!W11 -> 28440 | G14: =Statement!AA11 -> 63734
B15: Growth | C15: =Statement!AA94 -> 0.19048864 | F15: =IF(F14=0, IF(G14=0,0,IF(G14>0,1,-1)), (G14-F14)/ABS(F14) ) -> 1.2409986
B16: Net income | C16: =Statement!Z17 -> 58321 | D16: =Statement!AA17 -> 59688 | F16: =Statement!W17 -> 26422 | G16: =Statement!AA17 -> 59688
B17: Growth | C17: =Statement!AA96 -> 0.023439241 | F17: =IF(F16=0, IF(G16=0,0,IF(G16>0,1,-1)), (G16-F16)/ABS(F16) ) -> 1.2590266
B18: Diluted shares outstanding | C18: =Statement!Z21 -> 24391 | D18: =Statement!AA21 -> 24285 | F18: =Statement!W21 -> 24532 | G18: =Statement!AA21 -> 24285
B19: Growth | C19: =IF(C18=0, IF(D18=0,0,IF(D18>0,1,-1)), (D18-C18)/ABS(C18) ) -> -0.0043458653 | F19: =IF(F18=0, IF(G18=0,0,IF(G18>0,1,-1)), (G18-F18)/ABS(F18) ) -> -0.010068482
B20: Diluted EPS | C20: =Statement!Z25 -> 2.39 | D20: =Statement!AA25 -> 2.46 | F20: =Statement!W25 -> 1.08 | G20: =Statement!AA25 -> 2.46
B21: Growth | C21: =IF(C20=0, IF(D20=0,0,IF(D20>0,1,-1)), (D20-C20)/ABS(C20) ) -> 0.029288703 | F21: =IF(F20=0, IF(G20=0,0,IF(G20>0,1,-1)), (G20-F20)/ABS(F20) ) -> 1.2777778
B23: Revenue breakdown | C23: =C5 -> Q1 2027 | D23: =D5 -> Q2 2027 | F23: =F5 -> Q2 2026 | G23: =G5 -> Q2 2027
B24: HyperScale | C24: =Statement!Z189 -> 37869 | D24: =Statement!AA189 -> 48710 | F24: =Statement!W189 -> 23883 | G24: =Statement!AA189 -> 48710
B25: Growth | C25: =IF(C24=0, IF(D24=0,0,IF(D24>0,1,-1)), (D24-C24)/ABS(C24) ) -> 0.28627637 | F25: =IF(F24=0, IF(G24=0,0,IF(G24>0,1,-1)), (G24-F24)/ABS(F24) ) -> 1.039526
B26: AI Clouds | C26: =Statement!Z190 -> 37377 | D26: =Statement!AA190 -> 40313 | F26: =Statement!W190 -> 17213 | G26: =Statement!AA190 -> 40313
B27: Growth | C27: =IF(C26=0, IF(D26=0,0,IF(D26>0,1,-1)), (D26-C26)/ABS(C26) ) -> 0.078550981 | F27: =IF(F26=0, IF(G26=0,0,IF(G26>0,1,-1)), (G26-F26)/ABS(F26) ) -> 1.3420089
B28: Data Center | C28: =Statement!Z191 -> 75246 | D28: =Statement!AA191 -> 89023 | F28: =Statement!W191 -> 41096 | G28: =Statement!AA191 -> 89023
B29: Growth | C29: =IF(C28=0, IF(D28=0,0,IF(D28>0,1,-1)), (D28-C28)/ABS(C28) ) -> 0.18309279 | F29: =IF(F28=0, IF(G28=0,0,IF(G28>0,1,-1)), (G28-F28)/ABS(F28) ) -> 1.1662206
B30: Edge Computing | C30: =Statement!Z192 -> 6369 | D30: =Statement!AA192 -> 7198 | F30: =Statement!W192 -> 5647 | G30: =Statement!AA192 -> 7198
B31: Growth | C31: =IF(C30=0, IF(D30=0,0,IF(D30>0,1,-1)), (D30-C30)/ABS(C30) ) -> 0.13016172 | F31: =IF(F30=0, IF(G30=0,0,IF(G30>0,1,-1)), (G30-F30)/ABS(F30) ) -> 0.27465911

Sheet Graphs Year
C55: =Statement!H2 -> 0 | D55: =Statement!I2 -> 0 | E55: =Statement!J2 -> 0 | F55: =Statement!K2 -> 0 | G55: =Statement!L2 -> 0 | H55: =Statement!M2 -> 30.01.2022 | I55: =Statement!N2 -> 29.01.2023 | J55: =Statement!O2 -> 28.01.2024 | ... L55: =Statement!Q2 -> 25.01.2026
C56: =Statement!H3 -> 0 | D56: =Statement!I3 -> 0 | E56: =Statement!J3 -> 0 | F56: =Statement!K3 -> 0 | G56: =Statement!L3 -> 0 | H56: =Statement!M3 -> 2022 | I56: =Statement!N3 -> 2023 | J56: =Statement!O3 -> 2024 | ... L56: =Statement!Q3 -> 2026
B57: Revenue | C57: =Statement!H5 -> 0 | D57: =Statement!I5 -> 0 | E57: =Statement!J5 -> 0 | F57: =Statement!K5 -> 0 | G57: =Statement!L5 -> 0 | H57: =Statement!M5 -> 26914 | I57: =Statement!N5 -> 26974 | J57: =Statement!O5 -> 60922 | ... L57: =Statement!Q5 -> 215938
B58: Operating income | C58: =Statement!H11 -> 0 | D58: =Statement!I11 -> 0 | E58: =Statement!J11 -> 0 | F58: =Statement!K11 -> 0 | G58: =Statement!L11 -> 0 | H58: =Statement!M11 -> 10041 | I58: =Statement!N11 -> 4224 | J58: =Statement!O11 -> 32972 | ... L58: =Statement!Q11 -> 130387
B59: Net income | C59: =Statement!H17 -> 0 | D59: =Statement!I17 -> 0 | E59: =Statement!J17 -> 0 | F59: =Statement!K17 -> 0 | G59: =Statement!L17 -> 0 | H59: =Statement!M17 -> 9752 | I59: =Statement!N17 -> 4368 | J59: =Statement!O17 -> 29760 | ... L59: =Statement!Q17 -> 120067
B60: FCFE | C60: =Statement!H159 -> 0 | D60: =Statement!I159 -> 0 | E60: =Statement!J159 -> 0 | F60: =Statement!K159 -> 0 | G60: =Statement!L159 -> 0 | H60: =Statement!M159 -> 6128 | I60: =Statement!N159 -> 1099 | J60: =Statement!O159 -> 23472 | ... L60: =Statement!Q159 -> 90290
B61: FCFF | C61: =Statement!H160 -> 0 | D61: =Statement!I160 -> 0 | E61: =Statement!J160 -> 0 | F61: =Statement!K160 -> 0 | G61: =Statement!L160 -> 0 | H61: =Statement!M160 -> 6685.0988 | I61: =Statement!N160 -> 1728 | J61: =Statement!O160 -> 25732.516 | ... L61: =Statement!Q160 -> 91501.394
B62: Gross margin | C62: =Statement!H99 -> 0 | D62: =Statement!I99 -> 0 | E62: =Statement!J99 -> 0 | F62: =Statement!K99 -> 0 | G62: =Statement!L99 -> 0 | H62: =Statement!M99 -> 0.64929033 | I62: =Statement!N99 -> 0.56928894 | J62: =Statement!O99 -> 0.72717573 | ... L62: =Statement!Q99 -> 0.71068084
B63: Operating margin | C63: =Statement!H100 -> 0 | D63: =Statement!I100 -> 0 | E63: =Statement!J100 -> 0 | F63: =Statement!K100 -> 0 | G63: =Statement!L100 -> 0 | H63: =Statement!M100 -> 0.37307721 | I63: =Statement!N100 -> 0.15659524 | J63: =Statement!O100 -> 0.54121664 | ... L63: =Statement!Q100 -> 0.60381684
B64: Net margin | C64: =Statement!H101 -> 0 | D64: =Statement!I101 -> 0 | E64: =Statement!J101 -> 0 | F64: =Statement!K101 -> 0 | G64: =Statement!L101 -> 0 | H64: =Statement!M101 -> 0.3623393 | I64: =Statement!N101 -> 0.16193371 | J64: =Statement!O101 -> 0.48849348 | ... L64: =Statement!Q101 -> 0.55602534
B65: Revenue HyperScale | C65: =Statement!H189 -> 0 | D65: =Statement!I189 -> 0 | E65: =Statement!J189 -> 0 | F65: =Statement!K189 -> 0 | G65: =Statement!L189 -> 0 | H65: =Statement!M189 -> 0 | I65: =Statement!N189 -> 0 | J65: =Statement!O189 -> 0 | ... L65: =Statement!Q189 -> 105636
B66: Revenue AI Clouds | C66: =Statement!H190 -> 0 | D66: =Statement!I190 -> 0 | E66: =Statement!J190 -> 0 | F66: =Statement!K190 -> 0 | G66: =Statement!L190 -> 0 | H66: =Statement!M190 -> 0 | I66: =Statement!N190 -> 0 | J66: =Statement!O190 -> 0 | ... L66: =Statement!Q190 -> 88101
B67: Revenue Edge Computing | C67: =Statement!H192 -> 0 | D67: =Statement!I192 -> 0 | E67: =Statement!J192 -> 0 | F67: =Statement!K192 -> 0 | G67: =Statement!L192 -> 0 | H67: =Statement!M192 -> 0 | I67: =Statement!N192 -> 0 | J67: =Statement!O192 -> 0 | ... L67: =Statement!Q192 -> 22201
B68: ROA | C68: =Statement!H121 -> 0 | D68: =Statement!I121 -> 0 | E68: =Statement!J121 -> 0 | F68: =Statement!K121 -> 0 | G68: =Statement!L121 -> 0 | H68: =Statement!M121 -> 0.2206984 | I68: =Statement!N121 -> 0.10606576 | J68: =Statement!O121 -> 0.45277507 | ... L68: =Statement!Q121 -> 0.58058636
B69: ROE | C69: =Statement!H123 -> 0 | D69: =Statement!I123 -> 0 | E69: =Statement!J123 -> 0 | F69: =Statement!K123 -> 0 | G69: =Statement!L123 -> 0 | H69: =Statement!M123 -> 0.36645123 | I69: =Statement!N123 -> 0.19763812 | J69: =Statement!O123 -> 0.6924473 | ... L69: =Statement!Q123 -> 0.7633334
B70: ROIC | C70: =Statement!H142 -> 0 | D70: =Statement!I142 -> 0 | E70: =Statement!J142 -> 0 | F70: =Statement!K142 -> 0 | G70: =Statement!L142 -> 0 | H70: =Statement!M142 -> 0.60245252 | I70: =Statement!N142 -> 0.21378682 | J70: =Statement!O142 -> 1.0866014 | ... L70: =Statement!Q142 -> 1.0723937
B71: Price 5y | C71: =Statement!H207 -> 0 | D71: =Statement!I207 -> 0 | E71: =Statement!J207 -> 0 | F71: =Statement!K207 -> 0 | G71: =Statement!L207 -> 0 | H71: =Statement!M207 -> 100 | I71: =Statement!N207 -> 89.141856 | J71: =Statement!O207 -> 267.20665 | ... L71: =Statement!Q207 -> 821.6725
B72: Revenue 5y | C72: =Statement!H208 -> 0 | D72: =Statement!I208 -> 0 | E72: =Statement!J208 -> 0 | F72: =Statement!K208 -> 0 | G72: =Statement!L208 -> 0 | H72: =Statement!M208 -> 100 | I72: =Statement!N208 -> 100.22293 | J72: =Statement!O208 -> 226.35803 | ... L72: =Statement!Q208 -> 802.32593
B73: EPS 5y | C73: =Statement!H209 -> 0 | D73: =Statement!I209 -> 0 | E73: =Statement!J209 -> 0 | F73: =Statement!K209 -> 0 | G73: =Statement!L209 -> 0 | H73: =Statement!M209 -> 100 | I73: =Statement!N209 -> 45.194805 | J73: =Statement!O209 -> 309.87013 | ... L73: =Statement!Q209 -> 1272.7273

Sheet Graphs Quarter
C55: =Statement!T2 -> 27.10.2024 | D55: =Statement!U2 -> 26.01.2025 | E55: =Statement!V2 -> 27.04.2025 | F55: =Statement!W2 -> 27.07.2025 | G55: =Statement!X2 -> 26.10.2025 | H55: =Statement!Y2 -> 25.01.2026 | I55: =Statement!Z2 -> 26.04.2026 | J55: =Statement!AA2 -> 26.07.2026
C56: =Statement!T3 -> Q3 2025 | D56: =Statement!U3 -> Q4 2025 | E56: =Statement!V3 -> Q1 2026 | F56: =Statement!W3 -> Q2 2026 | G56: =Statement!X3 -> Q3 2026 | H56: =Statement!Y3 -> Q4 2026 | I56: =Statement!Z3 -> Q1 2027 | J56: =Statement!AA3 -> Q2 2027
B57: Revenue | C57: =Statement!T5 -> 35082 | D57: =Statement!U5 -> 39331 | E57: =Statement!V5 -> 44062 | F57: =Statement!W5 -> 46743 | G57: =Statement!X5 -> 57006 | H57: =Statement!Y5 -> 68127 | I57: =Statement!Z5 -> 81615 | J57: =Statement!AA5 -> 96221
B58: Operating income | C58: =Statement!T11 -> 21869 | D58: =Statement!U11 -> 24034 | E58: =Statement!V11 -> 21638 | F58: =Statement!W11 -> 28440 | G58: =Statement!X11 -> 36010 | H58: =Statement!Y11 -> 44299 | I58: =Statement!Z11 -> 53536 | J58: =Statement!AA11 -> 63734
B59: Net income | C59: =Statement!T17 -> 19309 | D59: =Statement!U17 -> 22091 | E59: =Statement!V17 -> 18775 | F59: =Statement!W17 -> 26422 | G59: =Statement!X17 -> 31910 | H59: =Statement!Y17 -> 42960 | I59: =Statement!Z17 -> 58321 | J59: =Statement!AA17 -> 59688
B60: Gross margin | C60: =Statement!T99 -> 0.74556753 | D60: =Statement!U99 -> 0.73028908 | E60: =Statement!V99 -> 0.60523807 | F60: =Statement!W99 -> 0.72423678 | G60: =Statement!X99 -> 0.73411571 | H60: =Statement!Y99 -> 0.74996697 | I60: =Statement!Z99 -> 0.74933529 | J60: =Statement!AA99 -> 0.74975317
B61: Operating margin | C61: =Statement!T100 -> 0.62336811 | D61: =Statement!U100 -> 0.61107015 | E61: =Statement!V100 -> 0.49108075 | F61: =Statement!W100 -> 0.60843335 | G61: =Statement!X100 -> 0.63168789 | H61: =Statement!Y100 -> 0.65024146 | I61: =Statement!Z100 -> 0.65595785 | J61: =Statement!AA100 -> 0.662371
B62: Net margin | C62: =Statement!T101 -> 0.55039621 | D62: =Statement!U101 -> 0.56166891 | E62: =Statement!V101 -> 0.42610413 | F62: =Statement!W101 -> 0.56526111 | G62: =Statement!X101 -> 0.55976564 | H62: =Statement!Y101 -> 0.63058699 | I62: =Statement!Z101 -> 0.71458678 | J62: =Statement!AA101 -> 0.62032197
B63: Revenue HyperScale | C63: =Statement!T189 -> 13390 | D63: =Statement!U189 -> 19094 | E63: =Statement!V189 -> 17599 | F63: =Statement!W189 -> 23883 | G63: =Statement!X189 -> 30340 | H63: =Statement!Y189 -> 33814 | I63: =Statement!Z189 -> 37869 | J63: =Statement!AA189 -> 48710
B64: Revenue AI | C64: =Statement!T190 -> 17381 | D64: =Statement!U190 -> 16486 | E64: =Statement!V190 -> 21513 | F64: =Statement!W190 -> 17213 | G64: =Statement!X190 -> 20875 | H64: =Statement!Y190 -> 28500 | I64: =Statement!Z190 -> 37377 | J64: =Statement!AA190 -> 40313
B65: Revenue Edge | C65: =Statement!T192 -> 4311 | D65: =Statement!U192 -> 3751 | E65: =Statement!V192 -> 4950 | F65: =Statement!W192 -> 5647 | G65: =Statement!X192 -> 5791 | H65: =Statement!Y192 -> 5813 | I65: =Statement!Z192 -> 6369 | J65: =Statement!AA192 -> 7198
B66: FCFE | C66: =Statement!T159 -> 15564 | D66: =Statement!U159 -> 14230 | E66: =Statement!V159 -> 24713 | F66: =Statement!W159 -> 11847 | G66: =Statement!X159 -> 20458 | H66: =Statement!Y159 -> 33273 | I66: =Statement!Z159 -> 46659 | J66: =Statement!AA159 -> 19374

Sheet Forecast ->
H5: Links
H6: Overview'!B3
H7: Financials ->'!B13
H8: Analysis ->'!B13
H9: Forecast ->'!B13
H10: Valuation ->'!B13
B13: Forecast ->

Sheet Revenue
B1: Revenue forecast
C2: History | H2: Forecast | S2: History | AA2: Forecast | AE2: TTM
C4: Revenues | S4: Revenues
B5: Revenues (thousand) | C5: =Statement!M3 -> 2022 | D5: =Statement!N3 -> 2023 | E5: =Statement!O3 -> 2024 | F5: =Statement!P3 -> 2025 | G5: =Statement!Q3 -> 2026 | H5: =G5+1 -> 2027 | I5: =H5+1 -> 2028 | J5: =I5+1 -> 2029 | K5: =J5+1 -> 2030 | L5: =K5+1 -> 2031 | R5: =B5 -> Revenues (thousand) | S5: =Statement!T3 -> Q3 2025 | T5: =Statement!U3 -> Q4 2025 | U5: =Statement!V3 -> Q1 2026 | V5: =Statement!W3 -> Q2 2026 | W5: =Statement!X3 -> Q3 2026 | X5: =Statement!Y3 -> Q4 2026 | Y5: =Statement!Z3 -> Q1 2027 | Z5: =Statement!AA3 -> Q2 2027 | AA5: FQ1 | AB5: FQ2 | AC5: FQ3 | AE5: FQ1
B6: =Statement!B189 -> HyperScale | C6: =Statement!M189 -> 0 | D6: =Statement!N189 -> 0 | E6: =Statement!O189 -> 0 | F6: =Statement!P189 -> 53796 | G6: =Statement!Q189 -> 105636 | H6: =G6+G6*H14 -> 205990.2 | I6: =H6+H6*I14 -> 360482.85 | J6: =I6+I6*J14 -> 558748.42 | K6: =J6+J6*K14 -> 698435.52 | L6: =K6+K6*L14 -> 768279.07 | N6: HyperScale Growth Rate | Q6: HyperScale Growth Rate | R6: =B6 -> HyperScale | S6: =Statement!T189 -> 13390 | T6: =Statement!U189 -> 19094 | U6: =Statement!V189 -> 17599 | V6: =Statement!W189 -> 23883 | W6: =Statement!X189 -> 30340 | X6: =Statement!Y189 -> 33814 | Y6: =Statement!Z189 -> 37869 | Z6: =Statement!AA189 -> 48710 | AA6: =Z6+Z6*AA14 -> 53581 | AE6: =SUM(X6:AA6) -> 173974
B7: =Statement!B190 -> AI Clouds | C7: =Statement!M190 -> 0 | D7: =Statement!N190 -> 0 | E7: =Statement!O190 -> 0 | F7: =Statement!P190 -> 61390 | G7: =Statement!Q190 -> 88101 | H7: =G7+G7*H15 -> 154176.75 | I7: =H7+H7*I15 -> 254391.64 | J7: =I7+I7*J15 -> 356148.29 | K7: =J7+J7*K15 -> 391763.12 | L7: =K7+K7*L15 -> 411351.28 | N7: AI Growth Rate | Q7: AI Growth Rate | R7: =B7 -> AI Clouds | S7: =Statement!T190 -> 17381 | T7: =Statement!U190 -> 16486 | U7: =Statement!V190 -> 21513 | V7: =Statement!W190 -> 17213 | W7: =Statement!X190 -> 20875 | X7: =Statement!Y190 -> 28500 | Y7: =Statement!Z190 -> 37377 | Z7: =Statement!AA190 -> 40313 | AA7: =Z7+Z7*AA15 -> 47569.34 | AE7: =SUM(X7:AA7) -> 153759.34
B8: =Statement!B191 -> Data Center | C8: =Statement!M191 -> 0 | D8: =Statement!N191 -> 0 | E8: =Statement!O191 -> 0 | F8: =Statement!P191 -> 115186 | G8: =Statement!Q191 -> 193737 | H8: =SUM(H6:H7) -> 360166.95 | I8: =SUM(I6:I7) -> 614874.49 | J8: =SUM(J6:J7) -> 914896.71 | K8: =SUM(K6:K7) -> 1090198.6 | L8: =SUM(L6:L7) -> 1179630.4 | R8: =B8 -> Data Center | S8: =Statement!T191 -> 30771 | T8: =Statement!U191 -> 35580 | U8: =Statement!V191 -> 39112 | V8: =Statement!W191 -> 41096 | W8: =Statement!X191 -> 51215 | X8: =Statement!Y191 -> 62314 | Y8: =Statement!Z191 -> 75246 | Z8: =Statement!AA191 -> 89023 | AA8: =SUM(AA6:AA7) -> 101150.34 | AE8: =SUM(X8:AA8) -> 327733.34
B9: =Statement!B192 -> Edge Computing | C9: =Statement!M192 -> 0 | D9: =Statement!N192 -> 0 | E9: =Statement!O192 -> 0 | F9: =Statement!P192 -> 15311 | G9: =Statement!Q192 -> 22201 | H9: =G9+G9*H17 -> 33301.5 | I9: =H9+H9*I17 -> 49952.25 | J9: =I9+I9*J17 -> 72430.762 | K9: =J9+J9*K17 -> 94159.991 | L9: =K9+K9*L17 -> 103575.99 | N9: Edge Growth Rate | Q9: Edge Growth Rate | R9: =B9 -> Edge Computing | S9: =Statement!T192 -> 4311 | T9: =Statement!U192 -> 3751 | U9: =Statement!V192 -> 4950 | V9: =Statement!W192 -> 5647 | W9: =Statement!X192 -> 5791 | X9: =Statement!Y192 -> 5813 | Y9: =Statement!Z192 -> 6369 | Z9: =Statement!AA192 -> 7198 | AA9: =Z9+Z9*AA17 -> 7845.82 | AE9: =SUM(X9:AA9) -> 27225.82
B10: Total | C10: =Statement!M5 -> 26914 | D10: =Statement!N5 -> 26974 | E10: =Statement!O5 -> 60922 | F10: =Statement!P5 -> 130497 | G10: =Statement!Q5 -> 215938 | H10: =SUM(H8:H9) -> 393468.45 | I10: =SUM(I8:I9) -> 664826.74 | J10: =SUM(J8:J9) -> 987327.47 | K10: =SUM(K8:K9) -> 1184358.6 | L10: =SUM(L8:L9) -> 1283206.3 | R10: Total | S10: =Statement!T5 -> 35082 | T10: =Statement!U5 -> 39331 | U10: =Statement!V5 -> 44062 | V10: =Statement!W5 -> 46743 | W10: =Statement!X5 -> 57006 | X10: =Statement!Y5 -> 68127 | Y10: =Statement!Z5 -> 81615 | Z10: =Statement!AA5 -> 96221 | AA10: =SUM(AA8:AA9) -> 108996.16 | AE10: =SUM(X10:AA10) -> 354959.16
C12: Growth rates | S12: Growth rates
B13: Revenue growth % | C13: =C5 -> 2022 | D13: =D5 -> 2023 | E13: =E5 -> 2024 | F13: =F5 -> 2025 | G13: =G5 -> 2026 | H13: =H5 -> 2027 | I13: =I5 -> 2028 | J13: =J5 -> 2029 | ... L13: =L5 -> 2031 | R13: Revenue growth % | S13: =S5 -> Q3 2025 | T13: =T5 -> Q4 2025 | U13: =U5 -> Q1 2026 | V13: =V5 -> Q2 2026 | W13: =W5 -> Q3 2026 | X13: =X5 -> Q4 2026 | Y13: =Y5 -> Q1 2027 | Z13: =Z5 -> Q2 2027 | ... AC13: =AC5 -> FQ3
B14: =B6 -> HyperScale | D14: =D6/C6-1 -> #DIV/0! | E14: =E6/D6-1 -> #DIV/0! | F14: =F6/E6-1 -> #DIV/0! | G14: =G6/F6-1 -> 0.96364042 | H14: 0.95 | I14: 0.75 | J14: 0.55 | K14: 0.25 | L14: 0.1 | R14: =R6 -> HyperScale | T14: =T6/S6-1 -> 0.42598954 | U14: =U6/T6-1 -> -0.078296847 | V14: =V6/U6-1 -> 0.35706574 | W14: =W6/V6-1 -> 0.27035967 | X14: =X6/W6-1 -> 0.11450231 | Y14: =Y6/X6-1 -> 0.11992074 | Z14: =Z6/Y6-1 -> 0.28627637 | AA14: 0.1
B15: =B7 -> AI Clouds | D15: =D7/C7-1 -> #DIV/0! | E15: =E7/D7-1 -> #DIV/0! | F15: =F7/E7-1 -> #DIV/0! | G15: =G7/F7-1 -> 0.43510344 | H15: 0.75 | I15: 0.65 | J15: 0.4 | K15: 0.1 | L15: 0.05 | R15: =R7 -> AI Clouds | T15: =T7/S7-1 -> -0.05149301 | U15: =U7/T7-1 -> 0.30492539 | V15: =V7/U7-1 -> -0.19987914 | W15: =W7/V7-1 -> 0.21274618 | X15: =X7/W7-1 -> 0.36526946 | Y15: =Y7/X7-1 -> 0.31147368 | Z15: =Z7/Y7-1 -> 0.078550981 | AA15: 0.18
B16: =B8 -> Data Center | D16: =D8/C8-1 -> #DIV/0! | E16: =E8/D8-1 -> #DIV/0! | F16: =F8/E8-1 -> #DIV/0! | G16: =G8/F8-1 -> 0.6819492 | H16: =H8/G8-1 -> 0.85905093 | I16: =I8/H8-1 -> 0.70719298 | J16: =J8/I8-1 -> 0.48794059 | K16: =K8/J8-1 -> 0.19160844 | L16: =L8/K8-1 -> 0.082032489 | R16: =R8 -> Data Center | T16: =T8/S8-1 -> 0.15628351 | U16: =U8/T8-1 -> 0.099269252 | V16: =V8/U8-1 -> 0.05072612 | W16: =W8/V8-1 -> 0.24622834 | X16: =X8/W8-1 -> 0.21671385 | Y16: =Y8/X8-1 -> 0.20752961 | Z16: =Z8/Y8-1 -> 0.18309279 | AA16: =AA8/Z8-1 -> 0.13622704
B17: =B9 -> Edge Computing | D17: =D9/C9-1 -> #DIV/0! | E17: =E9/D9-1 -> #DIV/0! | F17: =F9/E9-1 -> #DIV/0! | G17: =G9/F9-1 -> 0.45000327 | H17: 0.5 | I17: 0.5 | J17: 0.45 | K17: 0.3 | L17: 0.1 | R17: =R9 -> Edge Computing | T17: =T9/S9-1 -> -0.12990026 | U17: =U9/T9-1 -> 0.31964809 | V17: =V9/U9-1 -> 0.14080808 | W17: =W9/V9-1 -> 0.025500266 | X17: =X9/W9-1 -> 0.0037989984 | Y17: =Y9/X9-1 -> 0.095647686 | Z17: =Z9/Y9-1 -> 0.13016172 | AA17: 0.09
B18: =B10 -> Total | D18: =D10/C10-1 -> 0.002229323 | E18: =E10/D10-1 -> 1.2585453 | F18: =F10/E10-1 -> 1.1420341 | G18: =G10/F10-1 -> 0.65473536 | H18: =H10/G10-1 -> 0.82213622 | I18: =I10/H10-1 -> 0.68965704 | J18: =J10/I10-1 -> 0.4850899 | K18: =K10/J10-1 -> 0.19956009 | L18: =L10/K10-1 -> 0.083460959 | R18: =R10 -> Total | T18: =T10/S10-1 -> 0.12111624 | U18: =U10/T10-1 -> 0.1202868 | V18: =V10/U10-1 -> 0.060846081 | W18: =W10/V10-1 -> 0.21956229 | X18: =X10/W10-1 -> 0.19508473 | Y18: =Y10/X10-1 -> 0.19798318 | Z18: =Z10/Y10-1 -> 0.1789622 | AA18: =AA10/Z10-1 -> 0.13276894

Sheet COGS & OpEx
B1: COGS & OpEx forecast
C2: History | H2: Forecast | P2: History | X2: Forecast | AB2: TTM
C4: Revenues | P4: Revenues
B5: =Revenue!B5 -> Revenues (thousand) | C5: =Revenue!C5 -> 2022 | D5: =Revenue!D5 -> 2023 | E5: =Revenue!E5 -> 2024 | F5: =Revenue!F5 -> 2025 | G5: =Revenue!G5 -> 2026 | H5: =G5+1 -> 2027 | I5: =H5+1 -> 2028 | J5: =I5+1 -> 2029 | K5: =J5+1 -> 2030 | L5: =K5+1 -> 2031 | O5: Revenues (thousand) | P5: =Revenue!S5 -> Q3 2025 | Q5: =Revenue!T5 -> Q4 2025 | R5: =Revenue!U5 -> Q1 2026 | S5: =Revenue!V5 -> Q2 2026 | T5: =Revenue!W5 -> Q3 2026 | U5: =Revenue!X5 -> Q4 2026 | V5: =Revenue!Y5 -> Q1 2027 | W5: =Revenue!Z5 -> Q2 2027 | X5: FQ1 | Y5: FQ2 | Z5: FQ3 | AB5: =Revenue!AE5 -> FQ1
B6: Revenue | C6: =Revenue!C10 -> 26914 | D6: =Revenue!D10 -> 26974 | E6: =Revenue!E10 -> 60922 | F6: =Revenue!F10 -> 130497 | G6: =Revenue!G10 -> 215938 | H6: =Revenue!H10 -> 393468.45 | I6: =Revenue!I10 -> 664826.74 | J6: =Revenue!J10 -> 987327.47 | ... L6: =Revenue!L10 -> 1283206.3 | O6: Revenue | P6: =Revenue!S10 -> 35082 | Q6: =Revenue!T10 -> 39331 | R6: =Revenue!U10 -> 44062 | S6: =Revenue!V10 -> 46743 | T6: =Revenue!W10 -> 57006 | U6: =Revenue!X10 -> 68127 | V6: =Revenue!Y10 -> 81615 | W6: =Revenue!Z10 -> 96221 | X6: =Revenue!AA10 -> 108996.16 | AB6: =Revenue!AE10 -> 354959.16
C9: COGS and OpEx | P9: COGS & OpEx | AB9: =AB4 -> 0
B10: Expenses (tnousand) | C10: =C5 -> 2022 | D10: =D5 -> 2023 | E10: =E5 -> 2024 | F10: =F5 -> 2025 | G10: =G5 -> 2026 | H10: =H5 -> 2027 | I10: =I5 -> 2028 | J10: =J5 -> 2029 | ... L10: =L5 -> 2031 | O10: Expenses (thousand) | P10: =P5 -> Q3 2025 | Q10: =Q5 -> Q4 2025 | R10: =R5 -> Q1 2026 | S10: =S5 -> Q2 2026 | T10: =T5 -> Q3 2026 | U10: =U5 -> Q4 2026 | V10: =V5 -> Q1 2027 | W10: =W5 -> Q2 2027 | ... Z10: =Z5 -> FQ3 | AB10: =AB5 -> FQ1
B11: COGS | C11: =Statement!M6 -> 9439 | D11: =Statement!N6 -> 11618 | E11: =Statement!O6 -> 16621 | F11: =Statement!P6 -> 32639 | G11: =Statement!Q6 -> 62475 | H11: =H6*H19 -> 110171.17 | I11: =I6*I19 -> 179503.22 | J11: =J6*J19 -> 266578.42 | K11: =K6*K19 -> 296089.66 | L11: =L6*L19 -> 307969.52 | O11: =B11 -> COGS | P11: =Statement!T6 -> 8926 | Q11: =Statement!U6 -> 10608 | R11: =Statement!V6 -> 17394 | S11: =Statement!W6 -> 12890 | T11: =Statement!X6 -> 15157 | U11: =Statement!Y6 -> 17034 | V11: =Statement!Z6 -> 20458 | W11: =Statement!AA6 -> 24079 | X11: =X6*X19 -> 26159.078 | AB11: =SUM(U11:X11) -> 87730.078
B12: =Statement!B8 -> R&D | C12: =Statement!M8 -> 5268 | D12: =Statement!N8 -> 7339 | E12: =Statement!O8 -> 8675 | F12: =Statement!P8 -> 12914 | G12: =Statement!Q8 -> 18497 | H12: =H6*H20 -> 39346.845 | I12: =I6*I20 -> 59834.406 | J12: =J6*J20 -> 88859.473 | K12: =K6*K20 -> 94748.691 | L12: =L6*L20 -> 102656.51 | O12: =B12 -> R&D | P12: =Statement!T8 -> 3390 | Q12: =Statement!U8 -> 3714 | R12: =Statement!V8 -> 3989 | S12: =Statement!W8 -> 4291 | T12: =Statement!X8 -> 4705 | U12: =Statement!Y8 -> 5512 | V12: =Statement!Z8 -> 6321 | W12: =Statement!AA8 -> 7054 | X12: =X20*X$6 -> 10899.616 | AB12: =SUM(U12:X12) -> 29786.616
B13: =Statement!B9 -> SG&A | C13: =Statement!M9 -> 2166 | D13: =Statement!N9 -> 2440 | E13: =Statement!O9 -> 2654 | F13: =Statement!P9 -> 3491 | G13: =Statement!Q9 -> 4579 | H13: =H6*H21 -> 11804.053 | I13: =I6*I21 -> 16620.668 | J13: =J6*J21 -> 24683.187 | K13: =K6*K21 -> 27240.249 | L13: =L6*L21 -> 29513.746 | O13: =B13 -> SG&A | P13: =Statement!T9 -> 897 | Q13: =Statement!U9 -> 975 | R13: =Statement!V9 -> 1041 | S13: =Statement!W9 -> 1122 | T13: =Statement!X9 -> 1134 | U13: =Statement!Y9 -> 1282 | V13: =Statement!Z9 -> 1300 | W13: =Statement!AA9 -> 1354 | X13: =X21*X$6 -> 3269.8848 | AB13: =SUM(U13:X13) -> 7205.8848
B14: OpEx | C14: =Statement!M10 -> 7434 | D14: =Statement!N10 -> 11132 | E14: =Statement!O10 -> 11329 | F14: =Statement!P10 -> 16405 | G14: =Statement!Q10 -> 23076 | H14: =SUM(H12:H13) -> 51150.899 | I14: =SUM(I12:I13) -> 76455.075 | J14: =SUM(J12:J13) -> 113542.66 | K14: =SUM(K12:K13) -> 121988.94 | L14: =SUM(L12:L13) -> 132170.25 | O14: =B14 -> OpEx | P14: =Statement!T10 -> 4287 | Q14: =Statement!U10 -> 4689 | R14: =Statement!V10 -> 5030 | S14: =Statement!W10 -> 5413 | T14: =Statement!X10 -> 5839 | U14: =Statement!Y10 -> 6794 | V14: =Statement!Z10 -> 7621 | W14: =Statement!AA10 -> 8408 | X14: =SUM(X12:X13) -> 14169.501 | AB14: =SUM(U14:X14) -> 36992.501
C17: Expenses % of Revenue | P17: Expenses % of Revenue
B18: % of revenue | C18: =C5 -> 2022 | D18: =D5 -> 2023 | E18: =E5 -> 2024 | F18: =F5 -> 2025 | G18: =G5 -> 2026 | H18: =H5 -> 2027 | I18: =I5 -> 2028 | J18: =J5 -> 2029 | ... L18: =L5 -> 2031 | O18: % of revenue | P18: =P5 -> Q3 2025 | Q18: =Q5 -> Q4 2025 | R18: =R5 -> Q1 2026 | S18: =S5 -> Q2 2026 | T18: =T5 -> Q3 2026 | U18: =U5 -> Q4 2026 | V18: =V5 -> Q1 2027 | W18: =W5 -> Q2 2027 | ... Z18: =Z5 -> FQ3
B19: =B11 -> COGS | C19: =C11/C$6 -> 0.35070967 | D19: =D11/D$6 -> 0.43071106 | E19: =E11/E$6 -> 0.27282427 | F19: =F11/F$6 -> 0.25011303 | G19: =G11/G$6 -> 0.28931916 | H19: 0.28 | I19: 0.27 | J19: 0.27 | K19: 0.25 | L19: 0.24 | O19: =O11 -> COGS | P19: =P11/P$6 -> 0.25443247 | Q19: =Q11/Q$6 -> 0.26971092 | R19: =R11/R$6 -> 0.39476193 | S19: =S11/S$6 -> 0.27576322 | T19: =T11/T$6 -> 0.26588429 | U19: =U11/U$6 -> 0.25003303 | V19: =V11/V$6 -> 0.25066471 | W19: =W11/W$6 -> 0.25024683 | X19: 0.24
B20: =B12 -> R&D | C20: =C12/C$6 -> 0.19573456 | D20: =D12/D$6 -> 0.27207681 | E20: =E12/E$6 -> 0.14239519 | F20: =F12/F$6 -> 0.098960129 | G20: =G12/G$6 -> 0.085658847 | H20: 0.1 | I20: 0.09 | J20: 0.09 | K20: 0.08 | L20: 0.08 | O20: =O12 -> R&D | P20: =P12/P$6 -> 0.096630751 | Q20: =Q12/Q$6 -> 0.094429331 | R20: =R12/R$6 -> 0.090531524 | S20: =S12/S$6 -> 0.091799842 | T20: =T12/T$6 -> 0.082535172 | U20: =U12/U$6 -> 0.080907716 | V20: =V12/V$6 -> 0.077448998 | W20: =W12/W$6 -> 0.0733104 | X20: 0.1
B21: =B13 -> SG&A | C21: =C13/C$6 -> 0.080478561 | D21: =D13/D$6 -> 0.090457478 | E21: =E13/E$6 -> 0.043563901 | F21: =F13/F$6 -> 0.026751573 | G21: =G13/G$6 -> 0.021205161 | H21: 0.03 | I21: 0.025 | J21: 0.025 | K21: 0.023 | L21: 0.023 | O21: =O13 -> SG&A | P21: =P13/P$6 -> 0.025568668 | Q21: =Q13/Q$6 -> 0.024789606 | R21: =R13/R$6 -> 0.0236258 | S21: =S13/S$6 -> 0.024003594 | T21: =T13/T$6 -> 0.019892643 | U21: =U13/U$6 -> 0.018817796 | V21: =V13/V$6 -> 0.015928445 | W21: =W13/W$6 -> 0.014071772 | X21: 0.03
B22: =B14 -> OpEx | C22: =C14/C$6 -> 0.27621312 | D22: =D14/D$6 -> 0.41269371 | E22: =E14/E$6 -> 0.1859591 | F22: =F14/F$6 -> 0.1257117 | G22: =G14/G$6 -> 0.10686401 | H22: =H14/H$6 -> 0.13 | I22: =I14/I$6 -> 0.115 | J22: =J14/J$6 -> 0.115 | ... L22: =L14/L$6 -> 0.103 | O22: =O14 -> OpEx | P22: =P14/P$6 -> 0.12219942 | Q22: =Q14/Q$6 -> 0.11921894 | R22: =R14/R$6 -> 0.11415732 | S22: =S14/S$6 -> 0.11580344 | T22: =T14/T$6 -> 0.10242781 | U22: =U14/U$6 -> 0.099725513 | V22: =V14/V$6 -> 0.093377443 | W22: =W14/W$6 -> 0.087382172 | X22: =X14/X$6 -> 0.13

Sheet WC & Investments
B1: Working Capital, Capex, D&A
C3: History | H3: Forecast
C5: Revenues
B6: Revenues (thousand) | C6: =Revenue!C5 -> 2022 | D6: =Revenue!D5 -> 2023 | E6: =Revenue!E5 -> 2024 | F6: =Revenue!F5 -> 2025 | G6: =Revenue!G5 -> 2026 | H6: =G6+1 -> 2027 | I6: =H6+1 -> 2028 | J6: =I6+1 -> 2029 | K6: =J6+1 -> 2030 | L6: =K6+1 -> 2031
B7: Revenue | C7: =Revenue!C10 -> 26914 | D7: =Revenue!D10 -> 26974 | E7: =Revenue!E10 -> 60922 | F7: =Revenue!F10 -> 130497 | G7: =Revenue!G10 -> 215938 | H7: =Revenue!H10 -> 393468.45 | I7: =Revenue!I10 -> 664826.74 | J7: =Revenue!J10 -> 987327.47 | ... L7: =Revenue!L10 -> 1283206.3
B8: COGS | C8: ='COGS & OpEx'!C11 -> 9439 | D8: ='COGS & OpEx'!D11 -> 11618 | E8: ='COGS & OpEx'!E11 -> 16621 | F8: ='COGS & OpEx'!F11 -> 32639 | G8: ='COGS & OpEx'!G11 -> 62475 | H8: ='COGS & OpEx'!H11 -> 110171.17 | I8: ='COGS & OpEx'!I11 -> 179503.22 | J8: ='COGS & OpEx'!J11 -> 266578.42 | ... L8: ='COGS & OpEx'!L11 -> 307969.52
C11: Working Capital
B12: $ (thousand) | C12: =C6 -> 2022 | D12: =D6 -> 2023 | E12: =E6 -> 2024 | F12: =F6 -> 2025 | G12: =G6 -> 2026 | H12: =H6 -> 2027 | I12: =I6 -> 2028 | J12: =J6 -> 2029 | ... L12: =L6 -> 2031
B13: Accounts receivable | C13: =Statement!M29 -> 4650 | D13: =Statement!N29 -> 3827 | E13: =Statement!O29 -> 9999 | F13: =Statement!P29 -> 23065 | G13: =Statement!Q29 -> 38466 | H13: =H20*H7/365 -> 75459.703 | I13: =I20*I7/365 -> 123858.13 | J13: =J20*J7/365 -> 162300.41 | K13: =K20*K7/365 -> 194689.09 | L13: =L20*L7/365 -> 210938.03
B14: Inventory | C14: =Statement!M30 -> 2605 | D14: =Statement!N30 -> 5159 | E14: =Statement!O30 -> 5282 | F14: =Statement!P30 -> 10080 | G14: =Statement!Q30 -> 21403 | H14: =H21*H8/365 -> 41653.756 | I14: =I21*I8/365 -> 66391.602 | J14: =J21*J8/365 -> 87642.219 | K14: =K21*K8/365 -> 97344.545 | L14: =L21*L8/365 -> 101250.25
B15: Accounts payable | C15: =Statement!M37 -> 1783 | D15: =Statement!N37 -> 1193 | E15: =Statement!O37 -> 2699 | F15: =Statement!P37 -> 6310 | G15: =Statement!Q37 -> 9812 | H15: =H22*H8/365 -> 20525.039 | I15: =I22*I8/365 -> 32949.906 | J15: =J22*J8/365 -> 47472.869 | K15: =K22*K8/365 -> 52728.295 | L15: =L22*L8/365 -> 54843.888
C18: WC metrics and drivers
B19: Days | C19: =C6 -> 2022 | D19: =D6 -> 2023 | E19: =E6 -> 2024 | F19: =F6 -> 2025 | G19: =G6 -> 2026 | H19: =H6 -> 2027 | I19: =I6 -> 2028 | J19: =J6 -> 2029 | ... L19: =L6 -> 2031
B20: DSO | C20: =C13/C7*365 -> 63.061975 | D20: =D13/D7*365 -> 51.785238 | E20: =E13/E7*365 -> 59.906684 | F20: =F13/F7*365 -> 64.512786 | G20: =G13/G7*365 -> 65.01908 | H20: 70 | I20: 68 | J20: 60 | K20: 60 | L20: 60
B21: DIO | C21: =C14/C8*365 -> 100.73366 | D21: =D14/D8*365 -> 162.0791 | E21: =E14/E8*365 -> 115.99362 | F21: =F14/F8*365 -> 112.72404 | G21: =G14/G8*365 -> 125.04354 | H21: 138 | I21: 135 | J21: 120 | K21: 120 | L21: 120
B22: DPO | C22: =C15/C8*365 -> 68.947452 | D22: =D15/D8*365 -> 37.480203 | E22: =E15/E8*365 -> 59.270501 | F22: =F15/F8*365 -> 70.564356 | G22: =G15/G8*365 -> 57.32501 | H22: 68 | I22: 67 | J22: 65 | K22: 65 | L22: 65
B23: Net trade cycle | C23: =C20+C21-C22 -> 94.848181 | D23: =D20+D21-D22 -> 176.38414 | E23: =E20+E21-E22 -> 116.62981 | F23: =F20+F21-F22 -> 106.67247 | G23: =G20+G21-G22 -> 132.73761 | H23: =H20+H21-H22 -> 140 | I23: =I20+I21-I22 -> 136 | J23: =J20+J21-J22 -> 115 | ... L23: =L20+L21-L22 -> 115
C26: Change in SIP NWC
B27: $ (thousand) | C27: =C6 -> 2022 | D27: =D6 -> 2023 | E27: =E6 -> 2024 | F27: =F6 -> 2025 | G27: =G6 -> 2026 | H27: =H6 -> 2027 | I27: =I6 -> 2028 | J27: =J6 -> 2029 | ... L27: =L6 -> 2031
B28: Change in acc receivable | C28: =Statement!M54 -> -2215 | D28: =Statement!N54 -> 822 | E28: =Statement!O54 -> -6172 | F28: =Statement!P54 -> -13063 | G28: =Statement!Q54 -> -15399 | H28: =-(H13-G13) -> -36993.703 | I28: =-(I13-H13) -> -48398.429 | J28: =-(J13-I13) -> -38442.275 | K28: =-(K13-J13) -> -32388.684 | L28: =-(L13-K13) -> -16248.938
B29: Change in inventory | C29: =Statement!M55 -> -774 | D29: =Statement!N55 -> -2554 | E29: =Statement!O55 -> -98 | F29: =Statement!P55 -> -4781 | G29: =Statement!Q55 -> -11324 | H29: =-(H14-G14) -> -20250.756 | I29: =-(I14-H14) -> -24737.846 | J29: =-(J14-I14) -> -21250.618 | K29: =-(K14-J14) -> -9702.3259 | L29: =-(L14-K14) -> -3905.7085
B30: Change in acc payable | C30: =Statement!M56 -> 568 | D30: =Statement!N56 -> -551 | E30: =Statement!O56 -> 1531 | F30: =Statement!P56 -> 3357 | G30: =Statement!Q56 -> 3069 | H30: =H15-G15 -> 10713.039 | I30: =I15-H15 -> 12424.867 | J30: =J15-I15 -> 14522.963 | K30: =K15-J15 -> 5255.4265 | L30: =L15-K15 -> 2115.5921
C33: Total change in NWC and less SIP
B34: $ (thousand) | C34: =C6 -> 2022 | D34: =D6 -> 2023 | E34: =E6 -> 2024 | F34: =F6 -> 2025 | G34: =G6 -> 2026 | H34: =H6 -> 2027 | I34: =I6 -> 2028 | J34: =J6 -> 2029 | ... L34: =L6 -> 2031
B35: Total change in NWC | C35: =Statement!M54+Statement!M55+Statement!M56+Statement!M57 -> -3363 | D35: =Statement!N54+Statement!N55+Statement!N56+Statement!N57 -> -2207 | E35: =Statement!O54+Statement!O55+Statement!O56+Statement!O57 -> -3722 | F35: =Statement!P54+Statement!P55+Statement!P56+Statement!P57 -> -9383 | G35: =Statement!Q54+Statement!Q55+Statement!Q56+Statement!Q57 -> -15976 | H35: =H36+H28+H29+H30 -> -34727.366 | I35: =I36+I28+I29+I30 -> -40766.606 | J35: =J36+J28+J29+J30 -> -25423.38 | K35: =K36+K28+K29+K30 -> -60522.756 | L35: =L36+L28+L29+L30 -> -56535.245
B36: Change in NWC less SIP | C36: =C35-C28-C29-C30 -> -942 | D36: =D35-D28-D29-D30 -> 76 | E36: =E35-E28-E29-E30 -> 1017 | F36: =F35-F28-F29-F30 -> 5104 | G36: =G35-G28-G29-G30 -> 7678 | H36: =H7*H37 -> 11804.053 | I36: =I7*I37 -> 19944.802 | J36: =J7*J37 -> 19746.549 | K36: =K7*K37 -> -23687.173 | L36: =L7*L37 -> -38496.19
B37: % of revenue | C37: =C36/C7 -> -0.035000372 | D37: =D36/D7 -> 0.002817528 | E37: =E36/E7 -> 0.016693477 | F37: =F36/F7 -> 0.03911201 | G37: =G36/G7 -> 0.035556502 | H37: 0.03 | I37: 0.03 | J37: 0.02 | K37: -0.02 | L37: -0.03
C40: Investments
B41: $ (thousand) | C41: =C6 -> 2022 | D41: =D6 -> 2023 | E41: =E6 -> 2024 | F41: =F6 -> 2025 | G41: =G6 -> 2026 | H41: =H6 -> 2027 | I41: =I6 -> 2028 | J41: =J6 -> 2029 | ... L41: =L6 -> 2031
B42: D&A | C42: =Statement!M52 -> 1174 | D42: =Statement!N52 -> 1544 | E42: =Statement!O52 -> 1508 | F42: =Statement!P52 -> 1864 | G42: =Statement!Q52 -> 2843 | H42: =H7*H43 -> 4328.1529 | I42: =I7*I43 -> 7313.0941 | J42: =J7*J43 -> 11847.93 | K42: =K7*K43 -> 14212.304 | L42: =L7*L43 -> 15398.476
B43: % of Revenue | C43: =C42/C7 -> 0.043620421 | D43: =D42/D7 -> 0.057240305 | E43: =E42/E7 -> 0.024752963 | F43: =F42/F7 -> 0.014283853 | G43: =G42/G7 -> 0.013165816 | H43: 0.011 | I43: 0.011 | J43: 0.012 | K43: 0.012 | L43: 0.012
B44: % of CapEx | C44: =C42/C45 -> 1.2028689 | D44: =D42/D45 -> 0.84233497 | E44: =E42/E45 -> 1.4106642 | F44: =F42/F45 -> 0.57601978 | G44: =G42/G45 -> 0.47053956 | H44: =H42/H45 -> 0.44 | I44: =I42/I45 -> 0.44 | J44: =J42/J45 -> 0.48 | ... L44: =L42/L45 -> 0.4
B45: CapEx | C45: =-Statement!M108 -> 976 | D45: =-Statement!N108 -> 1833 | E45: =-Statement!O108 -> 1069 | F45: =-Statement!P108 -> 3236 | G45: =-Statement!Q108 -> 6042 | H45: =H7*H46 -> 9836.7113 | I45: =I7*I46 -> 16620.668 | J45: =J7*J46 -> 24683.187 | K45: =K7*K46 -> 35530.759 | L45: =L7*L46 -> 38496.19
B46: % of Revenue | C46: =C45/C7 -> 0.036263655 | D46: =D45/D7 -> 0.067954326 | E46: =E45/E7 -> 0.017547027 | F46: =F45/F7 -> 0.024797505 | G46: =G45/G7 -> 0.027980254 | H46: 0.025 | I46: 0.025 | J46: 0.025 | K46: 0.03 | L46: 0.03

Sheet FCF & Other
B1: Results
C2: History | H2: Forecast
C4: Income statement
B5: $ (thousand) | C5: =Revenue!C5 -> 2022 | D5: =Revenue!D5 -> 2023 | E5: =Revenue!E5 -> 2024 | F5: =Revenue!F5 -> 2025 | G5: =Revenue!G5 -> 2026 | H5: =G5+1 -> 2027 | I5: =H5+1 -> 2028 | J5: =I5+1 -> 2029 | K5: =J5+1 -> 2030 | L5: =K5+1 -> 2031
B6: Revenue | C6: =Revenue!C10 -> 26914 | D6: =Revenue!D10 -> 26974 | E6: =Revenue!E10 -> 60922 | F6: =Revenue!F10 -> 130497 | G6: =Revenue!G10 -> 215938 | H6: =Revenue!H10 -> 393468.45 | I6: =Revenue!I10 -> 664826.74 | J6: =Revenue!J10 -> 987327.47 | ... L6: =Revenue!L10 -> 1283206.3 | N6: From Revenue Sheet
B7: COGS | C7: ='COGS & OpEx'!C11 -> 9439 | D7: ='COGS & OpEx'!D11 -> 11618 | E7: ='COGS & OpEx'!E11 -> 16621 | F7: ='COGS & OpEx'!F11 -> 32639 | G7: ='COGS & OpEx'!G11 -> 62475 | H7: ='COGS & OpEx'!H11 -> 110171.17 | I7: ='COGS & OpEx'!I11 -> 179503.22 | J7: ='COGS & OpEx'!J11 -> 266578.42 | ... L7: ='COGS & OpEx'!L11 -> 307969.52 | N7: From COGS and OpEx Sheet
B8: Gross profit | C8: =C6-C7 -> 17475 | D8: =D6-D7 -> 15356 | E8: =E6-E7 -> 44301 | F8: =F6-F7 -> 97858 | G8: =G6-G7 -> 153463 | H8: =H6-H7 -> 283297.28 | I8: =I6-I7 -> 485323.52 | J8: =J6-J7 -> 720749.05 | ... L8: =L6-L7 -> 975236.82
B9: OpEx | C9: ='COGS & OpEx'!C14 -> 7434 | D9: ='COGS & OpEx'!D14 -> 11132 | E9: ='COGS & OpEx'!E14 -> 11329 | F9: ='COGS & OpEx'!F14 -> 16405 | G9: ='COGS & OpEx'!G14 -> 23076 | H9: ='COGS & OpEx'!H14 -> 51150.899 | I9: ='COGS & OpEx'!I14 -> 76455.075 | J9: ='COGS & OpEx'!J14 -> 113542.66 | ... L9: ='COGS & OpEx'!L14 -> 132170.25 | N9: From COGS and OpEx Sheet
B10: EBIT | C10: =C8-C9 -> 10041 | D10: =D8-D9 -> 4224 | E10: =E8-E9 -> 32972 | F10: =F8-F9 -> 81453 | G10: =G8-G9 -> 130387 | H10: =H8-H9 -> 232146.39 | I10: =I8-I9 -> 408868.44 | J10: =J8-J9 -> 607206.4 | ... L10: =L8-L9 -> 843066.57
C13: Drivers
C14: =C5 -> 2022 | D14: =D5 -> 2023 | E14: =E5 -> 2024 | F14: =F5 -> 2025 | G14: =G5 -> 2026 | H14: =H5 -> 2027 | I14: =I5 -> 2028 | J14: =J5 -> 2029 | ... L14: =L5 -> 2031
B15: Tax rate | C15: =Statement!M82 -> 0.019012172 | D15: =Statement!N82 -> 0 | E15: =Statement!O82 -> 0.11999527 | F15: =Statement!P82 -> 0.13264942 | G15: =Statement!Q82 -> 0.15117002 | H15: =Overview!$C$26 -> 0.21 | I15: =Overview!$C$26 -> 0.21 | J15: =Overview!$C$26 -> 0.21 | K15: =Overview!$C$26 -> 0.21 | L15: =Overview!$C$26 -> 0.21 | N15: From Statements and Overview sheet
C18: Cash Flow Statement
B19: $ (thousand) | C19: =C5 -> 2022 | D19: =D5 -> 2023 | E19: =E5 -> 2024 | F19: =F5 -> 2025 | G19: =G5 -> 2026 | H19: =H5 -> 2027 | I19: =I5 -> 2028 | J19: =J5 -> 2029 | ... L19: =L5 -> 2031
B20: D&A | C20: ='WC & Investments'!C42 -> 1174 | D20: ='WC & Investments'!D42 -> 1544 | E20: ='WC & Investments'!E42 -> 1508 | F20: ='WC & Investments'!F42 -> 1864 | G20: ='WC & Investments'!G42 -> 2843 | H20: ='WC & Investments'!H42 -> 4328.1529 | I20: ='WC & Investments'!I42 -> 7313.0941 | J20: ='WC & Investments'!J42 -> 11847.93 | ... L20: ='WC & Investments'!L42 -> 15398.476 | N20: From WC & Investments Sheet
B21: CapEx | C21: ='WC & Investments'!C45 -> 976 | D21: ='WC & Investments'!D45 -> 1833 | E21: ='WC & Investments'!E45 -> 1069 | F21: ='WC & Investments'!F45 -> 3236 | G21: ='WC & Investments'!G45 -> 6042 | H21: ='WC & Investments'!H45 -> 9836.7113 | I21: ='WC & Investments'!I45 -> 16620.668 | J21: ='WC & Investments'!J45 -> 24683.187 | ... L21: ='WC & Investments'!L45 -> 38496.19 | N21: From WC & Investments Sheet
B22: Change in NWC | C22: ='WC & Investments'!C35 -> -3363 | D22: ='WC & Investments'!D35 -> -2207 | E22: ='WC & Investments'!E35 -> -3722 | F22: ='WC & Investments'!F35 -> -9383 | G22: ='WC & Investments'!G35 -> -15976 | H22: ='WC & Investments'!H35 -> -34727.366 | I22: ='WC & Investments'!I35 -> -40766.606 | J22: ='WC & Investments'!J35 -> -25423.38 | ... L22: ='WC & Investments'!L35 -> -56535.245 | N22: From WC & Investments Sheet
C25: FCFF
B26: $ (thousand) | C26: =C5 -> 2022 | D26: =D5 -> 2023 | E26: =E5 -> 2024 | F26: =F5 -> 2025 | G26: =G5 -> 2026 | H26: =H5 -> 2027 | I26: =I5 -> 2028 | J26: =J5 -> 2029 | ... L26: =L5 -> 2031
B27: NOPAT | C27: =C10*(1-C15) -> 9850.0988 | D27: =D10*(1-D15) -> 4224 | E27: =E10*(1-E15) -> 29015.516 | F27: =F10*(1-F15) -> 70648.307 | G27: =G10*(1-G15) -> 110676.39 | H27: =H10*(1-H15) -> 183395.64 | I27: =I10*(1-I15) -> 323006.07 | J27: =J10*(1-J15) -> 479693.05 | ... L27: =L10*(1-L15) -> 666022.59
B28: FCFF | C28: =C27+C20-C21+C22 -> 6685.0988 | D28: =D27+D20-D21+D22 -> 1728 | E28: =E27+E20-E21+E22 -> 25732.516 | F28: =F27+F20-F21+F22 -> 59893.307 | G28: =G27+G20-G21+G22 -> 91501.394 | H28: =H27+H20-H21+H22 -> 143159.72 | I28: =I27+I20-I21+I22 -> 272931.89 | J28: =J27+J20-J21+J22 -> 441434.42 | ... L28: =L27+L20-L21+L22 -> 586389.63
C31: Margins
B32: % | C32: =C5 -> 2022 | D32: =D5 -> 2023 | E32: =E5 -> 2024 | F32: =F5 -> 2025 | G32: =G5 -> 2026 | H32: =H5 -> 2027 | I32: =I5 -> 2028 | J32: =J5 -> 2029 | ... L32: =L5 -> 2031
B33: Gross margin | C33: =Statement!M99 -> 0.64929033 | D33: =Statement!N99 -> 0.56928894 | E33: =Statement!O99 -> 0.72717573 | F33: =Statement!P99 -> 0.74988697 | G33: =Statement!Q99 -> 0.71068084 | H33: =H8/H6 -> 0.72 | I33: =I8/I6 -> 0.73 | J33: =J8/J6 -> 0.73 | K33: =K8/K6 -> 0.75 | L33: =L8/L6 -> 0.76
B34: Operating margin | C34: =Statement!M100 -> 0.37307721 | D34: =Statement!N100 -> 0.15659524 | E34: =Statement!O100 -> 0.54121664 | F34: =Statement!P100 -> 0.62417527 | G34: =Statement!Q100 -> 0.60381684 | H34: =H10/H6 -> 0.59 | I34: =I10/I6 -> 0.615 | J34: =J10/J6 -> 0.615 | K34: =K10/K6 -> 0.647 | L34: =L10/L6 -> 0.657

Sheet Valuation ->
H5: Links
H6: Overview'!B3
H7: Financials ->'!B13
H8: Analysis ->'!B13
H9: Forecast ->'!B13
H10: Valuation ->'!B13
B13: Valuation ->

Sheet WACC
B1: WACC
B4: Inputs
B5: Shares Outstanding | C5: =Statement!AC77 -> 24195
B6: Price | C6: =Overview!C5 -> 210.96
B7: Equity | C7: =C5*C6 -> 5104177.2
B8: Debt | C8: =Statement!AC106 -> 33266
B9: Risk free rate | C9: =Overview!F27 -> 0.04953
B10: Beta | C10: =Overview!C13 -> 2.1957
B11: Market risk premium | C11: =[1]Sheet1!$C$12 -> 0.045
B12: Tax rate | C12: =Overview!C26 -> 0.21
B13: Cost of debt | C13: =Overview!C27 -> 0.05
B15: Calculations
B16: Debt/(Debt+Equity) | C16: =C8/(C8+C7) -> 0.0064752054
B17: Equity/(Debt+Equity) | C17: =C7/(C8+C7) -> 0.99352479
B18: Cost of debt with tax | C18: =C13*(1-C12) -> 0.0395
B19: Cost of equity | C19: =C9+C10*C11 -> 0.1483365
B20: WACC | C20: =(C17*C19)+(C16*C18) -> 0.14763176

Sheet DCF
B1: DCF
C3: History | H3: Forecast
C5: PV of FCF
B6: $ (thousand) | C6: =Revenue!C5 -> 2022 | D6: =Revenue!D5 -> 2023 | E6: =Revenue!E5 -> 2024 | F6: =Revenue!F5 -> 2025 | G6: =Revenue!G5 -> 2026 | H6: =Revenue!H5 -> 2027 | I6: =Revenue!I5 -> 2028 | J6: =Revenue!J5 -> 2029 | ... L6: =Revenue!L5 -> 2031
B7: FCFF | C7: ='FCF & Other'!C28 -> 6685.0988 | D7: ='FCF & Other'!D28 -> 1728 | E7: ='FCF & Other'!E28 -> 25732.516 | F7: ='FCF & Other'!F28 -> 59893.307 | G7: ='FCF & Other'!G28 -> 91501.394 | H7: ='FCF & Other'!H28 -> 143159.72 | I7: ='FCF & Other'!I28 -> 272931.89 | J7: ='FCF & Other'!J28 -> 441434.42 | ... L7: ='FCF & Other'!L28 -> 586389.63
B8: Perpetual cashflow | C8: 0 | D8: 0 | E8: 0 | F8: 0 | G8: 0 | H8: 0 | I8: 0 | J8: 0 | K8: 0 | L8: =L7*(1+C14)/(C15-C14) -> 6326835.5
B9: Period | H9: 1 | I9: 2 | J9: 3 | K9: 4 | L9: 5
B10: PV of FCFF | H10: =H7/(1+$C$15)^H9 -> 127821.18 | I10: =I7/(1+$C$15)^I9 -> 217579.63 | J10: =J7/(1+$C$15)^J9 -> 314204.3 | K10: =K7/(1+$C$15)^K9 -> 332706.44 | L10: =L7/(1+$C$15)^L9 -> 332733.22
B11: PV of Perpetual cashflow | L11: =L8/(1+C15)^L9 -> 3590016.4
B13: Input parameters
B14: Perpetual growth | C14: 0.025
B15: WACC | C15: =IF(Overview!C28>0,Overview!C28,WACC!C20) -> 0.12
B18: Result
B19: Total PV of Unlevered FCF | C19: =SUM(H10:L10) -> 1325044.8
B20: PV of Perpetual cashflow | C20: =L11 -> 3590016.4
B21: Enterprise value | C21: =C19+C20 -> 4915061.1
B22: (+) Cash | C22: =Statement!AC105 -> 99369
B23: (-) Debt | C23: =Statement!AC106 -> 33266
B24: Equity value | C24: =C21+C22-C23 -> 4981164.1
B25: Shares outstanding | C25: =Statement!AC77 -> 24195
B26: Price per share | C26: =C24/C25 -> 205.87576

Sheet Multiples
B1: Multiples valuations
C2: History | H2: Forecast
C4: Revenues, earnings cash
B5: Revenues (thousand) | C5: =Revenue!C5 -> 2022 | D5: =Revenue!D5 -> 2023 | E5: =Revenue!E5 -> 2024 | F5: =Revenue!F5 -> 2025 | G5: =Revenue!G5 -> 2026 | H5: =Revenue!H5 -> 2027 | I5: =Revenue!I5 -> 2028 | J5: =Revenue!J5 -> 2029 | ... L5: =Revenue!L5 -> 2031
B6: Revenue | C6: =Revenue!C10 -> 26914 | D6: =Revenue!D10 -> 26974 | E6: =Revenue!E10 -> 60922 | F6: =Revenue!F10 -> 130497 | G6: =Revenue!G10 -> 215938 | H6: =Revenue!H10 -> 393468.45 | I6: =Revenue!I10 -> 664826.74 | J6: =Revenue!J10 -> 987327.47 | ... L6: =Revenue!L10 -> 1283206.3
B7: EBIT | C7: ='FCF & Other'!C10 -> 10041 | D7: ='FCF & Other'!D10 -> 4224 | E7: ='FCF & Other'!E10 -> 32972 | F7: ='FCF & Other'!F10 -> 81453 | G7: ='FCF & Other'!G10 -> 130387 | H7: ='FCF & Other'!H10 -> 232146.39 | I7: ='FCF & Other'!I10 -> 408868.44 | J7: ='FCF & Other'!J10 -> 607206.4 | ... L7: ='FCF & Other'!L10 -> 843066.57
B8: FCFF | C8: ='FCF & Other'!C28 -> 6685.0988 | D8: ='FCF & Other'!D28 -> 1728 | E8: ='FCF & Other'!E28 -> 25732.516 | F8: ='FCF & Other'!F28 -> 59893.307 | G8: ='FCF & Other'!G28 -> 91501.394 | H8: ='FCF & Other'!H28 -> 143159.72 | I8: ='FCF & Other'!I28 -> 272931.89 | J8: ='FCF & Other'!J28 -> 441434.42 | ... L8: ='FCF & Other'!L28 -> 586389.63
B9: PV of FCFF | H9: =DCF!H10 -> 127821.18 | I9: =DCF!I10 -> 217579.63 | J9: =DCF!J10 -> 314204.3 | K9: =DCF!K10 -> 332706.44 | L9: =DCF!L10 -> 332733.22
C11: Growth rates
B12: % Growth | C12: =C5 -> 2022 | D12: =D5 -> 2023 | E12: =E5 -> 2024 | F12: =F5 -> 2025 | G12: =G5 -> 2026 | H12: =H5 -> 2027 | I12: =I5 -> 2028 | J12: =J5 -> 2029 | ... L12: =L5 -> 2031
B13: Revenue | D13: =(D6-C6)/C6 -> 0.002229323 | E13: =(E6-D6)/D6 -> 1.2585453 | F13: =(F6-E6)/E6 -> 1.1420341 | G13: =(G6-F6)/F6 -> 0.65473536 | H13: =(H6-G6)/G6 -> 0.82213622 | I13: =(I6-H6)/H6 -> 0.68965704 | J13: =(J6-I6)/I6 -> 0.4850899 | K13: =(K6-J6)/J6 -> 0.19956009 | L13: =(L6-K6)/K6 -> 0.083460959
B14: EBIT | D14: =IF(C7=0, IF(D7=0,0,IF(D7>0,1,-1)), (D7-C7)/ABS(C7) ) -> -0.57932477 | E14: =IF(D7=0, IF(E7=0,0,IF(E7>0,1,-1)), (E7-D7)/ABS(D7) ) -> 6.8058712 | F14: =IF(E7=0, IF(F7=0,0,IF(F7>0,1,-1)), (F7-E7)/ABS(E7) ) -> 1.4703688 | G14: =IF(F7=0, IF(G7=0,0,IF(G7>0,1,-1)), (G7-F7)/ABS(F7) ) -> 0.60076363 | H14: =IF(G7=0, IF(H7=0,0,IF(H7>0,1,-1)), (H7-G7)/ABS(G7) ) -> 0.78044119 | I14: =IF(H7=0, IF(I7=0,0,IF(I7>0,1,-1)), (I7-H7)/ABS(H7) ) -> 0.76125268 | J14: =IF(I7=0, IF(J7=0,0,IF(J7>0,1,-1)), (J7-I7)/ABS(I7) ) -> 0.4850899 | K14: =IF(J7=0, IF(K7=0,0,IF(K7>0,1,-1)), (K7-J7)/ABS(J7) ) -> 0.26197623 | L14: =IF(K7=0, IF(L7=0,0,IF(L7>0,1,-1)), (L7-K7)/ABS(K7) ) -> 0.10020688
B15: FCFF | D15: =IF(C8=0, IF(D8=0,0,IF(D8>0,1,-1)), (D8-C8)/ABS(C8) ) -> -0.74151466 | E15: =IF(D8=0, IF(E8=0,0,IF(E8>0,1,-1)), (E8-D8)/ABS(D8) ) -> 13.891502 | F15: =IF(E8=0, IF(F8=0,0,IF(F8>0,1,-1)), (F8-E8)/ABS(E8) ) -> 1.327534 | G15: =IF(F8=0, IF(G8=0,0,IF(G8>0,1,-1)), (G8-F8)/ABS(F8) ) -> 0.52773989 | H15: =IF(G8=0, IF(H8=0,0,IF(H8>0,1,-1)), (H8-G8)/ABS(G8) ) -> 0.56456327 | I15: =IF(H8=0, IF(I8=0,0,IF(I8>0,1,-1)), (I8-H8)/ABS(H8) ) -> 0.90648522 | J15: =IF(I8=0, IF(J8=0,0,IF(J8>0,1,-1)), (J8-I8)/ABS(I8) ) -> 0.61737939 | K15: =IF(J8=0, IF(K8=0,0,IF(K8>0,1,-1)), (K8-J8)/ABS(J8) ) -> 0.18595198 | L15: =IF(K8=0, IF(L8=0,0,IF(L8>0,1,-1)), (L8-K8)/ABS(K8) ) -> 0.12009018
C17: Shares
C18: =C5 -> 2022 | D18: =D5 -> 2023 | E18: =E5 -> 2024 | F18: =F5 -> 2025 | G18: =G5 -> 2026 | H18: =H5 -> 2027 | I18: =I5 -> 2028 | J18: =J5 -> 2029 | ... L18: =L5 -> 2031
B19: Avg diluted shares | C19: =Statement!M21 -> 25350 | D19: =Statement!N21 -> 25070 | E19: =Statement!O21 -> 24940 | F19: =Statement!P21 -> 24804 | G19: =Statement!Q21 -> 24514 | H19: =G19*(1+H20) -> 24146.29 | I19: =H19*(1+I20) -> 23904.827 | J19: =I19*(1+J20) -> 23665.779 | K19: =J19*(1+K20) -> 23547.45 | L19: =K19*(1+L20) -> 23429.713
B20: Dilution rate | D20: =D19/C19-1 -> -0.011045365 | E20: =E19/D19-1 -> -0.0051854807 | F20: =F19/E19-1 -> -0.0054530874 | G20: =G19/F19-1 -> -0.011691663 | H20: -0.015 | I20: -0.01 | J20: -0.01 | K20: -0.005 | L20: -0.005
C22: Historical price
C23: =C5 -> 2022 | D23: =D5 -> 2023 | E23: =E5 -> 2024 | F23: =F5 -> 2025 | G23: =G5 -> 2026 | H23: =H5 -> 2027 | I23: =I5 -> 2028 | J23: =J5 -> 2029 | ... L23: =L5 -> 2031
B24: Price | C24: =Statement!M114 -> 228.4 | D24: =Statement!N114 -> 203.6 | E24: =Statement!O114 -> 610.3 | F24: =Statement!P114 -> 142.62 | G24: =Statement!Q114 -> 187.67
C27: Historical ratios
C28: =C5 -> 2022 | D28: =D5 -> 2023 | E28: =E5 -> 2024 | F28: =F5 -> 2025 | G28: =G5 -> 2026 | H28: =H5 -> 2027 | I28: =I5 -> 2028 | J28: =J5 -> 2029 | ... L28: =L5 -> 2031
B29: PS | C29: =C24/(C6/C19) -> 215.12744 | D29: =D24/(D6/D19) -> 189.22859 | E29: =E24/(E6/E19) -> 249.84213 | F29: =F24/(F6/F19) -> 27.108259 | G29: =G24/(G6/G19) -> 21.304923
B30: Market Cap | C30: =C24*C19 -> 5789940 | D30: =D24*D19 -> 5104252 | E30: =E24*E19 -> 15220882 | F30: =F24*F19 -> 3537546.5 | G30: =G24*G19 -> 4600542.4
B31: Debt | C31: =Statement!M106 -> 10946 | D31: =Statement!N106 -> 10953 | E31: =Statement!O106 -> 9709 | F31: =Statement!P106 -> 8463 | G31: =Statement!Q106 -> 8468
B32: Cash | C32: =Statement!M105 -> 21208 | D32: =Statement!N105 -> 13296 | E32: =Statement!O105 -> 25984 | F32: =Statement!P105 -> 43210 | G32: =Statement!Q105 -> 62556
B33: EV | C33: =C30+C31-C32 -> 5779678 | D33: =D30+D31-D32 -> 5101909 | E33: =E30+E31-E32 -> 15204607 | F33: =F30+F31-F32 -> 3502799.5 | G33: =G30+G31-G32 -> 4546454.4
B34: EV/EBIT | C34: =C33/C7 -> 575.60781 | D34: =D33/D7 -> 1207.8383 | E34: =E33/E7 -> 461.13693 | F34: =F33/F7 -> 43.003935 | G34: =G33/G7 -> 34.868924
B35: EV/FCFF | C35: =C33/C8 -> 864.56135 | D35: =D33/D8 -> 2952.4936 | E35: =E33/E8 -> 590.87137 | F35: =F33/F8 -> 58.483989 | G35: =G33/G8 -> 49.687269
B36: EV/Sales | C36: =C33/C6 -> 214.74615 | D36: =D33/D6 -> 189.14173 | E36: =E33/E6 -> 249.57498 | F36: =F33/F6 -> 26.841992 | G36: =G33/G6 -> 21.054443
B39: EV/EBIT valuation
B40: Year 5 EBIT | C40: =L7 -> 843066.57
B41: WACC | C41: =IF(Overview!C28>0,Overview!C28,WACC!C20) -> 0.12
B42: Applied EV/EBIT ratio | C42: 20
B43: Terminal EV | C43: =(C40*C42) -> 16861331
B44: PV of Terminal EV | C44: =C43/(1+C41)^5 -> 9567572.2
B45: Total EV | C45: =SUM(H9:K9)+C44 -> 10559884
B46: (+) Cash | C46: =Statement!AC105 -> 99369
B47: (-) Debt | C47: =Statement!AC106 -> 33266
B48: Equity value | C48: =C45+C46-C47 -> 10625987
B49: Shares outstanding | C49: =Statement!AC77 -> 24195
B50: PV of price per share | C50: =C48/C49 -> 439.1811
B52: PS valuation
B53: Year 5 sales | C53: =L6 -> 1283206.3
B54: Discount rate | C54: =IF(Overview!C29>0,Overview!C29,WACC!C19) -> 0.12
B55: Applied PS ratio | C55: 12
B56: Shares outstanding diluted | C56: =L19 -> 23429.713
B57: Price per share | C57: =(C53*C55)/C56 -> 657.22001
B58: PV of price per share | C58: =C57/(1+C54)^5 -> 372.92429
B60: EV/FCFF valuation
B61: Year 5 FCFF | C61: =L8 -> 586389.63
B62: WACC | C62: =IF(Overview!C28>0,Overview!C28,WACC!C20) -> 0.12
B63: Applied EV/FCFF ratio | C63: 30
B64: Terminal EV | C64: =(C61*C63) -> 17591689
B65: PV of Terminal EV | C65: =C64/(1+C62)^5 -> 9981996.7
B66: Total EV | C66: =SUM(H9:K9)+C65 -> 10974308
B67: (+) Cash | C67: =Statement!AC105 -> 99369
B68: (-) Debt | C68: =Statement!AC106 -> 33266
B69: Equity value | C69: =C66+C67-C68 -> 11040411
B70: Shares outstanding | C70: =Statement!AC77 -> 24195
B71: PV of price per share | C71: =C69/C70 -> 456.30962
B73: EV/Sales valuation
B74: Year 5 Sales | C74: =L6 -> 1283206.3
B75: WACC | C75: =IF(Overview!C28>0,Overview!C28,WACC!C20) -> 0.12
B76: Applied EV/Sales ratio | C76: 12
B77: Terminal EV | C77: =(C74*C76) -> 15398476
B78: PV of Terminal EV | C78: =C77/(1+C75)^5 -> 8737508.9
B79: Total EV | C79: =SUM(H9:K9)+C78 -> 9729820.4
B80: (+) Cash | C80: =Statement!AC105 -> 99369
B81: (-) Debt | C81: =Statement!AC106 -> 33266
B82: Equity value | C82: =C79+C80-C81 -> 9795923.4
B83: Shares outstanding | C83: =Statement!AC77 -> 24195
B84: PV of price per share | C84: =C82/C83 -> 404.87388

Sheet AVG target price
B1: AVG target price
B4: AVG target price
B5: DCF price | C5: =DCF!C26 -> 205.87576
B6: EV/EBIT price | C6: =Multiples!C50 -> 439.1811
B7: PS price | C7: =Multiples!C58 -> 372.92429
B8: EV/FCFF price | C8: =Multiples!C71 -> 456.30962
B9: EV/Sales price | C9: =Multiples!C84 -> 404.87388
B10: AVG price | C10: =AVERAGE(C5:C9) -> 375.83293
B11: Current price | C11: =Overview!C5 -> 210.96
B12: Upside/Downside | C12: =(C10-C11)/C11 -> 0.78153645

Sheet DDM
B1: Dividend discount model
C2: History | H2: Forecast
C4: Revenues, earnings cash
B5: Revenues (thousand) | C5: =[2]Revenue!C5 -> 2021 | D5: =[2]Revenue!D5 -> 2022 | E5: =[2]Revenue!E5 -> 2023 | F5: =[2]Revenue!F5 -> 2024 | G5: =[2]Revenue!G5 -> 2025 | H5: =[2]Revenue!H5 -> 2026 | I5: =[2]Revenue!I5 -> 2027 | J5: =[2]Revenue!J5 -> 2028 | ... L5: =[2]Revenue!L5 -> 2030
B6: EPS | C6: =Statement!M25 -> 0.385 | D6: =Statement!N25 -> 0.174 | E6: =Statement!O25 -> 1.193 | F6: =Statement!P25 -> 2.94 | G6: =Statement!Q25 -> 4.9
B7: Dividend per share | C7: =Statement!M81 -> 0.016 | D7: =Statement!N81 -> 0.016 | E7: =Statement!O81 -> 0.016 | F7: =Statement!P81 -> 0.034 | G7: =Statement!Q81 -> 0.04
C9: Growth rates
B10: % Growth | C10: =C5 -> 2021 | D10: =D5 -> 2022 | E10: =E5 -> 2023 | F10: =F5 -> 2024 | G10: =G5 -> 2025 | H10: =H5 -> 2026 | I10: =I5 -> 2027 | J10: =J5 -> 2028 | ... L10: =L5 -> 2030
B11: EPS | D11: =(D6-C6)/C6 -> -0.54805195 | E11: =(E6-D6)/D6 -> 5.8563218 | F11: =(F6-E6)/E6 -> 1.4643755 | G11: =(G6-F6)/F6 -> 0.66666667
B12: Dividend | D12: =IF(C7=0, IF(D7=0,0,IF(D7>0,1,-1)), (D7-C7)/ABS(C7) ) -> 0 | E12: =IF(D7=0, IF(E7=0,0,IF(E7>0,1,-1)), (E7-D7)/ABS(D7) ) -> 0 | F12: =IF(E7=0, IF(F7=0,0,IF(F7>0,1,-1)), (F7-E7)/ABS(E7) ) -> 1.125 | G12: =IF(F7=0, IF(G7=0,0,IF(G7>0,1,-1)), (G7-F7)/ABS(F7) ) -> 0.17647059
C14: Ratios
B15: % | C15: =C5 -> 2021 | D15: =D5 -> 2022 | E15: =E5 -> 2023 | F15: =F5 -> 2024 | G15: =G5 -> 2025 | H15: =H5 -> 2026 | I15: =I5 -> 2027 | J15: =J5 -> 2028 | ... L15: =L5 -> 2030
B16: Payout | C16: =C7/C6 -> 0.041558442 | D16: =D7/D6 -> 0.091954023 | E16: =E7/E6 -> 0.013411567 | F16: =F7/F6 -> 0.011564626 | G16: =G7/G6 -> 0.0081632653
B20: DDM valuation
B21: Latest dividend | C21: =G7 -> 0.04
B22: Year 1 growth rate | C22: 3
B23: Year 1 dividend | C23: =C21*(1+C22) -> 0.16
B24: Discount rate | C24: =IF(Overview!C29>0,Overview!C29,WACC!C19) -> 0.12
B25: Perpetual dividend growth | C25: 0.025
B26: PV of price per share | C26: =C23/(C24-C25) -> 1.6842105

Sheet Reverse DCF
B1: Reverse DCF
C3: History | H3: Forecast
C5: PV of FCF
B6: $ (thousand) | C6: =Revenue!C5 -> 2022 | D6: =Revenue!D5 -> 2023 | E6: =Revenue!E5 -> 2024 | F6: =Revenue!F5 -> 2025 | G6: =Revenue!G5 -> 2026 | H6: =Revenue!H5 -> 2027 | I6: =Revenue!I5 -> 2028 | J6: =Revenue!J5 -> 2029 | ... L6: =Revenue!L5 -> 2031
B7: FCFF | C7: ='FCF & Other'!C28 -> 6685.0988 | D7: ='FCF & Other'!D28 -> 1728 | E7: ='FCF & Other'!E28 -> 25732.516 | F7: ='FCF & Other'!F28 -> 59893.307 | G7: ='FCF & Other'!G28 -> 91501.394 | H7: =G7*(1+$C$17) -> 137252.09 | I7: =H7*(1+$C$17) -> 205878.14 | J7: =I7*(1+$C$17) -> 308817.2 | K7: =J7*(1+$C$17) -> 463225.81 | L7: =K7*(1+$C$17) -> 694838.71
B8: Perpetual cashflow | L8: =L7*(1+C20)/(C21-C20) -> 7496944
B9: Period | H9: 1 | I9: 2 | J9: 3 | K9: 4 | L9: 5
B10: PV of FCFF | H10: =H7/(1+$C$21)^H9 -> 122546.51 | I10: =I7/(1+$C$21)^I9 -> 164124.79 | J10: =J7/(1+$C$21)^J9 -> 219809.99 | K10: =K7/(1+$C$21)^K9 -> 294388.37 | L10: =L7/(1+$C$21)^L9 -> 394270.14
B11: PV of Perpetual cashflow | L11: =L8/(1+C21)^L9 -> 4253967.4
B14: Growth adjustment
B15: Current Price | C15: =Overview!C5 -> 210.96
B16: Calculated Price | C16: =C36 -> 228.84689
B17: FCFF Growth | C17: 0.5 | E17: Modify until Calculated Price is very close to Current Price
B19: Input parameters
B20: Perpetual growth | C20: 0.025
B21: WACC | C21: =IF(Overview!C28>0,Overview!C28,WACC!C20) -> 0.12
B22: Shares outstanding | C22: =Statement!AC74 -> 24100
B23: Market cap | C23: =C15*C22 -> 5084136
B24: Cash | C24: =Statement!AC105 -> 99369
B25: Debt | C25: =Statement!AC106 -> 33266
B26: Enterprise Value | C26: =C23+C25-C24 -> 5018033
B28: Result
B29: Total PV of Unlevered FCF | C29: =SUM(H10:L10) -> 1195139.8
B30: PV of Perpetual cashflow | C30: =L11 -> 4253967.4
B31: Enterprise value | C31: =C29+C30 -> 5449107.2
B32: (+) Cash | C32: =C24 -> 99369
B33: (-) Debt | C33: =C25 -> 33266
B34: Equity value | C34: =C31+C32-C33 -> 5515210.2
B35: Shares outstanding | C35: =C22 -> 24100
B36: Price per share | C36: =C34/C35 -> 228.84689
