Workbook

Sheet Overview
B2: Automatic Data | E2: At a glance | H2: Valuation | K2: Links
B3: Company | C3: #VALUE! | E3: Market capitalization | F3: =Statement!AC153 -> 6989162.4 | H3: ='AVG target price'!B5 -> DCF price | I3: ='AVG target price'!C5 -> 6.0868928 | K3: Financials ->'!B13
B4: Ticker | C4: {=_FV(C3,"Ticker symbol",TRUE)} -> PATH | E4: Enterprise value | F4: =Statement!AC154 -> 5584137.4 | H4: ='AVG target price'!B6 -> EV/EBIT price | I4: ='AVG target price'!C6 -> 15.500001 | K4: Analysis ->'!B13
B5: Price | C5: {=_FV(C3,"Price",TRUE)} -> 13.325 | E5: EPS | F5: =Statement!AC26 -> 0.67 | H5: ='AVG target price'!B7 -> PS price | I5: ='AVG target price'!C7 -> 11.635364 | K5: Forecast ->'!B13
B6: Price Extended Hours | C6: {=_FV(C3,"Price (Extended hours)",TRUE)} -> 13.32 | E6: PE | F6: =Statement!AC150 -> 19.88806 | H6: ='AVG target price'!B8 -> EV/FCFF price | I6: ='AVG target price'!C8 -> 9.9292211 | K6: Valuation ->'!B13
B7: Day change | C7: {=_FV(C3,"Change")} -> -0.155 | E7: PS | F7: =Statement!AC151 -> 4.1332067 | H7: ='AVG target price'!B9 -> EV/Sales | I7: ='AVG target price'!C9 -> 11.620184
B8: Day change extended | C8: {=_FV(C3,"Change (extended hours)",TRUE)} -> 0 | E8: FCF Yield | F8: =Statement!AC161 -> 0.018367866 | H8: ='AVG target price'!B10 -> AVG price | I8: ='AVG target price'!C10 -> 10.954333
B9: Day change % | C9: {=_FV(C3,"Change (%)",TRUE)} -> -0.011499 | E9: Earnings Yield | F9: =Statement!AC162 -> 0.050281426 | H9: ='AVG target price'!B12 -> Upside/Downside | I9: ='AVG target price'!C12 -> -0.17791124
B10: Day change extended % | C10: {=_FV(C3,"Change % (extended hours)",TRUE)} -> 0 | E10: Buyback Yield | F10: =Statement!AC164 -> 0.038423488
B11: 52 week high | C11: {=_FV(C3,"52 week high",TRUE)} -> 19.84 | E11: Dividend Yield | F11: =Statement!AC163 -> 0 | H11: DDM price | I11: =DDM!C26 -> 0
B12: 52 week low | C12: {=_FV(C3,"52 week low",TRUE)} -> 9.2002 | E12: ROA | F12: =Statement!AC123 -> 0.12448205
B13: Beta | C13: {=_FV(C3,"Beta")} -> 1.063 | E13: ROE | F13: =Statement!AC125 -> 0.18573545 | H13: Reverse DCF rate | I13: ='Reverse DCF'!C17 -> 1.4
B14: Avg volume | C14: {=_FV(C3,"Volume average",TRUE)} -> 46968664 | E14: ROIC | F14: =Statement!AC140 -> 0.2813996
E15: Net Cash/Market Cap | F15: =Statement!AC176 -> 0.2010291
E16: Net Cash/Share | F16: =Statement!AC175 -> 2.6959778 | H16: Discount rates used
B17: Unit data and other info | E17: Insider Ownership | F17: =Statement!AC171 -> 0.22269906 | H17: WACC | I17: =DCF!C15 -> 0.1
B18: Units | C18: K | E18: Net Trade Cycle | F18: =Statement!AC144 -> 45.101496 | H18: Cost of Equity | I18: =Multiples!C54 -> 0.12
B19: Units conversion | C19: 1000 | E19: Net Debt/Equity | F19: =Statement!AC146 -> -0.72106145
B20: Has operating lease | C20: Yes | E20: Quick Ratio | F20: =Statement!AC147 -> 2.1209291
B21: Has finance lease | C21: No
B22: Has debt | C22: No
B25: Constants | E25: 10 Year Bond Yield
B26: Default tax rate | C26: 0.21 | E26: #VALUE! | F26: {=_FV(E26,"Price")} -> 52.44
B27: Cost of debt | C27: 0 | E27: Percentage | F27: =F26/1000 -> 0.05244
B28: Manual WACC | C28: 0.1
B29: Manual Cost of Equity | C29: 0.12
B33: Info
B35: Mission: | C35: Empower customers to combine automation, AI agents and people, devilering end to end process orchestration that drives innovation
B36: Auditor: | C36: KPMG
B42: Notes
B44: Date: | C44: 03.09.2026 | E44: Q2 2027
B45: - | C45: Revenue and ARR for FY 2027 are 1789M-1794M and 2065B-2070B
B46: - | C46: Non GAAP EBIT for Q3 2027 and FY 2027 are 100M and 445M
B52: Adjustments
B54: Date: | C54: 30.04.2026 | E54: Q1 2027

Sheet Financials ->
H5: Links
H6: Overview'!B3
H7: Financials ->'!B13
H8: Analysis ->'!B13
H9: Forecast ->'!B13
H10: Valuation ->'!B13
B13: Financials ->

Sheet Statement
B2: Date | M2: 31.01.2022 | N2: 31.01.2023 | O2: 31.01.2024 | P2: 31.01.2025 | Q2: 31.01.2026 | T2: 31.10.2024 | U2: 31.01.2025 | V2: 30.04.2025 | W2: 31.07.2025 | X2: 31.10.2025 | Y2: 31.01.2026 | Z2: 30.04.2026 | AA2: 31.07.2026
B3: FY | M3: 2022 | N3: 2023 | O3: 2024 | P3: 2025 | Q3: 2026 | T3: Q3 2025 | U3: Q4 2025 | V3: Q1 2026 | W3: Q2 2026 | X3: Q3 2026 | Y3: Q4 2026 | Z3: Q1 2027 | AA3: Q2 2027 | AC3: TTM/YTD
B4: Income statement
B5: Revenue | M5: 892252 | N5: 1058581 | O5: 1308072 | P5: 1429664 | Q5: 1610572 | T5: 354653 | U5: 423646 | V5: 356624 | W5: 361728 | X5: 411113 | Y5: 481107 | Z5: 418382 | AA5: 410256 | AC5: =SUM(X5:AA5) -> 1720858
B6: COGS | M6: 168868 | N6: 180051 | O6: 195924 | P6: 246942 | Q6: 270984 | T6: 63763 | U6: 64534 | V6: 63857 | W6: 64380 | X6: 68812 | Y6: 73935 | Z6: 76928 | AA6: 80587 | AC6: =SUM(X6:AA6) -> 300262
B7: Gross Profit | C7: =C5-C6 -> 0 | D7: =D5-D6 -> 0 | E7: =E5-E6 -> 0 | F7: =F5-F6 -> 0 | G7: =G5-G6 -> 0 | H7: =H5-H6 -> 0 | I7: =I5-I6 -> 0 | J7: =J5-J6 -> 0 | ... Q7: =Q5-Q6 -> 1339588 | T7: =T5-T6 -> 290890 | U7: =U5-U6 -> 359112 | V7: =V5-V6 -> 292767 | W7: =W5-W6 -> 297348 | X7: =X5-X6 -> 342301 | Y7: =Y5-Y6 -> 407172 | Z7: =Z5-Z6 -> 341454 | AA7: =AA5-AA6 -> 329669 | AC7: =SUM(X7:AA7) -> 1420596
B8: Sales and marketing | M8: 697682 | N8: 701558 | O8: 713130 | P8: 738493 | Q8: 683329 | T8: 187188 | U8: 176836 | V8: 159661 | W8: 166303 | X8: 179186 | Y8: 178179 | Z8: 167859 | AA8: 164606 | AC8: =SUM(X8:AA8) -> 689830
B9: R&D | M9: 276657 | N9: 285750 | O9: 332101 | P9: 380682 | Q9: 385208 | T9: 96976 | U9: 99670 | V9: 94839 | W9: 98341 | X9: 96869 | Y9: 95159 | Z9: 92902 | AA9: 83393 | AC9: =SUM(X9:AA9) -> 368323
B10: General and administrative | M10: 249991 | N10: 239505 | O10: 231637 | P10: 226116 | Q10: 214291 | T10: 50090 | U10: 48997 | V10: 54679 | W10: 52889 | X10: 53175 | Y10: 53548 | Z10: 52706 | AA10: 50066 | AC10: =SUM(X10:AA10) -> 209495
B11: OpEx | C11: =SUM(C8:C10) -> 0 | D11: =SUM(D8:D10) -> 0 | E11: =SUM(E8:E10) -> 0 | F11: =SUM(F8:F10) -> 0 | G11: =SUM(G8:G10) -> 0 | H11: =SUM(H8:H10) -> 0 | I11: =SUM(I8:I10) -> 0 | J11: =SUM(J8:J10) -> 0 | ... Q11: =SUM(Q8:Q10) -> 1282828 | T11: =SUM(T8:T10) -> 334254 | U11: =SUM(U8:U10) -> 325503 | V11: =SUM(V8:V10) -> 309179 | W11: =SUM(W8:W10) -> 317533 | X11: =SUM(X8:X10) -> 329230 | Y11: =SUM(Y8:Y10) -> 326886 | Z11: =SUM(Z8:Z10) -> 313467 | AA11: =SUM(AA8:AA10) -> 298065 | AC11: =SUM(X11:AA11) -> 1267648
B12: Operating income | M12: -500946 | N12: -348283 | O12: -164720 | P12: -162569 | Q12: 56760 | T12: -43364 | U12: 33609 | V12: -16412 | W12: -20185 | X12: 13071 | Y12: 80286 | Z12: 27987 | AA12: 31604 | AC12: =SUM(X12:AA12) -> 152948
B13: Interest income/expense | M13: 3551 | N13: 27955 | O13: 57130 | P13: 49422 | Q13: 48023 | T13: 10055 | U13: 12167 | V13: 12648 | W13: 12004 | X13: 11701 | Y13: 11670 | Z13: 10401 | AA13: 10769 | AC13: =SUM(X13:AA13) -> 44541
B14: Other income/expense | M14: -13488 | N14: 2767 | O14: 31775 | P14: 35047 | Q14: -4155 | T14: 7810 | U14: 8848 | V14: -15964 | W14: 11508 | X14: -180 | Y14: 481 | Z14: 2580 | AA14: 10482 | AC14: =SUM(X14:AA14) -> 13363
B15: Income before taxes | M15: -510883 | N15: -317561 | O15: -75815 | P15: -78100 | Q15: 100628 | T15: -25499 | U15: 54624 | V15: -19728 | W15: 3327 | X15: 24592 | Y15: 92437 | Z15: 40968 | AA15: 52855 | AC15: =SUM(X15:AA15) -> 210852
B16: Income tax expense/benefit | M16: -14703 | N16: -10791 | O16: -14068 | P16: 4406 | Q16: 181702 | T16: 14844 | U16: -2830 | V16: -2827 | W16: -1743 | X16: 174247 | Y16: 12025 | Z16: -18443 | AA16: -16766 | AC16: =SUM(X16:AA16) -> 151063
B17: Non-controlling interest | M17: 0 | N17: 0 | O17: 0 | P17: 0 | Q17: 0 | T17: 0 | U17: 0 | V17: 0 | W17: 0 | X17: 0 | Y17: 0 | Z17: 0 | AA17: 0 | AC17: =SUM(X17:AA17) -> 0
B18: Net income | M18: -525586 | N18: -328352 | O18: -89883 | P18: -73694 | Q18: 282330 | T18: -10655 | U18: 51794 | V18: -22555 | W18: 1584 | X18: 198839 | Y18: 104462 | Z18: 22525 | AA18: 36089 | AC18: =SUM(X18:AA18) -> 361915
B19: Basic Shares outstanding avg | M19: 454625 | N19: 548022 | O19: 563855 | P19: 559933 | Q19: 538125 | T19: 551036 | U19: 550948 | V19: 548451 | W19: 536169 | X19: 532255 | Y19: 535962 | Z19: 523584 | AA19: 519654 | AC19: =AVERAGE(X19:AA19) -> 527863.75
B20: Basic Shares outstanding avg adjusted | C20: =C19*C$85 -> 0 | D20: =D19*D$85 -> 0 | E20: =E19*E$85 -> 0 | F20: =F19*F$85 -> 0 | G20: =G19*G$85 -> 0 | H20: =H19*H$85 -> 0 | I20: =I19*I$85 -> 0 | J20: =J19*J$85 -> 0 | ... Q20: =Q19*Q$85 -> 538125 | T20: =T19*T$85 -> 551036 | U20: =U19*U$85 -> 550948 | V20: =V19*V$85 -> 548451 | W20: =W19*W$85 -> 536169 | X20: =X19*X$85 -> 532255 | Y20: =Y19*Y$85 -> 535962 | Z20: =Z19*Z$85 -> 523584 | AA20: =AA19*AA$85 -> 519654 | AC20: =AC19*AC$85 -> 527863.75
B21: Diluted Shares outstanding avg | M21: 454625 | N21: 548022 | O21: 653855 | P21: 559933 | Q21: 544860 | T21: 551036 | U21: 555373 | V21: 548451 | W21: 542865 | X21: 539018 | Y21: 545284 | Z21: 527818 | AA21: 523013 | AC21: =AVERAGE(X21:AA21) -> 533783.25
B22: Diluted Shares outstanding avg adjusted | C22: =C21*C$85 -> 0 | D22: =D21*D$85 -> 0 | E22: =E21*E$85 -> 0 | F22: =F21*F$85 -> 0 | G22: =G21*G$85 -> 0 | H22: =H21*H$85 -> 0 | I22: =I21*I$85 -> 0 | J22: =J21*J$85 -> 0 | ... Q22: =Q21*Q$85 -> 544860 | T22: =T21*T$85 -> 551036 | U22: =U21*U$85 -> 555373 | V22: =V21*V$85 -> 548451 | W22: =W21*W$85 -> 542865 | X22: =X21*X$85 -> 539018 | Y22: =Y21*Y$85 -> 545284 | Z22: =Z21*Z$85 -> 527818 | AA22: =AA21*AA$85 -> 523013 | AC22: =AC21*AC$85 -> 533783.25
B23: Basic EPS | M23: -1.16 | N23: -0.6 | O23: -0.16 | P23: -0.13 | Q23: 0.52 | T23: -0.02 | U23: 0.09 | V23: -0.04 | W23: 0 | X23: 0.37 | Y23: 0.19 | Z23: 0.04 | AA23: 0.07 | AC23: =SUM(X23:AA23) -> 0.67
B24: Basic EPS adjusted | M24: =M23/M$85 -> -1.16 | N24: =N23/N$85 -> -0.6 | O24: =O23/O$85 -> -0.16 | P24: =P23/P$85 -> -0.13 | Q24: =Q23/Q$85 -> 0.52 | T24: =T23/T$85 -> -0.02 | U24: =U23/U$85 -> 0.09 | V24: =V23/V$85 -> -0.04 | W24: =W23/W$85 -> 0 | X24: =X23/X$85 -> 0.37 | Y24: =Y23/Y$85 -> 0.19 | Z24: =Z23/Z$85 -> 0.04 | AA24: =AA23/AA$85 -> 0.07 | AC24: =AC23/AC$85 -> 0.67
B25: Diluted EPS | M25: -1.16 | N25: -0.6 | O25: -0.16 | P25: -0.13 | Q25: 0.52 | T25: -0.02 | U25: 0.09 | V25: -0.04 | W25: 0 | X25: 0.37 | Y25: 0.19 | Z25: 0.04 | AA25: 0.07 | AC25: =SUM(X25:AA25) -> 0.67
B26: Diluted EPS adjusted | M26: =M25/M$85 -> -1.16 | N26: =N25/N$85 -> -0.6 | O26: =O25/O$85 -> -0.16 | P26: =P25/P$85 -> -0.13 | Q26: =Q25/Q$85 -> 0.52 | T26: =T25/T$85 -> -0.02 | U26: =U25/U$85 -> 0.09 | V26: =V25/V$85 -> -0.04 | W26: =W25/W$85 -> 0 | X26: =X25/X$85 -> 0.37 | Y26: =Y25/Y$85 -> 0.19 | Z26: =Z25/Z$85 -> 0.04 | AA26: =AA25/AA$85 -> 0.07 | AC26: =AC25/AC$85 -> 0.67
B28: Balance sheet
B29: Cash and cash equivalents | M29: =1768723+96417 -> 1865140 | N29: =1402119+354774 -> 1756893 | O29: =1061678+818145 -> 1879823 | P29: =879196+750322 -> 1629518 | Q29: =871157+601329 -> 1472486 | T29: =773630+795411 -> 1569041 | U29: =879196+750322 -> 1629518 | V29: =700641+854392 -> 1555033 | W29: =628617+818870 -> 1447487 | X29: =743660+654526 -> 1398186 | Y29: =871157+601329 -> 1472486 | Z29: =632195+675049 -> 1307244 | AA29: =607414+676576 -> 1283990 | AC29: =AA29 -> 1283990
B30: Acc receivable | M30: =251988+74831 -> 326819 | N30: =374217+69260 -> 443477 | O30: =436296+84197 -> 520493 | P30: =451131+88735 -> 539866 | Q30: =488265+92440 -> 580705 | T30: =336137+109918 -> 446055 | U30: =451131+88735 -> 539866 | V30: =266619+103150 -> 369769 | W30: =269810+117418 -> 387228 | X30: =366757+129335 -> 496092 | Y30: =488265+92440 -> 580705 | Z30: 299999 | AA30: 307112 | AC30: =AA30 -> 307112
B31: Inventory | M31: 0 | N31: 0 | O31: 0 | P31: 0 | Q31: 0 | T31: 0 | U31: 0 | V31: 0 | W31: 0 | X31: 0 | Y31: 0 | Z31: 0 | AA31: 0 | AC31: =AA31 -> 0
B32: Current assets | M32: 2277301 | N32: 2344407 | O32: 2580412 | P32: 2338559 | Q32: 2243945 | T32: 2176478 | U32: 2338559 | V32: 2109669 | W32: 2030736 | X32: 2093343 | Y32: 2243945 | Z32: 1918362 | AA32: 1926630 | AC32: =AA32 -> 1926630
B33: PP&E | M33: 17176 | N33: 29045 | O33: 23982 | P33: 32740 | Q33: 46014 | T33: 25132 | U33: 32740 | V33: 41964 | W33: 41545 | X33: 44604 | Y33: 46014 | Z33: 45585 | AA33: 46436 | AC33: =AA33 -> 46436
B34: Marketable securities and investments | M34: 19523 | N34: 2942 | O34: 0 | P34: 94113 | Q34: 216990 | T34: 34397 | U34: 94113 | V34: 36467 | W34: 75151 | X34: 121609 | Y34: 216990 | Z34: 108502 | AA34: 121035 | AC34: =AA34 -> 121035
B35: Goodwill | M35: 53564 | N35: 88010 | O35: 89026 | P35: 87304 | Q35: 125310 | T35: 89864 | U35: 87304 | V35: 121371 | W35: 120800 | X35: 120625 | Y35: 125310 | Z35: 185695 | AA35: 179481 | AC35: =AA35 -> 179481
B36: Long term assets | M36: =M37-M32 -> 295149 | N36: =N37-N32 -> 390799 | O36: =O37-O32 -> 374346 | P36: =P37-P32 -> 526711 | Q36: =Q37-Q32 -> 935255 | T36: =T37-T32 -> 486813 | U36: =U37-U32 -> 526711 | V36: =V37-V32 -> 534773 | W36: =W37-W32 -> 561581 | X36: =X37-X32 -> 802633 | Y36: =Y37-Y32 -> 935255 | Z36: =Z37-Z32 -> 986338 | AA36: =AA37-AA32 -> 980737 | AC36: =AA36 -> 980737
B37: Total assets | M37: 2572450 | N37: 2735206 | O37: 2954758 | P37: 2865270 | Q37: 3179200 | T37: 2663291 | U37: 2865270 | V37: 2644442 | W37: 2592317 | X37: 2895976 | Y37: 3179200 | Z37: 2904700 | AA37: 2907367 | AC37: =AA37 -> 2907367
B38: Acc payable | M38: 11515 | N38: 8891 | O38: 3447 | P38: 33178 | Q38: 10161 | T38: 18426 | U38: 33178 | V38: 16885 | W38: 19743 | X38: 14280 | Y38: 10161 | Z38: 19699 | AA38: 16484 | AC38: =AA38 -> 16484
B39: Debt | M39: 0 | N39: 0 | O39: 0 | P39: 0 | Q39: 0 | T39: 0 | U39: 0 | V39: 0 | W39: 0 | X39: 0 | Y39: 0 | Z39: 0 | AA39: 0 | AC39: =AA39 -> 0
B40: Current liabilities | M40: 527501 | N40: 626452 | O40: 711691 | P40: 798920 | Q40: 905423 | T40: 695473 | U40: 798920 | V40: 715867 | W40: 738417 | X40: 788700 | Y40: 905423 | Z40: 831666 | AA40: 807258 | AC40: =AA40 -> 807258
B41: Debt | M41: 0 | N41: 0 | O41: 0 | P41: 0 | Q41: 0 | T41: 0 | U41: 0 | V41: 0 | W41: 0 | X41: 0 | Y41: 0 | Z41: 0 | AA41: 0 | AC41: =AA41 -> 0
B42: Long term liabilities | M42: =M43-M40 -> 123032 | N42: =N43-N40 -> 188596 | O42: =O43-O40 -> 226953 | P42: =P43-P40 -> 220588 | Q42: =Q43-Q40 -> 191190 | T42: =T43-T40 -> 235973 | U42: =U43-U40 -> 220588 | V42: =V43-V40 -> 230114 | W42: =W43-W40 -> 188197 | X42: =X43-X40 -> 182659 | Y42: =Y43-Y40 -> 191190 | Z42: =Z43-Z40 -> 170069 | AA42: =AA43-AA40 -> 151558 | AC42: =AA42 -> 151558
B43: Total liabilities | M43: 650533 | N43: 815048 | O43: 938644 | P43: 1019508 | Q43: 1096613 | T43: 931446 | U43: 1019508 | V43: 945981 | W43: 926614 | X43: 971359 | Y43: 1096613 | Z43: 1001735 | AA43: 958816 | AC43: =AA43 -> 958816
B44: Treasury stock | M44: 0 | N44: 0 | O44: -102615 | P44: -494779 | Q44: -833905 | T44: -486985 | U44: -494779 | V44: -724224 | W44: -824842 | X44: -824329 | Y44: -833905 | Z44: -1069595 | AA44: -1092834 | AC44: =AA44 -> -1092834
B45: Preferred stock | M45: 0 | N45: 0 | O45: 0 | P45: 0 | Q45: 0 | T45: 0 | U45: 0 | V45: 0 | W45: 0 | X45: 0 | Y45: 0 | Z45: 0 | AA45: 0 | AC45: =AA45 -> 0
B46: Paid in capital | M46: 3406959 | N46: 3736838 | O46: 4024079 | P46: 4333300 | Q46: 4585430 | T46: 4149569 | U46: 4333300 | V46: 4403586 | W46: 4474638 | X46: 4531257 | Y46: 4585430 | Z46: 4628200 | AA46: 4673653 | AC46: =AA46 -> 4673653
B47: Accumulated income/loss | M47: -1495946 | N47: -1824298 | O47: -1914181 | P47: -1987875 | Q47: -1705545 | T47: -2039669 | U47: -1987875 | V47: -2010430 | W47: -2008846 | X47: -1810007 | Y47: -1705545 | Z47: -1683020 | AA47: -1646931 | AC47: =AA47 -> -1646931
B48: Non-controlling interest | M48: 0 | N48: 0 | O48: 0 | P48: 0 | Q48: 0 | T48: 0 | U48: 0 | V48: 0 | W48: 0 | X48: 0 | Y48: 0 | Z48: 0 | AA48: 0 | AC48: =AA48 -> 0
B49: Stockholder equity | M49: 1921917 | N49: 1920158 | O49: 2016114 | P49: 1845762 | Q49: 2082587 | T49: 1731845 | U49: 1845762 | V49: 1698461 | W49: 1665703 | X49: 1924617 | Y49: 2082587 | Z49: 1902965 | AA49: 1948551 | AC49: =AA49 -> 1948551
B50: Total liabilities and equity | M50: 2572450 | N50: 2735206 | O50: 2954758 | P50: 2865270 | Q50: 3179200 | T50: 2663291 | U50: 2865270 | V50: 2644442 | W50: 2592317 | X50: 2895976 | Y50: 3179200 | Z50: 2904700 | AA50: 2907367 | AC50: =AA50 -> 2907367
B52: Cashflow statement
B53: D&A | M53: 14705 | N53: 18723 | O53: 22597 | P53: 17232 | Q53: 16969 | T53: 4534 | V53: 3253 | W53: 4230 | X53: 4513 | Y53: 4973 | Z53: 7509 | AA53: 9005 | AC53: =SUM(X53:AA53) -> 26000
B54: Stock-based compensation | M54: 515583 | N54: 369840 | O54: 371955 | P54: 358151 | Q54: 290676 | T54: 87488 | V54: 76361 | W54: 78006 | X54: 71475 | Y54: 64834 | Z54: 53310 | AA54: 44962 | AC54: =SUM(X54:AA54) -> 234581
B55: Change in accounts receivable | M55: -86387 | N55: -123783 | O55: -64217 | P55: -22173 | Q55: -25802 | T55: -67719 | V55: 197443 | W55: -5039 | X55: -98947 | Y55: -119259 | Z55: 194865 | AA55: -13656 | AC55: =SUM(X55:AA55) -> -36997
B56: Change in inventory | M56: 0 | N56: 0 | O56: 0 | P56: 0 | Q56: 0 | T56: 0 | U56: 0 | V56: 0 | W56: 0 | X56: 0 | Y56: 0 | Z56: 0 | AA56: 0 | AC56: =SUM(X56:AA56) -> 0
B57: Change in accounts payable | M57: 3507 | N57: -1571 | O57: -5052 | P57: 27856 | Q57: -21675 | T57: 8180 | V57: -15025 | W57: 3319 | X57: -5695 | Y57: -4274 | Z57: 9390 | AA57: -2533 | AC57: =SUM(X57:AA57) -> -3112
B58: Change in other operating NWC | M58: =-43660-130186-15360+45729+24038-9064+105481 -> -23022 | N58: =-185-118909-59810-14954+15086-3307+160746 -> -21333 | O58: =-14694-118833+4222+11804-4039-13590+137471 -> 2341 | P58: =-3991-89157+7065+9235-23428-15527+68348 -> -47455 | Q58: =3208-116202-3933+46697+2583-11652-22431 -> -101730 | T58: 7517 | V58: =-9460-13954-13074+12352-72534-2146-60261 -> -159077 | W58: -55572 | X58: 9189 | Y58: 103730 | Z58: =-13977-26645-12870-24991-61062-4458-55423 -> -199426 | AA58: -87170 | AC58: =SUM(X58:AA58) -> -173677
B59: Operating cashflow | M59: -54963 | N59: -9981 | O59: 299082 | P59: 320565 | Q59: 371208 | T59: 28070 | V59: 119002 | W59: 41587 | X59: 28271 | Y59: 182348 | Z59: 131928 | AA59: 30699 | AC59: =SUM(X59:AA59) -> 373246
B60: CapEx | M60: -8879 | N60: -23815 | O60: -7342 | P60: -14923 | Q60: -19048 | T60: -4875 | V60: -12832 | W60: 0 | X60: -3164 | Y60: -3052 | Z60: -2684 | AA60: -1389 | AC60: =SUM(X60:AA60) -> -10289
B61: Capitalized software | M61: -2950 | N61: 0 | O61: 0 | P61: 0 | Q61: 0 | T61: 0 | V61: 0 | W61: 0 | X61: 0 | Y61: 0 | Z61: 0 | AA61: 0 | AC61: =SUM(X61:AA61) -> 0
B62: Investing cashflow | M62: -35442 | N62: -289143 | O62: -439569 | P62: -45503 | Q62: -22466 | T62: -22914 | V62: -79923 | W62: -655 | X62: 100764 | Y62: -42652 | Z62: -112841 | AA62: -15724 | AC62: =SUM(X62:AA62) -> -70453
B63: Repurchase stock | M63: 0 | N63: 0 | O63: -102615 | P63: -390751 | Q63: -329101 | T63: -162651 | V63: -227525 | W63: -101576 | X63: 0 | Y63: 0 | Z63: =-243796 -> -243796 | AA63: -24752 | AC63: =SUM(X63:AA63) -> -268548
B64: Dividends | M64: 0 | N64: 0 | O64: 0 | P64: 0 | Q64: 0 | T64: 0 | U64: 0 | V64: 0 | W64: 0 | X64: 0 | Y64: 0 | Z64: 0 | AA64: 0 | AC64: =SUM(X64:AA64) -> 0
B65: Dividends to minority interest | M65: 0 | N65: 0 | O65: 0 | P65: 0 | Q65: 0 | T65: 0 | U65: 0 | V65: 0 | W65: 0 | X65: 0 | Y65: 0 | Z65: 0 | AA65: 0 | AC65: =SUM(X65:AA65) -> 0
B66: Financing cashflow | M66: 1469673 | N66: -60669 | O66: -196895 | P66: -450515 | Q66: -372375 | T66: -172643 | V66: -235204 | W66: -111602 | X66: -11167 | Y66: -14402 | Z66: -252191 | AA66: -34933 | AC66: =SUM(X66:AA66) -> -312693
B68: Sanity checks
B69: Calculated Net Income | C69: =C5-C6-C11+C13+C14+C16-C17 -> 0 | D69: =D5-D6-D11+D13+D14+D16-D17 -> 0 | E69: =E5-E6-E11+E13+E14+E16-E17 -> 0 | F69: =F5-F6-F11+F13+F14+F16-F17 -> 0 | G69: =G5-G6-G11+G13+G14+G16-G17 -> 0 | H69: =H5-H6-H11+H13+H14+H16-H17 -> 0 | I69: =I5-I6-I11+I13+I14+I16-I17 -> 0 | J69: =J5-J6-J11+J13+J14+J16-J17 -> 0 | ... Q69: =Q5-Q6-Q11+Q13+Q14+Q16-Q17 -> 282330 | T69: =T5-T6-T11+T13+T14+T16-T17 -> -10655 | U69: =U5-U6-U11+U13+U14+U16-U17 -> 51794 | V69: =V5-V6-V11+V13+V14+V16-V17 -> -22555 | W69: =W5-W6-W11+W13+W14+W16-W17 -> 1584 | X69: =X5-X6-X11+X13+X14+X16-X17 -> 198839 | Y69: =Y5-Y6-Y11+Y13+Y14+Y16-Y17 -> 104462 | Z69: =Z5-Z6-Z11+Z13+Z14+Z16-Z17 -> 22525 | AA69: =AA5-AA6-AA11+AA13+AA14+AA16-AA17 -> 36089 | AC69: =AC5-AC6-AC11+AC13+AC14+AC16-AC17 -> 361915
B70: Check Net Income | C70: =C18-C69 -> 0 | D70: =D18-D69 -> 0 | E70: =E18-E69 -> 0 | F70: =F18-F69 -> 0 | G70: =G18-G69 -> 0 | H70: =H18-H69 -> 0 | I70: =I18-I69 -> 0 | J70: =J18-J69 -> 0 | ... Q70: =Q18-Q69 -> 0 | T70: =T18-T69 -> 0 | U70: =U18-U69 -> 0 | V70: =V18-V69 -> 0 | W70: =W18-W69 -> 0 | X70: =X18-X69 -> 0 | Y70: =Y18-Y69 -> 0 | Z70: =Z18-Z69 -> 0 | AA70: =AA18-AA69 -> 0 | AC70: =AC18-AC69 -> 0
B71: Check balance | C71: =C37-(C43+C112) -> 0 | D71: =D37-(D43+D112) -> 0 | E71: =E37-(E43+E112) -> 0 | F71: =F37-(F43+F112) -> 0 | G71: =G37-(G43+G112) -> 0 | H71: =H37-(H43+H112) -> 0 | I71: =I37-(I43+I112) -> 0 | J71: =J37-(J43+J112) -> 0 | ... Q71: =Q37-(Q43+Q112) -> 0 | T71: =T37-(T43+T112) -> 0 | U71: =U37-(U43+U112) -> 0 | V71: =V37-(V43+V112) -> 0 | W71: =W37-(W43+W112) -> 0 | X71: =X37-(X43+X112) -> 0 | Y71: =Y37-(Y43+Y112) -> 0 | Z71: =Z37-(Z43+Z112) -> 0 | AA71: =AA37-(AA43+AA112) -> 0 | AC71: =AC37-(AC43+AC112) -> 0
B73: Other data
B74: Shares outstanding | M74: =459635+82453 -> 542088 | N74: =474970+82453 -> 557423 | O74: =486560+82453 -> 569013 | P74: =474040+77453 -> 551493 | Q74: =459231+64691 -> 523922 | T74: =467146+82453 -> 549599 | U74: =474040+77453 -> 551493 | V74: =457586+77453 -> 535039 | W74: =453569+77453 -> 531022 | X74: =460444+74306 -> 534750 | Y74: =459231+64691 -> 523922 | Z74: =453430+64691 -> 518121 | AA74: =456465+64691 -> 521156 | AC74: =AA74 -> 521156
B75: Split adjusted shares outstanding | M75: =M74*M85 -> 542088 | N75: =N74*N85 -> 557423 | O75: =O74*O85 -> 569013 | P75: =P74*P85 -> 551493 | Q75: =Q74*Q85 -> 523922 | T75: =T74*T85 -> 549599 | U75: =U74*U85 -> 551493 | V75: =V74*V85 -> 535039 | W75: =W74*W85 -> 531022 | X75: =X74*X85 -> 534750 | Y75: =Y74*Y85 -> 523922 | Z75: =Z74*Z85 -> 518121 | AA75: =AA74*AA85 -> 521156 | AC75: =AA75 -> 521156
B76: Dilutive shares | M76: 0 | N76: 0 | O76: 0 | P76: 0 | Q76: 6735 | T76: 0 | U76: 0 | V76: 0 | W76: 6696 | X76: 6763 | Y76: 6735 | Z76: 4234 | AA76: 3359 | AC76: =AA76 -> 3359
B77: Split adjusted dilutive shares | M77: =M76*M85 -> 0 | N77: =N76*N85 -> 0 | O77: =O76*O85 -> 0 | P77: =P76*P85 -> 0 | Q77: =Q76*Q85 -> 6735 | T77: =T76*T85 -> 0 | U77: =U76*U85 -> 0 | V77: =V76*V85 -> 0 | W77: =W76*W85 -> 6696 | X77: =X76*X85 -> 6763 | Y77: =Y76*Y85 -> 6735 | Z77: =Z76*Z85 -> 4234 | AA77: =AA76*AA85 -> 3359 | AC77: =AA77 -> 3359
B78: Split adjusted diluted shares | M78: =M75+M77 -> 542088 | N78: =N75+N77 -> 557423 | O78: =O75+O77 -> 569013 | P78: =P75+P77 -> 551493 | Q78: =Q75+Q77 -> 530657 | T78: =T75+T77 -> 549599 | U78: =U75+U77 -> 551493 | V78: =V75+V77 -> 535039 | W78: =W75+W77 -> 537718 | X78: =X75+X77 -> 541513 | Y78: =Y75+Y77 -> 530657 | Z78: =Z75+Z77 -> 522355 | AA78: =AA75+AA77 -> 524515 | AC78: =AA78 -> 524515
B79: Shares held by insiders | M79: =91239+82453 -> 173692 | N79: =91503+82453 -> 173956 | O79: =45636+82453 -> 128089 | P79: =46600+77453 -> 124053 | Q79: =52118+64691 -> 116809 | AC79: =Q79 -> 116809
B80: Split adjusted shares held by insiders | M80: =M79*M85 -> 173692 | N80: =N79*N85 -> 173956 | O80: =O79*O85 -> 128089 | P80: =P79*P85 -> 124053 | Q80: =Q79*Q85 -> 116809 | AC80: =Q80 -> 116809
B81: Dividends per share | M81: 0 | N81: 0 | O81: 0 | P81: 0 | Q81: 0 | T81: 0 | U81: 0 | V81: 0 | W81: 0 | X81: 0 | Y81: 0 | Z81: 0 | AA81: 0 | AC81: =SUM(X81:AA81) -> 0
B82: Split adjusted dividends per share | M82: =M81/M85 -> 0 | N82: =N81/N85 -> 0 | O82: =O81/O85 -> 0 | P82: =P81/P85 -> 0 | Q82: =Q81/Q85 -> 0 | T82: =T81/T85 -> 0 | U82: =U81/U85 -> 0 | V82: =V81/V85 -> 0 | W82: =W81/W85 -> 0 | X82: =X81/X85 -> 0 | Y82: =Y81/Y85 -> 0 | Z82: =Z81/Z85 -> 0 | AA82: =AA81/AA85 -> 0 | AC82: =SUM(X82:AA82) -> 0
B83: Tax rate | C83: =IF(AND(C15>0,C16<0),-(C16)/C15,0) -> 0 | D83: =IF(AND(D15>0,D16<0),-(D16)/D15,0) -> 0 | E83: =IF(AND(E15>0,E16<0),-(E16)/E15,0) -> 0 | F83: =IF(AND(F15>0,F16<0),-(F16)/F15,0) -> 0 | G83: =IF(AND(G15>0,G16<0),-(G16)/G15,0) -> 0 | H83: =IF(AND(H15>0,H16<0),-(H16)/H15,0) -> 0 | I83: =IF(AND(I15>0,I16<0),-(I16)/I15,0) -> 0 | J83: =IF(AND(J15>0,J16<0),-(J16)/J15,0) -> 0 | ... Q83: =IF(AND(Q15>0,Q16<0),-(Q16)/Q15,0) -> 0 | T83: =IF(AND(T15>0,T16<0),-(T16)/T15,0) -> 0 | U83: =IF(AND(U15>0,U16<0),-(U16)/U15,0) -> 0.051808729 | V83: =IF(AND(V15>0,V16<0),-(V16)/V15,0) -> 0 | W83: =IF(AND(W15>0,W16<0),-(W16)/W15,0) -> 0.5238954 | X83: =IF(AND(X15>0,X16<0),-(X16)/X15,0) -> 0 | Y83: =IF(AND(Y15>0,Y16<0),-(Y16)/Y15,0) -> 0 | Z83: =IF(AND(Z15>0,Z16<0),-(Z16)/Z15,0) -> 0.45018063 | AA83: =IF(AND(AA15>0,AA16<0),-(AA16)/AA15,0) -> 0.31720745 | AC83: =IF(AND(AC15>0,AC16<0),-(AC16)/AC15,0) -> 0
B84: Employees | M84: 4013 | N84: 3833 | O84: 4035 | P84: 3868 | Q84: 3981 | AC84: =Q84 -> 3981
B85: Stock split factor | M85: 1 | N85: 1 | O85: 1 | P85: 1 | Q85: 1 | T85: 1 | U85: 1 | V85: 1 | W85: 1 | X85: 1 | Y85: 1 | Z85: 1 | AA85: 1 | AC85: 1
B88: Growth rates Income Statement
B89: Revenue | M89: =IF(L5=0, IF(M5=0,0,IF(M5>0,1,-1)), (M5-L5)/ABS(L5) ) -> 1 | N89: =IF(M5=0, IF(N5=0,0,IF(N5>0,1,-1)), (N5-M5)/ABS(M5) ) -> 0.18641482 | O89: =IF(N5=0, IF(O5=0,0,IF(O5>0,1,-1)), (O5-N5)/ABS(N5) ) -> 0.23568437 | P89: =IF(O5=0, IF(P5=0,0,IF(P5>0,1,-1)), (P5-O5)/ABS(O5) ) -> 0.092955128 | Q89: =IF(P5=0, IF(Q5=0,0,IF(Q5>0,1,-1)), (Q5-P5)/ABS(P5) ) -> 0.12653882 | T89: =IF(S5=0, IF(T5=0,0,IF(T5>0,1,-1)), (T5-S5)/ABS(S5) ) -> 1 | U89: =IF(T5=0, IF(U5=0,0,IF(U5>0,1,-1)), (U5-T5)/ABS(T5) ) -> 0.19453663 | V89: =IF(U5=0, IF(V5=0,0,IF(V5>0,1,-1)), (V5-U5)/ABS(U5) ) -> -0.15820284 | W89: =IF(V5=0, IF(W5=0,0,IF(W5>0,1,-1)), (W5-V5)/ABS(V5) ) -> 0.014311992 | X89: =IF(W5=0, IF(X5=0,0,IF(X5>0,1,-1)), (X5-W5)/ABS(W5) ) -> 0.13652523 | Y89: =IF(X5=0, IF(Y5=0,0,IF(Y5>0,1,-1)), (Y5-X5)/ABS(X5) ) -> 0.17025489 | Z89: =IF(Y5=0, IF(Z5=0,0,IF(Z5>0,1,-1)), (Z5-Y5)/ABS(Y5) ) -> -0.1303764 | AA89: =IF(Z5=0, IF(AA5=0,0,IF(AA5>0,1,-1)), (AA5-Z5)/ABS(Z5) ) -> -0.019422442
B90: COGS | M90: =IF(L6=0, IF(M6=0,0,IF(M6>0,1,-1)), (M6-L6)/ABS(L6) ) -> 1 | N90: =IF(M6=0, IF(N6=0,0,IF(N6>0,1,-1)), (N6-M6)/ABS(M6) ) -> 0.066223322 | O90: =IF(N6=0, IF(O6=0,0,IF(O6>0,1,-1)), (O6-N6)/ABS(N6) ) -> 0.088158355 | P90: =IF(O6=0, IF(P6=0,0,IF(P6>0,1,-1)), (P6-O6)/ABS(O6) ) -> 0.26039689 | Q90: =IF(P6=0, IF(Q6=0,0,IF(Q6>0,1,-1)), (Q6-P6)/ABS(P6) ) -> 0.097358894 | T90: =IF(S6=0, IF(T6=0,0,IF(T6>0,1,-1)), (T6-S6)/ABS(S6) ) -> 1 | U90: =IF(T6=0, IF(U6=0,0,IF(U6>0,1,-1)), (U6-T6)/ABS(T6) ) -> 0.012091652 | V90: =IF(U6=0, IF(V6=0,0,IF(V6>0,1,-1)), (V6-U6)/ABS(U6) ) -> -0.010490594 | W90: =IF(V6=0, IF(W6=0,0,IF(W6>0,1,-1)), (W6-V6)/ABS(V6) ) -> 0.0081901749 | X90: =IF(W6=0, IF(X6=0,0,IF(X6>0,1,-1)), (X6-W6)/ABS(W6) ) -> 0.068841255 | Y90: =IF(X6=0, IF(Y6=0,0,IF(Y6>0,1,-1)), (Y6-X6)/ABS(X6) ) -> 0.074449224 | Z90: =IF(Y6=0, IF(Z6=0,0,IF(Z6>0,1,-1)), (Z6-Y6)/ABS(Y6) ) -> 0.040481504 | AA90: =IF(Z6=0, IF(AA6=0,0,IF(AA6>0,1,-1)), (AA6-Z6)/ABS(Z6) ) -> 0.047563956
B91: Gross Profit | M91: =IF(L7=0, IF(M7=0,0,IF(M7>0,1,-1)), (M7-L7)/ABS(L7) ) -> 1 | N91: =IF(M7=0, IF(N7=0,0,IF(N7>0,1,-1)), (N7-M7)/ABS(M7) ) -> 0.21447253 | O91: =IF(N7=0, IF(O7=0,0,IF(O7>0,1,-1)), (O7-N7)/ABS(N7) ) -> 0.26591921 | P91: =IF(O7=0, IF(P7=0,0,IF(P7>0,1,-1)), (P7-O7)/ABS(O7) ) -> 0.063457382 | Q91: =IF(P7=0, IF(Q7=0,0,IF(Q7>0,1,-1)), (Q7-P7)/ABS(P7) ) -> 0.13263134 | T91: =IF(S7=0, IF(T7=0,0,IF(T7>0,1,-1)), (T7-S7)/ABS(S7) ) -> 1 | U91: =IF(T7=0, IF(U7=0,0,IF(U7>0,1,-1)), (U7-T7)/ABS(T7) ) -> 0.23452852 | V91: =IF(U7=0, IF(V7=0,0,IF(V7>0,1,-1)), (V7-U7)/ABS(U7) ) -> -0.18474738 | W91: =IF(V7=0, IF(W7=0,0,IF(W7>0,1,-1)), (W7-V7)/ABS(V7) ) -> 0.015647255 | X91: =IF(W7=0, IF(X7=0,0,IF(X7>0,1,-1)), (X7-W7)/ABS(W7) ) -> 0.15117976 | Y91: =IF(X7=0, IF(Y7=0,0,IF(Y7>0,1,-1)), (Y7-X7)/ABS(X7) ) -> 0.18951449 | Z91: =IF(Y7=0, IF(Z7=0,0,IF(Z7>0,1,-1)), (Z7-Y7)/ABS(Y7) ) -> -0.16140108 | AA91: =IF(Z7=0, IF(AA7=0,0,IF(AA7>0,1,-1)), (AA7-Z7)/ABS(Z7) ) -> -0.034514166
B92: Sales and marketing | M92: =IF(L8=0, IF(M8=0,0,IF(M8>0,1,-1)), (M8-L8)/ABS(L8) ) -> 1 | N92: =IF(M8=0, IF(N8=0,0,IF(N8>0,1,-1)), (N8-M8)/ABS(M8) ) -> 0.0055555396 | O92: =IF(N8=0, IF(O8=0,0,IF(O8>0,1,-1)), (O8-N8)/ABS(N8) ) -> 0.016494716 | P92: =IF(O8=0, IF(P8=0,0,IF(P8>0,1,-1)), (P8-O8)/ABS(O8) ) -> 0.035565745 | Q92: =IF(P8=0, IF(Q8=0,0,IF(Q8>0,1,-1)), (Q8-P8)/ABS(P8) ) -> -0.074698068 | T92: =IF(S8=0, IF(T8=0,0,IF(T8>0,1,-1)), (T8-S8)/ABS(S8) ) -> 1 | U92: =IF(T8=0, IF(U8=0,0,IF(U8>0,1,-1)), (U8-T8)/ABS(T8) ) -> -0.05530269 | V92: =IF(U8=0, IF(V8=0,0,IF(V8>0,1,-1)), (V8-U8)/ABS(U8) ) -> -0.097123889 | W92: =IF(V8=0, IF(W8=0,0,IF(W8>0,1,-1)), (W8-V8)/ABS(V8) ) -> 0.041600641 | X92: =IF(W8=0, IF(X8=0,0,IF(X8>0,1,-1)), (X8-W8)/ABS(W8) ) -> 0.077467033 | Y92: =IF(X8=0, IF(Y8=0,0,IF(Y8>0,1,-1)), (Y8-X8)/ABS(X8) ) -> -0.0056198587 | Z92: =IF(Y8=0, IF(Z8=0,0,IF(Z8>0,1,-1)), (Z8-Y8)/ABS(Y8) ) -> -0.057919283 | AA92: =IF(Z8=0, IF(AA8=0,0,IF(AA8>0,1,-1)), (AA8-Z8)/ABS(Z8) ) -> -0.01937936
B93: R&D | M93: =IF(L9=0, IF(M9=0,0,IF(M9>0,1,-1)), (M9-L9)/ABS(L9) ) -> 1 | N93: =IF(M9=0, IF(N9=0,0,IF(N9>0,1,-1)), (N9-M9)/ABS(M9) ) -> 0.032867413 | O93: =IF(N9=0, IF(O9=0,0,IF(O9>0,1,-1)), (O9-N9)/ABS(N9) ) -> 0.16220822 | P93: =IF(O9=0, IF(P9=0,0,IF(P9>0,1,-1)), (P9-O9)/ABS(O9) ) -> 0.14628381 | Q93: =IF(P9=0, IF(Q9=0,0,IF(Q9>0,1,-1)), (Q9-P9)/ABS(P9) ) -> 0.011889188 | T93: =IF(S9=0, IF(T9=0,0,IF(T9>0,1,-1)), (T9-S9)/ABS(S9) ) -> 1 | U93: =IF(T9=0, IF(U9=0,0,IF(U9>0,1,-1)), (U9-T9)/ABS(T9) ) -> 0.027780069 | V93: =IF(U9=0, IF(V9=0,0,IF(V9>0,1,-1)), (V9-U9)/ABS(U9) ) -> -0.048469951 | W93: =IF(V9=0, IF(W9=0,0,IF(W9>0,1,-1)), (W9-V9)/ABS(V9) ) -> 0.036925737 | X93: =IF(W9=0, IF(X9=0,0,IF(X9>0,1,-1)), (X9-W9)/ABS(W9) ) -> -0.014968325 | Y93: =IF(X9=0, IF(Y9=0,0,IF(Y9>0,1,-1)), (Y9-X9)/ABS(X9) ) -> -0.017652706 | Z93: =IF(Y9=0, IF(Z9=0,0,IF(Z9>0,1,-1)), (Z9-Y9)/ABS(Y9) ) -> -0.023718198 | AA93: =IF(Z9=0, IF(AA9=0,0,IF(AA9>0,1,-1)), (AA9-Z9)/ABS(Z9) ) -> -0.10235517
B94: General and administrative | M94: =IF(L10=0, IF(M10=0,0,IF(M10>0,1,-1)), (M10-L10)/ABS(L10) ) -> 1 | N94: =IF(M10=0, IF(N10=0,0,IF(N10>0,1,-1)), (N10-M10)/ABS(M10) ) -> -0.04194551 | O94: =IF(N10=0, IF(O10=0,0,IF(O10>0,1,-1)), (O10-N10)/ABS(N10) ) -> -0.032851089 | P94: =IF(O10=0, IF(P10=0,0,IF(P10>0,1,-1)), (P10-O10)/ABS(O10) ) -> -0.023834707 | Q94: =IF(P10=0, IF(Q10=0,0,IF(Q10>0,1,-1)), (Q10-P10)/ABS(P10) ) -> -0.052296167 | T94: =IF(S10=0, IF(T10=0,0,IF(T10>0,1,-1)), (T10-S10)/ABS(S10) ) -> 1 | U94: =IF(T10=0, IF(U10=0,0,IF(U10>0,1,-1)), (U10-T10)/ABS(T10) ) -> -0.021820723 | V94: =IF(U10=0, IF(V10=0,0,IF(V10>0,1,-1)), (V10-U10)/ABS(U10) ) -> 0.11596628 | W94: =IF(V10=0, IF(W10=0,0,IF(W10>0,1,-1)), (W10-V10)/ABS(V10) ) -> -0.032736517 | X94: =IF(W10=0, IF(X10=0,0,IF(X10>0,1,-1)), (X10-W10)/ABS(W10) ) -> 0.0054075517 | Y94: =IF(X10=0, IF(Y10=0,0,IF(Y10>0,1,-1)), (Y10-X10)/ABS(X10) ) -> 0.0070145745 | Z94: =IF(Y10=0, IF(Z10=0,0,IF(Z10>0,1,-1)), (Z10-Y10)/ABS(Y10) ) -> -0.01572421 | AA94: =IF(Z10=0, IF(AA10=0,0,IF(AA10>0,1,-1)), (AA10-Z10)/ABS(Z10) ) -> -0.050089174
B95: OpEx | M95: =IF(L11=0, IF(M11=0,0,IF(M11>0,1,-1)), (M11-L11)/ABS(L11) ) -> 1 | N95: =IF(M11=0, IF(N11=0,0,IF(N11>0,1,-1)), (N11-M11)/ABS(M11) ) -> 0.002028048 | O95: =IF(N11=0, IF(O11=0,0,IF(O11>0,1,-1)), (O11-N11)/ABS(N11) ) -> 0.040800839 | P95: =IF(O11=0, IF(P11=0,0,IF(P11>0,1,-1)), (P11-O11)/ABS(O11) ) -> 0.053586588 | Q95: =IF(P11=0, IF(Q11=0,0,IF(Q11>0,1,-1)), (Q11-P11)/ABS(P11) ) -> -0.046430847 | T95: =IF(S11=0, IF(T11=0,0,IF(T11>0,1,-1)), (T11-S11)/ABS(S11) ) -> 1 | U95: =IF(T11=0, IF(U11=0,0,IF(U11>0,1,-1)), (U11-T11)/ABS(T11) ) -> -0.026180689 | V95: =IF(U11=0, IF(V11=0,0,IF(V11>0,1,-1)), (V11-U11)/ABS(U11) ) -> -0.050150075 | W95: =IF(V11=0, IF(W11=0,0,IF(W11>0,1,-1)), (W11-V11)/ABS(V11) ) -> 0.027019946 | X95: =IF(W11=0, IF(X11=0,0,IF(X11>0,1,-1)), (X11-W11)/ABS(W11) ) -> 0.036837116 | Y95: =IF(X11=0, IF(Y11=0,0,IF(Y11>0,1,-1)), (Y11-X11)/ABS(X11) ) -> -0.0071196428 | Z95: =IF(Y11=0, IF(Z11=0,0,IF(Z11>0,1,-1)), (Z11-Y11)/ABS(Y11) ) -> -0.041051009 | AA95: =IF(Z11=0, IF(AA11=0,0,IF(AA11>0,1,-1)), (AA11-Z11)/ABS(Z11) ) -> -0.049134359
B96: Operating income | M96: =IF(L12=0, IF(M12=0,0,IF(M12>0,1,-1)), (M12-L12)/ABS(L12) ) -> -1 | N96: =IF(M12=0, IF(N12=0,0,IF(N12>0,1,-1)), (N12-M12)/ABS(M12) ) -> 0.30474941 | O96: =IF(N12=0, IF(O12=0,0,IF(O12>0,1,-1)), (O12-N12)/ABS(N12) ) -> 0.52705128 | P96: =IF(O12=0, IF(P12=0,0,IF(P12>0,1,-1)), (P12-O12)/ABS(O12) ) -> 0.013058524 | Q96: =IF(P12=0, IF(Q12=0,0,IF(Q12>0,1,-1)), (Q12-P12)/ABS(P12) ) -> 1.3491441 | T96: =IF(S12=0, IF(T12=0,0,IF(T12>0,1,-1)), (T12-S12)/ABS(S12) ) -> -1 | U96: =IF(T12=0, IF(U12=0,0,IF(U12>0,1,-1)), (U12-T12)/ABS(T12) ) -> 1.7750438 | V96: =IF(U12=0, IF(V12=0,0,IF(V12>0,1,-1)), (V12-U12)/ABS(U12) ) -> -1.4883216 | W96: =IF(V12=0, IF(W12=0,0,IF(W12>0,1,-1)), (W12-V12)/ABS(V12) ) -> -0.22989276 | X96: =IF(W12=0, IF(X12=0,0,IF(X12>0,1,-1)), (X12-W12)/ABS(W12) ) -> 1.6475601 | Y96: =IF(X12=0, IF(Y12=0,0,IF(Y12>0,1,-1)), (Y12-X12)/ABS(X12) ) -> 5.1422997 | Z96: =IF(Y12=0, IF(Z12=0,0,IF(Z12>0,1,-1)), (Z12-Y12)/ABS(Y12) ) -> -0.65140871 | AA96: =IF(Z12=0, IF(AA12=0,0,IF(AA12>0,1,-1)), (AA12-Z12)/ABS(Z12) ) -> 0.12923858
B97: Income before taxes | M97: =IF(L15=0, IF(M15=0,0,IF(M15>0,1,-1)), (M15-L15)/ABS(L15) ) -> -1 | N97: =IF(M15=0, IF(N15=0,0,IF(N15>0,1,-1)), (N15-M15)/ABS(M15) ) -> 0.37840758 | O97: =IF(N15=0, IF(O15=0,0,IF(O15>0,1,-1)), (O15-N15)/ABS(N15) ) -> 0.76125847 | P97: =IF(O15=0, IF(P15=0,0,IF(P15>0,1,-1)), (P15-O15)/ABS(O15) ) -> -0.030139155 | Q97: =IF(P15=0, IF(Q15=0,0,IF(Q15>0,1,-1)), (Q15-P15)/ABS(P15) ) -> 2.2884507 | T97: =IF(S15=0, IF(T15=0,0,IF(T15>0,1,-1)), (T15-S15)/ABS(S15) ) -> -1 | U97: =IF(T15=0, IF(U15=0,0,IF(U15>0,1,-1)), (U15-T15)/ABS(T15) ) -> 3.1422017 | V97: =IF(U15=0, IF(V15=0,0,IF(V15>0,1,-1)), (V15-U15)/ABS(U15) ) -> -1.3611599 | W97: =IF(V15=0, IF(W15=0,0,IF(W15>0,1,-1)), (W15-V15)/ABS(V15) ) -> 1.1686436 | X97: =IF(W15=0, IF(X15=0,0,IF(X15>0,1,-1)), (X15-W15)/ABS(W15) ) -> 6.3916441 | Y97: =IF(X15=0, IF(Y15=0,0,IF(Y15>0,1,-1)), (Y15-X15)/ABS(X15) ) -> 2.758824 | Z97: =IF(Y15=0, IF(Z15=0,0,IF(Z15>0,1,-1)), (Z15-Y15)/ABS(Y15) ) -> -0.55680085 | AA97: =IF(Z15=0, IF(AA15=0,0,IF(AA15>0,1,-1)), (AA15-Z15)/ABS(Z15) ) -> 0.29015329
B98: Net income | M98: =IF(L18=0, IF(M18=0,0,IF(M18>0,1,-1)), (M18-L18)/ABS(L18) ) -> -1 | N98: =IF(M18=0, IF(N18=0,0,IF(N18>0,1,-1)), (N18-M18)/ABS(M18) ) -> 0.37526494 | O98: =IF(N18=0, IF(O18=0,0,IF(O18>0,1,-1)), (O18-N18)/ABS(N18) ) -> 0.72626023 | P98: =IF(O18=0, IF(P18=0,0,IF(P18>0,1,-1)), (P18-O18)/ABS(O18) ) -> 0.18011192 | Q98: =IF(P18=0, IF(Q18=0,0,IF(Q18>0,1,-1)), (Q18-P18)/ABS(P18) ) -> 4.8311124 | T98: =IF(S18=0, IF(T18=0,0,IF(T18>0,1,-1)), (T18-S18)/ABS(S18) ) -> -1 | U98: =IF(T18=0, IF(U18=0,0,IF(U18>0,1,-1)), (U18-T18)/ABS(T18) ) -> 5.8610042 | V98: =IF(U18=0, IF(V18=0,0,IF(V18>0,1,-1)), (V18-U18)/ABS(U18) ) -> -1.4354752 | W98: =IF(V18=0, IF(W18=0,0,IF(W18>0,1,-1)), (W18-V18)/ABS(V18) ) -> 1.0702283 | X98: =IF(W18=0, IF(X18=0,0,IF(X18>0,1,-1)), (X18-W18)/ABS(W18) ) -> 124.52967 | Y98: =IF(X18=0, IF(Y18=0,0,IF(Y18>0,1,-1)), (Y18-X18)/ABS(X18) ) -> -0.47464029 | Z98: =IF(Y18=0, IF(Z18=0,0,IF(Z18>0,1,-1)), (Z18-Y18)/ABS(Y18) ) -> -0.78437135 | AA98: =IF(Z18=0, IF(AA18=0,0,IF(AA18>0,1,-1)), (AA18-Z18)/ABS(Z18) ) -> 0.60217536
B100: Margins
B101: Gross margin | M101: =M7/M5 -> 0.81073957 | N101: =N7/N5 -> 0.82991287 | O101: =O7/O5 -> 0.85021925 | P101: =P7/P5 -> 0.8272727 | Q101: =Q7/Q5 -> 0.83174673 | T101: =T7/T5 -> 0.82021018 | U101: =U7/U5 -> 0.84766999 | V101: =V7/V5 -> 0.82094026 | W101: =W7/W5 -> 0.82202097 | X101: =X7/X5 -> 0.83262023 | Y101: =Y7/Y5 -> 0.84632317 | Z101: =Z7/Z5 -> 0.81612976 | AA101: =AA7/AA5 -> 0.80356899 | AC101: =AC7/AC5 -> 0.82551611
B102: Operating margin | M102: =M12/M5 -> -0.56144004 | N102: =N12/N5 -> -0.32900931 | O102: =O12/O5 -> -0.12592579 | P102: =P12/P5 -> -0.11371133 | Q102: =Q12/Q5 -> 0.035242138 | T102: =T12/T5 -> -0.12227163 | U102: =U12/U5 -> 0.079332745 | V102: =V12/V5 -> -0.046020459 | W102: =W12/W5 -> -0.055801597 | X102: =X12/X5 -> 0.031794178 | Y102: =Y12/Y5 -> 0.16687764 | Z102: =Z12/Z5 -> 0.066893413 | AA102: =AA12/AA5 -> 0.077034827 | AC102: =AC12/AC5 -> 0.08887892
B103: Net margin | M103: =M111/M5 -> -0.58905556 | N103: =N111/N5 -> -0.31018127 | O103: =O111/O5 -> -0.068714107 | P103: =P111/P5 -> -0.051546377 | Q103: =Q111/Q5 -> 0.17529797 | T103: =T111/T5 -> -0.030043451 | U103: =U111/U5 -> 0.12225773 | V103: =V111/V5 -> -0.063245884 | W103: =W111/W5 -> 0.0043789809 | X103: =X111/X5 -> 0.48366021 | Y103: =Y111/Y5 -> 0.21712841 | Z103: =Z111/Z5 -> 0.053838358 | AA103: =AA111/AA5 -> 0.087967025 | AC103: =AC111/AC5 -> 0.21031079
B105: Adjustments
B106: Tax rate | C106: =IF(AND(C83>=0,C12>=0),C83,0) -> 0 | D106: =IF(AND(D83>=0,D12>=0),D83,0) -> 0 | E106: =IF(AND(E83>=0,E12>=0),E83,0) -> 0 | F106: =IF(AND(F83>=0,F12>=0),F83,0) -> 0 | G106: =IF(AND(G83>=0,G12>=0),G83,0) -> 0 | H106: =IF(AND(H83>=0,H12>=0),H83,0) -> 0 | I106: =IF(AND(I83>=0,I12>=0),I83,0) -> 0 | J106: =IF(AND(J83>=0,J12>=0),J83,0) -> 0 | ... Q106: =IF(AND(Q83>=0,Q12>=0),Q83,0) -> 0 | T106: =IF(AND(T83>=0,T12>=0),T83,0) -> 0 | U106: =IF(AND(U83>=0,U12>=0),U83,0) -> 0.051808729 | V106: =IF(AND(V83>=0,V12>=0),V83,0) -> 0 | W106: =IF(AND(W83>=0,W12>=0),W83,0) -> 0 | X106: =IF(AND(X83>=0,X12>=0),X83,0) -> 0 | Y106: =IF(AND(Y83>=0,Y12>=0),Y83,0) -> 0 | Z106: =IF(AND(Z83>=0,Z12>=0),Z83,0) -> 0.45018063 | AA106: =IF(AND(AA83>=0,AA12>=0),AA83,0) -> 0.31720745 | AC106: =IF(AND(AC83>=0,AC12>=0),AC83,0) -> 0
B107: Cash | M107: =M29+M34 -> 1884663 | N107: =N29+N34 -> 1759835 | O107: =O29+O34 -> 1879823 | P107: =P29+P34 -> 1723631 | Q107: =Q29+Q34 -> 1689476 | T107: =T29+T34 -> 1603438 | U107: =U29+U34 -> 1723631 | V107: =V29+V34 -> 1591500 | W107: =W29+W34 -> 1522638 | X107: =X29+X34 -> 1519795 | Y107: =Y29+Y34 -> 1689476 | Z107: =Z29+Z34 -> 1415746 | AA107: =AA29+AA34 -> 1405025 | AC107: =AA107 -> 1405025
B108: Debt | C108: 0 | D108: 0 | E108: 0 | F108: 0 | G108: 0 | H108: 0 | I108: 0 | J108: 0 | K108: 0 | L108: 0 | M108: =M39+M41 -> 0 | N108: =N39+N41 -> 0 | O108: =O39+O41 -> 0 | P108: =P39+P41 -> 0 | Q108: =Q39+Q41 -> 0 | T108: =T39+T41 -> 0 | U108: =U39+U41 -> 0 | V108: =V39+V41 -> 0 | W108: =W39+W41 -> 0 | X108: =X39+X41 -> 0 | Y108: =Y39+Y41 -> 0 | Z108: =Z39+Z41 -> 0 | AA108: =AA39+AA41 -> 0 | AC108: =AA108 -> 0
B109: NOPAT | M109: =M12*(1-M106) -> -500946 | N109: =N12*(1-N106) -> -348283 | O109: =O12*(1-O106) -> -164720 | P109: =P12*(1-P106) -> -162569 | Q109: =Q12*(1-Q106) -> 56760 | AC109: =AC12*(1-AC106) -> 152948
...

Sheet Analysis ->
H5: Links
H6: Overview'!B3
H7: Financials ->'!B13
H8: Analysis ->'!B13
H9: Forecast ->'!B13
H10: Valuation ->'!B13
B13: Analysis ->

Sheet Basic
B1: TTM/YTD data
B4: Overview | E4: CAGR
B5: Price | C5: =Overview!C5 -> 13.325 | F5: 5Y | G5: 10Y
B6: Market capitalization | C6: =Statement!AC153 -> 6989162.4 | E6: Revenue | F6: =IF(Statement!M5<=0,"N/A",_xlfn.RRI(4,Statement!M5,Statement!Q5)) -> 0.159106 | G6: =IF(Statement!H5<=0,"N/A",_xlfn.RRI(9,Statement!H5,Statement!Q5)) -> N/A
B7: Enterprise value | C7: =Statement!AC154 -> 5584137.4 | E7: Net income | F7: =IF(OR(Statement!M18<=0, Statement!Q18<=0), "N/A", _xlfn.RRI(4, Statement!M18, Statement!Q18)) -> N/A | G7: =IF(OR(Statement!H18<=0, Statement!Q18<=0), "N/A", _xlfn.RRI(9, Statement!H18, Statement!Q18)) -> N/A
B8: PE | C8: =Statement!AC150 -> 19.88806 | E8: EPS | F8: =IF(OR(Statement!M26<=0, Statement!Q26<=0), "N/A", _xlfn.RRI(4, Statement!M26, Statement!Q26)) -> N/A | G8: =IF(OR(Statement!H26<=0, Statement!Q26<=0), "N/A", _xlfn.RRI(9, Statement!H26, Statement!Q26)) -> N/A
B9: PS | C9: =Statement!AC151 -> 4.1332067 | E9: Dividend | F9: =IF(Statement!M82<=0,"N/A",_xlfn.RRI(4,Statement!M82,Statement!Q82)) -> N/A | G9: =IF(Statement!H82<=0,"N/A",_xlfn.RRI(9,Statement!H82,Statement!Q82)) -> N/A
B10: PB | C10: =Statement!AC152 -> 3.5638809 | E10: Price | F10: =IF(Statement!M117<=0,"N/A",_xlfn.RRI(4,Statement!M117,Statement!Q117)) -> -0.21662025 | G10: =IF(Statement!H117<=0,"N/A",_xlfn.RRI(9,Statement!H117,Statement!Q117)) -> N/A
B11: EV/Revenue | C11: =Statement!AC155 -> 3.2449728
B12: EV/EBIT | C12: =Statement!AC156 -> 36.510039
B15: Margins | E15: Earnings quality
B16: Gross margin | C16: =Statement!AC101 -> 0.82551611 | E16: Net income | F16: =Statement!AC18 -> 361915
B17: Operating margin | C17: =Statement!AC102 -> 0.08887892 | E17: Operating cash | F17: =Statement!AC59 -> 373246
B18: Net margin | C18: =Statement!AC103 -> 0.21031079 | E18: Cash accruals | F18: =IF(OR(F16<=0, F17<=0),"N/A",F16-F17) -> -11331
B21: DuPont Identity | E21: Performance indicators
B22: Profit Margin (Earnings/Revenue) | C22: =Statement!AC121 -> 0.21031079 | E22: ROA | F22: =C24 -> 0.12448205
B23: Asset Turnover (Revenue/Total assets) | C23: =Statement!AC122 -> 0.59189569 | E23: ROE | F23: =C26 -> 0.18573545
B24: ROA | C24: =Statement!AC123 -> 0.12448205 | E24: ROIC | F24: =Statement!AC140 -> 0.2813996
B25: Equity Multiplier (Total assets/Equity) | C25: =Statement!AC124 -> 1.4920662
B26: ROE | C26: =Statement!AC125 -> 0.18573545
B29: Cash conversion cycle | E29: Liquidity ratios
B30: DSO | C30: =Statement!AC141 -> 65.139529 | E30: Debt/Equity | F30: =Statement!AC145 -> 0
B31: DIO | C31: =Statement!AC142 -> 0 | E31: Net Debt/Equity | F31: =Statement!AC146 -> -0.72106145
B32: DPO | C32: =Statement!AC143 -> 20.038033 | E32: Current ratio | F32: =Statement!AC148 -> 2.3866348
B33: Net trade cycle | C33: =Statement!AC144 -> 45.101496 | E33: Quick ratio | F33: =Statement!AC147 -> 2.1209291
E34: Interest coverage | F34: =Statement!AC149 -> N/A
B37: Earnings yields | E37: Payout ratios
B38: Earnings yield | C38: =Statement!AC162 -> 0.050281426 | E38: Dividend payout ratio | F38: =Statement!AC168 -> 0
B39: FCF yield | C39: =Statement!AC161 -> 0.018367866 | E39: Buyback payout ratio | F39: =Statement!AC169 -> 2.0918863
B40: Dividend yield | C40: =Statement!AC163 -> 0 | E40: Full payout ratio | F40: =Statement!AC170 -> 2.0918863
B41: Buyback yield | C41: =Statement!AC164 -> 0.038423488
B42: Total shareholder yield | C42: =Statement!AC165 -> 0.038423488
B45: Ownership | E45: Cash holdings
B46: Insider ownership | C46: =Statement!AC171 -> 0.22269906 | E46: Cash per share | F46: =Statement!AC172 -> 2.6959778
E47: Net cash per share | F47: =Statement!AC175 -> 2.6959778
E48: Net cash to market cap | F48: =Statement!AC176 -> 0.2010291
B51: Stock based compensation | E51: CapEx usage
B52: Stock based compensation % OCF | C52: =Statement!AC173 -> 0.62848899 | E52: Capex to Revenue | F52: =Statement!AC177 -> 0.0059789942
B53: Stock based compensation % Revenue | C53: =Statement!AC174 -> 0.1363163 | E53: CapEx to OCF | F53: =Statement!AC178 -> 0.02756627
E54: CapEx to D&A | F54: =Statement!AC179 -> 0.39573077

Sheet Yearly Analysis
C2: =Statement!M2 -> 31.01.2022 | D2: =Statement!N2 -> 31.01.2023 | E2: =Statement!O2 -> 31.01.2024 | F2: =Statement!P2 -> 31.01.2025 | G2: =Statement!Q2 -> 31.01.2026
C3: =Statement!M3 -> 2022 | D3: =Statement!N3 -> 2023 | E3: =Statement!O3 -> 2024 | F3: =Statement!P3 -> 2025 | G3: =Statement!Q3 -> 2026 | I3: =Statement!AC3 -> TTM/YTD
B5: Overview
B6: Price | C6: =Statement!M116 -> 33.43 | D6: =Statement!N116 -> 14.57 | E6: =Statement!O116 -> 23.85 | F6: =Statement!P116 -> 14.58 | G6: =Statement!Q116 -> 12.59 | I6: =Statement!AC116 -> 13.325
B7: Market capitalization | C7: =Statement!M153 -> 18122002 | D7: =Statement!N153 -> 8121653.1 | E7: =Statement!O153 -> 13570960 | F7: =Statement!P153 -> 8040767.9 | G7: =Statement!Q153 -> 6680971.6 | I7: =Statement!AC153 -> 6989162.4
B8: Enterprise value | C8: =Statement!M154 -> 16237339 | D8: =Statement!N154 -> 6361818.1 | E8: =Statement!O154 -> 11691137 | F8: =Statement!P154 -> 6317136.9 | G8: =Statement!Q154 -> 4991495.6 | I8: =Statement!AC154 -> 5584137.4
B9: PE | C9: =Statement!M150 -> -28.818966 | D9: =Statement!N150 -> -24.283333 | E9: =Statement!O150 -> -149.0625 | F9: =Statement!P150 -> -112.15385 | G9: =Statement!Q150 -> 24.211538 | I9: =Statement!AC150 -> 19.88806
B10: PS | C10: =Statement!M151 -> 17.033432 | D10: =Statement!N151 -> 7.5428149 | E10: =Statement!O151 -> 11.9217 | F10: =Statement!P151 -> 5.710309 | G10: =Statement!Q151 -> 4.2592243 | I10: =Statement!AC151 -> 4.1332067
B11: PB | C11: =Statement!M152 -> 9.4291282 | D11: =Statement!N152 -> 4.2296796 | E11: =Statement!O152 -> 6.7312464 | F11: =Statement!P152 -> 4.3563406 | G11: =Statement!Q152 -> 3.1673001 | I11: =Statement!AC152 -> 3.5638809
B12: EV/Revenue | C12: =Statement!M155 -> 18.198153 | D12: =Statement!N155 -> 6.0097603 | E12: =Statement!O155 -> 8.9376862 | F12: =Statement!P155 -> 4.4186165 | G12: =Statement!Q155 -> 3.0992068 | I12: =Statement!AC155 -> 3.2449728
B13: EV/EBIT | C13: =Statement!M156 -> -32.413352 | D13: =Statement!N156 -> -18.266232 | E13: =Statement!O156 -> -70.97582 | F13: =Statement!P156 -> -38.858189 | G13: =Statement!Q156 -> 87.940374 | I13: =Statement!AC156 -> 36.510039
B15: Margins
B16: Gross margin | C16: =Statement!M101 -> 0.81073957 | D16: =Statement!N101 -> 0.82991287 | E16: =Statement!O101 -> 0.85021925 | F16: =Statement!P101 -> 0.8272727 | G16: =Statement!Q101 -> 0.83174673 | I16: =Statement!AC101 -> 0.82551611
B17: Operating margin | C17: =Statement!M102 -> -0.56144004 | D17: =Statement!N102 -> -0.32900931 | E17: =Statement!O102 -> -0.12592579 | F17: =Statement!P102 -> -0.11371133 | G17: =Statement!Q102 -> 0.035242138 | I17: =Statement!AC102 -> 0.08887892
B18: Net margin | C18: =Statement!M103 -> -0.58905556 | D18: =Statement!N103 -> -0.31018127 | E18: =Statement!O103 -> -0.068714107 | F18: =Statement!P103 -> -0.051546377 | G18: =Statement!Q103 -> 0.17529797 | I18: =Statement!AC103 -> 0.21031079
B20: Earnings quality
B21: Net income | C21: =Statement!M18 -> -525586 | D21: =Statement!N18 -> -328352 | E21: =Statement!O18 -> -89883 | F21: =Statement!P18 -> -73694 | G21: =Statement!Q18 -> 282330 | I21: =Statement!AC18 -> 361915
B22: Operating cash | C22: =Statement!M59 -> -54963 | D22: =Statement!N59 -> -9981 | E22: =Statement!O59 -> 299082 | F22: =Statement!P59 -> 320565 | G22: =Statement!Q59 -> 371208 | I22: =Statement!AC59 -> 373246
B23: Cash accruals | C23: =IF(OR(C21<=0, C22<=0),"N/A",C21-C22) -> N/A | D23: =IF(OR(D21<=0, D22<=0),"N/A",D21-D22) -> N/A | E23: =IF(OR(E21<=0, E22<=0),"N/A",E21-E22) -> N/A | F23: =IF(OR(F21<=0, F22<=0),"N/A",F21-F22) -> N/A | G23: =IF(OR(G21<=0, G22<=0),"N/A",G21-G22) -> -88878 | I23: =IF(OR(I21<=0, I22<=0),"N/A",I21-I22) -> -11331
B25: DuPont Identity
B26: Profit Margin (Earnings/Revenue) | C26: =Statement!M121 -> -0.58905556 | D26: =Statement!N121 -> -0.31018127 | E26: =Statement!O121 -> -0.068714107 | F26: =Statement!P121 -> -0.051546377 | G26: =Statement!Q121 -> 0.17529797 | I26: =Statement!AC121 -> 0.21031079
B27: Asset Turnover (Revenue/Total assets) | C27: =Statement!M122 -> 0.34684911 | D27: =Statement!N122 -> 0.38702058 | E27: =Statement!O122 -> 0.44270021 | F27: =Statement!P122 -> 0.4989631 | G27: =Statement!Q122 -> 0.50659663 | I27: =Statement!AC122 -> 0.59189569
B28: ROA | C28: =Statement!M123 -> -0.2043134 | D28: =Statement!N123 -> -0.12004653 | E28: =Statement!O123 -> -0.03041975 | F28: =Statement!P123 -> -0.02571974 | G28: =Statement!Q123 -> 0.08880536 | I28: =Statement!AC123 -> 0.12448205
B29: Equity Multiplier (Total assets/Equity) | C29: =Statement!M124 -> 1.3384813 | D29: =Statement!N124 -> 1.4244692 | E29: =Statement!O124 -> 1.4655709 | F29: =Statement!P124 -> 1.5523507 | G29: =Statement!Q124 -> 1.5265629 | I29: =Statement!AC124 -> 1.4920662
B30: ROE | C30: =Statement!M125 -> -0.27346967 | D30: =Statement!N125 -> -0.17100259 | E30: =Statement!O125 -> -0.0445823 | F30: =Statement!P125 -> -0.039926058 | G30: =Statement!Q125 -> 0.13556697 | I30: =Statement!AC125 -> 0.18573545
B32: Performance Indicators
B33: ROA | C33: =C28 -> -0.2043134 | D33: =D28 -> -0.12004653 | E33: =E28 -> -0.03041975 | F33: =F28 -> -0.02571974 | G33: =G28 -> 0.08880536 | I33: =I28 -> 0.12448205
B34: ROE | C34: =C30 -> -0.27346967 | D34: =D30 -> -0.17100259 | E34: =E30 -> -0.0445823 | F34: =F30 -> -0.039926058 | G34: =G30 -> 0.13556697 | I34: =I30 -> 0.18573545
B35: ROIC | C35: =Statement!M140 -> -13.446771 | D35: =Statement!N140 -> -2.1723833 | E35: =Statement!O140 -> -1.2085904 | F35: =Statement!P140 -> -1.3311035 | G35: =Statement!Q140 -> 0.1443867 | I35: =Statement!AC140 -> 0.2813996
B37: Cash conversion cycle
B38: DSO | C38: =Statement!M141 -> 133.69422 | D38: =Statement!N141 -> 152.9114 | E38: =Statement!O141 -> 145.23661 | F38: =Statement!P141 -> 137.83035 | G38: =Statement!Q141 -> 131.60376 | I38: =Statement!AC141 -> 65.139529
B39: DIO | C39: =Statement!M142 -> 0 | D39: =Statement!N142 -> 0 | E39: =Statement!O142 -> 0 | F39: =Statement!P142 -> 0 | G39: =Statement!Q142 -> 0 | I39: =Statement!AC142 -> 0
B40: DPO | C40: =Statement!M143 -> 24.889115 | D40: =Statement!N143 -> 18.023865 | E40: =Statement!O143 -> 6.4216482 | F40: =Statement!P143 -> 49.039734 | G40: =Statement!Q143 -> 13.686288 | I40: =Statement!AC143 -> 20.038033
B41: Net trade cycle | C41: =Statement!M144 -> 108.80511 | D41: =Statement!N144 -> 134.88754 | E41: =Statement!O144 -> 138.81496 | F41: =Statement!P144 -> 88.790616 | G41: =Statement!Q144 -> 117.91747 | I41: =Statement!AC144 -> 45.101496
B43: Liquidity ratios
B44: Debt/Equity | C44: =Statement!M145 -> 0 | D44: =Statement!N145 -> 0 | E44: =Statement!O145 -> 0 | F44: =Statement!P145 -> 0 | G44: =Statement!Q145 -> 0 | I44: =Statement!AC145 -> 0
B45: Net Debt/Equity | C45: =Statement!M146 -> -0.98061623 | D45: =Statement!N146 -> -0.91650531 | E45: =Statement!O146 -> -0.93239916 | F45: =Statement!P146 -> -0.93383166 | G45: =Statement!Q146 -> -0.8112391 | I45: =Statement!AC146 -> -0.72106145
B46: Quick ratio | C46: =Statement!M147 -> 4.192375 | D46: =Statement!N147 -> 3.5171282 | E46: =Statement!O147 -> 3.372694 | F46: =Statement!P147 -> 2.8331961 | G46: =Statement!Q147 -> 2.5073154 | I46: =Statement!AC147 -> 2.1209291
B47: Current ratio | C47: =Statement!M148 -> 4.3171501 | D47: =Statement!N148 -> 3.742357 | E47: =Statement!O148 -> 3.6257477 | F47: =Statement!P148 -> 2.9271504 | G47: =Statement!Q148 -> 2.4783389 | I47: =Statement!AC148 -> 2.3866348
B48: Interest coverage | C48: =Statement!M149 -> N/A | D48: =Statement!N149 -> N/A | E48: =Statement!O149 -> N/A | F48: =Statement!P149 -> N/A | G48: =Statement!Q149 -> N/A | I48: =Statement!AC149 -> N/A
B50: Earnings yields
B51: Earnings yield | C51: =Statement!M162 -> -0.034699372 | D51: =Statement!N162 -> -0.041180508 | E51: =Statement!O162 -> -0.0067085954 | F51: =Statement!P162 -> -0.0089163237 | G51: =Statement!Q162 -> 0.041302621 | I51: =Statement!AC162 -> 0.050281426
B52: FCF yield | C52: =Statement!M161 -> -0.03213635 | D52: =Statement!N161 -> -0.049698749 | E52: =Statement!O161 -> -0.005910783 | F52: =Statement!P161 -> -0.0065303464 | G52: =Statement!Q161 -> 0.009202853 | I52: =Statement!AC161 -> 0.018367866
B53: Dividend yield | C53: =Statement!M163 -> 0 | D53: =Statement!N163 -> 0 | E53: =Statement!O163 -> 0 | F53: =Statement!P163 -> 0 | G53: =Statement!Q163 -> 0 | I53: =Statement!AC163 -> 0
B54: Buyback yield | C54: =Statement!M164 -> 0 | D54: =Statement!N164 -> 0 | E54: =Statement!O164 -> 0.0075613663 | F54: =Statement!P164 -> 0.048596229 | G54: =Statement!Q164 -> 0.049259452 | I54: =Statement!AC164 -> 0.038423488
B55: Total shareholder yield | C55: =Statement!M165 -> 0 | D55: =Statement!N165 -> 0 | E55: =Statement!O165 -> 0.0075613663 | F55: =Statement!P165 -> 0.048596229 | G55: =Statement!Q165 -> 0.049259452 | I55: =Statement!AC165 -> 0.038423488
B57: Payout ratios
B58: Dividend payout ratio | C58: =Statement!M168 -> 0 | D58: =Statement!N168 -> 0 | E58: =Statement!O168 -> 0 | F58: =Statement!P168 -> 0 | G58: =Statement!Q168 -> 0 | I58: =Statement!AC168 -> 0
B59: Buyback payout ratio | C59: =Statement!M169 -> 0 | D59: =Statement!N169 -> 0 | E59: =Statement!O169 -> -1.2792495 | F59: =Statement!P169 -> -7.4416005 | G59: =Statement!Q169 -> 5.3526283 | I59: =Statement!AC169 -> 2.0918863
B60: Full payout ratio | C60: =Statement!M170 -> 0 | D60: =Statement!N170 -> 0 | E60: =Statement!O170 -> -1.2792495 | F60: =Statement!P170 -> -7.4416005 | G60: =Statement!Q170 -> 5.3526283 | I60: =Statement!AC170 -> 2.0918863
B62: Ownership
B63: Insider ownership | C63: =Statement!M171 -> 0.32041292 | D63: =Statement!N171 -> 0.3120718 | E63: =Statement!O171 -> 0.22510733 | F63: =Statement!P171 -> 0.2249403 | G63: =Statement!Q171 -> 0.22012147 | I63: =Statement!AC171 -> 0.22269906
B65: Cash holdings
B66: Cash per share | C66: =Statement!M172 -> 3.4766735 | D66: =Statement!N172 -> 3.1570908 | E66: =Statement!O172 -> 3.3036556 | F66: =Statement!P172 -> 3.1253905 | G66: =Statement!Q172 -> 3.2246708 | I66: =Statement!AC172 -> 2.6959778
B67: Net cash per share | C67: =Statement!M175 -> 3.4766735 | D67: =Statement!N175 -> 3.1570908 | E67: =Statement!O175 -> 3.3036556 | F67: =Statement!P175 -> 3.1253905 | G67: =Statement!Q175 -> 3.2246708 | I67: =Statement!AC175 -> 2.6959778
B68: Net cash to market cap | C68: =Statement!M176 -> 0.10399861 | D68: =Statement!N176 -> 0.21668433 | E68: =Statement!O176 -> 0.13851806 | F68: =Statement!P176 -> 0.21436149 | G68: =Statement!Q176 -> 0.25287879 | I68: =Statement!AC176 -> 0.2010291
B70: Stock Based Compensation
B71: Stock based compensation % OCF | C71: =Statement!M173 -> -9.3805469 | D71: =Statement!N173 -> -37.054403 | E71: =Statement!O173 -> 1.2436556 | F71: =Statement!P173 -> 1.1172492 | G71: =Statement!Q173 -> 0.78305424 | I71: =Statement!AC173 -> 0.62848899
B72: Stock based compensation % Revenue | C72: =Statement!M174 -> 0.5778446 | D72: =Statement!N174 -> 0.34937336 | E72: =Statement!O174 -> 0.28435361 | F72: =Statement!P174 -> 0.25051411 | G72: =Statement!Q174 -> 0.18047998 | I72: =Statement!AC174 -> 0.1363163
B74: CapEx Usage
B75: Capex to Revenue | C75: =Statement!M177 -> 0.013257465 | D75: =Statement!N177 -> 0.022497098 | E75: =Statement!O177 -> 0.0056128409 | F75: =Statement!P177 -> 0.010438117 | G75: =Statement!Q177 -> 0.011826854 | I75: =Statement!AC177 -> 0.0059789942
B76: CapEx to OCF | C76: =Statement!M178 -> -0.21521751 | D76: =Statement!N178 -> -2.3860335 | E76: =Statement!O178 -> 0.024548452 | F76: =Statement!P178 -> 0.046552181 | G76: =Statement!Q178 -> 0.051313549 | I76: =Statement!AC178 -> 0.02756627
B77: CapEx to D&A | C77: =Statement!M179 -> 0.80442027 | D77: =Statement!N179 -> 1.271965 | E77: =Statement!O179 -> 0.32491039 | F77: =Statement!P179 -> 0.86600511 | G77: =Statement!Q179 -> 1.1225175 | I77: =Statement!AC179 -> 0.39573077
B79: Growth rates
B80: Revenue | C80: =Statement!M89 -> 1 | D80: =Statement!N89 -> 0.18641482 | E80: =Statement!O89 -> 0.23568437 | F80: =Statement!P89 -> 0.092955128 | G80: =Statement!Q89 -> 0.12653882
B81: COGS | C81: =Statement!M90 -> 1 | D81: =Statement!N90 -> 0.066223322 | E81: =Statement!O90 -> 0.088158355 | F81: =Statement!P90 -> 0.26039689 | G81: =Statement!Q90 -> 0.097358894
B82: Gross Profit | C82: =Statement!M91 -> 1 | D82: =Statement!N91 -> 0.21447253 | E82: =Statement!O91 -> 0.26591921 | F82: =Statement!P91 -> 0.063457382 | G82: =Statement!Q91 -> 0.13263134
B83: OpEx | C83: =Statement!M95 -> 1 | D83: =Statement!N95 -> 0.002028048 | E83: =Statement!O95 -> 0.040800839 | F83: =Statement!P95 -> 0.053586588 | G83: =Statement!Q95 -> -0.046430847
B84: Operating Income | C84: =Statement!M96 -> -1 | D84: =Statement!N96 -> 0.30474941 | E84: =Statement!O96 -> 0.52705128 | F84: =Statement!P96 -> 0.013058524 | G84: =Statement!Q96 -> 1.3491441
B85: Net Income | C85: =Statement!M98 -> -1 | D85: =Statement!N98 -> 0.37526494 | E85: =Statement!O98 -> 0.72626023 | F85: =Statement!P98 -> 0.18011192 | G85: =Statement!Q98 -> 4.8311124
B88: Growth rates breakdown
B89: Licenses Revenue | C89: =Statement!M197 -> 1 | D89: =Statement!N197 -> 0.034084088 | E89: =Statement!O197 -> 0.24818615 | F89: =Statement!P197 -> -0.055102093 | G89: =Statement!Q197 -> 0.032771752
B90: Subscription services Revenue | C90: =Statement!M198 -> 1 | D90: =Statement!N198 -> 0.3756918 | E90: =Statement!O198 -> 0.27729682 | F90: =Statement!P198 -> 0.23392028 | G90: =Statement!Q198 -> 0.19019337
B91: Professional services Revenue | C91: =Statement!M199 -> 1 | D91: =Statement!N199 -> 0.26768885 | E91: =Statement!O199 -> -0.29197643 | F91: =Statement!P199 -> 0.10317719 | G91: =Statement!Q199 -> 0.22564419
B93: Other growth rates
B94: Dividends | C94: =Statement!M203 -> 0 | D94: =Statement!N203 -> 0 | E94: =Statement!O203 -> 0 | F94: =Statement!P203 -> 0 | G94: =Statement!Q203 -> 0

Sheet Quarter analysis
C3: Latest 2 quarters | F3: YoY
C4: =Statement!Z2 -> 30.04.2026 | D4: =Statement!AA2 -> 31.07.2026 | F4: =Statement!W2 -> 31.07.2025 | G4: =Statement!AA2 -> 31.07.2026
B5: Income statement growth | C5: =Statement!Z3 -> Q1 2027 | D5: =Statement!AA3 -> Q2 2027 | F5: =Statement!W3 -> Q2 2026 | G5: =Statement!AA3 -> Q2 2027
B6: Revenue | C6: =Statement!Z5 -> 418382 | D6: =Statement!AA5 -> 410256 | F6: =Statement!W5 -> 361728 | G6: =Statement!AA5 -> 410256
B7: Growth | C7: =Statement!AA89 -> -0.019422442 | F7: =IF(F6=0, IF(G6=0,0,IF(G6>0,1,-1)), (G6-F6)/ABS(F6) ) -> 0.13415605
B8: COGS | C8: =Statement!Z6 -> 76928 | D8: =Statement!AA6 -> 80587 | F8: =Statement!W6 -> 64380 | G8: =Statement!AA6 -> 80587
B9: Growth | C9: =Statement!AA90 -> 0.047563956 | F9: =IF(F8=0, IF(G8=0,0,IF(G8>0,1,-1)), (G8-F8)/ABS(F8) ) -> 0.25173967
B10: Gross Profit | C10: =Statement!Z7 -> 341454 | D10: =Statement!AA7 -> 329669 | F10: =Statement!W7 -> 297348 | G10: =Statement!AA7 -> 329669
B11: Growth | C11: =Statement!AA91 -> -0.034514166 | F11: =IF(F10=0, IF(G10=0,0,IF(G10>0,1,-1)), (G10-F10)/ABS(F10) ) -> 0.10869755
B12: OpEx | C12: =Statement!Z11 -> 313467 | D12: =Statement!AA11 -> 298065 | F12: =Statement!W11 -> 317533 | G12: =Statement!AA11 -> 298065
B13: Growth | C13: =Statement!AA95 -> -0.049134359 | F13: =IF(F12=0, IF(G12=0,0,IF(G12>0,1,-1)), (G12-F12)/ABS(F12) ) -> -0.061310163
B14: Operating profit | C14: =Statement!Z12 -> 27987 | D14: =Statement!AA12 -> 31604 | F14: =Statement!W12 -> -20185 | G14: =Statement!AA12 -> 31604
B15: Growth | C15: =Statement!AA96 -> 0.12923858 | F15: =IF(F14=0, IF(G14=0,0,IF(G14>0,1,-1)), (G14-F14)/ABS(F14) ) -> 2.5657171
B16: Net income | C16: =Statement!Z18 -> 22525 | D16: =Statement!AA18 -> 36089 | F16: =Statement!W18 -> 1584 | G16: =Statement!AA18 -> 36089
B17: Growth | C17: =Statement!AA98 -> 0.60217536 | F17: =IF(F16=0, IF(G16=0,0,IF(G16>0,1,-1)), (G16-F16)/ABS(F16) ) -> 21.78346
B18: Diluted shares outstanding | C18: =Statement!Z22 -> 527818 | D18: =Statement!AA22 -> 523013 | F18: =Statement!W22 -> 542865 | G18: =Statement!AA22 -> 523013
B19: Growth | C19: =IF(C18=0, IF(D18=0,0,IF(D18>0,1,-1)), (D18-C18)/ABS(C18) ) -> -0.0091035167 | F19: =IF(F18=0, IF(G18=0,0,IF(G18>0,1,-1)), (G18-F18)/ABS(F18) ) -> -0.036568944
B20: Diluted EPS | C20: =Statement!Z26 -> 0.04 | D20: =Statement!AA26 -> 0.07 | F20: =Statement!W26 -> 0 | G20: =Statement!AA26 -> 0.07
B21: Growth | C21: =IF(C20=0, IF(D20=0,0,IF(D20>0,1,-1)), (D20-C20)/ABS(C20) ) -> 0.75 | F21: =IF(F20=0, IF(G20=0,0,IF(G20>0,1,-1)), (G20-F20)/ABS(F20) ) -> 1
B23: Revenue breakdown | C23: =C5 -> Q1 2027 | D23: =D5 -> Q2 2027 | F23: =F5 -> Q2 2026 | G23: =G5 -> Q2 2027
B24: Licenses | C24: =Statement!Z187 -> 149309 | D24: =Statement!AA187 -> 123843 | F24: =Statement!W187 -> 112161 | G24: =Statement!AA187 -> 123843
B25: Growth | C25: =IF(C24=0, IF(D24=0,0,IF(D24>0,1,-1)), (D24-C24)/ABS(C24) ) -> -0.17055904 | F25: =IF(F24=0, IF(G24=0,0,IF(G24>0,1,-1)), (G24-F24)/ABS(F24) ) -> 0.10415385
B26: Subscription services | C26: =Statement!Z188 -> 252903 | D26: =Statement!AA188 -> 266067 | F26: =Statement!W188 -> 238363 | G26: =Statement!AA188 -> 266067
B27: Growth | C27: =IF(C26=0, IF(D26=0,0,IF(D26>0,1,-1)), (D26-C26)/ABS(C26) ) -> 0.052051577 | F27: =IF(F26=0, IF(G26=0,0,IF(G26>0,1,-1)), (G26-F26)/ABS(F26) ) -> 0.11622609
B28: Professional services | C28: =Statement!Z189 -> 16170 | D28: =Statement!AA189 -> 20346 | F28: =Statement!W189 -> 11204 | G28: =Statement!AA189 -> 20346
B29: Growth | C29: =IF(C28=0, IF(D28=0,0,IF(D28>0,1,-1)), (D28-C28)/ABS(C28) ) -> 0.25825603 | F29: =IF(F28=0, IF(G28=0,0,IF(G28>0,1,-1)), (G28-F28)/ABS(F28) ) -> 0.81595859
B31: Metrics growth | C31: =C5 -> Q1 2027 | D31: =D5 -> Q2 2027 | F31: =F5 -> Q2 2026 | G31: =G5 -> Q2 2027
B32: ARR | C32: =Statement!Z213 -> 1901211 | D32: =Statement!AA213 -> 1937722 | F32: =Statement!W213 -> 1723401 | G32: =Statement!AA213 -> 1937722
B33: Growth | C33: =IF(C32=0, IF(D32=0,0,IF(D32>0,1,-1)), (D32-C32)/ABS(C32) ) -> 0.019204076 | F33: =IF(F32=0, IF(G32=0,0,IF(G32>0,1,-1)), (G32-F32)/ABS(F32) ) -> 0.12435933
B34: Customers >= 100K | C34: =Statement!Z217 -> 2624 | D34: =Statement!AA217 -> 2666 | F34: =Statement!W217 -> 2432 | G34: =Statement!AA217 -> 2666
B35: Growth | C35: =IF(C34=0, IF(D34=0,0,IF(D34>0,1,-1)), (D34-C34)/ABS(C34) ) -> 0.016006098 | F35: =IF(F34=0, IF(G34=0,0,IF(G34>0,1,-1)), (G34-F34)/ABS(F34) ) -> 0.096217105

Sheet Graphs Year
C55: =Statement!H2 -> 0 | D55: =Statement!I2 -> 0 | E55: =Statement!J2 -> 0 | F55: =Statement!K2 -> 0 | G55: =Statement!L2 -> 0 | H55: =Statement!M2 -> 31.01.2022 | I55: =Statement!N2 -> 31.01.2023 | J55: =Statement!O2 -> 31.01.2024 | ... L55: =Statement!Q2 -> 31.01.2026
C56: =Statement!H3 -> 0 | D56: =Statement!I3 -> 0 | E56: =Statement!J3 -> 0 | F56: =Statement!K3 -> 0 | G56: =Statement!L3 -> 0 | H56: =Statement!M3 -> 2022 | I56: =Statement!N3 -> 2023 | J56: =Statement!O3 -> 2024 | ... L56: =Statement!Q3 -> 2026
B57: Revenue | C57: =Statement!H5 -> 0 | D57: =Statement!I5 -> 0 | E57: =Statement!J5 -> 0 | F57: =Statement!K5 -> 0 | G57: =Statement!L5 -> 0 | H57: =Statement!M5 -> 892252 | I57: =Statement!N5 -> 1058581 | J57: =Statement!O5 -> 1308072 | ... L57: =Statement!Q5 -> 1610572
B58: Operating income | C58: =Statement!H12 -> 0 | D58: =Statement!I12 -> 0 | E58: =Statement!J12 -> 0 | F58: =Statement!K12 -> 0 | G58: =Statement!L12 -> 0 | H58: =Statement!M12 -> -500946 | I58: =Statement!N12 -> -348283 | J58: =Statement!O12 -> -164720 | ... L58: =Statement!Q12 -> 56760
B59: Net income | C59: =Statement!H18 -> 0 | D59: =Statement!I18 -> 0 | E59: =Statement!J18 -> 0 | F59: =Statement!K18 -> 0 | G59: =Statement!L18 -> 0 | H59: =Statement!M18 -> -525586 | I59: =Statement!N18 -> -328352 | J59: =Statement!O18 -> -89883 | ... L59: =Statement!Q18 -> 282330
B60: FCFE | C60: =Statement!H157 -> 0 | D60: =Statement!I157 -> 0 | E60: =Statement!J157 -> 0 | F60: =Statement!K157 -> 0 | G60: =Statement!L157 -> 0 | H60: =Statement!M157 -> -582375 | I60: =Statement!N157 -> -403636 | J60: =Statement!O157 -> -80215 | ... L60: =Statement!Q157 -> 61484
B61: FCFF | C61: =Statement!H158 -> 0 | D61: =Statement!I158 -> 0 | E61: =Statement!J158 -> 0 | F61: =Statement!K158 -> 0 | G61: =Statement!L158 -> 0 | H61: =Statement!M158 -> -603972 | I61: =Statement!N158 -> -500062 | J61: =Statement!O158 -> -216393 | ... L61: =Statement!Q158 -> -94526
B62: Gross margin | C62: =Statement!H101 -> 0 | D62: =Statement!I101 -> 0 | E62: =Statement!J101 -> 0 | F62: =Statement!K101 -> 0 | G62: =Statement!L101 -> 0 | H62: =Statement!M101 -> 0.81073957 | I62: =Statement!N101 -> 0.82991287 | J62: =Statement!O101 -> 0.85021925 | ... L62: =Statement!Q101 -> 0.83174673
B63: Operating margin | C63: =Statement!H102 -> 0 | D63: =Statement!I102 -> 0 | E63: =Statement!J102 -> 0 | F63: =Statement!K102 -> 0 | G63: =Statement!L102 -> 0 | H63: =Statement!M102 -> -0.56144004 | I63: =Statement!N102 -> -0.32900931 | J63: =Statement!O102 -> -0.12592579 | ... L63: =Statement!Q102 -> 0.035242138
B64: Net margin | C64: =Statement!H103 -> 0 | D64: =Statement!I103 -> 0 | E64: =Statement!J103 -> 0 | F64: =Statement!K103 -> 0 | G64: =Statement!L103 -> 0 | H64: =Statement!M103 -> -0.58905556 | I64: =Statement!N103 -> -0.31018127 | J64: =Statement!O103 -> -0.068714107 | ... L64: =Statement!Q103 -> 0.17529797
B65: Revenue Licenses | C65: =Statement!H187 -> 0 | D65: =Statement!I187 -> 0 | E65: =Statement!J187 -> 0 | F65: =Statement!K187 -> 0 | G65: =Statement!L187 -> 0 | H65: =Statement!M187 -> 481427 | I65: =Statement!N187 -> 497836 | J65: =Statement!O187 -> 621392 | ... L65: =Statement!Q187 -> 606394
B66: Revenue Subscription | C66: =Statement!H188 -> 0 | D66: =Statement!I188 -> 0 | E66: =Statement!J188 -> 0 | F66: =Statement!K188 -> 0 | G66: =Statement!L188 -> 0 | H66: =Statement!M188 -> 369867 | I66: =Statement!N188 -> 508823 | J66: =Statement!O188 -> 649918 | ... L66: =Statement!Q188 -> 954472
B67: Revenue Professional | C67: =Statement!H189 -> 0 | D67: =Statement!I189 -> 0 | E67: =Statement!J189 -> 0 | F67: =Statement!K189 -> 0 | G67: =Statement!L189 -> 0 | H67: =Statement!M189 -> 40958 | I67: =Statement!N189 -> 51922 | J67: =Statement!O189 -> 36762 | ... L67: =Statement!Q189 -> 49706
B68: ROA | C68: =Statement!H123 -> 0 | D68: =Statement!I123 -> 0 | E68: =Statement!J123 -> 0 | F68: =Statement!K123 -> 0 | G68: =Statement!L123 -> 0 | H68: =Statement!M123 -> -0.2043134 | I68: =Statement!N123 -> -0.12004653 | J68: =Statement!O123 -> -0.03041975 | ... L68: =Statement!Q123 -> 0.08880536
B69: ROE | C69: =Statement!H125 -> 0 | D69: =Statement!I125 -> 0 | E69: =Statement!J125 -> 0 | F69: =Statement!K125 -> 0 | G69: =Statement!L125 -> 0 | H69: =Statement!M125 -> -0.27346967 | I69: =Statement!N125 -> -0.17100259 | J69: =Statement!O125 -> -0.0445823 | ... L69: =Statement!Q125 -> 0.13556697
B70: ROIC | C70: =Statement!H140 -> 0 | D70: =Statement!I140 -> 0 | E70: =Statement!J140 -> 0 | F70: =Statement!K140 -> 0 | G70: =Statement!L140 -> 0 | H70: =Statement!M140 -> -13.446771 | I70: =Statement!N140 -> -2.1723833 | J70: =Statement!O140 -> -1.2085904 | ... L70: =Statement!Q140 -> 0.1443867
B71: Price 5y | C71: =Statement!H207 -> 0 | D71: =Statement!I207 -> 0 | E71: =Statement!J207 -> 0 | F71: =Statement!K207 -> 0 | G71: =Statement!L207 -> 0 | H71: =Statement!M207 -> 100 | I71: =Statement!N207 -> 43.583608 | J71: =Statement!O207 -> 71.343105 | ... L71: =Statement!Q207 -> 37.660784
B72: Revenue 5y | C72: =Statement!H208 -> 0 | D72: =Statement!I208 -> 0 | E72: =Statement!J208 -> 0 | F72: =Statement!K208 -> 0 | G72: =Statement!L208 -> 0 | H72: =Statement!M208 -> 100 | I72: =Statement!N208 -> 118.64148 | J72: =Statement!O208 -> 146.60343 | ... L72: =Statement!Q208 -> 180.5064
B73: EPS 5y | C73: =Statement!H209 -> 0 | D73: =Statement!I209 -> 0 | E73: =Statement!J209 -> 0 | F73: =Statement!K209 -> 0 | G73: =Statement!L209 -> 0 | H73: =Statement!M209 -> 100 | I73: =Statement!N209 -> 148.27586 | J73: =Statement!O209 -> 186.2069 | ... L73: =Statement!Q209 -> 244.82759

Sheet Graphs Quarter
C55: =Statement!T2 -> 31.10.2024 | D55: =Statement!U2 -> 31.01.2025 | E55: =Statement!V2 -> 30.04.2025 | F55: =Statement!W2 -> 31.07.2025 | G55: =Statement!X2 -> 31.10.2025 | H55: =Statement!Y2 -> 31.01.2026 | I55: =Statement!Z2 -> 30.04.2026 | J55: =Statement!AA2 -> 31.07.2026
C56: =Statement!T3 -> Q3 2025 | D56: =Statement!U3 -> Q4 2025 | E56: =Statement!V3 -> Q1 2026 | F56: =Statement!W3 -> Q2 2026 | G56: =Statement!X3 -> Q3 2026 | H56: =Statement!Y3 -> Q4 2026 | I56: =Statement!Z3 -> Q1 2027 | J56: =Statement!AA3 -> Q2 2027
B57: Revenue | C57: =Statement!T5 -> 354653 | D57: =Statement!U5 -> 423646 | E57: =Statement!V5 -> 356624 | F57: =Statement!W5 -> 361728 | G57: =Statement!X5 -> 411113 | H57: =Statement!Y5 -> 481107 | I57: =Statement!Z5 -> 418382 | J57: =Statement!AA5 -> 410256
B58: Operating income | C58: =Statement!T12 -> -43364 | D58: =Statement!U12 -> 33609 | E58: =Statement!V12 -> -16412 | F58: =Statement!W12 -> -20185 | G58: =Statement!X12 -> 13071 | H58: =Statement!Y12 -> 80286 | I58: =Statement!Z12 -> 27987 | J58: =Statement!AA12 -> 31604
B59: Net income | C59: =Statement!T18 -> -10655 | D59: =Statement!U18 -> 51794 | E59: =Statement!V18 -> -22555 | F59: =Statement!W18 -> 1584 | G59: =Statement!X18 -> 198839 | H59: =Statement!Y18 -> 104462 | I59: =Statement!Z18 -> 22525 | J59: =Statement!AA18 -> 36089
B60: Gross margin | C60: =Statement!T101 -> 0.82021018 | D60: =Statement!U101 -> 0.84766999 | E60: =Statement!V101 -> 0.82094026 | F60: =Statement!W101 -> 0.82202097 | G60: =Statement!X101 -> 0.83262023 | H60: =Statement!Y101 -> 0.84632317 | I60: =Statement!Z101 -> 0.81612976 | J60: =Statement!AA101 -> 0.80356899
B61: Operating margin | C61: =Statement!T102 -> -0.12227163 | D61: =Statement!U102 -> 0.079332745 | E61: =Statement!V102 -> -0.046020459 | F61: =Statement!W102 -> -0.055801597 | G61: =Statement!X102 -> 0.031794178 | H61: =Statement!Y102 -> 0.16687764 | I61: =Statement!Z102 -> 0.066893413 | J61: =Statement!AA102 -> 0.077034827
B62: Net margin | C62: =Statement!T103 -> -0.030043451 | D62: =Statement!U103 -> 0.12225773 | E62: =Statement!V103 -> -0.063245884 | F62: =Statement!W103 -> 0.0043789809 | G62: =Statement!X103 -> 0.48366021 | H62: =Statement!Y103 -> 0.21712841 | I62: =Statement!Z103 -> 0.053838358 | J62: =Statement!AA103 -> 0.087967025
B63: Revenue Licenses | C63: =Statement!T187 -> 137174 | D63: =Statement!U187 -> 197609 | E63: =Statement!V187 -> 128286 | F63: =Statement!W187 -> 112161 | G63: =Statement!X187 -> 150043 | H63: =Statement!Y187 -> 215904 | I63: =Statement!Z187 -> 149309 | J63: =Statement!AA187 -> 123843
B64: Revenue Subscription | C64: =Statement!T188 -> 206922 | D64: =Statement!U188 -> 215221 | E64: =Statement!V188 -> 217303 | F64: =Statement!W188 -> 238363 | G64: =Statement!X188 -> 247573 | H64: =Statement!Y188 -> 251233 | I64: =Statement!Z188 -> 252903 | J64: =Statement!AA188 -> 266067
B65: Revenue Professional | C65: =Statement!T189 -> 10557 | D65: =Statement!U189 -> 10816 | E65: =Statement!V189 -> 11035 | F65: =Statement!W189 -> 11204 | G65: =Statement!X189 -> 13497 | H65: =Statement!Y189 -> 13970 | I65: =Statement!Z189 -> 16170 | J65: =Statement!AA189 -> 20346
B66: FCFE | C66: =Statement!T157 -> -64293 | D66: =Statement!U157 -> 0 | E66: =Statement!V157 -> 29809 | F66: =Statement!W157 -> -36419 | G66: =Statement!X157 -> -46368 | H66: =Statement!Y157 -> 114462 | I66: =Statement!Z157 -> 75934 | J66: =Statement!AA157 -> -15652

Sheet Forecast ->
H5: Links
H6: Overview'!B3
H7: Financials ->'!B13
H8: Analysis ->'!B13
H9: Forecast ->'!B13
H10: Valuation ->'!B13
B13: Forecast ->

Sheet Revenue
B1: Revenue forecast
C2: History | H2: Forecast | S2: History | AA2: Forecast | AE2: TTM
C4: Revenues | S4: Revenues
B5: Revenues (thousand) | C5: =Statement!M3 -> 2022 | D5: =Statement!N3 -> 2023 | E5: =Statement!O3 -> 2024 | F5: =Statement!P3 -> 2025 | G5: =Statement!Q3 -> 2026 | H5: =G5+1 -> 2027 | I5: =H5+1 -> 2028 | J5: =I5+1 -> 2029 | K5: =J5+1 -> 2030 | L5: =K5+1 -> 2031 | R5: =B5 -> Revenues (thousand) | S5: =Statement!T3 -> Q3 2025 | T5: =Statement!U3 -> Q4 2025 | U5: =Statement!V3 -> Q1 2026 | V5: =Statement!W3 -> Q2 2026 | W5: =Statement!X3 -> Q3 2026 | X5: =Statement!Y3 -> Q4 2026 | Y5: =Statement!Z3 -> Q1 2027 | Z5: =Statement!AA3 -> Q2 2027 | AA5: FQ1 | AB5: FQ2 | AC5: FQ3 | AE5: FQ1
B6: =Statement!B187 -> Licenses | C6: =Statement!M187 -> 481427 | D6: =Statement!N187 -> 497836 | E6: =Statement!O187 -> 621392 | F6: =Statement!P187 -> 587152 | G6: =Statement!Q187 -> 606394 | H6: =H9*H29 -> 626739.4 | I6: =I9*I29 -> 642960.25 | J6: =J9*J29 -> 663901.02 | K6: =K9*K29 -> 690821.45 | L6: =L9*L29 -> 692587.69 | N6: Revenue * Licenses % revenue | Q6: Revenue * Licenses % revenue | R6: =B6 -> Licenses | S6: =Statement!T187 -> 137174 | T6: =Statement!U187 -> 197609 | U6: =Statement!V187 -> 128286 | V6: =Statement!W187 -> 112161 | W6: =Statement!X187 -> 150043 | X6: =Statement!Y187 -> 215904 | Y6: =Statement!Z187 -> 149309 | Z6: =Statement!AA187 -> 123843 | AA6: =AA9*AA29 -> 153538 | AE6: =SUM(X6:AA6) -> 642594
B7: =Statement!B188 -> Subscription services | C7: =Statement!M188 -> 369867 | D7: =Statement!N188 -> 508823 | E7: =Statement!O188 -> 649918 | F7: =Statement!P188 -> 801947 | G7: =Statement!Q188 -> 954472 | H7: =H9-H6-H8 -> 1092317.2 | I7: =I9-I6-I8 -> 1241108.1 | J7: =J9-J6-J8 -> 1417749.9 | K7: =K9-K6-K8 -> 1552045.5 | L7: =L9-L6-L8 -> 1719101.6 | N7: Revenue - License - Professional services | Q7: Revenue - License - Professional services | R7: =B7 -> Subscription services | S7: =Statement!T188 -> 206922 | T7: =Statement!U188 -> 215221 | U7: =Statement!V188 -> 217303 | V7: =Statement!W188 -> 238363 | W7: =Statement!X188 -> 247573 | X7: =Statement!Y188 -> 251233 | Y7: =Statement!Z188 -> 252903 | Z7: =Statement!AA188 -> 266067 | AA7: =AA9-AA6-AA8 -> 263208 | AE7: =SUM(X7:AA7) -> 1033411
B8: =Statement!B189 -> Professional services | C8: =Statement!M189 -> 40958 | D8: =Statement!N189 -> 51922 | E8: =Statement!O189 -> 36762 | F8: =Statement!P189 -> 40555 | G8: =Statement!Q189 -> 49706 | H8: =H9*H28 -> 71627.36 | I8: =I9*I28 -> 64296.025 | J8: =J9*J28 -> 59965.253 | K8: =K9*K28 -> 59871.192 | L8: =L9*L28 -> 61838.186 | N8: Revenue * Professional services % revenue | Q8: Revenue * Professional services % revenue | R8: =B8 -> Professional services | S8: =Statement!T189 -> 10557 | T8: =Statement!U189 -> 10816 | U8: =Statement!V189 -> 11035 | V8: =Statement!W189 -> 11204 | W8: =Statement!X189 -> 13497 | X8: =Statement!Y189 -> 13970 | Y8: =Statement!Z189 -> 16170 | Z8: =Statement!AA189 -> 20346 | AA8: =AA9*AA28 -> 21934 | AE8: =SUM(X8:AA8) -> 72420
B9: Total | C9: =Statement!M5 -> 892252 | D9: =Statement!N5 -> 1058581 | E9: =Statement!O5 -> 1308072 | F9: =Statement!P5 -> 1429664 | G9: =Statement!Q5 -> 1610572 | H9: =H21*H27 -> 1790684 | I9: =I21*I27 -> 1948364.4 | J9: =J21*J27 -> 2141616.2 | K9: =K21*K27 -> 2302738.2 | L9: =L21*L27 -> 2473527.4 | N9: ARR * Revenue to ARR | Q9: ARR * Revenue to ARR | R9: Total | S9: =Statement!T5 -> 354653 | T9: =Statement!U5 -> 423646 | U9: =Statement!V5 -> 356624 | V9: =Statement!W5 -> 361728 | W9: =Statement!X5 -> 411113 | X9: =Statement!Y5 -> 481107 | Y9: =Statement!Z5 -> 418382 | Z9: =Statement!AA5 -> 410256 | AA9: =AA21*AA27 -> 438680 | AE9: =SUM(X9:AA9) -> 1748425
C11: Growth rates | S11: Growth rates
B12: Revenue growth % | C12: =C5 -> 2022 | D12: =D5 -> 2023 | E12: =E5 -> 2024 | F12: =F5 -> 2025 | G12: =G5 -> 2026 | H12: =H5 -> 2027 | I12: =I5 -> 2028 | J12: =J5 -> 2029 | ... L12: =L5 -> 2031 | R12: Revenue growth % | S12: =S5 -> Q3 2025 | T12: =T5 -> Q4 2025 | U12: =U5 -> Q1 2026 | V12: =V5 -> Q2 2026 | W12: =W5 -> Q3 2026 | X12: =X5 -> Q4 2026 | Y12: =Y5 -> Q1 2027 | Z12: =Z5 -> Q2 2027 | ... AC12: =AC5 -> FQ3
B13: =B6 -> Licenses | D13: =D6/C6-1 -> 0.034084088 | E13: =E6/D6-1 -> 0.24818615 | F13: =F6/E6-1 -> -0.055102093 | G13: =G6/F6-1 -> 0.032771752 | H13: =H6/G6-1 -> 0.033551453 | I13: =I6/H6-1 -> 0.025881334 | J13: =J6/I6-1 -> 0.032569301 | K13: =K6/J6-1 -> 0.04054886 | L13: =L6/K6-1 -> 0.0025567213 | R13: =R6 -> Licenses | T13: =T6/S6-1 -> 0.44057183 | U13: =U6/T6-1 -> -0.35080892 | V13: =V6/U6-1 -> -0.12569571 | W13: =W6/V6-1 -> 0.33774663 | X13: =X6/W6-1 -> 0.4389475 | Y13: =Y6/X6-1 -> -0.30844727 | Z13: =Z6/Y6-1 -> -0.17055904 | AA13: =AA6/Z6-1 -> 0.2397794
B14: =B7 -> Subscription services | D14: =D7/C7-1 -> 0.3756918 | E14: =E7/D7-1 -> 0.27729682 | F14: =F7/E7-1 -> 0.23392028 | G14: =G7/F7-1 -> 0.19019337 | H14: =H7/G7-1 -> 0.14442041 | I14: =I7/H7-1 -> 0.13621581 | J14: =J7/I7-1 -> 0.14232587 | K14: =K7/J7-1 -> 0.094724465 | L14: =L7/K7-1 -> 0.10763606 | R14: =R7 -> Subscription services | T14: =T7/S7-1 -> 0.0401069 | U14: =U7/T7-1 -> 0.0096737772 | V14: =V7/U7-1 -> 0.096915367 | W14: =W7/V7-1 -> 0.038638547 | X14: =X7/W7-1 -> 0.014783518 | Y14: =Y7/X7-1 -> 0.0066472159 | Z14: =Z7/Y7-1 -> 0.052051577 | AA14: =AA7/Z7-1 -> -0.010745414
B15: =B8 -> Professional services | D15: =D8/C8-1 -> 0.26768885 | E15: =E8/D8-1 -> -0.29197643 | F15: =F8/E8-1 -> 0.10317719 | G15: =G8/F8-1 -> 0.22564419 | H15: =H8/G8-1 -> 0.4410204 | I15: =I8/H8-1 -> -0.10235383 | J15: =J8/I8-1 -> -0.067356761 | K15: =K8/J8-1 -> -0.0015685938 | L15: =L8/K8-1 -> 0.032853765 | R15: =R8 -> Professional services | T15: =T8/S8-1 -> 0.024533485 | U15: =U8/T8-1 -> 0.020247781 | V15: =V8/U8-1 -> 0.015314907 | W15: =W8/V8-1 -> 0.20465905 | X15: =X8/W8-1 -> 0.035044825 | Y15: =Y8/X8-1 -> 0.15748031 | Z15: =Z8/Y8-1 -> 0.25825603 | AA15: =AA8/Z8-1 -> 0.07804974
B16: =B9 -> Total | D16: =D9/C9-1 -> 0.18641482 | E16: =E9/D9-1 -> 0.23568437 | F16: =F9/E9-1 -> 0.092955128 | G16: =G9/F9-1 -> 0.12653882 | H16: =H9/G9-1 -> 0.11183108 | I16: =I9/H9-1 -> 0.088055961 | J16: =J9/I9-1 -> 0.099186675 | K16: =K9/J9-1 -> 0.075233822 | L16: =L9/K9-1 -> 0.074167916 | R16: =R9 -> Total | T16: =T9/S9-1 -> 0.19453663 | U16: =U9/T9-1 -> -0.15820284 | V16: =V9/U9-1 -> 0.014311992 | W16: =W9/V9-1 -> 0.13652523 | X16: =X9/W9-1 -> 0.17025489 | Y16: =Y9/X9-1 -> -0.1303764 | Z16: =Z9/Y9-1 -> -0.019422442 | AA16: =AA9/Z9-1 -> 0.069283569
C19: Drivers and metrics | S19: Drivers and metrics | AE19: =AE4 -> 0
B20: Metric (thousand) | C20: =C5 -> 2022 | D20: =D5 -> 2023 | E20: =E5 -> 2024 | F20: =F5 -> 2025 | G20: =G5 -> 2026 | H20: =H5 -> 2027 | I20: =I5 -> 2028 | J20: =J5 -> 2029 | ... L20: =L5 -> 2031 | R20: Metric (thousand) | S20: =S5 -> Q3 2025 | T20: =T5 -> Q4 2025 | U20: =U5 -> Q1 2026 | V20: =V5 -> Q2 2026 | W20: =W5 -> Q3 2026 | X20: =X5 -> Q4 2026 | Y20: =Y5 -> Q1 2027 | Z20: =Z5 -> Q2 2027 | ... AC20: =AC5 -> FQ3 | AE20: =AE5 -> FQ1
B21: ARR | C21: =Statement!M213 -> 925276 | D21: =Statement!N213 -> 1203845 | E21: =Statement!O213 -> 1463698 | F21: =Statement!P213 -> 1666136 | G21: =Statement!Q213 -> 1852567 | H21: 2063000 | I21: =(H21*I22)+I24 -> 2265540 | J21: =(I21*J22)+J24 -> 2461627.8 | K21: =(J21*K22)+K24 -> 2646825.5 | L21: =(K21*L22)+L24 -> 2843135 | N21: ARR(t-1) * NRR + New logo ARR | Q21: ARR(t-1) * NRR + New logo ARR | R21: ARR | S21: =Statement!T213 -> 1606561 | T21: =Statement!U213 -> 1666136 | U21: =Statement!V213 -> 1692683 | V21: =Statement!W213 -> 1723401 | W21: =Statement!X213 -> 1782384 | X21: =Statement!Y213 -> 1852567 | Y21: =Statement!Z213 -> 1901211 | Z21: =Statement!AA213 -> 1937722 | AA21: 1994000 | AE21: =AA21 -> 1994000
B22: Net retention rate | C22: =Statement!M215 -> 1.45 | D22: =Statement!N215 -> 1.23 | E22: =Statement!O215 -> 1.19 | F22: =Statement!P215 -> 1.1 | G22: =Statement!Q215 -> 1.07 | H22: 1.08 | I22: 1.08 | J22: 1.07 | K22: 1.06 | L22: 1.06 | R22: Net retention rate | S22: =Statement!T215 -> 1.13 | T22: =Statement!U215 -> 1.1 | U22: =Statement!V215 -> 1.08 | V22: =Statement!W215 -> 1.08 | W22: =Statement!X215 -> 1.07 | X22: =Statement!Y215 -> 1.07 | Y22: =Statement!Z215 -> 1.09 | Z22: =Statement!AA215 -> 1.09 | AA22: 1.08 | AE22: =AA22 -> 1.08
B23: New ARR | C23: =Statement!M214 -> 344793 | D23: =Statement!N214 -> 278569 | E23: =Statement!O214 -> 259853 | F23: =Statement!P214 -> 202438 | G23: =Statement!Q214 -> 186431 | H23: =H21-G21 -> 210433 | I23: =I21-H21 -> 202540 | J23: =J21-I21 -> 196087.8 | K23: =K21-J21 -> 185197.67 | L23: =L21-K21 -> 196309.53 | N23: ARR(t) - ARR(t-1) | Q23: ARR(t) - ARR(t-1) | R23: New ARR | S23: =Statement!T214 -> 56000 | T23: =Statement!U214 -> 60000 | U23: =Statement!V214 -> 27000 | V23: =Statement!W214 -> 31000 | W23: =Statement!X214 -> 59000 | X23: =Statement!Y214 -> 70000 | Y23: =Statement!Z214 -> 49000 | Z23: =Statement!AA214 -> 37000 | AA23: =AA21-Z21 -> 56278 | AE23: =SUM(X23:AA23) -> 212278
B24: New logo ARR | H24: =H25*H26 -> 37500 | I24: =I25*I26 -> 37500 | J24: =J25*J26 -> 37500 | K24: =K25*K26 -> 37500 | L24: =L25*L26 -> 37500 | N24: New customers * avg initial contract value | Q24: New customers * avg initial contract value | R24: New logo ARR | AA24: =AA25*AA26 -> 7500
B25: New Customers >= 100k | D25: =Statement!N217-Statement!M217 -> 292 | E25: =Statement!O217-Statement!N217 -> 269 | F25: =Statement!P217-Statement!O217 -> 238 | G25: =Statement!Q217-Statement!P217 -> 273 | H25: 250 | I25: 250 | J25: 250 | K25: 250 | L25: 250 | R25: New Customers >= 100k | T25: =Statement!U217-Statement!T217 -> 57 | U25: =Statement!V217-Statement!U217 -> 73 | V25: =Statement!W217-Statement!V217 -> 67 | W25: =Statement!X217-Statement!W217 -> 74 | X25: =Statement!Y217-Statement!X217 -> 59 | Y25: =Statement!Z217-Statement!Y217 -> 59 | Z25: =Statement!AA217-Statement!Z217 -> 42 | AA25: 50 | AE25: =SUM(X25:AA25) -> 210
B26: Avg initial contract value | H26: 150 | I26: 150 | J26: 150 | K26: 150 | L26: 150 | R26: Avg initial contract value | AA26: 150
B27: Revenue to ARR | C27: =C9/C21 -> 0.96430903 | D27: =D9/D21 -> 0.8793333 | E27: =E9/E21 -> 0.89367615 | F27: =F9/F21 -> 0.85807161 | G27: =G9/G21 -> 0.86937315 | H27: 0.868 | I27: 0.86 | J27: 0.87 | K27: 0.87 | L27: 0.87 | R27: Revenue to ARR | S27: =S9/S21 -> 0.2207529 | T27: =T9/T21 -> 0.25426856 | U27: =U9/U21 -> 0.21068564 | V27: =V9/V21 -> 0.20989195 | W27: =W9/W21 -> 0.23065344 | X27: =X9/X21 -> 0.25969749 | Y27: =Y9/Y21 -> 0.22006079 | Z27: =Z9/Z21 -> 0.21172077 | AA27: 0.22
B28: Professional services % revenue | C28: =C8/C9 -> 0.045904072 | D28: =D8/D9 -> 0.049048679 | E28: =E8/E9 -> 0.028103958 | F28: =F8/F9 -> 0.028366805 | G28: =G8/G9 -> 0.030862327 | H28: 0.04 | I28: 0.033 | J28: 0.028 | K28: 0.026 | L28: 0.025 | R28: Professional services % revenue | S28: =S8/S9 -> 0.029767124 | T28: =T8/T9 -> 0.02553075 | U28: =U8/U9 -> 0.030942954 | V28: =V8/V9 -> 0.030973549 | W28: =W8/W9 -> 0.03283039 | X28: =X8/X9 -> 0.0290372 | Y28: =Y8/Y9 -> 0.03864889 | Z28: =Z8/Z9 -> 0.049593425 | AA28: 0.05
B29: Licenses % revenue | C29: =C6/C9 -> 0.53956393 | D29: =D6/D9 -> 0.47028617 | E29: =E6/E9 -> 0.47504419 | F29: =F6/F9 -> 0.4106923 | G29: =G6/G9 -> 0.37650847 | H29: 0.35 | I29: 0.33 | J29: 0.31 | K29: 0.3 | L29: 0.28 | R29: Licenses % revenue | S29: =S6/S9 -> 0.3867837 | T29: =T6/T9 -> 0.4664484 | U29: =U6/U9 -> 0.35972341 | V29: =V6/V9 -> 0.31007 | W29: =W6/W9 -> 0.36496778 | X29: =X6/X9 -> 0.44876504 | Y29: =Y6/Y9 -> 0.35687243 | Z29: =Z6/Z9 -> 0.30186761 | AA29: 0.35
C32: Growth rates for metrics | S32: Growth rates for metrics
B33: Metrics growth % | C33: =C5 -> 2022 | D33: =D5 -> 2023 | E33: =E5 -> 2024 | F33: =F5 -> 2025 | G33: =G5 -> 2026 | H33: =H5 -> 2027 | I33: =I5 -> 2028 | J33: =J5 -> 2029 | ... L33: =L5 -> 2031 | R33: Metrics growth % | S33: =S5 -> Q3 2025 | T33: =T5 -> Q4 2025 | U33: =U5 -> Q1 2026 | V33: =V5 -> Q2 2026 | W33: =W5 -> Q3 2026 | X33: =X5 -> Q4 2026 | Y33: =Y5 -> Q1 2027 | Z33: =Z5 -> Q2 2027 | ... AC33: =AC5 -> FQ3
B34: ARR | D34: =D21/C21-1 -> 0.30106584 | E34: =E21/D21-1 -> 0.21585254 | F34: =F21/E21-1 -> 0.13830585 | G34: =G21/F21-1 -> 0.11189423 | H34: =H21/G21-1 -> 0.11358995 | I34: =I21/H21-1 -> 0.098177412 | J34: =J21/I21-1 -> 0.086552345 | K34: =K21/J21-1 -> 0.075233822 | L34: =L21/K21-1 -> 0.074167916 | R34: =B34 -> ARR | T34: =T21/S21-1 -> 0.037082314 | U34: =U21/T21-1 -> 0.015933273 | V34: =V21/U21-1 -> 0.018147521 | W34: =W21/V21-1 -> 0.034224768 | X34: =X21/W21-1 -> 0.039375915 | Y34: =Y21/X21-1 -> 0.02625762 | Z34: =Z21/Y21-1 -> 0.019204076 | AA34: =AA21/Z21-1 -> 0.029043382
B35: New ARR | D35: =D23/C23-1 -> -0.19206886 | E35: =E23/D23-1 -> -0.067186227 | F35: =F23/E23-1 -> -0.22095185 | G35: =G23/F23-1 -> -0.079071123 | H35: =H23/G23-1 -> 0.12874468 | I35: =I23/H23-1 -> -0.037508376 | J35: =J23/I23-1 -> -0.031856423 | K35: =K23/J23-1 -> -0.05553702 | L35: =L23/K23-1 -> 0.06 | R35: =B35 -> New ARR | T35: =T23/S23-1 -> 0.071428571 | U35: =U23/T23-1 -> -0.55 | V35: =V23/U23-1 -> 0.14814815 | W35: =W23/V23-1 -> 0.90322581 | X35: =X23/W23-1 -> 0.18644068 | Y35: =Y23/X23-1 -> -0.3 | Z35: =Z23/Y23-1 -> -0.24489796 | AA35: =AA23/Z23-1 -> 0.52102703

Sheet COGS & OpEx
B1: COGS & OpEx forecast
C2: History | H2: Forecast | P2: History | X2: Forecast | AB2: TTM
C4: Revenues | P4: Revenues
B5: =Revenue!B5 -> Revenues (thousand) | C5: =Revenue!C5 -> 2022 | D5: =Revenue!D5 -> 2023 | E5: =Revenue!E5 -> 2024 | F5: =Revenue!F5 -> 2025 | G5: =Revenue!G5 -> 2026 | H5: =G5+1 -> 2027 | I5: =H5+1 -> 2028 | J5: =I5+1 -> 2029 | K5: =J5+1 -> 2030 | L5: =K5+1 -> 2031 | O5: Revenues (thousand) | P5: =Revenue!S5 -> Q3 2025 | Q5: =Revenue!T5 -> Q4 2025 | R5: =Revenue!U5 -> Q1 2026 | S5: =Revenue!V5 -> Q2 2026 | T5: =Revenue!W5 -> Q3 2026 | U5: =Revenue!X5 -> Q4 2026 | V5: =Revenue!Y5 -> Q1 2027 | W5: =Revenue!Z5 -> Q2 2027 | X5: FQ1 | Y5: FQ2 | Z5: FQ3 | AB5: =Revenue!AE5 -> FQ1
B6: Revenue | C6: =Revenue!C9 -> 892252 | D6: =Revenue!D9 -> 1058581 | E6: =Revenue!E9 -> 1308072 | F6: =Revenue!F9 -> 1429664 | G6: =Revenue!G9 -> 1610572 | H6: =Revenue!H9 -> 1790684 | I6: =Revenue!I9 -> 1948364.4 | J6: =Revenue!J9 -> 2141616.2 | ... L6: =Revenue!L9 -> 2473527.4 | O6: Revenue | P6: =Revenue!S9 -> 354653 | Q6: =Revenue!T9 -> 423646 | R6: =Revenue!U9 -> 356624 | S6: =Revenue!V9 -> 361728 | T6: =Revenue!W9 -> 411113 | U6: =Revenue!X9 -> 481107 | V6: =Revenue!Y9 -> 418382 | W6: =Revenue!Z9 -> 410256 | X6: =Revenue!AA9 -> 438680 | AB6: =Revenue!AE9 -> 1748425
C9: COGS and OpEx | P9: COGS & OpEx | AB9: =AB4 -> 0
B10: Expenses (tnousand) | C10: =C5 -> 2022 | D10: =D5 -> 2023 | E10: =E5 -> 2024 | F10: =F5 -> 2025 | G10: =G5 -> 2026 | H10: =H5 -> 2027 | I10: =I5 -> 2028 | J10: =J5 -> 2029 | ... L10: =L5 -> 2031 | O10: Expenses (thousand) | P10: =P5 -> Q3 2025 | Q10: =Q5 -> Q4 2025 | R10: =R5 -> Q1 2026 | S10: =S5 -> Q2 2026 | T10: =T5 -> Q3 2026 | U10: =U5 -> Q4 2026 | V10: =V5 -> Q1 2027 | W10: =W5 -> Q2 2027 | ... Z10: =Z5 -> FQ3 | AB10: =AB5 -> FQ1
B11: =Statement!B191 -> Licenses COGS | C11: =Statement!M191 -> 11888 | D11: =Statement!N191 -> 10421 | E11: =Statement!O191 -> 10469 | F11: =Statement!P191 -> 8565 | G11: =Statement!Q191 -> 5334 | H11: =H6*H23 -> 5372.052 | I11: =I6*I23 -> 5845.0932 | J11: =J6*J23 -> 4283.2324 | K11: =K6*K23 -> 4605.4763 | L11: =L6*L23 -> 4947.0549 | O11: =B11 -> Licenses COGS | P11: =Statement!T191 -> 2340 | Q11: =Statement!U191 -> 1231 | R11: =Statement!V191 -> 1268 | S11: =Statement!W191 -> 1200 | T11: =Statement!X191 -> 1311 | U11: =Statement!Y191 -> 1555 | V11: =Statement!Z191 -> 1664 | W11: =Statement!AA191 -> 1462 | X11: =X23*X$6 -> 1316.04 | AB11: =SUM(U11:X11) -> 5997.04
B12: =Statement!B192 -> Subscription services COGS | C12: =Statement!M192 -> 60565 | D12: =Statement!N192 -> 87366 | E12: =Statement!O192 -> 111922 | F12: =Statement!P192 -> 167630 | G12: =Statement!Q192 -> 157588 | H12: =H6*H24 -> 179068.4 | I12: =I6*I24 -> 194836.44 | J12: =J6*J24 -> 192745.46 | K12: =K6*K24 -> 207246.43 | L12: =L6*L24 -> 197882.2 | O12: =B12 -> Subscription services COGS | P12: =Statement!T192 -> 43487 | Q12: =Statement!U192 -> 43860 | R12: =Statement!V192 -> 38468 | S12: =Statement!W192 -> 38229 | T12: =Statement!X192 -> 40121 | U12: =Statement!Y192 -> 40770 | V12: =Statement!Z192 -> 43988 | W12: =Statement!AA192 -> 39679 | X12: =X24*X$6 -> 39481.2 | AB12: =SUM(U12:X12) -> 163918.2
B13: =Statement!B193 -> Professional services COGS | C13: =Statement!M193 -> 96415 | D13: =Statement!N193 -> 82264 | E13: =Statement!O193 -> 73533 | F13: =Statement!P193 -> 70747 | G13: =Statement!Q193 -> 108062 | H13: =H6*H25 -> 125347.88 | I13: =I6*I25 -> 126643.69 | J13: =J6*J25 -> 117788.89 | K13: =K6*K25 -> 115136.91 | L13: =L6*L25 -> 111308.74 | O13: =B13 -> Professional services COGS | P13: =Statement!T193 -> 17936 | Q13: =Statement!U193 -> 19443 | R13: =Statement!V193 -> 24121 | S13: =Statement!W193 -> 24951 | T13: =Statement!X193 -> 27380 | U13: =Statement!Y193 -> 31610 | V13: =Statement!Z193 -> 31276 | W13: =Statement!AA193 -> 39446 | X13: =X25*X$6 -> 35094.4 | AB13: =SUM(U13:X13) -> 137426.4
B14: COGS | C14: =Statement!M6 -> 168868 | D14: =Statement!N6 -> 180051 | E14: =Statement!O6 -> 195924 | F14: =Statement!P6 -> 246942 | G14: =Statement!Q6 -> 270984 | H14: =SUM(H11:H13) -> 309788.33 | I14: =SUM(I11:I13) -> 327325.22 | J14: =SUM(J11:J13) -> 314817.58 | K14: =SUM(K11:K13) -> 326988.82 | L14: =SUM(L11:L13) -> 314137.99 | O14: =B14 -> COGS | P14: =Statement!T6 -> 63763 | Q14: =Statement!U6 -> 64534 | R14: =Statement!V6 -> 63857 | S14: =Statement!W6 -> 64380 | T14: =Statement!X6 -> 68812 | U14: =Statement!Y6 -> 73935 | V14: =Statement!Z6 -> 76928 | W14: =Statement!AA6 -> 80587 | X14: =SUM(X11:X13) -> 75891.64 | AB14: =SUM(AB11:AB13) -> 307341.64
B15: =Statement!B8 -> Sales and marketing | C15: =Statement!M8 -> 697682 | D15: =Statement!N8 -> 701558 | E15: =Statement!O8 -> 713130 | F15: =Statement!P8 -> 738493 | G15: =Statement!Q8 -> 683329 | H15: =H6*H27 -> 716273.6 | I15: =I6*I27 -> 779345.76 | J15: =J6*J27 -> 813814.15 | K15: =K6*K27 -> 875040.5 | L15: =L6*L27 -> 890469.88 | O15: =B15 -> Sales and marketing | P15: =Statement!T8 -> 187188 | Q15: =Statement!U8 -> 176836 | R15: =Statement!V8 -> 159661 | S15: =Statement!W8 -> 166303 | T15: =Statement!X8 -> 179186 | U15: =Statement!Y8 -> 178179 | V15: =Statement!Z8 -> 167859 | W15: =Statement!AA8 -> 164606 | X15: =X27*X$6 -> 175472 | AB15: =SUM(U15:X15) -> 686116
B16: =Statement!B9 -> R&D | C16: =Statement!M9 -> 276657 | D16: =Statement!N9 -> 285750 | E16: =Statement!O9 -> 332101 | F16: =Statement!P9 -> 380682 | G16: =Statement!Q9 -> 385208 | H16: =H6*H28 -> 447671 | I16: =I6*I28 -> 487091.1 | J16: =J6*J28 -> 524695.97 | K16: =K6*K28 -> 552657.16 | L16: =L6*L28 -> 593646.59 | O16: =B16 -> R&D | P16: =Statement!T9 -> 96976 | Q16: =Statement!U9 -> 99670 | R16: =Statement!V9 -> 94839 | S16: =Statement!W9 -> 98341 | T16: =Statement!X9 -> 96869 | U16: =Statement!Y9 -> 95159 | V16: =Statement!Z9 -> 92902 | W16: =Statement!AA9 -> 83393 | X16: =X28*X$6 -> 100896.4 | AB16: =SUM(U16:X16) -> 372350.4
B17: =Statement!B10 -> General and administrative | C17: =Statement!M10 -> 249991 | D17: =Statement!N10 -> 239505 | E17: =Statement!O10 -> 231637 | F17: =Statement!P10 -> 226116 | G17: =Statement!Q10 -> 214291 | H17: =H6*H29 -> 214882.08 | I17: =I6*I29 -> 233803.73 | J17: =J6*J29 -> 235577.78 | K17: =K6*K29 -> 253301.2 | L17: =L6*L29 -> 247352.74 | O17: =B17 -> General and administrative | P17: =Statement!T10 -> 50090 | Q17: =Statement!U10 -> 48997 | R17: =Statement!V10 -> 54679 | S17: =Statement!W10 -> 52889 | T17: =Statement!X10 -> 53175 | U17: =Statement!Y10 -> 53548 | V17: =Statement!Z10 -> 52706 | W17: =Statement!AA10 -> 50066 | X17: =X29*X$6 -> 57028.4 | AB17: =SUM(U17:X17) -> 213348.4
B18: OpEx | C18: =Statement!M11 -> 1224330 | D18: =Statement!N11 -> 1226813 | E18: =Statement!O11 -> 1276868 | F18: =Statement!P11 -> 1345291 | G18: =Statement!Q11 -> 1282828 | H18: =SUM(H15:H17) -> 1378826.7 | I18: =SUM(I15:I17) -> 1500240.6 | J18: =SUM(J15:J17) -> 1574087.9 | K18: =SUM(K15:K17) -> 1680998.9 | L18: =SUM(L15:L17) -> 1731469.2 | O18: =B18 -> OpEx | P18: =Statement!T11 -> 334254 | Q18: =Statement!U11 -> 325503 | R18: =Statement!V11 -> 309179 | S18: =Statement!W11 -> 317533 | T18: =Statement!X11 -> 329230 | U18: =Statement!Y11 -> 326886 | V18: =Statement!Z11 -> 313467 | W18: =Statement!AA11 -> 298065 | X18: =SUM(X15:X17) -> 333396.8 | AB18: =SUM(U18:X18) -> 1271814.8
C21: Expenses % of Revenue | P21: Expenses % of Revenue
B22: % of revenue | C22: =C5 -> 2022 | D22: =D5 -> 2023 | E22: =E5 -> 2024 | F22: =F5 -> 2025 | G22: =G5 -> 2026 | H22: =H5 -> 2027 | I22: =I5 -> 2028 | J22: =J5 -> 2029 | ... L22: =L5 -> 2031 | O22: % of revenue | P22: =P5 -> Q3 2025 | Q22: =Q5 -> Q4 2025 | R22: =R5 -> Q1 2026 | S22: =S5 -> Q2 2026 | T22: =T5 -> Q3 2026 | U22: =U5 -> Q4 2026 | V22: =V5 -> Q1 2027 | W22: =W5 -> Q2 2027 | ... Z22: =Z5 -> FQ3
B23: =B11 -> Licenses COGS | C23: =C11/C$6 -> 0.01332359 | D23: =D11/D$6 -> 0.0098443104 | E23: =E11/E$6 -> 0.0080033821 | F23: =F11/F$6 -> 0.0059909181 | G23: =G11/G$6 -> 0.0033118668 | H23: 0.003 | I23: 0.003 | J23: 0.002 | K23: 0.002 | L23: 0.002 | O23: =O11 -> Licenses COGS | P23: =P11/P$6 -> 0.0065979986 | Q23: =Q11/Q$6 -> 0.0029057279 | R23: =R11/R$6 -> 0.0035555655 | S23: =S11/S$6 -> 0.0033174098 | T23: =T11/T$6 -> 0.0031889043 | U23: =U11/U$6 -> 0.0032321292 | V23: =V11/V$6 -> 0.0039772266 | W23: =W11/W$6 -> 0.0035636286 | X23: 0.003
B24: =B12 -> Subscription services COGS | C24: =C12/C$6 -> 0.067878806 | D24: =D12/D$6 -> 0.082531238 | E24: =E12/E$6 -> 0.085562568 | F24: =F12/F$6 -> 0.11725133 | G24: =G12/G$6 -> 0.097845983 | H24: 0.1 | I24: 0.1 | J24: 0.09 | K24: 0.09 | L24: 0.08 | O24: =O12 -> Subscription services COGS | P24: =P12/P$6 -> 0.12261845 | Q24: =Q12/Q$6 -> 0.10352983 | R24: =R12/R$6 -> 0.10786711 | S24: =S12/S$6 -> 0.10568438 | T24: =T12/T$6 -> 0.097591173 | U24: =U12/U$6 -> 0.084742064 | V24: =V12/V$6 -> 0.10513837 | W24: =W12/W$6 -> 0.096717659 | X24: 0.09
B25: =B13 -> Professional services COGS | C25: =C13/C$6 -> 0.10805804 | D25: =D13/D$6 -> 0.077711578 | E25: =E13/E$6 -> 0.056214796 | F25: =F13/F$6 -> 0.049485054 | G25: =G13/G$6 -> 0.067095417 | H25: 0.07 | I25: 0.065 | J25: 0.055 | K25: 0.05 | L25: 0.045 | O25: =O13 -> Professional services COGS | P25: =P13/P$6 -> 0.050573377 | Q25: =Q13/Q$6 -> 0.04589445 | R25: =R13/R$6 -> 0.067637063 | S25: =S13/S$6 -> 0.068977243 | T25: =T13/T$6 -> 0.066599694 | U25: =U13/U$6 -> 0.06570264 | V25: =V13/V$6 -> 0.07475465 | W25: =W13/W$6 -> 0.096149721 | X25: 0.08
B26: =B14 -> COGS | C26: =C14/C$6 -> 0.18926043 | D26: =D14/D$6 -> 0.17008713 | E26: =E14/E$6 -> 0.14978075 | F26: =F14/F$6 -> 0.1727273 | G26: =G14/G$6 -> 0.16825327 | H26: =H14/H$6 -> 0.173 | I26: =I14/I$6 -> 0.168 | J26: =J14/J$6 -> 0.147 | ... L26: =L14/L$6 -> 0.127 | O26: =O14 -> COGS | P26: =P14/P$6 -> 0.17978982 | Q26: =Q14/Q$6 -> 0.15233001 | R26: =R14/R$6 -> 0.17905974 | S26: =S14/S$6 -> 0.17797903 | T26: =T14/T$6 -> 0.16737977 | U26: =U14/U$6 -> 0.15367683 | V26: =V14/V$6 -> 0.18387024 | W26: =W14/W$6 -> 0.19643101 | X26: =X14/X$6 -> 0.173
B27: =B15 -> Sales and marketing | C27: =C15/C$6 -> 0.7819338 | D27: =D15/D$6 -> 0.66273436 | E27: =E15/E$6 -> 0.54517641 | F27: =F15/F$6 -> 0.51655004 | G27: =G15/G$6 -> 0.42427721 | H27: 0.4 | I27: 0.4 | J27: 0.38 | K27: 0.38 | L27: 0.36 | O27: =O15 -> Sales and marketing | P27: =P15/P$6 -> 0.52780605 | Q27: =Q15/Q$6 -> 0.41741454 | R27: =R15/R$6 -> 0.44770122 | S27: =S15/S$6 -> 0.459746 | T27: =T15/T$6 -> 0.43585584 | U27: =U15/U$6 -> 0.37035213 | V27: =V15/V$6 -> 0.4012099 | W27: =W15/W$6 -> 0.40122753 | X27: 0.4
B28: =B16 -> R&D | C28: =C16/C$6 -> 0.31006599 | D28: =D16/D$6 -> 0.26993683 | E28: =E16/E$6 -> 0.25388587 | F28: =F16/F$6 -> 0.26627375 | G28: =G16/G$6 -> 0.23917465 | H28: 0.25 | I28: 0.25 | J28: 0.245 | K28: 0.24 | L28: 0.24 | O28: =O16 -> R&D | P28: =P16/P$6 -> 0.27343911 | Q28: =Q16/Q$6 -> 0.23526718 | R28: =R16/R$6 -> 0.26593555 | S28: =S16/S$6 -> 0.27186449 | T28: =T16/T$6 -> 0.23562621 | U28: =U16/U$6 -> 0.19779176 | V28: =V16/V$6 -> 0.22205066 | W28: =W16/W$6 -> 0.20327064 | X28: 0.23
B29: =B17 -> General and administrative | C29: =C17/C$6 -> 0.28017981 | D29: =D17/D$6 -> 0.22625099 | E29: =E17/E$6 -> 0.17708276 | F29: =F17/F$6 -> 0.15816024 | G29: =G17/G$6 -> 0.13305273 | H29: 0.12 | I29: 0.12 | J29: 0.11 | K29: 0.11 | L29: 0.1 | O29: =O17 -> General and administrative | P29: =P17/P$6 -> 0.14123665 | Q29: =Q17/Q$6 -> 0.11565552 | R29: =R17/R$6 -> 0.15332395 | S29: =S17/S$6 -> 0.14621207 | T29: =T17/T$6 -> 0.129344 | U29: =U17/U$6 -> 0.11130164 | V29: =V17/V$6 -> 0.12597578 | W29: =W17/W$6 -> 0.122036 | X29: 0.13
B30: =B18 -> OpEx | C30: =C18/C$6 -> 1.3721796 | D30: =D18/D$6 -> 1.1589222 | E30: =E18/E$6 -> 0.97614504 | F30: =F18/F$6 -> 0.94098404 | G30: =G18/G$6 -> 0.7965046 | H30: =H18/H$6 -> 0.77 | I30: =I18/I$6 -> 0.77 | J30: =J18/J$6 -> 0.735 | ... L30: =L18/L$6 -> 0.7 | O30: =O18 -> OpEx | P30: =P18/P$6 -> 0.94248181 | Q30: =Q18/Q$6 -> 0.76833724 | R30: =R18/R$6 -> 0.86696072 | S30: =S18/S$6 -> 0.87782256 | T30: =T18/T$6 -> 0.80082605 | U30: =U18/U$6 -> 0.67944553 | V30: =V18/V$6 -> 0.74923634 | W30: =W18/W$6 -> 0.72653416 | X30: =X18/X$6 -> 0.76

Sheet WC & Investments
B1: Working Capital, Capex, D&A
C3: History | H3: Forecast
C5: Revenues
B6: Revenues (thousand) | C6: =Revenue!C5 -> 2022 | D6: =Revenue!D5 -> 2023 | E6: =Revenue!E5 -> 2024 | F6: =Revenue!F5 -> 2025 | G6: =Revenue!G5 -> 2026 | H6: =G6+1 -> 2027 | I6: =H6+1 -> 2028 | J6: =I6+1 -> 2029 | K6: =J6+1 -> 2030 | L6: =K6+1 -> 2031
B7: Revenue | C7: =Revenue!C9 -> 892252 | D7: =Revenue!D9 -> 1058581 | E7: =Revenue!E9 -> 1308072 | F7: =Revenue!F9 -> 1429664 | G7: =Revenue!G9 -> 1610572 | H7: =Revenue!H9 -> 1790684 | I7: =Revenue!I9 -> 1948364.4 | J7: =Revenue!J9 -> 2141616.2 | ... L7: =Revenue!L9 -> 2473527.4
B8: COGS | C8: ='COGS & OpEx'!C14 -> 168868 | D8: ='COGS & OpEx'!D14 -> 180051 | E8: ='COGS & OpEx'!E14 -> 195924 | F8: ='COGS & OpEx'!F14 -> 246942 | G8: ='COGS & OpEx'!G14 -> 270984 | H8: ='COGS & OpEx'!H14 -> 309788.33 | I8: ='COGS & OpEx'!I14 -> 327325.22 | J8: ='COGS & OpEx'!J14 -> 314817.58 | ... L8: ='COGS & OpEx'!L14 -> 314137.99
C11: Working Capital
B12: $ (thousand) | C12: =C6 -> 2022 | D12: =D6 -> 2023 | E12: =E6 -> 2024 | F12: =F6 -> 2025 | G12: =G6 -> 2026 | H12: =H6 -> 2027 | I12: =I6 -> 2028 | J12: =J6 -> 2029 | ... L12: =L6 -> 2031
B13: Accounts receivable | C13: =Statement!M30 -> 326819 | D13: =Statement!N30 -> 443477 | E13: =Statement!O30 -> 520493 | F13: =Statement!P30 -> 539866 | G13: =Statement!Q30 -> 580705 | H13: =H20*H7/365 -> 637777.86 | I13: =I20*I7/365 -> 693938.01 | J13: =J20*J7/365 -> 762767.41 | K13: =K20*K7/365 -> 820153.32 | L13: =L20*L7/365 -> 880982.38
B14: Inventory | C14: =Statement!M31 -> 0 | D14: =Statement!N31 -> 0 | E14: =Statement!O31 -> 0 | F14: =Statement!P31 -> 0 | G14: =Statement!Q31 -> 0 | H14: =H21*H8/365 -> 0 | I14: =I21*I8/365 -> 0 | J14: =J21*J8/365 -> 0 | K14: =K21*K8/365 -> 0 | L14: =L21*L8/365 -> 0
B15: Accounts payable | C15: =Statement!M38 -> 11515 | D15: =Statement!N38 -> 8891 | E15: =Statement!O38 -> 3447 | F15: =Statement!P38 -> 33178 | G15: =Statement!Q38 -> 10161 | H15: =H22*H8/365 -> 19520.909 | I15: =I22*I8/365 -> 20625.973 | J15: =J22*J8/365 -> 19837.82 | K15: =K22*K8/365 -> 20604.775 | L15: =L22*L8/365 -> 19794.996
C18: WC metrics and drivers
B19: Days | C19: =C6 -> 2022 | D19: =D6 -> 2023 | E19: =E6 -> 2024 | F19: =F6 -> 2025 | G19: =G6 -> 2026 | H19: =H6 -> 2027 | I19: =I6 -> 2028 | J19: =J6 -> 2029 | ... L19: =L6 -> 2031
B20: DSO | C20: =C13/C7*365 -> 133.69422 | D20: =D13/D7*365 -> 152.9114 | E20: =E13/E7*365 -> 145.23661 | F20: =F13/F7*365 -> 137.83035 | G20: =G13/G7*365 -> 131.60376 | H20: 130 | I20: 130 | J20: 130 | K20: 130 | L20: 130
B21: DIO | C21: =C14/C8*365 -> 0 | D21: =D14/D8*365 -> 0 | E21: =E14/E8*365 -> 0 | F21: =F14/F8*365 -> 0 | G21: =G14/G8*365 -> 0 | H21: 0 | I21: 0 | J21: 0 | K21: 0 | L21: 0
B22: DPO | C22: =C15/C8*365 -> 24.889115 | D22: =D15/D8*365 -> 18.023865 | E22: =E15/E8*365 -> 6.4216482 | F22: =F15/F8*365 -> 49.039734 | G22: =G15/G8*365 -> 13.686288 | H22: 23 | I22: 23 | J22: 23 | K22: 23 | L22: 23
B23: Net trade cycle | C23: =C20+C21-C22 -> 108.80511 | D23: =D20+D21-D22 -> 134.88754 | E23: =E20+E21-E22 -> 138.81496 | F23: =F20+F21-F22 -> 88.790616 | G23: =G20+G21-G22 -> 117.91747 | H23: =H20+H21-H22 -> 107 | I23: =I20+I21-I22 -> 107 | J23: =J20+J21-J22 -> 107 | ... L23: =L20+L21-L22 -> 107
C26: Change in SIP NWC
B27: $ (thousand) | C27: =C6 -> 2022 | D27: =D6 -> 2023 | E27: =E6 -> 2024 | F27: =F6 -> 2025 | G27: =G6 -> 2026 | H27: =H6 -> 2027 | I27: =I6 -> 2028 | J27: =J6 -> 2029 | ... L27: =L6 -> 2031
B28: Change in acc receivable | C28: =Statement!M55 -> -86387 | D28: =Statement!N55 -> -123783 | E28: =Statement!O55 -> -64217 | F28: =Statement!P55 -> -22173 | G28: =Statement!Q55 -> -25802 | H28: =-(H13-G13) -> -57072.863 | I28: =-(I13-H13) -> -56160.142 | J28: =-(J13-I13) -> -68829.403 | K28: =-(K13-J13) -> -57385.908 | L28: =-(L13-K13) -> -60829.062
B29: Change in inventory | C29: =Statement!M56 -> 0 | D29: =Statement!N56 -> 0 | E29: =Statement!O56 -> 0 | F29: =Statement!P56 -> 0 | G29: =Statement!Q56 -> 0 | H29: =-(H14-G14) -> 0 | I29: =-(I14-H14) -> 0 | J29: =-(J14-I14) -> 0 | K29: =-(K14-J14) -> 0 | L29: =-(L14-K14) -> 0
B30: Change in acc payable | C30: =Statement!M57 -> 3507 | D30: =Statement!N57 -> -1571 | E30: =Statement!O57 -> -5052 | F30: =Statement!P57 -> 27856 | G30: =Statement!Q57 -> -21675 | H30: =H15-G15 -> 9359.9086 | I30: =I15-H15 -> 1105.0641 | J30: =J15-I15 -> -788.15265 | K30: =K15-J15 -> 766.95478 | L30: =L15-K15 -> -809.77849
C33: Total change in NWC and less SIP
B34: $ (thousand) | C34: =C6 -> 2022 | D34: =D6 -> 2023 | E34: =E6 -> 2024 | F34: =F6 -> 2025 | G34: =G6 -> 2026 | H34: =H6 -> 2027 | I34: =I6 -> 2028 | J34: =J6 -> 2029 | ... L34: =L6 -> 2031
B35: Total change in NWC | C35: =Statement!M55+Statement!M56+Statement!M57+Statement!M58 -> -105902 | D35: =Statement!N55+Statement!N56+Statement!N57+Statement!N58 -> -146687 | E35: =Statement!O55+Statement!O56+Statement!O57+Statement!O58 -> -66928 | F35: =Statement!P55+Statement!P56+Statement!P57+Statement!P58 -> -41772 | G35: =Statement!Q55+Statement!Q56+Statement!Q57+Statement!Q58 -> -149207 | H35: =H36+H28+H29+H30 -> -101433.47 | I35: =I36+I28+I29+I30 -> -113506.01 | J35: =J36+J28+J29+J30 -> -133866.04 | K35: =K36+K28+K29+K30 -> -125701.1 | L35: =L36+L28+L29+L30 -> -135844.66
B36: Change in NWC less SIP | C36: =C35-C28-C29-C30 -> -23022 | D36: =D35-D28-D29-D30 -> -21333 | E36: =E35-E28-E29-E30 -> 2341 | F36: =F35-F28-F29-F30 -> -47455 | G36: =G35-G28-G29-G30 -> -101730 | H36: =H7*H37 -> -53720.52 | I36: =I7*I37 -> -58450.932 | J36: =J7*J37 -> -64248.486 | K36: =K7*K37 -> -69082.145 | L36: =L7*L37 -> -74205.823
B37: % of revenue | C37: =C36/C7 -> -0.025802128 | D37: =D36/D7 -> -0.020152449 | E37: =E36/E7 -> 0.0017896568 | F37: =F36/F7 -> -0.033193114 | G37: =G36/G7 -> -0.063163895 | H37: -0.03 | I37: -0.03 | J37: -0.03 | K37: -0.03 | L37: -0.03
C40: Investments
B41: $ (thousand) | C41: =C6 -> 2022 | D41: =D6 -> 2023 | E41: =E6 -> 2024 | F41: =F6 -> 2025 | G41: =G6 -> 2026 | H41: =H6 -> 2027 | I41: =I6 -> 2028 | J41: =J6 -> 2029 | ... L41: =L6 -> 2031
B42: D&A | C42: =Statement!M53 -> 14705 | D42: =Statement!N53 -> 18723 | E42: =Statement!O53 -> 22597 | F42: =Statement!P53 -> 17232 | G42: =Statement!Q53 -> 16969 | H42: =H7*H43 -> 17906.84 | I42: =I7*I43 -> 19483.644 | J42: =J7*J43 -> 21416.162 | K42: =K7*K43 -> 23027.382 | L42: =L7*L43 -> 24735.274
B43: % of Revenue | C43: =C42/C7 -> 0.01648077 | D43: =D42/D7 -> 0.017686885 | E43: =E42/E7 -> 0.017275043 | F43: =F42/F7 -> 0.012053182 | G43: =G42/G7 -> 0.010536008 | H43: 0.01 | I43: 0.01 | J43: 0.01 | K43: 0.01 | L43: 0.01
B44: % of CapEx | C44: =C42/C45 -> 1.2431313 | D44: =D42/D45 -> 0.78618518 | E44: =E42/E45 -> 3.0777717 | F44: =F42/F45 -> 1.1547276 | G44: =G42/G45 -> 0.89085468 | H44: =H42/H45 -> 0.90909091 | I44: =I42/I45 -> 0.90909091 | J44: =J42/J45 -> 0.90909091 | ... L44: =L42/L45 -> 0.90909091
B45: CapEx | C45: =-Statement!M110 -> 11829 | D45: =-Statement!N110 -> 23815 | E45: =-Statement!O110 -> 7342 | F45: =-Statement!P110 -> 14923 | G45: =-Statement!Q110 -> 19048 | H45: =H7*H46 -> 19697.524 | I45: =I7*I46 -> 21432.008 | J45: =J7*J46 -> 23557.778 | K45: =K7*K46 -> 25330.12 | L45: =L7*L46 -> 27208.802
B46: % of Revenue | C46: =C45/C7 -> 0.013257465 | D46: =D45/D7 -> 0.022497098 | E46: =E45/E7 -> 0.0056128409 | F46: =F45/F7 -> 0.010438117 | G46: =G45/G7 -> 0.011826854 | H46: 0.011 | I46: 0.011 | J46: 0.011 | K46: 0.011 | L46: 0.011

Sheet FCF & Other
B1: Results
C2: History | H2: Forecast
C4: Income statement
B5: $ (thousand) | C5: =Revenue!C5 -> 2022 | D5: =Revenue!D5 -> 2023 | E5: =Revenue!E5 -> 2024 | F5: =Revenue!F5 -> 2025 | G5: =Revenue!G5 -> 2026 | H5: =G5+1 -> 2027 | I5: =H5+1 -> 2028 | J5: =I5+1 -> 2029 | K5: =J5+1 -> 2030 | L5: =K5+1 -> 2031
B6: Revenue | C6: =Revenue!C9 -> 892252 | D6: =Revenue!D9 -> 1058581 | E6: =Revenue!E9 -> 1308072 | F6: =Revenue!F9 -> 1429664 | G6: =Revenue!G9 -> 1610572 | H6: =Revenue!H9 -> 1790684 | I6: =Revenue!I9 -> 1948364.4 | J6: =Revenue!J9 -> 2141616.2 | ... L6: =Revenue!L9 -> 2473527.4 | N6: From Revenue Sheet
B7: COGS | C7: ='COGS & OpEx'!C14 -> 168868 | D7: ='COGS & OpEx'!D14 -> 180051 | E7: ='COGS & OpEx'!E14 -> 195924 | F7: ='COGS & OpEx'!F14 -> 246942 | G7: ='COGS & OpEx'!G14 -> 270984 | H7: ='COGS & OpEx'!H14 -> 309788.33 | I7: ='COGS & OpEx'!I14 -> 327325.22 | J7: ='COGS & OpEx'!J14 -> 314817.58 | ... L7: ='COGS & OpEx'!L14 -> 314137.99 | N7: From COGS and OpEx Sheet
B8: Gross profit | C8: =C6-C7 -> 723384 | D8: =D6-D7 -> 878530 | E8: =E6-E7 -> 1112148 | F8: =F6-F7 -> 1182722 | G8: =G6-G7 -> 1339588 | H8: =H6-H7 -> 1480895.7 | I8: =I6-I7 -> 1621039.2 | J8: =J6-J7 -> 1826798.6 | ... L8: =L6-L7 -> 2159389.5
B9: OpEx | C9: ='COGS & OpEx'!C18 -> 1224330 | D9: ='COGS & OpEx'!D18 -> 1226813 | E9: ='COGS & OpEx'!E18 -> 1276868 | F9: ='COGS & OpEx'!F18 -> 1345291 | G9: ='COGS & OpEx'!G18 -> 1282828 | H9: ='COGS & OpEx'!H18 -> 1378826.7 | I9: ='COGS & OpEx'!I18 -> 1500240.6 | J9: ='COGS & OpEx'!J18 -> 1574087.9 | ... L9: ='COGS & OpEx'!L18 -> 1731469.2 | N9: From COGS and OpEx Sheet
B10: EBIT | C10: =C8-C9 -> -500946 | D10: =D8-D9 -> -348283 | E10: =E8-E9 -> -164720 | F10: =F8-F9 -> -162569 | G10: =G8-G9 -> 56760 | H10: =H8-H9 -> 102068.99 | I10: =I8-I9 -> 120798.59 | J10: =J8-J9 -> 252710.71 | ... L10: =L8-L9 -> 427920.25
C13: Drivers
C14: =C5 -> 2022 | D14: =D5 -> 2023 | E14: =E5 -> 2024 | F14: =F5 -> 2025 | G14: =G5 -> 2026 | H14: =H5 -> 2027 | I14: =I5 -> 2028 | J14: =J5 -> 2029 | ... L14: =L5 -> 2031
B15: Tax rate | C15: =Statement!M83 -> 0 | D15: =Statement!N83 -> 0 | E15: =Statement!O83 -> 0 | F15: =Statement!P83 -> 0 | G15: =Statement!Q83 -> 0 | H15: =Overview!$C$26 -> 0.21 | I15: =Overview!$C$26 -> 0.21 | J15: =Overview!$C$26 -> 0.21 | K15: =Overview!$C$26 -> 0.21 | L15: =Overview!$C$26 -> 0.21 | N15: From Statements and Overview sheet
C18: Cash Flow Statement
B19: $ (thousand) | C19: =C5 -> 2022 | D19: =D5 -> 2023 | E19: =E5 -> 2024 | F19: =F5 -> 2025 | G19: =G5 -> 2026 | H19: =H5 -> 2027 | I19: =I5 -> 2028 | J19: =J5 -> 2029 | ... L19: =L5 -> 2031
B20: D&A | C20: ='WC & Investments'!C42 -> 14705 | D20: ='WC & Investments'!D42 -> 18723 | E20: ='WC & Investments'!E42 -> 22597 | F20: ='WC & Investments'!F42 -> 17232 | G20: ='WC & Investments'!G42 -> 16969 | H20: ='WC & Investments'!H42 -> 17906.84 | I20: ='WC & Investments'!I42 -> 19483.644 | J20: ='WC & Investments'!J42 -> 21416.162 | ... L20: ='WC & Investments'!L42 -> 24735.274 | N20: From WC & Investments Sheet
B21: CapEx | C21: ='WC & Investments'!C45 -> 11829 | D21: ='WC & Investments'!D45 -> 23815 | E21: ='WC & Investments'!E45 -> 7342 | F21: ='WC & Investments'!F45 -> 14923 | G21: ='WC & Investments'!G45 -> 19048 | H21: ='WC & Investments'!H45 -> 19697.524 | I21: ='WC & Investments'!I45 -> 21432.008 | J21: ='WC & Investments'!J45 -> 23557.778 | ... L21: ='WC & Investments'!L45 -> 27208.802 | N21: From WC & Investments Sheet
B22: Change in NWC | C22: ='WC & Investments'!C35 -> -105902 | D22: ='WC & Investments'!D35 -> -146687 | E22: ='WC & Investments'!E35 -> -66928 | F22: ='WC & Investments'!F35 -> -41772 | G22: ='WC & Investments'!G35 -> -149207 | H22: ='WC & Investments'!H35 -> -101433.47 | I22: ='WC & Investments'!I35 -> -113506.01 | J22: ='WC & Investments'!J35 -> -133866.04 | ... L22: ='WC & Investments'!L35 -> -135844.66 | N22: From WC & Investments Sheet
C25: FCFF
B26: $ (thousand) | C26: =C5 -> 2022 | D26: =D5 -> 2023 | E26: =E5 -> 2024 | F26: =F5 -> 2025 | G26: =G5 -> 2026 | H26: =H5 -> 2027 | I26: =I5 -> 2028 | J26: =J5 -> 2029 | ... L26: =L5 -> 2031
B27: NOPAT | C27: =C10*(1-C15) -> -500946 | D27: =D10*(1-D15) -> -348283 | E27: =E10*(1-E15) -> -164720 | F27: =F10*(1-F15) -> -162569 | G27: =G10*(1-G15) -> 56760 | H27: =H10*(1-H15) -> 80634.501 | I27: =I10*(1-I15) -> 95430.888 | J27: =J10*(1-J15) -> 199641.46 | ... L27: =L10*(1-L15) -> 338057
B28: FCFF | C28: =C27+C20-C21+C22 -> -603972 | D28: =D27+D20-D21+D22 -> -500062 | E28: =E27+E20-E21+E22 -> -216393 | F28: =F27+F20-F21+F22 -> -202032 | G28: =G27+G20-G21+G22 -> -94526 | H28: =H27+H20-H21+H22 -> -22589.658 | I28: =I27+I20-I21+I22 -> -20023.486 | J28: =J27+J20-J21+J22 -> 63633.803 | ... L28: =L27+L20-L21+L22 -> 199738.8
C31: Margins
B32: % | C32: =C5 -> 2022 | D32: =D5 -> 2023 | E32: =E5 -> 2024 | F32: =F5 -> 2025 | G32: =G5 -> 2026 | H32: =H5 -> 2027 | I32: =I5 -> 2028 | J32: =J5 -> 2029 | ... L32: =L5 -> 2031
B33: Gross margin | C33: =Statement!M101 -> 0.81073957 | D33: =Statement!N101 -> 0.82991287 | E33: =Statement!O101 -> 0.85021925 | F33: =Statement!P101 -> 0.8272727 | G33: =Statement!Q101 -> 0.83174673 | H33: =H8/H6 -> 0.827 | I33: =I8/I6 -> 0.832 | J33: =J8/J6 -> 0.853 | K33: =K8/K6 -> 0.858 | L33: =L8/L6 -> 0.873
B34: Operating margin | C34: =Statement!M102 -> -0.56144004 | D34: =Statement!N102 -> -0.32900931 | E34: =Statement!O102 -> -0.12592579 | F34: =Statement!P102 -> -0.11371133 | G34: =Statement!Q102 -> 0.035242138 | H34: =H10/H6 -> 0.057 | I34: =I10/I6 -> 0.062 | J34: =J10/J6 -> 0.118 | K34: =K10/K6 -> 0.128 | L34: =L10/L6 -> 0.173

Sheet Valuation ->
H5: Links
H6: Overview'!B3
H7: Financials ->'!B13
H8: Analysis ->'!B13
H9: Forecast ->'!B13
H10: Valuation ->'!B13
B13: Valuation ->

Sheet WACC
B1: WACC
B4: Inputs
B5: Shares Outstanding | C5: =Statement!AC78 -> 524515
B6: Price | C6: =Overview!C5 -> 13.325
B7: Equity | C7: =C5*C6 -> 6989162.4
B8: Debt | C8: =Statement!AC108 -> 0
B9: Risk free rate | C9: =Overview!F27 -> 0.05244
B10: Beta | C10: =Overview!C13 -> 1.063
B11: Market risk premium | C11: =[1]Sheet1!$C$12 -> 0.045
B12: Tax rate | C12: =Overview!C26 -> 0.21
B13: Cost of debt | C13: =Overview!C27 -> 0
B15: Calculations
B16: Debt/(Debt+Equity) | C16: =C8/(C8+C7) -> 0
B17: Equity/(Debt+Equity) | C17: =C7/(C8+C7) -> 1
B18: Cost of debt with tax | C18: =C13*(1-C12) -> 0
B19: Cost of equity | C19: =C9+C10*C11 -> 0.100275
B20: WACC | C20: =(C17*C19)+(C16*C18) -> 0.100275

Sheet DCF
B1: DCF
C3: History | H3: Forecast
C5: PV of FCF
B6: $ (thousand) | C6: =Revenue!C5 -> 2022 | D6: =Revenue!D5 -> 2023 | E6: =Revenue!E5 -> 2024 | F6: =Revenue!F5 -> 2025 | G6: =Revenue!G5 -> 2026 | H6: =Revenue!H5 -> 2027 | I6: =Revenue!I5 -> 2028 | J6: =Revenue!J5 -> 2029 | ... L6: =Revenue!L5 -> 2031
B7: FCFF | C7: ='FCF & Other'!C28 -> -603972 | D7: ='FCF & Other'!D28 -> -500062 | E7: ='FCF & Other'!E28 -> -216393 | F7: ='FCF & Other'!F28 -> -202032 | G7: ='FCF & Other'!G28 -> -94526 | H7: ='FCF & Other'!H28 -> -22589.658 | I7: ='FCF & Other'!I28 -> -20023.486 | J7: ='FCF & Other'!J28 -> 63633.803 | ... L7: ='FCF & Other'!L28 -> 199738.8
B8: Perpetual cashflow | C8: 0 | D8: 0 | E8: 0 | F8: 0 | G8: 0 | H8: 0 | I8: 0 | J8: 0 | K8: 0 | L8: =L7*(1+C14)/(C15-C14) -> 2546669.8
B9: Period | H9: 1 | I9: 2 | J9: 3 | K9: 4 | L9: 5
B10: PV of FCFF | H10: =H7/(1+$C$15)^H9 -> -20536.053 | I10: =I7/(1+$C$15)^I9 -> -16548.336 | J10: =J7/(1+$C$15)^J9 -> 47809.018 | K10: =K7/(1+$C$15)^K9 -> 71613.31 | L10: =L7/(1+$C$15)^L9 -> 124022.08
B11: PV of Perpetual cashflow | L11: =L8/(1+C15)^L9 -> 1581281.6
B13: Input parameters
B14: Perpetual growth | C14: 0.02
B15: WACC | C15: =IF(Overview!C28>0,Overview!C28,WACC!C20) -> 0.1
B18: Result
B19: Total PV of Unlevered FCF | C19: =SUM(H10:L10) -> 206360.02
B20: PV of Perpetual cashflow | C20: =L11 -> 1581281.6
B21: Enterprise value | C21: =C19+C20 -> 1787641.6
B22: (+) Cash | C22: =Statement!AC107 -> 1405025
B23: (-) Debt | C23: =Statement!AC108 -> 0
B24: Equity value | C24: =C21+C22-C23 -> 3192666.6
B25: Shares outstanding | C25: =Statement!AC78 -> 524515
B26: Price per share | C26: =C24/C25 -> 6.0868928

Sheet Multiples
B1: Multiples valuations
C2: History | H2: Forecast
C4: Revenues, earnings cash
B5: Revenues (thousand) | C5: =Revenue!C5 -> 2022 | D5: =Revenue!D5 -> 2023 | E5: =Revenue!E5 -> 2024 | F5: =Revenue!F5 -> 2025 | G5: =Revenue!G5 -> 2026 | H5: =Revenue!H5 -> 2027 | I5: =Revenue!I5 -> 2028 | J5: =Revenue!J5 -> 2029 | ... L5: =Revenue!L5 -> 2031
B6: Revenue | C6: =Revenue!C9 -> 892252 | D6: =Revenue!D9 -> 1058581 | E6: =Revenue!E9 -> 1308072 | F6: =Revenue!F9 -> 1429664 | G6: =Revenue!G9 -> 1610572 | H6: =Revenue!H9 -> 1790684 | I6: =Revenue!I9 -> 1948364.4 | J6: =Revenue!J9 -> 2141616.2 | ... L6: =Revenue!L9 -> 2473527.4
B7: EBIT | C7: ='FCF & Other'!C10 -> -500946 | D7: ='FCF & Other'!D10 -> -348283 | E7: ='FCF & Other'!E10 -> -164720 | F7: ='FCF & Other'!F10 -> -162569 | G7: ='FCF & Other'!G10 -> 56760 | H7: ='FCF & Other'!H10 -> 102068.99 | I7: ='FCF & Other'!I10 -> 120798.59 | J7: ='FCF & Other'!J10 -> 252710.71 | ... L7: ='FCF & Other'!L10 -> 427920.25
B8: FCFF | C8: ='FCF & Other'!C28 -> -603972 | D8: ='FCF & Other'!D28 -> -500062 | E8: ='FCF & Other'!E28 -> -216393 | F8: ='FCF & Other'!F28 -> -202032 | G8: ='FCF & Other'!G28 -> -94526 | H8: ='FCF & Other'!H28 -> -22589.658 | I8: ='FCF & Other'!I28 -> -20023.486 | J8: ='FCF & Other'!J28 -> 63633.803 | ... L8: ='FCF & Other'!L28 -> 199738.8
B9: PV of FCFF | H9: =DCF!H10 -> -20536.053 | I9: =DCF!I10 -> -16548.336 | J9: =DCF!J10 -> 47809.018 | K9: =DCF!K10 -> 71613.31 | L9: =DCF!L10 -> 124022.08
C11: Growth rates
B12: % Growth | C12: =C5 -> 2022 | D12: =D5 -> 2023 | E12: =E5 -> 2024 | F12: =F5 -> 2025 | G12: =G5 -> 2026 | H12: =H5 -> 2027 | I12: =I5 -> 2028 | J12: =J5 -> 2029 | ... L12: =L5 -> 2031
B13: Revenue | D13: =(D6-C6)/C6 -> 0.18641482 | E13: =(E6-D6)/D6 -> 0.23568437 | F13: =(F6-E6)/E6 -> 0.092955128 | G13: =(G6-F6)/F6 -> 0.12653882 | H13: =(H6-G6)/G6 -> 0.11183108 | I13: =(I6-H6)/H6 -> 0.088055961 | J13: =(J6-I6)/I6 -> 0.099186675 | K13: =(K6-J6)/J6 -> 0.075233822 | L13: =(L6-K6)/K6 -> 0.074167916
B14: EBIT | D14: =IF(C7=0, IF(D7=0,0,IF(D7>0,1,-1)), (D7-C7)/ABS(C7) ) -> 0.30474941 | E14: =IF(D7=0, IF(E7=0,0,IF(E7>0,1,-1)), (E7-D7)/ABS(D7) ) -> 0.52705128 | F14: =IF(E7=0, IF(F7=0,0,IF(F7>0,1,-1)), (F7-E7)/ABS(E7) ) -> 0.013058524 | G14: =IF(F7=0, IF(G7=0,0,IF(G7>0,1,-1)), (G7-F7)/ABS(F7) ) -> 1.3491441 | H14: =IF(G7=0, IF(H7=0,0,IF(H7>0,1,-1)), (H7-G7)/ABS(G7) ) -> 0.7982556 | I14: =IF(H7=0, IF(I7=0,0,IF(I7>0,1,-1)), (I7-H7)/ABS(H7) ) -> 0.18349947 | J14: =IF(I7=0, IF(J7=0,0,IF(J7>0,1,-1)), (J7-I7)/ABS(I7) ) -> 1.0920004 | K14: =IF(J7=0, IF(K7=0,0,IF(K7>0,1,-1)), (K7-J7)/ABS(J7) ) -> 0.16635533 | L14: =IF(K7=0, IF(L7=0,0,IF(L7>0,1,-1)), (L7-K7)/ABS(K7) ) -> 0.45180507
B15: FCFF | D15: =IF(C8=0, IF(D8=0,0,IF(D8>0,1,-1)), (D8-C8)/ABS(C8) ) -> 0.1720444 | E15: =IF(D8=0, IF(E8=0,0,IF(E8>0,1,-1)), (E8-D8)/ABS(D8) ) -> 0.56726766 | F15: =IF(E8=0, IF(F8=0,0,IF(F8>0,1,-1)), (F8-E8)/ABS(E8) ) -> 0.066365363 | G15: =IF(F8=0, IF(G8=0,0,IF(G8>0,1,-1)), (G8-F8)/ABS(F8) ) -> 0.53212362 | H15: =IF(G8=0, IF(H8=0,0,IF(H8>0,1,-1)), (H8-G8)/ABS(G8) ) -> 0.76102175 | I15: =IF(H8=0, IF(I8=0,0,IF(I8>0,1,-1)), (I8-H8)/ABS(H8) ) -> 0.1135994 | J15: =IF(I8=0, IF(J8=0,0,IF(J8>0,1,-1)), (J8-I8)/ABS(I8) ) -> 4.1779582 | K15: =IF(J8=0, IF(K8=0,0,IF(K8>0,1,-1)), (K8-J8)/ABS(J8) ) -> 0.64769417 | L15: =IF(K8=0, IF(L8=0,0,IF(L8>0,1,-1)), (L8-K8)/ABS(K8) ) -> 0.90501307
C17: Shares
C18: =C5 -> 2022 | D18: =D5 -> 2023 | E18: =E5 -> 2024 | F18: =F5 -> 2025 | G18: =G5 -> 2026 | H18: =H5 -> 2027 | I18: =I5 -> 2028 | J18: =J5 -> 2029 | ... L18: =L5 -> 2031
B19: Avg diluted shares | C19: =Statement!M22 -> 454625 | D19: =Statement!N22 -> 548022 | E19: =Statement!O22 -> 653855 | F19: =Statement!P22 -> 559933 | G19: =Statement!Q22 -> 544860 | H19: =G19*(1+H20) -> 528514.2 | I19: =H19*(1+I20) -> 512658.77 | J19: =I19*(1+J20) -> 502405.6 | K19: =J19*(1+K20) -> 492357.49 | L19: =K19*(1+L20) -> 482510.34
B20: Dilution rate | D20: =D19/C19-1 -> 0.20543745 | E20: =E19/D19-1 -> 0.19311816 | F20: =F19/E19-1 -> -0.14364347 | G20: =G19/F19-1 -> -0.026919292 | H20: -0.03 | I20: -0.03 | J20: -0.02 | K20: -0.02 | L20: -0.02
C22: Historical price
C23: =C5 -> 2022 | D23: =D5 -> 2023 | E23: =E5 -> 2024 | F23: =F5 -> 2025 | G23: =G5 -> 2026 | H23: =H5 -> 2027 | I23: =I5 -> 2028 | J23: =J5 -> 2029 | ... L23: =L5 -> 2031
B24: Price | C24: =Statement!M116 -> 33.43 | D24: =Statement!N116 -> 14.57 | E24: =Statement!O116 -> 23.85 | F24: =Statement!P116 -> 14.58 | G24: =Statement!Q116 -> 12.59
C27: Historical ratios
C28: =C5 -> 2022 | D28: =D5 -> 2023 | E28: =E5 -> 2024 | F28: =F5 -> 2025 | G28: =G5 -> 2026 | H28: =H5 -> 2027 | I28: =I5 -> 2028 | J28: =J5 -> 2029 | ... L28: =L5 -> 2031
B29: PS | C29: =C24/(C6/C19) -> 17.033432 | D29: =D24/(D6/D19) -> 7.5428149 | E29: =E24/(E6/E19) -> 11.9217 | F29: =F24/(F6/F19) -> 5.710309 | G29: =G24/(G6/G19) -> 4.2592243
B30: Market Cap | C30: =C24*C19 -> 15198114 | D30: =D24*D19 -> 7984680.5 | E30: =E24*E19 -> 15594442 | F30: =F24*F19 -> 8163823.1 | G30: =G24*G19 -> 6859787.4
B31: Debt | C31: =Statement!M108 -> 0 | D31: =Statement!N108 -> 0 | E31: =Statement!O108 -> 0 | F31: =Statement!P108 -> 0 | G31: =Statement!Q108 -> 0
B32: Cash | C32: =Statement!M107 -> 1884663 | D32: =Statement!N107 -> 1759835 | E32: =Statement!O107 -> 1879823 | F32: =Statement!P107 -> 1723631 | G32: =Statement!Q107 -> 1689476
B33: EV | C33: =C30+C31-C32 -> 13313451 | D33: =D30+D31-D32 -> 6224845.5 | E33: =E30+E31-E32 -> 13714619 | F33: =F30+F31-F32 -> 6440192.1 | G33: =G30+G31-G32 -> 5170311.4
B34: EV/EBIT | C34: =C33/C7 -> -26.576619 | D34: =D33/D7 -> -17.872953 | E34: =E33/E7 -> -83.260192 | F34: =F33/F7 -> -39.61513 | G34: =G33/G7 -> 91.090758
B35: EV/FCFF | C35: =C33/C8 -> -22.043159 | D35: =D33/D8 -> -12.448148 | E35: =E33/E8 -> -63.378292 | F35: =F33/F8 -> -31.877089 | G35: =G33/G8 -> -54.697241
B36: EV/Sales | C36: =C33/C6 -> 14.921178 | D36: =D33/D6 -> 5.8803677 | E36: =E33/E6 -> 10.484605 | F36: =F33/F6 -> 4.5046893 | G36: =G33/G6 -> 3.210233
B39: EV/EBIT valuation
B40: Year 5 EBIT | C40: =L7 -> 427920.25
B41: WACC | C41: =IF(Overview!C28>0,Overview!C28,WACC!C20) -> 0.1
B42: Applied EV/EBIT ratio | C42: 25
B43: Terminal EV | C43: =(C40*C42) -> 10698006
B44: PV of Terminal EV | C44: =C43/(1+C41)^5 -> 6642620.2
B45: Total EV | C45: =SUM(H9:K9)+C44 -> 6724958.1
B46: (+) Cash | C46: =Statement!AC107 -> 1405025
B47: (-) Debt | C47: =Statement!AC108 -> 0
B48: Equity value | C48: =C45+C46-C47 -> 8129983.1
B49: Shares outstanding | C49: =Statement!AC78 -> 524515
B50: PV of price per share | C50: =C48/C49 -> 15.500001
B52: PS valuation
B53: Year 5 sales | C53: =L6 -> 2473527.4
B54: Discount rate | C54: =IF(Overview!C29>0,Overview!C29,WACC!C19) -> 0.12
B55: Applied PS ratio | C55: 4
B56: Shares outstanding diluted | C56: =L19 -> 482510.34
B57: Price per share | C57: =(C53*C55)/C56 -> 20.505488
B58: PV of price per share | C58: =C57/(1+C54)^5 -> 11.635364
B60: EV/FCFF valuation
B61: Year 5 FCFF | C61: =L8 -> 199738.8
B62: WACC | C62: =IF(Overview!C28>0,Overview!C28,WACC!C20) -> 0.1
B63: Applied EV/FCFF ratio | C63: 30
B64: Terminal EV | C64: =(C61*C63) -> 5992164.1
B65: PV of Terminal EV | C65: =C64/(1+C62)^5 -> 3720662.5
B66: Total EV | C66: =SUM(H9:K9)+C65 -> 3803000.4
B67: (+) Cash | C67: =Statement!AC107 -> 1405025
B68: (-) Debt | C68: =Statement!AC108 -> 0
B69: Equity value | C69: =C66+C67-C68 -> 5208025.4
B70: Shares outstanding | C70: =Statement!AC78 -> 524515
B71: PV of price per share | C71: =C69/C70 -> 9.9292211
B73: EV/Sales valuation
B74: Year 5 Sales | C74: =L6 -> 2473527.4
B75: WACC | C75: =IF(Overview!C28>0,Overview!C28,WACC!C20) -> 0.1
B76: Applied EV/Sales ratio | C76: 3
B77: Terminal EV | C77: =(C74*C76) -> 7420582.3
B78: PV of Terminal EV | C78: =C77/(1+C75)^5 -> 4607597.8
B79: Total EV | C79: =SUM(H9:K9)+C78 -> 4689935.7
B80: (+) Cash | C80: =Statement!AC107 -> 1405025
B81: (-) Debt | C81: =Statement!AC108 -> 0
B82: Equity value | C82: =C79+C80-C81 -> 6094960.7
B83: Shares outstanding | C83: =Statement!AC78 -> 524515
B84: PV of price per share | C84: =C82/C83 -> 11.620184

Sheet AVG target price
B1: AVG target price
B4: AVG target price
B5: DCF price | C5: =DCF!C26 -> 6.0868928
B6: EV/EBIT price | C6: =Multiples!C50 -> 15.500001
B7: PS price | C7: =Multiples!C58 -> 11.635364
B8: EV/FCFF price | C8: =Multiples!C71 -> 9.9292211
B9: EV/Sales | C9: =Multiples!C84 -> 11.620184
B10: AVG price | C10: =AVERAGE(C5:C9) -> 10.954333
B11: Current price | C11: =Overview!C5 -> 13.325
B12: Upside/Downside | C12: =(C10-C11)/C11 -> -0.17791124

Sheet DDM
B1: Dividend discount model
C2: History | H2: Forecast
C4: Revenues, earnings cash
B5: Revenues (thousand) | C5: =[2]Revenue!C5 -> 2021 | D5: =[2]Revenue!D5 -> 2022 | E5: =[2]Revenue!E5 -> 2023 | F5: =[2]Revenue!F5 -> 2024 | G5: =[2]Revenue!G5 -> 2025 | H5: =[2]Revenue!H5 -> 2026 | I5: =[2]Revenue!I5 -> 2027 | J5: =[2]Revenue!J5 -> 2028 | ... L5: =[2]Revenue!L5 -> 2030
B6: EPS | C6: =Statement!M26 -> -1.16 | D6: =Statement!N26 -> -0.6 | E6: =Statement!O26 -> -0.16 | F6: =Statement!P26 -> -0.13 | G6: =Statement!Q26 -> 0.52
B7: Dividend per share | C7: =Statement!M82 -> 0 | D7: =Statement!N82 -> 0 | E7: =Statement!O82 -> 0 | F7: =Statement!P82 -> 0 | G7: =Statement!Q82 -> 0
C9: Growth rates
B10: % Growth | C10: =C5 -> 2021 | D10: =D5 -> 2022 | E10: =E5 -> 2023 | F10: =F5 -> 2024 | G10: =G5 -> 2025 | H10: =H5 -> 2026 | I10: =I5 -> 2027 | J10: =J5 -> 2028 | ... L10: =L5 -> 2030
B11: EPS | D11: =(D6-C6)/C6 -> -0.48275862 | E11: =(E6-D6)/D6 -> -0.73333333 | F11: =(F6-E6)/E6 -> -0.1875 | G11: =(G6-F6)/F6 -> -5
B12: Dividend | D12: =IF(C7=0, IF(D7=0,0,IF(D7>0,1,-1)), (D7-C7)/ABS(C7) ) -> 0 | E12: =IF(D7=0, IF(E7=0,0,IF(E7>0,1,-1)), (E7-D7)/ABS(D7) ) -> 0 | F12: =IF(E7=0, IF(F7=0,0,IF(F7>0,1,-1)), (F7-E7)/ABS(E7) ) -> 0 | G12: =IF(F7=0, IF(G7=0,0,IF(G7>0,1,-1)), (G7-F7)/ABS(F7) ) -> 0
C14: Ratios
B15: % | C15: =C5 -> 2021 | D15: =D5 -> 2022 | E15: =E5 -> 2023 | F15: =F5 -> 2024 | G15: =G5 -> 2025 | H15: =H5 -> 2026 | I15: =I5 -> 2027 | J15: =J5 -> 2028 | ... L15: =L5 -> 2030
B16: Payout | C16: =C7/C6 -> 0 | D16: =D7/D6 -> 0 | E16: =E7/E6 -> 0 | F16: =F7/F6 -> 0 | G16: =G7/G6 -> 0
B20: DDM valuation
B21: Latest dividend | C21: =G7 -> 0
B22: Year 1 growth rate | C22: 0
B23: Year 1 dividend | C23: =C21*(1+C22) -> 0
B24: Discount rate | C24: =IF(Overview!C29>0,Overview!C29,WACC!C19) -> 0.12
B25: Perpetual dividend growth | C25: 0
B26: PV of price per share | C26: =C23/(C24-C25) -> 0

Sheet Reverse DCF
B1: Reverse DCF
C3: History | H3: Forecast
C5: PV of FCF
B6: $ (thousand) | C6: =Revenue!C5 -> 2022 | D6: =Revenue!D5 -> 2023 | E6: =Revenue!E5 -> 2024 | F6: =Revenue!F5 -> 2025 | G6: =Revenue!G5 -> 2026 | H6: =Revenue!H5 -> 2027 | I6: =Revenue!I5 -> 2028 | J6: =Revenue!J5 -> 2029 | ... L6: =Revenue!L5 -> 2031
B7: FCFF | C7: ='FCF & Other'!C28 -> -603972 | D7: ='FCF & Other'!D28 -> -500062 | E7: ='FCF & Other'!E28 -> -216393 | F7: ='FCF & Other'!F28 -> -202032 | G7: 8000 | H7: =G7*(1+$C$17) -> 19200 | I7: =H7*(1+$C$17) -> 46080 | J7: =I7*(1+$C$17) -> 110592 | K7: =J7*(1+$C$17) -> 265420.8 | L7: =K7*(1+$C$17) -> 637009.92
B8: Perpetual cashflow | L8: =L7*(1+C20)/(C21-C20) -> 8121876.5
B9: Period | H9: 1 | I9: 2 | J9: 3 | K9: 4 | L9: 5
B10: PV of FCFF | H10: =H7/(1+$C$21)^H9 -> 17454.545 | I10: =I7/(1+$C$21)^I9 -> 38082.645 | J10: =J7/(1+$C$21)^J9 -> 83089.406 | K10: =K7/(1+$C$21)^K9 -> 181285.98 | L10: =L7/(1+$C$21)^L9 -> 395533.04
B11: PV of Perpetual cashflow | L11: =L8/(1+C21)^L9 -> 5043046.3
B14: Growth adjustment
B15: Current Price | C15: =Overview!C5 -> 13.325
B16: Calculated Price | C16: =C36 -> 13.745437
B17: FCFF Growth | C17: 1.4 | E17: Modify until Calculated Price is very close to Current Price
B19: Input parameters
B20: Perpetual growth | C20: 0.02
B21: WACC | C21: =IF(Overview!C28>0,Overview!C28,WACC!C20) -> 0.1
B22: Shares outstanding | C22: =Statement!AC75 -> 521156
B23: Market cap | C23: =C15*C22 -> 6944403.7
B24: Cash | C24: =Statement!AC107 -> 1405025
B25: Debt | C25: =Statement!AC108 -> 0
B26: Enterprise Value | C26: =C23+C25-C24 -> 5539378.7
B28: Result
B29: Total PV of Unlevered FCF | C29: =SUM(H10:L10) -> 715445.62
B30: PV of Perpetual cashflow | C30: =L11 -> 5043046.3
B31: Enterprise value | C31: =C29+C30 -> 5758491.9
B32: (+) Cash | C32: =C24 -> 1405025
B33: (-) Debt | C33: =C25 -> 0
B34: Equity value | C34: =C31+C32-C33 -> 7163516.9
B35: Shares outstanding | C35: =C22 -> 521156
B36: Price per share | C36: =C34/C35 -> 13.745437
