Workbook

Sheet Overview
B2: Automatic Data | E2: At a glance | H2: Valuation | K2: Links
B3: Company | C3: #VALUE! | E3: Market capitalization | F3: =Statement!AC153 -> 816194.86 | H3: ='AVG target price'!B5 -> DCF price | I3: ='AVG target price'!C5 -> 11.213353 | K3: Financials ->'!B13
B4: Ticker | C4: {=_FV(C3,"Ticker symbol",TRUE)} -> PHR | E4: Enterprise value | F4: =Statement!AC154 -> 809695.86 | H4: ='AVG target price'!B6 -> EV/EBIT price | I4: ='AVG target price'!C6 -> 17.829749 | K4: Analysis ->'!B13
B5: Price | C5: {=_FV(C3,"Price",TRUE)} -> 12.61 | E5: EPS | F5: =Statement!AC28 -> -0.017861847 | H5: ='AVG target price'!B7 -> PS price | I5: ='AVG target price'!C7 -> 17.048124 | K5: Forecast ->'!B13
B6: Price Extended Hours | C6: {=_FV(C3,"Price (Extended hours)",TRUE)} -> 12.59 | E6: PE | F6: =Statement!AC150 -> -705.97403 | H6: ='AVG target price'!B8 -> EV/FCFF price | I6: ='AVG target price'!C8 -> 14.29173 | K6: Valuation ->'!B13
B7: Day change | C7: {=_FV(C3,"Change")} -> -0.09 | E7: PS | F7: =Statement!AC151 -> 1.5369177 | H7: ='AVG target price'!B9 -> EV/Sales price | I7: ='AVG target price'!C9 -> 25.875822
B8: Day change extended | C8: {=_FV(C3,"Change (extended hours)",TRUE)} -> -0.02 | E8: FCF Yield | F8: =Statement!AC161 -> 0.0099191999 | H8: ='AVG target price'!B10 -> AVG price | I8: ='AVG target price'!C10 -> 17.251756
B9: Day change % | C9: {=_FV(C3,"Change (%)",TRUE)} -> -0.007087 | E9: Earnings Yield | F9: =Statement!AC162 -> -0.0014164827 | H9: ='AVG target price'!B12 -> Upside/Downside | I9: ='AVG target price'!C12 -> 0.36810118
B10: Day change extended % | C10: {=_FV(C3,"Change % (extended hours)",TRUE)} -> -0.001586 | E10: Buyback Yield | F10: =Statement!AC164 -> 0
B11: 52 week high | C11: {=_FV(C3,"52 week high",TRUE)} -> 23.8651 | E11: Dividend Yield | F11: =Statement!AC163 -> 0 | H11: DDM price | I11: =DDM!C26 -> 0
B12: 52 week low | C12: {=_FV(C3,"52 week low",TRUE)} -> 7.77 | E12: ROA | F12: =Statement!AC127 -> -0.0018099561
B13: Beta | C13: {=_FV(C3,"Beta")} -> 0.7583 | E13: ROE | F13: =Statement!AC129 -> -0.0031491108 | H13: Reverse DCF rate | I13: ='Reverse DCF'!C17 -> 0.45
B14: Avg volume | C14: {=_FV(C3,"Volume average",TRUE)} -> 679066 | E14: ROIC | F14: =Statement!AC140 -> -0.014540196 | H14: Reverse DCF price | I14: ='Reverse DCF'!C16 -> 11.046079
E15: Net Cash/Market Cap | F15: =Statement!AC176 -> 0.0079625593
E16: Net Cash/Share | F16: =Statement!AC175 -> 0.10470268 | H16: Discount rates used
B17: Unit data and other info | E17: Insider Ownership | F17: =Statement!AC171 -> 0.050026265 | H17: WACC | I17: =DCF!C15 -> 0.081545315
B18: Units | C18: K | E18: Net Trade Cycle | F18: =Statement!AC144 -> 37.184518 | H18: Cost of Equity | I18: =Multiples!C54 -> 0.0840035
B19: Units conversion | C19: 1000 | E19: Net Debt/Equity | F19: =Statement!AC146 -> -0.01747743
B20: Has operating lease | C20: Yes | E20: Quick Ratio | F20: =Statement!AC147 -> 1.1287308
B21: Has finance lease | C21: Yes
B22: Has debt | C22: Yes
B25: Constants | E25: 10 Year Bond Yield
B26: Default tax rate | C26: 0.21 | E26: #VALUE! | F26: {=_FV(E26,"Price")} -> 49.88
B27: Cost of debt | C27: 0.065 | E27: Percentage | F27: =F26/1000 -> 0.04988
B28: Manual WACC | C28: 0
B29: Manual Cost of Equity | C29: 0
B33: Info
B35: Mission: | C35: Address 3 challenges in healthcare: access to care, affordability of care, health patient outcomes
B36: Auditor: | C36: KPMG
B42: Notes
B44: Date: | C44: 30.03.2026 | E44: Q4 2026
B45: - | C45: Revenue outlook for FY 2027 will be in the range 510-520 million
B46: - | C46: Network solution clients commiting lower spend levels for second half of fiscal 2027
B47: - | C47: AccessOne will contribute about 37 million to the total revenue range
B48: - | C48: Adjusted EBITDA in the range 125 to 135 million
B49: - | C49: AHSC growth in the mid single digit percentage range
B50: - | C50: Total revenue per AHSC in low single digit percentage range
B51: - | C51: TAM of 24B
B52: - | C52: It is expected that subscription growth will be slower than the other 2 revenue streams
B53: - | C53: Got a $250k revolving credit maturing on 13.03.2031
B58: Adjustments
B60: Date: | C60: 31.01.2026 | E60: FY 2026
B61: - | C61: Tax expense/benefit + income | E61: Take out the 11618 tax benefit since it is a one time accounting adjustment and adjust all net incomes
B63: Date: | C63: 31.01.2026 | E63: Q4 2026
B64: - | C64: Tax expense/benefit + income | E64: Take out the 11618 tax benefit since it is a one time accounting adjustment and adjust all net incomes

Sheet Financials ->
H5: Links
H6: Overview'!B3
H7: Financials ->'!B13
H8: Analysis ->'!B13
H9: Forecast ->'!B13
H10: Valuation ->'!B13
B13: Financials ->

Sheet Statement
B2: Date | M2: 31.01.2022 | N2: 31.01.2023 | O2: 31.01.2024 | P2: 31.01.2025 | Q2: 31.01.2026 | T2: 31.10.2024 | U2: 31.01.2025 | V2: 30.04.2025 | W2: 31.07.2025 | X2: 31.10.2025 | Y2: 31.01.2026 | Z2: 30.04.2026 | AA2: 31.07.2026
B3: FY | M3: 2022 | N3: 2023 | O3: 2024 | P3: 2025 | Q3: 2026 | T3: Q3 2025 | U3: Q4 2025 | V3: Q1 2026 | W3: Q2 2026 | X3: Q3 2026 | Y3: Q4 2026 | Z3: Q1 2027 | AA3: Q2 2027 | AC3: TTM/YTD
B4: Income statement
B5: Revenue | M5: 213233 | N5: 280910 | O5: 356299 | P5: 419813 | Q5: 480591 | T5: 106800 | U5: 109681 | V5: 115936 | W5: 117255 | X5: 120333 | Y5: 127067 | Z5: 130935 | AA5: 129458 | AC5: =SUM(X5:AA5) -> 507793
B6: COGS | M6: 81388 | N6: 109267 | O6: 124011 | P6: 134934 | Q6: 154123 | T6: 34537 | U6: 33566 | V6: 38065 | W6: 37641 | X6: 38027 | Y6: 40390 | Z6: =17659+25675 -> 43334 | AA6: =19271+23914 -> 43185 | AC6: =SUM(X6:AA6) -> 164936
B7: Gross Profit | C7: =C5-C6 -> 0 | D7: =D5-D6 -> 0 | E7: =E5-E6 -> 0 | F7: =F5-F6 -> 0 | G7: =G5-G6 -> 0 | H7: =H5-H6 -> 0 | I7: =I5-I6 -> 0 | J7: =J5-J6 -> 0 | ... Q7: =Q5-Q6 -> 326468 | T7: =T5-T6 -> 72263 | U7: =U5-U6 -> 76115 | V7: =V5-V6 -> 77871 | W7: =W5-W6 -> 79614 | X7: =X5-X6 -> 82306 | Y7: =Y5-Y6 -> 86677 | Z7: =Z5-Z6 -> 87601 | AA7: =AA5-AA6 -> 86273 | AC7: =SUM(X7:AA7) -> 342857
B8: Sales and marketing | M8: 106421 | N8: 151263 | O8: 147008 | P8: 121129 | Q8: 100243 | T8: 30071 | U8: 28863 | V8: 26043 | W8: 25396 | X8: 24148 | Y8: 24656 | Z8: 24209 | AA8: 24587 | AC8: =SUM(X8:AA8) -> 97600
B9: R&D | M9: 52265 | N9: 91244 | O9: 112346 | P9: 117364 | Q9: 121481 | T9: 29315 | U9: 29626 | V9: 31829 | W9: 29274 | X9: 29453 | Y9: 30925 | Z9: 28328 | AA9: 27571 | AC9: =SUM(X9:AA9) -> 116277
B10: General and administrative | M10: 68674 | N10: 80384 | O10: 79926 | P10: 76597 | Q10: 79903 | T10: 19633 | U10: 18415 | V10: 16408 | W10: 19042 | X10: 17488 | Y10: 26965 | Z10: 18361 | AA10: 16512 | AC10: =SUM(X10:AA10) -> 79326
B11: Depreciation | M11: 14985 | N11: 17988 | O11: 17584 | P11: 14183 | Q11: 12972 | T11: 3566 | U11: 3172 | V11: 2986 | W11: 3279 | X11: 3199 | Y11: 3508 | Z11: 3371 | AA11: 3340 | AC11: =SUM(X11:AA11) -> 13418
B12: Amortization | M12: 6317 | N12: 7316 | O12: 11903 | P12: 13703 | Q12: 18481 | T12: 3521 | U12: 3651 | V12: 3892 | W12: 4130 | X12: 4279 | Y12: 6180 | Z12: 6583 | AA12: 6655 | AC12: =SUM(X12:AA12) -> 23697
B13: OpEx | C13: =SUM(C8:C12) -> 0 | D13: =SUM(D8:D12) -> 0 | E13: =SUM(E8:E12) -> 0 | F13: =SUM(F8:F12) -> 0 | G13: =SUM(G8:G12) -> 0 | H13: =SUM(H8:H12) -> 0 | I13: =SUM(I8:I12) -> 0 | J13: =SUM(J8:J12) -> 0 | ... Q13: =SUM(Q8:Q12) -> 333080 | T13: =SUM(T8:T12) -> 86106 | U13: =SUM(U8:U12) -> 83727 | V13: =SUM(V8:V12) -> 81158 | W13: =SUM(W8:W12) -> 81121 | X13: =SUM(X8:X12) -> 78567 | Y13: =SUM(Y8:Y12) -> 92234 | Z13: =SUM(Z8:Z12) -> 80852 | AA13: =SUM(AA8:AA12) -> 78665 | AC13: =SUM(X13:AA13) -> 330318
B14: Operating income | M14: -116817 | N14: -176552 | O14: -136479 | P14: -58097 | Q14: -6612 | T14: -13843 | U14: -7612 | V14: -3287 | W14: -1507 | X14: 3739 | Y14: -5557 | Z14: 6749 | AA14: 7608 | AC14: =SUM(X14:AA14) -> 12539
B15: Interest income/expense | M15: -1084 | N15: 1064 | O15: 2211 | P15: 330 | Q15: =2173-6953 -> -4780 | T15: 26 | U15: 19 | V15: -230 | W15: 608 | X15: 380 | Y15: =269-5807 -> -5538 | Z15: =-2299+297 -> -2002 | AA15: =-1729+248 -> -1481 | AC15: =SUM(X15:AA15) -> -8641
B16: Other income/expense | M16: -78 | N16: -175 | O16: =44-1118 -> -1074 | P16: 1956 | Q16: =2953-501 -> 2452 | T16: -144 | U16: 2217 | V16: 338 | W16: 336 | X16: 1006 | Y16: =1273-501 -> 772 | Z16: -24 | AA16: -2888 | AC16: =SUM(X16:AA16) -> -1134
B17: Income before taxes | M17: -117979 | N17: -175663 | O17: -135342 | P17: -55811 | Q17: -8940 | T17: -13961 | U17: -5376 | V17: -3179 | W17: -563 | X17: 5125 | Y17: -10323 | Z17: 4723 | AA17: 3239 | AC17: =SUM(X17:AA17) -> 2764
B18: Income tax expense/benefit | M18: -182 | N18: -483 | O18: -1543 | P18: -2716 | Q18: -372 | T18: -442 | U18: -1014 | V18: -735 | W18: 1217 | X18: -854 | Y18: 0 | Z18: -1760 | AA18: -1321 | AC18: =SUM(X18:AA18) -> -3935
B19: Non-controlling interest | M19: 0 | N19: 0 | O19: 0 | P19: 0 | Q19: 0 | T19: 0 | U19: 0 | V19: 0 | W19: 0 | X19: 0 | Y19: 0 | Z19: 0 | AA19: 0 | AC19: =SUM(X19:AA19) -> 0
B20: Net income | M20: -118161 | N20: -176146 | O20: -136885 | P20: -58527 | Q20: -9312 | T20: -14403 | U20: -6390 | V20: -3914 | W20: 654 | X20: 4271 | Y20: -10323 | Z20: 2963 | AA20: 1918 | AC20: =SUM(X20:AA20) -> -1171
B21: Basic Shares outstanding avg | M21: 49888 | N21: 52440 | O21: 54561 | P21: 57590 | Q21: 59738 | T21: 57892 | U21: 58278 | V21: 58921 | W21: 59592 | X21: 60009 | Y21: 60404 | Z21: 60945 | AA21: 61878 | AC21: =AVERAGE(X21:AA21) -> 60809
B22: Basic Shares outstanding avg adjusted | C22: =C21*C$87 -> 0 | D22: =D21*D$87 -> 0 | E22: =E21*E$87 -> 0 | F22: =F21*F$87 -> 0 | G22: =G21*G$87 -> 0 | H22: =H21*H$87 -> 0 | I22: =I21*I$87 -> 0 | J22: =J21*J$87 -> 0 | ... Q22: =Q21*Q$87 -> 59738 | T22: =T21*T$87 -> 57892 | U22: =U21*U$87 -> 58278 | V22: =V21*V$87 -> 58921 | W22: =W21*W$87 -> 59592 | X22: =X21*X$87 -> 60009 | Y22: =Y21*Y$87 -> 60404 | Z22: =Z21*Z$87 -> 60945 | AA22: =AA21*AA$87 -> 61878 | AC22: =AC21*AC$87 -> 60809
B23: Diluted Shares outstanding avg | M23: 49888 | N23: 52440 | O23: 54561 | P23: 57590 | Q23: 61495 | T23: 57892 | U23: 58278 | V23: 58921 | W23: 61686 | X23: 61560 | Y23: 61497 | Z23: 62041 | AA23: 62463 | AC23: =AVERAGE(X23:AA23) -> 61890.25
B24: Diluted Shares outstanding avg adjusted | C24: =C23*C$87 -> 0 | D24: =D23*D$87 -> 0 | E24: =E23*E$87 -> 0 | F24: =F23*F$87 -> 0 | G24: =G23*G$87 -> 0 | H24: =H23*H$87 -> 0 | I24: =I23*I$87 -> 0 | J24: =J23*J$87 -> 0 | ... Q24: =Q23*Q$87 -> 61495 | T24: =T23*T$87 -> 57892 | U24: =U23*U$87 -> 58278 | V24: =V23*V$87 -> 58921 | W24: =W23*W$87 -> 61686 | X24: =X23*X$87 -> 61560 | Y24: =Y23*Y$87 -> 61497 | Z24: =Z23*Z$87 -> 62041 | AA24: =AA23*AA$87 -> 62463 | AC24: =AC23*AC$87 -> 61890.25
B25: Basic EPS | M25: -2.37 | N25: -3.36 | O25: -2.51 | P25: -1.02 | Q25: -0.16 | T25: -0.25 | U25: -0.11 | V25: -0.07 | W25: 0.01 | X25: 0.07 | Y25: -0.17089928 | Z25: 0.05 | AA25: 0.03 | AC25: =SUM(X25:AA25) -> -0.020899278
B26: Basic EPS adjusted | M26: =M25/M$87 -> -2.37 | N26: =N25/N$87 -> -3.36 | O26: =O25/O$87 -> -2.51 | P26: =P25/P$87 -> -1.02 | Q26: =Q25/Q$87 -> -0.16 | T26: =T25/T$87 -> -0.25 | U26: =U25/U$87 -> -0.11 | V26: =V25/V$87 -> -0.07 | W26: =W25/W$87 -> 0.01 | X26: =X25/X$87 -> 0.07 | Y26: =Y25/Y$87 -> -0.17089928 | Z26: =Z25/Z$87 -> 0.05 | AA26: =AA25/AA$87 -> 0.03 | AC26: =AC25/AC$87 -> -0.020899278
B27: Diluted EPS | M27: -2.37 | N27: -3.36 | O27: -2.51 | P27: -1.02 | Q27: -0.16 | T27: -0.25 | U27: -0.11 | V27: -0.07 | W27: 0.01 | X27: 0.07 | Y27: -0.16786185 | Z27: 0.05 | AA27: 0.03 | AC27: =SUM(X27:AA27) -> -0.017861847
B28: Diluted EPS adjusted | M28: =M27/M$87 -> -2.37 | N28: =N27/N$87 -> -3.36 | O28: =O27/O$87 -> -2.51 | P28: =P27/P$87 -> -1.02 | Q28: =Q27/Q$87 -> -0.16 | T28: =T27/T$87 -> -0.25 | U28: =U27/U$87 -> -0.11 | V28: =V27/V$87 -> -0.07 | W28: =W27/W$87 -> 0.01 | X28: =X27/X$87 -> 0.07 | Y28: =Y27/Y$87 -> -0.16786185 | Z28: =Z27/Z$87 -> 0.05 | AA28: =AA27/AA$87 -> 0.03 | AC28: =AC27/AC$87 -> -0.017861847
B30: Balance sheet
B31: Cash and cash equivalents | M31: 313812 | N31: 176683 | O31: 87520 | P31: 84220 | Q31: 73830 | T31: 81740 | U31: 84220 | V31: 90871 | W31: 98266 | X31: 106371 | Y31: 73830 | Z31: 74706 | AA31: 72945 | AC31: =AA31 -> 72945
B32: Acc receivable | M32: 40262 | N32: 51394 | O32: 64863 | P32: 73617 | Q32: 97453 | T32: 71408 | U32: 73617 | V32: 75099 | W32: 76842 | X32: 88257 | Y32: 97453 | Z32: 89607 | AA32: 89406 | AC32: =AA32 -> 89406
B33: Inventory | M33: 0 | N33: 0 | O33: 0 | P33: 0 | Q33: 0 | T33: 0 | U33: 0 | V33: 0 | W33: 0 | X33: 0 | Y33: 0 | Z33: 0 | AA33: 0 | AC33: =AA33 -> 0
B34: Current assets | M34: 386349 | N34: 262441 | O34: 195684 | P34: 203285 | Q34: 279843 | T34: 189573 | U34: 203285 | V34: 215409 | W34: 222641 | X34: 240906 | Y34: 279843 | Z34: 267251 | AA34: 253503 | AC34: =AA34 -> 253503
B35: PP&E | M35: =34645+17643 -> 52288 | N35: =21670+35150 -> 56820 | O35: =16902+46139 -> 63041 | P35: =23651+52763 -> 76414 | Q35: =20332+54270 -> 74602 | T35: =25973+51322 -> 77295 | U35: =23651+52763 -> 76414 | V35: =23492+53531 -> 77023 | W35: =22769+53881 -> 76650 | X35: =21111+54093 -> 75204 | Y35: =20332+54270 -> 74602 | Z35: =20568+54624 -> 75192 | AA35: =18122+54127 -> 72249 | AC35: =AA35 -> 72249
B36: Marketable securities and investments | M36: 0 | N36: 0 | O36: 0 | P36: 0 | Q36: 0 | T36: 0 | U36: 0 | V36: 0 | W36: 0 | X36: 0 | Y36: 0 | Z36: 0 | AA36: 0 | AC36: =AA36 -> 0
B37: Goodwill | M37: 33621 | N37: 33736 | O37: 75845 | P37: 75845 | Q37: 170064 | T37: 75845 | U37: 75845 | V37: 75845 | W37: 75845 | X37: 75845 | Y37: 170064 | Z37: 169513 | AA37: 171468 | AC37: =AA37 -> 171468
B38: Long term assets | M38: =M39-M34 -> 108127 | N38: =N39-N34 -> 107616 | O38: =O39-O34 -> 174642 | P38: =P39-P34 -> 185130 | Q38: =Q39-Q34 -> 383947 | T38: =T39-T34 -> 186130 | U38: =U39-U34 -> 185130 | V38: =V39-V34 -> 184986 | W38: =W39-W34 -> 185988 | X38: =X39-X34 -> 182566 | Y38: =Y39-Y34 -> 383947 | Z38: =Z39-Z34 -> 398890 | AA38: =AA39-AA34 -> 393474 | AC38: =AA38 -> 393474
B39: Total assets | M39: 494476 | N39: 370057 | O39: 370326 | P39: 388415 | Q39: 663790 | T39: 375703 | U39: 388415 | V39: 400395 | W39: 408629 | X39: 423472 | Y39: 663790 | Z39: 666141 | AA39: 646977 | AC39: =AA39 -> 646977
B40: Acc payable | M40: 5119 | N40: 10836 | O40: 8480 | P40: 5622 | Q40: 11477 | T40: 15870 | U40: 5622 | V40: 3204 | W40: 6527 | X40: 6218 | Y40: 11477 | Z40: 11891 | AA40: 12237 | AC40: =AA40 -> 12237
B41: Debt | M41: 5821 | N41: 5172 | O41: 6056 | P41: 8043 | Q41: 7971 | T41: 8866 | U41: 8043 | V41: 8348 | W41: 7096 | X41: 6199 | Y41: 7971 | Z41: 5301 | AA41: 5281 | AC41: =AA41 -> 5281
B42: Current liabilities | M42: 68432 | N42: 79039 | O42: 110119 | P42: 114023 | Q42: 183241 | T42: 109201 | U42: 114023 | V42: 110720 | W42: 105135 | X42: 98783 | Y42: 183241 | Z42: 152109 | AA42: 143835 | AC42: =AA42 -> 143835
B43: Debt | M43: 7423 | N43: 2725 | O43: 5400 | P43: 8150 | Q43: 92117 | T43: 10292 | U43: 8150 | V43: 6162 | W43: 4576 | X43: 3353 | Y43: 92117 | Z43: 85303 | AA43: 61165 | AC43: =AA43 -> 61165
B44: Long term liabilities | M44: =M45-M42 -> 8764 | N44: =N45-N42 -> 3199 | O44: =O45-O42 -> 8758 | P44: =P45-P42 -> 9584 | Q44: =Q45-Q42 -> 143342 | T44: =T45-T42 -> 11910 | U44: =U45-U42 -> 9584 | V44: =V45-V42 -> 7489 | W44: =W45-W42 -> 5507 | X44: =X45-X42 -> 4360 | Y44: =Y45-Y42 -> 143342 | Z44: =Z45-Z42 -> 154942 | AA44: =AA45-AA42 -> 131291 | AC44: =AA44 -> 131291
B45: Total liabilities | M45: 77196 | N45: 82238 | O45: 118877 | P45: 123607 | Q45: 326583 | T45: 121111 | U45: 123607 | V45: 118209 | W45: 110642 | X45: 103143 | Y45: 326583 | Z45: 307051 | AA45: 275126 | AC45: =AA45 -> 275126
B46: Treasury stock | M46: -13960 | N46: -33596 | O46: -45520 | P46: -45520 | Q46: -45520 | T46: -45520 | U46: -45520 | V46: -45520 | W46: -45520 | X46: -45520 | Y46: -45520 | Z46: -46615 | AA46: -46629 | AC46: =AA46 -> -46629
B47: Preferred stock | M47: 0 | N47: 0 | O47: 0 | P47: 0 | Q47: 0 | T47: 0 | U47: 0 | V47: 0 | W47: 0 | X47: 0 | Y47: 0 | Z47: 0 | AA47: 0 | AC47: =AA47 -> 0
B48: Paid in capital | M48: 860657 | N48: 926957 | O48: 1039361 | P48: 1111274 | Q48: 1181679 | T48: 1094629 | U48: 1111274 | V48: 1132124 | W48: 1147540 | X48: 1166078 | Y48: 1181679 | Z48: 1201871 | AA48: 1212775 | AC48: =AA48 -> 1212775
B49: Accumulated income/loss | M49: -429938 | N49: -606084 | O49: -742969 | P49: -801496 | Q49: -799190 | T49: -795106 | U49: -801496 | V49: -805410 | W49: -804756 | X49: -800485 | Y49: -799190 | Z49: -796227 | AA49: -794309 | AC49: =AA49 -> -794309
B50: Non-controlling interest | M50: 0 | N50: 0 | O50: 0 | P50: 0 | Q50: 0 | T50: 0 | U50: 0 | V50: 0 | W50: 0 | X50: 0 | Y50: 0 | Z50: 0 | AA50: 0 | AC50: =AA50 -> 0
B51: Stockholder equity | M51: 417280 | N51: 287819 | O51: 251449 | P51: 264808 | Q51: 337207 | T51: 254592 | U51: 264808 | V51: 282186 | W51: 297987 | X51: 320329 | Y51: 337207 | Z51: 359090 | AA51: 371851 | AC51: =AA51 -> 371851
B52: Total liabilities and equity | M52: 494476 | N52: 370057 | O52: 370326 | P52: 388415 | Q52: 663790 | T52: 375703 | U52: 388415 | V52: 400395 | W52: 408629 | X52: 423472 | Y52: 663790 | Z52: 666141 | AA52: 646977 | AC52: =AA52 -> 646977
B54: Cashflow statement
B55: D&A | M55: 21302 | N55: 25304 | O55: 29487 | P55: 27886 | Q55: 31453 | T55: 7087 | U55: 6823 | V55: 6878 | W55: 7409 | X55: 7478 | Y55: 9688 | Z55: 9954 | AA55: 9995 | AC55: =SUM(X55:AA55) -> 37115
B56: Stock-based compensation | M56: 36144 | N56: 58775 | O56: 71613 | P56: 66975 | Q56: 67452 | T56: 16525 | U56: 17162 | V56: 17225 | W56: 16230 | X56: 15959 | Y56: 18038 | Z56: 13554 | AA56: 11875 | AC56: =SUM(X56:AA56) -> 59426
B57: Change in accounts receivable | M57: -10216 | N57: -11132 | O57: -11205 | P57: -8812 | Q57: -23397 | T57: -10141 | U57: -2254 | V57: -1490 | W57: -1820 | X57: -11455 | Y57: -8632 | Z57: 7731 | AA57: 185 | AC57: =SUM(X57:AA57) -> -12171
B58: Change in inventory | M58: 0 | N58: 0 | O58: 0 | P58: 0 | Q58: 0 | T58: 0 | U58: 0 | V58: 0 | W58: 0 | X58: 0 | Y58: 0 | Z58: 0 | AA58: 0 | AC58: =SUM(X58:AA58) -> 0
B59: Change in accounts payable | M59: 2881 | N59: 4774 | O59: -1993 | P59: -3234 | Q59: 5261 | T59: 6948 | U59: -8432 | V59: -1739 | W59: 2068 | X59: 1303 | Y59: 3629 | Z59: 159 | AA59: 489 | AC59: =SUM(X59:AA59) -> 5580
B60: Change in other operating NWC | M60: -11236 | N60: 2496 | O60: 11561 | P60: 5553 | Q60: 4046 | T60: -2450 | U60: 10679 | V60: -3018 | W60: -8802 | X60: -2777 | Y60: 18643 | Z60: =7711+129+828-6985-5060-410-8317 -> -12104 | AA60: =995-12-2640+4982-8480-452-5524 -> -11131 | AC60: =SUM(X60:AA60) -> -7369
B61: Operating cashflow | M61: -74710 | N61: -90123 | O61: -32378 | P61: 32381 | Q61: 78814 | T61: 5785 | U61: 16256 | V61: 14850 | W61: 14835 | X61: 15467 | Y61: 33662 | Z61: 23922 | AA61: 18328 | AC61: =SUM(X61:AA61) -> 91379
B62: CapEx | M62: -18420 | N62: -4732 | O62: -5806 | P62: -8709 | Q62: -11101 | T62: -616 | U62: -2790 | V62: -3504 | W62: -1767 | X62: -3271 | Y62: -2559 | Z62: -4310 | AA62: -492 | AC62: =SUM(X62:AA62) -> -10632
B63: Capitalized software | M63: -12385 | N63: -21471 | O63: -19291 | P63: -15380 | Q63: -13296 | T63: -3566 | U63: -4268 | V63: -3888 | W63: -3435 | X63: -3395 | Y63: -2578 | Z63: -3240 | AA63: -4012 | AC63: =SUM(X63:AA63) -> -13225
B64: Investing cashflow | M64: -65228 | N64: -26203 | O64: -39670 | P64: -24089 | Q64: -161879 | T64: -4182 | U64: -7058 | V64: -7392 | W64: -5202 | X64: -6666 | Y64: -142619 | Z64: 4802 | AA64: 22168 | AC64: =SUM(X64:AA64) -> -122315
B65: Repurchase stock | M65: 0 | N65: 0 | O65: 0 | P65: 0 | Q65: 0 | T65: 0 | U65: 0 | V65: 0 | W65: 0 | X65: 0 | Y65: 0 | Z65: 0 | AA65: 0 | AC65: =SUM(X65:AA65) -> 0
B66: Dividends | M66: 0 | N66: 0 | O66: 0 | P66: 0 | Q66: 0 | T66: 0 | U66: 0 | V66: 0 | W66: 0 | X66: 0 | Y66: 0 | Z66: 0 | AA66: 0 | AC66: =SUM(X66:AA66) -> 0
B67: Dividends to minority interest | M67: 0 | N67: 0 | O67: 0 | P67: 0 | Q67: 0 | T67: 0 | U67: 0 | V67: 0 | W67: 0 | X67: 0 | Y67: 0 | Z67: 0 | AA67: 0 | AC67: =SUM(X67:AA67) -> 0
B68: Financing cashflow | M68: 234969 | N68: -20803 | O68: -17115 | P68: -11486 | Q68: 72851 | T68: -1651 | U68: -6629 | V68: -838 | W68: -2149 | X68: -667 | Y68: 76505 | Z68: -26093 | AA68: -42282 | AC68: =SUM(X68:AA68) -> 7463
B70: Sanity checks
B71: Calculated Net Income | C71: =C5-C6-C13+C15+C16+C18-C19 -> 0 | D71: =D5-D6-D13+D15+D16+D18-D19 -> 0 | E71: =E5-E6-E13+E15+E16+E18-E19 -> 0 | F71: =F5-F6-F13+F15+F16+F18-F19 -> 0 | G71: =G5-G6-G13+G15+G16+G18-G19 -> 0 | H71: =H5-H6-H13+H15+H16+H18-H19 -> 0 | I71: =I5-I6-I13+I15+I16+I18-I19 -> 0 | J71: =J5-J6-J13+J15+J16+J18-J19 -> 0 | ... Q71: =Q5-Q6-Q13+Q15+Q16+Q18-Q19 -> -9312 | T71: =T5-T6-T13+T15+T16+T18-T19 -> -14403 | U71: =U5-U6-U13+U15+U16+U18-U19 -> -6390 | V71: =V5-V6-V13+V15+V16+V18-V19 -> -3914 | W71: =W5-W6-W13+W15+W16+W18-W19 -> 654 | X71: =X5-X6-X13+X15+X16+X18-X19 -> 4271 | Y71: =Y5-Y6-Y13+Y15+Y16+Y18-Y19 -> -10323 | Z71: =Z5-Z6-Z13+Z15+Z16+Z18-Z19 -> 2963 | AA71: =AA5-AA6-AA13+AA15+AA16+AA18-AA19 -> 1918 | AC71: =AC5-AC6-AC13+AC15+AC16+AC18-AC19 -> -1171
B72: Check Net Income | C72: =C20-C71 -> 0 | D72: =D20-D71 -> 0 | E72: =E20-E71 -> 0 | F72: =F20-F71 -> 0 | G72: =G20-G71 -> 0 | H72: =H20-H71 -> 0 | I72: =I20-I71 -> 0 | J72: =J20-J71 -> 0 | ... Q72: =Q20-Q71 -> 0 | T72: =T20-T71 -> 0 | U72: =U20-U71 -> 0 | V72: =V20-V71 -> 0 | W72: =W20-W71 -> 0 | X72: =X20-X71 -> 0 | Y72: =Y20-Y71 -> 0 | Z72: =Z20-Z71 -> 0 | AA72: =AA20-AA71 -> 0 | AC72: =AC20-AC71 -> 0
B73: Check balance | C73: =C39-(C45+C116) -> 0 | D73: =D39-(D45+D116) -> 0 | E73: =E39-(E45+E116) -> 0 | F73: =F39-(F45+F116) -> 0 | G73: =G39-(G45+G116) -> 0 | H73: =H39-(H45+H116) -> 0 | I73: =I39-(I45+I116) -> 0 | J73: =J39-(J45+J116) -> 0 | ... Q73: =Q39-(Q45+Q116) -> 0 | T73: =T39-(T45+T116) -> 0 | U73: =U39-(U45+U116) -> 0 | V73: =V39-(V45+V116) -> 0 | W73: =W39-(W45+W116) -> 0 | X73: =X39-(X45+X116) -> 0 | Y73: =Y39-(Y45+Y116) -> 0 | Z73: =Z39-(Z45+Z116) -> 0 | AA73: =AA39-(AA45+AA116) -> 0 | AC73: =AC39-(AC45+AC116) -> 0
B75: Other data
B76: Shares outstanding | M76: 51946 | N76: 53355 | O76: 56387 | P76: 58772 | Q76: 60763 | T76: 58124 | U76: 58772 | V76: 59504 | W76: 59914 | X76: 60287 | Y76: 60763 | Z76: 61812 | AA76: 62071 | AC76: =AA76 -> 62071
B77: Split adjusted shares outstanding | M77: =M76*M87 -> 51946 | N77: =N76*N87 -> 53355 | O77: =O76*O87 -> 56387 | P77: =P76*P87 -> 58772 | Q77: =Q76*Q87 -> 60763 | T77: =T76*T87 -> 58124 | U77: =U76*U87 -> 58772 | V77: =V76*V87 -> 59504 | W77: =W76*W87 -> 59914 | X77: =X76*X87 -> 60287 | Y77: =Y76*Y87 -> 60763 | Z77: =Z76*Z87 -> 61812 | AA77: =AA76*AA87 -> 62071 | AC77: =AA77 -> 62071
B78: Dilutive shares | M78: 0 | N78: 0 | O78: 0 | P78: 0 | Q78: =698+556+335+148+19 -> 1756 | T78: 0 | U78: 0 | V78: 0 | W78: =764+625+575+93+37 -> 2094 | X78: =756+549+189+57 -> 1551 | Y78: 1756 | Z78: =293+197+606 -> 1096 | AA78: 2655 | AC78: =AA78 -> 2655
B79: Split adjusted dilutive shares | M79: =M78*M87 -> 0 | N79: =N78*N87 -> 0 | O79: =O78*O87 -> 0 | P79: =P78*P87 -> 0 | Q79: =Q78*Q87 -> 1756 | T79: =T78*T87 -> 0 | U79: =U78*U87 -> 0 | V79: =V78*V87 -> 0 | W79: =W78*W87 -> 2094 | X79: =X78*X87 -> 1551 | Y79: =Y78*Y87 -> 1756 | Z79: =Z78*Z87 -> 1096 | AA79: =AA78*AA87 -> 2655 | AC79: =AA79 -> 2655
B80: Split adjusted diluted shares | M80: =M77+M79 -> 51946 | N80: =N77+N79 -> 53355 | O80: =O77+O79 -> 56387 | P80: =P77+P79 -> 58772 | Q80: =Q77+Q79 -> 62519 | T80: =T77+T79 -> 58124 | U80: =U77+U79 -> 58772 | V80: =V77+V79 -> 59504 | W80: =W77+W79 -> 62008 | X80: =X77+X79 -> 61838 | Y80: =Y77+Y79 -> 62519 | Z80: =Z77+Z79 -> 62908 | AA80: =AA77+AA79 -> 64726 | AC80: =AA80 -> 64726
B81: Shares held by insiders | M81: 2892 | N81: 3116 | O81: 3332 | P81: 3302 | Q81: 3238 | AC81: =Q81 -> 3238
B82: Split adjusted shares held by insiders | M82: =M81*M87 -> 2892 | N82: =N81*N87 -> 3116 | O82: =O81*O87 -> 3332 | P82: =P81*P87 -> 3302 | Q82: =Q81*Q87 -> 3238 | AC82: =Q82 -> 3238
B83: Dividends per share | M83: 0 | N83: 0 | O83: 0 | P83: 0 | Q83: 0 | T83: 0 | U83: 0 | V83: 0 | W83: 0 | X83: 0 | Y83: 0 | Z83: 0 | AA83: 0 | AC83: =SUM(X83:AA83) -> 0
B84: Split adjusted dividends per share | M84: =M83/M87 -> 0 | N84: =N83/N87 -> 0 | O84: =O83/O87 -> 0 | P84: =P83/P87 -> 0 | Q84: =Q83/Q87 -> 0 | T84: =T83/T87 -> 0 | U84: =U83/U87 -> 0 | V84: =V83/V87 -> 0 | W84: =W83/W87 -> 0 | X84: =X83/X87 -> 0 | Y84: =Y83/Y87 -> 0 | Z84: =Z83/Z87 -> 0 | AA84: =AA83/AA87 -> 0 | AC84: =SUM(X84:AA84) -> 0
B85: Tax rate | C85: =IF(AND(C17>0,C18<0),-(C18)/C17,0) -> 0 | D85: =IF(AND(D17>0,D18<0),-(D18)/D17,0) -> 0 | E85: =IF(AND(E17>0,E18<0),-(E18)/E17,0) -> 0 | F85: =IF(AND(F17>0,F18<0),-(F18)/F17,0) -> 0 | G85: =IF(AND(G17>0,G18<0),-(G18)/G17,0) -> 0 | H85: =IF(AND(H17>0,H18<0),-(H18)/H17,0) -> 0 | I85: =IF(AND(I17>0,I18<0),-(I18)/I17,0) -> 0 | J85: =IF(AND(J17>0,J18<0),-(J18)/J17,0) -> 0 | ... Q85: =IF(AND(Q17>0,Q18<0),-(Q18)/Q17,0) -> 0 | T85: =IF(AND(T17>0,T18<0),-(T18)/T17,0) -> 0 | U85: =IF(AND(U17>0,U18<0),-(U18)/U17,0) -> 0 | V85: =IF(AND(V17>0,V18<0),-(V18)/V17,0) -> 0 | W85: =IF(AND(W17>0,W18<0),-(W18)/W17,0) -> 0 | X85: =IF(AND(X17>0,X18<0),-(X18)/X17,0) -> 0.16663415 | Y85: =IF(AND(Y17>0,Y18<0),-(Y18)/Y17,0) -> 0 | Z85: =IF(AND(Z17>0,Z18<0),-(Z18)/Z17,0) -> 0.37264451 | AA85: =IF(AND(AA17>0,AA18<0),-(AA18)/AA17,0) -> 0.40784193 | AC85: =IF(AND(AC17>0,AC18<0),-(AC18)/AC17,0) -> 1.4236614
B86: Employees | M86: 1701 | N86: 1546 | O86: 1438 | P86: 2082 | Q86: 1789 | AC86: =Q86 -> 1789
B87: Stock split factor | M87: 1 | N87: 1 | O87: 1 | P87: 1 | Q87: 1 | T87: 1 | U87: 1 | V87: 1 | W87: 1 | X87: 1 | Y87: 1 | Z87: 1 | AA87: 1 | AC87: 1
B90: Growth rates Income Statement
B91: Revenue | M91: =IF(L5=0, IF(M5=0,0,IF(M5>0,1,-1)), (M5-L5)/ABS(L5) ) -> 1 | N91: =IF(M5=0, IF(N5=0,0,IF(N5>0,1,-1)), (N5-M5)/ABS(M5) ) -> 0.31738521 | O91: =IF(N5=0, IF(O5=0,0,IF(O5>0,1,-1)), (O5-N5)/ABS(N5) ) -> 0.26837421 | P91: =IF(O5=0, IF(P5=0,0,IF(P5>0,1,-1)), (P5-O5)/ABS(O5) ) -> 0.17826039 | Q91: =IF(P5=0, IF(Q5=0,0,IF(Q5>0,1,-1)), (Q5-P5)/ABS(P5) ) -> 0.14477398 | T91: =IF(S5=0, IF(T5=0,0,IF(T5>0,1,-1)), (T5-S5)/ABS(S5) ) -> 1 | U91: =IF(T5=0, IF(U5=0,0,IF(U5>0,1,-1)), (U5-T5)/ABS(T5) ) -> 0.026975655 | V91: =IF(U5=0, IF(V5=0,0,IF(V5>0,1,-1)), (V5-U5)/ABS(U5) ) -> 0.057029021 | W91: =IF(V5=0, IF(W5=0,0,IF(W5>0,1,-1)), (W5-V5)/ABS(V5) ) -> 0.011376967 | X91: =IF(W5=0, IF(X5=0,0,IF(X5>0,1,-1)), (X5-W5)/ABS(W5) ) -> 0.02625048 | Y91: =IF(X5=0, IF(Y5=0,0,IF(Y5>0,1,-1)), (Y5-X5)/ABS(X5) ) -> 0.055961374 | Z91: =IF(Y5=0, IF(Z5=0,0,IF(Z5>0,1,-1)), (Z5-Y5)/ABS(Y5) ) -> 0.030440634 | AA91: =IF(Z5=0, IF(AA5=0,0,IF(AA5>0,1,-1)), (AA5-Z5)/ABS(Z5) ) -> -0.011280406
B92: COGS | M92: =IF(L6=0, IF(M6=0,0,IF(M6>0,1,-1)), (M6-L6)/ABS(L6) ) -> 1 | N92: =IF(M6=0, IF(N6=0,0,IF(N6>0,1,-1)), (N6-M6)/ABS(M6) ) -> 0.34254436 | O92: =IF(N6=0, IF(O6=0,0,IF(O6>0,1,-1)), (O6-N6)/ABS(N6) ) -> 0.13493552 | P92: =IF(O6=0, IF(P6=0,0,IF(P6>0,1,-1)), (P6-O6)/ABS(O6) ) -> 0.088080896 | Q92: =IF(P6=0, IF(Q6=0,0,IF(Q6>0,1,-1)), (Q6-P6)/ABS(P6) ) -> 0.14221027 | T92: =IF(S6=0, IF(T6=0,0,IF(T6>0,1,-1)), (T6-S6)/ABS(S6) ) -> 1 | U92: =IF(T6=0, IF(U6=0,0,IF(U6>0,1,-1)), (U6-T6)/ABS(T6) ) -> -0.028114775 | V92: =IF(U6=0, IF(V6=0,0,IF(V6>0,1,-1)), (V6-U6)/ABS(U6) ) -> 0.13403444 | W92: =IF(V6=0, IF(W6=0,0,IF(W6>0,1,-1)), (W6-V6)/ABS(V6) ) -> -0.011138841 | X92: =IF(W6=0, IF(X6=0,0,IF(X6>0,1,-1)), (X6-W6)/ABS(W6) ) -> 0.010254775 | Y92: =IF(X6=0, IF(Y6=0,0,IF(Y6>0,1,-1)), (Y6-X6)/ABS(X6) ) -> 0.062140058 | Z92: =IF(Y6=0, IF(Z6=0,0,IF(Z6>0,1,-1)), (Z6-Y6)/ABS(Y6) ) -> 0.072889329 | AA92: =IF(Z6=0, IF(AA6=0,0,IF(AA6>0,1,-1)), (AA6-Z6)/ABS(Z6) ) -> -0.0034384086
B93: Gross Profit | M93: =IF(L7=0, IF(M7=0,0,IF(M7>0,1,-1)), (M7-L7)/ABS(L7) ) -> 1 | N93: =IF(M7=0, IF(N7=0,0,IF(N7>0,1,-1)), (N7-M7)/ABS(M7) ) -> 0.30185445 | O93: =IF(N7=0, IF(O7=0,0,IF(O7>0,1,-1)), (O7-N7)/ABS(N7) ) -> 0.35332055 | P93: =IF(O7=0, IF(P7=0,0,IF(P7>0,1,-1)), (P7-O7)/ABS(O7) ) -> 0.22640429 | Q93: =IF(P7=0, IF(Q7=0,0,IF(Q7>0,1,-1)), (Q7-P7)/ABS(P7) ) -> 0.1459883 | T93: =IF(S7=0, IF(T7=0,0,IF(T7>0,1,-1)), (T7-S7)/ABS(S7) ) -> 1 | U93: =IF(T7=0, IF(U7=0,0,IF(U7>0,1,-1)), (U7-T7)/ABS(T7) ) -> 0.053305288 | V93: =IF(U7=0, IF(V7=0,0,IF(V7>0,1,-1)), (V7-U7)/ABS(U7) ) -> 0.023070354 | W93: =IF(V7=0, IF(W7=0,0,IF(W7>0,1,-1)), (W7-V7)/ABS(V7) ) -> 0.022383172 | X93: =IF(W7=0, IF(X7=0,0,IF(X7>0,1,-1)), (X7-W7)/ABS(W7) ) -> 0.033813148 | Y93: =IF(X7=0, IF(Y7=0,0,IF(Y7>0,1,-1)), (Y7-X7)/ABS(X7) ) -> 0.053106699 | Z93: =IF(Y7=0, IF(Z7=0,0,IF(Z7>0,1,-1)), (Z7-Y7)/ABS(Y7) ) -> 0.010660267 | AA93: =IF(Z7=0, IF(AA7=0,0,IF(AA7>0,1,-1)), (AA7-Z7)/ABS(Z7) ) -> -0.015159644
B94: Sales and marketing | M94: =IF(L8=0, IF(M8=0,0,IF(M8>0,1,-1)), (M8-L8)/ABS(L8) ) -> 1 | N94: =IF(M8=0, IF(N8=0,0,IF(N8>0,1,-1)), (N8-M8)/ABS(M8) ) -> 0.4213642 | O94: =IF(N8=0, IF(O8=0,0,IF(O8>0,1,-1)), (O8-N8)/ABS(N8) ) -> -0.028129814 | P94: =IF(O8=0, IF(P8=0,0,IF(P8>0,1,-1)), (P8-O8)/ABS(O8) ) -> -0.17603804 | Q94: =IF(P8=0, IF(Q8=0,0,IF(Q8>0,1,-1)), (Q8-P8)/ABS(P8) ) -> -0.17242774 | T94: =IF(S8=0, IF(T8=0,0,IF(T8>0,1,-1)), (T8-S8)/ABS(S8) ) -> 1 | U94: =IF(T8=0, IF(U8=0,0,IF(U8>0,1,-1)), (U8-T8)/ABS(T8) ) -> -0.040171594 | V94: =IF(U8=0, IF(V8=0,0,IF(V8>0,1,-1)), (V8-U8)/ABS(U8) ) -> -0.097702941 | W94: =IF(V8=0, IF(W8=0,0,IF(W8>0,1,-1)), (W8-V8)/ABS(V8) ) -> -0.024843528 | X94: =IF(W8=0, IF(X8=0,0,IF(X8>0,1,-1)), (X8-W8)/ABS(W8) ) -> -0.049141597 | Y94: =IF(X8=0, IF(Y8=0,0,IF(Y8>0,1,-1)), (Y8-X8)/ABS(X8) ) -> 0.021036939 | Z94: =IF(Y8=0, IF(Z8=0,0,IF(Z8>0,1,-1)), (Z8-Y8)/ABS(Y8) ) -> -0.018129461 | AA94: =IF(Z8=0, IF(AA8=0,0,IF(AA8>0,1,-1)), (AA8-Z8)/ABS(Z8) ) -> 0.015614028
B95: R&D | M95: =IF(L9=0, IF(M9=0,0,IF(M9>0,1,-1)), (M9-L9)/ABS(L9) ) -> 1 | N95: =IF(M9=0, IF(N9=0,0,IF(N9>0,1,-1)), (N9-M9)/ABS(M9) ) -> 0.74579547 | O95: =IF(N9=0, IF(O9=0,0,IF(O9>0,1,-1)), (O9-N9)/ABS(N9) ) -> 0.23127 | P95: =IF(O9=0, IF(P9=0,0,IF(P9>0,1,-1)), (P9-O9)/ABS(O9) ) -> 0.044665587 | Q95: =IF(P9=0, IF(Q9=0,0,IF(Q9>0,1,-1)), (Q9-P9)/ABS(P9) ) -> 0.0350789 | T95: =IF(S9=0, IF(T9=0,0,IF(T9>0,1,-1)), (T9-S9)/ABS(S9) ) -> 1 | U95: =IF(T9=0, IF(U9=0,0,IF(U9>0,1,-1)), (U9-T9)/ABS(T9) ) -> 0.010608903 | V95: =IF(U9=0, IF(V9=0,0,IF(V9>0,1,-1)), (V9-U9)/ABS(U9) ) -> 0.074360359 | W95: =IF(V9=0, IF(W9=0,0,IF(W9>0,1,-1)), (W9-V9)/ABS(V9) ) -> -0.080272707 | X95: =IF(W9=0, IF(X9=0,0,IF(X9>0,1,-1)), (X9-W9)/ABS(W9) ) -> 0.006114641 | Y95: =IF(X9=0, IF(Y9=0,0,IF(Y9>0,1,-1)), (Y9-X9)/ABS(X9) ) -> 0.049977931 | Z95: =IF(Y9=0, IF(Z9=0,0,IF(Z9>0,1,-1)), (Z9-Y9)/ABS(Y9) ) -> -0.083977365 | AA95: =IF(Z9=0, IF(AA9=0,0,IF(AA9>0,1,-1)), (AA9-Z9)/ABS(Z9) ) -> -0.026722677
B96: General and administrative | M96: =IF(L10=0, IF(M10=0,0,IF(M10>0,1,-1)), (M10-L10)/ABS(L10) ) -> 1 | N96: =IF(M10=0, IF(N10=0,0,IF(N10>0,1,-1)), (N10-M10)/ABS(M10) ) -> 0.17051577 | O96: =IF(N10=0, IF(O10=0,0,IF(O10>0,1,-1)), (O10-N10)/ABS(N10) ) -> -0.0056976513 | P96: =IF(O10=0, IF(P10=0,0,IF(P10>0,1,-1)), (P10-O10)/ABS(O10) ) -> -0.041651027 | Q96: =IF(P10=0, IF(Q10=0,0,IF(Q10>0,1,-1)), (Q10-P10)/ABS(P10) ) -> 0.043160959 | T96: =IF(S10=0, IF(T10=0,0,IF(T10>0,1,-1)), (T10-S10)/ABS(S10) ) -> 1 | U96: =IF(T10=0, IF(U10=0,0,IF(U10>0,1,-1)), (U10-T10)/ABS(T10) ) -> -0.062038405 | V96: =IF(U10=0, IF(V10=0,0,IF(V10>0,1,-1)), (V10-U10)/ABS(U10) ) -> -0.10898724 | W96: =IF(V10=0, IF(W10=0,0,IF(W10>0,1,-1)), (W10-V10)/ABS(V10) ) -> 0.16053145 | X96: =IF(W10=0, IF(X10=0,0,IF(X10>0,1,-1)), (X10-W10)/ABS(W10) ) -> -0.081609075 | Y96: =IF(X10=0, IF(Y10=0,0,IF(Y10>0,1,-1)), (Y10-X10)/ABS(X10) ) -> 0.54191446 | Z96: =IF(Y10=0, IF(Z10=0,0,IF(Z10>0,1,-1)), (Z10-Y10)/ABS(Y10) ) -> -0.31908029 | AA96: =IF(Z10=0, IF(AA10=0,0,IF(AA10>0,1,-1)), (AA10-Z10)/ABS(Z10) ) -> -0.10070258
B97: Depreciation | M97: =IF(L11=0, IF(M11=0,0,IF(M11>0,1,-1)), (M11-L11)/ABS(L11) ) -> 1 | N97: =IF(M11=0, IF(N11=0,0,IF(N11>0,1,-1)), (N11-M11)/ABS(M11) ) -> 0.2004004 | O97: =IF(N11=0, IF(O11=0,0,IF(O11>0,1,-1)), (O11-N11)/ABS(N11) ) -> -0.022459417 | P97: =IF(O11=0, IF(P11=0,0,IF(P11>0,1,-1)), (P11-O11)/ABS(O11) ) -> -0.19341447 | Q97: =IF(P11=0, IF(Q11=0,0,IF(Q11>0,1,-1)), (Q11-P11)/ABS(P11) ) -> -0.08538391 | T97: =IF(S11=0, IF(T11=0,0,IF(T11>0,1,-1)), (T11-S11)/ABS(S11) ) -> 1 | U97: =IF(T11=0, IF(U11=0,0,IF(U11>0,1,-1)), (U11-T11)/ABS(T11) ) -> -0.11048794 | V97: =IF(U11=0, IF(V11=0,0,IF(V11>0,1,-1)), (V11-U11)/ABS(U11) ) -> -0.058638083 | W97: =IF(V11=0, IF(W11=0,0,IF(W11>0,1,-1)), (W11-V11)/ABS(V11) ) -> 0.098124581 | X97: =IF(W11=0, IF(X11=0,0,IF(X11>0,1,-1)), (X11-W11)/ABS(W11) ) -> -0.024397682 | Y97: =IF(X11=0, IF(Y11=0,0,IF(Y11>0,1,-1)), (Y11-X11)/ABS(X11) ) -> 0.096592685 | Z97: =IF(Y11=0, IF(Z11=0,0,IF(Z11>0,1,-1)), (Z11-Y11)/ABS(Y11) ) -> -0.039053592 | AA97: =IF(Z11=0, IF(AA11=0,0,IF(AA11>0,1,-1)), (AA11-Z11)/ABS(Z11) ) -> -0.0091960842
B98: Amortization | M98: =IF(L12=0, IF(M12=0,0,IF(M12>0,1,-1)), (M12-L12)/ABS(L12) ) -> 1 | N98: =IF(M12=0, IF(N12=0,0,IF(N12>0,1,-1)), (N12-M12)/ABS(M12) ) -> 0.15814469 | O98: =IF(N12=0, IF(O12=0,0,IF(O12>0,1,-1)), (O12-N12)/ABS(N12) ) -> 0.62698196 | P98: =IF(O12=0, IF(P12=0,0,IF(P12>0,1,-1)), (P12-O12)/ABS(O12) ) -> 0.15122238 | Q98: =IF(P12=0, IF(Q12=0,0,IF(Q12>0,1,-1)), (Q12-P12)/ABS(P12) ) -> 0.34868277 | T98: =IF(S12=0, IF(T12=0,0,IF(T12>0,1,-1)), (T12-S12)/ABS(S12) ) -> 1 | U98: =IF(T12=0, IF(U12=0,0,IF(U12>0,1,-1)), (U12-T12)/ABS(T12) ) -> 0.036921329 | V98: =IF(U12=0, IF(V12=0,0,IF(V12>0,1,-1)), (V12-U12)/ABS(U12) ) -> 0.066009313 | W98: =IF(V12=0, IF(W12=0,0,IF(W12>0,1,-1)), (W12-V12)/ABS(V12) ) -> 0.061151079 | X98: =IF(W12=0, IF(X12=0,0,IF(X12>0,1,-1)), (X12-W12)/ABS(W12) ) -> 0.036077482 | Y98: =IF(X12=0, IF(Y12=0,0,IF(Y12>0,1,-1)), (Y12-X12)/ABS(X12) ) -> 0.44426268 | Z98: =IF(Y12=0, IF(Z12=0,0,IF(Z12>0,1,-1)), (Z12-Y12)/ABS(Y12) ) -> 0.065210356 | AA98: =IF(Z12=0, IF(AA12=0,0,IF(AA12>0,1,-1)), (AA12-Z12)/ABS(Z12) ) -> 0.010937263
B99: OpEx | M99: =IF(L13=0, IF(M13=0,0,IF(M13>0,1,-1)), (M13-L13)/ABS(L13) ) -> 1 | N99: =IF(M13=0, IF(N13=0,0,IF(N13>0,1,-1)), (N13-M13)/ABS(M13) ) -> 0.40027427 | O99: =IF(N13=0, IF(O13=0,0,IF(O13>0,1,-1)), (O13-N13)/ABS(N13) ) -> 0.059081836 | P99: =IF(O13=0, IF(P13=0,0,IF(P13>0,1,-1)), (P13-O13)/ABS(O13) ) -> -0.069938471 | Q99: =IF(P13=0, IF(Q13=0,0,IF(Q13>0,1,-1)), (Q13-P13)/ABS(P13) ) -> -0.028853331 | T99: =IF(S13=0, IF(T13=0,0,IF(T13>0,1,-1)), (T13-S13)/ABS(S13) ) -> 1 | U99: =IF(T13=0, IF(U13=0,0,IF(U13>0,1,-1)), (U13-T13)/ABS(T13) ) -> -0.027628737 | V99: =IF(U13=0, IF(V13=0,0,IF(V13>0,1,-1)), (V13-U13)/ABS(U13) ) -> -0.030683053 | W99: =IF(V13=0, IF(W13=0,0,IF(W13>0,1,-1)), (W13-V13)/ABS(V13) ) -> -0.00045590084 | X99: =IF(W13=0, IF(X13=0,0,IF(X13>0,1,-1)), (X13-W13)/ABS(W13) ) -> -0.031483833 | Y99: =IF(X13=0, IF(Y13=0,0,IF(Y13>0,1,-1)), (Y13-X13)/ABS(X13) ) -> 0.17395344 | Z99: =IF(Y13=0, IF(Z13=0,0,IF(Z13>0,1,-1)), (Z13-Y13)/ABS(Y13) ) -> -0.12340352 | AA99: =IF(Z13=0, IF(AA13=0,0,IF(AA13>0,1,-1)), (AA13-Z13)/ABS(Z13) ) -> -0.027049424
B100: Operating income | M100: =IF(L14=0, IF(M14=0,0,IF(M14>0,1,-1)), (M14-L14)/ABS(L14) ) -> -1 | N100: =IF(M14=0, IF(N14=0,0,IF(N14>0,1,-1)), (N14-M14)/ABS(M14) ) -> -0.51135537 | O100: =IF(N14=0, IF(O14=0,0,IF(O14>0,1,-1)), (O14-N14)/ABS(N14) ) -> 0.22697562 | P100: =IF(O14=0, IF(P14=0,0,IF(P14>0,1,-1)), (P14-O14)/ABS(O14) ) -> 0.57431546 | Q100: =IF(P14=0, IF(Q14=0,0,IF(Q14>0,1,-1)), (Q14-P14)/ABS(P14) ) -> 0.88619034 | T100: =IF(S14=0, IF(T14=0,0,IF(T14>0,1,-1)), (T14-S14)/ABS(S14) ) -> -1 | U100: =IF(T14=0, IF(U14=0,0,IF(U14>0,1,-1)), (U14-T14)/ABS(T14) ) -> 0.45011919 | V100: =IF(U14=0, IF(V14=0,0,IF(V14>0,1,-1)), (V14-U14)/ABS(U14) ) -> 0.56818182 | W100: =IF(V14=0, IF(W14=0,0,IF(W14>0,1,-1)), (W14-V14)/ABS(V14) ) -> 0.54152723 | X100: =IF(W14=0, IF(X14=0,0,IF(X14>0,1,-1)), (X14-W14)/ABS(W14) ) -> 3.4810883 | Y100: =IF(X14=0, IF(Y14=0,0,IF(Y14>0,1,-1)), (Y14-X14)/ABS(X14) ) -> -2.4862263 | Z100: =IF(Y14=0, IF(Z14=0,0,IF(Z14>0,1,-1)), (Z14-Y14)/ABS(Y14) ) -> 2.2145042 | AA100: =IF(Z14=0, IF(AA14=0,0,IF(AA14>0,1,-1)), (AA14-Z14)/ABS(Z14) ) -> 0.12727812
B101: Income before taxes | M101: =IF(L17=0, IF(M17=0,0,IF(M17>0,1,-1)), (M17-L17)/ABS(L17) ) -> -1 | N101: =IF(M17=0, IF(N17=0,0,IF(N17>0,1,-1)), (N17-M17)/ABS(M17) ) -> -0.48893447 | O101: =IF(N17=0, IF(O17=0,0,IF(O17>0,1,-1)), (O17-N17)/ABS(N17) ) -> 0.2295361 | P101: =IF(O17=0, IF(P17=0,0,IF(P17>0,1,-1)), (P17-O17)/ABS(O17) ) -> 0.58762986 | Q101: =IF(P17=0, IF(Q17=0,0,IF(Q17>0,1,-1)), (Q17-P17)/ABS(P17) ) -> 0.83981652 | T101: =IF(S17=0, IF(T17=0,0,IF(T17>0,1,-1)), (T17-S17)/ABS(S17) ) -> -1 | U101: =IF(T17=0, IF(U17=0,0,IF(U17>0,1,-1)), (U17-T17)/ABS(T17) ) -> 0.6149273 | V101: =IF(U17=0, IF(V17=0,0,IF(V17>0,1,-1)), (V17-U17)/ABS(U17) ) -> 0.40866815 | W101: =IF(V17=0, IF(W17=0,0,IF(W17>0,1,-1)), (W17-V17)/ABS(V17) ) -> 0.82290028 | X101: =IF(W17=0, IF(X17=0,0,IF(X17>0,1,-1)), (X17-W17)/ABS(W17) ) -> 10.10302 | Y101: =IF(X17=0, IF(Y17=0,0,IF(Y17>0,1,-1)), (Y17-X17)/ABS(X17) ) -> -3.0142439 | Z101: =IF(Y17=0, IF(Z17=0,0,IF(Z17>0,1,-1)), (Z17-Y17)/ABS(Y17) ) -> 1.457522 | AA101: =IF(Z17=0, IF(AA17=0,0,IF(AA17>0,1,-1)), (AA17-Z17)/ABS(Z17) ) -> -0.31420707
B102: Net income | M102: =IF(L20=0, IF(M20=0,0,IF(M20>0,1,-1)), (M20-L20)/ABS(L20) ) -> -1 | N102: =IF(M20=0, IF(N20=0,0,IF(N20>0,1,-1)), (N20-M20)/ABS(M20) ) -> -0.49072875 | O102: =IF(N20=0, IF(O20=0,0,IF(O20>0,1,-1)), (O20-N20)/ABS(N20) ) -> 0.22288897 | P102: =IF(O20=0, IF(P20=0,0,IF(P20>0,1,-1)), (P20-O20)/ABS(O20) ) -> 0.57243672 | Q102: =IF(P20=0, IF(Q20=0,0,IF(Q20>0,1,-1)), (Q20-P20)/ABS(P20) ) -> 0.84089395 | T102: =IF(S20=0, IF(T20=0,0,IF(T20>0,1,-1)), (T20-S20)/ABS(S20) ) -> -1 | U102: =IF(T20=0, IF(U20=0,0,IF(U20>0,1,-1)), (U20-T20)/ABS(T20) ) -> 0.55634243 | V102: =IF(U20=0, IF(V20=0,0,IF(V20>0,1,-1)), (V20-U20)/ABS(U20) ) -> 0.38748044 | W102: =IF(V20=0, IF(W20=0,0,IF(W20>0,1,-1)), (W20-V20)/ABS(V20) ) -> 1.1670925 | X102: =IF(W20=0, IF(X20=0,0,IF(X20>0,1,-1)), (X20-W20)/ABS(W20) ) -> 5.530581 | Y102: =IF(X20=0, IF(Y20=0,0,IF(Y20>0,1,-1)), (Y20-X20)/ABS(X20) ) -> -3.4169984 | Z102: =IF(Y20=0, IF(Z20=0,0,IF(Z20>0,1,-1)), (Z20-Y20)/ABS(Y20) ) -> 1.287029 | AA102: =IF(Z20=0, IF(AA20=0,0,IF(AA20>0,1,-1)), (AA20-Z20)/ABS(Z20) ) -> -0.35268309
B104: Margins
B105: Gross margin | M105: =M7/M5 -> 0.61831424 | N105: =N7/N5 -> 0.61102488 | O105: =O7/O5 -> 0.65194682 | P105: =P7/P5 -> 0.67858547 | Q105: =Q7/Q5 -> 0.67930527 | T105: =T7/T5 -> 0.67661985 | U105: =U7/U5 -> 0.69396705 | V105: =V7/V5 -> 0.6716723 | W105: =W7/W5 -> 0.67898171 | X105: =X7/X5 -> 0.68398527 | Y105: =Y7/Y5 -> 0.6821362 | Z105: =Z7/Z5 -> 0.66904189 | AA105: =AA7/AA5 -> 0.66641691 | AC105: =AC7/AC5 -> 0.67519048
B106: Operating margin | M106: =M14/M5 -> -0.54783734 | N106: =N14/N5 -> -0.62850023 | O106: =O14/O5 -> -0.38304626 | P106: =P14/P5 -> -0.13838781 | Q106: =Q14/Q5 -> -0.01375806 | T106: =T14/T5 -> -0.1296161 | U106: =U14/U5 -> -0.069401264 | V106: =V14/V5 -> -0.028351849 | W106: =W14/W5 -> -0.01285233 | X106: =X14/X5 -> 0.031072108 | Y106: =Y14/Y5 -> -0.043732834 | Z106: =Z14/Z5 -> 0.05154466 | AA106: =AA14/AA5 -> 0.058768095 | AC106: =AC14/AC5 -> 0.024693133
B107: Net margin | M107: =M115/M5 -> -0.55414031 | N107: =N115/N5 -> -0.62705493 | O107: =O115/O5 -> -0.38418575 | P107: =P115/P5 -> -0.13941207 | Q107: =Q115/Q5 -> -0.019376143 | T107: =T115/T5 -> -0.13485955 | U107: =U115/U5 -> -0.058259863 | V107: =V115/V5 -> -0.033760006 | W107: =W115/W5 -> 0.0055775873 | X107: =X115/X5 -> 0.035493173 | Y107: =Y115/Y5 -> -0.081240605 | Z107: =Z115/Z5 -> 0.022629549 | AA107: =AA115/AA5 -> 0.014815616 | AC107: =AC115/AC5 -> -0.0023060578
B109: Adjustments
...

Sheet Analysis ->
H5: Links
H6: Overview'!B3
H7: Financials ->'!B13
H8: Analysis ->'!B13
H9: Forecast ->'!B13
H10: Valuation ->'!B13
B13: Analysis ->

Sheet Basic
B1: TTM/YTD data
B4: Overview | E4: CAGR
B5: Price | C5: =Overview!C5 -> 12.61 | F5: 5Y | G5: 10Y
B6: Market capitalization | C6: =Statement!AC153 -> 816194.86 | E6: Revenue | F6: =IF(Statement!M5<=0,"N/A",_xlfn.RRI(4,Statement!M5,Statement!Q5)) -> 0.22526578 | G6: =IF(Statement!H5<=0,"N/A",_xlfn.RRI(9,Statement!H5,Statement!Q5)) -> N/A
B7: Enterprise value | C7: =Statement!AC154 -> 809695.86 | E7: Net income | F7: =IF(OR(Statement!M20<=0, Statement!Q20<=0), "N/A", _xlfn.RRI(4, Statement!M20, Statement!Q20)) -> N/A | G7: =IF(OR(Statement!H20<=0, Statement!Q20<=0), "N/A", _xlfn.RRI(9, Statement!H20, Statement!Q20)) -> N/A
B8: PE | C8: =Statement!AC150 -> -705.97403 | E8: EPS | F8: =IF(OR(Statement!M28<=0, Statement!Q28<=0), "N/A", _xlfn.RRI(4, Statement!M28, Statement!Q28)) -> N/A | G8: =IF(OR(Statement!H28<=0, Statement!Q28<=0), "N/A", _xlfn.RRI(9, Statement!H28, Statement!Q28)) -> N/A
B9: PS | C9: =Statement!AC151 -> 1.5369177 | E9: Dividend | F9: =IF(Statement!M84<=0,"N/A",_xlfn.RRI(4,Statement!M84,Statement!Q84)) -> N/A | G9: =IF(Statement!H84<=0,"N/A",_xlfn.RRI(9,Statement!H84,Statement!Q84)) -> N/A
B10: PB | C10: =Statement!AC152 -> 2.1049165 | E10: Price | F10: =IF(Statement!M121<=0,"N/A",_xlfn.RRI(4,Statement!M121,Statement!Q121)) -> -0.17103422 | G10: =IF(Statement!H121<=0,"N/A",_xlfn.RRI(9,Statement!H121,Statement!Q121)) -> N/A
B11: EV/Revenue | C11: =Statement!AC155 -> 1.5945392
B12: EV/EBIT | C12: =Statement!AC156 -> 64.574197
B15: Margins | E15: Earnings quality
B16: Gross margin | C16: =Statement!AC105 -> 0.67519048 | E16: Net income | F16: =Statement!AC20 -> -1171
B17: Operating margin | C17: =Statement!AC106 -> 0.024693133 | E17: Operating cash | F17: =Statement!AC61 -> 91379
B18: Net margin | C18: =Statement!AC107 -> -0.0023060578 | E18: Cash accruals | F18: =IF(OR(F16<=0, F17<=0),"N/A",F16-F17) -> N/A
B21: DuPont Identity | E21: Performance indicators
B22: Profit Margin (Earnings/Revenue) | C22: =Statement!AC125 -> -0.0023060578 | E22: ROA | F22: =C24 -> -0.0018099561
B23: Asset Turnover (Revenue/Total assets) | C23: =Statement!AC126 -> 0.78487025 | E23: ROE | F23: =C26 -> -0.0031491108
B24: ROA | C24: =Statement!AC127 -> -0.0018099561 | E24: ROIC | F24: =Statement!AC140 -> -0.014540196
B25: Equity Multiplier (Total assets/Equity) | C25: =Statement!AC128 -> 1.7398824
B26: ROE | C26: =Statement!AC129 -> -0.0031491108
B29: Cash conversion cycle | E29: Liquidity ratios
B30: DSO | C30: =Statement!AC141 -> 64.26475 | E30: Debt/Equity | F30: =Statement!AC145 -> 0.17868985
B31: DIO | C31: =Statement!AC142 -> 0 | E31: Net Debt/Equity | F31: =Statement!AC146 -> -0.01747743
B32: DPO | C32: =Statement!AC143 -> 27.080231 | E32: Current ratio | F32: =Statement!AC148 -> 1.762457
B33: Net trade cycle | C33: =Statement!AC144 -> 37.184518 | E33: Quick ratio | F33: =Statement!AC147 -> 1.1287308
E34: Interest coverage | F34: =Statement!AC149 -> 1.4511052
B37: Earnings yields | E37: Payout ratios
B38: Earnings yield | C38: =Statement!AC162 -> -0.0014164827 | E38: Dividend payout ratio | F38: =Statement!AC168 -> 0
B39: FCF yield | C39: =Statement!AC161 -> 0.0099191999 | E39: Buyback payout ratio | F39: =Statement!AC169 -> 0
B40: Dividend yield | C40: =Statement!AC163 -> 0 | E40: Full payout ratio | F40: =Statement!AC170 -> 0
B41: Buyback yield | C41: =Statement!AC164 -> 0
B42: Total shareholder yield | C42: =Statement!AC165 -> 0
B45: Ownership | E45: Cash holdings
B46: Insider ownership | C46: =Statement!AC171 -> 0.050026265 | E46: Cash per share | F46: =Statement!AC172 -> 1.1751865
E47: Net cash per share | F47: =Statement!AC175 -> 0.10470268
E48: Net cash to market cap | F48: =Statement!AC176 -> 0.0079625593
B51: Stock based compensation | E51: CapEx usage
B52: Stock based compensation % OCF | C52: =Statement!AC173 -> 0.65032447 | E52: Capex to Revenue | F52: =Statement!AC177 -> 0.046981743
B53: Stock based compensation % Revenue | C53: =Statement!AC174 -> 0.117028 | E53: CapEx to OCF | F53: =Statement!AC178 -> 0.26107749
E54: CapEx to D&A | F54: =Statement!AC179 -> 0.64278594

Sheet Yearly Analysis
C2: =Statement!M2 -> 31.01.2022 | D2: =Statement!N2 -> 31.01.2023 | E2: =Statement!O2 -> 31.01.2024 | F2: =Statement!P2 -> 31.01.2025 | G2: =Statement!Q2 -> 31.01.2026
C3: =Statement!M3 -> 2022 | D3: =Statement!N3 -> 2023 | E3: =Statement!O3 -> 2024 | F3: =Statement!P3 -> 2025 | G3: =Statement!Q3 -> 2026 | I3: =Statement!AC3 -> TTM/YTD
B5: Overview
B6: Price | C6: =Statement!M120 -> 28.44 | D6: =Statement!N120 -> 36.19 | E6: =Statement!O120 -> 25.61 | F6: =Statement!P120 -> 29 | G6: =Statement!Q120 -> 13.43 | I6: =Statement!AC120 -> 12.61
B7: Market capitalization | C7: =Statement!M153 -> 1477344.2 | D7: =Statement!N153 -> 1930917.4 | E7: =Statement!O153 -> 1444071.1 | F7: =Statement!P153 -> 1704388 | G7: =Statement!Q153 -> 839630.17 | I7: =Statement!AC153 -> 816194.86
B8: Enterprise value | C8: =Statement!M154 -> 1176776.2 | D8: =Statement!N154 -> 1762131.4 | E8: =Statement!O154 -> 1368007.1 | F8: =Statement!P154 -> 1636361 | G8: =Statement!Q154 -> 865888.17 | I8: =Statement!AC154 -> 809695.86
B9: PE | C9: =Statement!M150 -> -12 | D9: =Statement!N150 -> -10.770833 | E9: =Statement!O150 -> -10.203187 | F9: =Statement!P150 -> -28.431373 | G9: =Statement!Q150 -> -83.9375 | I9: =Statement!AC150 -> -705.97403
B10: PS | C10: =Statement!M151 -> 6.6538234 | D10: =Statement!N151 -> 6.7559133 | E10: =Statement!O151 -> 3.9217264 | F10: =Statement!P151 -> 3.9782236 | G10: =Statement!Q151 -> 1.718463 | I10: =Statement!AC151 -> 1.5369177
B11: PB | C11: =Statement!M152 -> 3.5404147 | D11: =Statement!N152 -> 6.7087908 | E11: =Statement!O152 -> 5.7429979 | F11: =Statement!P152 -> 6.4363161 | G11: =Statement!Q152 -> 2.4200182 | I11: =Statement!AC152 -> 2.1049165
B12: EV/Revenue | C12: =Statement!M155 -> 5.5187342 | D12: =Statement!N155 -> 6.2729396 | E12: =Statement!O155 -> 3.8394917 | F12: =Statement!P155 -> 3.8978331 | G12: =Statement!Q155 -> 1.8017153 | I12: =Statement!AC155 -> 1.5945392
B13: EV/EBIT | C13: =Statement!M156 -> -10.073673 | D13: =Statement!N156 -> -9.9808071 | E13: =Statement!O156 -> -10.023572 | F13: =Statement!P156 -> -28.166015 | G13: =Statement!Q156 -> -130.95707 | I13: =Statement!AC156 -> 64.574197
B15: Margins
B16: Gross margin | C16: =Statement!M105 -> 0.61831424 | D16: =Statement!N105 -> 0.61102488 | E16: =Statement!O105 -> 0.65194682 | F16: =Statement!P105 -> 0.67858547 | G16: =Statement!Q105 -> 0.67930527 | I16: =Statement!AC105 -> 0.67519048
B17: Operating margin | C17: =Statement!M106 -> -0.54783734 | D17: =Statement!N106 -> -0.62850023 | E17: =Statement!O106 -> -0.38304626 | F17: =Statement!P106 -> -0.13838781 | G17: =Statement!Q106 -> -0.01375806 | I17: =Statement!AC106 -> 0.024693133
B18: Net margin | C18: =Statement!M107 -> -0.55414031 | D18: =Statement!N107 -> -0.62705493 | E18: =Statement!O107 -> -0.38418575 | F18: =Statement!P107 -> -0.13941207 | G18: =Statement!Q107 -> -0.019376143 | I18: =Statement!AC107 -> -0.0023060578
B20: Earnings quality
B21: Net income | C21: =Statement!M20 -> -118161 | D21: =Statement!N20 -> -176146 | E21: =Statement!O20 -> -136885 | F21: =Statement!P20 -> -58527 | G21: =Statement!Q20 -> -9312 | I21: =Statement!AC20 -> -1171
B22: Operating cash | C22: =Statement!M61 -> -74710 | D22: =Statement!N61 -> -90123 | E22: =Statement!O61 -> -32378 | F22: =Statement!P61 -> 32381 | G22: =Statement!Q61 -> 78814 | I22: =Statement!AC61 -> 91379
B23: Cash accruals | C23: =IF(OR(C21<=0, C22<=0),"N/A",C21-C22) -> N/A | D23: =IF(OR(D21<=0, D22<=0),"N/A",D21-D22) -> N/A | E23: =IF(OR(E21<=0, E22<=0),"N/A",E21-E22) -> N/A | F23: =IF(OR(F21<=0, F22<=0),"N/A",F21-F22) -> N/A | G23: =IF(OR(G21<=0, G22<=0),"N/A",G21-G22) -> N/A | I23: =IF(OR(I21<=0, I22<=0),"N/A",I21-I22) -> N/A
B25: DuPont Identity
B26: Profit Margin (Earnings/Revenue) | C26: =Statement!M125 -> -0.55414031 | D26: =Statement!N125 -> -0.62705493 | E26: =Statement!O125 -> -0.38418575 | F26: =Statement!P125 -> -0.13941207 | G26: =Statement!Q125 -> -0.019376143 | I26: =Statement!AC125 -> -0.0023060578
B27: Asset Turnover (Revenue/Total assets) | C27: =Statement!M126 -> 0.43123023 | D27: =Statement!N126 -> 0.75909927 | E27: =Statement!O126 -> 0.96212256 | F27: =Statement!P126 -> 1.0808362 | G27: =Statement!Q126 -> 0.72401061 | I27: =Statement!AC126 -> 0.78487025
B28: ROA | C28: =Statement!M127 -> -0.23896205 | D28: =Statement!N127 -> -0.47599694 | E28: =Statement!O127 -> -0.36963378 | F28: =Statement!P127 -> -0.15068162 | G28: =Statement!Q127 -> -0.014028533 | I28: =Statement!AC127 -> -0.0018099561
B29: Equity Multiplier (Total assets/Equity) | C29: =Statement!M128 -> 1.1849981 | D29: =Statement!N128 -> 1.2857282 | E29: =Statement!O128 -> 1.4727678 | F29: =Statement!P128 -> 1.4667797 | G29: =Statement!Q128 -> 1.9684941 | I29: =Statement!AC128 -> 1.7398824
B30: ROE | C30: =Statement!M129 -> -0.28316957 | D30: =Statement!N129 -> -0.61200268 | E30: =Statement!O129 -> -0.54438475 | F30: =Statement!P129 -> -0.22101674 | G30: =Statement!Q129 -> -0.027615085 | I30: =Statement!AC129 -> -0.0031491108
B32: Performance Indicators
B33: ROA | C33: =C28 -> -0.23896205 | D33: =D28 -> -0.47599694 | E33: =E28 -> -0.36963378 | F33: =F28 -> -0.15068162 | G33: =G28 -> -0.014028533 | I33: =I28 -> -0.0018099561
B34: ROE | C34: =C30 -> -0.28316957 | D34: =D30 -> -0.61200268 | E34: =E30 -> -0.54438475 | F34: =F30 -> -0.22101674 | G34: =G30 -> -0.027615085 | I34: =I30 -> -0.0031491108
B35: ROIC | C35: =Statement!M140 -> -1.0008997 | D35: =Statement!N140 -> -1.4832189 | E35: =Statement!O140 -> -0.77816803 | F35: =Statement!P140 -> -0.29523684 | G35: =Statement!Q140 -> -0.018191573 | I35: =Statement!AC140 -> -0.014540196
B37: Cash conversion cycle
B38: DSO | C38: =Statement!M141 -> 68.918179 | D38: =Statement!N141 -> 66.778719 | E38: =Statement!O141 -> 66.446987 | F38: =Statement!P141 -> 64.005176 | G38: =Statement!Q141 -> 74.013756 | I38: =Statement!AC141 -> 64.26475
B39: DIO | C39: =Statement!M142 -> 0 | D39: =Statement!N142 -> 0 | E39: =Statement!O142 -> 0 | F39: =Statement!P142 -> 0 | G39: =Statement!Q142 -> 0 | I39: =Statement!AC142 -> 0
B40: DPO | C40: =Statement!M143 -> 22.957131 | D40: =Statement!N143 -> 36.197022 | E40: =Statement!O143 -> 24.959076 | F40: =Statement!P143 -> 15.207657 | G40: =Statement!Q143 -> 27.180272 | I40: =Statement!AC143 -> 27.080231
B41: Net trade cycle | C41: =Statement!M144 -> 45.961047 | D41: =Statement!N144 -> 30.581697 | E41: =Statement!O144 -> 41.487911 | F41: =Statement!P144 -> 48.797519 | G41: =Statement!Q144 -> 46.833484 | I41: =Statement!AC144 -> 37.184518
B43: Liquidity ratios
B44: Debt/Equity | C44: =Statement!M145 -> 0.03173888 | D44: =Statement!N145 -> 0.027437383 | E44: =Statement!O145 -> 0.045559935 | F44: =Statement!P145 -> 0.061149965 | G44: =Statement!Q145 -> 0.29681472 | I44: =Statement!AC145 -> 0.17868985
B45: Net Debt/Equity | C45: =Statement!M146 -> -0.72030291 | D45: =Statement!N146 -> -0.58643106 | E45: =Statement!O146 -> -0.30250269 | F45: =Statement!P146 -> -0.25689179 | G45: =Statement!Q146 -> 0.077869083 | I45: =Statement!AC146 -> -0.01747743
B46: Quick ratio | C46: =Statement!M147 -> 5.1740998 | D46: =Statement!N147 -> 2.8856261 | E46: =Statement!O147 -> 1.383803 | F46: =Statement!P147 -> 1.3842558 | G46: =Statement!Q147 -> 0.93474168 | I46: =Statement!AC147 -> 1.1287308
B47: Current ratio | C47: =Statement!M148 -> 5.6457359 | D47: =Statement!N148 -> 3.3203988 | E47: =Statement!O148 -> 1.777023 | F47: =Statement!P148 -> 1.7828421 | G47: =Statement!Q148 -> 1.5271855 | I47: =Statement!AC148 -> 1.762457
B48: Interest coverage | C48: =Statement!M149 -> N/A | D48: =Statement!N149 -> N/A | E48: =Statement!O149 -> N/A | F48: =Statement!P149 -> N/A | G48: =Statement!Q149 -> N/A | I48: =Statement!AC149 -> 1.4511052
B50: Earnings yields
B51: Earnings yield | C51: =Statement!M162 -> -0.083333333 | D51: =Statement!N162 -> -0.092843327 | E51: =Statement!O162 -> -0.09800859 | F51: =Statement!P162 -> -0.035172414 | G51: =Statement!Q162 -> -0.011913626 | I51: =Statement!AC162 -> -0.0014164827
B52: FCF yield | C52: =Statement!M161 -> -0.095887604 | D52: =Statement!N161 -> -0.0906828 | E52: =Statement!O161 -> -0.089391722 | F52: =Statement!P161 -> -0.03443054 | G52: =Statement!Q161 -> -0.015524692 | I52: =Statement!AC161 -> 0.0099191999
B53: Dividend yield | C53: =Statement!M163 -> 0 | D53: =Statement!N163 -> 0 | E53: =Statement!O163 -> 0 | F53: =Statement!P163 -> 0 | G53: =Statement!Q163 -> 0 | I53: =Statement!AC163 -> 0
B54: Buyback yield | C54: =Statement!M164 -> 0 | D54: =Statement!N164 -> 0 | E54: =Statement!O164 -> 0 | F54: =Statement!P164 -> 0 | G54: =Statement!Q164 -> 0 | I54: =Statement!AC164 -> 0
B55: Total shareholder yield | C55: =Statement!M165 -> 0 | D55: =Statement!N165 -> 0 | E55: =Statement!O165 -> 0 | F55: =Statement!P165 -> 0 | G55: =Statement!Q165 -> 0 | I55: =Statement!AC165 -> 0
B57: Payout ratios
B58: Dividend payout ratio | C58: =Statement!M168 -> 0 | D58: =Statement!N168 -> 0 | E58: =Statement!O168 -> 0 | F58: =Statement!P168 -> 0 | G58: =Statement!Q168 -> 0 | I58: =Statement!AC168 -> 0
B59: Buyback payout ratio | C59: =Statement!M169 -> 0 | D59: =Statement!N169 -> 0 | E59: =Statement!O169 -> 0 | F59: =Statement!P169 -> 0 | G59: =Statement!Q169 -> 0 | I59: =Statement!AC169 -> 0
B60: Full payout ratio | C60: =Statement!M170 -> 0 | D60: =Statement!N170 -> 0 | E60: =Statement!O170 -> 0 | F60: =Statement!P170 -> 0 | G60: =Statement!Q170 -> 0 | I60: =Statement!AC170 -> 0
B62: Ownership
B63: Insider ownership | C63: =Statement!M171 -> 0.055673199 | D63: =Statement!N171 -> 0.058401274 | E63: =Statement!O171 -> 0.059091635 | F63: =Statement!P171 -> 0.056183216 | G63: =Statement!Q171 -> 0.051792255 | I63: =Statement!AC171 -> 0.050026265
B65: Cash holdings
B66: Cash per share | C66: =Statement!M172 -> 6.0411196 | D66: =Statement!N172 -> 3.311461 | E66: =Statement!O172 -> 1.5521308 | F66: =Statement!P172 -> 1.4329953 | G66: =Statement!Q172 -> 1.2150486 | I66: =Statement!AC172 -> 1.1751865
B67: Net cash per share | C67: =Statement!M175 -> 5.7861626 | D67: =Statement!N175 -> 3.1634523 | E67: =Statement!O175 -> 1.3489634 | F67: =Statement!P175 -> 1.1574729 | G67: =Statement!Q175 -> -0.43213798 | I67: =Statement!AC175 -> 0.10470268
B68: Net cash to market cap | C68: =Statement!M176 -> 0.20345157 | D68: =Statement!N176 -> 0.087412333 | E68: =Statement!O176 -> 0.052673308 | F68: =Statement!P176 -> 0.03991286 | G68: =Statement!Q176 -> -0.031273293 | I68: =Statement!AC176 -> 0.0079625593
B70: Stock Based Compensation
B71: Stock based compensation % OCF | C71: =Statement!M173 -> -0.48379066 | D71: =Statement!N173 -> -0.65216426 | E71: =Statement!O173 -> -2.2117796 | F71: =Statement!P173 -> 2.0683425 | G71: =Statement!Q173 -> 0.8558378 | I71: =Statement!AC173 -> 0.65032447
B72: Stock based compensation % Revenue | C72: =Statement!M174 -> 0.16950472 | D72: =Statement!N174 -> 0.20923071 | E72: =Statement!O174 -> 0.2009913 | F72: =Statement!P174 -> 0.15953532 | G72: =Statement!Q174 -> 0.14035219 | I72: =Statement!AC174 -> 0.117028
B74: CapEx Usage
B75: Capex to Revenue | C75: =Statement!M177 -> 0.14446638 | D75: =Statement!N177 -> 0.093278986 | E75: =Statement!O177 -> 0.070438031 | F75: =Statement!P177 -> 0.05738031 | G75: =Statement!Q177 -> 0.050764579 | I75: =Statement!AC177 -> 0.046981743
B76: CapEx to OCF | C76: =Statement!M178 -> -0.41232767 | D76: =Statement!N178 -> -0.29074709 | E76: =Statement!O178 -> -0.77512508 | F76: =Statement!P178 -> 0.74392391 | G76: =Statement!Q178 -> 0.3095516 | I76: =Statement!AC178 -> 0.26107749
B77: CapEx to D&A | C77: =Statement!M179 -> 1.4461083 | D77: =Statement!N179 -> 1.035528 | E77: =Statement!O179 -> 0.85112083 | F77: =Statement!P179 -> 0.86383849 | G77: =Statement!Q179 -> 0.77566528 | I77: =Statement!AC179 -> 0.64278594
B79: Growth rates
B80: Revenue | C80: =Statement!M91 -> 1 | D80: =Statement!N91 -> 0.31738521 | E80: =Statement!O91 -> 0.26837421 | F80: =Statement!P91 -> 0.17826039 | G80: =Statement!Q91 -> 0.14477398
B81: COGS | C81: =Statement!M92 -> 1 | D81: =Statement!N92 -> 0.34254436 | E81: =Statement!O92 -> 0.13493552 | F81: =Statement!P92 -> 0.088080896 | G81: =Statement!Q92 -> 0.14221027
B82: Gross Profit | C82: =Statement!M93 -> 1 | D82: =Statement!N93 -> 0.30185445 | E82: =Statement!O93 -> 0.35332055 | F82: =Statement!P93 -> 0.22640429 | G82: =Statement!Q93 -> 0.1459883
B83: OpEx | C83: =Statement!M99 -> 1 | D83: =Statement!N99 -> 0.40027427 | E83: =Statement!O99 -> 0.059081836 | F83: =Statement!P99 -> -0.069938471 | G83: =Statement!Q99 -> -0.028853331
B84: Operating Income | C84: =Statement!M100 -> -1 | D84: =Statement!N100 -> -0.51135537 | E84: =Statement!O100 -> 0.22697562 | F84: =Statement!P100 -> 0.57431546 | G84: =Statement!Q100 -> 0.88619034
B85: Net Income | C85: =Statement!M102 -> -1 | D85: =Statement!N102 -> -0.49072875 | E85: =Statement!O102 -> 0.22288897 | F85: =Statement!P102 -> 0.57243672 | G85: =Statement!Q102 -> 0.84089395
B88: Growth rates breakdown
B89: =Statement!B193 -> Subscription and related services | C89: =Statement!M193 -> 1 | D89: =Statement!N193 -> 0.35032561 | E89: =Statement!O193 -> 0.2826982 | F89: =Statement!P193 -> 0.18783094 | G89: =Statement!Q193 -> 0.11679304
B90: =Statement!B194 -> Payment solutions | C90: =Statement!M194 -> 1 | D90: =Statement!N194 -> 0.20194476 | E90: =Statement!O194 -> 0.20725296 | F90: =Statement!P194 -> 0.075362012 | G90: =Statement!Q194 -> 0.19381757
B91: =Statement!B195 -> Network solutions | C91: =Statement!M195 -> 1 | D91: =Statement!N195 -> 0.40079592 | E91: =Statement!O195 -> 0.30837196 | F91: =Statement!P195 -> 0.26295284 | G91: =Statement!Q195 -> 0.1489598
B93: Other growth rates
B94: Dividends | C94: =Statement!M199 -> 0 | D94: =Statement!N199 -> 0 | E94: =Statement!O199 -> 0 | F94: =Statement!P199 -> 0 | G94: =Statement!Q199 -> 0

Sheet Quarter analysis
C3: Latest 2 quarters | F3: YoY
C4: =Statement!Z2 -> 30.04.2026 | D4: =Statement!AA2 -> 31.07.2026 | F4: =Statement!W2 -> 31.07.2025 | G4: =Statement!AA2 -> 31.07.2026
B5: Income statement growth | C5: =Statement!Z3 -> Q1 2027 | D5: =Statement!AA3 -> Q2 2027 | F5: =Statement!W3 -> Q2 2026 | G5: =Statement!AA3 -> Q2 2027
B6: Revenue | C6: =Statement!Z5 -> 130935 | D6: =Statement!AA5 -> 129458 | F6: =Statement!W5 -> 117255 | G6: =Statement!AA5 -> 129458
B7: Growth | C7: =Statement!AA91 -> -0.011280406 | F7: =IF(F6=0, IF(G6=0,0,IF(G6>0,1,-1)), (G6-F6)/ABS(F6) ) -> 0.10407232
B8: COGS | C8: =Statement!Z6 -> 43334 | D8: =Statement!AA6 -> 43185 | F8: =Statement!W6 -> 37641 | G8: =Statement!AA6 -> 43185
B9: Growth | C9: =Statement!AA92 -> -0.0034384086 | F9: =IF(F8=0, IF(G8=0,0,IF(G8>0,1,-1)), (G8-F8)/ABS(F8) ) -> 0.1472862
B10: Gross Profit | C10: =Statement!Z7 -> 87601 | D10: =Statement!AA7 -> 86273 | F10: =Statement!W7 -> 79614 | G10: =Statement!AA7 -> 86273
B11: Growth | C11: =Statement!AA93 -> -0.015159644 | F11: =IF(F10=0, IF(G10=0,0,IF(G10>0,1,-1)), (G10-F10)/ABS(F10) ) -> 0.083641068
B12: OpEx | C12: =Statement!Z13 -> 80852 | D12: =Statement!AA13 -> 78665 | F12: =Statement!W13 -> 81121 | G12: =Statement!AA13 -> 78665
B13: Growth | C13: =Statement!AA99 -> -0.027049424 | F13: =IF(F12=0, IF(G12=0,0,IF(G12>0,1,-1)), (G12-F12)/ABS(F12) ) -> -0.030275761
B14: Operating profit | C14: =Statement!Z14 -> 6749 | D14: =Statement!AA14 -> 7608 | F14: =Statement!W14 -> -1507 | G14: =Statement!AA14 -> 7608
B15: Growth | C15: =Statement!AA100 -> 0.12727812 | F15: =IF(F14=0, IF(G14=0,0,IF(G14>0,1,-1)), (G14-F14)/ABS(F14) ) -> 6.0484406
B16: Net income | C16: =Statement!Z20 -> 2963 | D16: =Statement!AA20 -> 1918 | F16: =Statement!W20 -> 654 | G16: =Statement!AA20 -> 1918
B17: Growth | C17: =Statement!AA102 -> -0.35268309 | F17: =IF(F16=0, IF(G16=0,0,IF(G16>0,1,-1)), (G16-F16)/ABS(F16) ) -> 1.9327217
B18: Diluted shares outstanding | C18: =Statement!Z24 -> 62041 | D18: =Statement!AA24 -> 62463 | F18: =Statement!W24 -> 61686 | G18: =Statement!AA24 -> 62463
B19: Growth | C19: =IF(C18=0, IF(D18=0,0,IF(D18>0,1,-1)), (D18-C18)/ABS(C18) ) -> 0.0068019535 | F19: =IF(F18=0, IF(G18=0,0,IF(G18>0,1,-1)), (G18-F18)/ABS(F18) ) -> 0.012596051
B20: Diluted EPS | C20: =Statement!Z28 -> 0.05 | D20: =Statement!AA28 -> 0.03 | F20: =Statement!W28 -> 0.01 | G20: =Statement!AA28 -> 0.03
B21: Growth | C21: =IF(C20=0, IF(D20=0,0,IF(D20>0,1,-1)), (D20-C20)/ABS(C20) ) -> -0.4 | F21: =IF(F20=0, IF(G20=0,0,IF(G20>0,1,-1)), (G20-F20)/ABS(F20) ) -> 2
B23: Revenue breakdown | C23: =C5 -> Q1 2027 | D23: =D5 -> Q2 2027 | F23: =F5 -> Q2 2026 | G23: =G5 -> Q2 2027
B24: =Statement!B193 -> Subscription and related services | C24: =Statement!Z187 -> 52721 | D24: =Statement!AA187 -> 52695 | F24: =Statement!W187 -> 53702 | G24: =Statement!AA187 -> 52695
B25: Growth | C25: =IF(C24=0, IF(D24=0,0,IF(D24>0,1,-1)), (D24-C24)/ABS(C24) ) -> -0.00049316212 | F25: =IF(F24=0, IF(G24=0,0,IF(G24>0,1,-1)), (G24-F24)/ABS(F24) ) -> -0.018751629
B26: =Statement!B194 -> Payment solutions | C26: =Statement!Z188 -> 41941 | D26: =Statement!AA188 -> 38489 | F26: =Statement!W188 -> 28392 | G26: =Statement!AA188 -> 38489
B27: Growth | C27: =IF(C26=0, IF(D26=0,0,IF(D26>0,1,-1)), (D26-C26)/ABS(C26) ) -> -0.082306097 | F27: =IF(F26=0, IF(G26=0,0,IF(G26>0,1,-1)), (G26-F26)/ABS(F26) ) -> 0.35562835
B28: =Statement!B195 -> Network solutions | C28: =Statement!Z189 -> 36273 | D28: =Statement!AA189 -> 38274 | F28: =Statement!W189 -> 35161 | G28: =Statement!AA189 -> 38274
B29: Growth | C29: =IF(C28=0, IF(D28=0,0,IF(D28>0,1,-1)), (D28-C28)/ABS(C28) ) -> 0.055164999 | F29: =IF(F28=0, IF(G28=0,0,IF(G28>0,1,-1)), (G28-F28)/ABS(F28) ) -> 0.088535593
B31: Metrics growth | C31: =C5 -> Q1 2027 | D31: =D5 -> Q2 2027 | F31: =F5 -> Q2 2026 | G31: =G5 -> Q2 2027
B32: =Statement!B209 -> AHSC | C32: =Statement!Z209 -> 4708 | D32: =Statement!AA209 -> 4744 | F32: =Statement!W209 -> 4467 | G32: =Statement!AA209 -> 4744
B33: Growth | C33: =IF(C32=0, IF(D32=0,0,IF(D32>0,1,-1)), (D32-C32)/ABS(C32) ) -> 0.007646559 | F33: =IF(F32=0, IF(G32=0,0,IF(G32>0,1,-1)), (G32-F32)/ABS(F32) ) -> 0.062010298
B34: =Statement!B210 -> Avg subscription revenue per AHSC | C34: =Statement!Z210 -> 11.198173 | D34: =Statement!AA210 -> 11.107715 | F34: =Statement!W210 -> 12.021939 | G34: =Statement!AA210 -> 11.107715
B35: Growth | C35: =IF(C34=0, IF(D34=0,0,IF(D34>0,1,-1)), (D34-C34)/ABS(C34) ) -> -0.0080779526 | F35: =IF(F34=0, IF(G34=0,0,IF(G34>0,1,-1)), (G34-F34)/ABS(F34) ) -> -0.076046275

Sheet Graphs Year
C55: =Statement!H2 -> 0 | D55: =Statement!I2 -> 0 | E55: =Statement!J2 -> 0 | F55: =Statement!K2 -> 0 | G55: =Statement!L2 -> 0 | H55: =Statement!M2 -> 31.01.2022 | I55: =Statement!N2 -> 31.01.2023 | J55: =Statement!O2 -> 31.01.2024 | ... L55: =Statement!Q2 -> 31.01.2026
C56: =Statement!H3 -> 0 | D56: =Statement!I3 -> 0 | E56: =Statement!J3 -> 0 | F56: =Statement!K3 -> 0 | G56: =Statement!L3 -> 0 | H56: =Statement!M3 -> 2022 | I56: =Statement!N3 -> 2023 | J56: =Statement!O3 -> 2024 | ... L56: =Statement!Q3 -> 2026
B57: Revenue | C57: =Statement!H5 -> 0 | D57: =Statement!I5 -> 0 | E57: =Statement!J5 -> 0 | F57: =Statement!K5 -> 0 | G57: =Statement!L5 -> 0 | H57: =Statement!M5 -> 213233 | I57: =Statement!N5 -> 280910 | J57: =Statement!O5 -> 356299 | ... L57: =Statement!Q5 -> 480591
B58: Operating income | C58: =Statement!H14 -> 0 | D58: =Statement!I14 -> 0 | E58: =Statement!J14 -> 0 | F58: =Statement!K14 -> 0 | G58: =Statement!L14 -> 0 | H58: =Statement!M14 -> -116817 | I58: =Statement!N14 -> -176552 | J58: =Statement!O14 -> -136479 | ... L58: =Statement!Q14 -> -6612
B59: Net income | C59: =Statement!H20 -> 0 | D59: =Statement!I20 -> 0 | E59: =Statement!J20 -> 0 | F59: =Statement!K20 -> 0 | G59: =Statement!L20 -> 0 | H59: =Statement!M20 -> -118161 | I59: =Statement!N20 -> -176146 | J59: =Statement!O20 -> -136885 | ... L59: =Statement!Q20 -> -9312
B60: FCFE | C60: =Statement!H157 -> 0 | D60: =Statement!I157 -> 0 | E60: =Statement!J157 -> 0 | F60: =Statement!K157 -> 0 | G60: =Statement!L157 -> 0 | H60: =Statement!M157 -> -141659 | I60: =Statement!N157 -> -175101 | J60: =Statement!O157 -> -129088 | ... L60: =Statement!Q157 -> -13035
B61: FCFF | C61: =Statement!H158 -> 0 | D61: =Statement!I158 -> 0 | E61: =Statement!J158 -> 0 | F61: =Statement!K158 -> 0 | G61: =Statement!L158 -> 0 | H61: =Statement!M158 -> -144891 | I61: =Statement!N158 -> -181313 | J61: =Statement!O158 -> -133726 | ... L61: =Statement!Q158 -> -13646
B62: Gross margin | C62: =Statement!H105 -> 0 | D62: =Statement!I105 -> 0 | E62: =Statement!J105 -> 0 | F62: =Statement!K105 -> 0 | G62: =Statement!L105 -> 0 | H62: =Statement!M105 -> 0.61831424 | I62: =Statement!N105 -> 0.61102488 | J62: =Statement!O105 -> 0.65194682 | ... L62: =Statement!Q105 -> 0.67930527
B63: Operating margin | C63: =Statement!H106 -> 0 | D63: =Statement!I106 -> 0 | E63: =Statement!J106 -> 0 | F63: =Statement!K106 -> 0 | G63: =Statement!L106 -> 0 | H63: =Statement!M106 -> -0.54783734 | I63: =Statement!N106 -> -0.62850023 | J63: =Statement!O106 -> -0.38304626 | ... L63: =Statement!Q106 -> -0.01375806
B64: Net margin | C64: =Statement!H107 -> 0 | D64: =Statement!I107 -> 0 | E64: =Statement!J107 -> 0 | F64: =Statement!K107 -> 0 | G64: =Statement!L107 -> 0 | H64: =Statement!M107 -> -0.55414031 | I64: =Statement!N107 -> -0.62705493 | J64: =Statement!O107 -> -0.38418575 | ... L64: =Statement!Q107 -> -0.019376143
B65: ="Revenue "&Statement!B193 -> Revenue Subscription and related services | C65: =Statement!H187 -> 0 | D65: =Statement!I187 -> 0 | E65: =Statement!J187 -> 0 | F65: =Statement!K187 -> 0 | G65: =Statement!L187 -> 0 | H65: =Statement!M187 -> 95514 | I65: =Statement!N187 -> 128975 | J65: =Statement!O187 -> 165436 | ... L65: =Statement!Q187 -> 219461
B66: ="Revenue "&Statement!B194 -> Revenue Payment solutions | C66: =Statement!H188 -> 0 | D66: =Statement!I188 -> 0 | E66: =Statement!J188 -> 0 | F66: =Statement!K188 -> 0 | G66: =Statement!L188 -> 0 | H66: =Statement!M188 -> 65201 | I66: =Statement!N188 -> 78368 | J66: =Statement!O188 -> 94610 | ... L66: =Statement!Q188 -> 121459
B67: ="Revenue "&Statement!B195 -> Revenue Network solutions | C67: =Statement!H189 -> 0 | D67: =Statement!I189 -> 0 | E67: =Statement!J189 -> 0 | F67: =Statement!K189 -> 0 | G67: =Statement!L189 -> 0 | H67: =Statement!M189 -> 52518 | I67: =Statement!N189 -> 73567 | J67: =Statement!O189 -> 96253 | ... L67: =Statement!Q189 -> 139671
B68: ROA | C68: =Statement!H127 -> 0 | D68: =Statement!I127 -> 0 | E68: =Statement!J127 -> 0 | F68: =Statement!K127 -> 0 | G68: =Statement!L127 -> 0 | H68: =Statement!M127 -> -0.23896205 | I68: =Statement!N127 -> -0.47599694 | J68: =Statement!O127 -> -0.36963378 | ... L68: =Statement!Q127 -> -0.014028533
B69: ROE | C69: =Statement!H129 -> 0 | D69: =Statement!I129 -> 0 | E69: =Statement!J129 -> 0 | F69: =Statement!K129 -> 0 | G69: =Statement!L129 -> 0 | H69: =Statement!M129 -> -0.28316957 | I69: =Statement!N129 -> -0.61200268 | J69: =Statement!O129 -> -0.54438475 | ... L69: =Statement!Q129 -> -0.027615085
B70: ROIC | C70: =Statement!H140 -> 0 | D70: =Statement!I140 -> 0 | E70: =Statement!J140 -> 0 | F70: =Statement!K140 -> 0 | G70: =Statement!L140 -> 0 | H70: =Statement!M140 -> -1.0008997 | I70: =Statement!N140 -> -1.4832189 | J70: =Statement!O140 -> -0.77816803 | ... L70: =Statement!Q140 -> -0.018191573
B71: Price 5y | C71: =Statement!H203 -> 0 | D71: =Statement!I203 -> 0 | E71: =Statement!J203 -> 0 | F71: =Statement!K203 -> 0 | G71: =Statement!L203 -> 0 | H71: =Statement!M203 -> 100 | I71: =Statement!N203 -> 127.25035 | J71: =Statement!O203 -> 90.049226 | ... L71: =Statement!Q203 -> 47.222222
B72: Revenue 5y | C72: =Statement!H204 -> 0 | D72: =Statement!I204 -> 0 | E72: =Statement!J204 -> 0 | F72: =Statement!K204 -> 0 | G72: =Statement!L204 -> 0 | H72: =Statement!M204 -> 100 | I72: =Statement!N204 -> 131.73852 | J72: =Statement!O204 -> 167.09374 | ... L72: =Statement!Q204 -> 225.38303
B73: EPS 5y | C73: =Statement!H205 -> 0 | D73: =Statement!I205 -> 0 | E73: =Statement!J205 -> 0 | F73: =Statement!K205 -> 0 | G73: =Statement!L205 -> 0 | H73: =Statement!M205 -> 100 | I73: =Statement!N205 -> 58.227848 | J73: =Statement!O205 -> 94.092827 | ... L73: =Statement!Q205 -> 193.24895

Sheet Graphs Quarter
C55: =Statement!T2 -> 31.10.2024 | D55: =Statement!U2 -> 31.01.2025 | E55: =Statement!V2 -> 30.04.2025 | F55: =Statement!W2 -> 31.07.2025 | G55: =Statement!X2 -> 31.10.2025 | H55: =Statement!Y2 -> 31.01.2026 | I55: =Statement!Z2 -> 30.04.2026 | J55: =Statement!AA2 -> 31.07.2026
C56: =Statement!T3 -> Q3 2025 | D56: =Statement!U3 -> Q4 2025 | E56: =Statement!V3 -> Q1 2026 | F56: =Statement!W3 -> Q2 2026 | G56: =Statement!X3 -> Q3 2026 | H56: =Statement!Y3 -> Q4 2026 | I56: =Statement!Z3 -> Q1 2027 | J56: =Statement!AA3 -> Q2 2027
B57: Revenue | C57: =Statement!T5 -> 106800 | D57: =Statement!U5 -> 109681 | E57: =Statement!V5 -> 115936 | F57: =Statement!W5 -> 117255 | G57: =Statement!X5 -> 120333 | H57: =Statement!Y5 -> 127067 | I57: =Statement!Z5 -> 130935 | J57: =Statement!AA5 -> 129458
B58: Operating income | C58: =Statement!T14 -> -13843 | D58: =Statement!U14 -> -7612 | E58: =Statement!V14 -> -3287 | F58: =Statement!W14 -> -1507 | G58: =Statement!X14 -> 3739 | H58: =Statement!Y14 -> -5557 | I58: =Statement!Z14 -> 6749 | J58: =Statement!AA14 -> 7608
B59: Net income | C59: =Statement!T20 -> -14403 | D59: =Statement!U20 -> -6390 | E59: =Statement!V20 -> -3914 | F59: =Statement!W20 -> 654 | G59: =Statement!X20 -> 4271 | H59: =Statement!Y20 -> -10323 | I59: =Statement!Z20 -> 2963 | J59: =Statement!AA20 -> 1918
B60: Gross margin | C60: =Statement!T105 -> 0.67661985 | D60: =Statement!U105 -> 0.69396705 | E60: =Statement!V105 -> 0.6716723 | F60: =Statement!W105 -> 0.67898171 | G60: =Statement!X105 -> 0.68398527 | H60: =Statement!Y105 -> 0.6821362 | I60: =Statement!Z105 -> 0.66904189 | J60: =Statement!AA105 -> 0.66641691
B61: Operating margin | C61: =Statement!T106 -> -0.1296161 | D61: =Statement!U106 -> -0.069401264 | E61: =Statement!V106 -> -0.028351849 | F61: =Statement!W106 -> -0.01285233 | G61: =Statement!X106 -> 0.031072108 | H61: =Statement!Y106 -> -0.043732834 | I61: =Statement!Z106 -> 0.05154466 | J61: =Statement!AA106 -> 0.058768095
B62: Net margin | C62: =Statement!T107 -> -0.13485955 | D62: =Statement!U107 -> -0.058259863 | E62: =Statement!V107 -> -0.033760006 | F62: =Statement!W107 -> 0.0055775873 | G62: =Statement!X107 -> 0.035493173 | H62: =Statement!Y107 -> -0.081240605 | I62: =Statement!Z107 -> 0.022629549 | J62: =Statement!AA107 -> 0.014815616
B63: ="Revenue "&Statement!B193 -> Revenue Subscription and related services | C63: =Statement!T187 -> 49363 | D63: =Statement!U187 -> 51793 | E63: =Statement!V187 -> 54355 | F63: =Statement!W187 -> 53702 | G63: =Statement!X187 -> 55480 | H63: =Statement!Y187 -> 55924 | I63: =Statement!Z187 -> 52721 | J63: =Statement!AA187 -> 52695
B64: ="Revenue "&Statement!B194 -> Revenue Payment solutions | C64: =Statement!T188 -> 24704 | D64: =Statement!U188 -> 24676 | E64: =Statement!V188 -> 29925 | F64: =Statement!W188 -> 28392 | G64: =Statement!X188 -> 27422 | H64: =Statement!Y188 -> 35720 | I64: =Statement!Z188 -> 41941 | J64: =Statement!AA188 -> 38489
B65: ="Revenue "&Statement!B195 -> Revenue Network solutions | C65: =Statement!T189 -> 32733 | D65: =Statement!U189 -> 33212 | E65: =Statement!V189 -> 31656 | F65: =Statement!W189 -> 35161 | G65: =Statement!X189 -> 37431 | H65: =Statement!Y189 -> 35423 | I65: =Statement!Z189 -> 36273 | J65: =Statement!AA189 -> 38274
B66: FCFE | C66: =Statement!T157 -> -14922 | D66: =Statement!U157 -> -7964 | E66: =Statement!V157 -> -9767 | F66: =Statement!W157 -> -6597 | G66: =Statement!X157 -> -7158 | H66: =Statement!Y157 -> 10487 | I66: =Statement!Z157 -> 2818 | J66: =Statement!AA157 -> 1949

Sheet Forecast ->
H5: Links
H6: Overview'!B3
H7: Financials ->'!B13
H8: Analysis ->'!B13
H9: Forecast ->'!B13
H10: Valuation ->'!B13
B13: Forecast ->

Sheet Revenue
B1: Revenue forecast
C2: History | H2: Forecast | S2: History | AA2: Forecast | AE2: TTM
C4: Revenues | S4: Revenues
B5: Revenues (thousand) | C5: =Statement!M3 -> 2022 | D5: =Statement!N3 -> 2023 | E5: =Statement!O3 -> 2024 | F5: =Statement!P3 -> 2025 | G5: =Statement!Q3 -> 2026 | H5: =G5+1 -> 2027 | I5: =H5+1 -> 2028 | J5: =I5+1 -> 2029 | K5: =J5+1 -> 2030 | L5: =K5+1 -> 2031 | R5: =B5 -> Revenues (thousand) | S5: =Statement!T3 -> Q3 2025 | T5: =Statement!U3 -> Q4 2025 | U5: =Statement!V3 -> Q1 2026 | V5: =Statement!W3 -> Q2 2026 | W5: =Statement!X3 -> Q3 2026 | X5: =Statement!Y3 -> Q4 2026 | Y5: =Statement!Z3 -> Q1 2027 | Z5: =Statement!AA3 -> Q2 2027 | AA5: FQ1 | AB5: FQ2 | AC5: FQ3 | AE5: FQ1
B6: =Statement!B187 -> Subscription and related services | C6: =Statement!M187 -> 95514 | D6: =Statement!N187 -> 128975 | E6: =Statement!O187 -> 165436 | F6: =Statement!P187 -> 196510 | G6: =Statement!Q187 -> 219461 | H6: =H25*H27 -> 236161.98 | I6: =I25*I27 -> 255285.2 | J6: =J25*J27 -> 274214.6 | K6: =K25*K27 -> 304652.42 | L6: =L25*L27 -> 346328.87 | N6: AHSC * avg sub revenue per AHSC | Q6: AHSC * avg sub revenue per AHSC | R6: =B6 -> Subscription and related services | S6: =Statement!T187 -> 49363 | T6: =Statement!U187 -> 51793 | U6: =Statement!V187 -> 54355 | V6: =Statement!W187 -> 53702 | W6: =Statement!X187 -> 55480 | X6: =Statement!Y187 -> 55924 | Y6: =Statement!Z187 -> 52721 | Z6: =Statement!AA187 -> 52695 | AA6: =AA25*AA27 -> 52689.731 | AE6: =SUM(X6:AA6) -> 214029.73
B7: =Statement!B188 -> Payment solutions | C7: =Statement!M188 -> 65201 | D7: =Statement!N188 -> 78368 | E7: =Statement!O188 -> 94610 | F7: =Statement!P188 -> 101740 | G7: =Statement!Q188 -> 121459 | H7: =H21*H23*H24 -> 132935.44 | I7: =I21*I23*I24 -> 139763.93 | J7: =J21*J23*J24 -> 148905.4 | K7: =K21*K23*K24 -> 159800.92 | L7: =L21*L23*L24 -> 171621.91 | N7: pacient payment volume * facilitator * take rate | Q7: pacient payment volume * facilitator * take rate | R7: =B7 -> Payment solutions | S7: =Statement!T188 -> 24704 | T7: =Statement!U188 -> 24676 | U7: =Statement!V188 -> 29925 | V7: =Statement!W188 -> 28392 | W7: =Statement!X188 -> 27422 | X7: =Statement!Y188 -> 35720 | Y7: =Statement!Z188 -> 41941 | Z7: =Statement!AA188 -> 38489 | AA7: =AA21*AA24 -> 37398 | AE7: =SUM(X7:AA7) -> 153548
B8: =Statement!B189 -> Network solutions | C8: =Statement!M189 -> 52518 | D8: =Statement!N189 -> 73567 | E8: =Statement!O189 -> 96253 | F8: =Statement!P189 -> 121563 | G8: =Statement!Q189 -> 139671 | H8: =H29*H33 -> 142906.53 | I8: =I29*I33 -> 149029.79 | J8: =J29*J33 -> 168084.37 | K8: =K29*K33 -> 205674.75 | L8: =L29*L33 -> 268479.6 | N8: annual patient visits * revenue per visit | Q8: network solutions per AHSC * AHSC | R8: =B8 -> Network solutions | S8: =Statement!T189 -> 32733 | T8: =Statement!U189 -> 33212 | U8: =Statement!V189 -> 31656 | V8: =Statement!W189 -> 35161 | W8: =Statement!X189 -> 37431 | X8: =Statement!Y189 -> 35423 | Y8: =Statement!Z189 -> 36273 | Z8: =Statement!AA189 -> 38274 | AA8: =AA25*AA29 -> 37497.038 | AE8: =SUM(X8:AA8) -> 147467.04
B9: Total | C9: =Statement!M5 -> 213233 | D9: =Statement!N5 -> 280910 | E9: =Statement!O5 -> 356299 | F9: =Statement!P5 -> 419813 | G9: =Statement!Q5 -> 480591 | H9: =SUM(H6:H8) -> 512003.95 | I9: =SUM(I6:I8) -> 544078.91 | J9: =SUM(J6:J8) -> 591204.37 | K9: =SUM(K6:K8) -> 670128.09 | L9: =SUM(L6:L8) -> 786430.37 | R9: Total | S9: =Statement!T5 -> 106800 | T9: =Statement!U5 -> 109681 | U9: =Statement!V5 -> 115936 | V9: =Statement!W5 -> 117255 | W9: =Statement!X5 -> 120333 | X9: =Statement!Y5 -> 127067 | Y9: =Statement!Z5 -> 130935 | Z9: =Statement!AA5 -> 129458 | AA9: =SUM(AA6:AA8) -> 127584.77 | AE9: =SUM(X9:AA9) -> 515044.77
C11: Growth rates | S11: Growth rates
B12: Revenue growth % | C12: =C5 -> 2022 | D12: =D5 -> 2023 | E12: =E5 -> 2024 | F12: =F5 -> 2025 | G12: =G5 -> 2026 | H12: =H5 -> 2027 | I12: =I5 -> 2028 | J12: =J5 -> 2029 | ... L12: =L5 -> 2031 | R12: Revenue growth % | S12: =S5 -> Q3 2025 | T12: =T5 -> Q4 2025 | U12: =U5 -> Q1 2026 | V12: =V5 -> Q2 2026 | W12: =W5 -> Q3 2026 | X12: =X5 -> Q4 2026 | Y12: =Y5 -> Q1 2027 | Z12: =Z5 -> Q2 2027 | ... AC12: =AC5 -> FQ3
B13: =B6 -> Subscription and related services | D13: =D6/C6-1 -> 0.35032561 | E13: =E6/D6-1 -> 0.2826982 | F13: =F6/E6-1 -> 0.18783094 | G13: =G6/F6-1 -> 0.11679304 | H13: =H6/G6-1 -> 0.0761 | I13: =I6/H6-1 -> 0.080975 | J13: =J6/I6-1 -> 0.07415 | K13: =K6/J6-1 -> 0.111 | L13: =L6/K6-1 -> 0.1368 | R13: =R6 -> Subscription and related services | T13: =T6/S6-1 -> 0.049227154 | U13: =U6/T6-1 -> 0.049466144 | V13: =V6/U6-1 -> -0.012013614 | W13: =W6/V6-1 -> 0.033108637 | X13: =X6/W6-1 -> 0.0080028839 | Y13: =Y6/X6-1 -> -0.057274158 | Z13: =Z6/Y6-1 -> -0.00049316212 | AA13: =AA6/Z6-1 -> -0.0001
B14: =B7 -> Payment solutions | D14: =D7/C7-1 -> 0.20194476 | E14: =E7/D7-1 -> 0.20725296 | F14: =F7/E7-1 -> 0.075362012 | G14: =G7/F7-1 -> 0.19381757 | H14: =H7/G7-1 -> 0.094488181 | I14: =I7/H7-1 -> 0.051366935 | J14: =J7/I7-1 -> 0.065406556 | K14: =K7/J7-1 -> 0.073170732 | L14: =L7/K7-1 -> 0.073973214 | R14: =R7 -> Payment solutions | T14: =T7/S7-1 -> -0.0011334197 | U14: =U7/T7-1 -> 0.21271681 | V14: =V7/U7-1 -> -0.05122807 | W14: =W7/V7-1 -> -0.034164553 | X14: =X7/W7-1 -> 0.30260375 | Y14: =Y7/X7-1 -> 0.17416013 | Z14: =Z7/Y7-1 -> -0.082306097 | AA14: =AA7/Z7-1 -> -0.028345761
B15: =B8 -> Network solutions | D15: =D8/C8-1 -> 0.40079592 | E15: =E8/D8-1 -> 0.30837196 | F15: =F8/E8-1 -> 0.26295284 | G15: =G8/F8-1 -> 0.1489598 | H15: =H8/G8-1 -> 0.023165375 | I15: =I8/H8-1 -> 0.042848 | J15: =J8/I8-1 -> 0.1278575 | K15: =K8/J8-1 -> 0.22364 | L15: =L8/K8-1 -> 0.30536 | R15: =R8 -> Network solutions | T15: =T8/S8-1 -> 0.01463355 | U15: =U8/T8-1 -> -0.046850536 | V15: =V8/U8-1 -> 0.11072151 | W15: =W8/V8-1 -> 0.064560166 | X15: =X8/W8-1 -> -0.053645374 | Y15: =Y8/X8-1 -> 0.023995709 | Z15: =Z8/Y8-1 -> 0.055164999 | AA15: =AA8/Z8-1 -> -0.0203
B16: =B9 -> Total | D16: =D9/C9-1 -> 0.31738521 | E16: =E9/D9-1 -> 0.26837421 | F16: =F9/E9-1 -> 0.17826039 | G16: =G9/F9-1 -> 0.14477398 | H16: =H9/G9-1 -> 0.065363174 | I16: =I9/H9-1 -> 0.062645926 | J16: =J9/I9-1 -> 0.086615102 | K16: =K9/J9-1 -> 0.13349652 | L16: =L9/K9-1 -> 0.17355231 | R16: =R9 -> Total | T16: =T9/S9-1 -> 0.026975655 | U16: =U9/T9-1 -> 0.057029021 | V16: =V9/U9-1 -> 0.011376967 | W16: =W9/V9-1 -> 0.02625048 | X16: =X9/W9-1 -> 0.055961374 | Y16: =Y9/X9-1 -> 0.030440634 | Z16: =Z9/Y9-1 -> -0.011280406 | AA16: =AA9/Z9-1 -> -0.014469803
C19: Drivers and metrics | S19: Drivers and metrics | AE19: =AE4 -> 0
B20: Metric (thousand) | C20: =C5 -> 2022 | D20: =D5 -> 2023 | E20: =E5 -> 2024 | F20: =F5 -> 2025 | G20: =G5 -> 2026 | H20: =H5 -> 2027 | I20: =I5 -> 2028 | J20: =J5 -> 2029 | ... L20: =L5 -> 2031 | R20: Metric (thousand) | S20: =S5 -> Q3 2025 | T20: =T5 -> Q4 2025 | U20: =U5 -> Q1 2026 | V20: =V5 -> Q2 2026 | W20: =W5 -> Q3 2026 | X20: =X5 -> Q4 2026 | Y20: =Y5 -> Q1 2027 | Z20: =Z5 -> Q2 2027 | ... AC20: =AC5 -> FQ3 | AE20: =AE5 -> FQ1
B21: Patient payment volume | C21: =Statement!M211 -> 2768000 | D21: =Statement!N211 -> 3284000 | E21: =Statement!O211 -> 3947000 | F21: =Statement!P211 -> 4420000 | G21: =Statement!Q211 -> 4873000 | H21: =G21*(1+H22) -> 5360300 | I21: =H21*(1+I22) -> 5949933 | J21: =I21*(1+J22) -> 6485427 | K21: =J21*(1+K22) -> 7133969.7 | L21: =K21*(1+L22) -> 7847366.6 | N21: Patient payment volume growth | Q21: Patient payment volume growth | R21: Patient payment volume | S21: =Statement!T211 -> 1081000 | T21: =Statement!U211 -> 1080000 | U21: =Statement!V211 -> 1314000 | V21: =Statement!W211 -> 1250000 | W21: =Statement!X211 -> 1181000 | X21: =Statement!Y211 -> 1128000 | Y21: =Statement!Z211 -> 1786000 | Z21: =Statement!AA211 -> 1626000 | AA21: =Z21*(1+AA22) -> 1626000 | AE21: =SUM(X21:AA21) -> 6166000
B22: Patient payment volume growth | D22: =(D21-C21)/C21 -> 0.18641618 | E22: =(E21-D21)/D21 -> 0.20188794 | F22: =(F21-E21)/E21 -> 0.11983785 | G22: =(G21-F21)/F21 -> 0.10248869 | H22: 0.1 | I22: 0.11 | J22: 0.09 | K22: 0.1 | L22: 0.1 | R22: Patient payment volume growth | T22: =(T21-S21)/S21 -> -0.00092506938 | U22: =(U21-T21)/T21 -> 0.21666667 | V22: =(V21-U21)/U21 -> -0.04870624 | W22: =(W21-V21)/V21 -> -0.0552 | X22: =(X21-W21)/W21 -> -0.044877223 | Y22: =(Y21-X21)/X21 -> 0.58333333 | Z22: =(Z21-Y21)/Y21 -> -0.089585666 | AA22: 0
B23: Payment facilitator volume | C23: =Statement!M212 -> 0.79 | D23: =Statement!N212 -> 0.8 | E23: =Statement!O212 -> 0.82 | F23: =Statement!P212 -> 0.81 | G23: =Statement!Q212 -> 0.83 | H23: 0.8 | I23: 0.81 | J23: 0.82 | K23: 0.8 | L23: 0.81 | R23: Payment facilitator volume | S23: =Statement!T212 -> 0.81 | T23: =Statement!U212 -> 0.82 | U23: =Statement!V212 -> 0.82 | V23: =Statement!W212 -> 0.82 | W23: =Statement!X212 -> 0.85 | X23: =Statement!Y212 -> 0.84 | Y23: =Statement!Z212 -> 0 | Z23: =Statement!AA212 -> 0 | AA23: 0 | AE23: =AA23 -> 0
B24: Take rate | C24: =Statement!M213 -> 0.0298 | D24: =Statement!N213 -> 0.0298 | E24: =Statement!O213 -> 0.0292 | F24: =Statement!P213 -> 0.0283 | G24: =Statement!Q213 -> 0.030029991 | H24: 0.031 | I24: 0.029 | J24: 0.028 | K24: 0.028 | L24: 0.027 | R24: Take rate | S24: =Statement!T213 -> 0.028 | T24: =Statement!U213 -> 0.028 | U24: =Statement!V213 -> 0.028 | V24: =Statement!W213 -> 0.028 | W24: =Statement!X213 -> 0.027 | X24: =Statement!Y213 -> 0.037698413 | Y24: =Statement!Z213 -> 0.023 | Z24: =Statement!AA213 -> 0.024 | AA24: 0.023
B25: AHSC | C25: =Statement!M209 -> 2074 | D25: =Statement!N209 -> 2856 | E25: =Statement!O209 -> 3601 | F25: =Statement!P209 -> 4203 | G25: =Statement!Q209 -> 4514 | H25: =G25*(1+H26) -> 4762.27 | I25: =H25*(1+I26) -> 5071.8175 | J25: =I25*(1+J26) -> 5502.922 | K25: =J25*(1+K26) -> 6053.2142 | L25: =K25*(1+L26) -> 6779.6 | N25: AHSC growth | Q25: AHSC growth | R25: AHSC | S25: =Statement!T209 -> 4237 | T25: =Statement!U209 -> 4341 | U25: =Statement!V209 -> 4411 | V25: =Statement!W209 -> 4467 | W25: =Statement!X209 -> 4520 | X25: =Statement!Y209 -> 4658 | Y25: =Statement!Z209 -> 4708 | Z25: =Statement!AA209 -> 4744 | AA25: =Z25*(1+AA26) -> 4791.44 | AE25: =AA25 -> 4791.44
B26: AHSC Growth | D26: =(D25-C25)/C25 -> 0.37704918 | E26: =(E25-D25)/D25 -> 0.26085434 | F26: =(F25-E25)/E25 -> 0.16717578 | G26: =(G25-F25)/F25 -> 0.073994766 | H26: 0.055 | I26: 0.065 | J26: 0.085 | K26: 0.1 | L26: 0.12 | R26: AHSC Growth | T26: =(T25-S25)/S25 -> 0.024545669 | U26: =(U25-T25)/T25 -> 0.016125317 | V26: =(V25-U25)/U25 -> 0.012695534 | W26: =(W25-V25)/V25 -> 0.011864786 | X26: =(X25-W25)/W25 -> 0.030530973 | Y26: =(Y25-X25)/X25 -> 0.010734221 | Z26: =(Z25-Y25)/Y25 -> 0.007646559 | AA26: 0.01
B27: Avg subscription revenue per AHSC | C27: =Statement!M210 -> 46.053038 | D27: =Statement!N210 -> 45.159314 | E27: =Statement!O210 -> 45.941683 | F27: =Statement!P210 -> 46.754699 | G27: =Statement!Q210 -> 48.617856 | H27: =G27*(1+H28) -> 49.590213 | I27: =H27*(1+I28) -> 50.334066 | J27: =I27*(1+J28) -> 49.830725 | K27: =J27*(1+K28) -> 50.329032 | L27: =K27*(1+L28) -> 51.083968 | N27: Avg revenue per AHSC growth | Q27: Avg revenue per AHSC growth | R27: Avg subscription revenue per AHSC | S27: =Statement!T210 -> 11.65046 | T27: =Statement!U210 -> 11.931122 | U27: =Statement!V210 -> 12.322603 | V27: =Statement!W210 -> 12.021939 | W27: =Statement!X210 -> 12.274336 | X27: =Statement!Y210 -> 12.006011 | Y27: =Statement!Z210 -> 11.198173 | Z27: =Statement!AA210 -> 11.107715 | AA27: =Z27*(1+AA28) -> 10.996638 | AE27: =SUM(X27:AA27) -> 45.308537
B28: Avg revenue AHSC growth | D28: =(D27-C27)/C27 -> -0.019406405 | E28: =(E27-D27)/D27 -> 0.017324646 | F28: =(F27-E27)/E27 -> 0.0176967 | G28: =(G27-F27)/F27 -> 0.03984961 | H28: 0.02 | I28: 0.015 | J28: -0.01 | K28: 0.01 | L28: 0.015 | R28: Avg revenue AHSC growth | T28: =(T27-S27)/S27 -> 0.024090175 | U28: =(U27-T27)/T27 -> 0.032811728 | V28: =(V27-U27)/U27 -> -0.024399385 | W28: =(W27-V27)/V27 -> 0.020994752 | X28: =(X27-W27)/W27 -> -0.021860662 | Y28: =(Y27-X27)/X27 -> -0.067286114 | Z28: =(Z27-Y27)/Y27 -> -0.0080779526 | AA28: -0.01
B29: Annual patient visits | D29: =Statement!N214 -> 120000 | E29: =Statement!O214 -> 150000 | F29: =Statement!P214 -> 170000 | G29: =Statement!Q214 -> 180000 | H29: =H25*H31 -> 183253.5 | I29: =I25*I31 -> 187358.38 | J29: =J25*J31 -> 201251 | K29: =K25*K31 -> 228017.39 | L29: =L25*L31 -> 268148.45 | N29: AHSC * patient visit per AHSC | Q29: Network revenue per AHSC growth | R29: Network solutions revenue per AHSC | S29: =Statement!T217 -> 7.7255133 | T29: =Statement!U217 -> 7.6507717 | U29: =Statement!V217 -> 7.1766039 | V29: =Statement!W217 -> 7.8712783 | W29: =Statement!X217 -> 8.2811947 | X29: =Statement!Y217 -> 7.604766 | Y29: =Statement!Z217 -> 7.7045455 | Z29: =Statement!AA217 -> 8.0678752 | AA29: =Z29*(1+AA30) -> 7.825839 | AE29: =SUM(X29:AA29) -> 31.203026
B30: Annual patient visits growth | E30: =(E29-D29)/D29 -> 0.25 | F30: =(F29-E29)/E29 -> 0.13333333 | G30: =(G29-F29)/F29 -> 0.058823529 | H30: =(H29-G29)/G29 -> 0.018075 | I30: =(I29-H29)/H29 -> 0.0224 | J30: =(J29-I29)/I29 -> 0.07415 | K30: =(K29-J29)/J29 -> 0.133 | L30: =(L29-K29)/K29 -> 0.176 | R30: Nw solutions revenue growth | T30: =(T29-S29)/S29 -> -0.0096746482 | U30: =(U29-T29)/T29 -> -0.061976463 | V30: =(V29-U29)/U29 -> 0.096797082 | W30: =(W29-V29)/V29 -> 0.052077492 | X30: =(X29-W29)/W29 -> -0.081682501 | Y30: =(Y29-X29)/X29 -> 0.013120648 | Z30: =(Z29-Y29)/Y29 -> 0.047157844 | AA30: -0.03
B31: Patient visits per AHSC | D31: =Statement!N215 -> 42.016807 | E31: =Statement!O215 -> 41.655096 | F31: =Statement!P215 -> 40.4473 | G31: =Statement!Q215 -> 39.875942 | H31: =G31*(1+H32) -> 38.480284 | I31: =H31*(1+I32) -> 36.941072 | J31: =I31*(1+J32) -> 36.571661 | K31: =J31*(1+K32) -> 37.668811 | L31: =K31*(1+L32) -> 39.552252 | N31: Patient visit per AHSC growth
B32: Patient visit per AHSC growth | E32: =(E31-D31)/D31 -> -0.0086087198 | F32: =(F31-E31)/E31 -> -0.028995162 | G32: =(G31-F31)/F31 -> -0.014125987 | H32: -0.035 | I32: -0.04 | J32: -0.01 | K32: 0.03 | L32: 0.05
B33: Revenue per visit | D33: =Statement!N216 -> 0.61305833 | E33: =Statement!O216 -> 0.64168667 | F33: =Statement!P216 -> 0.71507647 | G33: =Statement!Q216 -> 0.77595 | H33: =G33*(1+H34) -> 0.77982975 | I33: =H33*(1+I34) -> 0.79542634 | J33: =I33*(1+J34) -> 0.83519766 | K33: =J33*(1+K34) -> 0.90201348 | L33: =K33*(1+L34) -> 1.001235 | N33: Revenue per visit growth
B34: Revenue per visit growth | E34: =(E33-D33)/D33 -> 0.046697568 | F34: =(F33-E33)/E33 -> 0.11437016 | G34: =(G33-F33)/F33 -> 0.085128699 | H34: 0.005 | I34: 0.02 | J34: 0.05 | K34: 0.08 | L34: 0.11

Sheet COGS & OpEx
B1: COGS & OpEx forecast
C2: History | H2: Forecast | P2: History | X2: Forecast | AB2: TTM
C4: Revenues | P4: Revenues
B5: =Revenue!B5 -> Revenues (thousand) | C5: =Revenue!C5 -> 2022 | D5: =Revenue!D5 -> 2023 | E5: =Revenue!E5 -> 2024 | F5: =Revenue!F5 -> 2025 | G5: =Revenue!G5 -> 2026 | H5: =G5+1 -> 2027 | I5: =H5+1 -> 2028 | J5: =I5+1 -> 2029 | K5: =J5+1 -> 2030 | L5: =K5+1 -> 2031 | O5: Revenues (thousand) | P5: =Revenue!S5 -> Q3 2025 | Q5: =Revenue!T5 -> Q4 2025 | R5: =Revenue!U5 -> Q1 2026 | S5: =Revenue!V5 -> Q2 2026 | T5: =Revenue!W5 -> Q3 2026 | U5: =Revenue!X5 -> Q4 2026 | V5: =Revenue!Y5 -> Q1 2027 | W5: =Revenue!Z5 -> Q2 2027 | X5: FQ1 | Y5: FQ2 | Z5: FQ3 | AB5: =Revenue!AE5 -> FQ1
B6: Revenue | C6: =Revenue!C9 -> 213233 | D6: =Revenue!D9 -> 280910 | E6: =Revenue!E9 -> 356299 | F6: =Revenue!F9 -> 419813 | G6: =Revenue!G9 -> 480591 | H6: =Revenue!H9 -> 512003.95 | I6: =Revenue!I9 -> 544078.91 | J6: =Revenue!J9 -> 591204.37 | ... L6: =Revenue!L9 -> 786430.37 | O6: Revenue | P6: =Revenue!S9 -> 106800 | Q6: =Revenue!T9 -> 109681 | R6: =Revenue!U9 -> 115936 | S6: =Revenue!V9 -> 117255 | T6: =Revenue!W9 -> 120333 | U6: =Revenue!X9 -> 127067 | V6: =Revenue!Y9 -> 130935 | W6: =Revenue!Z9 -> 129458 | X6: =Revenue!AA9 -> 127584.77 | AB6: =Revenue!AE9 -> 515044.77
C9: COGS and OpEx | P9: COGS & OpEx | AB9: =AB4 -> 0
B10: Expenses (tnousand) | C10: =C5 -> 2022 | D10: =D5 -> 2023 | E10: =E5 -> 2024 | F10: =F5 -> 2025 | G10: =G5 -> 2026 | H10: =H5 -> 2027 | I10: =I5 -> 2028 | J10: =J5 -> 2029 | ... L10: =L5 -> 2031 | O10: Expenses (thousand) | P10: =P5 -> Q3 2025 | Q10: =Q5 -> Q4 2025 | R10: =R5 -> Q1 2026 | S10: =S5 -> Q2 2026 | T10: =T5 -> Q3 2026 | U10: =U5 -> Q4 2026 | V10: =V5 -> Q1 2027 | W10: =W5 -> Q2 2027 | ... Z10: =Z5 -> FQ3 | AB10: =AB5 -> FQ1
B11: COGS | C11: =Statement!M6 -> 81388 | D11: =Statement!N6 -> 109267 | E11: =Statement!O6 -> 124011 | F11: =Statement!P6 -> 134934 | G11: =Statement!Q6 -> 154123 | H11: =H6*H22 -> 158721.23 | I11: =I6*I22 -> 157782.89 | J11: =J6*J22 -> 165537.22 | K11: =K6*K22 -> 187635.87 | L11: =L6*L22 -> 228064.81 | O11: =B11 -> COGS | P11: =Statement!T6 -> 34537 | Q11: =Statement!U6 -> 33566 | R11: =Statement!V6 -> 38065 | S11: =Statement!W6 -> 37641 | T11: =Statement!X6 -> 38027 | U11: =Statement!Y6 -> 40390 | V11: =Statement!Z6 -> 43334 | W11: =Statement!AA6 -> 43185 | X11: =X6*X22 -> 40827.126 | AB11: =SUM(U11:X11) -> 167736.13
B12: =Statement!B8 -> Sales and marketing | C12: =Statement!M8 -> 106421 | D12: =Statement!N8 -> 151263 | E12: =Statement!O8 -> 147008 | F12: =Statement!P8 -> 121129 | G12: =Statement!Q8 -> 100243 | H12: =H6*H23 -> 107520.83 | I12: =I6*I23 -> 119697.36 | J12: =J6*J23 -> 124152.92 | K12: =K6*K23 -> 134025.62 | L12: =L6*L23 -> 157286.07 | O12: =B12 -> Sales and marketing | P12: =Statement!T8 -> 30071 | Q12: =Statement!U8 -> 28863 | R12: =Statement!V8 -> 26043 | S12: =Statement!W8 -> 25396 | T12: =Statement!X8 -> 24148 | U12: =Statement!Y8 -> 24656 | V12: =Statement!Z8 -> 24209 | W12: =Statement!AA8 -> 24587 | X12: =X23*X$6 -> 24241.106 | AB12: =SUM(U12:X12) -> 97693.106
B13: =Statement!B9 -> R&D | C13: =Statement!M9 -> 52265 | D13: =Statement!N9 -> 91244 | E13: =Statement!O9 -> 112346 | F13: =Statement!P9 -> 117364 | G13: =Statement!Q9 -> 121481 | H13: =H6*H24 -> 133121.03 | I13: =I6*I24 -> 141460.52 | J13: =J6*J24 -> 147801.09 | K13: =K6*K24 -> 147428.18 | L13: =L6*L24 -> 165150.38 | O13: =B13 -> R&D | P13: =Statement!T9 -> 29315 | Q13: =Statement!U9 -> 29626 | R13: =Statement!V9 -> 31829 | S13: =Statement!W9 -> 29274 | T13: =Statement!X9 -> 29453 | U13: =Statement!Y9 -> 30925 | V13: =Statement!Z9 -> 28328 | W13: =Statement!AA9 -> 27571 | X13: =X24*X$6 -> 29344.497 | AB13: =SUM(U13:X13) -> 116168.5
B14: =Statement!B10 -> General and administrative | C14: =Statement!M10 -> 68674 | D14: =Statement!N10 -> 80384 | E14: =Statement!O10 -> 79926 | F14: =Statement!P10 -> 76597 | G14: =Statement!Q10 -> 79903 | H14: =H6*H25 -> 79360.613 | I14: =I6*I25 -> 89228.942 | J14: =J6*J25 -> 94592.699 | K14: =K6*K25 -> 113921.78 | L14: =L6*L25 -> 125828.86 | O14: =B14 -> General and administrative | P14: =Statement!T10 -> 19633 | Q14: =Statement!U10 -> 18415 | R14: =Statement!V10 -> 16408 | S14: =Statement!W10 -> 19042 | T14: =Statement!X10 -> 17488 | U14: =Statement!Y10 -> 26965 | V14: =Statement!Z10 -> 18361 | W14: =Statement!AA10 -> 16512 | X14: =X25*X$6 -> 21689.411 | AB14: =SUM(U14:X14) -> 83527.411
B15: =Statement!B11 -> Depreciation | C15: =Statement!M11 -> 14985 | D15: =Statement!N11 -> 17988 | E15: =Statement!O11 -> 17584 | F15: =Statement!P11 -> 14183 | G15: =Statement!Q11 -> 12972 | H15: =H6*H26 -> 12288.095 | I15: =I6*I26 -> 13601.973 | J15: =J6*J26 -> 13597.7 | K15: =K6*K26 -> 13402.562 | L15: =L6*L26 -> 13369.316 | O15: =B15 -> Depreciation | P15: =Statement!T11 -> 3566 | Q15: =Statement!U11 -> 3172 | R15: =Statement!V11 -> 2986 | S15: =Statement!W11 -> 3279 | T15: =Statement!X11 -> 3199 | U15: =Statement!Y11 -> 3508 | V15: =Statement!Z11 -> 3371 | W15: =Statement!AA11 -> 3340 | X15: =X6*X26 -> 3827.543 | AB15: =SUM(U15:X15) -> 14046.543
B16: =Statement!B12 -> Amortization | C16: =Statement!M12 -> 6317 | D16: =Statement!N12 -> 7316 | E16: =Statement!O12 -> 11903 | F16: =Statement!P12 -> 13703 | G16: =Statement!Q12 -> 18481 | H16: =H6*H27 -> 20480.158 | I16: =I6*I27 -> 20674.999 | J16: =J6*J27 -> 18918.54 | K16: =K6*K27 -> 17423.33 | L16: =L6*L27 -> 17301.468 | O16: =B16 -> Amortization | P16: =Statement!T12 -> 3521 | Q16: =Statement!U12 -> 3651 | R16: =Statement!V12 -> 3892 | S16: =Statement!W12 -> 4130 | T16: =Statement!X12 -> 4279 | U16: =Statement!Y12 -> 6180 | V16: =Statement!Z12 -> 6583 | W16: =Statement!AA12 -> 6655 | X16: =X6*X27 -> 6379.2384 | AB16: =SUM(U16:X16) -> 25797.238
B17: OpEx | C17: =Statement!M13 -> 248662 | D17: =Statement!N13 -> 348195 | E17: =Statement!O13 -> 368767 | F17: =Statement!P13 -> 342976 | G17: =Statement!Q13 -> 333080 | H17: =SUM(H12:H16) -> 352770.72 | I17: =SUM(I12:I16) -> 384663.79 | J17: =SUM(J12:J16) -> 399062.95 | K17: =SUM(K12:K16) -> 426201.47 | L17: =SUM(L12:L16) -> 478936.1 | O17: =B17 -> OpEx | P17: =Statement!T13 -> 86106 | Q17: =Statement!U13 -> 83727 | R17: =Statement!V13 -> 81158 | S17: =Statement!W13 -> 81121 | T17: =Statement!X13 -> 78567 | U17: =Statement!Y13 -> 92234 | V17: =Statement!Z13 -> 80852 | W17: =Statement!AA13 -> 78665 | X17: =SUM(X12:X16) -> 85481.795 | AB17: =SUM(U17:X17) -> 337232.79
C20: Expenses % of Revenue | P20: Expenses % of Revenue
B21: % of revenue | C21: =C5 -> 2022 | D21: =D5 -> 2023 | E21: =E5 -> 2024 | F21: =F5 -> 2025 | G21: =G5 -> 2026 | H21: =H5 -> 2027 | I21: =I5 -> 2028 | J21: =J5 -> 2029 | ... L21: =L5 -> 2031 | O21: % of revenue | P21: =P5 -> Q3 2025 | Q21: =Q5 -> Q4 2025 | R21: =R5 -> Q1 2026 | S21: =S5 -> Q2 2026 | T21: =T5 -> Q3 2026 | U21: =U5 -> Q4 2026 | V21: =V5 -> Q1 2027 | W21: =W5 -> Q2 2027 | ... Z21: =Z5 -> FQ3
B22: =B11 -> COGS | C22: =C11/C$6 -> 0.38168576 | D22: =D11/D$6 -> 0.38897512 | E22: =E11/E$6 -> 0.34805318 | F22: =F11/F$6 -> 0.32141453 | G22: =G11/G$6 -> 0.32069473 | H22: 0.31 | I22: 0.29 | J22: 0.28 | K22: 0.28 | L22: 0.29 | O22: =O11 -> COGS | P22: =P11/P$6 -> 0.32338015 | Q22: =Q11/Q$6 -> 0.30603295 | R22: =R11/R$6 -> 0.3283277 | S22: =S11/S$6 -> 0.32101829 | T22: =T11/T$6 -> 0.31601473 | U22: =U11/U$6 -> 0.3178638 | V22: =V11/V$6 -> 0.33095811 | W22: =W11/W$6 -> 0.33358309 | X22: 0.32
B23: =B12 -> Sales and marketing | C23: =C12/C$6 -> 0.49908316 | D23: =D12/D$6 -> 0.53847496 | E23: =E12/E$6 -> 0.41259728 | F23: =F12/F$6 -> 0.28853085 | G23: =G12/G$6 -> 0.20858277 | H23: 0.21 | I23: 0.22 | J23: 0.21 | K23: 0.2 | L23: 0.2 | O23: =O12 -> Sales and marketing | P23: =P12/P$6 -> 0.28156367 | Q23: =Q12/Q$6 -> 0.26315406 | R23: =R12/R$6 -> 0.22463256 | S23: =S12/S$6 -> 0.21658778 | T23: =T12/T$6 -> 0.20067646 | U23: =U12/U$6 -> 0.19403937 | V23: =V12/V$6 -> 0.18489327 | W23: =W12/W$6 -> 0.1899226 | X23: 0.19
B24: =B13 -> R&D | C24: =C13/C$6 -> 0.24510746 | D24: =D13/D$6 -> 0.32481578 | E24: =E13/E$6 -> 0.31531382 | F24: =F13/F$6 -> 0.27956257 | G24: =G13/G$6 -> 0.25277419 | H24: 0.26 | I24: 0.26 | J24: 0.25 | K24: 0.22 | L24: 0.21 | O24: =O13 -> R&D | P24: =P13/P$6 -> 0.27448502 | Q24: =Q13/Q$6 -> 0.27011059 | R24: =R13/R$6 -> 0.2745394 | S24: =S13/S$6 -> 0.249661 | T24: =T13/T$6 -> 0.24476245 | U24: =U13/U$6 -> 0.24337554 | V24: =V13/V$6 -> 0.21635162 | W24: =W13/W$6 -> 0.21297255 | X24: 0.23
B25: =B14 -> General and administrative | C25: =C14/C$6 -> 0.32206084 | D25: =D14/D$6 -> 0.28615571 | E25: =E14/E$6 -> 0.22432283 | F25: =F14/F$6 -> 0.18245505 | G25: =G14/G$6 -> 0.16625988 | H25: 0.155 | I25: 0.164 | J25: 0.16 | K25: 0.17 | L25: 0.16 | O25: =O14 -> General and administrative | P25: =P14/P$6 -> 0.18382959 | Q25: =Q14/Q$6 -> 0.16789599 | R25: =R14/R$6 -> 0.14152636 | S25: =S14/S$6 -> 0.16239819 | T25: =T14/T$6 -> 0.14533004 | U25: =U14/U$6 -> 0.21221088 | V25: =V14/V$6 -> 0.14022989 | W25: =W14/W$6 -> 0.12754716 | X25: 0.17
B26: =B15 -> Depreciation | C26: =C15/C$6 -> 0.070275239 | D26: =D15/D$6 -> 0.064034744 | E26: =E15/E$6 -> 0.049351808 | F26: =F15/F$6 -> 0.03378409 | G26: =G15/G$6 -> 0.026991766 | H26: 0.024 | I26: 0.025 | J26: 0.023 | K26: 0.02 | L26: 0.017 | O26: =O15 -> Depreciation | P26: =P15/P$6 -> 0.033389513 | Q26: =Q15/Q$6 -> 0.028920232 | R26: =R15/R$6 -> 0.025755589 | S26: =S15/S$6 -> 0.027964692 | T26: =T15/T$6 -> 0.026584561 | U26: =U15/U$6 -> 0.027607483 | V26: =V15/V$6 -> 0.025745599 | W26: =W15/W$6 -> 0.025799873 | X26: 0.03
B27: =B16 -> Amortization | C27: =C16/C$6 -> 0.02962487 | D27: =D16/D$6 -> 0.026043929 | E27: =E16/E$6 -> 0.033407335 | F27: =F16/F$6 -> 0.032640723 | G27: =G16/G$6 -> 0.038454736 | H27: 0.04 | I27: 0.038 | J27: 0.032 | K27: 0.026 | L27: 0.022 | O27: =O16 -> Amortization | P27: =P16/P$6 -> 0.032968165 | Q27: =Q16/Q$6 -> 0.033287443 | R27: =R16/R$6 -> 0.033570246 | S27: =S16/S$6 -> 0.035222379 | T27: =T16/T$6 -> 0.035559655 | U27: =U16/U$6 -> 0.048635759 | V27: =V16/V$6 -> 0.050276855 | W27: =W16/W$6 -> 0.051406634 | X27: 0.05
B28: =B17 -> OpEx | C28: =C17/C$6 -> 1.1661516 | D28: =D17/D$6 -> 1.2395251 | E28: =E17/E$6 -> 1.0349931 | F28: =F17/F$6 -> 0.81697327 | G28: =G17/G$6 -> 0.69306333 | H28: =H17/H$6 -> 0.689 | I28: =I17/I$6 -> 0.707 | J28: =J17/J$6 -> 0.675 | ... L28: =L17/L$6 -> 0.609 | O28: =O17 -> OpEx | P28: =P17/P$6 -> 0.80623596 | Q28: =Q17/Q$6 -> 0.76336831 | R28: =R17/R$6 -> 0.70002415 | S28: =S17/S$6 -> 0.69183404 | T28: =T17/T$6 -> 0.65291317 | U28: =U17/U$6 -> 0.72586903 | V28: =V17/V$6 -> 0.61749723 | W28: =W17/W$6 -> 0.60764881 | X28: =X17/X$6 -> 0.67

Sheet WC & Investments
B1: Working Capital, Capex, D&A
C3: History | H3: Forecast
C5: Revenues
B6: Revenues (thousand) | C6: =Revenue!C5 -> 2022 | D6: =Revenue!D5 -> 2023 | E6: =Revenue!E5 -> 2024 | F6: =Revenue!F5 -> 2025 | G6: =Revenue!G5 -> 2026 | H6: =G6+1 -> 2027 | I6: =H6+1 -> 2028 | J6: =I6+1 -> 2029 | K6: =J6+1 -> 2030 | L6: =K6+1 -> 2031
B7: Revenue | C7: =Revenue!C9 -> 213233 | D7: =Revenue!D9 -> 280910 | E7: =Revenue!E9 -> 356299 | F7: =Revenue!F9 -> 419813 | G7: =Revenue!G9 -> 480591 | H7: =Revenue!H9 -> 512003.95 | I7: =Revenue!I9 -> 544078.91 | J7: =Revenue!J9 -> 591204.37 | ... L7: =Revenue!L9 -> 786430.37
B8: COGS | C8: ='COGS & OpEx'!C11 -> 81388 | D8: ='COGS & OpEx'!D11 -> 109267 | E8: ='COGS & OpEx'!E11 -> 124011 | F8: ='COGS & OpEx'!F11 -> 134934 | G8: ='COGS & OpEx'!G11 -> 154123 | H8: ='COGS & OpEx'!H11 -> 158721.23 | I8: ='COGS & OpEx'!I11 -> 157782.89 | J8: ='COGS & OpEx'!J11 -> 165537.22 | ... L8: ='COGS & OpEx'!L11 -> 228064.81
C11: Working Capital
B12: $ (thousand) | C12: =C6 -> 2022 | D12: =D6 -> 2023 | E12: =E6 -> 2024 | F12: =F6 -> 2025 | G12: =G6 -> 2026 | H12: =H6 -> 2027 | I12: =I6 -> 2028 | J12: =J6 -> 2029 | ... L12: =L6 -> 2031
B13: Accounts receivable | C13: =Statement!M32 -> 40262 | D13: =Statement!N32 -> 51394 | E13: =Statement!O32 -> 64863 | F13: =Statement!P32 -> 73617 | G13: =Statement!Q32 -> 97453 | H13: =H20*H7/365 -> 98192.539 | I13: =I20*I7/365 -> 104343.9 | J13: =J20*J7/365 -> 113381.66 | K13: =K20*K7/365 -> 128517.72 | L13: =L20*L7/365 -> 150822.26
B14: Inventory | C14: =Statement!M33 -> 0 | D14: =Statement!N33 -> 0 | E14: =Statement!O33 -> 0 | F14: =Statement!P33 -> 0 | G14: =Statement!Q33 -> 0 | H14: =H21*H8/365 -> 0 | I14: =I21*I8/365 -> 0 | J14: =J21*J8/365 -> 0 | K14: =K21*K8/365 -> 0 | L14: =L21*L8/365 -> 0
B15: Accounts payable | C15: =Statement!M40 -> 5119 | D15: =Statement!N40 -> 10836 | E15: =Statement!O40 -> 8480 | F15: =Statement!P40 -> 5622 | G15: =Statement!Q40 -> 11477 | H15: =H22*H8/365 -> 11306.169 | I15: =I22*I8/365 -> 11239.329 | J15: =J22*J8/365 -> 11791.693 | K15: =K22*K8/365 -> 13365.842 | L15: =L22*L8/365 -> 16245.712
C18: WC metrics and drivers
B19: Days | C19: =C6 -> 2022 | D19: =D6 -> 2023 | E19: =E6 -> 2024 | F19: =F6 -> 2025 | G19: =G6 -> 2026 | H19: =H6 -> 2027 | I19: =I6 -> 2028 | J19: =J6 -> 2029 | ... L19: =L6 -> 2031
B20: DSO | C20: =C13/C7*365 -> 68.918179 | D20: =D13/D7*365 -> 66.778719 | E20: =E13/E7*365 -> 66.446987 | F20: =F13/F7*365 -> 64.005176 | G20: =G13/G7*365 -> 74.013756 | H20: 70 | I20: 70 | J20: 70 | K20: 70 | L20: 70
B21: DIO | C21: =C14/C8*365 -> 0 | D21: =D14/D8*365 -> 0 | E21: =E14/E8*365 -> 0 | F21: =F14/F8*365 -> 0 | G21: =G14/G8*365 -> 0 | H21: 0 | I21: 0 | J21: 0 | K21: 0 | L21: 0
B22: DPO | C22: =C15/C8*365 -> 22.957131 | D22: =D15/D8*365 -> 36.197022 | E22: =E15/E8*365 -> 24.959076 | F22: =F15/F8*365 -> 15.207657 | G22: =G15/G8*365 -> 27.180272 | H22: 26 | I22: 26 | J22: 26 | K22: 26 | L22: 26
B23: Net trade cycle | C23: =C20+C21-C22 -> 45.961047 | D23: =D20+D21-D22 -> 30.581697 | E23: =E20+E21-E22 -> 41.487911 | F23: =F20+F21-F22 -> 48.797519 | G23: =G20+G21-G22 -> 46.833484 | H23: =H20+H21-H22 -> 44 | I23: =I20+I21-I22 -> 44 | J23: =J20+J21-J22 -> 44 | ... L23: =L20+L21-L22 -> 44
C26: Change in SIP NWC
B27: $ (thousand) | C27: =C6 -> 2022 | D27: =D6 -> 2023 | E27: =E6 -> 2024 | F27: =F6 -> 2025 | G27: =G6 -> 2026 | H27: =H6 -> 2027 | I27: =I6 -> 2028 | J27: =J6 -> 2029 | ... L27: =L6 -> 2031
B28: Change in acc receivable | C28: =Statement!M57 -> -10216 | D28: =Statement!N57 -> -11132 | E28: =Statement!O57 -> -11205 | F28: =Statement!P57 -> -8812 | G28: =Statement!Q57 -> -23397 | H28: =-(H13-G13) -> -739.53897 | I28: =-(I13-H13) -> -6151.3625 | J28: =-(J13-I13) -> -9037.7577 | K28: =-(K13-J13) -> -15136.057 | L28: =-(L13-K13) -> -22304.547
B29: Change in inventory | C29: =Statement!M58 -> 0 | D29: =Statement!N58 -> 0 | E29: =Statement!O58 -> 0 | F29: =Statement!P58 -> 0 | G29: =Statement!Q58 -> 0 | H29: =-(H14-G14) -> 0 | I29: =-(I14-H14) -> 0 | J29: =-(J14-I14) -> 0 | K29: =-(K14-J14) -> 0 | L29: =-(L14-K14) -> 0
B30: Change in acc payable | C30: =Statement!M59 -> 2881 | D30: =Statement!N59 -> 4774 | E30: =Statement!O59 -> -1993 | F30: =Statement!P59 -> -3234 | G30: =Statement!Q59 -> 5261 | H30: =H15-G15 -> -170.83051 | I30: =I15-H15 -> -66.840669 | J30: =J15-I15 -> 552.36374 | K30: =K15-J15 -> 1574.1499 | L30: =L15-K15 -> 2879.8699
C33: Total change in NWC and less SIP
B34: $ (thousand) | C34: =C6 -> 2022 | D34: =D6 -> 2023 | E34: =E6 -> 2024 | F34: =F6 -> 2025 | G34: =G6 -> 2026 | H34: =H6 -> 2027 | I34: =I6 -> 2028 | J34: =J6 -> 2029 | ... L34: =L6 -> 2031
B35: Total change in NWC | C35: =Statement!M57+Statement!M58+Statement!M59+Statement!M60 -> -18571 | D35: =Statement!N57+Statement!N58+Statement!N59+Statement!N60 -> -3862 | E35: =Statement!O57+Statement!O58+Statement!O59+Statement!O60 -> -1637 | F35: =Statement!P57+Statement!P58+Statement!P59+Statement!P60 -> -6493 | G35: =Statement!Q57+Statement!Q58+Statement!Q59+Statement!Q60 -> -14090 | H35: =H36+H28+H29+H30 -> 6769.6898 | I35: =I36+I28+I29+I30 -> 1942.9805 | J35: =J36+J28+J29+J30 -> 382.67151 | K35: =K36+K28+K29+K30 -> -3509.9856 | L35: =L36+L28+L29+L30 -> -7628.2216
B36: Change in NWC less SIP | C36: =C35-C28-C29-C30 -> -11236 | D36: =D35-D28-D29-D30 -> 2496 | E36: =E35-E28-E29-E30 -> 11561 | F36: =F35-F28-F29-F30 -> 5553 | G36: =G35-G28-G29-G30 -> 4046 | H36: =H7*H37 -> 7680.0593 | I36: =I7*I37 -> 8161.1837 | J36: =J7*J37 -> 8868.0655 | K36: =K7*K37 -> 10051.921 | L36: =L7*L37 -> 11796.456
B37: % of revenue | C37: =C36/C7 -> -0.052693532 | D37: =D36/D7 -> 0.0088854081 | E37: =E36/E7 -> 0.032447467 | F37: =F36/F7 -> 0.013227318 | G37: =G36/G7 -> 0.008418801 | H37: 0.015 | I37: 0.015 | J37: 0.015 | K37: 0.015 | L37: 0.015
C40: Investments
B41: $ (thousand) | C41: =C6 -> 2022 | D41: =D6 -> 2023 | E41: =E6 -> 2024 | F41: =F6 -> 2025 | G41: =G6 -> 2026 | H41: =H6 -> 2027 | I41: =I6 -> 2028 | J41: =J6 -> 2029 | ... L41: =L6 -> 2031
B42: D&A | C42: =Statement!M55 -> 21302 | D42: =Statement!N55 -> 25304 | E42: =Statement!O55 -> 29487 | F42: =Statement!P55 -> 27886 | G42: =Statement!Q55 -> 31453 | H42: ='COGS & OpEx'!H15+'COGS & OpEx'!H16 -> 32768.253 | I42: ='COGS & OpEx'!I15+'COGS & OpEx'!I16 -> 34276.972 | J42: ='COGS & OpEx'!J15+'COGS & OpEx'!J16 -> 32516.24 | K42: ='COGS & OpEx'!K15+'COGS & OpEx'!K16 -> 30825.892 | L42: ='COGS & OpEx'!L15+'COGS & OpEx'!L16 -> 30670.785
B43: % of Revenue | C43: =C42/C7 -> 0.099900109 | D43: =D42/D7 -> 0.090078673 | E43: =E42/E7 -> 0.082759143 | F43: =F42/F7 -> 0.066424813 | G43: =G42/G7 -> 0.065446502 | H43: =H42/H7 -> 0.064 | I43: =I42/I7 -> 0.063 | J43: =J42/J7 -> 0.055 | ... L43: =L42/L7 -> 0.039
B44: % of CapEx | C44: =C42/C45 -> 0.69151112 | D44: =D42/D45 -> 0.96569095 | E44: =E42/E45 -> 1.1749213 | F44: =F42/F45 -> 1.1576238 | G44: =G42/G45 -> 1.2892159 | H44: =H42/H45 -> 1.28 | I44: =I42/I45 -> 1.26 | J44: =J42/J45 -> 1.2222222 | ... L44: =L42/L45 -> 0.975
B45: CapEx | C45: =-Statement!M114 -> 30805 | D45: =-Statement!N114 -> 26203 | E45: =-Statement!O114 -> 25097 | F45: =-Statement!P114 -> 24089 | G45: =-Statement!Q114 -> 24397 | H45: =H7*H46 -> 25600.198 | I45: =I7*I46 -> 27203.946 | J45: =J7*J46 -> 26604.196 | K45: =K7*K46 -> 30155.764 | L45: =L7*L46 -> 31457.215
B46: % of Revenue | C46: =C45/C7 -> 0.14446638 | D46: =D45/D7 -> 0.093278986 | E46: =E45/E7 -> 0.070438031 | F46: =F45/F7 -> 0.05738031 | G46: =G45/G7 -> 0.050764579 | H46: 0.05 | I46: 0.05 | J46: 0.045 | K46: 0.045 | L46: 0.04

Sheet FCF & Other
B1: Results
C2: History | H2: Forecast
C4: Income statement
B5: $ (thousand) | C5: =Revenue!C5 -> 2022 | D5: =Revenue!D5 -> 2023 | E5: =Revenue!E5 -> 2024 | F5: =Revenue!F5 -> 2025 | G5: =Revenue!G5 -> 2026 | H5: =G5+1 -> 2027 | I5: =H5+1 -> 2028 | J5: =I5+1 -> 2029 | K5: =J5+1 -> 2030 | L5: =K5+1 -> 2031
B6: Revenue | C6: =Revenue!C9 -> 213233 | D6: =Revenue!D9 -> 280910 | E6: =Revenue!E9 -> 356299 | F6: =Revenue!F9 -> 419813 | G6: =Revenue!G9 -> 480591 | H6: =Revenue!H9 -> 512003.95 | I6: =Revenue!I9 -> 544078.91 | J6: =Revenue!J9 -> 591204.37 | ... L6: =Revenue!L9 -> 786430.37 | N6: From Revenue Sheet
B7: COGS | C7: ='COGS & OpEx'!C11 -> 81388 | D7: ='COGS & OpEx'!D11 -> 109267 | E7: ='COGS & OpEx'!E11 -> 124011 | F7: ='COGS & OpEx'!F11 -> 134934 | G7: ='COGS & OpEx'!G11 -> 154123 | H7: ='COGS & OpEx'!H11 -> 158721.23 | I7: ='COGS & OpEx'!I11 -> 157782.89 | J7: ='COGS & OpEx'!J11 -> 165537.22 | ... L7: ='COGS & OpEx'!L11 -> 228064.81 | N7: From COGS and OpEx Sheet
B8: Gross profit | C8: =C6-C7 -> 131845 | D8: =D6-D7 -> 171643 | E8: =E6-E7 -> 232288 | F8: =F6-F7 -> 284879 | G8: =G6-G7 -> 326468 | H8: =H6-H7 -> 353282.73 | I8: =I6-I7 -> 386296.03 | J8: =J6-J7 -> 425667.14 | ... L8: =L6-L7 -> 558365.56
B9: OpEx | C9: ='COGS & OpEx'!C17 -> 248662 | D9: ='COGS & OpEx'!D17 -> 348195 | E9: ='COGS & OpEx'!E17 -> 368767 | F9: ='COGS & OpEx'!F17 -> 342976 | G9: ='COGS & OpEx'!G17 -> 333080 | H9: ='COGS & OpEx'!H17 -> 352770.72 | I9: ='COGS & OpEx'!I17 -> 384663.79 | J9: ='COGS & OpEx'!J17 -> 399062.95 | ... L9: ='COGS & OpEx'!L17 -> 478936.1 | N9: From COGS and OpEx Sheet
B10: EBIT | C10: =C8-C9 -> -116817 | D10: =D8-D9 -> -176552 | E10: =E8-E9 -> -136479 | F10: =F8-F9 -> -58097 | G10: =G8-G9 -> -6612 | H10: =H8-H9 -> 512.00395 | I10: =I8-I9 -> 1632.2367 | J10: =J8-J9 -> 26604.196 | ... L10: =L8-L9 -> 79429.468
C13: Drivers
C14: =C5 -> 2022 | D14: =D5 -> 2023 | E14: =E5 -> 2024 | F14: =F5 -> 2025 | G14: =G5 -> 2026 | H14: =H5 -> 2027 | I14: =I5 -> 2028 | J14: =J5 -> 2029 | ... L14: =L5 -> 2031
B15: Tax rate | C15: =Statement!M85 -> 0 | D15: =Statement!N85 -> 0 | E15: =Statement!O85 -> 0 | F15: =Statement!P85 -> 0 | G15: =Statement!Q85 -> 0 | H15: =Overview!$C$26 -> 0.21 | I15: =Overview!$C$26 -> 0.21 | J15: =Overview!$C$26 -> 0.21 | K15: =Overview!$C$26 -> 0.21 | L15: =Overview!$C$26 -> 0.21 | N15: From Statements and Overview sheet
C18: Cash Flow Statement
B19: $ (thousand) | C19: =C5 -> 2022 | D19: =D5 -> 2023 | E19: =E5 -> 2024 | F19: =F5 -> 2025 | G19: =G5 -> 2026 | H19: =H5 -> 2027 | I19: =I5 -> 2028 | J19: =J5 -> 2029 | ... L19: =L5 -> 2031
B20: D&A | C20: ='WC & Investments'!C42 -> 21302 | D20: ='WC & Investments'!D42 -> 25304 | E20: ='WC & Investments'!E42 -> 29487 | F20: ='WC & Investments'!F42 -> 27886 | G20: ='WC & Investments'!G42 -> 31453 | H20: ='WC & Investments'!H42 -> 32768.253 | I20: ='WC & Investments'!I42 -> 34276.972 | J20: ='WC & Investments'!J42 -> 32516.24 | ... L20: ='WC & Investments'!L42 -> 30670.785 | N20: From WC & Investments Sheet
B21: CapEx | C21: ='WC & Investments'!C45 -> 30805 | D21: ='WC & Investments'!D45 -> 26203 | E21: ='WC & Investments'!E45 -> 25097 | F21: ='WC & Investments'!F45 -> 24089 | G21: ='WC & Investments'!G45 -> 24397 | H21: ='WC & Investments'!H45 -> 25600.198 | I21: ='WC & Investments'!I45 -> 27203.946 | J21: ='WC & Investments'!J45 -> 26604.196 | ... L21: ='WC & Investments'!L45 -> 31457.215 | N21: From WC & Investments Sheet
B22: Change in NWC | C22: ='WC & Investments'!C35 -> -18571 | D22: ='WC & Investments'!D35 -> -3862 | E22: ='WC & Investments'!E35 -> -1637 | F22: ='WC & Investments'!F35 -> -6493 | G22: ='WC & Investments'!G35 -> -14090 | H22: ='WC & Investments'!H35 -> 6769.6898 | I22: ='WC & Investments'!I35 -> 1942.9805 | J22: ='WC & Investments'!J35 -> 382.67151 | ... L22: ='WC & Investments'!L35 -> -7628.2216 | N22: From WC & Investments Sheet
C25: FCFF
B26: $ (thousand) | C26: =C5 -> 2022 | D26: =D5 -> 2023 | E26: =E5 -> 2024 | F26: =F5 -> 2025 | G26: =G5 -> 2026 | H26: =H5 -> 2027 | I26: =I5 -> 2028 | J26: =J5 -> 2029 | ... L26: =L5 -> 2031
B27: NOPAT | C27: =C10*(1-C15) -> -116817 | D27: =D10*(1-D15) -> -176552 | E27: =E10*(1-E15) -> -136479 | F27: =F10*(1-F15) -> -58097 | G27: =G10*(1-G15) -> -6612 | H27: =H10*(1-H15) -> 404.48312 | I27: =I10*(1-I15) -> 1289.467 | J27: =J10*(1-J15) -> 21017.315 | ... L27: =L10*(1-L15) -> 62749.279
B28: FCFF | C28: =C27+C20-C21+C22 -> -144891 | D28: =D27+D20-D21+D22 -> -181313 | E28: =E27+E20-E21+E22 -> -133726 | F28: =F27+F20-F21+F22 -> -60793 | G28: =G27+G20-G21+G22 -> -13646 | H28: =H27+H20-H21+H22 -> 14342.228 | I28: =I27+I20-I21+I22 -> 10305.473 | J28: =J27+J20-J21+J22 -> 27312.03 | ... L28: =L27+L20-L21+L22 -> 54334.627
C31: Margins
B32: % | C32: =C5 -> 2022 | D32: =D5 -> 2023 | E32: =E5 -> 2024 | F32: =F5 -> 2025 | G32: =G5 -> 2026 | H32: =H5 -> 2027 | I32: =I5 -> 2028 | J32: =J5 -> 2029 | ... L32: =L5 -> 2031
B33: Gross margin | C33: =Statement!M105 -> 0.61831424 | D33: =Statement!N105 -> 0.61102488 | E33: =Statement!O105 -> 0.65194682 | F33: =Statement!P105 -> 0.67858547 | G33: =Statement!Q105 -> 0.67930527 | H33: =H8/H6 -> 0.69 | I33: =I8/I6 -> 0.71 | J33: =J8/J6 -> 0.72 | K33: =K8/K6 -> 0.72 | L33: =L8/L6 -> 0.71
B34: Operating margin | C34: =Statement!M106 -> -0.54783734 | D34: =Statement!N106 -> -0.62850023 | E34: =Statement!O106 -> -0.38304626 | F34: =Statement!P106 -> -0.13838781 | G34: =Statement!Q106 -> -0.01375806 | H34: =H10/H6 -> 0.001 | I34: =I10/I6 -> 0.003 | J34: =J10/J6 -> 0.045 | K34: =K10/K6 -> 0.084 | L34: =L10/L6 -> 0.101

Sheet Valuation ->
H5: Links
H6: Overview'!B3
H7: Financials ->'!B13
H8: Analysis ->'!B13
H9: Forecast ->'!B13
H10: Valuation ->'!B13
B13: Valuation ->

Sheet WACC
B1: WACC
B4: Inputs
B5: Shares Outstanding | C5: =Statement!AC80 -> 64726
B6: Price | C6: =Overview!C5 -> 12.61
B7: Equity | C7: =C5*C6 -> 816194.86
B8: Debt | C8: =Statement!AC112 -> 66446
B9: Risk free rate | C9: =Overview!F27 -> 0.04988
B10: Beta | C10: =Overview!C13 -> 0.7583
B11: Market risk premium | C11: =[1]Sheet1!$C$12 -> 0.045
B12: Tax rate | C12: =Overview!C26 -> 0.21
B13: Cost of debt | C13: =Overview!C27 -> 0.065
B15: Calculations
B16: Debt/(Debt+Equity) | C16: =C8/(C8+C7) -> 0.075280902
B17: Equity/(Debt+Equity) | C17: =C7/(C8+C7) -> 0.9247191
B18: Cost of debt with tax | C18: =C13*(1-C12) -> 0.05135
B19: Cost of equity | C19: =C9+C10*C11 -> 0.0840035
B20: WACC | C20: =(C17*C19)+(C16*C18) -> 0.081545315

Sheet DCF
B1: DCF
C3: History | H3: Forecast
C5: PV of FCF
B6: $ (thousand) | C6: =Revenue!C5 -> 2022 | D6: =Revenue!D5 -> 2023 | E6: =Revenue!E5 -> 2024 | F6: =Revenue!F5 -> 2025 | G6: =Revenue!G5 -> 2026 | H6: =Revenue!H5 -> 2027 | I6: =Revenue!I5 -> 2028 | J6: =Revenue!J5 -> 2029 | ... L6: =Revenue!L5 -> 2031
B7: FCFF | C7: ='FCF & Other'!C28 -> -144891 | D7: ='FCF & Other'!D28 -> -181313 | E7: ='FCF & Other'!E28 -> -133726 | F7: ='FCF & Other'!F28 -> -60793 | G7: ='FCF & Other'!G28 -> -13646 | H7: ='FCF & Other'!H28 -> 14342.228 | I7: ='FCF & Other'!I28 -> 10305.473 | J7: ='FCF & Other'!J28 -> 27312.03 | ... L7: ='FCF & Other'!L28 -> 54334.627
B8: Perpetual cashflow | C8: 0 | D8: 0 | E8: 0 | F8: 0 | G8: 0 | H8: 0 | I8: 0 | J8: 0 | K8: 0 | L8: =L7*(1+C14)/(C15-C14) -> 900496.16
B9: Period | H9: 1 | I9: 2 | J9: 3 | K9: 4 | L9: 5
B10: PV of FCFF | H10: =H7/(1+$C$15)^H9 -> 13260.867 | I10: =I7/(1+$C$15)^I9 -> 8810.0527 | J10: =J7/(1+$C$15)^J9 -> 21588.369 | K10: =K7/(1+$C$15)^K9 -> 30424.671 | L10: =L7/(1+$C$15)^L9 -> 36715.808
B11: PV of Perpetual cashflow | L11: =L8/(1+C15)^L9 -> 608496.75
B13: Input parameters
B14: Perpetual growth | C14: 0.02
B15: WACC | C15: =IF(Overview!C28>0,Overview!C28,WACC!C20) -> 0.081545315
B18: Result
B19: Total PV of Unlevered FCF | C19: =SUM(H10:L10) -> 110799.77
B20: PV of Perpetual cashflow | C20: =L11 -> 608496.75
B21: Enterprise value | C21: =C19+C20 -> 719296.52
B22: (+) Cash | C22: =Statement!AC111 -> 72945
B23: (-) Debt | C23: =Statement!AC112 -> 66446
B24: Equity value | C24: =C21+C22-C23 -> 725795.52
B25: Shares outstanding | C25: =Statement!AC80 -> 64726
B26: Price per share | C26: =C24/C25 -> 11.213353

Sheet Multiples
B1: Multiples valuations
C2: History | H2: Forecast
C4: Revenues, earnings cash
B5: Revenues (thousand) | C5: =Revenue!C5 -> 2022 | D5: =Revenue!D5 -> 2023 | E5: =Revenue!E5 -> 2024 | F5: =Revenue!F5 -> 2025 | G5: =Revenue!G5 -> 2026 | H5: =Revenue!H5 -> 2027 | I5: =Revenue!I5 -> 2028 | J5: =Revenue!J5 -> 2029 | ... L5: =Revenue!L5 -> 2031
B6: Revenue | C6: =Revenue!C9 -> 213233 | D6: =Revenue!D9 -> 280910 | E6: =Revenue!E9 -> 356299 | F6: =Revenue!F9 -> 419813 | G6: =Revenue!G9 -> 480591 | H6: =Revenue!H9 -> 512003.95 | I6: =Revenue!I9 -> 544078.91 | J6: =Revenue!J9 -> 591204.37 | ... L6: =Revenue!L9 -> 786430.37
B7: EBIT | C7: ='FCF & Other'!C10 -> -116817 | D7: ='FCF & Other'!D10 -> -176552 | E7: ='FCF & Other'!E10 -> -136479 | F7: ='FCF & Other'!F10 -> -58097 | G7: ='FCF & Other'!G10 -> -6612 | H7: ='FCF & Other'!H10 -> 512.00395 | I7: ='FCF & Other'!I10 -> 1632.2367 | J7: ='FCF & Other'!J10 -> 26604.196 | ... L7: ='FCF & Other'!L10 -> 79429.468
B8: FCFF | C8: ='FCF & Other'!C28 -> -144891 | D8: ='FCF & Other'!D28 -> -181313 | E8: ='FCF & Other'!E28 -> -133726 | F8: ='FCF & Other'!F28 -> -60793 | G8: ='FCF & Other'!G28 -> -13646 | H8: ='FCF & Other'!H28 -> 14342.228 | I8: ='FCF & Other'!I28 -> 10305.473 | J8: ='FCF & Other'!J28 -> 27312.03 | ... L8: ='FCF & Other'!L28 -> 54334.627
B9: PV of FCFF | H9: =DCF!H10 -> 13260.867 | I9: =DCF!I10 -> 8810.0527 | J9: =DCF!J10 -> 21588.369 | K9: =DCF!K10 -> 30424.671 | L9: =DCF!L10 -> 36715.808
C11: Growth rates
B12: % Growth | C12: =C5 -> 2022 | D12: =D5 -> 2023 | E12: =E5 -> 2024 | F12: =F5 -> 2025 | G12: =G5 -> 2026 | H12: =H5 -> 2027 | I12: =I5 -> 2028 | J12: =J5 -> 2029 | ... L12: =L5 -> 2031
B13: Revenue | D13: =(D6-C6)/C6 -> 0.31738521 | E13: =(E6-D6)/D6 -> 0.26837421 | F13: =(F6-E6)/E6 -> 0.17826039 | G13: =(G6-F6)/F6 -> 0.14477398 | H13: =(H6-G6)/G6 -> 0.065363174 | I13: =(I6-H6)/H6 -> 0.062645926 | J13: =(J6-I6)/I6 -> 0.086615102 | K13: =(K6-J6)/J6 -> 0.13349652 | L13: =(L6-K6)/K6 -> 0.17355231
B14: EBIT | D14: =IF(C7=0, IF(D7=0,0,IF(D7>0,1,-1)), (D7-C7)/ABS(C7) ) -> -0.51135537 | E14: =IF(D7=0, IF(E7=0,0,IF(E7>0,1,-1)), (E7-D7)/ABS(D7) ) -> 0.22697562 | F14: =IF(E7=0, IF(F7=0,0,IF(F7>0,1,-1)), (F7-E7)/ABS(E7) ) -> 0.57431546 | G14: =IF(F7=0, IF(G7=0,0,IF(G7>0,1,-1)), (G7-F7)/ABS(F7) ) -> 0.88619034 | H14: =IF(G7=0, IF(H7=0,0,IF(H7>0,1,-1)), (H7-G7)/ABS(G7) ) -> 1.0774356 | I14: =IF(H7=0, IF(I7=0,0,IF(I7>0,1,-1)), (I7-H7)/ABS(H7) ) -> 2.1879378 | J14: =IF(I7=0, IF(J7=0,0,IF(J7>0,1,-1)), (J7-I7)/ABS(I7) ) -> 15.299227 | K14: =IF(J7=0, IF(K7=0,0,IF(K7>0,1,-1)), (K7-J7)/ABS(J7) ) -> 1.1158602 | L14: =IF(K7=0, IF(L7=0,0,IF(L7>0,1,-1)), (L7-K7)/ABS(K7) ) -> 0.41105695
B15: FCFF | D15: =IF(C8=0, IF(D8=0,0,IF(D8>0,1,-1)), (D8-C8)/ABS(C8) ) -> -0.25137517 | E15: =IF(D8=0, IF(E8=0,0,IF(E8>0,1,-1)), (E8-D8)/ABS(D8) ) -> 0.26245774 | F15: =IF(E8=0, IF(F8=0,0,IF(F8>0,1,-1)), (F8-E8)/ABS(E8) ) -> 0.54539132 | G15: =IF(F8=0, IF(G8=0,0,IF(G8>0,1,-1)), (G8-F8)/ABS(F8) ) -> 0.77553337 | H15: =IF(G8=0, IF(H8=0,0,IF(H8>0,1,-1)), (H8-G8)/ABS(G8) ) -> 2.0510207 | I15: =IF(H8=0, IF(I8=0,0,IF(I8>0,1,-1)), (I8-H8)/ABS(H8) ) -> -0.28145939 | J15: =IF(I8=0, IF(J8=0,0,IF(J8>0,1,-1)), (J8-I8)/ABS(I8) ) -> 1.6502451 | K15: =IF(J8=0, IF(K8=0,0,IF(K8>0,1,-1)), (K8-J8)/ABS(J8) ) -> 0.52423097 | L15: =IF(K8=0, IF(L8=0,0,IF(L8>0,1,-1)), (L8-K8)/ABS(K8) ) -> 0.30518455
C17: Shares
C18: =C5 -> 2022 | D18: =D5 -> 2023 | E18: =E5 -> 2024 | F18: =F5 -> 2025 | G18: =G5 -> 2026 | H18: =H5 -> 2027 | I18: =I5 -> 2028 | J18: =J5 -> 2029 | ... L18: =L5 -> 2031
B19: Avg diluted shares | C19: =Statement!M24 -> 49888 | D19: =Statement!N24 -> 52440 | E19: =Statement!O24 -> 54561 | F19: =Statement!P24 -> 57590 | G19: =Statement!Q24 -> 61495 | H19: =G19*(1+H20) -> 66107.125 | I19: =H19*(1+I20) -> 71395.695 | J19: =I19*(1+J20) -> 77821.308 | K19: =J19*(1+K20) -> 84825.225 | L19: =K19*(1+L20) -> 92459.496
B20: Dilution rate | D20: =D19/C19-1 -> 0.051154586 | E20: =E19/D19-1 -> 0.040446224 | F20: =F19/E19-1 -> 0.055515845 | G20: =G19/F19-1 -> 0.067806911 | H20: 0.075 | I20: 0.08 | J20: 0.09 | K20: 0.09 | L20: 0.09
C22: Historical price
C23: =C5 -> 2022 | D23: =D5 -> 2023 | E23: =E5 -> 2024 | F23: =F5 -> 2025 | G23: =G5 -> 2026 | H23: =H5 -> 2027 | I23: =I5 -> 2028 | J23: =J5 -> 2029 | ... L23: =L5 -> 2031
B24: Price | C24: =Statement!M120 -> 28.44 | D24: =Statement!N120 -> 36.19 | E24: =Statement!O120 -> 25.61 | F24: =Statement!P120 -> 29 | G24: =Statement!Q120 -> 13.43
C27: Historical ratios
C28: =C5 -> 2022 | D28: =D5 -> 2023 | E28: =E5 -> 2024 | F28: =F5 -> 2025 | G28: =G5 -> 2026 | H28: =H5 -> 2027 | I28: =I5 -> 2028 | J28: =J5 -> 2029 | ... L28: =L5 -> 2031
B29: PS | C29: =C24/(C6/C19) -> 6.6538234 | D29: =D24/(D6/D19) -> 6.7559133 | E29: =E24/(E6/E19) -> 3.9217264 | F29: =F24/(F6/F19) -> 3.9782236 | G29: =G24/(G6/G19) -> 1.718463
B30: Market Cap | C30: =C24*C19 -> 1418814.7 | D30: =D24*D19 -> 1897803.6 | E30: =E24*E19 -> 1397307.2 | F30: =F24*F19 -> 1670110 | G30: =G24*G19 -> 825877.85
B31: Debt | C31: =Statement!M112 -> 13244 | D31: =Statement!N112 -> 7897 | E31: =Statement!O112 -> 11456 | F31: =Statement!P112 -> 16193 | G31: =Statement!Q112 -> 100088
B32: Cash | C32: =Statement!M111 -> 313812 | D32: =Statement!N111 -> 176683 | E32: =Statement!O111 -> 87520 | F32: =Statement!P111 -> 84220 | G32: =Statement!Q111 -> 73830
B33: EV | C33: =C30+C31-C32 -> 1118246.7 | D33: =D30+D31-D32 -> 1729017.6 | E33: =E30+E31-E32 -> 1321243.2 | F33: =F30+F31-F32 -> 1602083 | G33: =G30+G31-G32 -> 852135.85
B34: EV/EBIT | C34: =C33/C7 -> -9.5726369 | D34: =D33/D7 -> -9.7932484 | E34: =E33/E7 -> -9.6809268 | F34: =F33/F7 -> -27.576002 | G34: =G33/G7 -> -128.87717
B35: EV/FCFF | C35: =C33/C8 -> -7.717848 | D35: =D33/D8 -> -9.5360928 | E35: =E33/E8 -> -9.8802268 | F35: =F33/F8 -> -26.353083 | G35: =G33/G8 -> -62.445834
B36: EV/Sales | C36: =C33/C6 -> 5.2442479 | D36: =D33/D6 -> 6.1550589 | E36: =E33/E6 -> 3.7082428 | F36: =F33/F6 -> 3.8161824 | G36: =G33/G6 -> 1.7730999
B39: EV/EBIT valuation
B40: Year 5 EBIT | C40: =L7 -> 79429.468
B41: WACC | C41: =IF(Overview!C28>0,Overview!C28,WACC!C20) -> 0.081545315
B42: Applied EV/EBIT ratio | C42: 20
B43: Terminal EV | C43: =(C40*C42) -> 1588589.4
B44: PV of Terminal EV | C44: =C43/(1+C41)^5 -> 1073465.4
B45: Total EV | C45: =SUM(H9:K9)+C44 -> 1147549.3
B46: (+) Cash | C46: =Statement!AC111 -> 72945
B47: (-) Debt | C47: =Statement!AC112 -> 66446
B48: Equity Value | C48: =C45+C46-C47 -> 1154048.3
B49: Shares outstanding | C49: =Statement!AC80 -> 64726
B50: PV of price per share | C50: =C48/C49 -> 17.829749
B52: PS valuation
B53: Year 5 sales | C53: =L6 -> 786430.37
B54: Discount rate | C54: =IF(Overview!C29>0,Overview!C29,WACC!C19) -> 0.0840035
B55: Applied PS ratio | C55: 3
B56: Shares outstanding diluted | C56: =L19 -> 92459.496
B57: Price per share | C57: =(C53*C55)/C56 -> 25.517023
B58: PV of price per share | C58: =C57/(1+C54)^5 -> 17.048124
B60: EV/FCFF valuation
B61: Year 5 FCFF | C61: =L8 -> 54334.627
B62: WACC | C62: =IF(Overview!C28>0,Overview!C28,WACC!C20) -> 0.081545315
B63: Applied EV/FCFF ratio | C63: 23
B64: Terminal EV | C64: =(C61*C63) -> 1249696.4
B65: PV of Terminal EV | C65: =C64/(1+C62)^5 -> 844463.59
B66: Total EV | C66: =SUM(H9:K9)+C65 -> 918547.54
B67: (+) Cash | C67: =Statement!AC111 -> 72945
B68: (-) Debt | C68: =Statement!AC112 -> 66446
B69: Equity Value | C69: =C66+C67-C68 -> 925046.54
B70: Shares outstanding | C70: =Statement!AC80 -> 64726
B71: PV of price per share | C71: =C69/C70 -> 14.29173
B73: EV/Sales valuation
B74: Year 5 Sales | C74: =L6 -> 786430.37
B75: WACC | C75: =IF(Overview!C28>0,Overview!C28,WACC!C20) -> 0.081545315
B76: Applied EV/Sales ratio | C76: 3
B77: Terminal EV | C77: =(C74*C76) -> 2359291.1
B78: PV of Terminal EV | C78: =C77/(1+C75)^5 -> 1594255.5
B79: Total EV | C79: =SUM(H9:K9)+C78 -> 1668339.5
B80: (+) Cash | C80: =Statement!AC111 -> 72945
B81: (-) Debt | C81: =Statement!AC112 -> 66446
B82: Equity Value | C82: =C79+C80-C81 -> 1674838.5
B83: Shares outstanding | C83: =Statement!AC80 -> 64726
B84: PV of price per share | C84: =C82/C83 -> 25.875822

Sheet AVG target price
B1: AVG target price
B4: AVG target price
B5: DCF price | C5: =DCF!C26 -> 11.213353
B6: EV/EBIT price | C6: =Multiples!C50 -> 17.829749
B7: PS price | C7: =Multiples!C58 -> 17.048124
B8: EV/FCFF price | C8: =Multiples!C71 -> 14.29173
B9: EV/Sales price | C9: =Multiples!C84 -> 25.875822
B10: AVG price | C10: =AVERAGE(C5:C9) -> 17.251756
B11: Current price | C11: =Overview!C5 -> 12.61
B12: Upside/Downside | C12: =(C10-C11)/C11 -> 0.36810118

Sheet DDM
B1: Dividend discount model
C2: History | H2: Forecast
C4: Revenues, earnings cash
B5: Revenues (thousand) | C5: =[2]Revenue!C5 -> 2021 | D5: =[2]Revenue!D5 -> 2022 | E5: =[2]Revenue!E5 -> 2023 | F5: =[2]Revenue!F5 -> 2024 | G5: =[2]Revenue!G5 -> 2025 | H5: =[2]Revenue!H5 -> 2026 | I5: =[2]Revenue!I5 -> 2027 | J5: =[2]Revenue!J5 -> 2028 | ... L5: =[2]Revenue!L5 -> 2030
B6: EPS | C6: =Statement!M28 -> -2.37 | D6: =Statement!N28 -> -3.36 | E6: =Statement!O28 -> -2.51 | F6: =Statement!P28 -> -1.02 | G6: =Statement!Q28 -> -0.16
B7: Dividend per share | C7: =Statement!M84 -> 0 | D7: =Statement!N84 -> 0 | E7: =Statement!O84 -> 0 | F7: =Statement!P84 -> 0 | G7: =Statement!Q84 -> 0
C9: Growth rates
B10: % Growth | C10: =C5 -> 2021 | D10: =D5 -> 2022 | E10: =E5 -> 2023 | F10: =F5 -> 2024 | G10: =G5 -> 2025 | H10: =H5 -> 2026 | I10: =I5 -> 2027 | J10: =J5 -> 2028 | ... L10: =L5 -> 2030
B11: EPS | D11: =(D6-C6)/C6 -> 0.41772152 | E11: =(E6-D6)/D6 -> -0.25297619 | F11: =(F6-E6)/E6 -> -0.5936255 | G11: =(G6-F6)/F6 -> -0.84313725
B12: Dividend | D12: =IF(C7=0, IF(D7=0,0,IF(D7>0,1,-1)), (D7-C7)/ABS(C7) ) -> 0 | E12: =IF(D7=0, IF(E7=0,0,IF(E7>0,1,-1)), (E7-D7)/ABS(D7) ) -> 0 | F12: =IF(E7=0, IF(F7=0,0,IF(F7>0,1,-1)), (F7-E7)/ABS(E7) ) -> 0 | G12: =IF(F7=0, IF(G7=0,0,IF(G7>0,1,-1)), (G7-F7)/ABS(F7) ) -> 0
C14: Ratios
B15: % | C15: =C5 -> 2021 | D15: =D5 -> 2022 | E15: =E5 -> 2023 | F15: =F5 -> 2024 | G15: =G5 -> 2025 | H15: =H5 -> 2026 | I15: =I5 -> 2027 | J15: =J5 -> 2028 | ... L15: =L5 -> 2030
B16: Payout | C16: =C7/C6 -> 0 | D16: =D7/D6 -> 0 | E16: =E7/E6 -> 0 | F16: =F7/F6 -> 0 | G16: =G7/G6 -> 0
B20: DDM valuation
B21: Latest dividend | C21: =G7 -> 0
B22: Year 1 growth rate | C22: 0
B23: Year 1 dividend | C23: =C21*(1+C22) -> 0
B24: Discount rate | C24: =IF(Overview!C29>0,Overview!C29,WACC!C19) -> 0.0840035
B25: Perpetual dividend growth | C25: 0
B26: PV of price per share | C26: =C23/(C24-C25) -> 0

Sheet Reverse DCF
B1: Reverse DCF
C3: History | H3: Forecast
C5: PV of FCF
B6: $ (thousand) | C6: =Revenue!C5 -> 2022 | D6: =Revenue!D5 -> 2023 | E6: =Revenue!E5 -> 2024 | F6: =Revenue!F5 -> 2025 | G6: =Revenue!G5 -> 2026 | H6: =Revenue!H5 -> 2027 | I6: =Revenue!I5 -> 2028 | J6: =Revenue!J5 -> 2029 | ... L6: =Revenue!L5 -> 2031
B7: FCFF | C7: ='FCF & Other'!C28 -> -144891 | D7: ='FCF & Other'!D28 -> -181313 | E7: ='FCF & Other'!E28 -> -133726 | F7: ='FCF & Other'!F28 -> -60793 | G7: 8000 | H7: =G7*(1+$C$17) -> 11600 | I7: =H7*(1+$C$17) -> 16820 | J7: =I7*(1+$C$17) -> 24389 | K7: =J7*(1+$C$17) -> 35364.05 | L7: =K7*(1+$C$17) -> 51277.872
B8: Perpetual cashflow | L8: =L7*(1+C20)/(C21-C20) -> 849836.09
B9: Period | H9: 1 | I9: 2 | J9: 3 | K9: 4 | L9: 5
B10: PV of FCFF | H10: =H7/(1+$C$21)^H9 -> 10725.394 | I10: =I7/(1+$C$21)^I9 -> 14379.26 | J10: =J7/(1+$C$21)^J9 -> 19277.905 | K10: =K7/(1+$C$21)^K9 -> 25845.391 | L10: =L7/(1+$C$21)^L9 -> 34650.252
B11: PV of Perpetual cashflow | L11: =L8/(1+C21)^L9 -> 574263.97
B14: Growth adjustment
B15: Current Price | C15: =Overview!C5 -> 12.61
B16: Calculated Price | C16: =C36 -> 11.046079
B17: FCFF Growth | C17: 0.45 | E17: Modify until Calculated Price is very close to Current Price
B19: Input parameters
B20: Perpetual growth | C20: 0.02
B21: WACC | C21: =IF(Overview!C28>0,Overview!C28,WACC!C20) -> 0.081545315
B22: Shares outstanding | C22: =Statement!AC77 -> 62071
B23: Market cap | C23: =C15*C22 -> 782715.31
B24: Cash | C24: =Statement!AC111 -> 72945
B25: Debt | C25: =Statement!AC112 -> 66446
B26: Enterprise Value | C26: =C23+C25-C24 -> 776216.31
B28: Result
B29: Total PV of Unlevered FCF | C29: =SUM(H10:L10) -> 104878.2
B30: PV of Perpetual cashflow | C30: =L11 -> 574263.97
B31: Enterprise value | C31: =C29+C30 -> 679142.17
B32: (+) Cash | C32: =C24 -> 72945
B33: (-) Debt | C33: =C25 -> 66446
B34: Equity value | C34: =C31+C32-C33 -> 685641.17
B35: Shares outstanding | C35: =C22 -> 62071
B36: Price per share | C36: =C34/C35 -> 11.046079
