Workbook

Sheet Overview
B2: Ticker | C2: SN
B3: Price | C3: =[1]Sheet1!$C$9 -> 115.49
B7: Units | C7: K
B9: Market cap | C9: =C3*'Statement Q'!J18 -> 16301529
B10: Net debt | C10: =(Statements!R40+Statements!R42+Statements!R43)-Statements!R23 -> 99831
B11: EV | C11: =C9+Overview!C10 -> 16401360
B13: PE | C13: =C3/'Statement Q'!N21 -> 23.394508
B14: PS | C14: =C3/('Statement Q'!N5/'Statement Q'!N19) -> 2.5641221
B16: Notes
B17: 10-K for SN are 20-F
B18: 10-Q for SN are 6-K
B19: Proxy for SN are 6-K

Sheet Statement Y
B2: Date | C2: 31.12.2021 | D2: 31.12.2022 | E2: 31.12.2023 | F2: 31.12.2024 | G2: 31.12.2025
B3: FY | C3: 2021 | D3: =C3+1 -> 2022 | E3: =D3+1 -> 2023 | F3: =E3+1 -> 2024 | G3: =F3+1 -> 2025 | H3: =G3+1 -> 2026 | I3: =H3+1 -> 2027 | J3: =I3+1 -> 2028 | K3: =J3+1 -> 2029
B4: Income statement
B5: Revenue | C5: 3726994 | D5: 3717366 | E5: 4253710 | F5: 5528639 | G5: 6399188
B6: COGS | C6: 2288810 | D6: 2307172 | E6: 2345858 | F6: 2866648 | G6: 3262698
B7: Gross Profit | C7: =C5-C6 -> 1438184 | D7: =D5-D6 -> 1410194 | E7: =E5-E6 -> 1907852 | F7: =F5-F6 -> 2661991 | G7: =G5-G6 -> 3136490 | H7: =H5-H6 -> 0 | I7: =I5-I6 -> 0 | J7: =J5-J6 -> 0 | K7: =K5-K6 -> 0
B8: R&D | C8: 200641 | D8: 215660 | E8: 249387 | F8: 341289 | G8: 368073
B9: Sales and marketing | C9: 619162 | D9: 621953 | E9: 897585 | F9: 1243145 | G9: 1458027
B10: General and administrative | C10: 180124 | D10: 251207 | E10: 387316 | F10: 433395 | G10: 390109
B11: OpEx | C11: =SUM(C8:C10) -> 999927 | D11: =SUM(D8:D10) -> 1088820 | E11: =SUM(E8:E10) -> 1534288 | F11: =SUM(F8:F10) -> 2017829 | G11: =SUM(G8:G10) -> 2216209 | H11: =SUM(H8:H10) -> 0 | I11: =SUM(I8:I10) -> 0 | J11: =SUM(J8:J10) -> 0 | K11: =SUM(K8:K10) -> 0
B12: Operating income | C12: 438257 | D12: 321374 | E12: 373564 | F12: 644162 | G12: 920281
B13: Interest income/expense | C13: -16287 | D13: -27021 | E13: -44909 | F13: -63715 | G13: -48600
B14: Other income/expense | C14: -7644 | D14: 7631 | E14: -35427 | F14: -7980 | G14: 28597
B15: Income before taxes | C15: 414326 | D15: 301984 | E15: 293228 | F15: 572467 | G15: 900278
B16: Income tax expense/benefit | C16: -83213 | D16: -69630 | E16: -126150 | F16: -133762 | G16: -198904
B17: Net income | C17: 331113 | D17: 232354 | E17: 167078 | F17: 438705 | G17: 701374
B18: Basic Shares outstanding avg | C18: 138983 | D18: 138983 | E18: 139026 | F18: 139936 | G18: 140984
B19: Diluted Shares outstanding avg | C19: 138983 | D19: 138983 | E19: 139420 | F19: 141084 | G19: 142090
B20: Basic EPS | C20: 2.38 | D20: 1.67 | E20: 1.2 | F20: 3.14 | G20: 4.97
B21: Diluted EPS | C21: 2.38 | D21: 1.67 | E21: 1.2 | F21: 3.11 | G21: 4.94
B23: Balance sheet
B24: Cash and cash equivalents | D24: 192890 | E24: 154061 | F24: 363669 | G24: 777289
B25: Restricted cash | D25: 25880 | E25: 0 | F25: 0 | G25: 0
B26: Acc receivable | D26: 766503 | E26: 985172 | F26: 1266595 | G26: 1667143
B27: Inventories | D27: 548588 | E27: 699740 | F27: 899989 | G27: 1002205
B28: Prepaid expenses & Other current | D28: 181831 | E28: 58311 | F28: 114008 | G28: 164628
B29: Current assets | D29: 1715692 | E29: 1897284 | F29: 2644261 | G29: 3611265
B30: PP&E | D30: 137341 | E30: 166252 | F30: 211464 | G30: 232226
B31: Operating lease right of use | D31: 67321 | E31: 63333 | F31: 146257 | G31: 142487
B32: Intangible assets | D32: 492709 | E32: 477816 | F32: 462678 | G32: 451137
B33: Goodwill | D33: 840148 | E33: 834203 | F33: 834781 | G33: 834781
B34: Deferred tax assets | D34: 6291 | E34: 12 | F34: 43093 | G34: 10706
B35: Other assets | D35: 35389 | E35: 48170 | F35: 51625 | G35: 66832
B36: Long term assets | C36: =SUM(C30:C35) -> 0 | D36: =SUM(D30:D35) -> 1579199 | E36: =SUM(E30:E35) -> 1589786 | F36: =SUM(F30:F35) -> 1749898 | G36: =SUM(G30:G35) -> 1738169 | H36: =SUM(H30:H35) -> 0 | I36: =SUM(I30:I35) -> 0 | J36: =SUM(J30:J35) -> 0 | K36: =SUM(K30:K35) -> 0
B37: Total assets | D37: 3294891 | E37: 3487070 | F37: 4394159 | G37: 5349434
B38: Acc payable | D38: 328122 | E38: 459651 | F38: 612031 | G38: 679534
B39: Accrued expenses | D39: 552023 | E39: 620333 | F39: 841529 | G39: 1016645
B40: Tax payable | D40: 1581 | E40: 20991 | F40: 36548 | G40: 38092
B41: Current portion long term debt | D41: 86972 | E41: 24157 | F41: 39344 | G41: 39344
B42: Current liabilities | D42: 968698 | E42: 1125132 | F42: 1529452 | G42: 1773615
B43: Long term debt | D43: 349169 | E43: 775483 | F43: 736139 | G43: 696795
B44: Operating lease | D44: 61779 | E44: 63043 | F44: 145377 | G44: 140981
B45: Deferred tax liabilities | D45: 60976 | E45: 16500 | F45: 9931 | G45: 16252
B46: Other liabilities | D46: 25980 | E46: 28019 | F46: 37288 | G46: 45580
B47: Long term liabilities | C47: =SUM(C43:C46) -> 0 | D47: =SUM(D43:D46) -> 497904 | E47: =SUM(E43:E46) -> 883045 | F47: =SUM(F43:F46) -> 928735 | G47: =SUM(G43:G46) -> 899608 | H47: =SUM(H43:H43) -> 0 | I47: =SUM(I43:I43) -> 0 | J47: =SUM(J43:J43) -> 0 | K47: =SUM(K43:K43) -> 0
B48: Total liabilities | D48: 1466602 | E48: 2008177 | F48: 2458187 | G48: 2673223
B49: Common stock par value | D49: 14 | E49: 14 | F49: 14 | G49: 14
B50: Additional paid-in capital | D50: 941206 | E50: 1009590 | F50: 1038213 | G50: 1045504
B51: Retained earnings | D51: 896738 | E51: 470319 | F51: 909024 | G51: 1610398
B52: Other comprehensive loss | D52: -9669 | E52: -1030 | F52: -11279 | G52: 20295
B53: Stockholder equity | D53: 1828289 | E53: 1478893 | F53: 1935972 | G53: 2676211
B54: Total liabilities and equity | D54: 3294891 | E54: 3487070 | F54: 4394159 | G54: 5349434
B56: Cashflow statement
B57: Net income | C57: =C17 -> 331113 | D57: =D17 -> 232354 | E57: =E17 -> 167078 | F57: =F17 -> 438705 | G57: =G17 -> 701374 | H57: =H17 -> 0 | I57: =I17 -> 0 | J57: =J17 -> 0 | K57: =K17 -> 0
B58: D&A | C58: 78183 | D58: 86708 | E58: 103821 | F58: 123109 | G58: 139631
B59: Stock-based compensation | C59: 13924 | D59: 5509 | E59: 46966 | F59: 84531 | G59: 43872
B60: Shareholder executive bonuses | C60: 0 | D60: 0 | E60: 32200 | F60: 0 | G60: 0
B61: Provision for credit losses | C61: 7913 | D61: 8965 | E61: 4474 | F61: 4724 | G61: 4740
B62: Provision for excess inventory | C62: 0 | D62: 0 | E62: 0 | F62: 0 | G62: 10468
B63: Non-cash lease expense | C63: 13062 | D63: 15475 | E63: 14708 | F63: 19466 | G63: 20431
B64: Deferred income taxes | C64: -15127 | D64: -16646 | E64: -41735 | F64: -47374 | G64: 38708
B65: Other | C65: 5398 | D65: 791 | E65: 8034 | F65: 886 | G65: 9386
B66: Change acc receivable | C66: -77444 | D66: 519 | E66: -229651 | F66: -299196 | G66: -350479
B67: Change inventory | C67: -185474 | D67: 53894 | E67: -155806 | F67: -204922 | G67: -87272
B68: Change prepaid expenses | C68: -47725 | D68: -114163 | E68: 99220 | F68: -57949 | G68: -84044
B69: Change acc payable | C69: 74850 | D69: -118161 | E69: 147513 | F69: 157341 | G69: 38147
... B93: End cash | C93: 240597 | D93: 218770 | E93: 154061 | F93: 363669 | G93: 777289
B95: Sanity checks
B96: Calculated Net Income | C96: =C5-C6-C11+C13+C14+C16 -> 331113 | D96: =D5-D6-D11+D13+D14+D16 -> 232354 | E96: =E5-E6-E11+E13+E14+E16 -> 167078 | F96: =F5-F6-F11+F13+F14+F16 -> 438705 | G96: =G5-G6-G11+G13+G14+G16 -> 701374 | H96: =H5-H6-H11+H13+H14+H16 -> 0 | I96: =I5-I6-I11+I13+I14+I16 -> 0 | J96: =J5-J6-J11+J13+J14+J16 -> 0 | K96: =K5-K6-K11+K13+K14+K16 -> 0
B97: Check Net Income | C97: =C17-C96 -> 0 | D97: =D17-D96 -> 0 | E97: =E17-E96 -> 0 | F97: =F17-F96 -> 0 | G97: =G17-G96 -> 0 | H97: =H17-H96 -> 0 | I97: =I17-I96 -> 0 | J97: =J17-J96 -> 0 | K97: =K17-K96 -> 0
B98: Calculated Assets | C98: =SUM(C24:C28)+SUM(C30:C35) -> 0 | D98: =SUM(D24:D28)+SUM(D30:D35) -> 3294891 | E98: =SUM(E24:E28)+SUM(E30:E35) -> 3487070 | F98: =SUM(F24:F28)+SUM(F30:F35) -> 4394159 | G98: =SUM(G24:G28)+SUM(G30:G35) -> 5349434 | H98: =SUM(H24:H28)+SUM(H30:H35) -> 0 | I98: =SUM(I24:I28)+SUM(I30:I35) -> 0 | J98: =SUM(J24:J28)+SUM(J30:J35) -> 0 | K98: =SUM(K24:K28)+SUM(K30:K35) -> 0
B99: Check Assets | C99: =C37-C98 -> 0 | D99: =D37-D98 -> 0 | E99: =E37-E98 -> 0 | F99: =F37-F98 -> 0 | G99: =G37-G98 -> 0 | H99: =H37-H98 -> 0 | I99: =I37-I98 -> 0 | J99: =J37-J98 -> 0 | K99: =K37-K98 -> 0
B100: Calculated Liabilities | C100: =SUM(C38:C41)+SUM(C43:C46) -> 0 | D100: =SUM(D38:D41)+SUM(D43:D46) -> 1466602 | E100: =SUM(E38:E41)+SUM(E43:E46) -> 2008177 | F100: =SUM(F38:F41)+SUM(F43:F46) -> 2458187 | G100: =SUM(G38:G41)+SUM(G43:G46) -> 2673223 | H100: =SUM(H38:H41)+SUM(H43:H43) -> 0 | I100: =SUM(I38:I41)+SUM(I43:I43) -> 0 | J100: =SUM(J38:J41)+SUM(J43:J43) -> 0 | K100: =SUM(K38:K41)+SUM(K43:K43) -> 0
B101: Check Liabilities | C101: =C48-C100 -> 0 | D101: =D48-D100 -> 0 | E101: =E48-E100 -> 0 | F101: =F48-F100 -> 0 | G101: =G48-G100 -> 0 | H101: =H48-H100 -> 0 | I101: =I48-I100 -> 0 | J101: =J48-J100 -> 0 | K101: =K48-K100 -> 0
B102: Calculated Stockholder Equity | C102: =SUM(C49:C52) -> 0 | D102: =SUM(D49:D52) -> 1828289 | E102: =SUM(E49:E52) -> 1478893 | F102: =SUM(F49:F52) -> 1935972 | G102: =SUM(G49:G52) -> 2676211 | H102: =SUM(H49:H52) -> 0 | I102: =SUM(I49:I52) -> 0 | J102: =SUM(J49:J52) -> 0 | K102: =SUM(K49:K52) -> 0
B103: Check Stockholder Equity | C103: =C53-C102 -> 0 | D103: =D53-D102 -> 0 | E103: =E53-E102 -> 0 | F103: =F53-F102 -> 0 | G103: =G53-G102 -> 0 | H103: =H53-H102 -> 0 | I103: =I53-I102 -> 0 | J103: =J53-J102 -> 0 | K103: =K53-K102 -> 0
B104: Check balance | C104: =C37-(C48+C53) -> 0 | D104: =D37-(D48+D53) -> 0 | E104: =E37-(E48+E53) -> 0 | F104: =F37-(F48+F53) -> 0 | G104: =G37-(G48+G53) -> 0 | H104: =H37-(H48+H53) -> 0 | I104: =I37-(I48+I53) -> 0 | J104: =J37-(J48+J53) -> 0 | K104: =K37-(K48+K53) -> 0
B105: Calculated Operating Cashflow | C105: =SUM(C57:C72) -> 229147 | D105: =SUM(D57:D72) -> 204964 | E105: =SUM(E57:E72) -> 280601 | F105: =SUM(F57:F72) -> 446620 | G105: =SUM(G57:G72) -> 634132 | H105: =SUM(H57:H72) -> 0 | I105: =SUM(I57:I72) -> 0 | J105: =SUM(J57:J72) -> 0 | K105: =SUM(K57:K72) -> 0
B106: Check Operating Cashflow | C106: =C73-C105 -> 0 | D106: =D73-D105 -> 0 | E106: =E73-E105 -> 0 | F106: =F73-F105 -> 0 | G106: =G73-G105 -> 0 | H106: =H73-H105 -> 0 | I106: =I73-I105 -> 0 | J106: =J73-J105 -> 0 | K106: =K73-K105 -> 0
B107: Calculated Investing Cashflow | C107: =SUM(C74:C79) -> -66366 | D107: =SUM(D74:D79) -> -52384 | E107: =SUM(E74:E79) -> -118075 | F107: =SUM(F74:F79) -> -151181 | G107: =SUM(G74:G79) -> -159779 | H107: =SUM(H74:H79) -> 0 | I107: =SUM(I74:I79) -> 0 | J107: =SUM(J74:J79) -> 0 | K107: =SUM(K74:K76) -> 0
B108: Check Investing Cashflow | C108: =C80-C107 -> 0 | D108: =D80-D107 -> 0 | E108: =E80-E107 -> 0 | F108: =F80-F107 -> 0 | G108: =G80-G107 -> 0 | H108: =H80-H107 -> 0 | I108: =I80-I107 -> 0 | J108: =J80-J107 -> 0 | K108: =K80-K107 -> 0
B109: Calculated Financing Cashflow | C109: =SUM(C81:C88) -> -54500 | D109: =SUM(D81:D88) -> -160170 | E109: =SUM(E81:E88) -> -234868 | F109: =SUM(F81:F88) -> -81221 | G109: =SUM(G81:G88) -> -77081 | H109: =SUM(H81:H88) -> 0 | I109: =SUM(I81:I88) -> 0 | J109: =SUM(J81:J88) -> 0 | K109: =SUM(K81:K88) -> 0
B110: Check Financing Cashflow | C110: =C89-C109 -> 0 | D110: =D89-D109 -> 0 | E110: =E89-E109 -> 0 | F110: =F89-F109 -> 0 | G110: =G89-G109 -> 0 | H110: =H89-H109 -> 0 | I110: =I89-I109 -> 0 | J110: =J89-J109 -> 0 | K110: =K89-K109 -> 0
B111: Calculated End Cash | C111: =C73+C80+C89+C92+C90 -> 240597 | D111: =D73+D80+D89+D92+D90 -> 218770 | E111: =E73+E80+E89+E92+E90 -> 154061 | F111: =F73+F80+F89+F92+F90 -> 363669 | G111: =G73+G80+G89+G92+G90 -> 777289 | H111: =H73+H80+H89+H92 -> 0 | I111: =I73+I80+I89+I92 -> 0 | J111: =J73+J80+J89+J92 -> 0 | K111: =K73+K80+K89+K92 -> 0
B112: Check End Cash | C112: =C93-C111 -> 0 | D112: =D93-D111 -> 0 | E112: =E93-E111 -> 0 | F112: =F93-F111 -> 0 | G112: =G93-G111 -> 0 | H112: =H93-H111 -> 0 | I112: =I93-I111 -> 0 | J112: =J93-J111 -> 0 | K112: =K93-K111 -> 0
B114: Other data
B115: Shares outstanding | E115: 139083 | F115: 140347 | G115: 141243
B116: Dividends per share | E116: 0 | F116: 0 | G116: 0
B117: Depreciation | C117: 56800 | D117: 64200 | E117: 81000 | F117: 98400 | G117: 115200
B118: Amortization | C118: 21341 | D118: 22535 | E118: 22782 | F118: 24665 | G118: 24388
B119: Tax rate | C119: =-(1*C16)/C15 -> 0.20083944 | D119: =-(1*D16)/D15 -> 0.23057513 | E119: =-(1*E16)/E15 -> 0.4302113 | F119: =-(1*F16)/F15 -> 0.23365888 | G119: =-(1*G16)/G15 -> 0.2209362
B120: Employees | C120: 2619 | E120: 3019 | F120: 3688 | G120: 4143
B123: Growth rates Income Statement
B124: Revenue | D124: =IF(C5=0, IF(D5=0,0,IF(D5>0,1,-1)), (D5-C5)/ABS(C5) ) -> -0.0025833151 | E124: =IF(D5=0, IF(E5=0,0,IF(E5>0,1,-1)), (E5-D5)/ABS(D5) ) -> 0.14428065 | F124: =IF(E5=0, IF(F5=0,0,IF(F5>0,1,-1)), (F5-E5)/ABS(E5) ) -> 0.29972165 | G124: =IF(F5=0, IF(G5=0,0,IF(G5>0,1,-1)), (G5-F5)/ABS(F5) ) -> 0.15746172
B125: COGS | D125: =IF(C6=0, IF(D6=0,0,IF(D6>0,1,-1)), (D6-C6)/ABS(C6) ) -> 0.0080225095 | E125: =IF(D6=0, IF(E6=0,0,IF(E6>0,1,-1)), (E6-D6)/ABS(D6) ) -> 0.016767714 | F125: =IF(E6=0, IF(F6=0,0,IF(F6>0,1,-1)), (F6-E6)/ABS(E6) ) -> 0.22200406 | G125: =IF(F6=0, IF(G6=0,0,IF(G6>0,1,-1)), (G6-F6)/ABS(F6) ) -> 0.13815788
B126: Gross Profit | D126: =IF(C7=0, IF(D7=0,0,IF(D7>0,1,-1)), (D7-C7)/ABS(C7) ) -> -0.019462044 | E126: =IF(D7=0, IF(E7=0,0,IF(E7>0,1,-1)), (E7-D7)/ABS(D7) ) -> 0.35290038 | F126: =IF(E7=0, IF(F7=0,0,IF(F7>0,1,-1)), (F7-E7)/ABS(E7) ) -> 0.39528171 | G126: =IF(F7=0, IF(G7=0,0,IF(G7>0,1,-1)), (G7-F7)/ABS(F7) ) -> 0.17824966
B127: R&D | D127: =IF(C8=0, IF(D8=0,0,IF(D8>0,1,-1)), (D8-C8)/ABS(C8) ) -> 0.074855089 | E127: =IF(D8=0, IF(E8=0,0,IF(E8>0,1,-1)), (E8-D8)/ABS(D8) ) -> 0.15638969 | F127: =IF(E8=0, IF(F8=0,0,IF(F8>0,1,-1)), (F8-E8)/ABS(E8) ) -> 0.36851159 | G127: =IF(F8=0, IF(G8=0,0,IF(G8>0,1,-1)), (G8-F8)/ABS(F8) ) -> 0.078478943
B128: Sales and marketing | D128: =IF(C9=0, IF(D9=0,0,IF(D9>0,1,-1)), (D9-C9)/ABS(C9) ) -> 0.0045077056 | E128: =IF(D9=0, IF(E9=0,0,IF(E9>0,1,-1)), (E9-D9)/ABS(D9) ) -> 0.44317175 | F128: =IF(E9=0, IF(F9=0,0,IF(F9>0,1,-1)), (F9-E9)/ABS(E9) ) -> 0.38498861 | G128: =IF(F9=0, IF(G9=0,0,IF(G9>0,1,-1)), (G9-F9)/ABS(F9) ) -> 0.17285353
B129: General and administrative | D129: =IF(C10=0, IF(D10=0,0,IF(D10>0,1,-1)), (D10-C10)/ABS(C10) ) -> 0.3946337 | E129: =IF(D10=0, IF(E10=0,0,IF(E10>0,1,-1)), (E10-D10)/ABS(D10) ) -> 0.54182009 | F129: =IF(E10=0, IF(F10=0,0,IF(F10>0,1,-1)), (F10-E10)/ABS(E10) ) -> 0.11897004 | G129: =IF(F10=0, IF(G10=0,0,IF(G10>0,1,-1)), (G10-F10)/ABS(F10) ) -> -0.099876556
B130: OpEx | D130: =IF(C11=0, IF(D11=0,0,IF(D11>0,1,-1)), (D11-C11)/ABS(C11) ) -> 0.08889949 | E130: =IF(D11=0, IF(E11=0,0,IF(E11>0,1,-1)), (E11-D11)/ABS(D11) ) -> 0.40912915 | F130: =IF(E11=0, IF(F11=0,0,IF(F11>0,1,-1)), (F11-E11)/ABS(E11) ) -> 0.31515661 | G130: =IF(F11=0, IF(G11=0,0,IF(G11>0,1,-1)), (G11-F11)/ABS(F11) ) -> 0.098313584
...

Sheet Statement Q
B2: Date | C2: 31.03.2024 | D2: 30.06.2024 | E2: 30.09.2024 | F2: 31.12.2024 | G2: 31.03.2025 | H2: 30.06.2025 | I2: 30.09.2025 | J2: 31.12.2025
B3: Q | C3: Q1 2024 | D3: Q2 2024 | E3: Q3 2024 | F3: Q4 2024 | G3: Q1 2025 | H3: Q2 2025 | I3: Q3 2025 | J3: Q4 2025 | P3: =I3 -> Q3 2025 | Q3: =J3 -> Q4 2025 | R3: Growth Rate
B4: Income statement | N4: TTM | P4: Quarter compare
B5: Revenue | C5: 1066228 | D5: 1248658 | E5: 1426566 | F5: 1787187 | G5: 1222638 | H5: 1444876 | I5: 1630240 | J5: 2101434 | N5: =SUM(G5:J5) -> 6399188 | P5: =I5 -> 1630240 | Q5: =J5 -> 2101434 | R5: =IF(P5=0, IF(Q5=0,0,IF(Q5>0,1,-1)), (Q5-P5)/ABS(P5) ) -> 0.28903352
B6: COGS | C6: 539611 | D6: 647759 | E6: 731559 | F6: 947719 | G6: 619412 | H6: 736709 | I6: 812771 | J6: 1093806 | N6: =SUM(G6:J6) -> 3262698 | P6: =I6 -> 812771 | Q6: =J6 -> 1093806 | R6: =IF(P6=0, IF(Q6=0,0,IF(Q6>0,1,-1)), (Q6-P6)/ABS(P6) ) -> 0.3457739
B7: Gross Profit | C7: =C5-C6 -> 526617 | D7: =D5-D6 -> 600899 | E7: =E5-E6 -> 695007 | F7: =F5-F6 -> 839468 | G7: =G5-G6 -> 603226 | H7: =H5-H6 -> 708167 | I7: =I5-I6 -> 817469 | J7: =J5-J6 -> 1007628 | N7: =SUM(G7:J7) -> 3136490 | P7: =I7 -> 817469 | Q7: =J7 -> 1007628 | R7: =IF(P7=0, IF(Q7=0,0,IF(Q7>0,1,-1)), (Q7-P7)/ABS(P7) ) -> 0.23261922
B8: R&D | C8: 69596 | D8: 90053 | E8: 94808 | F8: 86832 | G8: 87603 | H8: 89409 | I8: 92826 | J8: 98235 | N8: =SUM(G8:J8) -> 368073 | P8: =I8 -> 92826 | Q8: =J8 -> 98235 | R8: =IF(P8=0, IF(Q8=0,0,IF(Q8>0,1,-1)), (Q8-P8)/ABS(P8) ) -> 0.058270312
B9: Sales and marketing | C9: 214568 | D9: 303185 | E9: 300841 | F9: 424551 | G9: 275737 | H9: 357720 | I9: 365919 | J9: 458651 | N9: =SUM(G9:J9) -> 1458027 | P9: =I9 -> 365919 | Q9: =J9 -> 458651 | R9: =IF(P9=0, IF(Q9=0,0,IF(Q9>0,1,-1)), (Q9-P9)/ABS(P9) ) -> 0.25342221
B10: General and administrative | C10: 87511 | D10: 103825 | E10: 119096 | F10: 122963 | G10: 94940 | H10: 92391 | I10: 95833 | J10: 106945 | N10: =SUM(G10:J10) -> 390109 | P10: =I10 -> 95833 | Q10: =J10 -> 106945 | R10: =IF(P10=0, IF(Q10=0,0,IF(Q10>0,1,-1)), (Q10-P10)/ABS(P10) ) -> 0.11595171
B11: OpEx | C11: =SUM(C8:C10) -> 371675 | D11: =SUM(D8:D10) -> 497063 | E11: =SUM(E8:E10) -> 514745 | F11: =SUM(F8:F10) -> 634346 | G11: =SUM(G8:G10) -> 458280 | H11: =SUM(H8:H10) -> 539520 | I11: =SUM(I8:I10) -> 554578 | J11: =SUM(J8:J10) -> 663831 | N11: =SUM(G11:J11) -> 2216209 | P11: =I11 -> 554578 | Q11: =J11 -> 663831 | R11: =IF(P11=0, IF(Q11=0,0,IF(Q11>0,1,-1)), (Q11-P11)/ABS(P11) ) -> 0.19700204
B12: Operating income | C12: 154942 | D12: 103836 | E12: 180262 | F12: 205122 | G12: 144946 | H12: 168647 | I12: 262891 | J12: 343797 | N12: =SUM(G12:J12) -> 920281 | P12: =I12 -> 262891 | Q12: =J12 -> 343797 | R12: =IF(P12=0, IF(Q12=0,0,IF(Q12>0,1,-1)), (Q12-P12)/ABS(P12) ) -> 0.30775493
B13: Interest income/expense | C13: -14722 | D13: -14844 | E13: -16916 | F13: -17233 | G13: -12629 | H13: -13765 | I13: -12782 | J13: -9424 | N13: =SUM(G13:J13) -> -48600 | P13: =I13 -> -12782 | Q13: =J13 -> -9424 | R13: =IF(P13=0, IF(Q13=0,0,IF(Q13>0,1,-1)), (Q13-P13)/ABS(P13) ) -> 0.26271319
B14: Other income/expense | C14: 3248 | D14: 689 | E14: 11031 | F14: -22948 | G14: 13216 | H14: 26003 | I14: -6116 | J14: -4506 | N14: =SUM(G14:J14) -> 28597 | P14: =I14 -> -6116 | Q14: =J14 -> -4506 | R14: =IF(P14=0, IF(Q14=0,0,IF(Q14>0,1,-1)), (Q14-P14)/ABS(P14) ) -> 0.26324395
B15: Income before taxes | C15: 143468 | D15: 89681 | E15: 174377 | F15: 164941 | G15: 145533 | H15: 180885 | I15: 243993 | J15: 329867 | N15: =SUM(G15:J15) -> 900278 | P15: =I15 -> 243993 | Q15: =J15 -> 329867 | R15: =IF(P15=0, IF(Q15=0,0,IF(Q15>0,1,-1)), (Q15-P15)/ABS(P15) ) -> 0.35195272
B16: Income tax expense/benefit | C16: -33856 | D16: -21633 | E16: -42048 | F16: -36225 | G16: -27698 | H16: -41287 | I16: -55264 | J16: -74655 | N16: =SUM(G16:J16) -> -198904 | P16: =I16 -> -55264 | Q16: =J16 -> -74655 | R16: =IF(P16=0, IF(Q16=0,0,IF(Q16>0,1,-1)), (Q16-P16)/ABS(P16) ) -> -0.35087942
B17: Net income | C17: 109612 | D17: 68048 | E17: 132329 | F17: 128716 | G17: 117835 | H17: 139598 | I17: 188729 | J17: 255212 | N17: =SUM(G17:J17) -> 701374 | P17: =I17 -> 188729 | Q17: =J17 -> 255212 | R17: =IF(P17=0, IF(Q17=0,0,IF(Q17>0,1,-1)), (Q17-P17)/ABS(P17) ) -> 0.35226701
B18: Basic Shares outstanding avg | C18: 139449 | D18: 139888 | E18: 140114 | F18: 140285 | G18: 140622 | H18: 141044 | I18: 141112 | J18: 141151 | N18: =AVERAGE(G18:J18) -> 140982.25 | P18: =I18 -> 141112 | Q18: =J18 -> 141151 | R18: =IF(P18=0, IF(Q18=0,0,IF(Q18>0,1,-1)), (Q18-P18)/ABS(P18) ) -> 0.00027637621
B19: Diluted Shares outstanding avg | C19: 140703 | D19: 140924 | E19: 141306 | F19: 141518 | G19: 142183 | H19: 141871 | I19: 142119 | J19: 142129 | N19: =AVERAGE((G19:J19)) -> 142075.5 | P19: =I19 -> 142119 | Q19: =J19 -> 142129 | R19: =IF(P19=0, IF(Q19=0,0,IF(Q19>0,1,-1)), (Q19-P19)/ABS(P19) ) -> 7.0363569e-05
B20: Basic EPS | C20: 0.79 | D20: 0.49 | E20: 0.94 | F20: 0.92 | G20: 0.84 | H20: 0.99 | I20: 1.34 | J20: 1.81 | N20: =N17/N18 -> 4.97491 | P20: =I20 -> 1.34 | Q20: =J20 -> 1.81 | R20: =IF(P20=0, IF(Q20=0,0,IF(Q20>0,1,-1)), (Q20-P20)/ABS(P20) ) -> 0.35074627
B21: Diluted EPS | C21: 0.78 | D21: 0.48 | E21: 0.94 | F21: 0.91 | G21: 0.83 | H21: 0.98 | I21: 1.33 | J21: 1.8 | N21: =N17/N19 -> 4.9366288 | P21: =I21 -> 1.33 | Q21: =J21 -> 1.8 | R21: =IF(P21=0, IF(Q21=0,0,IF(Q21>0,1,-1)), (Q21-P21)/ABS(P21) ) -> 0.35338346
B23: Balance sheet
B24: Cash and cash equivalents | F24: 363669 | G24: 224696 | H24: 188229 | I24: 263816 | J24: 777289
B25: Restricted cash | F25: 0 | G25: 0 | H25: 0 | I25: 0 | J25: 0
B26: Acc receivable | F26: 1266595 | G26: 1040635 | H26: 1324984 | I26: 1595180 | J26: 1667143
B27: Inventories | F27: 899989 | G27: 973198 | H27: 1052711 | I27: 1158345 | J27: 1002205
B28: Prepaid expenses & Other current | F28: 114008 | G28: 157521 | H28: 190586 | I28: 226561 | J28: 164628
B29: Current assets | F29: 2644261 | G29: 2396050 | H29: 2756510 | I29: 3243902 | J29: 3611265
B30: PP&E | F30: 211464 | G30: 221700 | H30: 212771 | I30: 214693 | J30: 232226
B31: Operating lease right of use | F31: 146257 | G31: 143479 | H31: 140714 | I31: 147707 | J31: 142487
B32: Intangible assets | F32: 462678 | G32: 459539 | H32: 457536 | I32: 454477 | J32: 451137
B33: Goodwill | F33: 834781 | G33: 834781 | H33: 834781 | I33: 834781 | J33: 834781
B34: Deferred tax assets | F34: 43093 | G34: 58628 | H34: 73721 | I34: 10943 | J34: 10706
B35: Other assets | F35: 51625 | G35: 61225 | H35: 63224 | I35: 68469 | J35: 66832
B36: Long term assets | C36: =SUM(C30:C35) -> 0 | D36: =SUM(D30:D35) -> 0 | E36: =SUM(E30:E35) -> 0 | F36: =SUM(F30:F35) -> 1749898 | G36: =SUM(G30:G35) -> 1779352 | H36: =SUM(H30:H35) -> 1782747 | I36: =SUM(I30:I35) -> 1731070 | J36: =SUM(J30:J35) -> 1738169
B37: Total assets | F37: 4394159 | G37: 4175402 | H37: 4539257 | I37: 4974972 | J37: 5349434
B38: Acc payable | F38: 612031 | G38: 462495 | H38: 582560 | I38: 681808 | J38: 679534
B39: Accrued expenses | F39: 841529 | G39: 641667 | H39: 766630 | I39: 892459 | J39: 1016645
B40: Tax payable | F40: 36548 | G40: 70487 | H40: 29992 | I40: 43941 | J40: 38092
B41: Current portion long term debt | F41: 39344 | G41: 39344 | H41: 39344 | I41: 39344 | J41: 39344
B42: Current liabilities | F42: 1529452 | G42: 1213993 | H42: 1418526 | I42: 1657631 | J42: 1773615
B43: Long term debt | F43: 736139 | G43: 726303 | H43: 716467 | I43: 706631 | J43: 696795
B44: Operating lease | F44: 145377 | G44: 143339 | H44: 140126 | I44: 146661 | J44: 140981
B45: Deferred tax liabilities | F45: 9931 | G45: 16255 | H45: 19235 | I45: 18846 | J45: 16252
B46: Other liabilities | F46: 37288 | G46: 37279 | H46: 37230 | I46: 36985 | J46: 45580
B47: Long term liabilities | C47: =SUM(C43:C46) -> 0 | D47: =SUM(D43:D46) -> 0 | E47: =SUM(E43:E46) -> 0 | F47: =SUM(F43:F46) -> 928735 | G47: =SUM(G43:G46) -> 923176 | H47: =SUM(H43:H46) -> 913058 | I47: =SUM(I43:I46) -> 909123 | J47: =SUM(J43:J46) -> 899608
B48: Total liabilities | F48: 2458187 | G48: 2137169 | H48: 2331584 | I48: 2566675 | J48: 2673223
B49: Common stock par value | F49: 14 | G49: 14 | H49: 14 | I49: 14 | J49: 14
B50: Additional paid-in capital | F50: 1038213 | G50: 1008739 | H50: 1018879 | I50: 1034251 | J50: 1045504
B51: Retained earnings | F51: 909024 | G51: 1026859 | H51: 1166457 | I51: 1355186 | J51: 1610398
B52: Other comprehensive loss | F52: -11279 | G52: 2621 | H52: 22323 | I52: 18846 | J52: 20295
B53: Stockholder equity | F53: 1935972 | G53: 2038233 | H53: 2207673 | I53: 2408297 | J53: 2676211
B54: Total liabilities and equity | F54: 4394159 | G54: 4175402 | H54: 4539257 | I54: 4974972 | J54: 5349434
B56: Cashflow statement
B57: Net income | C57: =C17 -> 109612 | D57: =D17 -> 68048 | E57: =E17 -> 132329 | F57: =F17 -> 128716 | G57: =G17 -> 117835 | H57: =H17 -> 139598 | I57: =I17 -> 188729 | J57: =J17 -> 255212
B58: D&A | G58: 31946 | H58: 35071 | I58: 33673 | J58: 38941
B59: Stock-based compensation | G59: 11550 | H59: 10928 | I59: 9120 | J59: 12274
B60: Shareholder executive bonuses | G60: 0 | H60: 0 | I60: 0 | J60: 0
B61: Provision for credit losses | G61: 3178 | H61: 204 | I61: 90 | J61: 1268
B62: Provision excess inventory | G62: 0 | H62: 7364 | I62: 431 | J62: 2673
B63: Non-cash lease expense | G63: 4993 | H63: 4925 | I63: 5187 | J63: 5326
B64: Deferred income taxes | G64: -9211 | H64: -12113 | I64: 62389 | J64: -2357
B65: Other | G65: 870 | H65: 1204 | I65: 1558 | J65: 5754
B66: Change acc receivable | G66: 237353 | H66: -246190 | I66: -275878 | J66: -65764
B67: Change inventory | G67: -62850 | H67: -61872 | I67: -114166 | J67: 151616
B68: Change prepaid expenses | G68: -62900 | H68: -48198 | I68: -33765 | J68: 60819
B69: Change acc payable | G69: -156116 | H69: 94894 | I69: 99092 | J69: 277
... B78: Investment in equity method | G78: 0 | H78: 0 | I78: 0 | J78: 0
B79: Other investing | C79: 0 | D79: 0 | E79: 0 | F79: 0 | G79: 0 | H79: 0 | I79: 0 | J79: 0
B80: Investing cashflow | G80: -36809 | H80: -27606 | I80: -31624 | J80: -63740
B81: Issuance debt | G81: 0 | H81: 0 | I81: 0 | J81: 0
B82: Repayment debt | G82: -10125 | H82: -10125 | I82: -10125 | J82: -10125
B83: Shares issued employee purchse plan | G83: 7425 | H83: 0 | I83: 7399 | J83: 0
B84: Intercompany note former parent | G84: 0 | H84: 0 | I84: 0 | J84: 0
B85: Distribution to former parent | G85: 0 | H85: 0 | I85: 0 | J85: 0
B86: Recharge from former parent | G86: 0 | H86: 0 | I86: 0 | J86: 0
B87: Shares witheld for restricted stock units | G87: -48449 | H87: -788 | I87: -1147 | J87: -1021
B88: Dividend payments | G88: 0 | H88: 0 | I88: 0 | J88: 0
B89: Financing cashflow | G89: -51149 | H89: -10913 | I89: -3873 | J89: -11146
B90: Effect exchange rate | G90: 3841 | H90: 11134 | I90: 70 | J90: 1303
B91: Net increase/decrease in cash | G91: -138973 | H91: -36467 | I91: =L91-(G91+H91) -> 175440 | J91: 513473
B92: Begin cash | G92: 363669 | H92: 224696 | I92: 188229 | J92: 263816
B93: End cash | G93: 224696 | H93: 188229 | I93: 263816 | J93: =J91+J92 -> 777289
B95: Sanity checks
B96: Calculated Net Income | C96: =C5-C6-C11+C13+C14+C16 -> 109612 | D96: =D5-D6-D11+D13+D14+D16 -> 68048 | E96: =E5-E6-E11+E13+E14+E16 -> 132329 | F96: =F5-F6-F11+F13+F14+F16 -> 128716 | G96: =G5-G6-G11+G13+G14+G16 -> 117835 | H96: =H5-H6-H11+H13+H14+H16 -> 139598 | I96: =I5-I6-I11+I13+I14+I16 -> 188729 | J96: =J5-J6-J11+J13+J14+J16 -> 255212
B97: Check Net Income | C97: =C17-C96 -> 0 | D97: =D17-D96 -> 0 | E97: =E17-E96 -> 0 | F97: =F17-F96 -> 0 | G97: =G17-G96 -> 0 | H97: =H17-H96 -> 0 | I97: =I17-I96 -> 0 | J97: =J17-J96 -> 0
B98: Calculated Assets | C98: =SUM(C24:C28)+SUM(C30:C35) -> 0 | D98: =SUM(D24:D28)+SUM(D30:D35) -> 0 | E98: =SUM(E24:E28)+SUM(E30:E35) -> 0 | F98: =SUM(F24:F28)+SUM(F30:F35) -> 4394159 | G98: =SUM(G24:G28)+SUM(G30:G35) -> 4175402 | H98: =SUM(H24:H28)+SUM(H30:H35) -> 4539257 | I98: =SUM(I24:I28)+SUM(I30:I35) -> 4974972 | J98: =SUM(J24:J28)+SUM(J30:J35) -> 5349434
B99: Check Assets | C99: =C37-C98 -> 0 | D99: =D37-D98 -> 0 | E99: =E37-E98 -> 0 | F99: =F37-F98 -> 0 | G99: =G37-G98 -> 0 | H99: =H37-H98 -> 0 | I99: =I37-I98 -> 0 | J99: =J37-J98 -> 0
B100: Calculated Liabilities | C100: =SUM(C38:C41)+SUM(C43:C46) -> 0 | D100: =SUM(D38:D41)+SUM(D43:D46) -> 0 | E100: =SUM(E38:E41)+SUM(E43:E46) -> 0 | F100: =SUM(F38:F41)+SUM(F43:F46) -> 2458187 | G100: =SUM(G38:G41)+SUM(G43:G46) -> 2137169 | H100: =SUM(H38:H41)+SUM(H43:H46) -> 2331584 | I100: =SUM(I38:I41)+SUM(I43:I46) -> 2566675 | J100: =SUM(J38:J41)+SUM(J43:J46) -> 2673223
B101: Check Liabilities | C101: =C48-C100 -> 0 | D101: =D48-D100 -> 0 | E101: =E48-E100 -> 0 | F101: =F48-F100 -> 0 | G101: =G48-G100 -> 0 | H101: =H48-H100 -> 0 | I101: =I48-I100 -> 0 | J101: =J48-J100 -> 0
B102: Calculated Stockholder Equity | C102: =SUM(C49:C52) -> 0 | D102: =SUM(D49:D52) -> 0 | E102: =SUM(E49:E52) -> 0 | F102: =SUM(F49:F52) -> 1935972 | G102: =SUM(G49:G52) -> 2038233 | H102: =SUM(H49:H52) -> 2207673 | I102: =SUM(I49:I52) -> 2408297 | J102: =SUM(J49:J52) -> 2676211
B103: Check Stockholder Equity | C103: =C53-C102 -> 0 | D103: =D53-D102 -> 0 | E103: =E53-E102 -> 0 | F103: =F53-F102 -> 0 | G103: =G53-G102 -> 0 | H103: =H53-H102 -> 0 | I103: =I53-I102 -> 0 | J103: =J53-J102 -> 0
B104: Check balance | C104: =C37-(C48+C53) -> 0 | D104: =D37-(D48+D53) -> 0 | E104: =E37-(E48+E53) -> 0 | F104: =F37-(F48+F53) -> 0 | G104: =G37-(G48+G53) -> 0 | H104: =H37-(H48+H53) -> 0 | I104: =I37-(I48+I53) -> 0 | J104: =J37-(J48+J53) -> 0
B105: Calculated Operating Cashflow | C105: =SUM(C57:C72) -> 109612 | D105: =SUM(D57:D72) -> 68048 | E105: =SUM(E57:E72) -> 132329 | F105: =SUM(F57:F72) -> 128716 | G105: =SUM(G57:G72) -> -54856 | H105: =SUM(H57:H72) -> -9082 | I105: =SUM(I57:I72) -> 111014 | J105: =SUM(J57:J72) -> 587056
B106: Check Operating Cashflow | C106: =C73-C105 -> -109612 | D106: =D73-D105 -> -68048 | E106: =E73-E105 -> -132329 | F106: =F73-F105 -> -128716 | G106: =G73-G105 -> 0 | H106: =H73-H105 -> 0 | I106: =I73-I105 -> 0 | J106: =J73-J105 -> 0
B107: Calculated Investing Cashflow | C107: =SUM(C74:C78) -> 0 | D107: =SUM(D74:D78) -> 0 | E107: =SUM(E74:E78) -> 0 | F107: =SUM(F74:F78) -> 0 | G107: =SUM(G74:G78) -> -36809 | H107: =SUM(H74:H78) -> -27606 | I107: =SUM(I74:I78) -> -31624 | J107: =SUM(J74:J78) -> -63740
B108: Check Investing Cashflow | C108: =C80-C107 -> 0 | D108: =D80-D107 -> 0 | E108: =E80-E107 -> 0 | F108: =F80-F107 -> 0 | G108: =G80-G107 -> 0 | H108: =H80-H107 -> 0 | I108: =I80-I107 -> 0 | J108: =J80-J107 -> 0
B109: Calculated Financing Cashflow | C109: =SUM(C81:C88) -> 0 | D109: =SUM(D81:D88) -> 0 | E109: =SUM(E81:E88) -> 0 | F109: =SUM(F81:F88) -> 0 | G109: =SUM(G81:G88) -> -51149 | H109: =SUM(H81:H88) -> -10913 | I109: =SUM(I81:I88) -> -3873 | J109: =SUM(J81:J88) -> -11146
B110: Check Financing Cashflow | C110: =C89-C109 -> 0 | D110: =D89-D109 -> 0 | E110: =E89-E109 -> 0 | F110: =F89-F109 -> 0 | G110: =G89-G109 -> 0 | H110: =H89-H109 -> 0 | I110: =I89-I109 -> 0 | J110: =J89-J109 -> 0
B111: Calculated End Cash | C111: =C73+C80+C89+C92+C90 -> 0 | D111: =D73+D80+D89+D92+D90 -> 0 | E111: =E73+E80+E89+E92+E90 -> 0 | F111: =F73+F80+F89+F92+F90 -> 0 | G111: =G73+G80+G89+G92+G90 -> 224696 | H111: =H73+H80+H89+H92+H90 -> 188229 | I111: =I73+I80+I89+I92+I90 -> 263816 | J111: =J73+J80+J89+J92+J90 -> 777289
B112: Check End Cash | C112: =C93-C111 -> 0 | D112: =D93-D111 -> 0 | E112: =E93-E111 -> 0 | F112: =F93-F111 -> 0 | G112: =G93-G111 -> 0 | H112: =H93-H111 -> 0 | I112: =I93-I111 -> 0 | J112: =J93-J111 -> 0
...

Sheet Statements
B2: Date | C2: ='Statement Y'!C2 -> 31.12.2021 | D2: ='Statement Y'!D2 -> 31.12.2022 | E2: ='Statement Y'!E2 -> 31.12.2023 | F2: ='Statement Y'!F2 -> 31.12.2024 | G2: ='Statement Y'!G2 -> 31.12.2025 | I2: ='Statement Q'!C2 -> 31.03.2024 | J2: ='Statement Q'!D2 -> 30.06.2024 | K2: ='Statement Q'!E2 -> 30.09.2024 | L2: ='Statement Q'!F2 -> 31.12.2024 | M2: ='Statement Q'!G2 -> 31.03.2025 | N2: ='Statement Q'!H2 -> 30.06.2025 | O2: ='Statement Q'!I2 -> 30.09.2025 | P2: ='Statement Q'!J2 -> 31.12.2025
B3: FY | C3: ='Statement Y'!C3 -> 2021 | D3: ='Statement Y'!D3 -> 2022 | E3: ='Statement Y'!E3 -> 2023 | F3: ='Statement Y'!F3 -> 2024 | G3: ='Statement Y'!G3 -> 2025 | I3: ='Statement Q'!C3 -> Q1 2024 | J3: ='Statement Q'!D3 -> Q2 2024 | K3: ='Statement Q'!E3 -> Q3 2024 | L3: ='Statement Q'!F3 -> Q4 2024 | M3: ='Statement Q'!G3 -> Q1 2025 | N3: ='Statement Q'!H3 -> Q2 2025 | O3: ='Statement Q'!I3 -> Q3 2025 | P3: ='Statement Q'!J3 -> Q4 2025 | R3: TTM
B4: Income statement
B5: Revenue | C5: ='Statement Y'!C5 -> 3726994 | D5: ='Statement Y'!D5 -> 3717366 | E5: ='Statement Y'!E5 -> 4253710 | F5: ='Statement Y'!F5 -> 5528639 | G5: ='Statement Y'!G5 -> 6399188 | I5: ='Statement Q'!C5 -> 1066228 | J5: ='Statement Q'!D5 -> 1248658 | K5: ='Statement Q'!E5 -> 1426566 | L5: ='Statement Q'!F5 -> 1787187 | M5: ='Statement Q'!G5 -> 1222638 | N5: ='Statement Q'!H5 -> 1444876 | O5: ='Statement Q'!I5 -> 1630240 | P5: ='Statement Q'!J5 -> 2101434 | R5: =SUM(M5:P5) -> 6399188
B6: COGS | C6: ='Statement Y'!C6 -> 2288810 | D6: ='Statement Y'!D6 -> 2307172 | E6: ='Statement Y'!E6 -> 2345858 | F6: ='Statement Y'!F6 -> 2866648 | G6: ='Statement Y'!G6 -> 3262698 | I6: ='Statement Q'!C6 -> 539611 | J6: ='Statement Q'!D6 -> 647759 | K6: ='Statement Q'!E6 -> 731559 | L6: ='Statement Q'!F6 -> 947719 | M6: ='Statement Q'!G6 -> 619412 | N6: ='Statement Q'!H6 -> 736709 | O6: ='Statement Q'!I6 -> 812771 | P6: ='Statement Q'!J6 -> 1093806 | R6: =SUM(M6:P6) -> 3262698
B7: Gross Profit | C7: ='Statement Y'!C7 -> 1438184 | D7: ='Statement Y'!D7 -> 1410194 | E7: ='Statement Y'!E7 -> 1907852 | F7: ='Statement Y'!F7 -> 2661991 | G7: ='Statement Y'!G7 -> 3136490 | I7: ='Statement Q'!C7 -> 526617 | J7: ='Statement Q'!D7 -> 600899 | K7: ='Statement Q'!E7 -> 695007 | L7: ='Statement Q'!F7 -> 839468 | M7: ='Statement Q'!G7 -> 603226 | N7: ='Statement Q'!H7 -> 708167 | O7: ='Statement Q'!I7 -> 817469 | P7: ='Statement Q'!J7 -> 1007628 | R7: =SUM(M7:P7) -> 3136490
B8: R&D | C8: ='Statement Y'!C8 -> 200641 | D8: ='Statement Y'!D8 -> 215660 | E8: ='Statement Y'!E8 -> 249387 | F8: ='Statement Y'!F8 -> 341289 | G8: ='Statement Y'!G8 -> 368073 | I8: ='Statement Q'!C8 -> 69596 | J8: ='Statement Q'!D8 -> 90053 | K8: ='Statement Q'!E8 -> 94808 | L8: ='Statement Q'!F8 -> 86832 | M8: ='Statement Q'!G8 -> 87603 | N8: ='Statement Q'!H8 -> 89409 | O8: ='Statement Q'!I8 -> 92826 | P8: ='Statement Q'!J8 -> 98235 | R8: =SUM(M8:P8) -> 368073
B9: Sales and marketing | C9: ='Statement Y'!C9 -> 619162 | D9: ='Statement Y'!D9 -> 621953 | E9: ='Statement Y'!E9 -> 897585 | F9: ='Statement Y'!F9 -> 1243145 | G9: ='Statement Y'!G9 -> 1458027 | I9: ='Statement Q'!C9 -> 214568 | J9: ='Statement Q'!D9 -> 303185 | K9: ='Statement Q'!E9 -> 300841 | L9: ='Statement Q'!F9 -> 424551 | M9: ='Statement Q'!G9 -> 275737 | N9: ='Statement Q'!H9 -> 357720 | O9: ='Statement Q'!I9 -> 365919 | P9: ='Statement Q'!J9 -> 458651 | R9: =SUM(M9:P9) -> 1458027
B10: General and administrative | C10: ='Statement Y'!C10 -> 180124 | D10: ='Statement Y'!D10 -> 251207 | E10: ='Statement Y'!E10 -> 387316 | F10: ='Statement Y'!F10 -> 433395 | G10: ='Statement Y'!G10 -> 390109 | I10: ='Statement Q'!C10 -> 87511 | J10: ='Statement Q'!D10 -> 103825 | K10: ='Statement Q'!E10 -> 119096 | L10: ='Statement Q'!F10 -> 122963 | M10: ='Statement Q'!G10 -> 94940 | N10: ='Statement Q'!H10 -> 92391 | O10: ='Statement Q'!I10 -> 95833 | P10: ='Statement Q'!J10 -> 106945 | R10: =SUM(M10:P10) -> 390109
B11: OpEx | C11: ='Statement Y'!C11 -> 999927 | D11: ='Statement Y'!D11 -> 1088820 | E11: ='Statement Y'!E11 -> 1534288 | F11: ='Statement Y'!F11 -> 2017829 | G11: ='Statement Y'!G11 -> 2216209 | I11: ='Statement Q'!C11 -> 371675 | J11: ='Statement Q'!D11 -> 497063 | K11: ='Statement Q'!E11 -> 514745 | L11: ='Statement Q'!F11 -> 634346 | M11: ='Statement Q'!G11 -> 458280 | N11: ='Statement Q'!H11 -> 539520 | O11: ='Statement Q'!I11 -> 554578 | P11: ='Statement Q'!J11 -> 663831 | R11: =SUM(M11:P11) -> 2216209
B12: Operating income | C12: ='Statement Y'!C12 -> 438257 | D12: ='Statement Y'!D12 -> 321374 | E12: ='Statement Y'!E12 -> 373564 | F12: ='Statement Y'!F12 -> 644162 | G12: ='Statement Y'!G12 -> 920281 | I12: ='Statement Q'!C12 -> 154942 | J12: ='Statement Q'!D12 -> 103836 | K12: ='Statement Q'!E12 -> 180262 | L12: ='Statement Q'!F12 -> 205122 | M12: ='Statement Q'!G12 -> 144946 | N12: ='Statement Q'!H12 -> 168647 | O12: ='Statement Q'!I12 -> 262891 | P12: ='Statement Q'!J12 -> 343797 | R12: =SUM(M12:P12) -> 920281
B13: EBITDA | C13: =C12+C57 -> 516440 | D13: =D12+D57 -> 408082 | E13: =E12+E57 -> 477385 | F13: =F12+F57 -> 767271 | G13: =G12+G57 -> 1059912 | I13: =I12+I57 -> 154942 | J13: =J12+J57 -> 103836 | K13: =K12+K57 -> 180262 | L13: =L12+L57 -> 205122 | M13: =M12+M57 -> 176892 | N13: =N12+N57 -> 203718 | O13: =O12+O57 -> 296564 | P13: =P12+P57 -> 382738 | R13: =SUM(M13:P13) -> 1059912
B14: Other income/expense | C14: ='Statement Y'!C13 -> -16287 | D14: ='Statement Y'!D13 -> -27021 | E14: ='Statement Y'!E13 -> -44909 | F14: ='Statement Y'!F13 -> -63715 | G14: ='Statement Y'!G13 -> -48600 | I14: ='Statement Q'!C13 -> -14722 | J14: ='Statement Q'!D13 -> -14844 | K14: ='Statement Q'!E13 -> -16916 | L14: ='Statement Q'!F13 -> -17233 | M14: ='Statement Q'!G13 -> -12629 | N14: ='Statement Q'!H13 -> -13765 | O14: ='Statement Q'!I13 -> -12782 | P14: ='Statement Q'!J13 -> -9424 | R14: =SUM(M14:P14) -> -48600
B15: Interest income | C15: ='Statement Y'!C14 -> -7644 | D15: ='Statement Y'!D14 -> 7631 | E15: ='Statement Y'!E14 -> -35427 | F15: ='Statement Y'!F14 -> -7980 | G15: ='Statement Y'!G14 -> 28597 | I15: ='Statement Q'!C14 -> 3248 | J15: ='Statement Q'!D14 -> 689 | K15: ='Statement Q'!E14 -> 11031 | L15: ='Statement Q'!F14 -> -22948 | M15: ='Statement Q'!G14 -> 13216 | N15: ='Statement Q'!H14 -> 26003 | O15: ='Statement Q'!I14 -> -6116 | P15: ='Statement Q'!J14 -> -4506 | R15: =SUM(M15:P15) -> 28597
B16: Income before taxes | C16: ='Statement Y'!C15 -> 414326 | D16: ='Statement Y'!D15 -> 301984 | E16: ='Statement Y'!E15 -> 293228 | F16: ='Statement Y'!F15 -> 572467 | G16: ='Statement Y'!G15 -> 900278 | I16: ='Statement Q'!C15 -> 143468 | J16: ='Statement Q'!D15 -> 89681 | K16: ='Statement Q'!E15 -> 174377 | L16: ='Statement Q'!F15 -> 164941 | M16: ='Statement Q'!G15 -> 145533 | N16: ='Statement Q'!H15 -> 180885 | O16: ='Statement Q'!I15 -> 243993 | P16: ='Statement Q'!J15 -> 329867 | R16: =SUM(M16:P16) -> 900278
B17: Income tax expense/benefit | C17: ='Statement Y'!C16 -> -83213 | D17: ='Statement Y'!D16 -> -69630 | E17: ='Statement Y'!E16 -> -126150 | F17: ='Statement Y'!F16 -> -133762 | G17: ='Statement Y'!G16 -> -198904 | I17: ='Statement Q'!C16 -> -33856 | J17: ='Statement Q'!D16 -> -21633 | K17: ='Statement Q'!E16 -> -42048 | L17: ='Statement Q'!F16 -> -36225 | M17: ='Statement Q'!G16 -> -27698 | N17: ='Statement Q'!H16 -> -41287 | O17: ='Statement Q'!I16 -> -55264 | P17: ='Statement Q'!J16 -> -74655 | R17: =SUM(M17:P17) -> -198904
B18: Net income | C18: ='Statement Y'!C17 -> 331113 | D18: ='Statement Y'!D17 -> 232354 | E18: ='Statement Y'!E17 -> 167078 | F18: ='Statement Y'!F17 -> 438705 | G18: ='Statement Y'!G17 -> 701374 | I18: ='Statement Q'!C17 -> 109612 | J18: ='Statement Q'!D17 -> 68048 | K18: ='Statement Q'!E17 -> 132329 | L18: ='Statement Q'!F17 -> 128716 | M18: ='Statement Q'!G17 -> 117835 | N18: ='Statement Q'!H17 -> 139598 | O18: ='Statement Q'!I17 -> 188729 | P18: ='Statement Q'!J17 -> 255212 | R18: =SUM(M18:P18) -> 701374
B19: Diluted Shares outstanding avg | C19: ='Statement Y'!C19 -> 138983 | D19: ='Statement Y'!D19 -> 138983 | E19: ='Statement Y'!E19 -> 139420 | F19: ='Statement Y'!F19 -> 141084 | G19: ='Statement Y'!G19 -> 142090 | I19: ='Statement Q'!C19 -> 140703 | J19: ='Statement Q'!D19 -> 140924 | K19: ='Statement Q'!E19 -> 141306 | L19: ='Statement Q'!F19 -> 141518 | M19: ='Statement Q'!G19 -> 142183 | N19: ='Statement Q'!H19 -> 141871 | O19: ='Statement Q'!I19 -> 142119 | P19: ='Statement Q'!J19 -> 142129 | R19: =AVERAGE(M19:P19) -> 142075.5
B20: Diluted EPS | C20: ='Statement Y'!C21 -> 2.38 | D20: ='Statement Y'!D21 -> 1.67 | E20: ='Statement Y'!E21 -> 1.2 | F20: ='Statement Y'!F21 -> 3.11 | G20: ='Statement Y'!G21 -> 4.94 | I20: ='Statement Q'!C21 -> 0.78 | J20: ='Statement Q'!D21 -> 0.48 | K20: ='Statement Q'!E21 -> 0.94 | L20: ='Statement Q'!F21 -> 0.91 | M20: ='Statement Q'!G21 -> 0.83 | N20: ='Statement Q'!H21 -> 0.98 | O20: ='Statement Q'!I21 -> 1.33 | P20: ='Statement Q'!J21 -> 1.8 | R20: =SUM(M20:P20) -> 4.94
B22: Balance sheet
B23: Cash and cash equivalents | C23: ='Statement Y'!C24 -> 0 | D23: ='Statement Y'!D24 -> 192890 | E23: ='Statement Y'!E24 -> 154061 | F23: ='Statement Y'!F24 -> 363669 | G23: ='Statement Y'!G24 -> 777289 | I23: ='Statement Q'!C24 -> 0 | J23: ='Statement Q'!D24 -> 0 | K23: ='Statement Q'!E24 -> 0 | L23: ='Statement Q'!F24 -> 363669 | M23: ='Statement Q'!G24 -> 224696 | N23: ='Statement Q'!H24 -> 188229 | O23: ='Statement Q'!I24 -> 263816 | P23: ='Statement Q'!J24 -> 777289 | R23: =P23 -> 777289
B24: Restricted cash | C24: ='Statement Y'!C25 -> 0 | D24: ='Statement Y'!D25 -> 25880 | E24: ='Statement Y'!E25 -> 0 | F24: ='Statement Y'!F25 -> 0 | G24: ='Statement Y'!G25 -> 0 | I24: ='Statement Q'!C25 -> 0 | J24: ='Statement Q'!D25 -> 0 | K24: ='Statement Q'!E25 -> 0 | L24: ='Statement Q'!F25 -> 0 | M24: ='Statement Q'!G25 -> 0 | N24: ='Statement Q'!H25 -> 0 | O24: ='Statement Q'!I25 -> 0 | P24: ='Statement Q'!J25 -> 0 | R24: =P24 -> 0
B25: Acc receivable | C25: ='Statement Y'!C26 -> 0 | D25: ='Statement Y'!D26 -> 766503 | E25: ='Statement Y'!E26 -> 985172 | F25: ='Statement Y'!F26 -> 1266595 | G25: ='Statement Y'!G26 -> 1667143 | I25: ='Statement Q'!C26 -> 0 | J25: ='Statement Q'!D26 -> 0 | K25: ='Statement Q'!E26 -> 0 | L25: ='Statement Q'!F26 -> 1266595 | M25: ='Statement Q'!G26 -> 1040635 | N25: ='Statement Q'!H26 -> 1324984 | O25: ='Statement Q'!I26 -> 1595180 | P25: ='Statement Q'!J26 -> 1667143 | R25: =P25 -> 1667143
B26: Inventories | C26: ='Statement Y'!C27 -> 0 | D26: ='Statement Y'!D27 -> 548588 | E26: ='Statement Y'!E27 -> 699740 | F26: ='Statement Y'!F27 -> 899989 | G26: ='Statement Y'!G27 -> 1002205 | I26: ='Statement Q'!C27 -> 0 | J26: ='Statement Q'!D27 -> 0 | K26: ='Statement Q'!E27 -> 0 | L26: ='Statement Q'!F27 -> 899989 | M26: ='Statement Q'!G27 -> 973198 | N26: ='Statement Q'!H27 -> 1052711 | O26: ='Statement Q'!I27 -> 1158345 | P26: ='Statement Q'!J27 -> 1002205 | R26: =P26 -> 1002205
B27: Prepaid expenses & Other current | C27: ='Statement Y'!C28 -> 0 | D27: ='Statement Y'!D28 -> 181831 | E27: ='Statement Y'!E28 -> 58311 | F27: ='Statement Y'!F28 -> 114008 | G27: ='Statement Y'!G28 -> 164628 | I27: ='Statement Q'!C28 -> 0 | J27: ='Statement Q'!D28 -> 0 | K27: ='Statement Q'!E28 -> 0 | L27: ='Statement Q'!F28 -> 114008 | M27: ='Statement Q'!G28 -> 157521 | N27: ='Statement Q'!H28 -> 190586 | O27: ='Statement Q'!I28 -> 226561 | P27: ='Statement Q'!J28 -> 164628 | R27: =P27 -> 164628
B28: Current assets | C28: ='Statement Y'!C29 -> 0 | D28: ='Statement Y'!D29 -> 1715692 | E28: ='Statement Y'!E29 -> 1897284 | F28: ='Statement Y'!F29 -> 2644261 | G28: ='Statement Y'!G29 -> 3611265 | I28: ='Statement Q'!C29 -> 0 | J28: ='Statement Q'!D29 -> 0 | K28: ='Statement Q'!E29 -> 0 | L28: ='Statement Q'!F29 -> 2644261 | M28: ='Statement Q'!G29 -> 2396050 | N28: ='Statement Q'!H29 -> 2756510 | O28: ='Statement Q'!I29 -> 3243902 | P28: ='Statement Q'!J29 -> 3611265 | R28: =P28 -> 3611265
B29: PP&E | C29: ='Statement Y'!C30 -> 0 | D29: ='Statement Y'!D30 -> 137341 | E29: ='Statement Y'!E30 -> 166252 | F29: ='Statement Y'!F30 -> 211464 | G29: ='Statement Y'!G30 -> 232226 | I29: ='Statement Q'!C30 -> 0 | J29: ='Statement Q'!D30 -> 0 | K29: ='Statement Q'!E30 -> 0 | L29: ='Statement Q'!F30 -> 211464 | M29: ='Statement Q'!G30 -> 221700 | N29: ='Statement Q'!H30 -> 212771 | O29: ='Statement Q'!I30 -> 214693 | P29: ='Statement Q'!J30 -> 232226 | R29: =P29 -> 232226
B30: Operating lease right of use | C30: ='Statement Y'!C31 -> 0 | D30: ='Statement Y'!D31 -> 67321 | E30: ='Statement Y'!E31 -> 63333 | F30: ='Statement Y'!F31 -> 146257 | G30: ='Statement Y'!G31 -> 142487 | I30: ='Statement Q'!C31 -> 0 | J30: ='Statement Q'!D31 -> 0 | K30: ='Statement Q'!E31 -> 0 | L30: ='Statement Q'!F31 -> 146257 | M30: ='Statement Q'!G31 -> 143479 | N30: ='Statement Q'!H31 -> 140714 | O30: ='Statement Q'!I31 -> 147707 | P30: ='Statement Q'!J31 -> 142487 | R30: =P30 -> 142487
B31: Intangible assets | C31: ='Statement Y'!C32 -> 0 | D31: ='Statement Y'!D32 -> 492709 | E31: ='Statement Y'!E32 -> 477816 | F31: ='Statement Y'!F32 -> 462678 | G31: ='Statement Y'!G32 -> 451137 | I31: ='Statement Q'!C32 -> 0 | J31: ='Statement Q'!D32 -> 0 | K31: ='Statement Q'!E32 -> 0 | L31: ='Statement Q'!F32 -> 462678 | M31: ='Statement Q'!G32 -> 459539 | N31: ='Statement Q'!H32 -> 457536 | O31: ='Statement Q'!I32 -> 454477 | P31: ='Statement Q'!J32 -> 451137 | R31: =P31 -> 451137
B32: Goodwill | C32: ='Statement Y'!C33 -> 0 | D32: ='Statement Y'!D33 -> 840148 | E32: ='Statement Y'!E33 -> 834203 | F32: ='Statement Y'!F33 -> 834781 | G32: ='Statement Y'!G33 -> 834781 | I32: ='Statement Q'!C33 -> 0 | J32: ='Statement Q'!D33 -> 0 | K32: ='Statement Q'!E33 -> 0 | L32: ='Statement Q'!F33 -> 834781 | M32: ='Statement Q'!G33 -> 834781 | N32: ='Statement Q'!H33 -> 834781 | O32: ='Statement Q'!I33 -> 834781 | P32: ='Statement Q'!J33 -> 834781 | R32: =P32 -> 834781
B33: Deferred tax assets | C33: ='Statement Y'!C34 -> 0 | D33: ='Statement Y'!D34 -> 6291 | E33: ='Statement Y'!E34 -> 12 | F33: ='Statement Y'!F34 -> 43093 | G33: ='Statement Y'!G34 -> 10706 | I33: ='Statement Q'!C34 -> 0 | J33: ='Statement Q'!D34 -> 0 | K33: ='Statement Q'!E34 -> 0 | L33: ='Statement Q'!F34 -> 43093 | M33: ='Statement Q'!G34 -> 58628 | N33: ='Statement Q'!H34 -> 73721 | O33: ='Statement Q'!I34 -> 10943 | P33: ='Statement Q'!J34 -> 10706 | R33: =P33 -> 10706
B34: Other assets | C34: ='Statement Y'!C35 -> 0 | D34: ='Statement Y'!D35 -> 35389 | E34: ='Statement Y'!E35 -> 48170 | F34: ='Statement Y'!F35 -> 51625 | G34: ='Statement Y'!G35 -> 66832 | I34: ='Statement Q'!C35 -> 0 | J34: ='Statement Q'!D35 -> 0 | K34: ='Statement Q'!E35 -> 0 | L34: ='Statement Q'!F35 -> 51625 | M34: ='Statement Q'!G35 -> 61225 | N34: ='Statement Q'!H35 -> 63224 | O34: ='Statement Q'!I35 -> 68469 | P34: ='Statement Q'!J35 -> 66832 | R34: =P34 -> 66832
... B53: Total liabilities and equity | C53: ='Statement Y'!C54 -> 0 | D53: ='Statement Y'!D54 -> 3294891 | E53: ='Statement Y'!E54 -> 3487070 | F53: ='Statement Y'!F54 -> 4394159 | G53: ='Statement Y'!G54 -> 5349434 | I53: ='Statement Q'!C54 -> 0 | J53: ='Statement Q'!D54 -> 0 | K53: ='Statement Q'!E54 -> 0 | L53: ='Statement Q'!F54 -> 4394159 | M53: ='Statement Q'!G54 -> 4175402 | N53: ='Statement Q'!H54 -> 4539257 | O53: ='Statement Q'!I54 -> 4974972 | P53: ='Statement Q'!J54 -> 5349434 | R53: =P53 -> 5349434
B55: Cashflow statement
B56: Net income | C56: ='Statement Y'!C57 -> 331113 | D56: ='Statement Y'!D57 -> 232354 | E56: ='Statement Y'!E57 -> 167078 | F56: ='Statement Y'!F57 -> 438705 | G56: ='Statement Y'!G57 -> 701374 | I56: ='Statement Q'!C57 -> 109612 | J56: ='Statement Q'!D57 -> 68048 | K56: ='Statement Q'!E57 -> 132329 | L56: ='Statement Q'!F57 -> 128716 | M56: ='Statement Q'!G57 -> 117835 | N56: ='Statement Q'!H57 -> 139598 | O56: ='Statement Q'!I57 -> 188729 | P56: ='Statement Q'!J57 -> 255212 | R56: =SUM(M56:P56) -> 701374
B57: D&A | C57: ='Statement Y'!C58 -> 78183 | D57: ='Statement Y'!D58 -> 86708 | E57: ='Statement Y'!E58 -> 103821 | F57: ='Statement Y'!F58 -> 123109 | G57: ='Statement Y'!G58 -> 139631 | I57: ='Statement Q'!C58 -> 0 | J57: ='Statement Q'!D58 -> 0 | K57: ='Statement Q'!E58 -> 0 | L57: ='Statement Q'!F58 -> 0 | M57: ='Statement Q'!G58 -> 31946 | N57: ='Statement Q'!H58 -> 35071 | O57: ='Statement Q'!I58 -> 33673 | P57: ='Statement Q'!J58 -> 38941 | R57: =SUM(M57:P57) -> 139631
B58: Stock-based compensation | C58: ='Statement Y'!C59 -> 13924 | D58: ='Statement Y'!D59 -> 5509 | E58: ='Statement Y'!E59 -> 46966 | F58: ='Statement Y'!F59 -> 84531 | G58: ='Statement Y'!G59 -> 43872 | I58: ='Statement Q'!C59 -> 0 | J58: ='Statement Q'!D59 -> 0 | K58: ='Statement Q'!E59 -> 0 | L58: ='Statement Q'!F59 -> 0 | M58: ='Statement Q'!G59 -> 11550 | N58: ='Statement Q'!H59 -> 10928 | O58: ='Statement Q'!I59 -> 9120 | P58: ='Statement Q'!J59 -> 12274 | R58: =SUM(M58:P58) -> 43872
B59: Shareholder executive bonuses | C59: ='Statement Y'!C60 -> 0 | D59: ='Statement Y'!D60 -> 0 | E59: ='Statement Y'!E60 -> 32200 | F59: ='Statement Y'!F60 -> 0 | G59: ='Statement Y'!G60 -> 0 | I59: ='Statement Q'!C60 -> 0 | J59: ='Statement Q'!D60 -> 0 | K59: ='Statement Q'!E60 -> 0 | L59: ='Statement Q'!F60 -> 0 | M59: ='Statement Q'!G60 -> 0 | N59: ='Statement Q'!H60 -> 0 | O59: ='Statement Q'!I60 -> 0 | P59: ='Statement Q'!J60 -> 0 | R59: =SUM(M59:P59) -> 0
B60: Provision for credit losses | C60: ='Statement Y'!C61 -> 7913 | D60: ='Statement Y'!D61 -> 8965 | E60: ='Statement Y'!E61 -> 4474 | F60: ='Statement Y'!F61 -> 4724 | G60: ='Statement Y'!G61 -> 4740 | I60: ='Statement Q'!C61 -> 0 | J60: ='Statement Q'!D61 -> 0 | K60: ='Statement Q'!E61 -> 0 | L60: ='Statement Q'!F61 -> 0 | M60: ='Statement Q'!G61 -> 3178 | N60: ='Statement Q'!H61 -> 204 | O60: ='Statement Q'!I61 -> 90 | P60: ='Statement Q'!J61 -> 1268 | R60: =SUM(M60:P60) -> 4740
B61: Non-cash lease expense | C61: ='Statement Y'!C63 -> 13062 | D61: ='Statement Y'!D63 -> 15475 | E61: ='Statement Y'!E63 -> 14708 | F61: ='Statement Y'!F63 -> 19466 | G61: ='Statement Y'!G63 -> 20431 | I61: ='Statement Q'!C63 -> 0 | J61: ='Statement Q'!D63 -> 0 | K61: ='Statement Q'!E63 -> 0 | L61: ='Statement Q'!F63 -> 0 | M61: ='Statement Q'!G63 -> 4993 | N61: ='Statement Q'!H63 -> 4925 | O61: ='Statement Q'!I63 -> 5187 | P61: ='Statement Q'!J63 -> 5326 | R61: =SUM(M61:P61) -> 20431
B62: Deferred income taxes | C62: ='Statement Y'!C64 -> -15127 | D62: ='Statement Y'!D64 -> -16646 | E62: ='Statement Y'!E64 -> -41735 | F62: ='Statement Y'!F64 -> -47374 | G62: ='Statement Y'!G64 -> 38708 | I62: ='Statement Q'!C64 -> 0 | J62: ='Statement Q'!D64 -> 0 | K62: ='Statement Q'!E64 -> 0 | L62: ='Statement Q'!F64 -> 0 | M62: ='Statement Q'!G64 -> -9211 | N62: ='Statement Q'!H64 -> -12113 | O62: ='Statement Q'!I64 -> 62389 | P62: ='Statement Q'!J64 -> -2357 | R62: =SUM(M62:P62) -> 38708
B63: Other | C63: ='Statement Y'!C65 -> 5398 | D63: ='Statement Y'!D65 -> 791 | E63: ='Statement Y'!E65 -> 8034 | F63: ='Statement Y'!F65 -> 886 | G63: ='Statement Y'!G65 -> 9386 | I63: ='Statement Q'!C65 -> 0 | J63: ='Statement Q'!D65 -> 0 | K63: ='Statement Q'!E65 -> 0 | L63: ='Statement Q'!F65 -> 0 | M63: ='Statement Q'!G65 -> 870 | N63: ='Statement Q'!H65 -> 1204 | O63: ='Statement Q'!I65 -> 1558 | P63: ='Statement Q'!J65 -> 5754 | R63: =SUM(M63:P63) -> 9386
B64: Change NWC | C64: =SUM('Statement Y'!C66:C72) -> -205319 | D64: =SUM('Statement Y'!D66:D72) -> -128192 | E64: =SUM('Statement Y'!E66:E72) -> -54945 | F64: =SUM('Statement Y'!F66:F72) -> -177427 | G64: =SUM('Statement Y'!G66:G72) -> -334478 | I64: =SUM('Statement Q'!C69:C72) -> 0 | J64: =SUM('Statement Q'!D69:D72) -> 0 | K64: =SUM('Statement Q'!E69:E72) -> 0 | L64: =SUM('Statement Q'!F69:F72) -> 0 | M64: =SUM('Statement Q'!G69:G72) -> -327620 | N64: =SUM('Statement Q'!H69:H72) -> 159997 | O64: =SUM('Statement Q'!I69:I72) -> 233646 | P64: =SUM('Statement Q'!J69:J72) -> 121294 | R64: =SUM(M64:P64) -> 187317
B65: Operating cashflow | C65: ='Statement Y'!C73 -> 229147 | D65: ='Statement Y'!D73 -> 204964 | E65: ='Statement Y'!E73 -> 280601 | F65: ='Statement Y'!F73 -> 446620 | G65: ='Statement Y'!G73 -> 634132 | I65: ='Statement Q'!C73 -> 0 | J65: ='Statement Q'!D73 -> 0 | K65: ='Statement Q'!E73 -> 0 | L65: ='Statement Q'!F73 -> 0 | M65: ='Statement Q'!G73 -> -54856 | N65: ='Statement Q'!H73 -> -9082 | O65: ='Statement Q'!I73 -> 111014 | P65: ='Statement Q'!J73 -> 587056 | R65: =SUM(M65:P65) -> 634132
B66: Capex | C66: ='Statement Y'!C74 -> -47992 | D66: ='Statement Y'!D74 -> -80257 | E66: ='Statement Y'!E74 -> -122741 | F66: ='Statement Y'!F74 -> -137687 | G66: ='Statement Y'!G74 -> -146082 | I66: ='Statement Q'!C74 -> 0 | J66: ='Statement Q'!D74 -> 0 | K66: ='Statement Q'!E74 -> 0 | L66: ='Statement Q'!F74 -> 0 | M66: ='Statement Q'!G74 -> -32661 | N66: ='Statement Q'!H74 -> -27432 | O66: ='Statement Q'!I74 -> -24845 | P66: ='Statement Q'!J74 -> -61144 | R66: =SUM(M66:P66) -> -146082
B67: Purchase intangible assets | C67: ='Statement Y'!C75 -> -5068 | D67: ='Statement Y'!D75 -> -7348 | E67: ='Statement Y'!E75 -> -8497 | F67: ='Statement Y'!F75 -> -9916 | G67: ='Statement Y'!G75 -> -12374 | I67: ='Statement Q'!C75 -> 0 | J67: ='Statement Q'!D75 -> 0 | K67: ='Statement Q'!E75 -> 0 | L67: ='Statement Q'!F75 -> 0 | M67: ='Statement Q'!G75 -> -2836 | N67: ='Statement Q'!H75 -> -171 | O67: ='Statement Q'!I75 -> -6772 | P67: ='Statement Q'!J75 -> -2595 | R67: =SUM(M67:P67) -> -12374
B68: Capitalized internal use software | C68: ='Statement Y'!C76 -> -7014 | D68: ='Statement Y'!D76 -> -6829 | E68: ='Statement Y'!E76 -> -563 | F68: ='Statement Y'!F76 -> -3578 | G68: ='Statement Y'!G76 -> -1323 | I68: ='Statement Q'!C76 -> 0 | J68: ='Statement Q'!D76 -> 0 | K68: ='Statement Q'!E76 -> 0 | L68: ='Statement Q'!F76 -> 0 | M68: ='Statement Q'!G76 -> -1312 | N68: ='Statement Q'!H76 -> -3 | O68: ='Statement Q'!I76 -> -7 | P68: ='Statement Q'!J76 -> -1 | R68: =SUM(M68:P68) -> -1323
B69: Investing cashflow | C69: ='Statement Y'!C80 -> -66366 | D69: ='Statement Y'!D80 -> -52384 | E69: ='Statement Y'!E80 -> -118075 | F69: ='Statement Y'!F80 -> -151181 | G69: ='Statement Y'!G80 -> -159779 | I69: ='Statement Q'!C80 -> 0 | J69: ='Statement Q'!D80 -> 0 | K69: ='Statement Q'!E80 -> 0 | L69: ='Statement Q'!F80 -> 0 | M69: ='Statement Q'!G80 -> -36809 | N69: ='Statement Q'!H80 -> -27606 | O69: ='Statement Q'!I80 -> -31624 | P69: ='Statement Q'!J80 -> -63740 | R69: =SUM(M69:P69) -> -159779
B70: Issuance debt | C70: ='Statement Y'!C81 -> 110000 | D70: ='Statement Y'!D81 -> 259854 | E70: ='Statement Y'!E81 -> 800653 | F70: ='Statement Y'!F81 -> 0 | G70: ='Statement Y'!G81 -> 0 | I70: ='Statement Q'!C81 -> 0 | J70: ='Statement Q'!D81 -> 0 | K70: ='Statement Q'!E81 -> 0 | L70: ='Statement Q'!F81 -> 0 | M70: ='Statement Q'!G81 -> 0 | N70: ='Statement Q'!H81 -> 0 | O70: ='Statement Q'!I81 -> 0 | P70: ='Statement Q'!J81 -> 0 | R70: =SUM(M70:P70) -> 0
B71: Repayment debt | C71: ='Statement Y'!C82 -> -122500 | D71: ='Statement Y'!D82 -> -310000 | E71: ='Statement Y'!E82 -> -442563 | F71: ='Statement Y'!F82 -> -25313 | G71: ='Statement Y'!G82 -> -40500 | I71: ='Statement Q'!C82 -> 0 | J71: ='Statement Q'!D82 -> 0 | K71: ='Statement Q'!E82 -> 0 | L71: ='Statement Q'!F82 -> 0 | M71: ='Statement Q'!G82 -> -10125 | N71: ='Statement Q'!H82 -> -10125 | O71: ='Statement Q'!I82 -> -10125 | P71: ='Statement Q'!J82 -> -10125 | R71: =SUM(M71:P71) -> -40500
B72: Financing cashflow | C72: ='Statement Y'!C89 -> -54500 | D72: ='Statement Y'!D89 -> -160170 | E72: ='Statement Y'!E89 -> -234868 | F72: ='Statement Y'!F89 -> -81221 | G72: ='Statement Y'!G89 -> -77081 | I72: ='Statement Q'!C89 -> 0 | J72: ='Statement Q'!D89 -> 0 | K72: ='Statement Q'!E89 -> 0 | L72: ='Statement Q'!F89 -> 0 | M72: ='Statement Q'!G89 -> -51149 | N72: ='Statement Q'!H89 -> -10913 | O72: ='Statement Q'!I89 -> -3873 | P72: ='Statement Q'!J89 -> -11146 | R72: =SUM(M72:P72) -> -77081
B73: Net increase/decrease in cash | C73: ='Statement Y'!C91 -> 107577 | D73: ='Statement Y'!D91 -> -21827 | E73: ='Statement Y'!E91 -> -64709 | F73: ='Statement Y'!F91 -> 209608 | G73: ='Statement Y'!G91 -> 413620 | I73: ='Statement Q'!C91 -> 0 | J73: ='Statement Q'!D91 -> 0 | K73: ='Statement Q'!E91 -> 0 | L73: ='Statement Q'!F91 -> 0 | M73: ='Statement Q'!G91 -> -138973 | N73: ='Statement Q'!H91 -> -36467 | O73: ='Statement Q'!I91 -> 175440 | P73: ='Statement Q'!J91 -> 513473 | R73: =SUM(M73:P73) -> 513473
B74: Begin cash | C74: ='Statement Y'!C92 -> 133020 | D74: ='Statement Y'!D92 -> 240597 | E74: ='Statement Y'!E92 -> 218770 | F74: ='Statement Y'!F92 -> 154061 | G74: ='Statement Y'!G92 -> 363669 | I74: ='Statement Q'!C92 -> 0 | J74: ='Statement Q'!D92 -> 0 | K74: ='Statement Q'!E92 -> 0 | L74: ='Statement Q'!F92 -> 0 | M74: ='Statement Q'!G92 -> 363669 | N74: ='Statement Q'!H92 -> 224696 | O74: ='Statement Q'!I92 -> 188229 | P74: ='Statement Q'!J92 -> 263816 | R74: =M74 -> 363669
B75: End cash | C75: ='Statement Y'!C93 -> 240597 | D75: ='Statement Y'!D93 -> 218770 | E75: ='Statement Y'!E93 -> 154061 | F75: ='Statement Y'!F93 -> 363669 | G75: ='Statement Y'!G93 -> 777289 | I75: ='Statement Q'!C93 -> 0 | J75: ='Statement Q'!D93 -> 0 | K75: ='Statement Q'!E93 -> 0 | L75: ='Statement Q'!F93 -> 0 | M75: ='Statement Q'!G93 -> 224696 | N75: ='Statement Q'!H93 -> 188229 | O75: ='Statement Q'!I93 -> 263816 | P75: ='Statement Q'!J93 -> 777289 | R75: =P75 -> 777289
B77: DuPont Identity
B78: Profit Margin (Earnings/Revenue) | C78: =C18/C5 -> 0.088841839 | D78: =D18/D5 -> 0.06250501 | E78: =E18/E5 -> 0.039278183 | F78: =F18/F5 -> 0.079351356 | G78: =G18/G5 -> 0.10960359 | R78: =R18/R5 -> 0.10960359
B79: Asset Turnover (Revenue/Total assets) | D79: =D5/D36 -> 1.1282212 | E79: =E5/E36 -> 1.2198522 | F79: =F5/F36 -> 1.2581791 | G79: =G5/G36 -> 1.1962365 | R79: =R5/R36 -> 1.1962365
B80: ROA | D80: =D78*D79 -> 0.07051948 | E80: =E78*E79 -> 0.047913578 | F80: =F78*F79 -> 0.099838217 | G80: =G78*G79 -> 0.13111181 | R80: =R78*R79 -> 0.13111181
B81: Equity Multiplier (Total assets/Equity) | D81: =D36/D52 -> 1.8021719 | E81: =E36/E52 -> 2.357892 | F81: =F36/F52 -> 2.2697431 | G81: =G36/G52 -> 1.9988835 | R81: =R36/R52 -> 1.9988835
B82: ROE | D82: =D80*D81 -> 0.12708822 | E82: =E80*E81 -> 0.11297504 | F82: =F80*F81 -> 0.2266071 | G82: =G80*G81 -> 0.26207724 | R82: =R80*R81 -> 0.26207724
B84: Growth rates
B85: Revenue | D85: =(D5-C5)/C5 -> -0.0025833151 | E85: =(E5-D5)/D5 -> 0.14428065 | F85: =(F5-E5)/E5 -> 0.29972165 | G85: =(G5-F5)/F5 -> 0.15746172 | J85: =(J5-I5)/I5 -> 0.17109849 | K85: =(K5-J5)/J5 -> 0.14247937 | L85: =(L5-K5)/K5 -> 0.25278957 | M85: =(M5-L5)/L5 -> -0.31588692 | N85: =(N5-M5)/M5 -> 0.18176926 | O85: =(O5-N5)/N5 -> 0.12829059 | P85: =(P5-O5)/O5 -> 0.28903352
B86: COGS | D86: =(D6-C6)/C6 -> 0.0080225095 | E86: =(E6-D6)/D6 -> 0.016767714 | F86: =(F6-E6)/E6 -> 0.22200406 | G86: =(G6-F6)/F6 -> 0.13815788 | J86: =(J6-I6)/I6 -> 0.20041845 | K86: =(K6-J6)/J6 -> 0.1293691 | L86: =(L6-K6)/K6 -> 0.29547856 | M86: =(M6-L6)/L6 -> -0.34641808 | N86: =(N6-M6)/M6 -> 0.1893683 | O86: =(O6-N6)/N6 -> 0.10324565 | P86: =(P6-O6)/O6 -> 0.3457739
B87: Gross Profit | D87: =IF(C7=0, IF(D7=0,0,IF(D7>0,1,-1)), (D7-C7)/ABS(C7) ) -> -0.019462044 | E87: =IF(D7=0, IF(E7=0,0,IF(E7>0,1,-1)), (E7-D7)/ABS(D7) ) -> 0.35290038 | F87: =IF(E7=0, IF(F7=0,0,IF(F7>0,1,-1)), (F7-E7)/ABS(E7) ) -> 0.39528171 | G87: =IF(F7=0, IF(G7=0,0,IF(G7>0,1,-1)), (G7-F7)/ABS(F7) ) -> 0.17824966 | J87: =IF(I7=0, IF(J7=0,0,IF(J7>0,1,-1)), (J7-I7)/ABS(I7) ) -> 0.14105507 | K87: =IF(J7=0, IF(K7=0,0,IF(K7>0,1,-1)), (K7-J7)/ABS(J7) ) -> 0.15661201 | L87: =IF(K7=0, IF(L7=0,0,IF(L7>0,1,-1)), (L7-K7)/ABS(K7) ) -> 0.20785546 | M87: =IF(L7=0, IF(M7=0,0,IF(M7>0,1,-1)), (M7-L7)/ABS(L7) ) -> -0.28141871 | N87: =IF(M7=0, IF(N7=0,0,IF(N7>0,1,-1)), (N7-M7)/ABS(M7) ) -> 0.17396631 | O87: =IF(N7=0, IF(O7=0,0,IF(O7>0,1,-1)), (O7-N7)/ABS(N7) ) -> 0.15434495 | P87: =IF(O7=0, IF(P7=0,0,IF(P7>0,1,-1)), (P7-O7)/ABS(O7) ) -> 0.23261922
B88: OpEx | D88: =IF(C11=0, IF(D11=0,0,IF(D11>0,1,-1)), (D11-C11)/ABS(C11) ) -> 0.08889949 | E88: =IF(D11=0, IF(E11=0,0,IF(E11>0,1,-1)), (E11-D11)/ABS(D11) ) -> 0.40912915 | F88: =IF(E11=0, IF(F11=0,0,IF(F11>0,1,-1)), (F11-E11)/ABS(E11) ) -> 0.31515661 | G88: =IF(F11=0, IF(G11=0,0,IF(G11>0,1,-1)), (G11-F11)/ABS(F11) ) -> 0.098313584 | J88: =IF(I11=0, IF(J11=0,0,IF(J11>0,1,-1)), (J11-I11)/ABS(I11) ) -> 0.33735925 | K88: =IF(J11=0, IF(K11=0,0,IF(K11>0,1,-1)), (K11-J11)/ABS(J11) ) -> 0.035572956 | L88: =IF(K11=0, IF(L11=0,0,IF(L11>0,1,-1)), (L11-K11)/ABS(K11) ) -> 0.23235 | M88: =IF(L11=0, IF(M11=0,0,IF(M11>0,1,-1)), (M11-L11)/ABS(L11) ) -> -0.27755515 | N88: =IF(M11=0, IF(N11=0,0,IF(N11>0,1,-1)), (N11-M11)/ABS(M11) ) -> 0.17727154 | O88: =IF(N11=0, IF(O11=0,0,IF(O11>0,1,-1)), (O11-N11)/ABS(N11) ) -> 0.027909994 | P88: =IF(O11=0, IF(P11=0,0,IF(P11>0,1,-1)), (P11-O11)/ABS(O11) ) -> 0.19700204
B89: Operating income | D89: =IF(C12=0, IF(D12=0,0,IF(D12>0,1,-1)), (D12-C12)/ABS(C12) ) -> -0.26669968 | E89: =IF(D12=0, IF(E12=0,0,IF(E12>0,1,-1)), (E12-D12)/ABS(D12) ) -> 0.16239646 | F89: =IF(E12=0, IF(F12=0,0,IF(F12>0,1,-1)), (F12-E12)/ABS(E12) ) -> 0.72436852 | G89: =IF(F12=0, IF(G12=0,0,IF(G12>0,1,-1)), (G12-F12)/ABS(F12) ) -> 0.42864838 | J89: =IF(I12=0, IF(J12=0,0,IF(J12>0,1,-1)), (J12-I12)/ABS(I12) ) -> -0.32983955 | K89: =IF(J12=0, IF(K12=0,0,IF(K12>0,1,-1)), (K12-J12)/ABS(J12) ) -> 0.73602604 | L89: =IF(K12=0, IF(L12=0,0,IF(L12>0,1,-1)), (L12-K12)/ABS(K12) ) -> 0.13791037 | M89: =IF(L12=0, IF(M12=0,0,IF(M12>0,1,-1)), (M12-L12)/ABS(L12) ) -> -0.29336687 | N89: =IF(M12=0, IF(N12=0,0,IF(N12>0,1,-1)), (N12-M12)/ABS(M12) ) -> 0.16351607 | O89: =IF(N12=0, IF(O12=0,0,IF(O12>0,1,-1)), (O12-N12)/ABS(N12) ) -> 0.55882405 | P89: =IF(O12=0, IF(P12=0,0,IF(P12>0,1,-1)), (P12-O12)/ABS(O12) ) -> 0.30775493
B90: Income before taxes | D90: =IF(C16=0, IF(D16=0,0,IF(D16>0,1,-1)), (D16-C16)/ABS(C16) ) -> -0.27114398 | E90: =IF(D16=0, IF(E16=0,0,IF(E16>0,1,-1)), (E16-D16)/ABS(D16) ) -> -0.028994914 | F90: =IF(E16=0, IF(F16=0,0,IF(F16>0,1,-1)), (F16-E16)/ABS(E16) ) -> 0.9522931 | G90: =IF(F16=0, IF(G16=0,0,IF(G16>0,1,-1)), (G16-F16)/ABS(F16) ) -> 0.57262864 | J90: =IF(I16=0, IF(J16=0,0,IF(J16>0,1,-1)), (J16-I16)/ABS(I16) ) -> -0.3749059 | K90: =IF(J16=0, IF(K16=0,0,IF(K16>0,1,-1)), (K16-J16)/ABS(J16) ) -> 0.94441409 | L90: =IF(K16=0, IF(L16=0,0,IF(L16>0,1,-1)), (L16-K16)/ABS(K16) ) -> -0.054112641 | M90: =IF(L16=0, IF(M16=0,0,IF(M16>0,1,-1)), (M16-L16)/ABS(L16) ) -> -0.11766632 | N90: =IF(M16=0, IF(N16=0,0,IF(N16>0,1,-1)), (N16-M16)/ABS(M16) ) -> 0.24291398 | O90: =IF(N16=0, IF(O16=0,0,IF(O16>0,1,-1)), (O16-N16)/ABS(N16) ) -> 0.34888465 | P90: =IF(O16=0, IF(P16=0,0,IF(P16>0,1,-1)), (P16-O16)/ABS(O16) ) -> 0.35195272
B91: Net income | D91: =IF(C18=0, IF(D18=0,0,IF(D18>0,1,-1)), (D18-C18)/ABS(C18) ) -> -0.29826373 | E91: =IF(D18=0, IF(E18=0,0,IF(E18>0,1,-1)), (E18-D18)/ABS(D18) ) -> -0.2809334 | F91: =IF(E18=0, IF(F18=0,0,IF(F18>0,1,-1)), (F18-E18)/ABS(E18) ) -> 1.6257496 | G91: =IF(F18=0, IF(G18=0,0,IF(G18>0,1,-1)), (G18-F18)/ABS(F18) ) -> 0.59873719 | J91: =IF(I18=0, IF(J18=0,0,IF(J18>0,1,-1)), (J18-I18)/ABS(I18) ) -> -0.37919206 | K91: =IF(J18=0, IF(K18=0,0,IF(K18>0,1,-1)), (K18-J18)/ABS(J18) ) -> 0.94464202 | L91: =IF(K18=0, IF(L18=0,0,IF(L18>0,1,-1)), (L18-K18)/ABS(K18) ) -> -0.027303161 | M91: =IF(L18=0, IF(M18=0,0,IF(M18>0,1,-1)), (M18-L18)/ABS(L18) ) -> -0.084534945 | N91: =IF(M18=0, IF(N18=0,0,IF(N18>0,1,-1)), (N18-M18)/ABS(M18) ) -> 0.18469046 | O91: =IF(N18=0, IF(O18=0,0,IF(O18>0,1,-1)), (O18-N18)/ABS(N18) ) -> 0.3519463 | P91: =IF(O18=0, IF(P18=0,0,IF(P18>0,1,-1)), (P18-O18)/ABS(O18) ) -> 0.35226701
B92: Diluted Shares outstanding avg | D92: =(D19-C19)/C19 -> 0 | E92: =(E19-D19)/D19 -> 0.0031442694 | F92: =(F19-E19)/E19 -> 0.01193516 | G92: =(G19-F19)/F19 -> 0.0071305038 | J92: =(J19-I19)/I19 -> 0.0015706843 | K92: =(K19-J19)/J19 -> 0.0027106809 | L92: =(L19-K19)/K19 -> 0.0015002902 | M92: =(M19-L19)/L19 -> 0.0046990489 | N92: =(N19-M19)/M19 -> -0.0021943552 | O92: =(O19-N19)/N19 -> 0.0017480669 | P92: =(P19-O19)/O19 -> 7.0363569e-05
B93: Diluted EPS | D93: =IF(C20=0, IF(D20=0,0,IF(D20>0,1,-1)), (D20-C20)/ABS(C20) ) -> -0.29831933 | E93: =IF(D20=0, IF(E20=0,0,IF(E20>0,1,-1)), (E20-D20)/ABS(D20) ) -> -0.28143713 | F93: =IF(E20=0, IF(F20=0,0,IF(F20>0,1,-1)), (F20-E20)/ABS(E20) ) -> 1.5916667 | G93: =IF(F20=0, IF(G20=0,0,IF(G20>0,1,-1)), (G20-F20)/ABS(F20) ) -> 0.58842444 | J93: =IF(I20=0, IF(J20=0,0,IF(J20>0,1,-1)), (J20-I20)/ABS(I20) ) -> -0.38461538 | K93: =IF(J20=0, IF(K20=0,0,IF(K20>0,1,-1)), (K20-J20)/ABS(J20) ) -> 0.95833333 | L93: =IF(K20=0, IF(L20=0,0,IF(L20>0,1,-1)), (L20-K20)/ABS(K20) ) -> -0.031914894 | M93: =IF(L20=0, IF(M20=0,0,IF(M20>0,1,-1)), (M20-L20)/ABS(L20) ) -> -0.087912088 | N93: =IF(M20=0, IF(N20=0,0,IF(N20>0,1,-1)), (N20-M20)/ABS(M20) ) -> 0.18072289 | O93: =IF(N20=0, IF(O20=0,0,IF(O20>0,1,-1)), (O20-N20)/ABS(N20) ) -> 0.35714286 | P93: =IF(O20=0, IF(P20=0,0,IF(P20>0,1,-1)), (P20-O20)/ABS(O20) ) -> 0.35338346
B95: Margins
B96: Gross margin | C96: =C7/C5 -> 0.3858831 | D96: =D7/D5 -> 0.37935302 | E96: =E7/E5 -> 0.44851483 | F96: =F7/F5 -> 0.4814912 | G96: =G7/G5 -> 0.49013875 | I96: =I7/I5 -> 0.49390656 | J96: =J7/J5 -> 0.48123585 | K96: =K7/K5 -> 0.48718882 | L96: =L7/L5 -> 0.4697147 | M96: =M7/M5 -> 0.49338071 | N96: =N7/N5 -> 0.49012303 | O96: =O7/O5 -> 0.50144089 | P96: =P7/P5 -> 0.47949543 | R96: =R7/R5 -> 0.49013875
B97: Operating margin | C97: =C12/C5 -> 0.11758994 | D97: =D12/D5 -> 0.086452074 | E97: =E12/E5 -> 0.087820749 | F97: =F12/F5 -> 0.11651367 | G97: =G12/G5 -> 0.14381215 | I97: =I12/I5 -> 0.14531789 | J97: =J12/J5 -> 0.083158079 | K97: =K12/K5 -> 0.12636079 | L97: =L12/L5 -> 0.11477366 | M97: =M12/M5 -> 0.11855185 | N97: =N12/N5 -> 0.11672074 | O97: =O12/O5 -> 0.16125908 | P97: =P12/P5 -> 0.16360114 | R97: =R12/R5 -> 0.14381215
B98: Net margin | C98: =C18/C5 -> 0.088841839 | D98: =D18/D5 -> 0.06250501 | E98: =E18/E5 -> 0.039278183 | F98: =F18/F5 -> 0.079351356 | G98: =G18/G5 -> 0.10960359 | I98: =I18/I5 -> 0.10280353 | J98: =J18/J5 -> 0.054496908 | K98: =K18/K5 -> 0.092760517 | L98: =L18/L5 -> 0.072021562 | M98: =M18/M5 -> 0.096377669 | N98: =N18/N5 -> 0.096615903 | O98: =O18/O5 -> 0.11576762 | P98: =P18/P5 -> 0.12144659 | R98: =R18/R5 -> 0.10960359
