Workbook

Sheet Overview
B2: Automatic Data | E2: At a glance | H2: Valuation | K2: Links
B3: Company | C3: #VALUE! | E3: Market capitalization | F3: =Statement!AC151 -> 160394.49 | H3: ='AVG target price'!B5 -> DCF price | I3: ='AVG target price'!C5 -> 134.65123 | K3: Financials ->'!B13
B4: Ticker | C4: {=_FV(C3,"Ticker symbol",TRUE)} -> STX | E4: Enterprise value | F4: =Statement!AC152 -> 162255.49 | H4: ='AVG target price'!B6 -> EV/EBIT price | I4: ='AVG target price'!C6 -> 212.51771 | K4: Analysis ->'!B13
B5: Price | C5: {=_FV(C3,"Price",TRUE)} -> 676.77 | E5: EPS | F5: =Statement!AC25 -> 13.88 | H5: ='AVG target price'!B7 -> PS price | I5: ='AVG target price'!C7 -> 146.73746 | K5: Forecast ->'!B13
B6: Price Extended Hours | C6: {=_FV(C3,"Price (Extended hours)",TRUE)} -> #VALUE! | E6: PE | F6: =Statement!AC148 -> 48.758646 | H6: ='AVG target price'!B8 -> EV/FCFF price | I6: ='AVG target price'!C8 -> 227.6838 | K6: Valuation ->'!B13
B7: Day change | C7: {=_FV(C3,"Change")} -> 32.56 | E7: PS | F7: =Statement!AC149 -> 12.69464 | H7: ='AVG target price'!B9 -> EV/Sales | I7: ='AVG target price'!C9 -> 218.83792
B8: Day change extended | C8: {=_FV(C3,"Change (extended hours)",TRUE)} -> #VALUE! | E8: FCF Yield | F8: =Statement!AC159 -> 0.018030545 | H8: ='AVG target price'!B10 -> AVG price | I8: ='AVG target price'!C10 -> 188.08562
B9: Day change % | C9: {=_FV(C3,"Change (%)",TRUE)} -> 0.050543 | E9: Earnings Yield | F9: =Statement!AC160 -> 0.020509183 | H9: ='AVG target price'!B12 -> Upside/Downside | I9: ='AVG target price'!C12 -> -0.72208339
B10: Day change extended % | C10: {=_FV(C3,"Change % (extended hours)",TRUE)} -> #VALUE! | E10: Buyback Yield | F10: =Statement!AC162 -> 0.0010972946
B11: 52 week high | C11: {=_FV(C3,"52 week high",TRUE)} -> 1145 | E11: Dividend Yield | F11: =Statement!AC161 -> 0.0043146121 | H11: DDM price | I11: =DDM!C26 -> 23.779348
B12: 52 week low | C12: {=_FV(C3,"52 week low",TRUE)} -> 217.67 | E12: ROA | F12: =Statement!AC121 -> 0.31929402
B13: Beta | C13: {=_FV(C3,"Beta")} -> 2.1471 | E13: ROE | F13: =Statement!AC123 -> 1.4693124 | H13: Reverse DCF rate | I13: ='Reverse DCF'!C17 -> 0.56
B14: Avg volume | C14: {=_FV(C3,"Volume average",TRUE)} -> 4848790 | E14: ROIC | F14: =Statement!AC138 -> 0.87701106 | H14: Reverse DCF price | I14: ='Reverse DCF'!C16 -> 682.17154
E15: Net Cash/Market Cap | F15: =Statement!AC174 -> -0.011602643
E16: Net Cash/Share | F16: =Statement!AC173 -> -8.1982379 | H16: Discount rates used
B17: Unit data and other info | E17: Insider Ownership | F17: =Statement!AC169 -> 0.0084388186 | H17: WACC | I17: =DCF!C15 -> 0.1443252
B18: Units | C18: M | E18: Net Trade Cycle | F18: =Statement!AC142 -> 36.179013 | H18: Cost of Equity | I18: =Multiples!C54 -> 0.1464795
B19: Units conversion | C19: 1000000 | E19: Net Debt/Equity | F19: =Statement!AC144 -> 0.85879096
B20: Has operating lease | C20: No | E20: Quick Ratio | F20: =Statement!AC145 -> 1.0354973
B21: Has finance lease | C21: No
B22: Has debt | C22: Yes
B25: Constants | E25: 10 Year Bond Yield
B26: Default tax rate | C26: 0.21 | E26: #VALUE! | F26: {=_FV(E26,"Price")} -> 49.86
B27: Cost of debt | C27: 0.06 | E27: Percentage | F27: =F26/1000 -> 0.04986
B28: Manual WACC | C28: 0
B29: Manual Cost of Equity | C29: 0
B33: Info
B35: Mission: | C35: Enable enterprises and end-users to confidently store and unlock value of their data
B36: Auditor: | C36: Erns & young
B37: Business units: | C37: Datacenter represents high capacity nearline products sold to clouds and enterprise customers
C38: Edge & IoT includes consumer and client markets
B39: Competitors: | C39: Kioxia Holdings
C40: Micron
C41: Samsung Electronics
C42: Sandisk
C43: SK Hynix
C44: Western Digital
C45: Toshiba Corporation
B46: Patents: | C46: =3036+226 -> 3262
B52: Notes
B54: Date: | C54: 31.07.2026 | E54: Q4 2026
B55: - | C55: Nearline exabyte supply largely allocated into CY28 and some customers expand planning horizons into CY29 and beyond
B56: - | C56: Q1 operating margin will be about 50%
B57: - | C57: Q1 OpEx will be about 300M
B58: - | C58: Q1 diluted avg shares will be 231M
B60: Date: | C60: 27.04.2026 | E60: Q3 2026
B61: - | C61: Q4 operating margin will be 40%-44%
B62: - | C62: Q4 OpEx will be about 295M
B63: - | C63: Q4 diluted avg shares will be 231M
B68: Adjustments
B70: Date: | C70: 29.11.2024 | E70: FY 2024

Sheet Financials ->
H5: Links
H6: Overview'!B3
H7: Financials ->'!B13
H8: Analysis ->'!B13
H9: Forecast ->'!B13
H10: Valuation ->'!B13
B13: Financials ->

Sheet Statement
B2: Date | L2: 02.07.2021 | M2: 01.07.2022 | N2: 30.06.2023 | O2: 28.06.2024 | P2: 27.06.2025 | Q2: 03.07.2026 | T2: 27.09.2024 | U2: 27.12.2024 | V2: 28.03.2025 | W2: 27.06.2025 | X2: 03.10.2025 | Y2: 02.01.2026 | Z2: 03.04.2026 | AA2: 03.07.2026
B3: FY | L3: 2021 | M3: 2022 | N3: 2023 | O3: 2024 | P3: 2025 | Q3: 2026 | T3: Q1 2025 | U3: Q2 2025 | V3: Q3 2025 | W3: Q4 2025 | X3: Q1 2026 | Y3: Q2 2026 | Z3: Q3 2026 | AA3: Q4 2026 | AC3: TTM/YTD
B4: Income statement
B5: Revenue | L5: 10681 | M5: 11661 | N5: 7384 | O5: 6551 | P5: 9097 | Q5: 12195 | T5: 2168 | U5: 2325 | V5: 2160 | W5: 2444 | X5: 2629 | Y5: 2825 | Z5: 3112 | AA5: 3629 | AC5: =SUM(X5:AA5) -> 12195
B6: COGS | L6: 7764 | M6: 8192 | N6: 6033 | O6: 5015 | P6: 5897 | Q6: 6637 | T6: 1454 | U6: 1513 | V6: 1400 | W6: 1530 | X6: 1592 | Y6: 1649 | Z6: 1665 | AA6: 1731 | AC6: =SUM(X6:AA6) -> 6637
B7: Gross Profit | C7: =C5-C6 -> 0 | D7: =D5-D6 -> 0 | E7: =E5-E6 -> 0 | F7: =F5-F6 -> 0 | G7: =G5-G6 -> 0 | H7: =H5-H6 -> 0 | I7: =I5-I6 -> 0 | J7: =J5-J6 -> 0 | ... Q7: =Q5-Q6 -> 5558 | T7: =T5-T6 -> 714 | U7: =U5-U6 -> 812 | V7: =V5-V6 -> 760 | W7: =W5-W6 -> 914 | X7: =X5-X6 -> 1037 | Y7: =Y5-Y6 -> 1176 | Z7: =Z5-Z6 -> 1447 | AA7: =AA5-AA6 -> 1898 | AC7: =SUM(X7:AA7) -> 5558
B8: R&D | L8: 903 | M8: 941 | N8: 797 | O8: 654 | P8: 724 | Q8: 755 | T8: 181 | U8: 184 | V8: 180 | W8: 179 | X8: 186 | Y8: 187 | Z8: 194 | AA8: 188 | AC8: =SUM(X8:AA8) -> 755
B9: SG&A | L9: 502 | M9: 559 | N9: 491 | O9: 460 | P9: 561 | Q9: 577 | T9: 129 | U9: 139 | V9: 139 | W9: 154 | X9: 144 | Y9: 143 | Z9: 143 | AA9: 147 | AC9: =SUM(X9:AA9) -> 577
B10: Opex | L10: =903+502+20 -> 1425 | M10: =941+559+14 -> 1514 | N10: =797+491+3+300+102 -> 1693 | O10: =654+430 -> 1084 | P10: =724+561+25 -> 1310 | Q10: =755+577+105+27 -> 1464 | T10: =181+130 -> 311 | U10: =184+140 -> 324 | V10: =180+139+10 -> 329 | W10: =179+154+13 -> 346 | X10: =186+144+13 -> 343 | Y10: =187+146 -> 333 | Z10: =194+143+112 -> 449 | AA10: =188+147+4 -> 339 | AC10: =SUM(X10:AA10) -> 1464
B11: Operating income | L11: 1492 | M11: 1955 | N11: -342 | O11: 452 | P11: 1890 | Q11: 4094 | T11: 403 | U11: 488 | V11: 431 | W11: 568 | X11: 694 | Y11: 843 | Z11: 998 | AA11: 1559 | AC11: =SUM(X11:AA11) -> 4094
B12: Interest income/expense | L12: -218 | M12: -247 | N12: -303 | O12: =15-332 -> -317 | P12: =25-321 -> -296 | Q12: -254 | T12: -78 | U12: -76 | V12: -73 | W12: -69 | X12: -73 | Y12: -65 | Z12: -62 | AA12: -54 | AC12: =SUM(X12:AA12) -> -254
B13: Other income/expense | L13: 74 | M13: -29 | N13: =190-41 -> 149 | O13: =417-29-78 -> 310 | P13: -81 | Q13: -150 | T13: -9 | U13: -62 | V13: -3 | W13: -7 | X13: -7 | Y13: -71 | Z13: -72 | AA13: 0 | AC13: =SUM(X13:AA13) -> -150
B14: Income before taxes | L14: 1348 | M14: 1679 | N14: -496 | O14: 445 | P14: 1513 | Q14: 3690 | T14: 316 | U14: 350 | V14: 355 | W14: 492 | X14: 614 | Y14: 707 | Z14: 864 | AA14: 1505 | AC14: =SUM(X14:AA14) -> 3690
B15: Income tax expense/benefit | L15: -34 | M15: -30 | N15: -33 | O15: -110 | P15: -44 | Q15: -506 | T15: -11 | U15: -14 | V15: -15 | W15: -4 | X15: -65 | Y15: -114 | Z15: -116 | AA15: -211 | AC15: =SUM(X15:AA15) -> -506
B16: Non-controlling interest | L16: 0 | M16: 0 | N16: 0 | O16: 0 | P16: 0 | Q16: 0 | T16: 0 | U16: 0 | V16: 0 | W16: 0 | X16: 0 | Y16: 0 | Z16: 0 | AA16: 0 | AC16: =SUM(X16:AA16) -> 0
B17: Net income | L17: 1314 | M17: 1649 | N17: -529 | O17: 335 | P17: 1469 | Q17: 3184 | T17: 305 | U17: 336 | V17: 340 | W17: 488 | X17: 549 | Y17: 593 | Z17: 748 | AA17: 1294 | AC17: =SUM(X17:AA17) -> 3184
B18: Basic Shares outstanding avg | L18: 242 | M18: 220 | N18: 207 | O18: 209 | P18: 212 | Q18: 219 | T18: 211 | U18: 212 | V18: 212 | W18: 212 | X18: 213 | Y18: 216 | Z18: 221 | AA18: 225 | AC18: =AVERAGE(X18:AA18) -> 218.75
B19: Basic Shares outstanding avg adjusted | C19: =C18*C$84 -> 0 | D19: =D18*D$84 -> 0 | E19: =E18*E$84 -> 0 | F19: =F18*F$84 -> 0 | G19: =G18*G$84 -> 0 | H19: =H18*H$84 -> 0 | I19: =I18*I$84 -> 0 | J19: =J18*J$84 -> 0 | ... Q19: =Q18*Q$84 -> 219 | T19: =T18*T$84 -> 211 | U19: =U18*U$84 -> 212 | V19: =V18*V$84 -> 212 | W19: =W18*W$84 -> 212 | X19: =X18*X$84 -> 213 | Y19: =Y18*Y$84 -> 216 | Z19: =Z18*Z$84 -> 221 | AA19: =AA18*AA$84 -> 225 | AC19: =AC18*AC$84 -> 218.75
B20: Diluted Shares outstanding avg | L20: 245 | M20: 224 | N20: 207 | O20: 212 | P20: 217 | Q20: 229 | T20: 216 | U20: 217 | V20: 216 | W20: 218 | X20: 226 | Y20: 228 | Z20: 229 | AA20: 232 | AC20: =AVERAGE(X20:AA20) -> 228.75
B21: Diluted Shares outstanding avg adjusted | C21: =C20*C$84 -> 0 | D21: =D20*D$84 -> 0 | E21: =E20*E$84 -> 0 | F21: =F20*F$84 -> 0 | G21: =G20*G$84 -> 0 | H21: =H20*H$84 -> 0 | I21: =I20*I$84 -> 0 | J21: =J20*J$84 -> 0 | ... Q21: =Q20*Q$84 -> 229 | T21: =T20*T$84 -> 216 | U21: =U20*U$84 -> 217 | V21: =V20*V$84 -> 216 | W21: =W20*W$84 -> 218 | X21: =X20*X$84 -> 226 | Y21: =Y20*Y$84 -> 228 | Z21: =Z20*Z$84 -> 229 | AA21: =AA20*AA$84 -> 232 | AC21: =AC20*AC$84 -> 228.75
B22: Basic EPS | L22: 5.43 | M22: 7.5 | N22: -2.56 | O22: 1.6 | P22: 6.93 | Q22: 14.54 | T22: 1.45 | U22: 1.58 | V22: 1.6 | W22: 2.3 | X22: 2.58 | Y22: 2.75 | Z22: 3.38 | AA22: 5.75 | AC22: =SUM(X22:AA22) -> 14.46
B23: Basic EPS adjusted | L23: =L22/L$84 -> 5.43 | M23: =M22/M$84 -> 7.5 | N23: =N22/N$84 -> -2.56 | O23: =O22/O$84 -> 1.6 | P23: =P22/P$84 -> 6.93 | Q23: =Q22/Q$84 -> 14.54 | T23: =T22/T$84 -> 1.45 | U23: =U22/U$84 -> 1.58 | V23: =V22/V$84 -> 1.6 | W23: =W22/W$84 -> 2.3 | X23: =X22/X$84 -> 2.58 | Y23: =Y22/Y$84 -> 2.75 | Z23: =Z22/Z$84 -> 3.38 | AA23: =AA22/AA$84 -> 5.75 | AC23: =AC22/AC$84 -> 14.46
B24: Diluted EPS | L24: 5.36 | M24: 7.36 | N24: -2.56 | O24: 1.58 | P24: 6.77 | Q24: 13.9 | T24: 1.41 | U24: 1.55 | V24: 1.57 | W24: 2.24 | X24: 2.43 | Y24: 2.6 | Z24: 3.27 | AA24: 5.58 | AC24: =SUM(X24:AA24) -> 13.88
B25: Diluted EPS adjusted | L25: =L24/L$84 -> 5.36 | M25: =M24/M$84 -> 7.36 | N25: =N24/N$84 -> -2.56 | O25: =O24/O$84 -> 1.58 | P25: =P24/P$84 -> 6.77 | Q25: =Q24/Q$84 -> 13.9 | T25: =T24/T$84 -> 1.41 | U25: =U24/U$84 -> 1.55 | V25: =V24/V$84 -> 1.57 | W25: =W24/W$84 -> 2.24 | X25: =X24/X$84 -> 2.43 | Y25: =Y24/Y$84 -> 2.6 | Z25: =Z24/Z$84 -> 3.27 | AA25: =AA24/AA$84 -> 5.58 | AC25: =AC24/AC$84 -> 13.88
B27: Balance sheet
B28: Cash and cash equivalents | L28: 1209 | M28: 615 | N28: 786 | O28: 1358 | P28: 891 | Q28: 1704 | T28: 1239 | U28: 1238 | V28: 814 | W28: 891 | X28: 1112 | Y28: 1046 | Z28: 1146 | AA28: 1704 | AC28: =AA28 -> 1704
B29: Acc receivable | L29: 1158 | M29: 1532 | N29: 621 | O29: 429 | P29: 959 | Q29: 1534 | T29: 628 | U29: 587 | V29: 622 | W29: 959 | X29: 1073 | Y29: 1246 | Z29: 1197 | AA29: 1534 | AC29: =AA29 -> 1534
B30: Inventory | L30: 1204 | M30: 1565 | N30: 1140 | O30: 1239 | P30: 1440 | Q30: 1571 | T30: 1383 | U30: 1473 | V30: 1472 | W30: 1440 | X30: 1496 | Y30: 1498 | Z30: 1530 | AA30: 1571 | AC30: =AA30 -> 1571
B31: Current assets | L31: 3779 | M31: 4033 | N31: 2905 | O31: 3332 | P31: 3653 | Q31: 5221 | T31: 3608 | U31: 3662 | V31: 3282 | W31: 3653 | X31: 4032 | Y31: 4209 | Z31: 4299 | AA31: 5221 | AC31: =AA31 -> 5221
B32: PP&E | L32: 2181 | M32: 2239 | N32: 1706 | O32: 1614 | P32: 1657 | Q32: 2034 | T32: 1599 | U32: 1595 | V32: 1613 | W32: 1657 | X32: 1688 | Y32: 1771 | Z32: 1852 | AA32: 2034 | AC32: =AA32 -> 2034
B33: Marketable securities and investments | L33: 0 | M33: 0 | N33: 0 | O33: 0 | P33: 0 | Q33: 0 | T33: 0 | U33: 0 | V33: 0 | W33: 0 | X33: 0 | Y33: 0 | Z33: 0 | AA33: 0 | AC33: =AA33 -> 0
B34: Goodwill | L34: 1237 | M34: 1237 | N34: 1237 | O34: 1219 | P34: 1221 | Q34: 1221 | T34: 1219 | U34: 1219 | V34: 1219 | W34: 1221 | X34: 1221 | Y34: 1221 | Z34: 1221 | AA34: 1221 | AC34: =AA34 -> 1221
B35: Long term assets | L35: =L36-L31 -> 4896 | M35: =M36-M31 -> 4911 | N35: =N36-N31 -> 4651 | O35: =O36-O31 -> 4407 | P35: =P36-P31 -> 4370 | Q35: =Q36-Q31 -> 4751 | T35: =T36-T31 -> 4364 | U35: =U36-U31 -> 4297 | V35: =V36-V31 -> 4282 | W35: =W36-W31 -> 4370 | X35: =X36-X31 -> 4410 | Y35: =Y36-Y31 -> 4499 | Z35: =Z36-Z31 -> 4593 | AA35: =AA36-AA31 -> 4751 | AC35: =AA35 -> 4751
B36: Total assets | L36: 8675 | M36: 8944 | N36: 7556 | O36: 7739 | P36: 8023 | Q36: 9972 | T36: 7972 | U36: 7959 | V36: 7564 | W36: 8023 | X36: 8442 | Y36: 8708 | Z36: 8892 | AA36: 9972 | AC36: =AA36 -> 9972
B37: Acc payable | L37: 1725 | M37: 2058 | N37: 1603 | O37: 1786 | P37: 1604 | Q37: 1748 | T37: 1778 | U37: 1567 | V37: 1467 | W37: 1604 | X37: 1673 | Y37: 1771 | Z37: 1694 | AA37: 1748 | AC37: =AA37 -> 1748
B38: Debt | L38: 245 | M38: 584 | N38: 63 | O38: 479 | P38: 0 | Q38: 185 | T38: 479 | U38: 479 | V38: 0 | W38: 0 | X38: 1496 | Y38: 998 | Z38: 398 | AA38: 185 | AC38: =AA38 -> 185
B39: Current liabilities | L39: 2921 | M39: 3555 | N39: 2592 | O39: 3099 | P39: 2648 | Q39: 3127 | T39: 3161 | U39: 2969 | V39: 2412 | W39: 2648 | X39: 4117 | Y39: 3761 | Z39: 3241 | AA39: 3127 | AC39: =AA39 -> 3127
B40: Debt | L40: 4894 | M40: 5062 | N40: 5388 | O40: 5195 | P40: 4995 | Q40: 3380 | T40: 5197 | U40: 5200 | V40: 5146 | W40: 4995 | X40: 3498 | Y40: 3501 | Z40: 3465 | AA40: 3380 | AC40: =AA40 -> 3380
B41: Long term liabilities | L41: =L42-L39 -> 5123 | M41: =M42-M39 -> 5280 | N41: =N42-N39 -> 6163 | O41: =O42-O39 -> 6131 | P41: =P42-P39 -> 5828 | Q41: =Q42-Q39 -> 4678 | T41: =T42-T39 -> 6111 | U41: =U42-U39 -> 6069 | V41: =V42-V39 -> 5981 | W41: =W42-W39 -> 5828 | X41: =X42-X39 -> 4388 | Y41: =Y42-Y39 -> 4488 | Z41: =Z42-Z39 -> 4556 | AA41: =AA42-AA39 -> 4678 | AC41: =AA41 -> 4678
B42: Total liabilities | L42: 8044 | M42: 8835 | N42: 8755 | O42: 9230 | P42: 8476 | Q42: 7805 | T42: 9272 | U42: 9038 | V42: 8393 | W42: 8476 | X42: 8505 | Y42: 8249 | Z42: 7797 | AA42: 7805 | AC42: =AA42 -> 7805
B43: Treasury stock | L43: 0 | M43: 0 | N43: 0 | O43: 0 | P43: 0 | Q43: 0 | T43: 0 | U43: 0 | V43: 0 | W43: 0 | X43: 0 | Y43: 0 | Z43: 0 | AA43: 0 | AC43: =AA43 -> 0
B44: Preferred stock | L44: 0 | M44: 0 | N44: 0 | O44: 0 | P44: 0 | Q44: 0 | T44: 0 | U44: 0 | V44: 0 | W44: 0 | X44: 0 | Y44: 0 | Z44: 0 | AA44: 0 | AC44: =AA44 -> 0
B45: Paid in capital | L45: 6977 | M45: 7190 | N45: 7373 | O45: 7471 | P45: 7706 | Q45: 8078 | T45: 7533 | U45: 7577 | V45: 7648 | W45: 7706 | X45: 7780 | Y45: 7890 | Z45: 8021 | AA45: 8078 | AC45: =AA45 -> 8078
B46: Accumulated income/loss | L46: -6305 | M46: -7117 | N46: -8670 | O46: -8960 | P46: -8151 | Q46: -5911 | T46: -8831 | U46: -8654 | V46: -8376 | W46: -8151 | X46: -7835 | Y46: -7423 | Z46: -6918 | AA46: -5911 | AC46: =AA46 -> -5911
B47: Non-controlling interest | L47: 0 | M47: 0 | N47: 0 | O47: 0 | P47: 0 | Q47: 0 | T47: 0 | U47: 0 | V47: 0 | W47: 0 | X47: 0 | Y47: 0 | Z47: 0 | AA47: 0 | AC47: =AA47 -> 0
B48: Stockholder equity | L48: 631 | M48: 109 | N48: -1199 | O48: -1491 | P48: -453 | Q48: 2167 | T48: -1300 | U48: -1079 | V48: -829 | W48: -453 | X48: -63 | Y48: 459 | Z48: 1095 | AA48: 2167 | AC48: =AA48 -> 2167
B49: Total liabilities and equity | L49: 8675 | M49: 8944 | N49: 7556 | O49: 7739 | P49: 8023 | Q49: 9972 | T49: 7972 | U49: 7959 | V49: 7564 | W49: 8023 | X49: 8442 | Y49: 8708 | Z49: 8892 | AA49: 9972 | AC49: =AA49 -> 9972
B51: Cashflow statement
B52: D&A | L52: 397 | M52: 451 | N52: 513 | O52: 264 | P52: 251 | Q52: 276 | T52: 64 | U52: =127-64 -> 63 | V52: =190-64-63 -> 63 | W52: 61 | X52: 72 | Y52: =140-72 -> 68 | Z52: =206-72-68 -> 66 | AA52: 70 | AC52: =SUM(X52:AA52) -> 276
B53: Stock-based compensation | L53: 112 | M53: 145 | N53: 115 | O53: 127 | P53: 200 | Q53: 213 | T53: 38 | U53: =87-38 -> 49 | V53: =141-38-49 -> 54 | W53: 59 | X53: 52 | Y53: =105-52 -> 53 | Z53: =159-52-53 -> 54 | AA53: 54 | AC53: =SUM(X53:AA53) -> 213
B54: Change in accounts receivable | L54: -42 | M54: -374 | N54: 911 | O54: 192 | P54: -513 | Q54: -575 | T54: -199 | U54: =-158+199 -> 41 | V54: -35 | W54: -320 | X54: -114 | Y54: =-287+114 -> -173 | Z54: =-238+114+173 -> 49 | AA54: -337 | AC54: =SUM(X54:AA54) -> -575
B55: Change in inventory | L55: -64 | M55: -361 | N55: 425 | O55: -99 | P55: -201 | Q55: -131 | T55: -144 | U55: =-234+144 -> -90 | V55: =-233+144+90 -> 1 | W55: 32 | X55: -56 | Y55: =-58+56 -> -2 | Z55: =-90+56+2 -> -32 | AA55: -41 | AC55: =SUM(X55:AA55) -> -131
B56: Change in accounts payable | L56: -14 | M56: 228 | N56: -421 | O56: 227 | P56: -242 | Q56: 66 | T56: 10 | U56: -180 | V56: -161 | W56: 89 | X56: 84 | Y56: =162-84 -> 78 | Z56: =89-84-78 -> -73 | AA56: -23 | AC56: =SUM(X56:AA56) -> 66
B57: Change in other operating NWC | L57: =58-38-44 -> -24 | M57: =-30-26-80 -> -136 | N57: =-152+101+298 -> 247 | O57: =6-45-138+243 -> 66 | P57: =207-60-95-61 -> -9 | Q57: =525-44 -> 481 | T57: =37-15+16-37 -> 1 | U57: =85-30-42-71-1 -> -59 | V57: =-102+59 -> -43 | W57: 92 | X57: =-140-15+119-9 -> -45 | Y57: =-108-30+197-87+45 -> 17 | Z57: =-62+346-83+45-17 -> 229 | AA57: 280 | AC57: =SUM(X57:AA57) -> 481
B58: Operating cashflow | L58: 1626 | M58: 1657 | N58: 942 | O58: 918 | P58: 1083 | Q58: 3674 | T58: 95 | U58: =316-95 -> 221 | V58: =575-95-221 -> 259 | W58: 508 | X58: 532 | Y58: =1255-532 -> 723 | Z58: =2369-532-723 -> 1114 | AA58: 1305 | AC58: =SUM(X58:AA58) -> 3674
B59: CapEx | L59: -498 | M59: -381 | N59: -316 | O59: -254 | P59: -265 | Q59: -569 | T59: -68 | U59: =-139+68 -> -71 | V59: =-182+68+71 -> -43 | W59: -83 | X59: -105 | Y59: =-221+105 -> -116 | Z59: =-382+105+116 -> -161 | AA59: -187 | AC59: =SUM(X59:AA59) -> -569
B60: Capitalized software | L60: 0 | M60: 0 | N60: 0 | O60: 0 | P60: 0 | Q60: 0 | T60: 0 | U60: 0 | V60: 0 | W60: 0 | X60: 0 | Y60: 0 | Z60: 0 | AA60: 0 | AC60: =SUM(X60:AA60) -> 0
B61: Investing cashflow | L61: -466 | M61: -352 | N61: 217 | O61: 126 | P61: -276 | Q61: -525 | T61: -68 | U61: =-138+68 -> -70 | V61: =-146+68+70 -> -8 | W61: -130 | X61: -90 | Y61: =-206+90 -> -116 | Z61: =-369+90+116 -> -163 | AA61: -156 | AC61: =SUM(X61:AA61) -> -525
B62: Repurchase stock | L62: -2047 | M62: -1799 | N62: -408 | O62: 0 | P62: 0 | Q62: -176 | T62: 0 | U62: 0 | V62: 0 | W62: 0 | X62: -29 | Y62: 0 | Z62: =-59+29 -> -30 | AA62: -117 | AC62: =SUM(X62:AA62) -> -176
B63: Dividends | L63: -649 | M63: -610 | N63: -582 | O63: -585 | P63: -600 | Q63: -634 | T63: -147 | U63: =-295+147 -> -148 | V63: =-447+147+148 -> -152 | W63: -153 | X63: -153 | Y63: =-307+153 -> -154 | Z63: =-468+153+154 -> -161 | AA63: -166 | AC63: =SUM(X63:AA63) -> -634
B64: Dividends to minority interest | L64: 0 | M64: 0 | N64: 0 | O64: 0 | P64: 0 | Q64: 0 | T64: 0 | U64: 0 | V64: 0 | W64: 0 | X64: 0 | Y64: 0 | Z64: 0 | AA64: 0 | AC64: =SUM(X64:AA64) -> 0
B65: Financing cashflow | L65: -1673 | M65: -1899 | N65: -988 | O65: -473 | P65: -1274 | Q65: -2337 | T65: -146 | U65: =-298+146 -> -152 | V65: =-973+146+152 -> -675 | W65: -301 | X65: -221 | Y65: =-894+221 -> -673 | Z65: =-1746+221+673 -> -852 | AA65: -591 | AC65: =SUM(X65:AA65) -> -2337
B67: Sanity checks
B68: Calculated Net Income | C68: =C5-C6-C10+C12+C13+C15-C16 -> 0 | D68: =D5-D6-D10+D12+D13+D15-D16 -> 0 | E68: =E5-E6-E10+E12+E13+E15-E16 -> 0 | F68: =F5-F6-F10+F12+F13+F15-F16 -> 0 | G68: =G5-G6-G10+G12+G13+G15-G16 -> 0 | H68: =H5-H6-H10+H12+H13+H15-H16 -> 0 | I68: =I5-I6-I10+I12+I13+I15-I16 -> 0 | J68: =J5-J6-J10+J12+J13+J15-J16 -> 0 | ... Q68: =Q5-Q6-Q10+Q12+Q13+Q15-Q16 -> 3184 | T68: =T5-T6-T10+T12+T13+T15-T16 -> 305 | U68: =U5-U6-U10+U12+U13+U15-U16 -> 336 | V68: =V5-V6-V10+V12+V13+V15-V16 -> 340 | W68: =W5-W6-W10+W12+W13+W15-W16 -> 488 | X68: =X5-X6-X10+X12+X13+X15-X16 -> 549 | Y68: =Y5-Y6-Y10+Y12+Y13+Y15-Y16 -> 593 | Z68: =Z5-Z6-Z10+Z12+Z13+Z15-Z16 -> 748 | AA68: =AA5-AA6-AA10+AA12+AA13+AA15-AA16 -> 1294 | AC68: =AC5-AC6-AC10+AC12+AC13+AC15-AC16 -> 3184
B69: Check Net Income | C69: =C17-C68 -> 0 | D69: =D17-D68 -> 0 | E69: =E17-E68 -> 0 | F69: =F17-F68 -> 0 | G69: =G17-G68 -> 0 | H69: =H17-H68 -> 0 | I69: =I17-I68 -> 0 | J69: =J17-J68 -> 0 | ... Q69: =Q17-Q68 -> 0 | T69: =T17-T68 -> 0 | U69: =U17-U68 -> 0 | V69: =V17-V68 -> 0 | W69: =W17-W68 -> 0 | X69: =X17-X68 -> 0 | Y69: =Y17-Y68 -> 0 | Z69: =Z17-Z68 -> 0 | AA69: =AA17-AA68 -> 0 | AC69: =AC17-AC68 -> 0
B70: Check balance | C70: =C36-(C42+C110) -> 0 | D70: =D36-(D42+D110) -> 0 | E70: =E36-(E42+E110) -> 0 | F70: =F36-(F42+F110) -> 0 | G70: =G36-(G42+G110) -> 0 | H70: =H36-(H42+H110) -> 0 | I70: =I36-(I42+I110) -> 0 | J70: =J36-(J42+J110) -> 0 | ... Q70: =Q36-(Q42+Q110) -> 0 | T70: =T36-(T42+T110) -> 0 | U70: =U36-(U42+U110) -> 0 | V70: =V36-(V42+V110) -> 0 | W70: =W36-(W42+W110) -> 0 | X70: =X36-(X42+X110) -> 0 | Y70: =Y36-(Y42+Y110) -> 0 | Z70: =Z36-(Z42+Z110) -> 0 | AA70: =AA36-(AA42+AA110) -> 0 | AC70: =AC36-(AC42+AC110) -> 0
B72: Other data
B73: Shares outstanding | L73: 227 | M73: 209 | N73: 207 | O73: 210 | P73: 213 | Q73: 227 | T73: 212 | U73: 212 | V73: 212 | W73: 213 | X73: 214 | Y73: 218 | Z73: 224 | AA73: 227 | AC73: =AA73 -> 227
B74: Split adjusted shares outstanding | L74: =L73*L84 -> 227 | M74: =M73*M84 -> 209 | N74: =N73*N84 -> 207 | O74: =O73*O84 -> 210 | P74: =P73*P84 -> 213 | Q74: =Q73*Q84 -> 227 | T74: =T73*T84 -> 212 | U74: =U73*U84 -> 212 | V74: =V73*V84 -> 212 | W74: =W73*W84 -> 213 | X74: =X73*X84 -> 214 | Y74: =Y73*Y84 -> 218 | Z74: =Z73*Z84 -> 224 | AA74: =AA73*AA84 -> 227 | AC74: =AA74 -> 227
B75: Dilutive shares | L75: 3 | M75: 4 | N75: 0 | O75: 3 | P75: 5 | Q75: 10 | T75: 5 | U75: 5 | V75: 4 | W75: 5 | X75: 13 | Y75: 12 | Z75: 8 | AA75: 10 | AC75: =AA75 -> 10
B76: Split adjusted dilutive shares | L76: =L75*L84 -> 3 | M76: =M75*M84 -> 4 | N76: =N75*N84 -> 0 | O76: =O75*O84 -> 3 | P76: =P75*P84 -> 5 | Q76: =Q75*Q84 -> 10 | T76: =T75*T84 -> 5 | U76: =U75*U84 -> 5 | V76: =V75*V84 -> 4 | W76: =W75*W84 -> 5 | X76: =X75*X84 -> 13 | Y76: =Y75*Y84 -> 12 | Z76: =Z75*Z84 -> 8 | AA76: =AA75*AA84 -> 10 | AC76: =AA76 -> 10
B77: Split adjusted diluted shares | L77: =L74+L76 -> 230 | M77: =M74+M76 -> 213 | N77: =N74+N76 -> 207 | O77: =O74+O76 -> 213 | P77: =P74+P76 -> 218 | Q77: =Q74+Q76 -> 237 | T77: =T74+T76 -> 217 | U77: =U74+U76 -> 217 | V77: =V74+V76 -> 216 | W77: =W74+W76 -> 218 | X77: =X74+X76 -> 227 | Y77: =Y74+Y76 -> 230 | Z77: =Z74+Z76 -> 232 | AA77: =AA74+AA76 -> 237 | AC77: =AA77 -> 237
B78: Shares held by insiders | L78: 2 | M78: 2 | N78: 2 | O78: 2 | P78: 2 | Q78: 2 | AC78: =Q78 -> 2
B79: Split adjusted shares held by insiders | L79: =L78*L84 -> 2 | M79: =M78*M84 -> 2 | N79: =N78*N84 -> 2 | O79: =O78*O84 -> 2 | P79: =P78*P84 -> 2 | Q79: =Q78*Q84 -> 2 | AC79: =Q79 -> 2
B80: Dividends per share | L80: 2.66 | M80: 2.77 | N80: 2.8 | O80: 2.8 | P80: 2.86 | Q80: 2.92 | T80: 0.7 | U80: 0.72 | V80: 0.72 | W80: 0.72 | X80: 0.72 | Y80: 0.72 | Z80: 0.74 | AA80: 0.74 | AC80: =SUM(X80:AA80) -> 2.92
B81: Split adjusted dividends per share | L81: =L80/L84 -> 2.66 | M81: =M80/M84 -> 2.77 | N81: =N80/N84 -> 2.8 | O81: =O80/O84 -> 2.8 | P81: =P80/P84 -> 2.86 | Q81: =Q80/Q84 -> 2.92 | T81: =T80/T84 -> 0.7 | U81: =U80/U84 -> 0.72 | V81: =V80/V84 -> 0.72 | W81: =W80/W84 -> 0.72 | X81: =X80/X84 -> 0.72 | Y81: =Y80/Y84 -> 0.72 | Z81: =Z80/Z84 -> 0.74 | AA81: =AA80/AA84 -> 0.74 | AC81: =SUM(X81:AA81) -> 2.92
B82: Tax rate | C82: =IF(AND(C14>0,C15<0),-(C15)/C14,0) -> 0 | D82: =IF(AND(D14>0,D15<0),-(D15)/D14,0) -> 0 | E82: =IF(AND(E14>0,E15<0),-(E15)/E14,0) -> 0 | F82: =IF(AND(F14>0,F15<0),-(F15)/F14,0) -> 0 | G82: =IF(AND(G14>0,G15<0),-(G15)/G14,0) -> 0 | H82: =IF(AND(H14>0,H15<0),-(H15)/H14,0) -> 0 | I82: =IF(AND(I14>0,I15<0),-(I15)/I14,0) -> 0 | J82: =IF(AND(J14>0,J15<0),-(J15)/J14,0) -> 0 | ... Q82: =IF(AND(Q14>0,Q15<0),-(Q15)/Q14,0) -> 0.13712737 | T82: =IF(AND(T14>0,T15<0),-(T15)/T14,0) -> 0.034810127 | U82: =IF(AND(U14>0,U15<0),-(U15)/U14,0) -> 0.04 | V82: =IF(AND(V14>0,V15<0),-(V15)/V14,0) -> 0.042253521 | W82: =IF(AND(W14>0,W15<0),-(W15)/W14,0) -> 0.0081300813 | X82: =IF(AND(X14>0,X15<0),-(X15)/X14,0) -> 0.10586319 | Y82: =IF(AND(Y14>0,Y15<0),-(Y15)/Y14,0) -> 0.1612447 | Z82: =IF(AND(Z14>0,Z15<0),-(Z15)/Z14,0) -> 0.13425926 | AA82: =IF(AND(AA14>0,AA15<0),-(AA15)/AA14,0) -> 0.14019934 | AC82: =IF(AND(AC14>0,AC15<0),-(AC15)/AC14,0) -> 0.13712737
B83: Employees | L83: 40000 | M83: 40000 | N83: 33400 | O83: 30000 | P83: 30000 | Q83: 30000 | AC83: =Q83 -> 30000
B84: Stock split factor | L84: 1 | M84: 1 | N84: 1 | O84: 1 | P84: 1 | Q84: 1 | T84: 1 | U84: 1 | V84: 1 | W84: 1 | X84: 1 | Y84: 1 | Z84: 1 | AA84: 1 | AC84: 1
B87: Growth rates Income Statement
B88: Revenue | L88: =IF(K5=0, IF(L5=0,0,IF(L5>0,1,-1)), (L5-K5)/ABS(K5) ) -> 1 | M88: =IF(L5=0, IF(M5=0,0,IF(M5>0,1,-1)), (M5-L5)/ABS(L5) ) -> 0.091751709 | N88: =IF(M5=0, IF(N5=0,0,IF(N5>0,1,-1)), (N5-M5)/ABS(M5) ) -> -0.36677815 | O88: =IF(N5=0, IF(O5=0,0,IF(O5>0,1,-1)), (O5-N5)/ABS(N5) ) -> -0.11281148 | P88: =IF(O5=0, IF(P5=0,0,IF(P5>0,1,-1)), (P5-O5)/ABS(O5) ) -> 0.38864296 | Q88: =IF(P5=0, IF(Q5=0,0,IF(Q5>0,1,-1)), (Q5-P5)/ABS(P5) ) -> 0.34055183 | T88: =IF(S5=0, IF(T5=0,0,IF(T5>0,1,-1)), (T5-S5)/ABS(S5) ) -> 1 | U88: =IF(T5=0, IF(U5=0,0,IF(U5>0,1,-1)), (U5-T5)/ABS(T5) ) -> 0.072416974 | V88: =IF(U5=0, IF(V5=0,0,IF(V5>0,1,-1)), (V5-U5)/ABS(U5) ) -> -0.070967742 | W88: =IF(V5=0, IF(W5=0,0,IF(W5>0,1,-1)), (W5-V5)/ABS(V5) ) -> 0.13148148 | X88: =IF(W5=0, IF(X5=0,0,IF(X5>0,1,-1)), (X5-W5)/ABS(W5) ) -> 0.075695581 | Y88: =IF(X5=0, IF(Y5=0,0,IF(Y5>0,1,-1)), (Y5-X5)/ABS(X5) ) -> 0.074553062 | Z88: =IF(Y5=0, IF(Z5=0,0,IF(Z5>0,1,-1)), (Z5-Y5)/ABS(Y5) ) -> 0.10159292 | AA88: =IF(Z5=0, IF(AA5=0,0,IF(AA5>0,1,-1)), (AA5-Z5)/ABS(Z5) ) -> 0.16613111
B89: COGS | L89: =IF(K6=0, IF(L6=0,0,IF(L6>0,1,-1)), (L6-K6)/ABS(K6) ) -> 1 | M89: =IF(L6=0, IF(M6=0,0,IF(M6>0,1,-1)), (M6-L6)/ABS(L6) ) -> 0.055126224 | N89: =IF(M6=0, IF(N6=0,0,IF(N6>0,1,-1)), (N6-M6)/ABS(M6) ) -> -0.2635498 | O89: =IF(N6=0, IF(O6=0,0,IF(O6>0,1,-1)), (O6-N6)/ABS(N6) ) -> -0.1687386 | P89: =IF(O6=0, IF(P6=0,0,IF(P6>0,1,-1)), (P6-O6)/ABS(O6) ) -> 0.17587238 | Q89: =IF(P6=0, IF(Q6=0,0,IF(Q6>0,1,-1)), (Q6-P6)/ABS(P6) ) -> 0.12548754 | T89: =IF(S6=0, IF(T6=0,0,IF(T6>0,1,-1)), (T6-S6)/ABS(S6) ) -> 1 | U89: =IF(T6=0, IF(U6=0,0,IF(U6>0,1,-1)), (U6-T6)/ABS(T6) ) -> 0.040577717 | V89: =IF(U6=0, IF(V6=0,0,IF(V6>0,1,-1)), (V6-U6)/ABS(U6) ) -> -0.074686054 | W89: =IF(V6=0, IF(W6=0,0,IF(W6>0,1,-1)), (W6-V6)/ABS(V6) ) -> 0.092857143 | X89: =IF(W6=0, IF(X6=0,0,IF(X6>0,1,-1)), (X6-W6)/ABS(W6) ) -> 0.040522876 | Y89: =IF(X6=0, IF(Y6=0,0,IF(Y6>0,1,-1)), (Y6-X6)/ABS(X6) ) -> 0.03580402 | Z89: =IF(Y6=0, IF(Z6=0,0,IF(Z6>0,1,-1)), (Z6-Y6)/ABS(Y6) ) -> 0.0097028502 | AA89: =IF(Z6=0, IF(AA6=0,0,IF(AA6>0,1,-1)), (AA6-Z6)/ABS(Z6) ) -> 0.03963964
B90: Gross Profit | L90: =IF(K7=0, IF(L7=0,0,IF(L7>0,1,-1)), (L7-K7)/ABS(K7) ) -> 1 | M90: =IF(L7=0, IF(M7=0,0,IF(M7>0,1,-1)), (M7-L7)/ABS(L7) ) -> 0.18923552 | N90: =IF(M7=0, IF(N7=0,0,IF(N7>0,1,-1)), (N7-M7)/ABS(M7) ) -> -0.61055059 | O90: =IF(N7=0, IF(O7=0,0,IF(O7>0,1,-1)), (O7-N7)/ABS(N7) ) -> 0.1369356 | P90: =IF(O7=0, IF(P7=0,0,IF(P7>0,1,-1)), (P7-O7)/ABS(O7) ) -> 1.0833333 | Q90: =IF(P7=0, IF(Q7=0,0,IF(Q7>0,1,-1)), (Q7-P7)/ABS(P7) ) -> 0.736875 | T90: =IF(S7=0, IF(T7=0,0,IF(T7>0,1,-1)), (T7-S7)/ABS(S7) ) -> 1 | U90: =IF(T7=0, IF(U7=0,0,IF(U7>0,1,-1)), (U7-T7)/ABS(T7) ) -> 0.1372549 | V90: =IF(U7=0, IF(V7=0,0,IF(V7>0,1,-1)), (V7-U7)/ABS(U7) ) -> -0.064039409 | W90: =IF(V7=0, IF(W7=0,0,IF(W7>0,1,-1)), (W7-V7)/ABS(V7) ) -> 0.20263158 | X90: =IF(W7=0, IF(X7=0,0,IF(X7>0,1,-1)), (X7-W7)/ABS(W7) ) -> 0.1345733 | Y90: =IF(X7=0, IF(Y7=0,0,IF(Y7>0,1,-1)), (Y7-X7)/ABS(X7) ) -> 0.1340405 | Z90: =IF(Y7=0, IF(Z7=0,0,IF(Z7>0,1,-1)), (Z7-Y7)/ABS(Y7) ) -> 0.23044218 | AA90: =IF(Z7=0, IF(AA7=0,0,IF(AA7>0,1,-1)), (AA7-Z7)/ABS(Z7) ) -> 0.31167934
B91: Sales and marketing | L91: =IF(K8=0, IF(L8=0,0,IF(L8>0,1,-1)), (L8-K8)/ABS(K8) ) -> 1 | M91: =IF(L8=0, IF(M8=0,0,IF(M8>0,1,-1)), (M8-L8)/ABS(L8) ) -> 0.042081949 | N91: =IF(M8=0, IF(N8=0,0,IF(N8>0,1,-1)), (N8-M8)/ABS(M8) ) -> -0.15302869 | O91: =IF(N8=0, IF(O8=0,0,IF(O8>0,1,-1)), (O8-N8)/ABS(N8) ) -> -0.17942284 | P91: =IF(O8=0, IF(P8=0,0,IF(P8>0,1,-1)), (P8-O8)/ABS(O8) ) -> 0.10703364 | Q91: =IF(P8=0, IF(Q8=0,0,IF(Q8>0,1,-1)), (Q8-P8)/ABS(P8) ) -> 0.04281768 | T91: =IF(S8=0, IF(T8=0,0,IF(T8>0,1,-1)), (T8-S8)/ABS(S8) ) -> 1 | U91: =IF(T8=0, IF(U8=0,0,IF(U8>0,1,-1)), (U8-T8)/ABS(T8) ) -> 0.016574586 | V91: =IF(U8=0, IF(V8=0,0,IF(V8>0,1,-1)), (V8-U8)/ABS(U8) ) -> -0.02173913 | W91: =IF(V8=0, IF(W8=0,0,IF(W8>0,1,-1)), (W8-V8)/ABS(V8) ) -> -0.0055555556 | X91: =IF(W8=0, IF(X8=0,0,IF(X8>0,1,-1)), (X8-W8)/ABS(W8) ) -> 0.039106145 | Y91: =IF(X8=0, IF(Y8=0,0,IF(Y8>0,1,-1)), (Y8-X8)/ABS(X8) ) -> 0.0053763441 | Z91: =IF(Y8=0, IF(Z8=0,0,IF(Z8>0,1,-1)), (Z8-Y8)/ABS(Y8) ) -> 0.037433155 | AA91: =IF(Z8=0, IF(AA8=0,0,IF(AA8>0,1,-1)), (AA8-Z8)/ABS(Z8) ) -> -0.030927835
B92: R&D | L92: =IF(K9=0, IF(L9=0,0,IF(L9>0,1,-1)), (L9-K9)/ABS(K9) ) -> 1 | M92: =IF(L9=0, IF(M9=0,0,IF(M9>0,1,-1)), (M9-L9)/ABS(L9) ) -> 0.11354582 | N92: =IF(M9=0, IF(N9=0,0,IF(N9>0,1,-1)), (N9-M9)/ABS(M9) ) -> -0.1216458 | O92: =IF(N9=0, IF(O9=0,0,IF(O9>0,1,-1)), (O9-N9)/ABS(N9) ) -> -0.063136456 | P92: =IF(O9=0, IF(P9=0,0,IF(P9>0,1,-1)), (P9-O9)/ABS(O9) ) -> 0.21956522 | Q92: =IF(P9=0, IF(Q9=0,0,IF(Q9>0,1,-1)), (Q9-P9)/ABS(P9) ) -> 0.028520499 | T92: =IF(S9=0, IF(T9=0,0,IF(T9>0,1,-1)), (T9-S9)/ABS(S9) ) -> 1 | U92: =IF(T9=0, IF(U9=0,0,IF(U9>0,1,-1)), (U9-T9)/ABS(T9) ) -> 0.07751938 | V92: =IF(U9=0, IF(V9=0,0,IF(V9>0,1,-1)), (V9-U9)/ABS(U9) ) -> 0 | W92: =IF(V9=0, IF(W9=0,0,IF(W9>0,1,-1)), (W9-V9)/ABS(V9) ) -> 0.10791367 | X92: =IF(W9=0, IF(X9=0,0,IF(X9>0,1,-1)), (X9-W9)/ABS(W9) ) -> -0.064935065 | Y92: =IF(X9=0, IF(Y9=0,0,IF(Y9>0,1,-1)), (Y9-X9)/ABS(X9) ) -> -0.0069444444 | Z92: =IF(Y9=0, IF(Z9=0,0,IF(Z9>0,1,-1)), (Z9-Y9)/ABS(Y9) ) -> 0 | AA92: =IF(Z9=0, IF(AA9=0,0,IF(AA9>0,1,-1)), (AA9-Z9)/ABS(Z9) ) -> 0.027972028
B93: OpEx | L93: =IF(K10=0, IF(L10=0,0,IF(L10>0,1,-1)), (L10-K10)/ABS(K10) ) -> 1 | M93: =IF(L10=0, IF(M10=0,0,IF(M10>0,1,-1)), (M10-L10)/ABS(L10) ) -> 0.06245614 | N93: =IF(M10=0, IF(N10=0,0,IF(N10>0,1,-1)), (N10-M10)/ABS(M10) ) -> 0.11822985 | O93: =IF(N10=0, IF(O10=0,0,IF(O10>0,1,-1)), (O10-N10)/ABS(N10) ) -> -0.35971648 | P93: =IF(O10=0, IF(P10=0,0,IF(P10>0,1,-1)), (P10-O10)/ABS(O10) ) -> 0.20848708 | Q93: =IF(P10=0, IF(Q10=0,0,IF(Q10>0,1,-1)), (Q10-P10)/ABS(P10) ) -> 0.11755725 | T93: =IF(S10=0, IF(T10=0,0,IF(T10>0,1,-1)), (T10-S10)/ABS(S10) ) -> 1 | U93: =IF(T10=0, IF(U10=0,0,IF(U10>0,1,-1)), (U10-T10)/ABS(T10) ) -> 0.041800643 | V93: =IF(U10=0, IF(V10=0,0,IF(V10>0,1,-1)), (V10-U10)/ABS(U10) ) -> 0.015432099 | W93: =IF(V10=0, IF(W10=0,0,IF(W10>0,1,-1)), (W10-V10)/ABS(V10) ) -> 0.051671733 | X93: =IF(W10=0, IF(X10=0,0,IF(X10>0,1,-1)), (X10-W10)/ABS(W10) ) -> -0.0086705202 | Y93: =IF(X10=0, IF(Y10=0,0,IF(Y10>0,1,-1)), (Y10-X10)/ABS(X10) ) -> -0.029154519 | Z93: =IF(Y10=0, IF(Z10=0,0,IF(Z10>0,1,-1)), (Z10-Y10)/ABS(Y10) ) -> 0.34834835 | AA93: =IF(Z10=0, IF(AA10=0,0,IF(AA10>0,1,-1)), (AA10-Z10)/ABS(Z10) ) -> -0.24498886
B94: Operating income | L94: =IF(K11=0, IF(L11=0,0,IF(L11>0,1,-1)), (L11-K11)/ABS(K11) ) -> 1 | M94: =IF(L11=0, IF(M11=0,0,IF(M11>0,1,-1)), (M11-L11)/ABS(L11) ) -> 0.31032172 | N94: =IF(M11=0, IF(N11=0,0,IF(N11>0,1,-1)), (N11-M11)/ABS(M11) ) -> -1.1749361 | O94: =IF(N11=0, IF(O11=0,0,IF(O11>0,1,-1)), (O11-N11)/ABS(N11) ) -> 2.3216374 | P94: =IF(O11=0, IF(P11=0,0,IF(P11>0,1,-1)), (P11-O11)/ABS(O11) ) -> 3.1814159 | Q94: =IF(P11=0, IF(Q11=0,0,IF(Q11>0,1,-1)), (Q11-P11)/ABS(P11) ) -> 1.1661376 | T94: =IF(S11=0, IF(T11=0,0,IF(T11>0,1,-1)), (T11-S11)/ABS(S11) ) -> 1 | U94: =IF(T11=0, IF(U11=0,0,IF(U11>0,1,-1)), (U11-T11)/ABS(T11) ) -> 0.21091811 | V94: =IF(U11=0, IF(V11=0,0,IF(V11>0,1,-1)), (V11-U11)/ABS(U11) ) -> -0.11680328 | W94: =IF(V11=0, IF(W11=0,0,IF(W11>0,1,-1)), (W11-V11)/ABS(V11) ) -> 0.31786543 | X94: =IF(W11=0, IF(X11=0,0,IF(X11>0,1,-1)), (X11-W11)/ABS(W11) ) -> 0.22183099 | Y94: =IF(X11=0, IF(Y11=0,0,IF(Y11>0,1,-1)), (Y11-X11)/ABS(X11) ) -> 0.21469741 | Z94: =IF(Y11=0, IF(Z11=0,0,IF(Z11>0,1,-1)), (Z11-Y11)/ABS(Y11) ) -> 0.18386714 | AA94: =IF(Z11=0, IF(AA11=0,0,IF(AA11>0,1,-1)), (AA11-Z11)/ABS(Z11) ) -> 0.56212425
B95: Income before taxes | L95: =IF(K14=0, IF(L14=0,0,IF(L14>0,1,-1)), (L14-K14)/ABS(K14) ) -> 1 | M95: =IF(L14=0, IF(M14=0,0,IF(M14>0,1,-1)), (M14-L14)/ABS(L14) ) -> 0.24554896 | N95: =IF(M14=0, IF(N14=0,0,IF(N14>0,1,-1)), (N14-M14)/ABS(M14) ) -> -1.2954139 | O95: =IF(N14=0, IF(O14=0,0,IF(O14>0,1,-1)), (O14-N14)/ABS(N14) ) -> 1.8971774 | P95: =IF(O14=0, IF(P14=0,0,IF(P14>0,1,-1)), (P14-O14)/ABS(O14) ) -> 2.4 | Q95: =IF(P14=0, IF(Q14=0,0,IF(Q14>0,1,-1)), (Q14-P14)/ABS(P14) ) -> 1.4388632 | T95: =IF(S14=0, IF(T14=0,0,IF(T14>0,1,-1)), (T14-S14)/ABS(S14) ) -> 1 | U95: =IF(T14=0, IF(U14=0,0,IF(U14>0,1,-1)), (U14-T14)/ABS(T14) ) -> 0.10759494 | V95: =IF(U14=0, IF(V14=0,0,IF(V14>0,1,-1)), (V14-U14)/ABS(U14) ) -> 0.014285714 | W95: =IF(V14=0, IF(W14=0,0,IF(W14>0,1,-1)), (W14-V14)/ABS(V14) ) -> 0.38591549 | X95: =IF(W14=0, IF(X14=0,0,IF(X14>0,1,-1)), (X14-W14)/ABS(W14) ) -> 0.24796748 | Y95: =IF(X14=0, IF(Y14=0,0,IF(Y14>0,1,-1)), (Y14-X14)/ABS(X14) ) -> 0.1514658 | Z95: =IF(Y14=0, IF(Z14=0,0,IF(Z14>0,1,-1)), (Z14-Y14)/ABS(Y14) ) -> 0.22206506 | AA95: =IF(Z14=0, IF(AA14=0,0,IF(AA14>0,1,-1)), (AA14-Z14)/ABS(Z14) ) -> 0.74189815
B96: Net income | L96: =IF(K17=0, IF(L17=0,0,IF(L17>0,1,-1)), (L17-K17)/ABS(K17) ) -> 1 | M96: =IF(L17=0, IF(M17=0,0,IF(M17>0,1,-1)), (M17-L17)/ABS(L17) ) -> 0.25494673 | N96: =IF(M17=0, IF(N17=0,0,IF(N17>0,1,-1)), (N17-M17)/ABS(M17) ) -> -1.3208005 | O96: =IF(N17=0, IF(O17=0,0,IF(O17>0,1,-1)), (O17-N17)/ABS(N17) ) -> 1.6332703 | P96: =IF(O17=0, IF(P17=0,0,IF(P17>0,1,-1)), (P17-O17)/ABS(O17) ) -> 3.3850746 | Q96: =IF(P17=0, IF(Q17=0,0,IF(Q17>0,1,-1)), (Q17-P17)/ABS(P17) ) -> 1.1674609 | T96: =IF(S17=0, IF(T17=0,0,IF(T17>0,1,-1)), (T17-S17)/ABS(S17) ) -> 1 | U96: =IF(T17=0, IF(U17=0,0,IF(U17>0,1,-1)), (U17-T17)/ABS(T17) ) -> 0.10163934 | V96: =IF(U17=0, IF(V17=0,0,IF(V17>0,1,-1)), (V17-U17)/ABS(U17) ) -> 0.011904762 | W96: =IF(V17=0, IF(W17=0,0,IF(W17>0,1,-1)), (W17-V17)/ABS(V17) ) -> 0.43529412 | X96: =IF(W17=0, IF(X17=0,0,IF(X17>0,1,-1)), (X17-W17)/ABS(W17) ) -> 0.125 | Y96: =IF(X17=0, IF(Y17=0,0,IF(Y17>0,1,-1)), (Y17-X17)/ABS(X17) ) -> 0.080145719 | Z96: =IF(Y17=0, IF(Z17=0,0,IF(Z17>0,1,-1)), (Z17-Y17)/ABS(Y17) ) -> 0.2613828 | AA96: =IF(Z17=0, IF(AA17=0,0,IF(AA17>0,1,-1)), (AA17-Z17)/ABS(Z17) ) -> 0.72994652
B98: Margins
B99: Gross margin | L99: =L7/L5 -> 0.27310177 | M99: =M7/M5 -> 0.29748735 | N99: =N7/N5 -> 0.18296316 | O99: =O7/O5 -> 0.23446802 | P99: =P7/P5 -> 0.35176432 | Q99: =Q7/Q5 -> 0.45576056 | T99: =T7/T5 -> 0.32933579 | U99: =U7/U5 -> 0.34924731 | V99: =V7/V5 -> 0.35185185 | W99: =W7/W5 -> 0.37397709 | X99: =X7/X5 -> 0.39444656 | Y99: =Y7/Y5 -> 0.41628319 | Z99: =Z7/Z5 -> 0.46497429 | AA99: =AA7/AA5 -> 0.52300909 | AC99: =AC7/AC5 -> 0.45576056
B100: Operating margin | L100: =L11/L5 -> 0.1396873 | M100: =M11/M5 -> 0.16765286 | N100: =N11/N5 -> -0.04631636 | O100: =O11/O5 -> 0.0689971 | P100: =P11/P5 -> 0.2077608 | Q100: =Q11/Q5 -> 0.33571136 | T100: =T11/T5 -> 0.18588561 | U100: =U11/U5 -> 0.20989247 | V100: =V11/V5 -> 0.19953704 | W100: =W11/W5 -> 0.23240589 | X100: =X11/X5 -> 0.2639787 | Y100: =Y11/Y5 -> 0.29840708 | Z100: =Z11/Z5 -> 0.32069409 | AA100: =AA11/AA5 -> 0.42959493 | AC100: =AC11/AC5 -> 0.33571136
B101: Net margin | L101: =L109/L5 -> 0.12302219 | M101: =M109/M5 -> 0.14141154 | N101: =N109/N5 -> -0.071641387 | O101: =O109/O5 -> 0.051137231 | P101: =P109/P5 -> 0.16148181 | Q101: =Q109/Q5 -> 0.26109061 | T101: =T109/T5 -> 0.14068266 | U101: =U109/U5 -> 0.14451613 | V101: =V109/V5 -> 0.15740741 | W101: =W109/W5 -> 0.19967267 | X101: =X109/X5 -> 0.20882465 | Y101: =Y109/Y5 -> 0.2099115 | Z101: =Z109/Z5 -> 0.2403599 | AA101: =AA109/AA5 -> 0.35657206 | AC101: =AC109/AC5 -> 0.26109061
B103: Adjustments
B104: Tax rate | C104: =IF(AND(C82>=0,C11>=0),C82,0) -> 0 | D104: =IF(AND(D82>=0,D11>=0),D82,0) -> 0 | E104: =IF(AND(E82>=0,E11>=0),E82,0) -> 0 | F104: =IF(AND(F82>=0,F11>=0),F82,0) -> 0 | G104: =IF(AND(G82>=0,G11>=0),G82,0) -> 0 | H104: =IF(AND(H82>=0,H11>=0),H82,0) -> 0 | I104: =IF(AND(I82>=0,I11>=0),I82,0) -> 0 | J104: =IF(AND(J82>=0,J11>=0),J82,0) -> 0 | ... Q104: =IF(AND(Q82>=0,Q11>=0),Q82,0) -> 0.13712737 | T104: =IF(AND(T82>=0,T11>=0),T82,0) -> 0.034810127 | U104: =IF(AND(U82>=0,U11>=0),U82,0) -> 0.04 | V104: =IF(AND(V82>=0,V11>=0),V82,0) -> 0.042253521 | W104: =IF(AND(W82>=0,W11>=0),W82,0) -> 0.0081300813 | X104: =IF(AND(X82>=0,X11>=0),X82,0) -> 0.10586319 | Y104: =IF(AND(Y82>=0,Y11>=0),Y82,0) -> 0.1612447 | Z104: =IF(AND(Z82>=0,Z11>=0),Z82,0) -> 0.13425926 | AA104: =IF(AND(AA82>=0,AA11>=0),AA82,0) -> 0.14019934 | AC104: =IF(AND(AC82>=0,AC11>=0),AC82,0) -> 0.13712737
B105: Cash | L105: =L28+L33 -> 1209 | M105: =M28+M33 -> 615 | N105: =N28+N33 -> 786 | O105: =O28+O33 -> 1358 | P105: =P28+P33 -> 891 | Q105: =Q28+Q33 -> 1704 | T105: =T28+T33 -> 1239 | U105: =U28+U33 -> 1238 | V105: =V28+V33 -> 814 | W105: =W28+W33 -> 891 | X105: =X28+X33 -> 1112 | Y105: =Y28+Y33 -> 1046 | Z105: =Z28+Z33 -> 1146 | AA105: =AA28+AA33 -> 1704 | AC105: =AA105 -> 1704
B106: Debt | C106: 0 | D106: 0 | E106: 0 | F106: 0 | G106: 0 | H106: 0 | I106: 0 | J106: 0 | K106: 0 | L106: =L38+L40 -> 5139 | M106: =M38+M40 -> 5646 | N106: =N38+N40 -> 5451 | O106: =O38+O40 -> 5674 | P106: =P38+P40 -> 4995 | Q106: =Q38+Q40 -> 3565 | T106: =T38+T40 -> 5676 | U106: =U38+U40 -> 5679 | V106: =V38+V40 -> 5146 | W106: =W38+W40 -> 4995 | X106: =X38+X40 -> 4994 | Y106: =Y38+Y40 -> 4499 | Z106: =Z38+Z40 -> 3863 | AA106: =AA38+AA40 -> 3565 | AC106: =AA106 -> 3565
B107: NOPAT | L107: =L11*(1-L104) -> 1454.368 | M107: =M11*(1-M104) -> 1920.0685 | N107: =N11*(1-N104) -> -342 | O107: =O11*(1-O104) -> 340.26966 | P107: =P11*(1-P104) -> 1835.0364 | Q107: =Q11*(1-Q104) -> 3532.6005 | AC107: =AC11*(1-AC104) -> 3532.6005
B108: Capex | L108: =L59+L60 -> -498 | M108: =M59+M60 -> -381 | N108: =N59+N60 -> -316 | O108: =O59+O60 -> -254 | P108: =P59+P60 -> -265 | Q108: =Q59+Q60 -> -569 | T108: =T59+T60 -> -68 | U108: =U59+U60 -> -71 | V108: =V59+V60 -> -43 | W108: =W59+W60 -> -83 | X108: =X59+X60 -> -105 | Y108: =Y59+Y60 -> -116 | Z108: =Z59+Z60 -> -161 | AA108: =AA59+AA60 -> -187 | AC108: =AC59+AC60 -> -569
B109: Net income with non-controlling | L109: =L16+L17 -> 1314 | M109: =M16+M17 -> 1649 | N109: =N16+N17 -> -529 | O109: =O16+O17 -> 335 | P109: =P16+P17 -> 1469 | Q109: =Q16+Q17 -> 3184 | T109: =T16+T17 -> 305 | U109: =U16+U17 -> 336 | V109: =V16+V17 -> 340 | W109: =W16+W17 -> 488 | X109: =X16+X17 -> 549 | Y109: =Y16+Y17 -> 593 | Z109: =Z16+Z17 -> 748 | AA109: =AA16+AA17 -> 1294 | AC109: =AC16+AC17 -> 3184
...

Sheet Analysis ->
H5: Links
H6: Overview'!B3
H7: Financials ->'!B13
H8: Analysis ->'!B13
H9: Forecast ->'!B13
H10: Valuation ->'!B13
B13: Analysis ->

Sheet Basic
B1: TTM/YTD data
B4: Overview | E4: CAGR
B5: Price | C5: =Overview!C5 -> 676.77 | F5: 5Y | G5: 10Y
B6: Market capitalization | C6: =Statement!AC151 -> 160394.49 | E6: Revenue | F6: =IF(Statement!M5<=0,"N/A",_xlfn.RRI(4,Statement!M5,Statement!Q5)) -> 0.01125691 | G6: =IF(Statement!H5<=0,"N/A",_xlfn.RRI(9,Statement!H5,Statement!Q5)) -> N/A
B7: Enterprise value | C7: =Statement!AC152 -> 162255.49 | E7: Net income | F7: =IF(OR(Statement!M17<=0, Statement!Q17<=0), "N/A", _xlfn.RRI(4, Statement!M17, Statement!Q17)) -> 0.1787945 | G7: =IF(OR(Statement!H17<=0, Statement!Q17<=0), "N/A", _xlfn.RRI(9, Statement!H17, Statement!Q17)) -> N/A
B8: PE | C8: =Statement!AC148 -> 48.758646 | E8: EPS | F8: =IF(OR(Statement!M25<=0, Statement!Q25<=0), "N/A", _xlfn.RRI(4, Statement!M25, Statement!Q25)) -> 0.1722878 | G8: =IF(OR(Statement!H25<=0, Statement!Q25<=0), "N/A", _xlfn.RRI(9, Statement!H25, Statement!Q25)) -> N/A
B9: PS | C9: =Statement!AC149 -> 12.69464 | E9: Dividend | F9: =IF(Statement!M81<=0,"N/A",_xlfn.RRI(4,Statement!M81,Statement!Q81)) -> 0.013271367 | G9: =IF(Statement!H81<=0,"N/A",_xlfn.RRI(9,Statement!H81,Statement!Q81)) -> N/A
B10: PB | C10: =Statement!AC150 -> 70.893766 | E10: Price | F10: =IF(Statement!M115<=0,"N/A",_xlfn.RRI(4,Statement!M115,Statement!Q115)) -> 0.85618324 | G10: =IF(Statement!H115<=0,"N/A",_xlfn.RRI(9,Statement!H115,Statement!Q115)) -> N/A
B11: EV/Revenue | C11: =Statement!AC153 -> 13.305083
B12: EV/EBIT | C12: =Statement!AC154 -> 39.632509
B15: Margins | E15: Earnings quality
B16: Gross margin | C16: =Statement!AC99 -> 0.45576056 | E16: Net income | F16: =Statement!AC17 -> 3184
B17: Operating margin | C17: =Statement!AC100 -> 0.33571136 | E17: Operating cash | F17: =Statement!AC58 -> 3674
B18: Net margin | C18: =Statement!AC101 -> 0.26109061 | E18: Cash accruals | F18: =IF(OR(F16<=0, F17<=0),"N/A",F16-F17) -> -490
B21: DuPont Identity | E21: Performance indicators
B22: Profit Margin (Earnings/Revenue) | C22: =Statement!AC119 -> 0.26109061 | E22: ROA | F22: =C24 -> 0.31929402
B23: Asset Turnover (Revenue/Total assets) | C23: =Statement!AC120 -> 1.2229242 | E23: ROE | F23: =C26 -> 1.4693124
B24: ROA | C24: =Statement!AC121 -> 0.31929402 | E24: ROIC | F24: =Statement!AC138 -> 0.87701106
B25: Equity Multiplier (Total assets/Equity) | C25: =Statement!AC122 -> 4.6017536
B26: ROE | C26: =Statement!AC123 -> 1.4693124
B29: Cash conversion cycle | E29: Liquidity ratios
B30: DSO | C30: =Statement!AC139 -> 45.913079 | E30: Debt/Equity | F30: =Statement!AC143 -> 1.6451315
B31: DIO | C31: =Statement!AC140 -> 86.396715 | E31: Net Debt/Equity | F31: =Statement!AC144 -> 0.85879096
B32: DPO | C32: =Statement!AC141 -> 96.130782 | E32: Current ratio | F32: =Statement!AC146 -> 1.6696514
B33: Net trade cycle | C33: =Statement!AC142 -> 36.179013 | E33: Quick ratio | F33: =Statement!AC145 -> 1.0354973
E34: Interest coverage | F34: =Statement!AC147 -> 16.11811
B37: Earnings yields | E37: Payout ratios
B38: Earnings yield | C38: =Statement!AC160 -> 0.020509183 | E38: Dividend payout ratio | F38: =Statement!AC166 -> 0.21922545
B39: FCF yield | C39: =Statement!AC159 -> 0.018030545 | E39: Buyback payout ratio | F39: =Statement!AC167 -> 0.060857538
B40: Dividend yield | C40: =Statement!AC161 -> 0.0043146121 | E40: Full payout ratio | F40: =Statement!AC168 -> 0.28008299
B41: Buyback yield | C41: =Statement!AC162 -> 0.0010972946
B42: Total shareholder yield | C42: =Statement!AC163 -> 0.0050500488
B45: Ownership | E45: Cash holdings
B46: Insider ownership | C46: =Statement!AC169 -> 0.0084388186 | E46: Cash per share | F46: =Statement!AC170 -> 7.5066079
E47: Net cash per share | F47: =Statement!AC173 -> -8.1982379
E48: Net cash to market cap | F48: =Statement!AC174 -> -0.011602643
B51: Stock based compensation | E51: CapEx usage
B52: Stock based compensation % OCF | C52: =Statement!AC171 -> 0.057974959 | E52: Capex to Revenue | F52: =Statement!AC175 -> 0.046658467
B53: Stock based compensation % Revenue | C53: =Statement!AC172 -> 0.017466175 | E53: CapEx to OCF | F53: =Statement!AC176 -> 0.15487207
E54: CapEx to D&A | F54: =Statement!AC177 -> 2.0615942
B57: FCF ratios
B58: P/FCF | C58: =Statement!AC157 -> 55.461442
B59: EV/FCF | C59: =Statement!AC158 -> 52.670084
B60: FCFF/Sales | C60: =Statement!AC164 -> 0.25261177
B61: FCFE/Sales | C61: =Statement!AC165 -> 0.23714637

Sheet Yearly Analysis
C2: =Statement!M2 -> 01.07.2022 | D2: =Statement!N2 -> 30.06.2023 | E2: =Statement!O2 -> 28.06.2024 | F2: =Statement!P2 -> 27.06.2025 | G2: =Statement!Q2 -> 03.07.2026
C3: =Statement!M3 -> 2022 | D3: =Statement!N3 -> 2023 | E3: =Statement!O3 -> 2024 | F3: =Statement!P3 -> 2025 | G3: =Statement!Q3 -> 2026 | I3: =Statement!AC3 -> TTM/YTD
B5: Overview
B6: Price | C6: =Statement!M114 -> 69.09 | D6: =Statement!N114 -> 61.87 | E6: =Statement!O114 -> 103.27 | F6: =Statement!P114 -> 141.44 | G6: =Statement!Q114 -> 820.16 | I6: =Statement!AC114 -> 676.77
B7: Market capitalization | C7: =Statement!M151 -> 14716.17 | D7: =Statement!N151 -> 12807.09 | E7: =Statement!O151 -> 21996.51 | F7: =Statement!P151 -> 30833.92 | G7: =Statement!Q151 -> 194377.92 | I7: =Statement!AC151 -> 160394.49
B8: Enterprise value | C8: =Statement!M152 -> 19747.17 | D8: =Statement!N152 -> 17472.09 | E8: =Statement!O152 -> 26312.51 | F8: =Statement!P152 -> 34937.92 | G8: =Statement!Q152 -> 196238.92 | I8: =Statement!AC152 -> 162255.49
B9: PE | C9: =Statement!M148 -> 9.3872283 | D9: =Statement!N148 -> -24.167969 | E9: =Statement!O148 -> 65.360759 | F9: =Statement!P148 -> 20.892171 | G9: =Statement!Q148 -> 59.004317 | I9: =Statement!AC148 -> 48.758646
B10: PS | C10: =Statement!M149 -> 1.3271726 | D10: =Statement!N149 -> 1.734438 | E10: =Statement!O149 -> 3.3419692 | F10: =Statement!P149 -> 3.3739123 | G10: =Statement!Q149 -> 15.401118 | I10: =Statement!AC149 -> 12.69464
B11: PB | C11: =Statement!M150 -> 132.47532 | D11: =Statement!N150 -> -10.681476 | E11: =Statement!O150 -> -14.54507 | F11: =Statement!P150 -> -66.504901 | G11: =Statement!Q150 -> 85.914315 | I11: =Statement!AC150 -> 70.893766
B12: EV/Revenue | C12: =Statement!M153 -> 1.6934371 | D12: =Statement!N153 -> 2.3662094 | E12: =Statement!O153 -> 4.0165639 | F12: =Statement!P153 -> 3.840598 | G12: =Statement!Q153 -> 16.091752 | I12: =Statement!AC153 -> 13.305083
B13: EV/EBIT | C13: =Statement!M154 -> 10.100854 | D13: =Statement!N154 -> -51.087982 | E13: =Statement!O154 -> 58.213518 | F13: =Statement!P154 -> 18.485672 | G13: =Statement!Q154 -> 47.933298 | I13: =Statement!AC154 -> 39.632509
B15: Margins
B16: Gross margin | C16: =Statement!M99 -> 0.29748735 | D16: =Statement!N99 -> 0.18296316 | E16: =Statement!O99 -> 0.23446802 | F16: =Statement!P99 -> 0.35176432 | G16: =Statement!Q99 -> 0.45576056 | I16: =Statement!AC99 -> 0.45576056
B17: Operating margin | C17: =Statement!M100 -> 0.16765286 | D17: =Statement!N100 -> -0.04631636 | E17: =Statement!O100 -> 0.0689971 | F17: =Statement!P100 -> 0.2077608 | G17: =Statement!Q100 -> 0.33571136 | I17: =Statement!AC100 -> 0.33571136
B18: Net margin | C18: =Statement!M101 -> 0.14141154 | D18: =Statement!N101 -> -0.071641387 | E18: =Statement!O101 -> 0.051137231 | F18: =Statement!P101 -> 0.16148181 | G18: =Statement!Q101 -> 0.26109061 | I18: =Statement!AC101 -> 0.26109061
B20: Earnings quality
B21: Net income | C21: =Statement!M17 -> 1649 | D21: =Statement!N17 -> -529 | E21: =Statement!O17 -> 335 | F21: =Statement!P17 -> 1469 | G21: =Statement!Q17 -> 3184 | I21: =Statement!AC17 -> 3184
B22: Operating cash | C22: =Statement!M58 -> 1657 | D22: =Statement!N58 -> 942 | E22: =Statement!O58 -> 918 | F22: =Statement!P58 -> 1083 | G22: =Statement!Q58 -> 3674 | I22: =Statement!AC58 -> 3674
B23: Cash accruals | C23: =IF(OR(C21<=0, C22<=0),"N/A",C21-C22) -> -8 | D23: =IF(OR(D21<=0, D22<=0),"N/A",D21-D22) -> N/A | E23: =IF(OR(E21<=0, E22<=0),"N/A",E21-E22) -> -583 | F23: =IF(OR(F21<=0, F22<=0),"N/A",F21-F22) -> 386 | G23: =IF(OR(G21<=0, G22<=0),"N/A",G21-G22) -> -490 | I23: =IF(OR(I21<=0, I22<=0),"N/A",I21-I22) -> -490
B25: DuPont Identity
B26: Profit Margin (Earnings/Revenue) | C26: =Statement!M119 -> 0.14141154 | D26: =Statement!N119 -> -0.071641387 | E26: =Statement!O119 -> 0.051137231 | F26: =Statement!P119 -> 0.16148181 | G26: =Statement!Q119 -> 0.26109061 | I26: =Statement!AC119 -> 0.26109061
B27: Asset Turnover (Revenue/Total assets) | C27: =Statement!M120 -> 1.3037791 | D27: =Statement!N120 -> 0.97723663 | E27: =Statement!O120 -> 0.84649179 | F27: =Statement!P120 -> 1.1338651 | G27: =Statement!Q120 -> 1.2229242 | I27: =Statement!AC120 -> 1.2229242
B28: ROA | C28: =Statement!M121 -> 0.18436941 | D28: =Statement!N121 -> -0.070010588 | E28: =Statement!O121 -> 0.043287246 | F28: =Statement!P121 -> 0.18309859 | G28: =Statement!Q121 -> 0.31929402 | I28: =Statement!AC121 -> 0.31929402
B29: Equity Multiplier (Total assets/Equity) | C29: =Statement!M122 -> 82.055046 | D29: =Statement!N122 -> -6.3019183 | E29: =Statement!O122 -> -5.1904762 | F29: =Statement!P122 -> -17.710817 | G29: =Statement!Q122 -> 4.6017536 | I29: =Statement!AC122 -> 4.6017536
B30: ROE | C30: =Statement!M123 -> 15.12844 | D30: =Statement!N123 -> 0.441201 | E30: =Statement!O123 -> -0.22468142 | F30: =Statement!P123 -> -3.2428256 | G30: =Statement!Q123 -> 1.4693124 | I30: =Statement!AC123 -> 1.4693124
B32: Performance Indicators
B33: ROA | C33: =C28 -> 0.18436941 | D33: =D28 -> -0.070010588 | E33: =E28 -> 0.043287246 | F33: =F28 -> 0.18309859 | G33: =G28 -> 0.31929402 | I33: =I28 -> 0.31929402
B34: ROE | C34: =C30 -> 15.12844 | D34: =D30 -> 0.441201 | E34: =E30 -> -0.22468142 | F34: =F30 -> -3.2428256 | G34: =G30 -> 1.4693124 | I34: =I30 -> 1.4693124
B35: ROIC | C35: =Statement!M138 -> 0.37355418 | D35: =Statement!N138 -> -0.098672822 | E35: =Statement!O138 -> 0.12044944 | F35: =Statement!P138 -> 0.50261198 | G35: =Statement!Q138 -> 0.87701106 | I35: =Statement!AC138 -> 0.87701106
B37: Cash conversion cycle
B38: DSO | C38: =Statement!M139 -> 47.953006 | D38: =Statement!N139 -> 30.696777 | E38: =Statement!O139 -> 23.902458 | F38: =Statement!P139 -> 38.47807 | G38: =Statement!Q139 -> 45.913079 | I38: =Statement!AC139 -> 45.913079
B39: DIO | C39: =Statement!M140 -> 69.729614 | D39: =Statement!N140 -> 68.970661 | E39: =Statement!O140 -> 90.176471 | F39: =Statement!P140 -> 89.130066 | G39: =Statement!Q140 -> 86.396715 | I39: =Statement!AC140 -> 86.396715
B40: DPO | C40: =Statement!M141 -> 91.695557 | D40: =Statement!N141 -> 96.98243 | E40: =Statement!O141 -> 129.98804 | F40: =Statement!P141 -> 99.28099 | G40: =Statement!Q141 -> 96.130782 | I40: =Statement!AC141 -> 96.130782
B41: Net trade cycle | C41: =Statement!M142 -> 25.987063 | D41: =Statement!N142 -> 2.6850082 | E41: =Statement!O142 -> -15.909108 | F41: =Statement!P142 -> 28.327145 | G41: =Statement!Q142 -> 36.179013 | I41: =Statement!AC142 -> 36.179013
B43: Liquidity ratios
B44: Debt/Equity | C44: =Statement!M143 -> 51.798165 | D44: =Statement!N143 -> -4.5462886 | E44: =Statement!O143 -> -3.8054997 | F44: =Statement!P143 -> -11.02649 | G44: =Statement!Q143 -> 1.6451315 | I44: =Statement!AC143 -> 1.6451315
B45: Net Debt/Equity | C45: =Statement!M144 -> 46.155963 | D45: =Statement!N144 -> -3.8907423 | E45: =Statement!O144 -> -2.8947015 | F45: =Statement!P144 -> -9.0596026 | G45: =Statement!Q144 -> 0.85879096 | I45: =Statement!AC144 -> 0.85879096
B46: Quick ratio | C46: =Statement!M145 -> 0.60393812 | D46: =Statement!N145 -> 0.54282407 | E46: =Statement!O145 -> 0.57663763 | F46: =Statement!P145 -> 0.69864048 | G46: =Statement!Q145 -> 1.0354973 | I46: =Statement!AC145 -> 1.0354973
B47: Current ratio | C47: =Statement!M146 -> 1.1344585 | D47: =Statement!N146 -> 1.1207562 | E47: =Statement!O146 -> 1.0751855 | F47: =Statement!P146 -> 1.3795317 | G47: =Statement!Q146 -> 1.6696514 | I47: =Statement!AC146 -> 1.6696514
B48: Interest coverage | C48: =Statement!M147 -> 7.9149798 | D48: =Statement!N147 -> N/A | E48: =Statement!O147 -> 1.4258675 | F48: =Statement!P147 -> 6.3851351 | G48: =Statement!Q147 -> 16.11811 | I48: =Statement!AC147 -> 16.11811
B50: Earnings yields
B51: Earnings yield | C51: =Statement!M160 -> 0.10652772 | D51: =Statement!N160 -> -0.041377081 | E51: =Statement!O160 -> 0.0152997 | F51: =Statement!P160 -> 0.047864819 | G51: =Statement!Q160 -> 0.016947913 | I51: =Statement!AC160 -> 0.020509183
B52: FCF yield | C52: =Statement!M159 -> 0.076854236 | D52: =Statement!N159 -> 0.039899774 | E52: =Statement!O159 -> 0.024412964 | F52: =Statement!P159 -> 0.020042862 | G52: =Statement!Q159 -> 0.014878233 | I52: =Statement!AC159 -> 0.018030545
B53: Dividend yield | C53: =Statement!M161 -> 0.040092633 | D53: =Statement!N161 -> 0.045256182 | E53: =Statement!O161 -> 0.027113392 | F53: =Statement!P161 -> 0.020220588 | G53: =Statement!Q161 -> 0.0035602809 | I53: =Statement!AC161 -> 0.0043146121
B54: Buyback yield | C54: =Statement!M162 -> 0.12224648 | D54: =Statement!N162 -> 0.031857354 | E54: =Statement!O162 -> 0 | F54: =Statement!P162 -> 0 | G54: =Statement!Q162 -> 0.00090545264 | I54: =Statement!AC162 -> 0.0010972946
B55: Total shareholder yield | C55: =Statement!M163 -> 0.16369748 | D55: =Statement!N163 -> 0.077300933 | E55: =Statement!O163 -> 0.026595128 | F55: =Statement!P163 -> 0.019459089 | G55: =Statement!Q163 -> 0.00416714 | I55: =Statement!AC163 -> 0.0050500488
B57: Payout ratios
B58: Dividend payout ratio | C58: =Statement!M166 -> 0.53934571 | D58: =Statement!N166 -> 1.1389432 | E58: =Statement!O166 -> 1.0893855 | F58: =Statement!P166 -> 0.97087379 | G58: =Statement!Q166 -> 0.21922545 | I58: =Statement!AC166 -> 0.21922545
B59: Buyback payout ratio | C59: =Statement!M167 -> 1.5906278 | D59: =Statement!N167 -> 0.79843444 | E59: =Statement!O167 -> 0 | F59: =Statement!P167 -> 0 | G59: =Statement!Q167 -> 0.060857538 | I59: =Statement!AC167 -> 0.060857538
B60: Full payout ratio | C60: =Statement!M168 -> 2.1299735 | D60: =Statement!N168 -> 1.9373777 | E60: =Statement!O168 -> 1.0893855 | F60: =Statement!P168 -> 0.97087379 | G60: =Statement!Q168 -> 0.28008299 | I60: =Statement!AC168 -> 0.28008299
B62: Ownership
B63: Insider ownership | C63: =Statement!M169 -> 0.0093896714 | D63: =Statement!N169 -> 0.0096618357 | E63: =Statement!O169 -> 0.0093896714 | F63: =Statement!P169 -> 0.0091743119 | G63: =Statement!Q169 -> 0.0084388186 | I63: =Statement!AC169 -> 0.0084388186
B65: Cash holdings
B66: Cash per share | C66: =Statement!M170 -> 2.9425837 | D66: =Statement!N170 -> 3.7971014 | E66: =Statement!O170 -> 6.4666667 | F66: =Statement!P170 -> 4.1830986 | G66: =Statement!Q170 -> 7.5066079 | I66: =Statement!AC170 -> 7.5066079
B67: Net cash per share | C67: =Statement!M173 -> -24.07177 | D67: =Statement!N173 -> -22.536232 | E67: =Statement!O173 -> -20.552381 | F67: =Statement!P173 -> -19.267606 | G67: =Statement!Q173 -> -8.1982379 | I67: =Statement!AC173 -> -8.1982379
B68: Net cash to market cap | C68: =Statement!M174 -> -0.34186884 | D68: =Statement!N174 -> -0.36425136 | E68: =Statement!O174 -> -0.19621294 | F68: =Statement!P174 -> -0.13310017 | G68: =Statement!Q174 -> -0.0095741327 | I68: =Statement!AC174 -> -0.011602643
B70: Stock Based Compensation
B71: Stock based compensation % OCF | C71: =Statement!M171 -> 0.087507544 | D71: =Statement!N171 -> 0.12208068 | E71: =Statement!O171 -> 0.13834423 | F71: =Statement!P171 -> 0.18467221 | G71: =Statement!Q171 -> 0.057974959 | I71: =Statement!AC171 -> 0.057974959
B72: Stock based compensation % Revenue | C72: =Statement!M172 -> 0.012434611 | D72: =Statement!N172 -> 0.015574215 | E72: =Statement!O172 -> 0.019386353 | F72: =Statement!P172 -> 0.02198527 | G72: =Statement!Q172 -> 0.017466175 | I72: =Statement!AC172 -> 0.017466175
B74: CapEx Usage
B75: Capex to Revenue | C75: =Statement!M175 -> 0.032673013 | D75: =Statement!N175 -> 0.042795233 | E75: =Statement!O175 -> 0.038772706 | F75: =Statement!P175 -> 0.029130483 | G75: =Statement!Q175 -> 0.046658467 | I75: =Statement!AC175 -> 0.046658467
B76: CapEx to OCF | C76: =Statement!M176 -> 0.22993361 | D76: =Statement!N176 -> 0.33545648 | E76: =Statement!O176 -> 0.27668845 | F76: =Statement!P176 -> 0.24469067 | G76: =Statement!Q176 -> 0.15487207 | I76: =Statement!AC176 -> 0.15487207
B77: CapEx to D&A | C77: =Statement!M177 -> 0.84478936 | D77: =Statement!N177 -> 0.61598441 | E77: =Statement!O177 -> 0.96212121 | F77: =Statement!P177 -> 1.0557769 | G77: =Statement!Q177 -> 2.0615942 | I77: =Statement!AC177 -> 2.0615942
B79: Growth rates
B80: Revenue | C80: =Statement!M88 -> 0.091751709 | D80: =Statement!N88 -> -0.36677815 | E80: =Statement!O88 -> -0.11281148 | F80: =Statement!P88 -> 0.38864296 | G80: =Statement!Q88 -> 0.34055183
B81: COGS | C81: =Statement!M89 -> 0.055126224 | D81: =Statement!N89 -> -0.2635498 | E81: =Statement!O89 -> -0.1687386 | F81: =Statement!P89 -> 0.17587238 | G81: =Statement!Q89 -> 0.12548754
B82: Gross Profit | C82: =Statement!M90 -> 0.18923552 | D82: =Statement!N90 -> -0.61055059 | E82: =Statement!O90 -> 0.1369356 | F82: =Statement!P90 -> 1.0833333 | G82: =Statement!Q90 -> 0.736875
B83: OpEx | C83: =Statement!M93 -> 0.06245614 | D83: =Statement!N93 -> 0.11822985 | E83: =Statement!O93 -> -0.35971648 | F83: =Statement!P93 -> 0.20848708 | G83: =Statement!Q93 -> 0.11755725
B84: Operating Income | C84: =Statement!M94 -> 0.31032172 | D84: =Statement!N94 -> -1.1749361 | E84: =Statement!O94 -> 2.3216374 | F84: =Statement!P94 -> 3.1814159 | G84: =Statement!Q94 -> 1.1661376
B85: Net Income | C85: =Statement!M96 -> 0.25494673 | D85: =Statement!N96 -> -1.3208005 | E85: =Statement!O96 -> 1.6332703 | F85: =Statement!P96 -> 3.3850746 | G85: =Statement!Q96 -> 1.1674609
B87: FCF ratios
B88: P/FCF | C88: =Statement!M157 -> 13.011645 | D88: =Statement!N157 -> 25.062798 | E88: =Statement!O157 -> 40.961844 | F88: =Statement!P157 -> 49.893074 | G88: =Statement!Q157 -> 67.212282 | I88: =Statement!AC157 -> 55.461442
B89: EV/FCF | C89: =Statement!M158 -> 14.659366 | D89: =Statement!N158 -> 17.180029 | E89: =Statement!O158 -> 35.737599 | F89: =Statement!P158 -> 40.813594 | G89: =Statement!Q158 -> 63.701514 | I89: =Statement!AC158 -> 52.670084
B90: FCFF/Sales | C90: =Statement!M164 -> 0.11551912 | D90: =Statement!N164 -> 0.13773023 | E90: =Statement!O164 -> 0.11239042 | F90: =Statement!P164 -> 0.094100951 | G90: =Statement!Q164 -> 0.25261177 | I90: =Statement!AC164 -> 0.25261177
B91: FCFE/Sales | C91: =Statement!M165 -> 0.096989967 | D91: =Statement!N165 -> 0.069203684 | E91: =Statement!O165 -> 0.081972218 | F91: =Statement!P165 -> 0.067934484 | G91: =Statement!Q165 -> 0.23714637 | I91: =Statement!AC165 -> 0.23714637
B93: Other standard growth rates
B94: Dividends | C94: =Statement!M195 -> -0.06009245 | D94: =Statement!N195 -> -0.045901639 | E94: =Statement!O195 -> 0.0051546392 | F94: =Statement!P195 -> 0.025641026 | G94: =Statement!Q195 -> 0.056666667
B97: Growth rates breakdown
B98: =Statement!B190 -> Datacenter | C98: =Statement!M190 -> 0 | D98: =Statement!N190 -> 0 | E98: =Statement!O190 -> 0 | F98: =Statement!P190 -> 1 | G98: =Statement!Q190 -> 0.4377575
B99: =Statement!B191 -> Edge & IoT | C99: =Statement!M191 -> 0 | D99: =Statement!N191 -> 0 | E99: =Statement!O191 -> 0 | F99: =Statement!P191 -> 1 | G99: =Statement!Q191 -> 0.054347826

Sheet Quarter analysis
C3: Latest 2 quarters | F3: YoY
C4: =Statement!Z2 -> 03.04.2026 | D4: =Statement!AA2 -> 03.07.2026 | F4: =Statement!W2 -> 27.06.2025 | G4: =Statement!AA2 -> 03.07.2026
B5: Income statement growth | C5: =Statement!Z3 -> Q3 2026 | D5: =Statement!AA3 -> Q4 2026 | F5: =Statement!W3 -> Q4 2025 | G5: =Statement!AA3 -> Q4 2026
B6: Revenue | C6: =Statement!Z5 -> 3112 | D6: =Statement!AA5 -> 3629 | F6: =Statement!W5 -> 2444 | G6: =Statement!AA5 -> 3629
B7: Growth | C7: =Statement!AA88 -> 0.16613111 | F7: =IF(F6=0, IF(G6=0,0,IF(G6>0,1,-1)), (G6-F6)/ABS(F6) ) -> 0.48486088
B8: COGS | C8: =Statement!Z6 -> 1665 | D8: =Statement!AA6 -> 1731 | F8: =Statement!W6 -> 1530 | G8: =Statement!AA6 -> 1731
B9: Growth | C9: =Statement!AA89 -> 0.03963964 | F9: =IF(F8=0, IF(G8=0,0,IF(G8>0,1,-1)), (G8-F8)/ABS(F8) ) -> 0.13137255
B10: Gross Profit | C10: =Statement!Z7 -> 1447 | D10: =Statement!AA7 -> 1898 | F10: =Statement!W7 -> 914 | G10: =Statement!AA7 -> 1898
B11: Growth | C11: =Statement!AA90 -> 0.31167934 | F11: =IF(F10=0, IF(G10=0,0,IF(G10>0,1,-1)), (G10-F10)/ABS(F10) ) -> 1.0765864
B12: OpEx | C12: =Statement!Z10 -> 449 | D12: =Statement!AA10 -> 339 | F12: =Statement!W10 -> 346 | G12: =Statement!AA10 -> 339
B13: Growth | C13: =Statement!AA93 -> -0.24498886 | F13: =IF(F12=0, IF(G12=0,0,IF(G12>0,1,-1)), (G12-F12)/ABS(F12) ) -> -0.020231214
B14: Operating profit | C14: =Statement!Z11 -> 998 | D14: =Statement!AA11 -> 1559 | F14: =Statement!W11 -> 568 | G14: =Statement!AA11 -> 1559
B15: Growth | C15: =Statement!AA94 -> 0.56212425 | F15: =IF(F14=0, IF(G14=0,0,IF(G14>0,1,-1)), (G14-F14)/ABS(F14) ) -> 1.7447183
B16: Net income | C16: =Statement!Z17 -> 748 | D16: =Statement!AA17 -> 1294 | F16: =Statement!W17 -> 488 | G16: =Statement!AA17 -> 1294
B17: Growth | C17: =Statement!AA96 -> 0.72994652 | F17: =IF(F16=0, IF(G16=0,0,IF(G16>0,1,-1)), (G16-F16)/ABS(F16) ) -> 1.6516393
B18: Diluted shares outstanding | C18: =Statement!Z21 -> 229 | D18: =Statement!AA21 -> 232 | F18: =Statement!W21 -> 218 | G18: =Statement!AA21 -> 232
B19: Growth | C19: =IF(C18=0, IF(D18=0,0,IF(D18>0,1,-1)), (D18-C18)/ABS(C18) ) -> 0.013100437 | F19: =IF(F18=0, IF(G18=0,0,IF(G18>0,1,-1)), (G18-F18)/ABS(F18) ) -> 0.064220183
B20: Diluted EPS | C20: =Statement!Z25 -> 3.27 | D20: =Statement!AA25 -> 5.58 | F20: =Statement!W25 -> 2.24 | G20: =Statement!AA25 -> 5.58
B21: Growth | C21: =IF(C20=0, IF(D20=0,0,IF(D20>0,1,-1)), (D20-C20)/ABS(C20) ) -> 0.70642202 | F21: =IF(F20=0, IF(G20=0,0,IF(G20>0,1,-1)), (G20-F20)/ABS(F20) ) -> 1.4910714
B23: Revenue breakdown | C23: =C5 -> Q3 2026 | D23: =D5 -> Q4 2026 | F23: =F5 -> Q4 2025 | G23: =G5 -> Q4 2026
B24: =Statement!B185 -> Datacenter | C24: =Statement!Z185 -> 2500 | D24: =Statement!AA185 -> 2933 | F24: =Statement!W185 -> 1863 | G24: =Statement!AA185 -> 2933
B25: Growth | C25: =IF(C24=0, IF(D24=0,0,IF(D24>0,1,-1)), (D24-C24)/ABS(C24) ) -> 0.1732 | F25: =IF(F24=0, IF(G24=0,0,IF(G24>0,1,-1)), (G24-F24)/ABS(F24) ) -> 0.57434246
B26: =Statement!B186 -> Edge & IoT | C26: =Statement!Z186 -> 612 | D26: =Statement!AA186 -> 697 | F26: =Statement!W186 -> 581 | G26: =Statement!AA186 -> 697
B27: Growth | C27: =IF(C26=0, IF(D26=0,0,IF(D26>0,1,-1)), (D26-C26)/ABS(C26) ) -> 0.13888889 | F27: =IF(F26=0, IF(G26=0,0,IF(G26>0,1,-1)), (G26-F26)/ABS(F26) ) -> 0.19965577

Sheet Graphs Year
C55: =Statement!H2 -> 0 | D55: =Statement!I2 -> 0 | E55: =Statement!J2 -> 0 | F55: =Statement!K2 -> 0 | G55: =Statement!L2 -> 02.07.2021 | H55: =Statement!M2 -> 01.07.2022 | I55: =Statement!N2 -> 30.06.2023 | J55: =Statement!O2 -> 28.06.2024 | ... L55: =Statement!Q2 -> 03.07.2026
C56: =Statement!H3 -> 0 | D56: =Statement!I3 -> 0 | E56: =Statement!J3 -> 0 | F56: =Statement!K3 -> 0 | G56: =Statement!L3 -> 2021 | H56: =Statement!M3 -> 2022 | I56: =Statement!N3 -> 2023 | J56: =Statement!O3 -> 2024 | ... L56: =Statement!Q3 -> 2026
B57: Revenue | C57: =Statement!H5 -> 0 | D57: =Statement!I5 -> 0 | E57: =Statement!J5 -> 0 | F57: =Statement!K5 -> 0 | G57: =Statement!L5 -> 10681 | H57: =Statement!M5 -> 11661 | I57: =Statement!N5 -> 7384 | J57: =Statement!O5 -> 6551 | ... L57: =Statement!Q5 -> 12195
B58: Operating income | C58: =Statement!H11 -> 0 | D58: =Statement!I11 -> 0 | E58: =Statement!J11 -> 0 | F58: =Statement!K11 -> 0 | G58: =Statement!L11 -> 1492 | H58: =Statement!M11 -> 1955 | I58: =Statement!N11 -> -342 | J58: =Statement!O11 -> 452 | ... L58: =Statement!Q11 -> 4094
B59: Net income | C59: =Statement!H17 -> 0 | D59: =Statement!I17 -> 0 | E59: =Statement!J17 -> 0 | F59: =Statement!K17 -> 0 | G59: =Statement!L17 -> 1314 | H59: =Statement!M17 -> 1649 | I59: =Statement!N17 -> -529 | J59: =Statement!O17 -> 335 | ... L59: =Statement!Q17 -> 3184
B60: FCFE | C60: =Statement!H155 -> 0 | D60: =Statement!I155 -> 0 | E60: =Statement!J155 -> 0 | F60: =Statement!K155 -> 0 | G60: =Statement!L155 -> 1016 | H60: =Statement!M155 -> 1131 | I60: =Statement!N155 -> 511 | J60: =Statement!O155 -> 537 | ... L60: =Statement!Q155 -> 2892
B61: FCFF | C61: =Statement!H156 -> 0 | D61: =Statement!I156 -> 0 | E61: =Statement!J156 -> 0 | F61: =Statement!K156 -> 0 | G61: =Statement!L156 -> 1209.368 | H61: =Statement!M156 -> 1347.0685 | I61: =Statement!N156 -> 1017 | J61: =Statement!O156 -> 736.26966 | ... L61: =Statement!Q156 -> 3080.6005
B62: Gross margin | C62: =Statement!H99 -> 0 | D62: =Statement!I99 -> 0 | E62: =Statement!J99 -> 0 | F62: =Statement!K99 -> 0 | G62: =Statement!L99 -> 0.27310177 | H62: =Statement!M99 -> 0.29748735 | I62: =Statement!N99 -> 0.18296316 | J62: =Statement!O99 -> 0.23446802 | ... L62: =Statement!Q99 -> 0.45576056
B63: Operating margin | C63: =Statement!H100 -> 0 | D63: =Statement!I100 -> 0 | E63: =Statement!J100 -> 0 | F63: =Statement!K100 -> 0 | G63: =Statement!L100 -> 0.1396873 | H63: =Statement!M100 -> 0.16765286 | I63: =Statement!N100 -> -0.04631636 | J63: =Statement!O100 -> 0.0689971 | ... L63: =Statement!Q100 -> 0.33571136
B64: Net margin | C64: =Statement!H101 -> 0 | D64: =Statement!I101 -> 0 | E64: =Statement!J101 -> 0 | F64: =Statement!K101 -> 0 | G64: =Statement!L101 -> 0.12302219 | H64: =Statement!M101 -> 0.14141154 | I64: =Statement!N101 -> -0.071641387 | J64: =Statement!O101 -> 0.051137231 | ... L64: =Statement!Q101 -> 0.26109061
B65: ="Revenue "&Statement!B185 -> Revenue Datacenter | C65: =Statement!H185 -> 0 | D65: =Statement!I185 -> 0 | E65: =Statement!J185 -> 0 | F65: =Statement!K185 -> 0 | G65: =Statement!L185 -> 0 | H65: =Statement!M185 -> 0 | I65: =Statement!N185 -> 0 | J65: =Statement!O185 -> 0 | ... L65: =Statement!Q185 -> 9771
B66: ="Revenue "&Statement!B186 -> Revenue Edge & IoT | C66: =Statement!H186 -> 0 | D66: =Statement!I186 -> 0 | E66: =Statement!J186 -> 0 | F66: =Statement!K186 -> 0 | G66: =Statement!L186 -> 0 | H66: =Statement!M186 -> 0 | I66: =Statement!N186 -> 0 | J66: =Statement!O186 -> 0 | ... L66: =Statement!Q186 -> 2425
B67: ROA | C67: =Statement!H121 -> 0 | D67: =Statement!I121 -> 0 | E67: =Statement!J121 -> 0 | F67: =Statement!K121 -> 0 | G67: =Statement!L121 -> 0.15146974 | H67: =Statement!M121 -> 0.18436941 | I67: =Statement!N121 -> -0.070010588 | J67: =Statement!O121 -> 0.043287246 | ... L67: =Statement!Q121 -> 0.31929402
B68: ROE | C68: =Statement!H123 -> 0 | D68: =Statement!I123 -> 0 | E68: =Statement!J123 -> 0 | F68: =Statement!K123 -> 0 | G68: =Statement!L123 -> 2.0824089 | H68: =Statement!M123 -> 15.12844 | I68: =Statement!N123 -> 0.441201 | J68: =Statement!O123 -> -0.22468142 | ... L68: =Statement!Q123 -> 1.4693124
B69: ROIC | C69: =Statement!H138 -> 0 | D69: =Statement!I138 -> 0 | E69: =Statement!J138 -> 0 | F69: =Statement!K138 -> 0 | G69: =Statement!L138 -> 0.31887041 | H69: =Statement!M138 -> 0.37355418 | I69: =Statement!N138 -> -0.098672822 | J69: =Statement!O138 -> 0.12044944 | ... L69: =Statement!Q138 -> 0.87701106
B70: Price 5y | C70: =Statement!H199 -> 0 | D70: =Statement!I199 -> 0 | E70: =Statement!J199 -> 0 | F70: =Statement!K199 -> 0 | G70: =Statement!L199 -> 100 | H70: =Statement!M199 -> 100 | I70: =Statement!N199 -> 89.549862 | J70: =Statement!O199 -> 149.4717 | ... L70: =Statement!Q199 -> 1187.0893
B71: Revenue 5y | C71: =Statement!H200 -> 0 | D71: =Statement!I200 -> 0 | E71: =Statement!J200 -> 0 | F71: =Statement!K200 -> 0 | G71: =Statement!L200 -> 100 | H71: =Statement!M200 -> 100 | I71: =Statement!N200 -> 63.322185 | J71: =Statement!O200 -> 56.178715 | ... L71: =Statement!Q200 -> 104.57937
B72: EPS 5y | C72: =Statement!H201 -> 0 | D72: =Statement!I201 -> 0 | E72: =Statement!J201 -> 0 | F72: =Statement!K201 -> 0 | G72: =Statement!L201 -> 100 | H72: =Statement!M201 -> 100 | I72: =Statement!N201 -> -34.782609 | J72: =Statement!O201 -> 21.467391 | ... L72: =Statement!Q201 -> 188.8587

Sheet Graphs Quarter
C55: =Statement!T2 -> 27.09.2024 | D55: =Statement!U2 -> 27.12.2024 | E55: =Statement!V2 -> 28.03.2025 | F55: =Statement!W2 -> 27.06.2025 | G55: =Statement!X2 -> 03.10.2025 | H55: =Statement!Y2 -> 02.01.2026 | I55: =Statement!Z2 -> 03.04.2026 | J55: =Statement!AA2 -> 03.07.2026
C56: =Statement!T3 -> Q1 2025 | D56: =Statement!U3 -> Q2 2025 | E56: =Statement!V3 -> Q3 2025 | F56: =Statement!W3 -> Q4 2025 | G56: =Statement!X3 -> Q1 2026 | H56: =Statement!Y3 -> Q2 2026 | I56: =Statement!Z3 -> Q3 2026 | J56: =Statement!AA3 -> Q4 2026
B57: Revenue | C57: =Statement!T5 -> 2168 | D57: =Statement!U5 -> 2325 | E57: =Statement!V5 -> 2160 | F57: =Statement!W5 -> 2444 | G57: =Statement!X5 -> 2629 | H57: =Statement!Y5 -> 2825 | I57: =Statement!Z5 -> 3112 | J57: =Statement!AA5 -> 3629
B58: Operating income | C58: =Statement!T11 -> 403 | D58: =Statement!U11 -> 488 | E58: =Statement!V11 -> 431 | F58: =Statement!W11 -> 568 | G58: =Statement!X11 -> 694 | H58: =Statement!Y11 -> 843 | I58: =Statement!Z11 -> 998 | J58: =Statement!AA11 -> 1559
B59: Net income | C59: =Statement!T17 -> 305 | D59: =Statement!U17 -> 336 | E59: =Statement!V17 -> 340 | F59: =Statement!W17 -> 488 | G59: =Statement!X17 -> 549 | H59: =Statement!Y17 -> 593 | I59: =Statement!Z17 -> 748 | J59: =Statement!AA17 -> 1294
B60: Gross margin | C60: =Statement!T99 -> 0.32933579 | D60: =Statement!U99 -> 0.34924731 | E60: =Statement!V99 -> 0.35185185 | F60: =Statement!W99 -> 0.37397709 | G60: =Statement!X99 -> 0.39444656 | H60: =Statement!Y99 -> 0.41628319 | I60: =Statement!Z99 -> 0.46497429 | J60: =Statement!AA99 -> 0.52300909
B61: Operating margin | C61: =Statement!T100 -> 0.18588561 | D61: =Statement!U100 -> 0.20989247 | E61: =Statement!V100 -> 0.19953704 | F61: =Statement!W100 -> 0.23240589 | G61: =Statement!X100 -> 0.2639787 | H61: =Statement!Y100 -> 0.29840708 | I61: =Statement!Z100 -> 0.32069409 | J61: =Statement!AA100 -> 0.42959493
B62: Net margin | C62: =Statement!T101 -> 0.14068266 | D62: =Statement!U101 -> 0.14451613 | E62: =Statement!V101 -> 0.15740741 | F62: =Statement!W101 -> 0.19967267 | G62: =Statement!X101 -> 0.20882465 | H62: =Statement!Y101 -> 0.2099115 | I62: =Statement!Z101 -> 0.2403599 | J62: =Statement!AA101 -> 0.35657206
B63: ="Revenue "&Statement!B185 -> Revenue Datacenter | C63: =Statement!T185 -> 1582 | D63: =Statement!U185 -> 1736 | E63: =Statement!V185 -> 1615 | F63: =Statement!W185 -> 1863 | G63: =Statement!X185 -> 2114 | H63: =Statement!Y185 -> 2224 | I63: =Statement!Z185 -> 2500 | J63: =Statement!AA185 -> 2933
B64: ="Revenue "&Statement!B186 -> Revenue Edge & IoT | C64: =Statement!T186 -> 585 | D64: =Statement!U186 -> 589 | E64: =Statement!V186 -> 545 | F64: =Statement!W186 -> 581 | G64: =Statement!X186 -> 515 | H64: =Statement!Y186 -> 601 | I64: =Statement!Z186 -> 612 | J64: =Statement!AA186 -> 697
B65: FCFE | C65: =Statement!T155 -> -11 | D65: =Statement!U155 -> 101 | E65: =Statement!V155 -> 162 | F65: =Statement!W155 -> 366 | G65: =Statement!X155 -> 375 | H65: =Statement!Y155 -> 554 | I65: =Statement!Z155 -> 899 | J65: =Statement!AA155 -> 1064

Sheet Forecast ->
H5: Links
H6: Overview'!B3
H7: Financials ->'!B13
H8: Analysis ->'!B13
H9: Forecast ->'!B13
H10: Valuation ->'!B13
B13: Forecast ->

Sheet Revenue
B1: Revenue forecast
C2: History | H2: Forecast | S2: History | AA2: Forecast | AE2: TTM
C4: Revenues | S4: Revenues
B5: Revenues (thousand) | C5: =Statement!M3 -> 2022 | D5: =Statement!N3 -> 2023 | E5: =Statement!O3 -> 2024 | F5: =Statement!P3 -> 2025 | G5: =Statement!Q3 -> 2026 | H5: =G5+1 -> 2027 | I5: =H5+1 -> 2028 | J5: =I5+1 -> 2029 | K5: =J5+1 -> 2030 | L5: =K5+1 -> 2031 | R5: =B5 -> Revenues (thousand) | S5: =Statement!T3 -> Q1 2025 | T5: =Statement!U3 -> Q2 2025 | U5: =Statement!V3 -> Q3 2025 | V5: =Statement!W3 -> Q4 2025 | W5: =Statement!X3 -> Q1 2026 | X5: =Statement!Y3 -> Q2 2026 | Y5: =Statement!Z3 -> Q3 2026 | Z5: =Statement!AA3 -> Q4 2026 | AA5: FQ1 | AB5: FQ2 | AC5: FQ3 | AE5: FQ1
B6: =Statement!B185 -> Datacenter | C6: =Statement!M185 -> 0 | D6: =Statement!N185 -> 0 | E6: =Statement!O185 -> 0 | F6: =Statement!P185 -> 6796 | G6: =Statement!Q185 -> 9771 | H6: =H19*H20 -> 13366.728 | I6: =I19*I20 -> 17543.831 | J6: =J19*J20 -> 18333.303 | K6: =K19*K20 -> 17416.638 | L6: =L19*L20 -> 14891.225 | N6: Nearline exabytes * price per exabyte | Q6: Nearline exabytes * price per exabyte | R6: =B6 -> Datacenter | S6: =Statement!T185 -> 1582 | T6: =Statement!U185 -> 1736 | U6: =Statement!V185 -> 1615 | V6: =Statement!W185 -> 1863 | W6: =Statement!X185 -> 2114 | X6: =Statement!Y185 -> 2224 | Y6: =Statement!Z185 -> 2500 | Z6: =Statement!AA185 -> 2933 | AA6: =AA19*AA20 -> 3262.6692 | AE6: =SUM(X6:AA6) -> 10919.669
B7: =Statement!B186 -> Edge & IoT | C7: =Statement!M186 -> 0 | D7: =Statement!N186 -> 0 | E7: =Statement!O186 -> 0 | F7: =Statement!P186 -> 2300 | G7: =Statement!Q186 -> 2425 | H7: =G7*(1+H13) -> 2788.75 | I7: =H7*(1+I13) -> 3346.5 | J7: =I7*(1+J13) -> 3681.15 | K7: =J7*(1+K13) -> 3865.2075 | L7: =K7*(1+L13) -> 3478.6868 | N7: Edge & IoT Growth Rate | Q7: Edge & IoT Growth Rate | R7: =B7 -> Edge & IoT | S7: =Statement!T186 -> 585 | T7: =Statement!U186 -> 589 | U7: =Statement!V186 -> 545 | V7: =Statement!W186 -> 581 | W7: =Statement!X186 -> 515 | X7: =Statement!Y186 -> 601 | Y7: =Statement!Z186 -> 612 | Z7: =Statement!AA186 -> 697 | AA7: =Z7*(1+AA13) -> 738.82 | AE7: =SUM(X7:AA7) -> 2648.82
B8: Total | C8: =Statement!M5 -> 11661 | D8: =Statement!N5 -> 7384 | E8: =Statement!O5 -> 6551 | F8: =Statement!P5 -> 9097 | G8: =Statement!Q5 -> 12195 | H8: =SUM(H6:H7) -> 16155.478 | I8: =SUM(I6:I7) -> 20890.331 | J8: =SUM(J6:J7) -> 22014.453 | K8: =SUM(K6:K7) -> 21281.845 | L8: =SUM(L6:L7) -> 18369.912 | R8: Total | S8: =Statement!T5 -> 2168 | T8: =Statement!U5 -> 2325 | U8: =Statement!V5 -> 2160 | V8: =Statement!W5 -> 2444 | W8: =Statement!X5 -> 2629 | X8: =Statement!Y5 -> 2825 | Y8: =Statement!Z5 -> 3112 | Z8: =Statement!AA5 -> 3629 | AA8: =SUM(AA6:AA7) -> 4001.4892 | AE8: =SUM(X8:AA8) -> 13567.489
C10: Growth rates | S10: Growth rates
B11: Revenue growth % | C11: =C5 -> 2022 | D11: =D5 -> 2023 | E11: =E5 -> 2024 | F11: =F5 -> 2025 | G11: =G5 -> 2026 | H11: =H5 -> 2027 | I11: =I5 -> 2028 | J11: =J5 -> 2029 | ... L11: =L5 -> 2031 | R11: Revenue growth % | S11: =S5 -> Q1 2025 | T11: =T5 -> Q2 2025 | U11: =U5 -> Q3 2025 | V11: =V5 -> Q4 2025 | W11: =W5 -> Q1 2026 | X11: =X5 -> Q2 2026 | Y11: =Y5 -> Q3 2026 | Z11: =Z5 -> Q4 2026 | ... AC11: =AC5 -> FQ3
B12: =B6 -> Datacenter | D12: =D6/C6-1 -> #DIV/0! | E12: =E6/D6-1 -> #DIV/0! | F12: =F6/E6-1 -> #DIV/0! | G12: =G6/F6-1 -> 0.4377575 | H12: =H6/G6-1 -> 0.368 | I12: =I6/H6-1 -> 0.3125 | J12: =J6/I6-1 -> 0.045 | K12: =K6/J6-1 -> -0.05 | L12: =L6/K6-1 -> -0.145 | R12: =R6 -> Datacenter | T12: =T6/S6-1 -> 0.097345133 | U12: =U6/T6-1 -> -0.069700461 | V12: =V6/U6-1 -> 0.15356037 | W12: =W6/V6-1 -> 0.13472893 | X12: =X6/W6-1 -> 0.052034059 | Y12: =Y6/X6-1 -> 0.12410072 | Z12: =Z6/Y6-1 -> 0.1732 | AA12: =AA6/Z6-1 -> 0.1124
B13: =B7 -> Edge & IoT | D13: =D7/C7-1 -> #DIV/0! | E13: =E7/D7-1 -> #DIV/0! | F13: =F7/E7-1 -> #DIV/0! | G13: =G7/F7-1 -> 0.054347826 | H13: 0.15 | I13: 0.2 | J13: 0.1 | K13: 0.05 | L13: -0.1 | R13: =R7 -> Edge & IoT | T13: =T7/S7-1 -> 0.0068376068 | U13: =U7/T7-1 -> -0.074702886 | V13: =V7/U7-1 -> 0.066055046 | W13: =W7/V7-1 -> -0.11359725 | X13: =X7/W7-1 -> 0.16699029 | Y13: =Y7/X7-1 -> 0.018302829 | Z13: =Z7/Y7-1 -> 0.13888889 | AA13: 0.06
B14: =B8 -> Total | D14: =D8/C8-1 -> -0.36677815 | E14: =E8/D8-1 -> -0.11281148 | F14: =F8/E8-1 -> 0.38864296 | G14: =G8/F8-1 -> 0.34055183 | H14: =H8/G8-1 -> 0.32476244 | I14: =I8/H8-1 -> 0.29308031 | J14: =J8/I8-1 -> 0.053810655 | K14: =K8/J8-1 -> -0.033278485 | L14: =L8/K8-1 -> -0.1368271 | R14: =R8 -> Total | T14: =T8/S8-1 -> 0.072416974 | U14: =U8/T8-1 -> -0.070967742 | V14: =V8/U8-1 -> 0.13148148 | W14: =W8/V8-1 -> 0.075695581 | X14: =X8/W8-1 -> 0.074553062 | Y14: =Y8/X8-1 -> 0.10159292 | Z14: =Z8/Y8-1 -> 0.16613111 | AA14: =AA8/Z8-1 -> 0.10264238
C17: Metrics | S17: Revenues
C18: =C5 -> 2022 | D18: =D5 -> 2023 | E18: =E5 -> 2024 | F18: =F5 -> 2025 | G18: =G5 -> 2026 | H18: =H5 -> 2027 | I18: =I5 -> 2028 | J18: =J5 -> 2029 | ... L18: =L5 -> 2031 | S18: =S5 -> Q1 2025 | T18: =T5 -> Q2 2025 | U18: =U5 -> Q3 2025 | V18: =V5 -> Q4 2025 | W18: =W5 -> Q1 2026 | X18: =X5 -> Q2 2026 | Y18: =Y5 -> Q3 2026 | Z18: =Z5 -> Q4 2026 | ... AC18: =AC5 -> FQ3 | AE18: =AE5 -> FQ1
B19: =Statement!B206&" exabytes" -> Nearline exabytes | C19: =Statement!M206 -> 0 | D19: =Statement!N206 -> 0 | E19: =Statement!O206 -> 0 | F19: =Statement!P206 -> 496.6 | G19: =Statement!Q206 -> 695 | H19: =G19*(1+H21) -> 834 | I19: =H19*(1+I21) -> 1042.5 | J19: =I19*(1+J21) -> 1146.75 | K19: =J19*(1+K21) -> 1146.75 | L19: =K19*(1+L21) -> 1032.075 | N19: Nearline exabytes growth rate | Q19: Nearline exabytes growth rate | R19: =B19 -> Nearline exabytes | S19: =Statement!T206 -> 114 | T19: =Statement!U206 -> 126 | U19: =Statement!V206 -> 119.6 | V19: =Statement!W206 -> 137 | W19: =Statement!X206 -> 159 | X19: =Statement!Y206 -> 165 | Y19: =Statement!Z206 -> 175.4 | Z19: =Statement!AA206 -> 195 | AA19: =Z19*(1+AA21) -> 210.6 | AE19: =SUM(X19:AA19) -> 746
B20: =Statement!B209 -> Price per Exabyte | C20: =Statement!M209 -> #DIV/0! | D20: =Statement!N209 -> #DIV/0! | E20: =Statement!O209 -> #DIV/0! | F20: =Statement!P209 -> 13.685058 | G20: =Statement!Q209 -> 14.058993 | H20: =G20*(1+H22) -> 16.027252 | I20: =H20*(1+I22) -> 16.828614 | J20: =I20*(1+J22) -> 15.987184 | K20: =J20*(1+K22) -> 15.187824 | L20: =K20*(1+L22) -> 14.428433 | N20: Price per exabyte growth rate | Q20: Price per exabyte growth rate | R20: =B20 -> Price per Exabyte | S20: =Statement!T209 -> 13.877193 | T20: =Statement!U209 -> 13.777778 | U20: =Statement!V209 -> 13.503344 | V20: =Statement!W209 -> 13.59854 | W20: =Statement!X209 -> 13.295597 | X20: =Statement!Y209 -> 13.478788 | Y20: =Statement!Z209 -> 14.253136 | Z20: =Statement!AA209 -> 15.041026 | AA20: =Z20*(1+AA22) -> 15.492256 | AE20: =AE6/AE19 -> 14.637626
B21: =B19&" growth" -> Nearline exabytes growth | D21: =D19/C19-1 -> #DIV/0! | E21: =E19/D19-1 -> #DIV/0! | F21: =F19/E19-1 -> #DIV/0! | G21: =G19/F19-1 -> 0.39951671 | H21: 0.2 | I21: 0.25 | J21: 0.1 | K21: 0 | L21: -0.1 | R21: =R19&" growth" -> Nearline exabytes growth | T21: =T19/S19-1 -> 0.10526316 | U21: =U19/T19-1 -> -0.050793651 | V21: =V19/U19-1 -> 0.14548495 | W21: =W19/V19-1 -> 0.16058394 | X21: =X19/W19-1 -> 0.037735849 | Y21: =Y19/X19-1 -> 0.063030303 | Z21: =Z19/Y19-1 -> 0.11174458 | AA21: 0.08
B22: =B20&" growth" -> Price per Exabyte growth | D22: =D20/C20-1 -> #DIV/0! | E22: =E20/D20-1 -> #DIV/0! | F22: =F20/E20-1 -> #DIV/0! | G22: =G20/F20-1 -> 0.027324283 | H22: 0.14 | I22: 0.05 | J22: -0.05 | K22: -0.05 | L22: -0.05 | R22: =R20&" growth" -> Price per Exabyte growth | T22: =T20/S20-1 -> -0.0071639275 | U22: =U20/T20-1 -> -0.019918546 | V22: =V20/U20-1 -> 0.0070497842 | W22: =W20/V20-1 -> -0.022277587 | X22: =X20/W20-1 -> 0.013778275 | Y22: =Y20/X20-1 -> 0.057449365 | Z22: =Z20/Y20-1 -> 0.055278359 | AA22: 0.03

Sheet COGS & OpEx
B1: COGS & OpEx forecast
C2: History | H2: Forecast | P2: History | X2: Forecast | AB2: TTM
C4: Revenues | P4: Revenues
B5: =Revenue!B5 -> Revenues (thousand) | C5: =Revenue!C5 -> 2022 | D5: =Revenue!D5 -> 2023 | E5: =Revenue!E5 -> 2024 | F5: =Revenue!F5 -> 2025 | G5: =Revenue!G5 -> 2026 | H5: =G5+1 -> 2027 | I5: =H5+1 -> 2028 | J5: =I5+1 -> 2029 | K5: =J5+1 -> 2030 | L5: =K5+1 -> 2031 | O5: Revenues (thousand) | P5: =Revenue!S5 -> Q1 2025 | Q5: =Revenue!T5 -> Q2 2025 | R5: =Revenue!U5 -> Q3 2025 | S5: =Revenue!V5 -> Q4 2025 | T5: =Revenue!W5 -> Q1 2026 | U5: =Revenue!X5 -> Q2 2026 | V5: =Revenue!Y5 -> Q3 2026 | W5: =Revenue!Z5 -> Q4 2026 | X5: FQ1 | Y5: FQ2 | Z5: FQ3 | AB5: =Revenue!AE5 -> FQ1
B6: Revenue | C6: =Revenue!C8 -> 11661 | D6: =Revenue!D8 -> 7384 | E6: =Revenue!E8 -> 6551 | F6: =Revenue!F8 -> 9097 | G6: =Revenue!G8 -> 12195 | H6: =Revenue!H8 -> 16155.478 | I6: =Revenue!I8 -> 20890.331 | J6: =Revenue!J8 -> 22014.453 | ... L6: =Revenue!L8 -> 18369.912 | O6: Revenue | P6: =Revenue!S8 -> 2168 | Q6: =Revenue!T8 -> 2325 | R6: =Revenue!U8 -> 2160 | S6: =Revenue!V8 -> 2444 | T6: =Revenue!W8 -> 2629 | U6: =Revenue!X8 -> 2825 | V6: =Revenue!Y8 -> 3112 | W6: =Revenue!Z8 -> 3629 | X6: =Revenue!AA8 -> 4001.4892 | AB6: =Revenue!AE8 -> 13567.489
C9: COGS and OpEx | P9: COGS & OpEx | AB9: =AB4 -> 0
B10: Expenses (tnousand) | C10: =C5 -> 2022 | D10: =D5 -> 2023 | E10: =E5 -> 2024 | F10: =F5 -> 2025 | G10: =G5 -> 2026 | H10: =H5 -> 2027 | I10: =I5 -> 2028 | J10: =J5 -> 2029 | ... L10: =L5 -> 2031 | O10: Expenses (thousand) | P10: =P5 -> Q1 2025 | Q10: =Q5 -> Q2 2025 | R10: =R5 -> Q3 2025 | S10: =S5 -> Q4 2025 | T10: =T5 -> Q1 2026 | U10: =U5 -> Q2 2026 | V10: =V5 -> Q3 2026 | W10: =W5 -> Q4 2026 | ... Z10: =Z5 -> FQ3 | AB10: =AB5 -> FQ1
B11: COGS | C11: =Statement!M6 -> 8192 | D11: =Statement!N6 -> 6033 | E11: =Statement!O6 -> 5015 | F11: =Statement!P6 -> 5897 | G11: =Statement!Q6 -> 6637 | H11: =H6*H19 -> 8885.5129 | I11: =I6*I19 -> 10027.359 | J11: =J6*J19 -> 10346.793 | K11: =K6*K19 -> 10428.104 | L11: =L6*L19 -> 10103.452 | O11: =B11 -> COGS | P11: =Statement!T6 -> 1454 | Q11: =Statement!U6 -> 1513 | R11: =Statement!V6 -> 1400 | S11: =Statement!W6 -> 1530 | T11: =Statement!X6 -> 1592 | U11: =Statement!Y6 -> 1649 | V11: =Statement!Z6 -> 1665 | W11: =Statement!AA6 -> 1731 | X11: =X6*X19 -> 1800.6701 | AB11: =SUM(U11:X11) -> 6845.6701
B12: =Statement!B8 -> R&D | C12: =Statement!M8 -> 941 | D12: =Statement!N8 -> 797 | E12: =Statement!O8 -> 654 | F12: =Statement!P8 -> 724 | G12: =Statement!Q8 -> 755 | H12: =H6*H20 -> 1130.8835 | I12: =I6*I20 -> 1671.2264 | J12: =J6*J20 -> 1981.3008 | K12: =K6*K20 -> 1915.3661 | L12: =L6*L20 -> 1836.9912 | O12: =B12 -> R&D | P12: =Statement!T8 -> 181 | Q12: =Statement!U8 -> 184 | R12: =Statement!V8 -> 180 | S12: =Statement!W8 -> 179 | T12: =Statement!X8 -> 186 | U12: =Statement!Y8 -> 187 | V12: =Statement!Z8 -> 194 | W12: =Statement!AA8 -> 188 | X12: =X20*X$6 -> 200.07446 | AB12: =SUM(U12:X12) -> 769.07446
B13: =Statement!B9 -> SG&A | C13: =Statement!M9 -> 559 | D13: =Statement!N9 -> 491 | E13: =Statement!O9 -> 460 | F13: =Statement!P9 -> 561 | G13: =Statement!Q9 -> 577 | H13: =H6*H21 -> 726.99651 | I13: =I6*I21 -> 1044.5165 | J13: =J6*J21 -> 1320.8672 | K13: =K6*K21 -> 1702.5476 | L13: =L6*L21 -> 2020.6903 | O13: =B13 -> SG&A | P13: =Statement!T9 -> 129 | Q13: =Statement!U9 -> 139 | R13: =Statement!V9 -> 139 | S13: =Statement!W9 -> 154 | T13: =Statement!X9 -> 144 | U13: =Statement!Y9 -> 143 | V13: =Statement!Z9 -> 143 | W13: =Statement!AA9 -> 147 | X13: =X21*X$6 -> 160.05957 | AB13: =SUM(U13:X13) -> 593.05957
B14: OpEx | C14: =Statement!M10 -> 1514 | D14: =Statement!N10 -> 1693 | E14: =Statement!O10 -> 1084 | F14: =Statement!P10 -> 1310 | G14: =Statement!Q10 -> 1464 | H14: =SUM(H12:H13) -> 1857.88 | I14: =SUM(I12:I13) -> 2715.743 | J14: =SUM(J12:J13) -> 3302.1679 | K14: =SUM(K12:K13) -> 3617.9137 | L14: =SUM(L12:L13) -> 3857.6815 | O14: =B14 -> OpEx | P14: =Statement!T10 -> 311 | Q14: =Statement!U10 -> 324 | R14: =Statement!V10 -> 329 | S14: =Statement!W10 -> 346 | T14: =Statement!X10 -> 343 | U14: =Statement!Y10 -> 333 | V14: =Statement!Z10 -> 449 | W14: =Statement!AA10 -> 339 | X14: =SUM(X12:X13) -> 360.13403 | AB14: =SUM(U14:X14) -> 1481.134
C17: Expenses % of Revenue | P17: Expenses % of Revenue
B18: % of revenue | C18: =C5 -> 2022 | D18: =D5 -> 2023 | E18: =E5 -> 2024 | F18: =F5 -> 2025 | G18: =G5 -> 2026 | H18: =H5 -> 2027 | I18: =I5 -> 2028 | J18: =J5 -> 2029 | ... L18: =L5 -> 2031 | O18: % of revenue | P18: =P5 -> Q1 2025 | Q18: =Q5 -> Q2 2025 | R18: =R5 -> Q3 2025 | S18: =S5 -> Q4 2025 | T18: =T5 -> Q1 2026 | U18: =U5 -> Q2 2026 | V18: =V5 -> Q3 2026 | W18: =W5 -> Q4 2026 | ... Z18: =Z5 -> FQ3
B19: =B11 -> COGS | C19: =C11/C$6 -> 0.70251265 | D19: =D11/D$6 -> 0.81703684 | E19: =E11/E$6 -> 0.76553198 | F19: =F11/F$6 -> 0.64823568 | G19: =G11/G$6 -> 0.54423944 | H19: 0.55 | I19: 0.48 | J19: 0.47 | K19: 0.49 | L19: 0.55 | O19: =O11 -> COGS | P19: =P11/P$6 -> 0.67066421 | Q19: =Q11/Q$6 -> 0.65075269 | R19: =R11/R$6 -> 0.64814815 | S19: =S11/S$6 -> 0.62602291 | T19: =T11/T$6 -> 0.60555344 | U19: =U11/U$6 -> 0.58371681 | V19: =V11/V$6 -> 0.53502571 | W19: =W11/W$6 -> 0.47699091 | X19: 0.45
B20: =B12 -> R&D | C20: =C12/C$6 -> 0.080696338 | D20: =D12/D$6 -> 0.10793608 | E20: =E12/E$6 -> 0.099832087 | F20: =F12/F$6 -> 0.079586677 | G20: =G12/G$6 -> 0.061910619 | H20: 0.07 | I20: 0.08 | J20: 0.09 | K20: 0.09 | L20: 0.1 | O20: =O12 -> R&D | P20: =P12/P$6 -> 0.083487085 | Q20: =Q12/Q$6 -> 0.079139785 | R20: =R12/R$6 -> 0.083333333 | S20: =S12/S$6 -> 0.073240589 | T20: =T12/T$6 -> 0.070749334 | U20: =U12/U$6 -> 0.06619469 | V20: =V12/V$6 -> 0.062339332 | W20: =W12/W$6 -> 0.051804905 | X20: 0.05
B21: =B13 -> SG&A | C21: =C13/C$6 -> 0.04793757 | D21: =D13/D$6 -> 0.066495125 | E21: =E13/E$6 -> 0.070218287 | F21: =F13/F$6 -> 0.061668682 | G21: =G13/G$6 -> 0.047314473 | H21: 0.045 | I21: 0.05 | J21: 0.06 | K21: 0.08 | L21: 0.11 | O21: =O13 -> SG&A | P21: =P13/P$6 -> 0.059501845 | Q21: =Q13/Q$6 -> 0.059784946 | R21: =R13/R$6 -> 0.064351852 | S21: =S13/S$6 -> 0.063011457 | T21: =T13/T$6 -> 0.054773678 | U21: =U13/U$6 -> 0.050619469 | V21: =V13/V$6 -> 0.045951157 | W21: =W13/W$6 -> 0.040507027 | X21: 0.04
B22: =B14 -> OpEx | C22: =C14/C$6 -> 0.12983449 | D22: =D14/D$6 -> 0.22927952 | E22: =E14/E$6 -> 0.16547092 | F22: =F14/F$6 -> 0.14400352 | G22: =G14/G$6 -> 0.1200492 | H22: =H14/H$6 -> 0.115 | I22: =I14/I$6 -> 0.13 | J22: =J14/J$6 -> 0.15 | ... L22: =L14/L$6 -> 0.21 | O22: =O14 -> OpEx | P22: =P14/P$6 -> 0.14345018 | Q22: =Q14/Q$6 -> 0.13935484 | R22: =R14/R$6 -> 0.15231481 | S22: =S14/S$6 -> 0.14157119 | T22: =T14/T$6 -> 0.13046786 | U22: =U14/U$6 -> 0.11787611 | V22: =V14/V$6 -> 0.14428021 | W22: =W14/W$6 -> 0.093414164 | X22: =X14/X$6 -> 0.09

Sheet WC & Investments
B1: Working Capital, Capex, D&A
C3: History | H3: Forecast
C5: Revenues
B6: Revenues (thousand) | C6: =Revenue!C5 -> 2022 | D6: =Revenue!D5 -> 2023 | E6: =Revenue!E5 -> 2024 | F6: =Revenue!F5 -> 2025 | G6: =Revenue!G5 -> 2026 | H6: =G6+1 -> 2027 | I6: =H6+1 -> 2028 | J6: =I6+1 -> 2029 | K6: =J6+1 -> 2030 | L6: =K6+1 -> 2031
B7: Revenue | C7: =Revenue!C8 -> 11661 | D7: =Revenue!D8 -> 7384 | E7: =Revenue!E8 -> 6551 | F7: =Revenue!F8 -> 9097 | G7: =Revenue!G8 -> 12195 | H7: =Revenue!H8 -> 16155.478 | I7: =Revenue!I8 -> 20890.331 | J7: =Revenue!J8 -> 22014.453 | ... L7: =Revenue!L8 -> 18369.912
B8: COGS | C8: ='COGS & OpEx'!C11 -> 8192 | D8: ='COGS & OpEx'!D11 -> 6033 | E8: ='COGS & OpEx'!E11 -> 5015 | F8: ='COGS & OpEx'!F11 -> 5897 | G8: ='COGS & OpEx'!G11 -> 6637 | H8: ='COGS & OpEx'!H11 -> 8885.5129 | I8: ='COGS & OpEx'!I11 -> 10027.359 | J8: ='COGS & OpEx'!J11 -> 10346.793 | ... L8: ='COGS & OpEx'!L11 -> 10103.452
C11: Working Capital
B12: $ (thousand) | C12: =C6 -> 2022 | D12: =D6 -> 2023 | E12: =E6 -> 2024 | F12: =F6 -> 2025 | G12: =G6 -> 2026 | H12: =H6 -> 2027 | I12: =I6 -> 2028 | J12: =J6 -> 2029 | ... L12: =L6 -> 2031
B13: Accounts receivable | C13: =Statement!M29 -> 1532 | D13: =Statement!N29 -> 621 | E13: =Statement!O29 -> 429 | F13: =Statement!P29 -> 959 | G13: =Statement!Q29 -> 1534 | H13: =H20*H7/365 -> 1770.4633 | I13: =I20*I7/365 -> 2289.3513 | J13: =J20*J7/365 -> 2412.5428 | K13: =K20*K7/365 -> 2332.257 | L13: =L20*L7/365 -> 2013.141
B14: Inventory | C14: =Statement!M30 -> 1565 | D14: =Statement!N30 -> 1140 | E14: =Statement!O30 -> 1239 | F14: =Statement!P30 -> 1440 | G14: =Statement!Q30 -> 1571 | H14: =H21*H8/365 -> 1923.1658 | I14: =I21*I8/365 -> 2170.305 | J14: =J21*J8/365 -> 2239.4428 | K14: =K21*K8/365 -> 2257.0417 | L14: =L21*L8/365 -> 2186.7745
B15: Accounts payable | C15: =Statement!M37 -> 2058 | D15: =Statement!N37 -> 1603 | E15: =Statement!O37 -> 1786 | F15: =Statement!P37 -> 1604 | G15: =Statement!Q37 -> 1748 | H15: =H22*H8/365 -> 2312.6677 | I15: =I22*I8/365 -> 2609.8605 | J15: =J22*J8/365 -> 2693.0009 | K15: =K22*K8/365 -> 2714.1641 | L15: =L22*L8/365 -> 2629.6655
C18: WC metrics and drivers
B19: Days | C19: =C6 -> 2022 | D19: =D6 -> 2023 | E19: =E6 -> 2024 | F19: =F6 -> 2025 | G19: =G6 -> 2026 | H19: =H6 -> 2027 | I19: =I6 -> 2028 | J19: =J6 -> 2029 | ... L19: =L6 -> 2031
B20: DSO | C20: =C13/C7*365 -> 47.953006 | D20: =D13/D7*365 -> 30.696777 | E20: =E13/E7*365 -> 23.902458 | F20: =F13/F7*365 -> 38.47807 | G20: =G13/G7*365 -> 45.913079 | H20: 40 | I20: 40 | J20: 40 | K20: 40 | L20: 40
B21: DIO | C21: =C14/C8*365 -> 69.729614 | D21: =D14/D8*365 -> 68.970661 | E21: =E14/E8*365 -> 90.176471 | F21: =F14/F8*365 -> 89.130066 | G21: =G14/G8*365 -> 86.396715 | H21: 79 | I21: 79 | J21: 79 | K21: 79 | L21: 79
B22: DPO | C22: =C15/C8*365 -> 91.695557 | D22: =D15/D8*365 -> 96.98243 | E22: =E15/E8*365 -> 129.98804 | F22: =F15/F8*365 -> 99.28099 | G22: =G15/G8*365 -> 96.130782 | H22: 95 | I22: 95 | J22: 95 | K22: 95 | L22: 95
B23: Net trade cycle | C23: =C20+C21-C22 -> 25.987063 | D23: =D20+D21-D22 -> 2.6850082 | E23: =E20+E21-E22 -> -15.909108 | F23: =F20+F21-F22 -> 28.327145 | G23: =G20+G21-G22 -> 36.179013 | H23: =H20+H21-H22 -> 24 | I23: =I20+I21-I22 -> 24 | J23: =J20+J21-J22 -> 24 | ... L23: =L20+L21-L22 -> 24
C26: Change in SIP NWC
B27: $ (thousand) | C27: =C6 -> 2022 | D27: =D6 -> 2023 | E27: =E6 -> 2024 | F27: =F6 -> 2025 | G27: =G6 -> 2026 | H27: =H6 -> 2027 | I27: =I6 -> 2028 | J27: =J6 -> 2029 | ... L27: =L6 -> 2031
B28: Change in acc receivable | C28: =Statement!M54 -> -374 | D28: =Statement!N54 -> 911 | E28: =Statement!O54 -> 192 | F28: =Statement!P54 -> -513 | G28: =Statement!Q54 -> -575 | H28: =-(H13-G13) -> -236.46334 | I28: =-(I13-H13) -> -518.88795 | J28: =-(J13-I13) -> -123.19149 | K28: =-(K13-J13) -> 80.285769 | L28: =-(L13-K13) -> 319.11597
B29: Change in inventory | C29: =Statement!M55 -> -361 | D29: =Statement!N55 -> 425 | E29: =Statement!O55 -> -99 | F29: =Statement!P55 -> -201 | G29: =Statement!Q55 -> -131 | H29: =-(H14-G14) -> -352.16581 | I29: =-(I14-H14) -> -247.13921 | J29: =-(J14-I14) -> -69.137815 | K29: =-(K14-J14) -> -17.598887 | L29: =-(L14-K14) -> 70.267266
B30: Change in acc payable | C30: =Statement!M56 -> 228 | D30: =Statement!N56 -> -421 | E30: =Statement!O56 -> 227 | F30: =Statement!P56 -> -242 | G30: =Statement!Q56 -> 66 | H30: =H15-G15 -> 564.66774 | I30: =I15-H15 -> 297.19273 | J30: =J15-I15 -> 83.140411 | K30: =K15-J15 -> 21.163218 | L30: =L15-K15 -> -84.498611
C33: Total change in NWC and less SIP
B34: $ (thousand) | C34: =C6 -> 2022 | D34: =D6 -> 2023 | E34: =E6 -> 2024 | F34: =F6 -> 2025 | G34: =G6 -> 2026 | H34: =H6 -> 2027 | I34: =I6 -> 2028 | J34: =J6 -> 2029 | ... L34: =L6 -> 2031
B35: Total change in NWC | C35: =Statement!M54+Statement!M55+Statement!M56+Statement!M57 -> -643 | D35: =Statement!N54+Statement!N55+Statement!N56+Statement!N57 -> 1162 | E35: =Statement!O54+Statement!O55+Statement!O56+Statement!O57 -> 386 | F35: =Statement!P54+Statement!P55+Statement!P56+Statement!P57 -> -965 | G35: =Statement!Q54+Statement!Q55+Statement!Q56+Statement!Q57 -> -159 | H35: =H36+H28+H29+H30 -> 299.14815 | I35: =I36+I28+I29+I30 -> -51.027823 | J35: =J36+J28+J29+J30 -> 331.10016 | K35: =K36+K28+K29+K30 -> 509.48701 | L35: =L36+L28+L29+L30 -> 672.28286
B36: Change in NWC less SIP | C36: =C35-C28-C29-C30 -> -136 | D36: =D35-D28-D29-D30 -> 247 | E36: =E35-E28-E29-E30 -> 66 | F36: =F35-F28-F29-F30 -> -9 | G36: =G35-G28-G29-G30 -> 481 | H36: =H7*H37 -> 323.10956 | I36: =I7*I37 -> 417.80661 | J36: =J7*J37 -> 440.28906 | K36: =K7*K37 -> 425.6369 | L36: =L7*L37 -> 367.39824
B37: % of revenue | C37: =C36/C7 -> -0.011662808 | D37: =D36/D7 -> 0.033450704 | E37: =E36/E7 -> 0.010074798 | F37: =F36/F7 -> -0.00098933714 | G37: =G36/G7 -> 0.039442394 | H37: 0.02 | I37: 0.02 | J37: 0.02 | K37: 0.02 | L37: 0.02
C40: Investments
B41: $ (thousand) | C41: =C6 -> 2022 | D41: =D6 -> 2023 | E41: =E6 -> 2024 | F41: =F6 -> 2025 | G41: =G6 -> 2026 | H41: =H6 -> 2027 | I41: =I6 -> 2028 | J41: =J6 -> 2029 | ... L41: =L6 -> 2031
B42: D&A | C42: =Statement!M52 -> 451 | D42: =Statement!N52 -> 513 | E42: =Statement!O52 -> 264 | F42: =Statement!P52 -> 251 | G42: =Statement!Q52 -> 276 | H42: =H7*H43 -> 484.66434 | I42: =I7*I43 -> 626.70992 | J42: =J7*J43 -> 660.43359 | K42: =K7*K43 -> 638.45536 | L42: =L7*L43 -> 551.09736
B43: % of Revenue | C43: =C42/C7 -> 0.038675928 | D43: =D42/D7 -> 0.06947454 | E43: =E42/E7 -> 0.040299191 | F43: =F42/F7 -> 0.027591514 | G43: =G42/G7 -> 0.022632226 | H43: 0.03 | I43: 0.03 | J43: 0.03 | K43: 0.03 | L43: 0.03
B44: % of CapEx | C44: =C42/C45 -> 1.183727 | D44: =D42/D45 -> 1.6234177 | E44: =E42/E45 -> 1.0393701 | F44: =F42/F45 -> 0.94716981 | G44: =G42/G45 -> 0.48506151 | H44: =H42/H45 -> 0.66666667 | I44: =I42/I45 -> 0.66666667 | J44: =J42/J45 -> 0.66666667 | ... L44: =L42/L45 -> 0.66666667
B45: CapEx | C45: =-Statement!M108 -> 381 | D45: =-Statement!N108 -> 316 | E45: =-Statement!O108 -> 254 | F45: =-Statement!P108 -> 265 | G45: =-Statement!Q108 -> 569 | H45: =H7*H46 -> 726.99651 | I45: =I7*I46 -> 940.06487 | J45: =J7*J46 -> 990.65038 | K45: =K7*K46 -> 957.68304 | L45: =L7*L46 -> 826.64604
B46: % of Revenue | C46: =C45/C7 -> 0.032673013 | D46: =D45/D7 -> 0.042795233 | E46: =E45/E7 -> 0.038772706 | F46: =F45/F7 -> 0.029130483 | G46: =G45/G7 -> 0.046658467 | H46: 0.045 | I46: 0.045 | J46: 0.045 | K46: 0.045 | L46: 0.045

Sheet FCF & Other
B1: Results
C2: History | H2: Forecast
C4: Income statement
B5: $ (thousand) | C5: =Revenue!C5 -> 2022 | D5: =Revenue!D5 -> 2023 | E5: =Revenue!E5 -> 2024 | F5: =Revenue!F5 -> 2025 | G5: =Revenue!G5 -> 2026 | H5: =G5+1 -> 2027 | I5: =H5+1 -> 2028 | J5: =I5+1 -> 2029 | K5: =J5+1 -> 2030 | L5: =K5+1 -> 2031
B6: Revenue | C6: =Revenue!C8 -> 11661 | D6: =Revenue!D8 -> 7384 | E6: =Revenue!E8 -> 6551 | F6: =Revenue!F8 -> 9097 | G6: =Revenue!G8 -> 12195 | H6: =Revenue!H8 -> 16155.478 | I6: =Revenue!I8 -> 20890.331 | J6: =Revenue!J8 -> 22014.453 | ... L6: =Revenue!L8 -> 18369.912 | N6: From Revenue Sheet
B7: COGS | C7: ='COGS & OpEx'!C11 -> 8192 | D7: ='COGS & OpEx'!D11 -> 6033 | E7: ='COGS & OpEx'!E11 -> 5015 | F7: ='COGS & OpEx'!F11 -> 5897 | G7: ='COGS & OpEx'!G11 -> 6637 | H7: ='COGS & OpEx'!H11 -> 8885.5129 | I7: ='COGS & OpEx'!I11 -> 10027.359 | J7: ='COGS & OpEx'!J11 -> 10346.793 | ... L7: ='COGS & OpEx'!L11 -> 10103.452 | N7: From COGS and OpEx Sheet
B8: Gross profit | C8: =C6-C7 -> 3469 | D8: =D6-D7 -> 1351 | E8: =E6-E7 -> 1536 | F8: =F6-F7 -> 3200 | G8: =G6-G7 -> 5558 | H8: =H6-H7 -> 7269.9651 | I8: =I6-I7 -> 10862.972 | J8: =J6-J7 -> 11667.66 | ... L8: =L6-L7 -> 8266.4604
B9: OpEx | C9: ='COGS & OpEx'!C14 -> 1514 | D9: ='COGS & OpEx'!D14 -> 1693 | E9: ='COGS & OpEx'!E14 -> 1084 | F9: ='COGS & OpEx'!F14 -> 1310 | G9: ='COGS & OpEx'!G14 -> 1464 | H9: ='COGS & OpEx'!H14 -> 1857.88 | I9: ='COGS & OpEx'!I14 -> 2715.743 | J9: ='COGS & OpEx'!J14 -> 3302.1679 | ... L9: ='COGS & OpEx'!L14 -> 3857.6815 | N9: From COGS and OpEx Sheet
B10: EBIT | C10: =C8-C9 -> 1955 | D10: =D8-D9 -> -342 | E10: =E8-E9 -> 452 | F10: =F8-F9 -> 1890 | G10: =G8-G9 -> 4094 | H10: =H8-H9 -> 5412.0851 | I10: =I8-I9 -> 8147.2289 | J10: =J8-J9 -> 8365.4921 | ... L10: =L8-L9 -> 4408.7789
C13: Drivers
C14: =C5 -> 2022 | D14: =D5 -> 2023 | E14: =E5 -> 2024 | F14: =F5 -> 2025 | G14: =G5 -> 2026 | H14: =H5 -> 2027 | I14: =I5 -> 2028 | J14: =J5 -> 2029 | ... L14: =L5 -> 2031
B15: Tax rate | C15: =Statement!M82 -> 0.017867778 | D15: =Statement!N82 -> 0 | E15: =Statement!O82 -> 0.24719101 | F15: =Statement!P82 -> 0.029081295 | G15: =Statement!Q82 -> 0.13712737 | H15: =Overview!$C$26 -> 0.21 | I15: =Overview!$C$26 -> 0.21 | J15: =Overview!$C$26 -> 0.21 | K15: =Overview!$C$26 -> 0.21 | L15: =Overview!$C$26 -> 0.21 | N15: From Statements and Overview sheet
C18: Cash Flow Statement
B19: $ (thousand) | C19: =C5 -> 2022 | D19: =D5 -> 2023 | E19: =E5 -> 2024 | F19: =F5 -> 2025 | G19: =G5 -> 2026 | H19: =H5 -> 2027 | I19: =I5 -> 2028 | J19: =J5 -> 2029 | ... L19: =L5 -> 2031
B20: D&A | C20: ='WC & Investments'!C42 -> 451 | D20: ='WC & Investments'!D42 -> 513 | E20: ='WC & Investments'!E42 -> 264 | F20: ='WC & Investments'!F42 -> 251 | G20: ='WC & Investments'!G42 -> 276 | H20: ='WC & Investments'!H42 -> 484.66434 | I20: ='WC & Investments'!I42 -> 626.70992 | J20: ='WC & Investments'!J42 -> 660.43359 | ... L20: ='WC & Investments'!L42 -> 551.09736 | N20: From WC & Investments Sheet
B21: CapEx | C21: ='WC & Investments'!C45 -> 381 | D21: ='WC & Investments'!D45 -> 316 | E21: ='WC & Investments'!E45 -> 254 | F21: ='WC & Investments'!F45 -> 265 | G21: ='WC & Investments'!G45 -> 569 | H21: ='WC & Investments'!H45 -> 726.99651 | I21: ='WC & Investments'!I45 -> 940.06487 | J21: ='WC & Investments'!J45 -> 990.65038 | ... L21: ='WC & Investments'!L45 -> 826.64604 | N21: From WC & Investments Sheet
B22: Change in NWC | C22: ='WC & Investments'!C35 -> -643 | D22: ='WC & Investments'!D35 -> 1162 | E22: ='WC & Investments'!E35 -> 386 | F22: ='WC & Investments'!F35 -> -965 | G22: ='WC & Investments'!G35 -> -159 | H22: ='WC & Investments'!H35 -> 299.14815 | I22: ='WC & Investments'!I35 -> -51.027823 | J22: ='WC & Investments'!J35 -> 331.10016 | ... L22: ='WC & Investments'!L35 -> 672.28286 | N22: From WC & Investments Sheet
C25: FCFF
B26: $ (thousand) | C26: =C5 -> 2022 | D26: =D5 -> 2023 | E26: =E5 -> 2024 | F26: =F5 -> 2025 | G26: =G5 -> 2026 | H26: =H5 -> 2027 | I26: =I5 -> 2028 | J26: =J5 -> 2029 | ... L26: =L5 -> 2031
B27: NOPAT | C27: =C10*(1-C15) -> 1920.0685 | D27: =D10*(1-D15) -> -342 | E27: =E10*(1-E15) -> 340.26966 | F27: =F10*(1-F15) -> 1835.0364 | G27: =G10*(1-G15) -> 3532.6005 | H27: =H10*(1-H15) -> 4275.5473 | I27: =I10*(1-I15) -> 6436.3108 | J27: =J10*(1-J15) -> 6608.7388 | ... L27: =L10*(1-L15) -> 3482.9353
B28: FCFF | C28: =C27+C20-C21+C22 -> 1347.0685 | D28: =D27+D20-D21+D22 -> 1017 | E28: =E27+E20-E21+E22 -> 736.26966 | F28: =F27+F20-F21+F22 -> 856.03635 | G28: =G27+G20-G21+G22 -> 3080.6005 | H28: =H27+H20-H21+H22 -> 4332.3632 | I28: =I27+I20-I21+I22 -> 6071.928 | J28: =J27+J20-J21+J22 -> 6609.6221 | ... L28: =L27+L20-L21+L22 -> 3879.6695
C31: Margins
B32: % | C32: =C5 -> 2022 | D32: =D5 -> 2023 | E32: =E5 -> 2024 | F32: =F5 -> 2025 | G32: =G5 -> 2026 | H32: =H5 -> 2027 | I32: =I5 -> 2028 | J32: =J5 -> 2029 | ... L32: =L5 -> 2031
B33: Gross margin | C33: =Statement!M99 -> 0.29748735 | D33: =Statement!N99 -> 0.18296316 | E33: =Statement!O99 -> 0.23446802 | F33: =Statement!P99 -> 0.35176432 | G33: =Statement!Q99 -> 0.45576056 | H33: =H8/H6 -> 0.45 | I33: =I8/I6 -> 0.52 | J33: =J8/J6 -> 0.53 | K33: =K8/K6 -> 0.51 | L33: =L8/L6 -> 0.45
B34: Operating margin | C34: =Statement!M100 -> 0.16765286 | D34: =Statement!N100 -> -0.04631636 | E34: =Statement!O100 -> 0.0689971 | F34: =Statement!P100 -> 0.2077608 | G34: =Statement!Q100 -> 0.33571136 | H34: =H10/H6 -> 0.335 | I34: =I10/I6 -> 0.39 | J34: =J10/J6 -> 0.38 | K34: =K10/K6 -> 0.34 | L34: =L10/L6 -> 0.24

Sheet Valuation ->
H5: Links
H6: Overview'!B3
H7: Financials ->'!B13
H8: Analysis ->'!B13
H9: Forecast ->'!B13
H10: Valuation ->'!B13
B13: Valuation ->

Sheet WACC
B1: WACC
B4: Inputs
B5: Shares Outstanding | C5: =Statement!AC77 -> 237
B6: Price | C6: =Overview!C5 -> 676.77
B7: Equity | C7: =C5*C6 -> 160394.49
B8: Debt | C8: =Statement!AC106 -> 3565
B9: Risk free rate | C9: =Overview!F27 -> 0.04986
B10: Beta | C10: =Overview!C13 -> 2.1471
B11: Market risk premium | C11: =[1]Sheet1!$C$12 -> 0.045
B12: Tax rate | C12: =Overview!C26 -> 0.21
B13: Cost of debt | C13: =Overview!C27 -> 0.06
B15: Calculations
B16: Debt/(Debt+Equity) | C16: =C8/(C8+C7) -> 0.021743176
B17: Equity/(Debt+Equity) | C17: =C7/(C8+C7) -> 0.97825682
B18: Cost of debt with tax | C18: =C13*(1-C12) -> 0.0474
B19: Cost of equity | C19: =C9+C10*C11 -> 0.1464795
B20: WACC | C20: =(C17*C19)+(C16*C18) -> 0.1443252

Sheet DCF
B1: DCF
C3: History | H3: Forecast
C5: PV of FCF
B6: $ (thousand) | C6: =Revenue!C5 -> 2022 | D6: =Revenue!D5 -> 2023 | E6: =Revenue!E5 -> 2024 | F6: =Revenue!F5 -> 2025 | G6: =Revenue!G5 -> 2026 | H6: =Revenue!H5 -> 2027 | I6: =Revenue!I5 -> 2028 | J6: =Revenue!J5 -> 2029 | ... L6: =Revenue!L5 -> 2031
B7: FCFF | C7: ='FCF & Other'!C28 -> 1347.0685 | D7: ='FCF & Other'!D28 -> 1017 | E7: ='FCF & Other'!E28 -> 736.26966 | F7: ='FCF & Other'!F28 -> 856.03635 | G7: ='FCF & Other'!G28 -> 3080.6005 | H7: ='FCF & Other'!H28 -> 4332.3632 | I7: ='FCF & Other'!I28 -> 6071.928 | J7: ='FCF & Other'!J28 -> 6609.6221 | ... L7: ='FCF & Other'!L28 -> 3879.6695
B8: Perpetual cashflow | C8: 0 | D8: 0 | E8: 0 | F8: 0 | G8: 0 | H8: 0 | I8: 0 | J8: 0 | K8: 0 | L8: =L7*(1+C14)/(C15-C14) -> 30449.322
B9: Period | H9: 1 | I9: 2 | J9: 3 | K9: 4 | L9: 5
B10: PV of FCFF | H10: =H7/(1+$C$15)^H9 -> 3785.9546 | I10: =I7/(1+$C$15)^I9 -> 4636.8996 | J10: =J7/(1+$C$15)^J9 -> 4410.9105 | K10: =K7/(1+$C$15)^K9 -> 3444.5857 | L10: =L7/(1+$C$15)^L9 -> 1977.1855
B11: PV of Perpetual cashflow | L11: =L8/(1+C15)^L9 -> 15517.806
B13: Input parameters
B14: Perpetual growth | C14: 0.015
B15: WACC | C15: =IF(Overview!C28>0,Overview!C28,WACC!C20) -> 0.1443252
B18: Result
B19: Total PV of Unlevered FCF | C19: =SUM(H10:L10) -> 18255.536
B20: PV of Perpetual cashflow | C20: =L11 -> 15517.806
B21: Enterprise value | C21: =C19+C20 -> 33773.342
B22: (+) Cash | C22: =Statement!AC105 -> 1704
B23: (-) Debt | C23: =Statement!AC106 -> 3565
B24: Equity value | C24: =C21+C22-C23 -> 31912.342
B25: Shares outstanding | C25: =Statement!AC77 -> 237
B26: Price per share | C26: =C24/C25 -> 134.65123

Sheet Multiples
B1: Multiples valuations
C2: History | H2: Forecast
C4: Revenues, earnings cash
B5: Revenues (thousand) | C5: =Revenue!C5 -> 2022 | D5: =Revenue!D5 -> 2023 | E5: =Revenue!E5 -> 2024 | F5: =Revenue!F5 -> 2025 | G5: =Revenue!G5 -> 2026 | H5: =Revenue!H5 -> 2027 | I5: =Revenue!I5 -> 2028 | J5: =Revenue!J5 -> 2029 | ... L5: =Revenue!L5 -> 2031
B6: Revenue | C6: =Revenue!C8 -> 11661 | D6: =Revenue!D8 -> 7384 | E6: =Revenue!E8 -> 6551 | F6: =Revenue!F8 -> 9097 | G6: =Revenue!G8 -> 12195 | H6: =Revenue!H8 -> 16155.478 | I6: =Revenue!I8 -> 20890.331 | J6: =Revenue!J8 -> 22014.453 | ... L6: =Revenue!L8 -> 18369.912
B7: EBIT | C7: ='FCF & Other'!C10 -> 1955 | D7: ='FCF & Other'!D10 -> -342 | E7: ='FCF & Other'!E10 -> 452 | F7: ='FCF & Other'!F10 -> 1890 | G7: ='FCF & Other'!G10 -> 4094 | H7: ='FCF & Other'!H10 -> 5412.0851 | I7: ='FCF & Other'!I10 -> 8147.2289 | J7: ='FCF & Other'!J10 -> 8365.4921 | ... L7: ='FCF & Other'!L10 -> 4408.7789
B8: FCFF | C8: ='FCF & Other'!C28 -> 1347.0685 | D8: ='FCF & Other'!D28 -> 1017 | E8: ='FCF & Other'!E28 -> 736.26966 | F8: ='FCF & Other'!F28 -> 856.03635 | G8: ='FCF & Other'!G28 -> 3080.6005 | H8: ='FCF & Other'!H28 -> 4332.3632 | I8: ='FCF & Other'!I28 -> 6071.928 | J8: ='FCF & Other'!J28 -> 6609.6221 | ... L8: ='FCF & Other'!L28 -> 3879.6695
B9: PV of FCFF | H9: =DCF!H10 -> 3785.9546 | I9: =DCF!I10 -> 4636.8996 | J9: =DCF!J10 -> 4410.9105 | K9: =DCF!K10 -> 3444.5857 | L9: =DCF!L10 -> 1977.1855
C11: Growth rates
B12: % Growth | C12: =C5 -> 2022 | D12: =D5 -> 2023 | E12: =E5 -> 2024 | F12: =F5 -> 2025 | G12: =G5 -> 2026 | H12: =H5 -> 2027 | I12: =I5 -> 2028 | J12: =J5 -> 2029 | ... L12: =L5 -> 2031
B13: Revenue | D13: =(D6-C6)/C6 -> -0.36677815 | E13: =(E6-D6)/D6 -> -0.11281148 | F13: =(F6-E6)/E6 -> 0.38864296 | G13: =(G6-F6)/F6 -> 0.34055183 | H13: =(H6-G6)/G6 -> 0.32476244 | I13: =(I6-H6)/H6 -> 0.29308031 | J13: =(J6-I6)/I6 -> 0.053810655 | K13: =(K6-J6)/J6 -> -0.033278485 | L13: =(L6-K6)/K6 -> -0.1368271
B14: EBIT | D14: =IF(C7=0, IF(D7=0,0,IF(D7>0,1,-1)), (D7-C7)/ABS(C7) ) -> -1.1749361 | E14: =IF(D7=0, IF(E7=0,0,IF(E7>0,1,-1)), (E7-D7)/ABS(D7) ) -> 2.3216374 | F14: =IF(E7=0, IF(F7=0,0,IF(F7>0,1,-1)), (F7-E7)/ABS(E7) ) -> 3.1814159 | G14: =IF(F7=0, IF(G7=0,0,IF(G7>0,1,-1)), (G7-F7)/ABS(F7) ) -> 1.1661376 | H14: =IF(G7=0, IF(H7=0,0,IF(H7>0,1,-1)), (H7-G7)/ABS(G7) ) -> 0.32195533 | I14: =IF(H7=0, IF(I7=0,0,IF(I7>0,1,-1)), (I7-H7)/ABS(H7) ) -> 0.50537708 | J14: =IF(I7=0, IF(J7=0,0,IF(J7>0,1,-1)), (J7-I7)/ABS(I7) ) -> 0.026789869 | K14: =IF(J7=0, IF(K7=0,0,IF(K7>0,1,-1)), (K7-J7)/ABS(J7) ) -> -0.13503864 | L14: =IF(K7=0, IF(L7=0,0,IF(L7>0,1,-1)), (L7-K7)/ABS(K7) ) -> -0.39070148
B15: FCFF | D15: =IF(C8=0, IF(D8=0,0,IF(D8>0,1,-1)), (D8-C8)/ABS(C8) ) -> -0.24502725 | E15: =IF(D8=0, IF(E8=0,0,IF(E8>0,1,-1)), (E8-D8)/ABS(D8) ) -> -0.2760377 | F15: =IF(E8=0, IF(F8=0,0,IF(F8>0,1,-1)), (F8-E8)/ABS(E8) ) -> 0.16266688 | G15: =IF(F8=0, IF(G8=0,0,IF(G8>0,1,-1)), (G8-F8)/ABS(F8) ) -> 2.5986796 | H15: =IF(G8=0, IF(H8=0,0,IF(H8>0,1,-1)), (H8-G8)/ABS(G8) ) -> 0.40633723 | I15: =IF(H8=0, IF(I8=0,0,IF(I8>0,1,-1)), (I8-H8)/ABS(H8) ) -> 0.40152792 | J15: =IF(I8=0, IF(J8=0,0,IF(J8>0,1,-1)), (J8-I8)/ABS(I8) ) -> 0.088554092 | K15: =IF(J8=0, IF(K8=0,0,IF(K8>0,1,-1)), (K8-J8)/ABS(J8) ) -> -0.10636904 | L15: =IF(K8=0, IF(L8=0,0,IF(L8>0,1,-1)), (L8-K8)/ABS(K8) ) -> -0.34315954
C17: Shares
C18: =C5 -> 2022 | D18: =D5 -> 2023 | E18: =E5 -> 2024 | F18: =F5 -> 2025 | G18: =G5 -> 2026 | H18: =H5 -> 2027 | I18: =I5 -> 2028 | J18: =J5 -> 2029 | ... L18: =L5 -> 2031
B19: Avg diluted shares | C19: =Statement!M21 -> 224 | D19: =Statement!N21 -> 207 | E19: =Statement!O21 -> 212 | F19: =Statement!P21 -> 217 | G19: =Statement!Q21 -> 229 | H19: =G19*(1+H20) -> 233.58 | I19: =H19*(1+I20) -> 238.2516 | J19: =I19*(1+J20) -> 245.39915 | K19: =J19*(1+K20) -> 250.30713 | L19: =K19*(1+L20) -> 252.8102
B20: Dilution rate | D20: =D19/C19-1 -> -0.075892857 | E20: =E19/D19-1 -> 0.024154589 | F20: =F19/E19-1 -> 0.023584906 | G20: =G19/F19-1 -> 0.055299539 | H20: 0.02 | I20: 0.02 | J20: 0.03 | K20: 0.02 | L20: 0.01
C22: Historical price
C23: =C5 -> 2022 | D23: =D5 -> 2023 | E23: =E5 -> 2024 | F23: =F5 -> 2025 | G23: =G5 -> 2026 | H23: =H5 -> 2027 | I23: =I5 -> 2028 | J23: =J5 -> 2029 | ... L23: =L5 -> 2031
B24: Price | C24: =Statement!M114 -> 69.09 | D24: =Statement!N114 -> 61.87 | E24: =Statement!O114 -> 103.27 | F24: =Statement!P114 -> 141.44 | G24: =Statement!Q114 -> 820.16
C27: Historical ratios
C28: =C5 -> 2022 | D28: =D5 -> 2023 | E28: =E5 -> 2024 | F28: =F5 -> 2025 | G28: =G5 -> 2026 | H28: =H5 -> 2027 | I28: =I5 -> 2028 | J28: =J5 -> 2029 | ... L28: =L5 -> 2031
B29: PS | C29: =C24/(C6/C19) -> 1.3271726 | D29: =D24/(D6/D19) -> 1.734438 | E29: =E24/(E6/E19) -> 3.3419692 | F29: =F24/(F6/F19) -> 3.3739123 | G29: =G24/(G6/G19) -> 15.401118
B30: Market Cap | C30: =C24*C19 -> 15476.16 | D30: =D24*D19 -> 12807.09 | E30: =E24*E19 -> 21893.24 | F30: =F24*F19 -> 30692.48 | G30: =G24*G19 -> 187816.64
B31: Debt | C31: =Statement!M106 -> 5646 | D31: =Statement!N106 -> 5451 | E31: =Statement!O106 -> 5674 | F31: =Statement!P106 -> 4995 | G31: =Statement!Q106 -> 3565
B32: Cash | C32: =Statement!M105 -> 615 | D32: =Statement!N105 -> 786 | E32: =Statement!O105 -> 1358 | F32: =Statement!P105 -> 891 | G32: =Statement!Q105 -> 1704
B33: EV | C33: =C30+C31-C32 -> 20507.16 | D33: =D30+D31-D32 -> 17472.09 | E33: =E30+E31-E32 -> 26209.24 | F33: =F30+F31-F32 -> 34796.48 | G33: =G30+G31-G32 -> 189677.64
B34: EV/EBIT | C34: =C33/C7 -> 10.489596 | D34: =D33/D7 -> -51.087982 | E34: =E33/E7 -> 57.985044 | F34: =F33/F7 -> 18.410836 | G34: =G33/G7 -> 46.33064
B35: EV/FCFF | C35: =C33/C8 -> 15.223547 | D35: =D33/D8 -> 17.180029 | E35: =E33/E8 -> 35.597338 | F35: =F33/F8 -> 40.648367 | G35: =G33/G8 -> 61.571644
B36: EV/Sales | C36: =C33/C6 -> 1.7586108 | D36: =D33/D6 -> 2.3662094 | E36: =E33/E6 -> 4.0007999 | F36: =F33/F6 -> 3.82505 | G36: =G33/G6 -> 15.553722
B39: EV/EBIT valuation
B40: Year 5 EBIT | C40: =L7 -> 4408.7789
B41: WACC | C41: =IF(Overview!C28>0,Overview!C28,WACC!C20) -> 0.1443252
B42: Applied EV/EBIT ratio | C42: 16
B43: Terminal EV | C43: =(C40*C42) -> 70540.462
B44: PV of Terminal EV | C44: =C43/(1+C41)^5 -> 35949.346
B45: Total EV | C45: =SUM(H9:K9)+C44 -> 52227.697
B46: (+) Cash | C46: =Statement!AC105 -> 1704
B47: (-) Debt | C47: =Statement!AC106 -> 3565
B48: Equity value | C48: =C45+C46-C47 -> 50366.697
B49: Shares outstanding | C49: =Statement!AC77 -> 237
B50: PV of price per share | C50: =C48/C49 -> 212.51771
B52: PS valuation
B53: Year 5 sales | C53: =L6 -> 18369.912
B54: Discount rate | C54: =IF(Overview!C29>0,Overview!C29,WACC!C19) -> 0.1464795
B55: Applied PS ratio | C55: 4
B56: Shares outstanding diluted | C56: =L19 -> 252.8102
B57: Price per share | C57: =(C53*C55)/C56 -> 290.65143
B58: PV of price per share | C58: =C57/(1+C54)^5 -> 146.73746
B60: EV/FCFF valuation
B61: Year 5 FCFF | C61: =L8 -> 3879.6695
B62: WACC | C62: =IF(Overview!C28>0,Overview!C28,WACC!C20) -> 0.1443252
B63: Applied EV/FCFF ratio | C63: 20
B64: Terminal EV | C64: =(C61*C63) -> 77593.39
B65: PV of Terminal EV | C65: =C64/(1+C62)^5 -> 39543.711
B66: Total EV | C66: =SUM(H9:K9)+C65 -> 55822.061
B67: (+) Cash | C67: =Statement!AC105 -> 1704
B68: (-) Debt | C68: =Statement!AC106 -> 3565
B69: Equity value | C69: =C66+C67-C68 -> 53961.061
B70: Shares outstanding | C70: =Statement!AC77 -> 237
B71: PV of price per share | C71: =C69/C70 -> 227.6838
B73: EV/Sales valuation
B74: Year 5 Sales | C74: =L6 -> 18369.912
B75: WACC | C75: =IF(Overview!C28>0,Overview!C28,WACC!C20) -> 0.1443252
B76: Applied EV/Sales ratio | C76: 4
B77: Terminal EV | C77: =(C74*C76) -> 73479.648
B78: PV of Terminal EV | C78: =C77/(1+C75)^5 -> 37447.236
B79: Total EV | C79: =SUM(H9:K9)+C78 -> 53725.586
B80: (+) Cash | C80: =Statement!AC105 -> 1704
B81: (-) Debt | C81: =Statement!AC106 -> 3565
B82: Equity value | C82: =C79+C80-C81 -> 51864.586
B83: Shares outstanding | C83: =Statement!AC77 -> 237
B84: PV of price per share | C84: =C82/C83 -> 218.83792

Sheet AVG target price
B1: AVG target price
B4: AVG target price
B5: DCF price | C5: =DCF!C26 -> 134.65123
B6: EV/EBIT price | C6: =Multiples!C50 -> 212.51771
B7: PS price | C7: =Multiples!C58 -> 146.73746
B8: EV/FCFF price | C8: =Multiples!C71 -> 227.6838
B9: EV/Sales | C9: =Multiples!C84 -> 218.83792
B10: AVG price | C10: =AVERAGE(C5:C9) -> 188.08562
B11: Current price | C11: =Overview!C5 -> 676.77
B12: Upside/Downside | C12: =(C10-C11)/C11 -> -0.72208339

Sheet DDM
B1: Dividend discount model
C2: History | H2: Forecast
C4: Revenues, earnings cash
B5: Revenues (thousand) | C5: =[2]Revenue!C5 -> 2021 | D5: =[2]Revenue!D5 -> 2022 | E5: =[2]Revenue!E5 -> 2023 | F5: =[2]Revenue!F5 -> 2024 | G5: =[2]Revenue!G5 -> 2025 | H5: =[2]Revenue!H5 -> 2026 | I5: =[2]Revenue!I5 -> 2027 | J5: =[2]Revenue!J5 -> 2028 | ... L5: =[2]Revenue!L5 -> 2030
B6: EPS | C6: =Statement!M25 -> 7.36 | D6: =Statement!N25 -> -2.56 | E6: =Statement!O25 -> 1.58 | F6: =Statement!P25 -> 6.77 | G6: =Statement!Q25 -> 13.9
B7: Dividend per share | C7: =Statement!M81 -> 2.77 | D7: =Statement!N81 -> 2.8 | E7: =Statement!O81 -> 2.8 | F7: =Statement!P81 -> 2.86 | G7: =Statement!Q81 -> 2.92
C9: Growth rates
B10: % Growth | C10: =C5 -> 2021 | D10: =D5 -> 2022 | E10: =E5 -> 2023 | F10: =F5 -> 2024 | G10: =G5 -> 2025 | H10: =H5 -> 2026 | I10: =I5 -> 2027 | J10: =J5 -> 2028 | ... L10: =L5 -> 2030
B11: EPS | D11: =(D6-C6)/C6 -> -1.3478261 | E11: =(E6-D6)/D6 -> -1.6171875 | F11: =(F6-E6)/E6 -> 3.2848101 | G11: =(G6-F6)/F6 -> 1.0531758
B12: Dividend | D12: =IF(C7=0, IF(D7=0,0,IF(D7>0,1,-1)), (D7-C7)/ABS(C7) ) -> 0.010830325 | E12: =IF(D7=0, IF(E7=0,0,IF(E7>0,1,-1)), (E7-D7)/ABS(D7) ) -> 0 | F12: =IF(E7=0, IF(F7=0,0,IF(F7>0,1,-1)), (F7-E7)/ABS(E7) ) -> 0.021428571 | G12: =IF(F7=0, IF(G7=0,0,IF(G7>0,1,-1)), (G7-F7)/ABS(F7) ) -> 0.020979021
C14: Ratios
B15: % | C15: =C5 -> 2021 | D15: =D5 -> 2022 | E15: =E5 -> 2023 | F15: =F5 -> 2024 | G15: =G5 -> 2025 | H15: =H5 -> 2026 | I15: =I5 -> 2027 | J15: =J5 -> 2028 | ... L15: =L5 -> 2030
B16: Payout | C16: =C7/C6 -> 0.3763587 | D16: =D7/D6 -> -1.09375 | E16: =E7/E6 -> 1.7721519 | F16: =F7/F6 -> 0.42245199 | G16: =G7/G6 -> 0.21007194
B20: DDM valuation
B21: Latest dividend | C21: =G7 -> 2.92
B22: Year 1 growth rate | C22: 0.03
B23: Year 1 dividend | C23: =C21*(1+C22) -> 3.0076
B24: Discount rate | C24: =IF(Overview!C29>0,Overview!C29,WACC!C19) -> 0.1464795
B25: Perpetual dividend growth | C25: 0.02
B26: PV of price per share | C26: =C23/(C24-C25) -> 23.779348

Sheet Reverse DCF
B1: Reverse DCF
C3: History | H3: Forecast
C5: PV of FCF
B6: $ (thousand) | C6: =Revenue!C5 -> 2022 | D6: =Revenue!D5 -> 2023 | E6: =Revenue!E5 -> 2024 | F6: =Revenue!F5 -> 2025 | G6: =Revenue!G5 -> 2026 | H6: =Revenue!H5 -> 2027 | I6: =Revenue!I5 -> 2028 | J6: =Revenue!J5 -> 2029 | ... L6: =Revenue!L5 -> 2031
B7: FCFF | C7: ='FCF & Other'!C28 -> 1347.0685 | D7: ='FCF & Other'!D28 -> 1017 | E7: ='FCF & Other'!E28 -> 736.26966 | F7: ='FCF & Other'!F28 -> 856.03635 | G7: ='FCF & Other'!G28 -> 3080.6005 | H7: =G7*(1+$C$17) -> 4805.7368 | I7: =H7*(1+$C$17) -> 7496.9495 | J7: =I7*(1+$C$17) -> 11695.241 | K7: =J7*(1+$C$17) -> 18244.576 | L7: =K7*(1+$C$17) -> 28461.539
B8: Perpetual cashflow | L8: =L7*(1+C20)/(C21-C20) -> 223378.45
B9: Period | H9: 1 | I9: 2 | J9: 3 | K9: 4 | L9: 5
B10: PV of FCFF | H10: =H7/(1+$C$21)^H9 -> 4199.6251 | I10: =I7/(1+$C$21)^I9 -> 5725.1341 | J10: =J7/(1+$C$21)^J9 -> 7804.7824 | K10: =K7/(1+$C$21)^K9 -> 10639.861 | L10: =L7/(1+$C$21)^L9 -> 14504.778
B11: PV of Perpetual cashflow | L11: =L8/(1+C21)^L9 -> 113839.76
B14: Growth adjustment
B15: Current Price | C15: =Overview!C5 -> 676.77
B16: Calculated Price | C16: =C36 -> 682.17154
B17: FCFF Growth | C17: 0.56 | E17: Modify until Calculated Price is very close to Current Price
B19: Input parameters
B20: Perpetual growth | C20: 0.015
B21: WACC | C21: =IF(Overview!C28>0,Overview!C28,WACC!C20) -> 0.1443252
B22: Shares outstanding | C22: =Statement!AC74 -> 227
B23: Market cap | C23: =C15*C22 -> 153626.79
B24: Cash | C24: =Statement!AC105 -> 1704
B25: Debt | C25: =Statement!AC106 -> 3565
B26: Enterprise Value | C26: =C23+C25-C24 -> 155487.79
B28: Result
B29: Total PV of Unlevered FCF | C29: =SUM(H10:L10) -> 42874.18
B30: PV of Perpetual cashflow | C30: =L11 -> 113839.76
B31: Enterprise value | C31: =C29+C30 -> 156713.94
B32: (+) Cash | C32: =C24 -> 1704
B33: (-) Debt | C33: =C25 -> 3565
B34: Equity value | C34: =C31+C32-C33 -> 154852.94
B35: Shares outstanding | C35: =C22 -> 227
B36: Price per share | C36: =C34/C35 -> 682.17154
